{
  "type": "Feature",
  "properties": {
    "gn:admin1_code":"1.0",
    "gn:asciiname":"Orle",
    "gn:country_code":"BY",
    "gn:dem":147,
    "gn:feature_class":"P",
    "gn:feature_code":"PPL",
    "gn:name":"Orle",
    "gn:population":0,
    "gn:timezone":"Europe/Minsk",
    "iso:country":"BY",
    "name:rus_x_preferred":[
        "\u041e\u0440\u043b\u0435"
    ],
    "name:und_x_variant":[
        "Orlya"
    ],
    "wof:name":"Orle",
    "wof:placetype":"locality"
},
  "geometry": {"coordinates":[23.3049,52.2419],"type":"Point"}
}