{
  "type": "Feature",
  "properties": {
    "gn:admin1_code":"5.0",
    "gn:asciiname":"Zapur'ye",
    "gn:country_code":"BY",
    "gn:dem":161,
    "gn:feature_class":"P",
    "gn:feature_code":"PPL",
    "gn:name":"Zapur\u2019ye",
    "gn:population":0,
    "gn:timezone":"Europe/Minsk",
    "iso:country":"BY",
    "name:rus_x_preferred":[
        "\u0417\u0430\u043f\u0443\u0440\u044c\u0435"
    ],
    "name:und_x_variant":[
        "Zapur\u2019ye"
    ],
    "wof:name":"Zapur'ye",
    "wof:placetype":"locality"
},
  "geometry": {"coordinates":[26.2379,54.1317],"type":"Point"}
}