{
  "type": "Feature",
  "properties": {
    "gn:admin1_code":"5.0",
    "gn:asciiname":"Slobodka",
    "gn:country_code":"BY",
    "gn:dem":145,
    "gn:feature_class":"P",
    "gn:feature_code":"PPL",
    "gn:name":"Slobodka",
    "gn:population":0,
    "gn:timezone":"Europe/Minsk",
    "iso:country":"BY",
    "name:ceb_x_preferred":[
        "Slobodka"
    ],
    "name:lav_x_preferred":[
        "Slobodka"
    ],
    "name:rus_x_preferred":[
        "\u0421\u043b\u043e\u0431\u043e\u0434\u043a\u0430"
    ],
    "name:swe_x_preferred":[
        "Slobodka"
    ],
    "wof:name":"Slobodka",
    "wof:placetype":"locality"
},
  "geometry": {"coordinates":[26.75,54.4049],"type":"Point"}
}