{
  "type": "Feature",
  "properties": {
    "gn:admin1_code":"3.0",
    "gn:asciiname":"Koyatenyata",
    "gn:country_code":"BY",
    "gn:dem":248,
    "gn:feature_class":"P",
    "gn:feature_code":"PPL",
    "gn:name":"Koyatenyata",
    "gn:population":0,
    "gn:timezone":"Europe/Minsk",
    "iso:country":"BY",
    "name:rus_x_preferred":[
        "\u041a\u043e\u044f\u0442\u0435\u043d\u044f\u0442\u0430"
    ],
    "name:und_x_variant":[
        "Kayatseneta",
        "Kajacienieta",
        "Kayatenyata",
        "Koyatenyata",
        "Koyetenyata"
    ],
    "wof:name":"Koyatenyata",
    "wof:placetype":"locality"
},
  "geometry": {"coordinates":[26.0965,54.2821],"type":"Point"}
}