{
  "type": "Feature",
  "properties": {
    "gn:admin1_code":"3.0",
    "gn:asciiname":"Mizhevo",
    "gn:country_code":"BY",
    "gn:dem":118,
    "gn:feature_class":"P",
    "gn:feature_code":"PPL",
    "gn:name":"Mizh\u00ebvo",
    "gn:population":0,
    "gn:timezone":"Europe/Minsk",
    "iso:country":"BY",
    "name:rus_x_preferred":[
        "\u041c\u0438\u0436\u0451\u0432\u043e"
    ],
    "name:und_x_variant":[
        "Mizh\u00ebvo"
    ],
    "wof:name":"Mizhevo",
    "wof:placetype":"locality"
},
  "geometry": {"coordinates":[24.5832,53.3478],"type":"Point"}
}