{
  "type": "Feature",
  "properties": {
    "gn:admin1_code":"6.0",
    "gn:asciiname":"Oryzhnya",
    "gn:country_code":"BY",
    "gn:dem":154,
    "gn:feature_class":"P",
    "gn:feature_code":"PPL",
    "gn:name":"Oryzhnya",
    "gn:population":0,
    "gn:timezone":"Europe/Minsk",
    "iso:country":"BY",
    "name:rus_x_preferred":[
        "\u041e\u0440\u044b\u0436\u043d\u044f"
    ],
    "wof:name":"Oryzhnya",
    "wof:placetype":"locality"
},
  "geometry": {"coordinates":[28.5293,53.1015],"type":"Point"}
}