{
  "type": "Feature",
  "properties": {
    "gn:admin1_code":"6.0",
    "gn:asciiname":"Glukhaya Seliba",
    "gn:country_code":"BY",
    "gn:dem":163,
    "gn:feature_class":"P",
    "gn:feature_code":"PPL",
    "gn:name":"Glukhaya Seliba",
    "gn:population":0,
    "gn:timezone":"Europe/Minsk",
    "iso:country":"BY",
    "name:rus_x_preferred":[
        "\u0413\u043b\u0443\u0445\u0430\u044f \u0421\u0435\u043b\u0438\u0431\u0430"
    ],
    "name:und_x_variant":[
        "Glukhaya",
        "Glukhaya Seliba"
    ],
    "wof:name":"Glukhaya Seliba",
    "wof:placetype":"locality"
},
  "geometry": {"coordinates":[30.0296,53.6587],"type":"Point"}
}