{
  "type": "Feature",
  "properties": {
    "gn:admin1_code":"7.0",
    "gn:asciiname":"Bol'shiye Osetki",
    "gn:country_code":"BY",
    "gn:dem":161,
    "gn:feature_class":"P",
    "gn:feature_code":"PPL",
    "gn:name":"Bol\u2019shiye Osetki",
    "gn:population":0,
    "gn:timezone":"Europe/Minsk",
    "iso:country":"BY",
    "name:rus_x_preferred":[
        "\u0411\u043e\u043b\u044c\u0448\u0438\u0435 \u041e\u0441\u0435\u0442\u043a\u0438"
    ],
    "name:und_x_variant":[
        "Bol\u2019shiye Osetki"
    ],
    "wof:name":"Bol'shiye Osetki",
    "wof:placetype":"locality"
},
  "geometry": {"coordinates":[29.219,55.7915],"type":"Point"}
}