{
  "type": "Feature",
  "properties": {
    "gn:admin1_code":"7.0",
    "gn:asciiname":"Obukhovo",
    "gn:country_code":"BY",
    "gn:dem":123,
    "gn:feature_class":"P",
    "gn:feature_code":"PPL",
    "gn:name":"Obukhovo",
    "gn:population":0,
    "gn:timezone":"Europe/Minsk",
    "iso:country":"BY",
    "name:rus_x_preferred":[
        "\u041e\u0431\u0443\u0445\u043e\u0432\u043e"
    ],
    "name:und_x_variant":[
        "Obuchowo",
        "Bol\u2019shoye Obukhovo",
        "Obukhovo"
    ],
    "wof:name":"Obukhovo",
    "wof:placetype":"locality"
},
  "geometry": {"coordinates":[27.8907,55.872],"type":"Point"}
}