{
  "type": "Feature",
  "properties": {
    "gn:admin1_code":"5.0",
    "gn:asciiname":"Teraspol'",
    "gn:country_code":"BY",
    "gn:dem":168,
    "gn:feature_class":"P",
    "gn:feature_code":"PPL",
    "gn:name":"Teraspol\u2019",
    "gn:population":0,
    "gn:timezone":"Europe/Minsk",
    "iso:country":"BY",
    "name:rus_x_preferred":[
        "\u0422\u0435\u0440\u0430\u0441\u043f\u043e\u043b\u044c"
    ],
    "name:und_x_variant":[
        "Teraspol\u2019"
    ],
    "wof:name":"Teraspol'",
    "wof:placetype":"locality"
},
  "geometry": {"coordinates":[27.3073,53.0029],"type":"Point"}
}