{
  "type": "Feature",
  "properties": {
    "gn:country":"BY",
    "gn:fcode":"PPL",
    "gn:pop":1000,
    "iso:country":"BY",
    "name:bel_x_preferred":[
        "\u0417\u0430\u043b\u0435\u0441\u0441\u0435"
    ],
    "name:eng_x_preferred":[
        "Zales'ye"
    ],
    "name:rus_x_preferred":[
        "\u0417\u0430\u043b\u0435\u0441\u044c\u0435"
    ],
    "name:unk_x_variant":[
        "Zalesie"
    ],
    "qs:name":"Zalyessye",
    "qs:photos_9r":0,
    "qs:photos_sr":0,
    "qs:pop_sr":"2",
    "wof:name":"Zalyessye",
    "wof:placetype":"locality",
    "wof:population":1000
},
  "geometry": {"coordinates":[26.548,54.4192],"type":"Point"}
}