{
  "type": "Feature",
  "properties": {
    "gn:admin1_code":"5.0",
    "gn:asciiname":"Baturino",
    "gn:country_code":"BY",
    "gn:dem":219,
    "gn:feature_class":"P",
    "gn:feature_code":"PPL",
    "gn:name":"Baturino",
    "gn:population":0,
    "gn:timezone":"Europe/Minsk",
    "iso:country":"BY",
    "name:rus_x_preferred":[
        "\u0411\u0430\u0442\u0443\u0440\u0438\u043d\u043e"
    ],
    "wof:name":"Baturino",
    "wof:placetype":"locality"
},
  "geometry": {"coordinates":[27.4623,54.3347],"type":"Point"}
}