{
  "type": "Feature",
  "properties": {
    "gn:admin1_code":"5.0",
    "gn:asciiname":"Domashi",
    "gn:country_code":"BY",
    "gn:dem":314,
    "gn:feature_class":"P",
    "gn:feature_code":"PPL",
    "gn:name":"Domashi",
    "gn:population":0,
    "gn:timezone":"Europe/Minsk",
    "iso:country":"BY",
    "name:rus_x_preferred":[
        "\u0414\u043e\u043c\u0430\u0448\u0438"
    ],
    "wof:name":"Domashi",
    "wof:placetype":"locality"
},
  "geometry": {"coordinates":[27.6454,54.2258],"type":"Point"}
}