{
  "type": "Feature",
  "properties": {
    "gn:admin1_code":"5.0",
    "gn:asciiname":"Nivishche",
    "gn:country_code":"BY",
    "gn:dem":166,
    "gn:feature_class":"P",
    "gn:feature_code":"PPL",
    "gn:name":"Nivishche",
    "gn:population":0,
    "gn:timezone":"Europe/Minsk",
    "iso:country":"BY",
    "name:rus_x_preferred":[
        "\u041d\u0438\u0432\u0438\u0449\u0435"
    ],
    "name:und_x_variant":[
        "Novishche"
    ],
    "wof:name":"Nivishche",
    "wof:placetype":"locality"
},
  "geometry": {"coordinates":[28.5246,53.5794],"type":"Point"}
}