{
  "type": "Feature",
  "properties": {
    "gn:admin1_code":"7.0",
    "gn:asciiname":"Shmidel'shchina",
    "gn:country_code":"BY",
    "gn:dem":208,
    "gn:feature_class":"P",
    "gn:feature_code":"PPL",
    "gn:name":"Shmidel\u2019shchina",
    "gn:population":0,
    "gn:timezone":"Europe/Minsk",
    "iso:country":"BY",
    "name:rus_x_preferred":[
        "\u0428\u043c\u0438\u0434\u0435\u043b\u044c\u0449\u0438\u043d\u0430"
    ],
    "name:und_x_variant":[
        "Shmidel\u2019shchina",
        "Shmedel\u2019shchina"
    ],
    "wof:name":"Shmidel'shchina",
    "wof:placetype":"locality"
},
  "geometry": {"coordinates":[29.7049,54.4818],"type":"Point"}
}