{
  "type": "Feature",
  "properties": {
    "gn:admin1_code":"7.0",
    "gn:asciiname":"Plyssy",
    "gn:country_code":"BY",
    "gn:dem":127,
    "gn:feature_class":"P",
    "gn:feature_code":"PPL",
    "gn:name":"Plyssy",
    "gn:population":0,
    "gn:timezone":"Europe/Minsk",
    "iso:country":"BY",
    "name:rus_x_preferred":[
        "\u041f\u043b\u044b\u0441\u0441\u044b"
    ],
    "wof:name":"Plyssy",
    "wof:placetype":"locality"
},
  "geometry": {"coordinates":[28.7894,55.3235],"type":"Point"}
}