{
  "type": "Feature",
  "properties": {
    "gn:admin1_code":"7.0",
    "gn:asciiname":"Budislovo",
    "gn:country_code":"BY",
    "gn:dem":155,
    "gn:feature_class":"P",
    "gn:feature_code":"PPL",
    "gn:name":"Budislovo",
    "gn:population":0,
    "gn:timezone":"Europe/Minsk",
    "iso:country":"BY",
    "name:rus_x_preferred":[
        "\u0411\u0443\u0434\u0438\u0441\u043b\u043e\u0432\u043e"
    ],
    "wof:name":"Budislovo",
    "wof:placetype":"locality"
},
  "geometry": {"coordinates":[30.4835,55.416],"type":"Point"}
}