{
  "type": "Feature",
  "properties": {
    "gn:admin1_code":"2.0",
    "gn:asciiname":"Molot",
    "gn:country_code":"BY",
    "gn:dem":134,
    "gn:feature_class":"P",
    "gn:feature_code":"PPL",
    "gn:name":"Molot",
    "gn:population":0,
    "gn:timezone":"Europe/Minsk",
    "iso:country":"BY",
    "name:rus_x_preferred":[
        "\u041c\u043e\u043b\u043e\u0442"
    ],
    "wof:name":"Molot",
    "wof:placetype":"locality"
},
  "geometry": {"coordinates":[28.1623,52.2004],"type":"Point"}
}