{
  "type": "Feature",
  "properties": {
    "gn:admin1_code":"7.0",
    "gn:asciiname":"Kalachi",
    "gn:country_code":"BY",
    "gn:dem":135,
    "gn:feature_class":"P",
    "gn:feature_code":"PPL",
    "gn:name":"Kalachi",
    "gn:population":0,
    "gn:timezone":"Europe/Minsk",
    "iso:country":"BY",
    "name:ceb_x_preferred":[
        "Kalachi"
    ],
    "name:rus_x_preferred":[
        "\u041a\u0430\u043b\u0430\u0447\u0438"
    ],
    "name:swe_x_preferred":[
        "Kalachi"
    ],
    "wof:name":"Kalachi",
    "wof:placetype":"locality"
},
  "geometry": {"coordinates":[28.2113,55.4095],"type":"Point"}
}