{
  "type": "Feature",
  "properties": {
    "gn:admin1_code":"7.0",
    "gn:asciiname":"Krikaly",
    "gn:country_code":"BY",
    "gn:dem":151,
    "gn:feature_class":"P",
    "gn:feature_code":"PPL",
    "gn:name":"Krikaly",
    "gn:population":0,
    "gn:timezone":"Europe/Minsk",
    "iso:country":"BY",
    "name:rus_x_preferred":[
        "\u041a\u0440\u0438\u043a\u0430\u043b\u044b"
    ],
    "wof:name":"Krikaly",
    "wof:placetype":"locality"
},
  "geometry": {"coordinates":[27.2261,55.0748],"type":"Point"}
}