{
  "type": "Feature",
  "properties": {
    "gn:admin1_code":"7.0",
    "gn:asciiname":"Trudovoy",
    "gn:country_code":"BY",
    "gn:dem":213,
    "gn:feature_class":"P",
    "gn:feature_code":"PPL",
    "gn:name":"Trudovoy",
    "gn:population":0,
    "gn:timezone":"Europe/Minsk",
    "iso:country":"BY",
    "name:rus_x_preferred":[
        "\u0422\u0440\u0443\u0434\u043e\u0432\u043e\u0439"
    ],
    "wof:name":"Trudovoy",
    "wof:placetype":"locality"
},
  "geometry": {"coordinates":[30.0885,54.6075],"type":"Point"}
}