{
  "type": "Feature",
  "properties": {
    "gn:admin1_code":"2.0",
    "gn:asciiname":"Makawye",
    "gn:country_code":"BY",
    "gn:dem":143,
    "gn:feature_class":"P",
    "gn:feature_code":"PPL",
    "gn:name":"Makawye",
    "gn:population":0,
    "gn:timezone":"Europe/Minsk",
    "iso:country":"BY",
    "name:rus_x_preferred":[
        "\u041c\u0430\u043a\u043e\u0432\u044c\u0435"
    ],
    "name:und_x_variant":[
        "Makov\u2019ye"
    ],
    "wof:name":"Makawye",
    "wof:placetype":"locality"
},
  "geometry": {"coordinates":[31.2571,52.1556],"type":"Point"}
}