{
  "type": "Feature",
  "properties": {
    "gn:admin1_code":"6.0",
    "gn:asciiname":"Lytkovka",
    "gn:country_code":"BY",
    "gn:dem":184,
    "gn:feature_class":"P",
    "gn:feature_code":"PPL",
    "gn:name":"Lytkovka",
    "gn:population":0,
    "gn:timezone":"Europe/Minsk",
    "iso:country":"BY",
    "name:rus_x_preferred":[
        "\u041b\u044b\u0442\u043a\u043e\u0432\u043a\u0430"
    ],
    "wof:name":"Lytkovka",
    "wof:placetype":"locality"
},
  "geometry": {"coordinates":[32.1393,53.6747],"type":"Point"}
}