{
  "type": "Feature",
  "properties": {
    "gn:admin1_code":"3.0",
    "gn:asciiname":"Gezgaly",
    "gn:country_code":"BY",
    "gn:dem":130,
    "gn:feature_class":"P",
    "gn:feature_code":"PPL",
    "gn:name":"Gezgaly",
    "gn:population":0,
    "gn:timezone":"Europe/Minsk",
    "iso:country":"BY",
    "name:bel_x_preferred":[
        "\u0413\u0435\u0437\u0433\u0430\u043b\u044b"
    ],
    "name:und_x_variant":[
        "Hyez\u00b7haly"
    ],
    "wof:name":"Gezgaly",
    "wof:placetype":"locality"
},
  "geometry": {"coordinates":[25.3725,53.5999],"type":"Point"}
}