{
  "type": "Feature",
  "properties": {
    "gn:admin1_code":"2.0",
    "gn:asciiname":"Lesnoye",
    "gn:country_code":"BY",
    "gn:dem":132,
    "gn:feature_class":"P",
    "gn:feature_code":"PPL",
    "gn:name":"Lesnoye",
    "gn:population":0,
    "gn:timezone":"Europe/Minsk",
    "iso:country":"BY",
    "name:rus_x_preferred":[
        "\u041b\u0435\u0441\u043d\u043e\u0435"
    ],
    "name:und_x_variant":[
        "Krasnyy Ostrov"
    ],
    "wof:name":"Lesnoye",
    "wof:placetype":"locality"
},
  "geometry": {"coordinates":[30.1478,52.1645],"type":"Point"}
}