{
  "type": "Feature",
  "properties": {
    "gn:admin1_code":"6.0",
    "gn:asciiname":"Pnevshchina",
    "gn:country_code":"BY",
    "gn:dem":174,
    "gn:feature_class":"P",
    "gn:feature_code":"PPL",
    "gn:name":"Pnevshchina",
    "gn:population":0,
    "gn:timezone":"Europe/Minsk",
    "iso:country":"BY",
    "name:rus_x_preferred":[
        "\u041f\u043d\u0435\u0432\u0449\u0438\u043d\u0430"
    ],
    "wof:name":"Pnevshchina",
    "wof:placetype":"locality"
},
  "geometry": {"coordinates":[31.2302,54.1918],"type":"Point"}
}