{
  "type": "Feature",
  "properties": {
    "gn:admin1_code":"7.0",
    "gn:asciiname":"Demyakhi",
    "gn:country_code":"BY",
    "gn:dem":145,
    "gn:feature_class":"P",
    "gn:feature_code":"PPL",
    "gn:name":"Demyakhi",
    "gn:population":0,
    "gn:timezone":"Europe/Minsk",
    "iso:country":"BY",
    "name:rus_x_preferred":[
        "\u0414\u0435\u043c\u044f\u0445\u0438"
    ],
    "wof:name":"Demyakhi",
    "wof:placetype":"locality"
},
  "geometry": {"coordinates":[30.7814,55.4949],"type":"Point"}
}