{
  "type": "Feature",
  "properties": {
    "gn:admin1_code":"2.0",
    "gn:asciiname":"Malyye Litvinovichi",
    "gn:country_code":"BY",
    "gn:dem":136,
    "gn:feature_class":"P",
    "gn:feature_code":"PPL",
    "gn:name":"Malyye Litvinovichi",
    "gn:population":0,
    "gn:timezone":"Europe/Minsk",
    "iso:country":"BY",
    "name:rus_x_preferred":[
        "\u041c\u0430\u043b\u044b\u0435 \u041b\u0438\u0442\u0432\u0438\u043d\u043e\u0432\u0438\u0447\u0438"
    ],
    "wof:name":"Malyye Litvinovichi",
    "wof:placetype":"locality"
},
  "geometry": {"coordinates":[29.2473,52.5125],"type":"Point"}
}