{
  "type": "Feature",
  "properties": {
    "gn:admin1_code":"7.0",
    "gn:asciiname":"Matsury",
    "gn:country_code":"BY",
    "gn:dem":185,
    "gn:feature_class":"P",
    "gn:feature_code":"PPL",
    "gn:name":"Matsury",
    "gn:population":0,
    "gn:timezone":"Europe/Minsk",
    "iso:country":"BY",
    "name:rus_x_preferred":[
        "\u041c\u0430\u0446\u0443\u0440\u044b"
    ],
    "wof:name":"Matsury",
    "wof:placetype":"locality"
},
  "geometry": {"coordinates":[27.0578,55.1161],"type":"Point"}
}