{
  "type": "Feature",
  "properties": {
    "gn:admin1_code":"6.0",
    "gn:asciiname":"Mayshchina",
    "gn:country_code":"BY",
    "gn:dem":161,
    "gn:feature_class":"P",
    "gn:feature_code":"PPL",
    "gn:name":"Mayshchina",
    "gn:population":0,
    "gn:timezone":"Europe/Minsk",
    "iso:country":"BY",
    "name:rus_x_preferred":[
        "\u041c\u0430\u0439\u0449\u0438\u043d\u0430"
    ],
    "wof:name":"Mayshchina",
    "wof:placetype":"locality"
},
  "geometry": {"coordinates":[29.8191,53.825],"type":"Point"}
}