{
  "type": "Feature",
  "properties": {
    "gn:admin1_code":"2.0",
    "gn:asciiname":"Yagodnoye",
    "gn:country_code":"BY",
    "gn:dem":139,
    "gn:feature_class":"P",
    "gn:feature_code":"PPL",
    "gn:name":"Yagodnoye",
    "gn:population":0,
    "gn:timezone":"Europe/Minsk",
    "iso:country":"BY",
    "name:rus_x_preferred":[
        "\u042f\u0433\u043e\u0434\u043d\u043e\u0435"
    ],
    "name:und_x_variant":[
        "Yagodnyy"
    ],
    "wof:name":"Yagodnoye",
    "wof:placetype":"locality"
},
  "geometry": {"coordinates":[31.0224,52.6279],"type":"Point"}
}