{
  "type": "Feature",
  "properties": {
    "gn:admin1_code":"2.0",
    "gn:asciiname":"Medkov",
    "gn:country_code":"BY",
    "gn:dem":132,
    "gn:feature_class":"P",
    "gn:feature_code":"PPL",
    "gn:name":"Medkov",
    "gn:population":0,
    "gn:timezone":"Europe/Minsk",
    "iso:country":"BY",
    "name:rus_x_preferred":[
        "\u041c\u0435\u0434\u043a\u043e\u0432"
    ],
    "wof:name":"Medkov",
    "wof:placetype":"locality"
},
  "geometry": {"coordinates":[29.6576,52.6518],"type":"Point"}
}