{
  "type": "Feature",
  "properties": {
    "gn:admin1_code":"3.0",
    "gn:asciiname":"Katenovichi",
    "gn:country_code":"BY",
    "gn:dem":160,
    "gn:feature_class":"P",
    "gn:feature_code":"PPL",
    "gn:name":"Katenovichi",
    "gn:population":0,
    "gn:timezone":"Europe/Minsk",
    "iso:country":"BY",
    "name:rus_x_preferred":[
        "\u041a\u0430\u0442\u0435\u043d\u043e\u0432\u0438\u0447\u0438"
    ],
    "wof:name":"Katenovichi",
    "wof:placetype":"locality"
},
  "geometry": {"coordinates":[26.0813,54.8083],"type":"Point"}
}