{
  "type": "Feature",
  "properties": {
    "gn:admin1_code":"5.0",
    "gn:asciiname":"Vishen'ka",
    "gn:country_code":"BY",
    "gn:dem":184,
    "gn:feature_class":"P",
    "gn:feature_code":"PPL",
    "gn:name":"Vishen\u2019ka",
    "gn:population":0,
    "gn:timezone":"Europe/Minsk",
    "iso:country":"BY",
    "name:rus_x_preferred":[
        "\u0412\u0438\u0448\u0435\u043d\u044c\u043a\u0430"
    ],
    "name:und_x_variant":[
        "Vishen\u2019ka"
    ],
    "wof:name":"Vishen'ka",
    "wof:placetype":"locality"
},
  "geometry": {"coordinates":[28.4537,53.8321],"type":"Point"}
}