{
  "type": "Feature",
  "properties": {
    "gn:admin1_code":"3.0",
    "gn:asciiname":"Dubrovo",
    "gn:country_code":"BY",
    "gn:dem":234,
    "gn:feature_class":"P",
    "gn:feature_code":"PPL",
    "gn:name":"Dubrovo",
    "gn:population":0,
    "gn:timezone":"Europe/Minsk",
    "iso:country":"BY",
    "name:che_x_preferred":[
        "\u0414\u0443\u0431\u0440\u043e\u0432\u043e"
    ],
    "name:rus_x_preferred":[
        "\u0414\u0443\u0431\u0440\u043e\u0432\u043e"
    ],
    "wof:name":"Dubrovo",
    "wof:placetype":"locality"
},
  "geometry": {"coordinates":[26.0254,53.4508],"type":"Point"}
}