{
  "type": "Feature",
  "properties": {
    "gn:admin1_code":"1.0",
    "gn:asciiname":"Dzyevyatki",
    "gn:country_code":"BY",
    "gn:dem":150,
    "gn:feature_class":"P",
    "gn:feature_code":"PPL",
    "gn:name":"Dzyevyatki",
    "gn:population":0,
    "gn:timezone":"Europe/Minsk",
    "iso:country":"BY",
    "name:bel_x_preferred":[
        "\u0414\u0437\u0435\u0432\u044f\u0442\u043a\u0456"
    ],
    "name:eng_x_preferred":[
        "Devyatki"
    ],
    "name:rus_x_preferred":[
        "\u0414\u0435\u0432\u044f\u0442\u043a\u0438"
    ],
    "name:und_x_variant":[
        "Dzeventki",
        "Dzyevyatki"
    ],
    "wof:name":"Dzyevyatki",
    "wof:placetype":"locality"
},
  "geometry": {"coordinates":[24.1847,52.3479],"type":"Point"}
}