{
  "type": "Feature",
  "properties": {
    "gn:admin1_code":"2.0",
    "gn:asciiname":"Krasnaye",
    "gn:country_code":"BY",
    "gn:dem":135,
    "gn:feature_class":"P",
    "gn:feature_code":"PPL",
    "gn:name":"Krasnaye",
    "gn:population":0,
    "gn:timezone":"Europe/Minsk",
    "iso:country":"BY",
    "name:bel_x_preferred":[
        "\u041a\u0440\u0430\u0441\u043d\u0430\u0435"
    ],
    "name:und_x_variant":[
        "Krasnoye"
    ],
    "wof:name":"Krasnaye",
    "wof:placetype":"locality"
},
  "geometry": {"coordinates":[30.9191,52.4732],"type":"Point"}
}