{
  "type": "Feature",
  "properties": {
    "gn:admin1_code":"5.0",
    "gn:asciiname":"Hranichy",
    "gn:country_code":"BY",
    "gn:dem":193,
    "gn:feature_class":"P",
    "gn:feature_code":"PPL",
    "gn:name":"Hranichy",
    "gn:population":0,
    "gn:timezone":"Europe/Minsk",
    "iso:country":"BY",
    "name:bel_x_preferred":[
        "\u0413\u0440\u0430\u043d\u0456\u0447\u044b"
    ],
    "name:und_x_variant":[
        "Hranicze",
        "Graniche",
        "Granichi",
        "Hranichy"
    ],
    "wof:name":"Hranichy",
    "wof:placetype":"locality"
},
  "geometry": {"coordinates":[27.1904,54.2187],"type":"Point"}
}