{
  "type": "Feature",
  "properties": {
    "gn:admin1_code":"7.0",
    "gn:asciiname":"Zhawry",
    "gn:country_code":"BY",
    "gn:dem":152,
    "gn:feature_class":"P",
    "gn:feature_code":"PPL",
    "gn:name":"Zhawry",
    "gn:population":0,
    "gn:timezone":"Europe/Minsk",
    "iso:country":"BY",
    "name:bel_x_preferred":[
        "\u0416\u0430\u045e\u0440\u044b"
    ],
    "name:eng_x_preferred":[
        "Zhaury"
    ],
    "name:rus_x_preferred":[
        "\u0416\u0430\u0443\u0440\u044b"
    ],
    "name:und_x_variant":[
        "Zhawry"
    ],
    "wof:name":"Zhawry",
    "wof:placetype":"locality"
},
  "geometry": {"coordinates":[29.8213,55.0456],"type":"Point"}
}