{
  "type": "Feature",
  "properties": {
    "gn:admin1_code":"3.0",
    "gn:asciiname":"Romashki",
    "gn:country_code":"BY",
    "gn:dem":129,
    "gn:feature_class":"P",
    "gn:feature_code":"PPL",
    "gn:name":"Romashki",
    "gn:population":0,
    "gn:timezone":"Europe/Minsk",
    "iso:country":"BY",
    "name:bel_x_preferred":[
        "Ramashki"
    ],
    "name:bel_x_variant":[
        "\u0420\u0430\u043c\u0430\u0448\u043a\u0456"
    ],
    "name:rus_x_preferred":[
        "\u0420\u043e\u043c\u0430\u0448\u043a\u0438"
    ],
    "wof:name":"Romashki",
    "wof:placetype":"locality"
},
  "geometry": {"coordinates":[24.4924,53.5652],"type":"Point"}
}