{
  "type": "Feature",
  "properties": {
    "gn:country":"BY",
    "gn:fcode":"PPL",
    "gn:pop":126,
    "iso:country":"BY",
    "name:rus_x_preferred":[
        "\u0411\u043e\u043b\u044c\u0448\u043e\u0439 \u041d\u0435\u0436\u043a\u043e\u0432"
    ],
    "qs:name":"Bol\u2019shoy Nezhkov",
    "qs:photos_9r":0,
    "qs:photos_sr":0,
    "qs:pop_sr":"1",
    "wof:name":"Bol\u2019shoy Nezhkov",
    "wof:placetype":"locality",
    "wof:population":126
},
  "geometry": {"coordinates":[29.9492,53.9835],"type":"Point"}
}