{
  "type": "Feature",
  "properties": {
    "gn:admin1_code":"5.0",
    "gn:asciiname":"Gribovshchina",
    "gn:country_code":"BY",
    "gn:dem":186,
    "gn:feature_class":"P",
    "gn:feature_code":"PPL",
    "gn:name":"Gribovshchina",
    "gn:population":0,
    "gn:timezone":"Europe/Minsk",
    "iso:country":"BY",
    "name:rus_x_preferred":[
        "\u0413\u0440\u0438\u0431\u043e\u0432\u0449\u0438\u043d\u0430"
    ],
    "wof:name":"Gribovshchina",
    "wof:placetype":"locality"
},
  "geometry": {"coordinates":[26.8171,53.2115],"type":"Point"}
}