{
  "type": "Feature",
  "properties": {
    "gn:admin1_code":"3.0",
    "gn:asciiname":"Netsech",
    "gn:country_code":"BY",
    "gn:dem":140,
    "gn:feature_class":"P",
    "gn:feature_code":"PPL",
    "gn:name":"Netsech",
    "gn:population":0,
    "gn:timezone":"Europe/Minsk",
    "iso:country":"BY",
    "name:rus_x_preferred":[
        "\u041d\u0435\u0442\u0435\u0447\u044c"
    ],
    "name:und_x_variant":[
        "Netech\u2019",
        "Netsech"
    ],
    "wof:name":"Netsech",
    "wof:placetype":"locality"
},
  "geometry": {"coordinates":[25.4241,53.8909],"type":"Point"}
}