{
  "type": "Feature",
  "properties": {
    "gn:admin1_code":"5.0",
    "gn:asciiname":"Dubeyki",
    "gn:country_code":"BY",
    "gn:dem":181,
    "gn:feature_class":"P",
    "gn:feature_code":"PPL",
    "gn:name":"Dubeyki",
    "gn:population":0,
    "gn:timezone":"Europe/Minsk",
    "iso:country":"BY",
    "name:rus_x_preferred":[
        "\u0414\u0443\u0431\u0435\u0439\u043a\u0438"
    ],
    "wof:name":"Dubeyki",
    "wof:placetype":"locality"
},
  "geometry": {"coordinates":[27.3781,53.1843],"type":"Point"}
}