{
  "type": "Feature",
  "properties": {
    "gn:admin1_code":"5.0",
    "gn:asciiname":"Staryye Gumny",
    "gn:country_code":"BY",
    "gn:dem":174,
    "gn:feature_class":"P",
    "gn:feature_code":"PPL",
    "gn:name":"Staryye Gumny",
    "gn:population":0,
    "gn:timezone":"Europe/Minsk",
    "iso:country":"BY",
    "name:rus_x_preferred":[
        "\u0421\u0442\u0430\u0440\u044b\u0435 \u0413\u0443\u043c\u043d\u044b"
    ],
    "name:und_x_variant":[
        "Staraya Gumna"
    ],
    "wof:name":"Staryye Gumny",
    "wof:placetype":"locality"
},
  "geometry": {"coordinates":[29.2292,53.9797],"type":"Point"}
}