{
  "type": "Feature",
  "properties": {
    "gn:admin1_code":"7.0",
    "gn:asciiname":"Kolosovo",
    "gn:country_code":"BY",
    "gn:dem":217,
    "gn:feature_class":"P",
    "gn:feature_code":"PPL",
    "gn:name":"Kolosovo",
    "gn:population":0,
    "gn:timezone":"Europe/Minsk",
    "iso:country":"BY",
    "name:rus_x_preferred":[
        "\u041a\u043e\u043b\u043e\u0441\u043e\u0432\u043e"
    ],
    "wof:name":"Kolosovo",
    "wof:placetype":"locality"
},
  "geometry": {"coordinates":[29.627,54.3659],"type":"Point"}
}