{
  "type": "Feature",
  "properties": {
    "gn:admin1_code":"7.0",
    "gn:asciiname":"Gorovyye Pervyye",
    "gn:country_code":"BY",
    "gn:dem":170,
    "gn:feature_class":"P",
    "gn:feature_code":"PPL",
    "gn:name":"Gorovyye Pervyye",
    "gn:population":0,
    "gn:timezone":"Europe/Minsk",
    "iso:country":"BY",
    "name:rus_x_preferred":[
        "\u0413\u043e\u0440\u043e\u0432\u044b\u0435 \u041f\u0435\u0440\u0432\u044b\u0435"
    ],
    "name:und_x_variant":[
        "Gorovyye"
    ],
    "wof:name":"Gorovyye Pervyye",
    "wof:placetype":"locality"
},
  "geometry": {"coordinates":[27.8209,55.2378],"type":"Point"}
}