{
  "type": "Feature",
  "properties": {
    "gn:admin1_code":"5.0",
    "gn:asciiname":"Pil'nitsa",
    "gn:country_code":"BY",
    "gn:dem":232,
    "gn:feature_class":"P",
    "gn:feature_code":"PPL",
    "gn:name":"Pil\u2019nitsa",
    "gn:population":0,
    "gn:timezone":"Europe/Minsk",
    "iso:country":"BY",
    "name:rus_x_preferred":[
        "\u041f\u0438\u043b\u044c\u043d\u0438\u0446\u0430"
    ],
    "name:und_x_variant":[
        "Pil\u2019nitsa"
    ],
    "wof:name":"Pil'nitsa",
    "wof:placetype":"locality"
},
  "geometry": {"coordinates":[27.5829,54.0575],"type":"Point"}
}