{
  "type": "Feature",
  "properties": {
    "gn:country":"BY",
    "gn:fcode":"PPLA2",
    "gn:population":14345,
    "iso:country":"BY",
    "name:bel_x_preferred":[
        "\u0410\u0448\u043c\u044f\u043d\u044b"
    ],
    "name:bel_x_variant":[
        "\u0413\u043e\u0440\u0430\u0434 \u0410\u0448\u043c\u044f\u043d\u044b"
    ],
    "name:bul_x_preferred":[
        "\u041e\u0448\u043c\u044f\u043d\u0438"
    ],
    "name:ceb_x_preferred":[
        "Ashmyany"
    ],
    "name:ces_x_preferred":[
        "A\u0161mjany"
    ],
    "name:che_x_preferred":[
        "\u041e\u0448\u043c\u044f\u043d\u044b"
    ],
    "name:deu_x_preferred":[
        "Aschmjany"
    ],
    "name:eng_x_preferred":[
        "Ashmyany"
    ],
    "name:est_x_preferred":[
        "A\u0161miany"
    ],
    "name:fin_x_preferred":[
        "A\u0161mjany"
    ],
    "name:fra_x_preferred":[
        "Achmiany"
    ],
    "name:frr_x_preferred":[
        "Aschmjany"
    ],
    "name:heb_x_preferred":[
        "\u05d0\u05e9\u05de\u05d9\u05d0\u05e0\u05d9"
    ],
    "name:hsb_x_preferred":[
        "A\u0161mjany"
    ],
    "name:hye_x_preferred":[
        "\u0555\u0577\u0574\u0575\u0561\u0576\u056b"
    ],
    "name:ita_x_preferred":[
        "A\u0161mjany"
    ],
    "name:jpn_x_preferred":[
        "\u30a2\u30b7\u30e5\u30de\u30cb"
    ],
    "name:lav_x_preferred":[
        "A\u0161mjani"
    ],
    "name:lit_x_preferred":[
        "A\u0161mena"
    ],
    "name:nld_x_preferred":[
        "Ashmyany"
    ],
    "name:pol_x_preferred":[
        "Oszmiana"
    ],
    "name:rus_x_preferred":[
        "\u041e\u0448\u043c\u044f\u043d\u044b"
    ],
    "name:slv_x_preferred":[
        "A\u0161mjanj"
    ],
    "name:spa_x_preferred":[
        "Ashmiany"
    ],
    "name:srp_x_preferred":[
        "\u0410\u0448\u043c\u0458\u0430\u043d\u0438"
    ],
    "name:swe_x_preferred":[
        "Asjmjany"
    ],
    "name:szl_x_preferred":[
        "Aszmjany"
    ],
    "name:tat_x_preferred":[
        "\u0410\u0448\u043c\u04d9\u043d\u044b"
    ],
    "name:ukr_x_preferred":[
        "\u041e\u0448\u043c\u044f\u043d\u0438"
    ],
    "name:und_x_variant":[
        "Oshmyana"
    ],
    "name:yid_x_preferred":[
        "\u05d0\u05b8\u05e9\u05de\u05e2\u05e0\u05e2/Oshmene"
    ],
    "name:zho_x_preferred":[
        "\u5967\u4ec0\u7c73\u4e9e\u5167"
    ],
    "qs:name":"Ashmyany",
    "qs:photos_9r":0,
    "qs:photos_sr":0,
    "qs:pop_sr":"6",
    "wd:population":15046,
    "wd:wordcount":1280,
    "wof:name":"Ashmyany",
    "wof:placetype":"locality",
    "wof:population":15046
},
  "geometry": {"coordinates":[25.936,54.421],"type":"Point"}
}