{
  "type": "Feature",
  "properties": {
    "gn:admin1_code":"7.0",
    "gn:asciiname":"Kollektivnaya",
    "gn:country_code":"BY",
    "gn:dem":130,
    "gn:feature_class":"P",
    "gn:feature_code":"PPL",
    "gn:name":"Kollektivnaya",
    "gn:population":0,
    "gn:timezone":"Europe/Minsk",
    "iso:country":"BY",
    "name:rus_x_preferred":[
        "\u041a\u043e\u043b\u043b\u0435\u043a\u0442\u0438\u0432\u043d\u0430\u044f"
    ],
    "wof:name":"Kollektivnaya",
    "wof:placetype":"locality"
},
  "geometry": {"coordinates":[28.7204,55.5338],"type":"Point"}
}