{
  "type": "Feature",
  "properties": {
    "gn:admin1_code":"7.0",
    "gn:asciiname":"Mileyki",
    "gn:country_code":"BY",
    "gn:dem":154,
    "gn:feature_class":"P",
    "gn:feature_code":"PPL",
    "gn:name":"Mileyki",
    "gn:population":0,
    "gn:timezone":"Europe/Minsk",
    "iso:country":"BY",
    "name:rus_x_preferred":[
        "\u041c\u0438\u043b\u0435\u0439\u043a\u0438"
    ],
    "wof:name":"Mileyki",
    "wof:placetype":"locality"
},
  "geometry": {"coordinates":[27.5708,55.542],"type":"Point"}
}