{
  "type": "Feature",
  "properties": {
    "gn:admin1_code":"5.0",
    "gn:asciiname":"Mokrad'",
    "gn:country_code":"BY",
    "gn:dem":225,
    "gn:feature_class":"P",
    "gn:feature_code":"PPL",
    "gn:name":"Mokrad\u2019",
    "gn:population":0,
    "gn:timezone":"Europe/Minsk",
    "iso:country":"BY",
    "name:rus_x_preferred":[
        "\u041c\u043e\u043a\u0440\u0430\u0434\u044c"
    ],
    "name:und_x_variant":[
        "Mokrad\u2019"
    ],
    "wof:name":"Mokrad'",
    "wof:placetype":"locality"
},
  "geometry": {"coordinates":[27.9673,54.3388],"type":"Point"}
}