{
  "type": "Feature",
  "properties": {
    "gn:admin1_code":"5.0",
    "gn:asciiname":"Vygoda",
    "gn:country_code":"BY",
    "gn:dem":160,
    "gn:feature_class":"P",
    "gn:feature_code":"PPL",
    "gn:name":"Vygoda",
    "gn:population":0,
    "gn:timezone":"Europe/Minsk",
    "iso:country":"BY",
    "name:rus_x_preferred":[
        "\u0412\u044b\u0433\u043e\u0434\u0430"
    ],
    "wof:name":"Vygoda",
    "wof:placetype":"locality"
},
  "geometry": {"coordinates":[27.0355,52.9273],"type":"Point"}
}