{
  "type": "Feature",
  "properties": {
    "gn:admin1_code":"5.0",
    "gn:asciiname":"Poselok Luchitsy",
    "gn:country_code":"BY",
    "gn:dem":198,
    "gn:feature_class":"P",
    "gn:feature_code":"PPL",
    "gn:name":"Pos\u00eblok Luchitsy",
    "gn:population":0,
    "gn:timezone":"Europe/Minsk",
    "iso:country":"BY",
    "name:rus_x_preferred":[
        "\u041f\u043e\u0441\u0451\u043b\u043e\u043a \u041b\u0443\u0447\u0438\u0446\u044b"
    ],
    "name:und_x_variant":[
        "Pos\u00eblok Luchitsy"
    ],
    "wof:name":"Poselok Luchitsy",
    "wof:placetype":"locality"
},
  "geometry": {"coordinates":[26.9559,53.6747],"type":"Point"}
}