{
  "type": "Feature",
  "properties": {
    "gn:admin1_code":"6.0",
    "gn:asciiname":"Zelenyy Klin",
    "gn:country_code":"BY",
    "gn:dem":169,
    "gn:feature_class":"P",
    "gn:feature_code":"PPL",
    "gn:name":"Zel\u00ebnyy Klin",
    "gn:population":0,
    "gn:timezone":"Europe/Minsk",
    "iso:country":"BY",
    "name:rus_x_preferred":[
        "\u0417\u0435\u043b\u0451\u043d\u044b\u0439 \u041a\u043b\u0438\u043d"
    ],
    "name:und_x_variant":[
        "Zel\u00ebnyy Klin"
    ],
    "wof:name":"Zelenyy Klin",
    "wof:placetype":"locality"
},
  "geometry": {"coordinates":[31.9735,53.6517],"type":"Point"}
}