{
  "type": "Feature",
  "properties": {
    "gn:admin1_code":"3.0",
    "gn:asciiname":"Vostrava",
    "gn:country_code":"BY",
    "gn:dem":165,
    "gn:feature_class":"P",
    "gn:feature_code":"PPL",
    "gn:name":"Vostrava",
    "gn:population":0,
    "gn:timezone":"Europe/Minsk",
    "iso:country":"BY",
    "name:bel_x_preferred":[
        "\u0412\u043e\u0441\u0442\u0440\u0430\u0432\u0430"
    ],
    "name:und_x_variant":[
        "Ostrovo"
    ],
    "wof:name":"Vostrava",
    "wof:placetype":"locality"
},
  "geometry": {"coordinates":[25.0253,52.9504],"type":"Point"}
}