{
  "type": "Feature",
  "properties": {
    "gn:admin1_code":"2.0",
    "gn:asciiname":"Sinitsyn",
    "gn:country_code":"BY",
    "gn:dem":155,
    "gn:feature_class":"P",
    "gn:feature_code":"PPL",
    "gn:name":"Sinitsyn",
    "gn:population":0,
    "gn:timezone":"Europe/Minsk",
    "iso:country":"BY",
    "name:rus_x_preferred":[
        "\u0421\u0438\u043d\u0438\u0446\u044b\u043d"
    ],
    "wof:name":"Sinitsyn",
    "wof:placetype":"locality"
},
  "geometry": {"coordinates":[31.5281,52.7115],"type":"Point"}
}