{
  "type": "Feature",
  "properties": {
    "gn:admin1_code":"3.0",
    "gn:asciiname":"Lesniki",
    "gn:country_code":"BY",
    "gn:dem":169,
    "gn:feature_class":"P",
    "gn:feature_code":"PPL",
    "gn:name":"Lesniki",
    "gn:population":0,
    "gn:timezone":"Europe/Minsk",
    "iso:country":"BY",
    "name:rus_x_preferred":[
        "\u041b\u0435\u0441\u043d\u0438\u043a\u0438"
    ],
    "name:und_x_variant":[
        "Lesnyaki"
    ],
    "wof:name":"Lesniki",
    "wof:placetype":"locality"
},
  "geometry": {"coordinates":[24.2005,53.1144],"type":"Point"}
}