{
  "type": "Feature",
  "properties": {
    "gn:admin1_code":"7.0",
    "gn:asciiname":"Buraki",
    "gn:country_code":"BY",
    "gn:dem":194,
    "gn:feature_class":"P",
    "gn:feature_code":"PPL",
    "gn:name":"Buraki",
    "gn:population":0,
    "gn:timezone":"Europe/Minsk",
    "iso:country":"BY",
    "name:rus_x_preferred":[
        "\u0411\u0443\u0440\u0430\u043a\u0438"
    ],
    "wof:name":"Buraki",
    "wof:placetype":"locality"
},
  "geometry": {"coordinates":[30.8402,55.2436],"type":"Point"}
}