{
  "type": "Feature",
  "properties": {
    "gn:admin1_code":"3.0",
    "gn:asciiname":"Szumieliszki Wielkie",
    "gn:country_code":"BY",
    "gn:dem":186,
    "gn:feature_class":"P",
    "gn:feature_code":"PPL",
    "gn:name":"Szumieliszki Wielkie",
    "gn:population":0,
    "gn:timezone":"Europe/Minsk",
    "iso:country":"BY",
    "name:rus_x_preferred":[
        "\u0411\u043e\u043b\u044c\u0448\u0438\u0435 \u0428\u0443\u043c\u0438\u043b\u0438\u0448\u043a\u0438"
    ],
    "name:und_x_variant":[
        "Shumelishki",
        "Bol\u2019shiye Shumilishki"
    ],
    "wof:name":"Szumieliszki Wielkie",
    "wof:placetype":"locality"
},
  "geometry": {"coordinates":[26.0518,54.4733],"type":"Point"}
}