{
  "type": "Feature",
  "properties": {
    "gn:admin1_code":"5.0",
    "gn:asciiname":"Lukavtsy",
    "gn:country_code":"BY",
    "gn:dem":179,
    "gn:feature_class":"P",
    "gn:feature_code":"PPL",
    "gn:name":"Lukavtsy",
    "gn:population":0,
    "gn:timezone":"Europe/Minsk",
    "iso:country":"BY",
    "name:rus_x_preferred":[
        "\u041b\u0443\u043a\u0430\u0432\u0446\u044b"
    ],
    "name:und_x_variant":[
        "Lukavtse"
    ],
    "wof:name":"Lukavtsy",
    "wof:placetype":"locality"
},
  "geometry": {"coordinates":[26.5993,53.088],"type":"Point"}
}