{
  "type": "Feature",
  "properties": {
    "gn:admin1_code":"6.0",
    "gn:asciiname":"Sevast'yanovka",
    "gn:country_code":"BY",
    "gn:dem":142,
    "gn:feature_class":"P",
    "gn:feature_code":"PPL",
    "gn:name":"Sevast\u2019yanovka",
    "gn:population":0,
    "gn:timezone":"Europe/Minsk",
    "iso:country":"BY",
    "name:rus_x_preferred":[
        "\u0421\u0435\u0432\u0430\u0441\u0442\u044c\u044f\u043d\u043e\u0432\u043a\u0430"
    ],
    "name:und_x_variant":[
        "Sevast\u2019yanovka"
    ],
    "wof:name":"Sevast'yanovka",
    "wof:placetype":"locality"
},
  "geometry": {"coordinates":[29.836,53.3543],"type":"Point"}
}