{
  "type": "Feature",
  "properties": {
    "gn:admin1_code":"3.0",
    "gn:asciiname":"Kuplya",
    "gn:country_code":"BY",
    "gn:dem":158,
    "gn:feature_class":"P",
    "gn:feature_code":"PPL",
    "gn:name":"Kuplya",
    "gn:population":0,
    "gn:timezone":"Europe/Minsk",
    "iso:country":"BY",
    "name:rus_x_preferred":[
        "\u041a\u0443\u043f\u043b\u044f"
    ],
    "wof:name":"Kuplya",
    "wof:placetype":"locality"
},
  "geometry": {"coordinates":[26.4485,54.7413],"type":"Point"}
}