{
  "type": "Feature",
  "properties": {
    "gn:admin1_code":"5.0",
    "gn:asciiname":"Gorodechno",
    "gn:country_code":"BY",
    "gn:dem":187,
    "gn:feature_class":"P",
    "gn:feature_code":"PPL",
    "gn:name":"Gorodechno",
    "gn:population":0,
    "gn:timezone":"Europe/Minsk",
    "iso:country":"BY",
    "name:rus_x_preferred":[
        "\u0413\u043e\u0440\u043e\u0434\u0435\u0447\u043d\u043e"
    ],
    "wof:name":"Gorodechno",
    "wof:placetype":"locality"
},
  "geometry": {"coordinates":[26.4708,54.2268],"type":"Point"}
}