{
  "type": "Feature",
  "properties": {
    "gn:admin1_code":"7.0",
    "gn:asciiname":"Deriporty",
    "gn:country_code":"BY",
    "gn:dem":137,
    "gn:feature_class":"P",
    "gn:feature_code":"PPL",
    "gn:name":"Deriporty",
    "gn:population":0,
    "gn:timezone":"Europe/Minsk",
    "iso:country":"BY",
    "name:rus_x_preferred":[
        "\u0414\u0435\u0440\u0438\u043f\u043e\u0440\u0442\u044b"
    ],
    "wof:name":"Deriporty",
    "wof:placetype":"locality"
},
  "geometry": {"coordinates":[27.5769,55.733],"type":"Point"}
}