{
  "type": "Feature",
  "properties": {
    "gn:admin1_code":"3.0",
    "gn:asciiname":"Panartsy",
    "gn:country_code":"BY",
    "gn:dem":150,
    "gn:feature_class":"P",
    "gn:feature_code":"PPL",
    "gn:name":"Panartsy",
    "gn:population":0,
    "gn:timezone":"Europe/Minsk",
    "iso:country":"BY",
    "name:rus_x_preferred":[
        "\u041f\u0430\u043d\u0430\u0440\u0446\u044b"
    ],
    "wof:name":"Panartsy",
    "wof:placetype":"locality"
},
  "geometry": {"coordinates":[26.017,54.8282],"type":"Point"}
}