{
  "type": "Feature",
  "properties": {
    "gn:admin1_code":"7.0",
    "gn:asciiname":"Tyaplyaki",
    "gn:country_code":"BY",
    "gn:dem":171,
    "gn:feature_class":"P",
    "gn:feature_code":"PPL",
    "gn:name":"Tyaplyaki",
    "gn:population":0,
    "gn:timezone":"Europe/Minsk",
    "iso:country":"BY",
    "name:rus_x_preferred":[
        "\u0422\u044f\u043f\u043b\u044f\u043a\u0438"
    ],
    "name:und_x_variant":[
        "Teplyaki"
    ],
    "wof:name":"Tyaplyaki",
    "wof:placetype":"locality"
},
  "geometry": {"coordinates":[29.9223,54.9037],"type":"Point"}
}