{
  "type": "Feature",
  "properties": {
    "gn:admin1_code":"7.0",
    "gn:asciiname":"Zhestyanka",
    "gn:country_code":"BY",
    "gn:dem":149,
    "gn:feature_class":"P",
    "gn:feature_code":"PPL",
    "gn:name":"Zhestyanka",
    "gn:population":0,
    "gn:timezone":"Europe/Minsk",
    "iso:country":"BY",
    "name:rus_x_preferred":[
        "\u0416\u0435\u0441\u0442\u044f\u043d\u043a\u0430"
    ],
    "wof:name":"Zhestyanka",
    "wof:placetype":"locality"
},
  "geometry": {"coordinates":[29.0533,54.8742],"type":"Point"}
}