{
  "type": "Feature",
  "properties": {
    "gn:admin1_code":"2.0",
    "gn:asciiname":"Artel'",
    "gn:country_code":"BY",
    "gn:dem":133,
    "gn:feature_class":"P",
    "gn:feature_code":"PPL",
    "gn:name":"Artel\u2019",
    "gn:population":0,
    "gn:timezone":"Europe/Minsk",
    "iso:country":"BY",
    "wof:name":"Artel'",
    "wof:placetype":"locality"
},
  "geometry": {"coordinates":[30.74028,52.56417],"type":"Point"}
}