{
  "type": "Feature",
  "properties": {
    "gn:admin1_code":"5.0",
    "gn:asciiname":"Teleshevichi",
    "gn:country_code":"BY",
    "gn:dem":206,
    "gn:feature_class":"P",
    "gn:feature_code":"PPL",
    "gn:name":"Teleshevichi",
    "gn:population":0,
    "gn:timezone":"Europe/Minsk",
    "iso:country":"BY",
    "name:rus_x_preferred":[
        "\u0422\u0435\u043b\u0435\u0448\u0435\u0432\u0438\u0447\u0438"
    ],
    "name:und_x_variant":[
        "Telyashevichi"
    ],
    "wof:name":"Teleshevichi",
    "wof:placetype":"locality"
},
  "geometry": {"coordinates":[26.906,53.7239],"type":"Point"}
}