{
  "type": "Feature",
  "properties": {
    "gn:admin1_code":"2.0",
    "gn:asciiname":"Boderyy",
    "gn:country_code":"BY",
    "gn:dem":137,
    "gn:feature_class":"P",
    "gn:feature_code":"PPL",
    "gn:name":"Boderyy",
    "gn:population":0,
    "gn:timezone":"Europe/Minsk",
    "iso:country":"BY",
    "name:rus_x_preferred":[
        "\u0411\u043e\u0434\u0435\u0440\u044b\u0439"
    ],
    "wof:name":"Boderyy",
    "wof:placetype":"locality"
},
  "geometry": {"coordinates":[30.5924,52.6706],"type":"Point"}
}