{
  "type": "Feature",
  "properties": {
    "gn:admin1_code":"6.0",
    "gn:asciiname":"Dudakovichy",
    "gn:country_code":"BY",
    "gn:dem":203,
    "gn:feature_class":"P",
    "gn:feature_code":"PPL",
    "gn:name":"Dudakovichy",
    "gn:population":0,
    "gn:timezone":"Europe/Minsk",
    "iso:country":"BY",
    "name:bel_x_preferred":[
        "\u0414\u0443\u0434\u0430\u043a\u043e\u0432\u0456\u0447\u044b"
    ],
    "name:und_x_variant":[
        "Dudakovichi"
    ],
    "wof:name":"Dudakovichy",
    "wof:placetype":"locality"
},
  "geometry": {"coordinates":[29.9076,54.2881],"type":"Point"}
}