{
  "type": "Feature",
  "properties": {
    "gn:admin1_code":"5.0",
    "gn:asciiname":"Belavichi",
    "gn:country_code":"BY",
    "gn:dem":166,
    "gn:feature_class":"P",
    "gn:feature_code":"PPL",
    "gn:name":"Belavichi",
    "gn:population":0,
    "gn:timezone":"Europe/Minsk",
    "iso:country":"BY",
    "name:eng_x_preferred":[
        "Belavichi"
    ],
    "name:rus_x_preferred":[
        "\u0411\u0435\u043b\u0430\u0432\u0438\u0447\u0438"
    ],
    "name:und_x_variant":[
        "Byelavichi",
        "Belavichi"
    ],
    "wof:name":"Belavichi",
    "wof:placetype":"locality"
},
  "geometry": {"coordinates":[29.1796,54.0456],"type":"Point"}
}