{
  "type": "Feature",
  "properties": {
    "gn:admin1_code":"7.0",
    "gn:asciiname":"Pustynki",
    "gn:country_code":"BY",
    "gn:dem":156,
    "gn:feature_class":"P",
    "gn:feature_code":"PPL",
    "gn:name":"Pustynki",
    "gn:population":0,
    "gn:timezone":"Europe/Minsk",
    "iso:country":"BY",
    "name:rus_x_preferred":[
        "\u041f\u0443\u0441\u0442\u044b\u043d\u043a\u0438"
    ],
    "wof:name":"Pustynki",
    "wof:placetype":"locality"
},
  "geometry": {"coordinates":[29.9079,54.8484],"type":"Point"}
}