{
  "type": "Feature",
  "properties": {
    "gn:admin1_code":"6.0",
    "gn:asciiname":"Kholdeyevka",
    "gn:country_code":"BY",
    "gn:dem":172,
    "gn:feature_class":"P",
    "gn:feature_code":"PPL",
    "gn:name":"Kholdeyevka",
    "gn:population":0,
    "gn:timezone":"Europe/Minsk",
    "iso:country":"BY",
    "name:rus_x_preferred":[
        "\u0425\u043e\u043b\u0434\u0435\u0435\u0432\u043a\u0430"
    ],
    "wof:name":"Kholdeyevka",
    "wof:placetype":"locality"
},
  "geometry": {"coordinates":[32.1764,53.47600000000001],"type":"Point"}
}