{
  "type": "Feature",
  "properties": {
    "gn:admin1_code":"2.0",
    "gn:asciiname":"Mitski",
    "gn:country_code":"BY",
    "gn:dem":142,
    "gn:feature_class":"P",
    "gn:feature_code":"PPL",
    "gn:name":"Mitski",
    "gn:population":0,
    "gn:timezone":"Europe/Minsk",
    "iso:country":"BY",
    "name:fra_x_preferred":[
        "Mitski"
    ],
    "name:ita_x_preferred":[
        "Mitski"
    ],
    "name:jpn_x_preferred":[
        "\u30df\u30c4\u30ad\u30fb\u30df\u30e4\u30ef\u30ad"
    ],
    "name:por_x_preferred":[
        "Mitski"
    ],
    "name:rus_x_preferred":[
        "\u041c\u0438\u0442\u044c\u043a\u0438"
    ],
    "name:swe_x_preferred":[
        "Mitski"
    ],
    "name:und_x_variant":[
        "Mit\u2019ki"
    ],
    "wof:name":"Mitski",
    "wof:placetype":"locality"
},
  "geometry": {"coordinates":[29.3392,51.9243],"type":"Point"}
}