{
  "type": "Feature",
  "properties": {
    "gn:admin1_code":"6.0",
    "gn:asciiname":"Vetrenka",
    "gn:country_code":"BY",
    "gn:dem":144,
    "gn:feature_class":"P",
    "gn:feature_code":"PPL",
    "gn:name":"Vetrenka",
    "gn:population":0,
    "gn:timezone":"Europe/Minsk",
    "iso:country":"BY",
    "name:rus_x_preferred":[
        "\u0412\u0435\u0442\u0440\u0435\u043d\u043a\u0430"
    ],
    "wof:name":"Vetrenka",
    "wof:placetype":"locality"
},
  "geometry": {"coordinates":[30.4698,53.5257],"type":"Point"}
}