{
  "type": "Feature",
  "properties": {
    "gn:admin1_code":"5.0",
    "gn:asciiname":"Selitskoye",
    "gn:country_code":"BY",
    "gn:dem":171,
    "gn:feature_class":"P",
    "gn:feature_code":"PPL",
    "gn:name":"Selitskoye",
    "gn:population":0,
    "gn:timezone":"Europe/Minsk",
    "iso:country":"BY",
    "name:rus_x_preferred":[
        "\u0421\u0435\u043b\u0438\u0446\u043a\u043e\u0435"
    ],
    "wof:name":"Selitskoye",
    "wof:placetype":"locality"
},
  "geometry": {"coordinates":[29.0379,54.3068],"type":"Point"}
}