{
  "type": "Feature",
  "properties": {
    "gn:admin1_code":"6.0",
    "gn:asciiname":"Davydavichy",
    "gn:country_code":"BY",
    "gn:dem":152,
    "gn:feature_class":"P",
    "gn:feature_code":"PPL",
    "gn:name":"Davydavichy",
    "gn:population":0,
    "gn:timezone":"Europe/Minsk",
    "iso:country":"BY",
    "name:bel_x_preferred":[
        "\u0414\u0430\u0432\u044b\u0434\u0430\u0432\u0456\u0447\u044b"
    ],
    "name:und_x_variant":[
        "Davydovichi"
    ],
    "wof:name":"Davydavichy",
    "wof:placetype":"locality"
},
  "geometry": {"coordinates":[30.6221,53.6245],"type":"Point"}
}