{
  "type": "Feature",
  "properties": {
    "gn:admin1_code":"2.0",
    "gn:asciiname":"Parkhimkovskaya Sloboda",
    "gn:country_code":"BY",
    "gn:dem":146,
    "gn:feature_class":"P",
    "gn:feature_code":"PPL",
    "gn:name":"Parkhimkovskaya Sloboda",
    "gn:population":0,
    "gn:timezone":"Europe/Minsk",
    "iso:country":"BY",
    "name:rus_x_preferred":[
        "\u041f\u0430\u0440\u0445\u0438\u043c\u043a\u043e\u0432\u0441\u043a\u0430\u044f \u0421\u043b\u043e\u0431\u043e\u0434\u0430"
    ],
    "wof:name":"Parkhimkovskaya Sloboda",
    "wof:placetype":"locality"
},
  "geometry": {"coordinates":[29.6933,53.1458],"type":"Point"}
}