{
  "type": "Feature",
  "properties": {
    "gn:admin1_code":"7.0",
    "gn:asciiname":"Gudelishki",
    "gn:country_code":"BY",
    "gn:dem":175,
    "gn:feature_class":"P",
    "gn:feature_code":"PPL",
    "gn:name":"Gudelishki",
    "gn:population":0,
    "gn:timezone":"Europe/Minsk",
    "iso:country":"BY",
    "name:rus_x_preferred":[
        "\u0413\u0443\u0434\u0435\u043b\u0438\u0448\u043a\u0438"
    ],
    "wof:name":"Gudelishki",
    "wof:placetype":"locality"
},
  "geometry": {"coordinates":[26.3843,55.1368],"type":"Point"}
}