{
  "type": "Feature",
  "properties": {
    "gn:admin1_code":"5.0",
    "gn:admin2_code":"625140",
    "gn:asciiname":"Halowki",
    "gn:country_code":"BY",
    "gn:dem":276,
    "gn:feature_class":"P",
    "gn:feature_code":"PPL",
    "gn:name":"Halowki",
    "gn:population":0,
    "gn:timezone":"Europe/Minsk",
    "iso:country":"BY",
    "name:bel_x_preferred":[
        "\u0413\u0430\u043b\u043e\u045e\u043a\u0456"
    ],
    "name:bel_x_variant":[
        "Halo\u016dki"
    ],
    "name:pol_x_preferred":[
        "Ho\u0142\u00f3wki"
    ],
    "name:rus_x_preferred":[
        "Golovki"
    ],
    "name:rus_x_variant":[
        "\u0413\u043e\u043b\u043e\u0432\u043a\u0438"
    ],
    "name:ukr_x_preferred":[
        "\u0413\u0430\u043b\u043e\u0432\u043a\u0456"
    ],
    "name:und_x_variant":[
        "Galovki",
        "Galowki"
    ],
    "wof:name":"Halowki",
    "wof:placetype":"locality"
},
  "geometry": {"coordinates":[27.31900000000001,53.899],"type":"Point"}
}