{
  "type": "Feature",
  "properties": {
    "gn:admin1_code":"7.0",
    "gn:asciiname":"Sinitsy",
    "gn:country_code":"BY",
    "gn:dem":144,
    "gn:feature_class":"P",
    "gn:feature_code":"PPL",
    "gn:name":"Sinitsy",
    "gn:population":0,
    "gn:timezone":"Europe/Minsk",
    "iso:country":"BY",
    "name:rus_x_preferred":[
        "\u0421\u0438\u043d\u0438\u0446\u044b"
    ],
    "wof:name":"Sinitsy",
    "wof:placetype":"locality"
},
  "geometry": {"coordinates":[29.779,55.0696],"type":"Point"}
}