{
  "type": "Feature",
  "properties": {
    "gn:admin1_code":"5.0",
    "gn:asciiname":"Galimtsy",
    "gn:country_code":"BY",
    "gn:dem":204,
    "gn:feature_class":"P",
    "gn:feature_code":"PPL",
    "gn:name":"Galimtsy",
    "gn:population":0,
    "gn:timezone":"Europe/Minsk",
    "iso:country":"BY",
    "name:rus_x_preferred":[
        "\u0413\u0430\u043b\u0438\u043c\u0446\u044b"
    ],
    "name:und_x_variant":[
        "Galimtse",
        "Galimtsy"
    ],
    "wof:name":"Galimtsy",
    "wof:placetype":"locality"
},
  "geometry": {"coordinates":[26.8937,53.9596],"type":"Point"}
}