{
  "type": "Feature",
  "properties": {
    "gn:admin1_code":"7.0",
    "gn:asciiname":"Solov'i",
    "gn:country_code":"BY",
    "gn:dem":171,
    "gn:feature_class":"P",
    "gn:feature_code":"PPL",
    "gn:name":"Solov\u2019i",
    "gn:population":0,
    "gn:timezone":"Europe/Minsk",
    "iso:country":"BY",
    "name:rus_x_preferred":[
        "\u0421\u043e\u043b\u043e\u0432\u044c\u0438"
    ],
    "name:und_x_variant":[
        "Solov\u2019i"
    ],
    "wof:name":"Solov'i",
    "wof:placetype":"locality"
},
  "geometry": {"coordinates":[26.7664,55.0632],"type":"Point"}
}