{
  "type": "Feature",
  "properties": {
    "gn:admin1_code":"7.0",
    "gn:asciiname":"Luni",
    "gn:country_code":"BY",
    "gn:dem":129,
    "gn:feature_class":"P",
    "gn:feature_code":"PPL",
    "gn:name":"Luni",
    "gn:population":0,
    "gn:timezone":"Europe/Minsk",
    "iso:country":"BY",
    "name:rus_x_preferred":[
        "\u041b\u0443\u043d\u0438"
    ],
    "name:und_x_variant":[
        "\u0141unie",
        "Lune",
        "Luni"
    ],
    "wof:name":"Luni",
    "wof:placetype":"locality"
},
  "geometry": {"coordinates":[27.1609,55.7165],"type":"Point"}
}