{
  "type": "Feature",
  "properties": {
    "gn:admin1_code":"3.0",
    "gn:asciiname":"Tolochki",
    "gn:country_code":"BY",
    "gn:dem":122,
    "gn:feature_class":"P",
    "gn:feature_code":"PPL",
    "gn:name":"Tolochki",
    "gn:population":0,
    "gn:timezone":"Europe/Minsk",
    "iso:country":"BY",
    "name:bel_x_preferred":[
        "Talochki"
    ],
    "name:bel_x_variant":[
        "\u0422\u0430\u043b\u043e\u0447\u043a\u0456"
    ],
    "name:rus_x_preferred":[
        "\u0422\u043e\u043b\u043b\u043e\u0447\u043a\u0438"
    ],
    "name:rus_x_variant":[
        "\u0422\u043e\u043b\u043e\u0447\u043a\u0438"
    ],
    "name:und_x_variant":[
        "Tollochki",
        "Tolochki"
    ],
    "wof:name":"Tolochki",
    "wof:placetype":"locality"
},
  "geometry": {"coordinates":[24.1038,53.6467],"type":"Point"}
}