{
  "type": "Feature",
  "properties": {
    "gn:admin1_code":"7.0",
    "gn:asciiname":"Doluyevo",
    "gn:country_code":"BY",
    "gn:dem":141,
    "gn:feature_class":"P",
    "gn:feature_code":"PPL",
    "gn:name":"Doluyevo",
    "gn:population":0,
    "gn:timezone":"Europe/Minsk",
    "iso:country":"BY",
    "name:rus_x_preferred":[
        "\u0414\u043e\u043b\u0443\u0435\u0432\u043e"
    ],
    "wof:name":"Doluyevo",
    "wof:placetype":"locality"
},
  "geometry": {"coordinates":[29.3646,55.1637],"type":"Point"}
}