{
  "type": "Feature",
  "properties": {
    "gn:admin1_code":"7.0",
    "gn:asciiname":"Oreshniki",
    "gn:country_code":"BY",
    "gn:dem":157,
    "gn:feature_class":"P",
    "gn:feature_code":"PPL",
    "gn:name":"Oreshniki",
    "gn:population":0,
    "gn:timezone":"Europe/Minsk",
    "iso:country":"BY",
    "name:rus_x_preferred":[
        "\u041e\u0440\u0435\u0448\u043d\u0438\u043a\u0438"
    ],
    "wof:name":"Oreshniki",
    "wof:placetype":"locality"
},
  "geometry": {"coordinates":[30.7073,55.3801],"type":"Point"}
}