{
  "type": "Feature",
  "properties": {
    "gn:admin1_code":"2.0",
    "gn:asciiname":"Novaya Niva",
    "gn:country_code":"BY",
    "gn:dem":146,
    "gn:feature_class":"P",
    "gn:feature_code":"PPL",
    "gn:name":"Novaya Niva",
    "gn:population":0,
    "gn:timezone":"Europe/Minsk",
    "iso:country":"BY",
    "name:rus_x_preferred":[
        "\u041d\u043e\u0432\u0430\u044f \u041d\u0438\u0432\u0430"
    ],
    "wof:name":"Novaya Niva",
    "wof:placetype":"locality"
},
  "geometry": {"coordinates":[29.4695,51.9367],"type":"Point"}
}