{
  "type": "Feature",
  "properties": {
    "gn:admin1_code":"1.0",
    "gn:asciiname":"Pruska",
    "gn:country_code":"BY",
    "gn:dem":149,
    "gn:feature_class":"P",
    "gn:feature_code":"PPL",
    "gn:name":"Pruska",
    "gn:population":0,
    "gn:timezone":"Europe/Minsk",
    "iso:country":"BY",
    "name:fra_x_preferred":[
        "Pruska"
    ],
    "name:lit_x_preferred":[
        "Pruska"
    ],
    "name:pol_x_preferred":[
        "Pruska"
    ],
    "name:rus_x_preferred":[
        "\u041f\u0440\u0443\u0441\u043a\u0430-\u0412\u0435\u043b\u0438\u0432\u0435\u0439\u0441\u043a\u0430\u044f"
    ],
    "name:ukr_x_preferred":[
        "\u041f\u0440\u0443\u0441\u044c\u043a\u0430"
    ],
    "name:und_x_variant":[
        "Pruska Veloveyska",
        "Pruska Veliveyskaya"
    ],
    "wof:name":"Pruska",
    "wof:placetype":"locality"
},
  "geometry": {"coordinates":[23.8872,52.3734],"type":"Point"}
}