{
  "type": "Feature",
  "properties": {
    "gn:admin1_code":"7.0",
    "gn:asciiname":"Kupelka",
    "gn:country_code":"BY",
    "gn:dem":166,
    "gn:feature_class":"P",
    "gn:feature_code":"PPL",
    "gn:name":"Kupelka",
    "gn:population":0,
    "gn:timezone":"Europe/Minsk",
    "iso:country":"BY",
    "name:rus_x_preferred":[
        "\u041a\u0443\u043f\u0435\u043b\u043a\u0430"
    ],
    "wof:name":"Kupelka",
    "wof:placetype":"locality"
},
  "geometry": {"coordinates":[30.451,54.6611],"type":"Point"}
}