{
  "type": "Feature",
  "properties": {
    "gn:admin1_code":"7.0",
    "gn:asciiname":"Timoshkovo",
    "gn:country_code":"BY",
    "gn:dem":129,
    "gn:feature_class":"P",
    "gn:feature_code":"PPL",
    "gn:name":"Timoshkovo",
    "gn:population":0,
    "gn:timezone":"Europe/Minsk",
    "iso:country":"BY",
    "name:eng_x_preferred":[
        "Timoshki"
    ],
    "name:rus_x_preferred":[
        "\u0422\u0438\u043c\u043e\u0448\u043a\u043e\u0432\u043e"
    ],
    "name:und_x_variant":[
        "Cimoszkowo",
        "Tsimoshkovo",
        "Timoshki",
        "Timoshkovo"
    ],
    "wof:name":"Timoshkovo",
    "wof:placetype":"locality"
},
  "geometry": {"coordinates":[28.0482,55.6379],"type":"Point"}
}