{
  "type": "Feature",
  "properties": {
    "gn:admin1_code":"3.0",
    "gn:asciiname":"Lizheyki",
    "gn:country_code":"BY",
    "gn:dem":175,
    "gn:feature_class":"P",
    "gn:feature_code":"PPL",
    "gn:name":"Lizheyki",
    "gn:population":0,
    "gn:timezone":"Europe/Minsk",
    "iso:country":"BY",
    "name:bel_x_preferred":[
        "\u041b\u0456\u0436\u044d\u0439\u043a\u0456"
    ],
    "name:rus_x_preferred":[
        "\u041b\u0438\u0436\u0435\u0439\u043a\u0438"
    ],
    "wof:name":"Lizheyki",
    "wof:placetype":"locality"
},
  "geometry": {"coordinates":[25.589,53.5022],"type":"Point"}
}