{
  "type": "Feature",
  "properties": {
    "gn:admin1_code":"5.0",
    "gn:asciiname":"Stepury",
    "gn:country_code":"BY",
    "gn:dem":191,
    "gn:feature_class":"P",
    "gn:feature_code":"PPL",
    "gn:name":"Stepury",
    "gn:population":0,
    "gn:timezone":"Europe/Minsk",
    "iso:country":"BY",
    "name:rus_x_preferred":[
        "\u0421\u0442\u0435\u043f\u0443\u0440\u044b"
    ],
    "wof:name":"Stepury",
    "wof:placetype":"locality"
},
  "geometry": {"coordinates":[26.976,53.1268],"type":"Point"}
}