{
  "type": "Feature",
  "properties": {
    "gn:admin1_code":"0.0",
    "gn:asciiname":"Mazulevo",
    "gn:cc2":"BY",
    "gn:country_code":"BY",
    "gn:dem":234,
    "gn:feature_class":"P",
    "gn:feature_code":"PPL",
    "gn:name":"Mazul\u00ebvo",
    "gn:population":0,
    "gn:timezone":"Europe/Minsk",
    "iso:country":"BY",
    "name:und_x_variant":[
        "Mazulewo",
        "Mazul\u00ebvo"
    ],
    "wof:name":"Mazulevo",
    "wof:placetype":"locality"
},
  "geometry": {"coordinates":[26.91667,54.05],"type":"Point"}
}