{
  "type": "Feature",
  "properties": {
    "gn:admin1_code":"6.0",
    "gn:asciiname":"Ivanovichi",
    "gn:country_code":"BY",
    "gn:dem":177,
    "gn:feature_class":"P",
    "gn:feature_code":"PPL",
    "gn:name":"Ivanovichi",
    "gn:population":0,
    "gn:timezone":"Europe/Minsk",
    "iso:country":"BY",
    "name:eng_x_preferred":[
        "Ivanovichi"
    ],
    "name:rus_x_preferred":[
        "\u0412\u0430\u0441\u044c\u043a\u043e\u0432\u0438\u0447\u0438"
    ],
    "name:rus_x_variant":[
        "\u0418\u0432\u0430\u043d\u043e\u0432\u0438\u0447\u0438"
    ],
    "wof:name":"Ivanovichi",
    "wof:placetype":"locality"
},
  "geometry": {"coordinates":[30.7169,53.9204],"type":"Point"}
}