{
  "type": "Feature",
  "properties": {
    "gn:admin1_code":"2.0",
    "gn:asciiname":"Muraveynitsa",
    "gn:country_code":"BY",
    "gn:dem":124,
    "gn:feature_class":"P",
    "gn:feature_code":"PPL",
    "gn:name":"Muraveynitsa",
    "gn:population":0,
    "gn:timezone":"Europe/Minsk",
    "iso:country":"BY",
    "name:rus_x_preferred":[
        "\u041c\u0443\u0440\u0430\u0432\u0435\u0439\u043d\u0438\u0446\u0430"
    ],
    "wof:name":"Muraveynitsa",
    "wof:placetype":"locality"
},
  "geometry": {"coordinates":[29.331,52.1948],"type":"Point"}
}