{
  "type": "Feature",
  "properties": {
    "gn:admin1_code":"6.0",
    "gn:asciiname":"Nezovka",
    "gn:country_code":"BY",
    "gn:dem":169,
    "gn:feature_class":"P",
    "gn:feature_code":"PPL",
    "gn:name":"Nezovka",
    "gn:population":0,
    "gn:timezone":"Europe/Minsk",
    "iso:country":"BY",
    "name:rus_x_preferred":[
        "\u041d\u0435\u0437\u043e\u0432\u043a\u0430"
    ],
    "wof:name":"Nezovka",
    "wof:placetype":"locality"
},
  "geometry": {"coordinates":[30.0145,53.7046],"type":"Point"}
}