{
  "type": "Feature",
  "properties": {
    "gn:admin1_code":"7.0",
    "gn:asciiname":"Lukashova",
    "gn:country_code":"BY",
    "gn:dem":182,
    "gn:feature_class":"P",
    "gn:feature_code":"PPL",
    "gn:name":"Lukashova",
    "gn:population":0,
    "gn:timezone":"Europe/Minsk",
    "iso:country":"BY",
    "name:bel_x_preferred":[
        "\u041b\u0443\u043a\u0430\u0448\u043e\u0432\u0430"
    ],
    "name:und_x_variant":[
        "\u0141ukaszewo",
        "Lukash\u00ebvo",
        "Lukashova",
        "Lukashovo"
    ],
    "wof:name":"Lukashova",
    "wof:placetype":"locality"
},
  "geometry": {"coordinates":[27.0449,55.0451],"type":"Point"}
}