{
  "type": "Feature",
  "properties": {
    "gn:admin1_code":"1.0",
    "gn:asciiname":"Bulkowo",
    "gn:country_code":"BY",
    "gn:dem":137,
    "gn:feature_class":"P",
    "gn:feature_code":"PPL",
    "gn:name":"Bulkowo",
    "gn:population":0,
    "gn:timezone":"Europe/Minsk",
    "iso:country":"BY",
    "name:azb_x_preferred":[
        "\u0628\u0648\u0644\u06a9\u0648\u0648\u0648"
    ],
    "name:ceb_x_preferred":[
        "Bulkowo"
    ],
    "name:deu_x_preferred":[
        "Bulkowo"
    ],
    "name:fas_x_preferred":[
        "\u0628\u0648\u0644\u06a9\u0648\u0648\u0648"
    ],
    "name:fra_x_preferred":[
        "Bulkowo"
    ],
    "name:nld_x_preferred":[
        "Bulkowo"
    ],
    "name:pol_x_preferred":[
        "Bulkowo"
    ],
    "name:rus_x_preferred":[
        "Bul\u2019kovo"
    ],
    "name:rus_x_variant":[
        "\u0411\u0443\u043b\u044c\u043a\u043e\u0432\u043e"
    ],
    "name:ukr_x_preferred":[
        "\u0411\u0443\u043b\u044c\u043a\u043e\u0432\u043e"
    ],
    "name:und_x_variant":[
        "Bul\u2019koro"
    ],
    "wof:name":"Bulkowo",
    "wof:placetype":"locality"
},
  "geometry": {"coordinates":[23.938,52.1209],"type":"Point"}
}