{
  "type": "Feature",
  "properties": {
    "gn:admin1_code":"7.0",
    "gn:asciiname":"Moskovskaya Gora",
    "gn:country_code":"BY",
    "gn:dem":184,
    "gn:feature_class":"P",
    "gn:feature_code":"PPL",
    "gn:name":"Moskovskaya Gora",
    "gn:population":0,
    "gn:timezone":"Europe/Minsk",
    "iso:country":"BY",
    "name:rus_x_preferred":[
        "\u041c\u043e\u0441\u043a\u043e\u0432\u0441\u043a\u0430\u044f \u0413\u043e\u0440\u0430"
    ],
    "wof:name":"Moskovskaya Gora",
    "wof:placetype":"locality"
},
  "geometry": {"coordinates":[29.0281,54.724],"type":"Point"}
}