{
  "type": "Feature",
  "properties": {
    "gn:admin1_code":"7.0",
    "gn:asciiname":"Lemnitsa",
    "gn:country_code":"BY",
    "gn:dem":173,
    "gn:feature_class":"P",
    "gn:feature_code":"PPL",
    "gn:name":"Lemnitsa",
    "gn:population":0,
    "gn:timezone":"Europe/Minsk",
    "iso:country":"BY",
    "name:eng_x_preferred":[
        "Lemnitsa"
    ],
    "name:rus_x_preferred":[
        "\u041b\u0435\u043c\u043d\u0438\u0446\u0430"
    ],
    "wof:name":"Lemnitsa",
    "wof:placetype":"locality"
},
  "geometry": {"coordinates":[30.5684,55.3852],"type":"Point"}
}