{
  "type": "Feature",
  "properties": {
    "gn:admin1_code":"7.0",
    "gn:asciiname":"Lesovyye",
    "gn:country_code":"BY",
    "gn:dem":159,
    "gn:feature_class":"P",
    "gn:feature_code":"PPL",
    "gn:name":"Lesovyye",
    "gn:population":0,
    "gn:timezone":"Europe/Minsk",
    "iso:country":"BY",
    "name:rus_x_preferred":[
        "\u041b\u0435\u0441\u043e\u0432\u044b\u0435"
    ],
    "wof:name":"Lesovyye",
    "wof:placetype":"locality"
},
  "geometry": {"coordinates":[30.0547,55.195],"type":"Point"}
}