{
  "type": "Feature",
  "properties": {
    "gn:admin1_code":"7.0",
    "gn:asciiname":"Lavruki",
    "gn:country_code":"BY",
    "gn:dem":116,
    "gn:feature_class":"P",
    "gn:feature_code":"PPL",
    "gn:name":"Lavruki",
    "gn:population":0,
    "gn:timezone":"Europe/Minsk",
    "iso:country":"BY",
    "name:rus_x_preferred":[
        "\u041b\u0430\u0432\u0440\u0443\u043a\u0438"
    ],
    "wof:name":"Lavruki",
    "wof:placetype":"locality"
},
  "geometry": {"coordinates":[28.2165,55.769],"type":"Point"}
}