{
  "type": "Feature",
  "properties": {
    "gn:admin1_code":"5.0",
    "gn:asciiname":"Rusaki",
    "gn:country_code":"BY",
    "gn:dem":230,
    "gn:feature_class":"P",
    "gn:feature_code":"PPL",
    "gn:name":"Rusaki",
    "gn:population":0,
    "gn:timezone":"Europe/Minsk",
    "iso:country":"BY",
    "name:fra_x_preferred":[
        "Rusaki"
    ],
    "name:lit_x_preferred":[
        "Rusakai"
    ],
    "name:pol_x_preferred":[
        "Rusaki"
    ],
    "name:rus_x_preferred":[
        "\u0420\u0443\u0441\u0430\u043a\u0438"
    ],
    "name:ukr_x_preferred":[
        "\u0420\u0443\u0441\u0430\u043a\u0456"
    ],
    "wof:name":"Rusaki",
    "wof:placetype":"locality"
},
  "geometry": {"coordinates":[27.8532,54.4373],"type":"Point"}
}