{
  "type": "Feature",
  "properties": {
    "gn:admin1_code":"6.0",
    "gn:asciiname":"Kowbcha",
    "gn:country_code":"BY",
    "gn:dem":160,
    "gn:feature_class":"P",
    "gn:feature_code":"PPL",
    "gn:name":"Kowbcha",
    "gn:population":0,
    "gn:timezone":"Europe/Minsk",
    "iso:country":"BY",
    "name:bel_x_preferred":[
        "\u041a\u043e\u045e\u0431\u0447\u0430"
    ],
    "name:eng_x_preferred":[
        "Kolbcha"
    ],
    "name:rus_x_preferred":[
        "\u041a\u043e\u043b\u0431\u0447\u0430"
    ],
    "name:und_x_variant":[
        "Kowbcha"
    ],
    "wof:name":"Kowbcha",
    "wof:placetype":"locality"
},
  "geometry": {"coordinates":[29.2346,53.6485],"type":"Point"}
}