{
  "type": "Feature",
  "properties": {
    "gn:admin1_code":"6.0",
    "gn:asciiname":"Rudnya",
    "gn:country_code":"BY",
    "gn:dem":152,
    "gn:feature_class":"P",
    "gn:feature_code":"PPL",
    "gn:name":"Rudnya",
    "gn:population":0,
    "gn:timezone":"Europe/Minsk",
    "iso:country":"BY",
    "name:ceb_x_preferred":[
        "Rudnya"
    ],
    "name:rus_x_preferred":[
        "\u0420\u0443\u0434\u043d\u044f"
    ],
    "name:swe_x_preferred":[
        "Rudnya"
    ],
    "wof:name":"Rudnya",
    "wof:placetype":"locality"
},
  "geometry": {"coordinates":[29.4024,53.3654],"type":"Point"}
}