{
  "type": "Feature",
  "properties": {
    "gn:admin1_code":"7.0",
    "gn:asciiname":"Azyertsy",
    "gn:country_code":"BY",
    "gn:dem":199,
    "gn:feature_class":"P",
    "gn:feature_code":"PPL",
    "gn:name":"Azyertsy",
    "gn:population":0,
    "gn:timezone":"Europe/Minsk",
    "iso:country":"BY",
    "name:bel_x_preferred":[
        "\u0410\u0437\u0435\u0440\u0446\u044b"
    ],
    "name:und_x_variant":[
        "Ozertsy"
    ],
    "wof:name":"Azyertsy",
    "wof:placetype":"locality"
},
  "geometry": {"coordinates":[29.7672,54.4203],"type":"Point"}
}