{
  "type": "Feature",
  "properties": {
    "gn:admin1_code":"2.0",
    "gn:asciiname":"Kunishche",
    "gn:country_code":"BY",
    "gn:dem":156,
    "gn:feature_class":"P",
    "gn:feature_code":"PPL",
    "gn:name":"Kunishche",
    "gn:population":0,
    "gn:timezone":"Europe/Minsk",
    "iso:country":"BY",
    "name:rus_x_preferred":[
        "\u041a\u0443\u043d\u0438\u0449\u0435"
    ],
    "wof:name":"Kunishche",
    "wof:placetype":"locality"
},
  "geometry": {"coordinates":[28.5766,51.8104],"type":"Point"}
}