{
  "type": "Feature",
  "properties": {
    "gn:admin1_code":"5.0",
    "gn:asciiname":"Levkovo",
    "gn:country_code":"BY",
    "gn:dem":184,
    "gn:feature_class":"P",
    "gn:feature_code":"PPL",
    "gn:name":"Levkovo",
    "gn:population":0,
    "gn:timezone":"Europe/Minsk",
    "iso:country":"BY",
    "name:rus_x_preferred":[
        "\u041b\u0435\u0432\u043a\u043e\u0432\u043e"
    ],
    "wof:name":"Levkovo",
    "wof:placetype":"locality"
},
  "geometry": {"coordinates":[27.1801,54.3901],"type":"Point"}
}