{
  "type": "Feature",
  "properties": {
    "gn:admin1_code":"3.0",
    "gn:asciiname":"Berdashi",
    "gn:country_code":"BY",
    "gn:dem":183,
    "gn:feature_class":"P",
    "gn:feature_code":"PPL",
    "gn:name":"Berdashi",
    "gn:population":0,
    "gn:timezone":"Europe/Minsk",
    "iso:country":"BY",
    "name:rus_x_preferred":[
        "\u0411\u0435\u0440\u0434\u0430\u0448\u0438"
    ],
    "wof:name":"Berdashi",
    "wof:placetype":"locality"
},
  "geometry": {"coordinates":[26.518,53.4931],"type":"Point"}
}