{
  "type": "Feature",
  "properties": {
    "gn:admin1_code":"3.0",
    "gn:asciiname":"Lyakhovichi Vtoryye",
    "gn:country_code":"BY",
    "gn:dem":132,
    "gn:feature_class":"P",
    "gn:feature_code":"PPL",
    "gn:name":"Lyakhovichi Vtoryye",
    "gn:population":0,
    "gn:timezone":"Europe/Minsk",
    "iso:country":"BY",
    "name:rus_x_preferred":[
        "\u041b\u044f\u0445\u043e\u0432\u0438\u0447\u0438 \u0412\u0442\u043e\u0440\u044b\u0435"
    ],
    "wof:name":"Lyakhovichi Vtoryye",
    "wof:placetype":"locality"
},
  "geometry": {"coordinates":[25.8104,53.8427],"type":"Point"}
}