{
  "type": "Feature",
  "properties": {
    "gn:admin1_code":"6.0",
    "gn:asciiname":"Karpovskiy",
    "gn:country_code":"BY",
    "gn:dem":172,
    "gn:feature_class":"P",
    "gn:feature_code":"PPL",
    "gn:name":"Karpovskiy",
    "gn:population":0,
    "gn:timezone":"Europe/Minsk",
    "iso:country":"BY",
    "name:rus_x_preferred":[
        "\u041a\u0430\u0440\u043f\u043e\u0432\u0441\u043a\u0438\u0439"
    ],
    "wof:name":"Karpovskiy",
    "wof:placetype":"locality"
},
  "geometry": {"coordinates":[31.2767,53.5838],"type":"Point"}
}