{
  "type": "Feature",
  "properties": {
    "gn:admin1_code":"2.0",
    "gn:asciiname":"Grabniki",
    "gn:country_code":"BY",
    "gn:dem":137,
    "gn:feature_class":"P",
    "gn:feature_code":"PPL",
    "gn:name":"Grabniki",
    "gn:population":0,
    "gn:timezone":"Europe/Minsk",
    "iso:country":"BY",
    "name:rus_x_preferred":[
        "\u0413\u0440\u0430\u0431\u043d\u0438\u043a\u0438"
    ],
    "wof:name":"Grabniki",
    "wof:placetype":"locality"
},
  "geometry": {"coordinates":[28.9239,52.60100000000001],"type":"Point"}
}