{
  "type": "Feature",
  "properties": {
    "gn:admin1_code":"2.0",
    "gn:asciiname":"Oleynikov",
    "gn:country_code":"BY",
    "gn:dem":145,
    "gn:feature_class":"P",
    "gn:feature_code":"PPL",
    "gn:name":"Oleynikov",
    "gn:population":0,
    "gn:timezone":"Europe/Minsk",
    "iso:country":"BY",
    "name:rus_x_preferred":[
        "\u041e\u043b\u0435\u0439\u043d\u0438\u043a\u043e\u0432"
    ],
    "wof:name":"Oleynikov",
    "wof:placetype":"locality"
},
  "geometry": {"coordinates":[30.3212,53.054],"type":"Point"}
}