{
  "type": "Feature",
  "properties": {
    "gn:admin1_code":"7.0",
    "gn:asciiname":"Dneprovka",
    "gn:country_code":"BY",
    "gn:dem":158,
    "gn:feature_class":"P",
    "gn:feature_code":"PPL",
    "gn:name":"Dneprovka",
    "gn:population":0,
    "gn:timezone":"Europe/Minsk",
    "iso:country":"BY",
    "name:rus_x_preferred":[
        "\u0414\u043d\u0435\u043f\u0440\u043e\u0432\u043a\u0430"
    ],
    "wof:name":"Dneprovka",
    "wof:placetype":"locality"
},
  "geometry": {"coordinates":[30.784,54.6395],"type":"Point"}
}