{
  "type": "Feature",
  "properties": {
    "gn:admin1_code":"5.0",
    "gn:asciiname":"Brawki",
    "gn:country_code":"BY",
    "gn:dem":250,
    "gn:feature_class":"P",
    "gn:feature_code":"PPL",
    "gn:name":"Brawki",
    "gn:population":0,
    "gn:timezone":"Europe/Minsk",
    "iso:country":"BY",
    "name:bel_x_preferred":[
        "\u0411\u0440\u0430\u045e\u043a\u0456"
    ],
    "name:und_x_variant":[
        "Brovki"
    ],
    "wof:name":"Brawki",
    "wof:placetype":"locality"
},
  "geometry": {"coordinates":[27.3858,54.0432],"type":"Point"}
}