{
  "type": "Feature",
  "properties": {
    "gn:admin1_code":"6.0",
    "gn:asciiname":"Ksaverovo",
    "gn:country_code":"BY",
    "gn:dem":165,
    "gn:feature_class":"P",
    "gn:feature_code":"PPL",
    "gn:name":"Ksaverovo",
    "gn:population":0,
    "gn:timezone":"Europe/Minsk",
    "iso:country":"BY",
    "name:rus_x_preferred":[
        "\u041a\u0441\u0430\u0432\u0435\u0440\u043e\u0432\u043e"
    ],
    "wof:name":"Ksaverovo",
    "wof:placetype":"locality"
},
  "geometry": {"coordinates":[29.6808,53.7665],"type":"Point"}
}