{
  "type": "Feature",
  "properties": {
    "gn:admin1_code":"7.0",
    "gn:asciiname":"Shchepernya",
    "gn:country_code":"BY",
    "gn:dem":145,
    "gn:feature_class":"P",
    "gn:feature_code":"PPL",
    "gn:name":"Shchepernya",
    "gn:population":0,
    "gn:timezone":"Europe/Minsk",
    "iso:country":"BY",
    "name:rus_x_preferred":[
        "\u0429\u0435\u043f\u0435\u0440\u043d\u044f"
    ],
    "wof:name":"Shchepernya",
    "wof:placetype":"locality"
},
  "geometry": {"coordinates":[28.9464,55.7093],"type":"Point"}
}