{
  "type": "Feature",
  "properties": {
    "gn:admin1_code":"2.0",
    "gn:asciiname":"Tereben'",
    "gn:country_code":"BY",
    "gn:dem":132,
    "gn:feature_class":"P",
    "gn:feature_code":"PPL",
    "gn:name":"Tereben\u2019",
    "gn:population":0,
    "gn:timezone":"Europe/Minsk",
    "iso:country":"BY",
    "name:rus_x_preferred":[
        "\u0422\u0435\u0440\u0435\u0431\u0435\u043d\u044c"
    ],
    "name:und_x_variant":[
        "Tereben\u2019"
    ],
    "wof:name":"Tereben'",
    "wof:placetype":"locality"
},
  "geometry": {"coordinates":[28.3549,52.2972],"type":"Point"}
}