{
  "type": "Feature",
  "properties": {
    "gn:admin1_code":"6.0",
    "gn:asciiname":"Kolbovo",
    "gn:country_code":"BY",
    "gn:dem":152,
    "gn:feature_class":"P",
    "gn:feature_code":"PPL",
    "gn:name":"Kolbovo",
    "gn:population":0,
    "gn:timezone":"Europe/Minsk",
    "iso:country":"BY",
    "name:rus_x_preferred":[
        "\u041a\u043e\u043b\u0431\u043e\u0432\u043e"
    ],
    "wof:name":"Kolbovo",
    "wof:placetype":"locality"
},
  "geometry": {"coordinates":[29.7975,53.4431],"type":"Point"}
}