{
  "type": "Feature",
  "properties": {
    "gn:admin1_code":"5.0",
    "gn:asciiname":"Zabegi",
    "gn:country_code":"BY",
    "gn:dem":173,
    "gn:feature_class":"P",
    "gn:feature_code":"PPL",
    "gn:name":"Zabegi",
    "gn:population":0,
    "gn:timezone":"Europe/Minsk",
    "iso:country":"BY",
    "name:rus_x_preferred":[
        "\u0417\u0430\u0431\u0435\u0433\u0438"
    ],
    "name:und_x_variant":[
        "Zabeg",
        "Zabiegi",
        "Zabegi"
    ],
    "wof:name":"Zabegi",
    "wof:placetype":"locality"
},
  "geometry": {"coordinates":[27.4727,54.8326],"type":"Point"}
}