{
  "type": "Feature",
  "properties": {
    "gn:admin1_code":"2.0",
    "gn:asciiname":"Novaya Korma",
    "gn:country_code":"BY",
    "gn:dem":136,
    "gn:feature_class":"P",
    "gn:feature_code":"PPL",
    "gn:name":"Novaya Korma",
    "gn:population":0,
    "gn:timezone":"Europe/Minsk",
    "iso:country":"BY",
    "name:rus_x_preferred":[
        "\u041d\u043e\u0432\u0430\u044f \u041a\u043e\u0440\u043c\u0430"
    ],
    "wof:name":"Novaya Korma",
    "wof:placetype":"locality"
},
  "geometry": {"coordinates":[29.923,52.7466],"type":"Point"}
}