{
  "type": "Feature",
  "properties": {
    "gn:admin1_code":"1.0",
    "gn:asciiname":"Oborki",
    "gn:country_code":"BY",
    "gn:dem":131,
    "gn:feature_class":"P",
    "gn:feature_code":"PPL",
    "gn:name":"Oborki",
    "gn:population":0,
    "gn:timezone":"Europe/Minsk",
    "iso:country":"BY",
    "name:rus_x_preferred":[
        "\u041e\u0431\u043e\u0440\u043a\u0438"
    ],
    "wof:name":"Oborki",
    "wof:placetype":"locality"
},
  "geometry": {"coordinates":[27.0147,52.2445],"type":"Point"}
}