{
  "type": "Feature",
  "properties": {
    "gn:admin1_code":"2.0",
    "gn:asciiname":"Kotlovitsa",
    "gn:country_code":"BY",
    "gn:dem":112,
    "gn:feature_class":"P",
    "gn:feature_code":"PPL",
    "gn:name":"Kotlovitsa",
    "gn:population":0,
    "gn:timezone":"Europe/Minsk",
    "iso:country":"BY",
    "name:rus_x_preferred":[
        "\u041a\u043e\u0442\u043b\u043e\u0432\u0438\u0446\u0430"
    ],
    "wof:name":"Kotlovitsa",
    "wof:placetype":"locality"
},
  "geometry": {"coordinates":[30.3659,51.7958],"type":"Point"}
}