{
  "type": "Feature",
  "properties": {
    "gn:admin1_code":"3.0",
    "gn:asciiname":"Simakovo",
    "gn:country_code":"BY",
    "gn:dem":177,
    "gn:feature_class":"P",
    "gn:feature_code":"PPL",
    "gn:name":"Simakovo",
    "gn:population":0,
    "gn:timezone":"Europe/Minsk",
    "iso:country":"BY",
    "name:eng_x_preferred":[
        "Simakovo"
    ],
    "name:rus_x_preferred":[
        "\u0421\u0438\u043c\u0430\u043a\u043e\u0432\u043e"
    ],
    "name:und_x_variant":[
        "Simokovo"
    ],
    "wof:name":"Simakovo",
    "wof:placetype":"locality"
},
  "geometry": {"coordinates":[26.4856,53.4042],"type":"Point"}
}