{
  "type": "Feature",
  "properties": {
    "gn:admin1_code":"2.0",
    "gn:asciiname":"Prosmychi",
    "gn:country_code":"BY",
    "gn:dem":116,
    "gn:feature_class":"P",
    "gn:feature_code":"PPL",
    "gn:name":"Prosmychi",
    "gn:population":0,
    "gn:timezone":"Europe/Minsk",
    "iso:country":"BY",
    "name:rus_x_preferred":[
        "\u041f\u0440\u043e\u0441\u043c\u044b\u0447\u0438"
    ],
    "wof:name":"Prosmychi",
    "wof:placetype":"locality"
},
  "geometry": {"coordinates":[30.3726,51.6568],"type":"Point"}
}