{
  "type": "Feature",
  "properties": {
    "gn:admin1_code":"7.0",
    "gn:asciiname":"Poselok Nomer Vosem'",
    "gn:country_code":"BY",
    "gn:dem":175,
    "gn:feature_class":"P",
    "gn:feature_code":"PPL",
    "gn:name":"Pos\u00eblok Nomer Vosem\u2019",
    "gn:population":0,
    "gn:timezone":"Europe/Minsk",
    "iso:country":"BY",
    "name:rus_x_preferred":[
        "\u041f\u043e\u0441\u0451\u043b\u043e\u043a \u041d\u043e\u043c\u0435\u0440 \u0412\u043e\u0441\u0435\u043c\u044c"
    ],
    "name:und_x_variant":[
        "Pos\u00eblok Nomer Vosem\u2019"
    ],
    "wof:name":"Poselok Nomer Vosem'",
    "wof:placetype":"locality"
},
  "geometry": {"coordinates":[30.6574,54.7288],"type":"Point"}
}