{
  "type": "Feature",
  "properties": {
    "gn:admin1_code":"5.0",
    "gn:asciiname":"Karpilovka",
    "gn:country_code":"BY",
    "gn:dem":179,
    "gn:feature_class":"P",
    "gn:feature_code":"PPL",
    "gn:name":"Karpilovka",
    "gn:population":0,
    "gn:timezone":"Europe/Minsk",
    "iso:country":"BY",
    "name:rus_x_preferred":[
        "\u041a\u0430\u0440\u043f\u0438\u043b\u043e\u0432\u043a\u0430"
    ],
    "wof:name":"Karpilovka",
    "wof:placetype":"locality"
},
  "geometry": {"coordinates":[27.4498,53.4774],"type":"Point"}
}