{
  "type": "Feature",
  "properties": {
    "gn:admin1_code":"6.0",
    "gn:asciiname":"Vishenka",
    "gn:country_code":"BY",
    "gn:dem":153,
    "gn:feature_class":"P",
    "gn:feature_code":"PPL",
    "gn:name":"Vishenka",
    "gn:population":0,
    "gn:timezone":"Europe/Minsk",
    "iso:country":"BY",
    "name:rus_x_preferred":[
        "\u0412\u0438\u0448\u0435\u043d\u043a\u0430"
    ],
    "wof:name":"Vishenka",
    "wof:placetype":"locality"
},
  "geometry": {"coordinates":[29.59,53.1919],"type":"Point"}
}