{
  "type": "Feature",
  "properties": {
    "gn:admin1_code":"6.0",
    "gn:asciiname":"Paporotka",
    "gn:country_code":"BY",
    "gn:dem":183,
    "gn:feature_class":"P",
    "gn:feature_code":"PPL",
    "gn:name":"Paporotka",
    "gn:population":0,
    "gn:timezone":"Europe/Minsk",
    "iso:country":"BY",
    "name:rus_x_preferred":[
        "\u041f\u0430\u043f\u043e\u0440\u043e\u0442\u043a\u0430"
    ],
    "name:und_x_variant":[
        "Paporodka"
    ],
    "wof:name":"Paporotka",
    "wof:placetype":"locality"
},
  "geometry": {"coordinates":[32.1988,53.7517],"type":"Point"}
}