{
  "type": "Feature",
  "properties": {
    "gn:admin1_code":"6.0",
    "gn:asciiname":"Likhachevo",
    "gn:country_code":"BY",
    "gn:dem":189,
    "gn:feature_class":"P",
    "gn:feature_code":"PPL",
    "gn:name":"Likhach\u00ebvo",
    "gn:population":0,
    "gn:timezone":"Europe/Minsk",
    "iso:country":"BY",
    "name:rus_x_preferred":[
        "\u041b\u0438\u0445\u0430\u0447\u0451\u0432\u043e"
    ],
    "name:und_x_variant":[
        "Likhach\u00ebvo"
    ],
    "wof:name":"Likhachevo",
    "wof:placetype":"locality"
},
  "geometry": {"coordinates":[30.752,54.3141],"type":"Point"}
}