{
  "type": "Feature",
  "properties": {
    "gn:admin1_code":"7.0",
    "gn:asciiname":"Dorogokupovo",
    "gn:country_code":"BY",
    "gn:dem":134,
    "gn:feature_class":"P",
    "gn:feature_code":"PPL",
    "gn:name":"Dorogokupovo",
    "gn:population":0,
    "gn:timezone":"Europe/Minsk",
    "iso:country":"BY",
    "name:rus_x_preferred":[
        "\u0414\u043e\u0440\u043e\u0433\u043e\u043a\u0443\u043f\u043e\u0432\u043e"
    ],
    "wof:name":"Dorogokupovo",
    "wof:placetype":"locality"
},
  "geometry": {"coordinates":[29.9415,55.161],"type":"Point"}
}