{
  "type": "Feature",
  "properties": {
    "gn:admin1_code":"5.0",
    "gn:asciiname":"Novyy Rabak",
    "gn:country_code":"BY",
    "gn:dem":152,
    "gn:feature_class":"P",
    "gn:feature_code":"PPL",
    "gn:name":"Novyy Rabak",
    "gn:population":0,
    "gn:timezone":"Europe/Minsk",
    "iso:country":"BY",
    "name:rus_x_preferred":[
        "\u041d\u043e\u0432\u044b\u0439 \u0420\u0430\u0431\u0430\u043a"
    ],
    "name:und_x_variant":[
        "Rabak"
    ],
    "wof:name":"Novyy Rabak",
    "wof:placetype":"locality"
},
  "geometry": {"coordinates":[27.9081,52.9968],"type":"Point"}
}