{
  "type": "Feature",
  "properties": {
    "gn:admin1_code":"6.0",
    "gn:asciiname":"Krushinka",
    "gn:country_code":"BY",
    "gn:dem":169,
    "gn:feature_class":"P",
    "gn:feature_code":"PPL",
    "gn:name":"Krushinka",
    "gn:population":0,
    "gn:timezone":"Europe/Minsk",
    "iso:country":"BY",
    "name:rus_x_preferred":[
        "\u041a\u0440\u0443\u0448\u0438\u043d\u043a\u0430"
    ],
    "wof:name":"Krushinka",
    "wof:placetype":"locality"
},
  "geometry": {"coordinates":[28.8904,53.0958],"type":"Point"}
}