{
  "type": "Feature",
  "properties": {
    "gn:admin1_code":"6.0",
    "gn:asciiname":"Rakitnik",
    "gn:country_code":"BY",
    "gn:dem":167,
    "gn:feature_class":"P",
    "gn:feature_code":"PPL",
    "gn:name":"Rakitnik",
    "gn:population":0,
    "gn:timezone":"Europe/Minsk",
    "iso:country":"BY",
    "name:rus_x_preferred":[
        "\u0420\u0430\u043a\u0438\u0442\u043d\u0438\u043a"
    ],
    "wof:name":"Rakitnik",
    "wof:placetype":"locality"
},
  "geometry": {"coordinates":[32.2145,53.3761],"type":"Point"}
}