{
  "type": "Feature",
  "properties": {
    "gn:admin1_code":"1.0",
    "gn:asciiname":"Khatsislaw",
    "gn:country_code":"BY",
    "gn:dem":157,
    "gn:feature_class":"P",
    "gn:feature_code":"PPL",
    "gn:name":"Khatsislaw",
    "gn:population":0,
    "gn:timezone":"Europe/Minsk",
    "iso:country":"BY",
    "name:bel_x_preferred":[
        "\u0425\u0430\u0446\u0456\u0441\u043b\u0430\u045e"
    ],
    "name:und_x_variant":[
        "Khotislav",
        "Khatsislaw"
    ],
    "wof:name":"Khatsislaw",
    "wof:placetype":"locality"
},
  "geometry": {"coordinates":[24.0969,51.7121],"type":"Point"}
}