{
  "type": "Feature",
  "properties": {
    "gn:admin1_code":"1.0",
    "gn:asciiname":"Vysadovichi",
    "gn:country_code":"BY",
    "gn:dem":193,
    "gn:feature_class":"P",
    "gn:feature_code":"PPL",
    "gn:name":"Vysadovichi",
    "gn:population":0,
    "gn:timezone":"Europe/Minsk",
    "iso:country":"BY",
    "name:rus_x_preferred":[
        "\u0412\u044b\u0441\u0430\u0434\u043e\u0432\u0438\u0447\u0438"
    ],
    "wof:name":"Vysadovichi",
    "wof:placetype":"locality"
},
  "geometry": {"coordinates":[26.187,53.3648],"type":"Point"}
}