{
  "type": "Feature",
  "properties": {
    "gn:admin1_code":"1.0",
    "gn:asciiname":"Yezhiki",
    "gn:country_code":"BY",
    "gn:dem":138,
    "gn:feature_class":"P",
    "gn:feature_code":"PPL",
    "gn:name":"Y\u00ebzhiki",
    "gn:population":0,
    "gn:timezone":"Europe/Minsk",
    "iso:country":"BY",
    "name:rus_x_preferred":[
        "Y\u00ebzhiki"
    ],
    "name:rus_x_variant":[
        "\u0401\u0436\u0438\u043a\u0438"
    ],
    "name:und_x_variant":[
        "Y\u00ebzhiki"
    ],
    "wof:name":"Yezhiki",
    "wof:placetype":"locality"
},
  "geometry": {"coordinates":[24.089,52.1771],"type":"Point"}
}