{
  "type": "Feature",
  "properties": {
    "gn:admin1_code":"7.0",
    "gn:asciiname":"Slizhovo",
    "gn:country_code":"BY",
    "gn:dem":164,
    "gn:feature_class":"P",
    "gn:feature_code":"PPL",
    "gn:name":"Slizhovo",
    "gn:population":0,
    "gn:timezone":"Europe/Minsk",
    "iso:country":"BY",
    "name:rus_x_preferred":[
        "\u0421\u043b\u0438\u0436\u043e\u0432\u043e"
    ],
    "wof:name":"Slizhovo",
    "wof:placetype":"locality"
},
  "geometry": {"coordinates":[26.9763,55.0214],"type":"Point"}
}