{
  "type": "Feature",
  "properties": {
    "gn:admin1_code":"5.0",
    "gn:asciiname":"Yemel'yanovo",
    "gn:country_code":"BY",
    "gn:dem":210,
    "gn:feature_class":"P",
    "gn:feature_code":"PPL",
    "gn:name":"Yemel\u2019yanovo",
    "gn:population":0,
    "gn:timezone":"Europe/Minsk",
    "iso:country":"BY",
    "name:rus_x_preferred":[
        "\u0415\u043c\u0435\u043b\u044c\u044f\u043d\u043e\u0432\u043e"
    ],
    "name:und_x_variant":[
        "Mel\u2019yanovo",
        "Yemel\u2019yanovo"
    ],
    "wof:name":"Yemel'yanovo",
    "wof:placetype":"locality"
},
  "geometry": {"coordinates":[28.0307,54.07],"type":"Point"}
}