{
  "type": "Feature",
  "properties": {
    "gn:admin1_code":"5.0",
    "gn:asciiname":"Falichi",
    "gn:country_code":"BY",
    "gn:dem":164,
    "gn:feature_class":"P",
    "gn:feature_code":"PPL",
    "gn:name":"Falichi",
    "gn:population":0,
    "gn:timezone":"Europe/Minsk",
    "iso:country":"BY",
    "name:rus_x_preferred":[
        "\u0424\u0430\u043b\u0438\u0447\u0438"
    ],
    "wof:name":"Falichi",
    "wof:placetype":"locality"
},
  "geometry": {"coordinates":[28.325,53.1216],"type":"Point"}
}