{
  "type": "Feature",
  "properties": {
    "gn:admin1_code":"5.0",
    "gn:asciiname":"Seredina",
    "gn:country_code":"BY",
    "gn:dem":175,
    "gn:feature_class":"P",
    "gn:feature_code":"PPL",
    "gn:name":"Seredina",
    "gn:population":0,
    "gn:timezone":"Europe/Minsk",
    "iso:country":"BY",
    "name:rus_x_preferred":[
        "\u0421\u0435\u0440\u0435\u0434\u0438\u043d\u0430"
    ],
    "name:und_x_variant":[
        "Seredino"
    ],
    "wof:name":"Seredina",
    "wof:placetype":"locality"
},
  "geometry": {"coordinates":[27.5517,53.4022],"type":"Point"}
}