{
  "type": "Feature",
  "properties": {
    "gn:admin1_code":"6.0",
    "gn:asciiname":"Lyubizh",
    "gn:country_code":"BY",
    "gn:dem":187,
    "gn:feature_class":"P",
    "gn:feature_code":"PPL",
    "gn:name":"Lyubizh",
    "gn:population":0,
    "gn:timezone":"Europe/Minsk",
    "iso:country":"BY",
    "name:eng_x_preferred":[
        "Lyubizh"
    ],
    "name:rus_x_preferred":[
        "\u041b\u044e\u0431\u0438\u0436"
    ],
    "wof:name":"Lyubizh",
    "wof:placetype":"locality"
},
  "geometry": {"coordinates":[30.7525,54.2101],"type":"Point"}
}