{
  "type": "Feature",
  "properties": {
    "gn:admin1_code":"1.0",
    "gn:asciiname":"Zabolot'ye",
    "gn:country_code":"BY",
    "gn:dem":144,
    "gn:feature_class":"P",
    "gn:feature_code":"PPL",
    "gn:name":"Zabolot\u2019ye",
    "gn:population":0,
    "gn:timezone":"Europe/Minsk",
    "iso:country":"BY",
    "name:rus_x_preferred":[
        "\u0417\u0430\u0431\u043e\u043b\u043e\u0442\u044c\u0435"
    ],
    "name:und_x_variant":[
        "Zabolot\u2019ye"
    ],
    "wof:name":"Zabolot'ye",
    "wof:placetype":"locality"
},
  "geometry": {"coordinates":[24.6685,52.1099],"type":"Point"}
}