{
  "type": "Feature",
  "properties": {
    "gn:admin1_code":"3.0",
    "gn:asciiname":"Kuz'michi",
    "gn:country_code":"BY",
    "gn:dem":112,
    "gn:feature_class":"P",
    "gn:feature_code":"PPL",
    "gn:name":"Kuz\u2019michi",
    "gn:population":0,
    "gn:timezone":"Europe/Minsk",
    "iso:country":"BY",
    "name:rus_x_preferred":[
        "\u041a\u0443\u0437\u044c\u043c\u0438\u0447\u0438"
    ],
    "name:und_x_variant":[
        "Kuz\u2019michi"
    ],
    "wof:name":"Kuz'michi",
    "wof:placetype":"locality"
},
  "geometry": {"coordinates":[24.0895,53.4601],"type":"Point"}
}