{
  "type": "Feature",
  "properties": {
    "gn:admin1_code":"7.0",
    "gn:asciiname":"Butory",
    "gn:country_code":"BY",
    "gn:dem":212,
    "gn:feature_class":"P",
    "gn:feature_code":"PPL",
    "gn:name":"Butory",
    "gn:population":0,
    "gn:timezone":"Europe/Minsk",
    "iso:country":"BY",
    "name:rus_x_preferred":[
        "\u0411\u0443\u0442\u043e\u0440\u044b"
    ],
    "wof:name":"Butory",
    "wof:placetype":"locality"
},
  "geometry": {"coordinates":[29.4643,54.5199],"type":"Point"}
}