{
  "type": "Feature",
  "properties": {
    "gn:admin1_code":"7.0",
    "gn:asciiname":"Zasitnitsa",
    "gn:country_code":"BY",
    "gn:dem":146,
    "gn:feature_class":"P",
    "gn:feature_code":"PPL",
    "gn:name":"Zasitnitsa",
    "gn:population":0,
    "gn:timezone":"Europe/Minsk",
    "iso:country":"BY",
    "name:rus_x_preferred":[
        "\u0417\u0430\u0441\u0438\u0442\u043d\u0438\u0446\u0430"
    ],
    "wof:name":"Zasitnitsa",
    "wof:placetype":"locality"
},
  "geometry": {"coordinates":[29.4066,55.6345],"type":"Point"}
}