{
  "type": "Feature",
  "properties": {
    "gn:admin1_code":"5.0",
    "gn:asciiname":"Krasny Aktsyabr",
    "gn:country_code":"BY",
    "gn:dem":163,
    "gn:feature_class":"P",
    "gn:feature_code":"PPL",
    "gn:name":"Krasny Aktsyabr",
    "gn:population":0,
    "gn:timezone":"Europe/Minsk",
    "iso:country":"BY",
    "name:bel_x_preferred":[
        "\u041a\u0440\u0430\u0441\u043d\u044b \u0410\u043a\u0446\u044f\u0431\u0440"
    ],
    "name:rus_x_preferred":[
        "Krasnyy Oktyabr\u2019"
    ],
    "wof:name":"Krasny Aktsyabr",
    "wof:placetype":"locality"
},
  "geometry": {"coordinates":[28.4008,53.51],"type":"Point"}
}