{
  "type": "Feature",
  "properties": {
    "gn:admin1_code":"5.0",
    "gn:asciiname":"Pamorovshchina",
    "gn:country_code":"BY",
    "gn:dem":188,
    "gn:feature_class":"P",
    "gn:feature_code":"PPL",
    "gn:name":"Pamorovshchina",
    "gn:population":0,
    "gn:timezone":"Europe/Minsk",
    "iso:country":"BY",
    "name:rus_x_preferred":[
        "\u041f\u0430\u043c\u043e\u0440\u043e\u0432\u0449\u0438\u043d\u0430"
    ],
    "wof:name":"Pamorovshchina",
    "wof:placetype":"locality"
},
  "geometry": {"coordinates":[27.0423,54.7705],"type":"Point"}
}