{
  "type": "Feature",
  "properties": {
    "gn:admin1_code":"1.0",
    "gn:asciiname":"Tsmen' Vtoraya",
    "gn:country_code":"BY",
    "gn:dem":135,
    "gn:feature_class":"P",
    "gn:feature_code":"PPL",
    "gn:name":"Tsmen\u2019 Vtoraya",
    "gn:population":0,
    "gn:timezone":"Europe/Minsk",
    "iso:country":"BY",
    "name:rus_x_preferred":[
        "\u0426\u043c\u0435\u043d\u044c \u0412\u0442\u043e\u0440\u0430\u044f"
    ],
    "name:und_x_variant":[
        "Tsmen\u2019 Vtoraya"
    ],
    "wof:name":"Tsmen' Vtoraya",
    "wof:placetype":"locality"
},
  "geometry": {"coordinates":[26.6753,51.9775],"type":"Point"}
}