{
  "type": "Feature",
  "properties": {
    "gn:admin1_code":"3.0",
    "gn:asciiname":"Malyuki",
    "gn:country_code":"BY",
    "gn:dem":148,
    "gn:feature_class":"P",
    "gn:feature_code":"PPL",
    "gn:name":"Malyuki",
    "gn:population":0,
    "gn:timezone":"Europe/Minsk",
    "iso:country":"BY",
    "name:rus_x_preferred":[
        "\u041c\u0430\u043b\u044e\u043a\u0438"
    ],
    "wof:name":"Malyuki",
    "wof:placetype":"locality"
},
  "geometry": {"coordinates":[24.7991,53.9084],"type":"Point"}
}