{
  "type": "Feature",
  "properties": {
    "gn:admin1_code":"7.0",
    "gn:asciiname":"Medynki-Domashskiye",
    "gn:country_code":"BY",
    "gn:dem":144,
    "gn:feature_class":"P",
    "gn:feature_code":"PPL",
    "gn:name":"Medynki-Domashskiye",
    "gn:population":0,
    "gn:timezone":"Europe/Minsk",
    "iso:country":"BY",
    "name:rus_x_preferred":[
        "\u041c\u0435\u0434\u044b\u043d\u043a\u0438-\u0414\u043e\u043c\u0430\u0448\u0441\u043a\u0438\u0435"
    ],
    "wof:name":"Medynki-Domashskiye",
    "wof:placetype":"locality"
},
  "geometry": {"coordinates":[26.9439,55.5189],"type":"Point"}
}