{
  "type": "Feature",
  "properties": {
    "gn:admin1_code":"5.0",
    "gn:asciiname":"Harbuzy",
    "gn:country_code":"BY",
    "gn:dem":176,
    "gn:feature_class":"P",
    "gn:feature_code":"PPL",
    "gn:name":"Harbuzy",
    "gn:population":0,
    "gn:timezone":"Europe/Minsk",
    "iso:country":"BY",
    "name:bel_x_preferred":[
        "\u0413\u0430\u0440\u0431\u0443\u0437\u044b"
    ],
    "name:und_x_variant":[
        "Garbuzy"
    ],
    "wof:name":"Harbuzy",
    "wof:placetype":"locality"
},
  "geometry": {"coordinates":[27.0744,53.569],"type":"Point"}
}