{
  "type": "Feature",
  "properties": {
    "gn:admin1_code":"5.0",
    "gn:asciiname":"Yefimovichi",
    "gn:country_code":"BY",
    "gn:dem":180,
    "gn:feature_class":"P",
    "gn:feature_code":"PPL",
    "gn:name":"Yefimovichi",
    "gn:population":0,
    "gn:timezone":"Europe/Minsk",
    "iso:country":"BY",
    "name:rus_x_preferred":[
        "\u0415\u0444\u0438\u043c\u043e\u0432\u0438\u0447\u0438"
    ],
    "name:und_x_variant":[
        "Yefimoviche"
    ],
    "wof:name":"Yefimovichi",
    "wof:placetype":"locality"
},
  "geometry": {"coordinates":[26.4662,53.0148],"type":"Point"}
}