{
  "type": "Feature",
  "properties": {
    "gn:admin1_code":"2.0",
    "gn:asciiname":"Selivonovka",
    "gn:country_code":"BY",
    "gn:dem":146,
    "gn:feature_class":"P",
    "gn:feature_code":"PPL",
    "gn:name":"Selivonovka",
    "gn:population":0,
    "gn:timezone":"Europe/Minsk",
    "iso:country":"BY",
    "name:rus_x_preferred":[
        "\u0421\u0435\u043b\u0438\u0432\u043e\u043d\u043e\u0432\u043a\u0430"
    ],
    "name:und_x_variant":[
        "Khutora Novo Selivonovskiye",
        "Selivanovskiye",
        "Selivonovka"
    ],
    "wof:name":"Selivonovka",
    "wof:placetype":"locality"
},
  "geometry": {"coordinates":[30.352,52.8644],"type":"Point"}
}