{
  "type": "Feature",
  "properties": {
    "gn:admin1_code":"5.0",
    "gn:asciiname":"Zaleshany",
    "gn:country_code":"BY",
    "gn:dem":191,
    "gn:feature_class":"P",
    "gn:feature_code":"PPL",
    "gn:name":"Zaleshany",
    "gn:population":0,
    "gn:timezone":"Europe/Minsk",
    "iso:country":"BY",
    "name:rus_x_preferred":[
        "\u0417\u0430\u043b\u0435\u0448\u0430\u043d\u044b"
    ],
    "name:und_x_variant":[
        "Zalesshany",
        "Zaleshany"
    ],
    "wof:name":"Zaleshany",
    "wof:placetype":"locality"
},
  "geometry": {"coordinates":[26.4821,53.0309],"type":"Point"}
}