{
  "type": "Feature",
  "properties": {
    "gn:admin1_code":"7.0",
    "gn:asciiname":"Krasnaya Sloboda",
    "gn:country_code":"BY",
    "gn:dem":205,
    "gn:feature_class":"P",
    "gn:feature_code":"PPL",
    "gn:name":"Krasnaya Sloboda",
    "gn:population":0,
    "gn:timezone":"Europe/Minsk",
    "iso:country":"BY",
    "name:rus_x_preferred":[
        "\u041a\u0440\u0430\u0441\u043d\u0430\u044f \u0421\u043b\u043e\u0431\u043e\u0434\u0430"
    ],
    "name:und_x_variant":[
        "Chirvonaya Sloboda",
        "Sloboda",
        "Durnaya",
        "Krasnaya Sloboda"
    ],
    "wof:name":"Krasnaya Sloboda",
    "wof:placetype":"locality"
},
  "geometry": {"coordinates":[30.8368,54.5861],"type":"Point"}
}