{
  "type": "Feature",
  "properties": {
    "gn:admin1_code":"5.0",
    "gn:asciiname":"Zaspornya",
    "gn:country_code":"BY",
    "gn:dem":149,
    "gn:feature_class":"P",
    "gn:feature_code":"PPL",
    "gn:name":"Zaspornya",
    "gn:population":0,
    "gn:timezone":"Europe/Minsk",
    "iso:country":"BY",
    "name:rus_x_preferred":[
        "\u0417\u0430\u0441\u043f\u043e\u0440\u043d\u044f"
    ],
    "wof:name":"Zaspornya",
    "wof:placetype":"locality"
},
  "geometry": {"coordinates":[26.8579,54.4668],"type":"Point"}
}