{
  "type": "Feature",
  "properties": {
    "gn:admin1_code":"3.0",
    "gn:asciiname":"Goduny",
    "gn:country_code":"BY",
    "gn:dem":121,
    "gn:feature_class":"P",
    "gn:feature_code":"PPL",
    "gn:name":"Goduny",
    "gn:population":0,
    "gn:timezone":"Europe/Minsk",
    "iso:country":"BY",
    "name:bel_x_preferred":[
        "Haduny"
    ],
    "name:bel_x_variant":[
        "\u0413\u0430\u0434\u0443\u043d\u044b"
    ],
    "name:rus_x_preferred":[
        "\u0413\u043e\u0434\u0443\u043d\u044b"
    ],
    "wof:name":"Goduny",
    "wof:placetype":"locality"
},
  "geometry": {"coordinates":[24.1662,53.9181],"type":"Point"}
}