{
  "type": "Feature",
  "properties": {
    "gn:admin1_code":"5.0",
    "gn:asciiname":"Ragozino",
    "gn:country_code":"BY",
    "gn:dem":174,
    "gn:feature_class":"P",
    "gn:feature_code":"PPL",
    "gn:name":"Ragozino",
    "gn:population":0,
    "gn:timezone":"Europe/Minsk",
    "iso:country":"BY",
    "name:rus_x_preferred":[
        "\u0420\u0430\u0433\u043e\u0437\u0438\u043d\u043e"
    ],
    "name:und_x_variant":[
        "Rogozin",
        "Rogozino",
        "Ragozino"
    ],
    "wof:name":"Ragozino",
    "wof:placetype":"locality"
},
  "geometry": {"coordinates":[27.4878,54.5405],"type":"Point"}
}