{
  "type": "Feature",
  "properties": {
    "gn:admin1_code":"5.0",
    "gn:asciiname":"Ozerichino",
    "gn:country_code":"BY",
    "gn:dem":175,
    "gn:feature_class":"P",
    "gn:feature_code":"PPL",
    "gn:name":"Ozerichino",
    "gn:population":0,
    "gn:timezone":"Europe/Minsk",
    "iso:country":"BY",
    "name:rus_x_preferred":[
        "\u041e\u0437\u0435\u0440\u0438\u0447\u0438\u043d\u043e"
    ],
    "name:und_x_variant":[
        "Ozerchin"
    ],
    "wof:name":"Ozerichino",
    "wof:placetype":"locality"
},
  "geometry": {"coordinates":[27.7533,53.5753],"type":"Point"}
}