{
  "type": "Feature",
  "properties": {
    "gn:admin1_code":"3.0",
    "gn:asciiname":"Peski",
    "gn:country_code":"BY",
    "gn:dem":136,
    "gn:feature_class":"P",
    "gn:feature_code":"PPL",
    "gn:name":"Peski",
    "gn:population":0,
    "gn:timezone":"Europe/Minsk",
    "iso:country":"BY",
    "name:bel_x_preferred":[
        "\u041f\u044f\u0441\u043a\u0456"
    ],
    "name:est_x_preferred":[
        "Peski"
    ],
    "name:fin_x_preferred":[
        "Peski"
    ],
    "name:hye_x_preferred":[
        "\u054a\u0565\u057d\u056f\u056b"
    ],
    "name:rus_x_preferred":[
        "\u041f\u0435\u0441\u043a\u0438"
    ],
    "wof:name":"Peski",
    "wof:placetype":"locality"
},
  "geometry": {"coordinates":[25.152,53.7479],"type":"Point"}
}