{
  "type": "Feature",
  "properties": {
    "gn:admin1_code":"5.0",
    "gn:asciiname":"Niwki",
    "gn:country_code":"BY",
    "gn:dem":206,
    "gn:feature_class":"P",
    "gn:feature_code":"PPL",
    "gn:name":"Niwki",
    "gn:population":0,
    "gn:timezone":"Europe/Minsk",
    "iso:country":"BY",
    "name:bel_x_preferred":[
        "\u041d\u0456\u045e\u043a\u0456"
    ],
    "name:und_x_variant":[
        "Nivki"
    ],
    "wof:name":"Niwki",
    "wof:placetype":"locality"
},
  "geometry": {"coordinates":[28.1432,54.6018],"type":"Point"}
}