{
  "type": "Feature",
  "properties": {
    "gn:admin1_code":"6.0",
    "gn:asciiname":"Urechcha Pyershaye",
    "gn:country_code":"BY",
    "gn:dem":151,
    "gn:feature_class":"P",
    "gn:feature_code":"PPL",
    "gn:name":"Urechcha Pyershaye",
    "gn:population":0,
    "gn:timezone":"Europe/Minsk",
    "iso:country":"BY",
    "name:bel_x_preferred":[
        "\u0423\u0440\u044d\u0447\u0447\u0430 \u041f\u0435\u0440\u0448\u0430\u0435"
    ],
    "name:rus_x_preferred":[
        "Urech\u2019ye Pervoye"
    ],
    "wof:name":"Urechcha Pyershaye",
    "wof:placetype":"locality"
},
  "geometry": {"coordinates":[30.8571,53.4323],"type":"Point"}
}