{
  "type": "Feature",
  "properties": {
    "gn:admin1_code":"1.0",
    "gn:asciiname":"Lyasoty",
    "gn:country_code":"BY",
    "gn:dem":144,
    "gn:feature_class":"P",
    "gn:feature_code":"PPL",
    "gn:name":"Lyasoty",
    "gn:population":0,
    "gn:timezone":"Europe/Minsk",
    "iso:country":"BY",
    "name:rus_x_preferred":[
        "\u041b\u044f\u0441\u043e\u0442\u044b"
    ],
    "wof:name":"Lyasoty",
    "wof:placetype":"locality"
},
  "geometry": {"coordinates":[23.9152,52.267],"type":"Point"}
}