{
  "type": "Feature",
  "properties": {
    "gn:admin1_code":"3.0",
    "gn:asciiname":"Toltishki",
    "gn:country_code":"BY",
    "gn:dem":157,
    "gn:feature_class":"P",
    "gn:feature_code":"PPL",
    "gn:name":"Toltishki",
    "gn:population":0,
    "gn:timezone":"Europe/Minsk",
    "iso:country":"BY",
    "name:rus_x_preferred":[
        "\u0422\u043e\u043b\u0442\u0438\u0448\u043a\u0438"
    ],
    "wof:name":"Toltishki",
    "wof:placetype":"locality"
},
  "geometry": {"coordinates":[24.8991,54.039],"type":"Point"}
}