{
  "type": "Feature",
  "properties": {
    "gn:admin1_code":"7.0",
    "gn:asciiname":"Mazurino",
    "gn:country_code":"BY",
    "gn:dem":132,
    "gn:feature_class":"P",
    "gn:feature_code":"PPL",
    "gn:name":"Mazurino",
    "gn:population":0,
    "gn:timezone":"Europe/Minsk",
    "iso:country":"BY",
    "name:rus_x_preferred":[
        "\u041c\u0430\u0437\u0443\u0440\u0438\u043d\u043e"
    ],
    "wof:name":"Mazurino",
    "wof:placetype":"locality"
},
  "geometry": {"coordinates":[28.2923,55.6283],"type":"Point"}
}