{
  "type": "Feature",
  "properties": {
    "gn:admin1_code":"2.0",
    "gn:asciiname":"Babrovichy",
    "gn:country_code":"BY",
    "gn:dem":134,
    "gn:feature_class":"P",
    "gn:feature_code":"PPL",
    "gn:name":"Babrovichy",
    "gn:population":0,
    "gn:timezone":"Europe/Minsk",
    "iso:country":"BY",
    "name:bel_x_preferred":[
        "\u0411\u0430\u0431\u0440\u043e\u0432\u0456\u0447\u044b"
    ],
    "name:und_x_variant":[
        "Bobrowitschi",
        "Bobrovichi",
        "Babrovichy"
    ],
    "wof:name":"Babrovichy",
    "wof:placetype":"locality"
},
  "geometry": {"coordinates":[29.3684,52.2935],"type":"Point"}
}