{
  "type": "Feature",
  "properties": {
    "gn:admin1_code":"2.0",
    "gn:asciiname":"Galoye",
    "gn:country_code":"BY",
    "gn:dem":143,
    "gn:feature_class":"P",
    "gn:feature_code":"PPL",
    "gn:name":"Galoye",
    "gn:population":0,
    "gn:timezone":"Europe/Minsk",
    "iso:country":"BY",
    "name:rus_x_preferred":[
        "\u0413\u0430\u043b\u043e\u0435"
    ],
    "wof:name":"Galoye",
    "wof:placetype":"locality"
},
  "geometry": {"coordinates":[31.6379,52.26600000000001],"type":"Point"}
}