{
  "type": "Feature",
  "properties": {
    "gn:admin1_code":"7.0",
    "gn:asciiname":"Svileli",
    "gn:country_code":"BY",
    "gn:dem":138,
    "gn:feature_class":"P",
    "gn:feature_code":"PPL",
    "gn:name":"Svileli",
    "gn:population":0,
    "gn:timezone":"Europe/Minsk",
    "iso:country":"BY",
    "name:rus_x_preferred":[
        "\u0421\u0432\u0438\u043b\u0435\u043b\u0438"
    ],
    "name:und_x_variant":[
        "S\u2019vilele",
        "Svileli"
    ],
    "wof:name":"Svileli",
    "wof:placetype":"locality"
},
  "geometry": {"coordinates":[26.6915,55.1555],"type":"Point"}
}