{
  "type": "Feature",
  "properties": {
    "gn:admin1_code":"1.0",
    "gn:asciiname":"Kabyolki",
    "gn:country_code":"BY",
    "gn:dem":151,
    "gn:feature_class":"P",
    "gn:feature_code":"PPL",
    "gn:name":"Kabyolki",
    "gn:population":0,
    "gn:timezone":"Europe/Minsk",
    "iso:country":"BY",
    "name:bel_x_preferred":[
        "\u041a\u0430\u0431\u0451\u043b\u043a\u0456"
    ],
    "name:und_x_variant":[
        "Kobelka",
        "Kabelka",
        "Kabyolki"
    ],
    "wof:name":"Kabyolki",
    "wof:placetype":"locality"
},
  "geometry": {"coordinates":[23.6313,51.7442],"type":"Point"}
}