{
  "type": "Feature",
  "properties": {
    "gn:admin1_code":"3.0",
    "gn:asciiname":"Vyalikaya Izva",
    "gn:country_code":"BY",
    "gn:dem":176,
    "gn:feature_class":"P",
    "gn:feature_code":"PPL",
    "gn:name":"Vyalikaya Izva",
    "gn:population":0,
    "gn:timezone":"Europe/Minsk",
    "iso:country":"BY",
    "name:bel_x_preferred":[
        "Vyalikaya Izva"
    ],
    "name:bel_x_variant":[
        "\u0412\u044f\u043b\u0456\u043a\u0430\u044f \u0406\u0437\u0432\u0430"
    ],
    "name:rus_x_preferred":[
        "\u0411\u043e\u043b\u044c\u0448\u0430\u044f \u0418\u0437\u0432\u0430"
    ],
    "name:und_x_variant":[
        "Bol\u2019shaya Izva"
    ],
    "wof:name":"Vyalikaya Izva",
    "wof:placetype":"locality"
},
  "geometry": {"coordinates":[25.6431,53.63],"type":"Point"}
}