{
  "type": "Feature",
  "properties": {
    "gn:admin1_code":"2.0",
    "gn:asciiname":"Dyatlik",
    "gn:country_code":"BY",
    "gn:dem":160,
    "gn:feature_class":"P",
    "gn:feature_code":"PPL",
    "gn:name":"Dyatlik",
    "gn:population":0,
    "gn:timezone":"Europe/Minsk",
    "iso:country":"BY",
    "name:rus_x_preferred":[
        "\u0414\u044f\u0442\u043b\u0438\u043a"
    ],
    "wof:name":"Dyatlik",
    "wof:placetype":"locality"
},
  "geometry": {"coordinates":[29.3783,51.4209],"type":"Point"}
}