{
  "type": "Feature",
  "properties": {
    "gn:admin1_code":"7.0",
    "gn:asciiname":"Novosyulki",
    "gn:country_code":"BY",
    "gn:dem":190,
    "gn:feature_class":"P",
    "gn:feature_code":"PPL",
    "gn:name":"Novosyulki",
    "gn:population":0,
    "gn:timezone":"Europe/Minsk",
    "iso:country":"BY",
    "name:rus_x_preferred":[
        "\u041d\u043e\u0432\u043e\u0441\u0451\u043b\u043a\u0438"
    ],
    "name:und_x_variant":[
        "Nowosi\u00f3\u0142ki",
        "Novoselki Vtoryye",
        "Novos\u00eblki"
    ],
    "wof:name":"Novosyulki",
    "wof:placetype":"locality"
},
  "geometry": {"coordinates":[26.5328,55.0145],"type":"Point"}
}