{
  "type": "Feature",
  "properties": {
    "gn:admin1_code":"5.0",
    "gn:asciiname":"Zelenki",
    "gn:country_code":"BY",
    "gn:dem":147,
    "gn:feature_class":"P",
    "gn:feature_code":"PPL",
    "gn:name":"Zel\u00ebnki",
    "gn:population":0,
    "gn:timezone":"Europe/Minsk",
    "iso:country":"BY",
    "name:rus_x_preferred":[
        "\u0417\u0435\u043b\u0451\u043d\u043a\u0438"
    ],
    "name:und_x_variant":[
        "Zel\u00ebnki"
    ],
    "wof:name":"Zelenki",
    "wof:placetype":"locality"
},
  "geometry": {"coordinates":[28.1748,52.8693],"type":"Point"}
}