{
  "type": "Feature",
  "properties": {
    "gn:admin1_code":"7.0",
    "gn:asciiname":"Pekotino",
    "gn:country_code":"BY",
    "gn:dem":128,
    "gn:feature_class":"P",
    "gn:feature_code":"PPL",
    "gn:name":"Pekotino",
    "gn:population":0,
    "gn:timezone":"Europe/Minsk",
    "iso:country":"BY",
    "name:rus_x_preferred":[
        "\u041f\u0435\u043a\u043e\u0442\u0438\u043d\u043e"
    ],
    "wof:name":"Pekotino",
    "wof:placetype":"locality"
},
  "geometry": {"coordinates":[28.1062,55.6014],"type":"Point"}
}