{
  "type": "Feature",
  "properties": {
    "gn:admin1_code":"6.0",
    "gn:asciiname":"Malyye Belevichi",
    "gn:country_code":"BY",
    "gn:dem":164,
    "gn:feature_class":"P",
    "gn:feature_code":"PPL",
    "gn:name":"Malyye Belevichi",
    "gn:population":0,
    "gn:timezone":"Europe/Minsk",
    "iso:country":"BY",
    "name:rus_x_preferred":[
        "\u041c\u0430\u043b\u044b\u0435 \u0411\u0435\u043b\u0435\u0432\u0438\u0447\u0438"
    ],
    "wof:name":"Malyye Belevichi",
    "wof:placetype":"locality"
},
  "geometry": {"coordinates":[29.8341,53.8353],"type":"Point"}
}