{
  "type": "Feature",
  "properties": {
    "gn:admin1_code":"2.0",
    "gn:asciiname":"Staraya Dubrova",
    "gn:country_code":"BY",
    "gn:dem":133,
    "gn:feature_class":"P",
    "gn:feature_code":"PPL",
    "gn:name":"Staraya Dubrova",
    "gn:population":0,
    "gn:timezone":"Europe/Minsk",
    "iso:country":"BY",
    "name:bel_x_preferred":[
        "\u0421\u0442\u0430\u0440\u0430\u044f \u0414\u0443\u0431\u0440\u043e\u0432\u0430"
    ],
    "wof:name":"Staraya Dubrova",
    "wof:placetype":"locality"
},
  "geometry": {"coordinates":[28.8757,52.6602],"type":"Point"}
}