{
  "type": "Feature",
  "properties": {
    "gn:admin1_code":"6.0",
    "gn:asciiname":"Krasnaya Zarya",
    "gn:country_code":"BY",
    "gn:dem":179,
    "gn:feature_class":"P",
    "gn:feature_code":"PPL",
    "gn:name":"Krasnaya Zarya",
    "gn:population":0,
    "gn:timezone":"Europe/Minsk",
    "iso:country":"BY",
    "name:rus_x_preferred":[
        "\u041a\u0440\u0430\u0441\u043d\u0430\u044f \u0417\u0430\u0440\u044f"
    ],
    "wof:name":"Krasnaya Zarya",
    "wof:placetype":"locality"
},
  "geometry": {"coordinates":[31.0013,53.8513],"type":"Point"}
}