{
  "type": "Feature",
  "properties": {
    "gn:admin1_code":"3.0",
    "gn:asciiname":"Bernatovshchina",
    "gn:country_code":"BY",
    "gn:dem":212,
    "gn:feature_class":"P",
    "gn:feature_code":"PPL",
    "gn:name":"Bernatovshchina",
    "gn:population":0,
    "gn:timezone":"Europe/Minsk",
    "iso:country":"BY",
    "name:bel_x_preferred":[
        "Byarnatawshchyna"
    ],
    "name:bel_x_variant":[
        "\u0411\u044f\u0440\u043d\u0430\u0442\u0430\u045e\u0448\u0447\u044b\u043d\u0430"
    ],
    "name:rus_x_preferred":[
        "\u0411\u0435\u0440\u043d\u0430\u0442\u043e\u0432\u0449\u0438\u043d\u0430"
    ],
    "wof:name":"Bernatovshchina",
    "wof:placetype":"locality"
},
  "geometry": {"coordinates":[25.6531,53.4176],"type":"Point"}
}