{
  "type": "Feature",
  "properties": {
    "gn:admin1_code":"1.0",
    "gn:asciiname":"Staruny",
    "gn:country_code":"BY",
    "gn:dem":145,
    "gn:feature_class":"P",
    "gn:feature_code":"PPL",
    "gn:name":"Staruny",
    "gn:population":0,
    "gn:timezone":"Europe/Minsk",
    "iso:country":"BY",
    "name:rus_x_preferred":[
        "\u0421\u0442\u0430\u0440\u0443\u043d\u044b"
    ],
    "wof:name":"Staruny",
    "wof:placetype":"locality"
},
  "geometry": {"coordinates":[24.0683,52.4245],"type":"Point"}
}