{
  "type": "Feature",
  "properties": {
    "gn:admin1_code":"7.0",
    "gn:asciiname":"Buchany",
    "gn:country_code":"BY",
    "gn:dem":129,
    "gn:feature_class":"P",
    "gn:feature_code":"PPL",
    "gn:name":"Buchany",
    "gn:population":0,
    "gn:timezone":"Europe/Minsk",
    "iso:country":"BY",
    "name:rus_x_preferred":[
        "\u0411\u0443\u0447\u0430\u043d\u044b"
    ],
    "wof:name":"Buchany",
    "wof:placetype":"locality"
},
  "geometry": {"coordinates":[26.7995,55.3216],"type":"Point"}
}