{
  "type": "Feature",
  "properties": {
    "gn:admin1_code":"2.0",
    "gn:asciiname":"Vetkhin'",
    "gn:country_code":"BY",
    "gn:dem":130,
    "gn:feature_class":"P",
    "gn:feature_code":"PPL",
    "gn:name":"Vetkhin\u2019",
    "gn:population":0,
    "gn:timezone":"Europe/Minsk",
    "iso:country":"BY",
    "name:rus_x_preferred":[
        "\u0412\u0435\u0442\u0445\u0438\u043d\u044c"
    ],
    "name:und_x_variant":[
        "Vetkhin\u2019"
    ],
    "wof:name":"Vetkhin'",
    "wof:placetype":"locality"
},
  "geometry": {"coordinates":[30.5078,52.1763],"type":"Point"}
}