{
  "type": "Feature",
  "properties": {
    "gn:admin1_code":"2.0",
    "gn:asciiname":"Peredovaya",
    "gn:country_code":"BY",
    "gn:dem":142,
    "gn:feature_class":"P",
    "gn:feature_code":"PPL",
    "gn:name":"Peredovaya",
    "gn:population":0,
    "gn:timezone":"Europe/Minsk",
    "iso:country":"BY",
    "name:rus_x_preferred":[
        "\u041f\u0435\u0440\u0435\u0434\u043e\u0432\u0430\u044f"
    ],
    "wof:name":"Peredovaya",
    "wof:placetype":"locality"
},
  "geometry": {"coordinates":[29.712,53.0297],"type":"Point"}
}