{
  "type": "Feature",
  "properties": {
    "gn:admin1_code":"7.0",
    "gn:asciiname":"Ust'ye",
    "gn:country_code":"BY",
    "gn:dem":134,
    "gn:feature_class":"P",
    "gn:feature_code":"PPL",
    "gn:name":"Ust\u2019ye",
    "gn:population":0,
    "gn:timezone":"Europe/Minsk",
    "iso:country":"BY",
    "name:rus_x_preferred":[
        "\u0423\u0441\u0442\u044c\u0435"
    ],
    "name:und_x_variant":[
        "Ust\u2019ye"
    ],
    "wof:name":"Ust'ye",
    "wof:placetype":"locality"
},
  "geometry": {"coordinates":[27.1454,55.6941],"type":"Point"}
}