{
  "type": "Feature",
  "properties": {
    "gn:admin1_code":"5.0",
    "gn:asciiname":"Gnet'ki",
    "gn:country_code":"BY",
    "gn:dem":175,
    "gn:feature_class":"P",
    "gn:feature_code":"PPL",
    "gn:name":"Gnet\u2019ki",
    "gn:population":0,
    "gn:timezone":"Europe/Minsk",
    "iso:country":"BY",
    "name:rus_x_preferred":[
        "\u0413\u043d\u0435\u0442\u044c\u043a\u0438"
    ],
    "name:und_x_variant":[
        "Gnet\u2019ki"
    ],
    "wof:name":"Gnet'ki",
    "wof:placetype":"locality"
},
  "geometry": {"coordinates":[26.8281,53.682],"type":"Point"}
}