{
  "type": "Feature",
  "properties": {
    "gn:admin1_code":"1.0",
    "gn:asciiname":"Teresiny",
    "gn:country_code":"BY",
    "gn:dem":159,
    "gn:feature_class":"P",
    "gn:feature_code":"PPL",
    "gn:name":"Teresiny",
    "gn:population":0,
    "gn:timezone":"Europe/Minsk",
    "iso:country":"BY",
    "name:rus_x_preferred":[
        "\u0422\u0435\u0440\u0435\u0441\u0438\u043d\u044b"
    ],
    "wof:name":"Teresiny",
    "wof:placetype":"locality"
},
  "geometry": {"coordinates":[23.6912,52.5056],"type":"Point"}
}