{
  "type": "Feature",
  "properties": {
    "gn:admin1_code":"5.0",
    "gn:asciiname":"Niwnaye",
    "gn:country_code":"BY",
    "gn:dem":194,
    "gn:feature_class":"P",
    "gn:feature_code":"PPL",
    "gn:name":"Niwnaye",
    "gn:population":0,
    "gn:timezone":"Europe/Minsk",
    "iso:country":"BY",
    "name:bel_x_preferred":[
        "\u041d\u0456\u045e\u043d\u0430\u0435"
    ],
    "name:und_x_variant":[
        "Nivno",
        "Nivnoye"
    ],
    "wof:name":"Niwnaye",
    "wof:placetype":"locality"
},
  "geometry": {"coordinates":[26.5071,53.713],"type":"Point"}
}