{
  "type": "Feature",
  "properties": {
    "gn:admin1_code":"3.0",
    "gn:asciiname":"Hawya",
    "gn:country_code":"BY",
    "gn:dem":146,
    "gn:feature_class":"P",
    "gn:feature_code":"PPL",
    "gn:name":"Hawya",
    "gn:population":0,
    "gn:timezone":"Europe/Minsk",
    "iso:country":"BY",
    "name:bel_x_preferred":[
        "Hawya"
    ],
    "name:bel_x_variant":[
        "\u0413\u0430\u045e\u044f"
    ],
    "name:rus_x_preferred":[
        "\u0413\u0430\u0432\u044c\u044f"
    ],
    "name:und_x_variant":[
        "Gav\u2019ya"
    ],
    "wof:name":"Hawya",
    "wof:placetype":"locality"
},
  "geometry": {"coordinates":[25.6498,53.97975],"type":"Point"}
}