{
  "type": "Feature",
  "properties": {
    "gn:admin1_code":"7.0",
    "gn:asciiname":"Russki",
    "gn:country_code":"BY",
    "gn:dem":141,
    "gn:feature_class":"P",
    "gn:feature_code":"PPL",
    "gn:name":"Russki",
    "gn:population":0,
    "gn:timezone":"Europe/Minsk",
    "iso:country":"BY",
    "name:rus_x_preferred":[
        "\u0420\u0443\u0441\u0441\u043a\u0438"
    ],
    "name:und_x_variant":[
        "Russkiye"
    ],
    "wof:name":"Russki",
    "wof:placetype":"locality"
},
  "geometry": {"coordinates":[29.6877,55.1832],"type":"Point"}
}