{
  "type": "Feature",
  "properties": {
    "gn:admin1_code":"5.0",
    "gn:asciiname":"Izbishche",
    "gn:country_code":"BY",
    "gn:dem":159,
    "gn:feature_class":"P",
    "gn:feature_code":"PPL",
    "gn:name":"Izbishche",
    "gn:population":0,
    "gn:timezone":"Europe/Minsk",
    "iso:country":"BY",
    "name:rus_x_preferred":[
        "\u0418\u0437\u0431\u0438\u0449\u0435"
    ],
    "wof:name":"Izbishche",
    "wof:placetype":"locality"
},
  "geometry": {"coordinates":[28.2487,53.6013],"type":"Point"}
}