{
  "type": "Feature",
  "properties": {
    "gn:admin1_code":"5.0",
    "gn:asciiname":"Golovki",
    "gn:country_code":"BY",
    "gn:dem":171,
    "gn:feature_class":"P",
    "gn:feature_code":"PPL",
    "gn:name":"Golovki",
    "gn:population":0,
    "gn:timezone":"Europe/Minsk",
    "iso:country":"BY",
    "name:rus_x_preferred":[
        "\u0413\u043e\u043b\u043e\u0432\u043a\u0438"
    ],
    "wof:name":"Golovki",
    "wof:placetype":"locality"
},
  "geometry": {"coordinates":[26.995,53.3679],"type":"Point"}
}