{
  "type": "Feature",
  "properties": {
    "gn:admin1_code":"1.0",
    "gn:asciiname":"Kupichy",
    "gn:country_code":"BY",
    "gn:dem":159,
    "gn:feature_class":"P",
    "gn:feature_code":"PPL",
    "gn:name":"Kupichy",
    "gn:population":0,
    "gn:timezone":"Europe/Minsk",
    "iso:country":"BY",
    "name:bel_x_preferred":[
        "\u041a\u0443\u043f\u0456\u0447\u044b"
    ],
    "name:und_x_variant":[
        "Kupiche",
        "Kupicze",
        "Kupichy",
        "Kupichi"
    ],
    "wof:name":"Kupichy",
    "wof:placetype":"locality"
},
  "geometry": {"coordinates":[24.1886,52.5882],"type":"Point"}
}