{
  "type": "Feature",
  "properties": {
    "gn:admin1_code":"1.0",
    "gn:asciiname":"Bobrovtsy",
    "gn:country_code":"BY",
    "gn:dem":132,
    "gn:feature_class":"P",
    "gn:feature_code":"PPL",
    "gn:name":"Bobrovtsy",
    "gn:population":0,
    "gn:timezone":"Europe/Minsk",
    "iso:country":"BY",
    "name:rus_x_preferred":[
        "\u0411\u043e\u0431\u0440\u043e\u0432\u0446\u044b"
    ],
    "wof:name":"Bobrovtsy",
    "wof:placetype":"locality"
},
  "geometry": {"coordinates":[23.643,52.1552],"type":"Point"}
}