{
  "type": "Feature",
  "properties": {
    "gn:admin1_code":"2.0",
    "gn:asciiname":"Barshchowka",
    "gn:country_code":"BY",
    "gn:dem":152,
    "gn:feature_class":"P",
    "gn:feature_code":"PPL",
    "gn:name":"Barshchowka",
    "gn:population":0,
    "gn:timezone":"Europe/Minsk",
    "iso:country":"BY",
    "name:bel_x_preferred":[
        "\u0411\u0430\u0440\u0448\u0447\u043e\u045e\u043a\u0430"
    ],
    "name:eng_x_preferred":[
        "Borshch\u00ebvka"
    ],
    "name:rus_x_preferred":[
        "\u0411\u043e\u0440\u0449\u043e\u0432\u043a\u0430"
    ],
    "name:und_x_variant":[
        "Borshchovka",
        "Borshch\u00ebvka"
    ],
    "wof:name":"Barshchowka",
    "wof:placetype":"locality"
},
  "geometry": {"coordinates":[31.5629,52.2117],"type":"Point"}
}