{
  "type": "Feature",
  "properties": {
    "gn:admin1_code":"3.0",
    "gn:asciiname":"Vizgirdy",
    "gn:country_code":"BY",
    "gn:dem":167,
    "gn:feature_class":"P",
    "gn:feature_code":"PPL",
    "gn:name":"Vizgirdy",
    "gn:population":0,
    "gn:timezone":"Europe/Minsk",
    "iso:country":"BY",
    "name:rus_x_preferred":[
        "\u0412\u0438\u0437\u0433\u0438\u0440\u0434\u044b"
    ],
    "wof:name":"Vizgirdy",
    "wof:placetype":"locality"
},
  "geometry": {"coordinates":[25.2987,54.2462],"type":"Point"}
}