{
  "type": "Feature",
  "properties": {
    "gn:admin1_code":"7.0",
    "gn:asciiname":"Pridvor'ye",
    "gn:country_code":"BY",
    "gn:dem":139,
    "gn:feature_class":"P",
    "gn:feature_code":"PPL",
    "gn:name":"Pridvor\u2019ye",
    "gn:population":0,
    "gn:timezone":"Europe/Minsk",
    "iso:country":"BY",
    "name:rus_x_preferred":[
        "\u041f\u0440\u0438\u0434\u0432\u043e\u0440\u044c\u0435"
    ],
    "name:und_x_variant":[
        "Pridvor\u2019ye"
    ],
    "wof:name":"Pridvor'ye",
    "wof:placetype":"locality"
},
  "geometry": {"coordinates":[29.1668,54.8094],"type":"Point"}
}