{
  "type": "Feature",
  "properties": {
    "gn:admin1_code":"5.0",
    "gn:asciiname":"Yanushkavichy",
    "gn:country_code":"BY",
    "gn:dem":226,
    "gn:feature_class":"P",
    "gn:feature_code":"PPL",
    "gn:name":"Yanushkavichy",
    "gn:population":0,
    "gn:timezone":"Europe/Minsk",
    "iso:country":"BY",
    "name:bel_x_preferred":[
        "\u042f\u043d\u0443\u0448\u043a\u0430\u0432\u0456\u0447\u044b"
    ],
    "name:eng_x_preferred":[
        "Yanushkovichi"
    ],
    "name:rus_x_preferred":[
        "\u042f\u043d\u0443\u0448\u043a\u043e\u0432\u0438\u0447\u0438"
    ],
    "name:und_x_variant":[
        "Yanushkovichi",
        "Yanushkavichy"
    ],
    "wof:name":"Yanushkavichy",
    "wof:placetype":"locality"
},
  "geometry": {"coordinates":[27.6108,54.2691],"type":"Point"}
}