{
  "type": "Feature",
  "properties": {
    "gn:admin1_code":"7.0",
    "gn:asciiname":"Asintorf",
    "gn:country_code":"BY",
    "gn:dem":176,
    "gn:feature_class":"P",
    "gn:feature_code":"PPL",
    "gn:name":"Asintorf",
    "gn:population":0,
    "gn:timezone":"Europe/Minsk",
    "iso:country":"BY",
    "name:bel_x_preferred":[
        "\u0410\u0441\u0456\u043d\u0442\u043e\u0440\u0444"
    ],
    "name:eng_x_preferred":[
        "Osintorf"
    ],
    "name:rus_x_preferred":[
        "\u041e\u0441\u0438\u043d\u0442\u043e\u0440\u0444"
    ],
    "name:und_x_variant":[
        "Osinstroy",
        "Asintorf"
    ],
    "wof:name":"Asintorf",
    "wof:placetype":"locality"
},
  "geometry": {"coordinates":[30.6581,54.7148],"type":"Point"}
}