{
  "type": "Feature",
  "properties": {
    "gn:admin1_code":"6.0",
    "gn:asciiname":"Mashenoye",
    "gn:country_code":"BY",
    "gn:dem":194,
    "gn:feature_class":"P",
    "gn:feature_code":"PPL",
    "gn:name":"Mashenoye",
    "gn:population":0,
    "gn:timezone":"Europe/Minsk",
    "iso:country":"BY",
    "name:rus_x_preferred":[
        "\u041c\u0430\u0448\u0435\u043d\u043e\u0435"
    ],
    "name:und_x_variant":[
        "Moshanoye"
    ],
    "wof:name":"Mashenoye",
    "wof:placetype":"locality"
},
  "geometry": {"coordinates":[31.5154,53.8991],"type":"Point"}
}