{
  "type": "Feature",
  "properties": {
    "gn:admin1_code":"5.0",
    "gn:asciiname":"Stayki",
    "gn:country_code":"BY",
    "gn:dem":208,
    "gn:feature_class":"P",
    "gn:feature_code":"PPL",
    "gn:name":"Stayki",
    "gn:population":0,
    "gn:timezone":"Europe/Minsk",
    "iso:country":"BY",
    "name:eng_x_preferred":[
        "Stayki"
    ],
    "name:rus_x_preferred":[
        "\u0421\u0442\u0430\u0439\u043a\u0438"
    ],
    "name:und_x_variant":[
        "Stajki",
        "Stayki"
    ],
    "wof:name":"Stayki",
    "wof:placetype":"locality"
},
  "geometry": {"coordinates":[27.4346,54.4692],"type":"Point"}
}