{
  "type": "Feature",
  "properties": {
    "gn:admin1_code":"7.0",
    "gn:asciiname":"Fedorenki",
    "gn:country_code":"BY",
    "gn:dem":136,
    "gn:feature_class":"P",
    "gn:feature_code":"PPL",
    "gn:name":"Fedorenki",
    "gn:population":0,
    "gn:timezone":"Europe/Minsk",
    "iso:country":"BY",
    "name:rus_x_preferred":[
        "\u0424\u0435\u0434\u043e\u0440\u0435\u043d\u043a\u0438"
    ],
    "wof:name":"Fedorenki",
    "wof:placetype":"locality"
},
  "geometry": {"coordinates":[28.6929,55.2242],"type":"Point"}
}