{
  "type": "Feature",
  "properties": {
    "gn:admin1_code":"7.0",
    "gn:asciiname":"Buda Blizhnyaya",
    "gn:country_code":"BY",
    "gn:dem":129,
    "gn:feature_class":"P",
    "gn:feature_code":"PPL",
    "gn:name":"Buda Blizhnyaya",
    "gn:population":0,
    "gn:timezone":"Europe/Minsk",
    "iso:country":"BY",
    "name:rus_x_preferred":[
        "\u0411\u0443\u0434\u0430 \u0411\u043b\u0438\u0436\u043d\u044f\u044f"
    ],
    "wof:name":"Buda Blizhnyaya",
    "wof:placetype":"locality"
},
  "geometry": {"coordinates":[27.2116,55.4137],"type":"Point"}
}