{
  "type": "Feature",
  "properties": {
    "gn:admin1_code":"1.0",
    "gn:asciiname":"Mykshitsy",
    "gn:country_code":"BY",
    "gn:dem":148,
    "gn:feature_class":"P",
    "gn:feature_code":"PPL",
    "gn:name":"Mykshitsy",
    "gn:population":0,
    "gn:timezone":"Europe/Minsk",
    "iso:country":"BY",
    "name:rus_x_preferred":[
        "\u041c\u044b\u043a\u0448\u0438\u0446\u044b"
    ],
    "wof:name":"Mykshitsy",
    "wof:placetype":"locality"
},
  "geometry": {"coordinates":[23.3995,52.383],"type":"Point"}
}