{
  "type": "Feature",
  "properties": {
    "gn:admin1_code":"2.0",
    "gn:asciiname":"Listvin",
    "gn:country_code":"BY",
    "gn:dem":126,
    "gn:feature_class":"P",
    "gn:feature_code":"PPL",
    "gn:name":"Listvin",
    "gn:population":0,
    "gn:timezone":"Europe/Minsk",
    "iso:country":"BY",
    "name:rus_x_preferred":[
        "\u041b\u0438\u0441\u0442\u0432\u0438\u043d"
    ],
    "wof:name":"Listvin",
    "wof:placetype":"locality"
},
  "geometry": {"coordinates":[30.0586,51.8526],"type":"Point"}
}