{
  "type": "Feature",
  "properties": {
    "gn:admin1_code":"2.0",
    "gn:asciiname":"Otskovannoye",
    "gn:country_code":"BY",
    "gn:dem":124,
    "gn:feature_class":"P",
    "gn:feature_code":"PPL",
    "gn:name":"Otskovannoye",
    "gn:population":0,
    "gn:timezone":"Europe/Minsk",
    "iso:country":"BY",
    "name:rus_x_preferred":[
        "\u041e\u0446\u043a\u043e\u0432\u0430\u043d\u043d\u043e\u0435"
    ],
    "wof:name":"Otskovannoye",
    "wof:placetype":"locality"
},
  "geometry": {"coordinates":[27.799,52.1464],"type":"Point"}
}