{
  "type": "Feature",
  "properties": {
    "gn:admin1_code":"5.0",
    "gn:asciiname":"Shilino",
    "gn:country_code":"BY",
    "gn:dem":184,
    "gn:feature_class":"P",
    "gn:feature_code":"PPL",
    "gn:name":"Shilino",
    "gn:population":0,
    "gn:timezone":"Europe/Minsk",
    "iso:country":"BY",
    "name:rus_x_preferred":[
        "\u0428\u0438\u043b\u0438\u043d\u043e"
    ],
    "wof:name":"Shilino",
    "wof:placetype":"locality"
},
  "geometry": {"coordinates":[28.7114,54.24100000000001],"type":"Point"}
}