{
  "type": "Feature",
  "properties": {
    "gn:admin1_code":"2.0",
    "gn:asciiname":"Luki",
    "gn:country_code":"BY",
    "gn:dem":137,
    "gn:feature_class":"P",
    "gn:feature_code":"PPL",
    "gn:name":"Luki",
    "gn:population":0,
    "gn:timezone":"Europe/Minsk",
    "iso:country":"BY",
    "name:bel_x_preferred":[
        "\u041b\u0443\u043a\u0456"
    ],
    "name:ceb_x_preferred":[
        "Luki"
    ],
    "name:deu_x_preferred":[
        "Luky"
    ],
    "name:eng_x_preferred":[
        "Luki"
    ],
    "name:fra_x_preferred":[
        "Luki"
    ],
    "name:rus_x_preferred":[
        "\u041b\u0443\u043a\u0438"
    ],
    "name:slk_x_preferred":[
        "L\u00faky"
    ],
    "name:srp_x_preferred":[
        "\u041b\u0443\u043a\u0438"
    ],
    "name:swe_x_preferred":[
        "Luki"
    ],
    "name:ukr_x_preferred":[
        "\u041b\u0443\u043a\u0438"
    ],
    "wof:name":"Luki",
    "wof:placetype":"locality"
},
  "geometry": {"coordinates":[29.9746,52.9589],"type":"Point"}
}