{
  "type": "Feature",
  "properties": {
    "gn:admin1_code":"3.0",
    "gn:asciiname":"Putno",
    "gn:country_code":"BY",
    "gn:dem":176,
    "gn:feature_class":"P",
    "gn:feature_code":"PPL",
    "gn:name":"Putno",
    "gn:population":0,
    "gn:timezone":"Europe/Minsk",
    "iso:country":"BY",
    "name:pol_x_preferred":[
        "Putno"
    ],
    "name:rus_x_preferred":[
        "\u041f\u0443\u0442\u043d\u043e"
    ],
    "name:vie_x_preferred":[
        "Putno"
    ],
    "wof:name":"Putno",
    "wof:placetype":"locality"
},
  "geometry": {"coordinates":[23.8136,53.5169],"type":"Point"}
}