{
  "type": "Feature",
  "properties": {
    "gn:admin1_code":"5.0",
    "gn:asciiname":"Savoni",
    "gn:country_code":"BY",
    "gn:dem":173,
    "gn:feature_class":"P",
    "gn:feature_code":"PPL",
    "gn:name":"Savoni",
    "gn:population":0,
    "gn:timezone":"Europe/Minsk",
    "iso:country":"BY",
    "name:eng_x_preferred":[
        "Savoni"
    ],
    "name:rus_x_preferred":[
        "\u0421\u0430\u0432\u043e\u043d\u0438"
    ],
    "name:und_x_variant":[
        "Savone"
    ],
    "wof:name":"Savoni",
    "wof:placetype":"locality"
},
  "geometry": {"coordinates":[26.6429,53.4008],"type":"Point"}
}