{
  "type": "Feature",
  "properties": {
    "gn:admin1_code":"7.0",
    "gn:asciiname":"Turinets",
    "gn:country_code":"BY",
    "gn:dem":189,
    "gn:feature_class":"P",
    "gn:feature_code":"PPL",
    "gn:name":"Turinets",
    "gn:population":0,
    "gn:timezone":"Europe/Minsk",
    "iso:country":"BY",
    "name:rus_x_preferred":[
        "\u0422\u0443\u0440\u0438\u043d\u0435\u0446"
    ],
    "wof:name":"Turinets",
    "wof:placetype":"locality"
},
  "geometry": {"coordinates":[29.8919,55.5296],"type":"Point"}
}