{
  "type": "Feature",
  "properties": {
    "gn:admin1_code":"6.0",
    "gn:asciiname":"Turkovskaya Sloboda",
    "gn:country_code":"BY",
    "gn:dem":137,
    "gn:feature_class":"P",
    "gn:feature_code":"PPL",
    "gn:name":"Turkovskaya Sloboda",
    "gn:population":0,
    "gn:timezone":"Europe/Minsk",
    "iso:country":"BY",
    "name:rus_x_preferred":[
        "\u0422\u0443\u0440\u043a\u043e\u0432\u0441\u043a\u0430\u044f \u0421\u043b\u043e\u0431\u043e\u0434\u0430"
    ],
    "wof:name":"Turkovskaya Sloboda",
    "wof:placetype":"locality"
},
  "geometry": {"coordinates":[29.6287,53.0254],"type":"Point"}
}