{
  "type": "Feature",
  "properties": {
    "gn:admin1_code":"7.0",
    "gn:asciiname":"Lobachevo",
    "gn:country_code":"BY",
    "gn:dem":140,
    "gn:feature_class":"P",
    "gn:feature_code":"PPL",
    "gn:name":"Lobach\u00ebvo",
    "gn:population":0,
    "gn:timezone":"Europe/Minsk",
    "iso:country":"BY",
    "name:rus_x_preferred":[
        "\u041b\u043e\u0431\u0430\u0447\u0451\u0432\u043e"
    ],
    "name:und_x_variant":[
        "Lobach\u00ebvo"
    ],
    "wof:name":"Lobachevo",
    "wof:placetype":"locality"
},
  "geometry": {"coordinates":[29.4443,55.0247],"type":"Point"}
}