{
  "type": "Feature",
  "properties": {
    "gn:admin1_code":"7.0",
    "gn:asciiname":"Uzrech'ye",
    "gn:country_code":"BY",
    "gn:dem":141,
    "gn:feature_class":"P",
    "gn:feature_code":"PPL",
    "gn:name":"Uzrech\u2019ye",
    "gn:population":0,
    "gn:timezone":"Europe/Minsk",
    "iso:country":"BY",
    "name:rus_x_preferred":[
        "\u0423\u0437\u0440\u0435\u0447\u044c\u0435"
    ],
    "name:und_x_variant":[
        "Uzrech\u2019ye"
    ],
    "wof:name":"Uzrech'ye",
    "wof:placetype":"locality"
},
  "geometry": {"coordinates":[29.404,55.13],"type":"Point"}
}