{
  "type": "Feature",
  "properties": {
    "gn:admin1_code":"7.0",
    "gn:asciiname":"Potashenki",
    "gn:country_code":"BY",
    "gn:dem":134,
    "gn:feature_class":"P",
    "gn:feature_code":"PPL",
    "gn:name":"Potashenki",
    "gn:population":0,
    "gn:timezone":"Europe/Minsk",
    "iso:country":"BY",
    "name:rus_x_preferred":[
        "\u041f\u043e\u0442\u0430\u0448\u0435\u043d\u043a\u0438"
    ],
    "wof:name":"Potashenki",
    "wof:placetype":"locality"
},
  "geometry": {"coordinates":[28.8432,55.6972],"type":"Point"}
}