{
  "type": "Feature",
  "properties": {
    "gn:admin1_code":"7.0",
    "gn:asciiname":"Shchaty",
    "gn:country_code":"BY",
    "gn:dem":134,
    "gn:feature_class":"P",
    "gn:feature_code":"PPL",
    "gn:name":"Shchaty",
    "gn:population":0,
    "gn:timezone":"Europe/Minsk",
    "iso:country":"BY",
    "name:rus_x_preferred":[
        "\u0429\u0430\u0442\u044b"
    ],
    "wof:name":"Shchaty",
    "wof:placetype":"locality"
},
  "geometry": {"coordinates":[28.806,55.3056],"type":"Point"}
}