{
  "type": "Feature",
  "properties": {
    "gn:admin1_code":"3.0",
    "gn:asciiname":"Krivulichi",
    "gn:country_code":"BY",
    "gn:dem":168,
    "gn:feature_class":"P",
    "gn:feature_code":"PPL",
    "gn:name":"Krivulichi",
    "gn:population":0,
    "gn:timezone":"Europe/Minsk",
    "iso:country":"BY",
    "name:rus_x_preferred":[
        "\u041a\u0440\u0438\u0432\u0443\u043b\u0438\u0447\u0438"
    ],
    "wof:name":"Krivulichi",
    "wof:placetype":"locality"
},
  "geometry": {"coordinates":[24.4436,53.0351],"type":"Point"}
}