{
  "type": "Feature",
  "properties": {
    "gn:admin1_code":"3.0",
    "gn:asciiname":"Mokritsy",
    "gn:country_code":"BY",
    "gn:dem":234,
    "gn:feature_class":"P",
    "gn:feature_code":"PPL",
    "gn:name":"Mokritsy",
    "gn:population":0,
    "gn:timezone":"Europe/Minsk",
    "iso:country":"BY",
    "name:rus_x_preferred":[
        "\u041c\u043e\u043a\u0440\u0438\u0446\u044b"
    ],
    "wof:name":"Mokritsy",
    "wof:placetype":"locality"
},
  "geometry": {"coordinates":[25.8119,54.5365],"type":"Point"}
}