{
  "type": "Feature",
  "properties": {
    "gn:admin1_code":"7.0",
    "gn:asciiname":"Bol'shoye Gal'tsevo",
    "gn:country_code":"BY",
    "gn:dem":208,
    "gn:feature_class":"P",
    "gn:feature_code":"PPL",
    "gn:name":"Bol\u2019shoye Gal\u2019tsevo",
    "gn:population":0,
    "gn:timezone":"Europe/Minsk",
    "iso:country":"BY",
    "name:rus_x_preferred":[
        "\u0411\u043e\u043b\u044c\u0448\u043e\u0435 \u0413\u0430\u043b\u044c\u0446\u0435\u0432\u043e"
    ],
    "name:und_x_variant":[
        "Bol\u2019shoye Gal\u2019tsevo"
    ],
    "wof:name":"Bol'shoye Gal'tsevo",
    "wof:placetype":"locality"
},
  "geometry": {"coordinates":[30.00800000000001,54.5196],"type":"Point"}
}