{
  "type": "Feature",
  "properties": {
    "gn:admin1_code":"6.0",
    "gn:asciiname":"Azarichi",
    "gn:country_code":"BY",
    "gn:dem":143,
    "gn:feature_class":"P",
    "gn:feature_code":"PPL",
    "gn:name":"Azarichi",
    "gn:population":0,
    "gn:timezone":"Europe/Minsk",
    "iso:country":"BY",
    "name:rus_x_preferred":[
        "\u0410\u0437\u0430\u0440\u0438\u0447\u0438"
    ],
    "name:und_x_variant":[
        "Anarichi",
        "Azarichi"
    ],
    "wof:name":"Azarichi",
    "wof:placetype":"locality"
},
  "geometry": {"coordinates":[30.8487,53.61600000000001],"type":"Point"}
}