{
  "type": "Feature",
  "properties": {
    "gn:admin1_code":"5.0",
    "gn:asciiname":"Vytropovshchina",
    "gn:country_code":"BY",
    "gn:dem":209,
    "gn:feature_class":"P",
    "gn:feature_code":"PPL",
    "gn:name":"Vytropovshchina",
    "gn:population":0,
    "gn:timezone":"Europe/Minsk",
    "iso:country":"BY",
    "name:rus_x_preferred":[
        "\u0412\u044b\u0442\u0440\u043e\u043f\u043e\u0432\u0449\u0438\u043d\u0430"
    ],
    "wof:name":"Vytropovshchina",
    "wof:placetype":"locality"
},
  "geometry": {"coordinates":[26.8102,54.2908],"type":"Point"}
}