{
  "type": "Feature",
  "properties": {
    "gn:admin1_code":"1.0",
    "gn:asciiname":"Malaya Zhabinka",
    "gn:country_code":"BY",
    "gn:dem":140,
    "gn:feature_class":"P",
    "gn:feature_code":"PPL",
    "gn:name":"Malaya Zhabinka",
    "gn:population":0,
    "gn:timezone":"Europe/Minsk",
    "iso:country":"BY",
    "name:rus_x_preferred":[
        "\u041c\u0430\u043b\u0430\u044f \u0416\u0430\u0431\u0438\u043d\u043a\u0430"
    ],
    "wof:name":"Malaya Zhabinka",
    "wof:placetype":"locality"
},
  "geometry": {"coordinates":[24.0373,52.2045],"type":"Point"}
}