{
  "type": "Feature",
  "properties": {
    "gn:admin1_code":"7.0",
    "gn:asciiname":"Cherenka",
    "gn:country_code":"BY",
    "gn:dem":134,
    "gn:feature_class":"P",
    "gn:feature_code":"PPL",
    "gn:name":"Cherenka",
    "gn:population":0,
    "gn:timezone":"Europe/Minsk",
    "iso:country":"BY",
    "name:rus_x_preferred":[
        "\u0427\u0435\u0440\u0435\u043d\u043a\u0430"
    ],
    "name:und_x_variant":[
        "Cher\u00ebmka"
    ],
    "wof:name":"Cherenka",
    "wof:placetype":"locality"
},
  "geometry": {"coordinates":[29.3632,55.4148],"type":"Point"}
}