{
  "type": "Feature",
  "properties": {
    "gn:admin1_code":"7.0",
    "gn:asciiname":"Blinovshchina",
    "gn:country_code":"BY",
    "gn:dem":127,
    "gn:feature_class":"P",
    "gn:feature_code":"PPL",
    "gn:name":"Blinovshchina",
    "gn:population":0,
    "gn:timezone":"Europe/Minsk",
    "iso:country":"BY",
    "name:rus_x_preferred":[
        "\u0411\u043b\u0438\u043d\u043e\u0432\u0449\u0438\u043d\u0430"
    ],
    "wof:name":"Blinovshchina",
    "wof:placetype":"locality"
},
  "geometry": {"coordinates":[27.1884,55.383],"type":"Point"}
}