{
  "type": "Feature",
  "properties": {
    "gn:admin1_code":"5.0",
    "gn:asciiname":"Krechevtsy",
    "gn:country_code":"BY",
    "gn:dem":300,
    "gn:feature_class":"P",
    "gn:feature_code":"PPL",
    "gn:name":"Krechevtsy",
    "gn:population":0,
    "gn:timezone":"Europe/Minsk",
    "iso:country":"BY",
    "name:rus_x_preferred":[
        "\u041a\u0440\u0435\u0447\u0435\u0432\u0446\u044b"
    ],
    "wof:name":"Krechevtsy",
    "wof:placetype":"locality"
},
  "geometry": {"coordinates":[27.0202,54.0696],"type":"Point"}
}