{
  "type": "Feature",
  "properties": {
    "gn:admin1_code":"1.0",
    "gn:asciiname":"Chernichnoye",
    "gn:country_code":"BY",
    "gn:dem":155,
    "gn:feature_class":"P",
    "gn:feature_code":"PPL",
    "gn:name":"Chernichnoye",
    "gn:population":0,
    "gn:timezone":"Europe/Minsk",
    "iso:country":"BY",
    "name:rus_x_preferred":[
        "\u0427\u0435\u0440\u043d\u0438\u0447\u043d\u043e\u0435"
    ],
    "wof:name":"Chernichnoye",
    "wof:placetype":"locality"
},
  "geometry": {"coordinates":[24.6978,52.5496],"type":"Point"}
}