{
  "type": "Feature",
  "properties": {
    "gn:admin1_code":"7.0",
    "gn:asciiname":"Lomachino",
    "gn:country_code":"BY",
    "gn:dem":184,
    "gn:feature_class":"P",
    "gn:feature_code":"PPL",
    "gn:name":"Lomachino",
    "gn:population":0,
    "gn:timezone":"Europe/Minsk",
    "iso:country":"BY",
    "name:rus_x_preferred":[
        "\u041b\u043e\u043c\u0430\u0447\u0438\u043d\u043e"
    ],
    "wof:name":"Lomachino",
    "wof:placetype":"locality"
},
  "geometry": {"coordinates":[30.2413,54.5036],"type":"Point"}
}