{
  "type": "Feature",
  "properties": {
    "gn:admin1_code":"6.0",
    "gn:asciiname":"Pererozhki",
    "gn:country_code":"BY",
    "gn:dem":158,
    "gn:feature_class":"P",
    "gn:feature_code":"PPL",
    "gn:name":"Pererozhki",
    "gn:population":0,
    "gn:timezone":"Europe/Minsk",
    "iso:country":"BY",
    "name:rus_x_preferred":[
        "\u041f\u0435\u0440\u0435\u0440\u043e\u0436\u043a\u0438"
    ],
    "wof:name":"Pererozhki",
    "wof:placetype":"locality"
},
  "geometry": {"coordinates":[28.484,53.3434],"type":"Point"}
}