{
  "type": "Feature",
  "properties": {
    "gn:admin1_code":"5.0",
    "gn:asciiname":"Zador'ye",
    "gn:country_code":"BY",
    "gn:dem":194,
    "gn:feature_class":"P",
    "gn:feature_code":"PPL",
    "gn:name":"Zador\u2019ye",
    "gn:population":0,
    "gn:timezone":"Europe/Minsk",
    "iso:country":"BY",
    "name:bel_x_preferred":[
        "\u0417\u0430\u0434\u043e\u0440\u044c\u0435"
    ],
    "name:und_x_variant":[
        "Zadorje",
        "Zador\u2019ya",
        "Zador\u2019ye"
    ],
    "wof:name":"Zador'ye",
    "wof:placetype":"locality"
},
  "geometry": {"coordinates":[27.7669,54.592],"type":"Point"}
}