{
  "type": "Feature",
  "properties": {
    "gn:admin1_code":"3.0",
    "gn:asciiname":"Kremeshovo",
    "gn:country_code":"BY",
    "gn:dem":195,
    "gn:feature_class":"P",
    "gn:feature_code":"PPL",
    "gn:name":"Kremeshovo",
    "gn:population":0,
    "gn:timezone":"Europe/Minsk",
    "iso:country":"BY",
    "name:rus_x_preferred":[
        "\u041a\u0440\u0435\u043c\u0435\u0448\u043e\u0432\u043e"
    ],
    "wof:name":"Kremeshovo",
    "wof:placetype":"locality"
},
  "geometry": {"coordinates":[25.9631,54.3935],"type":"Point"}
}