{
  "type": "Feature",
  "properties": {
    "gn:admin1_code":"7.0",
    "gn:asciiname":"Zakur'ye",
    "gn:country_code":"BY",
    "gn:dem":146,
    "gn:feature_class":"P",
    "gn:feature_code":"PPL",
    "gn:name":"Zakur\u2019ye",
    "gn:population":0,
    "gn:timezone":"Europe/Minsk",
    "iso:country":"BY",
    "name:rus_x_preferred":[
        "\u0417\u0430\u043a\u0443\u0440\u044c\u0435"
    ],
    "name:und_x_variant":[
        "Zakur\u2019ye"
    ],
    "wof:name":"Zakur'ye",
    "wof:placetype":"locality"
},
  "geometry": {"coordinates":[29.1548,54.7773],"type":"Point"}
}