{
  "type": "Feature",
  "properties": {
    "gn:country":"BY",
    "gn:fcode":"PPL",
    "gn:pop":3800,
    "iso:country":"BY",
    "name:eng_x_preferred":[
        "Konstantinovo"
    ],
    "name:rus_x_preferred":[
        "\u041a\u043e\u043d\u0441\u0442\u0430\u043d\u0442\u0438\u043d\u043e\u0432\u043e"
    ],
    "qs:name":"Konstantinovo",
    "qs:photos_9r":0,
    "qs:photos_sr":0,
    "qs:pop_sr":"4",
    "wd:wordcount":48,
    "wof:name":"Konstantinovo",
    "wof:placetype":"locality",
    "wof:population":3800
},
  "geometry": {"coordinates":[29.2684,54.6593],"type":"Point"}
}