{
  "type": "Feature",
  "properties": {
    "gn:country":"BY",
    "gn:fcode":"PPL",
    "gn:population":3800,
    "iso:country":"BY",
    "name:bel_x_preferred":[
        "\u041a\u0430\u043d\u0441\u0442\u0430\u043d\u0446\u0456\u043d\u0430\u0432\u0430"
    ],
    "name:bul_x_preferred":[
        "\u041a\u043e\u043d\u0441\u0442\u0430\u043d\u0442\u0438\u043d\u043e\u0432\u043e"
    ],
    "name:ceb_x_preferred":[
        "Konstantinovo"
    ],
    "name:eng_x_preferred":[
        "Konstantinovo"
    ],
    "name:est_x_preferred":[
        "Konstantinovo"
    ],
    "name:fra_x_preferred":[
        "Konstantinovo"
    ],
    "name:ron_x_preferred":[
        "Konstantinovo"
    ],
    "name:rus_x_preferred":[
        "\u041a\u043e\u043d\u0441\u0442\u0430\u043d\u0442\u0438\u043d\u043e\u0432\u043e"
    ],
    "name:swe_x_preferred":[
        "Konstantinovo"
    ],
    "name:ukr_x_preferred":[
        "\u041a\u043e\u043d\u0441\u0442\u0430\u043d\u0442\u0438\u043d\u043e\u0432\u043e"
    ],
    "qs:name":"Konstantinovo",
    "qs:photos_9r":0,
    "qs:photos_sr":0,
    "qs:pop_sr":"4",
    "wd:wordcount":48,
    "wof:name":"Konstantinovo",
    "wof:placetype":"locality",
    "wof:population":3800
},
  "geometry": {"coordinates":[29.2684,54.6593],"type":"Point"}
}