{
  "type": "Feature",
  "properties": {
    "gn:admin1_code":"5.0",
    "gn:asciiname":"Zabrodskiye",
    "gn:country_code":"BY",
    "gn:dem":156,
    "gn:feature_class":"P",
    "gn:feature_code":"PPL",
    "gn:name":"Zabrodskiye",
    "gn:population":0,
    "gn:timezone":"Europe/Minsk",
    "iso:country":"BY",
    "name:rus_x_preferred":[
        "\u0417\u0430\u0431\u0440\u043e\u0434\u0441\u043a\u0438\u0435"
    ],
    "wof:name":"Zabrodskiye",
    "wof:placetype":"locality"
},
  "geometry": {"coordinates":[27.4977,52.7947],"type":"Point"}
}