{
  "type": "Feature",
  "properties": {
    "gn:admin1_code":"5.0",
    "gn:asciiname":"Mkhereno Vtoroye",
    "gn:country_code":"BY",
    "gn:dem":183,
    "gn:feature_class":"P",
    "gn:feature_code":"PPL",
    "gn:name":"Mkhereno Vtoroye",
    "gn:population":0,
    "gn:timezone":"Europe/Minsk",
    "iso:country":"BY",
    "name:rus_x_preferred":[
        "\u041c\u0445\u0435\u0440\u0435\u043d\u043e \u0412\u0442\u043e\u0440\u043e\u0435"
    ],
    "name:und_x_variant":[
        "Mkherino",
        "Mkherino Vtoroye"
    ],
    "wof:name":"Mkhereno Vtoroye",
    "wof:placetype":"locality"
},
  "geometry": {"coordinates":[28.8815,54.5243],"type":"Point"}
}