{
  "type": "Feature",
  "properties": {
    "gn:admin1_code":"5.0",
    "gn:asciiname":"Osovo",
    "gn:country_code":"BY",
    "gn:dem":209,
    "gn:feature_class":"P",
    "gn:feature_code":"PPL",
    "gn:name":"Osovo",
    "gn:population":0,
    "gn:timezone":"Europe/Minsk",
    "iso:country":"BY",
    "name:rus_x_preferred":[
        "\u041e\u0441\u043e\u0432\u043e"
    ],
    "wof:name":"Osovo",
    "wof:placetype":"locality"
},
  "geometry": {"coordinates":[26.8464,53.7393],"type":"Point"}
}