{
  "type": "Feature",
  "properties": {
    "gn:admin1_code":"5.0",
    "gn:asciiname":"Stayetskiye",
    "gn:country_code":"BY",
    "gn:dem":186,
    "gn:feature_class":"P",
    "gn:feature_code":"PPL",
    "gn:name":"Stayetskiye",
    "gn:population":0,
    "gn:timezone":"Europe/Minsk",
    "iso:country":"BY",
    "name:rus_x_preferred":[
        "\u0421\u0442\u0430\u0435\u0446\u043a\u0438\u0435"
    ],
    "name:und_x_variant":[
        "Stoyetskiye"
    ],
    "wof:name":"Stayetskiye",
    "wof:placetype":"locality"
},
  "geometry": {"coordinates":[28.1254,54.4655],"type":"Point"}
}