{
  "type": "Feature",
  "properties": {
    "gn:admin1_code":"6.0",
    "gn:asciiname":"Sbornyy",
    "gn:country_code":"BY",
    "gn:dem":166,
    "gn:feature_class":"P",
    "gn:feature_code":"PPL",
    "gn:name":"Sbornyy",
    "gn:population":0,
    "gn:timezone":"Europe/Minsk",
    "iso:country":"BY",
    "name:und_x_variant":[
        "Sborny",
        "Sbornyy"
    ],
    "wof:name":"Sbornyy",
    "wof:placetype":"locality"
},
  "geometry": {"coordinates":[32.49778,53.51056],"type":"Point"}
}