{
  "type": "Feature",
  "properties": {
    "gn:admin1_code":"3.0",
    "gn:asciiname":"Verki",
    "gn:country_code":"BY",
    "gn:dem":183,
    "gn:feature_class":"P",
    "gn:feature_code":"PPL",
    "gn:name":"Verki",
    "gn:population":0,
    "gn:timezone":"Europe/Minsk",
    "iso:country":"BY",
    "name:rus_x_preferred":[
        "\u0412\u0435\u0440\u043a\u0438"
    ],
    "wof:name":"Verki",
    "wof:placetype":"locality"
},
  "geometry": {"coordinates":[25.4605,54.0679],"type":"Point"}
}