{
  "type": "Feature",
  "properties": {
    "gn:admin1_code":"3.0",
    "gn:asciiname":"Malaya Chapun'",
    "gn:country_code":"BY",
    "gn:dem":131,
    "gn:feature_class":"P",
    "gn:feature_code":"PPL",
    "gn:name":"Malaya Chapun\u2019",
    "gn:population":0,
    "gn:timezone":"Europe/Minsk",
    "iso:country":"BY",
    "name:rus_x_preferred":[
        "\u041c\u0430\u043b\u0430\u044f \u0427\u0430\u043f\u0443\u043d\u044c"
    ],
    "name:und_x_variant":[
        "Malaya Chapun\u2019"
    ],
    "wof:name":"Malaya Chapun'",
    "wof:placetype":"locality"
},
  "geometry": {"coordinates":[26.1044,53.8265],"type":"Point"}
}