{
  "type": "Feature",
  "properties": {
    "gn:admin1_code":"7.0",
    "gn:asciiname":"Stralki",
    "gn:country_code":"BY",
    "gn:dem":135,
    "gn:feature_class":"P",
    "gn:feature_code":"PPL",
    "gn:name":"Stralki",
    "gn:population":0,
    "gn:timezone":"Europe/Minsk",
    "iso:country":"BY",
    "name:bel_x_preferred":[
        "\u0421\u0442\u0440\u0430\u043b\u043a\u0456"
    ],
    "name:und_x_variant":[
        "Strelki"
    ],
    "wof:name":"Stralki",
    "wof:placetype":"locality"
},
  "geometry": {"coordinates":[28.1976,55.9372],"type":"Point"}
}