{
  "type": "Feature",
  "properties": {
    "gn:admin1_code":"3.0",
    "gn:asciiname":"Vysotskiye",
    "gn:country_code":"BY",
    "gn:dem":157,
    "gn:feature_class":"P",
    "gn:feature_code":"PPL",
    "gn:name":"Vysotskiye",
    "gn:population":0,
    "gn:timezone":"Europe/Minsk",
    "iso:country":"BY",
    "name:rus_x_preferred":[
        "\u0412\u044b\u0441\u043e\u0446\u043a\u0438\u0435"
    ],
    "wof:name":"Vysotskiye",
    "wof:placetype":"locality"
},
  "geometry": {"coordinates":[25.7477,54.1462],"type":"Point"}
}