{
  "type": "Feature",
  "properties": {
    "gn:admin1_code":"5.0",
    "gn:asciiname":"Kodunovo",
    "gn:country_code":"BY",
    "gn:dem":180,
    "gn:feature_class":"P",
    "gn:feature_code":"PPL",
    "gn:name":"Kodunovo",
    "gn:population":0,
    "gn:timezone":"Europe/Minsk",
    "iso:country":"BY",
    "name:rus_x_preferred":[
        "\u041a\u043e\u0434\u0443\u043d\u043e\u0432\u043e"
    ],
    "wof:name":"Kodunovo",
    "wof:placetype":"locality"
},
  "geometry": {"coordinates":[27.8766,53.6742],"type":"Point"}
}