{
  "type": "Feature",
  "properties": {
    "gn:admin1_code":"7.0",
    "gn:asciiname":"Kalen'ki",
    "gn:country_code":"BY",
    "gn:dem":175,
    "gn:feature_class":"P",
    "gn:feature_code":"PPL",
    "gn:name":"Kalen\u2019ki",
    "gn:population":0,
    "gn:timezone":"Europe/Minsk",
    "iso:country":"BY",
    "name:rus_x_preferred":[
        "\u041a\u0430\u043b\u0435\u043d\u044c\u043a\u0438"
    ],
    "name:und_x_variant":[
        "Kolen\u2019ki",
        "Kalen\u2019ki"
    ],
    "wof:name":"Kalen'ki",
    "wof:placetype":"locality"
},
  "geometry": {"coordinates":[30.2382,54.8245],"type":"Point"}
}