{
  "type": "Feature",
  "properties": {
    "gn:admin1_code":"6.0",
    "gn:asciiname":"Svyatsilavichy",
    "gn:country_code":"BY",
    "gn:dem":176,
    "gn:feature_class":"P",
    "gn:feature_code":"PPL",
    "gn:name":"Svyatsilavichy",
    "gn:population":0,
    "gn:timezone":"Europe/Minsk",
    "iso:country":"BY",
    "name:bel_x_preferred":[
        "\u0421\u0432\u044f\u0446\u0456\u043b\u0430\u0432\u0456\u0447\u044b"
    ],
    "name:und_x_variant":[
        "Svetilovichi"
    ],
    "wof:name":"Svyatsilavichy",
    "wof:placetype":"locality"
},
  "geometry": {"coordinates":[29.8623,53.973],"type":"Point"}
}