{
  "type": "Feature",
  "properties": {
    "gn:admin1_code":"5.0",
    "gn:asciiname":"Semki",
    "gn:country_code":"BY",
    "gn:dem":202,
    "gn:feature_class":"P",
    "gn:feature_code":"PPL",
    "gn:name":"S\u00ebmki",
    "gn:population":0,
    "gn:timezone":"Europe/Minsk",
    "iso:country":"BY",
    "name:rus_x_preferred":[
        "\u0421\u0451\u043c\u043a\u0438"
    ],
    "name:und_x_variant":[
        "S\u00ebmki"
    ],
    "wof:name":"Semki",
    "wof:placetype":"locality"
},
  "geometry": {"coordinates":[26.4517,54.8854],"type":"Point"}
}