{
  "type": "Feature",
  "properties": {
    "gn:admin1_code":"1.0",
    "gn:asciiname":"Dvartsy",
    "gn:country_code":"BY",
    "gn:dem":149,
    "gn:feature_class":"P",
    "gn:feature_code":"PPL",
    "gn:name":"Dvartsy",
    "gn:population":0,
    "gn:timezone":"Europe/Minsk",
    "iso:country":"BY",
    "name:bel_x_preferred":[
        "\u0414\u0432\u0430\u0440\u0446\u044b"
    ],
    "name:und_x_variant":[
        "Dvortse",
        "Dvortsy",
        "Dvartsy"
    ],
    "wof:name":"Dvartsy",
    "wof:placetype":"locality"
},
  "geometry": {"coordinates":[23.97105,52.4514],"type":"Point"}
}