{
  "type": "Feature",
  "properties": {
    "gn:admin1_code":"7.0",
    "gn:asciiname":"Bliznitsa",
    "gn:country_code":"BY",
    "gn:dem":130,
    "gn:feature_class":"P",
    "gn:feature_code":"PPL",
    "gn:name":"Bliznitsa",
    "gn:population":0,
    "gn:timezone":"Europe/Minsk",
    "iso:country":"BY",
    "name:rus_x_preferred":[
        "\u0411\u043b\u0438\u0437\u043d\u0438\u0446\u0430"
    ],
    "name:und_x_variant":[
        "Bli\u017anica",
        "Bliznitsa"
    ],
    "wof:name":"Bliznitsa",
    "wof:placetype":"locality"
},
  "geometry": {"coordinates":[27.8348,55.3756],"type":"Point"}
}