{
  "type": "Feature",
  "properties": {
    "gn:admin1_code":"7.0",
    "gn:asciiname":"Manevshchina",
    "gn:country_code":"BY",
    "gn:dem":125,
    "gn:feature_class":"P",
    "gn:feature_code":"PPL",
    "gn:name":"Manevshchina",
    "gn:population":0,
    "gn:timezone":"Europe/Minsk",
    "iso:country":"BY",
    "name:rus_x_preferred":[
        "\u041c\u0430\u043d\u0435\u0432\u0449\u0438\u043d\u0430"
    ],
    "wof:name":"Manevshchina",
    "wof:placetype":"locality"
},
  "geometry": {"coordinates":[27.2289,55.1827],"type":"Point"}
}