{
  "type": "Feature",
  "properties": {
    "gn:admin1_code":"3.0",
    "gn:asciiname":"Voykuntsy",
    "gn:country_code":"BY",
    "gn:dem":143,
    "gn:feature_class":"P",
    "gn:feature_code":"PPL",
    "gn:name":"Voykuntsy",
    "gn:population":0,
    "gn:timezone":"Europe/Minsk",
    "iso:country":"BY",
    "name:rus_x_preferred":[
        "\u0412\u043e\u0439\u043a\u0443\u043d\u0446\u044b"
    ],
    "name:und_x_variant":[
        "Vaynuntsy",
        "Vaykuntsy",
        "Voykuntsy"
    ],
    "wof:name":"Voykuntsy",
    "wof:placetype":"locality"
},
  "geometry": {"coordinates":[25.0865,54.0933],"type":"Point"}
}