{
  "type": "Feature",
  "properties": {
    "gn:admin1_code":"3.0",
    "gn:asciiname":"Zapol'ye",
    "gn:country_code":"BY",
    "gn:dem":165,
    "gn:feature_class":"P",
    "gn:feature_code":"PPL",
    "gn:name":"Zapol\u2019ye",
    "gn:population":0,
    "gn:timezone":"Europe/Minsk",
    "iso:country":"BY",
    "name:bel_x_preferred":[
        "Zapol\u2019l\u2019ye"
    ],
    "name:bel_x_variant":[
        "\u0417\u0430\u043f\u043e\u043b\u044c\u043b\u0435"
    ],
    "name:rus_x_preferred":[
        "\u0417\u0430\u043f\u043e\u043b\u044c\u0435"
    ],
    "name:und_x_variant":[
        "Zapol\u2019ye"
    ],
    "wof:name":"Zapol'ye",
    "wof:placetype":"locality"
},
  "geometry": {"coordinates":[25.19481,53.88393000000001],"type":"Point"}
}