{
  "type": "Feature",
  "properties": {
    "gn:admin1_code":"6.0",
    "gn:asciiname":"Machulki",
    "gn:country_code":"BY",
    "gn:dem":151,
    "gn:feature_class":"P",
    "gn:feature_code":"PPL",
    "gn:name":"Machulki",
    "gn:population":0,
    "gn:timezone":"Europe/Minsk",
    "iso:country":"BY",
    "name:rus_x_preferred":[
        "\u041c\u0430\u0447\u0443\u043b\u043a\u0438"
    ],
    "name:und_x_variant":[
        "Mochulki"
    ],
    "wof:name":"Machulki",
    "wof:placetype":"locality"
},
  "geometry": {"coordinates":[29.0154,53.0146],"type":"Point"}
}