{
  "type": "Feature",
  "properties": {
    "gn:admin1_code":"5.0",
    "gn:asciiname":"Yanovshchina",
    "gn:country_code":"BY",
    "gn:dem":224,
    "gn:feature_class":"P",
    "gn:feature_code":"PPL",
    "gn:name":"Yanovshchina",
    "gn:population":0,
    "gn:timezone":"Europe/Minsk",
    "iso:country":"BY",
    "name:rus_x_preferred":[
        "\u042f\u043d\u043e\u0432\u0449\u0438\u043d\u0430"
    ],
    "name:und_x_variant":[
        "Yakovshchina"
    ],
    "wof:name":"Yanovshchina",
    "wof:placetype":"locality"
},
  "geometry": {"coordinates":[26.7906,53.8807],"type":"Point"}
}