{
  "type": "Feature",
  "properties": {
    "gn:admin1_code":"3.0",
    "gn:asciiname":"Shustiki",
    "gn:country_code":"BY",
    "gn:dem":161,
    "gn:feature_class":"P",
    "gn:feature_code":"PPL",
    "gn:name":"Shustiki",
    "gn:population":0,
    "gn:timezone":"Europe/Minsk",
    "iso:country":"BY",
    "name:rus_x_preferred":[
        "\u0428\u0443\u0441\u0442\u0438\u043a\u0438"
    ],
    "wof:name":"Shustiki",
    "wof:placetype":"locality"
},
  "geometry": {"coordinates":[24.2289,53.0881],"type":"Point"}
}