{
  "type": "Feature",
  "properties": {
    "gn:admin1_code":"7.0",
    "gn:asciiname":"Savinichi",
    "gn:country_code":"BY",
    "gn:dem":155,
    "gn:feature_class":"P",
    "gn:feature_code":"PPL",
    "gn:name":"Savinichi",
    "gn:population":0,
    "gn:timezone":"Europe/Minsk",
    "iso:country":"BY",
    "name:rus_x_preferred":[
        "\u0421\u0430\u0432\u0438\u043d\u0438\u0447\u0438"
    ],
    "wof:name":"Savinichi",
    "wof:placetype":"locality"
},
  "geometry": {"coordinates":[29.7366,54.8602],"type":"Point"}
}