{
  "type": "Feature",
  "properties": {
    "gn:admin1_code":"0.0",
    "gn:asciiname":"Shimanovka",
    "gn:country_code":"BY",
    "gn:dem":215,
    "gn:feature_class":"P",
    "gn:feature_code":"PPL",
    "gn:name":"Shimanovka",
    "gn:population":0,
    "gn:timezone":"Europe/Minsk",
    "iso:country":"BY",
    "name:und_x_variant":[
        "Shimanovk",
        "Shimanovka"
    ],
    "wof:name":"Shimanovka",
    "wof:placetype":"locality"
},
  "geometry": {"coordinates":[31.04568,54.35927],"type":"Point"}
}