{
  "type": "Feature",
  "properties": {
    "gn:admin1_code":"6.0",
    "gn:asciiname":"Yel'nya",
    "gn:country_code":"BY",
    "gn:dem":178,
    "gn:feature_class":"P",
    "gn:feature_code":"PPL",
    "gn:name":"Yel\u2019nya",
    "gn:population":0,
    "gn:timezone":"Europe/Minsk",
    "iso:country":"BY",
    "name:bel_x_preferred":[
        "\u0415\u043b\u044c\u043d\u044f"
    ],
    "name:und_x_variant":[
        "Yelna",
        "Yel\u2019nya"
    ],
    "wof:name":"Yel'nya",
    "wof:placetype":"locality"
},
  "geometry": {"coordinates":[32.3195,53.4394],"type":"Point"}
}