{
  "type": "Feature",
  "properties": {
    "gn:admin1_code":"3.0",
    "gn:asciiname":"Szulniki",
    "gn:country_code":"BY",
    "gn:dem":174,
    "gn:feature_class":"P",
    "gn:feature_code":"PPL",
    "gn:name":"Szulniki",
    "gn:population":0,
    "gn:timezone":"Europe/Minsk",
    "iso:country":"BY",
    "name:rus_x_preferred":[
        "\u0428\u0443\u043b\u044c\u043d\u0438\u043a\u0438"
    ],
    "name:und_x_variant":[
        "Shul\u2019niki"
    ],
    "wof:name":"Szulniki",
    "wof:placetype":"locality"
},
  "geometry": {"coordinates":[26.0894,54.7737],"type":"Point"}
}