{
  "type": "Feature",
  "properties": {
    "gn:admin1_code":"7.0",
    "gn:asciiname":"Dedki",
    "gn:country_code":"BY",
    "gn:dem":195,
    "gn:feature_class":"P",
    "gn:feature_code":"PPL",
    "gn:name":"Dedki",
    "gn:population":0,
    "gn:timezone":"Europe/Minsk",
    "iso:country":"BY",
    "name:rus_x_preferred":[
        "\u0414\u0435\u0434\u043a\u0438"
    ],
    "name:und_x_variant":[
        "Dzyadki",
        "Dziadki",
        "Detki",
        "Dedki"
    ],
    "wof:name":"Dedki",
    "wof:placetype":"locality"
},
  "geometry": {"coordinates":[27.5873,54.9494],"type":"Point"}
}