{
  "type": "Feature",
  "properties": {
    "gn:admin1_code":"5.0",
    "gn:asciiname":"Kapskiye",
    "gn:country_code":"BY",
    "gn:dem":172,
    "gn:feature_class":"P",
    "gn:feature_code":"PPL",
    "gn:name":"Kapskiye",
    "gn:population":0,
    "gn:timezone":"Europe/Minsk",
    "iso:country":"BY",
    "name:rus_x_preferred":[
        "\u041a\u0430\u043f\u0441\u043a\u0438\u0435"
    ],
    "wof:name":"Kapskiye",
    "wof:placetype":"locality"
},
  "geometry": {"coordinates":[28.1402,53.6143],"type":"Point"}
}