{
  "type": "Feature",
  "properties": {
    "gn:admin1_code":"7.0",
    "gn:asciiname":"Novaya Tukhinya",
    "gn:country_code":"BY",
    "gn:dem":170,
    "gn:feature_class":"P",
    "gn:feature_code":"PPL",
    "gn:name":"Novaya Tukhinya",
    "gn:population":0,
    "gn:timezone":"Europe/Minsk",
    "iso:country":"BY",
    "name:rus_x_preferred":[
        "\u041d\u043e\u0432\u0430\u044f \u0422\u0443\u0445\u0438\u043d\u044c"
    ],
    "name:und_x_variant":[
        "Novaya Tukhin\u2019",
        "Novaya Tukhinya"
    ],
    "wof:name":"Novaya Tukhinya",
    "wof:placetype":"locality"
},
  "geometry": {"coordinates":[30.841,54.6534],"type":"Point"}
}