{
  "type": "Feature",
  "properties": {
    "gn:admin1_code":"6.0",
    "gn:asciiname":"Trilesino",
    "gn:country_code":"BY",
    "gn:dem":211,
    "gn:feature_class":"P",
    "gn:feature_code":"PPL",
    "gn:name":"Trilesino",
    "gn:population":0,
    "gn:timezone":"Europe/Minsk",
    "iso:country":"BY",
    "name:rus_x_preferred":[
        "\u0422\u0440\u0438\u043b\u0435\u0441\u0438\u043d\u043e"
    ],
    "wof:name":"Trilesino",
    "wof:placetype":"locality"
},
  "geometry": {"coordinates":[30.0521,54.2286],"type":"Point"}
}