{
  "type": "Feature",
  "properties": {
    "gn:admin1_code":"3.0",
    "gn:asciiname":"Primen'",
    "gn:country_code":"BY",
    "gn:dem":228,
    "gn:feature_class":"P",
    "gn:feature_code":"PPL",
    "gn:name":"Primen\u2019",
    "gn:population":0,
    "gn:timezone":"Europe/Minsk",
    "iso:country":"BY",
    "name:bel_x_preferred":[
        "Prymyen\u2019"
    ],
    "name:bel_x_variant":[
        "\u041f\u0440\u044b\u043c\u0435\u043d\u044c"
    ],
    "name:rus_x_preferred":[
        "\u041f\u0440\u0438\u043c\u0435\u043d\u044c"
    ],
    "name:und_x_variant":[
        "Primen\u2019"
    ],
    "wof:name":"Primen'",
    "wof:placetype":"locality"
},
  "geometry": {"coordinates":[25.9037,53.6297],"type":"Point"}
}