{
  "type": "Feature",
  "properties": {
    "gn:admin1_code":"7.0",
    "gn:asciiname":"Podvarinka",
    "gn:country_code":"BY",
    "gn:dem":145,
    "gn:feature_class":"P",
    "gn:feature_code":"PPL",
    "gn:name":"Podvarinka",
    "gn:population":0,
    "gn:timezone":"Europe/Minsk",
    "iso:country":"BY",
    "name:rus_x_preferred":[
        "\u041f\u043e\u0434\u0432\u0430\u0440\u0438\u043d\u043a\u0430"
    ],
    "name:und_x_variant":[
        "Podvarynka"
    ],
    "wof:name":"Podvarinka",
    "wof:placetype":"locality"
},
  "geometry": {"coordinates":[26.6184,55.4234],"type":"Point"}
}