{
  "type": "Feature",
  "properties": {
    "gn:admin1_code":"3.0",
    "gn:asciiname":"Linki",
    "gn:country_code":"BY",
    "gn:dem":107,
    "gn:feature_class":"P",
    "gn:feature_code":"PPL",
    "gn:name":"Linki",
    "gn:population":0,
    "gn:timezone":"Europe/Minsk",
    "iso:country":"BY",
    "name:rus_x_preferred":[
        "\u041b\u0438\u043d\u043a\u0438"
    ],
    "wof:name":"Linki",
    "wof:placetype":"locality"
},
  "geometry": {"coordinates":[23.8222,53.803],"type":"Point"}
}