{
  "type": "Feature",
  "properties": {
    "gn:admin1_code":"6.0",
    "gn:asciiname":"Martynovka",
    "gn:country_code":"BY",
    "gn:dem":150,
    "gn:feature_class":"P",
    "gn:feature_code":"PPL",
    "gn:name":"Martynovka",
    "gn:population":0,
    "gn:timezone":"Europe/Minsk",
    "iso:country":"BY",
    "name:rus_x_preferred":[
        "\u041c\u0430\u0440\u0442\u044b\u043d\u043e\u0432\u043a\u0430"
    ],
    "wof:name":"Martynovka",
    "wof:placetype":"locality"
},
  "geometry": {"coordinates":[29.6008,53.1613],"type":"Point"}
}