{
  "type": "Feature",
  "properties": {
    "gn:admin1_code":"6.0",
    "gn:asciiname":"Skuraty",
    "gn:country_code":"BY",
    "gn:dem":191,
    "gn:feature_class":"P",
    "gn:feature_code":"PPL",
    "gn:name":"Skuraty",
    "gn:population":0,
    "gn:timezone":"Europe/Minsk",
    "iso:country":"BY",
    "name:rus_x_preferred":[
        "\u0421\u043a\u0443\u0440\u0430\u0442\u044b"
    ],
    "wof:name":"Skuraty",
    "wof:placetype":"locality"
},
  "geometry": {"coordinates":[29.7025,54.2814],"type":"Point"}
}