{
  "type": "Feature",
  "properties": {
    "gn:admin1_code":"5.0",
    "gn:asciiname":"Tabory",
    "gn:country_code":"BY",
    "gn:dem":275,
    "gn:feature_class":"P",
    "gn:feature_code":"PPL",
    "gn:name":"Tabory",
    "gn:population":0,
    "gn:timezone":"Europe/Minsk",
    "iso:country":"BY",
    "name:ceb_x_preferred":[
        "Tabory"
    ],
    "name:deu_x_preferred":[
        "Tabory"
    ],
    "name:rus_x_preferred":[
        "\u0422\u0430\u0431\u043e\u0440\u044b"
    ],
    "wof:name":"Tabory",
    "wof:placetype":"locality"
},
  "geometry": {"coordinates":[27.3333,53.8933],"type":"Point"}
}