{
  "type": "Feature",
  "properties": {
    "gn:admin1_code":"7.0",
    "gn:asciiname":"Lyadniki",
    "gn:country_code":"BY",
    "gn:dem":126,
    "gn:feature_class":"P",
    "gn:feature_code":"PPL",
    "gn:name":"Lyadniki",
    "gn:population":0,
    "gn:timezone":"Europe/Minsk",
    "iso:country":"BY",
    "name:rus_x_preferred":[
        "\u041b\u044f\u0434\u043d\u0438\u043a\u0438"
    ],
    "wof:name":"Lyadniki",
    "wof:placetype":"locality"
},
  "geometry": {"coordinates":[27.3925,55.3302],"type":"Point"}
}