{
  "type": "Feature",
  "properties": {
    "gn:admin1_code":"1.0",
    "gn:asciiname":"Turki",
    "gn:country_code":"BY",
    "gn:dem":180,
    "gn:feature_class":"P",
    "gn:feature_code":"PPL",
    "gn:name":"Turki",
    "gn:population":0,
    "gn:timezone":"Europe/Minsk",
    "iso:country":"BY",
    "name:rus_x_preferred":[
        "\u0422\u0443\u0440\u043a\u0438"
    ],
    "wof:name":"Turki",
    "wof:placetype":"locality"
},
  "geometry": {"coordinates":[26.2126,53.0593],"type":"Point"}
}