{
  "type": "Feature",
  "properties": {
    "gn:admin1_code":"6.0",
    "gn:asciiname":"Chervonoarmeyets",
    "gn:country_code":"BY",
    "gn:dem":170,
    "gn:feature_class":"P",
    "gn:feature_code":"PPL",
    "gn:name":"Chervonoarmeyets",
    "gn:population":0,
    "gn:timezone":"Europe/Minsk",
    "iso:country":"BY",
    "wof:name":"Chervonoarmeyets",
    "wof:placetype":"locality"
},
  "geometry": {"coordinates":[30.52861,53.76167],"type":"Point"}
}