{
  "type": "Feature",
  "properties": {
    "gn:admin1_code":"1.0",
    "gn:asciiname":"Nikol'skoye",
    "gn:country_code":"BY",
    "gn:dem":158,
    "gn:feature_class":"P",
    "gn:feature_code":"PPL",
    "gn:name":"Nikol\u2019skoye",
    "gn:population":0,
    "gn:timezone":"Europe/Minsk",
    "iso:country":"BY",
    "name:rus_x_preferred":[
        "Nikol\u2019skoye"
    ],
    "name:rus_x_variant":[
        "\u041d\u0438\u043a\u043e\u043b\u044c\u0441\u043a\u043e\u0435"
    ],
    "name:und_x_variant":[
        "Nikol\u2019skaya",
        "Nikol\u2019skoye"
    ],
    "wof:name":"Nikol'skoye",
    "wof:placetype":"locality"
},
  "geometry": {"coordinates":[23.9705,51.7127],"type":"Point"}
}