{
  "type": "Feature",
  "properties": {
    "gn:admin1_code":"5.0",
    "gn:asciiname":"Mozoli",
    "gn:country_code":"BY",
    "gn:dem":193,
    "gn:feature_class":"P",
    "gn:feature_code":"PPL",
    "gn:name":"Mozoli",
    "gn:population":0,
    "gn:timezone":"Europe/Minsk",
    "iso:country":"BY",
    "name:rus_x_preferred":[
        "\u041c\u043e\u0437\u043e\u043b\u0438"
    ],
    "name:und_x_variant":[
        "Mozole",
        "Mozoly",
        "Mozoli"
    ],
    "wof:name":"Mozoli",
    "wof:placetype":"locality"
},
  "geometry": {"coordinates":[27.145,54.2528],"type":"Point"}
}