{
  "type": "Feature",
  "properties": {
    "gn:admin1_code":"0.0",
    "gn:asciiname":"Kalinino",
    "gn:country_code":"BY",
    "gn:dem":130,
    "gn:feature_class":"P",
    "gn:feature_code":"PPL",
    "gn:name":"Kalinino",
    "gn:population":0,
    "gn:timezone":"Europe/Minsk",
    "iso:country":"BY",
    "name:ceb_x_preferred":[
        "Kalinino"
    ],
    "name:deu_x_preferred":[
        "Kalinino"
    ],
    "name:kat_x_preferred":[
        "\u10d9\u10d0\u10da\u10d8\u10dc\u10d8\u10dc\u10dd"
    ],
    "name:swe_x_preferred":[
        "Kalinino"
    ],
    "name:und_x_variant":[
        "Dubrovitsa",
        "Kalinino"
    ],
    "wof:name":"Kalinino",
    "wof:placetype":"locality"
},
  "geometry": {"coordinates":[30.106,52.04765],"type":"Point"}
}