{
  "type": "Feature",
  "properties": {
    "gn:admin1_code":"7.0",
    "gn:asciiname":"Rudobist'",
    "gn:country_code":"BY",
    "gn:dem":137,
    "gn:feature_class":"P",
    "gn:feature_code":"PPL",
    "gn:name":"Rudobist\u2019",
    "gn:population":0,
    "gn:timezone":"Europe/Minsk",
    "iso:country":"BY",
    "name:rus_x_preferred":[
        "\u0420\u0443\u0434\u043e\u0431\u0438\u0441\u0442\u044c"
    ],
    "name:und_x_variant":[
        "Rudobist\u2019"
    ],
    "wof:name":"Rudobist'",
    "wof:placetype":"locality"
},
  "geometry": {"coordinates":[27.2528,55.46],"type":"Point"}
}