{
  "type": "Feature",
  "properties": {
    "gn:admin1_code":"3.0",
    "gn:asciiname":"Krivonosovtsy",
    "gn:country_code":"BY",
    "gn:dem":134,
    "gn:feature_class":"P",
    "gn:feature_code":"PPL",
    "gn:name":"Krivonosovtsy",
    "gn:population":0,
    "gn:timezone":"Europe/Minsk",
    "iso:country":"BY",
    "name:rus_x_preferred":[
        "\u041a\u0440\u0438\u0432\u043e\u043d\u043e\u0441\u043e\u0432\u0446\u044b"
    ],
    "wof:name":"Krivonosovtsy",
    "wof:placetype":"locality"
},
  "geometry": {"coordinates":[24.324,53.31399999999999],"type":"Point"}
}