{
  "type": "Feature",
  "properties": {
    "gn:admin1_code":"1.0",
    "gn:asciiname":"Vostraw",
    "gn:country_code":"BY",
    "gn:dem":164,
    "gn:feature_class":"P",
    "gn:feature_code":"PPL",
    "gn:name":"Vostraw",
    "gn:population":0,
    "gn:timezone":"Europe/Minsk",
    "iso:country":"BY",
    "name:bel_x_preferred":[
        "\u0412\u043e\u0441\u0442\u0440\u0430\u045e"
    ],
    "name:und_x_variant":[
        "Ostrow",
        "Ostrov",
        "Vostraw"
    ],
    "wof:name":"Vostraw",
    "wof:placetype":"locality"
},
  "geometry": {"coordinates":[26.6079,52.8552],"type":"Point"}
}