{
  "type": "Feature",
  "properties": {
    "gn:admin1_code":"5.0",
    "gn:asciiname":"Dobrovichi",
    "gn:country_code":"BY",
    "gn:dem":172,
    "gn:feature_class":"P",
    "gn:feature_code":"PPL",
    "gn:name":"Dobrovichi",
    "gn:population":0,
    "gn:timezone":"Europe/Minsk",
    "iso:country":"BY",
    "name:rus_x_preferred":[
        "\u0414\u043e\u0431\u0440\u043e\u0432\u0438\u0447\u0438"
    ],
    "wof:name":"Dobrovichi",
    "wof:placetype":"locality"
},
  "geometry": {"coordinates":[27.3232,54.6336],"type":"Point"}
}