{
  "type": "Feature",
  "properties": {
    "gn:admin1_code":"7.0",
    "gn:asciiname":"Punishche",
    "gn:country_code":"BY",
    "gn:dem":166,
    "gn:feature_class":"P",
    "gn:feature_code":"PPL",
    "gn:name":"Punishche",
    "gn:population":0,
    "gn:timezone":"Europe/Minsk",
    "iso:country":"BY",
    "name:rus_x_preferred":[
        "\u041f\u0443\u043d\u0438\u0449\u0435"
    ],
    "wof:name":"Punishche",
    "wof:placetype":"locality"
},
  "geometry": {"coordinates":[28.5539,54.9692],"type":"Point"}
}