{
  "type": "Feature",
  "properties": {
    "gn:admin1_code":"3.0",
    "gn:asciiname":"Bol'shiye Lepi",
    "gn:country_code":"BY",
    "gn:dem":170,
    "gn:feature_class":"P",
    "gn:feature_code":"PPL",
    "gn:name":"Bol\u2019shiye Lepi",
    "gn:population":0,
    "gn:timezone":"Europe/Minsk",
    "iso:country":"BY",
    "name:rus_x_preferred":[
        "\u0411\u043e\u043b\u044c\u0448\u0438\u0435 \u041b\u0435\u043f\u0438"
    ],
    "name:und_x_variant":[
        "Bol\u2019shiye Lepi"
    ],
    "wof:name":"Bol'shiye Lepi",
    "wof:placetype":"locality"
},
  "geometry": {"coordinates":[25.4878,54.2523],"type":"Point"}
}