{
  "type": "Feature",
  "properties": {
    "gn:admin1_code":"3.0",
    "gn:asciiname":"Nozdraki",
    "gn:country_code":"BY",
    "gn:dem":164,
    "gn:feature_class":"P",
    "gn:feature_code":"PPL",
    "gn:name":"Nozdraki",
    "gn:population":0,
    "gn:timezone":"Europe/Minsk",
    "iso:country":"BY",
    "name:rus_x_preferred":[
        "\u041d\u043e\u0437\u0434\u0440\u0430\u043a\u0438"
    ],
    "wof:name":"Nozdraki",
    "wof:placetype":"locality"
},
  "geometry": {"coordinates":[25.877,54.1605],"type":"Point"}
}