{
  "type": "Feature",
  "properties": {
    "gn:admin1_code":"1.0",
    "gn:asciiname":"Vul'ka",
    "gn:country_code":"BY",
    "gn:dem":151,
    "gn:feature_class":"P",
    "gn:feature_code":"PPL",
    "gn:name":"Vul\u2019ka",
    "gn:population":0,
    "gn:timezone":"Europe/Minsk",
    "iso:country":"BY",
    "name:rus_x_preferred":[
        "Vul\u2019ka"
    ],
    "name:rus_x_variant":[
        "\u0412\u0443\u043b\u044c\u043a\u0430"
    ],
    "name:und_x_variant":[
        "Vul\u2019ka"
    ],
    "wof:name":"Vul'ka",
    "wof:placetype":"locality"
},
  "geometry": {"coordinates":[25.8766,52.5447],"type":"Point"}
}