{
  "type": "Feature",
  "properties": {
    "gn:admin1_code":"2.0",
    "gn:asciiname":"Kosel'skiy Prudok",
    "gn:country_code":"BY",
    "gn:dem":132,
    "gn:feature_class":"P",
    "gn:feature_code":"PPL",
    "gn:name":"Kosel\u2019skiy Prudok",
    "gn:population":0,
    "gn:timezone":"Europe/Minsk",
    "iso:country":"BY",
    "name:rus_x_preferred":[
        "\u041a\u043e\u0441\u0435\u043b\u044c\u0441\u043a\u0438\u0439 \u041f\u0440\u0443\u0434\u043e\u043a"
    ],
    "name:und_x_variant":[
        "Kosel\u2019skiy Prudok"
    ],
    "wof:name":"Kosel'skiy Prudok",
    "wof:placetype":"locality"
},
  "geometry": {"coordinates":[30.8178,53.279],"type":"Point"}
}