{
  "type": "Feature",
  "properties": {
    "gn:admin1_code":"5.0",
    "gn:asciiname":"Sudniki",
    "gn:country_code":"BY",
    "gn:dem":154,
    "gn:feature_class":"P",
    "gn:feature_code":"PPL",
    "gn:name":"Sudniki",
    "gn:population":0,
    "gn:timezone":"Europe/Minsk",
    "iso:country":"BY",
    "name:rus_x_preferred":[
        "\u0421\u0443\u0434\u043d\u0438\u043a\u0438"
    ],
    "wof:name":"Sudniki",
    "wof:placetype":"locality"
},
  "geometry": {"coordinates":[26.6263,53.4969],"type":"Point"}
}