{
  "type": "Feature",
  "properties": {
    "gn:admin1_code":"7.0",
    "gn:asciiname":"Zarov'ye",
    "gn:country_code":"BY",
    "gn:dem":179,
    "gn:feature_class":"P",
    "gn:feature_code":"PPL",
    "gn:name":"Zarov\u2019ye",
    "gn:population":0,
    "gn:timezone":"Europe/Minsk",
    "iso:country":"BY",
    "name:rus_x_preferred":[
        "\u0417\u0430\u0440\u043e\u0432\u044c\u0435"
    ],
    "name:und_x_variant":[
        "Zarov\u2019ye"
    ],
    "wof:name":"Zarov'ye",
    "wof:placetype":"locality"
},
  "geometry": {"coordinates":[28.4398,55.1471],"type":"Point"}
}