{
  "type": "Feature",
  "properties": {
    "gn:admin1_code":"6.0",
    "gn:asciiname":"Dobasna",
    "gn:country_code":"BY",
    "gn:dem":148,
    "gn:feature_class":"P",
    "gn:feature_code":"PPL",
    "gn:name":"Dobasna",
    "gn:population":0,
    "gn:timezone":"Europe/Minsk",
    "iso:country":"BY",
    "name:bel_x_preferred":[
        "\u0414\u043e\u0431\u0430\u0441\u043d\u0430"
    ],
    "name:eng_x_preferred":[
        "Dobosna"
    ],
    "name:rus_x_preferred":[
        "\u0414\u043e\u0431\u043e\u0441\u043d\u0430"
    ],
    "name:und_x_variant":[
        "Dobysno",
        "Dobysna",
        "Dobasna",
        "Staraya Dobosna"
    ],
    "wof:name":"Dobasna",
    "wof:placetype":"locality"
},
  "geometry": {"coordinates":[29.678,53.2014],"type":"Point"}
}