{
  "type": "Feature",
  "properties": {
    "gn:admin1_code":"7.0",
    "gn:asciiname":"Lasitsa",
    "gn:country_code":"BY",
    "gn:dem":167,
    "gn:feature_class":"P",
    "gn:feature_code":"PPL",
    "gn:name":"Lasitsa",
    "gn:population":0,
    "gn:timezone":"Europe/Minsk",
    "iso:country":"BY",
    "name:rus_x_preferred":[
        "\u041b\u0430\u0441\u0438\u0446\u0430"
    ],
    "wof:name":"Lasitsa",
    "wof:placetype":"locality"
},
  "geometry": {"coordinates":[27.3965,55.0915],"type":"Point"}
}