{
  "type": "Feature",
  "properties": {
    "gn:admin1_code":"3.0",
    "gn:asciiname":"Zhilyantsy",
    "gn:country_code":"BY",
    "gn:dem":142,
    "gn:feature_class":"P",
    "gn:feature_code":"PPL",
    "gn:name":"Zhilyantsy",
    "gn:population":0,
    "gn:timezone":"Europe/Minsk",
    "iso:country":"BY",
    "name:rus_x_preferred":[
        "\u0416\u0438\u043b\u044f\u043d\u0446\u044b"
    ],
    "wof:name":"Zhilyantsy",
    "wof:placetype":"locality"
},
  "geometry": {"coordinates":[25.1891,54.0591],"type":"Point"}
}