{
  "type": "Feature",
  "properties": {
    "gn:admin1_code":"5.0",
    "gn:asciiname":"Ostrovy",
    "gn:country_code":"BY",
    "gn:dem":173,
    "gn:feature_class":"P",
    "gn:feature_code":"PPL",
    "gn:name":"Ostrovy",
    "gn:population":0,
    "gn:timezone":"Europe/Minsk",
    "iso:country":"BY",
    "name:rus_x_preferred":[
        "\u041e\u0441\u0442\u0440\u043e\u0432\u044b"
    ],
    "name:und_x_variant":[
        "Astrovy"
    ],
    "wof:name":"Ostrovy",
    "wof:placetype":"locality"
},
  "geometry": {"coordinates":[27.856,53.6137],"type":"Point"}
}