{
  "type": "Feature",
  "properties": {
    "gn:admin1_code":"5.0",
    "gn:asciiname":"Ostrov",
    "gn:country_code":"BY",
    "gn:dem":172,
    "gn:feature_class":"P",
    "gn:feature_code":"PPL",
    "gn:name":"Ostrov",
    "gn:population":0,
    "gn:timezone":"Europe/Minsk",
    "iso:country":"BY",
    "name:rus_x_preferred":[
        "\u041e\u0441\u0442\u0440\u043e\u0432"
    ],
    "wof:name":"Ostrov",
    "wof:placetype":"locality"
},
  "geometry": {"coordinates":[27.9095,53.6038],"type":"Point"}
}