{
  "type": "Feature",
  "properties": {
    "gn:admin1_code":"3.0",
    "gn:asciiname":"Puzynovtsy",
    "gn:country_code":"BY",
    "gn:dem":124,
    "gn:feature_class":"P",
    "gn:feature_code":"PPL",
    "gn:name":"Puzynovtsy",
    "gn:population":0,
    "gn:timezone":"Europe/Minsk",
    "iso:country":"BY",
    "name:bel_x_preferred":[
        "Puzynawtsy"
    ],
    "name:bel_x_variant":[
        "\u041f\u0443\u0437\u044b\u043d\u0430\u045e\u0446\u044b"
    ],
    "name:rus_x_preferred":[
        "\u041f\u0443\u0437\u044b\u043d\u043e\u0432\u0446\u044b"
    ],
    "wof:name":"Puzynovtsy",
    "wof:placetype":"locality"
},
  "geometry": {"coordinates":[24.4521,53.5482],"type":"Point"}
}