{
  "type": "Feature",
  "properties": {
    "gn:admin1_code":"3.0",
    "gn:asciiname":"Shchani",
    "gn:country_code":"BY",
    "gn:dem":163,
    "gn:feature_class":"P",
    "gn:feature_code":"PPL",
    "gn:name":"Shchani",
    "gn:population":0,
    "gn:timezone":"Europe/Minsk",
    "iso:country":"BY",
    "name:rus_x_preferred":[
        "\u0429\u0430\u043d\u0438"
    ],
    "wof:name":"Shchani",
    "wof:placetype":"locality"
},
  "geometry": {"coordinates":[26.6145,54.5875],"type":"Point"}
}