{
  "type": "Feature",
  "properties": {
    "gn:admin1_code":"6.0",
    "gn:asciiname":"Staroye Selo",
    "gn:country_code":"BY",
    "gn:dem":177,
    "gn:feature_class":"P",
    "gn:feature_code":"PPL",
    "gn:name":"Staroye Selo",
    "gn:population":0,
    "gn:timezone":"Europe/Minsk",
    "iso:country":"BY",
    "name:eng_x_preferred":[
        "Staroye Selo"
    ],
    "name:rus_x_preferred":[
        "\u0421\u0442\u0430\u0440.\u0421\u0435\u043b\u043e"
    ],
    "name:rus_x_variant":[
        "\u0421\u0442\u0430\u0440\u043e\u0435 \u0421\u0435\u043b\u043e"
    ],
    "name:und_x_variant":[
        "Podtserkovshchina"
    ],
    "wof:name":"Staroye Selo",
    "wof:placetype":"locality"
},
  "geometry": {"coordinates":[31.6145,54.073],"type":"Point"}
}