{
  "type": "Feature",
  "properties": {
    "gn:admin1_code":"5.0",
    "gn:asciiname":"Zadvorniki",
    "gn:country_code":"BY",
    "gn:dem":226,
    "gn:feature_class":"P",
    "gn:feature_code":"PPL",
    "gn:name":"Zadvorniki",
    "gn:population":0,
    "gn:timezone":"Europe/Minsk",
    "iso:country":"BY",
    "name:rus_x_preferred":[
        "\u0417\u0430\u0434\u0432\u043e\u0440\u043d\u0438\u043a\u0438"
    ],
    "name:und_x_variant":[
        "Zadworniki",
        "Zadvorinki",
        "Zadvorniki"
    ],
    "wof:name":"Zadvorniki",
    "wof:placetype":"locality"
},
  "geometry": {"coordinates":[27.9568,54.3764],"type":"Point"}
}