{
  "type": "Feature",
  "properties": {
    "gn:admin1_code":"1.0",
    "gn:asciiname":"Koloniya",
    "gn:country_code":"BY",
    "gn:dem":148,
    "gn:feature_class":"P",
    "gn:feature_code":"PPL",
    "gn:name":"Koloniya",
    "gn:population":0,
    "gn:timezone":"Europe/Minsk",
    "iso:country":"BY",
    "name:rus_x_preferred":[
        "\u041a\u043e\u043b\u043e\u043d\u0438\u044f"
    ],
    "wof:name":"Koloniya",
    "wof:placetype":"locality"
},
  "geometry": {"coordinates":[26.4478,51.8689],"type":"Point"}
}