{
  "type": "Feature",
  "properties": {
    "gn:admin1_code":"7.0",
    "gn:asciiname":"Artel'nyy",
    "gn:country_code":"BY",
    "gn:dem":182,
    "gn:feature_class":"P",
    "gn:feature_code":"PPL",
    "gn:name":"Artel\u2019nyy",
    "gn:population":0,
    "gn:timezone":"Europe/Minsk",
    "iso:country":"BY",
    "name:rus_x_preferred":[
        "\u0410\u0440\u0442\u0435\u043b\u044c\u043d\u044b\u0439"
    ],
    "name:und_x_variant":[
        "Artel\u2019nyy"
    ],
    "wof:name":"Artel'nyy",
    "wof:placetype":"locality"
},
  "geometry": {"coordinates":[30.0354,55.4512],"type":"Point"}
}