{
  "type": "Feature",
  "properties": {
    "gn:admin1_code":"0.0",
    "gn:asciiname":"Male Polyaki",
    "gn:country_code":"BY",
    "gn:dem":126,
    "gn:feature_class":"P",
    "gn:feature_code":"PPL",
    "gn:name":"Male Polyaki",
    "gn:population":0,
    "gn:timezone":"Europe/Minsk",
    "iso:country":"BY",
    "wof:name":"Male Polyaki",
    "wof:placetype":"locality"
},
  "geometry": {"coordinates":[27.81667,55.68333000000001],"type":"Point"}
}