{
  "type": "Feature",
  "properties": {
    "gn:admin1_code":"3.0",
    "gn:asciiname":"Slavatsichy",
    "gn:country_code":"BY",
    "gn:dem":147,
    "gn:feature_class":"P",
    "gn:feature_code":"PPL",
    "gn:name":"Slavatsichy",
    "gn:population":0,
    "gn:timezone":"Europe/Minsk",
    "iso:country":"BY",
    "name:bel_x_preferred":[
        "\u0421\u043b\u0430\u0432\u0430\u0446\u0456\u0447\u044b"
    ],
    "name:und_x_variant":[
        "Slovatyche",
        "Slovatichi",
        "Slavatsichy"
    ],
    "wof:name":"Slavatsichy",
    "wof:placetype":"locality"
},
  "geometry": {"coordinates":[24.8584,52.9876],"type":"Point"}
}