{
  "type": "Feature",
  "properties": {
    "gn:admin1_code":"1.0",
    "gn:asciiname":"Novyy Svet",
    "gn:country_code":"BY",
    "gn:dem":190,
    "gn:feature_class":"P",
    "gn:feature_code":"PPL",
    "gn:name":"Novyy Svet",
    "gn:population":0,
    "gn:timezone":"Europe/Minsk",
    "iso:country":"BY",
    "name:rus_x_preferred":[
        "\u041d\u043e\u0432\u044b\u0439 \u0421\u0432\u0435\u0442"
    ],
    "wof:name":"Novyy Svet",
    "wof:placetype":"locality"
},
  "geometry": {"coordinates":[26.0649,53.1836],"type":"Point"}
}