{
  "type": "Feature",
  "properties": {
    "gn:admin1_code":"7.0",
    "gn:asciiname":"Lozhanshchina",
    "gn:country_code":"BY",
    "gn:dem":161,
    "gn:feature_class":"P",
    "gn:feature_code":"PPL",
    "gn:name":"Lozhanshchina",
    "gn:population":0,
    "gn:timezone":"Europe/Minsk",
    "iso:country":"BY",
    "name:rus_x_preferred":[
        "\u041b\u043e\u0436\u0430\u043d\u0449\u0438\u043d\u0430"
    ],
    "wof:name":"Lozhanshchina",
    "wof:placetype":"locality"
},
  "geometry": {"coordinates":[28.4585,55.1366],"type":"Point"}
}