{
  "type": "Feature",
  "properties": {
    "gn:admin1_code":"5.0",
    "gn:asciiname":"Sadkovshchina",
    "gn:country_code":"BY",
    "gn:dem":212,
    "gn:feature_class":"P",
    "gn:feature_code":"PPL",
    "gn:name":"Sadkovshchina",
    "gn:population":0,
    "gn:timezone":"Europe/Minsk",
    "iso:country":"BY",
    "name:rus_x_preferred":[
        "\u0421\u0430\u0434\u043a\u043e\u0432\u0449\u0438\u043d\u0430"
    ],
    "wof:name":"Sadkovshchina",
    "wof:placetype":"locality"
},
  "geometry": {"coordinates":[27.0693,53.6976],"type":"Point"}
}