{
  "type": "Feature",
  "properties": {
    "gn:admin1_code":"6.0",
    "gn:asciiname":"Lyulevo",
    "gn:country_code":"BY",
    "gn:dem":160,
    "gn:feature_class":"P",
    "gn:feature_code":"PPL",
    "gn:name":"Lyulevo",
    "gn:population":0,
    "gn:timezone":"Europe/Minsk",
    "iso:country":"BY",
    "name:rus_x_preferred":[
        "\u041b\u044e\u043b\u0435\u0432\u043e"
    ],
    "wof:name":"Lyulevo",
    "wof:placetype":"locality"
},
  "geometry": {"coordinates":[28.8976,53.231],"type":"Point"}
}