{
  "type": "Feature",
  "properties": {
    "gn:admin1_code":"1.0",
    "gn:asciiname":"Karolin",
    "gn:country_code":"BY",
    "gn:dem":182,
    "gn:feature_class":"P",
    "gn:feature_code":"PPL",
    "gn:name":"Karolin",
    "gn:population":0,
    "gn:timezone":"Europe/Minsk",
    "iso:country":"BY",
    "name:bel_x_preferred":[
        "\u041a\u0430\u0440\u0430\u043b\u0456\u043d"
    ],
    "name:ceb_x_preferred":[
        "Karolin"
    ],
    "name:deu_x_preferred":[
        "Karolin"
    ],
    "name:fra_x_preferred":[
        "Karolin"
    ],
    "name:nld_x_preferred":[
        "Karolin"
    ],
    "name:pol_x_preferred":[
        "Karolin"
    ],
    "name:rus_x_preferred":[
        "\u041a\u0430\u0440\u043e\u043b\u0438\u043d"
    ],
    "name:srp_x_preferred":[
        "\u041a\u0430\u0440\u043e\u043b\u0438\u043d"
    ],
    "name:swe_x_preferred":[
        "Karolin"
    ],
    "name:ukr_x_preferred":[
        "\u041a\u0430\u0440\u043e\u043b\u0456\u043d"
    ],
    "wof:name":"Karolin",
    "wof:placetype":"locality"
},
  "geometry": {"coordinates":[23.4627,52.441],"type":"Point"}
}