{
  "type": "Feature",
  "properties": {
    "gn:admin1_code":"6.0",
    "gn:asciiname":"Karnitsa",
    "gn:country_code":"BY",
    "gn:dem":145,
    "gn:feature_class":"P",
    "gn:feature_code":"PPL",
    "gn:name":"Karnitsa",
    "gn:population":0,
    "gn:timezone":"Europe/Minsk",
    "iso:country":"BY",
    "name:rus_x_preferred":[
        "\u041a\u0430\u0440\u043d\u0438\u0446\u0430"
    ],
    "name:und_x_variant":[
        "Kornitsa"
    ],
    "wof:name":"Karnitsa",
    "wof:placetype":"locality"
},
  "geometry": {"coordinates":[28.5613,52.889],"type":"Point"}
}