{
  "type": "Feature",
  "properties": {
    "gn:admin1_code":"3.0",
    "gn:asciiname":"Shilovichi",
    "gn:country_code":"BY",
    "gn:dem":133,
    "gn:feature_class":"P",
    "gn:feature_code":"PPL",
    "gn:name":"Shilovichi",
    "gn:population":0,
    "gn:timezone":"Europe/Minsk",
    "iso:country":"BY",
    "name:bel_x_preferred":[
        "Shylavichy"
    ],
    "name:bel_x_variant":[
        "\u0428\u044b\u043b\u0430\u0432\u0456\u0447\u044b"
    ],
    "name:eng_x_preferred":[
        "Shilovichi"
    ],
    "name:rus_x_preferred":[
        "\u0411\u043e\u043b.\u0428\u0438\u043b\u043e\u0432\u0438\u0447\u0438"
    ],
    "name:rus_x_variant":[
        "\u0428\u0438\u043b\u043e\u0432\u0438\u0447\u0438"
    ],
    "name:und_x_variant":[
        "Szyd\u0142owicze",
        "Shilovichi-Malyye",
        "Shilovichi"
    ],
    "wof:name":"Shilovichi",
    "wof:placetype":"locality"
},
  "geometry": {"coordinates":[25.3606,53.0354],"type":"Point"}
}