{
  "type": "Feature",
  "properties": {
    "gn:admin1_code":"7.0",
    "gn:asciiname":"Zhel'tsy",
    "gn:country_code":"BY",
    "gn:dem":142,
    "gn:feature_class":"P",
    "gn:feature_code":"PPL",
    "gn:name":"Zhel\u2019tsy",
    "gn:population":0,
    "gn:timezone":"Europe/Minsk",
    "iso:country":"BY",
    "name:rus_x_preferred":[
        "\u0416\u0435\u043b\u044c\u0446\u044b"
    ],
    "name:und_x_variant":[
        "Zhel\u2019tsy"
    ],
    "wof:name":"Zhel'tsy",
    "wof:placetype":"locality"
},
  "geometry": {"coordinates":[29.3843,55.6253],"type":"Point"}
}