{
  "type": "Feature",
  "properties": {
    "gn:admin1_code":"3.0",
    "gn:asciiname":"Berezovets",
    "gn:country_code":"BY",
    "gn:dem":152,
    "gn:feature_class":"P",
    "gn:feature_code":"PPL",
    "gn:name":"Ber\u00ebzovets",
    "gn:population":0,
    "gn:timezone":"Europe/Minsk",
    "iso:country":"BY",
    "name:rus_x_preferred":[
        "\u0411\u0435\u0440\u0451\u0437\u043e\u0432\u0435\u0446"
    ],
    "name:und_x_variant":[
        "Ber\u00ebzovets"
    ],
    "wof:name":"Berezovets",
    "wof:placetype":"locality"
},
  "geometry": {"coordinates":[26.1681,53.5209],"type":"Point"}
}