{
  "type": "Feature",
  "properties": {
    "gn:admin1_code":"7.0",
    "gn:asciiname":"Gorbuli",
    "gn:country_code":"BY",
    "gn:dem":120,
    "gn:feature_class":"P",
    "gn:feature_code":"PPL",
    "gn:name":"Gorbuli",
    "gn:population":0,
    "gn:timezone":"Europe/Minsk",
    "iso:country":"BY",
    "name:rus_x_preferred":[
        "\u0413\u043e\u0440\u0431\u0443\u043b\u0438"
    ],
    "wof:name":"Gorbuli",
    "wof:placetype":"locality"
},
  "geometry": {"coordinates":[27.8907,55.8433],"type":"Point"}
}