{
  "type": "Feature",
  "properties": {
    "gn:admin1_code":"0.0",
    "gn:asciiname":"Pechishche",
    "gn:cc2":"BY",
    "gn:country_code":"BY",
    "gn:dem":152,
    "gn:feature_class":"P",
    "gn:feature_code":"PPL",
    "gn:name":"Pechishche",
    "gn:population":0,
    "gn:timezone":"Europe/Minsk",
    "iso:country":"BY",
    "name:und_x_variant":[
        "Pieczyszcze",
        "Pechishche"
    ],
    "wof:name":"Pechishche",
    "wof:placetype":"locality"
},
  "geometry": {"coordinates":[26.18333,52.65],"type":"Point"}
}