{
  "type": "Feature",
  "properties": {
    "gn:admin1_code":"7.0",
    "gn:asciiname":"Brilek",
    "gn:country_code":"BY",
    "gn:dem":131,
    "gn:feature_class":"P",
    "gn:feature_code":"PPL",
    "gn:name":"Brilek",
    "gn:population":0,
    "gn:timezone":"Europe/Minsk",
    "iso:country":"BY",
    "name:rus_x_preferred":[
        "\u0411\u0440\u0438\u043b\u0435\u043a"
    ],
    "wof:name":"Brilek",
    "wof:placetype":"locality"
},
  "geometry": {"coordinates":[27.6495,55.4492],"type":"Point"}
}