{
  "type": "Feature",
  "properties": {
    "gn:admin1_code":"2.0",
    "gn:asciiname":"Staryy Barsuk",
    "gn:country_code":"BY",
    "gn:dem":137,
    "gn:feature_class":"P",
    "gn:feature_code":"PPL",
    "gn:name":"Staryy Barsuk",
    "gn:population":0,
    "gn:timezone":"Europe/Minsk",
    "iso:country":"BY",
    "name:rus_x_preferred":[
        "\u0421\u0442\u0430\u0440\u044b\u0439 \u0411\u0430\u0440\u0441\u0443\u043a"
    ],
    "name:und_x_variant":[
        "Staryye Barsuki",
        "Staryy Barsuk"
    ],
    "wof:name":"Staryy Barsuk",
    "wof:placetype":"locality"
},
  "geometry": {"coordinates":[30.2626,52.1315],"type":"Point"}
}