{
  "type": "Feature",
  "properties": {
    "gn:admin1_code":"1.0",
    "gn:asciiname":"Poselok Gorodishche",
    "gn:country_code":"BY",
    "gn:dem":135,
    "gn:feature_class":"P",
    "gn:feature_code":"PPL",
    "gn:name":"Pos\u00eblok Gorodishche",
    "gn:population":0,
    "gn:timezone":"Europe/Minsk",
    "iso:country":"BY",
    "name:rus_x_preferred":[
        "\u041f\u043e\u0441\u0451\u043b\u043e\u043a \u0413\u043e\u0440\u043e\u0434\u0438\u0449\u0435"
    ],
    "name:und_x_variant":[
        "Pos\u00eblok Gorodishche"
    ],
    "wof:name":"Poselok Gorodishche",
    "wof:placetype":"locality"
},
  "geometry": {"coordinates":[26.262,52.1719],"type":"Point"}
}