{
  "type": "Feature",
  "properties": {
    "gn:admin1_code":"1.0",
    "gn:asciiname":"Rovchak",
    "gn:country_code":"BY",
    "gn:dem":146,
    "gn:feature_class":"P",
    "gn:feature_code":"PPL",
    "gn:name":"Rovchak",
    "gn:population":0,
    "gn:timezone":"Europe/Minsk",
    "iso:country":"BY",
    "name:rus_x_preferred":[
        "\u0420\u043e\u0432\u0447\u0430\u043a"
    ],
    "wof:name":"Rovchak",
    "wof:placetype":"locality"
},
  "geometry": {"coordinates":[26.5499,51.8768],"type":"Point"}
}