{
  "type": "Feature",
  "properties": {
    "gn:admin1_code":"5.0",
    "gn:asciiname":"Osovets",
    "gn:country_code":"BY",
    "gn:dem":188,
    "gn:feature_class":"P",
    "gn:feature_code":"PPL",
    "gn:name":"Osovets",
    "gn:population":0,
    "gn:timezone":"Europe/Minsk",
    "iso:country":"BY",
    "name:rus_x_preferred":[
        "\u041e\u0441\u043e\u0432\u0435\u0446"
    ],
    "name:und_x_variant":[
        "Osowiec",
        "Osovets"
    ],
    "wof:name":"Osovets",
    "wof:placetype":"locality"
},
  "geometry": {"coordinates":[27.1235,54.2655],"type":"Point"}
}