{
  "type": "Feature",
  "properties": {
    "gn:admin1_code":"1.0",
    "gn:asciiname":"Lukoye",
    "gn:country_code":"BY",
    "gn:dem":135,
    "gn:feature_class":"P",
    "gn:feature_code":"PPL",
    "gn:name":"Lukoye",
    "gn:population":0,
    "gn:timezone":"Europe/Minsk",
    "iso:country":"BY",
    "name:rus_x_preferred":[
        "\u041b\u0443\u043a\u043e\u0435"
    ],
    "name:und_x_variant":[
        "Luki"
    ],
    "wof:name":"Lukoye",
    "wof:placetype":"locality"
},
  "geometry": {"coordinates":[26.9672,51.7815],"type":"Point"}
}