{
  "type": "Feature",
  "properties": {
    "gn:admin1_code":"7.0",
    "gn:asciiname":"Keziki",
    "gn:country_code":"BY",
    "gn:dem":131,
    "gn:feature_class":"P",
    "gn:feature_code":"PPL",
    "gn:name":"Keziki",
    "gn:population":0,
    "gn:timezone":"Europe/Minsk",
    "iso:country":"BY",
    "name:rus_x_preferred":[
        "\u041a\u0435\u0437\u0438\u043a\u0438"
    ],
    "wof:name":"Keziki",
    "wof:placetype":"locality"
},
  "geometry": {"coordinates":[27.0541,55.7229],"type":"Point"}
}