{
  "type": "Feature",
  "properties": {
    "gn:admin1_code":"6.0",
    "gn:asciiname":"Krasnaya Gora",
    "gn:country_code":"BY",
    "gn:dem":149,
    "gn:feature_class":"P",
    "gn:feature_code":"PPL",
    "gn:name":"Krasnaya Gora",
    "gn:population":0,
    "gn:timezone":"Europe/Minsk",
    "iso:country":"BY",
    "name:rus_x_preferred":[
        "\u041a\u0440\u0430\u0441\u043d\u0430\u044f \u0413\u043e\u0440\u0430"
    ],
    "wof:name":"Krasnaya Gora",
    "wof:placetype":"locality"
},
  "geometry": {"coordinates":[29.7307,53.1547],"type":"Point"}
}