{
  "type": "Feature",
  "properties": {
    "gn:admin1_code":"7.0",
    "gn:asciiname":"Yaryzhino",
    "gn:country_code":"BY",
    "gn:dem":161,
    "gn:feature_class":"P",
    "gn:feature_code":"PPL",
    "gn:name":"Yaryzhino",
    "gn:population":0,
    "gn:timezone":"Europe/Minsk",
    "iso:country":"BY",
    "name:rus_x_preferred":[
        "\u042f\u0440\u044b\u0436\u0438\u043d\u043e"
    ],
    "wof:name":"Yaryzhino",
    "wof:placetype":"locality"
},
  "geometry": {"coordinates":[27.4357,55.1683],"type":"Point"}
}