{
  "type": "Feature",
  "properties": {
    "gn:admin1_code":"5.0",
    "gn:asciiname":"Khripkovo",
    "gn:country_code":"BY",
    "gn:dem":195,
    "gn:feature_class":"P",
    "gn:feature_code":"PPL",
    "gn:name":"Khripkovo",
    "gn:population":0,
    "gn:timezone":"Europe/Minsk",
    "iso:country":"BY",
    "name:rus_x_preferred":[
        "\u0425\u0440\u0438\u043f\u043a\u043e\u0432\u043e"
    ],
    "wof:name":"Khripkovo",
    "wof:placetype":"locality"
},
  "geometry": {"coordinates":[26.5725,53.1446],"type":"Point"}
}