{
  "type": "Feature",
  "properties": {
    "gn:admin1_code":"3.0",
    "gn:asciiname":"Zamosh'ye Pervoye",
    "gn:country_code":"BY",
    "gn:dem":143,
    "gn:feature_class":"P",
    "gn:feature_code":"PPL",
    "gn:name":"Zamosh\u2019ye Pervoye",
    "gn:population":0,
    "gn:timezone":"Europe/Minsk",
    "iso:country":"BY",
    "name:rus_x_preferred":[
        "\u0417\u0430\u043c\u043e\u0448\u044c\u0435 \u041f\u0435\u0440\u0432\u043e\u0435"
    ],
    "name:und_x_variant":[
        "Zamosh\u2019ye Pervoye"
    ],
    "wof:name":"Zamosh'ye Pervoye",
    "wof:placetype":"locality"
},
  "geometry": {"coordinates":[26.1156,53.9536],"type":"Point"}
}