{
  "type": "Feature",
  "properties": {
    "gn:admin1_code":"6.0",
    "gn:asciiname":"Golysheno",
    "gn:country_code":"BY",
    "gn:dem":176,
    "gn:feature_class":"P",
    "gn:feature_code":"PPL",
    "gn:name":"Golysheno",
    "gn:population":0,
    "gn:timezone":"Europe/Minsk",
    "iso:country":"BY",
    "name:rus_x_preferred":[
        "\u0413\u043e\u043b\u044b\u0448\u0435\u043d\u043e"
    ],
    "name:und_x_variant":[
        "Golyshino"
    ],
    "wof:name":"Golysheno",
    "wof:placetype":"locality"
},
  "geometry": {"coordinates":[30.981,54.2029],"type":"Point"}
}