{
  "type": "Feature",
  "properties": {
    "gn:admin1_code":"3.0",
    "gn:asciiname":"Kravtsevichi",
    "gn:country_code":"BY",
    "gn:dem":185,
    "gn:feature_class":"P",
    "gn:feature_code":"PPL",
    "gn:name":"Kravtsevichi",
    "gn:population":0,
    "gn:timezone":"Europe/Minsk",
    "iso:country":"BY",
    "name:bel_x_preferred":[
        "Krawtsevichy"
    ],
    "name:bel_x_variant":[
        "\u041a\u0440\u0430\u045e\u0446\u044d\u0432\u0456\u0447\u044b"
    ],
    "name:rus_x_preferred":[
        "\u041a\u0440\u0430\u0432\u0446\u0435\u0432\u0438\u0447\u0438"
    ],
    "wof:name":"Kravtsevichi",
    "wof:placetype":"locality"
},
  "geometry": {"coordinates":[25.9516,53.6183],"type":"Point"}
}