{
  "type": "Feature",
  "properties": {
    "gn:admin1_code":"7.0",
    "gn:asciiname":"Zhelezkovo",
    "gn:country_code":"BY",
    "gn:dem":188,
    "gn:feature_class":"P",
    "gn:feature_code":"PPL",
    "gn:name":"Zhelezkovo",
    "gn:population":0,
    "gn:timezone":"Europe/Minsk",
    "iso:country":"BY",
    "name:rus_x_preferred":[
        "\u0416\u0435\u043b\u0435\u0437\u043a\u043e\u0432\u043e"
    ],
    "wof:name":"Zhelezkovo",
    "wof:placetype":"locality"
},
  "geometry": {"coordinates":[31.0204,54.5496],"type":"Point"}
}