{
  "type": "Feature",
  "properties": {
    "gn:admin1_code":"7.0",
    "gn:asciiname":"Simonyata",
    "gn:country_code":"BY",
    "gn:dem":145,
    "gn:feature_class":"P",
    "gn:feature_code":"PPL",
    "gn:name":"Simonyata",
    "gn:population":0,
    "gn:timezone":"Europe/Minsk",
    "iso:country":"BY",
    "name:rus_x_preferred":[
        "\u0421\u0438\u043c\u043e\u043d\u044f\u0442\u0430"
    ],
    "wof:name":"Simonyata",
    "wof:placetype":"locality"
},
  "geometry": {"coordinates":[29.5945,55.4882],"type":"Point"}
}