{
  "type": "Feature",
  "properties": {
    "gn:admin1_code":"2.0",
    "gn:asciiname":"Kanichev",
    "gn:country_code":"BY",
    "gn:dem":134,
    "gn:feature_class":"P",
    "gn:feature_code":"PPL",
    "gn:name":"Kanichev",
    "gn:population":0,
    "gn:timezone":"Europe/Minsk",
    "iso:country":"BY",
    "name:rus_x_preferred":[
        "\u041a\u0430\u043d\u0438\u0447\u0435\u0432"
    ],
    "name:und_x_variant":[
        "Konichev"
    ],
    "wof:name":"Kanichev",
    "wof:placetype":"locality"
},
  "geometry": {"coordinates":[31.0399,52.5436],"type":"Point"}
}