{
  "type": "Feature",
  "properties": {
    "gn:admin1_code":"1.0",
    "gn:asciiname":"Ol'pen'",
    "gn:country_code":"BY",
    "gn:dem":127,
    "gn:feature_class":"P",
    "gn:feature_code":"PPL",
    "gn:name":"Ol\u2019pen\u2019",
    "gn:population":0,
    "gn:timezone":"Europe/Minsk",
    "iso:country":"BY",
    "name:rus_x_preferred":[
        "Ol\u2019pen\u2019"
    ],
    "name:rus_x_variant":[
        "\u041e\u043b\u044c\u043f\u0435\u043d\u044c"
    ],
    "name:und_x_variant":[
        "Olpien\u2019",
        "Olypen\u2019"
    ],
    "wof:name":"Ol'pen'",
    "wof:placetype":"locality"
},
  "geometry": {"coordinates":[27.1692,52.0191],"type":"Point"}
}