{
  "type": "Feature",
  "properties": {
    "gn:admin1_code":"7.0",
    "gn:asciiname":"Novoye Barsuchino",
    "gn:country_code":"BY",
    "gn:dem":142,
    "gn:feature_class":"P",
    "gn:feature_code":"PPL",
    "gn:name":"Novoye Barsuchino",
    "gn:population":0,
    "gn:timezone":"Europe/Minsk",
    "iso:country":"BY",
    "name:rus_x_preferred":[
        "\u041d\u043e\u0432\u043e\u0435 \u0411\u0430\u0440\u0441\u0443\u0447\u0438\u043d\u043e"
    ],
    "wof:name":"Novoye Barsuchino",
    "wof:placetype":"locality"
},
  "geometry": {"coordinates":[29.6181,55.4849],"type":"Point"}
}