{
  "type": "Feature",
  "properties": {
    "gn:admin1_code":"3.0",
    "gn:asciiname":"Baranovichi",
    "gn:country_code":"BY",
    "gn:dem":173,
    "gn:feature_class":"P",
    "gn:feature_code":"PPL",
    "gn:name":"Baranovichi",
    "gn:population":0,
    "gn:timezone":"Europe/Minsk",
    "iso:country":"BY",
    "name:rus_x_preferred":[
        "\u0411\u0430\u0440\u0430\u043d\u043e\u0432\u0438\u0447\u0438"
    ],
    "wof:name":"Baranovichi",
    "wof:placetype":"locality"
},
  "geometry": {"coordinates":[25.795,54.2098],"type":"Point"}
}