{
  "type": "Feature",
  "properties": {
    "gn:admin1_code":"5.0",
    "gn:asciiname":"Nizkavichy",
    "gn:country_code":"BY",
    "gn:dem":194,
    "gn:feature_class":"P",
    "gn:feature_code":"PPL",
    "gn:name":"Nizkavichy",
    "gn:population":0,
    "gn:timezone":"Europe/Minsk",
    "iso:country":"BY",
    "name:bel_x_preferred":[
        "\u041d\u0456\u0437\u043a\u0430\u0432\u0456\u0447\u044b"
    ],
    "name:eng_x_preferred":[
        "Niskovichi"
    ],
    "name:rus_x_preferred":[
        "\u041d\u0438\u0437\u043a\u043e\u0432\u0438\u0447\u0438"
    ],
    "name:und_x_variant":[
        "Nizkavichy",
        "Nizkovichi"
    ],
    "wof:name":"Nizkavichy",
    "wof:placetype":"locality"
},
  "geometry": {"coordinates":[27.0452,53.203],"type":"Point"}
}