{
  "type": "Feature",
  "properties": {
    "gn:admin1_code":"2.0",
    "gn:asciiname":"Syamyencha",
    "gn:country_code":"BY",
    "gn:dem":133,
    "gn:feature_class":"P",
    "gn:feature_code":"PPL",
    "gn:name":"Syamyencha",
    "gn:population":0,
    "gn:timezone":"Europe/Minsk",
    "iso:country":"BY",
    "name:bel_x_preferred":[
        "\u0421\u044f\u043c\u0435\u043d\u0447\u0430"
    ],
    "name:und_x_variant":[
        "Semencha"
    ],
    "wof:name":"Syamyencha",
    "wof:placetype":"locality"
},
  "geometry": {"coordinates":[27.8768,52.3459],"type":"Point"}
}