{
  "type": "Feature",
  "properties": {
    "gn:admin1_code":"6.0",
    "gn:asciiname":"Gannovka",
    "gn:country_code":"BY",
    "gn:dem":164,
    "gn:feature_class":"P",
    "gn:feature_code":"PPL",
    "gn:name":"Gannovka",
    "gn:population":0,
    "gn:timezone":"Europe/Minsk",
    "iso:country":"BY",
    "name:rus_x_preferred":[
        "\u0413\u0430\u043d\u043d\u043e\u0432\u043a\u0430"
    ],
    "name:und_x_variant":[
        "Ganovka"
    ],
    "wof:name":"Gannovka",
    "wof:placetype":"locality"
},
  "geometry": {"coordinates":[31.9458,53.74100000000001],"type":"Point"}
}