{
  "type": "Feature",
  "properties": {
    "gn:admin1_code":"2.0",
    "gn:asciiname":"Rassvyet",
    "gn:country_code":"BY",
    "gn:dem":149,
    "gn:feature_class":"P",
    "gn:feature_code":"PPL",
    "gn:name":"Rassvyet",
    "gn:population":0,
    "gn:timezone":"Europe/Minsk",
    "iso:country":"BY",
    "name:bel_x_preferred":[
        "\u0420\u0430\u0441\u0441\u0432\u0435\u0442"
    ],
    "name:und_x_variant":[
        "Rassvet"
    ],
    "wof:name":"Rassvyet",
    "wof:placetype":"locality"
},
  "geometry": {"coordinates":[29.174,52.7793],"type":"Point"}
}