{
  "type": "Feature",
  "properties": {
    "gn:admin1_code":"5.0",
    "gn:asciiname":"Rybakovshchina",
    "gn:country_code":"BY",
    "gn:dem":174,
    "gn:feature_class":"P",
    "gn:feature_code":"PPL",
    "gn:name":"Rybakovshchina",
    "gn:population":0,
    "gn:timezone":"Europe/Minsk",
    "iso:country":"BY",
    "name:rus_x_preferred":[
        "\u0420\u044b\u0431\u0430\u043a\u043e\u0432\u0449\u0438\u043d\u0430"
    ],
    "wof:name":"Rybakovshchina",
    "wof:placetype":"locality"
},
  "geometry": {"coordinates":[27.5712,53.5451],"type":"Point"}
}