{
  "type": "Feature",
  "properties": {
    "gn:admin1_code":"2.0",
    "gn:asciiname":"Gromkiy",
    "gn:country_code":"BY",
    "gn:dem":114,
    "gn:feature_class":"P",
    "gn:feature_code":"PPL",
    "gn:name":"Gromkiy",
    "gn:population":0,
    "gn:timezone":"Europe/Minsk",
    "iso:country":"BY",
    "name:rus_x_preferred":[
        "\u0413\u0440\u043e\u043c\u043a\u0438\u0439"
    ],
    "wof:name":"Gromkiy",
    "wof:placetype":"locality"
},
  "geometry": {"coordinates":[30.5236,51.7466],"type":"Point"}
}