{
  "type": "Feature",
  "properties": {
    "gn:admin1_code":"7.0",
    "gn:asciiname":"Kupcheli",
    "gn:country_code":"BY",
    "gn:dem":149,
    "gn:feature_class":"P",
    "gn:feature_code":"PPL",
    "gn:name":"Kupcheli",
    "gn:population":0,
    "gn:timezone":"Europe/Minsk",
    "iso:country":"BY",
    "name:rus_x_preferred":[
        "\u041a\u0443\u043f\u0447\u0435\u043b\u0438"
    ],
    "name:und_x_variant":[
        "Kupchele",
        "Kupczele",
        "Kupcheli"
    ],
    "wof:name":"Kupcheli",
    "wof:placetype":"locality"
},
  "geometry": {"coordinates":[26.8286,55.5779],"type":"Point"}
}