{
  "type": "Feature",
  "properties": {
    "gn:admin1_code":"7.0",
    "gn:asciiname":"Zamostoch'ye",
    "gn:country_code":"BY",
    "gn:dem":162,
    "gn:feature_class":"P",
    "gn:feature_code":"PPL",
    "gn:name":"Zamostoch\u2019ye",
    "gn:population":0,
    "gn:timezone":"Europe/Minsk",
    "iso:country":"BY",
    "name:rus_x_preferred":[
        "\u0417\u0430\u043c\u043e\u0441\u0442\u043e\u0447\u044c\u0435"
    ],
    "name:und_x_variant":[
        "Zamostoch\u2019ye"
    ],
    "wof:name":"Zamostoch'ye",
    "wof:placetype":"locality"
},
  "geometry": {"coordinates":[30.3691,54.784],"type":"Point"}
}