{
  "type": "Feature",
  "properties": {
    "gn:admin1_code":"6.0",
    "gn:asciiname":"Belorus'",
    "gn:country_code":"BY",
    "gn:dem":185,
    "gn:feature_class":"P",
    "gn:feature_code":"PPL",
    "gn:name":"Belorus\u2019",
    "gn:population":0,
    "gn:timezone":"Europe/Minsk",
    "iso:country":"BY",
    "name:rus_x_preferred":[
        "\u0411\u0435\u043b\u043e\u0440\u0443\u0441\u044c"
    ],
    "name:und_x_variant":[
        "Belorus\u2019"
    ],
    "wof:name":"Belorus'",
    "wof:placetype":"locality"
},
  "geometry": {"coordinates":[29.563,54.1166],"type":"Point"}
}