{
  "type": "Feature",
  "properties": {
    "gn:admin1_code":"5.0",
    "gn:asciiname":"Yaskavichy",
    "gn:country_code":"BY",
    "gn:dem":140,
    "gn:feature_class":"P",
    "gn:feature_code":"PPL",
    "gn:name":"Yaskavichy",
    "gn:population":0,
    "gn:timezone":"Europe/Minsk",
    "iso:country":"BY",
    "name:bel_x_preferred":[
        "\u042f\u0441\u043a\u0430\u0432\u0456\u0447\u044b"
    ],
    "name:eng_x_preferred":[
        "Yas'kovichi"
    ],
    "name:rus_x_preferred":[
        "\u042f\u0441\u043a\u043e\u0432\u0438\u0447\u0438"
    ],
    "name:und_x_variant":[
        "Ja\u015bkowicze",
        "Yas\u2019koviche",
        "Yaskovichi",
        "Yaskavichy"
    ],
    "wof:name":"Yaskavichy",
    "wof:placetype":"locality"
},
  "geometry": {"coordinates":[27.5065,52.5731],"type":"Point"}
}