{
  "type": "Feature",
  "properties": {
    "gn:admin1_code":"6.0",
    "gn:asciiname":"Yadrina Sloboda",
    "gn:country_code":"BY",
    "gn:dem":147,
    "gn:feature_class":"P",
    "gn:feature_code":"PPL",
    "gn:name":"Yadrina Sloboda",
    "gn:population":0,
    "gn:timezone":"Europe/Minsk",
    "iso:country":"BY",
    "name:rus_x_preferred":[
        "\u042f\u0434\u0440\u0451\u043d\u0430\u044f \u0421\u043b\u043e\u0431\u043e\u0434\u0430"
    ],
    "name:und_x_variant":[
        "Yadrika Sloboda",
        "Yadrina Sloboda",
        "Yadr\u00ebnaya Sloboda"
    ],
    "wof:name":"Yadrina Sloboda",
    "wof:placetype":"locality"
},
  "geometry": {"coordinates":[29.8193,53.6682],"type":"Point"}
}