{
  "type": "Feature",
  "properties": {
    "gn:admin1_code":"3.0",
    "gn:asciiname":"Poludy",
    "gn:country_code":"BY",
    "gn:dem":237,
    "gn:feature_class":"P",
    "gn:feature_code":"PPL",
    "gn:name":"Poludy",
    "gn:population":0,
    "gn:timezone":"Europe/Minsk",
    "iso:country":"BY",
    "name:rus_x_preferred":[
        "\u041f\u043e\u043b\u0443\u0434\u044b"
    ],
    "wof:name":"Poludy",
    "wof:placetype":"locality"
},
  "geometry": {"coordinates":[26.1174,54.2301],"type":"Point"}
}