{
  "type": "Feature",
  "properties": {
    "gn:admin1_code":"3.0",
    "gn:asciiname":"Koreni",
    "gn:country_code":"BY",
    "gn:dem":158,
    "gn:feature_class":"P",
    "gn:feature_code":"PPL",
    "gn:name":"Koreni",
    "gn:population":0,
    "gn:timezone":"Europe/Minsk",
    "iso:country":"BY",
    "name:rus_x_preferred":[
        "\u041a\u043e\u0440\u0435\u043d\u0438"
    ],
    "name:und_x_variant":[
        "Korzenie",
        "Koreni"
    ],
    "wof:name":"Koreni",
    "wof:placetype":"locality"
},
  "geometry": {"coordinates":[26.3696,54.5039],"type":"Point"}
}