{
  "type": "Feature",
  "properties": {
    "gn:admin1_code":"0.0",
    "gn:asciiname":"Pirash",
    "gn:country_code":"BY",
    "gn:dem":171,
    "gn:feature_class":"P",
    "gn:feature_code":"PPL",
    "gn:name":"Pirash",
    "gn:population":0,
    "gn:timezone":"Europe/Minsk",
    "iso:country":"BY",
    "wof:name":"Pirash",
    "wof:placetype":"locality"
},
  "geometry": {"coordinates":[31.83333,53.31667],"type":"Point"}
}