{
  "type": "Feature",
  "properties": {
    "gn:admin1_code":"1.0",
    "gn:asciiname":"Gorodishche Maloye",
    "gn:country_code":"BY",
    "gn:dem":183,
    "gn:feature_class":"P",
    "gn:feature_code":"PPL",
    "gn:name":"Gorodishche Maloye",
    "gn:population":0,
    "gn:timezone":"Europe/Minsk",
    "iso:country":"BY",
    "name:rus_x_preferred":[
        "\u0413\u043e\u0440\u043e\u0434\u0438\u0449\u0435 \u041c\u0430\u043b\u043e\u0435"
    ],
    "name:und_x_variant":[
        "Male Gorodyshche",
        "Male Horodyszcze",
        "Maloye Gorodishche",
        "Gorodishche Maloye"
    ],
    "wof:name":"Gorodishche Maloye",
    "wof:placetype":"locality"
},
  "geometry": {"coordinates":[26.0667,52.9562],"type":"Point"}
}