{
  "type": "Feature",
  "properties": {
    "gn:admin1_code":"5.0",
    "gn:asciiname":"Lyakhi",
    "gn:country_code":"BY",
    "gn:dem":181,
    "gn:feature_class":"P",
    "gn:feature_code":"PPL",
    "gn:name":"Lyakhi",
    "gn:population":0,
    "gn:timezone":"Europe/Minsk",
    "iso:country":"BY",
    "name:rus_x_preferred":[
        "\u041b\u044f\u0445\u0438"
    ],
    "name:und_x_variant":[
        "Lyakhy"
    ],
    "wof:name":"Lyakhi",
    "wof:placetype":"locality"
},
  "geometry": {"coordinates":[26.7693,53.1008],"type":"Point"}
}