{
  "type": "Feature",
  "properties": {
    "gn:admin1_code":"0.0",
    "gn:asciiname":"Ivaniki",
    "gn:cc2":"BY",
    "gn:country_code":"BY",
    "gn:dem":137,
    "gn:feature_class":"P",
    "gn:feature_code":"PPL",
    "gn:name":"Ivaniki",
    "gn:population":0,
    "gn:timezone":"Europe/Minsk",
    "iso:country":"BY",
    "name:und_x_variant":[
        "Iwaniki",
        "Ivaniki"
    ],
    "wof:name":"Ivaniki",
    "wof:placetype":"locality"
},
  "geometry": {"coordinates":[26.08333,52.18333],"type":"Point"}
}