{
  "type": "Feature",
  "properties": {
    "gn:admin1_code":"5.0",
    "gn:asciiname":"Bulakhovka",
    "gn:country_code":"BY",
    "gn:dem":192,
    "gn:feature_class":"P",
    "gn:feature_code":"PPL",
    "gn:name":"Bulakhovka",
    "gn:population":0,
    "gn:timezone":"Europe/Minsk",
    "iso:country":"BY",
    "name:rus_x_preferred":[
        "\u0411\u0443\u043b\u0430\u0445\u043e\u0432\u043a\u0430"
    ],
    "wof:name":"Bulakhovka",
    "wof:placetype":"locality"
},
  "geometry": {"coordinates":[27.7455,54.5019],"type":"Point"}
}