{
  "type": "Feature",
  "properties": {
    "gn:admin1_code":"7.0",
    "gn:asciiname":"Orekhovno",
    "gn:country_code":"BY",
    "gn:dem":184,
    "gn:feature_class":"P",
    "gn:feature_code":"PPL",
    "gn:name":"Orekhovno",
    "gn:population":0,
    "gn:timezone":"Europe/Minsk",
    "iso:country":"BY",
    "name:rus_x_preferred":[
        "\u041e\u0440\u0435\u0445\u043e\u0432\u043d\u043e"
    ],
    "name:und_x_variant":[
        "Orekhovo"
    ],
    "wof:name":"Orekhovno",
    "wof:placetype":"locality"
},
  "geometry": {"coordinates":[27.7277,55.1431],"type":"Point"}
}