{
  "type": "Feature",
  "properties": {
    "gn:admin1_code":"5.0",
    "gn:asciiname":"Novosady",
    "gn:country_code":"BY",
    "gn:dem":189,
    "gn:feature_class":"P",
    "gn:feature_code":"PPL",
    "gn:name":"Novosady",
    "gn:population":0,
    "gn:timezone":"Europe/Minsk",
    "iso:country":"BY",
    "name:rus_x_preferred":[
        "\u041d\u043e\u0432\u043e\u0441\u0430\u0434\u044b"
    ],
    "wof:name":"Novosady",
    "wof:placetype":"locality"
},
  "geometry": {"coordinates":[27.1848,53.14],"type":"Point"}
}