{
  "type": "Feature",
  "properties": {
    "gn:admin1_code":"7.0",
    "gn:asciiname":"Moseyevka",
    "gn:country_code":"BY",
    "gn:dem":168,
    "gn:feature_class":"P",
    "gn:feature_code":"PPL",
    "gn:name":"Moseyevka",
    "gn:population":0,
    "gn:timezone":"Europe/Minsk",
    "iso:country":"BY",
    "name:rus_x_preferred":[
        "\u041c\u043e\u0441\u0435\u0435\u0432\u043a\u0430"
    ],
    "wof:name":"Moseyevka",
    "wof:placetype":"locality"
},
  "geometry": {"coordinates":[30.4028,54.5572],"type":"Point"}
}