{
  "type": "Feature",
  "properties": {
    "gn:admin1_code":"7.0",
    "gn:asciiname":"Kireyevo",
    "gn:country_code":"BY",
    "gn:dem":203,
    "gn:feature_class":"P",
    "gn:feature_code":"PPL",
    "gn:name":"Kireyevo",
    "gn:population":0,
    "gn:timezone":"Europe/Minsk",
    "iso:country":"BY",
    "name:rus_x_preferred":[
        "\u041a\u0438\u0440\u0435\u0435\u0432\u043e"
    ],
    "name:und_x_variant":[
        "Kirygvo",
        "Kiriyevo",
        "Kireyevo"
    ],
    "wof:name":"Kireyevo",
    "wof:placetype":"locality"
},
  "geometry": {"coordinates":[29.8221,55.6165],"type":"Point"}
}