{
  "type": "Feature",
  "properties": {
    "gn:admin1_code":"3.0",
    "gn:asciiname":"Dovgyalishki",
    "gn:country_code":"BY",
    "gn:dem":158,
    "gn:feature_class":"P",
    "gn:feature_code":"PPL",
    "gn:name":"Dovgyalishki",
    "gn:population":0,
    "gn:timezone":"Europe/Minsk",
    "iso:country":"BY",
    "name:bel_x_preferred":[
        "Dawhyalishki"
    ],
    "name:bel_x_variant":[
        "\u0414\u0430\u045e\u0433\u044f\u043b\u0456\u0448\u043a\u0456"
    ],
    "name:rus_x_preferred":[
        "\u0414\u043e\u0432\u0433\u044f\u043b\u0438\u0448\u043a\u0438"
    ],
    "wof:name":"Dovgyalishki",
    "wof:placetype":"locality"
},
  "geometry": {"coordinates":[25.03152,53.98515],"type":"Point"}
}