{
  "type": "Feature",
  "properties": {
    "gn:admin1_code":"6.0",
    "gn:asciiname":"Belanovo",
    "gn:country_code":"BY",
    "gn:dem":203,
    "gn:feature_class":"P",
    "gn:feature_code":"PPL",
    "gn:name":"Belanovo",
    "gn:population":0,
    "gn:timezone":"Europe/Minsk",
    "iso:country":"BY",
    "name:rus_x_preferred":[
        "\u0411\u0435\u043b\u0430\u043d\u043e\u0432\u043e"
    ],
    "wof:name":"Belanovo",
    "wof:placetype":"locality"
},
  "geometry": {"coordinates":[30.2117,54.2078],"type":"Point"}
}