{
  "type": "Feature",
  "properties": {
    "gn:admin1_code":"5.0",
    "gn:asciiname":"Komarovka",
    "gn:country_code":"BY",
    "gn:dem":242,
    "gn:feature_class":"P",
    "gn:feature_code":"PPL",
    "gn:name":"Komarovka",
    "gn:population":0,
    "gn:timezone":"Europe/Minsk",
    "iso:country":"BY",
    "name:che_x_preferred":[
        "\u041a\u043e\u043c\u0430\u0440\u043e\u0432\u043a\u0430"
    ],
    "name:rus_x_preferred":[
        "\u041a\u043e\u043c\u0430\u0440\u043e\u0432\u043a\u0430"
    ],
    "name:tgk_x_preferred":[
        "\u041a\u043e\u043c\u0430\u0440\u043e\u0432\u043a\u0430"
    ],
    "wof:name":"Komarovka",
    "wof:placetype":"locality"
},
  "geometry": {"coordinates":[26.6094,54.0822],"type":"Point"}
}