{
  "type": "Feature",
  "properties": {
    "gn:admin1_code":"6.0",
    "gn:asciiname":"Andrany",
    "gn:country_code":"BY",
    "gn:dem":189,
    "gn:feature_class":"P",
    "gn:feature_code":"PPL",
    "gn:name":"Andrany",
    "gn:population":0,
    "gn:timezone":"Europe/Minsk",
    "iso:country":"BY",
    "name:bel_x_preferred":[
        "\u0410\u043d\u0434\u0440\u0430\u043d\u044b"
    ],
    "name:und_x_variant":[
        "Androny"
    ],
    "wof:name":"Andrany",
    "wof:placetype":"locality"
},
  "geometry": {"coordinates":[31.3122,53.9804],"type":"Point"}
}