{
  "type": "Feature",
  "properties": {
    "gn:admin1_code":"7.0",
    "gn:asciiname":"Bocharovo",
    "gn:country_code":"BY",
    "gn:dem":193,
    "gn:feature_class":"P",
    "gn:feature_code":"PPL",
    "gn:name":"Bocharovo",
    "gn:population":0,
    "gn:timezone":"Europe/Minsk",
    "iso:country":"BY",
    "name:rus_x_preferred":[
        "\u0411\u043e\u0447\u0430\u0440\u043e\u0432\u043e"
    ],
    "wof:name":"Bocharovo",
    "wof:placetype":"locality"
},
  "geometry": {"coordinates":[29.5549,54.68600000000001],"type":"Point"}
}