{
  "type": "Feature",
  "properties": {
    "gn:admin1_code":"7.0",
    "gn:asciiname":"Zharnasyeki",
    "gn:country_code":"BY",
    "gn:dem":146,
    "gn:feature_class":"P",
    "gn:feature_code":"PPL",
    "gn:name":"Zharnasyeki",
    "gn:population":0,
    "gn:timezone":"Europe/Minsk",
    "iso:country":"BY",
    "name:bel_x_preferred":[
        "\u0416\u0430\u0440\u043d\u0430\u0441\u0435\u043a\u0456"
    ],
    "name:und_x_variant":[
        "Zhernoseki"
    ],
    "wof:name":"Zharnasyeki",
    "wof:placetype":"locality"
},
  "geometry": {"coordinates":[28.4784,55.4238],"type":"Point"}
}