{
  "type": "Feature",
  "properties": {
    "gn:admin1_code":"5.0",
    "gn:asciiname":"Novikovshchina",
    "gn:country_code":"BY",
    "gn:dem":248,
    "gn:feature_class":"P",
    "gn:feature_code":"PPL",
    "gn:name":"Novikovshchina",
    "gn:population":0,
    "gn:timezone":"Europe/Minsk",
    "iso:country":"BY",
    "name:rus_x_preferred":[
        "\u041d\u043e\u0432\u0438\u043a\u043e\u0432\u0449\u0438\u043d\u0430"
    ],
    "wof:name":"Novikovshchina",
    "wof:placetype":"locality"
},
  "geometry": {"coordinates":[26.8329,53.9222],"type":"Point"}
}