{
  "type": "Feature",
  "properties": {
    "gn:admin1_code":"3.0",
    "gn:asciiname":"Khlistovichi",
    "gn:country_code":"BY",
    "gn:dem":135,
    "gn:feature_class":"P",
    "gn:feature_code":"PPL",
    "gn:name":"Khlistovichi",
    "gn:population":0,
    "gn:timezone":"Europe/Minsk",
    "iso:country":"BY",
    "name:rus_x_preferred":[
        "\u0425\u043b\u0438\u0441\u0442\u043e\u0432\u0438\u0447\u0438"
    ],
    "wof:name":"Khlistovichi",
    "wof:placetype":"locality"
},
  "geometry": {"coordinates":[23.9733,53.5302],"type":"Point"}
}