{
  "type": "Feature",
  "properties": {
    "gn:admin1_code":"1.0",
    "gn:asciiname":"Amyal'naya",
    "gn:country_code":"BY",
    "gn:dem":148,
    "gn:feature_class":"P",
    "gn:feature_code":"PPL",
    "gn:name":"Amyal\u2019naya",
    "gn:population":0,
    "gn:timezone":"Europe/Minsk",
    "iso:country":"BY",
    "name:bel_x_preferred":[
        "\u0410\u043c\u044f\u043b\u044c\u043d\u0430\u044f"
    ],
    "name:rus_x_preferred":[
        "Omel\u2019naya"
    ],
    "name:und_x_variant":[
        "Omel\u2019no",
        "Amyal\u2019naya"
    ],
    "wof:name":"Amyal'naya",
    "wof:placetype":"locality"
},
  "geometry": {"coordinates":[25.7535,52.4766],"type":"Point"}
}