{
  "type": "Feature",
  "properties": {
    "gn:admin1_code":"7.0",
    "gn:asciiname":"Mikhnichi",
    "gn:country_code":"BY",
    "gn:dem":162,
    "gn:feature_class":"P",
    "gn:feature_code":"PPL",
    "gn:name":"Mikhnichi",
    "gn:population":0,
    "gn:timezone":"Europe/Minsk",
    "iso:country":"BY",
    "name:rus_x_preferred":[
        "\u041c\u0438\u0445\u043d\u0438\u0447\u0438"
    ],
    "name:und_x_variant":[
        "Michnicze",
        "Mikhniche",
        "Mikhnichi"
    ],
    "wof:name":"Mikhnichi",
    "wof:placetype":"locality"
},
  "geometry": {"coordinates":[26.9595,55.0798],"type":"Point"}
}