{
  "type": "Feature",
  "properties": {
    "gn:admin1_code":"3.0",
    "gn:asciiname":"Mizgiri",
    "gn:country_code":"BY",
    "gn:dem":164,
    "gn:feature_class":"P",
    "gn:feature_code":"PPL",
    "gn:name":"Mizgiri",
    "gn:population":0,
    "gn:timezone":"Europe/Minsk",
    "iso:country":"BY",
    "name:rus_x_preferred":[
        "\u041c\u0438\u0437\u0433\u0438\u0440\u0438"
    ],
    "wof:name":"Mizgiri",
    "wof:placetype":"locality"
},
  "geometry": {"coordinates":[25.0729,52.8686],"type":"Point"}
}