{
  "type": "Feature",
  "properties": {
    "gn:admin1_code":"3.0",
    "gn:asciiname":"Kozlovshchina",
    "gn:country_code":"BY",
    "gn:dem":158,
    "gn:feature_class":"P",
    "gn:feature_code":"PPL",
    "gn:name":"Kozlovshchina",
    "gn:population":0,
    "gn:timezone":"Europe/Minsk",
    "iso:country":"BY",
    "name:bel_x_preferred":[
        "\u041a\u0430\u0437\u043b\u043e\u045e\u0448\u0447\u044b\u043d\u0430"
    ],
    "name:eng_x_preferred":[
        "Kozlovshchina"
    ],
    "name:rus_x_preferred":[
        "\u041a\u043e\u0437\u043b\u043e\u0432\u0449\u0438\u043d\u0430"
    ],
    "name:und_x_variant":[
        "Kozlovshchyzna",
        "Koz\u0142owszczyzna",
        "Kozlovshchina",
        "Kazlowshchyna"
    ],
    "wof:name":"Kozlovshchina",
    "wof:placetype":"locality"
},
  "geometry": {"coordinates":[25.2848,53.3176],"type":"Point"}
}