{
  "type": "Feature",
  "properties": {
    "gn:admin1_code":"7.0",
    "gn:asciiname":"Revyaki",
    "gn:country_code":"BY",
    "gn:dem":129,
    "gn:feature_class":"P",
    "gn:feature_code":"PPL",
    "gn:name":"Revyaki",
    "gn:population":0,
    "gn:timezone":"Europe/Minsk",
    "iso:country":"BY",
    "name:rus_x_preferred":[
        "\u0420\u0435\u0432\u044f\u043a\u0438"
    ],
    "wof:name":"Revyaki",
    "wof:placetype":"locality"
},
  "geometry": {"coordinates":[28.5488,55.4433],"type":"Point"}
}