{
  "type": "Feature",
  "properties": {
    "gn:admin1_code":"7.0",
    "gn:asciiname":"Ostapenki",
    "gn:country_code":"BY",
    "gn:dem":149,
    "gn:feature_class":"P",
    "gn:feature_code":"PPL",
    "gn:name":"Ostapenki",
    "gn:population":0,
    "gn:timezone":"Europe/Minsk",
    "iso:country":"BY",
    "name:rus_x_preferred":[
        "\u041e\u0441\u0442\u0430\u043f\u0435\u043d\u043a\u0438"
    ],
    "name:und_x_variant":[
        "Astapenki"
    ],
    "wof:name":"Ostapenki",
    "wof:placetype":"locality"
},
  "geometry": {"coordinates":[30.2681,54.8799],"type":"Point"}
}