{
  "type": "Feature",
  "properties": {
    "gn:admin1_code":"5.0",
    "gn:asciiname":"Triguzi",
    "gn:country_code":"BY",
    "gn:dem":171,
    "gn:feature_class":"P",
    "gn:feature_code":"PPL",
    "gn:name":"Triguzi",
    "gn:population":0,
    "gn:timezone":"Europe/Minsk",
    "iso:country":"BY",
    "name:rus_x_preferred":[
        "\u0422\u0440\u0438\u0433\u0443\u0437\u0438"
    ],
    "wof:name":"Triguzi",
    "wof:placetype":"locality"
},
  "geometry": {"coordinates":[27.103,54.3386],"type":"Point"}
}