{
  "type": "Feature",
  "properties": {
    "gn:admin1_code":"6.0",
    "gn:asciiname":"Masnoye",
    "gn:country_code":"BY",
    "gn:dem":159,
    "gn:feature_class":"P",
    "gn:feature_code":"PPL",
    "gn:name":"Masnoye",
    "gn:population":0,
    "gn:timezone":"Europe/Minsk",
    "iso:country":"BY",
    "name:rus_x_preferred":[
        "\u041c\u0430\u0441\u043d\u043e\u0435"
    ],
    "wof:name":"Masnoye",
    "wof:placetype":"locality"
},
  "geometry": {"coordinates":[29.0261,53.569],"type":"Point"}
}