{
  "type": "Feature",
  "properties": {
    "gn:admin1_code":"1.0",
    "gn:asciiname":"Gritsevichi",
    "gn:country_code":"BY",
    "gn:dem":143,
    "gn:feature_class":"P",
    "gn:feature_code":"PPL",
    "gn:name":"Gritsevichi",
    "gn:population":0,
    "gn:timezone":"Europe/Minsk",
    "iso:country":"BY",
    "name:rus_x_preferred":[
        "\u0413\u0440\u0438\u0446\u0435\u0432\u0438\u0447\u0438"
    ],
    "wof:name":"Gritsevichi",
    "wof:placetype":"locality"
},
  "geometry": {"coordinates":[24.0502,52.2291],"type":"Point"}
}