{
  "type": "Feature",
  "properties": {
    "gn:admin1_code":"6.0",
    "gn:asciiname":"Nyasyata",
    "gn:country_code":"BY",
    "gn:dem":150,
    "gn:feature_class":"P",
    "gn:feature_code":"PPL",
    "gn:name":"Nyasyata",
    "gn:population":0,
    "gn:timezone":"Europe/Minsk",
    "iso:country":"BY",
    "name:bel_x_preferred":[
        "\u041d\u044f\u0441\u044f\u0442\u0430"
    ],
    "name:eng_x_preferred":[
        "Nesyata"
    ],
    "name:rus_x_preferred":[
        "\u041d\u0435\u0441\u044f\u0442\u0430"
    ],
    "name:und_x_variant":[
        "Neseta",
        "Nyasyata"
    ],
    "wof:name":"Nyasyata",
    "wof:placetype":"locality"
},
  "geometry": {"coordinates":[29.2263,53.48],"type":"Point"}
}