{
  "type": "Feature",
  "properties": {
    "gn:admin1_code":"5.0",
    "gn:asciiname":"Skorobogatovshchina",
    "gn:country_code":"BY",
    "gn:dem":294,
    "gn:feature_class":"P",
    "gn:feature_code":"PPL",
    "gn:name":"Skorobogatovshchina",
    "gn:population":0,
    "gn:timezone":"Europe/Minsk",
    "iso:country":"BY",
    "name:rus_x_preferred":[
        "\u0421\u043a\u043e\u0440\u043e\u0431\u043e\u0433\u0430\u0442\u043e\u0432\u0449\u0438\u043d\u0430"
    ],
    "wof:name":"Skorobogatovshchina",
    "wof:placetype":"locality"
},
  "geometry": {"coordinates":[27.0066,53.8462],"type":"Point"}
}