{
  "type": "Feature",
  "properties": {
    "gn:admin1_code":"2.0",
    "gn:asciiname":"Groza",
    "gn:country_code":"BY",
    "gn:dem":145,
    "gn:feature_class":"P",
    "gn:feature_code":"PPL",
    "gn:name":"Groza",
    "gn:population":0,
    "gn:timezone":"Europe/Minsk",
    "iso:country":"BY",
    "name:rus_x_preferred":[
        "\u0413\u0440\u043e\u0437\u0430"
    ],
    "wof:name":"Groza",
    "wof:placetype":"locality"
},
  "geometry": {"coordinates":[31.2322,52.3195],"type":"Point"}
}