{
  "type": "Feature",
  "properties": {
    "gn:admin1_code":"1.0",
    "gn:asciiname":"Zhdanki",
    "gn:country_code":"BY",
    "gn:dem":139,
    "gn:feature_class":"P",
    "gn:feature_code":"PPL",
    "gn:name":"Zhdanki",
    "gn:population":0,
    "gn:timezone":"Europe/Minsk",
    "iso:country":"BY",
    "name:rus_x_preferred":[
        "\u0416\u0434\u0430\u043d\u043a\u0438"
    ],
    "wof:name":"Zhdanki",
    "wof:placetype":"locality"
},
  "geometry": {"coordinates":[23.8718,52.4342],"type":"Point"}
}