{
  "type": "Feature",
  "properties": {
    "gn:admin1_code":"3.0",
    "gn:asciiname":"Chernyavka",
    "gn:country_code":"BY",
    "gn:dem":146,
    "gn:feature_class":"P",
    "gn:feature_code":"PPL",
    "gn:name":"Chernyavka",
    "gn:population":0,
    "gn:timezone":"Europe/Minsk",
    "iso:country":"BY",
    "name:rus_x_preferred":[
        "\u0427\u0435\u0440\u043d\u044f\u0432\u043a\u0430"
    ],
    "wof:name":"Chernyavka",
    "wof:placetype":"locality"
},
  "geometry": {"coordinates":[24.5445,53.7925],"type":"Point"}
}