{
  "type": "Feature",
  "properties": {
    "gn:admin1_code":"2.0",
    "gn:asciiname":"Galubitsa",
    "gn:country_code":"BY",
    "gn:dem":126,
    "gn:feature_class":"P",
    "gn:feature_code":"PPL",
    "gn:name":"Galubitsa",
    "gn:population":0,
    "gn:timezone":"Europe/Minsk",
    "iso:country":"BY",
    "name:bel_x_preferred":[
        "\u0413\u0430\u043b\u0443\u0431\u0456\u0446\u0430"
    ],
    "name:und_x_variant":[
        "Golubitsa"
    ],
    "wof:name":"Galubitsa",
    "wof:placetype":"locality"
},
  "geometry": {"coordinates":[28.289,52.1071],"type":"Point"}
}