{
  "type": "Feature",
  "properties": {
    "gn:admin1_code":"6.0",
    "gn:asciiname":"Podluzh'ye",
    "gn:country_code":"BY",
    "gn:dem":149,
    "gn:feature_class":"P",
    "gn:feature_code":"PPL",
    "gn:name":"Podluzh\u2019ye",
    "gn:population":0,
    "gn:timezone":"Europe/Minsk",
    "iso:country":"BY",
    "name:rus_x_preferred":[
        "\u041f\u043e\u0434\u043b\u0443\u0436\u044c\u0435"
    ],
    "name:und_x_variant":[
        "Podluzh\u2019ye"
    ],
    "wof:name":"Podluzh'ye",
    "wof:placetype":"locality"
},
  "geometry": {"coordinates":[29.8351,53.4562],"type":"Point"}
}