{
  "type": "Feature",
  "properties": {
    "gn:admin1_code":"2.0",
    "gn:asciiname":"Kirovka",
    "gn:country_code":"BY",
    "gn:dem":130,
    "gn:feature_class":"P",
    "gn:feature_code":"PPL",
    "gn:name":"Kirovka",
    "gn:population":0,
    "gn:timezone":"Europe/Minsk",
    "iso:country":"BY",
    "name:aze_x_preferred":[
        "Kirovka"
    ],
    "name:ceb_x_preferred":[
        "Kirovka"
    ],
    "name:rus_x_preferred":[
        "\u041a\u0438\u0440\u043e\u0432\u043a\u0430"
    ],
    "name:swe_x_preferred":[
        "Kirovka"
    ],
    "wof:name":"Kirovka",
    "wof:placetype":"locality"
},
  "geometry": {"coordinates":[30.4445,52.3252],"type":"Point"}
}