{
  "type": "Feature",
  "properties": {
    "gn:admin1_code":"6.0",
    "gn:asciiname":"Byelaya Dubrova",
    "gn:country_code":"BY",
    "gn:dem":151,
    "gn:feature_class":"P",
    "gn:feature_code":"PPL",
    "gn:name":"Byelaya Dubrova",
    "gn:population":0,
    "gn:timezone":"Europe/Minsk",
    "iso:country":"BY",
    "name:bel_x_preferred":[
        "\u0411\u0435\u043b\u0430\u044f \u0414\u0443\u0431\u0440\u043e\u0432\u0430"
    ],
    "name:eng_x_preferred":[
        "Belaya Dubrova"
    ],
    "name:rus_x_preferred":[
        "\u0411\u0435\u043b.\u0434\u0443\u0431\u0440\u043e\u0432\u0430"
    ],
    "name:und_x_variant":[
        "Belaya Dubrovka",
        "Bel Dubrava",
        "Belaya Dubrava",
        "Belaya Dubrova",
        "Byelaya Dubrova"
    ],
    "wof:name":"Byelaya Dubrova",
    "wof:placetype":"locality"
},
  "geometry": {"coordinates":[31.9772,53.2504],"type":"Point"}
}