{
  "type": "Feature",
  "properties": {
    "gn:admin1_code":"5.0",
    "gn:asciiname":"Prudki",
    "gn:country_code":"BY",
    "gn:dem":215,
    "gn:feature_class":"P",
    "gn:feature_code":"PPL",
    "gn:name":"Prudki",
    "gn:population":0,
    "gn:timezone":"Europe/Minsk",
    "iso:country":"BY",
    "name:rus_x_preferred":[
        "\u041f\u0440\u0443\u0434\u043a\u0438"
    ],
    "wof:name":"Prudki",
    "wof:placetype":"locality"
},
  "geometry": {"coordinates":[27.7911,54.3142],"type":"Point"}
}