{
  "type": "Feature",
  "properties": {
    "gn:admin1_code":"5.0",
    "gn:asciiname":"Markhachevshchina",
    "gn:country_code":"BY",
    "gn:dem":167,
    "gn:feature_class":"P",
    "gn:feature_code":"PPL",
    "gn:name":"Markhach\u00ebvshchina",
    "gn:population":0,
    "gn:timezone":"Europe/Minsk",
    "iso:country":"BY",
    "name:rus_x_preferred":[
        "\u041c\u0430\u0440\u0445\u0430\u0447\u0451\u0432\u0449\u0438\u043d\u0430"
    ],
    "name:und_x_variant":[
        "Markhach\u00ebvshchina"
    ],
    "wof:name":"Markhachevshchina",
    "wof:placetype":"locality"
},
  "geometry": {"coordinates":[26.7162,53.4107],"type":"Point"}
}