{
  "type": "Feature",
  "properties": {
    "gn:admin1_code":"5.0",
    "gn:asciiname":"Budenichi",
    "gn:country_code":"BY",
    "gn:dem":211,
    "gn:feature_class":"P",
    "gn:feature_code":"PPL",
    "gn:name":"Budenichi",
    "gn:population":0,
    "gn:timezone":"Europe/Minsk",
    "iso:country":"BY",
    "name:rus_x_preferred":[
        "\u0411\u0443\u0434\u0435\u043d\u0438\u0447\u0438"
    ],
    "name:und_x_variant":[
        "Budzienicze",
        "Budenichi"
    ],
    "wof:name":"Budenichi",
    "wof:placetype":"locality"
},
  "geometry": {"coordinates":[27.639,54.504],"type":"Point"}
}