{
  "type": "Feature",
  "properties": {
    "gn:admin1_code":"7.0",
    "gn:asciiname":"Khromyye",
    "gn:country_code":"BY",
    "gn:dem":144,
    "gn:feature_class":"P",
    "gn:feature_code":"PPL",
    "gn:name":"Khromyye",
    "gn:population":0,
    "gn:timezone":"Europe/Minsk",
    "iso:country":"BY",
    "name:rus_x_preferred":[
        "\u0425\u0440\u043e\u043c\u044b\u0435"
    ],
    "wof:name":"Khromyye",
    "wof:placetype":"locality"
},
  "geometry": {"coordinates":[27.6108,55.2502],"type":"Point"}
}