{
  "type": "Feature",
  "properties": {
    "gn:admin1_code":"6.0",
    "gn:asciiname":"Stupeni",
    "gn:country_code":"BY",
    "gn:dem":144,
    "gn:feature_class":"P",
    "gn:feature_code":"PPL",
    "gn:name":"Stupeni",
    "gn:population":0,
    "gn:timezone":"Europe/Minsk",
    "iso:country":"BY",
    "name:rus_x_preferred":[
        "\u0421\u0442\u0443\u043f\u0435\u043d\u0438"
    ],
    "wof:name":"Stupeni",
    "wof:placetype":"locality"
},
  "geometry": {"coordinates":[29.3745,53.0654],"type":"Point"}
}