{
  "type": "Feature",
  "properties": {
    "gn:admin1_code":"5.0",
    "gn:asciiname":"Tsesino",
    "gn:country_code":"BY",
    "gn:dem":194,
    "gn:feature_class":"P",
    "gn:feature_code":"PPL",
    "gn:name":"Tsesino",
    "gn:population":0,
    "gn:timezone":"Europe/Minsk",
    "iso:country":"BY",
    "name:rus_x_preferred":[
        "\u0426\u0435\u0441\u0438\u043d\u043e"
    ],
    "wof:name":"Tsesino",
    "wof:placetype":"locality"
},
  "geometry": {"coordinates":[27.6505,53.7655],"type":"Point"}
}