{
  "type": "Feature",
  "properties": {
    "gn:admin1_code":"6.0",
    "gn:asciiname":"Krivaya Niva",
    "gn:country_code":"BY",
    "gn:dem":167,
    "gn:feature_class":"P",
    "gn:feature_code":"PPL",
    "gn:name":"Krivaya Niva",
    "gn:population":0,
    "gn:timezone":"Europe/Minsk",
    "iso:country":"BY",
    "name:rus_x_preferred":[
        "\u041a\u0440\u0438\u0432\u0430\u044f \u041d\u0438\u0432\u0430"
    ],
    "wof:name":"Krivaya Niva",
    "wof:placetype":"locality"
},
  "geometry": {"coordinates":[31.8378,53.3515],"type":"Point"}
}