{
  "type": "Feature",
  "properties": {
    "gn:admin1_code":"0.0",
    "gn:asciiname":"Novyy Kholoblin",
    "gn:country_code":"BY",
    "gn:dem":156,
    "gn:feature_class":"P",
    "gn:feature_code":"PPL",
    "gn:name":"Novyy Kholoblin",
    "gn:population":0,
    "gn:timezone":"Europe/Minsk",
    "iso:country":"BY",
    "wof:name":"Novyy Kholoblin",
    "wof:placetype":"locality"
},
  "geometry": {"coordinates":[31.53333,53.68333000000001],"type":"Point"}
}