{
  "type": "Feature",
  "properties": {
    "gn:admin1_code":"2.0",
    "gn:asciiname":"Shcherbovka",
    "gn:country_code":"BY",
    "gn:dem":133,
    "gn:feature_class":"P",
    "gn:feature_code":"PPL",
    "gn:name":"Shcherbovka",
    "gn:population":0,
    "gn:timezone":"Europe/Minsk",
    "iso:country":"BY",
    "name:rus_x_preferred":[
        "\u0429\u0435\u0440\u0431\u043e\u0432\u043a\u0430"
    ],
    "wof:name":"Shcherbovka",
    "wof:placetype":"locality"
},
  "geometry": {"coordinates":[30.699,52.3856],"type":"Point"}
}