{
  "type": "Feature",
  "properties": {
    "gn:admin1_code":"3.0",
    "gn:asciiname":"Markovichi",
    "gn:country_code":"BY",
    "gn:dem":172,
    "gn:feature_class":"P",
    "gn:feature_code":"PPL",
    "gn:name":"Markovichi",
    "gn:population":0,
    "gn:timezone":"Europe/Minsk",
    "iso:country":"BY",
    "name:bel_x_preferred":[
        "Markavichy"
    ],
    "name:bel_x_variant":[
        "\u041c\u0430\u0440\u043a\u0430\u0432\u0456\u0447\u044b"
    ],
    "name:rus_x_preferred":[
        "\u041c\u0430\u0440\u043a\u043e\u0432\u0438\u0447\u0438"
    ],
    "wof:name":"Markovichi",
    "wof:placetype":"locality"
},
  "geometry": {"coordinates":[25.4477,53.2319],"type":"Point"}
}