{
  "type": "Feature",
  "properties": {
    "gn:admin1_code":"2.0",
    "gn:asciiname":"Rudnya-Dudichskaya",
    "gn:country_code":"BY",
    "gn:dem":125,
    "gn:feature_class":"P",
    "gn:feature_code":"PPL",
    "gn:name":"Rudnya-Dudichskaya",
    "gn:population":0,
    "gn:timezone":"Europe/Minsk",
    "iso:country":"BY",
    "name:rus_x_preferred":[
        "\u0420\u0443\u0434\u043d\u044f-\u0414\u0443\u0434\u0438\u0447\u0441\u043a\u0430\u044f"
    ],
    "wof:name":"Rudnya-Dudichskaya",
    "wof:placetype":"locality"
},
  "geometry": {"coordinates":[30.8413,52.7524],"type":"Point"}
}