{
  "type": "Feature",
  "properties": {
    "gn:admin1_code":"6.0",
    "gn:asciiname":"Sorochino",
    "gn:country_code":"BY",
    "gn:dem":148,
    "gn:feature_class":"P",
    "gn:feature_code":"PPL",
    "gn:name":"Sorochino",
    "gn:population":0,
    "gn:timezone":"Europe/Minsk",
    "iso:country":"BY",
    "name:rus_x_preferred":[
        "\u0421\u043e\u0440\u043e\u0447\u0438\u043d\u043e"
    ],
    "wof:name":"Sorochino",
    "wof:placetype":"locality"
},
  "geometry": {"coordinates":[30.2244,53.6094],"type":"Point"}
}