{
  "type": "Feature",
  "properties": {
    "gn:admin1_code":"5.0",
    "gn:asciiname":"Lukovo",
    "gn:country_code":"BY",
    "gn:dem":215,
    "gn:feature_class":"P",
    "gn:feature_code":"PPL",
    "gn:name":"Lukovo",
    "gn:population":0,
    "gn:timezone":"Europe/Minsk",
    "iso:country":"BY",
    "name:bel_x_preferred":[
        "\u041b\u0443\u043a\u0430\u0432\u0430"
    ],
    "name:bos_x_preferred":[
        "Lukovo"
    ],
    "name:ceb_x_preferred":[
        "Lukovo"
    ],
    "name:deu_x_preferred":[
        "Lukovo"
    ],
    "name:fra_x_preferred":[
        "Lukovo"
    ],
    "name:hrv_x_preferred":[
        "Lukovo"
    ],
    "name:hun_x_preferred":[
        "Lukovo"
    ],
    "name:nld_x_preferred":[
        "Lukovo"
    ],
    "name:rus_x_preferred":[
        "\u041b\u0443\u043a\u043e\u0432\u043e"
    ],
    "name:slv_x_preferred":[
        "Lukovo"
    ],
    "name:swe_x_preferred":[
        "Lukovo"
    ],
    "name:ukr_x_preferred":[
        "\u041b\u0443\u043a\u043e\u0432\u0435"
    ],
    "wof:name":"Lukovo",
    "wof:placetype":"locality"
},
  "geometry": {"coordinates":[28.0115,53.8488],"type":"Point"}
}