{
  "type": "Feature",
  "properties": {
    "gn:admin1_code":"2.0",
    "gn:asciiname":"Kazyaluzhzha",
    "gn:country_code":"BY",
    "gn:dem":136,
    "gn:feature_class":"P",
    "gn:feature_code":"PPL",
    "gn:name":"Kazyaluzhzha",
    "gn:population":0,
    "gn:timezone":"Europe/Minsk",
    "iso:country":"BY",
    "name:bel_x_preferred":[
        "\u041a\u0430\u0437\u044f\u043b\u0443\u0436\u0436\u0430"
    ],
    "name:rus_x_preferred":[
        "Kozeluzh\u2019ye"
    ],
    "wof:name":"Kazyaluzhzha",
    "wof:placetype":"locality"
},
  "geometry": {"coordinates":[29.9019,51.8998],"type":"Point"}
}