{
  "type": "Feature",
  "properties": {
    "gn:admin1_code":"2.0",
    "gn:asciiname":"Vikov",
    "gn:country_code":"BY",
    "gn:dem":132,
    "gn:feature_class":"P",
    "gn:feature_code":"PPL",
    "gn:name":"Vikov",
    "gn:population":0,
    "gn:timezone":"Europe/Minsk",
    "iso:country":"BY",
    "name:rus_x_preferred":[
        "\u0412\u0438\u043a\u043e\u0432"
    ],
    "name:und_x_variant":[
        "Vikovo"
    ],
    "wof:name":"Vikov",
    "wof:placetype":"locality"
},
  "geometry": {"coordinates":[30.1126,53.0603],"type":"Point"}
}