{
  "type": "Feature",
  "properties": {
    "gn:admin1_code":"1.0",
    "gn:asciiname":"Bekeshevka",
    "gn:country_code":"BY",
    "gn:dem":160,
    "gn:feature_class":"P",
    "gn:feature_code":"PPL",
    "gn:name":"Bekeshevka",
    "gn:population":0,
    "gn:timezone":"Europe/Minsk",
    "iso:country":"BY",
    "name:rus_x_preferred":[
        "\u0411\u0435\u043a\u0435\u0448\u0435\u0432\u043a\u0430"
    ],
    "wof:name":"Bekeshevka",
    "wof:placetype":"locality"
},
  "geometry": {"coordinates":[24.2973,52.4998],"type":"Point"}
}