{
  "type": "Feature",
  "properties": {
    "gn:admin1_code":"3.0",
    "gn:asciiname":"Malyshchina",
    "gn:country_code":"BY",
    "gn:dem":143,
    "gn:feature_class":"P",
    "gn:feature_code":"PPL",
    "gn:name":"Malyshchina",
    "gn:population":0,
    "gn:timezone":"Europe/Minsk",
    "iso:country":"BY",
    "name:rus_x_preferred":[
        "\u041c\u0430\u043b\u044b\u0449\u0438\u043d\u0430"
    ],
    "name:und_x_variant":[
        "Malyshchino"
    ],
    "wof:name":"Malyshchina",
    "wof:placetype":"locality"
},
  "geometry": {"coordinates":[23.8694,53.7108],"type":"Point"}
}