{
  "type": "Feature",
  "properties": {
    "gn:admin1_code":"0.0",
    "gn:asciiname":"Lelyushovtsy",
    "gn:cc2":"BY",
    "gn:country_code":"BY",
    "gn:dem":234,
    "gn:feature_class":"P",
    "gn:feature_code":"PPL",
    "gn:name":"Lelyushovtsy",
    "gn:population":0,
    "gn:timezone":"Europe/Minsk",
    "iso:country":"BY",
    "name:und_x_variant":[
        "Lelyushovtse",
        "Lelyushovtsy"
    ],
    "wof:name":"Lelyushovtsy",
    "wof:placetype":"locality"
},
  "geometry": {"coordinates":[24.86667000000001,50.71667],"type":"Point"}
}