{
  "type": "Feature",
  "properties": {
    "gn:admin1_code":"7.0",
    "gn:asciiname":"Babinavichy",
    "gn:country_code":"BY",
    "gn:dem":161,
    "gn:feature_class":"P",
    "gn:feature_code":"PPL",
    "gn:name":"Babinavichy",
    "gn:population":0,
    "gn:timezone":"Europe/Minsk",
    "iso:country":"BY",
    "name:bel_x_preferred":[
        "\u0411\u0430\u0431\u0456\u043d\u0430\u0432\u0456\u0447\u044b"
    ],
    "name:eng_x_preferred":[
        "Babinovichi"
    ],
    "name:rus_x_preferred":[
        "\u0411\u0430\u0431\u0438\u043d\u043e\u0432\u0438\u0447\u0438"
    ],
    "name:und_x_variant":[
        "Babinovichi",
        "Babinavichy"
    ],
    "wof:name":"Babinavichy",
    "wof:placetype":"locality"
},
  "geometry": {"coordinates":[30.5725,54.8351],"type":"Point"}
}