{
  "type": "Feature",
  "properties": {
    "gn:admin1_code":"7.0",
    "gn:asciiname":"Babinavichy",
    "gn:country_code":"BY",
    "gn:dem":161,
    "gn:feature_class":"P",
    "gn:feature_code":"PPL",
    "gn:name":"Babinavichy",
    "gn:population":0,
    "gn:timezone":"Europe/Minsk",
    "iso:country":"BY",
    "name:bel_x_preferred":[
        "\u0411\u0430\u0431\u0456\u043d\u0430\u0432\u0456\u0447\u044b"
    ],
    "name:ceb_x_preferred":[
        "Babinavichy"
    ],
    "name:eng_x_preferred":[
        "Babinovichi"
    ],
    "name:fra_x_preferred":[
        "Babinavichy"
    ],
    "name:heb_x_preferred":[
        "\u05d1\u05d1\u05d9\u05e0\u05d5\u05d1\u05d9\u05e6'\u05d9"
    ],
    "name:jpn_x_preferred":[
        "\u30d0\u30d3\u30ca\u30f4\u30a3\u30fc\u30c1"
    ],
    "name:kor_x_preferred":[
        "\ubc14\ube44\ub098\ube44\uce58"
    ],
    "name:rus_x_preferred":[
        "\u0411\u0430\u0431\u0438\u043d\u043e\u0432\u0438\u0447\u0438"
    ],
    "name:spa_x_preferred":[
        "Babinavichy"
    ],
    "name:swe_x_preferred":[
        "Babinavichy"
    ],
    "name:ukr_x_preferred":[
        "\u0411\u0430\u0431\u0438\u043d\u043e\u0432\u0438\u0447\u0456"
    ],
    "wof:name":"Babinavichy",
    "wof:placetype":"locality"
},
  "geometry": {"coordinates":[30.5725,54.8351],"type":"Point"}
}