{
  "type": "Feature",
  "properties": {
    "gn:admin1_code":"5.0",
    "gn:asciiname":"Novaya Niva",
    "gn:country_code":"BY",
    "gn:dem":174,
    "gn:feature_class":"P",
    "gn:feature_code":"PPL",
    "gn:name":"Novaya Niva",
    "gn:population":0,
    "gn:timezone":"Europe/Minsk",
    "iso:country":"BY",
    "name:eng_x_preferred":[
        "Novaya Niva"
    ],
    "name:rus_x_preferred":[
        "\u041d\u043e\u0432.\u041d\u0438\u0432\u0430"
    ],
    "name:rus_x_variant":[
        "\u041d\u043e\u0432\u0430\u044f \u041d\u0438\u0432\u0430"
    ],
    "wof:name":"Novaya Niva",
    "wof:placetype":"locality"
},
  "geometry": {"coordinates":[28.6652,53.7365],"type":"Point"}
}