{
  "type": "Feature",
  "properties": {
    "gn:admin1_code":"5.0",
    "gn:asciiname":"Treskovshchina",
    "gn:country_code":"BY",
    "gn:dem":270,
    "gn:feature_class":"P",
    "gn:feature_code":"PPL",
    "gn:name":"Treskovshchina",
    "gn:population":0,
    "gn:timezone":"Europe/Minsk",
    "iso:country":"BY",
    "name:rus_x_preferred":[
        "\u0422\u0440\u0435\u0441\u043a\u043e\u0432\u0449\u0438\u043d\u0430"
    ],
    "wof:name":"Treskovshchina",
    "wof:placetype":"locality"
},
  "geometry": {"coordinates":[27.0801,53.9018],"type":"Point"}
}