{
  "type": "Feature",
  "properties": {
    "gn:admin1_code":"1.0",
    "gn:asciiname":"Baranki",
    "gn:country_code":"BY",
    "gn:dem":142,
    "gn:feature_class":"P",
    "gn:feature_code":"PPL",
    "gn:name":"Baranki",
    "gn:population":0,
    "gn:timezone":"Europe/Minsk",
    "iso:country":"BY",
    "name:lit_x_preferred":[
        "Barankai"
    ],
    "name:pol_x_preferred":[
        "Baranki"
    ],
    "name:rus_x_preferred":[
        "Bol\u2019shiye Baranki"
    ],
    "name:rus_x_variant":[
        "\u0411\u0430\u0440\u0430\u043d\u043a\u0438"
    ],
    "name:ukr_x_preferred":[
        "\u0411\u0430\u0440\u0430\u043d\u043a\u0456"
    ],
    "name:und_x_variant":[
        "Vel\u2019ke-Baranki",
        "Velikiye Baranki",
        "Baranki"
    ],
    "wof:name":"Baranki",
    "wof:placetype":"locality"
},
  "geometry": {"coordinates":[23.755,52.3538],"type":"Point"}
}