{
  "type": "Feature",
  "properties": {
    "gn:admin1_code":"1.0",
    "gn:asciiname":"Podrech'ye",
    "gn:country_code":"BY",
    "gn:dem":144,
    "gn:feature_class":"P",
    "gn:feature_code":"PPL",
    "gn:name":"Podrech\u2019ye",
    "gn:population":0,
    "gn:timezone":"Europe/Minsk",
    "iso:country":"BY",
    "name:rus_x_preferred":[
        "\u041f\u043e\u0434\u0440\u0435\u0447\u044c\u0435"
    ],
    "name:und_x_variant":[
        "Podrech\u2019ye"
    ],
    "wof:name":"Podrech'ye",
    "wof:placetype":"locality"
},
  "geometry": {"coordinates":[23.9678,52.2535],"type":"Point"}
}