{
  "type": "Feature",
  "properties": {
    "gn:admin1_code":"2.0",
    "gn:asciiname":"Pyeravaloka",
    "gn:country_code":"BY",
    "gn:dem":128,
    "gn:feature_class":"P",
    "gn:feature_code":"PPL",
    "gn:name":"Pyeravaloka",
    "gn:population":0,
    "gn:timezone":"Europe/Minsk",
    "iso:country":"BY",
    "name:bel_x_preferred":[
        "\u041f\u0435\u0440\u0430\u0432\u0430\u043b\u043e\u043a\u0430"
    ],
    "name:eng_x_preferred":[
        "Perevoloka"
    ],
    "name:rus_x_preferred":[
        "\u041f\u0435\u0440\u0435\u0432\u043e\u043b\u043e\u043a\u0430"
    ],
    "wof:name":"Pyeravaloka",
    "wof:placetype":"locality"
},
  "geometry": {"coordinates":[30.2103,52.2085],"type":"Point"}
}