{
  "type": "Feature",
  "properties": {
    "gn:admin1_code":"5.0",
    "gn:asciiname":"Zaduben'ye",
    "gn:country_code":"BY",
    "gn:dem":173,
    "gn:feature_class":"P",
    "gn:feature_code":"PPL",
    "gn:name":"Zaduben\u2019ye",
    "gn:population":0,
    "gn:timezone":"Europe/Minsk",
    "iso:country":"BY",
    "name:rus_x_preferred":[
        "\u0417\u0430\u0434\u0443\u0431\u0435\u043d\u044c\u0435"
    ],
    "name:und_x_variant":[
        "Zaduben\u2019ye"
    ],
    "wof:name":"Zaduben'ye",
    "wof:placetype":"locality"
},
  "geometry": {"coordinates":[27.2756,54.7578],"type":"Point"}
}