{
  "type": "Feature",
  "properties": {
    "gn:admin1_code":"6.0",
    "gn:asciiname":"Azarovka",
    "gn:country_code":"BY",
    "gn:dem":179,
    "gn:feature_class":"P",
    "gn:feature_code":"PPL",
    "gn:name":"Azarovka",
    "gn:population":0,
    "gn:timezone":"Europe/Minsk",
    "iso:country":"BY",
    "name:rus_x_preferred":[
        "\u0410\u0437\u0430\u0440\u043e\u0432\u043a\u0430"
    ],
    "wof:name":"Azarovka",
    "wof:placetype":"locality"
},
  "geometry": {"coordinates":[30.1108,53.9989],"type":"Point"}
}