{
  "type": "Feature",
  "properties": {
    "gn:admin1_code":"5.0",
    "gn:asciiname":"Malyye Besyady",
    "gn:country_code":"BY",
    "gn:dem":254,
    "gn:feature_class":"P",
    "gn:feature_code":"PPL",
    "gn:name":"Malyye Besyady",
    "gn:population":0,
    "gn:timezone":"Europe/Minsk",
    "iso:country":"BY",
    "name:rus_x_preferred":[
        "\u041c\u0430\u043b\u044b\u0435 \u0411\u0435\u0441\u044f\u0434\u044b"
    ],
    "name:und_x_variant":[
        "Biesiady",
        "Malyye Besyady"
    ],
    "wof:name":"Malyye Besyady",
    "wof:placetype":"locality"
},
  "geometry": {"coordinates":[27.491,54.2351],"type":"Point"}
}