{
  "type": "Feature",
  "properties": {
    "gn:admin1_code":"6.0",
    "gn:asciiname":"Kovalevka Vtoraya",
    "gn:country_code":"BY",
    "gn:dem":189,
    "gn:feature_class":"P",
    "gn:feature_code":"PPL",
    "gn:name":"Kovalevka Vtoraya",
    "gn:population":0,
    "gn:timezone":"Europe/Minsk",
    "iso:country":"BY",
    "wof:name":"Kovalevka Vtoraya",
    "wof:placetype":"locality"
},
  "geometry": {"coordinates":[32.31972,53.73472],"type":"Point"}
}