{
  "type": "Feature",
  "properties": {
    "gn:admin1_code":"6.0",
    "gn:asciiname":"Krasnyy Bereg",
    "gn:country_code":"BY",
    "gn:dem":147,
    "gn:feature_class":"P",
    "gn:feature_code":"PPL",
    "gn:name":"Krasnyy Bereg",
    "gn:population":2359,
    "gn:timezone":"Europe/Minsk",
    "iso:country":"BY",
    "name:rus_x_preferred":[
        "\u041a\u0440\u0430\u0441\u043d\u044b\u0439 \u0411\u0435\u0440\u0435\u0433"
    ],
    "name:und_x_variant":[
        "Krasny Bereg",
        "Krasnyy Bereg"
    ],
    "wof:name":"Krasnyy Bereg",
    "wof:placetype":"locality",
    "wof:population":2359
},
  "geometry": {"coordinates":[30.1929,53.3291],"type":"Point"}
}