{
  "type": "Feature",
  "properties": {
    "gn:admin1_code":"5.0",
    "gn:asciiname":"Bluzhskiy Bor",
    "gn:country_code":"BY",
    "gn:dem":156,
    "gn:feature_class":"P",
    "gn:feature_code":"PPL",
    "gn:name":"Bluzhskiy Bor",
    "gn:population":0,
    "gn:timezone":"Europe/Minsk",
    "iso:country":"BY",
    "name:rus_x_preferred":[
        "\u0411\u043b\u0443\u0436\u0441\u043a\u0438\u0439 \u0411\u043e\u0440"
    ],
    "wof:name":"Bluzhskiy Bor",
    "wof:placetype":"locality"
},
  "geometry": {"coordinates":[28.3404,53.4545],"type":"Point"}
}