{
  "type": "Feature",
  "properties": {
    "gn:admin1_code":"7.0",
    "gn:asciiname":"Yukovo",
    "gn:country_code":"BY",
    "gn:dem":207,
    "gn:feature_class":"P",
    "gn:feature_code":"PPL",
    "gn:name":"Yukovo",
    "gn:population":0,
    "gn:timezone":"Europe/Minsk",
    "iso:country":"BY",
    "name:rus_x_preferred":[
        "\u042e\u043a\u043e\u0432\u043e"
    ],
    "wof:name":"Yukovo",
    "wof:placetype":"locality"
},
  "geometry": {"coordinates":[30.9159,54.5458],"type":"Point"}
}