{
  "type": "Feature",
  "properties": {
    "gn:admin1_code":"1.0",
    "gn:asciiname":"Obrub",
    "gn:country_code":"BY",
    "gn:dem":156,
    "gn:feature_class":"P",
    "gn:feature_code":"PPL",
    "gn:name":"Obrub",
    "gn:population":0,
    "gn:timezone":"Europe/Minsk",
    "iso:country":"BY",
    "name:rus_x_preferred":[
        "\u041e\u0431\u0440\u0443\u0431"
    ],
    "name:und_x_variant":[
        "Obrab"
    ],
    "wof:name":"Obrub",
    "wof:placetype":"locality"
},
  "geometry": {"coordinates":[24.2912,52.5512],"type":"Point"}
}