{
  "type": "Feature",
  "properties": {
    "gn:admin1_code":"7.0",
    "gn:asciiname":"Pustyn'ki",
    "gn:country_code":"BY",
    "gn:dem":144,
    "gn:feature_class":"P",
    "gn:feature_code":"PPL",
    "gn:name":"Pustyn\u2019ki",
    "gn:population":0,
    "gn:timezone":"Europe/Minsk",
    "iso:country":"BY",
    "name:rus_x_preferred":[
        "\u041f\u0443\u0441\u0442\u044b\u043d\u044c\u043a\u0438"
    ],
    "name:und_x_variant":[
        "Pustyn\u2019ki"
    ],
    "wof:name":"Pustyn'ki",
    "wof:placetype":"locality"
},
  "geometry": {"coordinates":[27.5245,55.7346],"type":"Point"}
}