{
  "type": "Feature",
  "properties": {
    "gn:admin1_code":"5.0",
    "gn:asciiname":"Kuranyets",
    "gn:country_code":"BY",
    "gn:dem":173,
    "gn:feature_class":"P",
    "gn:feature_code":"PPL",
    "gn:name":"Kuranyets",
    "gn:population":0,
    "gn:timezone":"Europe/Minsk",
    "iso:country":"BY",
    "name:bel_x_preferred":[
        "\u041a\u0443\u0440\u0430\u043d\u0435\u0446"
    ],
    "name:eng_x_preferred":[
        "Kurenets"
    ],
    "name:rus_x_preferred":[
        "\u041a\u0443\u0440\u0435\u043d\u0435\u0446"
    ],
    "name:und_x_variant":[
        "Kuzhenets",
        "Kurzeniec",
        "Kurenets",
        "Kuranyets"
    ],
    "wof:name":"Kuranyets",
    "wof:placetype":"locality"
},
  "geometry": {"coordinates":[26.9585,54.56100000000001],"type":"Point"}
}