{
  "type": "Feature",
  "properties": {
    "gn:admin1_code":"1.0",
    "gn:asciiname":"Poselok Ptitsefabrika",
    "gn:country_code":"BY",
    "gn:dem":147,
    "gn:feature_class":"P",
    "gn:feature_code":"PPL",
    "gn:name":"Pos\u00eblok Ptitsefabrika",
    "gn:population":0,
    "gn:timezone":"Europe/Minsk",
    "iso:country":"BY",
    "name:rus_x_preferred":[
        "\u041f\u043e\u0441\u0451\u043b\u043e\u043a \u041f\u0442\u0438\u0446\u0435\u0444\u0430\u0431\u0440\u0438\u043a\u0430"
    ],
    "name:und_x_variant":[
        "Pos\u00eblok Ptitsefabrika"
    ],
    "wof:name":"Poselok Ptitsefabrika",
    "wof:placetype":"locality"
},
  "geometry": {"coordinates":[24.302,52.2358],"type":"Point"}
}