{
  "type": "Feature",
  "properties": {
    "gn:admin1_code":"5.0",
    "gn:asciiname":"Dolidovshchina",
    "gn:country_code":"BY",
    "gn:dem":168,
    "gn:feature_class":"P",
    "gn:feature_code":"PPL",
    "gn:name":"Dolidovshchina",
    "gn:population":0,
    "gn:timezone":"Europe/Minsk",
    "iso:country":"BY",
    "name:rus_x_preferred":[
        "\u0414\u043e\u043b\u0438\u0434\u043e\u0432\u0449\u0438\u043d\u0430"
    ],
    "wof:name":"Dolidovshchina",
    "wof:placetype":"locality"
},
  "geometry": {"coordinates":[27.8863,53.2842],"type":"Point"}
}