{
  "type": "Feature",
  "properties": {
    "gn:admin1_code":"3.0",
    "gn:asciiname":"Losi",
    "gn:country_code":"BY",
    "gn:dem":132,
    "gn:feature_class":"P",
    "gn:feature_code":"PPL",
    "gn:name":"Losi",
    "gn:population":0,
    "gn:timezone":"Europe/Minsk",
    "iso:country":"BY",
    "name:ceb_x_preferred":[
        "Losi"
    ],
    "name:deu_x_preferred":[
        "Losi"
    ],
    "name:ita_x_preferred":[
        "Losi"
    ],
    "name:rus_x_preferred":[
        "\u041b\u043e\u0441\u0438"
    ],
    "name:swe_x_preferred":[
        "Losi"
    ],
    "wof:name":"Losi",
    "wof:placetype":"locality"
},
  "geometry": {"coordinates":[26.1965,54.8496],"type":"Point"}
}