{
  "type": "Feature",
  "properties": {
    "gn:admin1_code":"2.0",
    "gn:asciiname":"Knyazhebor'ye",
    "gn:country_code":"BY",
    "gn:dem":137,
    "gn:feature_class":"P",
    "gn:feature_code":"PPL",
    "gn:name":"Knyazhebor\u2019ye",
    "gn:population":0,
    "gn:timezone":"Europe/Minsk",
    "iso:country":"BY",
    "name:rus_x_preferred":[
        "\u041a\u043d\u044f\u0436\u0435\u0431\u043e\u0440\u044c\u0435"
    ],
    "name:und_x_variant":[
        "Knyazhebor\u2019ye"
    ],
    "wof:name":"Knyazhebor'ye",
    "wof:placetype":"locality"
},
  "geometry": {"coordinates":[29.2371,51.802],"type":"Point"}
}