{
  "type": "Feature",
  "properties": {
    "gn:admin1_code":"7.0",
    "gn:asciiname":"Chervino",
    "gn:country_code":"BY",
    "gn:dem":186,
    "gn:feature_class":"P",
    "gn:feature_code":"PPL",
    "gn:name":"Chervino",
    "gn:population":0,
    "gn:timezone":"Europe/Minsk",
    "iso:country":"BY",
    "name:rus_x_preferred":[
        "\u0427\u0435\u0440\u0432\u0438\u043d\u043e"
    ],
    "name:und_x_variant":[
        "Cherven\u2019"
    ],
    "wof:name":"Chervino",
    "wof:placetype":"locality"
},
  "geometry": {"coordinates":[30.3213,54.4564],"type":"Point"}
}