{
  "type": "Feature",
  "properties": {
    "gn:admin1_code":"3.0",
    "gn:asciiname":"Bruzgi",
    "gn:country_code":"BY",
    "gn:dem":139,
    "gn:feature_class":"P",
    "gn:feature_code":"PPL",
    "gn:name":"Bruzgi",
    "gn:population":0,
    "gn:timezone":"Europe/Minsk",
    "iso:country":"BY",
    "name:bel_x_preferred":[
        "\u0411\u0440\u0443\u0437\u0433\u0456"
    ],
    "name:und_x_variant":[
        "Bryuzgi"
    ],
    "wof:name":"Bruzgi",
    "wof:placetype":"locality"
},
  "geometry": {"coordinates":[23.6867,53.5552],"type":"Point"}
}