{
  "type": "Feature",
  "properties": {
    "gn:admin1_code":"7.0",
    "gn:asciiname":"Kazaki",
    "gn:country_code":"BY",
    "gn:dem":178,
    "gn:feature_class":"P",
    "gn:feature_code":"PPL",
    "gn:name":"Kazaki",
    "gn:population":0,
    "gn:timezone":"Europe/Minsk",
    "iso:country":"BY",
    "name:ceb_x_preferred":[
        "Kazaki"
    ],
    "name:che_x_preferred":[
        "\u041a\u0430\u0437\u0430\u043a\u0438"
    ],
    "name:hye_x_preferred":[
        "\u053f\u0561\u0566\u0561\u056f\u056b"
    ],
    "name:rus_x_preferred":[
        "\u041a\u0430\u0437\u0430\u043a\u0438"
    ],
    "wof:name":"Kazaki",
    "wof:placetype":"locality"
},
  "geometry": {"coordinates":[30.2779,54.7951],"type":"Point"}
}