{
  "type": "Feature",
  "properties": {
    "gn:admin1_code":"6.0",
    "gn:asciiname":"Novoye Vil'yanovo",
    "gn:country_code":"BY",
    "gn:dem":184,
    "gn:feature_class":"P",
    "gn:feature_code":"PPL",
    "gn:name":"Novoye Vil\u2019yanovo",
    "gn:population":0,
    "gn:timezone":"Europe/Minsk",
    "iso:country":"BY",
    "name:rus_x_preferred":[
        "\u041d\u043e\u0432\u043e\u0435 \u0412\u0438\u043b\u044c\u044f\u043d\u043e\u0432\u043e"
    ],
    "name:und_x_variant":[
        "Novoye Vil\u2019yanovo"
    ],
    "wof:name":"Novoye Vil'yanovo",
    "wof:placetype":"locality"
},
  "geometry": {"coordinates":[30.6502,54.1671],"type":"Point"}
}