{
  "type": "Feature",
  "properties": {
    "gn:admin1_code":"6.0",
    "gn:asciiname":"Karowchyna",
    "gn:country_code":"BY",
    "gn:dem":186,
    "gn:feature_class":"P",
    "gn:feature_code":"PPL",
    "gn:name":"Karowchyna",
    "gn:population":0,
    "gn:timezone":"Europe/Minsk",
    "iso:country":"BY",
    "name:bel_x_preferred":[
        "\u041a\u0430\u0440\u043e\u045e\u0447\u044b\u043d\u0430"
    ],
    "name:und_x_variant":[
        "Korovchino"
    ],
    "wof:name":"Karowchyna",
    "wof:placetype":"locality"
},
  "geometry": {"coordinates":[30.8274,54.0463],"type":"Point"}
}