{
  "type": "Feature",
  "properties": {
    "gn:admin1_code":"2.0",
    "gn:asciiname":"Anastas'yevka",
    "gn:country_code":"BY",
    "gn:dem":153,
    "gn:feature_class":"P",
    "gn:feature_code":"PPL",
    "gn:name":"Anastas\u2019yevka",
    "gn:population":0,
    "gn:timezone":"Europe/Minsk",
    "iso:country":"BY",
    "name:ind_x_preferred":[
        "Anastas'yevka"
    ],
    "name:msa_x_preferred":[
        "Anastas'yevka"
    ],
    "name:rus_x_preferred":[
        "\u0410\u043d\u0430\u0441\u0442\u0430\u0441\u044c\u0435\u0432\u043a\u0430"
    ],
    "name:und_x_variant":[
        "Anastas\u2019yevka",
        "Nastas\u2019yevka"
    ],
    "wof:name":"Anastas'yevka",
    "wof:placetype":"locality"
},
  "geometry": {"coordinates":[30.5826,52.9171],"type":"Point"}
}