{
  "type": "Feature",
  "properties": {
    "gn:admin1_code":"5.0",
    "gn:asciiname":"Duboviki",
    "gn:country_code":"BY",
    "gn:dem":180,
    "gn:feature_class":"P",
    "gn:feature_code":"PPL",
    "gn:name":"Duboviki",
    "gn:population":0,
    "gn:timezone":"Europe/Minsk",
    "iso:country":"BY",
    "name:rus_x_preferred":[
        "\u0414\u0443\u0431\u043e\u0432\u0438\u043a\u0438"
    ],
    "wof:name":"Duboviki",
    "wof:placetype":"locality"
},
  "geometry": {"coordinates":[28.446,54.3516],"type":"Point"}
}