{
  "type": "Feature",
  "properties": {
    "gn:admin1_code":"1.0",
    "gn:asciiname":"Perkovichi",
    "gn:country_code":"BY",
    "gn:dem":163,
    "gn:feature_class":"P",
    "gn:feature_code":"PPL",
    "gn:name":"Perkovichi",
    "gn:population":0,
    "gn:timezone":"Europe/Minsk",
    "iso:country":"BY",
    "name:rus_x_preferred":[
        "\u041f\u0435\u0440\u043a\u043e\u0432\u0438\u0447\u0438"
    ],
    "wof:name":"Perkovichi",
    "wof:placetype":"locality"
},
  "geometry": {"coordinates":[23.5926,52.4098],"type":"Point"}
}