{
  "type": "Feature",
  "properties": {
    "gn:admin1_code":"7.0",
    "gn:asciiname":"Ilantsy",
    "gn:country_code":"BY",
    "gn:dem":150,
    "gn:feature_class":"P",
    "gn:feature_code":"PPL",
    "gn:name":"Ilantsy",
    "gn:population":0,
    "gn:timezone":"Europe/Minsk",
    "iso:country":"BY",
    "name:rus_x_preferred":[
        "\u0418\u043b\u0430\u043d\u0446\u044b"
    ],
    "wof:name":"Ilantsy",
    "wof:placetype":"locality"
},
  "geometry": {"coordinates":[26.841,55.6737],"type":"Point"}
}