{
  "type": "Feature",
  "properties": {
    "gn:admin1_code":"3.0",
    "gn:asciiname":"Slobodka",
    "gn:country_code":"BY",
    "gn:dem":208,
    "gn:feature_class":"P",
    "gn:feature_code":"PPL",
    "gn:name":"Slobodka",
    "gn:population":0,
    "gn:timezone":"Europe/Minsk",
    "iso:country":"BY",
    "name:bel_x_preferred":[
        "Slabodka"
    ],
    "name:bel_x_variant":[
        "\u0421\u043b\u0430\u0431\u043e\u0434\u043a\u0430"
    ],
    "name:rus_x_preferred":[
        "\u0421\u043b\u043e\u0431\u043e\u0434\u043a\u0430"
    ],
    "wof:name":"Slobodka",
    "wof:placetype":"locality"
},
  "geometry": {"coordinates":[25.8926,53.6167],"type":"Point"}
}