{
  "type": "Feature",
  "properties": {
    "gn:admin1_code":"7.0",
    "gn:asciiname":"Gvozdovo",
    "gn:country_code":"BY",
    "gn:dem":186,
    "gn:feature_class":"P",
    "gn:feature_code":"PPL",
    "gn:name":"Gvozdovo",
    "gn:population":0,
    "gn:timezone":"Europe/Minsk",
    "iso:country":"BY",
    "name:rus_x_preferred":[
        "\u0413\u0432\u043e\u0437\u0434\u043e\u0432\u043e"
    ],
    "name:und_x_variant":[
        "Gwozdowo",
        "Gvozdovo"
    ],
    "wof:name":"Gvozdovo",
    "wof:placetype":"locality"
},
  "geometry": {"coordinates":[27.8089,55.1742],"type":"Point"}
}