{
  "type": "Feature",
  "properties": {
    "gn:admin1_code":"5.0",
    "gn:asciiname":"Petrelevtsy",
    "gn:country_code":"BY",
    "gn:dem":182,
    "gn:feature_class":"P",
    "gn:feature_code":"PPL",
    "gn:name":"Petrelevtsy",
    "gn:population":0,
    "gn:timezone":"Europe/Minsk",
    "iso:country":"BY",
    "name:rus_x_preferred":[
        "\u041f\u0435\u0442\u0440\u0435\u043b\u0435\u0432\u0446\u044b"
    ],
    "name:und_x_variant":[
        "Petrolevo"
    ],
    "wof:name":"Petrelevtsy",
    "wof:placetype":"locality"
},
  "geometry": {"coordinates":[27.2634,54.9518],"type":"Point"}
}