{
  "type": "Feature",
  "properties": {
    "gn:admin1_code":"2.0",
    "gn:asciiname":"Azdzyelina",
    "gn:country_code":"BY",
    "gn:dem":129,
    "gn:feature_class":"P",
    "gn:feature_code":"PPL",
    "gn:name":"Azdzyelina",
    "gn:population":0,
    "gn:timezone":"Europe/Minsk",
    "iso:country":"BY",
    "name:bel_x_preferred":[
        "\u0410\u0437\u0434\u0437\u0435\u043b\u0456\u043d\u0430"
    ],
    "name:und_x_variant":[
        "Azdelin",
        "Azdelino"
    ],
    "wof:name":"Azdzyelina",
    "wof:placetype":"locality"
},
  "geometry": {"coordinates":[30.7443,52.5384],"type":"Point"}
}