{
  "type": "Feature",
  "properties": {
    "gn:admin1_code":"3.0",
    "gn:asciiname":"Glinno",
    "gn:country_code":"BY",
    "gn:dem":230,
    "gn:feature_class":"P",
    "gn:feature_code":"PPL",
    "gn:name":"Glinno",
    "gn:population":0,
    "gn:timezone":"Europe/Minsk",
    "iso:country":"BY",
    "name:rus_x_preferred":[
        "\u0413\u043b\u0438\u043d\u043d\u043e"
    ],
    "name:und_x_variant":[
        "Glinnaya"
    ],
    "wof:name":"Glinno",
    "wof:placetype":"locality"
},
  "geometry": {"coordinates":[26.2913,54.3995],"type":"Point"}
}