{
  "type": "Feature",
  "properties": {
    "gn:admin1_code":"7.0",
    "gn:asciiname":"Yankovichi",
    "gn:country_code":"BY",
    "gn:dem":162,
    "gn:feature_class":"P",
    "gn:feature_code":"PPL",
    "gn:name":"Yankovichi",
    "gn:population":0,
    "gn:timezone":"Europe/Minsk",
    "iso:country":"BY",
    "name:rus_x_preferred":[
        "\u042f\u043d\u043a\u043e\u0432\u0438\u0447\u0438"
    ],
    "wof:name":"Yankovichi",
    "wof:placetype":"locality"
},
  "geometry": {"coordinates":[26.5919,55.1389],"type":"Point"}
}