{
  "type": "Feature",
  "properties": {
    "gn:admin1_code":"7.0",
    "gn:asciiname":"Budilovo",
    "gn:country_code":"BY",
    "gn:dem":187,
    "gn:feature_class":"P",
    "gn:feature_code":"PPL",
    "gn:name":"Budilovo",
    "gn:population":0,
    "gn:timezone":"Europe/Minsk",
    "iso:country":"BY",
    "name:rus_x_preferred":[
        "\u0411\u0443\u0434\u0438\u043b\u043e\u0432\u043e"
    ],
    "wof:name":"Budilovo",
    "wof:placetype":"locality"
},
  "geometry": {"coordinates":[29.3008,54.669],"type":"Point"}
}