{
  "type": "Feature",
  "properties": {
    "gn:admin1_code":"5.0",
    "gn:asciiname":"Kamki",
    "gn:country_code":"BY",
    "gn:dem":261,
    "gn:feature_class":"P",
    "gn:feature_code":"PPL",
    "gn:name":"Kamki",
    "gn:population":0,
    "gn:timezone":"Europe/Minsk",
    "iso:country":"BY",
    "name:rus_x_preferred":[
        "\u041a\u0430\u043c\u043a\u0438"
    ],
    "wof:name":"Kamki",
    "wof:placetype":"locality"
},
  "geometry": {"coordinates":[27.4162,54.1571],"type":"Point"}
}