{
  "type": "Feature",
  "properties": {
    "gn:admin1_code":"5.0",
    "gn:asciiname":"Peretoki",
    "gn:country_code":"BY",
    "gn:dem":165,
    "gn:feature_class":"P",
    "gn:feature_code":"PPL",
    "gn:name":"Peretoki",
    "gn:population":0,
    "gn:timezone":"Europe/Minsk",
    "iso:country":"BY",
    "name:eng_x_preferred":[
        "Peretoki"
    ],
    "name:rus_x_preferred":[
        "\u041f\u0435\u0440\u0435\u0442\u043e\u043a\u0438"
    ],
    "wof:name":"Peretoki",
    "wof:placetype":"locality"
},
  "geometry": {"coordinates":[26.6462,53.4681],"type":"Point"}
}