{
  "type": "Feature",
  "properties": {
    "gn:admin1_code":"1.0",
    "gn:asciiname":"Kazemirovo",
    "gn:country_code":"BY",
    "gn:dem":164,
    "gn:feature_class":"P",
    "gn:feature_code":"PPL",
    "gn:name":"Kazemirovo",
    "gn:population":0,
    "gn:timezone":"Europe/Minsk",
    "iso:country":"BY",
    "name:rus_x_preferred":[
        "\u041a\u0430\u0437\u0435\u043c\u0438\u0440\u043e\u0432\u043e"
    ],
    "wof:name":"Kazemirovo",
    "wof:placetype":"locality"
},
  "geometry": {"coordinates":[24.3853,52.4939],"type":"Point"}
}