{
  "type": "Feature",
  "properties": {
    "gn:admin1_code":"5.0",
    "gn:asciiname":"Orekhovka",
    "gn:country_code":"BY",
    "gn:dem":189,
    "gn:feature_class":"P",
    "gn:feature_code":"PPL",
    "gn:name":"Orekhovka",
    "gn:population":0,
    "gn:timezone":"Europe/Minsk",
    "iso:country":"BY",
    "name:rus_x_preferred":[
        "\u041e\u0440\u0435\u0445\u043e\u0432\u043a\u0430"
    ],
    "wof:name":"Orekhovka",
    "wof:placetype":"locality"
},
  "geometry": {"coordinates":[27.1922,53.6728],"type":"Point"}
}