{
  "type": "Feature",
  "properties": {
    "gn:admin1_code":"5.0",
    "gn:asciiname":"Pribornyye",
    "gn:country_code":"BY",
    "gn:dem":155,
    "gn:feature_class":"P",
    "gn:feature_code":"PPL",
    "gn:name":"Pribornyye",
    "gn:population":0,
    "gn:timezone":"Europe/Minsk",
    "iso:country":"BY",
    "name:rus_x_preferred":[
        "\u041f\u0440\u0438\u0431\u043e\u0440\u043d\u044b\u0435"
    ],
    "wof:name":"Pribornyye",
    "wof:placetype":"locality"
},
  "geometry": {"coordinates":[26.5398,54.028],"type":"Point"}
}