{
  "type": "Feature",
  "properties": {
    "gn:admin1_code":"2.0",
    "gn:asciiname":"Zapollye",
    "gn:country_code":"BY",
    "gn:dem":135,
    "gn:feature_class":"P",
    "gn:feature_code":"PPL",
    "gn:name":"Zapollye",
    "gn:population":0,
    "gn:timezone":"Europe/Minsk",
    "iso:country":"BY",
    "name:bel_x_preferred":[
        "\u0417\u0430\u043f\u043e\u043b\u043b\u0435"
    ],
    "name:eng_x_preferred":[
        "Zapol'ye"
    ],
    "name:rus_x_preferred":[
        "\u0417\u0430\u043f\u043e\u043b\u044c\u0435"
    ],
    "name:rus_x_variant":[
        "Zapol\u2019ye"
    ],
    "name:und_x_variant":[
        "Zapol\u2019ye",
        "Zapollye"
    ],
    "wof:name":"Zapollye",
    "wof:placetype":"locality"
},
  "geometry": {"coordinates":[29.9589,53.1187],"type":"Point"}
}