{
  "type": "Feature",
  "properties": {
    "gn:admin1_code":"7.0",
    "gn:asciiname":"Matyushki",
    "gn:country_code":"BY",
    "gn:dem":150,
    "gn:feature_class":"P",
    "gn:feature_code":"PPL",
    "gn:name":"Matyushki",
    "gn:population":0,
    "gn:timezone":"Europe/Minsk",
    "iso:country":"BY",
    "name:rus_x_preferred":[
        "\u041c\u0430\u0442\u044e\u0448\u043a\u0438"
    ],
    "wof:name":"Matyushki",
    "wof:placetype":"locality"
},
  "geometry": {"coordinates":[27.6219,55.2539],"type":"Point"}
}