{
  "type": "Feature",
  "properties": {
    "gn:admin1_code":"3.0",
    "gn:asciiname":"Kartimovshchina",
    "gn:country_code":"BY",
    "gn:dem":179,
    "gn:feature_class":"P",
    "gn:feature_code":"PPL",
    "gn:name":"Kartimovshchina",
    "gn:population":0,
    "gn:timezone":"Europe/Minsk",
    "iso:country":"BY",
    "name:rus_x_preferred":[
        "\u041a\u0430\u0440\u0442\u0438\u043c\u043e\u0432\u0449\u0438\u043d\u0430"
    ],
    "wof:name":"Kartimovshchina",
    "wof:placetype":"locality"
},
  "geometry": {"coordinates":[25.4442,54.2921],"type":"Point"}
}