{
  "type": "Feature",
  "properties": {
    "gn:admin1_code":"0.0",
    "gn:asciiname":"Podrechany",
    "gn:cc2":"BY",
    "gn:country_code":"BY",
    "gn:dem":144,
    "gn:feature_class":"P",
    "gn:feature_code":"PPL",
    "gn:name":"Podrechany",
    "gn:population":0,
    "gn:timezone":"Europe/Minsk",
    "iso:country":"BY",
    "name:und_x_variant":[
        "Podzhechany",
        "Podrechany"
    ],
    "wof:name":"Podrechany",
    "wof:placetype":"locality"
},
  "geometry": {"coordinates":[23.93333,52.41667],"type":"Point"}
}