{
  "type": "Feature",
  "properties": {
    "gn:admin1_code":"3.0",
    "gn:asciiname":"Semkovo",
    "gn:country_code":"BY",
    "gn:dem":221,
    "gn:feature_class":"P",
    "gn:feature_code":"PPL",
    "gn:name":"Semkovo",
    "gn:population":0,
    "gn:timezone":"Europe/Minsk",
    "iso:country":"BY",
    "name:bel_x_preferred":[
        "Syamkova"
    ],
    "name:bel_x_variant":[
        "\u0421\u044f\u043c\u043a\u043e\u0432\u0430"
    ],
    "name:bul_x_preferred":[
        "\u0421\u0435\u043c\u043a\u043e\u0432\u043e"
    ],
    "name:rus_x_preferred":[
        "\u0421\u0435\u043c\u043a\u043e\u0432\u043e"
    ],
    "wof:name":"Semkovo",
    "wof:placetype":"locality"
},
  "geometry": {"coordinates":[25.7264,53.5784],"type":"Point"}
}