{
  "type": "Feature",
  "properties": {
    "gn:admin1_code":"5.0",
    "gn:asciiname":"Yashkovichi",
    "gn:country_code":"BY",
    "gn:dem":185,
    "gn:feature_class":"P",
    "gn:feature_code":"PPL",
    "gn:name":"Yashkovichi",
    "gn:population":0,
    "gn:timezone":"Europe/Minsk",
    "iso:country":"BY",
    "name:rus_x_preferred":[
        "\u042f\u0448\u043a\u043e\u0432\u0438\u0447\u0438"
    ],
    "wof:name":"Yashkovichi",
    "wof:placetype":"locality"
},
  "geometry": {"coordinates":[26.6248,54.0404],"type":"Point"}
}