{
  "type": "Feature",
  "properties": {
    "gn:admin1_code":"5.0",
    "gn:asciiname":"Starinki",
    "gn:country_code":"BY",
    "gn:dem":185,
    "gn:feature_class":"P",
    "gn:feature_code":"PPL",
    "gn:name":"Starinki",
    "gn:population":0,
    "gn:timezone":"Europe/Minsk",
    "iso:country":"BY",
    "name:rus_x_preferred":[
        "\u0421\u0442\u0430\u0440\u0438\u043d\u043a\u0438"
    ],
    "wof:name":"Starinki",
    "wof:placetype":"locality"
},
  "geometry": {"coordinates":[26.4711,54.2376],"type":"Point"}
}