{
  "type": "Feature",
  "properties": {
    "gn:admin1_code":"2.0",
    "gn:asciiname":"Krylov",
    "gn:country_code":"BY",
    "gn:dem":129,
    "gn:feature_class":"P",
    "gn:feature_code":"PPL",
    "gn:name":"Krylov",
    "gn:population":0,
    "gn:timezone":"Europe/Minsk",
    "iso:country":"BY",
    "name:rus_x_preferred":[
        "\u041a\u0440\u044b\u043b\u043e\u0432"
    ],
    "wof:name":"Krylov",
    "wof:placetype":"locality"
},
  "geometry": {"coordinates":[30.3068,52.5912],"type":"Point"}
}