{
  "type": "Feature",
  "properties": {
    "gn:admin1_code":"7.0",
    "gn:asciiname":"Novyya Valosavichy",
    "gn:country_code":"BY",
    "gn:dem":190,
    "gn:feature_class":"P",
    "gn:feature_code":"PPL",
    "gn:name":"Novyya Valosavichy",
    "gn:population":0,
    "gn:timezone":"Europe/Minsk",
    "iso:country":"BY",
    "name:bel_x_preferred":[
        "\u041d\u043e\u0432\u044b\u044f \u0412\u0430\u043b\u043e\u0441\u0430\u0432\u0456\u0447\u044b"
    ],
    "name:eng_x_preferred":[
        "Volosovichi"
    ],
    "name:rus_x_preferred":[
        "\u041d\u043e\u0432.\u0412\u043e\u043b\u043e\u0441\u043e\u0432\u0438\u0447\u0438"
    ],
    "name:und_x_variant":[
        "Novyya Valosavichy",
        "Novyye Volosovichi"
    ],
    "wof:name":"Novyya Valosavichy",
    "wof:placetype":"locality"
},
  "geometry": {"coordinates":[28.8407,54.7607],"type":"Point"}
}