{
  "type": "Feature",
  "properties": {
    "gn:admin1_code":"2.0",
    "gn:asciiname":"Klyapinskaya Buda",
    "gn:country_code":"BY",
    "gn:dem":154,
    "gn:feature_class":"P",
    "gn:feature_code":"PPL",
    "gn:name":"Klyapinskaya Buda",
    "gn:population":0,
    "gn:timezone":"Europe/Minsk",
    "iso:country":"BY",
    "name:rus_x_preferred":[
        "\u041a\u043b\u044f\u043f\u0438\u043d\u0441\u043a\u0430\u044f \u0411\u0443\u0434\u0430"
    ],
    "name:und_x_variant":[
        "Buda Klyapinskaya"
    ],
    "wof:name":"Klyapinskaya Buda",
    "wof:placetype":"locality"
},
  "geometry": {"coordinates":[31.093,53.1665],"type":"Point"}
}