{
  "type": "Feature",
  "properties": {
    "gn:admin1_code":"6.0",
    "gn:asciiname":"Budishche",
    "gn:country_code":"BY",
    "gn:dem":174,
    "gn:feature_class":"P",
    "gn:feature_code":"PPL",
    "gn:name":"Budishche",
    "gn:population":0,
    "gn:timezone":"Europe/Minsk",
    "iso:country":"BY",
    "name:rus_x_preferred":[
        "\u0411\u0443\u0434\u0438\u0449\u0435"
    ],
    "wof:name":"Budishche",
    "wof:placetype":"locality"
},
  "geometry": {"coordinates":[29.9406,53.8674],"type":"Point"}
}