{
  "type": "Feature",
  "properties": {
    "gn:admin1_code":"5.0",
    "gn:asciiname":"Zahraddzye",
    "gn:country_code":"BY",
    "gn:dem":151,
    "gn:feature_class":"P",
    "gn:feature_code":"PPL",
    "gn:name":"Zahraddzye",
    "gn:population":0,
    "gn:timezone":"Europe/Minsk",
    "iso:country":"BY",
    "name:bel_x_preferred":[
        "\u0417\u0430\u0433\u0440\u0430\u0434\u0434\u0437\u0435"
    ],
    "name:rus_x_preferred":[
        "Zagrad\u2019ye"
    ],
    "wof:name":"Zahraddzye",
    "wof:placetype":"locality"
},
  "geometry": {"coordinates":[27.7611,52.9729],"type":"Point"}
}