{
  "type": "Feature",
  "properties": {
    "gn:admin1_code":"7.0",
    "gn:asciiname":"Krivino",
    "gn:country_code":"BY",
    "gn:dem":141,
    "gn:feature_class":"P",
    "gn:feature_code":"PPL",
    "gn:name":"Krivino",
    "gn:population":0,
    "gn:timezone":"Europe/Minsk",
    "iso:country":"BY",
    "name:rus_x_preferred":[
        "\u041a\u0440\u0438\u0432\u0438\u043d\u043e"
    ],
    "wof:name":"Krivino",
    "wof:placetype":"locality"
},
  "geometry": {"coordinates":[29.5443,55.0535],"type":"Point"}
}