{
  "type": "Feature",
  "properties": {
    "gn:admin1_code":"7.0",
    "gn:asciiname":"Skrydlevo",
    "gn:country_code":"BY",
    "gn:dem":158,
    "gn:feature_class":"P",
    "gn:feature_code":"PPL",
    "gn:name":"Skrydl\u00ebvo",
    "gn:population":0,
    "gn:timezone":"Europe/Minsk",
    "iso:country":"BY",
    "name:rus_x_preferred":[
        "\u0421\u043a\u0440\u044b\u0434\u043b\u0451\u0432\u043e"
    ],
    "name:und_x_variant":[
        "Skrydl\u00ebvo"
    ],
    "wof:name":"Skrydlevo",
    "wof:placetype":"locality"
},
  "geometry": {"coordinates":[30.0553,55.0269],"type":"Point"}
}