{
  "type": "Feature",
  "properties": {
    "gn:admin1_code":"6.0",
    "gn:asciiname":"Pavlovsk",
    "gn:country_code":"BY",
    "gn:dem":162,
    "gn:feature_class":"P",
    "gn:feature_code":"PPL",
    "gn:name":"Pavlovsk",
    "gn:population":0,
    "gn:timezone":"Europe/Minsk",
    "iso:country":"BY",
    "name:bel_x_preferred":[
        "\u041f\u0430\u045e\u043b\u0430\u045e\u0441\u043a"
    ],
    "name:ceb_x_preferred":[
        "Pavlovsk"
    ],
    "name:deu_x_preferred":[
        "Pawlowsk"
    ],
    "name:epo_x_preferred":[
        "Pavlovsk"
    ],
    "name:fra_x_preferred":[
        "Pavlovsk"
    ],
    "name:hsb_x_preferred":[
        "Pawlowsk"
    ],
    "name:hun_x_preferred":[
        "Pavlovszk"
    ],
    "name:ita_x_preferred":[
        "Pavlovsk"
    ],
    "name:kor_x_preferred":[
        "\ud30c\ube14\ub86d\uc2a4\ud06c"
    ],
    "name:lav_x_preferred":[
        "Pavlovska"
    ],
    "name:mkd_x_preferred":[
        "\u041f\u0430\u0432\u043b\u043e\u0432\u0441\u043a"
    ],
    "name:nld_x_preferred":[
        "Pavlovsk"
    ],
    "name:nor_x_preferred":[
        "Pavlovsk"
    ],
    "name:rus_x_preferred":[
        "\u041f\u0430\u0432\u043b\u043e\u0432\u0441\u043a"
    ],
    "name:spa_x_preferred":[
        "Pavlovsk"
    ],
    "name:tgl_x_preferred":[
        "Pavlovsk"
    ],
    "name:ukr_x_preferred":[
        "\u041f\u0430\u0432\u043b\u043e\u0432\u0441\u044c\u043a"
    ],
    "name:vep_x_preferred":[
        "Pavlovsk"
    ],
    "name:vie_x_preferred":[
        "Pavlovsk"
    ],
    "wof:name":"Pavlovsk",
    "wof:placetype":"locality"
},
  "geometry": {"coordinates":[29.8219,53.8154],"type":"Point"}
}