{
  "type": "Feature",
  "properties": {
    "gn:admin1_code":"1.0",
    "gn:asciiname":"Kulyany",
    "gn:country_code":"BY",
    "gn:dem":158,
    "gn:feature_class":"P",
    "gn:feature_code":"PPL",
    "gn:name":"Kulyany",
    "gn:population":0,
    "gn:timezone":"Europe/Minsk",
    "iso:country":"BY",
    "name:eng_x_preferred":[
        "Kulyany"
    ],
    "name:rus_x_preferred":[
        "\u041a\u0443\u043b\u044f\u043d\u044b"
    ],
    "wof:name":"Kulyany",
    "wof:placetype":"locality"
},
  "geometry": {"coordinates":[24.8212,52.9339],"type":"Point"}
}