{
  "type": "Feature",
  "properties": {
    "gn:admin1_code":"0.0",
    "gn:asciiname":"Stazhynki",
    "gn:cc2":"BY",
    "gn:country_code":"BY",
    "gn:dem":182,
    "gn:feature_class":"P",
    "gn:feature_code":"PPL",
    "gn:name":"Stazhynki",
    "gn:population":0,
    "gn:timezone":"Europe/Minsk",
    "iso:country":"BY",
    "name:und_x_variant":[
        "Starzynki",
        "Stazhynki"
    ],
    "wof:name":"Stazhynki",
    "wof:placetype":"locality"
},
  "geometry": {"coordinates":[27.33333,54.63333000000001],"type":"Point"}
}