{
  "type": "Feature",
  "properties": {
    "gn:admin1_code":"5.0",
    "gn:asciiname":"Telyaki",
    "gn:country_code":"BY",
    "gn:dem":193,
    "gn:feature_class":"P",
    "gn:feature_code":"PPL",
    "gn:name":"Telyaki",
    "gn:population":0,
    "gn:timezone":"Europe/Minsk",
    "iso:country":"BY",
    "name:rus_x_preferred":[
        "\u0422\u0435\u043b\u044f\u043a\u0438"
    ],
    "wof:name":"Telyaki",
    "wof:placetype":"locality"
},
  "geometry": {"coordinates":[26.7949,54.8965],"type":"Point"}
}