{
  "type": "Feature",
  "properties": {
    "gn:admin1_code":"7.0",
    "gn:asciiname":"Andronovichi",
    "gn:country_code":"BY",
    "gn:dem":170,
    "gn:feature_class":"P",
    "gn:feature_code":"PPL",
    "gn:name":"Andronovichi",
    "gn:population":0,
    "gn:timezone":"Europe/Minsk",
    "iso:country":"BY",
    "name:rus_x_preferred":[
        "\u0410\u043d\u0434\u0440\u043e\u043d\u043e\u0432\u0438\u0447\u0438"
    ],
    "wof:name":"Andronovichi",
    "wof:placetype":"locality"
},
  "geometry": {"coordinates":[30.2757,55.243],"type":"Point"}
}