{
  "type": "Feature",
  "properties": {
    "gn:admin1_code":"7.0",
    "gn:asciiname":"Gurby",
    "gn:country_code":"BY",
    "gn:dem":185,
    "gn:feature_class":"P",
    "gn:feature_code":"PPL",
    "gn:name":"Gurby",
    "gn:population":0,
    "gn:timezone":"Europe/Minsk",
    "iso:country":"BY",
    "name:rus_x_preferred":[
        "\u0413\u0443\u0440\u0431\u044b"
    ],
    "wof:name":"Gurby",
    "wof:placetype":"locality"
},
  "geometry": {"coordinates":[27.854,55.0488],"type":"Point"}
}