{
  "type": "Feature",
  "properties": {
    "gn:admin1_code":"5.0",
    "gn:asciiname":"Oktyabr'",
    "gn:country_code":"BY",
    "gn:dem":187,
    "gn:feature_class":"P",
    "gn:feature_code":"PPL",
    "gn:name":"Oktyabr\u2019",
    "gn:population":0,
    "gn:timezone":"Europe/Minsk",
    "iso:country":"BY",
    "name:rus_x_preferred":[
        "\u041e\u043a\u0442\u044f\u0431\u0440\u044c"
    ],
    "name:und_x_variant":[
        "Oktyabr\u2019"
    ],
    "wof:name":"Oktyabr'",
    "wof:placetype":"locality"
},
  "geometry": {"coordinates":[29.4021,54.416],"type":"Point"}
}