{
  "type": "Feature",
  "properties": {
    "gn:admin1_code":"3.0",
    "gn:asciiname":"Skirdimy",
    "gn:country_code":"BY",
    "gn:dem":214,
    "gn:feature_class":"P",
    "gn:feature_code":"PPL",
    "gn:name":"Skirdimy",
    "gn:population":0,
    "gn:timezone":"Europe/Minsk",
    "iso:country":"BY",
    "name:rus_x_preferred":[
        "\u0421\u043a\u0438\u0440\u0434\u0438\u043c\u044b"
    ],
    "wof:name":"Skirdimy",
    "wof:placetype":"locality"
},
  "geometry": {"coordinates":[26.146,54.3579],"type":"Point"}
}