{
  "type": "Feature",
  "properties": {
    "gn:admin1_code":"6.0",
    "gn:asciiname":"Mikhalyova",
    "gn:country_code":"BY",
    "gn:dem":182,
    "gn:feature_class":"P",
    "gn:feature_code":"PPL",
    "gn:name":"Mikhalyova",
    "gn:population":0,
    "gn:timezone":"Europe/Minsk",
    "iso:country":"BY",
    "name:bel_x_preferred":[
        "\u041c\u0456\u0445\u0430\u043b\u0451\u0432\u0430"
    ],
    "name:rus_x_preferred":[
        "Mikhal\u00ebvo"
    ],
    "name:und_x_variant":[
        "Mikhalevka"
    ],
    "wof:name":"Mikhalyova",
    "wof:placetype":"locality"
},
  "geometry": {"coordinates":[30.0517,53.8715],"type":"Point"}
}