{
  "type": "Feature",
  "properties": {
    "gn:admin1_code":"1.0",
    "gn:asciiname":"Kutnevichi",
    "gn:country_code":"BY",
    "gn:dem":156,
    "gn:feature_class":"P",
    "gn:feature_code":"PPL",
    "gn:name":"Kutnevichi",
    "gn:population":0,
    "gn:timezone":"Europe/Minsk",
    "iso:country":"BY",
    "name:rus_x_preferred":[
        "\u041a\u0443\u0442\u043d\u0435\u0432\u0438\u0447\u0438"
    ],
    "wof:name":"Kutnevichi",
    "wof:placetype":"locality"
},
  "geometry": {"coordinates":[24.6213,52.4972],"type":"Point"}
}