{
  "type": "Feature",
  "properties": {
    "gn:admin1_code":"2.0",
    "gn:asciiname":"Ignato-Fabianovka",
    "gn:country_code":"BY",
    "gn:dem":119,
    "gn:feature_class":"P",
    "gn:feature_code":"PPL",
    "gn:name":"Ignato-Fabianovka",
    "gn:population":0,
    "gn:timezone":"Europe/Minsk",
    "iso:country":"BY",
    "name:rus_x_preferred":[
        "\u0418\u0433\u043d\u0430\u0442\u043e-\u0424\u0430\u0431\u0438\u0430\u043d\u043e\u0432\u043a\u0430"
    ],
    "wof:name":"Ignato-Fabianovka",
    "wof:placetype":"locality"
},
  "geometry": {"coordinates":[29.4607,52.0211],"type":"Point"}
}