{
  "type": "Feature",
  "properties": {
    "gn:admin1_code":"0.0",
    "gn:asciiname":"Yel'na",
    "gn:country_code":"BY",
    "gn:dem":117,
    "gn:feature_class":"P",
    "gn:feature_code":"PPL",
    "gn:name":"Yel\u2019na",
    "gn:population":0,
    "gn:timezone":"Europe/Minsk",
    "iso:country":"BY",
    "wof:name":"Yel'na",
    "wof:placetype":"locality"
},
  "geometry": {"coordinates":[25.35,53.66667],"type":"Point"}
}