{
  "type": "Feature",
  "properties": {
    "gn:admin1_code":"5.0",
    "gn:asciiname":"Staryy Bobr",
    "gn:country_code":"BY",
    "gn:dem":176,
    "gn:feature_class":"P",
    "gn:feature_code":"PPL",
    "gn:name":"Staryy Bobr",
    "gn:population":0,
    "gn:timezone":"Europe/Minsk",
    "iso:country":"BY",
    "name:rus_x_preferred":[
        "\u0421\u0442\u0430\u0440\u044b\u0439 \u0411\u043e\u0431\u0440"
    ],
    "name:und_x_variant":[
        "Stary Bobr",
        "Staryy Bobr"
    ],
    "wof:name":"Staryy Bobr",
    "wof:placetype":"locality"
},
  "geometry": {"coordinates":[29.3053,54.3791],"type":"Point"}
}