{
  "type": "Feature",
  "properties": {
    "gn:admin1_code":"6.0",
    "gn:asciiname":"Kletki",
    "gn:country_code":"BY",
    "gn:dem":160,
    "gn:feature_class":"P",
    "gn:feature_code":"PPL",
    "gn:name":"Kletki",
    "gn:population":0,
    "gn:timezone":"Europe/Minsk",
    "iso:country":"BY",
    "name:rus_x_preferred":[
        "\u041a\u043b\u0435\u0442\u043a\u0438"
    ],
    "wof:name":"Kletki",
    "wof:placetype":"locality"
},
  "geometry": {"coordinates":[31.8742,53.2593],"type":"Point"}
}