{
  "type": "Feature",
  "properties": {
    "gn:admin1_code":"1.0",
    "gn:asciiname":"Sredibor'ye",
    "gn:country_code":"BY",
    "gn:dem":139,
    "gn:feature_class":"P",
    "gn:feature_code":"PPL",
    "gn:name":"Sredibor\u2019ye",
    "gn:population":0,
    "gn:timezone":"Europe/Minsk",
    "iso:country":"BY",
    "name:rus_x_preferred":[
        "\u0421\u0440\u0435\u0434\u0438\u0431\u043e\u0440\u044c\u0435"
    ],
    "name:und_x_variant":[
        "Sredibor\u2019ye"
    ],
    "wof:name":"Sredibor'ye",
    "wof:placetype":"locality"
},
  "geometry": {"coordinates":[27.0439,52.3132],"type":"Point"}
}