{
  "type": "Feature",
  "properties": {
    "gn:admin1_code":"3.0",
    "gn:asciiname":"Novitskiye Vtoryye",
    "gn:country_code":"BY",
    "gn:dem":136,
    "gn:feature_class":"P",
    "gn:feature_code":"PPL",
    "gn:name":"Novitskiye Vtoryye",
    "gn:population":0,
    "gn:timezone":"Europe/Minsk",
    "iso:country":"BY",
    "name:rus_x_preferred":[
        "\u041d\u043e\u0432\u0438\u0446\u043a\u0438\u0435 \u0412\u0442\u043e\u0440\u044b\u0435"
    ],
    "wof:name":"Novitskiye Vtoryye",
    "wof:placetype":"locality"
},
  "geometry": {"coordinates":[25.3768,53.8437],"type":"Point"}
}