{
  "type": "Feature",
  "properties": {
    "gn:admin1_code":"5.0",
    "gn:asciiname":"Chervonaya Niva",
    "gn:country_code":"BY",
    "gn:dem":168,
    "gn:feature_class":"P",
    "gn:feature_code":"PPL",
    "gn:name":"Chervonaya Niva",
    "gn:population":0,
    "gn:timezone":"Europe/Minsk",
    "iso:country":"BY",
    "name:rus_x_preferred":[
        "\u0427\u0435\u0440\u0432\u043e\u043d\u0430\u044f \u041d\u0438\u0432\u0430"
    ],
    "name:und_x_variant":[
        "Krasnaya Niva"
    ],
    "wof:name":"Chervonaya Niva",
    "wof:placetype":"locality"
},
  "geometry": {"coordinates":[27.3245,53.0466],"type":"Point"}
}