{
  "type": "Feature",
  "properties": {
    "gn:admin1_code":"1.0",
    "gn:asciiname":"Kosicze Wielkie",
    "gn:country_code":"BY",
    "gn:dem":138,
    "gn:feature_class":"P",
    "gn:feature_code":"PPL",
    "gn:name":"Kosicze Wielkie",
    "gn:population":0,
    "gn:timezone":"Europe/Minsk",
    "iso:country":"BY",
    "name:rus_x_preferred":[
        "Kosichi Bol\u2019shiye"
    ],
    "name:rus_x_variant":[
        "\u041a\u043e\u0441\u0438\u0447\u0438-\u0411\u043e\u043b\u044c\u0448\u0438\u0435"
    ],
    "name:und_x_variant":[
        "Kosice",
        "Kosiche Vel\u2019ke",
        "Bol\u2019shiye Kosichi"
    ],
    "wof:name":"Kosicze Wielkie",
    "wof:placetype":"locality"
},
  "geometry": {"coordinates":[23.8212,52.1347],"type":"Point"}
}