{
  "type": "Feature",
  "properties": {
    "gn:admin1_code":"3.0",
    "gn:asciiname":"Starinki",
    "gn:country_code":"BY",
    "gn:dem":147,
    "gn:feature_class":"P",
    "gn:feature_code":"PPL",
    "gn:name":"Starinki",
    "gn:population":0,
    "gn:timezone":"Europe/Minsk",
    "iso:country":"BY",
    "name:bel_x_preferred":[
        "Starynki"
    ],
    "name:bel_x_variant":[
        "\u0421\u0442\u0430\u0440\u044b\u043d\u043a\u0456"
    ],
    "name:rus_x_preferred":[
        "\u0421\u0442\u0430\u0440\u0438\u043d\u043a\u0438"
    ],
    "wof:name":"Starinki",
    "wof:placetype":"locality"
},
  "geometry": {"coordinates":[24.9385,53.5484],"type":"Point"}
}