{
  "type": "Feature",
  "properties": {
    "gn:admin1_code":"6.0",
    "gn:asciiname":"Razrytaya",
    "gn:country_code":"BY",
    "gn:dem":171,
    "gn:feature_class":"P",
    "gn:feature_code":"PPL",
    "gn:name":"Razrytaya",
    "gn:population":0,
    "gn:timezone":"Europe/Minsk",
    "iso:country":"BY",
    "name:rus_x_preferred":[
        "\u0420\u0430\u0437\u0440\u044b\u0442\u0430\u044f"
    ],
    "wof:name":"Razrytaya",
    "wof:placetype":"locality"
},
  "geometry": {"coordinates":[32.2257,53.1142],"type":"Point"}
}