{
  "type": "Feature",
  "properties": {
    "gn:admin1_code":"5.0",
    "gn:asciiname":"Kontinenty",
    "gn:country_code":"BY",
    "gn:dem":164,
    "gn:feature_class":"P",
    "gn:feature_code":"PPL",
    "gn:name":"Kontinenty",
    "gn:population":0,
    "gn:timezone":"Europe/Minsk",
    "iso:country":"BY",
    "name:rus_x_preferred":[
        "\u041a\u043e\u043d\u0442\u0438\u043d\u0435\u043d\u0442\u044b"
    ],
    "name:und_x_variant":[
        "Katsenenta",
        "Kontenety",
        "Kontinenty"
    ],
    "wof:name":"Kontinenty",
    "wof:placetype":"locality"
},
  "geometry": {"coordinates":[26.5206,54.8043],"type":"Point"}
}