{
  "type": "Feature",
  "properties": {
    "gn:admin1_code":"1.0",
    "gn:asciiname":"Kregli",
    "gn:country_code":"BY",
    "gn:dem":181,
    "gn:feature_class":"P",
    "gn:feature_code":"PPL",
    "gn:name":"Kregli",
    "gn:population":0,
    "gn:timezone":"Europe/Minsk",
    "iso:country":"BY",
    "name:rus_x_preferred":[
        "\u041a\u0440\u0435\u0433\u043b\u0438"
    ],
    "wof:name":"Kregli",
    "wof:placetype":"locality"
},
  "geometry": {"coordinates":[26.2628,53.103],"type":"Point"}
}