{
  "type": "Feature",
  "properties": {
    "gn:admin1_code":"1.0",
    "gn:asciiname":"Gorodets",
    "gn:country_code":"BY",
    "gn:dem":132,
    "gn:feature_class":"P",
    "gn:feature_code":"PPL",
    "gn:name":"Gorodets",
    "gn:population":0,
    "gn:timezone":"Europe/Minsk",
    "iso:country":"BY",
    "name:rus_x_preferred":[
        "\u0413\u043e\u0440\u043e\u0434\u0435\u0446"
    ],
    "name:und_x_variant":[
        "Gorodzets",
        "Horocziec",
        "Gorodets"
    ],
    "wof:name":"Gorodets",
    "wof:placetype":"locality"
},
  "geometry": {"coordinates":[27.0902,52.0419],"type":"Point"}
}