{
  "type": "Feature",
  "properties": {
    "gn:admin1_code":"2.0",
    "gn:asciiname":"Belitsa",
    "gn:country_code":"BY",
    "gn:dem":135,
    "gn:feature_class":"P",
    "gn:feature_code":"PPL",
    "gn:name":"Belitsa",
    "gn:population":0,
    "gn:timezone":"Europe/Minsk",
    "iso:country":"BY",
    "name:rus_x_preferred":[
        "\u0411\u0435\u043b\u0438\u0446\u0430"
    ],
    "wof:name":"Belitsa",
    "wof:placetype":"locality"
},
  "geometry": {"coordinates":[29.9641,52.9336],"type":"Point"}
}