{
  "type": "Feature",
  "properties": {
    "gn:admin1_code":"3.0",
    "gn:asciiname":"Bol'shiye Iodkovichi",
    "gn:country_code":"BY",
    "gn:dem":114,
    "gn:feature_class":"P",
    "gn:feature_code":"PPL",
    "gn:name":"Bol\u2019shiye Iodkovichi",
    "gn:population":0,
    "gn:timezone":"Europe/Minsk",
    "iso:country":"BY",
    "name:rus_x_preferred":[
        "\u0411\u043e\u043b\u044c\u0448\u0438\u0435 \u0418\u043e\u0434\u043a\u043e\u0432\u0438\u0447\u0438"
    ],
    "name:und_x_variant":[
        "Iodkeviche-Vel\u2019ke",
        "Bol\u2019shiye Iodkovichi"
    ],
    "wof:name":"Bol'shiye Iodkovichi",
    "wof:placetype":"locality"
},
  "geometry": {"coordinates":[24.0067,53.4134],"type":"Point"}
}