{
  "type": "Feature",
  "properties": {
    "gn:admin1_code":"6.0",
    "gn:asciiname":"Krutoy Ruchey",
    "gn:country_code":"BY",
    "gn:dem":155,
    "gn:feature_class":"P",
    "gn:feature_code":"PPL",
    "gn:name":"Krutoy Ruchey",
    "gn:population":0,
    "gn:timezone":"Europe/Minsk",
    "iso:country":"BY",
    "wof:name":"Krutoy Ruchey",
    "wof:placetype":"locality"
},
  "geometry": {"coordinates":[31.29917,53.14028],"type":"Point"}
}