{
  "type": "Feature",
  "properties": {
    "gn:admin1_code":"1.0",
    "gn:asciiname":"Lyuban'",
    "gn:country_code":"BY",
    "gn:dem":127,
    "gn:feature_class":"P",
    "gn:feature_code":"PPL",
    "gn:name":"Lyuban\u2019",
    "gn:population":0,
    "gn:timezone":"Europe/Minsk",
    "iso:country":"BY",
    "name:bel_x_preferred":[
        "\u041b\u044e\u0431\u0430\u043d\u044c"
    ],
    "name:und_x_variant":[
        "Lubo\u0144",
        "Lyubon\u2019",
        "Lyuban\u2019"
    ],
    "wof:name":"Lyuban'",
    "wof:placetype":"locality"
},
  "geometry": {"coordinates":[27.153,52.2097],"type":"Point"}
}