{
  "type": "Feature",
  "properties": {
    "gn:admin1_code":"7.0",
    "gn:asciiname":"Tinkovtsy",
    "gn:country_code":"BY",
    "gn:dem":115,
    "gn:feature_class":"P",
    "gn:feature_code":"PPL",
    "gn:name":"Tinkovtsy",
    "gn:population":0,
    "gn:timezone":"Europe/Minsk",
    "iso:country":"BY",
    "name:rus_x_preferred":[
        "\u0422\u0438\u043d\u043a\u043e\u0432\u0446\u044b"
    ],
    "name:und_x_variant":[
        "Tynkowicze",
        "Tinkovtsy"
    ],
    "wof:name":"Tinkovtsy",
    "wof:placetype":"locality"
},
  "geometry": {"coordinates":[27.7643,55.8055],"type":"Point"}
}