{
  "type": "Feature",
  "properties": {
    "gn:admin1_code":"7.0",
    "gn:asciiname":"Anikevshchina",
    "gn:country_code":"BY",
    "gn:dem":183,
    "gn:feature_class":"P",
    "gn:feature_code":"PPL",
    "gn:name":"Anikevshchina",
    "gn:population":0,
    "gn:timezone":"Europe/Minsk",
    "iso:country":"BY",
    "name:rus_x_preferred":[
        "\u0410\u043d\u0438\u043a\u0435\u0432\u0449\u0438\u043d\u0430"
    ],
    "wof:name":"Anikevshchina",
    "wof:placetype":"locality"
},
  "geometry": {"coordinates":[28.4021,55.2157],"type":"Point"}
}