{
  "type": "Feature",
  "properties": {
    "gn:admin1_code":"7.0",
    "gn:asciiname":"Stavishovo",
    "gn:country_code":"BY",
    "gn:dem":199,
    "gn:feature_class":"P",
    "gn:feature_code":"PPL",
    "gn:name":"Stavishovo",
    "gn:population":0,
    "gn:timezone":"Europe/Minsk",
    "iso:country":"BY",
    "name:rus_x_preferred":[
        "\u0421\u0442\u0430\u0432\u0438\u0448\u043e\u0432\u043e"
    ],
    "wof:name":"Stavishovo",
    "wof:placetype":"locality"
},
  "geometry": {"coordinates":[26.8031,54.9882],"type":"Point"}
}