{
  "type": "Feature",
  "properties": {
    "gn:country":"BY",
    "gn:fcode":"PPL",
    "gn:pop":2900,
    "iso:country":"BY",
    "name:bel_x_preferred":[
        "\u041f\u0440\u0430\u045e\u0434\u0437\u0456\u043d\u0441\u043a\u0456"
    ],
    "name:dut_x_preferred":[
        "Pra\u016ddz\u0456nsk\u0456"
    ],
    "name:eng_x_preferred":[
        "Pravdinskiy"
    ],
    "name:est_x_preferred":[
        "Pra\u016ddzinski"
    ],
    "name:pol_x_preferred":[
        "Praudzinski"
    ],
    "name:rus_x_preferred":[
        "\u041f\u0440\u0430\u0432\u0434\u0438\u043d\u0441\u043a\u0438\u0439"
    ],
    "name:srp_x_preferred":[
        "\u041f\u0440\u0430\u0432\u0434\u0437\u0438\u043d\u0441\u043a\u0438"
    ],
    "name:swe_x_preferred":[
        "Pra\u016ddz\u0456nsk\u0456"
    ],
    "name:ukr_x_preferred":[
        "\u041f\u0440\u0430\u0432\u0434\u0438\u043d\u0441\u044c\u043a\u0438\u0439"
    ],
    "name:unk_x_variant":[
        "Pravdinskiy"
    ],
    "qs:name":"Prawdzinski",
    "qs:photos_9r":0,
    "qs:photos_sr":0,
    "qs:pop_sr":"4",
    "wof:name":"Prawdzinski",
    "wof:placetype":"locality",
    "wof:population":2900
},
  "geometry": {"coordinates":[27.8303,53.5248],"type":"Point"}
}