{
  "type": "Feature",
  "properties": {
    "gn:admin1_code":"0.0",
    "gn:asciiname":"Sokolinyy",
    "gn:cc2":"BY",
    "gn:country_code":"BY",
    "gn:dem":149,
    "gn:feature_class":"P",
    "gn:feature_code":"PPL",
    "gn:name":"Sokolinyy",
    "gn:population":0,
    "gn:timezone":"Europe/Minsk",
    "iso:country":"BY",
    "name:und_x_variant":[
        "Sokoliny",
        "Sokolinyy"
    ],
    "wof:name":"Sokolinyy",
    "wof:placetype":"locality"
},
  "geometry": {"coordinates":[30.83333,52.81667],"type":"Point"}
}