{
  "type": "Feature",
  "properties": {
    "gn:admin1_code":"1.0",
    "gn:asciiname":"Mostyki",
    "gn:country_code":"BY",
    "gn:dem":143,
    "gn:feature_class":"P",
    "gn:feature_code":"PPL",
    "gn:name":"Mostyki",
    "gn:population":0,
    "gn:timezone":"Europe/Minsk",
    "iso:country":"BY",
    "name:rus_x_preferred":[
        "\u041c\u043e\u0441\u0442\u044b\u043a\u0438"
    ],
    "wof:name":"Mostyki",
    "wof:placetype":"locality"
},
  "geometry": {"coordinates":[25.1622,52.3767],"type":"Point"}
}