{
  "type": "Feature",
  "properties": {
    "gn:admin1_code":"5.0",
    "gn:asciiname":"Zhorovka",
    "gn:country_code":"BY",
    "gn:dem":171,
    "gn:feature_class":"P",
    "gn:feature_code":"PPL",
    "gn:name":"Zhorovka",
    "gn:population":0,
    "gn:timezone":"Europe/Minsk",
    "iso:country":"BY",
    "name:rus_x_preferred":[
        "\u0416\u043e\u0440\u043e\u0432\u043a\u0430"
    ],
    "wof:name":"Zhorovka",
    "wof:placetype":"locality"
},
  "geometry": {"coordinates":[28.0098,53.6449],"type":"Point"}
}