{
  "type": "Feature",
  "properties": {
    "gn:admin1_code":"7.0",
    "gn:asciiname":"Volki",
    "gn:country_code":"BY",
    "gn:dem":128,
    "gn:feature_class":"P",
    "gn:feature_code":"PPL",
    "gn:name":"Volki",
    "gn:population":0,
    "gn:timezone":"Europe/Minsk",
    "iso:country":"BY",
    "name:rus_x_preferred":[
        "\u0412\u043e\u043b\u043a\u0438"
    ],
    "wof:name":"Volki",
    "wof:placetype":"locality"
},
  "geometry": {"coordinates":[26.9705,55.2782],"type":"Point"}
}