{
  "type": "Feature",
  "properties": {
    "gn:admin1_code":"7.0",
    "gn:asciiname":"Sheteni",
    "gn:country_code":"BY",
    "gn:dem":146,
    "gn:feature_class":"P",
    "gn:feature_code":"PPL",
    "gn:name":"Sheteni",
    "gn:population":0,
    "gn:timezone":"Europe/Minsk",
    "iso:country":"BY",
    "name:rus_x_preferred":[
        "\u0428\u0435\u0442\u0435\u043d\u0438"
    ],
    "name:und_x_variant":[
        "Shoteni"
    ],
    "wof:name":"Sheteni",
    "wof:placetype":"locality"
},
  "geometry": {"coordinates":[29.724,54.9296],"type":"Point"}
}