{
  "type": "Feature",
  "properties": {
    "gn:admin1_code":"2.0",
    "gn:asciiname":"Ramyazy",
    "gn:country_code":"BY",
    "gn:dem":138,
    "gn:feature_class":"P",
    "gn:feature_code":"PPL",
    "gn:name":"Ramyazy",
    "gn:population":0,
    "gn:timezone":"Europe/Minsk",
    "iso:country":"BY",
    "name:bel_x_preferred":[
        "\u0420\u0430\u043c\u044f\u0437\u044b"
    ],
    "name:und_x_variant":[
        "Romezy",
        "Remezy",
        "Ramyazy"
    ],
    "wof:name":"Ramyazy",
    "wof:placetype":"locality"
},
  "geometry": {"coordinates":[28.9625,51.8225],"type":"Point"}
}