{
  "type": "Feature",
  "properties": {
    "gn:admin1_code":"7.0",
    "gn:asciiname":"Borovyye",
    "gn:country_code":"BY",
    "gn:dem":150,
    "gn:feature_class":"P",
    "gn:feature_code":"PPL",
    "gn:name":"Borovyye",
    "gn:population":0,
    "gn:timezone":"Europe/Minsk",
    "iso:country":"BY",
    "name:rus_x_preferred":[
        "\u0411\u043e\u0440\u043e\u0432\u044b\u0435"
    ],
    "wof:name":"Borovyye",
    "wof:placetype":"locality"
},
  "geometry": {"coordinates":[28.7701,55.1551],"type":"Point"}
}