{
  "type": "Feature",
  "properties": {
    "gn:admin1_code":"2.0",
    "gn:asciiname":"Tsuper",
    "gn:country_code":"BY",
    "gn:dem":132,
    "gn:feature_class":"P",
    "gn:feature_code":"PPL",
    "gn:name":"Tsuper",
    "gn:population":0,
    "gn:timezone":"Europe/Minsk",
    "iso:country":"BY",
    "name:rus_x_preferred":[
        "\u0426\u0443\u043f\u0435\u0440"
    ],
    "wof:name":"Tsuper",
    "wof:placetype":"locality"
},
  "geometry": {"coordinates":[30.0972,52.9552],"type":"Point"}
}