{
  "type": "Feature",
  "properties": {
    "gn:admin1_code":"7.0",
    "gn:asciiname":"Sinsk",
    "gn:country_code":"BY",
    "gn:dem":145,
    "gn:feature_class":"P",
    "gn:feature_code":"PPL",
    "gn:name":"Sinsk",
    "gn:population":0,
    "gn:timezone":"Europe/Minsk",
    "iso:country":"BY",
    "name:rus_x_preferred":[
        "\u0421\u0438\u043d\u0441\u043a"
    ],
    "wof:name":"Sinsk",
    "wof:placetype":"locality"
},
  "geometry": {"coordinates":[28.6841,55.8531],"type":"Point"}
}