{
  "type": "Feature",
  "properties": {
    "gn:admin1_code":"7.0",
    "gn:asciiname":"Svobodnoye",
    "gn:country_code":"BY",
    "gn:dem":151,
    "gn:feature_class":"P",
    "gn:feature_code":"PPL",
    "gn:name":"Svobodnoye",
    "gn:population":0,
    "gn:timezone":"Europe/Minsk",
    "iso:country":"BY",
    "name:rus_x_preferred":[
        "\u0421\u0432\u043e\u0431\u043e\u0434\u043d\u043e\u0435"
    ],
    "wof:name":"Svobodnoye",
    "wof:placetype":"locality"
},
  "geometry": {"coordinates":[29.7149,54.8417],"type":"Point"}
}