{
  "type": "Feature",
  "properties": {
    "gn:admin1_code":"1.0",
    "gn:asciiname":"Pogubyatichi",
    "gn:country_code":"BY",
    "gn:dem":156,
    "gn:feature_class":"P",
    "gn:feature_code":"PPL",
    "gn:name":"Pogubyatichi",
    "gn:population":0,
    "gn:timezone":"Europe/Minsk",
    "iso:country":"BY",
    "name:rus_x_preferred":[
        "\u041f\u043e\u0433\u0443\u0431\u044f\u0442\u0438\u0447\u0438"
    ],
    "wof:name":"Pogubyatichi",
    "wof:placetype":"locality"
},
  "geometry": {"coordinates":[23.4058,52.2787],"type":"Point"}
}