{
  "type": "Feature",
  "properties": {
    "gn:admin1_code":"5.0",
    "gn:asciiname":"Palik",
    "gn:country_code":"BY",
    "gn:dem":150,
    "gn:feature_class":"P",
    "gn:feature_code":"PPL",
    "gn:name":"Palik",
    "gn:population":0,
    "gn:timezone":"Europe/Minsk",
    "iso:country":"BY",
    "name:eng_x_preferred":[
        "Palik"
    ],
    "name:rus_x_preferred":[
        "\u041f\u0430\u043b\u0438\u043a"
    ],
    "wof:name":"Palik",
    "wof:placetype":"locality"
},
  "geometry": {"coordinates":[28.4497,54.5256],"type":"Point"}
}