{
  "type": "Feature",
  "properties": {
    "gn:admin1_code":"2.0",
    "gn:asciiname":"Gayek",
    "gn:country_code":"BY",
    "gn:dem":146,
    "gn:feature_class":"P",
    "gn:feature_code":"PPL",
    "gn:name":"Gayek",
    "gn:population":0,
    "gn:timezone":"Europe/Minsk",
    "iso:country":"BY",
    "name:rus_x_preferred":[
        "\u0413\u0430\u0435\u043a"
    ],
    "wof:name":"Gayek",
    "wof:placetype":"locality"
},
  "geometry": {"coordinates":[31.1503,52.9648],"type":"Point"}
}