{
  "type": "Feature",
  "properties": {
    "gn:admin1_code":"7.0",
    "gn:asciiname":"Zachist'ye",
    "gn:country_code":"BY",
    "gn:dem":146,
    "gn:feature_class":"P",
    "gn:feature_code":"PPL",
    "gn:name":"Zachist\u2019ye",
    "gn:population":0,
    "gn:timezone":"Europe/Minsk",
    "iso:country":"BY",
    "name:rus_x_preferred":[
        "\u0417\u0430\u0447\u0438\u0441\u0442\u044c\u0435"
    ],
    "name:und_x_variant":[
        "Zachist\u2019ye"
    ],
    "wof:name":"Zachist'ye",
    "wof:placetype":"locality"
},
  "geometry": {"coordinates":[28.9006,55.0799],"type":"Point"}
}