{
  "type": "Feature",
  "properties": {
    "gn:admin1_code":"3.0",
    "gn:asciiname":"Tadino",
    "gn:country_code":"BY",
    "gn:dem":203,
    "gn:feature_class":"P",
    "gn:feature_code":"PPL",
    "gn:name":"Tadino",
    "gn:population":0,
    "gn:timezone":"Europe/Minsk",
    "iso:country":"BY",
    "name:bel_x_preferred":[
        "Tadzino"
    ],
    "name:bel_x_variant":[
        "\u0422\u0430\u0434\u0437\u0456\u043d\u043e"
    ],
    "name:rus_x_preferred":[
        "\u0422\u0430\u0434\u0438\u043d\u043e"
    ],
    "wof:name":"Tadino",
    "wof:placetype":"locality"
},
  "geometry": {"coordinates":[24.5817,53.1971],"type":"Point"}
}