{
  "type": "Feature",
  "properties": {
    "gn:admin1_code":"7.0",
    "gn:asciiname":"Mateykovo",
    "gn:country_code":"BY",
    "gn:dem":136,
    "gn:feature_class":"P",
    "gn:feature_code":"PPL",
    "gn:name":"Mateykovo",
    "gn:population":0,
    "gn:timezone":"Europe/Minsk",
    "iso:country":"BY",
    "name:rus_x_preferred":[
        "\u041c\u0430\u0442\u0435\u0439\u043a\u043e\u0432\u043e"
    ],
    "name:und_x_variant":[
        "Moteykovo"
    ],
    "wof:name":"Mateykovo",
    "wof:placetype":"locality"
},
  "geometry": {"coordinates":[28.5703,55.6391],"type":"Point"}
}