{
  "type": "Feature",
  "properties": {
    "gn:admin1_code":"7.0",
    "gn:asciiname":"Dorokhi",
    "gn:country_code":"BY",
    "gn:dem":158,
    "gn:feature_class":"P",
    "gn:feature_code":"PPL",
    "gn:name":"Dorokhi",
    "gn:population":0,
    "gn:timezone":"Europe/Minsk",
    "iso:country":"BY",
    "name:rus_x_preferred":[
        "\u0414\u043e\u0440\u043e\u0445\u0438"
    ],
    "wof:name":"Dorokhi",
    "wof:placetype":"locality"
},
  "geometry": {"coordinates":[30.3662,55.8055],"type":"Point"}
}