{
  "type": "Feature",
  "properties": {
    "gn:admin1_code":"3.0",
    "gn:asciiname":"Khoruzhevtsy",
    "gn:country_code":"BY",
    "gn:dem":147,
    "gn:feature_class":"P",
    "gn:feature_code":"PPL",
    "gn:name":"Khoruzhevtsy",
    "gn:population":0,
    "gn:timezone":"Europe/Minsk",
    "iso:country":"BY",
    "name:rus_x_preferred":[
        "\u0425\u043e\u0440\u0443\u0436\u0435\u0432\u0446\u044b"
    ],
    "wof:name":"Khoruzhevtsy",
    "wof:placetype":"locality"
},
  "geometry": {"coordinates":[25.4789,53.9247],"type":"Point"}
}