{
  "type": "Feature",
  "properties": {
    "gn:admin1_code":"7.0",
    "gn:asciiname":"Osipovshchina",
    "gn:country_code":"BY",
    "gn:dem":231,
    "gn:feature_class":"P",
    "gn:feature_code":"PPL",
    "gn:name":"Osipovshchina",
    "gn:population":0,
    "gn:timezone":"Europe/Minsk",
    "iso:country":"BY",
    "name:rus_x_preferred":[
        "\u041e\u0441\u0438\u043f\u043e\u0432\u0449\u0438\u043d\u0430"
    ],
    "wof:name":"Osipovshchina",
    "wof:placetype":"locality"
},
  "geometry": {"coordinates":[30.5313,55.093],"type":"Point"}
}