{
  "type": "Feature",
  "properties": {
    "gn:admin1_code":"7.0",
    "gn:asciiname":"Peshkovtsy",
    "gn:country_code":"BY",
    "gn:dem":199,
    "gn:feature_class":"P",
    "gn:feature_code":"PPL",
    "gn:name":"Peshkovtsy",
    "gn:population":0,
    "gn:timezone":"Europe/Minsk",
    "iso:country":"BY",
    "name:rus_x_preferred":[
        "\u041f\u0435\u0448\u043a\u043e\u0432\u0446\u044b"
    ],
    "name:und_x_variant":[
        "Pieszkowce",
        "Peshkovtsy",
        "Peshkovtse"
    ],
    "wof:name":"Peshkovtsy",
    "wof:placetype":"locality"
},
  "geometry": {"coordinates":[26.3769,54.9984],"type":"Point"}
}