{
  "type": "Feature",
  "properties": {
    "gn:admin1_code":"3.0",
    "gn:asciiname":"Cherkasy",
    "gn:country_code":"BY",
    "gn:dem":217,
    "gn:feature_class":"P",
    "gn:feature_code":"PPL",
    "gn:name":"Cherkasy",
    "gn:population":0,
    "gn:timezone":"Europe/Minsk",
    "iso:country":"BY",
    "name:rus_x_preferred":[
        "\u0427\u0435\u0440\u043a\u0430\u0441\u044b"
    ],
    "wof:name":"Cherkasy",
    "wof:placetype":"locality"
},
  "geometry": {"coordinates":[26.1226,54.356],"type":"Point"}
}