{
  "type": "Feature",
  "properties": {
    "gn:admin1_code":"5.0",
    "gn:asciiname":"Magalevshchina",
    "gn:country_code":"BY",
    "gn:dem":188,
    "gn:feature_class":"P",
    "gn:feature_code":"PPL",
    "gn:name":"Magalevshchina",
    "gn:population":0,
    "gn:timezone":"Europe/Minsk",
    "iso:country":"BY",
    "name:rus_x_preferred":[
        "\u041c\u0430\u0433\u0430\u043b\u0435\u0432\u0449\u0438\u043d\u0430"
    ],
    "name:und_x_variant":[
        "Mogilevshchina"
    ],
    "wof:name":"Magalevshchina",
    "wof:placetype":"locality"
},
  "geometry": {"coordinates":[27.2701,53.6488],"type":"Point"}
}