{
  "type": "Feature",
  "properties": {
    "gn:admin1_code":"3.0",
    "gn:asciiname":"Goroshki",
    "gn:country_code":"BY",
    "gn:dem":127,
    "gn:feature_class":"P",
    "gn:feature_code":"PPL",
    "gn:name":"Goroshki",
    "gn:population":0,
    "gn:timezone":"Europe/Minsk",
    "iso:country":"BY",
    "name:rus_x_preferred":[
        "\u0413\u043e\u0440\u043e\u0448\u043a\u0438"
    ],
    "wof:name":"Goroshki",
    "wof:placetype":"locality"
},
  "geometry": {"coordinates":[24.31866,53.5543],"type":"Point"}
}