{
  "type": "Feature",
  "properties": {
    "gn:admin1_code":"7.0",
    "gn:asciiname":"Pishchakino",
    "gn:country_code":"BY",
    "gn:dem":221,
    "gn:feature_class":"P",
    "gn:feature_code":"PPL",
    "gn:name":"Pishchakino",
    "gn:population":0,
    "gn:timezone":"Europe/Minsk",
    "iso:country":"BY",
    "name:rus_x_preferred":[
        "\u041f\u0438\u0449\u0430\u043a\u0438\u043d\u043e"
    ],
    "wof:name":"Pishchakino",
    "wof:placetype":"locality"
},
  "geometry": {"coordinates":[29.8799,54.5735],"type":"Point"}
}