{
  "type": "Feature",
  "properties": {
    "gn:admin1_code":"6.0",
    "gn:asciiname":"Aleksandrovka Pervaya",
    "gn:country_code":"BY",
    "gn:dem":145,
    "gn:feature_class":"P",
    "gn:feature_code":"PPL",
    "gn:name":"Aleksandrovka Pervaya",
    "gn:population":0,
    "gn:timezone":"Europe/Minsk",
    "iso:country":"BY",
    "name:rus_x_preferred":[
        "\u0410\u043b\u0435\u043a\u0441\u0430\u043d\u0434\u0440\u043e\u0432\u043a\u0430 \u041f\u0435\u0440\u0432\u0430\u044f"
    ],
    "wof:name":"Aleksandrovka Pervaya",
    "wof:placetype":"locality"
},
  "geometry": {"coordinates":[31.1427,53.5058],"type":"Point"}
}