{
  "type": "Feature",
  "properties": {
    "gn:admin1_code":"2.0",
    "gn:asciiname":"Temnyy Osov",
    "gn:country_code":"BY",
    "gn:dem":139,
    "gn:feature_class":"P",
    "gn:feature_code":"PPL",
    "gn:name":"T\u00ebmnyy Osov",
    "gn:population":0,
    "gn:timezone":"Europe/Minsk",
    "iso:country":"BY",
    "name:rus_x_preferred":[
        "\u0422\u0451\u043c\u043d\u044b\u0439 \u041e\u0441\u043e\u0432"
    ],
    "name:und_x_variant":[
        "T\u00ebmnyy Osov"
    ],
    "wof:name":"Temnyy Osov",
    "wof:placetype":"locality"
},
  "geometry": {"coordinates":[30.7983,52.649],"type":"Point"}
}