{
  "type": "Feature",
  "properties": {
    "gn:admin1_code":"3.0",
    "gn:asciiname":"Yuzefovka",
    "gn:country_code":"BY",
    "gn:dem":155,
    "gn:feature_class":"P",
    "gn:feature_code":"PPL",
    "gn:name":"Yuzefovka",
    "gn:population":0,
    "gn:timezone":"Europe/Minsk",
    "iso:country":"BY",
    "name:rus_x_preferred":[
        "\u042e\u0437\u0435\u0444\u043e\u0432\u043a\u0430"
    ],
    "wof:name":"Yuzefovka",
    "wof:placetype":"locality"
},
  "geometry": {"coordinates":[23.7991,53.6009],"type":"Point"}
}