{
  "type": "Feature",
  "properties": {
    "gn:admin1_code":"3.0",
    "gn:asciiname":"Klyukovichi",
    "gn:country_code":"BY",
    "gn:dem":143,
    "gn:feature_class":"P",
    "gn:feature_code":"PPL",
    "gn:name":"Klyukovichi",
    "gn:population":0,
    "gn:timezone":"Europe/Minsk",
    "iso:country":"BY",
    "name:bel_x_preferred":[
        "Klyukavichy"
    ],
    "name:bel_x_variant":[
        "\u041a\u043b\u044e\u043a\u0430\u0432\u0456\u0447\u044b"
    ],
    "name:rus_x_preferred":[
        "\u041a\u043b\u044e\u043a\u043e\u0432\u0438\u0447\u0438"
    ],
    "wof:name":"Klyukovichi",
    "wof:placetype":"locality"
},
  "geometry": {"coordinates":[25.20429,53.68895],"type":"Point"}
}