{
  "type": "Feature",
  "properties": {
    "gn:admin1_code":"1.0",
    "gn:asciiname":"Turskoye",
    "gn:country_code":"BY",
    "gn:dem":129,
    "gn:feature_class":"P",
    "gn:feature_code":"PPL",
    "gn:name":"Turskoye",
    "gn:population":0,
    "gn:timezone":"Europe/Minsk",
    "iso:country":"BY",
    "name:rus_x_preferred":[
        "\u0422\u0443\u0440\u0441\u043a\u043e\u0435"
    ],
    "wof:name":"Turskoye",
    "wof:placetype":"locality"
},
  "geometry": {"coordinates":[27.2933,52.0345],"type":"Point"}
}