{
  "type": "Feature",
  "properties": {
    "gn:admin1_code":"6.0",
    "gn:asciiname":"Ganaratovo",
    "gn:country_code":"BY",
    "gn:dem":160,
    "gn:feature_class":"P",
    "gn:feature_code":"PPL",
    "gn:name":"Ganaratovo",
    "gn:population":0,
    "gn:timezone":"Europe/Minsk",
    "iso:country":"BY",
    "name:rus_x_preferred":[
        "\u0413\u0430\u043d\u0430\u0440\u0430\u0442\u043e\u0432\u043e"
    ],
    "name:und_x_variant":[
        "Gonoratovo"
    ],
    "wof:name":"Ganaratovo",
    "wof:placetype":"locality"
},
  "geometry": {"coordinates":[29.2921,53.6241],"type":"Point"}
}