{
  "type": "Feature",
  "properties": {
    "gn:admin1_code":"0.0",
    "gn:asciiname":"Novaya Derevnya",
    "gn:country_code":"BY",
    "gn:dem":157,
    "gn:feature_class":"P",
    "gn:feature_code":"PPL",
    "gn:name":"Novaya Derevnya",
    "gn:population":0,
    "gn:timezone":"Europe/Minsk",
    "iso:country":"BY",
    "name:ceb_x_preferred":[
        "Novaya Derevnya"
    ],
    "name:rus_x_preferred":[
        "\u041d\u043e\u0432\u0430\u044f \u0414\u0435\u0440\u0435\u0432\u043d\u044f"
    ],
    "name:ukr_x_preferred":[
        "\u041d\u043e\u0432\u0435 \u0421\u0435\u043b\u043e"
    ],
    "wof:name":"Novaya Derevnya",
    "wof:placetype":"locality"
},
  "geometry": {"coordinates":[29.36667000000001,53.16667],"type":"Point"}
}