{
  "type": "Feature",
  "properties": {
    "gn:admin1_code":"5.0",
    "gn:asciiname":"Zavishino",
    "gn:country_code":"BY",
    "gn:dem":200,
    "gn:feature_class":"P",
    "gn:feature_code":"PPL",
    "gn:name":"Zavishino",
    "gn:population":0,
    "gn:timezone":"Europe/Minsk",
    "iso:country":"BY",
    "name:rus_x_preferred":[
        "\u0417\u0430\u0432\u0438\u0448\u0438\u043d\u043e"
    ],
    "wof:name":"Zavishino",
    "wof:placetype":"locality"
},
  "geometry": {"coordinates":[27.6545,54.4774],"type":"Point"}
}