{
  "type": "Feature",
  "properties": {
    "gn:admin1_code":"7.0",
    "gn:asciiname":"Sergi",
    "gn:country_code":"BY",
    "gn:dem":168,
    "gn:feature_class":"P",
    "gn:feature_code":"PPL",
    "gn:name":"Sergi",
    "gn:population":0,
    "gn:timezone":"Europe/Minsk",
    "iso:country":"BY",
    "name:rus_x_preferred":[
        "\u0421\u0435\u0440\u0433\u0438"
    ],
    "name:und_x_variant":[
        "Sierhy",
        "Sergy",
        "Sergi"
    ],
    "wof:name":"Sergi",
    "wof:placetype":"locality"
},
  "geometry": {"coordinates":[27.2879,54.9963],"type":"Point"}
}