{
  "type": "Feature",
  "properties": {
    "gn:admin1_code":"2.0",
    "gn:asciiname":"Malimony",
    "gn:country_code":"BY",
    "gn:dem":139,
    "gn:feature_class":"P",
    "gn:feature_code":"PPL",
    "gn:name":"Malimony",
    "gn:population":0,
    "gn:timezone":"Europe/Minsk",
    "iso:country":"BY",
    "name:rus_x_preferred":[
        "\u041c\u0430\u043b\u0438\u043c\u043e\u043d\u044b"
    ],
    "wof:name":"Malimony",
    "wof:placetype":"locality"
},
  "geometry": {"coordinates":[29.281,52.8689],"type":"Point"}
}