{
  "type": "Feature",
  "properties": {
    "gn:admin1_code":"6.0",
    "gn:asciiname":"Zatish'ye",
    "gn:country_code":"BY",
    "gn:dem":174,
    "gn:feature_class":"P",
    "gn:feature_code":"PPL",
    "gn:name":"Zatish\u2019ye",
    "gn:population":0,
    "gn:timezone":"Europe/Minsk",
    "iso:country":"BY",
    "name:rus_x_preferred":[
        "\u0417\u0430\u0442\u0438\u0448\u044c\u0435"
    ],
    "name:und_x_variant":[
        "Zatish\u2019ye"
    ],
    "wof:name":"Zatish'ye",
    "wof:placetype":"locality"
},
  "geometry": {"coordinates":[30.3776,53.8461],"type":"Point"}
}