{
  "type": "Feature",
  "properties": {
    "gn:admin1_code":"6.0",
    "gn:asciiname":"Malaya Grava",
    "gn:country_code":"BY",
    "gn:dem":157,
    "gn:feature_class":"P",
    "gn:feature_code":"PPL",
    "gn:name":"Malaya Grava",
    "gn:population":0,
    "gn:timezone":"Europe/Minsk",
    "iso:country":"BY",
    "name:rus_x_preferred":[
        "\u041c\u0430\u043b\u0430\u044f \u0413\u0440\u0430\u0432\u0430"
    ],
    "wof:name":"Malaya Grava",
    "wof:placetype":"locality"
},
  "geometry": {"coordinates":[28.5935,53.4477],"type":"Point"}
}