{
  "type": "Feature",
  "properties": {
    "gn:admin1_code":"5.0",
    "gn:asciiname":"Krichki",
    "gn:country_code":"BY",
    "gn:dem":269,
    "gn:feature_class":"P",
    "gn:feature_code":"PPL",
    "gn:name":"Krichki",
    "gn:population":0,
    "gn:timezone":"Europe/Minsk",
    "iso:country":"BY",
    "name:rus_x_preferred":[
        "\u041a\u0440\u0438\u0447\u043a\u0438"
    ],
    "wof:name":"Krichki",
    "wof:placetype":"locality"
},
  "geometry": {"coordinates":[27.2231,54.0737],"type":"Point"}
}