{
  "type": "Feature",
  "properties": {
    "gn:admin1_code":"7.0",
    "gn:asciiname":"Snegi",
    "gn:country_code":"BY",
    "gn:dem":133,
    "gn:feature_class":"P",
    "gn:feature_code":"PPL",
    "gn:name":"Snegi",
    "gn:population":0,
    "gn:timezone":"Europe/Minsk",
    "iso:country":"BY",
    "name:rus_x_preferred":[
        "\u0421\u043d\u0435\u0433\u0438"
    ],
    "name:und_x_variant":[
        "\u015aniegi",
        "Snegi"
    ],
    "wof:name":"Snegi",
    "wof:placetype":"locality"
},
  "geometry": {"coordinates":[27.3142,55.451],"type":"Point"}
}