{
  "type": "Feature",
  "properties": {
    "gn:admin1_code":"7.0",
    "gn:asciiname":"Zhurzhevo",
    "gn:country_code":"BY",
    "gn:dem":163,
    "gn:feature_class":"P",
    "gn:feature_code":"PPL",
    "gn:name":"Zhurzh\u00ebvo",
    "gn:population":0,
    "gn:timezone":"Europe/Minsk",
    "iso:country":"BY",
    "name:rus_x_preferred":[
        "\u0416\u0443\u0440\u0436\u0451\u0432\u043e"
    ],
    "name:und_x_variant":[
        "Zhurzh\u00ebvo"
    ],
    "wof:name":"Zhurzhevo",
    "wof:placetype":"locality"
},
  "geometry": {"coordinates":[30.2496,55.2253],"type":"Point"}
}