{
  "type": "Feature",
  "properties": {
    "gn:admin1_code":"2.0",
    "gn:asciiname":"Fizinki",
    "gn:country_code":"BY",
    "gn:dem":114,
    "gn:feature_class":"P",
    "gn:feature_code":"PPL",
    "gn:name":"Fizinki",
    "gn:population":0,
    "gn:timezone":"Europe/Minsk",
    "iso:country":"BY",
    "name:rus_x_preferred":[
        "\u0424\u0438\u0437\u0438\u043d\u043a\u0438"
    ],
    "wof:name":"Fizinki",
    "wof:placetype":"locality"
},
  "geometry": {"coordinates":[29.4794,51.7721],"type":"Point"}
}