{
  "type": "Feature",
  "properties": {
    "gn:admin1_code":"5.0",
    "gn:asciiname":"Bol'shiye Bakshty",
    "gn:country_code":"BY",
    "gn:dem":203,
    "gn:feature_class":"P",
    "gn:feature_code":"PPL",
    "gn:name":"Bol\u2019shiye Bakshty",
    "gn:population":0,
    "gn:timezone":"Europe/Minsk",
    "iso:country":"BY",
    "name:rus_x_preferred":[
        "\u0411\u043e\u043b\u044c\u0448\u0438\u0435 \u0411\u0430\u043a\u0448\u0442\u044b"
    ],
    "name:und_x_variant":[
        "Bol\u2019shiye Bakshty"
    ],
    "wof:name":"Bol'shiye Bakshty",
    "wof:placetype":"locality"
},
  "geometry": {"coordinates":[27.2844,54.1904],"type":"Point"}
}