{
  "type": "Feature",
  "properties": {
    "gn:admin1_code":"7.0",
    "gn:asciiname":"Osinniki",
    "gn:country_code":"BY",
    "gn:dem":156,
    "gn:feature_class":"P",
    "gn:feature_code":"PPL",
    "gn:name":"Osinniki",
    "gn:population":0,
    "gn:timezone":"Europe/Minsk",
    "iso:country":"BY",
    "name:rus_x_preferred":[
        "\u041e\u0441\u0438\u043d\u043d\u0438\u043a\u0438"
    ],
    "wof:name":"Osinniki",
    "wof:placetype":"locality"
},
  "geometry": {"coordinates":[28.8404,55.9301],"type":"Point"}
}