{
  "type": "Feature",
  "properties": {
    "gn:admin1_code":"5.0",
    "gn:asciiname":"Budslaw",
    "gn:country_code":"BY",
    "gn:dem":178,
    "gn:feature_class":"P",
    "gn:feature_code":"PPL",
    "gn:name":"Buds\u0142aw",
    "gn:population":0,
    "gn:timezone":"Europe/Minsk",
    "iso:country":"BY",
    "name:bel_x_preferred":[
        "\u0411\u0443\u0434\u0441\u043b\u0430\u045e"
    ],
    "name:rus_x_preferred":[
        "Pos\u00eblok Budslav"
    ],
    "name:und_x_variant":[
        "Stary Buds\u0142aw",
        "Staryy Budslav",
        "Buds\u0142aw"
    ],
    "wof:name":"Budslaw",
    "wof:placetype":"locality"
},
  "geometry": {"coordinates":[27.4132,54.7985],"type":"Point"}
}