{
  "type": "Feature",
  "properties": {
    "gn:admin1_code":"0.0",
    "gn:asciiname":"Korost'",
    "gn:country_code":"BY",
    "gn:dem":128,
    "gn:feature_class":"P",
    "gn:feature_code":"PPL",
    "gn:name":"Korost\u2019",
    "gn:population":0,
    "gn:timezone":"Europe/Minsk",
    "iso:country":"BY",
    "name:und_x_variant":[
        "Lesnichestvo Koros\u2019is",
        "Korost\u2019"
    ],
    "wof:name":"Korost'",
    "wof:placetype":"locality"
},
  "geometry": {"coordinates":[27.21667,51.93333],"type":"Point"}
}