{
  "type": "Feature",
  "properties": {
    "gn:admin1_code":"3.0",
    "gn:asciiname":"Yubileynaya",
    "gn:country_code":"BY",
    "gn:dem":165,
    "gn:feature_class":"P",
    "gn:feature_code":"PPL",
    "gn:name":"Yubileynaya",
    "gn:population":0,
    "gn:timezone":"Europe/Minsk",
    "iso:country":"BY",
    "name:rus_x_preferred":[
        "\u042e\u0431\u0438\u043b\u0435\u0439\u043d\u0430\u044f"
    ],
    "wof:name":"Yubileynaya",
    "wof:placetype":"locality"
},
  "geometry": {"coordinates":[24.0789,53.0239],"type":"Point"}
}