{
  "type": "Feature",
  "properties": {
    "gn:admin1_code":"0.0",
    "gn:asciiname":"Dobryy Ostrov",
    "gn:cc2":"BY",
    "gn:country_code":"BY",
    "gn:dem":138,
    "gn:feature_class":"P",
    "gn:feature_code":"PPL",
    "gn:name":"Dobryy Ostrov",
    "gn:population":0,
    "gn:timezone":"Europe/Minsk",
    "iso:country":"BY",
    "name:und_x_variant":[
        "Dobry Ostrov",
        "Dobryy Ostrov"
    ],
    "wof:name":"Dobryy Ostrov",
    "wof:placetype":"locality"
},
  "geometry": {"coordinates":[28.46667,52.61666999999999],"type":"Point"}
}