{
  "type": "Feature",
  "properties": {
    "gn:admin1_code":"2.0",
    "gn:asciiname":"Sverkov",
    "gn:country_code":"BY",
    "gn:dem":140,
    "gn:feature_class":"P",
    "gn:feature_code":"PPL",
    "gn:name":"Sverkov",
    "gn:population":0,
    "gn:timezone":"Europe/Minsk",
    "iso:country":"BY",
    "name:rus_x_preferred":[
        "\u0421\u0432\u0435\u0440\u043a\u043e\u0432"
    ],
    "wof:name":"Sverkov",
    "wof:placetype":"locality"
},
  "geometry": {"coordinates":[30.025,53.0499],"type":"Point"}
}