{
  "type": "Feature",
  "properties": {
    "gn:admin1_code":"5.0",
    "gn:asciiname":"Khotenovo",
    "gn:country_code":"BY",
    "gn:dem":165,
    "gn:feature_class":"P",
    "gn:feature_code":"PPL",
    "gn:name":"Khotenovo",
    "gn:population":0,
    "gn:timezone":"Europe/Minsk",
    "iso:country":"BY",
    "name:rus_x_preferred":[
        "\u0425\u043e\u0442\u0435\u043d\u043e\u0432\u043e"
    ],
    "wof:name":"Khotenovo",
    "wof:placetype":"locality"
},
  "geometry": {"coordinates":[28.0281,54.1394],"type":"Point"}
}