{
  "type": "Feature",
  "properties": {
    "gn:admin1_code":"2.0",
    "gn:asciiname":"Brilev",
    "gn:country_code":"BY",
    "gn:dem":139,
    "gn:feature_class":"P",
    "gn:feature_code":"PPL",
    "gn:name":"Brilev",
    "gn:population":0,
    "gn:timezone":"Europe/Minsk",
    "iso:country":"BY",
    "name:rus_x_preferred":[
        "\u0411\u0440\u0438\u043b\u0435\u0432"
    ],
    "wof:name":"Brilev",
    "wof:placetype":"locality"
},
  "geometry": {"coordinates":[30.8181,52.9553],"type":"Point"}
}