{
  "type": "Feature",
  "properties": {
    "gn:admin1_code":"5.0",
    "gn:asciiname":"Kukhty",
    "gn:country_code":"BY",
    "gn:dem":159,
    "gn:feature_class":"P",
    "gn:feature_code":"PPL",
    "gn:name":"Kukhty",
    "gn:population":0,
    "gn:timezone":"Europe/Minsk",
    "iso:country":"BY",
    "name:rus_x_preferred":[
        "\u041a\u0443\u0445\u0442\u044b"
    ],
    "wof:name":"Kukhty",
    "wof:placetype":"locality"
},
  "geometry": {"coordinates":[27.5554,53.1088],"type":"Point"}
}