{
  "type": "Feature",
  "properties": {
    "gn:admin1_code":"0.0",
    "gn:asciiname":"Samodumka",
    "gn:country_code":"BY",
    "gn:dem":156,
    "gn:feature_class":"P",
    "gn:feature_code":"PPL",
    "gn:name":"Samodumka",
    "gn:population":0,
    "gn:timezone":"Europe/Minsk",
    "iso:country":"BY",
    "wof:name":"Samodumka",
    "wof:placetype":"locality"
},
  "geometry": {"coordinates":[29.76667,53.55],"type":"Point"}
}