{
  "type": "Feature",
  "properties": {
    "gn:admin1_code":"1.0",
    "gn:asciiname":"Sashytsa",
    "gn:country_code":"BY",
    "gn:dem":159,
    "gn:feature_class":"P",
    "gn:feature_code":"PPL",
    "gn:name":"Sashytsa",
    "gn:population":0,
    "gn:timezone":"Europe/Minsk",
    "iso:country":"BY",
    "name:bel_x_preferred":[
        "\u0421\u0430\u0448\u044b\u0446\u0430"
    ],
    "name:und_x_variant":[
        "Soshytsa",
        "Soshitsa",
        "Sashytsa"
    ],
    "wof:name":"Sashytsa",
    "wof:placetype":"locality"
},
  "geometry": {"coordinates":[24.8094,52.5967],"type":"Point"}
}