{
  "type": "Feature",
  "properties": {
    "gn:admin1_code":"5.0",
    "gn:asciiname":"Zabrod'ye",
    "gn:country_code":"BY",
    "gn:dem":153,
    "gn:feature_class":"P",
    "gn:feature_code":"PPL",
    "gn:name":"Zabrod\u2019ye",
    "gn:population":0,
    "gn:timezone":"Europe/Minsk",
    "iso:country":"BY",
    "name:rus_x_preferred":[
        "\u0417\u0430\u0431\u0440\u043e\u0434\u044c\u0435"
    ],
    "name:und_x_variant":[
        "Zabrod\u2019ye"
    ],
    "wof:name":"Zabrod'ye",
    "wof:placetype":"locality"
},
  "geometry": {"coordinates":[26.7301,54.5444],"type":"Point"}
}