{
  "type": "Feature",
  "properties": {
    "gn:admin1_code":"7.0",
    "gn:asciiname":"Ivanovo",
    "gn:country_code":"BY",
    "gn:dem":170,
    "gn:feature_class":"P",
    "gn:feature_code":"PPL",
    "gn:name":"Ivanovo",
    "gn:population":0,
    "gn:timezone":"Europe/Minsk",
    "iso:country":"BY",
    "name:rus_x_preferred":[
        "\u0418\u0432\u0430\u043d\u043e\u0432\u043e"
    ],
    "wof:name":"Ivanovo",
    "wof:placetype":"locality"
},
  "geometry": {"coordinates":[29.9138,55.3611],"type":"Point"}
}