{
  "type": "Feature",
  "properties": {
    "gn:admin1_code":"5.0",
    "gn:asciiname":"Mezhnaya Sloboda",
    "gn:country_code":"BY",
    "gn:dem":180,
    "gn:feature_class":"P",
    "gn:feature_code":"PPL",
    "gn:name":"Mezhnaya Sloboda",
    "gn:population":0,
    "gn:timezone":"Europe/Minsk",
    "iso:country":"BY",
    "name:rus_x_preferred":[
        "\u041c\u0435\u0436\u043d\u0430\u044f \u0421\u043b\u043e\u0431\u043e\u0434\u0430"
    ],
    "name:und_x_variant":[
        "Slobudka",
        "S\u0142ob\u00f3dka",
        "Mezhnaya Sloboda"
    ],
    "wof:name":"Mezhnaya Sloboda",
    "wof:placetype":"locality"
},
  "geometry": {"coordinates":[26.5991,52.94300000000001],"type":"Point"}
}