{
  "type": "Feature",
  "properties": {
    "gn:admin1_code":"0.0",
    "gn:asciiname":"Stazhyna",
    "gn:cc2":"BY",
    "gn:country_code":"BY",
    "gn:dem":182,
    "gn:feature_class":"P",
    "gn:feature_code":"PPL",
    "gn:name":"Stazhyna",
    "gn:population":0,
    "gn:timezone":"Europe/Minsk",
    "iso:country":"BY",
    "name:und_x_variant":[
        "Starzyna",
        "Stazhyna"
    ],
    "wof:name":"Stazhyna",
    "wof:placetype":"locality"
},
  "geometry": {"coordinates":[27.46667,55.06667],"type":"Point"}
}