{
  "type": "Feature",
  "properties": {
    "gn:admin1_code":"3.0",
    "gn:asciiname":"Bol'shiye Bobrovniki",
    "gn:country_code":"BY",
    "gn:dem":184,
    "gn:feature_class":"P",
    "gn:feature_code":"PPL",
    "gn:name":"Bol\u2019shiye Bobrovniki",
    "gn:population":0,
    "gn:timezone":"Europe/Minsk",
    "iso:country":"BY",
    "name:rus_x_preferred":[
        "\u0411\u043e\u043b\u044c\u0448\u0438\u0435 \u0411\u043e\u0431\u0440\u043e\u0432\u043d\u0438\u043a\u0438"
    ],
    "name:und_x_variant":[
        "Bol\u2019shiye Bobrovniki"
    ],
    "wof:name":"Bol'shiye Bobrovniki",
    "wof:placetype":"locality"
},
  "geometry": {"coordinates":[24.2586,52.9717],"type":"Point"}
}