{
  "type": "Feature",
  "properties": {
    "gn:admin1_code":"5.0",
    "gn:asciiname":"Kulevshchina",
    "gn:country_code":"BY",
    "gn:dem":189,
    "gn:feature_class":"P",
    "gn:feature_code":"PPL",
    "gn:name":"Kulevshchina",
    "gn:population":0,
    "gn:timezone":"Europe/Minsk",
    "iso:country":"BY",
    "name:rus_x_preferred":[
        "\u041a\u0443\u043b\u0435\u0432\u0449\u0438\u043d\u0430"
    ],
    "wof:name":"Kulevshchina",
    "wof:placetype":"locality"
},
  "geometry": {"coordinates":[26.896,54.231],"type":"Point"}
}