{
  "type": "Feature",
  "properties": {
    "gn:admin1_code":"1.0",
    "gn:asciiname":"Uzlyazh'ye",
    "gn:country_code":"BY",
    "gn:dem":132,
    "gn:feature_class":"P",
    "gn:feature_code":"PPL",
    "gn:name":"Uzlyazh\u2019ye",
    "gn:population":0,
    "gn:timezone":"Europe/Minsk",
    "iso:country":"BY",
    "name:rus_x_preferred":[
        "\u0423\u0437\u043b\u044f\u0436\u044c\u0435"
    ],
    "name:und_x_variant":[
        "Uzlyazh\u2019ye"
    ],
    "wof:name":"Uzlyazh'ye",
    "wof:placetype":"locality"
},
  "geometry": {"coordinates":[26.95,51.8494],"type":"Point"}
}