{
  "type": "Feature",
  "properties": {
    "gn:admin1_code":"6.0",
    "gn:asciiname":"Tserkovishche",
    "gn:country_code":"BY",
    "gn:dem":162,
    "gn:feature_class":"P",
    "gn:feature_code":"PPL",
    "gn:name":"Tserkovishche",
    "gn:population":0,
    "gn:timezone":"Europe/Minsk",
    "iso:country":"BY",
    "name:rus_x_preferred":[
        "\u0426\u0435\u0440\u043a\u043e\u0432\u0438\u0449\u0435"
    ],
    "wof:name":"Tserkovishche",
    "wof:placetype":"locality"
},
  "geometry": {"coordinates":[31.9324,53.6785],"type":"Point"}
}