{
  "type": "Feature",
  "properties": {
    "gn:admin1_code":"6.0",
    "gn:asciiname":"Voytekhovo",
    "gn:country_code":"BY",
    "gn:dem":142,
    "gn:feature_class":"P",
    "gn:feature_code":"PPL",
    "gn:name":"Voytekhovo",
    "gn:population":0,
    "gn:timezone":"Europe/Minsk",
    "iso:country":"BY",
    "name:rus_x_preferred":[
        "\u0412\u043e\u0439\u0442\u0435\u0445\u043e\u0432\u043e"
    ],
    "name:und_x_variant":[
        "Voytsekhovo"
    ],
    "wof:name":"Voytekhovo",
    "wof:placetype":"locality"
},
  "geometry": {"coordinates":[28.7055,52.8446],"type":"Point"}
}