{
  "type": "Feature",
  "properties": {
    "gn:admin1_code":"2.0",
    "gn:asciiname":"Glushets",
    "gn:country_code":"BY",
    "gn:dem":109,
    "gn:feature_class":"P",
    "gn:feature_code":"PPL",
    "gn:name":"Glushets",
    "gn:population":0,
    "gn:timezone":"Europe/Minsk",
    "iso:country":"BY",
    "name:rus_x_preferred":[
        "\u0413\u043b\u0443\u0448\u0435\u0446"
    ],
    "wof:name":"Glushets",
    "wof:placetype":"locality"
},
  "geometry": {"coordinates":[30.6088,51.7325],"type":"Point"}
}