{
  "type": "Feature",
  "properties": {
    "gn:admin1_code":"5.0",
    "gn:asciiname":"Rozovka",
    "gn:country_code":"BY",
    "gn:dem":225,
    "gn:feature_class":"P",
    "gn:feature_code":"PPL",
    "gn:name":"Rozovka",
    "gn:population":0,
    "gn:timezone":"Europe/Minsk",
    "iso:country":"BY",
    "name:rus_x_preferred":[
        "\u0420\u043e\u0437\u043e\u0432\u043a\u0430"
    ],
    "wof:name":"Rozovka",
    "wof:placetype":"locality"
},
  "geometry": {"coordinates":[27.0864,53.7471],"type":"Point"}
}