{
  "type": "Feature",
  "properties": {
    "gn:admin1_code":"3.0",
    "gn:asciiname":"Mokhnachi",
    "gn:country_code":"BY",
    "gn:dem":172,
    "gn:feature_class":"P",
    "gn:feature_code":"PPL",
    "gn:name":"Mokhnachi",
    "gn:population":0,
    "gn:timezone":"Europe/Minsk",
    "iso:country":"BY",
    "name:rus_x_preferred":[
        "\u041c\u043e\u0445\u043d\u0430\u0447\u0438"
    ],
    "wof:name":"Mokhnachi",
    "wof:placetype":"locality"
},
  "geometry": {"coordinates":[25.0776,52.9476],"type":"Point"}
}