{
  "type": "Feature",
  "properties": {
    "gn:admin1_code":"7.0",
    "gn:asciiname":"Pishchalevka",
    "gn:country_code":"BY",
    "gn:dem":140,
    "gn:feature_class":"P",
    "gn:feature_code":"PPL",
    "gn:name":"Pishchalevka",
    "gn:population":0,
    "gn:timezone":"Europe/Minsk",
    "iso:country":"BY",
    "name:rus_x_preferred":[
        "\u041f\u0438\u0449\u0430\u043b\u0435\u0432\u043a\u0430"
    ],
    "name:und_x_variant":[
        "Pishchelevka"
    ],
    "wof:name":"Pishchalevka",
    "wof:placetype":"locality"
},
  "geometry": {"coordinates":[27.7224,55.4927],"type":"Point"}
}