{
  "type": "Feature",
  "properties": {
    "gn:admin1_code":"5.0",
    "gn:asciiname":"Veleshino",
    "gn:country_code":"BY",
    "gn:dem":213,
    "gn:feature_class":"P",
    "gn:feature_code":"PPL",
    "gn:name":"Veleshino",
    "gn:population":0,
    "gn:timezone":"Europe/Minsk",
    "iso:country":"BY",
    "name:rus_x_preferred":[
        "\u0412\u0435\u043b\u0435\u0448\u0438\u043d\u043e"
    ],
    "name:und_x_variant":[
        "Veleshin"
    ],
    "wof:name":"Veleshino",
    "wof:placetype":"locality"
},
  "geometry": {"coordinates":[27.1688,53.1757],"type":"Point"}
}