{
  "type": "Feature",
  "properties": {
    "gn:admin1_code":"3.0",
    "gn:asciiname":"Kastsyani",
    "gn:country_code":"BY",
    "gn:dem":175,
    "gn:feature_class":"P",
    "gn:feature_code":"PPL",
    "gn:name":"Kastsyani",
    "gn:population":0,
    "gn:timezone":"Europe/Minsk",
    "iso:country":"BY",
    "name:bel_x_preferred":[
        "\u041a\u0430\u0441\u0446\u044f\u043d\u0456"
    ],
    "name:eng_x_preferred":[
        "Kosten\u00ebvo"
    ],
    "name:rus_x_preferred":[
        "\u041a\u043e\u0441\u0442\u0435\u043d\u0438"
    ],
    "name:und_x_variant":[
        "Kosten\u00ebvo",
        "Kastsyani",
        "Kosteni"
    ],
    "wof:name":"Kastsyani",
    "wof:placetype":"locality"
},
  "geometry": {"coordinates":[25.2055,53.0683],"type":"Point"}
}