{
  "type": "Feature",
  "properties": {
    "gn:admin1_code":"5.0",
    "gn:asciiname":"Dolgiy",
    "gn:country_code":"BY",
    "gn:dem":168,
    "gn:feature_class":"P",
    "gn:feature_code":"PPL",
    "gn:name":"Dolgiy",
    "gn:population":0,
    "gn:timezone":"Europe/Minsk",
    "iso:country":"BY",
    "name:rus_x_preferred":[
        "\u0414\u043e\u043b\u0433\u0438\u0439"
    ],
    "wof:name":"Dolgiy",
    "wof:placetype":"locality"
},
  "geometry": {"coordinates":[27.8714,53.5604],"type":"Point"}
}