{
  "type": "Feature",
  "properties": {
    "gn:admin1_code":"5.0",
    "gn:asciiname":"Lunitsa",
    "gn:country_code":"BY",
    "gn:dem":173,
    "gn:feature_class":"P",
    "gn:feature_code":"PPL",
    "gn:name":"Lunitsa",
    "gn:population":0,
    "gn:timezone":"Europe/Minsk",
    "iso:country":"BY",
    "name:rus_x_preferred":[
        "\u041b\u0443\u043d\u0438\u0446\u0430"
    ],
    "wof:name":"Lunitsa",
    "wof:placetype":"locality"
},
  "geometry": {"coordinates":[28.7304,53.7545],"type":"Point"}
}