{
  "type": "Feature",
  "properties": {
    "gn:admin1_code":"7.0",
    "gn:asciiname":"Pyatnitskoye",
    "gn:country_code":"BY",
    "gn:dem":142,
    "gn:feature_class":"P",
    "gn:feature_code":"PPL",
    "gn:name":"Pyatnitskoye",
    "gn:population":0,
    "gn:timezone":"Europe/Minsk",
    "iso:country":"BY",
    "name:rus_x_preferred":[
        "\u041f\u044f\u0442\u043d\u0438\u0446\u043a\u043e\u0435"
    ],
    "wof:name":"Pyatnitskoye",
    "wof:placetype":"locality"
},
  "geometry": {"coordinates":[29.7202,55.143],"type":"Point"}
}