{
  "type": "Feature",
  "properties": {
    "gn:admin1_code":"5.0",
    "gn:asciiname":"Mochulishche",
    "gn:country_code":"BY",
    "gn:dem":243,
    "gn:feature_class":"P",
    "gn:feature_code":"PPL",
    "gn:name":"Mochulishche",
    "gn:population":0,
    "gn:timezone":"Europe/Minsk",
    "iso:country":"BY",
    "name:rus_x_preferred":[
        "\u041c\u043e\u0447\u0443\u043b\u0438\u0449\u0435"
    ],
    "name:und_x_variant":[
        "Machulishche"
    ],
    "wof:name":"Mochulishche",
    "wof:placetype":"locality"
},
  "geometry": {"coordinates":[27.6384,54.0981],"type":"Point"}
}