{
  "type": "Feature",
  "properties": {
    "gn:admin1_code":"6.0",
    "gn:asciiname":"Shabli",
    "gn:country_code":"BY",
    "gn:dem":154,
    "gn:feature_class":"P",
    "gn:feature_code":"PPL",
    "gn:name":"Shabli",
    "gn:population":0,
    "gn:timezone":"Europe/Minsk",
    "iso:country":"BY",
    "name:rus_x_preferred":[
        "\u0428\u0430\u0431\u043b\u0438"
    ],
    "wof:name":"Shabli",
    "wof:placetype":"locality"
},
  "geometry": {"coordinates":[31.9465,53.0954],"type":"Point"}
}