{
  "type": "Feature",
  "properties": {
    "gn:admin1_code":"2.0",
    "gn:asciiname":"Berestechko",
    "gn:country_code":"BY",
    "gn:dem":124,
    "gn:feature_class":"P",
    "gn:feature_code":"PPL",
    "gn:name":"Berestechko",
    "gn:population":0,
    "gn:timezone":"Europe/Minsk",
    "iso:country":"BY",
    "name:rus_x_preferred":[
        "\u0411\u0435\u0440\u0435\u0441\u0442\u0435\u0447\u043a\u043e"
    ],
    "wof:name":"Berestechko",
    "wof:placetype":"locality"
},
  "geometry": {"coordinates":[30.0215,51.8422],"type":"Point"}
}