{
  "type": "Feature",
  "properties": {
    "gn:admin1_code":"2.0",
    "gn:asciiname":"Berestechko",
    "gn:country_code":"BY",
    "gn:dem":124,
    "gn:feature_class":"P",
    "gn:feature_code":"PPL",
    "gn:name":"Berestechko",
    "gn:population":0,
    "gn:timezone":"Europe/Minsk",
    "iso:country":"BY",
    "name:ara_x_preferred":[
        "\u0628\u064a\u0631\u064a\u0633\u062a\u064a\u062a\u0634\u0643\u0648"
    ],
    "name:azb_x_preferred":[
        "\u0628\u0631\u0633\u062a\u0686\u06a9\u0648"
    ],
    "name:bel_x_preferred":[
        "\u0411\u044d\u0440\u044d\u0441\u0442\u044d\u0447\u043a\u0430"
    ],
    "name:ceb_x_preferred":[
        "Berestechko"
    ],
    "name:ces_x_preferred":[
        "Bereste\u010dko"
    ],
    "name:crh_x_preferred":[
        "Bereste\u00e7ko"
    ],
    "name:deu_x_preferred":[
        "Berestetschko"
    ],
    "name:fas_x_preferred":[
        "\u0628\u0631\u0633\u062a\u0686\u06a9\u0648"
    ],
    "name:fra_x_preferred":[
        "Berestetchko"
    ],
    "name:heb_x_preferred":[
        "\u05d1\u05e8\u05e1\u05d8\u05e6'\u05e7\u05d4"
    ],
    "name:hsb_x_preferred":[
        "Bereste\u010dko"
    ],
    "name:hye_x_preferred":[
        "\u0532\u0565\u0580\u0565\u057d\u057f\u0565\u0579\u056f\u0578"
    ],
    "name:ita_x_preferred":[
        "Bereste\u010dko"
    ],
    "name:jpn_x_preferred":[
        "\u30d9\u30ec\u30b9\u30c6\u30fc\u30c1\u30b3"
    ],
    "name:kat_x_preferred":[
        "\u10d1\u10d4\u10e0\u10d4\u10e1\u10e2\u10d4\u10e9\u10d9\u10dd"
    ],
    "name:lav_x_preferred":[
        "Bereste\u010dko"
    ],
    "name:lit_x_preferred":[
        "Bereste\u010dka"
    ],
    "name:nno_x_preferred":[
        "Berestetsjko"
    ],
    "name:nor_x_preferred":[
        "Berestetsjko"
    ],
    "name:pol_x_preferred":[
        "Beresteczko"
    ],
    "name:ron_x_preferred":[
        "Beresteciko"
    ],
    "name:rue_x_preferred":[
        "\u0411\u0435\u0440\u0435\u0441\u0442\u0435\u0447\u043a\u043e"
    ],
    "name:rus_x_preferred":[
        "\u0411\u0435\u0440\u0435\u0441\u0442\u0435\u0447\u043a\u043e"
    ],
    "name:swe_x_preferred":[
        "Berestetjko"
    ],
    "name:ukr_x_preferred":[
        "\u0411\u0435\u0440\u0435\u0441\u0442\u0435\u0447\u043a\u043e"
    ],
    "name:vie_x_preferred":[
        "Berestechko"
    ],
    "name:zho_x_preferred":[
        "\u67cf\u65af\u53f0\u5947\u53ef"
    ],
    "wof:name":"Berestechko",
    "wof:placetype":"locality"
},
  "geometry": {"coordinates":[30.0215,51.8422],"type":"Point"}
}