{
  "type": "Feature",
  "properties": {
    "gn:admin1_code":"2.0",
    "gn:asciiname":"Kommunar",
    "gn:country_code":"BY",
    "gn:dem":159,
    "gn:feature_class":"P",
    "gn:feature_code":"PPL",
    "gn:name":"Kommunar",
    "gn:population":0,
    "gn:timezone":"Europe/Minsk",
    "iso:country":"BY",
    "name:rus_x_preferred":[
        "\u041a\u043e\u043c\u043c\u0443\u043d\u0430\u0440"
    ],
    "wof:name":"Kommunar",
    "wof:placetype":"locality"
},
  "geometry": {"coordinates":[31.2454,53.103],"type":"Point"}
}