{
  "type": "Feature",
  "properties": {
    "gn:admin1_code":"6.0",
    "gn:asciiname":"Volovtsy",
    "gn:country_code":"BY",
    "gn:dem":199,
    "gn:feature_class":"P",
    "gn:feature_code":"PPL",
    "gn:name":"Volovtsy",
    "gn:population":0,
    "gn:timezone":"Europe/Minsk",
    "iso:country":"BY",
    "name:rus_x_preferred":[
        "\u0412\u043e\u043b\u043e\u0432\u0446\u044b"
    ],
    "name:und_x_variant":[
        "Volkovtsy"
    ],
    "wof:name":"Volovtsy",
    "wof:placetype":"locality"
},
  "geometry": {"coordinates":[30.6911,54.4157],"type":"Point"}
}