{
  "type": "Feature",
  "properties": {
    "gn:admin1_code":"7.0",
    "gn:asciiname":"Tyabuty",
    "gn:country_code":"BY",
    "gn:dem":182,
    "gn:feature_class":"P",
    "gn:feature_code":"PPL",
    "gn:name":"Tyabuty",
    "gn:population":0,
    "gn:timezone":"Europe/Minsk",
    "iso:country":"BY",
    "name:rus_x_preferred":[
        "\u0422\u044f\u0431\u0443\u0442\u044b"
    ],
    "wof:name":"Tyabuty",
    "wof:placetype":"locality"
},
  "geometry": {"coordinates":[26.6078,55.1208],"type":"Point"}
}