{
  "type": "Feature",
  "properties": {
    "gn:admin1_code":"7.0",
    "gn:asciiname":"Mateyevtsy",
    "gn:country_code":"BY",
    "gn:dem":192,
    "gn:feature_class":"P",
    "gn:feature_code":"PPL",
    "gn:name":"Mateyevtsy",
    "gn:population":0,
    "gn:timezone":"Europe/Minsk",
    "iso:country":"BY",
    "name:rus_x_preferred":[
        "\u041c\u0430\u0442\u0435\u0435\u0432\u0446\u044b"
    ],
    "name:und_x_variant":[
        "Matseyyevtse",
        "Maciejowce",
        "Matsey\u00ebvtse",
        "Mateyevtsy"
    ],
    "wof:name":"Mateyevtsy",
    "wof:placetype":"locality"
},
  "geometry": {"coordinates":[27.6523,54.81100000000001],"type":"Point"}
}