{
  "type": "Feature",
  "properties": {
    "gn:admin1_code":"7.0",
    "gn:asciiname":"Yerygino",
    "gn:country_code":"BY",
    "gn:dem":176,
    "gn:feature_class":"P",
    "gn:feature_code":"PPL",
    "gn:name":"Yerygino",
    "gn:population":0,
    "gn:timezone":"Europe/Minsk",
    "iso:country":"BY",
    "name:rus_x_preferred":[
        "\u0415\u0440\u044b\u0433\u0438\u043d\u043e"
    ],
    "name:und_x_variant":[
        "Yarygino"
    ],
    "wof:name":"Yerygino",
    "wof:placetype":"locality"
},
  "geometry": {"coordinates":[29.8238,55.7368],"type":"Point"}
}