{
  "type": "Feature",
  "properties": {
    "gn:admin1_code":"7.0",
    "gn:asciiname":"Klevzy",
    "gn:country_code":"BY",
    "gn:dem":215,
    "gn:feature_class":"P",
    "gn:feature_code":"PPL",
    "gn:name":"Klevzy",
    "gn:population":0,
    "gn:timezone":"Europe/Minsk",
    "iso:country":"BY",
    "name:rus_x_preferred":[
        "\u041a\u043b\u0435\u0432\u0437\u044b"
    ],
    "wof:name":"Klevzy",
    "wof:placetype":"locality"
},
  "geometry": {"coordinates":[28.5955,54.9315],"type":"Point"}
}