{
  "type": "Feature",
  "properties": {
    "gn:admin1_code":"3.0",
    "gn:asciiname":"Boruki",
    "gn:country_code":"BY",
    "gn:dem":119,
    "gn:feature_class":"P",
    "gn:feature_code":"PPL",
    "gn:name":"Boruki",
    "gn:population":0,
    "gn:timezone":"Europe/Minsk",
    "iso:country":"BY",
    "name:bel_x_preferred":[
        "Baruki"
    ],
    "name:bel_x_variant":[
        "\u0411\u0430\u0440\u0443\u043a\u0456"
    ],
    "name:rus_x_preferred":[
        "\u0411\u043e\u0440\u0443\u043a\u0438"
    ],
    "wof:name":"Boruki",
    "wof:placetype":"locality"
},
  "geometry": {"coordinates":[25.112,53.2784],"type":"Point"}
}