{
  "type": "Feature",
  "properties": {
    "gn:admin1_code":"7.0",
    "gn:asciiname":"Myasoyedovo",
    "gn:country_code":"BY",
    "gn:dem":139,
    "gn:feature_class":"P",
    "gn:feature_code":"PPL",
    "gn:name":"Myasoyedovo",
    "gn:population":0,
    "gn:timezone":"Europe/Minsk",
    "iso:country":"BY",
    "name:rus_x_preferred":[
        "\u041c\u044f\u0441\u043e\u0435\u0434\u043e\u0432\u043e"
    ],
    "wof:name":"Myasoyedovo",
    "wof:placetype":"locality"
},
  "geometry": {"coordinates":[29.36,55.2844],"type":"Point"}
}