{
  "type": "Feature",
  "properties": {
    "gn:admin1_code":"7.0",
    "gn:asciiname":"Il'intsy",
    "gn:country_code":"BY",
    "gn:dem":143,
    "gn:feature_class":"P",
    "gn:feature_code":"PPL",
    "gn:name":"Il\u2019intsy",
    "gn:population":0,
    "gn:timezone":"Europe/Minsk",
    "iso:country":"BY",
    "name:rus_x_preferred":[
        "\u0418\u043b\u044c\u0438\u043d\u0446\u044b"
    ],
    "name:und_x_variant":[
        "Il\u2019intsy"
    ],
    "wof:name":"Il'intsy",
    "wof:placetype":"locality"
},
  "geometry": {"coordinates":[29.5785,55.2876],"type":"Point"}
}