{
  "type": "Feature",
  "properties": {
    "gn:admin1_code":"5.0",
    "gn:asciiname":"Listopadovichi",
    "gn:country_code":"BY",
    "gn:dem":145,
    "gn:feature_class":"P",
    "gn:feature_code":"PPL",
    "gn:name":"Listopadovichi",
    "gn:population":0,
    "gn:timezone":"Europe/Minsk",
    "iso:country":"BY",
    "name:rus_x_preferred":[
        "\u041b\u0438\u0441\u0442\u043e\u043f\u0430\u0434\u043e\u0432\u0438\u0447\u0438"
    ],
    "name:und_x_variant":[
        "Bol\u2019shiye Listopadovichi",
        "Listopadowicze",
        "Listopadovichi"
    ],
    "wof:name":"Listopadovichi",
    "wof:placetype":"locality"
},
  "geometry": {"coordinates":[27.5231,52.7309],"type":"Point"}
}