{
  "type": "Feature",
  "properties": {
    "gn:admin1_code":"1.0",
    "gn:asciiname":"Molotkavichy",
    "gn:country_code":"BY",
    "gn:dem":147,
    "gn:feature_class":"P",
    "gn:feature_code":"PPL",
    "gn:name":"Molotkavichy",
    "gn:population":0,
    "gn:timezone":"Europe/Minsk",
    "iso:country":"BY",
    "name:bel_x_preferred":[
        "\u041c\u043e\u043b\u043e\u0442\u043a\u0430\u0432\u0456\u0447\u044b"
    ],
    "name:eng_x_preferred":[
        "Molotkovichi"
    ],
    "name:rus_x_preferred":[
        "\u041c\u043e\u043b\u043e\u0442\u043a\u043e\u0432\u0438\u0447\u0438"
    ],
    "name:und_x_variant":[
        "Molodkoviche",
        "Molotkoviche",
        "Molodkovichi",
        "Molotkavichy"
    ],
    "wof:name":"Molotkavichy",
    "wof:placetype":"locality"
},
  "geometry": {"coordinates":[25.9229,52.1211],"type":"Point"}
}