{
  "type": "Feature",
  "properties": {
    "gn:admin1_code":"7.0",
    "gn:asciiname":"Uvoloki",
    "gn:country_code":"BY",
    "gn:dem":143,
    "gn:feature_class":"P",
    "gn:feature_code":"PPL",
    "gn:name":"Uvoloki",
    "gn:population":0,
    "gn:timezone":"Europe/Minsk",
    "iso:country":"BY",
    "name:rus_x_preferred":[
        "\u0423\u0432\u043e\u043b\u043e\u043a\u0438"
    ],
    "wof:name":"Uvoloki",
    "wof:placetype":"locality"
},
  "geometry": {"coordinates":[29.8308,55.2193],"type":"Point"}
}