{
  "type": "Feature",
  "properties": {
    "gn:admin1_code":"5.0",
    "gn:asciiname":"Skirmantava",
    "gn:country_code":"BY",
    "gn:dem":303,
    "gn:feature_class":"P",
    "gn:feature_code":"PPL",
    "gn:name":"Skirmantava",
    "gn:population":0,
    "gn:timezone":"Europe/Minsk",
    "iso:country":"BY",
    "name:bel_x_preferred":[
        "\u0421\u043a\u0456\u0440\u043c\u0430\u043d\u0442\u0430\u0432\u0430"
    ],
    "name:und_x_variant":[
        "Skirmantovo",
        "Skirmuntovo"
    ],
    "wof:name":"Skirmantava",
    "wof:placetype":"locality"
},
  "geometry": {"coordinates":[27.0563,53.8401],"type":"Point"}
}