{
  "type": "Feature",
  "properties": {
    "gn:admin1_code":"6.0",
    "gn:asciiname":"Grinevka",
    "gn:country_code":"BY",
    "gn:dem":154,
    "gn:feature_class":"P",
    "gn:feature_code":"PPL",
    "gn:name":"Grin\u00ebvka",
    "gn:population":0,
    "gn:timezone":"Europe/Minsk",
    "iso:country":"BY",
    "name:rus_x_preferred":[
        "\u0413\u0440\u0438\u043d\u0451\u0432\u043a\u0430"
    ],
    "name:und_x_variant":[
        "Grin\u00ebvka"
    ],
    "wof:name":"Grinevka",
    "wof:placetype":"locality"
},
  "geometry": {"coordinates":[28.9467,53.2331],"type":"Point"}
}