{
  "type": "Feature",
  "properties": {
    "gn:admin1_code":"5.0",
    "gn:asciiname":"Sharai",
    "gn:country_code":"BY",
    "gn:dem":244,
    "gn:feature_class":"P",
    "gn:feature_code":"PPL",
    "gn:name":"Sharai",
    "gn:population":0,
    "gn:timezone":"Europe/Minsk",
    "iso:country":"BY",
    "name:rus_x_preferred":[
        "\u0428\u0430\u0440\u0430\u0438"
    ],
    "wof:name":"Sharai",
    "wof:placetype":"locality"
},
  "geometry": {"coordinates":[26.7753,54.0551],"type":"Point"}
}