{
  "type": "Feature",
  "properties": {
    "gn:admin1_code":"2.0",
    "gn:asciiname":"Naspa",
    "gn:country_code":"BY",
    "gn:dem":136,
    "gn:feature_class":"P",
    "gn:feature_code":"PPL",
    "gn:name":"Naspa",
    "gn:population":0,
    "gn:timezone":"Europe/Minsk",
    "iso:country":"BY",
    "name:rus_x_preferred":[
        "\u041d\u0430\u0441\u043f\u0430"
    ],
    "wof:name":"Naspa",
    "wof:placetype":"locality"
},
  "geometry": {"coordinates":[30.3382,52.7106],"type":"Point"}
}