{
  "type": "Feature",
  "properties": {
    "gn:admin1_code":"0.0",
    "gn:asciiname":"Semenovshchina",
    "gn:country_code":"BY",
    "gn:dem":170,
    "gn:feature_class":"P",
    "gn:feature_code":"PPL",
    "gn:name":"Sem\u00ebnovshchina",
    "gn:population":0,
    "gn:timezone":"Europe/Minsk",
    "iso:country":"BY",
    "wof:name":"Semenovshchina",
    "wof:placetype":"locality"
},
  "geometry": {"coordinates":[30.86667000000001,53.88333000000001],"type":"Point"}
}