{
  "type": "Feature",
  "properties": {
    "gn:admin1_code":"5.0",
    "gn:asciiname":"Gory",
    "gn:country_code":"BY",
    "gn:dem":275,
    "gn:feature_class":"P",
    "gn:feature_code":"PPL",
    "gn:name":"Gory",
    "gn:population":0,
    "gn:timezone":"Europe/Minsk",
    "iso:country":"BY",
    "name:rus_x_preferred":[
        "\u0413\u043e\u0440\u044b"
    ],
    "wof:name":"Gory",
    "wof:placetype":"locality"
},
  "geometry": {"coordinates":[27.3763,54.1783],"type":"Point"}
}