{
  "type": "Feature",
  "properties": {
    "gn:admin1_code":"3.0",
    "gn:asciiname":"Sochenyaty",
    "gn:country_code":"BY",
    "gn:dem":145,
    "gn:feature_class":"P",
    "gn:feature_code":"PPL",
    "gn:name":"Sochenyaty",
    "gn:population":0,
    "gn:timezone":"Europe/Minsk",
    "iso:country":"BY",
    "name:rus_x_preferred":[
        "\u0421\u043e\u0447\u0435\u043d\u044f\u0442\u044b"
    ],
    "wof:name":"Sochenyaty",
    "wof:placetype":"locality"
},
  "geometry": {"coordinates":[26.4615,54.6229],"type":"Point"}
}