{
  "type": "Feature",
  "properties": {
    "gn:admin1_code":"1.0",
    "gn:asciiname":"Gorizdrichi",
    "gn:country_code":"BY",
    "gn:dem":146,
    "gn:feature_class":"P",
    "gn:feature_code":"PPL",
    "gn:name":"Gorizdrichi",
    "gn:population":0,
    "gn:timezone":"Europe/Minsk",
    "iso:country":"BY",
    "name:rus_x_preferred":[
        "\u0413\u043e\u0440\u0438\u0437\u0434\u0440\u0438\u0447\u0438"
    ],
    "wof:name":"Gorizdrichi",
    "wof:placetype":"locality"
},
  "geometry": {"coordinates":[24.4195,52.3125],"type":"Point"}
}