{
  "type": "Feature",
  "properties": {
    "gn:admin1_code":"1.0",
    "gn:asciiname":"Lyusina",
    "gn:country_code":"BY",
    "gn:dem":151,
    "gn:feature_class":"P",
    "gn:feature_code":"PPL",
    "gn:name":"Lyusina",
    "gn:population":0,
    "gn:timezone":"Europe/Minsk",
    "iso:country":"BY",
    "name:bel_x_preferred":[
        "\u041b\u044e\u0441\u0456\u043d\u0430"
    ],
    "name:eng_x_preferred":[
        "Lyusino"
    ],
    "name:rus_x_preferred":[
        "\u041b\u044e\u0441\u0438\u043d\u043e"
    ],
    "name:und_x_variant":[
        "Lusino",
        "Lyusino",
        "Lyusina"
    ],
    "wof:name":"Lyusina",
    "wof:placetype":"locality"
},
  "geometry": {"coordinates":[26.5131,52.628],"type":"Point"}
}