{
  "type": "Feature",
  "properties": {
    "gn:admin1_code":"1.0",
    "gn:asciiname":"Yazvinets",
    "gn:country_code":"BY",
    "gn:dem":159,
    "gn:feature_class":"P",
    "gn:feature_code":"PPL",
    "gn:name":"Yazvinets",
    "gn:population":0,
    "gn:timezone":"Europe/Minsk",
    "iso:country":"BY",
    "name:rus_x_preferred":[
        "\u042f\u0437\u0432\u0438\u043d\u0435\u0446"
    ],
    "name:und_x_variant":[
        "Yazhvinets"
    ],
    "wof:name":"Yazvinets",
    "wof:placetype":"locality"
},
  "geometry": {"coordinates":[24.4019,51.9512],"type":"Point"}
}