{
  "type": "Feature",
  "properties": {
    "gn:admin1_code":"7.0",
    "gn:asciiname":"Dubrovitsy",
    "gn:country_code":"BY",
    "gn:dem":142,
    "gn:feature_class":"P",
    "gn:feature_code":"PPL",
    "gn:name":"Dubrovitsy",
    "gn:population":0,
    "gn:timezone":"Europe/Minsk",
    "iso:country":"BY",
    "name:rus_x_preferred":[
        "\u0414\u0443\u0431\u0440\u043e\u0432\u0438\u0446\u044b"
    ],
    "wof:name":"Dubrovitsy",
    "wof:placetype":"locality"
},
  "geometry": {"coordinates":[29.234,54.7608],"type":"Point"}
}