{
  "type": "Feature",
  "properties": {
    "gn:admin1_code":"7.0",
    "gn:asciiname":"Barvin",
    "gn:country_code":"BY",
    "gn:dem":147,
    "gn:feature_class":"P",
    "gn:feature_code":"PPL",
    "gn:name":"Barvin",
    "gn:population":0,
    "gn:timezone":"Europe/Minsk",
    "iso:country":"BY",
    "name:rus_x_preferred":[
        "\u0411\u0430\u0440\u0432\u0438\u043d"
    ],
    "wof:name":"Barvin",
    "wof:placetype":"locality"
},
  "geometry": {"coordinates":[30.222,55.267],"type":"Point"}
}