{
  "type": "Feature",
  "properties": {
    "gn:admin1_code":"5.0",
    "gn:asciiname":"Melkovichi",
    "gn:country_code":"BY",
    "gn:dem":141,
    "gn:feature_class":"P",
    "gn:feature_code":"PPL",
    "gn:name":"Melkovichi",
    "gn:population":0,
    "gn:timezone":"Europe/Minsk",
    "iso:country":"BY",
    "name:rus_x_preferred":[
        "\u041c\u0435\u043b\u043a\u043e\u0432\u0438\u0447\u0438"
    ],
    "name:und_x_variant":[
        "Milkovichi"
    ],
    "wof:name":"Melkovichi",
    "wof:placetype":"locality"
},
  "geometry": {"coordinates":[27.5431,52.6621],"type":"Point"}
}