{
  "type": "Feature",
  "properties": {
    "gn:admin1_code":"7.0",
    "gn:asciiname":"Saveyki",
    "gn:country_code":"BY",
    "gn:dem":152,
    "gn:feature_class":"P",
    "gn:feature_code":"PPL",
    "gn:name":"Saveyki",
    "gn:population":0,
    "gn:timezone":"Europe/Minsk",
    "iso:country":"BY",
    "name:rus_x_preferred":[
        "\u0421\u0430\u0432\u0435\u0439\u043a\u0438"
    ],
    "wof:name":"Saveyki",
    "wof:placetype":"locality"
},
  "geometry": {"coordinates":[26.6033,55.4142],"type":"Point"}
}