{
  "type": "Feature",
  "properties": {
    "gn:admin1_code":"6.0",
    "gn:asciiname":"Lariyanovo",
    "gn:country_code":"BY",
    "gn:dem":191,
    "gn:feature_class":"P",
    "gn:feature_code":"PPL",
    "gn:name":"Lariyanovo",
    "gn:population":0,
    "gn:timezone":"Europe/Minsk",
    "iso:country":"BY",
    "name:rus_x_preferred":[
        "\u041b\u0430\u0440\u044c\u044f\u043d\u043e\u0432\u043e"
    ],
    "name:und_x_variant":[
        "Lar\u2019yanovo",
        "Lariyanovo"
    ],
    "wof:name":"Lariyanovo",
    "wof:placetype":"locality"
},
  "geometry": {"coordinates":[31.7246,53.9553],"type":"Point"}
}