{
  "type": "Feature",
  "properties": {
    "gn:admin1_code":"7.0",
    "gn:asciiname":"Shaltiny",
    "gn:country_code":"BY",
    "gn:dem":139,
    "gn:feature_class":"P",
    "gn:feature_code":"PPL",
    "gn:name":"Shaltiny",
    "gn:population":0,
    "gn:timezone":"Europe/Minsk",
    "iso:country":"BY",
    "name:rus_x_preferred":[
        "\u0428\u0430\u043b\u0442\u0438\u043d\u044b"
    ],
    "wof:name":"Shaltiny",
    "wof:placetype":"locality"
},
  "geometry": {"coordinates":[27.5525,55.7604],"type":"Point"}
}