{
  "type": "Feature",
  "properties": {
    "gn:admin1_code":"3.0",
    "gn:asciiname":"Vigushki",
    "gn:country_code":"BY",
    "gn:dem":145,
    "gn:feature_class":"P",
    "gn:feature_code":"PPL",
    "gn:name":"Vigushki",
    "gn:population":0,
    "gn:timezone":"Europe/Minsk",
    "iso:country":"BY",
    "name:rus_x_preferred":[
        "\u0412\u0438\u0433\u0443\u0448\u043a\u0438"
    ],
    "wof:name":"Vigushki",
    "wof:placetype":"locality"
},
  "geometry": {"coordinates":[25.7461,54.0288],"type":"Point"}
}