{
  "type": "Feature",
  "properties": {
    "gn:admin1_code":"1.0",
    "gn:asciiname":"Karlovichi",
    "gn:country_code":"BY",
    "gn:dem":148,
    "gn:feature_class":"P",
    "gn:feature_code":"PPL",
    "gn:name":"Karlovichi",
    "gn:population":0,
    "gn:timezone":"Europe/Minsk",
    "iso:country":"BY",
    "name:rus_x_preferred":[
        "\u041a\u0430\u0440\u043b\u043e\u0432\u0438\u0447\u0438"
    ],
    "wof:name":"Karlovichi",
    "wof:placetype":"locality"
},
  "geometry": {"coordinates":[25.0426,52.1269],"type":"Point"}
}