{
  "type": "Feature",
  "properties": {
    "gn:admin1_code":"1.0",
    "gn:asciiname":"Bol'shiye Shchitniki",
    "gn:country_code":"BY",
    "gn:dem":152,
    "gn:feature_class":"P",
    "gn:feature_code":"PPL",
    "gn:name":"Bol\u2019shiye Shchitniki",
    "gn:population":0,
    "gn:timezone":"Europe/Minsk",
    "iso:country":"BY",
    "name:rus_x_preferred":[
        "\u0411\u043e\u043b\u044c\u0448\u0438\u0435 \u0429\u0438\u0442\u043d\u0438\u043a\u0438"
    ],
    "name:und_x_variant":[
        "Bol\u2019shiye Shchitniki"
    ],
    "wof:name":"Bol'shiye Shchitniki",
    "wof:placetype":"locality"
},
  "geometry": {"coordinates":[23.4634,52.2488],"type":"Point"}
}