{
  "type": "Feature",
  "properties": {
    "gn:admin1_code":"5.0",
    "gn:asciiname":"Kravtsova Niva",
    "gn:country_code":"BY",
    "gn:dem":212,
    "gn:feature_class":"P",
    "gn:feature_code":"PPL",
    "gn:name":"Kravtsova Niva",
    "gn:population":0,
    "gn:timezone":"Europe/Minsk",
    "iso:country":"BY",
    "name:rus_x_preferred":[
        "\u041a\u0440\u0430\u0432\u0446\u043e\u0432\u0430 \u041d\u0438\u0432\u0430"
    ],
    "wof:name":"Kravtsova Niva",
    "wof:placetype":"locality"
},
  "geometry": {"coordinates":[28.7647,54.4578],"type":"Point"}
}