{
  "type": "Feature",
  "properties": {
    "gn:admin1_code":"7.0",
    "gn:asciiname":"Mikhaylovshchina",
    "gn:country_code":"BY",
    "gn:dem":204,
    "gn:feature_class":"P",
    "gn:feature_code":"PPL",
    "gn:name":"Mikhaylovshchina",
    "gn:population":0,
    "gn:timezone":"Europe/Minsk",
    "iso:country":"BY",
    "name:rus_x_preferred":[
        "\u041c\u0438\u0445\u0430\u0439\u043b\u043e\u0432\u0449\u0438\u043d\u0430"
    ],
    "wof:name":"Mikhaylovshchina",
    "wof:placetype":"locality"
},
  "geometry": {"coordinates":[29.8122,54.4387],"type":"Point"}
}