{
  "type": "Feature",
  "properties": {
    "gn:admin1_code":"2.0",
    "gn:asciiname":"Kurakovshchina",
    "gn:country_code":"BY",
    "gn:dem":144,
    "gn:feature_class":"P",
    "gn:feature_code":"PPL",
    "gn:name":"Kurakovshchina",
    "gn:population":0,
    "gn:timezone":"Europe/Minsk",
    "iso:country":"BY",
    "name:rus_x_preferred":[
        "\u041a\u0443\u0440\u0430\u043a\u043e\u0432\u0449\u0438\u043d\u0430"
    ],
    "name:und_x_variant":[
        "Kuranovshchina"
    ],
    "wof:name":"Kurakovshchina",
    "wof:placetype":"locality"
},
  "geometry": {"coordinates":[30.7976,53.1244],"type":"Point"}
}