{
  "type": "Feature",
  "properties": {
    "gn:admin1_code":"7.0",
    "gn:asciiname":"Perekopovo",
    "gn:country_code":"BY",
    "gn:dem":156,
    "gn:feature_class":"P",
    "gn:feature_code":"PPL",
    "gn:name":"Perekopovo",
    "gn:population":0,
    "gn:timezone":"Europe/Minsk",
    "iso:country":"BY",
    "name:rus_x_preferred":[
        "\u041f\u0435\u0440\u0435\u043a\u043e\u043f\u043e\u0432\u043e"
    ],
    "name:und_x_variant":[
        "Perekopov"
    ],
    "wof:name":"Perekopovo",
    "wof:placetype":"locality"
},
  "geometry": {"coordinates":[29.7986,54.9737],"type":"Point"}
}