{
  "type": "Feature",
  "properties": {
    "gn:admin1_code":"7.0",
    "gn:asciiname":"Staraya Lepel'",
    "gn:country_code":"BY",
    "gn:dem":160,
    "gn:feature_class":"P",
    "gn:feature_code":"PPL",
    "gn:name":"Staraya Lepel\u2019",
    "gn:population":0,
    "gn:timezone":"Europe/Minsk",
    "iso:country":"BY",
    "name:rus_x_preferred":[
        "\u0421\u0442\u0430\u0440\u0430\u044f \u041b\u0435\u043f\u0435\u043b\u044c"
    ],
    "name:und_x_variant":[
        "Staraya Lepel\u2019"
    ],
    "wof:name":"Staraya Lepel'",
    "wof:placetype":"locality"
},
  "geometry": {"coordinates":[28.6837,54.9297],"type":"Point"}
}