{
  "type": "Feature",
  "properties": {
    "gn:admin1_code":"5.0",
    "gn:asciiname":"Dudari",
    "gn:country_code":"BY",
    "gn:dem":175,
    "gn:feature_class":"P",
    "gn:feature_code":"PPL",
    "gn:name":"Dudari",
    "gn:population":0,
    "gn:timezone":"Europe/Minsk",
    "iso:country":"BY",
    "name:rus_x_preferred":[
        "\u0414\u0443\u0434\u0430\u0440\u0438"
    ],
    "wof:name":"Dudari",
    "wof:placetype":"locality"
},
  "geometry": {"coordinates":[29.1061,54.6088],"type":"Point"}
}