{
  "type": "Feature",
  "properties": {
    "gn:admin1_code":"7.0",
    "gn:asciiname":"Kazimirovo",
    "gn:country_code":"BY",
    "gn:dem":161,
    "gn:feature_class":"P",
    "gn:feature_code":"PPL",
    "gn:name":"Kazimirovo",
    "gn:population":0,
    "gn:timezone":"Europe/Minsk",
    "iso:country":"BY",
    "name:rus_x_preferred":[
        "\u041a\u0430\u0437\u0438\u043c\u0438\u0440\u043e\u0432\u043e"
    ],
    "wof:name":"Kazimirovo",
    "wof:placetype":"locality"
},
  "geometry": {"coordinates":[30.6764,55.2812],"type":"Point"}
}