{
  "type": "Feature",
  "properties": {
    "gn:admin1_code":"3.0",
    "gn:asciiname":"Rudi",
    "gn:country_code":"BY",
    "gn:dem":204,
    "gn:feature_class":"P",
    "gn:feature_code":"PPL",
    "gn:name":"Rudi",
    "gn:population":0,
    "gn:timezone":"Europe/Minsk",
    "iso:country":"BY",
    "name:rus_x_preferred":[
        "\u0420\u0443\u0434\u0438"
    ],
    "wof:name":"Rudi",
    "wof:placetype":"locality"
},
  "geometry": {"coordinates":[25.7687,54.2618],"type":"Point"}
}