{
  "type": "Feature",
  "properties": {
    "gn:admin1_code":"7.0",
    "gn:asciiname":"Khorevshchina",
    "gn:country_code":"BY",
    "gn:dem":197,
    "gn:feature_class":"P",
    "gn:feature_code":"PPL",
    "gn:name":"Khor\u00ebvshchina",
    "gn:population":0,
    "gn:timezone":"Europe/Minsk",
    "iso:country":"BY",
    "name:rus_x_preferred":[
        "\u0425\u043e\u0440\u0451\u0432\u0449\u0438\u043d\u0430"
    ],
    "name:und_x_variant":[
        "Khor\u00ebvshchina"
    ],
    "wof:name":"Khorevshchina",
    "wof:placetype":"locality"
},
  "geometry": {"coordinates":[30.0357,54.6524],"type":"Point"}
}