{
  "type": "Feature",
  "properties": {
    "gn:admin1_code":"5.0",
    "gn:asciiname":"Shipki",
    "gn:country_code":"BY",
    "gn:dem":175,
    "gn:feature_class":"P",
    "gn:feature_code":"PPL",
    "gn:name":"Shipki",
    "gn:population":0,
    "gn:timezone":"Europe/Minsk",
    "iso:country":"BY",
    "name:rus_x_preferred":[
        "\u0428\u0438\u043f\u043a\u0438"
    ],
    "name:und_x_variant":[
        "Szypki",
        "Shypki",
        "Shipki"
    ],
    "wof:name":"Shipki",
    "wof:placetype":"locality"
},
  "geometry": {"coordinates":[27.2668,54.3321],"type":"Point"}
}