{
  "type": "Feature",
  "properties": {
    "iso:country":"BY",
    "name:rus_x_preferred":[
        "\u041d\u043e\u0432\u043e\u0441\u0451\u043b\u043a\u0438"
    ],
    "name:unk_x_variant":[
        "Novos\u00eblki"
    ],
    "qs:gn_country":"BY",
    "qs:gn_fcode":"PPL",
    "qs:gn_pop":512,
    "qs:name":"Novoselki",
    "qs:name_adm0":"Belarus",
    "qs:name_adm1":"Mahilyowskaya Voblasts'",
    "qs:photos":0,
    "qs:photos_1k":0,
    "qs:photos_9k":0,
    "qs:photos_9r":0,
    "qs:photos_all":0,
    "qs:photos_sr":0,
    "qs:placetype":"Town",
    "qs:pop_sr":"2",
    "qs:woe_adm0":23424765,
    "wof:name":"Novoselki",
    "wof:placetype":"locality",
    "wof:population":512
},
  "geometry": {"coordinates":[30.3769,53.813],"type":"Point"}
}