{
  "type": "Feature",
  "properties": {
    "iso:country":"BY",
    "name:arz_x_preferred":[
        "\u0646\u0627\u06a4\u0627\u0633\u064a\u0648\u0644\u0643\u0649"
    ],
    "name:bel_x_preferred":[
        "\u0412\u0451\u0441\u043a\u0430 \u041d\u0430\u0432\u0430\u0441\u0451\u043b\u043a\u0456"
    ],
    "name:bel_x_variant":[
        "\u041d\u0430\u0432\u0430\u0441\u0451\u043b\u043a\u0456"
    ],
    "name:ceb_x_preferred":[
        "Novos\u00eblki"
    ],
    "name:ceb_x_variant":[
        "Navasiolki"
    ],
    "name:che_x_preferred":[
        "\u041d\u043e\u0432\u043e\u0441\u0435\u043b\u043a\u0438"
    ],
    "name:deu_x_preferred":[
        "Navasiolki"
    ],
    "name:eng_x_preferred":[
        "Navasyolki"
    ],
    "name:eng_x_variant":[
        "Navasiolki"
    ],
    "name:fra_x_preferred":[
        "Novosiolki"
    ],
    "name:fra_x_variant":[
        "Navasiolki"
    ],
    "name:gle_x_preferred":[
        "Navasiolki"
    ],
    "name:lit_x_preferred":[
        "Navasiolkai"
    ],
    "name:nld_x_preferred":[
        "Novosiolki"
    ],
    "name:nld_x_variant":[
        "Navasiolki"
    ],
    "name:pol_x_preferred":[
        "Nawasio\u0142ki"
    ],
    "name:rus_x_preferred":[
        "\u041d\u043e\u0432\u043e\u0441\u0451\u043b\u043a\u0438"
    ],
    "name:swe_x_preferred":[
        "Novosiolki"
    ],
    "name:tat_x_preferred":[
        "\u041d\u0430\u0432\u0430\u0441\u0451\u043b\u043a\u0438"
    ],
    "name:ukr_x_preferred":[
        "\u0411\u0454\u043b\u0438\u043d\u0438\u0447\u0456"
    ],
    "qs:gn_country":"BY",
    "qs:gn_fcode":"PPL",
    "qs:gn_pop":512,
    "qs:name":"Novoselki",
    "qs:name_adm0":"Belarus",
    "qs:name_adm1":"Mahilyowskaya Voblasts'",
    "qs:photos":0,
    "qs:photos_1k":0,
    "qs:photos_9k":0,
    "qs:photos_9r":0,
    "qs:photos_all":0,
    "qs:photos_sr":0,
    "qs:placetype":"Town",
    "qs:pop_sr":"2",
    "qs:woe_adm0":23424765,
    "wof:name":"Novoselki",
    "wof:placetype":"locality",
    "wof:population":512
},
  "geometry": {"coordinates":[30.3769,53.813],"type":"Point"}
}