{
  "type": "Feature",
  "properties": {
    "gn:admin1_code":"5.0",
    "gn:asciiname":"Gureshchina",
    "gn:country_code":"BY",
    "gn:dem":160,
    "gn:feature_class":"P",
    "gn:feature_code":"PPL",
    "gn:name":"Gureshchina",
    "gn:population":0,
    "gn:timezone":"Europe/Minsk",
    "iso:country":"BY",
    "name:rus_x_preferred":[
        "\u0413\u0443\u0440\u0435\u0449\u0438\u043d\u0430"
    ],
    "wof:name":"Gureshchina",
    "wof:placetype":"locality"
},
  "geometry": {"coordinates":[29.0286,53.7994],"type":"Point"}
}