{
  "type": "Feature",
  "properties": {
    "gn:admin1_code":"7.0",
    "gn:asciiname":"Pozhenki",
    "gn:country_code":"BY",
    "gn:dem":188,
    "gn:feature_class":"P",
    "gn:feature_code":"PPL",
    "gn:name":"Pozhenki",
    "gn:population":0,
    "gn:timezone":"Europe/Minsk",
    "iso:country":"BY",
    "name:rus_x_preferred":[
        "\u041f\u043e\u0436\u0435\u043d\u043a\u0438"
    ],
    "name:und_x_variant":[
        "Pozhanki"
    ],
    "wof:name":"Pozhenki",
    "wof:placetype":"locality"
},
  "geometry": {"coordinates":[29.806,55.703],"type":"Point"}
}