{
  "type": "Feature",
  "properties": {
    "gn:admin1_code":"5.0",
    "gn:asciiname":"Lyubcha",
    "gn:country_code":"BY",
    "gn:dem":176,
    "gn:feature_class":"P",
    "gn:feature_code":"PPL",
    "gn:name":"Lyubcha",
    "gn:population":0,
    "gn:timezone":"Europe/Minsk",
    "iso:country":"BY",
    "name:bul_x_preferred":[
        "\u041b\u044e\u0431\u0447\u0430"
    ],
    "name:ceb_x_preferred":[
        "Lyubcha"
    ],
    "name:fas_x_preferred":[
        "\u0644\u06cc\u0648\u0628\u0686\u0627"
    ],
    "name:kat_x_preferred":[
        "\u10da\u10d8\u10e3\u10d1\u10e9\u10d0"
    ],
    "name:kaz_x_preferred":[
        "\u041b\u044e\u0431\u0447\u0430"
    ],
    "name:msa_x_preferred":[
        "Lyubcha"
    ],
    "name:ron_x_preferred":[
        "Liubcea"
    ],
    "name:rus_x_preferred":[
        "\u041b\u044e\u0431\u0447\u0430"
    ],
    "name:ukr_x_preferred":[
        "\u041b\u044e\u0431\u0447\u0430"
    ],
    "wof:name":"Lyubcha",
    "wof:placetype":"locality"
},
  "geometry": {"coordinates":[28.2351,54.3305],"type":"Point"}
}