{
  "type": "Feature",
  "properties": {
    "gn:admin1_code":"1.0",
    "gn:asciiname":"Bol'shaya Rakovitsa",
    "gn:country_code":"BY",
    "gn:dem":134,
    "gn:feature_class":"P",
    "gn:feature_code":"PPL",
    "gn:name":"Bol\u2019shaya Rakovitsa",
    "gn:population":0,
    "gn:timezone":"Europe/Minsk",
    "iso:country":"BY",
    "name:rus_x_preferred":[
        "\u0411\u043e\u043b\u044c\u0448\u0430\u044f \u0420\u0430\u043a\u043e\u0432\u0438\u0446\u0430"
    ],
    "name:und_x_variant":[
        "Bol\u2019shaya Rakovitsa"
    ],
    "wof:name":"Bol'shaya Rakovitsa",
    "wof:placetype":"locality"
},
  "geometry": {"coordinates":[23.5105,52.2136],"type":"Point"}
}