{
  "type": "Feature",
  "properties": {
    "gn:admin1_code":"7.0",
    "gn:asciiname":"Osovo",
    "gn:country_code":"BY",
    "gn:dem":196,
    "gn:feature_class":"P",
    "gn:feature_code":"PPL",
    "gn:name":"Osovo",
    "gn:population":0,
    "gn:timezone":"Europe/Minsk",
    "iso:country":"BY",
    "name:eng_x_preferred":[
        "Osovo"
    ],
    "name:rus_x_preferred":[
        "\u041e\u0441\u043e\u0432\u043e"
    ],
    "name:und_x_variant":[
        "Osowo",
        "Osovo"
    ],
    "wof:name":"Osovo",
    "wof:placetype":"locality"
},
  "geometry": {"coordinates":[27.8172,54.8383],"type":"Point"}
}