{
  "type": "Feature",
  "properties": {
    "gn:admin1_code":"2.0",
    "gn:asciiname":"Kuntorovka",
    "gn:country_code":"BY",
    "gn:dem":137,
    "gn:feature_class":"P",
    "gn:feature_code":"PPL",
    "gn:name":"Kuntorovka",
    "gn:population":0,
    "gn:timezone":"Europe/Minsk",
    "iso:country":"BY",
    "name:rus_x_preferred":[
        "\u041a\u0443\u043d\u0442\u043e\u0440\u043e\u0432\u043a\u0430"
    ],
    "name:und_x_variant":[
        "Kongurovka",
        "Konturovka",
        "Kuntorovka"
    ],
    "wof:name":"Kuntorovka",
    "wof:placetype":"locality"
},
  "geometry": {"coordinates":[31.0361,52.5847],"type":"Point"}
}