{
  "type": "Feature",
  "properties": {
    "gn:admin1_code":"7.0",
    "gn:asciiname":"Nizhneye Fomino",
    "gn:country_code":"BY",
    "gn:dem":120,
    "gn:feature_class":"P",
    "gn:feature_code":"PPL",
    "gn:name":"Nizhneye Fomino",
    "gn:population":0,
    "gn:timezone":"Europe/Minsk",
    "iso:country":"BY",
    "name:rus_x_preferred":[
        "\u041d\u0438\u0436\u043d\u0435\u0435 \u0424\u043e\u043c\u0438\u043d\u043e"
    ],
    "wof:name":"Nizhneye Fomino",
    "wof:placetype":"locality"
},
  "geometry": {"coordinates":[27.9005,55.897],"type":"Point"}
}