{
  "type": "Feature",
  "properties": {
    "gn:admin1_code":"6.0",
    "gn:asciiname":"Goleni Vtoryye",
    "gn:country_code":"BY",
    "gn:dem":173,
    "gn:feature_class":"P",
    "gn:feature_code":"PPL",
    "gn:name":"Goleni Vtoryye",
    "gn:population":0,
    "gn:timezone":"Europe/Minsk",
    "iso:country":"BY",
    "name:rus_x_preferred":[
        "\u0413\u043e\u043b\u0435\u043d\u0438 \u0412\u0442\u043e\u0440\u044b\u0435"
    ],
    "wof:name":"Goleni Vtoryye",
    "wof:placetype":"locality"
},
  "geometry": {"coordinates":[30.5642,53.7924],"type":"Point"}
}