{
  "type": "Feature",
  "properties": {
    "gn:admin1_code":"6.0",
    "gn:asciiname":"Kalasha",
    "gn:country_code":"BY",
    "gn:dem":171,
    "gn:feature_class":"P",
    "gn:feature_code":"PPL",
    "gn:name":"Kalasha",
    "gn:population":0,
    "gn:timezone":"Europe/Minsk",
    "iso:country":"BY",
    "name:rus_x_preferred":[
        "\u041a\u0430\u043b\u0430\u0448\u0430"
    ],
    "wof:name":"Kalasha",
    "wof:placetype":"locality"
},
  "geometry": {"coordinates":[30.0329,53.7279],"type":"Point"}
}