{
  "type": "Feature",
  "properties": {
    "gn:admin1_code":"6.0",
    "gn:asciiname":"Kalasha",
    "gn:country_code":"BY",
    "gn:dem":171,
    "gn:feature_class":"P",
    "gn:feature_code":"PPL",
    "gn:name":"Kalasha",
    "gn:population":0,
    "gn:timezone":"Europe/Minsk",
    "iso:country":"BY",
    "name:deu_x_preferred":[
        "Kalasha"
    ],
    "name:fra_x_preferred":[
        "Kalasha"
    ],
    "name:guj_x_preferred":[
        "\u0a95\u0ab3\u0ab6"
    ],
    "name:hin_x_preferred":[
        "\u0915\u0932\u0936"
    ],
    "name:kan_x_preferred":[
        "\u0c95\u0cb2\u0cb6"
    ],
    "name:mar_x_preferred":[
        "\u0915\u0932\u0936"
    ],
    "name:nep_x_preferred":[
        "\u0915\u0932\u0936"
    ],
    "name:pan_x_preferred":[
        "\u0a15\u0a32\u0a38\u0a3c"
    ],
    "name:rus_x_preferred":[
        "\u041a\u0430\u043b\u0430\u0448\u0430"
    ],
    "name:san_x_preferred":[
        "\u0915\u0932\u0936\u0903"
    ],
    "name:tel_x_preferred":[
        "\u0c2a\u0c42\u0c30\u0c4d\u0c23\u0c15\u0c41\u0c02\u0c2d\u0c02"
    ],
    "name:tha_x_preferred":[
        "\u0e2b\u0e21\u0e49\u0e2d\u0e1b\u0e39\u0e23\u0e13\u0e06\u0e0f\u0e30"
    ],
    "name:urd_x_preferred":[
        "\u06a9\u0644\u0634"
    ],
    "wof:name":"Kalasha",
    "wof:placetype":"locality"
},
  "geometry": {"coordinates":[30.0329,53.7279],"type":"Point"}
}