{
  "type": "Feature",
  "properties": {
    "gn:admin1_code":"5.0",
    "gn:asciiname":"Belichany",
    "gn:country_code":"BY",
    "gn:dem":168,
    "gn:feature_class":"P",
    "gn:feature_code":"PPL",
    "gn:name":"Belichany",
    "gn:population":0,
    "gn:timezone":"Europe/Minsk",
    "iso:country":"BY",
    "name:rus_x_preferred":[
        "\u0411\u0435\u043b\u0438\u0447\u0430\u043d\u044b"
    ],
    "wof:name":"Belichany",
    "wof:placetype":"locality"
},
  "geometry": {"coordinates":[28.7473,53.8993],"type":"Point"}
}