{
  "type": "Feature",
  "properties": {
    "gn:admin1_code":"7.0",
    "gn:asciiname":"Yanchuki",
    "gn:country_code":"BY",
    "gn:dem":187,
    "gn:feature_class":"P",
    "gn:feature_code":"PPL",
    "gn:name":"Yanchuki",
    "gn:population":0,
    "gn:timezone":"Europe/Minsk",
    "iso:country":"BY",
    "name:rus_x_preferred":[
        "\u042f\u043d\u0447\u0443\u043a\u0438"
    ],
    "wof:name":"Yanchuki",
    "wof:placetype":"locality"
},
  "geometry": {"coordinates":[27.401,55.0034],"type":"Point"}
}