{
  "type": "Feature",
  "properties": {
    "gn:admin1_code":"3.0",
    "gn:asciiname":"Byelitsa",
    "gn:country_code":"BY",
    "gn:dem":123,
    "gn:feature_class":"P",
    "gn:feature_code":"PPL",
    "gn:name":"Byelitsa",
    "gn:population":0,
    "gn:timezone":"Europe/Minsk",
    "iso:country":"BY",
    "name:bel_x_preferred":[
        "\u0411\u0435\u043b\u0456\u0446\u0430"
    ],
    "name:eng_x_preferred":[
        "Belitsa"
    ],
    "name:rus_x_preferred":[
        "\u0411\u0435\u043b\u0438\u0446\u0430"
    ],
    "name:und_x_variant":[
        "Bielica",
        "Belitsy",
        "Byelitsa"
    ],
    "wof:name":"Byelitsa",
    "wof:placetype":"locality"
},
  "geometry": {"coordinates":[25.31582,53.6502],"type":"Point"}
}