{
  "type": "Feature",
  "properties": {
    "gn:admin1_code":"7.0",
    "gn:asciiname":"Azina",
    "gn:country_code":"BY",
    "gn:dem":144,
    "gn:feature_class":"P",
    "gn:feature_code":"PPL",
    "gn:name":"Azina",
    "gn:population":0,
    "gn:timezone":"Europe/Minsk",
    "iso:country":"BY",
    "name:bel_x_preferred":[
        "\u0410\u0437\u0456\u043d\u0430"
    ],
    "name:und_x_variant":[
        "Azino"
    ],
    "wof:name":"Azina",
    "wof:placetype":"locality"
},
  "geometry": {"coordinates":[28.643,55.6299],"type":"Point"}
}