{
  "type": "Feature",
  "properties": {
    "gn:admin1_code":"2.0",
    "gn:asciiname":"Kosetov",
    "gn:country_code":"BY",
    "gn:dem":137,
    "gn:feature_class":"P",
    "gn:feature_code":"PPL",
    "gn:name":"Kosetov",
    "gn:population":0,
    "gn:timezone":"Europe/Minsk",
    "iso:country":"BY",
    "name:rus_x_preferred":[
        "\u041a\u043e\u0441\u0435\u0442\u043e\u0432"
    ],
    "name:und_x_variant":[
        "Kositov"
    ],
    "wof:name":"Kosetov",
    "wof:placetype":"locality"
},
  "geometry": {"coordinates":[29.6593,52.3915],"type":"Point"}
}