{
  "type": "Feature",
  "properties": {
    "gn:admin1_code":"5.0",
    "gn:asciiname":"Yagodka",
    "gn:country_code":"BY",
    "gn:dem":174,
    "gn:feature_class":"P",
    "gn:feature_code":"PPL",
    "gn:name":"Yagodka",
    "gn:population":0,
    "gn:timezone":"Europe/Minsk",
    "iso:country":"BY",
    "name:rus_x_preferred":[
        "\u042f\u0433\u043e\u0434\u043a\u0430"
    ],
    "wof:name":"Yagodka",
    "wof:placetype":"locality"
},
  "geometry": {"coordinates":[29.3979,53.8112],"type":"Point"}
}