{
  "type": "Feature",
  "properties": {
    "gn:admin1_code":"5.0",
    "gn:asciiname":"Amlyntsy",
    "gn:country_code":"BY",
    "gn:dem":190,
    "gn:feature_class":"P",
    "gn:feature_code":"PPL",
    "gn:name":"Amlyntsy",
    "gn:population":0,
    "gn:timezone":"Europe/Minsk",
    "iso:country":"BY",
    "name:rus_x_preferred":[
        "\u0410\u043c\u043b\u044b\u043d\u0446\u044b"
    ],
    "wof:name":"Amlyntsy",
    "wof:placetype":"locality"
},
  "geometry": {"coordinates":[26.7143,53.3012],"type":"Point"}
}