{
  "type": "Feature",
  "properties": {
    "gn:admin1_code":"7.0",
    "gn:asciiname":"Vostrava",
    "gn:country_code":"BY",
    "gn:dem":179,
    "gn:feature_class":"P",
    "gn:feature_code":"PPL",
    "gn:name":"Vostrava",
    "gn:population":0,
    "gn:timezone":"Europe/Minsk",
    "iso:country":"BY",
    "name:bel_x_preferred":[
        "\u0412\u043e\u0441\u0442\u0440\u0430\u0432\u0430"
    ],
    "name:eng_x_preferred":[
        "Ostrov"
    ],
    "name:rus_x_preferred":[
        "\u041e\u0441\u0442\u0440\u043e\u0432"
    ],
    "name:und_x_variant":[
        "Ostr\u00f3w",
        "Ostruv",
        "Ostrov",
        "Vostrava",
        "Ostrovo"
    ],
    "wof:name":"Vostrava",
    "wof:placetype":"locality"
},
  "geometry": {"coordinates":[28.1351,55.1358],"type":"Point"}
}