{
  "type": "Feature",
  "properties": {
    "gn:admin1_code":"7.0",
    "gn:asciiname":"Ventsevoye",
    "gn:country_code":"BY",
    "gn:dem":111,
    "gn:feature_class":"P",
    "gn:feature_code":"PPL",
    "gn:name":"Ventsevoye",
    "gn:population":0,
    "gn:timezone":"Europe/Minsk",
    "iso:country":"BY",
    "name:rus_x_preferred":[
        "\u0412\u0435\u043d\u0446\u0435\u0432\u043e\u0435"
    ],
    "wof:name":"Ventsevoye",
    "wof:placetype":"locality"
},
  "geometry": {"coordinates":[28.4533,55.5327],"type":"Point"}
}