{
  "type": "Feature",
  "properties": {
    "gn:admin1_code":"2.0",
    "gn:asciiname":"Konoplitsy",
    "gn:country_code":"BY",
    "gn:dem":136,
    "gn:feature_class":"P",
    "gn:feature_code":"PPL",
    "gn:name":"Konoplitsy",
    "gn:population":0,
    "gn:timezone":"Europe/Minsk",
    "iso:country":"BY",
    "name:rus_x_preferred":[
        "\u041a\u043e\u043d\u043e\u043f\u043b\u0438\u0446\u044b"
    ],
    "wof:name":"Konoplitsy",
    "wof:placetype":"locality"
},
  "geometry": {"coordinates":[29.9335,53.1998],"type":"Point"}
}