{
  "type": "Feature",
  "properties": {
    "gn:admin1_code":"7.0",
    "gn:asciiname":"Kryskovichi",
    "gn:country_code":"BY",
    "gn:dem":147,
    "gn:feature_class":"P",
    "gn:feature_code":"PPL",
    "gn:name":"Kryskovichi",
    "gn:population":0,
    "gn:timezone":"Europe/Minsk",
    "iso:country":"BY",
    "name:rus_x_preferred":[
        "\u041a\u0440\u044b\u0441\u043a\u043e\u0432\u0438\u0447\u0438"
    ],
    "wof:name":"Kryskovichi",
    "wof:placetype":"locality"
},
  "geometry": {"coordinates":[28.6623,55.1755],"type":"Point"}
}