{
  "type": "Feature",
  "properties": {
    "gn:admin1_code":"7.0",
    "gn:asciiname":"Khlusovo",
    "gn:country_code":"BY",
    "gn:dem":183,
    "gn:feature_class":"P",
    "gn:feature_code":"PPL",
    "gn:name":"Khlusovo",
    "gn:population":0,
    "gn:timezone":"Europe/Minsk",
    "iso:country":"BY",
    "name:rus_x_preferred":[
        "\u0425\u043b\u0443\u0441\u043e\u0432\u043e"
    ],
    "wof:name":"Khlusovo",
    "wof:placetype":"locality"
},
  "geometry": {"coordinates":[30.4055,54.5845],"type":"Point"}
}