{
  "type": "Feature",
  "properties": {
    "gn:admin1_code":"6.0",
    "gn:asciiname":"Aksen'kovichi",
    "gn:country_code":"BY",
    "gn:dem":163,
    "gn:feature_class":"P",
    "gn:feature_code":"PPL",
    "gn:name":"Aks\u00ebn\u2019kovichi",
    "gn:population":0,
    "gn:timezone":"Europe/Minsk",
    "iso:country":"BY",
    "name:rus_x_preferred":[
        "\u0410\u043a\u0441\u0451\u043d\u044c\u043a\u043e\u0432\u0438\u0447\u0438"
    ],
    "name:und_x_variant":[
        "Aks\u00ebn\u2019kovichi"
    ],
    "wof:name":"Aksen'kovichi",
    "wof:placetype":"locality"
},
  "geometry": {"coordinates":[29.6658,53.7577],"type":"Point"}
}