{
  "type": "Feature",
  "properties": {
    "gn:admin1_code":"7.0",
    "gn:asciiname":"Voroshki",
    "gn:country_code":"BY",
    "gn:dem":134,
    "gn:feature_class":"P",
    "gn:feature_code":"PPL",
    "gn:name":"Voroshki",
    "gn:population":0,
    "gn:timezone":"Europe/Minsk",
    "iso:country":"BY",
    "name:rus_x_preferred":[
        "\u0412\u043e\u0440\u043e\u0448\u043a\u0438"
    ],
    "wof:name":"Voroshki",
    "wof:placetype":"locality"
},
  "geometry": {"coordinates":[29.0102,55.0494],"type":"Point"}
}