{
  "type": "Feature",
  "properties": {
    "gn:admin1_code":"7.0",
    "gn:asciiname":"Sardyki",
    "gn:country_code":"BY",
    "gn:dem":114,
    "gn:feature_class":"P",
    "gn:feature_code":"PPL",
    "gn:name":"Sardyki",
    "gn:population":0,
    "gn:timezone":"Europe/Minsk",
    "iso:country":"BY",
    "name:rus_x_preferred":[
        "\u0421\u0430\u0440\u0434\u044b\u043a\u0438"
    ],
    "wof:name":"Sardyki",
    "wof:placetype":"locality"
},
  "geometry": {"coordinates":[27.8805,55.8543],"type":"Point"}
}