{
  "type": "Feature",
  "properties": {
    "gn:admin1_code":"5.0",
    "gn:asciiname":"Staryy Sokol",
    "gn:country_code":"BY",
    "gn:dem":165,
    "gn:feature_class":"P",
    "gn:feature_code":"PPL",
    "gn:name":"Staryy Sokol",
    "gn:population":0,
    "gn:timezone":"Europe/Minsk",
    "iso:country":"BY",
    "name:rus_x_preferred":[
        "\u0421\u0442\u0430\u0440\u044b\u0439 \u0421\u043e\u043a\u043e\u043b"
    ],
    "wof:name":"Staryy Sokol",
    "wof:placetype":"locality"
},
  "geometry": {"coordinates":[29.2131,54.1322],"type":"Point"}
}