{
  "type": "Feature",
  "properties": {
    "gn:admin1_code":"0.0",
    "gn:asciiname":"Loshitsa",
    "gn:country_code":"BY",
    "gn:dem":207,
    "gn:feature_class":"P",
    "gn:feature_code":"PPL",
    "gn:name":"Loshitsa",
    "gn:population":0,
    "gn:timezone":"Europe/Minsk",
    "iso:country":"BY",
    "name:und_x_variant":[
        "Lozhitsa",
        "Loshitsa"
    ],
    "wof:name":"Loshitsa",
    "wof:placetype":"locality"
},
  "geometry": {"coordinates":[27.58333,53.83333],"type":"Point"}
}