{
  "type": "Feature",
  "properties": {
    "gn:admin1_code":"1.0",
    "gn:asciiname":"Vistychy",
    "gn:country_code":"BY",
    "gn:dem":143,
    "gn:feature_class":"P",
    "gn:feature_code":"PPL",
    "gn:name":"Vistychy",
    "gn:population":0,
    "gn:timezone":"Europe/Minsk",
    "iso:country":"BY",
    "name:bel_x_preferred":[
        "\u0412\u0456\u0441\u0442\u044b\u0447\u044b"
    ],
    "name:bel_x_variant":[
        "Vistychy"
    ],
    "name:und_x_variant":[
        "Vistychi"
    ],
    "wof:name":"Vistychy",
    "wof:placetype":"locality"
},
  "geometry": {"coordinates":[23.67643,52.20749],"type":"Point"}
}