{
  "type": "Feature",
  "properties": {
    "gn:admin1_code":"3.0",
    "gn:asciiname":"Bondari",
    "gn:country_code":"BY",
    "gn:dem":120,
    "gn:feature_class":"P",
    "gn:feature_code":"PPL",
    "gn:name":"Bondari",
    "gn:population":0,
    "gn:timezone":"Europe/Minsk",
    "iso:country":"BY",
    "name:bel_x_preferred":[
        "\u0411\u0430\u043d\u0434\u0430\u0440\u044b"
    ],
    "name:deu_x_preferred":[
        "Bondari"
    ],
    "name:hye_x_preferred":[
        "\u0532\u0578\u0576\u0564\u0561\u0580\u056b"
    ],
    "name:lav_x_preferred":[
        "Bondari"
    ],
    "name:rus_x_preferred":[
        "\u0411\u043e\u043d\u0434\u0430\u0440\u0438"
    ],
    "name:ukr_x_preferred":[
        "\u0411\u043e\u043d\u0434\u0430\u0440\u0456"
    ],
    "name:und_x_variant":[
        "Bondary"
    ],
    "wof:name":"Bondari",
    "wof:placetype":"locality"
},
  "geometry": {"coordinates":[25.3928,53.6587],"type":"Point"}
}