{
  "type": "Feature",
  "properties": {
    "gn:admin1_code":"1.0",
    "gn:asciiname":"Sitnitsa",
    "gn:country_code":"BY",
    "gn:dem":128,
    "gn:feature_class":"P",
    "gn:feature_code":"PPL",
    "gn:name":"Sitnitsa",
    "gn:population":0,
    "gn:timezone":"Europe/Minsk",
    "iso:country":"BY",
    "name:bel_x_preferred":[
        "\u0421\u0456\u0442\u043d\u0456\u0446\u0430"
    ],
    "name:und_x_variant":[
        "Sytnica",
        "Sitnitsa"
    ],
    "wof:name":"Sitnitsa",
    "wof:placetype":"locality"
},
  "geometry": {"coordinates":[27.3622,52.1993],"type":"Point"}
}