{
  "type": "Feature",
  "properties": {
    "gn:admin1_code":"1.0",
    "gn:asciiname":"Pirshtuki",
    "gn:country_code":"BY",
    "gn:dem":184,
    "gn:feature_class":"P",
    "gn:feature_code":"PPL",
    "gn:name":"Pirshtuki",
    "gn:population":0,
    "gn:timezone":"Europe/Minsk",
    "iso:country":"BY",
    "name:rus_x_preferred":[
        "\u041f\u0438\u0440\u0448\u0442\u0443\u043a\u0438"
    ],
    "wof:name":"Pirshtuki",
    "wof:placetype":"locality"
},
  "geometry": {"coordinates":[26.3259,53.1225],"type":"Point"}
}