{
  "type": "Feature",
  "properties": {
    "gn:admin1_code":"2.0",
    "gn:asciiname":"Radkov",
    "gn:country_code":"BY",
    "gn:dem":121,
    "gn:feature_class":"P",
    "gn:feature_code":"PPL",
    "gn:name":"Radkov",
    "gn:population":0,
    "gn:timezone":"Europe/Minsk",
    "iso:country":"BY",
    "name:bul_x_preferred":[
        "\u0420\u0430\u0434\u043a\u043e\u0432"
    ],
    "name:ceb_x_preferred":[
        "Radkov"
    ],
    "name:ces_x_preferred":[
        "Radkov"
    ],
    "name:deu_x_preferred":[
        "Radkov"
    ],
    "name:epo_x_preferred":[
        "Radkov"
    ],
    "name:fra_x_preferred":[
        "Radkov"
    ],
    "name:glg_x_preferred":[
        "Radkov"
    ],
    "name:ita_x_preferred":[
        "Radkov"
    ],
    "name:nld_x_preferred":[
        "Radkov"
    ],
    "name:pol_x_preferred":[
        "Radkov"
    ],
    "name:rus_x_preferred":[
        "\u0420\u0430\u0434\u043a\u043e\u0432"
    ],
    "name:slk_x_preferred":[
        "Radkov"
    ],
    "name:srp_x_preferred":[
        "\u0420\u0430\u0442\u043a\u043e\u0432"
    ],
    "name:swe_x_preferred":[
        "Radkov"
    ],
    "wof:name":"Radkov",
    "wof:placetype":"locality"
},
  "geometry": {"coordinates":[28.6937,52.2241],"type":"Point"}
}