{
  "type": "Feature",
  "properties": {
    "gn:admin1_code":"2.0",
    "gn:asciiname":"Radkov",
    "gn:country_code":"BY",
    "gn:dem":121,
    "gn:feature_class":"P",
    "gn:feature_code":"PPL",
    "gn:name":"Radkov",
    "gn:population":0,
    "gn:timezone":"Europe/Minsk",
    "iso:country":"BY",
    "name:rus_x_preferred":[
        "\u0420\u0430\u0434\u043a\u043e\u0432"
    ],
    "wof:name":"Radkov",
    "wof:placetype":"locality"
},
  "geometry": {"coordinates":[28.6937,52.2241],"type":"Point"}
}