{
  "type": "Feature",
  "properties": {
    "gn:admin1_code":"5.0",
    "gn:asciiname":"Prudok",
    "gn:country_code":"BY",
    "gn:dem":156,
    "gn:feature_class":"P",
    "gn:feature_code":"PPL",
    "gn:name":"Prudok",
    "gn:population":0,
    "gn:timezone":"Europe/Minsk",
    "iso:country":"BY",
    "name:rus_x_preferred":[
        "\u041f\u0440\u0443\u0434\u043e\u043a"
    ],
    "name:und_x_variant":[
        "Oreshkovskiy Prudok"
    ],
    "wof:name":"Prudok",
    "wof:placetype":"locality"
},
  "geometry": {"coordinates":[28.9326,54.0198],"type":"Point"}
}