{
  "type": "Feature",
  "properties": {
    "gn:admin1_code":"1.0",
    "gn:asciiname":"Pryazyornaya",
    "gn:country_code":"BY",
    "gn:dem":181,
    "gn:feature_class":"P",
    "gn:feature_code":"PPL",
    "gn:name":"Pryazyornaya",
    "gn:population":0,
    "gn:timezone":"Europe/Minsk",
    "iso:country":"BY",
    "name:bel_x_preferred":[
        "Pryazyornaya"
    ],
    "name:bel_x_variant":[
        "\u041f\u0440\u044b\u0430\u0437\u0451\u0440\u043d\u0430\u044f"
    ],
    "name:rus_x_preferred":[
        "\u041f\u0440\u0438\u043e\u0437\u0451\u0440\u043d\u0430\u044f"
    ],
    "name:und_x_variant":[
        "Prioz\u00ebrnaya"
    ],
    "wof:name":"Pryazyornaya",
    "wof:placetype":"locality"
},
  "geometry": {"coordinates":[25.908,53.1119],"type":"Point"}
}