{
  "type": "Feature",
  "properties": {
    "gn:admin1_code":"6.0",
    "gn:asciiname":"Iony",
    "gn:country_code":"BY",
    "gn:dem":202,
    "gn:feature_class":"P",
    "gn:feature_code":"PPL",
    "gn:name":"Iony",
    "gn:population":0,
    "gn:timezone":"Europe/Minsk",
    "iso:country":"BY",
    "name:rus_x_preferred":[
        "\u0418\u043e\u043d\u044b"
    ],
    "name:und_x_variant":[
        "Ivony"
    ],
    "wof:name":"Iony",
    "wof:placetype":"locality"
},
  "geometry": {"coordinates":[31.4096,54.0921],"type":"Point"}
}