{
  "type": "Feature",
  "properties": {
    "gn:admin1_code":"7.0",
    "gn:asciiname":"Krypuli",
    "gn:country_code":"BY",
    "gn:dem":186,
    "gn:feature_class":"P",
    "gn:feature_code":"PPL",
    "gn:name":"Krypuli",
    "gn:population":0,
    "gn:timezone":"Europe/Minsk",
    "iso:country":"BY",
    "name:bel_x_preferred":[
        "\u041a\u0440\u044b\u043f\u0443\u043b\u0456"
    ],
    "name:und_x_variant":[
        "Krypule",
        "Kripuli",
        "Krypuli"
    ],
    "wof:name":"Krypuli",
    "wof:placetype":"locality"
},
  "geometry": {"coordinates":[27.6351,54.786],"type":"Point"}
}