{
  "type": "Feature",
  "properties": {
    "gn:admin1_code":"3.0",
    "gn:asciiname":"Voyteshuny",
    "gn:country_code":"BY",
    "gn:dem":169,
    "gn:feature_class":"P",
    "gn:feature_code":"PPL",
    "gn:name":"Voyteshuny",
    "gn:population":0,
    "gn:timezone":"Europe/Minsk",
    "iso:country":"BY",
    "name:rus_x_preferred":[
        "\u0412\u043e\u0439\u0442\u0435\u0448\u0443\u043d\u044b"
    ],
    "wof:name":"Voyteshuny",
    "wof:placetype":"locality"
},
  "geometry": {"coordinates":[25.3896,54.1177],"type":"Point"}
}