{
  "type": "Feature",
  "properties": {
    "gn:admin1_code":"5.0",
    "gn:asciiname":"Yatskovo Korchemnyye",
    "gn:country_code":"BY",
    "gn:dem":158,
    "gn:feature_class":"P",
    "gn:feature_code":"PPL",
    "gn:name":"Yatskovo Korchemnyye",
    "gn:population":0,
    "gn:timezone":"Europe/Minsk",
    "iso:country":"BY",
    "name:rus_x_preferred":[
        "\u042f\u0446\u043a\u043e\u0432\u043e \u041a\u043e\u0440\u0447\u0435\u043c\u043d\u044b\u0435"
    ],
    "wof:name":"Yatskovo Korchemnyye",
    "wof:placetype":"locality"
},
  "geometry": {"coordinates":[26.6079,54.0153],"type":"Point"}
}