{
  "type": "Feature",
  "properties": {
    "gn:admin1_code":"5.0",
    "gn:asciiname":"Igrishche",
    "gn:country_code":"BY",
    "gn:dem":192,
    "gn:feature_class":"P",
    "gn:feature_code":"PPL",
    "gn:name":"Igrishche",
    "gn:population":0,
    "gn:timezone":"Europe/Minsk",
    "iso:country":"BY",
    "name:rus_x_preferred":[
        "\u0418\u0440\u0433\u0438\u0449\u0435"
    ],
    "wof:name":"Igrishche",
    "wof:placetype":"locality"
},
  "geometry": {"coordinates":[28.7839,54.4334],"type":"Point"}
}