{
  "type": "Feature",
  "properties": {
    "gn:admin1_code":"1.0",
    "gn:asciiname":"Perevis'",
    "gn:country_code":"BY",
    "gn:dem":159,
    "gn:feature_class":"P",
    "gn:feature_code":"PPL",
    "gn:name":"Perevis\u2019",
    "gn:population":0,
    "gn:timezone":"Europe/Minsk",
    "iso:country":"BY",
    "name:rus_x_preferred":[
        "\u041f\u0435\u0440\u0435\u0432\u0438\u0441\u044c"
    ],
    "name:und_x_variant":[
        "Perevis\u2019",
        "Perevys\u2019"
    ],
    "wof:name":"Perevis'",
    "wof:placetype":"locality"
},
  "geometry": {"coordinates":[23.9021,51.6157],"type":"Point"}
}