{
  "type": "Feature",
  "properties": {
    "gn:admin1_code":"7.0",
    "gn:asciiname":"Zaprud'ye",
    "gn:country_code":"BY",
    "gn:dem":138,
    "gn:feature_class":"P",
    "gn:feature_code":"PPL",
    "gn:name":"Zaprud\u2019ye",
    "gn:population":0,
    "gn:timezone":"Europe/Minsk",
    "iso:country":"BY",
    "name:rus_x_preferred":[
        "\u0417\u0430\u043f\u0440\u0443\u0434\u044c\u0435"
    ],
    "name:und_x_variant":[
        "Zaprud\u2019ye"
    ],
    "wof:name":"Zaprud'ye",
    "wof:placetype":"locality"
},
  "geometry": {"coordinates":[29.9237,55.2313],"type":"Point"}
}