{
  "type": "Feature",
  "properties": {
    "gn:admin1_code":"5.0",
    "gn:asciiname":"Bol'shiye Zhaberichi",
    "gn:country_code":"BY",
    "gn:dem":172,
    "gn:feature_class":"P",
    "gn:feature_code":"PPL",
    "gn:name":"Bol\u2019shiye Zhaberichi",
    "gn:population":0,
    "gn:timezone":"Europe/Minsk",
    "iso:country":"BY",
    "name:rus_x_preferred":[
        "\u0411\u043e\u043b\u044c\u0448\u0438\u0435 \u0416\u0430\u0431\u0435\u0440\u0438\u0447\u0438"
    ],
    "name:und_x_variant":[
        "Bol\u2019shiye Zhaberichi"
    ],
    "wof:name":"Bol'shiye Zhaberichi",
    "wof:placetype":"locality"
},
  "geometry": {"coordinates":[28.9308,54.3449],"type":"Point"}
}