{
  "type": "Feature",
  "properties": {
    "gn:country":"BY",
    "gn:fcode":"PPLA2",
    "gn:population":7500,
    "iso:country":"BY",
    "name:bel_x_preferred":[
        "\u0428\u0430\u0440\u043a\u0430\u045e\u0448\u0447\u044b\u043d\u0430"
    ],
    "name:ceb_x_preferred":[
        "Sharkawshchyna"
    ],
    "name:ceb_x_variant":[
        "\u0160arka\u016d\u0161\u010dyna"
    ],
    "name:che_x_preferred":[
        "\u0428\u0430\u0440\u043a\u043e\u0432\u0449\u0438\u043d\u0430"
    ],
    "name:eng_x_preferred":[
        "Sharkowshchyna"
    ],
    "name:eng_x_variant":[
        "Sharkaushchyna",
        "\u0160arka\u016d\u0161\u010dyna"
    ],
    "name:est_x_preferred":[
        "\u0160arka\u016d\u0161\u010dyna"
    ],
    "name:fas_x_preferred":[
        "\u0634\u0627\u0631\u06a9\u0627\u0648\u0634\u0686\u06cc\u0646\u0627"
    ],
    "name:fin_x_preferred":[
        "\u0160arkau\u0161t\u0161yna"
    ],
    "name:fra_x_preferred":[
        "Charkowchtchyna"
    ],
    "name:frr_x_preferred":[
        "Scharkauschtschyna"
    ],
    "name:heb_x_preferred":[
        "\u05e9\u05e8\u05e7\u05d5\u05d1\u05e9\u05e6'\u05d9\u05d6\u05e0\u05d4"
    ],
    "name:hye_x_preferred":[
        "\u0547\u0561\u0580\u056f\u0578\u057e\u0577\u056b\u0576\u0561"
    ],
    "name:ita_x_preferred":[
        "\u0160arokv\u0161ina"
    ],
    "name:ita_x_variant":[
        "\u0160arka\u016d\u0161\u010dyna"
    ],
    "name:lav_x_preferred":[
        "\u0160arkav\u0161\u010dina"
    ],
    "name:lit_x_preferred":[
        "\u0160arkau\u0161\u010dina"
    ],
    "name:nld_x_preferred":[
        "Sharkaushchyna"
    ],
    "name:pol_x_preferred":[
        "Szarkowszczyzna"
    ],
    "name:ron_x_preferred":[
        "\u0160arka\u016d\u0161\u010dyna"
    ],
    "name:rus_x_preferred":[
        "\u0428\u0430\u0440\u043a\u043e\u0432\u0449\u0438\u043d\u0430"
    ],
    "name:srp_x_preferred":[
        "\u0428\u0430\u0440\u043a\u0430\u0432\u0448\u0447\u0438\u043d\u0430"
    ],
    "name:swe_x_preferred":[
        "Sjarka\u016dsjtjyna"
    ],
    "name:tat_x_preferred":[
        "\u0428\u0430\u0440\u043a\u0430\u0432\u0448\u0447\u044b\u043d\u0430"
    ],
    "name:ukr_x_preferred":[
        "\u0428\u0430\u0440\u043a\u043e\u0432\u0449\u0438\u043d\u0430"
    ],
    "name:yid_x_preferred":[
        "\u05e9\u05d0\u05e8\u05e7\u05d5\u05d9\u05e1\u05e6\u05e2\u05e0\u05e2"
    ],
    "qs:name":"Sharkawshchyna",
    "qs:photos_9r":0,
    "qs:photos_sr":0,
    "qs:pop_sr":"5",
    "wd:wordcount":150,
    "wof:name":"Sharkawshchyna",
    "wof:placetype":"locality",
    "wof:population":7500
},
  "geometry": {"coordinates":[27.4686,55.3689],"type":"Point"}
}