{
  "type": "Feature",
  "properties": {
    "gn:admin1_code":"1.0",
    "gn:asciiname":"Dashevichi",
    "gn:country_code":"BY",
    "gn:dem":160,
    "gn:feature_class":"P",
    "gn:feature_code":"PPL",
    "gn:name":"Dashevichi",
    "gn:population":0,
    "gn:timezone":"Europe/Minsk",
    "iso:country":"BY",
    "name:rus_x_preferred":[
        "\u0414\u0430\u0448\u0435\u0432\u0438\u0447\u0438"
    ],
    "name:und_x_variant":[
        "Deshevichi"
    ],
    "wof:name":"Dashevichi",
    "wof:placetype":"locality"
},
  "geometry": {"coordinates":[23.7345,52.5098],"type":"Point"}
}