{
  "type": "Feature",
  "properties": {
    "gn:admin1_code":"7.0",
    "gn:asciiname":"Ostrovno",
    "gn:country_code":"BY",
    "gn:dem":137,
    "gn:feature_class":"P",
    "gn:feature_code":"PPL",
    "gn:name":"Ostrovno",
    "gn:population":0,
    "gn:timezone":"Europe/Minsk",
    "iso:country":"BY",
    "name:rus_x_preferred":[
        "\u041e\u0441\u0442\u0440\u043e\u0432\u043d\u043e"
    ],
    "wof:name":"Ostrovno",
    "wof:placetype":"locality"
},
  "geometry": {"coordinates":[28.9436,55.0061],"type":"Point"}
}