{
  "type": "Feature",
  "properties": {
    "gn:admin1_code":"3.0",
    "gn:asciiname":"Misyury",
    "gn:country_code":"BY",
    "gn:dem":130,
    "gn:feature_class":"P",
    "gn:feature_code":"PPL",
    "gn:name":"Misyury",
    "gn:population":0,
    "gn:timezone":"Europe/Minsk",
    "iso:country":"BY",
    "name:rus_x_preferred":[
        "\u041c\u0438\u0441\u044e\u0440\u044b"
    ],
    "name:rus_x_variant":[
        "\u041c\u0438\u0441\u0441\u0443\u0440\u0438"
    ],
    "name:und_x_variant":[
        "Misyuri",
        "Missuri"
    ],
    "wof:name":"Misyury",
    "wof:placetype":"locality"
},
  "geometry": {"coordinates":[25.5802,53.8834],"type":"Point"}
}