{
  "type": "Feature",
  "properties": {
    "gn:admin1_code":"7.0",
    "gn:asciiname":"Karandashi",
    "gn:country_code":"BY",
    "gn:dem":130,
    "gn:feature_class":"P",
    "gn:feature_code":"PPL",
    "gn:name":"Karandashi",
    "gn:population":0,
    "gn:timezone":"Europe/Minsk",
    "iso:country":"BY",
    "name:rus_x_preferred":[
        "\u041a\u0430\u0440\u0430\u043d\u0434\u0430\u0448\u0438"
    ],
    "wof:name":"Karandashi",
    "wof:placetype":"locality"
},
  "geometry": {"coordinates":[27.8796,55.7051],"type":"Point"}
}