{
  "type": "Feature",
  "properties": {
    "gn:admin1_code":"7.0",
    "gn:asciiname":"Avlasenki",
    "gn:country_code":"BY",
    "gn:dem":143,
    "gn:feature_class":"P",
    "gn:feature_code":"PPL",
    "gn:name":"Avlasenki",
    "gn:population":0,
    "gn:timezone":"Europe/Minsk",
    "iso:country":"BY",
    "name:rus_x_preferred":[
        "\u0410\u0432\u043b\u0430\u0441\u0435\u043d\u043a\u0438"
    ],
    "wof:name":"Avlasenki",
    "wof:placetype":"locality"
},
  "geometry": {"coordinates":[28.1818,55.4063],"type":"Point"}
}