{
  "type": "Feature",
  "properties": {
    "gn:admin1_code":"1.0",
    "gn:asciiname":"Peredel'sk",
    "gn:country_code":"BY",
    "gn:dem":162,
    "gn:feature_class":"P",
    "gn:feature_code":"PPL",
    "gn:name":"Peredel\u2019sk",
    "gn:population":0,
    "gn:timezone":"Europe/Minsk",
    "iso:country":"BY",
    "name:rus_x_preferred":[
        "Peredel\u2019sk"
    ],
    "name:rus_x_variant":[
        "\u041f\u0435\u0440\u0435\u0434\u0435\u043b\u044c\u0441\u043a"
    ],
    "name:und_x_variant":[
        "Pshedzel\u2019sk"
    ],
    "wof:name":"Peredel'sk",
    "wof:placetype":"locality"
},
  "geometry": {"coordinates":[24.3089,52.5931],"type":"Point"}
}