{
  "type": "Feature",
  "properties": {
    "gn:admin1_code":"2.0",
    "gn:asciiname":"Bahdanavichy",
    "gn:country_code":"BY",
    "gn:dem":149,
    "gn:feature_class":"P",
    "gn:feature_code":"PPL",
    "gn:name":"Bahdanavichy",
    "gn:population":0,
    "gn:timezone":"Europe/Minsk",
    "iso:country":"BY",
    "name:bel_x_preferred":[
        "\u0411\u0430\u0433\u0434\u0430\u043d\u0430\u0432\u0456\u0447\u044b"
    ],
    "name:eng_x_preferred":[
        "Bogdanovichi"
    ],
    "name:rus_x_preferred":[
        "\u0411\u043e\u0433\u0434\u0430\u043d\u043e\u0432\u0438\u0447\u0438"
    ],
    "name:und_x_variant":[
        "Bogdanovichi",
        "Bahdanavichy"
    ],
    "wof:name":"Bahdanavichy",
    "wof:placetype":"locality"
},
  "geometry": {"coordinates":[30.6909,53.0736],"type":"Point"}
}