{
  "type": "Feature",
  "properties": {
    "gn:admin1_code":"3.0",
    "gn:asciiname":"Khutor-Provozha",
    "gn:country_code":"BY",
    "gn:dem":140,
    "gn:feature_class":"P",
    "gn:feature_code":"PPL",
    "gn:name":"Khutor-Provozha",
    "gn:population":0,
    "gn:timezone":"Europe/Minsk",
    "iso:country":"BY",
    "name:rus_x_preferred":[
        "\u0425\u0443\u0442\u043e\u0440-\u041f\u0440\u043e\u0432\u043e\u0436\u0430"
    ],
    "wof:name":"Khutor-Provozha",
    "wof:placetype":"locality"
},
  "geometry": {"coordinates":[24.84800000000001,53.9221],"type":"Point"}
}