{
  "type": "Feature",
  "properties": {
    "gn:admin1_code":"7.0",
    "gn:asciiname":"Dedino",
    "gn:country_code":"BY",
    "gn:dem":191,
    "gn:feature_class":"P",
    "gn:feature_code":"PPL",
    "gn:name":"Dedino",
    "gn:population":0,
    "gn:timezone":"Europe/Minsk",
    "iso:country":"BY",
    "name:bul_x_preferred":[
        "\u0414\u0435\u0434\u0438\u043d\u043e"
    ],
    "name:fas_x_preferred":[
        "\u062f\u062f\u06cc\u0646\u0648"
    ],
    "name:kat_x_preferred":[
        "\u10d3\u10d4\u10d3\u10d8\u10dc\u10dd"
    ],
    "name:kaz_x_preferred":[
        "\u0414\u0435\u0434\u0438\u043d\u043e"
    ],
    "name:ron_x_preferred":[
        "Dedino"
    ],
    "name:rus_x_preferred":[
        "\u0414\u0435\u0434\u0438\u043d\u043e"
    ],
    "name:ukr_x_preferred":[
        "\u0414\u0435\u0434\u0438\u043d\u043e"
    ],
    "wof:name":"Dedino",
    "wof:placetype":"locality"
},
  "geometry": {"coordinates":[27.9343,55.1056],"type":"Point"}
}