{
  "type": "Feature",
  "properties": {
    "gn:admin1_code":"7.0",
    "gn:asciiname":"Dedino",
    "gn:country_code":"BY",
    "gn:dem":191,
    "gn:feature_class":"P",
    "gn:feature_code":"PPL",
    "gn:name":"Dedino",
    "gn:population":0,
    "gn:timezone":"Europe/Minsk",
    "iso:country":"BY",
    "name:rus_x_preferred":[
        "\u0414\u0435\u0434\u0438\u043d\u043e"
    ],
    "wof:name":"Dedino",
    "wof:placetype":"locality"
},
  "geometry": {"coordinates":[27.9343,55.1056],"type":"Point"}
}