{
  "type": "Feature",
  "properties": {
    "gn:admin1_code":"7.0",
    "gn:asciiname":"Lakonovshchina",
    "gn:country_code":"BY",
    "gn:dem":168,
    "gn:feature_class":"P",
    "gn:feature_code":"PPL",
    "gn:name":"Lakonovshchina",
    "gn:population":0,
    "gn:timezone":"Europe/Minsk",
    "iso:country":"BY",
    "name:rus_x_preferred":[
        "\u041b\u0430\u043a\u043e\u043d\u043e\u0432\u0449\u0438\u043d\u0430"
    ],
    "wof:name":"Lakonovshchina",
    "wof:placetype":"locality"
},
  "geometry": {"coordinates":[27.1679,55.6317],"type":"Point"}
}