{
  "type": "Feature",
  "properties": {
    "gn:admin1_code":"7.0",
    "gn:asciiname":"Borov'ye",
    "gn:country_code":"BY",
    "gn:dem":133,
    "gn:feature_class":"P",
    "gn:feature_code":"PPL",
    "gn:name":"Borov\u2019ye",
    "gn:population":0,
    "gn:timezone":"Europe/Minsk",
    "iso:country":"BY",
    "name:rus_x_preferred":[
        "\u0411\u043e\u0440\u043e\u0432\u044c\u0435"
    ],
    "name:und_x_variant":[
        "Borov\u2019ye"
    ],
    "wof:name":"Borov'ye",
    "wof:placetype":"locality"
},
  "geometry": {"coordinates":[26.9204,55.2954],"type":"Point"}
}