{
  "type": "Feature",
  "properties": {
    "gn:admin1_code":"7.0",
    "gn:asciiname":"Pechishche",
    "gn:country_code":"BY",
    "gn:dem":190,
    "gn:feature_class":"P",
    "gn:feature_code":"PPL",
    "gn:name":"Pechishche",
    "gn:population":0,
    "gn:timezone":"Europe/Minsk",
    "iso:country":"BY",
    "name:rus_x_preferred":[
        "\u041f\u0435\u0447\u0438\u0449\u0435"
    ],
    "wof:name":"Pechishche",
    "wof:placetype":"locality"
},
  "geometry": {"coordinates":[30.6636,54.4216],"type":"Point"}
}