{
  "type": "Feature",
  "properties": {
    "gn:admin1_code":"5.0",
    "gn:asciiname":"Murovanka",
    "gn:country_code":"BY",
    "gn:dem":213,
    "gn:feature_class":"P",
    "gn:feature_code":"PPL",
    "gn:name":"Murovanka",
    "gn:population":0,
    "gn:timezone":"Europe/Minsk",
    "iso:country":"BY",
    "name:rus_x_preferred":[
        "\u041c\u0443\u0440\u043e\u0432\u0430\u043d\u043a\u0430"
    ],
    "name:und_x_variant":[
        "Murovanyy Dvor"
    ],
    "wof:name":"Murovanka",
    "wof:placetype":"locality"
},
  "geometry": {"coordinates":[27.7159,54.2867],"type":"Point"}
}