{
  "type": "Feature",
  "properties": {
    "gn:admin1_code":"7.0",
    "gn:asciiname":"Velikaya Chernitsa",
    "gn:country_code":"BY",
    "gn:dem":146,
    "gn:feature_class":"P",
    "gn:feature_code":"PPL",
    "gn:name":"Velikaya Chernitsa",
    "gn:population":0,
    "gn:timezone":"Europe/Minsk",
    "iso:country":"BY",
    "name:rus_x_preferred":[
        "\u0411\u043e\u043b\u044c\u0448\u0430\u044f \u0427\u0435\u0440\u043d\u0438\u0446\u0430"
    ],
    "name:und_x_variant":[
        "Bol\u2019shaya Chernitsa",
        "Velikaya Chernitsa"
    ],
    "wof:name":"Velikaya Chernitsa",
    "wof:placetype":"locality"
},
  "geometry": {"coordinates":[30.097,55.0147],"type":"Point"}
}