{
  "type": "Feature",
  "properties": {
    "gn:admin1_code":"7.0",
    "gn:asciiname":"Demidovo",
    "gn:country_code":"BY",
    "gn:dem":132,
    "gn:feature_class":"P",
    "gn:feature_code":"PPL",
    "gn:name":"Demidovo",
    "gn:population":0,
    "gn:timezone":"Europe/Minsk",
    "iso:country":"BY",
    "name:che_x_preferred":[
        "\u0414\u0435\u043c\u0438\u0434\u043e\u0432\u043e"
    ],
    "name:rus_x_preferred":[
        "\u0414\u0435\u043c\u0438\u0434\u043e\u0432\u043e"
    ],
    "wof:name":"Demidovo",
    "wof:placetype":"locality"
},
  "geometry": {"coordinates":[28.0772,55.5653],"type":"Point"}
}