{
  "type": "Feature",
  "properties": {
    "gn:admin1_code":"3.0",
    "gn:asciiname":"Igol'niki",
    "gn:country_code":"BY",
    "gn:dem":243,
    "gn:feature_class":"P",
    "gn:feature_code":"PPL",
    "gn:name":"Igol\u2019niki",
    "gn:population":0,
    "gn:timezone":"Europe/Minsk",
    "iso:country":"BY",
    "name:bel_x_preferred":[
        "Ihol\u2019niki"
    ],
    "name:bel_x_variant":[
        "\u0406\u0433\u043e\u043b\u044c\u043d\u0456\u043a\u0456"
    ],
    "name:rus_x_preferred":[
        "\u0418\u0433\u043e\u043b\u044c\u043d\u0438\u043a\u0438"
    ],
    "name:und_x_variant":[
        "Igol\u2019niki"
    ],
    "wof:name":"Igol'niki",
    "wof:placetype":"locality"
},
  "geometry": {"coordinates":[25.7744,53.5214],"type":"Point"}
}