{
  "type": "Feature",
  "properties": {
    "gn:admin1_code":"7.0",
    "gn:asciiname":"Puzany",
    "gn:country_code":"BY",
    "gn:dem":205,
    "gn:feature_class":"P",
    "gn:feature_code":"PPL",
    "gn:name":"Puzany",
    "gn:population":0,
    "gn:timezone":"Europe/Minsk",
    "iso:country":"BY",
    "name:rus_x_preferred":[
        "\u041f\u0443\u0437\u0430\u043d\u044b"
    ],
    "wof:name":"Puzany",
    "wof:placetype":"locality"
},
  "geometry": {"coordinates":[27.7197,54.9683],"type":"Point"}
}