{
  "type": "Feature",
  "properties": {
    "gn:admin1_code":"6.0",
    "gn:asciiname":"Kashin",
    "gn:country_code":"BY",
    "gn:dem":173,
    "gn:feature_class":"P",
    "gn:feature_code":"PPL",
    "gn:name":"Kashin",
    "gn:population":0,
    "gn:timezone":"Europe/Minsk",
    "iso:country":"BY",
    "name:ceb_x_preferred":[
        "Kashin"
    ],
    "name:deu_x_preferred":[
        "Kaschin"
    ],
    "name:ita_x_preferred":[
        "Kashin"
    ],
    "name:jpn_x_preferred":[
        "\u30ab\u30b7\u30f3"
    ],
    "name:rus_x_preferred":[
        "\u041a\u0430\u0448\u0438\u043d"
    ],
    "name:ukr_x_preferred":[
        "\u041a\u0430\u0448\u0438\u043d"
    ],
    "wof:name":"Kashin",
    "wof:placetype":"locality"
},
  "geometry": {"coordinates":[31.88,53.72667],"type":"Point"}
}