{
  "type": "Feature",
  "properties": {
    "gn:admin1_code":"6.0",
    "gn:asciiname":"Slaviki",
    "gn:country_code":"BY",
    "gn:dem":199,
    "gn:feature_class":"P",
    "gn:feature_code":"PPL",
    "gn:name":"Slaviki",
    "gn:population":0,
    "gn:timezone":"Europe/Minsk",
    "iso:country":"BY",
    "name:rus_x_preferred":[
        "\u0421\u043b\u0430\u0432\u0438\u043a\u0438"
    ],
    "wof:name":"Slaviki",
    "wof:placetype":"locality"
},
  "geometry": {"coordinates":[31.0508,54.287],"type":"Point"}
}