{
  "type": "Feature",
  "properties": {
    "gn:admin1_code":"5.0",
    "gn:asciiname":"Barsuki",
    "gn:country_code":"BY",
    "gn:dem":275,
    "gn:feature_class":"P",
    "gn:feature_code":"PPL",
    "gn:name":"Barsuki",
    "gn:population":0,
    "gn:timezone":"Europe/Minsk",
    "iso:country":"BY",
    "name:rus_x_preferred":[
        "\u0411\u0430\u0440\u0441\u0443\u043a\u0438"
    ],
    "wof:name":"Barsuki",
    "wof:placetype":"locality"
},
  "geometry": {"coordinates":[27.1396,53.9167],"type":"Point"}
}