{
  "type": "Feature",
  "properties": {
    "gn:admin1_code":"2.0",
    "gn:asciiname":"Smykovichi",
    "gn:country_code":"BY",
    "gn:dem":134,
    "gn:feature_class":"P",
    "gn:feature_code":"PPL",
    "gn:name":"Smykovichi",
    "gn:population":0,
    "gn:timezone":"Europe/Minsk",
    "iso:country":"BY",
    "name:rus_x_preferred":[
        "\u0421\u043c\u044b\u043a\u043e\u0432\u0438\u0447\u0438"
    ],
    "wof:name":"Smykovichi",
    "wof:placetype":"locality"
},
  "geometry": {"coordinates":[28.9342,52.6375],"type":"Point"}
}