{
  "type": "Feature",
  "properties": {
    "gn:admin1_code":"1.0",
    "gn:asciiname":"Batchy",
    "gn:country_code":"BY",
    "gn:dem":145,
    "gn:feature_class":"P",
    "gn:feature_code":"PPL",
    "gn:name":"Batchy",
    "gn:population":0,
    "gn:timezone":"Europe/Minsk",
    "iso:country":"BY",
    "name:bel_x_preferred":[
        "\u0411\u0430\u0442\u0447\u044b"
    ],
    "name:eng_x_preferred":[
        "Batchi"
    ],
    "name:rus_x_preferred":[
        "\u0411\u0430\u0442\u0447\u0438"
    ],
    "name:und_x_variant":[
        "Batche",
        "Batchy",
        "Batchi"
    ],
    "wof:name":"Batchy",
    "wof:placetype":"locality"
},
  "geometry": {"coordinates":[24.2306,52.2438],"type":"Point"}
}