{
  "type": "Feature",
  "properties": {
    "gn:admin1_code":"1.0",
    "gn:asciiname":"Baraviki",
    "gn:country_code":"BY",
    "gn:dem":141,
    "gn:feature_class":"P",
    "gn:feature_code":"PPL",
    "gn:name":"Baraviki",
    "gn:population":0,
    "gn:timezone":"Europe/Minsk",
    "iso:country":"BY",
    "name:bel_x_preferred":[
        "\u0411\u0430\u0440\u0430\u0432\u0456\u043a\u0456"
    ],
    "name:und_x_variant":[
        "Borowiki",
        "Boroviki",
        "Baraviki"
    ],
    "wof:name":"Baraviki",
    "wof:placetype":"locality"
},
  "geometry": {"coordinates":[26.9425,52.515],"type":"Point"}
}