{
  "type": "Feature",
  "properties": {
    "gn:admin1_code":"7.0",
    "gn:asciiname":"Krivoy Most",
    "gn:country_code":"BY",
    "gn:dem":133,
    "gn:feature_class":"P",
    "gn:feature_code":"PPL",
    "gn:name":"Krivoy Most",
    "gn:population":0,
    "gn:timezone":"Europe/Minsk",
    "iso:country":"BY",
    "name:fas_x_preferred":[
        "\u06a9\u0631\u06cc\u0648\u0648\u06cc \u0645\u0648\u0633\u062a"
    ],
    "name:rus_x_preferred":[
        "\u041a\u0440\u0438\u0432\u043e\u0439 \u041c\u043e\u0441\u0442"
    ],
    "wof:name":"Krivoy Most",
    "wof:placetype":"locality"
},
  "geometry": {"coordinates":[27.0237,55.1886],"type":"Point"}
}