{
  "type": "Feature",
  "properties": {
    "gn:admin1_code":"7.0",
    "gn:asciiname":"Koptevo",
    "gn:country_code":"BY",
    "gn:dem":126,
    "gn:feature_class":"P",
    "gn:feature_code":"PPL",
    "gn:name":"Kopt\u00ebvo",
    "gn:population":0,
    "gn:timezone":"Europe/Minsk",
    "iso:country":"BY",
    "name:rus_x_preferred":[
        "\u041a\u043e\u043f\u0442\u0451\u0432\u043e"
    ],
    "name:und_x_variant":[
        "Kopt\u00ebvo"
    ],
    "wof:name":"Koptevo",
    "wof:placetype":"locality"
},
  "geometry": {"coordinates":[28.2661,55.4878],"type":"Point"}
}