{
  "type": "Feature",
  "properties": {
    "gn:admin1_code":"3.0",
    "gn:asciiname":"Pikelka",
    "gn:country_code":"BY",
    "gn:dem":102,
    "gn:feature_class":"P",
    "gn:feature_code":"PPL",
    "gn:name":"Pikelka",
    "gn:population":0,
    "gn:timezone":"Europe/Minsk",
    "iso:country":"BY",
    "name:rus_x_preferred":[
        "\u041f\u0438\u043a\u0435\u043b\u043a\u0430"
    ],
    "wof:name":"Pikelka",
    "wof:placetype":"locality"
},
  "geometry": {"coordinates":[24.0159,53.4439],"type":"Point"}
}