{
  "type": "Feature",
  "properties": {
    "gn:admin1_code":"7.0",
    "gn:asciiname":"Mostishche Pervoye",
    "gn:country_code":"BY",
    "gn:dem":134,
    "gn:feature_class":"P",
    "gn:feature_code":"PPL",
    "gn:name":"Mostishche Pervoye",
    "gn:population":0,
    "gn:timezone":"Europe/Minsk",
    "iso:country":"BY",
    "name:rus_x_preferred":[
        "\u041c\u043e\u0441\u0442\u0438\u0449\u0435 \u041f\u0435\u0440\u0432\u043e\u0435"
    ],
    "wof:name":"Mostishche Pervoye",
    "wof:placetype":"locality"
},
  "geometry": {"coordinates":[27.1271,55.8241],"type":"Point"}
}