{
  "type": "Feature",
  "properties": {
    "gn:admin1_code":"5.0",
    "gn:asciiname":"Malaya Trostyanitsa",
    "gn:country_code":"BY",
    "gn:dem":170,
    "gn:feature_class":"P",
    "gn:feature_code":"PPL",
    "gn:name":"Malaya Trostyanitsa",
    "gn:population":0,
    "gn:timezone":"Europe/Minsk",
    "iso:country":"BY",
    "name:rus_x_preferred":[
        "\u041c\u0430\u043b\u0430\u044f \u0422\u0440\u043e\u0441\u0442\u044f\u043d\u0438\u0446\u0430"
    ],
    "wof:name":"Malaya Trostyanitsa",
    "wof:placetype":"locality"
},
  "geometry": {"coordinates":[28.399,54.3498],"type":"Point"}
}