{
  "type": "Feature",
  "properties": {
    "gn:admin1_code":"5.0",
    "gn:asciiname":"Yel'nitsa",
    "gn:country_code":"BY",
    "gn:dem":174,
    "gn:feature_class":"P",
    "gn:feature_code":"PPL",
    "gn:name":"Yel\u2019nitsa",
    "gn:population":0,
    "gn:timezone":"Europe/Minsk",
    "iso:country":"BY",
    "name:rus_x_preferred":[
        "\u0415\u043b\u044c\u043d\u0438\u0446\u0430"
    ],
    "name:und_x_variant":[
        "Yel\u2019nitsa"
    ],
    "wof:name":"Yel'nitsa",
    "wof:placetype":"locality"
},
  "geometry": {"coordinates":[27.1756,54.7727],"type":"Point"}
}