{
  "type": "Feature",
  "properties": {
    "gn:admin1_code":"6.0",
    "gn:asciiname":"Izobishche",
    "gn:country_code":"BY",
    "gn:dem":191,
    "gn:feature_class":"P",
    "gn:feature_code":"PPL",
    "gn:name":"Izobishche",
    "gn:population":0,
    "gn:timezone":"Europe/Minsk",
    "iso:country":"BY",
    "name:rus_x_preferred":[
        "\u0418\u0437\u043e\u0431\u0438\u0449\u0435"
    ],
    "wof:name":"Izobishche",
    "wof:placetype":"locality"
},
  "geometry": {"coordinates":[30.0221,54.01],"type":"Point"}
}