{
  "type": "Feature",
  "properties": {
    "gn:admin1_code":"7.0",
    "gn:asciiname":"Svidershchina",
    "gn:country_code":"BY",
    "gn:dem":213,
    "gn:feature_class":"P",
    "gn:feature_code":"PPL",
    "gn:name":"Svidershchina",
    "gn:population":0,
    "gn:timezone":"Europe/Minsk",
    "iso:country":"BY",
    "name:rus_x_preferred":[
        "\u0421\u0432\u0438\u0434\u0435\u0440\u0449\u0438\u043d\u0430"
    ],
    "wof:name":"Svidershchina",
    "wof:placetype":"locality"
},
  "geometry": {"coordinates":[29.868,54.469],"type":"Point"}
}