{
  "type": "Feature",
  "properties": {
    "gn:admin1_code":"3.0",
    "gn:asciiname":"Raslo",
    "gn:country_code":"BY",
    "gn:dem":156,
    "gn:feature_class":"P",
    "gn:feature_code":"PPL",
    "gn:name":"Raslo",
    "gn:population":0,
    "gn:timezone":"Europe/Minsk",
    "iso:country":"BY",
    "name:rus_x_preferred":[
        "\u0420\u0430\u0441\u043b\u043e"
    ],
    "wof:name":"Raslo",
    "wof:placetype":"locality"
},
  "geometry": {"coordinates":[26.4765,54.595],"type":"Point"}
}