{
  "type": "Feature",
  "properties": {
    "gn:admin1_code":"3.0",
    "gn:asciiname":"Malyshi",
    "gn:country_code":"BY",
    "gn:dem":135,
    "gn:feature_class":"P",
    "gn:feature_code":"PPL",
    "gn:name":"Malyshi",
    "gn:population":0,
    "gn:timezone":"Europe/Minsk",
    "iso:country":"BY",
    "name:bel_x_preferred":[
        "Malyshy"
    ],
    "name:bel_x_variant":[
        "\u041c\u0430\u043b\u044b\u0448\u044b"
    ],
    "name:che_x_preferred":[
        "\u041c\u0430\u043b\u044b\u0448\u0438"
    ],
    "name:rus_x_preferred":[
        "\u041c\u0430\u043b\u044b\u0448\u0438"
    ],
    "wof:name":"Malyshi",
    "wof:placetype":"locality"
},
  "geometry": {"coordinates":[25.1117,53.6717],"type":"Point"}
}