{
  "type": "Feature",
  "properties": {
    "gn:admin1_code":"3.0",
    "gn:asciiname":"Serbinichi",
    "gn:country_code":"BY",
    "gn:dem":150,
    "gn:feature_class":"P",
    "gn:feature_code":"PPL",
    "gn:name":"Serbinichi",
    "gn:population":0,
    "gn:timezone":"Europe/Minsk",
    "iso:country":"BY",
    "name:rus_x_preferred":[
        "\u0421\u0435\u0440\u0431\u0438\u043d\u0438\u0447\u0438"
    ],
    "wof:name":"Serbinichi",
    "wof:placetype":"locality"
},
  "geometry": {"coordinates":[24.9048,54.0746],"type":"Point"}
}