{
  "type": "Feature",
  "properties": {
    "gn:admin1_code":"6.0",
    "gn:asciiname":"Khimy",
    "gn:country_code":"BY",
    "gn:dem":156,
    "gn:feature_class":"P",
    "gn:feature_code":"PPL",
    "gn:name":"Khimy",
    "gn:population":0,
    "gn:timezone":"Europe/Minsk",
    "iso:country":"BY",
    "name:bel_x_preferred":[
        "\u0425\u0456\u043c\u044b"
    ],
    "wof:name":"Khimy",
    "wof:placetype":"locality"
},
  "geometry": {"coordinates":[29.4001,53.1644],"type":"Point"}
}