{
  "type": "Feature",
  "properties": {
    "gn:admin1_code":"5.0",
    "gn:asciiname":"Bakun'ki",
    "gn:country_code":"BY",
    "gn:dem":166,
    "gn:feature_class":"P",
    "gn:feature_code":"PPL",
    "gn:name":"Bakun\u2019ki",
    "gn:population":0,
    "gn:timezone":"Europe/Minsk",
    "iso:country":"BY",
    "name:rus_x_preferred":[
        "\u0411\u0430\u043a\u0443\u043d\u044c\u043a\u0438"
    ],
    "name:und_x_variant":[
        "Bakun\u2019ki"
    ],
    "wof:name":"Bakun'ki",
    "wof:placetype":"locality"
},
  "geometry": {"coordinates":[27.4277,54.5775],"type":"Point"}
}