{
  "type": "Feature",
  "properties": {
    "gn:admin1_code":"7.0",
    "gn:asciiname":"Kakhanavichy",
    "gn:country_code":"BY",
    "gn:dem":140,
    "gn:feature_class":"P",
    "gn:feature_code":"PPL",
    "gn:name":"Kakhanavichy",
    "gn:population":0,
    "gn:timezone":"Europe/Minsk",
    "iso:country":"BY",
    "name:bel_x_preferred":[
        "\u041a\u0430\u0445\u0430\u043d\u0430\u0432\u0456\u0447\u044b"
    ],
    "name:eng_x_preferred":[
        "Kokhanovichi"
    ],
    "name:rus_x_preferred":[
        "\u041a\u043e\u0445\u0430\u043d\u043e\u0432\u0438\u0447\u0438"
    ],
    "name:und_x_variant":[
        "Kakhanavichy"
    ],
    "wof:name":"Kakhanavichy",
    "wof:placetype":"locality"
},
  "geometry": {"coordinates":[28.1315,55.8698],"type":"Point"}
}