{
  "type": "Feature",
  "properties": {
    "gn:admin1_code":"7.0",
    "gn:asciiname":"Otradnoye",
    "gn:country_code":"BY",
    "gn:dem":143,
    "gn:feature_class":"P",
    "gn:feature_code":"PPL",
    "gn:name":"Otradnoye",
    "gn:population":0,
    "gn:timezone":"Europe/Minsk",
    "iso:country":"BY",
    "name:rus_x_preferred":[
        "\u041e\u0442\u0440\u0430\u0434\u043d\u043e\u0435"
    ],
    "name:und_x_variant":[
        "Otryadnoye"
    ],
    "wof:name":"Otradnoye",
    "wof:placetype":"locality"
},
  "geometry": {"coordinates":[27.2457,55.4925],"type":"Point"}
}