{
  "type": "Feature",
  "properties": {
    "gn:admin1_code":"6.0",
    "gn:asciiname":"Khvorostyany",
    "gn:country_code":"BY",
    "gn:dem":148,
    "gn:feature_class":"P",
    "gn:feature_code":"PPL",
    "gn:name":"Khvorostyany",
    "gn:population":0,
    "gn:timezone":"Europe/Minsk",
    "iso:country":"BY",
    "name:rus_x_preferred":[
        "\u0425\u0432\u043e\u0440\u043e\u0441\u0442\u044f\u043d\u044b"
    ],
    "wof:name":"Khvorostyany",
    "wof:placetype":"locality"
},
  "geometry": {"coordinates":[30.859,53.6281],"type":"Point"}
}