{
  "type": "Feature",
  "properties": {
    "gn:admin1_code":"5.0",
    "gn:asciiname":"Krestintern",
    "gn:country_code":"BY",
    "gn:dem":193,
    "gn:feature_class":"P",
    "gn:feature_code":"PPL",
    "gn:name":"Krestintern",
    "gn:population":0,
    "gn:timezone":"Europe/Minsk",
    "iso:country":"BY",
    "name:bul_x_preferred":[
        "\u0421\u0435\u043b\u0441\u043a\u0438 \u0438\u043d\u0442\u0435\u0440\u043d\u0430\u0446\u0438\u043e\u043d\u0430\u043b"
    ],
    "name:hrv_x_preferred":[
        "Selja\u010dka internacionala"
    ],
    "name:ita_x_preferred":[
        "Internazionale contadina"
    ],
    "name:pol_x_preferred":[
        "Mi\u0119dzynarod\u00f3wka Ch\u0142opska"
    ],
    "name:rus_x_preferred":[
        "\u041a\u0440\u0435\u0441\u0442\u0438\u043d\u0442\u0435\u0440\u043d"
    ],
    "name:rus_x_variant":[
        "\u041a\u0440\u0435\u0441\u0442\u044c\u044f\u043d\u0441\u043a\u0438\u0439 \u0438\u043d\u0442\u0435\u0440\u043d\u0430\u0446\u0438\u043e\u043d\u0430\u043b"
    ],
    "name:zho_x_preferred":[
        "\u519c\u6c11\u56fd\u9645"
    ],
    "wof:name":"Krestintern",
    "wof:placetype":"locality"
},
  "geometry": {"coordinates":[27.3862,53.4651],"type":"Point"}
}