{
  "type": "Feature",
  "properties": {
    "gn:admin1_code":"5.0",
    "gn:asciiname":"Krestintern",
    "gn:country_code":"BY",
    "gn:dem":193,
    "gn:feature_class":"P",
    "gn:feature_code":"PPL",
    "gn:name":"Krestintern",
    "gn:population":0,
    "gn:timezone":"Europe/Minsk",
    "iso:country":"BY",
    "name:rus_x_preferred":[
        "\u041a\u0440\u0435\u0441\u0442\u0438\u043d\u0442\u0435\u0440\u043d"
    ],
    "wof:name":"Krestintern",
    "wof:placetype":"locality"
},
  "geometry": {"coordinates":[27.3862,53.4651],"type":"Point"}
}