{
  "type": "Feature",
  "properties": {
    "gn:admin1_code":"6.0",
    "gn:asciiname":"Usterkhi",
    "gn:country_code":"BY",
    "gn:dem":141,
    "gn:feature_class":"P",
    "gn:feature_code":"PPL",
    "gn:name":"Usterkhi",
    "gn:population":0,
    "gn:timezone":"Europe/Minsk",
    "iso:country":"BY",
    "name:rus_x_preferred":[
        "\u0423\u0441\u0442\u0435\u0440\u0445\u0438"
    ],
    "name:und_x_variant":[
        "Ustrekhi"
    ],
    "wof:name":"Usterkhi",
    "wof:placetype":"locality"
},
  "geometry": {"coordinates":[28.8667,52.8988],"type":"Point"}
}