{
  "type": "Feature",
  "properties": {
    "gn:admin1_code":"7.0",
    "gn:asciiname":"Mikhali",
    "gn:country_code":"BY",
    "gn:dem":172,
    "gn:feature_class":"P",
    "gn:feature_code":"PPL",
    "gn:name":"Mikhali",
    "gn:population":0,
    "gn:timezone":"Europe/Minsk",
    "iso:country":"BY",
    "name:rus_x_preferred":[
        "\u041c\u0438\u0445\u0430\u043b\u0438"
    ],
    "wof:name":"Mikhali",
    "wof:placetype":"locality"
},
  "geometry": {"coordinates":[30.0079,55.2871],"type":"Point"}
}