{
  "type": "Feature",
  "properties": {
    "gn:admin1_code":"6.0",
    "gn:asciiname":"Babinki",
    "gn:country_code":"BY",
    "gn:dem":209,
    "gn:feature_class":"P",
    "gn:feature_code":"PPL",
    "gn:name":"Babinki",
    "gn:population":0,
    "gn:timezone":"Europe/Minsk",
    "iso:country":"BY",
    "name:rus_x_preferred":[
        "\u0411\u0430\u0431\u0438\u043d\u043a\u0438"
    ],
    "wof:name":"Babinki",
    "wof:placetype":"locality"
},
  "geometry": {"coordinates":[31.2337,54.0251],"type":"Point"}
}