{
  "type": "Feature",
  "properties": {
    "gn:admin1_code":"0.0",
    "gn:asciiname":"Zastenok Dubrovo",
    "gn:country_code":"BY",
    "gn:dem":141,
    "gn:feature_class":"P",
    "gn:feature_code":"PPL",
    "gn:name":"Zastenok Dubrovo",
    "gn:population":0,
    "gn:timezone":"Europe/Minsk",
    "iso:country":"BY",
    "wof:name":"Zastenok Dubrovo",
    "wof:placetype":"locality"
},
  "geometry": {"coordinates":[29.71667,53.03333000000001],"type":"Point"}
}