{
  "type": "Feature",
  "properties": {
    "gn:admin1_code":"3.0",
    "gn:asciiname":"Gurchiny",
    "gn:country_code":"BY",
    "gn:dem":180,
    "gn:feature_class":"P",
    "gn:feature_code":"PPL",
    "gn:name":"Gurchiny",
    "gn:population":0,
    "gn:timezone":"Europe/Minsk",
    "iso:country":"BY",
    "name:rus_x_preferred":[
        "\u0413\u0443\u0440\u0447\u0438\u043d\u044b"
    ],
    "wof:name":"Gurchiny",
    "wof:placetype":"locality"
},
  "geometry": {"coordinates":[24.3645,52.9648],"type":"Point"}
}