{
  "type": "Feature",
  "properties": {
    "gn:admin1_code":"1.0",
    "gn:asciiname":"Yuzefiny",
    "gn:country_code":"BY",
    "gn:dem":154,
    "gn:feature_class":"P",
    "gn:feature_code":"PPL",
    "gn:name":"Yuzefiny",
    "gn:population":0,
    "gn:timezone":"Europe/Minsk",
    "iso:country":"BY",
    "name:rus_x_preferred":[
        "\u042e\u0437\u0435\u0444\u0438\u043d\u044b"
    ],
    "wof:name":"Yuzefiny",
    "wof:placetype":"locality"
},
  "geometry": {"coordinates":[25.2773,52.21100000000001],"type":"Point"}
}