{
  "type": "Feature",
  "properties": {
    "gn:admin1_code":"7.0",
    "gn:asciiname":"Morochi",
    "gn:country_code":"BY",
    "gn:dem":179,
    "gn:feature_class":"P",
    "gn:feature_code":"PPL",
    "gn:name":"Morochi",
    "gn:population":0,
    "gn:timezone":"Europe/Minsk",
    "iso:country":"BY",
    "name:rus_x_preferred":[
        "\u041c\u043e\u0440\u043e\u0447\u0438"
    ],
    "name:und_x_variant":[
        "Maracze",
        "Marache",
        "Morochi"
    ],
    "wof:name":"Morochi",
    "wof:placetype":"locality"
},
  "geometry": {"coordinates":[26.5952,54.9897],"type":"Point"}
}