{
  "type": "Feature",
  "properties": {
    "gn:admin1_code":"1.0",
    "gn:asciiname":"Goshchevo",
    "gn:country_code":"BY",
    "gn:dem":156,
    "gn:feature_class":"P",
    "gn:feature_code":"PPL",
    "gn:name":"Goshchevo",
    "gn:population":0,
    "gn:timezone":"Europe/Minsk",
    "iso:country":"BY",
    "name:eng_x_preferred":[
        "Goshchevo"
    ],
    "name:rus_x_preferred":[
        "\u0413\u043e\u0449\u0435\u0432\u043e"
    ],
    "name:und_x_variant":[
        "Goshchev",
        "Hoszczewo",
        "Goshchevo"
    ],
    "wof:name":"Goshchevo",
    "wof:placetype":"locality"
},
  "geometry": {"coordinates":[25.2066,52.6892],"type":"Point"}
}