{
  "type": "Feature",
  "properties": {
    "gn:admin1_code":"6.0",
    "gn:asciiname":"Kholoblin",
    "gn:country_code":"BY",
    "gn:dem":159,
    "gn:feature_class":"P",
    "gn:feature_code":"PPL",
    "gn:name":"Kholoblin",
    "gn:population":0,
    "gn:timezone":"Europe/Minsk",
    "iso:country":"BY",
    "name:rus_x_preferred":[
        "\u0425\u043e\u043b\u043e\u0431\u043b\u0438\u043d"
    ],
    "wof:name":"Kholoblin",
    "wof:placetype":"locality"
},
  "geometry": {"coordinates":[31.5269,53.6729],"type":"Point"}
}