{
  "type": "Feature",
  "properties": {
    "gn:country":"BY",
    "gn:fcode":"PPL",
    "gn:pop":1807,
    "iso:country":"BY",
    "name:bel_x_preferred":[
        "\u041c\u044f\u0436\u044b\u0441\u044f\u0442\u043a\u0456"
    ],
    "name:eng_x_preferred":[
        "Mezhisyatki"
    ],
    "name:rus_x_preferred":[
        "\u041c\u0435\u0436\u0438\u0441\u044f\u0442\u043a\u0438"
    ],
    "name:unk_x_variant":[
        "Mezhisyatki"
    ],
    "qs:name":"Myazhysyatki",
    "qs:photos_9r":0,
    "qs:photos_sr":0,
    "qs:pop_sr":"3",
    "wof:name":"Myazhysyatki",
    "wof:placetype":"locality",
    "wof:population":1807
},
  "geometry": {"coordinates":[30.1765,53.7776],"type":"Point"}
}