{
  "type": "Feature",
  "properties": {
    "gn:admin1_code":"5.0",
    "gn:asciiname":"Kiltovtsy",
    "gn:country_code":"BY",
    "gn:dem":236,
    "gn:feature_class":"P",
    "gn:feature_code":"PPL",
    "gn:name":"Kiltovtsy",
    "gn:population":0,
    "gn:timezone":"Europe/Minsk",
    "iso:country":"BY",
    "name:rus_x_preferred":[
        "\u041a\u0438\u043b\u0442\u043e\u0432\u0446\u044b"
    ],
    "name:und_x_variant":[
        "Kiltovtsi"
    ],
    "wof:name":"Kiltovtsy",
    "wof:placetype":"locality"
},
  "geometry": {"coordinates":[26.9109,54.1341],"type":"Point"}
}