{
  "type": "Feature",
  "properties": {
    "gn:admin1_code":"7.0",
    "gn:asciiname":"Kavalyova",
    "gn:country_code":"BY",
    "gn:dem":164,
    "gn:feature_class":"P",
    "gn:feature_code":"PPL",
    "gn:name":"Kavalyova",
    "gn:population":0,
    "gn:timezone":"Europe/Minsk",
    "iso:country":"BY",
    "name:bel_x_preferred":[
        "\u041a\u0430\u0432\u0430\u043b\u0451\u0432\u0430"
    ],
    "name:rus_x_preferred":[
        "Koval\u00ebvo"
    ],
    "wof:name":"Kavalyova",
    "wof:placetype":"locality"
},
  "geometry": {"coordinates":[30.677,55.5535],"type":"Point"}
}