{
  "type": "Feature",
  "properties": {
    "gn:admin1_code":"7.0",
    "gn:asciiname":"Prudnyane",
    "gn:country_code":"BY",
    "gn:dem":184,
    "gn:feature_class":"P",
    "gn:feature_code":"PPL",
    "gn:name":"Prudnyane",
    "gn:population":0,
    "gn:timezone":"Europe/Minsk",
    "iso:country":"BY",
    "name:rus_x_preferred":[
        "\u041f\u0440\u0443\u0434\u043d\u044f\u043d\u0435"
    ],
    "wof:name":"Prudnyane",
    "wof:placetype":"locality"
},
  "geometry": {"coordinates":[30.1641,55.5559],"type":"Point"}
}