{
  "type": "Feature",
  "properties": {
    "gn:admin1_code":"3.0",
    "gn:asciiname":"Franopol'ye",
    "gn:country_code":"BY",
    "gn:dem":168,
    "gn:feature_class":"P",
    "gn:feature_code":"PPL",
    "gn:name":"Franopol\u2019ye",
    "gn:population":0,
    "gn:timezone":"Europe/Minsk",
    "iso:country":"BY",
    "name:rus_x_preferred":[
        "\u0424\u0440\u0430\u043d\u043e\u043f\u043e\u043b\u044c\u0435"
    ],
    "name:und_x_variant":[
        "Franopol\u2019ye"
    ],
    "wof:name":"Franopol'ye",
    "wof:placetype":"locality"
},
  "geometry": {"coordinates":[25.4105,54.1273],"type":"Point"}
}