{
  "type": "Feature",
  "properties": {
    "gn:admin1_code":"3.0",
    "gn:asciiname":"Koshlovichi",
    "gn:country_code":"BY",
    "gn:dem":165,
    "gn:feature_class":"P",
    "gn:feature_code":"PPL",
    "gn:name":"Koshlovichi",
    "gn:population":0,
    "gn:timezone":"Europe/Minsk",
    "iso:country":"BY",
    "name:rus_x_preferred":[
        "\u041a\u043e\u0448\u043b\u043e\u0432\u0438\u0447\u0438"
    ],
    "wof:name":"Koshlovichi",
    "wof:placetype":"locality"
},
  "geometry": {"coordinates":[25.1521,52.9585],"type":"Point"}
}