{
  "type": "Feature",
  "properties": {
    "gn:admin1_code":"3.0",
    "gn:asciiname":"Lasosna",
    "gn:country_code":"BY",
    "gn:dem":106,
    "gn:feature_class":"P",
    "gn:feature_code":"PPL",
    "gn:name":"Lasosna",
    "gn:population":0,
    "gn:timezone":"Europe/Minsk",
    "iso:country":"BY",
    "name:bel_x_preferred":[
        "\u041b\u0430\u0441\u043e\u0441\u043d\u0430"
    ],
    "name:ceb_x_preferred":[
        "Lososna"
    ],
    "name:est_x_preferred":[
        "\u0141asosna"
    ],
    "name:lit_x_preferred":[
        "Lasosna"
    ],
    "name:pol_x_preferred":[
        "\u0141oso\u015bna"
    ],
    "name:rus_x_preferred":[
        "\u041b\u043e\u0441\u043e\u0441\u043d\u0430"
    ],
    "name:srp_x_preferred":[
        "\u041b\u0430\u0441\u043e\u0441\u043d\u0430"
    ],
    "name:und_x_variant":[
        "Lososna",
        "Lossosna",
        "Lososno",
        "Lasosna"
    ],
    "wof:name":"Lasosna",
    "wof:placetype":"locality"
},
  "geometry": {"coordinates":[23.7794,53.67100000000001],"type":"Point"}
}