{
  "type": "Feature",
  "properties": {
    "gn:admin1_code":"7.0",
    "gn:asciiname":"Lesnichiye",
    "gn:country_code":"BY",
    "gn:dem":200,
    "gn:feature_class":"P",
    "gn:feature_code":"PPL",
    "gn:name":"Lesnichiye",
    "gn:population":0,
    "gn:timezone":"Europe/Minsk",
    "iso:country":"BY",
    "name:rus_x_preferred":[
        "\u041b\u0435\u0441\u043d\u0438\u0447\u0438\u0435"
    ],
    "wof:name":"Lesnichiye",
    "wof:placetype":"locality"
},
  "geometry": {"coordinates":[30.28,54.7158],"type":"Point"}
}