{
  "type": "Feature",
  "properties": {
    "gn:admin1_code":"1.0",
    "gn:asciiname":"Ziolovo",
    "gn:country_code":"BY",
    "gn:dem":150,
    "gn:feature_class":"P",
    "gn:feature_code":"PPL",
    "gn:name":"Ziolovo",
    "gn:population":0,
    "gn:timezone":"Europe/Minsk",
    "iso:country":"BY",
    "name:rus_x_preferred":[
        "Z\u00eblovo"
    ],
    "name:rus_x_variant":[
        "\u0417\u0451\u043b\u043e\u0432\u043e"
    ],
    "wof:name":"Ziolovo",
    "wof:placetype":"locality"
},
  "geometry": {"coordinates":[24.813,52.2514],"type":"Point"}
}