{
  "type": "Feature",
  "properties": {
    "gn:admin1_code":"3.0",
    "gn:asciiname":"Poddubno",
    "gn:country_code":"BY",
    "gn:dem":132,
    "gn:feature_class":"P",
    "gn:feature_code":"PPL",
    "gn:name":"Poddubno",
    "gn:population":0,
    "gn:timezone":"Europe/Minsk",
    "iso:country":"BY",
    "name:rus_x_preferred":[
        "\u041f\u043e\u0434\u0434\u0443\u0431\u043d\u043e"
    ],
    "name:und_x_variant":[
        "Poddubnoye"
    ],
    "wof:name":"Poddubno",
    "wof:placetype":"locality"
},
  "geometry": {"coordinates":[25.345,53.8202],"type":"Point"}
}