{
  "type": "Feature",
  "properties": {
    "gn:admin1_code":"1.0",
    "gn:asciiname":"Osovtsy",
    "gn:country_code":"BY",
    "gn:dem":154,
    "gn:feature_class":"P",
    "gn:feature_code":"PPL",
    "gn:name":"Osovtsy",
    "gn:population":0,
    "gn:timezone":"Europe/Minsk",
    "iso:country":"BY",
    "name:rus_x_preferred":[
        "\u041e\u0441\u043e\u0432\u0446\u044b"
    ],
    "name:und_x_variant":[
        "Osovtse",
        "Osawtsy"
    ],
    "wof:name":"Osovtsy",
    "wof:placetype":"locality"
},
  "geometry": {"coordinates":[24.8451,52.5465],"type":"Point"}
}