{
  "type": "Feature",
  "properties": {
    "gn:admin1_code":"3.0",
    "gn:asciiname":"Derkachi",
    "gn:country_code":"BY",
    "gn:dem":164,
    "gn:feature_class":"P",
    "gn:feature_code":"PPL",
    "gn:name":"Derkachi",
    "gn:population":0,
    "gn:timezone":"Europe/Minsk",
    "iso:country":"BY",
    "name:bel_x_preferred":[
        "Dzyerkachy"
    ],
    "name:bel_x_variant":[
        "\u0414\u0437\u0435\u0440\u043a\u0430\u0447\u044b"
    ],
    "name:rus_x_preferred":[
        "\u0414\u0435\u0440\u043a\u0430\u0447\u0438"
    ],
    "wof:name":"Derkachi",
    "wof:placetype":"locality"
},
  "geometry": {"coordinates":[24.624,53.2079],"type":"Point"}
}