{
  "type": "Feature",
  "properties": {
    "gn:country":"BY",
    "gn:fcode":"PPLA2",
    "gn:population":15700,
    "iso:country":"BY",
    "name:bel_x_preferred":[
        "\u0428\u0447\u0443\u0447\u044b\u043d"
    ],
    "name:bul_x_preferred":[
        "\u0428\u0447\u0443\u0447\u0438\u043d"
    ],
    "name:ceb_x_preferred":[
        "Shchuchin"
    ],
    "name:ceb_x_variant":[
        "\u0160\u010du\u010dyn"
    ],
    "name:ces_x_preferred":[
        "\u0160\u010du\u010dyn"
    ],
    "name:che_x_preferred":[
        "\u0429\u0443\u0447\u0438\u043d"
    ],
    "name:deu_x_preferred":[
        "\u0160\u010du\u010dyn"
    ],
    "name:eng_x_preferred":[
        "Shchuchyn"
    ],
    "name:eng_x_variant":[
        "\u0160\u010du\u010dyn"
    ],
    "name:epo_x_preferred":[
        "\u015c\u0109u\u0109in"
    ],
    "name:est_x_preferred":[
        "\u0160\u010du\u010dyn"
    ],
    "name:fas_x_preferred":[
        "\u0634\u0686\u0648\u0686\u06cc\u0646"
    ],
    "name:fin_x_preferred":[
        "\u0160t\u0161ut\u0161yn"
    ],
    "name:fra_x_preferred":[
        "Chtchoutchyn"
    ],
    "name:frr_x_preferred":[
        "Schtschutschyn"
    ],
    "name:heb_x_preferred":[
        "\u05e9\u05e6'\u05d5\u05e6'\u05d9\u05df"
    ],
    "name:hsb_x_preferred":[
        "\u0160\u0107u\u010dyn"
    ],
    "name:ita_x_preferred":[
        "\u0160\u010du\u010dyn"
    ],
    "name:jpn_x_preferred":[
        "\u30b7\u30c1\u30e5\u30c1\u30f3"
    ],
    "name:kor_x_preferred":[
        "\uc288\uc288\uce5c"
    ],
    "name:lav_x_preferred":[
        "\u0160\u010du\u010dina"
    ],
    "name:lit_x_preferred":[
        "\u0160\u010diutinas"
    ],
    "name:nld_x_preferred":[
        "Shchuchyn"
    ],
    "name:oss_x_preferred":[
        "\u0429\u0443\u0447\u0438\u043d"
    ],
    "name:pol_x_preferred":[
        "Szczuczyn"
    ],
    "name:ron_x_preferred":[
        "\u0160\u010du\u010dyn"
    ],
    "name:rus_x_preferred":[
        "\u0429\u0443\u0447\u0438\u043d"
    ],
    "name:spa_x_preferred":[
        "Shchuchyn"
    ],
    "name:spa_x_variant":[
        "\u0160\u010du\u010dyn"
    ],
    "name:srp_x_preferred":[
        "\u0428\u0447\u0443\u0447\u0438\u043d"
    ],
    "name:swe_x_preferred":[
        "Sjtjutjyn"
    ],
    "name:szl_x_preferred":[
        "Szczuczyn"
    ],
    "name:tat_x_preferred":[
        "\u0428\u0447\u0443\u0447\u044b\u043d"
    ],
    "name:ukr_x_preferred":[
        "\u0429\u0443\u0447\u0438\u043d"
    ],
    "name:yid_x_preferred":[
        "\u05e9\u05d8\u05e9\u05d5\u05d8\u05e9\u05d9\u05df"
    ],
    "name:zho_x_preferred":[
        "\u4f11\u6b3d"
    ],
    "qs:name":"Shchuchin",
    "qs:photos_9r":0,
    "qs:photos_sr":0,
    "qs:pop_sr":"6",
    "wd:population":15042,
    "wd:wordcount":769,
    "wof:name":"Shchuchin",
    "wof:placetype":"locality",
    "wof:population":15042
},
  "geometry": {"coordinates":[24.7465,53.6014],"type":"Point"}
}