{
  "type": "Feature",
  "properties": {
    "gn:admin1_code":"5.0",
    "gn:asciiname":"Davydki",
    "gn:country_code":"BY",
    "gn:dem":189,
    "gn:feature_class":"P",
    "gn:feature_code":"PPL",
    "gn:name":"Davydki",
    "gn:population":0,
    "gn:timezone":"Europe/Minsk",
    "iso:country":"BY",
    "name:rus_x_preferred":[
        "\u0414\u0430\u0432\u044b\u0434\u043a\u0438"
    ],
    "wof:name":"Davydki",
    "wof:placetype":"locality"
},
  "geometry": {"coordinates":[27.1984,54.6069],"type":"Point"}
}