{
  "type": "Feature",
  "properties": {
    "gn:admin1_code":"5.0",
    "gn:asciiname":"Al'byanka",
    "gn:country_code":"BY",
    "gn:dem":177,
    "gn:feature_class":"P",
    "gn:feature_code":"PPL",
    "gn:name":"Al\u2019byanka",
    "gn:population":0,
    "gn:timezone":"Europe/Minsk",
    "iso:country":"BY",
    "name:rus_x_preferred":[
        "\u0410\u043b\u044c\u0431\u044f\u043d\u043a\u0430"
    ],
    "name:und_x_variant":[
        "Al\u2019byanka"
    ],
    "wof:name":"Al'byanka",
    "wof:placetype":"locality"
},
  "geometry": {"coordinates":[26.6116,53.2022],"type":"Point"}
}