{
  "type": "Feature",
  "properties": {
    "gn:admin1_code":"7.0",
    "gn:asciiname":"Lisovshchina",
    "gn:country_code":"BY",
    "gn:dem":205,
    "gn:feature_class":"P",
    "gn:feature_code":"PPL",
    "gn:name":"Lisovshchina",
    "gn:population":0,
    "gn:timezone":"Europe/Minsk",
    "iso:country":"BY",
    "name:rus_x_preferred":[
        "\u041b\u0438\u0441\u043e\u0432\u0449\u0438\u043d\u0430"
    ],
    "wof:name":"Lisovshchina",
    "wof:placetype":"locality"
},
  "geometry": {"coordinates":[29.7285,54.4444],"type":"Point"}
}