{
  "type": "Feature",
  "properties": {
    "gn:admin1_code":"6.0",
    "gn:asciiname":"Ostravy",
    "gn:country_code":"BY",
    "gn:dem":159,
    "gn:feature_class":"P",
    "gn:feature_code":"PPL",
    "gn:name":"Ostravy",
    "gn:population":0,
    "gn:timezone":"Europe/Minsk",
    "iso:country":"BY",
    "name:rus_x_preferred":[
        "\u041e\u0441\u0442\u0440\u0430\u0432\u044b"
    ],
    "wof:name":"Ostravy",
    "wof:placetype":"locality"
},
  "geometry": {"coordinates":[29.0094,53.0447],"type":"Point"}
}