{
  "type": "Feature",
  "properties": {
    "gn:admin1_code":"7.0",
    "gn:asciiname":"Vyshadki",
    "gn:country_code":"BY",
    "gn:dem":182,
    "gn:feature_class":"P",
    "gn:feature_code":"PPL",
    "gn:name":"Vyshadki",
    "gn:population":0,
    "gn:timezone":"Europe/Minsk",
    "iso:country":"BY",
    "name:bel_x_preferred":[
        "\u0412\u044b\u0448\u0430\u0434\u043a\u0456"
    ],
    "name:und_x_variant":[
        "Vyshedki"
    ],
    "wof:name":"Vyshadki",
    "wof:placetype":"locality"
},
  "geometry": {"coordinates":[30.1448,55.6255],"type":"Point"}
}