{
  "type": "Feature",
  "properties": {
    "gn:admin1_code":"7.0",
    "gn:asciiname":"Huta",
    "gn:country_code":"BY",
    "gn:dem":135,
    "gn:feature_class":"P",
    "gn:feature_code":"PPL",
    "gn:name":"Huta",
    "gn:population":0,
    "gn:timezone":"Europe/Minsk",
    "iso:country":"BY",
    "name:bel_x_preferred":[
        "\u0413\u0443\u0442\u0430"
    ],
    "name:ceb_x_preferred":[
        "Huta"
    ],
    "name:deu_x_preferred":[
        "Huta"
    ],
    "name:epo_x_preferred":[
        "Huta"
    ],
    "name:fra_x_preferred":[
        "Huta"
    ],
    "name:hun_x_preferred":[
        "Huta"
    ],
    "name:hye_x_preferred":[
        "\u0533\u0578\u0582\u057f\u0561"
    ],
    "name:jpn_x_preferred":[
        "\u30d5\u30fc\u30bf"
    ],
    "name:lit_x_preferred":[
        "\u016ata"
    ],
    "name:pol_x_preferred":[
        "Huta"
    ],
    "name:ron_x_preferred":[
        "Huta"
    ],
    "name:srp_x_preferred":[
        "\u0425\u0443\u0442\u0430"
    ],
    "name:swe_x_preferred":[
        "Huta"
    ],
    "name:ukr_x_preferred":[
        "\u0413\u0443\u0442\u0430"
    ],
    "name:und_x_variant":[
        "Guta"
    ],
    "wof:name":"Huta",
    "wof:placetype":"locality"
},
  "geometry": {"coordinates":[27.1973,55.2013],"type":"Point"}
}