{
  "type": "Feature",
  "properties": {
    "gn:admin1_code":"7.0",
    "gn:asciiname":"Poselok Nomer Chetyre",
    "gn:country_code":"BY",
    "gn:dem":173,
    "gn:feature_class":"P",
    "gn:feature_code":"PPL",
    "gn:name":"Pos\u00eblok Nomer Chetyre",
    "gn:population":0,
    "gn:timezone":"Europe/Minsk",
    "iso:country":"BY",
    "name:rus_x_preferred":[
        "\u041f\u043e\u0441\u0451\u043b\u043e\u043a \u041d\u043e\u043c\u0435\u0440 \u0427\u0435\u0442\u044b\u0440\u0435"
    ],
    "name:und_x_variant":[
        "Pos\u00eblok Nomer Chetyre"
    ],
    "wof:name":"Poselok Nomer Chetyre",
    "wof:placetype":"locality"
},
  "geometry": {"coordinates":[30.7149,54.7407],"type":"Point"}
}