{
  "type": "Feature",
  "properties": {
    "gn:admin1_code":"2.0",
    "gn:asciiname":"Zaton",
    "gn:country_code":"BY",
    "gn:dem":137,
    "gn:feature_class":"P",
    "gn:feature_code":"PPL",
    "gn:name":"Zaton",
    "gn:population":0,
    "gn:timezone":"Europe/Minsk",
    "iso:country":"BY",
    "name:rus_x_preferred":[
        "\u0417\u0430\u0442\u043e\u043d"
    ],
    "wof:name":"Zaton",
    "wof:placetype":"locality"
},
  "geometry": {"coordinates":[30.1124,52.7764],"type":"Point"}
}