{
  "type": "Feature",
  "properties": {
    "gn:admin1_code":"6.0",
    "gn:asciiname":"Pavlinka",
    "gn:country_code":"BY",
    "gn:dem":186,
    "gn:feature_class":"P",
    "gn:feature_code":"PPL",
    "gn:name":"Pavlinka",
    "gn:population":0,
    "gn:timezone":"Europe/Minsk",
    "iso:country":"BY",
    "name:rus_x_preferred":[
        "\u041f\u0430\u0432\u043b\u0438\u043d\u043a\u0430"
    ],
    "wof:name":"Pavlinka",
    "wof:placetype":"locality"
},
  "geometry": {"coordinates":[29.9178,53.9164],"type":"Point"}
}