{
  "type": "Feature",
  "properties": {
    "gn:admin1_code":"7.0",
    "gn:asciiname":"Rozhno",
    "gn:country_code":"BY",
    "gn:dem":185,
    "gn:feature_class":"P",
    "gn:feature_code":"PPL",
    "gn:name":"Rozhno",
    "gn:population":0,
    "gn:timezone":"Europe/Minsk",
    "iso:country":"BY",
    "name:rus_x_preferred":[
        "\u0420\u043e\u0436\u043d\u043e"
    ],
    "wof:name":"Rozhno",
    "wof:placetype":"locality"
},
  "geometry": {"coordinates":[28.2808,54.7671],"type":"Point"}
}