{
  "type": "Feature",
  "properties": {
    "gn:admin1_code":"5.0",
    "gn:asciiname":"Dolzhany",
    "gn:country_code":"BY",
    "gn:dem":268,
    "gn:feature_class":"P",
    "gn:feature_code":"PPL",
    "gn:name":"Dolzhany",
    "gn:population":0,
    "gn:timezone":"Europe/Minsk",
    "iso:country":"BY",
    "name:rus_x_preferred":[
        "\u0414\u043e\u043b\u0436\u0430\u043d\u044b"
    ],
    "wof:name":"Dolzhany",
    "wof:placetype":"locality"
},
  "geometry": {"coordinates":[27.2007,54.0281],"type":"Point"}
}