{
  "type": "Feature",
  "properties": {
    "gn:admin1_code":"6.0",
    "gn:asciiname":"Tushevaya",
    "gn:country_code":"BY",
    "gn:dem":191,
    "gn:feature_class":"P",
    "gn:feature_code":"PPL",
    "gn:name":"Tushevaya",
    "gn:population":0,
    "gn:timezone":"Europe/Minsk",
    "iso:country":"BY",
    "name:rus_x_preferred":[
        "\u0422\u0443\u0448\u0435\u0432\u0430\u044f"
    ],
    "wof:name":"Tushevaya",
    "wof:placetype":"locality"
},
  "geometry": {"coordinates":[30.7503,54.2932],"type":"Point"}
}