{
  "type": "Feature",
  "properties": {
    "gn:admin1_code":"7.0",
    "gn:asciiname":"Kavali",
    "gn:country_code":"BY",
    "gn:dem":142,
    "gn:feature_class":"P",
    "gn:feature_code":"PPL",
    "gn:name":"Kavali",
    "gn:population":0,
    "gn:timezone":"Europe/Minsk",
    "iso:country":"BY",
    "name:bel_x_preferred":[
        "\u041a\u0430\u0432\u0430\u043b\u0456"
    ],
    "name:bpy_x_preferred":[
        "\u0995\u09ad\u09be\u09b2\u09c0"
    ],
    "name:ceb_x_preferred":[
        "K\u0101vali"
    ],
    "name:fas_x_preferred":[
        "\u06a9\u0627\u0648\u0627\u0644\u06cc"
    ],
    "name:fra_x_preferred":[
        "Kavali"
    ],
    "name:ita_x_preferred":[
        "Kavali"
    ],
    "name:mlg_x_preferred":[
        "Kavali"
    ],
    "name:msa_x_preferred":[
        "Kavali"
    ],
    "name:new_x_preferred":[
        "\u0915\u093e\u092d\u0947\u0932\u0940"
    ],
    "name:ori_x_preferred":[
        "\u0b15\u0b3e\u0b2c\u0b3e\u0b32\u0b3f"
    ],
    "name:por_x_preferred":[
        "Kavali"
    ],
    "name:swe_x_preferred":[
        "Kavali"
    ],
    "name:tam_x_preferred":[
        "\u0b95\u0bbe\u0bb5\u0bb2\u0bbf"
    ],
    "name:tel_x_preferred":[
        "\u0c15\u0c3e\u0c35\u0c32\u0c3f"
    ],
    "name:und_x_variant":[
        "Kovali"
    ],
    "name:urd_x_preferred":[
        "\u06a9\u0627\u0648\u0644\u06cc"
    ],
    "name:vie_x_preferred":[
        "Kavali"
    ],
    "name:zho_x_preferred":[
        "\u5361\u74e6\u5229"
    ],
    "wof:name":"Kavali",
    "wof:placetype":"locality"
},
  "geometry": {"coordinates":[28.5026,55.8402],"type":"Point"}
}