{
  "type": "Feature",
  "properties": {
    "gn:admin1_code":"7.0",
    "gn:asciiname":"Kavali",
    "gn:country_code":"BY",
    "gn:dem":142,
    "gn:feature_class":"P",
    "gn:feature_code":"PPL",
    "gn:name":"Kavali",
    "gn:population":0,
    "gn:timezone":"Europe/Minsk",
    "iso:country":"BY",
    "name:bel_x_preferred":[
        "\u041a\u0430\u0432\u0430\u043b\u0456"
    ],
    "name:und_x_variant":[
        "Kovali"
    ],
    "wof:name":"Kavali",
    "wof:placetype":"locality"
},
  "geometry": {"coordinates":[28.5026,55.8402],"type":"Point"}
}