{
  "type": "Feature",
  "properties": {
    "gn:admin1_code":"2.0",
    "gn:asciiname":"Krasnobudskiy",
    "gn:country_code":"BY",
    "gn:dem":142,
    "gn:feature_class":"P",
    "gn:feature_code":"PPL",
    "gn:name":"Krasnobudskiy",
    "gn:population":0,
    "gn:timezone":"Europe/Minsk",
    "iso:country":"BY",
    "name:rus_x_preferred":[
        "\u041a\u0440\u0430\u0441\u043d\u043e\u0431\u0443\u0434\u0441\u043a\u0438\u0439"
    ],
    "wof:name":"Krasnobudskiy",
    "wof:placetype":"locality"
},
  "geometry": {"coordinates":[30.4462,52.588],"type":"Point"}
}