{
  "type": "Feature",
  "properties": {
    "gn:admin1_code":"7.0",
    "gn:asciiname":"Shustevo",
    "gn:country_code":"BY",
    "gn:dem":233,
    "gn:feature_class":"P",
    "gn:feature_code":"PPL",
    "gn:name":"Shustevo",
    "gn:population":0,
    "gn:timezone":"Europe/Minsk",
    "iso:country":"BY",
    "name:rus_x_preferred":[
        "\u0428\u0443\u0441\u0442\u0435\u0432\u043e"
    ],
    "wof:name":"Shustevo",
    "wof:placetype":"locality"
},
  "geometry": {"coordinates":[30.7452,55.129],"type":"Point"}
}