{
  "type": "Feature",
  "properties": {
    "gn:admin1_code":"5.0",
    "gn:asciiname":"Zamostyany",
    "gn:country_code":"BY",
    "gn:dem":204,
    "gn:feature_class":"P",
    "gn:feature_code":"PPL",
    "gn:name":"Zamostyany",
    "gn:population":0,
    "gn:timezone":"Europe/Minsk",
    "iso:country":"BY",
    "name:rus_x_preferred":[
        "\u0417\u0430\u043c\u043e\u0441\u0442\u044f\u043d\u044b"
    ],
    "wof:name":"Zamostyany",
    "wof:placetype":"locality"
},
  "geometry": {"coordinates":[26.791,53.8602],"type":"Point"}
}