{
  "type": "Feature",
  "properties": {
    "gn:admin1_code":"1.0",
    "gn:asciiname":"Krasiyevo",
    "gn:country_code":"BY",
    "gn:dem":139,
    "gn:feature_class":"P",
    "gn:feature_code":"PPL",
    "gn:name":"Krasiyevo",
    "gn:population":0,
    "gn:timezone":"Europe/Minsk",
    "iso:country":"BY",
    "name:rus_x_preferred":[
        "\u041a\u0440\u0430\u0441\u0438\u0435\u0432\u043e"
    ],
    "wof:name":"Krasiyevo",
    "wof:placetype":"locality"
},
  "geometry": {"coordinates":[26.0545,52.1925],"type":"Point"}
}