{
  "type": "Feature",
  "properties": {
    "gn:admin1_code":"2.0",
    "gn:asciiname":"Tremlya",
    "gn:country_code":"BY",
    "gn:dem":121,
    "gn:feature_class":"P",
    "gn:feature_code":"PPL",
    "gn:name":"Tremlya",
    "gn:population":0,
    "gn:timezone":"Europe/Minsk",
    "iso:country":"BY",
    "name:rus_x_preferred":[
        "\u0422\u0440\u0435\u043c\u043b\u044f"
    ],
    "wof:name":"Tremlya",
    "wof:placetype":"locality"
},
  "geometry": {"coordinates":[28.8684,52.2657],"type":"Point"}
}