{
  "type": "Feature",
  "properties": {
    "gn:admin1_code":"5.0",
    "gn:asciiname":"Zayamnoye",
    "gn:country_code":"BY",
    "gn:dem":184,
    "gn:feature_class":"P",
    "gn:feature_code":"PPL",
    "gn:name":"Zayamnoye",
    "gn:population":0,
    "gn:timezone":"Europe/Minsk",
    "iso:country":"BY",
    "name:rus_x_preferred":[
        "\u0417\u0430\u044f\u043c\u043d\u043e\u0435"
    ],
    "wof:name":"Zayamnoye",
    "wof:placetype":"locality"
},
  "geometry": {"coordinates":[28.7919,53.7952],"type":"Point"}
}