{
  "type": "Feature",
  "properties": {
    "gn:admin1_code":"5.0",
    "gn:asciiname":"Proshyka",
    "gn:country_code":"BY",
    "gn:dem":168,
    "gn:feature_class":"P",
    "gn:feature_code":"PPL",
    "gn:name":"Proshyka",
    "gn:population":0,
    "gn:timezone":"Europe/Minsk",
    "iso:country":"BY",
    "name:bel_x_preferred":[
        "\u041f\u0440\u043e\u0448\u044b\u043a\u0430"
    ],
    "name:und_x_variant":[
        "Proshitsa",
        "Proshika"
    ],
    "wof:name":"Proshyka",
    "wof:placetype":"locality"
},
  "geometry": {"coordinates":[29.1478,54.4875],"type":"Point"}
}