{
  "type": "Feature",
  "properties": {
    "gn:admin1_code":"6.0",
    "gn:asciiname":"Cherevach",
    "gn:country_code":"BY",
    "gn:dem":159,
    "gn:feature_class":"P",
    "gn:feature_code":"PPL",
    "gn:name":"Cherevach",
    "gn:population":0,
    "gn:timezone":"Europe/Minsk",
    "iso:country":"BY",
    "name:rus_x_preferred":[
        "\u0427\u0435\u0440\u0435\u0432\u0430\u0447"
    ],
    "name:und_x_variant":[
        "Chereva"
    ],
    "wof:name":"Cherevach",
    "wof:placetype":"locality"
},
  "geometry": {"coordinates":[29.1445,53.5391],"type":"Point"}
}