{
  "type": "Feature",
  "properties": {
    "gn:admin1_code":"1.0",
    "gn:asciiname":"Makhro",
    "gn:country_code":"BY",
    "gn:dem":140,
    "gn:feature_class":"P",
    "gn:feature_code":"PPL",
    "gn:name":"Makhro",
    "gn:population":0,
    "gn:timezone":"Europe/Minsk",
    "iso:country":"BY",
    "name:bel_x_preferred":[
        "\u041c\u0430\u0445\u0440\u043e"
    ],
    "name:und_x_variant":[
        "Mochre",
        "Mokhre",
        "Mokhro",
        "Makhro"
    ],
    "wof:name":"Makhro",
    "wof:placetype":"locality"
},
  "geometry": {"coordinates":[25.38333,51.96667],"type":"Point"}
}