{
  "type": "Feature",
  "properties": {
    "gn:admin1_code":"7.0",
    "gn:asciiname":"Krukhanovichi",
    "gn:country_code":"BY",
    "gn:dem":177,
    "gn:feature_class":"P",
    "gn:feature_code":"PPL",
    "gn:name":"Krukhanovichi",
    "gn:population":0,
    "gn:timezone":"Europe/Minsk",
    "iso:country":"BY",
    "name:rus_x_preferred":[
        "\u041a\u0440\u0443\u0445\u0430\u043d\u043e\u0432\u0438\u0447\u0438"
    ],
    "wof:name":"Krukhanovichi",
    "wof:placetype":"locality"
},
  "geometry": {"coordinates":[30.1103,54.5135],"type":"Point"}
}