{
  "type": "Feature",
  "properties": {
    "gn:admin1_code":"5.0",
    "gn:asciiname":"Butsevichi",
    "gn:country_code":"BY",
    "gn:dem":261,
    "gn:feature_class":"P",
    "gn:feature_code":"PPL",
    "gn:name":"Butsevichi",
    "gn:population":0,
    "gn:timezone":"Europe/Minsk",
    "iso:country":"BY",
    "name:rus_x_preferred":[
        "\u0411\u0443\u0446\u0435\u0432\u0438\u0447\u0438"
    ],
    "wof:name":"Butsevichi",
    "wof:placetype":"locality"
},
  "geometry": {"coordinates":[27.4732,54.1277],"type":"Point"}
}