{
  "type": "Feature",
  "properties": {
    "gn:admin1_code":"5.0",
    "gn:asciiname":"Lipki",
    "gn:country_code":"BY",
    "gn:dem":176,
    "gn:feature_class":"P",
    "gn:feature_code":"PPL",
    "gn:name":"Lipki",
    "gn:population":0,
    "gn:timezone":"Europe/Minsk",
    "iso:country":"BY",
    "name:rus_x_preferred":[
        "\u041b\u0438\u043f\u043a\u0438"
    ],
    "wof:name":"Lipki",
    "wof:placetype":"locality"
},
  "geometry": {"coordinates":[28.6608,54.2661],"type":"Point"}
}