{
  "type": "Feature",
  "properties": {
    "gn:admin1_code":"5.0",
    "gn:asciiname":"Dzyahili",
    "gn:country_code":"BY",
    "gn:dem":208,
    "gn:feature_class":"P",
    "gn:feature_code":"PPL",
    "gn:name":"Dzyahili",
    "gn:population":0,
    "gn:timezone":"Europe/Minsk",
    "iso:country":"BY",
    "name:bel_x_preferred":[
        "\u0414\u0437\u044f\u0433\u0456\u043b\u0456"
    ],
    "name:und_x_variant":[
        "Dzyagile",
        "Dziahile",
        "Dyagili",
        "Dzyahili"
    ],
    "wof:name":"Dzyahili",
    "wof:placetype":"locality"
},
  "geometry": {"coordinates":[27.0892,54.9242],"type":"Point"}
}