{
  "type": "Feature",
  "properties": {
    "gn:admin1_code":"3.0",
    "gn:asciiname":"Khartsitsa",
    "gn:country_code":"BY",
    "gn:dem":112,
    "gn:feature_class":"P",
    "gn:feature_code":"PPL",
    "gn:name":"Khartsitsa",
    "gn:population":0,
    "gn:timezone":"Europe/Minsk",
    "iso:country":"BY",
    "name:bel_x_preferred":[
        "\u0425\u0430\u0440\u0446\u0456\u0446\u0430"
    ],
    "name:rus_x_preferred":[
        "\u0425\u0430\u0440\u0442\u0438\u0446\u0430"
    ],
    "name:und_x_variant":[
        "Khartitsa"
    ],
    "wof:name":"Khartsitsa",
    "wof:placetype":"locality"
},
  "geometry": {"coordinates":[24.2567,53.5053],"type":"Point"}
}