{
  "type": "Feature",
  "properties": {
    "gn:admin1_code":"6.0",
    "gn:asciiname":"Vysokaye",
    "gn:country_code":"BY",
    "gn:dem":178,
    "gn:feature_class":"P",
    "gn:feature_code":"PPL",
    "gn:name":"Vysokaye",
    "gn:population":0,
    "gn:timezone":"Europe/Minsk",
    "iso:country":"BY",
    "name:bel_x_preferred":[
        "\u0412\u044b\u0441\u043e\u043a\u0430\u0435"
    ],
    "name:und_x_variant":[
        "Vysokoye",
        "Vysokiye",
        "Vysokaye"
    ],
    "wof:name":"Vysokaye",
    "wof:placetype":"locality"
},
  "geometry": {"coordinates":[31.8701,53.5144],"type":"Point"}
}