{
  "type": "Feature",
  "properties": {
    "gn:admin1_code":"6.0",
    "gn:asciiname":"Vysokaye",
    "gn:country_code":"BY",
    "gn:dem":178,
    "gn:feature_class":"P",
    "gn:feature_code":"PPL",
    "gn:name":"Vysokaye",
    "gn:population":0,
    "gn:timezone":"Europe/Minsk",
    "iso:country":"BY",
    "name:ara_x_preferred":[
        "\u0641\u064a\u0633\u0648\u0643\u0627\u064a"
    ],
    "name:bel_x_preferred":[
        "\u0412\u044b\u0441\u043e\u043a\u0430\u0435"
    ],
    "name:ceb_x_preferred":[
        "Vysokaye"
    ],
    "name:ces_x_preferred":[
        "Vysokaje"
    ],
    "name:deu_x_preferred":[
        "Wyssokaje"
    ],
    "name:est_x_preferred":[
        "Vysokaje"
    ],
    "name:fin_x_preferred":[
        "Vysokaje"
    ],
    "name:fra_x_preferred":[
        "Vyssoka\u00efe"
    ],
    "name:heb_x_preferred":[
        "\u05d5\u05d9\u05e1\u05d5\u05e7\u05d9"
    ],
    "name:hsb_x_preferred":[
        "Wysokaje"
    ],
    "name:ita_x_preferred":[
        "Vysokae"
    ],
    "name:lav_x_preferred":[
        "Visokaje"
    ],
    "name:lit_x_preferred":[
        "Vysokaj\u0117"
    ],
    "name:pol_x_preferred":[
        "Wysokie"
    ],
    "name:rus_x_preferred":[
        "\u0412\u044b\u0441\u043e\u043a\u043e\u0435"
    ],
    "name:srp_x_preferred":[
        "\u0412\u0438\u0441\u043e\u043a\u0430\u0458\u0435"
    ],
    "name:swe_x_preferred":[
        "Vysokaje"
    ],
    "name:ukr_x_preferred":[
        "\u0412\u0438\u0441\u043e\u043a\u0435"
    ],
    "name:und_x_variant":[
        "Vysokoye",
        "Vysokiye",
        "Vysokaye"
    ],
    "name:zho_x_preferred":[
        "\u7dad\u7d22\u79d1\u8036"
    ],
    "wof:name":"Vysokaye",
    "wof:placetype":"locality"
},
  "geometry": {"coordinates":[31.8701,53.5144],"type":"Point"}
}