{
  "type": "Feature",
  "properties": {
    "gn:admin1_code":"2.0",
    "gn:asciiname":"Glushitsa",
    "gn:country_code":"BY",
    "gn:dem":133,
    "gn:feature_class":"P",
    "gn:feature_code":"PPL",
    "gn:name":"Glushitsa",
    "gn:population":0,
    "gn:timezone":"Europe/Minsk",
    "iso:country":"BY",
    "name:rus_x_preferred":[
        "\u0413\u043b\u0443\u0448\u0438\u0446\u0430"
    ],
    "wof:name":"Glushitsa",
    "wof:placetype":"locality"
},
  "geometry": {"coordinates":[30.1122,52.5858],"type":"Point"}
}