{
  "type": "Feature",
  "properties": {
    "gn:admin1_code":"1.0",
    "gn:asciiname":"Zamosze",
    "gn:country_code":"BY",
    "gn:dem":145,
    "gn:feature_class":"P",
    "gn:feature_code":"PPL",
    "gn:name":"Zamosze",
    "gn:population":0,
    "gn:timezone":"Europe/Minsk",
    "iso:country":"BY",
    "name:lit_x_preferred":[
        "Zamo\u0161\u0117"
    ],
    "name:pol_x_preferred":[
        "Zamosze"
    ],
    "name:rus_x_preferred":[
        "Zamosh\u2019ye"
    ],
    "name:rus_x_variant":[
        "\u0417\u0430\u043c\u043e\u0448\u044c\u0435"
    ],
    "name:und_x_variant":[
        "Zamoshe",
        "Zamosze",
        "Zamosh\u2019ye"
    ],
    "wof:name":"Zamosze",
    "wof:placetype":"locality"
},
  "geometry": {"coordinates":[26.7079,52.3798],"type":"Point"}
}