{
  "type": "Feature",
  "properties": {
    "gn:admin1_code":"2.0",
    "gn:asciiname":"Vuhly",
    "gn:country_code":"BY",
    "gn:dem":115,
    "gn:feature_class":"P",
    "gn:feature_code":"PPL",
    "gn:name":"Vuhly",
    "gn:population":0,
    "gn:timezone":"Europe/Minsk",
    "iso:country":"BY",
    "name:bel_x_preferred":[
        "\u0412\u0443\u0433\u043b\u044b"
    ],
    "name:eng_x_preferred":[
        "Ugly"
    ],
    "name:rus_x_preferred":[
        "\u0423\u0433\u043b\u044b"
    ],
    "name:und_x_variant":[
        "Vuhly"
    ],
    "wof:name":"Vuhly",
    "wof:placetype":"locality"
},
  "geometry": {"coordinates":[30.3004,51.8643],"type":"Point"}
}