{
  "type": "Feature",
  "properties": {
    "gn:admin1_code":"3.0",
    "gn:asciiname":"Nizovtsy",
    "gn:country_code":"BY",
    "gn:dem":158,
    "gn:feature_class":"P",
    "gn:feature_code":"PPL",
    "gn:name":"Nizovtsy",
    "gn:population":0,
    "gn:timezone":"Europe/Minsk",
    "iso:country":"BY",
    "name:rus_x_preferred":[
        "\u041d\u0438\u0437\u043e\u0432\u0446\u044b"
    ],
    "wof:name":"Nizovtsy",
    "wof:placetype":"locality"
},
  "geometry": {"coordinates":[25.8178,53.7654],"type":"Point"}
}