{
  "type": "Feature",
  "properties": {
    "gn:admin1_code":"3.0",
    "gn:asciiname":"Slezki",
    "gn:country_code":"BY",
    "gn:dem":190,
    "gn:feature_class":"P",
    "gn:feature_code":"PPL",
    "gn:name":"Sl\u00ebzki",
    "gn:population":0,
    "gn:timezone":"Europe/Minsk",
    "iso:country":"BY",
    "name:rus_x_preferred":[
        "\u0421\u043b\u0451\u0437\u043a\u0438"
    ],
    "name:und_x_variant":[
        "Sl\u00ebzki"
    ],
    "wof:name":"Slezki",
    "wof:placetype":"locality"
},
  "geometry": {"coordinates":[25.5213,54.1959],"type":"Point"}
}