{
  "type": "Feature",
  "properties": {
    "gn:admin1_code":"7.0",
    "gn:asciiname":"Tratsevshchina",
    "gn:country_code":"BY",
    "gn:dem":185,
    "gn:feature_class":"P",
    "gn:feature_code":"PPL",
    "gn:name":"Tratsevshchina",
    "gn:population":0,
    "gn:timezone":"Europe/Minsk",
    "iso:country":"BY",
    "name:rus_x_preferred":[
        "\u0422\u0440\u0430\u0446\u0435\u0432\u0449\u0438\u043d\u0430"
    ],
    "wof:name":"Tratsevshchina",
    "wof:placetype":"locality"
},
  "geometry": {"coordinates":[27.7641,54.7504],"type":"Point"}
}