{
  "type": "Feature",
  "properties": {
    "gn:admin1_code":"7.0",
    "gn:asciiname":"Zales'ki",
    "gn:country_code":"BY",
    "gn:dem":150,
    "gn:feature_class":"P",
    "gn:feature_code":"PPL",
    "gn:name":"Zales\u2019ki",
    "gn:population":0,
    "gn:timezone":"Europe/Minsk",
    "iso:country":"BY",
    "name:rus_x_preferred":[
        "\u0417\u0430\u043b\u0435\u0441\u044c\u043a\u0438"
    ],
    "name:und_x_variant":[
        "Zales\u2019ki"
    ],
    "wof:name":"Zales'ki",
    "wof:placetype":"locality"
},
  "geometry": {"coordinates":[27.4913,55.1906],"type":"Point"}
}