{
  "type": "Feature",
  "properties": {
    "gn:admin1_code":"3.0",
    "gn:asciiname":"Shostaki",
    "gn:country_code":"BY",
    "gn:dem":164,
    "gn:feature_class":"P",
    "gn:feature_code":"PPL",
    "gn:name":"Shostaki",
    "gn:population":0,
    "gn:timezone":"Europe/Minsk",
    "iso:country":"BY",
    "name:rus_x_preferred":[
        "\u0428\u043e\u0441\u0442\u0430\u043a\u0438"
    ],
    "name:und_x_variant":[
        "Szostaki",
        "Shostaki",
        "Shestaki"
    ],
    "wof:name":"Shostaki",
    "wof:placetype":"locality"
},
  "geometry": {"coordinates":[26.5978,54.5302],"type":"Point"}
}