{
  "type": "Feature",
  "properties": {
    "gn:admin1_code":"3.0",
    "gn:asciiname":"Pelyuntsy",
    "gn:country_code":"BY",
    "gn:dem":167,
    "gn:feature_class":"P",
    "gn:feature_code":"PPL",
    "gn:name":"Pelyuntsy",
    "gn:population":0,
    "gn:timezone":"Europe/Minsk",
    "iso:country":"BY",
    "name:rus_x_preferred":[
        "\u041f\u0435\u043b\u044e\u043d\u0446\u044b"
    ],
    "name:rus_x_variant":[
        "\u041f\u0438\u043b\u044e\u043d\u0446\u044b"
    ],
    "name:und_x_variant":[
        "Pilyuntsy"
    ],
    "wof:name":"Pelyuntsy",
    "wof:placetype":"locality"
},
  "geometry": {"coordinates":[25.00086,53.93866],"type":"Point"}
}