{
  "type": "Feature",
  "properties": {
    "gn:admin1_code":"5.0",
    "gn:asciiname":"Zagat'ye",
    "gn:country_code":"BY",
    "gn:dem":177,
    "gn:feature_class":"P",
    "gn:feature_code":"PPL",
    "gn:name":"Zagat\u2019ye",
    "gn:population":0,
    "gn:timezone":"Europe/Minsk",
    "iso:country":"BY",
    "name:rus_x_preferred":[
        "\u0417\u0430\u0433\u0430\u0442\u044c\u0435"
    ],
    "name:und_x_variant":[
        "Zagat\u2019ye"
    ],
    "wof:name":"Zagat'ye",
    "wof:placetype":"locality"
},
  "geometry": {"coordinates":[27.0489,53.5151],"type":"Point"}
}