{
  "type": "Feature",
  "properties": {
    "gn:admin1_code":"3.0",
    "gn:asciiname":"Trokeniki Vtoryye",
    "gn:country_code":"BY",
    "gn:dem":178,
    "gn:feature_class":"P",
    "gn:feature_code":"PPL",
    "gn:name":"Trokeniki Vtoryye",
    "gn:population":0,
    "gn:timezone":"Europe/Minsk",
    "iso:country":"BY",
    "name:rus_x_preferred":[
        "\u0422\u0440\u043e\u043a\u0435\u043d\u0438\u043a\u0438 \u0412\u0442\u043e\u0440\u044b\u0435"
    ],
    "name:und_x_variant":[
        "Trokinki",
        "Trokeniki",
        "Trokeniki Vtoryye"
    ],
    "wof:name":"Trokeniki Vtoryye",
    "wof:placetype":"locality"
},
  "geometry": {"coordinates":[25.8711,54.7608],"type":"Point"}
}