{
  "type": "Feature",
  "properties": {
    "gn:admin1_code":"5.0",
    "gn:asciiname":"Shikovichi",
    "gn:country_code":"BY",
    "gn:dem":166,
    "gn:feature_class":"P",
    "gn:feature_code":"PPL",
    "gn:name":"Shikovichi",
    "gn:population":0,
    "gn:timezone":"Europe/Minsk",
    "iso:country":"BY",
    "name:rus_x_preferred":[
        "\u0428\u0438\u043a\u043e\u0432\u0438\u0447\u0438"
    ],
    "name:und_x_variant":[
        "Szykowicze",
        "Shykoviche",
        "Shikovichi"
    ],
    "wof:name":"Shikovichi",
    "wof:placetype":"locality"
},
  "geometry": {"coordinates":[26.9523,54.8391],"type":"Point"}
}