{
  "type": "Feature",
  "properties": {
    "gn:admin1_code":"5.0",
    "gn:asciiname":"Lyenina",
    "gn:country_code":"BY",
    "gn:dem":164,
    "gn:feature_class":"P",
    "gn:feature_code":"PPL",
    "gn:name":"Lyenina",
    "gn:population":0,
    "gn:timezone":"Europe/Minsk",
    "iso:country":"BY",
    "name:bel_x_preferred":[
        "\u041b\u0435\u043d\u0456\u043d\u0430"
    ],
    "name:eng_x_preferred":[
        "Lenino"
    ],
    "name:rus_x_preferred":[
        "\u041b\u0435\u043d\u0438\u043d\u043e"
    ],
    "name:und_x_variant":[
        "Lenino",
        "Lyenina"
    ],
    "wof:name":"Lyenina",
    "wof:placetype":"locality"
},
  "geometry": {"coordinates":[27.2328,53.0518],"type":"Point"}
}