{
  "type": "Feature",
  "properties": {
    "gn:admin1_code":"3.0",
    "gn:asciiname":"Navasyolki",
    "gn:country_code":"BY",
    "gn:dem":148,
    "gn:feature_class":"P",
    "gn:feature_code":"PPL",
    "gn:name":"Navasyolki",
    "gn:population":0,
    "gn:timezone":"Europe/Minsk",
    "iso:country":"BY",
    "name:bel_x_preferred":[
        "Navasyolki"
    ],
    "name:bel_x_variant":[
        "\u041d\u0430\u0432\u0430\u0441\u0451\u043b\u043a\u0456"
    ],
    "name:rus_x_preferred":[
        "\u041d\u043e\u0432\u043e\u0441\u0451\u043b\u043a\u0438"
    ],
    "name:und_x_variant":[
        "Novos\u00eblki"
    ],
    "wof:name":"Navasyolki",
    "wof:placetype":"locality"
},
  "geometry": {"coordinates":[25.2328,53.172],"type":"Point"}
}