{
  "type": "Feature",
  "properties": {
    "gn:admin1_code":"1.0",
    "gn:asciiname":"Malyye Dikovichi",
    "gn:country_code":"BY",
    "gn:dem":135,
    "gn:feature_class":"P",
    "gn:feature_code":"PPL",
    "gn:name":"Malyye Dikovichi",
    "gn:population":0,
    "gn:timezone":"Europe/Minsk",
    "iso:country":"BY",
    "name:rus_x_preferred":[
        "\u041c\u0430\u043b\u044b\u0435 \u0414\u0438\u043a\u043e\u0432\u0438\u0447\u0438"
    ],
    "wof:name":"Malyye Dikovichi",
    "wof:placetype":"locality"
},
  "geometry": {"coordinates":[26.1115,52.0038],"type":"Point"}
}