{
  "type": "Feature",
  "properties": {
    "gn:admin1_code":"7.0",
    "gn:asciiname":"Zhernelishki",
    "gn:country_code":"BY",
    "gn:dem":138,
    "gn:feature_class":"P",
    "gn:feature_code":"PPL",
    "gn:name":"Zhernelishki",
    "gn:population":0,
    "gn:timezone":"Europe/Minsk",
    "iso:country":"BY",
    "name:rus_x_preferred":[
        "\u0416\u0435\u0440\u043d\u0435\u043b\u0438\u0448\u043a\u0438"
    ],
    "name:und_x_variant":[
        "Zhirnelishki"
    ],
    "wof:name":"Zhernelishki",
    "wof:placetype":"locality"
},
  "geometry": {"coordinates":[26.978,55.4674],"type":"Point"}
}