{
  "type": "Feature",
  "properties": {
    "gn:admin1_code":"5.0",
    "gn:asciiname":"Novyye Falichi",
    "gn:country_code":"BY",
    "gn:dem":158,
    "gn:feature_class":"P",
    "gn:feature_code":"PPL",
    "gn:name":"Novyye Falichi",
    "gn:population":0,
    "gn:timezone":"Europe/Minsk",
    "iso:country":"BY",
    "name:rus_x_preferred":[
        "\u041d\u043e\u0432\u044b\u0435 \u0424\u0430\u043b\u0438\u0447\u0438"
    ],
    "wof:name":"Novyye Falichi",
    "wof:placetype":"locality"
},
  "geometry": {"coordinates":[28.4639,53.0849],"type":"Point"}
}