{
  "type": "Feature",
  "properties": {
    "gn:admin1_code":"2.0",
    "gn:asciiname":"Veselyy Kurgan",
    "gn:country_code":"BY",
    "gn:dem":136,
    "gn:feature_class":"P",
    "gn:feature_code":"PPL",
    "gn:name":"Ves\u00eblyy Kurgan",
    "gn:population":0,
    "gn:timezone":"Europe/Minsk",
    "iso:country":"BY",
    "name:rus_x_preferred":[
        "\u0412\u0435\u0441\u0451\u043b\u044b\u0439 \u041a\u0443\u0440\u0433\u0430\u043d"
    ],
    "name:und_x_variant":[
        "Ves\u00eblyy Kurgan"
    ],
    "wof:name":"Veselyy Kurgan",
    "wof:placetype":"locality"
},
  "geometry": {"coordinates":[30.7048,52.7486],"type":"Point"}
}