{
  "type": "Feature",
  "properties": {
    "gn:admin1_code":"0.0",
    "gn:asciiname":"Soboli",
    "gn:country_code":"BY",
    "gn:dem":153,
    "gn:feature_class":"P",
    "gn:feature_code":"PPL",
    "gn:name":"Soboli",
    "gn:population":0,
    "gn:timezone":"Europe/Minsk",
    "iso:country":"BY",
    "name:bos_x_preferred":[
        "Soboli"
    ],
    "name:ceb_x_preferred":[
        "Soboli"
    ],
    "name:fra_x_preferred":[
        "Soboli"
    ],
    "name:hrv_x_preferred":[
        "Soboli"
    ],
    "name:hun_x_preferred":[
        "Soboli"
    ],
    "name:slv_x_preferred":[
        "Soboli"
    ],
    "name:spa_x_preferred":[
        "Soboli"
    ],
    "name:srp_x_preferred":[
        "\u0421\u043e\u0431\u043e\u043b\u0438"
    ],
    "name:swe_x_preferred":[
        "Soboli"
    ],
    "name:ukr_x_preferred":[
        "\u0421\u043e\u0431\u043e\u043b\u0456"
    ],
    "wof:name":"Soboli",
    "wof:placetype":"locality"
},
  "geometry": {"coordinates":[30.73333,55.33333],"type":"Point"}
}