{
  "type": "Feature",
  "properties": {
    "gn:admin1_code":"5.0",
    "gn:asciiname":"Yazyl'",
    "gn:country_code":"BY",
    "gn:dem":149,
    "gn:feature_class":"P",
    "gn:feature_code":"PPL",
    "gn:name":"Yazyl\u2019",
    "gn:population":0,
    "gn:timezone":"Europe/Minsk",
    "iso:country":"BY",
    "name:bel_x_preferred":[
        "\u042f\u0437\u044b\u043b\u044c"
    ],
    "name:eng_x_preferred":[
        "Yazyl'"
    ],
    "name:rus_x_preferred":[
        "\u042f\u0437\u044b\u043b\u044c"
    ],
    "name:und_x_variant":[
        "Yazyl\u2019"
    ],
    "wof:name":"Yazyl'",
    "wof:placetype":"locality"
},
  "geometry": {"coordinates":[27.9723,52.9797],"type":"Point"}
}