{
  "type": "Feature",
  "properties": {
    "gn:admin1_code":"7.0",
    "gn:asciiname":"Dobromysli",
    "gn:country_code":"BY",
    "gn:dem":223,
    "gn:feature_class":"P",
    "gn:feature_code":"PPL",
    "gn:name":"Dobromysli",
    "gn:population":0,
    "gn:timezone":"Europe/Minsk",
    "iso:country":"BY",
    "name:rus_x_preferred":[
        "\u0414\u043e\u0431\u0440\u043e\u043c\u044b\u0441\u043b\u0438"
    ],
    "wof:name":"Dobromysli",
    "wof:placetype":"locality"
},
  "geometry": {"coordinates":[28.8997,54.7092],"type":"Point"}
}