{
  "type": "Feature",
  "properties": {
    "gn:admin1_code":"1.0",
    "gn:asciiname":"Gulichi",
    "gn:country_code":"BY",
    "gn:dem":204,
    "gn:feature_class":"P",
    "gn:feature_code":"PPL",
    "gn:name":"Gulichi",
    "gn:population":0,
    "gn:timezone":"Europe/Minsk",
    "iso:country":"BY",
    "name:rus_x_preferred":[
        "\u0413\u0443\u043b\u0438\u0447\u0438"
    ],
    "name:und_x_variant":[
        "Guliche"
    ],
    "wof:name":"Gulichi",
    "wof:placetype":"locality"
},
  "geometry": {"coordinates":[26.4969,53.0609],"type":"Point"}
}