{
  "type": "Feature",
  "properties": {
    "gn:admin1_code":"5.0",
    "gn:asciiname":"Leonovo",
    "gn:country_code":"BY",
    "gn:dem":160,
    "gn:feature_class":"P",
    "gn:feature_code":"PPL",
    "gn:name":"Leonovo",
    "gn:population":0,
    "gn:timezone":"Europe/Minsk",
    "iso:country":"BY",
    "name:rus_x_preferred":[
        "\u041b\u0435\u043e\u043d\u043e\u0432\u043e"
    ],
    "wof:name":"Leonovo",
    "wof:placetype":"locality"
},
  "geometry": {"coordinates":[28.7934,54.1363],"type":"Point"}
}