{
  "type": "Feature",
  "properties": {
    "gn:admin1_code":"5.0",
    "gn:asciiname":"Trusovichi",
    "gn:country_code":"BY",
    "gn:dem":242,
    "gn:feature_class":"P",
    "gn:feature_code":"PPL",
    "gn:name":"Trusovichi",
    "gn:population":0,
    "gn:timezone":"Europe/Minsk",
    "iso:country":"BY",
    "name:rus_x_preferred":[
        "\u0422\u0440\u0443\u0441\u043e\u0432\u0438\u0447\u0438"
    ],
    "wof:name":"Trusovichi",
    "wof:placetype":"locality"
},
  "geometry": {"coordinates":[27.4128,54.258],"type":"Point"}
}