{
  "type": "Feature",
  "properties": {
    "gn:admin1_code":"1.0",
    "gn:asciiname":"Badiny",
    "gn:country_code":"BY",
    "gn:dem":169,
    "gn:feature_class":"P",
    "gn:feature_code":"PPL",
    "gn:name":"Badiny",
    "gn:population":0,
    "gn:timezone":"Europe/Minsk",
    "iso:country":"BY",
    "name:rus_x_preferred":[
        "\u0411\u0430\u0434\u0438\u043d\u044b"
    ],
    "wof:name":"Badiny",
    "wof:placetype":"locality"
},
  "geometry": {"coordinates":[25.5889,53.0244],"type":"Point"}
}