{
  "type": "Feature",
  "properties": {
    "gn:admin1_code":"3.0",
    "gn:asciiname":"Mol'nichi",
    "gn:country_code":"BY",
    "gn:dem":164,
    "gn:feature_class":"P",
    "gn:feature_code":"PPL",
    "gn:name":"Mol\u2019nichi",
    "gn:population":0,
    "gn:timezone":"Europe/Minsk",
    "iso:country":"BY",
    "name:bel_x_preferred":[
        "Mol\u2019nichy"
    ],
    "name:bel_x_variant":[
        "\u041c\u043e\u043b\u044c\u043d\u0456\u0447\u044b"
    ],
    "name:rus_x_preferred":[
        "\u041c\u043e\u043b\u044c\u043d\u0438\u0447\u0438"
    ],
    "name:und_x_variant":[
        "Mol\u2019nichi"
    ],
    "wof:name":"Mol'nichi",
    "wof:placetype":"locality"
},
  "geometry": {"coordinates":[25.9944,53.6391],"type":"Point"}
}