{
  "type": "Feature",
  "properties": {
    "gn:admin1_code":"3.0",
    "gn:asciiname":"Bergeli",
    "gn:country_code":"BY",
    "gn:dem":190,
    "gn:feature_class":"P",
    "gn:feature_code":"PPL",
    "gn:name":"Bergeli",
    "gn:population":0,
    "gn:timezone":"Europe/Minsk",
    "iso:country":"BY",
    "name:rus_x_preferred":[
        "\u0411\u0435\u0440\u0433\u0435\u043b\u0438"
    ],
    "wof:name":"Bergeli",
    "wof:placetype":"locality"
},
  "geometry": {"coordinates":[24.0925,53.2807],"type":"Point"}
}