{
  "type": "Feature",
  "properties": {
    "gn:admin1_code":"7.0",
    "gn:asciiname":"Opechki",
    "gn:country_code":"BY",
    "gn:dem":205,
    "gn:feature_class":"P",
    "gn:feature_code":"PPL",
    "gn:name":"Opechki",
    "gn:population":0,
    "gn:timezone":"Europe/Minsk",
    "iso:country":"BY",
    "name:rus_x_preferred":[
        "\u041e\u043f\u0435\u0447\u043a\u0438"
    ],
    "wof:name":"Opechki",
    "wof:placetype":"locality"
},
  "geometry": {"coordinates":[29.6765,54.7327],"type":"Point"}
}