{
  "type": "Feature",
  "properties": {
    "gn:country":"BY",
    "gn:fcode":"PPL",
    "gn:population":15500,
    "iso:country":"BY",
    "name:aze_x_preferred":[
        "Stolbts\u0131"
    ],
    "name:bel_x_preferred":[
        "\u0421\u0442\u043e\u045e\u0431\u0446\u044b"
    ],
    "name:bel_x_variant":[
        "\u0413\u043e\u0440\u0430\u0434 \u0421\u0442\u043e\u045e\u0431\u0446\u044b"
    ],
    "name:bul_x_preferred":[
        "\u0421\u0442\u043e\u043b\u0431\u0446\u0438"
    ],
    "name:ceb_x_preferred":[
        "Stowbtsy"
    ],
    "name:ces_x_preferred":[
        "Stoubcy"
    ],
    "name:eng_x_preferred":[
        "Stowbtsy"
    ],
    "name:est_x_preferred":[
        "Sto\u016dbcy"
    ],
    "name:fin_x_preferred":[
        "Stoubtsy"
    ],
    "name:fra_x_preferred":[
        "Stowbtsy"
    ],
    "name:frr_x_preferred":[
        "Stoubtsy"
    ],
    "name:heb_x_preferred":[
        "\u05e1\u05d8\u05d5\u05d5\u05d1\u05e6\u05d9"
    ],
    "name:hsb_x_preferred":[
        "Stowbcy"
    ],
    "name:hun_x_preferred":[
        "Sztovbci"
    ],
    "name:hye_x_preferred":[
        "\u054d\u057f\u0578\u056c\u0562\u0581\u056b"
    ],
    "name:ind_x_preferred":[
        "Stolbtzy"
    ],
    "name:ita_x_preferred":[
        "Stolbcy"
    ],
    "name:jpn_x_preferred":[
        "\u30b9\u30c8\u30fc\u30d6\u30b7\u30fc"
    ],
    "name:lav_x_preferred":[
        "Stovbci"
    ],
    "name:lit_x_preferred":[
        "Stolpcai"
    ],
    "name:nld_x_preferred":[
        "Stowbtsy"
    ],
    "name:pol_x_preferred":[
        "Sto\u0142pce"
    ],
    "name:ron_x_preferred":[
        "Sto\u016dbcy"
    ],
    "name:rus_x_preferred":[
        "\u0421\u0442\u043e\u043b\u0431\u0446\u044b"
    ],
    "name:srp_x_preferred":[
        "\u0421\u0442\u043e\u0432\u043f\u0446\u0438"
    ],
    "name:swe_x_preferred":[
        "Sto\u016dbtsy"
    ],
    "name:tat_x_preferred":[
        "\u0421\u0442\u043e\u0443\u0431\u0441\u044b"
    ],
    "name:ukr_x_preferred":[
        "\u0421\u0442\u043e\u043b\u0431\u0446\u0456"
    ],
    "name:und_x_variant":[
        "Stolpze"
    ],
    "name:urd_x_preferred":[
        "\u0633\u0679\u0648\u067e\u062a\u0633\u06cc"
    ],
    "name:yid_x_preferred":[
        "\u05e1\u05d8\u05d5\u05d9\u05e4\u05e5"
    ],
    "name:zho_x_preferred":[
        "\u65af\u6258\u723e\u5e03\u9f4a"
    ],
    "qs:name":"Stowbtsy",
    "qs:photos_9r":0,
    "qs:photos_sr":0,
    "qs:pop_sr":"6",
    "wd:population":15991,
    "wd:wordcount":379,
    "wof:name":"Stowbtsy",
    "wof:placetype":"locality",
    "wof:population":15991
},
  "geometry": {"coordinates":[26.7434,53.4785],"type":"Point"}
}