{
  "type": "Feature",
  "properties": {
    "gn:admin1_code":"3.0",
    "gn:asciiname":"Kashali",
    "gn:country_code":"BY",
    "gn:dem":139,
    "gn:feature_class":"P",
    "gn:feature_code":"PPL",
    "gn:name":"Kashali",
    "gn:population":0,
    "gn:timezone":"Europe/Minsk",
    "iso:country":"BY",
    "name:bel_x_preferred":[
        "\u041a\u0430\u0448\u0430\u043b\u0456"
    ],
    "name:und_x_variant":[
        "Koshel\u2019ye",
        "Kosheli"
    ],
    "wof:name":"Kashali",
    "wof:placetype":"locality"
},
  "geometry": {"coordinates":[24.9149,53.047],"type":"Point"}
}