{
  "type": "Feature",
  "properties": {
    "gn:admin1_code":"6.0",
    "gn:asciiname":"Udoha",
    "gn:country_code":"BY",
    "gn:dem":166,
    "gn:feature_class":"P",
    "gn:feature_code":"PPL",
    "gn:name":"Udoha",
    "gn:population":0,
    "gn:timezone":"Europe/Minsk",
    "iso:country":"BY",
    "name:bel_x_preferred":[
        "\u0423\u0434\u043e\u0433\u0430"
    ],
    "name:und_x_variant":[
        "Udoga"
    ],
    "wof:name":"Udoha",
    "wof:placetype":"locality"
},
  "geometry": {"coordinates":[31.3844,53.6713],"type":"Point"}
}