{
  "type": "Feature",
  "properties": {
    "gn:admin1_code":"3.0",
    "gn:asciiname":"Churki",
    "gn:country_code":"BY",
    "gn:dem":187,
    "gn:feature_class":"P",
    "gn:feature_code":"PPL",
    "gn:name":"Churki",
    "gn:population":0,
    "gn:timezone":"Europe/Minsk",
    "iso:country":"BY",
    "name:rus_x_preferred":[
        "\u0427\u0443\u0440\u043a\u0438"
    ],
    "wof:name":"Churki",
    "wof:placetype":"locality"
},
  "geometry": {"coordinates":[25.984,54.2601],"type":"Point"}
}