{
  "type": "Feature",
  "properties": {
    "gn:admin1_code":"3.0",
    "gn:asciiname":"Tsviklichi",
    "gn:country_code":"BY",
    "gn:dem":192,
    "gn:feature_class":"P",
    "gn:feature_code":"PPL",
    "gn:name":"Tsviklichi",
    "gn:population":0,
    "gn:timezone":"Europe/Minsk",
    "iso:country":"BY",
    "name:rus_x_preferred":[
        "\u0426\u0432\u0438\u043a\u043b\u0438\u0447\u0438"
    ],
    "wof:name":"Tsviklichi",
    "wof:placetype":"locality"
},
  "geometry": {"coordinates":[23.8357,53.5648],"type":"Point"}
}