{
  "type": "Feature",
  "properties": {
    "gn:admin1_code":"3.0",
    "gn:asciiname":"Vil'butovo",
    "gn:country_code":"BY",
    "gn:dem":211,
    "gn:feature_class":"P",
    "gn:feature_code":"PPL",
    "gn:name":"Vil\u2019butovo",
    "gn:population":0,
    "gn:timezone":"Europe/Minsk",
    "iso:country":"BY",
    "name:rus_x_preferred":[
        "\u0412\u0438\u043b\u044c\u0431\u0443\u0442\u043e\u0432\u043e"
    ],
    "name:und_x_variant":[
        "Vil\u2019butovo",
        "Okolitsa Vel\u2019butovo"
    ],
    "wof:name":"Vil'butovo",
    "wof:placetype":"locality"
},
  "geometry": {"coordinates":[25.7818,54.3688],"type":"Point"}
}