{
  "type": "Feature",
  "properties": {
    "gn:admin1_code":"3.0",
    "gn:asciiname":"Nortsevichi",
    "gn:country_code":"BY",
    "gn:dem":145,
    "gn:feature_class":"P",
    "gn:feature_code":"PPL",
    "gn:name":"Nortsevichi",
    "gn:population":0,
    "gn:timezone":"Europe/Minsk",
    "iso:country":"BY",
    "name:bel_x_preferred":[
        "Nortsavichy"
    ],
    "name:bel_x_variant":[
        "\u041d\u043e\u0440\u0446\u0430\u0432\u0456\u0447\u044b"
    ],
    "name:rus_x_preferred":[
        "\u041d\u043e\u0440\u0446\u0435\u0432\u0438\u0447\u0438"
    ],
    "name:und_x_variant":[
        "Nortsovichi"
    ],
    "wof:name":"Nortsevichi",
    "wof:placetype":"locality"
},
  "geometry": {"coordinates":[25.4245,53.5162],"type":"Point"}
}