{
  "type": "Feature",
  "properties": {
    "gn:admin1_code":"5.0",
    "gn:asciiname":"Sosny",
    "gn:country_code":"BY",
    "gn:dem":137,
    "gn:feature_class":"P",
    "gn:feature_code":"PPL",
    "gn:name":"Sosny",
    "gn:population":0,
    "gn:timezone":"Europe/Minsk",
    "iso:country":"BY",
    "name:bel_x_preferred":[
        "\u0421\u043e\u0441\u043d\u044b"
    ],
    "wof:name":"Sosny",
    "wof:placetype":"locality"
},
  "geometry": {"coordinates":[28.25,52.668],"type":"Point"}
}