{
  "type": "Feature",
  "properties": {
    "gn:admin1_code":"6.0",
    "gn:asciiname":"Bol'shaya Grava",
    "gn:country_code":"BY",
    "gn:dem":156,
    "gn:feature_class":"P",
    "gn:feature_code":"PPL",
    "gn:name":"Bol\u2019shaya Grava",
    "gn:population":0,
    "gn:timezone":"Europe/Minsk",
    "iso:country":"BY",
    "name:rus_x_preferred":[
        "\u0411\u043e\u043b\u044c\u0448\u0430\u044f \u0413\u0440\u0430\u0432\u0430"
    ],
    "name:und_x_variant":[
        "Bol\u2019shaya Grava"
    ],
    "wof:name":"Bol'shaya Grava",
    "wof:placetype":"locality"
},
  "geometry": {"coordinates":[28.5875,53.4369],"type":"Point"}
}