{
  "type": "Feature",
  "properties": {
    "gn:admin1_code":"2.0",
    "gn:asciiname":"Smagorin",
    "gn:country_code":"BY",
    "gn:dem":131,
    "gn:feature_class":"P",
    "gn:feature_code":"PPL",
    "gn:name":"Smagorin",
    "gn:population":0,
    "gn:timezone":"Europe/Minsk",
    "iso:country":"BY",
    "name:rus_x_preferred":[
        "\u0421\u043c\u0430\u0433\u043e\u0440\u0438\u043d"
    ],
    "name:und_x_variant":[
        "Smaharyn",
        "Smogorino",
        "Smagorin"
    ],
    "wof:name":"Smagorin",
    "wof:placetype":"locality"
},
  "geometry": {"coordinates":[30.3417,52.1671],"type":"Point"}
}