{
  "type": "Feature",
  "properties": {
    "gn:admin1_code":"6.0",
    "gn:asciiname":"Kolodlivo",
    "gn:country_code":"BY",
    "gn:dem":152,
    "gn:feature_class":"P",
    "gn:feature_code":"PPL",
    "gn:name":"Kolodlivo",
    "gn:population":0,
    "gn:timezone":"Europe/Minsk",
    "iso:country":"BY",
    "name:rus_x_preferred":[
        "\u041a\u043e\u043b\u043e\u0434\u043b\u0438\u0432\u043e"
    ],
    "name:und_x_variant":[
        "Kolodliv"
    ],
    "wof:name":"Kolodlivo",
    "wof:placetype":"locality"
},
  "geometry": {"coordinates":[32.037,53.2392],"type":"Point"}
}