{
  "type": "Feature",
  "properties": {
    "gn:admin1_code":"1.0",
    "gn:asciiname":"Yatvez'",
    "gn:country_code":"BY",
    "gn:dem":166,
    "gn:feature_class":"P",
    "gn:feature_code":"PPL",
    "gn:name":"Yatvez\u2019",
    "gn:population":0,
    "gn:timezone":"Europe/Minsk",
    "iso:country":"BY",
    "name:rus_x_preferred":[
        "Yatvez\u2019"
    ],
    "name:rus_x_variant":[
        "\u042f\u0442\u0432\u0435\u0437\u044c"
    ],
    "wof:name":"Yatvez'",
    "wof:placetype":"locality"
},
  "geometry": {"coordinates":[24.9644,52.7502],"type":"Point"}
}