{
  "type": "Feature",
  "properties": {
    "gn:admin1_code":"3.0",
    "gn:asciiname":"Lugomovichi",
    "gn:country_code":"BY",
    "gn:dem":147,
    "gn:feature_class":"P",
    "gn:feature_code":"PPL",
    "gn:name":"Lugomovichi",
    "gn:population":0,
    "gn:timezone":"Europe/Minsk",
    "iso:country":"BY",
    "name:rus_x_preferred":[
        "\u041b\u0443\u0433\u043e\u043c\u043e\u0432\u0438\u0447\u0438"
    ],
    "name:und_x_variant":[
        "Lugomoviche",
        "Lugomovichi"
    ],
    "wof:name":"Lugomovichi",
    "wof:placetype":"locality"
},
  "geometry": {"coordinates":[25.9635,53.8937],"type":"Point"}
}