{
  "type": "Feature",
  "properties": {
    "gn:admin1_code":"7.0",
    "gn:asciiname":"Brody",
    "gn:country_code":"BY",
    "gn:dem":134,
    "gn:feature_class":"P",
    "gn:feature_code":"PPL",
    "gn:name":"Brody",
    "gn:population":0,
    "gn:timezone":"Europe/Minsk",
    "iso:country":"BY",
    "name:rus_x_preferred":[
        "\u0411\u0440\u043e\u0434\u044b"
    ],
    "wof:name":"Brody",
    "wof:placetype":"locality"
},
  "geometry": {"coordinates":[29.2624,55.13399999999999],"type":"Point"}
}