{
  "type": "Feature",
  "properties": {
    "gn:admin1_code":"7.0",
    "gn:asciiname":"Belo-Mateykovo",
    "gn:country_code":"BY",
    "gn:dem":140,
    "gn:feature_class":"P",
    "gn:feature_code":"PPL",
    "gn:name":"Belo-Mateykovo",
    "gn:population":0,
    "gn:timezone":"Europe/Minsk",
    "iso:country":"BY",
    "name:rus_x_preferred":[
        "\u0411\u0435\u043b\u043e-\u041c\u0430\u0442\u0435\u0439\u043a\u043e\u0432\u043e"
    ],
    "wof:name":"Belo-Mateykovo",
    "wof:placetype":"locality"
},
  "geometry": {"coordinates":[28.5746,55.6562],"type":"Point"}
}