{
  "type": "Feature",
  "properties": {
    "gn:admin1_code":"7.0",
    "gn:asciiname":"Golubovshchina",
    "gn:country_code":"BY",
    "gn:dem":140,
    "gn:feature_class":"P",
    "gn:feature_code":"PPL",
    "gn:name":"Golubovshchina",
    "gn:population":0,
    "gn:timezone":"Europe/Minsk",
    "iso:country":"BY",
    "name:rus_x_preferred":[
        "\u0413\u043e\u043b\u0443\u0431\u043e\u0432\u0449\u0438\u043d\u0430"
    ],
    "name:und_x_variant":[
        "Golubovshchizna",
        "Golubovshchina"
    ],
    "wof:name":"Golubovshchina",
    "wof:placetype":"locality"
},
  "geometry": {"coordinates":[27.2858,55.5681],"type":"Point"}
}