{
  "type": "Feature",
  "properties": {
    "gn:admin1_code":"7.0",
    "gn:asciiname":"Tolkuny",
    "gn:country_code":"BY",
    "gn:dem":234,
    "gn:feature_class":"P",
    "gn:feature_code":"PPL",
    "gn:name":"Tolkuny",
    "gn:population":0,
    "gn:timezone":"Europe/Minsk",
    "iso:country":"BY",
    "name:rus_x_preferred":[
        "\u0422\u043e\u043b\u043a\u0443\u043d\u044b"
    ],
    "wof:name":"Tolkuny",
    "wof:placetype":"locality"
},
  "geometry": {"coordinates":[30.8731,55.2178],"type":"Point"}
}