{
  "type": "Feature",
  "properties": {
    "gn:admin1_code":"7.0",
    "gn:asciiname":"Poselok Pozhen'ki",
    "gn:country_code":"BY",
    "gn:dem":178,
    "gn:feature_class":"P",
    "gn:feature_code":"PPL",
    "gn:name":"Pos\u00eblok Pozhen\u2019ki",
    "gn:population":0,
    "gn:timezone":"Europe/Minsk",
    "iso:country":"BY",
    "name:rus_x_preferred":[
        "\u041f\u043e\u0441\u0451\u043b\u043e\u043a \u041f\u043e\u0436\u0435\u043d\u044c\u043a\u0438"
    ],
    "name:und_x_variant":[
        "Pos\u00eblok Pozhen\u2019ki"
    ],
    "wof:name":"Poselok Pozhen'ki",
    "wof:placetype":"locality"
},
  "geometry": {"coordinates":[29.5279,54.8323],"type":"Point"}
}