{
  "type": "Feature",
  "properties": {
    "gn:admin1_code":"3.0",
    "gn:asciiname":"Hlowsyevichy",
    "gn:country_code":"BY",
    "gn:dem":172,
    "gn:feature_class":"P",
    "gn:feature_code":"PPL",
    "gn:name":"Hlowsyevichy",
    "gn:population":0,
    "gn:timezone":"Europe/Minsk",
    "iso:country":"BY",
    "name:bel_x_preferred":[
        "\u0413\u043b\u043e\u045e\u0441\u0435\u0432\u0456\u0447\u044b"
    ],
    "name:eng_x_preferred":[
        "Glovsevichi"
    ],
    "name:rus_x_preferred":[
        "\u0413\u043b\u043e\u0432\u0441\u0435\u0432\u0438\u0447\u0438"
    ],
    "name:und_x_variant":[
        "Glovseviche",
        "Hlowsyevichy"
    ],
    "wof:name":"Hlowsyevichy",
    "wof:placetype":"locality"
},
  "geometry": {"coordinates":[25.2612,52.98],"type":"Point"}
}