{
  "type": "Feature",
  "properties": {
    "iso:country":"BY",
    "name:bel_x_preferred":[
        "\u0413\u043e\u0440\u0430\u0434 \u041a\u0430\u043b\u0456\u043d\u043a\u0430\u0432\u0456\u0447\u044b"
    ],
    "name:bel_x_variant":[
        "\u041a\u0430\u043b\u0456\u043d\u043a\u0430\u0432\u0456\u0447\u044b",
        "\u041a\u0430\u043b\u0438\u043d\u043a\u0430\u0432\u0438\u0447\u044b"
    ],
    "name:bul_x_preferred":[
        "\u041a\u0430\u043b\u0438\u043d\u043a\u043e\u0432\u0438\u0447\u0438"
    ],
    "name:ceb_x_preferred":[
        "Kalinkavichy"
    ],
    "name:ces_x_preferred":[
        "Kalinkavi\u010dy"
    ],
    "name:che_x_preferred":[
        "\u041a\u0430\u043b\u0438\u043d\u043a\u043e\u0432\u0438\u0447\u0438"
    ],
    "name:deu_x_preferred":[
        "Kalinkawitschy"
    ],
    "name:eng_x_preferred":[
        "Kalinkavichy"
    ],
    "name:epo_x_preferred":[
        "Kalinkavi\u0109i"
    ],
    "name:est_x_preferred":[
        "Kalinkavi\u010dy"
    ],
    "name:fin_x_preferred":[
        "Kalinkavit\u0161y"
    ],
    "name:fra_x_preferred":[
        "Kalinkavitchy"
    ],
    "name:frr_x_preferred":[
        "Kalinkawitschy"
    ],
    "name:hsb_x_preferred":[
        "Kalinkawi\u010dy"
    ],
    "name:hun_x_preferred":[
        "Kalinkavicsi"
    ],
    "name:ita_x_preferred":[
        "Kalinkavi\u010dy"
    ],
    "name:lav_x_preferred":[
        "Ka\u013cinkavi\u010di"
    ],
    "name:lit_x_preferred":[
        "Kalinkavi\u010dai"
    ],
    "name:nld_x_preferred":[
        "Kalinkavi\u010dy"
    ],
    "name:pol_x_preferred":[
        "Kalinkowicze"
    ],
    "name:rus_x_preferred":[
        "\u041a\u0430\u043b\u0438\u043d\u043a\u043e\u0432\u0438\u0447\u0438"
    ],
    "name:srp_x_preferred":[
        "\u041a\u0430\u043b\u0438\u043d\u043a\u0430\u0432\u0438\u0447\u0438"
    ],
    "name:swe_x_preferred":[
        "Kalynkavytjy"
    ],
    "name:tat_x_preferred":[
        "\u041a\u0430\u043b\u0438\u043d\u043a\u043e\u0432\u0438\u0447\u0438"
    ],
    "name:tat_x_variant":[
        "\u041a\u0430\u043b\u0438\u043d\u043a\u0430\u0432\u0438\u0447\u044b"
    ],
    "name:ukr_x_preferred":[
        "\u041a\u0430\u043b\u0438\u043d\u043a\u043e\u0432\u0438\u0447\u0456"
    ],
    "name:unk_x_variant":[
        "Kalinkowitschi"
    ],
    "name:zho_x_preferred":[
        "\u5361\u6797\u79d1\u7dad\u5947"
    ],
    "qs:gn_country":"BY",
    "qs:gn_fcode":"PPLA2",
    "qs:gn_pop":37190,
    "qs:name":"Kalinkavichy",
    "qs:name_adm0":"Belarus",
    "qs:name_adm1":"Homyel'skaya Voblasts'",
    "qs:photos":0,
    "qs:photos_1k":0,
    "qs:photos_9k":1,
    "qs:photos_9r":1,
    "qs:photos_all":1,
    "qs:photos_sr":0,
    "qs:placetype":"Town",
    "qs:pop_sr":"7",
    "qs:woe_adm0":23424765,
    "wd:elevation":172.0,
    "wd:population":38100,
    "wd:wordcount":296,
    "wof:name":"Kalinkavichy",
    "wof:placetype":"locality",
    "wof:population":38100
},
  "geometry": {"coordinates":[29.3257,52.1323],"type":"Point"}
}