{
  "type": "Feature",
  "properties": {
    "gn:admin1_code":"6.0",
    "gn:asciiname":"Novyye Komsinichi",
    "gn:country_code":"BY",
    "gn:dem":202,
    "gn:feature_class":"P",
    "gn:feature_code":"PPL",
    "gn:name":"Novyye Komsinichi",
    "gn:population":0,
    "gn:timezone":"Europe/Minsk",
    "iso:country":"BY",
    "name:rus_x_preferred":[
        "\u041d\u043e\u0432\u044b\u0435 \u041a\u043e\u043c\u0441\u0438\u043d\u0438\u0447\u0438"
    ],
    "name:und_x_variant":[
        "Komsenichi"
    ],
    "wof:name":"Novyye Komsinichi",
    "wof:placetype":"locality"
},
  "geometry": {"coordinates":[30.2247,54.1063],"type":"Point"}
}