{
  "type": "Feature",
  "properties": {
    "gn:admin1_code":"1.0",
    "gn:asciiname":"Darguzhi",
    "gn:country_code":"BY",
    "gn:dem":168,
    "gn:feature_class":"P",
    "gn:feature_code":"PPL",
    "gn:name":"Darguzhi",
    "gn:population":0,
    "gn:timezone":"Europe/Minsk",
    "iso:country":"BY",
    "name:rus_x_preferred":[
        "\u0414\u0430\u0440\u0433\u0443\u0436\u0438"
    ],
    "wof:name":"Darguzhi",
    "wof:placetype":"locality"
},
  "geometry": {"coordinates":[25.0844,52.8308],"type":"Point"}
}