{
  "type": "Feature",
  "properties": {
    "gn:admin1_code":"5.0",
    "gn:asciiname":"Antonovo",
    "gn:country_code":"BY",
    "gn:dem":166,
    "gn:feature_class":"P",
    "gn:feature_code":"PPL",
    "gn:name":"Antonovo",
    "gn:population":0,
    "gn:timezone":"Europe/Minsk",
    "iso:country":"BY",
    "name:rus_x_preferred":[
        "\u0410\u043d\u0442\u043e\u043d\u043e\u0432\u043e"
    ],
    "wof:name":"Antonovo",
    "wof:placetype":"locality"
},
  "geometry": {"coordinates":[27.7857,53.3712],"type":"Point"}
}