{
  "type": "Feature",
  "properties": {
    "gn:admin1_code":"3.0",
    "gn:asciiname":"Povilantsy",
    "gn:country_code":"BY",
    "gn:dem":162,
    "gn:feature_class":"P",
    "gn:feature_code":"PPL",
    "gn:name":"Povilantsy",
    "gn:population":0,
    "gn:timezone":"Europe/Minsk",
    "iso:country":"BY",
    "name:rus_x_preferred":[
        "\u041f\u043e\u0432\u0438\u043b\u0430\u043d\u0446\u044b"
    ],
    "wof:name":"Povilantsy",
    "wof:placetype":"locality"
},
  "geometry": {"coordinates":[24.8961,54.1226],"type":"Point"}
}