{
  "type": "Feature",
  "properties": {
    "gn:admin1_code":"7.0",
    "gn:asciiname":"Malyzheno",
    "gn:country_code":"BY",
    "gn:dem":183,
    "gn:feature_class":"P",
    "gn:feature_code":"PPL",
    "gn:name":"Malyzheno",
    "gn:population":0,
    "gn:timezone":"Europe/Minsk",
    "iso:country":"BY",
    "name:rus_x_preferred":[
        "\u041c\u0430\u043b\u044b\u0436\u0435\u043d\u043e"
    ],
    "name:und_x_variant":[
        "Malyzhano"
    ],
    "wof:name":"Malyzheno",
    "wof:placetype":"locality"
},
  "geometry": {"coordinates":[30.5634,55.2083],"type":"Point"}
}