{
  "type": "Feature",
  "properties": {
    "gn:admin1_code":"0.0",
    "gn:asciiname":"Ogrodniki",
    "gn:cc2":"BY",
    "gn:country_code":"BY",
    "gn:dem":225,
    "gn:feature_class":"P",
    "gn:feature_code":"PPL",
    "gn:name":"Ogrodniki",
    "gn:population":0,
    "gn:timezone":"Europe/Minsk",
    "iso:country":"BY",
    "name:und_x_variant":[
        "Ogrodnik",
        "Ogrodniki"
    ],
    "wof:name":"Ogrodniki",
    "wof:placetype":"locality"
},
  "geometry": {"coordinates":[26.91667,54.13333000000001],"type":"Point"}
}