{
  "type": "Feature",
  "properties": {
    "gn:admin1_code":"0.0",
    "gn:asciiname":"Ogrodniki",
    "gn:cc2":"BY",
    "gn:country_code":"BY",
    "gn:dem":225,
    "gn:feature_class":"P",
    "gn:feature_code":"PPL",
    "gn:name":"Ogrodniki",
    "gn:population":0,
    "gn:timezone":"Europe/Minsk",
    "iso:country":"BY",
    "name:fra_x_preferred":[
        "Ogrodniki"
    ],
    "name:lit_x_preferred":[
        "Ogrodnikai"
    ],
    "name:pol_x_preferred":[
        "Ogrodniki"
    ],
    "name:ukr_x_preferred":[
        "\u041e\u0491\u0440\u043e\u0434\u043d\u0438\u043a\u0438"
    ],
    "name:und_x_variant":[
        "Ogrodnik"
    ],
    "wof:name":"Ogrodniki",
    "wof:placetype":"locality"
},
  "geometry": {"coordinates":[26.91667,54.13333000000001],"type":"Point"}
}