{
  "type": "Feature",
  "properties": {
    "gn:admin1_code":"3.0",
    "gn:asciiname":"Korsaki",
    "gn:country_code":"BY",
    "gn:dem":166,
    "gn:feature_class":"P",
    "gn:feature_code":"PPL",
    "gn:name":"Korsaki",
    "gn:population":0,
    "gn:timezone":"Europe/Minsk",
    "iso:country":"BY",
    "name:bel_x_preferred":[
        "Karsaki"
    ],
    "name:bel_x_variant":[
        "\u041a\u0430\u0440\u0441\u0430\u043a\u0456"
    ],
    "name:che_x_preferred":[
        "\u041a\u043e\u0440\u0441\u0430\u043a\u0438"
    ],
    "name:rus_x_preferred":[
        "\u041a\u043e\u0440\u0441\u0430\u043a\u0438"
    ],
    "wof:name":"Korsaki",
    "wof:placetype":"locality"
},
  "geometry": {"coordinates":[24.887,53.5591],"type":"Point"}
}