{
  "type": "Feature",
  "properties": {
    "gn:admin1_code":"5.0",
    "gn:asciiname":"Silichi",
    "gn:country_code":"BY",
    "gn:dem":282,
    "gn:feature_class":"P",
    "gn:feature_code":"PPL",
    "gn:name":"Silichi",
    "gn:population":0,
    "gn:timezone":"Europe/Minsk",
    "iso:country":"BY",
    "name:bel_x_preferred":[
        "\u0421\u0456\u043b\u0456\u0447\u044b"
    ],
    "name:lit_x_preferred":[
        "Sili\u010diai"
    ],
    "name:por_x_preferred":[
        "Silichy"
    ],
    "name:rus_x_preferred":[
        "\u0421\u0438\u043b\u0438\u0447\u0438"
    ],
    "name:spa_x_preferred":[
        "Silichy"
    ],
    "name:ukr_x_preferred":[
        "\u0421\u0438\u043b\u0438\u0447\u0456"
    ],
    "wof:name":"Silichi",
    "wof:placetype":"locality"
},
  "geometry": {"coordinates":[27.8222,54.1632],"type":"Point"}
}