{
  "type": "Feature",
  "properties": {
    "gn:admin1_code":"7.0",
    "gn:asciiname":"Solodukhi-Pushchevyye",
    "gn:country_code":"BY",
    "gn:dem":148,
    "gn:feature_class":"P",
    "gn:feature_code":"PPL",
    "gn:name":"Solodukhi-Pushchevyye",
    "gn:population":0,
    "gn:timezone":"Europe/Minsk",
    "iso:country":"BY",
    "name:rus_x_preferred":[
        "\u0421\u043e\u043b\u043e\u0434\u0443\u0445\u0438-\u041f\u0443\u0449\u0435\u0432\u044b\u0435"
    ],
    "wof:name":"Solodukhi-Pushchevyye",
    "wof:placetype":"locality"
},
  "geometry": {"coordinates":[29.6968,55.2152],"type":"Point"}
}