{
  "type": "Feature",
  "properties": {
    "gn:admin1_code":"6.0",
    "gn:asciiname":"Hrudzinawka",
    "gn:country_code":"BY",
    "gn:dem":154,
    "gn:feature_class":"P",
    "gn:feature_code":"PPL",
    "gn:name":"Hrudzinawka",
    "gn:population":110,
    "gn:timezone":"Europe/Minsk",
    "iso:country":"BY",
    "name:bel_x_preferred":[
        "\u0413\u0440\u0443\u0434\u0437\u0456\u043d\u0430\u045e\u043a\u0430"
    ],
    "name:und_x_variant":[
        "Grudinovka",
        "Hrudzinawka"
    ],
    "wof:name":"Hrudzinawka",
    "wof:placetype":"locality",
    "wof:population":110
},
  "geometry": {"coordinates":[30.4733,53.6354],"type":"Point"}
}