{
  "type": "Feature",
  "properties": {
    "gn:admin1_code":"6.0",
    "gn:asciiname":"Sychkava",
    "gn:country_code":"BY",
    "gn:dem":155,
    "gn:feature_class":"P",
    "gn:feature_code":"PPL",
    "gn:name":"Sychkava",
    "gn:population":0,
    "gn:timezone":"Europe/Minsk",
    "iso:country":"BY",
    "name:bel_x_preferred":[
        "\u0421\u044b\u0447\u043a\u0430\u0432\u0430"
    ],
    "name:eng_x_preferred":[
        "Sychkovo"
    ],
    "name:rus_x_preferred":[
        "\u0421\u044b\u0447\u043a\u043e\u0432\u043e"
    ],
    "name:und_x_variant":[
        "Sychkava"
    ],
    "wof:name":"Sychkava",
    "wof:placetype":"locality"
},
  "geometry": {"coordinates":[29.1104,53.2029],"type":"Point"}
}