{
  "type": "Feature",
  "properties": {
    "gn:admin1_code":"5.0",
    "gn:asciiname":"Dubrova",
    "gn:country_code":"BY",
    "gn:dem":267,
    "gn:feature_class":"P",
    "gn:feature_code":"PPL",
    "gn:name":"Dubrova",
    "gn:population":0,
    "gn:timezone":"Europe/Minsk",
    "iso:country":"BY",
    "name:rus_x_preferred":[
        "\u0414\u0443\u0431\u0440\u043e\u0432\u0430"
    ],
    "name:und_x_variant":[
        "Dubrovo"
    ],
    "wof:name":"Dubrova",
    "wof:placetype":"locality"
},
  "geometry": {"coordinates":[27.1602,53.8751],"type":"Point"}
}