{
  "type": "Feature",
  "properties": {
    "gn:admin1_code":"5.0",
    "gn:asciiname":"Tyavlovo",
    "gn:country_code":"BY",
    "gn:dem":211,
    "gn:feature_class":"P",
    "gn:feature_code":"PPL",
    "gn:name":"Tyavlovo",
    "gn:population":0,
    "gn:timezone":"Europe/Minsk",
    "iso:country":"BY",
    "name:rus_x_preferred":[
        "\u0422\u044f\u0432\u043b\u043e\u0432\u043e"
    ],
    "wof:name":"Tyavlovo",
    "wof:placetype":"locality"
},
  "geometry": {"coordinates":[27.2083,53.7532],"type":"Point"}
}