{
  "type": "Feature",
  "properties": {
    "gn:admin1_code":"5.0",
    "gn:asciiname":"Zadvor'ye",
    "gn:country_code":"BY",
    "gn:dem":156,
    "gn:feature_class":"P",
    "gn:feature_code":"PPL",
    "gn:name":"Zadvor\u2019ye",
    "gn:population":0,
    "gn:timezone":"Europe/Minsk",
    "iso:country":"BY",
    "name:rus_x_preferred":[
        "\u0417\u0430\u0434\u0432\u043e\u0440\u044c\u0435"
    ],
    "name:und_x_variant":[
        "Zadvor\u2019ye"
    ],
    "wof:name":"Zadvor'ye",
    "wof:placetype":"locality"
},
  "geometry": {"coordinates":[26.7756,53.4938],"type":"Point"}
}