{
  "type": "Feature",
  "properties": {
    "gn:admin1_code":"7.0",
    "gn:asciiname":"Zanivoch'ye",
    "gn:country_code":"BY",
    "gn:dem":206,
    "gn:feature_class":"P",
    "gn:feature_code":"PPL",
    "gn:name":"Zanivoch\u2019ye",
    "gn:population":0,
    "gn:timezone":"Europe/Minsk",
    "iso:country":"BY",
    "name:rus_x_preferred":[
        "\u0417\u0430\u043d\u0438\u0432\u043e\u0447\u044c\u0435"
    ],
    "name:und_x_variant":[
        "Zanivoch\u2019ye"
    ],
    "wof:name":"Zanivoch'ye",
    "wof:placetype":"locality"
},
  "geometry": {"coordinates":[28.9043,54.6799],"type":"Point"}
}