{
  "type": "Feature",
  "properties": {
    "gn:admin1_code":"5.0",
    "gn:asciiname":"Molodi",
    "gn:country_code":"BY",
    "gn:dem":205,
    "gn:feature_class":"P",
    "gn:feature_code":"PPL",
    "gn:name":"Molodi",
    "gn:population":0,
    "gn:timezone":"Europe/Minsk",
    "iso:country":"BY",
    "name:rus_x_preferred":[
        "\u041c\u043e\u043b\u043e\u0434\u0438"
    ],
    "name:und_x_variant":[
        "Mo\u0142ode",
        "Mo\u0142adzi",
        "Molodzi",
        "Molodi"
    ],
    "wof:name":"Molodi",
    "wof:placetype":"locality"
},
  "geometry": {"coordinates":[27.9851,54.2468],"type":"Point"}
}