{
  "type": "Feature",
  "properties": {
    "gn:admin1_code":"7.0",
    "gn:asciiname":"Vordev'ye",
    "gn:country_code":"BY",
    "gn:dem":262,
    "gn:feature_class":"P",
    "gn:feature_code":"PPL",
    "gn:name":"Vordev\u2019ye",
    "gn:population":0,
    "gn:timezone":"Europe/Minsk",
    "iso:country":"BY",
    "name:rus_x_preferred":[
        "\u0412\u043e\u0440\u0434\u0435\u0432\u044c\u0435"
    ],
    "name:und_x_variant":[
        "Vordev\u2019ye"
    ],
    "wof:name":"Vordev'ye",
    "wof:placetype":"locality"
},
  "geometry": {"coordinates":[30.8467,55.1685],"type":"Point"}
}