{
  "type": "Feature",
  "properties": {
    "gn:admin1_code":"2.0",
    "gn:asciiname":"Lapichi",
    "gn:country_code":"BY",
    "gn:dem":137,
    "gn:feature_class":"P",
    "gn:feature_code":"PPL",
    "gn:name":"Lapichi",
    "gn:population":0,
    "gn:timezone":"Europe/Minsk",
    "iso:country":"BY",
    "name:rus_x_preferred":[
        "\u041b\u0430\u043f\u0438\u0447\u0438"
    ],
    "wof:name":"Lapichi",
    "wof:placetype":"locality"
},
  "geometry": {"coordinates":[30.7559,52.6393],"type":"Point"}
}