{
  "type": "Feature",
  "properties": {
    "gn:country":"BY",
    "gn:fcode":"PPL",
    "gn:population":59,
    "iso:country":"BY",
    "qs:name":"\u041f\u0440\u0438\u0441\u043d\u043e-2",
    "qs:photos_9r":0,
    "qs:photos_sr":0,
    "qs:pop_sr":"1",
    "wof:name":"\u041f\u0440\u0438\u0441\u043d\u043e-2",
    "wof:placetype":"locality",
    "wof:population":59
},
  "geometry": {"coordinates":[30.20322,53.92314],"type":"Point"}
}