{
  "type": "Feature",
  "properties": {
    "gn:admin1_code":"6.0",
    "gn:asciiname":"Iskra",
    "gn:country_code":"BY",
    "gn:dem":192,
    "gn:feature_class":"P",
    "gn:feature_code":"PPL",
    "gn:name":"Iskra",
    "gn:population":0,
    "gn:timezone":"Europe/Minsk",
    "iso:country":"BY",
    "name:rus_x_preferred":[
        "\u0418\u0441\u043a\u0440\u0430"
    ],
    "wof:name":"Iskra",
    "wof:placetype":"locality"
},
  "geometry": {"coordinates":[29.7427,54.097],"type":"Point"}
}