{
  "type": "Feature",
  "properties": {
    "gn:admin1_code":"5.0",
    "gn:asciiname":"Ugly",
    "gn:country_code":"BY",
    "gn:dem":164,
    "gn:feature_class":"P",
    "gn:feature_code":"PPL",
    "gn:name":"Ugly",
    "gn:population":0,
    "gn:timezone":"Europe/Minsk",
    "iso:country":"BY",
    "name:rus_x_preferred":[
        "\u0423\u0433\u043b\u044b"
    ],
    "wof:name":"Ugly",
    "wof:placetype":"locality"
},
  "geometry": {"coordinates":[26.3093,54.2008],"type":"Point"}
}