{
  "type": "Feature",
  "properties": {
    "gn:admin1_code":"7.0",
    "gn:asciiname":"Zastodol'ye",
    "gn:country_code":"BY",
    "gn:dem":152,
    "gn:feature_class":"P",
    "gn:feature_code":"PPL",
    "gn:name":"Zastodol\u2019ye",
    "gn:population":0,
    "gn:timezone":"Europe/Minsk",
    "iso:country":"BY",
    "name:rus_x_preferred":[
        "\u0417\u0430\u0441\u0442\u043e\u0434\u043e\u043b\u044c\u0435"
    ],
    "name:und_x_variant":[
        "Zastodol\u2019ye"
    ],
    "wof:name":"Zastodol'ye",
    "wof:placetype":"locality"
},
  "geometry": {"coordinates":[29.9894,54.8197],"type":"Point"}
}