{
  "type": "Feature",
  "properties": {
    "gn:admin1_code":"6.0",
    "gn:asciiname":"Zvezda",
    "gn:country_code":"BY",
    "gn:dem":149,
    "gn:feature_class":"P",
    "gn:feature_code":"PPL",
    "gn:name":"Zvezda",
    "gn:population":0,
    "gn:timezone":"Europe/Minsk",
    "iso:country":"BY",
    "name:rus_x_preferred":[
        "\u0417\u0432\u0435\u0437\u0434\u0430"
    ],
    "wof:name":"Zvezda",
    "wof:placetype":"locality"
},
  "geometry": {"coordinates":[29.4459,53.0628],"type":"Point"}
}