{
  "type": "Feature",
  "properties": {
    "gn:admin1_code":"1.0",
    "gn:asciiname":"Druzhnyy",
    "gn:country_code":"BY",
    "gn:dem":144,
    "gn:feature_class":"P",
    "gn:feature_code":"PPL",
    "gn:name":"Druzhnyy",
    "gn:population":0,
    "gn:timezone":"Europe/Minsk",
    "iso:country":"BY",
    "name:rus_x_preferred":[
        "\u0414\u0440\u0443\u0436\u043d\u044b\u0439"
    ],
    "wof:name":"Druzhnyy",
    "wof:placetype":"locality"
},
  "geometry": {"coordinates":[26.1336,52.1815],"type":"Point"}
}