{
  "type": "Feature",
  "properties": {
    "gn:admin1_code":"3.0",
    "gn:asciiname":"Khodarawtsy",
    "gn:country_code":"BY",
    "gn:dem":128,
    "gn:feature_class":"P",
    "gn:feature_code":"PPL",
    "gn:name":"Khodarawtsy",
    "gn:population":0,
    "gn:timezone":"Europe/Minsk",
    "iso:country":"BY",
    "name:bel_x_preferred":[
        "\u0425\u043e\u0434\u0430\u0440\u0430\u045e\u0446\u044b"
    ],
    "name:eng_x_preferred":[
        "Khodorovtsy"
    ],
    "name:rus_x_preferred":[
        "\u0425\u043e\u0434\u043e\u0440\u043e\u0432\u0446\u044b"
    ],
    "name:und_x_variant":[
        "Khodorovtsy",
        "Khodarawtsy"
    ],
    "wof:name":"Khodarawtsy",
    "wof:placetype":"locality"
},
  "geometry": {"coordinates":[25.0648,53.6366],"type":"Point"}
}