{
  "type": "Feature",
  "properties": {
    "gn:admin1_code":"7.0",
    "gn:asciiname":"Radyuki",
    "gn:country_code":"BY",
    "gn:dem":139,
    "gn:feature_class":"P",
    "gn:feature_code":"PPL",
    "gn:name":"Radyuki",
    "gn:population":0,
    "gn:timezone":"Europe/Minsk",
    "iso:country":"BY",
    "name:rus_x_preferred":[
        "\u0420\u0430\u0434\u044e\u043a\u0438"
    ],
    "wof:name":"Radyuki",
    "wof:placetype":"locality"
},
  "geometry": {"coordinates":[29.4116,55.0348],"type":"Point"}
}