{
  "type": "Feature",
  "properties": {
    "gn:admin1_code":"6.0",
    "gn:asciiname":"Podleshchenka",
    "gn:country_code":"BY",
    "gn:dem":149,
    "gn:feature_class":"P",
    "gn:feature_code":"PPL",
    "gn:name":"Podleshch\u00ebnka",
    "gn:population":0,
    "gn:timezone":"Europe/Minsk",
    "iso:country":"BY",
    "name:rus_x_preferred":[
        "\u041f\u043e\u0434\u043b\u0435\u0449\u0451\u043d\u043a\u0430"
    ],
    "name:und_x_variant":[
        "Podleshch\u00ebnka"
    ],
    "wof:name":"Podleshchenka",
    "wof:placetype":"locality"
},
  "geometry": {"coordinates":[29.6271,53.2345],"type":"Point"}
}