{
  "type": "Feature",
  "properties": {
    "gn:admin1_code":"2.0",
    "gn:asciiname":"Zelenyy Ostrov",
    "gn:country_code":"BY",
    "gn:dem":131,
    "gn:feature_class":"P",
    "gn:feature_code":"PPL",
    "gn:name":"Zel\u00ebnyy Ostrov",
    "gn:population":0,
    "gn:timezone":"Europe/Minsk",
    "iso:country":"BY",
    "name:rus_x_preferred":[
        "\u0417\u0435\u043b\u0451\u043d\u044b\u0439 \u041e\u0441\u0442\u0440\u043e\u0432"
    ],
    "name:und_x_variant":[
        "Zel\u00ebnyy Ostrov"
    ],
    "wof:name":"Zelenyy Ostrov",
    "wof:placetype":"locality"
},
  "geometry": {"coordinates":[30.7517,52.621],"type":"Point"}
}