{
  "type": "Feature",
  "properties": {
    "gn:admin1_code":"3.0",
    "gn:asciiname":"Voloki",
    "gn:country_code":"BY",
    "gn:dem":171,
    "gn:feature_class":"P",
    "gn:feature_code":"PPL",
    "gn:name":"Voloki",
    "gn:population":0,
    "gn:timezone":"Europe/Minsk",
    "iso:country":"BY",
    "name:rus_x_preferred":[
        "\u0412\u043e\u043b\u043e\u043a\u0438"
    ],
    "wof:name":"Voloki",
    "wof:placetype":"locality"
},
  "geometry": {"coordinates":[26.0853,53.4594],"type":"Point"}
}