{
  "type": "Feature",
  "properties": {
    "gn:admin1_code":"3.0",
    "gn:asciiname":"Novoorlovichi",
    "gn:country_code":"BY",
    "gn:dem":177,
    "gn:feature_class":"P",
    "gn:feature_code":"PPL",
    "gn:name":"Novoorlovichi",
    "gn:population":0,
    "gn:timezone":"Europe/Minsk",
    "iso:country":"BY",
    "name:bel_x_preferred":[
        "Navaorlavichy"
    ],
    "name:bel_x_variant":[
        "\u041d\u0430\u0432\u0430\u043e\u0440\u043b\u0430\u0432\u0456\u0447\u044b"
    ],
    "name:rus_x_preferred":[
        "\u041d\u043e\u0432\u043e\u043e\u0440\u043b\u043e\u0432\u0438\u0447\u0438"
    ],
    "name:und_x_variant":[
        "Orlovichi"
    ],
    "wof:name":"Novoorlovichi",
    "wof:placetype":"locality"
},
  "geometry": {"coordinates":[25.1852,53.0185],"type":"Point"}
}