{
  "type": "Feature",
  "properties": {
    "gn:admin1_code":"7.0",
    "gn:asciiname":"Ambrosenki",
    "gn:country_code":"BY",
    "gn:dem":129,
    "gn:feature_class":"P",
    "gn:feature_code":"PPL",
    "gn:name":"Ambrosenki",
    "gn:population":0,
    "gn:timezone":"Europe/Minsk",
    "iso:country":"BY",
    "name:rus_x_preferred":[
        "\u0410\u043c\u0431\u0440\u043e\u0441\u0435\u043d\u043a\u0438"
    ],
    "wof:name":"Ambrosenki",
    "wof:placetype":"locality"
},
  "geometry": {"coordinates":[28.1154,55.4119],"type":"Point"}
}