{
  "type": "Feature",
  "properties": {
    "gn:admin1_code":"2.0",
    "gn:asciiname":"Leteshin",
    "gn:country_code":"BY",
    "gn:dem":128,
    "gn:feature_class":"P",
    "gn:feature_code":"PPL",
    "gn:name":"Leteshin",
    "gn:population":0,
    "gn:timezone":"Europe/Minsk",
    "iso:country":"BY",
    "name:rus_x_preferred":[
        "\u041b\u0435\u0442\u0435\u0448\u0438\u043d"
    ],
    "wof:name":"Leteshin",
    "wof:placetype":"locality"
},
  "geometry": {"coordinates":[30.3668,52.0812],"type":"Point"}
}