{
  "type": "Feature",
  "properties": {
    "gn:admin1_code":"6.0",
    "gn:asciiname":"Kremok",
    "gn:country_code":"BY",
    "gn:dem":161,
    "gn:feature_class":"P",
    "gn:feature_code":"PPL",
    "gn:name":"Kremok",
    "gn:population":0,
    "gn:timezone":"Europe/Minsk",
    "iso:country":"BY",
    "name:eng_x_preferred":[
        "Kremok"
    ],
    "name:rus_x_preferred":[
        "\u041a\u0440\u0435\u043c\u043e\u043a"
    ],
    "wof:name":"Kremok",
    "wof:placetype":"locality"
},
  "geometry": {"coordinates":[28.2196,53.2351],"type":"Point"}
}