{
  "type": "Feature",
  "properties": {
    "iso:country":"BY",
    "qs:gn_pop":0,
    "qs:name":"Motel'",
    "qs:name_adm0":"Belarus",
    "qs:name_adm1":"Minskaya Voblasts'",
    "qs:photos":480,
    "qs:photos_1k":97,
    "qs:photos_9k":2,
    "qs:photos_9r":5,
    "qs:photos_all":480,
    "qs:photos_sr":7,
    "qs:placetype":"Town",
    "qs:pop_sr":"0",
    "qs:woe_adm0":23424765,
    "wof:name":"Motel'",
    "wof:placetype":"locality"
},
  "geometry": {"coordinates":[27.481613,53.906209],"type":"Point"}
}