{
  "type": "Feature",
  "properties": {
    "gn:admin1_code":"6.0",
    "gn:asciiname":"Maloye Zarechcha",
    "gn:country_code":"BY",
    "gn:dem":152,
    "gn:feature_class":"P",
    "gn:feature_code":"PPL",
    "gn:name":"Maloye Zarechcha",
    "gn:population":0,
    "gn:timezone":"Europe/Minsk",
    "iso:country":"BY",
    "name:bel_x_preferred":[
        "\u041c\u0430\u043b\u043e\u0435 \u0417\u0430\u0440\u044d\u0447\u0447\u0430"
    ],
    "name:rus_x_preferred":[
        "Maloye Zarech\u2019ye"
    ],
    "name:rus_x_variant":[
        "Bol\u2019shoye Zarech\u2019ye"
    ],
    "name:und_x_variant":[
        "Zarech\u2019ye",
        "Zarechnyy Shklov",
        "Maloye Zarechcha"
    ],
    "wof:name":"Maloye Zarechcha",
    "wof:placetype":"locality"
},
  "geometry": {"coordinates":[30.3195,54.1973],"type":"Point"}
}