{
  "type": "Feature",
  "properties": {
    "gn:admin1_code":"5.0",
    "gn:asciiname":"Peretyatki",
    "gn:country_code":"BY",
    "gn:dem":255,
    "gn:feature_class":"P",
    "gn:feature_code":"PPL",
    "gn:name":"Peretyatki",
    "gn:population":0,
    "gn:timezone":"Europe/Minsk",
    "iso:country":"BY",
    "name:rus_x_preferred":[
        "\u041f\u0435\u0440\u0435\u0442\u044f\u0442\u043a\u0438"
    ],
    "name:und_x_variant":[
        "Peretsyatki Pervyye"
    ],
    "wof:name":"Peretyatki",
    "wof:placetype":"locality"
},
  "geometry": {"coordinates":[27.0401,53.7594],"type":"Point"}
}