{
  "type": "Feature",
  "properties": {
    "gn:admin1_code":"7.0",
    "gn:asciiname":"Ruba",
    "gn:country_code":"BY",
    "gn:dem":148,
    "gn:feature_class":"P",
    "gn:feature_code":"PPL",
    "gn:name":"Ruba",
    "gn:population":0,
    "gn:timezone":"Europe/Minsk",
    "iso:country":"BY",
    "name:bel_x_preferred":[
        "\u0420\u0443\u0431\u0430"
    ],
    "name:bul_x_preferred":[
        "\u0420\u0443\u0431\u0430"
    ],
    "name:est_x_preferred":[
        "Ruba"
    ],
    "name:fin_x_preferred":[
        "Ruba"
    ],
    "name:ita_x_preferred":[
        "Ruba"
    ],
    "name:pol_x_preferred":[
        "Ruba"
    ],
    "name:rus_x_preferred":[
        "\u0420\u0443\u0431\u0430"
    ],
    "name:srp_x_preferred":[
        "\u0420\u0443\u0431\u0430"
    ],
    "name:ukr_x_preferred":[
        "\u0420\u0443\u0431\u0430"
    ],
    "wof:name":"Ruba",
    "wof:placetype":"locality"
},
  "geometry": {"coordinates":[30.2566,55.2869],"type":"Point"}
}