{
  "type": "Feature",
  "properties": {
    "gn:admin1_code":"6.0",
    "gn:asciiname":"Zahatstsye",
    "gn:country_code":"BY",
    "gn:dem":160,
    "gn:feature_class":"P",
    "gn:feature_code":"PPL",
    "gn:name":"Zahatstsye",
    "gn:population":0,
    "gn:timezone":"Europe/Minsk",
    "iso:country":"BY",
    "name:bel_x_preferred":[
        "\u0417\u0430\u0433\u0430\u0446\u0446\u0435"
    ],
    "name:eng_x_preferred":[
        "Zagat'ye"
    ],
    "name:rus_x_preferred":[
        "\u0417\u0430\u0433\u0430\u0442\u044c\u0435"
    ],
    "name:und_x_variant":[
        "Zagat\u2019ye",
        "Zahatstsye"
    ],
    "wof:name":"Zahatstsye",
    "wof:placetype":"locality"
},
  "geometry": {"coordinates":[29.6884,53.6659],"type":"Point"}
}