{
  "type": "Feature",
  "properties": {
    "gn:admin1_code":"6.0",
    "gn:asciiname":"Mayskaya",
    "gn:country_code":"BY",
    "gn:dem":191,
    "gn:feature_class":"P",
    "gn:feature_code":"PPL",
    "gn:name":"Mayskaya",
    "gn:population":0,
    "gn:timezone":"Europe/Minsk",
    "iso:country":"BY",
    "name:rus_x_preferred":[
        "\u041c\u0430\u0439\u0441\u043a\u0430\u044f"
    ],
    "wof:name":"Mayskaya",
    "wof:placetype":"locality"
},
  "geometry": {"coordinates":[31.6237,53.9499],"type":"Point"}
}