{
  "type": "Feature",
  "properties": {
    "gn:admin1_code":"3.0",
    "gn:asciiname":"Belyye Lugi",
    "gn:country_code":"BY",
    "gn:dem":243,
    "gn:feature_class":"P",
    "gn:feature_code":"PPL",
    "gn:name":"Belyye Lugi",
    "gn:population":0,
    "gn:timezone":"Europe/Minsk",
    "iso:country":"BY",
    "name:bel_x_preferred":[
        "Byelyya Luhi"
    ],
    "name:bel_x_variant":[
        "\u0411\u0435\u043b\u044b\u044f \u041b\u0443\u0433\u0456"
    ],
    "name:rus_x_preferred":[
        "\u0411\u0435\u043b\u044b\u0435 \u041b\u0443\u0433\u0438"
    ],
    "wof:name":"Belyye Lugi",
    "wof:placetype":"locality"
},
  "geometry": {"coordinates":[25.9843,53.4106],"type":"Point"}
}