{
  "type": "Feature",
  "properties": {
    "gn:admin1_code":"7.0",
    "gn:asciiname":"Zhdanovka",
    "gn:country_code":"BY",
    "gn:dem":141,
    "gn:feature_class":"P",
    "gn:feature_code":"PPL",
    "gn:name":"Zhdanovka",
    "gn:population":0,
    "gn:timezone":"Europe/Minsk",
    "iso:country":"BY",
    "name:rus_x_preferred":[
        "\u0416\u0434\u0430\u043d\u043e\u0432\u043a\u0430"
    ],
    "wof:name":"Zhdanovka",
    "wof:placetype":"locality"
},
  "geometry": {"coordinates":[29.5697,55.4584],"type":"Point"}
}