{
  "type": "Feature",
  "properties": {
    "gn:country":"BY",
    "gn:fcode":"PPL",
    "gn:pop":5900,
    "iso:country":"BY",
    "name:bel_x_preferred":[
        "\u0412\u044f\u043b\u0456\u043a\u0430\u044f \u0411\u0435\u0440\u0430\u0441\u0442\u0430\u0432\u0456\u0446\u0430"
    ],
    "name:cze_x_preferred":[
        "Vjalikaja B\u011brastavica"
    ],
    "name:eng_x_preferred":[
        "Vyalikaya Byerastavitsa"
    ],
    "name:est_x_preferred":[
        "Vialikaja Bierastavica"
    ],
    "name:fin_x_preferred":[
        "Vjalikaja Berastavitsa"
    ],
    "name:fre_x_preferred":[
        "Vyalikaya Byerastavitsa"
    ],
    "name:heb_x_preferred":[
        "\u05d1\u05d6'\u05d5\u05e1\u05d8\u05d5\u05d1\u05d9\u05e6\u05d4 \u05d5\u05d9\u05d9\u05dc\u05e7\u05d4"
    ],
    "name:hun_x_preferred":[
        "Vjalikaja Berasztavica"
    ],
    "name:ita_x_preferred":[
        "Vyalikaya Byerastavitsa"
    ],
    "name:jpn_x_preferred":[
        "\u30f4\u30e3\u30ea\u30fc\u30ab\u30e4\u30fb"
    ],
    "name:lit_x_preferred":[
        "Vileika Berastavica"
    ],
    "name:pol_x_preferred":[
        "Brzostowica Wielka"
    ],
    "name:rus_x_preferred":[
        "\u0411\u043e\u043b\u044c\u0448\u0430\u044f \u0411\u0435\u0440\u0435\u0441\u0442\u043e\u0432\u0438\u0446\u0430"
    ],
    "name:rus_x_variant":[
        "Bol\u2019shaya Berestovitsa"
    ],
    "name:srp_x_preferred":[
        "\u0412\u0435\u043b\u0438\u043a\u0430 \u0411\u0435\u0440\u0430\u0441\u0442\u0430\u0432\u0438\u0446\u0430"
    ],
    "name:swe_x_preferred":[
        "Vjal\u0456kaja Berastav\u0456tsa"
    ],
    "name:ukr_x_preferred":[
        "\u0412\u0435\u043b\u0438\u043a\u0430 \u0411\u0435\u0440\u0435\u0441\u0442\u043e\u0432\u0438\u0446\u044f"
    ],
    "name:unk_x_variant":[
        "Bol\u2019\u0161aja Berestovica"
    ],
    "qs:name":"Vyalikaya Byerastavitsa",
    "qs:photos_9r":0,
    "qs:photos_sr":0,
    "qs:pop_sr":"5",
    "wd:wordcount":40,
    "wof:name":"Vyalikaya Byerastavitsa",
    "wof:placetype":"locality",
    "wof:population":5900
},
  "geometry": {"coordinates":[24.0166,53.196],"type":"Point"}
}