{
  "type": "Feature",
  "properties": {
    "gn:admin1_code":"7.0",
    "gn:asciiname":"Bychki",
    "gn:country_code":"BY",
    "gn:dem":207,
    "gn:feature_class":"P",
    "gn:feature_code":"PPL",
    "gn:name":"Bychki",
    "gn:population":0,
    "gn:timezone":"Europe/Minsk",
    "iso:country":"BY",
    "name:rus_x_preferred":[
        "\u0411\u044b\u0447\u043a\u0438"
    ],
    "wof:name":"Bychki",
    "wof:placetype":"locality"
},
  "geometry": {"coordinates":[28.3813,55.1655],"type":"Point"}
}