{
  "type": "Feature",
  "properties": {
    "gn:admin1_code":"1.0",
    "gn:asciiname":"Haradzyechna",
    "gn:country_code":"BY",
    "gn:dem":153,
    "gn:feature_class":"P",
    "gn:feature_code":"PPL",
    "gn:name":"Haradzyechna",
    "gn:population":0,
    "gn:timezone":"Europe/Minsk",
    "iso:country":"BY",
    "name:bel_x_preferred":[
        "\u0413\u0430\u0440\u0430\u0434\u0437\u0435\u0447\u043d\u0430"
    ],
    "name:und_x_variant":[
        "Gorodechno",
        "Gorodechna",
        "Haradzyechna"
    ],
    "wof:name":"Haradzyechna",
    "wof:placetype":"locality"
},
  "geometry": {"coordinates":[24.3099,52.4235],"type":"Point"}
}