{
  "type": "Feature",
  "properties": {
    "gn:admin1_code":"7.0",
    "gn:asciiname":"Pustosel'ye",
    "gn:country_code":"BY",
    "gn:dem":162,
    "gn:feature_class":"P",
    "gn:feature_code":"PPL",
    "gn:name":"Pustosel\u2019ye",
    "gn:population":0,
    "gn:timezone":"Europe/Minsk",
    "iso:country":"BY",
    "name:rus_x_preferred":[
        "\u041f\u0443\u0441\u0442\u043e\u0441\u0435\u043b\u044c\u0435"
    ],
    "name:und_x_variant":[
        "Pustosel\u2019ye"
    ],
    "wof:name":"Pustosel'ye",
    "wof:placetype":"locality"
},
  "geometry": {"coordinates":[26.8219,55.6292],"type":"Point"}
}