{
  "type": "Feature",
  "properties": {
    "gn:admin1_code":"7.0",
    "gn:asciiname":"Smal'ki",
    "gn:country_code":"BY",
    "gn:dem":189,
    "gn:feature_class":"P",
    "gn:feature_code":"PPL",
    "gn:name":"Smal\u2019ki",
    "gn:population":0,
    "gn:timezone":"Europe/Minsk",
    "iso:country":"BY",
    "name:rus_x_preferred":[
        "\u0421\u043c\u0430\u043b\u044c\u043a\u0438"
    ],
    "name:und_x_variant":[
        "Smal\u2019ki",
        "Smol\u2019ki"
    ],
    "wof:name":"Smal'ki",
    "wof:placetype":"locality"
},
  "geometry": {"coordinates":[29.925,55.472],"type":"Point"}
}