{
  "type": "Feature",
  "properties": {
    "gn:admin1_code":"3.0",
    "gn:asciiname":"Malaya Byerastavitsa",
    "gn:country_code":"BY",
    "gn:dem":140,
    "gn:feature_class":"P",
    "gn:feature_code":"PPL",
    "gn:name":"Malaya Byerastavitsa",
    "gn:population":0,
    "gn:timezone":"Europe/Minsk",
    "iso:country":"BY",
    "name:bel_x_preferred":[
        "\u041c\u0430\u043b\u0430\u044f \u0411\u0435\u0440\u0430\u0441\u0442\u0430\u0432\u0456\u0446\u0430"
    ],
    "name:ell_x_preferred":[
        "\u039c\u03b1\u03bb\u03ac\u03b3\u03b9\u03b1 \u039c\u03c0\u03b5\u03c1\u03b5\u03c3\u03c4\u03cc\u03b2\u03b9\u03c4\u03c3\u03b1"
    ],
    "name:eng_x_preferred":[
        "Malaya Berestovitsa"
    ],
    "name:est_x_preferred":[
        "Ma\u0142aja Bierastavica"
    ],
    "name:fra_x_preferred":[
        "Malaya Berestovitsa"
    ],
    "name:pol_x_preferred":[
        "Brzostowica Ma\u0142a"
    ],
    "name:rus_x_preferred":[
        "\u041c\u0430\u043b\u0430\u044f \u0411\u0435\u0440\u0435\u0441\u0442\u043e\u0432\u0438\u0446\u0430"
    ],
    "name:ukr_x_preferred":[
        "\u041c\u0430\u043b\u0430 \u0411\u0435\u0440\u0435\u0441\u0442\u043e\u0432\u0438\u0446\u044f"
    ],
    "name:und_x_variant":[
        "Brzostowica Ma\u0142a",
        "Malaja Berestovica",
        "Bzhostovitsa-Mala",
        "Malaya Berestovitsa",
        "Malaya Byerastavitsa"
    ],
    "wof:name":"Malaya Byerastavitsa",
    "wof:placetype":"locality"
},
  "geometry": {"coordinates":[23.9377,53.2875],"type":"Point"}
}