{
  "type": "Feature",
  "properties": {
    "gn:admin1_code":"7.0",
    "gn:asciiname":"Usomlya",
    "gn:country_code":"BY",
    "gn:dem":136,
    "gn:feature_class":"P",
    "gn:feature_code":"PPL",
    "gn:name":"Usomlya",
    "gn:population":0,
    "gn:timezone":"Europe/Minsk",
    "iso:country":"BY",
    "name:rus_x_preferred":[
        "\u0423\u0441\u043e\u043c\u043b\u044f"
    ],
    "wof:name":"Usomlya",
    "wof:placetype":"locality"
},
  "geometry": {"coordinates":[28.7016,55.3539],"type":"Point"}
}