{
  "type": "Feature",
  "properties": {
    "gn:admin1_code":"5.0",
    "gn:asciiname":"Kurgan'ye",
    "gn:country_code":"BY",
    "gn:dem":206,
    "gn:feature_class":"P",
    "gn:feature_code":"PPL",
    "gn:name":"Kurgan\u2019ye",
    "gn:population":0,
    "gn:timezone":"Europe/Minsk",
    "iso:country":"BY",
    "name:rus_x_preferred":[
        "\u041a\u0443\u0440\u0433\u0430\u043d\u044c\u0435"
    ],
    "name:und_x_variant":[
        "Kurgan\u2019ye"
    ],
    "wof:name":"Kurgan'ye",
    "wof:placetype":"locality"
},
  "geometry": {"coordinates":[27.4427,53.688],"type":"Point"}
}