{
  "type": "Feature",
  "properties": {
    "gn:admin1_code":"7.0",
    "gn:asciiname":"Staritsa",
    "gn:country_code":"BY",
    "gn:dem":155,
    "gn:feature_class":"P",
    "gn:feature_code":"PPL",
    "gn:name":"Staritsa",
    "gn:population":0,
    "gn:timezone":"Europe/Minsk",
    "iso:country":"BY",
    "name:rus_x_preferred":[
        "\u0421\u0442\u0430\u0440\u0438\u0446\u0430"
    ],
    "wof:name":"Staritsa",
    "wof:placetype":"locality"
},
  "geometry": {"coordinates":[29.1255,55.8931],"type":"Point"}
}