{
  "type": "Feature",
  "properties": {
    "gn:admin1_code":"3.0",
    "gn:asciiname":"Vyalikaye Syalo",
    "gn:country_code":"BY",
    "gn:dem":177,
    "gn:feature_class":"P",
    "gn:feature_code":"PPL",
    "gn:name":"Vyalikaye Syalo",
    "gn:population":0,
    "gn:timezone":"Europe/Minsk",
    "iso:country":"BY",
    "name:bel_x_preferred":[
        "\u0412\u044f\u043b\u0456\u043a\u0430\u0435 \u0421\u044f\u043b\u043e"
    ],
    "name:und_x_variant":[
        "Vel\u2019ka Selo",
        "Vel\u2019ke Selo",
        "Velikoye Selo",
        "Vyalikaye Syalo"
    ],
    "wof:name":"Vyalikaye Syalo",
    "wof:placetype":"locality"
},
  "geometry": {"coordinates":[24.3271,53.0495],"type":"Point"}
}