{
  "type": "Feature",
  "properties": {
    "gn:admin1_code":"6.0",
    "gn:asciiname":"Gumnitskoye",
    "gn:country_code":"BY",
    "gn:dem":172,
    "gn:feature_class":"P",
    "gn:feature_code":"PPL",
    "gn:name":"Gumnitskoye",
    "gn:population":0,
    "gn:timezone":"Europe/Minsk",
    "iso:country":"BY",
    "name:rus_x_preferred":[
        "\u0413\u0443\u043c\u043d\u0438\u0446\u043a\u043e\u0435"
    ],
    "wof:name":"Gumnitskoye",
    "wof:placetype":"locality"
},
  "geometry": {"coordinates":[32.0184,53.3872],"type":"Point"}
}