{
  "type": "Feature",
  "properties": {
    "gn:admin1_code":"2.0",
    "gn:asciiname":"Dolgovskoye",
    "gn:country_code":"BY",
    "gn:dem":143,
    "gn:feature_class":"P",
    "gn:feature_code":"PPL",
    "gn:name":"Dolgovskoye",
    "gn:population":0,
    "gn:timezone":"Europe/Minsk",
    "iso:country":"BY",
    "name:rus_x_preferred":[
        "\u0414\u043e\u043b\u0433\u043e\u0432\u0441\u043a\u043e\u0435"
    ],
    "wof:name":"Dolgovskoye",
    "wof:placetype":"locality"
},
  "geometry": {"coordinates":[28.4848,51.8163],"type":"Point"}
}