{
  "type": "Feature",
  "properties": {
    "gn:admin1_code":"7.0",
    "gn:asciiname":"Turowlya",
    "gn:country_code":"BY",
    "gn:dem":134,
    "gn:feature_class":"P",
    "gn:feature_code":"PPL",
    "gn:name":"Turowlya",
    "gn:population":0,
    "gn:timezone":"Europe/Minsk",
    "iso:country":"BY",
    "name:bel_x_preferred":[
        "\u0422\u0443\u0440\u043e\u045e\u043b\u044f"
    ],
    "name:eng_x_preferred":[
        "Turovlya"
    ],
    "name:rus_x_preferred":[
        "\u0422\u0443\u0440\u043e\u0432\u043b\u044f"
    ],
    "name:und_x_variant":[
        "Turowlya"
    ],
    "wof:name":"Turowlya",
    "wof:placetype":"locality"
},
  "geometry": {"coordinates":[28.9402,55.3655],"type":"Point"}
}