{
  "type": "Feature",
  "properties": {
    "gn:admin1_code":"3.0",
    "gn:asciiname":"Skryniki",
    "gn:country_code":"BY",
    "gn:dem":171,
    "gn:feature_class":"P",
    "gn:feature_code":"PPL",
    "gn:name":"Skryniki",
    "gn:population":0,
    "gn:timezone":"Europe/Minsk",
    "iso:country":"BY",
    "name:rus_x_preferred":[
        "\u0421\u043a\u0440\u044b\u043d\u0438\u043a\u0438"
    ],
    "name:und_x_variant":[
        "Skriniki"
    ],
    "wof:name":"Skryniki",
    "wof:placetype":"locality"
},
  "geometry": {"coordinates":[23.6904,53.7528],"type":"Point"}
}