{
  "type": "Feature",
  "properties": {
    "gn:admin1_code":"2.0",
    "gn:asciiname":"Znamya Truda",
    "gn:country_code":"BY",
    "gn:dem":128,
    "gn:feature_class":"P",
    "gn:feature_code":"PPL",
    "gn:name":"Znamya Truda",
    "gn:population":0,
    "gn:timezone":"Europe/Minsk",
    "iso:country":"BY",
    "name:rus_x_preferred":[
        "\u0417\u043d\u0430\u043c\u044f \u0422\u0440\u0443\u0434\u0430"
    ],
    "wof:name":"Znamya Truda",
    "wof:placetype":"locality"
},
  "geometry": {"coordinates":[31.1424,52.3772],"type":"Point"}
}