{
  "type": "Feature",
  "properties": {
    "gn:admin1_code":"6.0",
    "gn:asciiname":"Sobolevka",
    "gn:country_code":"BY",
    "gn:dem":200,
    "gn:feature_class":"P",
    "gn:feature_code":"PPL",
    "gn:name":"Sobolevka",
    "gn:population":0,
    "gn:timezone":"Europe/Minsk",
    "iso:country":"BY",
    "name:rus_x_preferred":[
        "\u0421\u043e\u0431\u043e\u043b\u0435\u0432\u043a\u0430"
    ],
    "wof:name":"Sobolevka",
    "wof:placetype":"locality"
},
  "geometry": {"coordinates":[32.2506,53.5716],"type":"Point"}
}