{
  "type": "Feature",
  "properties": {
    "gn:admin1_code":"6.0",
    "gn:asciiname":"Kavyaza",
    "gn:country_code":"BY",
    "gn:dem":153,
    "gn:feature_class":"P",
    "gn:feature_code":"PPL",
    "gn:name":"Kavyaza",
    "gn:population":0,
    "gn:timezone":"Europe/Minsk",
    "iso:country":"BY",
    "name:rus_x_preferred":[
        "\u041a\u0430\u0432\u044f\u0437\u0430"
    ],
    "name:und_x_variant":[
        "Kaveza"
    ],
    "wof:name":"Kavyaza",
    "wof:placetype":"locality"
},
  "geometry": {"coordinates":[29.401,53.434],"type":"Point"}
}