{
  "type": "Feature",
  "properties": {
    "gn:admin1_code":"5.0",
    "gn:asciiname":"Gerasimovka",
    "gn:country_code":"BY",
    "gn:dem":161,
    "gn:feature_class":"P",
    "gn:feature_code":"PPL",
    "gn:name":"Gerasimovka",
    "gn:population":0,
    "gn:timezone":"Europe/Minsk",
    "iso:country":"BY",
    "name:rus_x_preferred":[
        "\u0413\u0435\u0440\u0430\u0441\u0438\u043c\u043e\u0432\u043a\u0430"
    ],
    "wof:name":"Gerasimovka",
    "wof:placetype":"locality"
},
  "geometry": {"coordinates":[27.2821,52.8768],"type":"Point"}
}