{
  "type": "Feature",
  "properties": {
    "gn:admin1_code":"3.0",
    "gn:asciiname":"Podeyki",
    "gn:country_code":"BY",
    "gn:dem":138,
    "gn:feature_class":"P",
    "gn:feature_code":"PPL",
    "gn:name":"Podeyki",
    "gn:population":0,
    "gn:timezone":"Europe/Minsk",
    "iso:country":"BY",
    "name:rus_x_preferred":[
        "\u041f\u043e\u0434\u0435\u0439\u043a\u0438"
    ],
    "wof:name":"Podeyki",
    "wof:placetype":"locality"
},
  "geometry": {"coordinates":[24.8553,53.9264],"type":"Point"}
}