{
  "type": "Feature",
  "properties": {
    "gn:admin1_code":"7.0",
    "gn:asciiname":"Galyni",
    "gn:country_code":"BY",
    "gn:dem":125,
    "gn:feature_class":"P",
    "gn:feature_code":"PPL",
    "gn:name":"Galyni",
    "gn:population":0,
    "gn:timezone":"Europe/Minsk",
    "iso:country":"BY",
    "name:rus_x_preferred":[
        "\u0413\u0430\u043b\u044b\u043d\u0438"
    ],
    "name:und_x_variant":[
        "Golyni"
    ],
    "wof:name":"Galyni",
    "wof:placetype":"locality"
},
  "geometry": {"coordinates":[29.4301,55.1215],"type":"Point"}
}