{
  "type": "Feature",
  "properties": {
    "iso:country":"BY",
    "name:bel_x_preferred":[
        "\u0413\u0430\u0440\u0430\u0434\u0441\u043a\u0456 \u043f\u0430\u0441\u0451\u043b\u0430\u043a \u041b\u044e\u0431\u0447\u0430"
    ],
    "name:bel_x_variant":[
        "\u041b\u044e\u0431\u0447\u0430"
    ],
    "name:ceb_x_preferred":[
        "Lyubcha"
    ],
    "name:ceb_x_variant":[
        "Liub\u010da"
    ],
    "name:che_x_preferred":[
        "\u041b\u044e\u0431\u0447\u0430"
    ],
    "name:ell_x_preferred":[
        "\u039b\u03bf\u03c5\u03bc\u03c0\u03c4\u03c3\u03ac"
    ],
    "name:eng_x_preferred":[
        "Lyubcha"
    ],
    "name:eng_x_variant":[
        "Lubcha",
        "Liub\u010da"
    ],
    "name:est_x_preferred":[
        "Lub\u010da"
    ],
    "name:fra_x_preferred":[
        "Lubcha"
    ],
    "name:fra_x_variant":[
        "Liub\u010da"
    ],
    "name:heb_x_preferred":[
        "\u05dc\u05d5\u05d1\u05e6'\u05d4"
    ],
    "name:lit_x_preferred":[
        "Liub\u010dia"
    ],
    "name:nld_x_preferred":[
        "Lubcha"
    ],
    "name:nld_x_variant":[
        "Liub\u010da"
    ],
    "name:pol_x_preferred":[
        "Lubcz"
    ],
    "name:rus_x_preferred":[
        "\u041b\u044e\u0431\u0447\u0430"
    ],
    "name:srp_x_preferred":[
        "\u0409\u0443\u043f\u0447\u0430"
    ],
    "name:srp_x_variant":[
        "\u0409\u0443\u0431\u0447\u0430"
    ],
    "name:swe_x_preferred":[
        "Ljubtja"
    ],
    "name:tat_x_preferred":[
        "\u041b\u044e\u0431\u0447\u0430"
    ],
    "name:ukr_x_preferred":[
        "\u041b\u044e\u0431\u0447\u0430"
    ],
    "name:zho_x_preferred":[
        "\u67f3\u5e03\u6070"
    ],
    "qs:gn_country":"BY",
    "qs:gn_fcode":"PPL",
    "qs:gn_pop":1300,
    "qs:name":"Lyubcha",
    "qs:name_adm0":"Belarus",
    "qs:name_adm1":"Haradzyenskaya Voblasts'",
    "qs:photos":0,
    "qs:photos_1k":0,
    "qs:photos_9k":1,
    "qs:photos_9r":1,
    "qs:photos_all":3,
    "qs:photos_sr":0,
    "qs:placetype":"Town",
    "qs:pop_sr":"3",
    "qs:woe_adm0":23424765,
    "wd:population":1157,
    "wd:wordcount":250,
    "wof:name":"Lyubcha",
    "wof:placetype":"locality",
    "wof:population":1157
},
  "geometry": {"coordinates":[26.0603,53.7522],"type":"Point"}
}