{
  "type": "Feature",
  "properties": {
    "gn:admin1_code":"3.0",
    "gn:asciiname":"Tatarshchina",
    "gn:country_code":"BY",
    "gn:dem":251,
    "gn:feature_class":"P",
    "gn:feature_code":"PPL",
    "gn:name":"Tatarshchina",
    "gn:population":0,
    "gn:timezone":"Europe/Minsk",
    "iso:country":"BY",
    "name:rus_x_preferred":[
        "\u0422\u0430\u0442\u0430\u0440\u0449\u0438\u043d\u0430"
    ],
    "wof:name":"Tatarshchina",
    "wof:placetype":"locality"
},
  "geometry": {"coordinates":[26.2505,54.3733],"type":"Point"}
}