{
  "type": "Feature",
  "properties": {
    "gn:admin1_code":"5.0",
    "gn:asciiname":"Chizhovka",
    "gn:country_code":"BY",
    "gn:dem":156,
    "gn:feature_class":"P",
    "gn:feature_code":"PPL",
    "gn:name":"Chizhovka",
    "gn:population":0,
    "gn:timezone":"Europe/Minsk",
    "iso:country":"BY",
    "name:rus_x_preferred":[
        "\u0427\u0438\u0436\u043e\u0432\u043a\u0430"
    ],
    "wof:name":"Chizhovka",
    "wof:placetype":"locality"
},
  "geometry": {"coordinates":[27.4897,52.8093],"type":"Point"}
}