{
  "type": "Feature",
  "properties": {
    "gn:admin1_code":"5.0",
    "gn:asciiname":"Khoruzhi",
    "gn:country_code":"BY",
    "gn:dem":207,
    "gn:feature_class":"P",
    "gn:feature_code":"PPL",
    "gn:name":"Khoruzhi",
    "gn:population":0,
    "gn:timezone":"Europe/Minsk",
    "iso:country":"BY",
    "name:rus_x_preferred":[
        "\u0425\u043e\u0440\u0443\u0436\u0438"
    ],
    "wof:name":"Khoruzhi",
    "wof:placetype":"locality"
},
  "geometry": {"coordinates":[26.8767,54.0034],"type":"Point"}
}