{
  "type": "Feature",
  "properties": {
    "gn:admin1_code":"5.0",
    "gn:asciiname":"Shulyaki",
    "gn:country_code":"BY",
    "gn:dem":161,
    "gn:feature_class":"P",
    "gn:feature_code":"PPL",
    "gn:name":"Shulyaki",
    "gn:population":0,
    "gn:timezone":"Europe/Minsk",
    "iso:country":"BY",
    "name:rus_x_preferred":[
        "\u0428\u0443\u043b\u044f\u043a\u0438"
    ],
    "wof:name":"Shulyaki",
    "wof:placetype":"locality"
},
  "geometry": {"coordinates":[27.4819,53.1119],"type":"Point"}
}