{
  "type": "Feature",
  "properties": {
    "gn:admin1_code":"5.0",
    "gn:asciiname":"Red'ki",
    "gn:country_code":"BY",
    "gn:dem":199,
    "gn:feature_class":"P",
    "gn:feature_code":"PPL",
    "gn:name":"Red\u2019ki",
    "gn:population":0,
    "gn:timezone":"Europe/Minsk",
    "iso:country":"BY",
    "name:rus_x_preferred":[
        "\u0420\u0435\u0434\u044c\u043a\u0438"
    ],
    "name:und_x_variant":[
        "Red\u2019ki"
    ],
    "wof:name":"Red'ki",
    "wof:placetype":"locality"
},
  "geometry": {"coordinates":[26.5264,54.3305],"type":"Point"}
}