{
  "type": "Feature",
  "properties": {
    "gn:admin1_code":"6.0",
    "gn:asciiname":"Tsvyrkovo",
    "gn:country_code":"BY",
    "gn:dem":189,
    "gn:feature_class":"P",
    "gn:feature_code":"PPL",
    "gn:name":"Tsvyrkovo",
    "gn:population":0,
    "gn:timezone":"Europe/Minsk",
    "iso:country":"BY",
    "name:rus_x_preferred":[
        "\u0426\u0432\u044b\u0440\u043a\u043e\u0432\u043e"
    ],
    "wof:name":"Tsvyrkovo",
    "wof:placetype":"locality"
},
  "geometry": {"coordinates":[30.2522,54.0631],"type":"Point"}
}