{
  "type": "Feature",
  "properties": {
    "gn:admin1_code":"5.0",
    "gn:asciiname":"Rusovshchina",
    "gn:country_code":"BY",
    "gn:dem":194,
    "gn:feature_class":"P",
    "gn:feature_code":"PPL",
    "gn:name":"Rusovshchina",
    "gn:population":0,
    "gn:timezone":"Europe/Minsk",
    "iso:country":"BY",
    "name:rus_x_preferred":[
        "\u0420\u0443\u0441\u043e\u0432\u0449\u0438\u043d\u0430"
    ],
    "wof:name":"Rusovshchina",
    "wof:placetype":"locality"
},
  "geometry": {"coordinates":[26.4854,53.0424],"type":"Point"}
}