{
  "type": "Feature",
  "properties": {
    "gn:admin1_code":"2.0",
    "gn:asciiname":"Zavayts'",
    "gn:country_code":"BY",
    "gn:dem":121,
    "gn:feature_class":"P",
    "gn:feature_code":"PPL",
    "gn:name":"Zavayts\u2019",
    "gn:population":0,
    "gn:timezone":"Europe/Minsk",
    "iso:country":"BY",
    "name:bel_x_preferred":[
        "\u0417\u0430\u0432\u0430\u0439\u0446\u044c"
    ],
    "name:rus_x_preferred":[
        "Zavoyt\u2019"
    ],
    "name:und_x_variant":[
        "Zavoit\u2019",
        "Zavoyt\u2019",
        "Zavayts\u2019"
    ],
    "wof:name":"Zavayts'",
    "wof:placetype":"locality"
},
  "geometry": {"coordinates":[29.3838,51.8039],"type":"Point"}
}