{
  "type": "Feature",
  "properties": {
    "gn:admin1_code":"7.0",
    "gn:asciiname":"Bol'shoye Losvido",
    "gn:country_code":"BY",
    "gn:dem":180,
    "gn:feature_class":"P",
    "gn:feature_code":"PPL",
    "gn:name":"Bol\u2019shoye Losvido",
    "gn:population":0,
    "gn:timezone":"Europe/Minsk",
    "iso:country":"BY",
    "name:rus_x_preferred":[
        "\u0411\u043e\u043b\u044c\u0448\u043e\u0435 \u041b\u043e\u0441\u0432\u0438\u0434\u043e"
    ],
    "name:und_x_variant":[
        "Bol\u2019shoye Losvido"
    ],
    "wof:name":"Bol'shoye Losvido",
    "wof:placetype":"locality"
},
  "geometry": {"coordinates":[29.9901,55.3944],"type":"Point"}
}