{
  "type": "Feature",
  "properties": {
    "gn:admin1_code":"7.0",
    "gn:asciiname":"Bel'",
    "gn:country_code":"BY",
    "gn:dem":183,
    "gn:feature_class":"P",
    "gn:feature_code":"PPL",
    "gn:name":"Bel\u2019",
    "gn:population":0,
    "gn:timezone":"Europe/Minsk",
    "iso:country":"BY",
    "name:eng_x_preferred":[
        "Bel'"
    ],
    "name:rus_x_preferred":[
        "\u0411\u0435\u043b\u044c"
    ],
    "name:und_x_variant":[
        "Bel\u2019"
    ],
    "wof:name":"Bel'",
    "wof:placetype":"locality"
},
  "geometry": {"coordinates":[31.0226,54.6435],"type":"Point"}
}