{
  "type": "Feature",
  "properties": {
    "gn:admin1_code":"5.0",
    "gn:asciiname":"Kosheli",
    "gn:country_code":"BY",
    "gn:dem":166,
    "gn:feature_class":"P",
    "gn:feature_code":"PPL",
    "gn:name":"Kosheli",
    "gn:population":0,
    "gn:timezone":"Europe/Minsk",
    "iso:country":"BY",
    "name:rus_x_preferred":[
        "\u041a\u043e\u0448\u0435\u043b\u0438"
    ],
    "wof:name":"Kosheli",
    "wof:placetype":"locality"
},
  "geometry": {"coordinates":[27.8327,53.2776],"type":"Point"}
}