{
  "type": "Feature",
  "properties": {
    "gn:admin1_code":"1.0",
    "gn:asciiname":"Bol'shoy Kholozhin",
    "gn:country_code":"BY",
    "gn:dem":158,
    "gn:feature_class":"P",
    "gn:feature_code":"PPL",
    "gn:name":"Bol\u2019shoy Kholozhin",
    "gn:population":0,
    "gn:timezone":"Europe/Minsk",
    "iso:country":"BY",
    "name:rus_x_preferred":[
        "\u0411\u043e\u043b\u044c\u0448\u043e\u0439 \u0425\u043e\u043b\u043e\u0436\u0438\u043d"
    ],
    "name:und_x_variant":[
        "Bol\u2019shoy Kholozhin"
    ],
    "wof:name":"Bol'shoy Kholozhin",
    "wof:placetype":"locality"
},
  "geometry": {"coordinates":[25.9164,52.2163],"type":"Point"}
}