{
  "type": "Feature",
  "properties": {
    "gn:admin1_code":"5.0",
    "gn:asciiname":"Kurniki",
    "gn:country_code":"BY",
    "gn:dem":166,
    "gn:feature_class":"P",
    "gn:feature_code":"PPL",
    "gn:name":"Kurniki",
    "gn:population":0,
    "gn:timezone":"Europe/Minsk",
    "iso:country":"BY",
    "name:rus_x_preferred":[
        "\u041a\u0443\u0440\u043d\u0438\u043a\u0438"
    ],
    "wof:name":"Kurniki",
    "wof:placetype":"locality"
},
  "geometry": {"coordinates":[26.7089,54.6838],"type":"Point"}
}