{
  "type": "Feature",
  "properties": {
    "gn:admin1_code":"1.0",
    "gn:asciiname":"Rukhcha Vtoraya",
    "gn:country_code":"BY",
    "gn:dem":135,
    "gn:feature_class":"P",
    "gn:feature_code":"PPL",
    "gn:name":"Rukhcha Vtoraya",
    "gn:population":0,
    "gn:timezone":"Europe/Minsk",
    "iso:country":"BY",
    "name:rus_x_preferred":[
        "\u0420\u0443\u0445\u0447\u0430 \u0412\u0442\u043e\u0440\u0430\u044f"
    ],
    "name:und_x_variant":[
        "Rukhcha Druga"
    ],
    "wof:name":"Rukhcha Vtoraya",
    "wof:placetype":"locality"
},
  "geometry": {"coordinates":[26.6001,51.9925],"type":"Point"}
}