{
  "type": "Feature",
  "properties": {
    "gn:admin1_code":"6.0",
    "gn:asciiname":"Volozhenka",
    "gn:country_code":"BY",
    "gn:dem":174,
    "gn:feature_class":"P",
    "gn:feature_code":"PPL",
    "gn:name":"Volozhenka",
    "gn:population":0,
    "gn:timezone":"Europe/Minsk",
    "iso:country":"BY",
    "name:rus_x_preferred":[
        "\u0412\u043e\u043b\u043e\u0436\u0435\u043d\u043a\u0430"
    ],
    "name:und_x_variant":[
        "Valozhinka"
    ],
    "wof:name":"Volozhenka",
    "wof:placetype":"locality"
},
  "geometry": {"coordinates":[30.8619,53.7854],"type":"Point"}
}