{
  "type": "Feature",
  "properties": {
    "gn:admin1_code":"0.0",
    "gn:asciiname":"Kobylki",
    "gn:country_code":"BY",
    "gn:dem":233,
    "gn:feature_class":"P",
    "gn:feature_code":"PPL",
    "gn:name":"Kobylki",
    "gn:population":0,
    "gn:timezone":"Europe/Minsk",
    "iso:country":"BY",
    "wof:name":"Kobylki",
    "wof:placetype":"locality"
},
  "geometry": {"coordinates":[26.68333,54.25],"type":"Point"}
}