{
  "type": "Feature",
  "properties": {
    "gn:admin1_code":"5.0",
    "gn:asciiname":"Brokhovshchina",
    "gn:country_code":"BY",
    "gn:dem":190,
    "gn:feature_class":"P",
    "gn:feature_code":"PPL",
    "gn:name":"Brokhovshchina",
    "gn:population":0,
    "gn:timezone":"Europe/Minsk",
    "iso:country":"BY",
    "name:rus_x_preferred":[
        "\u0411\u0440\u043e\u0445\u043e\u0432\u0449\u0438\u043d\u0430"
    ],
    "wof:name":"Brokhovshchina",
    "wof:placetype":"locality"
},
  "geometry": {"coordinates":[26.9134,54.2378],"type":"Point"}
}