{
  "type": "Feature",
  "properties": {
    "gn:admin1_code":"3.0",
    "gn:asciiname":"Yetsevichi",
    "gn:country_code":"BY",
    "gn:dem":212,
    "gn:feature_class":"P",
    "gn:feature_code":"PPL",
    "gn:name":"Yetsevichi",
    "gn:population":0,
    "gn:timezone":"Europe/Minsk",
    "iso:country":"BY",
    "name:bel_x_preferred":[
        "Yotsavichy"
    ],
    "name:bel_x_variant":[
        "\u0401\u0446\u0430\u0432\u0456\u0447\u044b"
    ],
    "name:rus_x_preferred":[
        "\u0415\u0446\u0435\u0432\u0438\u0447\u0438"
    ],
    "name:und_x_variant":[
        "Iotsevichi"
    ],
    "wof:name":"Yetsevichi",
    "wof:placetype":"locality"
},
  "geometry": {"coordinates":[25.4508,53.2806],"type":"Point"}
}