{
  "type": "Feature",
  "properties": {
    "gn:admin1_code":"5.0",
    "gn:asciiname":"Novosel'ye",
    "gn:country_code":"BY",
    "gn:dem":161,
    "gn:feature_class":"P",
    "gn:feature_code":"PPL",
    "gn:name":"Novosel\u2019ye",
    "gn:population":0,
    "gn:timezone":"Europe/Minsk",
    "iso:country":"BY",
    "name:rus_x_preferred":[
        "\u041d\u043e\u0432\u043e\u0441\u0435\u043b\u044c\u0435"
    ],
    "name:und_x_variant":[
        "Novosel\u2019ye"
    ],
    "wof:name":"Novosel'ye",
    "wof:placetype":"locality"
},
  "geometry": {"coordinates":[28.9832,54.0502],"type":"Point"}
}