{
  "type": "Feature",
  "properties": {
    "gn:admin1_code":"7.0",
    "gn:asciiname":"Samuyly",
    "gn:country_code":"BY",
    "gn:dem":154,
    "gn:feature_class":"P",
    "gn:feature_code":"PPL",
    "gn:name":"Samuyly",
    "gn:population":0,
    "gn:timezone":"Europe/Minsk",
    "iso:country":"BY",
    "name:rus_x_preferred":[
        "\u0421\u0430\u043c\u0443\u0439\u043b\u044b"
    ],
    "wof:name":"Samuyly",
    "wof:placetype":"locality"
},
  "geometry": {"coordinates":[27.286,55.6205],"type":"Point"}
}