{
  "type": "Feature",
  "properties": {
    "gn:admin1_code":"6.0",
    "gn:asciiname":"Yezershchina",
    "gn:country_code":"BY",
    "gn:dem":187,
    "gn:feature_class":"P",
    "gn:feature_code":"PPL",
    "gn:name":"Yezershchina",
    "gn:population":0,
    "gn:timezone":"Europe/Minsk",
    "iso:country":"BY",
    "name:rus_x_preferred":[
        "\u0415\u0437\u0435\u0440\u0449\u0438\u043d\u0430"
    ],
    "wof:name":"Yezershchina",
    "wof:placetype":"locality"
},
  "geometry": {"coordinates":[30.1406,54.0466],"type":"Point"}
}