{
  "type": "Feature",
  "properties": {
    "gn:admin1_code":"3.0",
    "gn:asciiname":"Yedantsa",
    "gn:country_code":"BY",
    "gn:dem":177,
    "gn:feature_class":"P",
    "gn:feature_code":"PPL",
    "gn:name":"Yedantsa",
    "gn:population":0,
    "gn:timezone":"Europe/Minsk",
    "iso:country":"BY",
    "name:rus_x_preferred":[
        "\u0415\u0434\u0430\u043d\u0446\u0430"
    ],
    "wof:name":"Yedantsa",
    "wof:placetype":"locality"
},
  "geometry": {"coordinates":[25.56,54.0788],"type":"Point"}
}