{
  "type": "Feature",
  "properties": {
    "gn:admin1_code":"6.0",
    "gn:asciiname":"Zavoroty",
    "gn:country_code":"BY",
    "gn:dem":187,
    "gn:feature_class":"P",
    "gn:feature_code":"PPL",
    "gn:name":"Zavoroty",
    "gn:population":0,
    "gn:timezone":"Europe/Minsk",
    "iso:country":"BY",
    "name:rus_x_preferred":[
        "\u0417\u0430\u0432\u043e\u0440\u043e\u0442\u044b"
    ],
    "wof:name":"Zavoroty",
    "wof:placetype":"locality"
},
  "geometry": {"coordinates":[30.5536,54.0456],"type":"Point"}
}