{
  "type": "Feature",
  "properties": {
    "gn:admin1_code":"2.0",
    "gn:asciiname":"Vasil'pol'ye",
    "gn:country_code":"BY",
    "gn:dem":137,
    "gn:feature_class":"P",
    "gn:feature_code":"PPL",
    "gn:name":"Vasil\u2019pol\u2019ye",
    "gn:population":0,
    "gn:timezone":"Europe/Minsk",
    "iso:country":"BY",
    "name:rus_x_preferred":[
        "\u0412\u0430\u0441\u0438\u043b\u044c\u043f\u043e\u043b\u044c\u0435"
    ],
    "name:und_x_variant":[
        "Vasil\u2019pol\u2019ye"
    ],
    "wof:name":"Vasil'pol'ye",
    "wof:placetype":"locality"
},
  "geometry": {"coordinates":[30.4739,52.5043],"type":"Point"}
}