{
  "type": "Feature",
  "properties": {
    "gn:admin1_code":"3.0",
    "gn:asciiname":"Kovshary",
    "gn:country_code":"BY",
    "gn:dem":171,
    "gn:feature_class":"P",
    "gn:feature_code":"PPL",
    "gn:name":"Kovshary",
    "gn:population":0,
    "gn:timezone":"Europe/Minsk",
    "iso:country":"BY",
    "name:rus_x_preferred":[
        "\u041a\u043e\u0432\u0448\u0430\u0440\u044b"
    ],
    "name:und_x_variant":[
        "Kowszary",
        "Kovshary"
    ],
    "wof:name":"Kovshary",
    "wof:placetype":"locality"
},
  "geometry": {"coordinates":[26.0139,54.1025],"type":"Point"}
}