{
  "type": "Feature",
  "properties": {
    "gn:admin1_code":"5.0",
    "gn:asciiname":"Chirvonaya Polyana",
    "gn:country_code":"BY",
    "gn:dem":188,
    "gn:feature_class":"P",
    "gn:feature_code":"PPL",
    "gn:name":"Chirvonaya Polyana",
    "gn:population":0,
    "gn:timezone":"Europe/Minsk",
    "iso:country":"BY",
    "name:rus_x_preferred":[
        "\u0427\u0438\u0440\u0432\u043e\u043d\u0430\u044f \u041f\u043e\u043b\u044f\u043d\u0430"
    ],
    "name:und_x_variant":[
        "Krasnaya Polyana"
    ],
    "wof:name":"Chirvonaya Polyana",
    "wof:placetype":"locality"
},
  "geometry": {"coordinates":[28.7971,53.8046],"type":"Point"}
}