{
  "type": "Feature",
  "properties": {
    "gn:admin1_code":"2.0",
    "gn:asciiname":"Staraya Aleshkovka",
    "gn:country_code":"BY",
    "gn:dem":119,
    "gn:feature_class":"P",
    "gn:feature_code":"PPL",
    "gn:name":"Staraya Aleshkovka",
    "gn:population":0,
    "gn:timezone":"Europe/Minsk",
    "iso:country":"BY",
    "name:rus_x_preferred":[
        "\u0421\u0442\u0430\u0440\u0430\u044f \u0410\u043b\u0435\u0448\u043a\u043e\u0432\u043a\u0430"
    ],
    "name:und_x_variant":[
        "Staraya Ol\u2019shevka",
        "Ol\u2019sh\u00ebvka",
        "Staraya Aleshkovka",
        "Staraya Oleshkovka"
    ],
    "wof:name":"Staraya Aleshkovka",
    "wof:placetype":"locality"
},
  "geometry": {"coordinates":[30.5049,51.83600000000001],"type":"Point"}
}