{
  "type": "Feature",
  "properties": {
    "gn:admin1_code":"2.0",
    "gn:asciiname":"Dudarevo",
    "gn:country_code":"BY",
    "gn:dem":125,
    "gn:feature_class":"P",
    "gn:feature_code":"PPL",
    "gn:name":"Dudarevo",
    "gn:population":0,
    "gn:timezone":"Europe/Minsk",
    "iso:country":"BY",
    "name:rus_x_preferred":[
        "\u0414\u0443\u0434\u0430\u0440\u0435\u0432\u043e"
    ],
    "wof:name":"Dudarevo",
    "wof:placetype":"locality"
},
  "geometry": {"coordinates":[31.237,52.3818],"type":"Point"}
}