{
  "type": "Feature",
  "properties": {
    "gn:admin1_code":"5.0",
    "gn:asciiname":"Lyakhovichi",
    "gn:country_code":"BY",
    "gn:dem":188,
    "gn:feature_class":"P",
    "gn:feature_code":"PPL",
    "gn:name":"Lyakhovichi",
    "gn:population":0,
    "gn:timezone":"Europe/Minsk",
    "iso:country":"BY",
    "name:rus_x_preferred":[
        "\u041b\u044f\u0445\u043e\u0432\u0438\u0447\u0438"
    ],
    "wof:name":"Lyakhovichi",
    "wof:placetype":"locality"
},
  "geometry": {"coordinates":[27.0484,54.8886],"type":"Point"}
}