{
  "type": "Feature",
  "properties": {
    "gn:admin1_code":"5.0",
    "gn:asciiname":"Gryadki",
    "gn:country_code":"BY",
    "gn:dem":169,
    "gn:feature_class":"P",
    "gn:feature_code":"PPL",
    "gn:name":"Gryadki",
    "gn:population":0,
    "gn:timezone":"Europe/Minsk",
    "iso:country":"BY",
    "name:rus_x_preferred":[
        "\u0413\u0440\u044f\u0434\u043a\u0438"
    ],
    "wof:name":"Gryadki",
    "wof:placetype":"locality"
},
  "geometry": {"coordinates":[28.2675,54.1154],"type":"Point"}
}