{
  "type": "Feature",
  "properties": {
    "gn:admin1_code":"2.0",
    "gn:asciiname":"Zarech'ye",
    "gn:country_code":"BY",
    "gn:dem":112,
    "gn:feature_class":"P",
    "gn:feature_code":"PPL",
    "gn:name":"Zarech\u2019ye",
    "gn:population":0,
    "gn:timezone":"Europe/Minsk",
    "iso:country":"BY",
    "name:rus_x_preferred":[
        "\u0417\u0430\u0440\u0435\u0447\u044c\u0435"
    ],
    "name:und_x_variant":[
        "Zarech\u2019ye"
    ],
    "wof:name":"Zarech'ye",
    "wof:placetype":"locality"
},
  "geometry": {"coordinates":[30.3696,51.7756],"type":"Point"}
}