{
  "type": "Feature",
  "properties": {
    "gn:admin1_code":"7.0",
    "gn:asciiname":"Vesnitsk",
    "gn:country_code":"BY",
    "gn:dem":216,
    "gn:feature_class":"P",
    "gn:feature_code":"PPL",
    "gn:name":"Vesnitsk",
    "gn:population":0,
    "gn:timezone":"Europe/Minsk",
    "iso:country":"BY",
    "name:eng_x_preferred":[
        "Vesnitsk"
    ],
    "name:rus_x_preferred":[
        "\u0412\u0435\u0441\u043d\u0438\u0446\u043a"
    ],
    "wof:name":"Vesnitsk",
    "wof:placetype":"locality"
},
  "geometry": {"coordinates":[28.345,55.0454],"type":"Point"}
}