{
  "type": "Feature",
  "properties": {
    "gn:admin1_code":"7.0",
    "gn:asciiname":"Dulino",
    "gn:country_code":"BY",
    "gn:dem":128,
    "gn:feature_class":"P",
    "gn:feature_code":"PPL",
    "gn:name":"Dulino",
    "gn:population":0,
    "gn:timezone":"Europe/Minsk",
    "iso:country":"BY",
    "name:eng_x_preferred":[
        "Dulino"
    ],
    "name:rus_x_preferred":[
        "\u0414\u0443\u043b\u0438\u043d\u043e"
    ],
    "wof:name":"Dulino",
    "wof:placetype":"locality"
},
  "geometry": {"coordinates":[27.4055,55.3078],"type":"Point"}
}