{
  "type": "Feature",
  "properties": {
    "gn:admin1_code":"3.0",
    "gn:asciiname":"Monkevichi",
    "gn:country_code":"BY",
    "gn:dem":125,
    "gn:feature_class":"P",
    "gn:feature_code":"PPL",
    "gn:name":"Monkevichi",
    "gn:population":0,
    "gn:timezone":"Europe/Minsk",
    "iso:country":"BY",
    "name:bel_x_preferred":[
        "Mon\u2019kavichy"
    ],
    "name:bel_x_variant":[
        "\u041c\u043e\u043d\u044c\u043a\u0430\u0432\u0456\u0447\u044b"
    ],
    "name:rus_x_preferred":[
        "\u041c\u043e\u043d\u044c\u043a\u043e\u0432\u0438\u0447\u0438"
    ],
    "name:und_x_variant":[
        "Monkeviche",
        "Monkevichi",
        "Mon\u2019kovichi"
    ],
    "wof:name":"Monkevichi",
    "wof:placetype":"locality"
},
  "geometry": {"coordinates":[24.8725,53.3246],"type":"Point"}
}