{
  "type": "Feature",
  "properties": {
    "gn:admin1_code":"1.0",
    "gn:asciiname":"Karpin",
    "gn:country_code":"BY",
    "gn:dem":165,
    "gn:feature_class":"P",
    "gn:feature_code":"PPL",
    "gn:name":"Karpin",
    "gn:population":0,
    "gn:timezone":"Europe/Minsk",
    "iso:country":"BY",
    "name:rus_x_preferred":[
        "\u041a\u0430\u0440\u043f\u0438\u043d"
    ],
    "wof:name":"Karpin",
    "wof:placetype":"locality"
},
  "geometry": {"coordinates":[24.0319,51.7604],"type":"Point"}
}