{
  "type": "Feature",
  "properties": {
    "gn:admin1_code":"5.0",
    "gn:asciiname":"Milty",
    "gn:country_code":"BY",
    "gn:dem":176,
    "gn:feature_class":"P",
    "gn:feature_code":"PPL",
    "gn:name":"Milty",
    "gn:population":0,
    "gn:timezone":"Europe/Minsk",
    "iso:country":"BY",
    "name:rus_x_preferred":[
        "\u041c\u0438\u043b\u0442\u044b"
    ],
    "wof:name":"Milty",
    "wof:placetype":"locality"
},
  "geometry": {"coordinates":[27.0783,54.9581],"type":"Point"}
}