{
  "type": "Feature",
  "properties": {
    "gn:admin1_code":"7.0",
    "gn:asciiname":"Molyavka",
    "gn:country_code":"BY",
    "gn:dem":178,
    "gn:feature_class":"P",
    "gn:feature_code":"PPL",
    "gn:name":"Molyavka",
    "gn:population":0,
    "gn:timezone":"Europe/Minsk",
    "iso:country":"BY",
    "name:rus_x_preferred":[
        "\u041c\u043e\u043b\u044f\u0432\u043a\u0430"
    ],
    "wof:name":"Molyavka",
    "wof:placetype":"locality"
},
  "geometry": {"coordinates":[29.4015,54.3392],"type":"Point"}
}