{
  "type": "Feature",
  "properties": {
    "gn:admin1_code":"5.0",
    "gn:asciiname":"Serkuli",
    "gn:country_code":"BY",
    "gn:dem":186,
    "gn:feature_class":"P",
    "gn:feature_code":"PPL",
    "gn:name":"Serkuli",
    "gn:population":0,
    "gn:timezone":"Europe/Minsk",
    "iso:country":"BY",
    "name:rus_x_preferred":[
        "\u0421\u0435\u0440\u043a\u0443\u043b\u0438"
    ],
    "wof:name":"Serkuli",
    "wof:placetype":"locality"
},
  "geometry": {"coordinates":[26.7429,53.7585],"type":"Point"}
}