{
  "type": "Feature",
  "properties": {
    "gn:gn_country":"BY",
    "gn:gn_fcode":"PPL",
    "gn:gn_pop":77,
    "gn:population":77,
    "iso:country":"BY",
    "name:bel_x_preferred":[
        "\u0420\u0430\u0442\u0430\u043c\u043a\u0430"
    ],
    "name:eng_x_preferred":[
        "Ratomka"
    ],
    "name:rus_x_preferred":[
        "\u0420\u0430\u0442\u043e\u043c\u043a\u0430"
    ],
    "name:unk_x_variant":[
        "Ratomka"
    ],
    "qs_pg:aaroncc":"BY",
    "qs_pg:gn_country":"BY",
    "qs_pg:gn_fcode":"PPL",
    "qs_pg:gn_pop":77,
    "qs_pg:name":"Ratamka",
    "qs_pg:photos_9r":0,
    "qs_pg:photos_sr":0,
    "qs_pg:pop_sr":1,
    "qs_pg:qs_pg_placetype":"locality",
    "wof:name":"Ratamka",
    "wof:placetype":"locality",
    "wof:population":77
},
  "geometry": {"coordinates":[27.3444,53.9404],"type":"Point"}
}