{
  "type": "Feature",
  "properties": {
    "gn:admin1_code":"5.0",
    "gn:asciiname":"Otochnaya Sloboda",
    "gn:country_code":"BY",
    "gn:dem":165,
    "gn:feature_class":"P",
    "gn:feature_code":"PPL",
    "gn:name":"Otochnaya Sloboda",
    "gn:population":0,
    "gn:timezone":"Europe/Minsk",
    "iso:country":"BY",
    "name:rus_x_preferred":[
        "\u041e\u0442\u043e\u0447\u043d\u0430\u044f \u0421\u043b\u043e\u0431\u043e\u0434\u0430"
    ],
    "wof:name":"Otochnaya Sloboda",
    "wof:placetype":"locality"
},
  "geometry": {"coordinates":[28.3082,53.6664],"type":"Point"}
}