{
  "type": "Feature",
  "properties": {
    "gn:admin1_code":"3.0",
    "gn:asciiname":"Ulezly",
    "gn:country_code":"BY",
    "gn:dem":174,
    "gn:feature_class":"P",
    "gn:feature_code":"PPL",
    "gn:name":"Ulezly",
    "gn:population":0,
    "gn:timezone":"Europe/Minsk",
    "iso:country":"BY",
    "name:bel_x_preferred":[
        "Ulyezly"
    ],
    "name:rus_x_preferred":[
        "\u0423\u043b\u0435\u0437\u043b\u044b"
    ],
    "wof:name":"Ulezly",
    "wof:placetype":"locality"
},
  "geometry": {"coordinates":[24.579,53.0653],"type":"Point"}
}