{
  "type": "Feature",
  "properties": {
    "gn:admin1_code":"5.0",
    "gn:asciiname":"Lezhnevka",
    "gn:country_code":"BY",
    "gn:dem":178,
    "gn:feature_class":"P",
    "gn:feature_code":"PPL",
    "gn:name":"Lezhnevka",
    "gn:population":0,
    "gn:timezone":"Europe/Minsk",
    "iso:country":"BY",
    "name:rus_x_preferred":[
        "\u041b\u0435\u0436\u043d\u0435\u0432\u043a\u0430"
    ],
    "wof:name":"Lezhnevka",
    "wof:placetype":"locality"
},
  "geometry": {"coordinates":[28.3898,53.7424],"type":"Point"}
}