{
  "type": "Feature",
  "properties": {
    "gn:admin1_code":"2.0",
    "gn:asciiname":"Stralichava",
    "gn:country_code":"BY",
    "gn:dem":128,
    "gn:feature_class":"P",
    "gn:feature_code":"PPL",
    "gn:name":"Stralichava",
    "gn:population":0,
    "gn:timezone":"Europe/Minsk",
    "iso:country":"BY",
    "name:bel_x_preferred":[
        "\u0421\u0442\u0440\u0430\u043b\u0456\u0447\u0430\u0432\u0430"
    ],
    "name:bel_x_variant":[
        "Stralichava"
    ],
    "name:und_x_variant":[
        "Strelichev",
        "Strelichevo"
    ],
    "wof:name":"Stralichava",
    "wof:placetype":"locality"
},
  "geometry": {"coordinates":[29.9769,51.8342],"type":"Point"}
}