{
  "type": "Feature",
  "properties": {
    "gn:admin1_code":"6.0",
    "gn:asciiname":"Skoklevo",
    "gn:country_code":"BY",
    "gn:dem":146,
    "gn:feature_class":"P",
    "gn:feature_code":"PPL",
    "gn:name":"Skoklevo",
    "gn:population":0,
    "gn:timezone":"Europe/Minsk",
    "iso:country":"BY",
    "name:rus_x_preferred":[
        "\u0421\u043a\u043e\u043a\u043b\u0435\u0432\u043e"
    ],
    "wof:name":"Skoklevo",
    "wof:placetype":"locality"
},
  "geometry": {"coordinates":[30.9222,53.6599],"type":"Point"}
}