{
  "type": "Feature",
  "properties": {
    "gn:admin1_code":"5.0",
    "gn:asciiname":"Gelenovo",
    "gn:country_code":"BY",
    "gn:dem":225,
    "gn:feature_class":"P",
    "gn:feature_code":"PPL",
    "gn:name":"Gelenovo",
    "gn:population":0,
    "gn:timezone":"Europe/Minsk",
    "iso:country":"BY",
    "name:rus_x_preferred":[
        "\u0413\u0435\u043b\u0435\u043d\u043e\u0432\u043e"
    ],
    "name:und_x_variant":[
        "Galenovo"
    ],
    "wof:name":"Gelenovo",
    "wof:placetype":"locality"
},
  "geometry": {"coordinates":[26.1904,54.2259],"type":"Point"}
}