{
  "type": "Feature",
  "properties": {
    "gn:admin1_code":"2.0",
    "gn:asciiname":"Gazhin",
    "gn:country_code":"BY",
    "gn:dem":120,
    "gn:feature_class":"P",
    "gn:feature_code":"PPL",
    "gn:name":"Gazhin",
    "gn:population":0,
    "gn:timezone":"Europe/Minsk",
    "iso:country":"BY",
    "name:rus_x_preferred":[
        "\u0413\u0430\u0436\u0438\u043d"
    ],
    "wof:name":"Gazhin",
    "wof:placetype":"locality"
},
  "geometry": {"coordinates":[29.2153,51.6542],"type":"Point"}
}