{
  "type": "Feature",
  "properties": {
    "gn:admin1_code":"5.0",
    "gn:asciiname":"Plisa",
    "gn:country_code":"BY",
    "gn:dem":189,
    "gn:feature_class":"P",
    "gn:feature_code":"PPL",
    "gn:name":"Plisa",
    "gn:population":0,
    "gn:timezone":"Europe/Minsk",
    "iso:country":"BY",
    "name:bel_x_preferred":[
        "\u041f\u043b\u0456\u0441\u0430"
    ],
    "name:eng_x_preferred":[
        "Plisa"
    ],
    "name:rus_x_preferred":[
        "\u041f\u043b\u0438\u0441\u0430"
    ],
    "name:und_x_variant":[
        "Plissa"
    ],
    "wof:name":"Plisa",
    "wof:placetype":"locality"
},
  "geometry": {"coordinates":[28.193,54.0501],"type":"Point"}
}