{
  "type": "Feature",
  "properties": {
    "gn:admin1_code":"7.0",
    "gn:asciiname":"Zastenki",
    "gn:country_code":"BY",
    "gn:dem":180,
    "gn:feature_class":"P",
    "gn:feature_code":"PPL",
    "gn:name":"Zastenki",
    "gn:population":0,
    "gn:timezone":"Europe/Minsk",
    "iso:country":"BY",
    "name:rus_x_preferred":[
        "\u0417\u0430\u0441\u0442\u0435\u043d\u043a\u0438"
    ],
    "wof:name":"Zastenki",
    "wof:placetype":"locality"
},
  "geometry": {"coordinates":[30.5022,55.3531],"type":"Point"}
}