{
  "type": "Feature",
  "properties": {
    "iso:country":"BY",
    "name:bel_x_preferred":[
        "\u0413\u043e\u0440\u0430\u0434 \u041c\u0430\u0440'\u0456\u043d\u0430 \u0413\u043e\u0440\u043a\u0430"
    ],
    "name:bel_x_variant":[
        "\u041c\u0430\u0440\u2019\u0456\u043d\u0430 \u0413\u043e\u0440\u043a\u0430"
    ],
    "name:bul_x_preferred":[
        "\u041c\u0430\u0440\u0438\u043d\u0430 \u0413\u043e\u0440\u043a\u0430"
    ],
    "name:ceb_x_preferred":[
        "Mar'ina Horka"
    ],
    "name:ceb_x_variant":[
        "Mar''ina Horka"
    ],
    "name:ces_x_preferred":[
        "Marjina Horka"
    ],
    "name:che_x_preferred":[
        "\u041c\u0430\u0440\u044c\u0438\u043d\u0430 \u0413\u043e\u0440\u043a\u0430"
    ],
    "name:deu_x_preferred":[
        "Marjina Horka"
    ],
    "name:ell_x_preferred":[
        "\u039c\u03b1\u03c1\u03b3\u03af\u03bd\u03b1 \u03a7\u03cc\u03c1\u03ba\u03b1"
    ],
    "name:eng_x_preferred":[
        "Mar''ina Horka"
    ],
    "name:eng_x_variant":[
        "Marjina Horka"
    ],
    "name:est_x_preferred":[
        "Marjina Horka"
    ],
    "name:fin_x_preferred":[
        "Marina Horka"
    ],
    "name:fra_x_preferred":[
        "Marina Horka"
    ],
    "name:frr_x_preferred":[
        "Marjina Horka"
    ],
    "name:heb_x_preferred":[
        "\u05de\u05e8\u05d9\u05e0\u05d4 \u05d4\u05d5\u05e8\u05e7\u05d4"
    ],
    "name:hsb_x_preferred":[
        "Marjina Gorka"
    ],
    "name:ita_x_preferred":[
        "Marina Gorka"
    ],
    "name:lav_x_preferred":[
        "Marjina Horka"
    ],
    "name:lit_x_preferred":[
        "Marjina Horka"
    ],
    "name:mkd_x_preferred":[
        "\u041c\u0430\u0440\u0438\u043d\u0430 \u0413\u043e\u0440\u043a\u0430"
    ],
    "name:nld_x_preferred":[
        "Maryina Horka"
    ],
    "name:pol_x_preferred":[
        "Marina Horka"
    ],
    "name:rus_x_preferred":[
        "\u041c\u0430\u0440\u044c\u0438\u043d\u0430 \u0413\u043e\u0440\u043a\u0430"
    ],
    "name:srp_x_preferred":[
        "\u041c\u0430\u0440\u0438\u043d\u0430 \u0413\u043e\u0440\u043a\u0430"
    ],
    "name:swe_x_preferred":[
        "Mar'ina Horka"
    ],
    "name:swe_x_variant":[
        "Mar'\u0456na Horka"
    ],
    "name:tat_x_preferred":[
        "\u041c\u0430\u0440\u044c\u0438\u043d\u0430 \u0413\u043e\u0440\u043a\u0430"
    ],
    "name:tat_x_variant":[
        "\u041c\u0430\u0440\u044c\u0438\u043d\u0430-\u04ba\u043e\u0440\u043a\u0430"
    ],
    "name:ukr_x_preferred":[
        "\u041c\u0430\u0440'\u0457\u043d\u0430 \u0413\u043e\u0440\u043a\u0430"
    ],
    "name:unk_x_variant":[
        "Maryina Gorka"
    ],
    "name:urd_x_preferred":[
        "\u0645\u0627\u0631\u0626\u06cc\u0646\u0627 \u06c1\u0648\u0631\u06a9\u0627"
    ],
    "name:zho_x_preferred":[
        "\u99ac\u91cc\u7d0d\u6208\u723e\u5361"
    ],
    "qs:gn_country":"BY",
    "qs:gn_fcode":"PPL",
    "qs:gn_pop":20100,
    "qs:name":"Mar'ina Gorka",
    "qs:name_adm0":"Belarus",
    "qs:name_adm1":"Minskaya Voblasts'",
    "qs:photos":0,
    "qs:photos_1k":0,
    "qs:photos_9k":1,
    "qs:photos_9r":1,
    "qs:photos_all":1,
    "qs:photos_sr":0,
    "qs:placetype":"Town",
    "qs:pop_sr":"7",
    "qs:woe_adm0":23424765,
    "wd:elevation":169.0,
    "wd:population":21446,
    "wd:wordcount":160,
    "wof:name":"Mar'ina Gorka",
    "wof:placetype":"locality",
    "wof:population":21446
},
  "geometry": {"coordinates":[28.147,53.509],"type":"Point"}
}