{
  "type": "Feature",
  "properties": {
    "gn:admin1_code":"5.0",
    "gn:asciiname":"Yasyukovka",
    "gn:country_code":"BY",
    "gn:dem":181,
    "gn:feature_class":"P",
    "gn:feature_code":"PPL",
    "gn:name":"Yasyukovka",
    "gn:population":0,
    "gn:timezone":"Europe/Minsk",
    "iso:country":"BY",
    "name:rus_x_preferred":[
        "\u042f\u0441\u044e\u043a\u043e\u0432\u043a\u0430"
    ],
    "wof:name":"Yasyukovka",
    "wof:placetype":"locality"
},
  "geometry": {"coordinates":[27.5512,54.7585],"type":"Point"}
}