{
  "type": "Feature",
  "properties": {
    "gn:admin1_code":"6.0",
    "gn:asciiname":"Lyady",
    "gn:country_code":"BY",
    "gn:dem":172,
    "gn:feature_class":"P",
    "gn:feature_code":"PPL",
    "gn:name":"Lyady",
    "gn:population":0,
    "gn:timezone":"Europe/Minsk",
    "iso:country":"BY",
    "name:bel_x_preferred":[
        "\u041b\u044f\u0434\u044b"
    ],
    "name:hye_x_preferred":[
        "\u053c\u0575\u0561\u0564\u056b"
    ],
    "name:rus_x_preferred":[
        "\u041b\u044f\u0434\u044b"
    ],
    "name:ukr_x_preferred":[
        "\u041b\u044f\u0434\u0438"
    ],
    "wof:name":"Lyady",
    "wof:placetype":"locality"
},
  "geometry": {"coordinates":[31.5024,53.7438],"type":"Point"}
}