{
  "type": "Feature",
  "properties": {
    "gn:admin1_code":"6.0",
    "gn:asciiname":"Goloburdy",
    "gn:country_code":"BY",
    "gn:dem":179,
    "gn:feature_class":"P",
    "gn:feature_code":"PPL",
    "gn:name":"Goloburdy",
    "gn:population":0,
    "gn:timezone":"Europe/Minsk",
    "iso:country":"BY",
    "name:rus_x_preferred":[
        "\u0413\u043e\u043b\u043e\u0431\u0443\u0440\u0434\u044b"
    ],
    "name:und_x_variant":[
        "Galaburdy",
        "Goloburdy"
    ],
    "wof:name":"Goloburdy",
    "wof:placetype":"locality"
},
  "geometry": {"coordinates":[30.7356,54.1751],"type":"Point"}
}