{
  "type": "Feature",
  "properties": {
    "gn:admin1_code":"2.0",
    "gn:asciiname":"Dubrovka",
    "gn:country_code":"BY",
    "gn:dem":135,
    "gn:feature_class":"P",
    "gn:feature_code":"PPL",
    "gn:name":"Dubrovka",
    "gn:population":0,
    "gn:timezone":"Europe/Minsk",
    "iso:country":"BY",
    "name:rus_x_preferred":[
        "\u0414\u0443\u0431\u0440\u043e\u0432\u043a\u0430"
    ],
    "name:und_x_variant":[
        "Dubrovki"
    ],
    "wof:name":"Dubrovka",
    "wof:placetype":"locality"
},
  "geometry": {"coordinates":[28.6833,51.7073],"type":"Point"}
}