{
  "type": "Feature",
  "properties": {
    "gn:admin1_code":"6.0",
    "gn:asciiname":"Bakunovichi",
    "gn:country_code":"BY",
    "gn:dem":141,
    "gn:feature_class":"P",
    "gn:feature_code":"PPL",
    "gn:name":"Bakunovichi",
    "gn:population":0,
    "gn:timezone":"Europe/Minsk",
    "iso:country":"BY",
    "name:rus_x_preferred":[
        "\u0411\u0430\u043a\u0443\u043d\u043e\u0432\u0438\u0447\u0438"
    ],
    "name:und_x_variant":[
        "Bukunovichi",
        "Bakunovichi"
    ],
    "wof:name":"Bakunovichi",
    "wof:placetype":"locality"
},
  "geometry": {"coordinates":[31.2538,53.4535],"type":"Point"}
}