{
  "type": "Feature",
  "properties": {
    "gn:admin1_code":"7.0",
    "gn:asciiname":"Zazyby Vtoryye",
    "gn:country_code":"BY",
    "gn:dem":168,
    "gn:feature_class":"P",
    "gn:feature_code":"PPL",
    "gn:name":"Zazyby Vtoryye",
    "gn:population":0,
    "gn:timezone":"Europe/Minsk",
    "iso:country":"BY",
    "name:rus_x_preferred":[
        "\u0417\u0430\u0437\u044b\u0431\u044b \u0412\u0442\u043e\u0440\u044b\u0435"
    ],
    "name:und_x_variant":[
        "Zazyby Pervyye"
    ],
    "wof:name":"Zazyby Vtoryye",
    "wof:placetype":"locality"
},
  "geometry": {"coordinates":[30.365,55.0387],"type":"Point"}
}