{
  "type": "Feature",
  "properties": {
    "gn:admin1_code":"7.0",
    "gn:asciiname":"Yerashovo",
    "gn:country_code":"BY",
    "gn:dem":121,
    "gn:feature_class":"P",
    "gn:feature_code":"PPL",
    "gn:name":"Yerashovo",
    "gn:population":0,
    "gn:timezone":"Europe/Minsk",
    "iso:country":"BY",
    "name:rus_x_preferred":[
        "\u0415\u0440\u0430\u0448\u043e\u0432\u043e"
    ],
    "name:und_x_variant":[
        "Yerosheva"
    ],
    "wof:name":"Yerashovo",
    "wof:placetype":"locality"
},
  "geometry": {"coordinates":[29.2907,55.1794],"type":"Point"}
}