{
  "type": "Feature",
  "properties": {
    "gn:admin1_code":"5.0",
    "gn:asciiname":"Kalita",
    "gn:country_code":"BY",
    "gn:dem":189,
    "gn:feature_class":"P",
    "gn:feature_code":"PPL",
    "gn:name":"Kalita",
    "gn:population":0,
    "gn:timezone":"Europe/Minsk",
    "iso:country":"BY",
    "name:rus_x_preferred":[
        "\u041a\u0430\u043b\u0438\u0442\u0430"
    ],
    "wof:name":"Kalita",
    "wof:placetype":"locality"
},
  "geometry": {"coordinates":[27.896,53.8342],"type":"Point"}
}