{
  "type": "Feature",
  "properties": {
    "gn:admin1_code":"5.0",
    "gn:asciiname":"Mkhereno Pervoye",
    "gn:country_code":"BY",
    "gn:dem":195,
    "gn:feature_class":"P",
    "gn:feature_code":"PPL",
    "gn:name":"Mkhereno Pervoye",
    "gn:population":0,
    "gn:timezone":"Europe/Minsk",
    "iso:country":"BY",
    "name:rus_x_preferred":[
        "\u041c\u0445\u0435\u0440\u0435\u043d\u043e \u041f\u0435\u0440\u0432\u043e\u0435"
    ],
    "name:und_x_variant":[
        "Mkherino Pervoye"
    ],
    "wof:name":"Mkhereno Pervoye",
    "wof:placetype":"locality"
},
  "geometry": {"coordinates":[28.8489,54.5423],"type":"Point"}
}