{
  "type": "Feature",
  "properties": {
    "gn:admin1_code":"5.0",
    "gn:asciiname":"Zhaki",
    "gn:country_code":"BY",
    "gn:dem":199,
    "gn:feature_class":"P",
    "gn:feature_code":"PPL",
    "gn:name":"Zhaki",
    "gn:population":0,
    "gn:timezone":"Europe/Minsk",
    "iso:country":"BY",
    "name:rus_x_preferred":[
        "\u0416\u0430\u043a\u0438"
    ],
    "wof:name":"Zhaki",
    "wof:placetype":"locality"
},
  "geometry": {"coordinates":[27.4357,53.6667],"type":"Point"}
}