{
  "type": "Feature",
  "properties": {
    "gn:admin1_code":"2.0",
    "gn:asciiname":"Borets",
    "gn:country_code":"BY",
    "gn:dem":120,
    "gn:feature_class":"P",
    "gn:feature_code":"PPL",
    "gn:name":"Borets",
    "gn:population":0,
    "gn:timezone":"Europe/Minsk",
    "iso:country":"BY",
    "name:rus_x_preferred":[
        "\u0411\u043e\u0440\u0435\u0446"
    ],
    "wof:name":"Borets",
    "wof:placetype":"locality"
},
  "geometry": {"coordinates":[30.9534,52.2992],"type":"Point"}
}