{
  "type": "Feature",
  "properties": {
    "gn:admin1_code":"0.0",
    "gn:asciiname":"Kuty",
    "gn:country_code":"BY",
    "gn:dem":146,
    "gn:feature_class":"P",
    "gn:feature_code":"PPL",
    "gn:name":"Kuty",
    "gn:population":0,
    "gn:timezone":"Europe/Minsk",
    "iso:country":"BY",
    "name:bel_x_preferred":[
        "\u041a\u0443\u0442\u044b"
    ],
    "name:ceb_x_preferred":[
        "Kuty"
    ],
    "name:crh_x_preferred":[
        "Kut\u0131"
    ],
    "name:deu_x_preferred":[
        "Kuty"
    ],
    "name:epo_x_preferred":[
        "Kuti"
    ],
    "name:fra_x_preferred":[
        "Kouty"
    ],
    "name:heb_x_preferred":[
        "\u05e7\u05d5\u05d8\u05d9"
    ],
    "name:pol_x_preferred":[
        "Kuty"
    ],
    "name:ron_x_preferred":[
        "Cuturi"
    ],
    "name:rus_x_preferred":[
        "\u041a\u0443\u0442\u044b"
    ],
    "name:ukr_x_preferred":[
        "\u041a\u0443\u0442\u0438"
    ],
    "wof:name":"Kuty",
    "wof:placetype":"locality"
},
  "geometry": {"coordinates":[30.58333,53.41667],"type":"Point"}
}