{
  "type": "Feature",
  "properties": {
    "gn:admin1_code":"6.0",
    "gn:asciiname":"Mikhalev",
    "gn:country_code":"BY",
    "gn:dem":150,
    "gn:feature_class":"P",
    "gn:feature_code":"PPL",
    "gn:name":"Mikhalev",
    "gn:population":0,
    "gn:timezone":"Europe/Minsk",
    "iso:country":"BY",
    "name:rus_x_preferred":[
        "\u041c\u0438\u0445\u0430\u043b\u0451\u0432\u043a\u0430"
    ],
    "name:und_x_variant":[
        "Mikhal\u00ebvka",
        "Mikhalev"
    ],
    "wof:name":"Mikhalev",
    "wof:placetype":"locality"
},
  "geometry": {"coordinates":[30.2411,53.3279],"type":"Point"}
}