{
  "type": "Feature",
  "properties": {
    "gn:admin1_code":"7.0",
    "gn:asciiname":"Glodanki",
    "gn:country_code":"BY",
    "gn:dem":191,
    "gn:feature_class":"P",
    "gn:feature_code":"PPL",
    "gn:name":"Glodanki",
    "gn:population":0,
    "gn:timezone":"Europe/Minsk",
    "iso:country":"BY",
    "name:rus_x_preferred":[
        "\u0413\u043b\u043e\u0434\u0430\u043d\u043a\u0438"
    ],
    "name:und_x_variant":[
        "Glodynki",
        "Glodanki"
    ],
    "wof:name":"Glodanki",
    "wof:placetype":"locality"
},
  "geometry": {"coordinates":[30.8187,55.2309],"type":"Point"}
}