{
  "type": "Feature",
  "properties": {
    "gn:admin1_code":"3.0",
    "gn:asciiname":"Staryye Lagodki",
    "gn:country_code":"BY",
    "gn:dem":275,
    "gn:feature_class":"P",
    "gn:feature_code":"PPL",
    "gn:name":"Staryye Lagodki",
    "gn:population":0,
    "gn:timezone":"Europe/Minsk",
    "iso:country":"BY",
    "name:bel_x_preferred":[
        "Staryya Lahadki"
    ],
    "name:bel_x_variant":[
        "\u0421\u0442\u0430\u0440\u044b\u044f \u041b\u0430\u0433\u0430\u0434\u043a\u0456"
    ],
    "name:rus_x_preferred":[
        "\u0421\u0442\u0430\u0440\u044b\u0435 \u041b\u0430\u0433\u043e\u0434\u043a\u0438"
    ],
    "name:und_x_variant":[
        "Lagodka"
    ],
    "wof:name":"Staryye Lagodki",
    "wof:placetype":"locality"
},
  "geometry": {"coordinates":[25.8884,53.5368],"type":"Point"}
}