{
  "type": "Feature",
  "properties": {
    "gn:admin1_code":"7.0",
    "gn:asciiname":"Matskovo",
    "gn:country_code":"BY",
    "gn:dem":235,
    "gn:feature_class":"P",
    "gn:feature_code":"PPL",
    "gn:name":"Matskovo",
    "gn:population":0,
    "gn:timezone":"Europe/Minsk",
    "iso:country":"BY",
    "name:rus_x_preferred":[
        "\u041c\u0430\u0446\u043a\u043e\u0432\u043e"
    ],
    "name:und_x_variant":[
        "Motskovo"
    ],
    "wof:name":"Matskovo",
    "wof:placetype":"locality"
},
  "geometry": {"coordinates":[30.0188,54.6988],"type":"Point"}
}