{
  "type": "Feature",
  "properties": {
    "gn:admin1_code":"1.0",
    "gn:asciiname":"Ulasawtsy Druhiya",
    "gn:cc2":"BY",
    "gn:country_code":"BY",
    "gn:dem":141,
    "gn:feature_class":"P",
    "gn:feature_code":"PPL",
    "gn:name":"Ulasawtsy Druhiya",
    "gn:population":0,
    "gn:timezone":"Europe/Minsk",
    "iso:country":"BY",
    "name:bel_x_preferred":[
        "\u0423\u043b\u0430\u0441\u0430\u045e\u0446\u044b \u0414\u0440\u0443\u0433\u0456\u044f"
    ],
    "name:und_x_variant":[
        "Vlasovtsy",
        "Vlasovtse",
        "Ulasawtsy Druhiya",
        "Vlasovtsy Vtoryye"
    ],
    "wof:name":"Ulasawtsy Druhiya",
    "wof:placetype":"locality"
},
  "geometry": {"coordinates":[25.50244,52.00986],"type":"Point"}
}