{
  "type": "Feature",
  "properties": {
    "gn:admin1_code":"3.0",
    "gn:asciiname":"Zygmuntishki",
    "gn:country_code":"BY",
    "gn:dem":142,
    "gn:feature_class":"P",
    "gn:feature_code":"PPL",
    "gn:name":"Zygmuntishki",
    "gn:population":0,
    "gn:timezone":"Europe/Minsk",
    "iso:country":"BY",
    "name:rus_x_preferred":[
        "\u0417\u044b\u0433\u043c\u0443\u043d\u0442\u0438\u0448\u043a\u0438"
    ],
    "name:und_x_variant":[
        "Zygmuntsyshki"
    ],
    "wof:name":"Zygmuntishki",
    "wof:placetype":"locality"
},
  "geometry": {"coordinates":[25.6557,54.0131],"type":"Point"}
}