{
  "type": "Feature",
  "properties": {
    "gn:admin1_code":"7.0",
    "gn:asciiname":"Yeremino",
    "gn:country_code":"BY",
    "gn:dem":207,
    "gn:feature_class":"P",
    "gn:feature_code":"PPL",
    "gn:name":"Yer\u00ebmino",
    "gn:population":0,
    "gn:timezone":"Europe/Minsk",
    "iso:country":"BY",
    "name:eng_x_preferred":[
        "Yer\u00ebmino"
    ],
    "name:rus_x_preferred":[
        "\u0415\u0440\u0435\u043c\u0438\u043d\u043e"
    ],
    "name:rus_x_variant":[
        "\u0415\u0440\u0451\u043c\u0438\u043d\u043e"
    ],
    "wof:name":"Yeremino",
    "wof:placetype":"locality"
},
  "geometry": {"coordinates":[30.4655,55.1282],"type":"Point"}
}