{
  "type": "Feature",
  "properties": {
    "gn:admin1_code":"2.0",
    "gn:asciiname":"Rossokhi",
    "gn:country_code":"BY",
    "gn:dem":149,
    "gn:feature_class":"P",
    "gn:feature_code":"PPL",
    "gn:name":"Rossokhi",
    "gn:population":0,
    "gn:timezone":"Europe/Minsk",
    "iso:country":"BY",
    "name:rus_x_preferred":[
        "\u0420\u043e\u0441\u0441\u043e\u0445\u0438"
    ],
    "name:und_x_variant":[
        "Staryye Rossokhi"
    ],
    "wof:name":"Rossokhi",
    "wof:placetype":"locality"
},
  "geometry": {"coordinates":[30.7705,52.9981],"type":"Point"}
}