{
  "type": "Feature",
  "properties": {
    "gn:admin1_code":"6.0",
    "gn:asciiname":"Kamenka",
    "gn:country_code":"BY",
    "gn:dem":157,
    "gn:feature_class":"P",
    "gn:feature_code":"PPL",
    "gn:name":"Kamenka",
    "gn:population":0,
    "gn:timezone":"Europe/Minsk",
    "iso:country":"BY",
    "name:aze_x_preferred":[
        "Kamenka"
    ],
    "name:bel_x_preferred":[
        "\u041a\u0430\u043c\u0435\u043d\u043a\u0430"
    ],
    "name:ceb_x_preferred":[
        "Kamenka"
    ],
    "name:ces_x_preferred":[
        "Kamenka"
    ],
    "name:deu_x_preferred":[
        "Kamenka"
    ],
    "name:epo_x_preferred":[
        "Kamenka"
    ],
    "name:est_x_preferred":[
        "Kamenka"
    ],
    "name:fin_x_preferred":[
        "Kamenka"
    ],
    "name:fra_x_preferred":[
        "Kamenka"
    ],
    "name:hye_x_preferred":[
        "\u053f\u0561\u0574\u0565\u0576\u056f\u0561"
    ],
    "name:ita_x_preferred":[
        "Kamenka"
    ],
    "name:kat_x_preferred":[
        "\u10d9\u10d0\u10db\u10d4\u10dc\u10d9\u10d0"
    ],
    "name:kaz_x_preferred":[
        "\u041a\u0430\u043c\u0435\u043d\u043a\u0430"
    ],
    "name:lav_x_preferred":[
        "Kamenka"
    ],
    "name:lit_x_preferred":[
        "Kamenka"
    ],
    "name:myv_x_preferred":[
        "\u041a\u0430\u043c\u0435\u043d\u043a\u0430"
    ],
    "name:rus_x_preferred":[
        "\u0411\u043e\u043b\u044c\u0448\u0430\u044f \u041a\u0430\u043c\u0435\u043d\u043a\u0430"
    ],
    "name:rus_x_variant":[
        "\u041a\u0430\u043c\u0435\u043d\u043a\u0430"
    ],
    "name:srp_x_preferred":[
        "\u041a\u0430\u043c\u0435\u043d\u043a\u0430"
    ],
    "name:swe_x_preferred":[
        "Kamenka"
    ],
    "name:ukr_x_preferred":[
        "\u041a\u0430\u043c\u0435\u043d\u043a\u0430"
    ],
    "name:und_x_variant":[
        "Bol\u2019shaya Kamenka",
        "Kamenka",
        "Malaya Kamenka"
    ],
    "wof:name":"Kamenka",
    "wof:placetype":"locality"
},
  "geometry": {"coordinates":[29.0904,53.0997],"type":"Point"}
}