{
  "type": "Feature",
  "properties": {
    "gn:admin1_code":"7.0",
    "gn:asciiname":"Lisovskiye",
    "gn:country_code":"BY",
    "gn:dem":172,
    "gn:feature_class":"P",
    "gn:feature_code":"PPL",
    "gn:name":"Lisovskiye",
    "gn:population":0,
    "gn:timezone":"Europe/Minsk",
    "iso:country":"BY",
    "name:rus_x_preferred":[
        "\u041b\u0438\u0441\u043e\u0432\u0441\u043a\u0438\u0435"
    ],
    "wof:name":"Lisovskiye",
    "wof:placetype":"locality"
},
  "geometry": {"coordinates":[30.4953,54.7446],"type":"Point"}
}