{
  "type": "Feature",
  "properties": {
    "gn:admin1_code":"3.0",
    "gn:asciiname":"Podles'ye",
    "gn:country_code":"BY",
    "gn:dem":163,
    "gn:feature_class":"P",
    "gn:feature_code":"PPL",
    "gn:name":"Podles\u2019ye",
    "gn:population":0,
    "gn:timezone":"Europe/Minsk",
    "iso:country":"BY",
    "name:rus_x_preferred":[
        "\u041f\u043e\u0434\u043b\u0435\u0441\u044c\u0435"
    ],
    "name:und_x_variant":[
        "Podles\u2019ye"
    ],
    "wof:name":"Podles'ye",
    "wof:placetype":"locality"
},
  "geometry": {"coordinates":[25.1452,52.9007],"type":"Point"}
}