{
  "type": "Feature",
  "properties": {
    "gn:admin1_code":"3.0",
    "gn:asciiname":"Malyye Semyuny",
    "gn:country_code":"BY",
    "gn:dem":204,
    "gn:feature_class":"P",
    "gn:feature_code":"PPL",
    "gn:name":"Malyye Semyuny",
    "gn:population":0,
    "gn:timezone":"Europe/Minsk",
    "iso:country":"BY",
    "name:rus_x_preferred":[
        "\u041c\u0430\u043b\u044b\u0435 \u0421\u0435\u043c\u044e\u043d\u044b"
    ],
    "wof:name":"Malyye Semyuny",
    "wof:placetype":"locality"
},
  "geometry": {"coordinates":[25.859,54.368],"type":"Point"}
}