{
  "type": "Feature",
  "properties": {
    "gn:admin1_code":"7.0",
    "gn:asciiname":"Kozlovshchina",
    "gn:country_code":"BY",
    "gn:dem":128,
    "gn:feature_class":"P",
    "gn:feature_code":"PPL",
    "gn:name":"Kozlovshchina",
    "gn:population":0,
    "gn:timezone":"Europe/Minsk",
    "iso:country":"BY",
    "name:rus_x_preferred":[
        "\u041a\u043e\u0437\u043b\u043e\u0432\u0449\u0438\u043d\u0430"
    ],
    "wof:name":"Kozlovshchina",
    "wof:placetype":"locality"
},
  "geometry": {"coordinates":[28.1115,55.8501],"type":"Point"}
}