{
  "type": "Feature",
  "properties": {
    "gn:admin1_code":"5.0",
    "gn:asciiname":"Barberovka",
    "gn:country_code":"BY",
    "gn:dem":153,
    "gn:feature_class":"P",
    "gn:feature_code":"PPL",
    "gn:name":"Barberovka",
    "gn:population":0,
    "gn:timezone":"Europe/Minsk",
    "iso:country":"BY",
    "name:rus_x_preferred":[
        "\u0411\u0430\u0440\u0431\u0435\u0440\u043e\u0432\u043a\u0430"
    ],
    "wof:name":"Barberovka",
    "wof:placetype":"locality"
},
  "geometry": {"coordinates":[28.4256,52.9353],"type":"Point"}
}