{
  "type": "Feature",
  "properties": {
    "gn:admin1_code":"5.0",
    "gn:asciiname":"Kamyenny Barok",
    "gn:country_code":"BY",
    "gn:dem":162,
    "gn:feature_class":"P",
    "gn:feature_code":"PPL",
    "gn:name":"Kamyenny Barok",
    "gn:population":0,
    "gn:timezone":"Europe/Minsk",
    "iso:country":"BY",
    "name:bel_x_preferred":[
        "\u041a\u0430\u043c\u0435\u043d\u043d\u044b \u0411\u0430\u0440\u043e\u043a"
    ],
    "name:und_x_variant":[
        "Kamennyy Borok"
    ],
    "wof:name":"Kamyenny Barok",
    "wof:placetype":"locality"
},
  "geometry": {"coordinates":[29.1688,53.7355],"type":"Point"}
}