{
  "type": "Feature",
  "properties": {
    "gn:admin1_code":"3.0",
    "gn:asciiname":"Pilyuki",
    "gn:country_code":"BY",
    "gn:dem":121,
    "gn:feature_class":"P",
    "gn:feature_code":"PPL",
    "gn:name":"Pilyuki",
    "gn:population":0,
    "gn:timezone":"Europe/Minsk",
    "iso:country":"BY",
    "name:rus_x_preferred":[
        "\u041f\u0438\u043b\u044e\u043a\u0438"
    ],
    "wof:name":"Pilyuki",
    "wof:placetype":"locality"
},
  "geometry": {"coordinates":[24.0402,53.7045],"type":"Point"}
}