{
  "type": "Feature",
  "properties": {
    "gn:admin1_code":"3.0",
    "gn:asciiname":"Kayshovka",
    "gn:country_code":"BY",
    "gn:dem":155,
    "gn:feature_class":"P",
    "gn:feature_code":"PPL",
    "gn:name":"Kayshovka",
    "gn:population":0,
    "gn:timezone":"Europe/Minsk",
    "iso:country":"BY",
    "name:rus_x_preferred":[
        "\u041a\u0430\u0439\u0448\u043e\u0432\u043a\u0430"
    ],
    "name:und_x_variant":[
        "Kayshovki",
        "Kayshovka"
    ],
    "wof:name":"Kayshovka",
    "wof:placetype":"locality"
},
  "geometry": {"coordinates":[26.1272,53.4598],"type":"Point"}
}