{
  "type": "Feature",
  "properties": {
    "gn:admin1_code":"6.0",
    "gn:asciiname":"Gireyevichi",
    "gn:country_code":"BY",
    "gn:dem":171,
    "gn:feature_class":"P",
    "gn:feature_code":"PPL",
    "gn:name":"Gireyevichi",
    "gn:population":0,
    "gn:timezone":"Europe/Minsk",
    "iso:country":"BY",
    "name:rus_x_preferred":[
        "\u0413\u0438\u0440\u0435\u0435\u0432\u0438\u0447\u0438"
    ],
    "wof:name":"Gireyevichi",
    "wof:placetype":"locality"
},
  "geometry": {"coordinates":[31.9032,53.5474],"type":"Point"}
}