{
  "type": "Feature",
  "properties": {
    "gn:admin1_code":"6.0",
    "gn:asciiname":"Pil'shychy",
    "gn:country_code":"BY",
    "gn:dem":155,
    "gn:feature_class":"P",
    "gn:feature_code":"PPL",
    "gn:name":"Pil\u2019shychy",
    "gn:population":0,
    "gn:timezone":"Europe/Minsk",
    "iso:country":"BY",
    "name:bel_x_preferred":[
        "\u041f\u0456\u043b\u044c\u0448\u044b\u0447\u044b"
    ],
    "name:rus_x_preferred":[
        "Pil\u2019shichi"
    ],
    "name:und_x_variant":[
        "Pil\u2019shychy",
        "Pil\u2019shchichi"
    ],
    "wof:name":"Pil'shychy",
    "wof:placetype":"locality"
},
  "geometry": {"coordinates":[29.7525,53.7848],"type":"Point"}
}