{
  "type": "Feature",
  "properties": {
    "gn:admin1_code":"5.0",
    "gn:asciiname":"Pukhovshchina",
    "gn:country_code":"BY",
    "gn:dem":182,
    "gn:feature_class":"P",
    "gn:feature_code":"PPL",
    "gn:name":"Pukhovshchina",
    "gn:population":0,
    "gn:timezone":"Europe/Minsk",
    "iso:country":"BY",
    "name:rus_x_preferred":[
        "\u041f\u0443\u0445\u043e\u0432\u0449\u0438\u043d\u0430"
    ],
    "wof:name":"Pukhovshchina",
    "wof:placetype":"locality"
},
  "geometry": {"coordinates":[26.9897,53.4918],"type":"Point"}
}