{
  "type": "Feature",
  "properties": {
    "gn:admin1_code":"2.0",
    "gn:asciiname":"Seliba",
    "gn:country_code":"BY",
    "gn:dem":142,
    "gn:feature_class":"P",
    "gn:feature_code":"PPL",
    "gn:name":"Seliba",
    "gn:population":0,
    "gn:timezone":"Europe/Minsk",
    "iso:country":"BY",
    "name:rus_x_preferred":[
        "\u0421\u0435\u043b\u0438\u0431\u0430"
    ],
    "wof:name":"Seliba",
    "wof:placetype":"locality"
},
  "geometry": {"coordinates":[29.4966,52.9013],"type":"Point"}
}