{
  "type": "Feature",
  "properties": {
    "gn:admin1_code":"6.0",
    "gn:asciiname":"Voskhod",
    "gn:country_code":"BY",
    "gn:dem":170,
    "gn:feature_class":"P",
    "gn:feature_code":"PPL",
    "gn:name":"Voskhod",
    "gn:population":0,
    "gn:timezone":"Europe/Minsk",
    "iso:country":"BY",
    "name:rus_x_preferred":[
        "\u0412\u043e\u0441\u0445\u043e\u0434"
    ],
    "wof:name":"Voskhod",
    "wof:placetype":"locality"
},
  "geometry": {"coordinates":[31.3935,53.3145],"type":"Point"}
}