{
  "type": "Feature",
  "properties": {
    "gn:admin1_code":"7.0",
    "gn:asciiname":"Teleshi",
    "gn:country_code":"BY",
    "gn:dem":174,
    "gn:feature_class":"P",
    "gn:feature_code":"PPL",
    "gn:name":"Teleshi",
    "gn:population":0,
    "gn:timezone":"Europe/Minsk",
    "iso:country":"BY",
    "name:rus_x_preferred":[
        "\u0422\u0435\u043b\u0435\u0448\u0438"
    ],
    "wof:name":"Teleshi",
    "wof:placetype":"locality"
},
  "geometry": {"coordinates":[28.3168,55.2707],"type":"Point"}
}