{
  "type": "Feature",
  "properties": {
    "gn:admin1_code":"5.0",
    "gn:asciiname":"Pnivoda",
    "gn:country_code":"BY",
    "gn:dem":182,
    "gn:feature_class":"P",
    "gn:feature_code":"PPL",
    "gn:name":"Pnivoda",
    "gn:population":0,
    "gn:timezone":"Europe/Minsk",
    "iso:country":"BY",
    "name:rus_x_preferred":[
        "\u041f\u043d\u0438\u0432\u043e\u0434\u0430"
    ],
    "wof:name":"Pnivoda",
    "wof:placetype":"locality"
},
  "geometry": {"coordinates":[26.8736,53.2068],"type":"Point"}
}