{
  "type": "Feature",
  "properties": {
    "gn:admin1_code":"5.0",
    "gn:asciiname":"Lipniki",
    "gn:country_code":"BY",
    "gn:dem":189,
    "gn:feature_class":"P",
    "gn:feature_code":"PPL",
    "gn:name":"Lipniki",
    "gn:population":0,
    "gn:timezone":"Europe/Minsk",
    "iso:country":"BY",
    "name:bel_x_preferred":[
        "\u041b\u0456\u043f\u043d\u0456\u043a\u0456"
    ],
    "name:fra_x_preferred":[
        "Lipniki"
    ],
    "name:lit_x_preferred":[
        "Lipnikai"
    ],
    "name:pol_x_preferred":[
        "Lipniki"
    ],
    "name:rus_x_preferred":[
        "\u041b\u0438\u043f\u043d\u0438\u043a\u0438"
    ],
    "name:ukr_x_preferred":[
        "\u041b\u0456\u043f\u043d\u0438\u043a\u0438"
    ],
    "wof:name":"Lipniki",
    "wof:placetype":"locality"
},
  "geometry": {"coordinates":[27.945,54.033],"type":"Point"}
}