{
  "type": "Feature",
  "properties": {
    "gn:admin1_code":"7.0",
    "gn:asciiname":"Osinovka",
    "gn:country_code":"BY",
    "gn:dem":207,
    "gn:feature_class":"P",
    "gn:feature_code":"PPL",
    "gn:name":"Osinovka",
    "gn:population":0,
    "gn:timezone":"Europe/Minsk",
    "iso:country":"BY",
    "name:ceb_x_preferred":[
        "Osinovka"
    ],
    "name:lav_x_preferred":[
        "Osinovka"
    ],
    "name:swe_x_preferred":[
        "Osinovka"
    ],
    "wof:name":"Osinovka",
    "wof:placetype":"locality"
},
  "geometry": {"coordinates":[30.19056,55.74056],"type":"Point"}
}