{
  "type": "Feature",
  "properties": {
    "gn:admin1_code":"7.0",
    "gn:asciiname":"Mishukovo",
    "gn:country_code":"BY",
    "gn:dem":173,
    "gn:feature_class":"P",
    "gn:feature_code":"PPL",
    "gn:name":"Mishukovo",
    "gn:population":0,
    "gn:timezone":"Europe/Minsk",
    "iso:country":"BY",
    "name:rus_x_preferred":[
        "\u041c\u0438\u0448\u0443\u043a\u043e\u0432\u043e"
    ],
    "name:und_x_variant":[
        "Mishchukovo"
    ],
    "wof:name":"Mishukovo",
    "wof:placetype":"locality"
},
  "geometry": {"coordinates":[30.0696,54.8086],"type":"Point"}
}