{
  "type": "Feature",
  "properties": {
    "gn:admin1_code":"1.0",
    "gn:asciiname":"Lanskaya",
    "gn:country_code":"BY",
    "gn:dem":160,
    "gn:feature_class":"P",
    "gn:feature_code":"PPL",
    "gn:name":"Lanskaya",
    "gn:population":0,
    "gn:timezone":"Europe/Minsk",
    "iso:country":"BY",
    "name:rus_x_preferred":[
        "\u041b\u0430\u043d\u0441\u043a\u0430\u044f"
    ],
    "wof:name":"Lanskaya",
    "wof:placetype":"locality"
},
  "geometry": {"coordinates":[23.9476,51.6932],"type":"Point"}
}