{
  "type": "Feature",
  "properties": {
    "gn:admin1_code":"3.0",
    "gn:asciiname":"Aleksichi",
    "gn:country_code":"BY",
    "gn:dem":136,
    "gn:feature_class":"P",
    "gn:feature_code":"PPL",
    "gn:name":"Aleksichi",
    "gn:population":0,
    "gn:timezone":"Europe/Minsk",
    "iso:country":"BY",
    "name:bel_x_preferred":[
        "Alyeksichy"
    ],
    "name:bel_x_variant":[
        "\u0410\u043b\u0435\u043a\u0441\u0456\u0447\u044b"
    ],
    "name:rus_x_preferred":[
        "\u0410\u043b\u0435\u043a\u0441\u0438\u0447\u0438"
    ],
    "wof:name":"Aleksichi",
    "wof:placetype":"locality"
},
  "geometry": {"coordinates":[24.9225,53.26300000000001],"type":"Point"}
}