{
  "type": "Feature",
  "properties": {
    "gn:admin1_code":"7.0",
    "gn:asciiname":"Zabor'ye",
    "gn:country_code":"BY",
    "gn:dem":202,
    "gn:feature_class":"P",
    "gn:feature_code":"PPL",
    "gn:name":"Zabor\u2019ye",
    "gn:population":0,
    "gn:timezone":"Europe/Minsk",
    "iso:country":"BY",
    "name:rus_x_preferred":[
        "\u0417\u0430\u0431\u043e\u0440\u044c\u0435"
    ],
    "name:und_x_variant":[
        "Zabor\u2019ye"
    ],
    "wof:name":"Zabor'ye",
    "wof:placetype":"locality"
},
  "geometry": {"coordinates":[27.8995,54.7408],"type":"Point"}
}