{
  "type": "Feature",
  "properties": {
    "gn:admin1_code":"6.0",
    "gn:asciiname":"Podzamsha",
    "gn:country_code":"BY",
    "gn:dem":139,
    "gn:feature_class":"P",
    "gn:feature_code":"PPL",
    "gn:name":"Podzamsha",
    "gn:population":0,
    "gn:timezone":"Europe/Minsk",
    "iso:country":"BY",
    "name:rus_x_preferred":[
        "\u041f\u043e\u0434\u0437\u0430\u043c\u0448\u0430"
    ],
    "wof:name":"Podzamsha",
    "wof:placetype":"locality"
},
  "geometry": {"coordinates":[28.689,52.8806],"type":"Point"}
}