{
  "type": "Feature",
  "properties": {
    "gn:admin1_code":"3.0",
    "gn:asciiname":"Pyatkovshchizna",
    "gn:country_code":"BY",
    "gn:dem":148,
    "gn:feature_class":"P",
    "gn:feature_code":"PPL",
    "gn:name":"Pyatkovshchizna",
    "gn:population":0,
    "gn:timezone":"Europe/Minsk",
    "iso:country":"BY",
    "name:rus_x_preferred":[
        "\u041f\u044f\u0442\u0438\u043a\u043e\u0432\u0449\u0438\u0437\u043d\u0430"
    ],
    "name:und_x_variant":[
        "Pyatkovshchina"
    ],
    "wof:name":"Pyatkovshchizna",
    "wof:placetype":"locality"
},
  "geometry": {"coordinates":[25.206,54.0539],"type":"Point"}
}