{
  "type": "Feature",
  "properties": {
    "gn:admin1_code":"6.0",
    "gn:asciiname":"Zasozh'ye",
    "gn:country_code":"BY",
    "gn:dem":154,
    "gn:feature_class":"P",
    "gn:feature_code":"PPL",
    "gn:name":"Zasozh\u2019ye",
    "gn:population":0,
    "gn:timezone":"Europe/Minsk",
    "iso:country":"BY",
    "name:rus_x_preferred":[
        "\u0417\u0430\u0441\u043e\u0436\u044c\u0435"
    ],
    "name:und_x_variant":[
        "Zasozh\u2019ye"
    ],
    "wof:name":"Zasozh'ye",
    "wof:placetype":"locality"
},
  "geometry": {"coordinates":[31.8843,53.9826],"type":"Point"}
}