{
  "type": "Feature",
  "properties": {
    "gn:admin1_code":"1.0",
    "gn:asciiname":"Yasenets",
    "gn:country_code":"BY",
    "gn:dem":167,
    "gn:feature_class":"P",
    "gn:feature_code":"PPL",
    "gn:name":"Yasenets",
    "gn:population":0,
    "gn:timezone":"Europe/Minsk",
    "iso:country":"BY",
    "name:rus_x_preferred":[
        "\u042f\u0441\u0435\u043d\u0435\u0446"
    ],
    "name:und_x_variant":[
        "Jasieniec",
        "Yasenets"
    ],
    "wof:name":"Yasenets",
    "wof:placetype":"locality"
},
  "geometry": {"coordinates":[26.649,52.8179],"type":"Point"}
}