{
  "type": "Feature",
  "properties": {
    "gn:admin1_code":"2.0",
    "gn:asciiname":"Fashchevka",
    "gn:country_code":"BY",
    "gn:dem":132,
    "gn:feature_class":"P",
    "gn:feature_code":"PPL",
    "gn:name":"Fashch\u00ebvka",
    "gn:population":0,
    "gn:timezone":"Europe/Minsk",
    "iso:country":"BY",
    "name:rus_x_preferred":[
        "\u0424\u0430\u0449\u0451\u0432\u043a\u0430"
    ],
    "name:und_x_variant":[
        "Fashch\u00ebvka"
    ],
    "wof:name":"Fashchevka",
    "wof:placetype":"locality"
},
  "geometry": {"coordinates":[30.5806,52.5121],"type":"Point"}
}