{
  "type": "Feature",
  "properties": {
    "gn:admin1_code":"3.0",
    "gn:asciiname":"Poludovshchina",
    "gn:country_code":"BY",
    "gn:dem":184,
    "gn:feature_class":"P",
    "gn:feature_code":"PPL",
    "gn:name":"Poludovshchina",
    "gn:population":0,
    "gn:timezone":"Europe/Minsk",
    "iso:country":"BY",
    "name:rus_x_preferred":[
        "\u041f\u043e\u043b\u0443\u0434\u043e\u0432\u0449\u0438\u043d\u0430"
    ],
    "wof:name":"Poludovshchina",
    "wof:placetype":"locality"
},
  "geometry": {"coordinates":[25.9626,54.1398],"type":"Point"}
}