{
  "type": "Feature",
  "properties": {
    "gn:admin1_code":"7.0",
    "gn:asciiname":"Staroye Grudinovo",
    "gn:country_code":"BY",
    "gn:dem":114,
    "gn:feature_class":"P",
    "gn:feature_code":"PPL",
    "gn:name":"Staroye Grudinovo",
    "gn:population":0,
    "gn:timezone":"Europe/Minsk",
    "iso:country":"BY",
    "name:rus_x_preferred":[
        "\u0421\u0442\u0430\u0440\u043e\u0435 \u0413\u0440\u0443\u0434\u0438\u043d\u043e\u0432\u043e"
    ],
    "wof:name":"Staroye Grudinovo",
    "wof:placetype":"locality"
},
  "geometry": {"coordinates":[27.8249,55.809],"type":"Point"}
}