{
  "type": "Feature",
  "properties": {
    "gn:admin1_code":"6.0",
    "gn:asciiname":"Zor'ka",
    "gn:country_code":"BY",
    "gn:dem":145,
    "gn:feature_class":"P",
    "gn:feature_code":"PPL",
    "gn:name":"Zor\u2019ka",
    "gn:population":0,
    "gn:timezone":"Europe/Minsk",
    "iso:country":"BY",
    "name:rus_x_preferred":[
        "\u0417\u043e\u0440\u044c\u043a\u0430"
    ],
    "name:und_x_variant":[
        "Zor\u2019ka"
    ],
    "wof:name":"Zor'ka",
    "wof:placetype":"locality"
},
  "geometry": {"coordinates":[28.4616,52.7158],"type":"Point"}
}