{
  "type": "Feature",
  "properties": {
    "gn:admin1_code":"5.0",
    "gn:asciiname":"Navry",
    "gn:country_code":"BY",
    "gn:dem":173,
    "gn:feature_class":"P",
    "gn:feature_code":"PPL",
    "gn:name":"Navry",
    "gn:population":0,
    "gn:timezone":"Europe/Minsk",
    "iso:country":"BY",
    "name:rus_x_preferred":[
        "\u041d\u0430\u0432\u0440\u044b"
    ],
    "name:und_x_variant":[
        "Nawry",
        "Navry"
    ],
    "wof:name":"Navry",
    "wof:placetype":"locality"
},
  "geometry": {"coordinates":[27.1305,54.7597],"type":"Point"}
}