{
  "type": "Feature",
  "properties": {
    "gn:admin1_code":"3.0",
    "gn:asciiname":"Lobzovo",
    "gn:country_code":"BY",
    "gn:dem":127,
    "gn:feature_class":"P",
    "gn:feature_code":"PPL",
    "gn:name":"Lobzovo",
    "gn:population":0,
    "gn:timezone":"Europe/Minsk",
    "iso:country":"BY",
    "name:bel_x_preferred":[
        "Labzova"
    ],
    "name:bel_x_variant":[
        "\u041b\u0430\u0431\u0437\u043e\u0432\u0430"
    ],
    "name:rus_x_preferred":[
        "\u041b\u043e\u0431\u0437\u043e\u0432\u043e"
    ],
    "wof:name":"Lobzovo",
    "wof:placetype":"locality"
},
  "geometry": {"coordinates":[24.9804,53.2671],"type":"Point"}
}