{
  "type": "Feature",
  "properties": {
    "gn:admin1_code":"1.0",
    "gn:asciiname":"Bastyn'",
    "gn:country_code":"BY",
    "gn:dem":140,
    "gn:feature_class":"P",
    "gn:feature_code":"PPL",
    "gn:name":"Bastyn\u2019",
    "gn:population":0,
    "gn:timezone":"Europe/Minsk",
    "iso:country":"BY",
    "name:bel_x_preferred":[
        "\u0411\u0430\u0441\u0442\u044b\u043d\u044c"
    ],
    "name:eng_x_preferred":[
        "Bostyn'"
    ],
    "name:rus_x_preferred":[
        "\u0411\u043e\u0441\u0442\u044b\u043d\u044c"
    ],
    "name:rus_x_variant":[
        "Bostyn\u2019"
    ],
    "name:und_x_variant":[
        "Bostyng",
        "Bastyn\u2019"
    ],
    "wof:name":"Bastyn'",
    "wof:placetype":"locality"
},
  "geometry": {"coordinates":[26.7565,52.3916],"type":"Point"}
}