{
  "type": "Feature",
  "properties": {
    "gn:admin1_code":"0.0",
    "gn:asciiname":"Belundi",
    "gn:country_code":"BY",
    "gn:dem":135,
    "gn:feature_class":"P",
    "gn:feature_code":"PPL",
    "gn:name":"Belundi",
    "gn:population":0,
    "gn:timezone":"Europe/Minsk",
    "iso:country":"BY",
    "name:rus_x_preferred":[
        "\u0411\u0435\u043b\u0443\u043d\u0434\u0438"
    ],
    "name:und_x_variant":[
        "Byalundze",
        "Belundzi",
        "Belundi"
    ],
    "wof:name":"Belundi",
    "wof:placetype":"locality"
},
  "geometry": {"coordinates":[25.52823,53.91956999999999],"type":"Point"}
}