{
  "type": "Feature",
  "properties": {
    "gn:admin1_code":"5.0",
    "gn:asciiname":"Goraviny",
    "gn:country_code":"BY",
    "gn:dem":211,
    "gn:feature_class":"P",
    "gn:feature_code":"PPL",
    "gn:name":"Goraviny",
    "gn:population":0,
    "gn:timezone":"Europe/Minsk",
    "iso:country":"BY",
    "name:rus_x_preferred":[
        "\u0413\u043e\u0440\u0430\u0432\u0438\u043d\u044b"
    ],
    "wof:name":"Goraviny",
    "wof:placetype":"locality"
},
  "geometry": {"coordinates":[26.8728,54.2769],"type":"Point"}
}