{
  "type": "Feature",
  "properties": {
    "gn:admin1_code":"6.0",
    "gn:asciiname":"Poblin",
    "gn:country_code":"BY",
    "gn:dem":138,
    "gn:feature_class":"P",
    "gn:feature_code":"PPL",
    "gn:name":"Poblin",
    "gn:population":0,
    "gn:timezone":"Europe/Minsk",
    "iso:country":"BY",
    "name:rus_x_preferred":[
        "\u041f\u043e\u0431\u043b\u0438\u043d"
    ],
    "name:und_x_variant":[
        "Dublin",
        "Pablin"
    ],
    "wof:name":"Poblin",
    "wof:placetype":"locality"
},
  "geometry": {"coordinates":[28.8072,52.8811],"type":"Point"}
}