{
  "type": "Feature",
  "properties": {
    "gn:admin1_code":"3.0",
    "gn:asciiname":"Bitonyaty",
    "gn:country_code":"BY",
    "gn:dem":184,
    "gn:feature_class":"P",
    "gn:feature_code":"PPL",
    "gn:name":"Bitonyaty",
    "gn:population":0,
    "gn:timezone":"Europe/Minsk",
    "iso:country":"BY",
    "name:rus_x_preferred":[
        "\u0411\u0438\u0442\u043e\u043d\u044f\u0442\u044b"
    ],
    "name:und_x_variant":[
        "Bicieni\u0119ta",
        "Bitsenenta",
        "Bitonyaty"
    ],
    "wof:name":"Bitonyaty",
    "wof:placetype":"locality"
},
  "geometry": {"coordinates":[26.2092,54.2554],"type":"Point"}
}