{
  "type": "Feature",
  "properties": {
    "gn:admin1_code":"5.0",
    "gn:asciiname":"Gritskovichi",
    "gn:country_code":"BY",
    "gn:dem":187,
    "gn:feature_class":"P",
    "gn:feature_code":"PPL",
    "gn:name":"Gritskovichi",
    "gn:population":0,
    "gn:timezone":"Europe/Minsk",
    "iso:country":"BY",
    "name:rus_x_preferred":[
        "\u0413\u0440\u0438\u0446\u043a\u043e\u0432\u0438\u0447\u0438"
    ],
    "wof:name":"Gritskovichi",
    "wof:placetype":"locality"
},
  "geometry": {"coordinates":[28.9402,54.5811],"type":"Point"}
}