{
  "type": "Feature",
  "properties": {
    "gn:admin1_code":"6.0",
    "gn:asciiname":"Lyubonichy",
    "gn:country_code":"BY",
    "gn:dem":151,
    "gn:feature_class":"P",
    "gn:feature_code":"PPL",
    "gn:name":"Lyubonichy",
    "gn:population":0,
    "gn:timezone":"Europe/Minsk",
    "iso:country":"BY",
    "name:bel_x_preferred":[
        "\u041b\u044e\u0431\u043e\u043d\u0456\u0447\u044b"
    ],
    "name:eng_x_preferred":[
        "Lyubonichi"
    ],
    "name:rus_x_preferred":[
        "\u041b\u044e\u0431\u043e\u043d\u0438\u0447\u0438"
    ],
    "name:und_x_variant":[
        "Lyubonichy"
    ],
    "wof:name":"Lyubonichy",
    "wof:placetype":"locality"
},
  "geometry": {"coordinates":[29.241,53.2767],"type":"Point"}
}