{
  "type": "Feature",
  "properties": {
    "gn:admin1_code":"1.0",
    "gn:asciiname":"Smol'niki",
    "gn:country_code":"BY",
    "gn:dem":141,
    "gn:feature_class":"P",
    "gn:feature_code":"PPL",
    "gn:name":"Smol\u2019niki",
    "gn:population":0,
    "gn:timezone":"Europe/Minsk",
    "iso:country":"BY",
    "name:bel_x_preferred":[
        "\u0421\u043c\u043e\u043b\u044c\u043d\u0456\u043a\u0456"
    ],
    "name:bel_x_variant":[
        "Smol\u2019niki"
    ],
    "name:und_x_variant":[
        "Smol\u2019niki"
    ],
    "wof:name":"Smol'niki",
    "wof:placetype":"locality"
},
  "geometry": {"coordinates":[25.3286,52.0125],"type":"Point"}
}