{
  "type": "Feature",
  "properties": {
    "gn:admin1_code":"2.0",
    "gn:asciiname":"Korma",
    "gn:country_code":"BY",
    "gn:dem":136,
    "gn:feature_class":"P",
    "gn:feature_code":"PPL",
    "gn:name":"Korma",
    "gn:population":0,
    "gn:timezone":"Europe/Minsk",
    "iso:country":"BY",
    "name:rus_x_preferred":[
        "\u041a\u043e\u0440\u043c\u0430"
    ],
    "wof:name":"Korma",
    "wof:placetype":"locality"
},
  "geometry": {"coordinates":[29.631,52.2996],"type":"Point"}
}