{
  "type": "Feature",
  "properties": {
    "gn:admin1_code":"7.0",
    "gn:asciiname":"Skavyshki",
    "gn:country_code":"BY",
    "gn:dem":214,
    "gn:feature_class":"P",
    "gn:feature_code":"PPL",
    "gn:name":"Skavyshki",
    "gn:population":0,
    "gn:timezone":"Europe/Minsk",
    "iso:country":"BY",
    "name:rus_x_preferred":[
        "\u0421\u043a\u0430\u0432\u044b\u0448\u043a\u0438"
    ],
    "wof:name":"Skavyshki",
    "wof:placetype":"locality"
},
  "geometry": {"coordinates":[29.7733,54.4827],"type":"Point"}
}