{
  "type": "Feature",
  "properties": {
    "gn:admin1_code":"5.0",
    "gn:asciiname":"Protasovshchina",
    "gn:country_code":"BY",
    "gn:dem":172,
    "gn:feature_class":"P",
    "gn:feature_code":"PPL",
    "gn:name":"Protasovshchina",
    "gn:population":0,
    "gn:timezone":"Europe/Minsk",
    "iso:country":"BY",
    "name:rus_x_preferred":[
        "\u041f\u0440\u043e\u0442\u0430\u0441\u043e\u0432\u0449\u0438\u043d\u0430"
    ],
    "wof:name":"Protasovshchina",
    "wof:placetype":"locality"
},
  "geometry": {"coordinates":[27.7386,53.3723],"type":"Point"}
}