{
  "type": "Feature",
  "properties": {
    "gn:admin1_code":"5.0",
    "gn:asciiname":"Vinorovo",
    "gn:country_code":"BY",
    "gn:dem":153,
    "gn:feature_class":"P",
    "gn:feature_code":"PPL",
    "gn:name":"Vinorovo",
    "gn:population":0,
    "gn:timezone":"Europe/Minsk",
    "iso:country":"BY",
    "name:rus_x_preferred":[
        "\u0412\u0438\u043d\u043e\u0440\u043e\u0432\u043e"
    ],
    "wof:name":"Vinorovo",
    "wof:placetype":"locality"
},
  "geometry": {"coordinates":[28.9325,53.7066],"type":"Point"}
}