{
  "type": "Feature",
  "properties": {
    "gn:admin1_code":"0.0",
    "gn:asciiname":"Khutor Kureni",
    "gn:cc2":"BY",
    "gn:country_code":"BY",
    "gn:dem":109,
    "gn:feature_class":"P",
    "gn:feature_code":"PPL",
    "gn:name":"Khutor Kureni",
    "gn:population":0,
    "gn:timezone":"Europe/Minsk",
    "iso:country":"BY",
    "name:und_x_variant":[
        "Kureni",
        "Khutor Kureni"
    ],
    "wof:name":"Khutor Kureni",
    "wof:placetype":"locality"
},
  "geometry": {"coordinates":[29.85,51.51667],"type":"Point"}
}