{
  "type": "Feature",
  "properties": {
    "gn:admin1_code":"5.0",
    "gn:asciiname":"Domanovo",
    "gn:country_code":"BY",
    "gn:dem":151,
    "gn:feature_class":"P",
    "gn:feature_code":"PPL",
    "gn:name":"Domanovo",
    "gn:population":0,
    "gn:timezone":"Europe/Minsk",
    "iso:country":"BY",
    "name:rus_x_preferred":[
        "\u0414\u043e\u043c\u0430\u043d\u043e\u0432\u043e"
    ],
    "wof:name":"Domanovo",
    "wof:placetype":"locality"
},
  "geometry": {"coordinates":[26.8403,54.4258],"type":"Point"}
}