{
  "type": "Feature",
  "properties": {
    "gn:admin1_code":"3.0",
    "gn:asciiname":"Bocheshniki",
    "gn:country_code":"BY",
    "gn:dem":156,
    "gn:feature_class":"P",
    "gn:feature_code":"PPL",
    "gn:name":"Bocheshniki",
    "gn:population":0,
    "gn:timezone":"Europe/Minsk",
    "iso:country":"BY",
    "name:rus_x_preferred":[
        "\u0411\u043e\u0447\u0435\u0448\u043d\u0438\u043a\u0438"
    ],
    "wof:name":"Bocheshniki",
    "wof:placetype":"locality"
},
  "geometry": {"coordinates":[25.94327,53.98211],"type":"Point"}
}