{
  "type": "Feature",
  "properties": {
    "gn:admin1_code":"5.0",
    "gn:asciiname":"Kibuti",
    "gn:country_code":"BY",
    "gn:dem":262,
    "gn:feature_class":"P",
    "gn:feature_code":"PPL",
    "gn:name":"Kibuti",
    "gn:population":0,
    "gn:timezone":"Europe/Minsk",
    "iso:country":"BY",
    "name:rus_x_preferred":[
        "\u041a\u0438\u0431\u0443\u0442\u0438"
    ],
    "wof:name":"Kibuti",
    "wof:placetype":"locality"
},
  "geometry": {"coordinates":[26.602,54.1257],"type":"Point"}
}