{
  "type": "Feature",
  "properties": {
    "gn:admin1_code":"5.0",
    "gn:asciiname":"Novoye Zhit'ye",
    "gn:country_code":"BY",
    "gn:dem":163,
    "gn:feature_class":"P",
    "gn:feature_code":"PPL",
    "gn:name":"Novoye Zhit\u2019y\u00eb",
    "gn:population":0,
    "gn:timezone":"Europe/Minsk",
    "iso:country":"BY",
    "name:rus_x_preferred":[
        "\u041d\u043e\u0432\u043e\u0435 \u0416\u0438\u0442\u044c\u0451"
    ],
    "name:und_x_variant":[
        "Novoye Zhit\u2019y\u00eb"
    ],
    "wof:name":"Novoye Zhit'ye",
    "wof:placetype":"locality"
},
  "geometry": {"coordinates":[29.0817,53.6399],"type":"Point"}
}