{
  "type": "Feature",
  "properties": {
    "gn:admin1_code":"3.0",
    "gn:asciiname":"Savishki",
    "gn:country_code":"BY",
    "gn:dem":147,
    "gn:feature_class":"P",
    "gn:feature_code":"PPL",
    "gn:name":"Savishki",
    "gn:population":0,
    "gn:timezone":"Europe/Minsk",
    "iso:country":"BY",
    "name:rus_x_preferred":[
        "\u0421\u0430\u0432\u0438\u0448\u043a\u0438"
    ],
    "wof:name":"Savishki",
    "wof:placetype":"locality"
},
  "geometry": {"coordinates":[25.9992,54.8267],"type":"Point"}
}