{
  "type": "Feature",
  "properties": {
    "gn:admin1_code":"6.0",
    "gn:asciiname":"Vorod'kov Pervyy",
    "gn:country_code":"BY",
    "gn:dem":168,
    "gn:feature_class":"P",
    "gn:feature_code":"PPL",
    "gn:name":"Vorod\u2019kov Pervyy",
    "gn:population":0,
    "gn:timezone":"Europe/Minsk",
    "iso:country":"BY",
    "name:rus_x_preferred":[
        "\u0412\u043e\u0440\u043e\u0434\u044c\u043a\u043e\u0432 \u041f\u0435\u0440\u0432\u044b\u0439"
    ],
    "name:und_x_variant":[
        "Vorod\u2019kov Pervyy",
        "Vorod\u2019kovo Pervoye",
        "Vorod\u2019kovo"
    ],
    "wof:name":"Vorod'kov Pervyy",
    "wof:placetype":"locality"
},
  "geometry": {"coordinates":[31.4053,53.7664],"type":"Point"}
}