{
  "type": "Feature",
  "properties": {
    "gn:admin1_code":"5.0",
    "gn:asciiname":"Guta",
    "gn:country_code":"BY",
    "gn:dem":214,
    "gn:feature_class":"P",
    "gn:feature_code":"PPL",
    "gn:name":"Guta",
    "gn:population":0,
    "gn:timezone":"Europe/Minsk",
    "iso:country":"BY",
    "name:rus_x_preferred":[
        "\u0413\u0443\u0442\u0430"
    ],
    "wof:name":"Guta",
    "wof:placetype":"locality"
},
  "geometry": {"coordinates":[26.2128,54.1927],"type":"Point"}
}