{
  "type": "Feature",
  "properties": {
    "gn:admin1_code":"7.0",
    "gn:asciiname":"Zazheche",
    "gn:country_code":"BY",
    "gn:dem":161,
    "gn:feature_class":"P",
    "gn:feature_code":"PPL",
    "gn:name":"Zazheche",
    "gn:population":0,
    "gn:timezone":"Europe/Minsk",
    "iso:country":"BY",
    "name:rus_x_preferred":[
        "\u0417\u0430\u0440\u0435\u0447\u044c\u0435"
    ],
    "name:und_x_variant":[
        "Zarzecze",
        "Zazheche",
        "Zarech\u2019ye"
    ],
    "wof:name":"Zazheche",
    "wof:placetype":"locality"
},
  "geometry": {"coordinates":[28.0565,55.3369],"type":"Point"}
}