{
  "type": "Feature",
  "properties": {
    "gn:admin1_code":"5.0",
    "gn:asciiname":"Podozernoye",
    "gn:country_code":"BY",
    "gn:dem":163,
    "gn:feature_class":"P",
    "gn:feature_code":"PPL",
    "gn:name":"Podoz\u00ebrnoye",
    "gn:population":0,
    "gn:timezone":"Europe/Minsk",
    "iso:country":"BY",
    "name:rus_x_preferred":[
        "\u041f\u043e\u0434\u043e\u0437\u0451\u0440\u043d\u043e\u0435"
    ],
    "name:und_x_variant":[
        "Podoz\u00ebrnoye"
    ],
    "wof:name":"Podozernoye",
    "wof:placetype":"locality"
},
  "geometry": {"coordinates":[27.1604,52.902],"type":"Point"}
}