{
  "type": "Feature",
  "properties": {
    "gn:admin1_code":"7.0",
    "gn:asciiname":"Stanyuki",
    "gn:country_code":"BY",
    "gn:dem":214,
    "gn:feature_class":"P",
    "gn:feature_code":"PPL",
    "gn:name":"Stanyuki",
    "gn:population":0,
    "gn:timezone":"Europe/Minsk",
    "iso:country":"BY",
    "name:rus_x_preferred":[
        "\u0421\u0442\u0430\u043d\u044e\u043a\u0438"
    ],
    "wof:name":"Stanyuki",
    "wof:placetype":"locality"
},
  "geometry": {"coordinates":[29.661,54.7331],"type":"Point"}
}