{
  "type": "Feature",
  "properties": {
    "gn:admin1_code":"6.0",
    "gn:asciiname":"Bynovo",
    "gn:country_code":"BY",
    "gn:dem":178,
    "gn:feature_class":"P",
    "gn:feature_code":"PPL",
    "gn:name":"Bynovo",
    "gn:population":0,
    "gn:timezone":"Europe/Minsk",
    "iso:country":"BY",
    "name:eng_x_preferred":[
        "Bynovo"
    ],
    "name:rus_x_preferred":[
        "\u0411\u044b\u043d\u043e\u0432\u043e"
    ],
    "wof:name":"Bynovo",
    "wof:placetype":"locality"
},
  "geometry": {"coordinates":[31.1697,53.8656],"type":"Point"}
}