{
  "type": "Feature",
  "properties": {
    "gn:admin1_code":"1.0",
    "gn:asciiname":"Nizhneye Chernikhovo",
    "gn:country_code":"BY",
    "gn:dem":194,
    "gn:feature_class":"P",
    "gn:feature_code":"PPL",
    "gn:name":"Nizhneye Chernikhovo",
    "gn:population":0,
    "gn:timezone":"Europe/Minsk",
    "iso:country":"BY",
    "name:rus_x_preferred":[
        "\u041d\u0438\u0436\u043d\u0435\u0435 \u0427\u0435\u0440\u043d\u0438\u0445\u043e\u0432\u043e"
    ],
    "wof:name":"Nizhneye Chernikhovo",
    "wof:placetype":"locality"
},
  "geometry": {"coordinates":[26.2849,53.2447],"type":"Point"}
}