{
  "type": "Feature",
  "properties": {
    "gn:admin1_code":"1.0",
    "gn:asciiname":"Zhabchitsy",
    "gn:country_code":"BY",
    "gn:dem":145,
    "gn:feature_class":"P",
    "gn:feature_code":"PPL",
    "gn:name":"Zhabchitsy",
    "gn:population":0,
    "gn:timezone":"Europe/Minsk",
    "iso:country":"BY",
    "name:rus_x_preferred":[
        "\u0416\u0430\u0431\u0447\u0438\u0446\u044b"
    ],
    "name:und_x_variant":[
        "Zhabchitse",
        "Zhabchitsy"
    ],
    "wof:name":"Zhabchitsy",
    "wof:placetype":"locality"
},
  "geometry": {"coordinates":[25.9727,52.1315],"type":"Point"}
}