{
  "type": "Feature",
  "properties": {
    "gn:admin1_code":"5.0",
    "gn:asciiname":"Selivonovka",
    "gn:country_code":"BY",
    "gn:dem":171,
    "gn:feature_class":"P",
    "gn:feature_code":"PPL",
    "gn:name":"Selivonovka",
    "gn:population":0,
    "gn:timezone":"Europe/Minsk",
    "iso:country":"BY",
    "name:rus_x_preferred":[
        "\u0421\u0435\u043b\u0438\u0432\u043e\u043d\u043e\u0432\u043a\u0430"
    ],
    "wof:name":"Selivonovka",
    "wof:placetype":"locality"
},
  "geometry": {"coordinates":[26.915,54.2889],"type":"Point"}
}