{
  "type": "Feature",
  "properties": {
    "gn:admin1_code":"7.0",
    "gn:asciiname":"Subbotovo",
    "gn:country_code":"BY",
    "gn:dem":189,
    "gn:feature_class":"P",
    "gn:feature_code":"PPL",
    "gn:name":"Subbotovo",
    "gn:population":0,
    "gn:timezone":"Europe/Minsk",
    "iso:country":"BY",
    "name:rus_x_preferred":[
        "\u0421\u0443\u0431\u0431\u043e\u0442\u043e\u0432\u043e"
    ],
    "wof:name":"Subbotovo",
    "wof:placetype":"locality"
},
  "geometry": {"coordinates":[27.7673,55.0606],"type":"Point"}
}