{
  "type": "Feature",
  "properties": {
    "gn:admin1_code":"3.0",
    "gn:asciiname":"Zadvoryane",
    "gn:country_code":"BY",
    "gn:dem":171,
    "gn:feature_class":"P",
    "gn:feature_code":"PPL",
    "gn:name":"Zadvoryane",
    "gn:population":0,
    "gn:timezone":"Europe/Minsk",
    "iso:country":"BY",
    "name:rus_x_preferred":[
        "\u0417\u0430\u0434\u0432\u043e\u0440\u044f\u043d\u0435"
    ],
    "wof:name":"Zadvoryane",
    "wof:placetype":"locality"
},
  "geometry": {"coordinates":[24.5337,52.9346],"type":"Point"}
}