{
  "type": "Feature",
  "properties": {
    "gn:admin1_code":"1.0",
    "gn:asciiname":"Pridatki",
    "gn:country_code":"BY",
    "gn:dem":182,
    "gn:feature_class":"P",
    "gn:feature_code":"PPL",
    "gn:name":"Pridatki",
    "gn:population":0,
    "gn:timezone":"Europe/Minsk",
    "iso:country":"BY",
    "name:rus_x_preferred":[
        "\u041f\u0440\u0438\u0434\u0430\u0442\u043a\u0438"
    ],
    "wof:name":"Pridatki",
    "wof:placetype":"locality"
},
  "geometry": {"coordinates":[26.1771,53.2142],"type":"Point"}
}