{
  "type": "Feature",
  "properties": {
    "gn:admin1_code":"6.0",
    "gn:asciiname":"Kamen'",
    "gn:country_code":"BY",
    "gn:dem":183,
    "gn:feature_class":"P",
    "gn:feature_code":"PPL",
    "gn:name":"Kamen\u2019",
    "gn:population":0,
    "gn:timezone":"Europe/Minsk",
    "iso:country":"BY",
    "name:rus_x_preferred":[
        "\u041a\u0430\u043c\u0435\u043d\u044c"
    ],
    "name:und_x_variant":[
        "Kamen\u2019"
    ],
    "wof:name":"Kamen'",
    "wof:placetype":"locality"
},
  "geometry": {"coordinates":[32.1785,53.4129],"type":"Point"}
}