{
  "type": "Feature",
  "properties": {
    "gn:admin1_code":"7.0",
    "gn:asciiname":"Kruhlitsa",
    "gn:country_code":"BY",
    "gn:dem":152,
    "gn:feature_class":"P",
    "gn:feature_code":"PPL",
    "gn:name":"Kruhlitsa",
    "gn:population":0,
    "gn:timezone":"Europe/Minsk",
    "iso:country":"BY",
    "name:bel_x_preferred":[
        "\u041a\u0440\u0443\u0433\u043b\u0456\u0446\u0430"
    ],
    "name:und_x_variant":[
        "Kruglitsa"
    ],
    "wof:name":"Kruhlitsa",
    "wof:placetype":"locality"
},
  "geometry": {"coordinates":[29.3207,54.7773],"type":"Point"}
}