{
  "type": "Feature",
  "properties": {
    "gn:admin1_code":"5.0",
    "gn:asciiname":"Novyye Skorinichi",
    "gn:country_code":"BY",
    "gn:dem":217,
    "gn:feature_class":"P",
    "gn:feature_code":"PPL",
    "gn:name":"Novyye Skorinichi",
    "gn:population":0,
    "gn:timezone":"Europe/Minsk",
    "iso:country":"BY",
    "name:rus_x_preferred":[
        "\u041d\u043e\u0432\u044b\u0435 \u0421\u043a\u043e\u0440\u0438\u043d\u0438\u0447\u0438"
    ],
    "wof:name":"Novyye Skorinichi",
    "wof:placetype":"locality"
},
  "geometry": {"coordinates":[27.5054,53.8088],"type":"Point"}
}