{
  "type": "Feature",
  "properties": {
    "gn:admin1_code":"6.0",
    "gn:asciiname":"Barok",
    "gn:country_code":"BY",
    "gn:dem":164,
    "gn:feature_class":"P",
    "gn:feature_code":"PPL",
    "gn:name":"Barok",
    "gn:population":0,
    "gn:timezone":"Europe/Minsk",
    "iso:country":"BY",
    "name:rus_x_preferred":[
        "\u0411\u0430\u0440\u043e\u043a"
    ],
    "name:tgl_x_preferred":[
        "Barok"
    ],
    "name:und_x_variant":[
        "Borok"
    ],
    "wof:name":"Barok",
    "wof:placetype":"locality"
},
  "geometry": {"coordinates":[28.9263,53.0917],"type":"Point"}
}