{
  "type": "Feature",
  "properties": {
    "gn:admin1_code":"1.0",
    "gn:asciiname":"Postolovo",
    "gn:country_code":"BY",
    "gn:dem":149,
    "gn:feature_class":"P",
    "gn:feature_code":"PPL",
    "gn:name":"Postolovo",
    "gn:population":0,
    "gn:timezone":"Europe/Minsk",
    "iso:country":"BY",
    "name:rus_x_preferred":[
        "\u041f\u043e\u0441\u0442\u043e\u043b\u043e\u0432\u043e"
    ],
    "name:und_x_variant":[
        "Postoyalovo",
        "Postolovo"
    ],
    "wof:name":"Postolovo",
    "wof:placetype":"locality"
},
  "geometry": {"coordinates":[24.7657,52.4302],"type":"Point"}
}