{
  "type": "Feature",
  "properties": {
    "gn:admin1_code":"5.0",
    "gn:asciiname":"Rossokha",
    "gn:country_code":"BY",
    "gn:dem":210,
    "gn:feature_class":"P",
    "gn:feature_code":"PPL",
    "gn:name":"Rossokha",
    "gn:population":0,
    "gn:timezone":"Europe/Minsk",
    "iso:country":"BY",
    "name:rus_x_preferred":[
        "\u0420\u043e\u0441\u0441\u043e\u0445\u0430"
    ],
    "name:und_x_variant":[
        "Rassokha"
    ],
    "wof:name":"Rossokha",
    "wof:placetype":"locality"
},
  "geometry": {"coordinates":[27.6906,54.4428],"type":"Point"}
}