{
  "type": "Feature",
  "properties": {
    "gn:admin1_code":"1.0",
    "gn:asciiname":"Myslobozh",
    "gn:country_code":"BY",
    "gn:dem":183,
    "gn:feature_class":"P",
    "gn:feature_code":"PPL",
    "gn:name":"Myslobozh",
    "gn:population":0,
    "gn:timezone":"Europe/Minsk",
    "iso:country":"BY",
    "name:rus_x_preferred":[
        "\u041c\u044b\u0441\u043b\u043e\u0431\u043e\u0436"
    ],
    "name:und_x_variant":[
        "Mys\u0142oboje",
        "Myslobozh",
        "Mysloboye"
    ],
    "wof:name":"Myslobozh",
    "wof:placetype":"locality"
},
  "geometry": {"coordinates":[26.2527,52.9895],"type":"Point"}
}