{
  "type": "Feature",
  "properties": {
    "gn:admin1_code":"3.0",
    "gn:asciiname":"Kukenishki",
    "gn:country_code":"BY",
    "gn:dem":119,
    "gn:feature_class":"P",
    "gn:feature_code":"PPL",
    "gn:name":"Kukenishki",
    "gn:population":0,
    "gn:timezone":"Europe/Minsk",
    "iso:country":"BY",
    "name:rus_x_preferred":[
        "\u041a\u0443\u043a\u0435\u043d\u0438\u0448\u043a\u0438"
    ],
    "wof:name":"Kukenishki",
    "wof:placetype":"locality"
},
  "geometry": {"coordinates":[25.9557,54.8001],"type":"Point"}
}