{
  "type": "Feature",
  "properties": {
    "gn:country":"BY",
    "gn:fcode":"PPLA2",
    "gn:population":19135,
    "iso:country":"BY",
    "name:bel_x_preferred":[
        "\u041f\u0440\u0443\u0436\u0430\u043d\u044b"
    ],
    "name:bul_x_preferred":[
        "\u041f\u0440\u0443\u0436\u0430\u043d\u0438"
    ],
    "name:cat_x_preferred":[
        "Prujani"
    ],
    "name:ceb_x_preferred":[
        "Pruzhany"
    ],
    "name:ceb_x_variant":[
        "Pru\u017eany"
    ],
    "name:ces_x_preferred":[
        "Pru\u017eany"
    ],
    "name:che_x_preferred":[
        "\u041f\u0440\u0443\u0436\u0430\u043d\u044b"
    ],
    "name:cym_x_preferred":[
        "Pruzhany"
    ],
    "name:deu_x_preferred":[
        "Pruschany"
    ],
    "name:eng_x_preferred":[
        "Pruzhany"
    ],
    "name:eng_x_variant":[
        "Pru\u017eany"
    ],
    "name:est_x_preferred":[
        "Pru\u017eany"
    ],
    "name:fas_x_preferred":[
        "\u067e\u0631\u0648\u0698\u0627\u0646\u06cc"
    ],
    "name:fin_x_preferred":[
        "Pru\u017eany"
    ],
    "name:fra_x_preferred":[
        "Proujany"
    ],
    "name:frr_x_preferred":[
        "Pruschany"
    ],
    "name:heb_x_preferred":[
        "\u05e4\u05e8\u05d5\u05d6'\u05e0\u05d9"
    ],
    "name:hsb_x_preferred":[
        "Pru\u017eany"
    ],
    "name:hun_x_preferred":[
        "Pruzsani"
    ],
    "name:hye_x_preferred":[
        "\u054a\u0580\u0578\u0582\u056a\u0561\u0576\u056b"
    ],
    "name:ita_x_preferred":[
        "Pru\u017eany"
    ],
    "name:jpn_x_preferred":[
        "\u30d7\u30eb\u30b8\u30e3\u30cc\u30a4"
    ],
    "name:lav_x_preferred":[
        "Pru\u017eani"
    ],
    "name:lit_x_preferred":[
        "Pru\u017eanai"
    ],
    "name:nld_x_preferred":[
        "Pruzhany"
    ],
    "name:nld_x_variant":[
        "Pru\u017eany"
    ],
    "name:pol_x_preferred":[
        "Pru\u017cana"
    ],
    "name:por_x_preferred":[
        "Pruzhany"
    ],
    "name:ron_x_preferred":[
        "Pru\u017eany"
    ],
    "name:rus_x_preferred":[
        "\u041f\u0440\u0443\u0436\u0430\u043d\u044b"
    ],
    "name:sah_x_preferred":[
        "\u041f\u0440\u0443\u0436\u0430\u043d\u044b"
    ],
    "name:spa_x_preferred":[
        "Pruzhany"
    ],
    "name:srp_x_preferred":[
        "\u041f\u0440\u0443\u0436\u0430\u043d\u0438"
    ],
    "name:swe_x_preferred":[
        "Pruschany"
    ],
    "name:swe_x_variant":[
        "Pruzjany"
    ],
    "name:tat_x_preferred":[
        "\u041f\u0440\u0443\u0436\u0430\u043d\u044b"
    ],
    "name:udm_x_preferred":[
        "\u041f\u0440\u0443\u0436\u0430\u043d\u044b"
    ],
    "name:ukr_x_preferred":[
        "\u041f\u0440\u0443\u0436\u0430\u043d\u0438"
    ],
    "name:und_x_variant":[
        "Pruzhana"
    ],
    "name:yid_x_preferred":[
        "\u05e4\u05e8\u05d5\u05d6\u05e9\u05e2\u05e0\u05e2"
    ],
    "name:zho_x_preferred":[
        "\u666e\u9b6f\u624e\u5167"
    ],
    "qs:name":"Pruzhany",
    "qs:photos_9r":0,
    "qs:photos_sr":0,
    "qs:pop_sr":"6",
    "wd:population":19032,
    "wd:wordcount":424,
    "wof:name":"Pruzhany",
    "wof:placetype":"locality",
    "wof:population":19032
},
  "geometry": {"coordinates":[24.4573,52.556],"type":"Point"}
}