{
  "type": "Feature",
  "properties": {
    "gn:admin1_code":"6.0",
    "gn:asciiname":"Staryy Pribuzh",
    "gn:country_code":"BY",
    "gn:dem":167,
    "gn:feature_class":"P",
    "gn:feature_code":"PPL",
    "gn:name":"Staryy Pribuzh",
    "gn:population":0,
    "gn:timezone":"Europe/Minsk",
    "iso:country":"BY",
    "name:rus_x_preferred":[
        "\u041f\u0440\u0438\u0431\u0443\u0436\u044c\u0435 \u0421\u0442\u0430\u0440\u043e\u0435"
    ],
    "name:und_x_variant":[
        "Pribuzh",
        "Staryy Pribuzh",
        "Staroye Pribuzh\u2019ye",
        "Pribuzh\u2019ye Staroye"
    ],
    "wof:name":"Staryy Pribuzh",
    "wof:placetype":"locality"
},
  "geometry": {"coordinates":[31.0428,54.0926],"type":"Point"}
}