{
  "type": "Feature",
  "properties": {
    "gn:admin1_code":"6.0",
    "gn:asciiname":"Lyutnya",
    "gn:country_code":"BY",
    "gn:dem":160,
    "gn:feature_class":"P",
    "gn:feature_code":"PPL",
    "gn:name":"Lyutnya",
    "gn:population":0,
    "gn:timezone":"Europe/Minsk",
    "iso:country":"BY",
    "name:rus_x_preferred":[
        "\u041b\u044e\u0442\u043d\u044f"
    ],
    "wof:name":"Lyutnya",
    "wof:placetype":"locality"
},
  "geometry": {"coordinates":[31.3268,53.3296],"type":"Point"}
}