{
  "type": "Feature",
  "properties": {
    "gn:admin1_code":"0.0",
    "gn:asciiname":"Popelevo",
    "gn:country_code":"BY",
    "gn:dem":171,
    "gn:feature_class":"P",
    "gn:feature_code":"PPL",
    "gn:name":"Popel\u00ebvo",
    "gn:population":0,
    "gn:timezone":"Europe/Minsk",
    "iso:country":"BY",
    "name:rus_x_preferred":[
        "\u041f\u043e\u043f\u0435\u043b\u0435\u0432\u043e"
    ],
    "name:und_x_variant":[
        "Popel\u00ebvo",
        "Bol\u2019shoye Popel\u00ebvo"
    ],
    "wof:name":"Popelevo",
    "wof:placetype":"locality"
},
  "geometry": {"coordinates":[24.09887,52.74514],"type":"Point"}
}