{
  "type": "Feature",
  "properties": {
    "gn:admin1_code":"7.0",
    "gn:asciiname":"Tishkovo",
    "gn:country_code":"BY",
    "gn:dem":223,
    "gn:feature_class":"P",
    "gn:feature_code":"PPL",
    "gn:name":"Tishkovo",
    "gn:population":0,
    "gn:timezone":"Europe/Minsk",
    "iso:country":"BY",
    "name:che_x_preferred":[
        "\u0422\u0438\u0448\u043a\u043e\u0432\u043e"
    ],
    "name:rus_x_preferred":[
        "\u0422\u0438\u0448\u043a\u043e\u0432\u043e"
    ],
    "name:tgk_x_preferred":[
        "\u0422\u0438\u0448\u043a\u043e\u0432\u043e"
    ],
    "name:und_x_variant":[
        "Tishkova"
    ],
    "wof:name":"Tishkovo",
    "wof:placetype":"locality"
},
  "geometry": {"coordinates":[30.4328,55.1627],"type":"Point"}
}