{
  "type": "Feature",
  "properties": {
    "gn:admin1_code":"5.0",
    "gn:asciiname":"Kiyevichi",
    "gn:country_code":"BY",
    "gn:dem":159,
    "gn:feature_class":"P",
    "gn:feature_code":"PPL",
    "gn:name":"Kiyevichi",
    "gn:population":0,
    "gn:timezone":"Europe/Minsk",
    "iso:country":"BY",
    "name:rus_x_preferred":[
        "\u041a\u0438\u0435\u0432\u0438\u0447\u0438"
    ],
    "name:und_x_variant":[
        "Kijewicze",
        "Kiyevichi"
    ],
    "wof:name":"Kiyevichi",
    "wof:placetype":"locality"
},
  "geometry": {"coordinates":[26.9896,52.9869],"type":"Point"}
}