{
  "type": "Feature",
  "properties": {
    "gn:admin1_code":"3.0",
    "gn:asciiname":"Strel'niki",
    "gn:country_code":"BY",
    "gn:dem":164,
    "gn:feature_class":"P",
    "gn:feature_code":"PPL",
    "gn:name":"Strel\u2019niki",
    "gn:population":0,
    "gn:timezone":"Europe/Minsk",
    "iso:country":"BY",
    "name:rus_x_preferred":[
        "\u0421\u0442\u0440\u0435\u043b\u044c\u043d\u0438\u043a\u0438"
    ],
    "name:und_x_variant":[
        "Strel\u2019niki"
    ],
    "wof:name":"Strel'niki",
    "wof:placetype":"locality"
},
  "geometry": {"coordinates":[26.0989,53.5906],"type":"Point"}
}