{
  "type": "Feature",
  "properties": {
    "gn:admin1_code":"6.0",
    "gn:asciiname":"Peregon",
    "gn:country_code":"BY",
    "gn:dem":159,
    "gn:feature_class":"P",
    "gn:feature_code":"PPL",
    "gn:name":"Peregon",
    "gn:population":0,
    "gn:timezone":"Europe/Minsk",
    "iso:country":"BY",
    "name:rus_x_preferred":[
        "\u041f\u0435\u0440\u0435\u0433\u043e\u043d"
    ],
    "wof:name":"Peregon",
    "wof:placetype":"locality"
},
  "geometry": {"coordinates":[30.9469,53.3148],"type":"Point"}
}