{
  "type": "Feature",
  "properties": {
    "gn:admin1_code":"5.0",
    "gn:asciiname":"Karbovtsy",
    "gn:country_code":"BY",
    "gn:dem":190,
    "gn:feature_class":"P",
    "gn:feature_code":"PPL",
    "gn:name":"Karbovtsy",
    "gn:population":0,
    "gn:timezone":"Europe/Minsk",
    "iso:country":"BY",
    "name:rus_x_preferred":[
        "\u041a\u0430\u0440\u0431\u043e\u0432\u0446\u044b"
    ],
    "wof:name":"Karbovtsy",
    "wof:placetype":"locality"
},
  "geometry": {"coordinates":[26.4186,52.9943],"type":"Point"}
}