{
  "type": "Feature",
  "properties": {
    "gn:admin1_code":"7.0",
    "gn:asciiname":"Zheludovo",
    "gn:country_code":"BY",
    "gn:dem":223,
    "gn:feature_class":"P",
    "gn:feature_code":"PPL",
    "gn:name":"Zh\u00ebludovo",
    "gn:population":0,
    "gn:timezone":"Europe/Minsk",
    "iso:country":"BY",
    "name:rus_x_preferred":[
        "\u0416\u0451\u043b\u0443\u0434\u043e\u0432\u043e"
    ],
    "name:und_x_variant":[
        "Zh\u00ebludovo"
    ],
    "wof:name":"Zheludovo",
    "wof:placetype":"locality"
},
  "geometry": {"coordinates":[30.7222,54.9079],"type":"Point"}
}