{
  "type": "Feature",
  "properties": {
    "gn:admin1_code":"5.0",
    "gn:asciiname":"Paderichi",
    "gn:country_code":"BY",
    "gn:dem":277,
    "gn:feature_class":"P",
    "gn:feature_code":"PPL",
    "gn:name":"Paderichi",
    "gn:population":0,
    "gn:timezone":"Europe/Minsk",
    "iso:country":"BY",
    "name:rus_x_preferred":[
        "\u041f\u0430\u0434\u0435\u0440\u0438\u0447\u0438"
    ],
    "wof:name":"Paderichi",
    "wof:placetype":"locality"
},
  "geometry": {"coordinates":[26.9326,53.8336],"type":"Point"}
}