{
  "type": "Feature",
  "properties": {
    "gn:admin1_code":"7.0",
    "gn:asciiname":"Smorodnik",
    "gn:country_code":"BY",
    "gn:dem":190,
    "gn:feature_class":"P",
    "gn:feature_code":"PPL",
    "gn:name":"Smorodnik",
    "gn:population":0,
    "gn:timezone":"Europe/Minsk",
    "iso:country":"BY",
    "name:rus_x_preferred":[
        "\u0421\u043c\u043e\u0440\u043e\u0434\u043d\u0438\u043a"
    ],
    "name:und_x_variant":[
        "Smorodniki"
    ],
    "wof:name":"Smorodnik",
    "wof:placetype":"locality"
},
  "geometry": {"coordinates":[29.884,55.7261],"type":"Point"}
}