{
  "type": "Feature",
  "properties": {
    "gn:admin1_code":"0.0",
    "gn:asciiname":"Telyatnikova",
    "gn:country_code":"BY",
    "gn:dem":162,
    "gn:feature_class":"P",
    "gn:feature_code":"PPL",
    "gn:name":"Telyatnikova",
    "gn:population":0,
    "gn:timezone":"Europe/Minsk",
    "iso:country":"BY",
    "wof:name":"Telyatnikova",
    "wof:placetype":"locality"
},
  "geometry": {"coordinates":[30.43333,55.25],"type":"Point"}
}