{
  "type": "Feature",
  "properties": {
    "gn:admin1_code":"7.0",
    "gn:asciiname":"Bolbechino",
    "gn:country_code":"BY",
    "gn:dem":128,
    "gn:feature_class":"P",
    "gn:feature_code":"PPL",
    "gn:name":"Bolbechino",
    "gn:population":0,
    "gn:timezone":"Europe/Minsk",
    "iso:country":"BY",
    "name:rus_x_preferred":[
        "\u0411\u043e\u043b\u0431\u0435\u0447\u0438\u043d\u043e"
    ],
    "wof:name":"Bolbechino",
    "wof:placetype":"locality"
},
  "geometry": {"coordinates":[28.8492,55.7766],"type":"Point"}
}