{
  "type": "Feature",
  "properties": {
    "gn:admin1_code":"1.0",
    "gn:asciiname":"Iodchiki",
    "gn:country_code":"BY",
    "gn:dem":171,
    "gn:feature_class":"P",
    "gn:feature_code":"PPL",
    "gn:name":"Iodchiki",
    "gn:population":0,
    "gn:timezone":"Europe/Minsk",
    "iso:country":"BY",
    "name:rus_x_preferred":[
        "\u0418\u043e\u0434\u0447\u0438\u043a\u0438"
    ],
    "name:und_x_variant":[
        "Yubchiki",
        "Jodczyki",
        "Iodchyki",
        "Iodchiki"
    ],
    "wof:name":"Iodchiki",
    "wof:placetype":"locality"
},
  "geometry": {"coordinates":[25.0126,52.7558],"type":"Point"}
}