{
  "type": "Feature",
  "properties": {
    "gn:admin1_code":"3.0",
    "gn:asciiname":"Voytovichi",
    "gn:country_code":"BY",
    "gn:dem":166,
    "gn:feature_class":"P",
    "gn:feature_code":"PPL",
    "gn:name":"Voytovichi",
    "gn:population":0,
    "gn:timezone":"Europe/Minsk",
    "iso:country":"BY",
    "name:rus_x_preferred":[
        "\u0412\u043e\u0439\u0442\u043e\u0432\u0438\u0447\u0438"
    ],
    "wof:name":"Voytovichi",
    "wof:placetype":"locality"
},
  "geometry": {"coordinates":[25.4751,54.0322],"type":"Point"}
}