{
  "type": "Feature",
  "properties": {
    "gn:admin1_code":"2.0",
    "gn:asciiname":"Pokats'",
    "gn:country_code":"BY",
    "gn:dem":147,
    "gn:feature_class":"P",
    "gn:feature_code":"PPL",
    "gn:name":"Pokats\u2019",
    "gn:population":0,
    "gn:timezone":"Europe/Minsk",
    "iso:country":"BY",
    "name:bel_x_preferred":[
        "\u041f\u043e\u043a\u0430\u0446\u044c"
    ],
    "name:eng_x_preferred":[
        "Pokot'"
    ],
    "name:rus_x_preferred":[
        "\u041f\u043e\u043a\u043e\u0442\u044c"
    ],
    "name:und_x_variant":[
        "Pokats\u2019",
        "Pokot\u2019"
    ],
    "wof:name":"Pokats'",
    "wof:placetype":"locality"
},
  "geometry": {"coordinates":[31.1068,52.8728],"type":"Point"}
}