{
  "type": "Feature",
  "properties": {
    "gn:admin1_code":"7.0",
    "gn:asciiname":"Eyvidovichi",
    "gn:country_code":"BY",
    "gn:dem":150,
    "gn:feature_class":"P",
    "gn:feature_code":"PPL",
    "gn:name":"Eyvidovichi",
    "gn:population":0,
    "gn:timezone":"Europe/Minsk",
    "iso:country":"BY",
    "name:rus_x_preferred":[
        "\u042d\u0439\u0432\u0438\u0434\u043e\u0432\u0438\u0447\u0438"
    ],
    "name:und_x_variant":[
        "Eyvidoviche",
        "Ejwidowicze",
        "Eyvidovichi"
    ],
    "wof:name":"Eyvidovichi",
    "wof:placetype":"locality"
},
  "geometry": {"coordinates":[26.9303,55.4781],"type":"Point"}
}