{
  "type": "Feature",
  "properties": {
    "gn:admin1_code":"7.0",
    "gn:asciiname":"Vintsentovo",
    "gn:country_code":"BY",
    "gn:dem":207,
    "gn:feature_class":"P",
    "gn:feature_code":"PPL",
    "gn:name":"Vintsentovo",
    "gn:population":0,
    "gn:timezone":"Europe/Minsk",
    "iso:country":"BY",
    "name:rus_x_preferred":[
        "\u0412\u0438\u043d\u0446\u0435\u043d\u0442\u043e\u0432\u043e"
    ],
    "wof:name":"Vintsentovo",
    "wof:placetype":"locality"
},
  "geometry": {"coordinates":[26.3405,55.0305],"type":"Point"}
}