{
  "type": "Feature",
  "properties": {
    "gn:admin1_code":"0.0",
    "gn:asciiname":"Zagrashev'ye",
    "gn:country_code":"BY",
    "gn:dem":200,
    "gn:feature_class":"P",
    "gn:feature_code":"PPL",
    "gn:name":"Zagrashev\u2019ye",
    "gn:population":0,
    "gn:timezone":"Europe/Minsk",
    "iso:country":"BY",
    "wof:name":"Zagrashev'ye",
    "wof:placetype":"locality"
},
  "geometry": {"coordinates":[29.48333,53.86666999999999],"type":"Point"}
}