{
  "type": "Feature",
  "properties": {
    "gn:admin1_code":"2.0",
    "gn:asciiname":"Staryye Yurkovichi",
    "gn:country_code":"BY",
    "gn:dem":117,
    "gn:feature_class":"P",
    "gn:feature_code":"PPL",
    "gn:name":"Staryye Yurkovichi",
    "gn:population":0,
    "gn:timezone":"Europe/Minsk",
    "iso:country":"BY",
    "name:rus_x_preferred":[
        "\u0421\u0442\u0430\u0440\u044b\u0435 \u042e\u0440\u043a\u043e\u0432\u0438\u0447\u0438"
    ],
    "wof:name":"Staryye Yurkovichi",
    "wof:placetype":"locality"
},
  "geometry": {"coordinates":[30.3719,51.7178],"type":"Point"}
}