{
  "type": "Feature",
  "properties": {
    "gn:admin1_code":"3.0",
    "gn:asciiname":"Kordiki",
    "gn:country_code":"BY",
    "gn:dem":152,
    "gn:feature_class":"P",
    "gn:feature_code":"PPL",
    "gn:name":"Kordiki",
    "gn:population":0,
    "gn:timezone":"Europe/Minsk",
    "iso:country":"BY",
    "name:rus_x_preferred":[
        "\u041a\u043e\u0440\u0434\u0438\u043a\u0438"
    ],
    "wof:name":"Kordiki",
    "wof:placetype":"locality"
},
  "geometry": {"coordinates":[24.0302,53.3182],"type":"Point"}
}