{
  "type": "Feature",
  "properties": {
    "gn:admin1_code":"1.0",
    "gn:asciiname":"Yanovo",
    "gn:country_code":"BY",
    "gn:dem":185,
    "gn:feature_class":"P",
    "gn:feature_code":"PPL",
    "gn:name":"Yanovo",
    "gn:population":0,
    "gn:timezone":"Europe/Minsk",
    "iso:country":"BY",
    "name:bul_x_preferred":[
        "\u042f\u043d\u043e\u0432\u043e"
    ],
    "name:fas_x_preferred":[
        "\u06cc\u0627\u0646\u0648\u0648\u0648"
    ],
    "name:kaz_x_preferred":[
        "\u042f\u043d\u043e\u0432\u043e"
    ],
    "name:mkd_x_preferred":[
        "\u0408\u0430\u043d\u043e\u0432\u043e"
    ],
    "name:pol_x_preferred":[
        "Janowo"
    ],
    "name:ron_x_preferred":[
        "Ianovo"
    ],
    "name:rus_x_preferred":[
        "\u042f\u043d\u043e\u0432\u043e"
    ],
    "name:ukr_x_preferred":[
        "\u042f\u043d\u043e\u0432\u043e"
    ],
    "wof:name":"Yanovo",
    "wof:placetype":"locality"
},
  "geometry": {"coordinates":[26.074,53.1108],"type":"Point"}
}