{
  "type": "Feature",
  "properties": {
    "gn:admin1_code":"1.0",
    "gn:asciiname":"Glinna",
    "gn:country_code":"BY",
    "gn:dem":141,
    "gn:feature_class":"P",
    "gn:feature_code":"PPL",
    "gn:name":"Glinna",
    "gn:population":0,
    "gn:timezone":"Europe/Minsk",
    "iso:country":"BY",
    "name:ceb_x_preferred":[
        "Glinna"
    ],
    "name:pol_x_preferred":[
        "Glinna"
    ],
    "name:rus_x_preferred":[
        "\u0413\u043b\u0438\u043d\u043d\u0430"
    ],
    "name:ukr_x_preferred":[
        "\u0490\u043b\u0456\u043d\u043d\u0430"
    ],
    "name:und_x_variant":[
        "Glina"
    ],
    "name:vie_x_preferred":[
        "Glinna"
    ],
    "wof:name":"Glinna",
    "wof:placetype":"locality"
},
  "geometry": {"coordinates":[25.4289,52.0219],"type":"Point"}
}