{
  "type": "Feature",
  "properties": {
    "gn:admin1_code":"2.0",
    "gn:asciiname":"Ivan'kov",
    "gn:country_code":"BY",
    "gn:dem":133,
    "gn:feature_class":"P",
    "gn:feature_code":"PPL",
    "gn:name":"Ivan\u2019kov",
    "gn:population":0,
    "gn:timezone":"Europe/Minsk",
    "iso:country":"BY",
    "name:rus_x_preferred":[
        "\u0418\u0432\u0430\u043d\u044c\u043a\u043e\u0432"
    ],
    "name:und_x_variant":[
        "Ivan\u2019kov"
    ],
    "wof:name":"Ivan'kov",
    "wof:placetype":"locality"
},
  "geometry": {"coordinates":[30.6714,52.422],"type":"Point"}
}