{
  "type": "Feature",
  "properties": {
    "gn:admin1_code":"7.0",
    "gn:asciiname":"Teraspol'ye",
    "gn:country_code":"BY",
    "gn:dem":129,
    "gn:feature_class":"P",
    "gn:feature_code":"PPL",
    "gn:name":"Teraspol\u2019ye",
    "gn:population":0,
    "gn:timezone":"Europe/Minsk",
    "iso:country":"BY",
    "name:rus_x_preferred":[
        "\u0422\u0435\u0440\u0430\u0441\u043f\u043e\u043b\u044c\u0435"
    ],
    "name:und_x_variant":[
        "Teraspol\u2019ye"
    ],
    "wof:name":"Teraspol'ye",
    "wof:placetype":"locality"
},
  "geometry": {"coordinates":[28.3579,55.587],"type":"Point"}
}