{
  "type": "Feature",
  "properties": {
    "gn:admin1_code":"7.0",
    "gn:asciiname":"Rogachi",
    "gn:country_code":"BY",
    "gn:dem":131,
    "gn:feature_class":"P",
    "gn:feature_code":"PPL",
    "gn:name":"Rogachi",
    "gn:population":0,
    "gn:timezone":"Europe/Minsk",
    "iso:country":"BY",
    "name:rus_x_preferred":[
        "\u0420\u043e\u0433\u0430\u0447\u0438"
    ],
    "wof:name":"Rogachi",
    "wof:placetype":"locality"
},
  "geometry": {"coordinates":[28.5332,55.4255],"type":"Point"}
}