{
  "type": "Feature",
  "properties": {
    "gn:admin1_code":"3.0",
    "gn:asciiname":"Chernitsa",
    "gn:country_code":"BY",
    "gn:dem":154,
    "gn:feature_class":"P",
    "gn:feature_code":"PPL",
    "gn:name":"Chernitsa",
    "gn:population":0,
    "gn:timezone":"Europe/Minsk",
    "iso:country":"BY",
    "name:ceb_x_preferred":[
        "Chernitsa"
    ],
    "name:rus_x_preferred":[
        "\u0427\u0435\u0440\u043d\u0438\u0446\u0430"
    ],
    "name:swe_x_preferred":[
        "Chernitsa"
    ],
    "wof:name":"Chernitsa",
    "wof:placetype":"locality"
},
  "geometry": {"coordinates":[26.057,54.1012],"type":"Point"}
}