{
  "type": "Feature",
  "properties": {
    "gn:admin1_code":"7.0",
    "gn:asciiname":"Slaboda",
    "gn:country_code":"BY",
    "gn:dem":205,
    "gn:feature_class":"P",
    "gn:feature_code":"PPL",
    "gn:name":"Slaboda",
    "gn:population":0,
    "gn:timezone":"Europe/Minsk",
    "iso:country":"BY",
    "name:rus_x_preferred":[
        "\u0421\u043b\u0430\u0431\u043e\u0434\u0430"
    ],
    "name:und_x_variant":[
        "Sloboda"
    ],
    "wof:name":"Slaboda",
    "wof:placetype":"locality"
},
  "geometry": {"coordinates":[29.8779,55.6363],"type":"Point"}
}