{
  "type": "Feature",
  "properties": {
    "gn:admin1_code":"7.0",
    "gn:asciiname":"Vyatny",
    "gn:country_code":"BY",
    "gn:dem":151,
    "gn:feature_class":"P",
    "gn:feature_code":"PPL",
    "gn:name":"Vyatny",
    "gn:population":0,
    "gn:timezone":"Europe/Minsk",
    "iso:country":"BY",
    "name:rus_x_preferred":[
        "\u0412\u044f\u0442\u043d\u044b"
    ],
    "wof:name":"Vyatny",
    "wof:placetype":"locality"
},
  "geometry": {"coordinates":[29.3729,54.7537],"type":"Point"}
}