{
  "type": "Feature",
  "properties": {
    "gn:admin1_code":"5.0",
    "gn:asciiname":"Palazhevichy",
    "gn:country_code":"BY",
    "gn:dem":154,
    "gn:feature_class":"P",
    "gn:feature_code":"PPL",
    "gn:name":"Palazhevichy",
    "gn:population":0,
    "gn:timezone":"Europe/Minsk",
    "iso:country":"BY",
    "name:bel_x_preferred":[
        "\u041f\u0430\u043b\u0430\u0436\u044d\u0432\u0456\u0447\u044b"
    ],
    "name:und_x_variant":[
        "Palazhevichi",
        "Polozhevichi",
        "Palazhevichy"
    ],
    "wof:name":"Palazhevichy",
    "wof:placetype":"locality"
},
  "geometry": {"coordinates":[28.4326,52.9294],"type":"Point"}
}