{
  "type": "Feature",
  "properties": {
    "gn:admin1_code":"1.0",
    "gn:asciiname":"Novy Dvor",
    "gn:country_code":"BY",
    "gn:dem":135,
    "gn:feature_class":"P",
    "gn:feature_code":"PPL",
    "gn:name":"Novy Dvor",
    "gn:population":0,
    "gn:timezone":"Europe/Minsk",
    "iso:country":"BY",
    "name:bel_x_preferred":[
        "\u041d\u043e\u0432\u044b \u0414\u0432\u043e\u0440"
    ],
    "name:eng_x_preferred":[
        "Novyy Dvor"
    ],
    "name:rus_x_preferred":[
        "\u041d\u043e\u0432.\u0414\u0432\u043e\u0440"
    ],
    "name:und_x_variant":[
        "Nowy Dw\u00f3r",
        "Novy Dvur",
        "Novy Dvor"
    ],
    "wof:name":"Novy Dvor",
    "wof:placetype":"locality"
},
  "geometry": {"coordinates":[26.2469,52.3031],"type":"Point"}
}