{
  "type": "Feature",
  "properties": {
    "gn:admin1_code":"6.0",
    "gn:asciiname":"Kontsy",
    "gn:country_code":"BY",
    "gn:dem":159,
    "gn:feature_class":"P",
    "gn:feature_code":"PPL",
    "gn:name":"Kontsy",
    "gn:population":0,
    "gn:timezone":"Europe/Minsk",
    "iso:country":"BY",
    "name:rus_x_preferred":[
        "\u041a\u043e\u043d\u0446\u044b"
    ],
    "wof:name":"Kontsy",
    "wof:placetype":"locality"
},
  "geometry": {"coordinates":[28.3169,53.2129],"type":"Point"}
}