{
  "type": "Feature",
  "properties": {
    "gn:admin1_code":"7.0",
    "gn:asciiname":"Zhigalovo",
    "gn:country_code":"BY",
    "gn:dem":157,
    "gn:feature_class":"P",
    "gn:feature_code":"PPL",
    "gn:name":"Zhigalovo",
    "gn:population":0,
    "gn:timezone":"Europe/Minsk",
    "iso:country":"BY",
    "name:rus_x_preferred":[
        "\u0416\u0438\u0433\u0430\u043b\u043e\u0432\u043e"
    ],
    "wof:name":"Zhigalovo",
    "wof:placetype":"locality"
},
  "geometry": {"coordinates":[29.8509,55.3121],"type":"Point"}
}