{
  "type": "Feature",
  "properties": {
    "gn:admin1_code":"3.0",
    "gn:asciiname":"Skomoroshki",
    "gn:country_code":"BY",
    "gn:dem":150,
    "gn:feature_class":"P",
    "gn:feature_code":"PPL",
    "gn:name":"Skomoroshki",
    "gn:population":0,
    "gn:timezone":"Europe/Minsk",
    "iso:country":"BY",
    "name:rus_x_preferred":[
        "\u0421\u043a\u043e\u043c\u043e\u0440\u043e\u0448\u043a\u0438"
    ],
    "wof:name":"Skomoroshki",
    "wof:placetype":"locality"
},
  "geometry": {"coordinates":[23.7848,53.6213],"type":"Point"}
}