{
  "type": "Feature",
  "properties": {
    "gn:admin1_code":"3.0",
    "gn:asciiname":"Yaremichy",
    "gn:country_code":"BY",
    "gn:dem":144,
    "gn:feature_class":"P",
    "gn:feature_code":"PPL",
    "gn:name":"Yaremichy",
    "gn:population":0,
    "gn:timezone":"Europe/Minsk",
    "iso:country":"BY",
    "name:bel_x_preferred":[
        "\u042f\u0440\u044d\u043c\u0456\u0447\u044b"
    ],
    "name:und_x_variant":[
        "Jeremicze",
        "Yeremichi",
        "Yaremichy"
    ],
    "wof:name":"Yaremichy",
    "wof:placetype":"locality"
},
  "geometry": {"coordinates":[26.3476,53.5692],"type":"Point"}
}