{
  "type": "Feature",
  "properties": {
    "gn:admin1_code":"5.0",
    "gn:asciiname":"Tolkany",
    "gn:country_code":"BY",
    "gn:dem":219,
    "gn:feature_class":"P",
    "gn:feature_code":"PPL",
    "gn:name":"Tolkany",
    "gn:population":0,
    "gn:timezone":"Europe/Minsk",
    "iso:country":"BY",
    "name:rus_x_preferred":[
        "\u0422\u043e\u043b\u043a\u0430\u043d\u044b"
    ],
    "wof:name":"Tolkany",
    "wof:placetype":"locality"
},
  "geometry": {"coordinates":[26.7377,53.8457],"type":"Point"}
}