{
  "type": "Feature",
  "properties": {
    "gn:admin1_code":"7.0",
    "gn:asciiname":"Simonovo",
    "gn:country_code":"BY",
    "gn:dem":224,
    "gn:feature_class":"P",
    "gn:feature_code":"PPL",
    "gn:name":"Simonovo",
    "gn:population":0,
    "gn:timezone":"Europe/Minsk",
    "iso:country":"BY",
    "name:rus_x_preferred":[
        "\u0421\u0438\u043c\u043e\u043d\u043e\u0432\u043e"
    ],
    "wof:name":"Simonovo",
    "wof:placetype":"locality"
},
  "geometry": {"coordinates":[29.9359,54.4238],"type":"Point"}
}