{
  "type": "Feature",
  "properties": {
    "gn:admin1_code":"6.0",
    "gn:asciiname":"Velenka",
    "gn:country_code":"BY",
    "gn:dem":154,
    "gn:feature_class":"P",
    "gn:feature_code":"PPL",
    "gn:name":"Velenka",
    "gn:population":0,
    "gn:timezone":"Europe/Minsk",
    "iso:country":"BY",
    "name:ceb_x_preferred":[
        "Velenka"
    ],
    "name:ces_x_preferred":[
        "Velenka"
    ],
    "name:deu_x_preferred":[
        "Velenka"
    ],
    "name:eus_x_preferred":[
        "Velenka"
    ],
    "name:fra_x_preferred":[
        "Velenka"
    ],
    "name:hun_x_preferred":[
        "Velenka"
    ],
    "name:ita_x_preferred":[
        "Velenka"
    ],
    "name:msa_x_preferred":[
        "Velenka"
    ],
    "name:nld_x_preferred":[
        "Velenka"
    ],
    "name:pol_x_preferred":[
        "Velenka"
    ],
    "name:por_x_preferred":[
        "Velenka"
    ],
    "name:rus_x_preferred":[
        "\u0412\u0435\u043b\u0435\u043d\u043a\u0430"
    ],
    "name:slk_x_preferred":[
        "Velenka"
    ],
    "name:spa_x_preferred":[
        "Velenka"
    ],
    "name:srp_x_preferred":[
        "\u0412\u0435\u043b\u0435\u043d\u043a\u0430"
    ],
    "name:swe_x_preferred":[
        "Velenka"
    ],
    "name:vie_x_preferred":[
        "Velenka"
    ],
    "wof:name":"Velenka",
    "wof:placetype":"locality"
},
  "geometry": {"coordinates":[29.7447,53.3732],"type":"Point"}
}