{
  "type": "Feature",
  "properties": {
    "gn:admin1_code":"3.0",
    "gn:asciiname":"Malynishki",
    "gn:country_code":"BY",
    "gn:dem":290,
    "gn:feature_class":"P",
    "gn:feature_code":"PPL",
    "gn:name":"Malynishki",
    "gn:population":0,
    "gn:timezone":"Europe/Minsk",
    "iso:country":"BY",
    "name:rus_x_preferred":[
        "\u041c\u0430\u043b\u044b\u043d\u0438\u0448\u043a\u0438"
    ],
    "wof:name":"Malynishki",
    "wof:placetype":"locality"
},
  "geometry": {"coordinates":[25.6789,54.4915],"type":"Point"}
}