{
  "type": "Feature",
  "properties": {
    "gn:admin1_code":"3.0",
    "gn:asciiname":"Bol'shiye Yatsyny",
    "gn:country_code":"BY",
    "gn:dem":137,
    "gn:feature_class":"P",
    "gn:feature_code":"PPL",
    "gn:name":"Bol\u2019shiye Yatsyny",
    "gn:population":0,
    "gn:timezone":"Europe/Minsk",
    "iso:country":"BY",
    "name:rus_x_preferred":[
        "\u0411\u043e\u043b\u044c\u0448\u0438\u0435 \u042f\u0446\u044b\u043d\u044b"
    ],
    "name:und_x_variant":[
        "Bol\u2019shiye Yatsyny"
    ],
    "wof:name":"Bol'shiye Yatsyny",
    "wof:placetype":"locality"
},
  "geometry": {"coordinates":[26.2064,54.7458],"type":"Point"}
}