{
  "type": "Feature",
  "properties": {
    "gn:admin1_code":"5.0",
    "gn:asciiname":"Romeyki",
    "gn:country_code":"BY",
    "gn:dem":174,
    "gn:feature_class":"P",
    "gn:feature_code":"PPL",
    "gn:name":"Romeyki",
    "gn:population":0,
    "gn:timezone":"Europe/Minsk",
    "iso:country":"BY",
    "name:rus_x_preferred":[
        "\u0420\u043e\u043c\u0435\u0439\u043a\u0438"
    ],
    "wof:name":"Romeyki",
    "wof:placetype":"locality"
},
  "geometry": {"coordinates":[27.1009,54.37],"type":"Point"}
}