{
  "type": "Feature",
  "properties": {
    "gn:admin1_code":"6.0",
    "gn:asciiname":"Rusinovka",
    "gn:country_code":"BY",
    "gn:dem":174,
    "gn:feature_class":"P",
    "gn:feature_code":"PPL",
    "gn:name":"Rusinovka",
    "gn:population":0,
    "gn:timezone":"Europe/Minsk",
    "iso:country":"BY",
    "name:rus_x_preferred":[
        "\u0420\u0443\u0441\u0438\u043d\u043e\u0432\u043a\u0430"
    ],
    "wof:name":"Rusinovka",
    "wof:placetype":"locality"
},
  "geometry": {"coordinates":[31.0372,53.8585],"type":"Point"}
}