{
  "type": "Feature",
  "properties": {
    "gn:admin1_code":"3.0",
    "gn:asciiname":"Malyy Ugrin'",
    "gn:country_code":"BY",
    "gn:dem":144,
    "gn:feature_class":"P",
    "gn:feature_code":"PPL",
    "gn:name":"Malyy Ugrin\u2019",
    "gn:population":0,
    "gn:timezone":"Europe/Minsk",
    "iso:country":"BY",
    "name:bel_x_preferred":[
        "Malaya Uhryn\u2019"
    ],
    "name:bel_x_variant":[
        "\u041c\u0430\u043b\u0430\u044f \u0423\u0433\u0440\u044b\u043d\u044c",
        "\u041c\u0430\u043b\u0430\u044f \u0423\u0433\u0440\u0438\u043d\u044c"
    ],
    "name:rus_x_preferred":[
        "\u041c\u0430\u043b\u044b\u0439 \u0423\u0433\u0440\u0438\u043d\u044c"
    ],
    "name:rus_x_variant":[
        "Malaya Ugrin\u2019"
    ],
    "name:und_x_variant":[
        "Malyy Ugrin\u2019",
        "Ugryn\u2019 Maly"
    ],
    "wof:name":"Malyy Ugrin'",
    "wof:placetype":"locality"
},
  "geometry": {"coordinates":[24.9726,53.2412],"type":"Point"}
}