{
  "type": "Feature",
  "properties": {
    "gn:admin1_code":"7.0",
    "gn:asciiname":"Bel'chitsa",
    "gn:country_code":"BY",
    "gn:dem":126,
    "gn:feature_class":"P",
    "gn:feature_code":"PPL",
    "gn:name":"Bel\u2019chitsa",
    "gn:population":0,
    "gn:timezone":"Europe/Minsk",
    "iso:country":"BY",
    "name:eng_x_preferred":[
        "Bel'chitsa"
    ],
    "name:rus_x_preferred":[
        "\u0411\u0435\u043b\u044c\u0447\u0438\u0446\u0430"
    ],
    "name:und_x_variant":[
        "Bel\u2019chitsa"
    ],
    "wof:name":"Bel'chitsa",
    "wof:placetype":"locality"
},
  "geometry": {"coordinates":[28.7782,55.463],"type":"Point"}
}