{
  "type": "Feature",
  "properties": {
    "gn:admin1_code":"3.0",
    "gn:asciiname":"Vyerdamichy",
    "gn:country_code":"BY",
    "gn:dem":182,
    "gn:feature_class":"P",
    "gn:feature_code":"PPL",
    "gn:name":"Vyerdamichy",
    "gn:population":0,
    "gn:timezone":"Europe/Minsk",
    "iso:country":"BY",
    "name:bel_x_preferred":[
        "\u0412\u0435\u0440\u0434\u0430\u043c\u0456\u0447\u044b"
    ],
    "name:eng_x_preferred":[
        "Verdomichi"
    ],
    "name:rus_x_preferred":[
        "\u0412\u0435\u0440\u0434\u043e\u043c\u0438\u0447\u0438"
    ],
    "name:und_x_variant":[
        "Verdomiche",
        "Verdomichi",
        "Vyerdamichy"
    ],
    "wof:name":"Vyerdamichy",
    "wof:placetype":"locality"
},
  "geometry": {"coordinates":[24.2764,53.0279],"type":"Point"}
}