{
  "type": "Feature",
  "properties": {
    "gn:admin1_code":"6.0",
    "gn:asciiname":"Dubovka",
    "gn:country_code":"BY",
    "gn:dem":189,
    "gn:feature_class":"P",
    "gn:feature_code":"PPL",
    "gn:name":"Dubovka",
    "gn:population":0,
    "gn:timezone":"Europe/Minsk",
    "iso:country":"BY",
    "name:rus_x_preferred":[
        "\u0414\u0443\u0431\u043e\u0432\u043a\u0430"
    ],
    "wof:name":"Dubovka",
    "wof:placetype":"locality"
},
  "geometry": {"coordinates":[29.8568,54.2058],"type":"Point"}
}