{
  "type": "Feature",
  "properties": {
    "gn:admin1_code":"7.0",
    "gn:asciiname":"Kstovka",
    "gn:country_code":"BY",
    "gn:dem":133,
    "gn:feature_class":"P",
    "gn:feature_code":"PPL",
    "gn:name":"Kstovka",
    "gn:population":0,
    "gn:timezone":"Europe/Minsk",
    "iso:country":"BY",
    "name:rus_x_preferred":[
        "\u041a\u0441\u0442\u043e\u0432\u043a\u0430"
    ],
    "wof:name":"Kstovka",
    "wof:placetype":"locality"
},
  "geometry": {"coordinates":[28.7295,55.4532],"type":"Point"}
}