{
  "type": "Feature",
  "properties": {
    "gn:admin1_code":"7.0",
    "gn:asciiname":"Stavitsa",
    "gn:country_code":"BY",
    "gn:dem":148,
    "gn:feature_class":"P",
    "gn:feature_code":"PPL",
    "gn:name":"Stavitsa",
    "gn:population":0,
    "gn:timezone":"Europe/Minsk",
    "iso:country":"BY",
    "name:rus_x_preferred":[
        "\u0421\u0442\u0430\u0432\u0438\u0446\u0430"
    ],
    "name:und_x_variant":[
        "Stavitsy"
    ],
    "wof:name":"Stavitsa",
    "wof:placetype":"locality"
},
  "geometry": {"coordinates":[29.589,55.5704],"type":"Point"}
}