{
  "type": "Feature",
  "properties": {
    "gn:admin1_code":"7.0",
    "gn:asciiname":"Mikitsikha",
    "gn:country_code":"BY",
    "gn:dem":134,
    "gn:feature_class":"P",
    "gn:feature_code":"PPL",
    "gn:name":"Mikitsikha",
    "gn:population":0,
    "gn:timezone":"Europe/Minsk",
    "iso:country":"BY",
    "name:bel_x_preferred":[
        "\u041c\u0456\u043a\u0456\u0446\u0456\u0445\u0430"
    ],
    "name:und_x_variant":[
        "Nikitikha"
    ],
    "wof:name":"Mikitsikha",
    "wof:placetype":"locality"
},
  "geometry": {"coordinates":[29.4391,55.3161],"type":"Point"}
}