{
  "type": "Feature",
  "properties": {
    "gn:admin1_code":"5.0",
    "gn:asciiname":"Myslivo",
    "gn:country_code":"BY",
    "gn:dem":183,
    "gn:feature_class":"P",
    "gn:feature_code":"PPL",
    "gn:name":"Myslivo",
    "gn:population":0,
    "gn:timezone":"Europe/Minsk",
    "iso:country":"BY",
    "name:rus_x_preferred":[
        "\u041c\u044b\u0441\u043b\u0438\u0432\u043e"
    ],
    "wof:name":"Myslivo",
    "wof:placetype":"locality"
},
  "geometry": {"coordinates":[26.7986,53.2237],"type":"Point"}
}