{
  "type": "Feature",
  "properties": {
    "gn:admin1_code":"7.0",
    "gn:asciiname":"Prud",
    "gn:country_code":"BY",
    "gn:dem":172,
    "gn:feature_class":"P",
    "gn:feature_code":"PPL",
    "gn:name":"Prud",
    "gn:population":0,
    "gn:timezone":"Europe/Minsk",
    "iso:country":"BY",
    "name:bel_x_preferred":[
        "\u041f\u0440\u0443\u0434"
    ],
    "name:bos_x_preferred":[
        "Prud"
    ],
    "name:hrv_x_preferred":[
        "Prud"
    ],
    "name:hun_x_preferred":[
        "Prud"
    ],
    "name:nld_x_preferred":[
        "Prud"
    ],
    "name:rus_x_preferred":[
        "\u041f\u0440\u0443\u0434"
    ],
    "name:slv_x_preferred":[
        "Prud"
    ],
    "name:srp_x_preferred":[
        "\u041f\u0440\u0443\u0434"
    ],
    "wof:name":"Prud",
    "wof:placetype":"locality"
},
  "geometry": {"coordinates":[29.8418,55.7323],"type":"Point"}
}