{
  "type": "Feature",
  "properties": {
    "iso:country":"BY",
    "name:bel_x_preferred":[
        "\u0413\u043e\u0440\u0430\u0434 \u0412\u0435\u0440\u0445\u043d\u044f\u0434\u0437\u0432\u0456\u043d\u0441\u043a"
    ],
    "name:bel_x_variant":[
        "\u0414\u0440\u044b\u0441\u0430",
        "\u0412\u0435\u0440\u0445\u043d\u044f\u0434\u0437\u0432\u0456\u043d\u0441\u043a"
    ],
    "name:bul_x_preferred":[
        "\u0412\u0435\u0440\u0445\u043d\u0435\u0434\u0432\u0438\u043d\u0441\u043a"
    ],
    "name:ceb_x_preferred":[
        "Vyerkhnyadzvinsk"
    ],
    "name:deu_x_preferred":[
        "Werchnjadswinsk"
    ],
    "name:eng_x_preferred":[
        "Vyerkhnyadzvinsk"
    ],
    "name:est_x_preferred":[
        "Vierchniad\u017avinsk"
    ],
    "name:fin_x_preferred":[
        "Verh\u2019njadzvinsk"
    ],
    "name:fra_x_preferred":[
        "Verkhniadzvinsk"
    ],
    "name:heb_x_preferred":[
        "\u05d5\u05e8\u05d7\u05e0\u05d9\u05d0\u05d3\u05d6\u05d1\u05d9\u05e0\u05e1\u05e7"
    ],
    "name:hsb_x_preferred":[
        "Wjerchnjadzwinsk"
    ],
    "name:lav_x_preferred":[
        "Vjerh\u0146adzvinska"
    ],
    "name:lit_x_preferred":[
        "Verchniadzvinskas"
    ],
    "name:nld_x_preferred":[
        "Verkhnyadzvinsk"
    ],
    "name:pol_x_preferred":[
        "Wierchnied\u017awi\u0144sk"
    ],
    "name:rus_x_preferred":[
        "\u0412\u0435\u0440\u0445\u043d\u0435\u0434\u0432\u0438\u043d\u0441\u043a"
    ],
    "name:srp_x_preferred":[
        "\u0412\u0435\u0440\u0445\u045a\u0435\u0434\u0432\u0438\u043d\u0441\u043a"
    ],
    "name:swe_x_preferred":[
        "Verchnjadzvinsk"
    ],
    "name:tat_x_preferred":[
        "\u0412\u0435\u0440\u0445\u043d\u04d9\u0434\u0437\u0432\u0438\u043d\u0441\u043a"
    ],
    "name:ukr_x_preferred":[
        "\u0412\u0435\u0440\u0445\u043d\u044c\u043e\u0434\u0432\u0456\u043d\u0441\u044c\u043a"
    ],
    "name:unk_x_variant":[
        "Drissa"
    ],
    "name:zho_x_preferred":[
        "\u4e0a\u7b2c\u6587\u65af\u57fa"
    ],
    "qs:gn_country":"BY",
    "qs:gn_fcode":"PPLA2",
    "qs:gn_pop":7700,
    "qs:name":"Verkhnedvinsk",
    "qs:name_adm0":"Belarus",
    "qs:name_adm1":"Vitsyebskaya Voblasts'",
    "qs:photos":0,
    "qs:photos_1k":0,
    "qs:photos_9k":1,
    "qs:photos_9r":1,
    "qs:photos_all":1,
    "qs:photos_sr":0,
    "qs:placetype":"Town",
    "qs:pop_sr":"5",
    "qs:woe_adm0":23424765,
    "wd:population":7300,
    "wd:wordcount":192,
    "wof:name":"Verkhnedvinsk",
    "wof:placetype":"locality",
    "wof:population":7300
},
  "geometry": {"coordinates":[27.9389,55.7777],"type":"Point"}
}