{
  "type": "Feature",
  "properties": {
    "gn:admin1_code":"3.0",
    "gn:asciiname":"Den'kovtsy",
    "gn:country_code":"BY",
    "gn:dem":115,
    "gn:feature_class":"P",
    "gn:feature_code":"PPL",
    "gn:name":"Den\u2019kovtsy",
    "gn:population":0,
    "gn:timezone":"Europe/Minsk",
    "iso:country":"BY",
    "name:rus_x_preferred":[
        "\u0414\u0435\u043d\u044c\u043a\u043e\u0432\u0446\u044b"
    ],
    "name:und_x_variant":[
        "Den\u2019kovtsy",
        "Den\u2019kovtse"
    ],
    "wof:name":"Den'kovtsy",
    "wof:placetype":"locality"
},
  "geometry": {"coordinates":[24.4864,53.4009],"type":"Point"}
}