{
  "type": "Feature",
  "properties": {
    "gn:admin1_code":"1.0",
    "gn:asciiname":"Tel'my Pyershyya",
    "gn:country_code":"BY",
    "gn:dem":138,
    "gn:feature_class":"P",
    "gn:feature_code":"PPL",
    "gn:name":"Tel\u2019my Pyershyya",
    "gn:population":0,
    "gn:timezone":"Europe/Minsk",
    "iso:country":"BY",
    "name:bel_x_preferred":[
        "\u0422\u044d\u043b\u044c\u043c\u044b \u041f\u0435\u0440\u0448\u044b\u044f"
    ],
    "name:rus_x_preferred":[
        "Tel\u2019my Pervyye"
    ],
    "name:und_x_variant":[
        "Tel\u2019my Vlasne",
        "Tel\u2019my",
        "Tel\u2019my Pyershyya"
    ],
    "wof:name":"Tel'my Pyershyya",
    "wof:placetype":"neighbourhood"
},
  "geometry": {"coordinates":[23.83167,52.11717],"type":"Point"}
}