{
  "type": "Feature",
  "properties": {
    "gn:admin1_code":"5.0",
    "gn:asciiname":"Letenets",
    "gn:country_code":"BY",
    "gn:dem":145,
    "gn:feature_class":"P",
    "gn:feature_code":"PPL",
    "gn:name":"Letenets",
    "gn:population":0,
    "gn:timezone":"Europe/Minsk",
    "iso:country":"BY",
    "name:rus_x_preferred":[
        "\u041b\u0435\u0442\u0435\u043d\u0435\u0446"
    ],
    "wof:name":"Letenets",
    "wof:placetype":"locality"
},
  "geometry": {"coordinates":[27.464,52.6771],"type":"Point"}
}