{
  "type": "Feature",
  "properties": {
    "gn:admin1_code":"5.0",
    "gn:asciiname":"Levdanshchina",
    "gn:country_code":"BY",
    "gn:dem":190,
    "gn:feature_class":"P",
    "gn:feature_code":"PPL",
    "gn:name":"Levdanshchina",
    "gn:population":0,
    "gn:timezone":"Europe/Minsk",
    "iso:country":"BY",
    "name:rus_x_preferred":[
        "\u041b\u0435\u0432\u0434\u0430\u043d\u0449\u0438\u043d\u0430"
    ],
    "wof:name":"Levdanshchina",
    "wof:placetype":"locality"
},
  "geometry": {"coordinates":[27.7027,54.4886],"type":"Point"}
}