{
  "type": "Feature",
  "properties": {
    "gn:admin1_code":"1.0",
    "gn:asciiname":"Balandichi",
    "gn:country_code":"BY",
    "gn:dem":146,
    "gn:feature_class":"P",
    "gn:feature_code":"PPL",
    "gn:name":"Balandichi",
    "gn:population":0,
    "gn:timezone":"Europe/Minsk",
    "iso:country":"BY",
    "name:rus_x_preferred":[
        "\u0411\u0430\u043b\u0430\u043d\u0434\u0438\u0447\u0438"
    ],
    "wof:name":"Balandichi",
    "wof:placetype":"locality"
},
  "geometry": {"coordinates":[25.5102,51.9261],"type":"Point"}
}