{
  "type": "Feature",
  "properties": {
    "gn:admin1_code":"6.0",
    "gn:asciiname":"Loza",
    "gn:country_code":"BY",
    "gn:dem":155,
    "gn:feature_class":"P",
    "gn:feature_code":"PPL",
    "gn:name":"Loza",
    "gn:population":0,
    "gn:timezone":"Europe/Minsk",
    "iso:country":"BY",
    "name:bos_x_preferred":[
        "Loza"
    ],
    "name:bul_x_preferred":[
        "\u041b\u043e\u0437\u0430"
    ],
    "name:ceb_x_preferred":[
        "Loza"
    ],
    "name:deu_x_preferred":[
        "Loza"
    ],
    "name:eus_x_preferred":[
        "Loza"
    ],
    "name:fra_x_preferred":[
        "Loza"
    ],
    "name:mkd_x_preferred":[
        "\u041b\u043e\u0437\u0430"
    ],
    "name:nld_x_preferred":[
        "Loza"
    ],
    "name:rus_x_preferred":[
        "\u041b\u043e\u0437\u0430"
    ],
    "name:spa_x_preferred":[
        "Loza"
    ],
    "name:srp_x_preferred":[
        "\u041b\u043e\u0437\u0430"
    ],
    "name:swe_x_preferred":[
        "Loza"
    ],
    "name:ukr_x_preferred":[
        "\u041b\u043e\u0437\u0430"
    ],
    "wof:name":"Loza",
    "wof:placetype":"locality"
},
  "geometry": {"coordinates":[31.45833,53.61111],"type":"Point"}
}