{
  "type": "Feature",
  "properties": {
    "gn:admin1_code":"5.0",
    "gn:asciiname":"Yakshytsy",
    "gn:country_code":"BY",
    "gn:dem":154,
    "gn:feature_class":"P",
    "gn:feature_code":"PPL",
    "gn:name":"Yakshytsy",
    "gn:population":0,
    "gn:timezone":"Europe/Minsk",
    "iso:country":"BY",
    "name:bel_x_preferred":[
        "\u042f\u043a\u0448\u044b\u0446\u044b"
    ],
    "name:eng_x_preferred":[
        "Yakshitsy"
    ],
    "name:rus_x_preferred":[
        "\u042f\u043a\u0448\u0438\u0446\u044b"
    ],
    "name:und_x_variant":[
        "Yakshytsy"
    ],
    "wof:name":"Yakshytsy",
    "wof:placetype":"locality"
},
  "geometry": {"coordinates":[28.9128,53.6198],"type":"Point"}
}