{
  "type": "Feature",
  "properties": {
    "gn:admin1_code":"3.0",
    "gn:asciiname":"Kodi",
    "gn:country_code":"BY",
    "gn:dem":124,
    "gn:feature_class":"P",
    "gn:feature_code":"PPL",
    "gn:name":"Kodi",
    "gn:population":0,
    "gn:timezone":"Europe/Minsk",
    "iso:country":"BY",
    "name:ceb_x_preferred":[
        "Kodi"
    ],
    "name:deu_x_preferred":[
        "Kodi"
    ],
    "name:fra_x_preferred":[
        "Kodi"
    ],
    "name:nld_x_preferred":[
        "Kodi"
    ],
    "name:rus_x_preferred":[
        "\u041a\u043e\u0434\u0438"
    ],
    "name:swe_x_preferred":[
        "Kodi"
    ],
    "wof:name":"Kodi",
    "wof:placetype":"locality"
},
  "geometry": {"coordinates":[23.5736,53.93899999999999],"type":"Point"}
}