{
  "type": "Feature",
  "properties": {
    "gn:country":"BY",
    "gn:fcode":"PPL",
    "gn:pop":308,
    "iso:country":"BY",
    "name:rus_x_preferred":[
        "\u041e\u0431\u0447\u0430\u043a"
    ],
    "name:unk_x_variant":[
        "Apchak"
    ],
    "qs:name":"Obchak",
    "qs:photos_9r":0,
    "qs:photos_sr":0,
    "qs:pop_sr":"2",
    "wof:name":"Obchak",
    "wof:placetype":"locality",
    "wof:population":308
},
  "geometry": {"coordinates":[27.8136,53.8142],"type":"Point"}
}