{
  "type": "Feature",
  "properties": {
    "gn:admin1_code":"5.0",
    "gn:asciiname":"Rassvetnaya",
    "gn:country_code":"BY",
    "gn:dem":182,
    "gn:feature_class":"P",
    "gn:feature_code":"PPL",
    "gn:name":"Rassvetnaya",
    "gn:population":0,
    "gn:timezone":"Europe/Minsk",
    "iso:country":"BY",
    "name:rus_x_preferred":[
        "\u0420\u0430\u0441\u0441\u0432\u0435\u0442\u043d\u0430\u044f"
    ],
    "wof:name":"Rassvetnaya",
    "wof:placetype":"locality"
},
  "geometry": {"coordinates":[26.7686,53.0599],"type":"Point"}
}