{
  "type": "Feature",
  "properties": {
    "gn:admin1_code":"7.0",
    "gn:asciiname":"Grigorovshchina",
    "gn:country_code":"BY",
    "gn:dem":128,
    "gn:feature_class":"P",
    "gn:feature_code":"PPL",
    "gn:name":"Grigorovshchina",
    "gn:population":0,
    "gn:timezone":"Europe/Minsk",
    "iso:country":"BY",
    "name:rus_x_preferred":[
        "\u0413\u0440\u0438\u0433\u043e\u0440\u043e\u0432\u0449\u0438\u043d\u0430"
    ],
    "wof:name":"Grigorovshchina",
    "wof:placetype":"locality"
},
  "geometry": {"coordinates":[27.0074,55.2796],"type":"Point"}
}