{
  "type": "Feature",
  "properties": {
    "gn:admin1_code":"3.0",
    "gn:asciiname":"Skeldychi",
    "gn:country_code":"BY",
    "gn:dem":151,
    "gn:feature_class":"P",
    "gn:feature_code":"PPL",
    "gn:name":"Skeldychi",
    "gn:population":0,
    "gn:timezone":"Europe/Minsk",
    "iso:country":"BY",
    "name:rus_x_preferred":[
        "\u0421\u043a\u0435\u043b\u044c\u0434\u044b\u0447\u0438"
    ],
    "name:und_x_variant":[
        "Skel\u2019dychi",
        "Skeldychi"
    ],
    "wof:name":"Skeldychi",
    "wof:placetype":"locality"
},
  "geometry": {"coordinates":[24.5822,53.7959],"type":"Point"}
}