{
  "type": "Feature",
  "properties": {
    "gn:admin1_code":"3.0",
    "gn:asciiname":"Misyavichy",
    "gn:country_code":"BY",
    "gn:dem":149,
    "gn:feature_class":"P",
    "gn:feature_code":"PPL",
    "gn:name":"Misyavichy",
    "gn:population":0,
    "gn:timezone":"Europe/Minsk",
    "iso:country":"BY",
    "name:bel_x_preferred":[
        "\u041c\u0456\u0441\u044f\u0432\u0456\u0447\u044b"
    ],
    "name:rus_x_preferred":[
        "\u041c\u0438\u0441\u0435\u0432\u0438\u0447\u0438"
    ],
    "name:und_x_variant":[
        "Misevichi"
    ],
    "wof:name":"Misyavichy",
    "wof:placetype":"locality"
},
  "geometry": {"coordinates":[24.8918,53.8775],"type":"Point"}
}