{
  "type": "Feature",
  "properties": {
    "gn:admin1_code":"5.0",
    "gn:asciiname":"Prudishche",
    "gn:country_code":"BY",
    "gn:dem":290,
    "gn:feature_class":"P",
    "gn:feature_code":"PPL",
    "gn:name":"Prudishche",
    "gn:population":0,
    "gn:timezone":"Europe/Minsk",
    "iso:country":"BY",
    "name:rus_x_preferred":[
        "\u041f\u0440\u0443\u0434\u0438\u0449\u0435"
    ],
    "name:und_x_variant":[
        "Prudzishche",
        "Prudishcha",
        "Prudishche"
    ],
    "wof:name":"Prudishche",
    "wof:placetype":"locality"
},
  "geometry": {"coordinates":[27.6364,54.1817],"type":"Point"}
}