{
  "type": "Feature",
  "properties": {
    "gn:admin1_code":"6.0",
    "gn:asciiname":"Ragozno",
    "gn:country_code":"BY",
    "gn:dem":186,
    "gn:feature_class":"P",
    "gn:feature_code":"PPL",
    "gn:name":"Ragozno",
    "gn:population":0,
    "gn:timezone":"Europe/Minsk",
    "iso:country":"BY",
    "name:rus_x_preferred":[
        "\u0420\u0430\u0433\u043e\u0437\u043d\u043e"
    ],
    "name:und_x_variant":[
        "Rogozna"
    ],
    "wof:name":"Ragozno",
    "wof:placetype":"locality"
},
  "geometry": {"coordinates":[29.98,54.1858],"type":"Point"}
}