{
  "type": "Feature",
  "properties": {
    "gn:admin1_code":"5.0",
    "gn:asciiname":"Zaskavichy",
    "gn:country_code":"BY",
    "gn:dem":148,
    "gn:feature_class":"P",
    "gn:feature_code":"PPL",
    "gn:name":"Zaskavichy",
    "gn:population":0,
    "gn:timezone":"Europe/Minsk",
    "iso:country":"BY",
    "name:bel_x_preferred":[
        "\u0417\u0430\u0441\u043a\u0430\u0432\u0456\u0447\u044b"
    ],
    "name:eng_x_preferred":[
        "Zaskevichi"
    ],
    "name:rus_x_preferred":[
        "\u0417\u0430\u0441\u043a\u043e\u0432\u0438\u0447\u0438"
    ],
    "name:und_x_variant":[
        "Za\u015bkiewicze",
        "Zaskavichy",
        "Zaskovichi"
    ],
    "wof:name":"Zaskavichy",
    "wof:placetype":"locality"
},
  "geometry": {"coordinates":[26.6083,54.3967],"type":"Point"}
}