{
  "type": "Feature",
  "properties": {
    "gn:admin1_code":"2.0",
    "gn:asciiname":"Komsomol'sk",
    "gn:country_code":"BY",
    "gn:dem":121,
    "gn:feature_class":"P",
    "gn:feature_code":"PPL",
    "gn:name":"Komsomol\u2019sk",
    "gn:population":0,
    "gn:timezone":"Europe/Minsk",
    "iso:country":"BY",
    "name:rus_x_preferred":[
        "\u041a\u043e\u043c\u0441\u043e\u043c\u043e\u043b\u044c\u0441\u043a"
    ],
    "name:und_x_variant":[
        "Komsomol\u2019sk"
    ],
    "wof:name":"Komsomol'sk",
    "wof:placetype":"locality"
},
  "geometry": {"coordinates":[30.3094,52.5773],"type":"Point"}
}