{
  "type": "Feature",
  "properties": {
    "gn:admin1_code":"1.0",
    "gn:asciiname":"Bogdany",
    "gn:country_code":"BY",
    "gn:dem":141,
    "gn:feature_class":"P",
    "gn:feature_code":"PPL",
    "gn:name":"Bogdany",
    "gn:population":0,
    "gn:timezone":"Europe/Minsk",
    "iso:country":"BY",
    "name:fra_x_preferred":[
        "Bogdany"
    ],
    "name:pol_x_preferred":[
        "Bogdany"
    ],
    "name:rus_x_preferred":[
        "\u0411\u043e\u0433\u0434\u0430\u043d\u044b"
    ],
    "wof:name":"Bogdany",
    "wof:placetype":"locality"
},
  "geometry": {"coordinates":[24.1812,52.1383],"type":"Point"}
}