{
  "type": "Feature",
  "properties": {
    "gn:admin1_code":"7.0",
    "gn:asciiname":"Malaya Belitsa",
    "gn:country_code":"BY",
    "gn:dem":212,
    "gn:feature_class":"P",
    "gn:feature_code":"PPL",
    "gn:name":"Malaya Belitsa",
    "gn:population":0,
    "gn:timezone":"Europe/Minsk",
    "iso:country":"BY",
    "name:rus_x_preferred":[
        "\u041c\u0430\u043b\u0430\u044f \u0411\u0435\u043b\u0438\u0446\u0430"
    ],
    "wof:name":"Malaya Belitsa",
    "wof:placetype":"locality"
},
  "geometry": {"coordinates":[29.6595,54.6814],"type":"Point"}
}