{
  "type": "Feature",
  "properties": {
    "gn:admin1_code":"6.0",
    "gn:asciiname":"Tsimanava",
    "gn:country_code":"BY",
    "gn:dem":161,
    "gn:feature_class":"P",
    "gn:feature_code":"PPL",
    "gn:name":"Tsimanava",
    "gn:population":0,
    "gn:timezone":"Europe/Minsk",
    "iso:country":"BY",
    "name:bel_x_preferred":[
        "\u0426\u0456\u043c\u0430\u043d\u0430\u0432\u0430"
    ],
    "name:eng_x_preferred":[
        "Timonovo"
    ],
    "name:rus_x_preferred":[
        "\u0422\u0438\u043c\u043e\u043d\u043e\u0432\u043e"
    ],
    "name:und_x_variant":[
        "Tsimanava"
    ],
    "wof:name":"Tsimanava",
    "wof:placetype":"locality"
},
  "geometry": {"coordinates":[31.8916,53.5785],"type":"Point"}
}