{
  "type": "Feature",
  "properties": {
    "gn:admin1_code":"5.0",
    "gn:asciiname":"Klyni",
    "gn:country_code":"BY",
    "gn:dem":168,
    "gn:feature_class":"P",
    "gn:feature_code":"PPL",
    "gn:name":"Klyni",
    "gn:population":0,
    "gn:timezone":"Europe/Minsk",
    "iso:country":"BY",
    "name:rus_x_preferred":[
        "\u041a\u043b\u044b\u043d\u0438"
    ],
    "wof:name":"Klyni",
    "wof:placetype":"locality"
},
  "geometry": {"coordinates":[27.0037,54.53],"type":"Point"}
}