{
  "type": "Feature",
  "properties": {
    "gn:admin1_code":"5.0",
    "gn:asciiname":"Podbzheze",
    "gn:country_code":"BY",
    "gn:dem":194,
    "gn:feature_class":"P",
    "gn:feature_code":"PPL",
    "gn:name":"Podbzheze",
    "gn:population":0,
    "gn:timezone":"Europe/Minsk",
    "iso:country":"BY",
    "name:rus_x_preferred":[
        "\u041f\u043e\u0434\u0431\u0435\u0440\u0435\u0437\u044c\u0435"
    ],
    "name:und_x_variant":[
        "Podbrzezie Pierusze",
        "Podbzheze",
        "Podberez\u2019ye"
    ],
    "wof:name":"Podbzheze",
    "wof:placetype":"locality"
},
  "geometry": {"coordinates":[27.1028,54.6474],"type":"Point"}
}