{
  "type": "Feature",
  "properties": {
    "gn:admin1_code":"3.0",
    "gn:asciiname":"Rymki",
    "gn:country_code":"BY",
    "gn:dem":131,
    "gn:feature_class":"P",
    "gn:feature_code":"PPL",
    "gn:name":"Rymki",
    "gn:population":0,
    "gn:timezone":"Europe/Minsk",
    "iso:country":"BY",
    "name:deu_x_preferred":[
        "Rymki"
    ],
    "name:fra_x_preferred":[
        "Rymki"
    ],
    "name:pol_x_preferred":[
        "Rymki"
    ],
    "name:rus_x_preferred":[
        "\u0420\u044b\u043c\u043a\u0438"
    ],
    "wof:name":"Rymki",
    "wof:placetype":"locality"
},
  "geometry": {"coordinates":[24.882,53.492],"type":"Point"}
}