{
  "type": "Feature",
  "properties": {
    "gn:admin1_code":"7.0",
    "gn:asciiname":"Lonsk",
    "gn:country_code":"BY",
    "gn:dem":119,
    "gn:feature_class":"P",
    "gn:feature_code":"PPL",
    "gn:name":"Lonsk",
    "gn:population":0,
    "gn:timezone":"Europe/Minsk",
    "iso:country":"BY",
    "name:rus_x_preferred":[
        "\u041b\u043e\u043d\u0441\u043a"
    ],
    "wof:name":"Lonsk",
    "wof:placetype":"locality"
},
  "geometry": {"coordinates":[27.4362,55.3523],"type":"Point"}
}