{
  "type": "Feature",
  "properties": {
    "gn:admin1_code":"7.0",
    "gn:asciiname":"Artemy",
    "gn:country_code":"BY",
    "gn:dem":163,
    "gn:feature_class":"P",
    "gn:feature_code":"PPL",
    "gn:name":"Art\u00ebmy",
    "gn:population":0,
    "gn:timezone":"Europe/Minsk",
    "iso:country":"BY",
    "name:rus_x_preferred":[
        "\u0410\u0440\u0442\u0451\u043c\u044b"
    ],
    "name:und_x_variant":[
        "Art\u00ebmy"
    ],
    "wof:name":"Artemy",
    "wof:placetype":"locality"
},
  "geometry": {"coordinates":[27.9521,55.3083],"type":"Point"}
}