{
  "type": "Feature",
  "properties": {
    "gn:admin1_code":"7.0",
    "gn:asciiname":"Navoloki",
    "gn:country_code":"BY",
    "gn:dem":185,
    "gn:feature_class":"P",
    "gn:feature_code":"PPL",
    "gn:name":"Navoloki",
    "gn:population":0,
    "gn:timezone":"Europe/Minsk",
    "iso:country":"BY",
    "name:rus_x_preferred":[
        "\u041d\u0430\u0432\u043e\u043b\u043e\u043a\u0438"
    ],
    "wof:name":"Navoloki",
    "wof:placetype":"locality"
},
  "geometry": {"coordinates":[28.9868,54.6883],"type":"Point"}
}