{
  "type": "Feature",
  "properties": {
    "gn:admin1_code":"5.0",
    "gn:asciiname":"Tucha",
    "gn:country_code":"BY",
    "gn:dem":172,
    "gn:feature_class":"P",
    "gn:feature_code":"PPL",
    "gn:name":"Tucha",
    "gn:population":0,
    "gn:timezone":"Europe/Minsk",
    "iso:country":"BY",
    "name:bel_x_preferred":[
        "\u0422\u0443\u0447\u0430"
    ],
    "name:und_x_variant":[
        "Tucza",
        "Tucha"
    ],
    "wof:name":"Tucha",
    "wof:placetype":"locality"
},
  "geometry": {"coordinates":[26.5429,52.9606],"type":"Point"}
}