{
  "type": "Feature",
  "properties": {
    "gn:admin1_code":"2.0",
    "gn:asciiname":"Hrabyani",
    "gn:country_code":"BY",
    "gn:dem":151,
    "gn:feature_class":"P",
    "gn:feature_code":"PPL",
    "gn:name":"Hrabyani",
    "gn:population":0,
    "gn:timezone":"Europe/Minsk",
    "iso:country":"BY",
    "name:bel_x_preferred":[
        "\u0413\u0440\u0430\u0431\u044f\u043d\u0456"
    ],
    "name:und_x_variant":[
        "Grebeni"
    ],
    "wof:name":"Hrabyani",
    "wof:placetype":"locality"
},
  "geometry": {"coordinates":[28.4167,51.6656],"type":"Point"}
}