{
  "type": "Feature",
  "properties": {
    "gn:admin1_code":"1.0",
    "gn:asciiname":"Goshevo",
    "gn:country_code":"BY",
    "gn:dem":150,
    "gn:feature_class":"P",
    "gn:feature_code":"PPL",
    "gn:name":"Goshevo",
    "gn:population":0,
    "gn:timezone":"Europe/Minsk",
    "iso:country":"BY",
    "name:rus_x_preferred":[
        "\u0413\u043e\u0448\u0435\u0432\u043e"
    ],
    "name:und_x_variant":[
        "Hoszewo",
        "Goshevo"
    ],
    "wof:name":"Goshevo",
    "wof:placetype":"locality"
},
  "geometry": {"coordinates":[25.2288,52.2933],"type":"Point"}
}