{
  "type": "Feature",
  "properties": {
    "gn:country":"BY",
    "gn:fcode":"PPL",
    "gn:population":8300,
    "iso:country":"BY",
    "name:bel_x_preferred":[
        "\u0414\u0437\u044f\u0442\u043b\u0430\u0432\u0430"
    ],
    "name:bul_x_preferred":[
        "\u0414\u044f\u0442\u043b\u043e\u0432\u043e"
    ],
    "name:cat_x_preferred":[
        "Dziat\u0142ava"
    ],
    "name:ceb_x_preferred":[
        "Dzyatlava"
    ],
    "name:ceb_x_variant":[
        "Dziatlava"
    ],
    "name:ces_x_preferred":[
        "\u010ejatlava"
    ],
    "name:ces_x_variant":[
        "Dzjatlava"
    ],
    "name:che_x_preferred":[
        "\u0414\u044f\u0442\u043b\u043e\u0432\u043e"
    ],
    "name:deu_x_preferred":[
        "Dsjatlawa"
    ],
    "name:eng_x_preferred":[
        "Dzyatlava"
    ],
    "name:est_x_preferred":[
        "Dziat\u0142ava"
    ],
    "name:fas_x_preferred":[
        "\u062f\u0632\u06cc\u0627\u062a\u0644\u0627\u0648\u0627"
    ],
    "name:fin_x_preferred":[
        "Dzjatlava"
    ],
    "name:fra_x_preferred":[
        "Dziatlava"
    ],
    "name:frr_x_preferred":[
        "Dsjatlawa"
    ],
    "name:heb_x_preferred":[
        "\u05d6'\u05d8\u05dc"
    ],
    "name:hsb_x_preferred":[
        "Dzjatlawa"
    ],
    "name:ita_x_preferred":[
        "Dzjatlava"
    ],
    "name:jpn_x_preferred":[
        "\u30b8\u30e3\u30c8\u30e9\u30f4\u30a1"
    ],
    "name:lav_x_preferred":[
        "Dzjatlava"
    ],
    "name:lit_x_preferred":[
        "Zietela"
    ],
    "name:nld_x_preferred":[
        "Dzyatlava"
    ],
    "name:nld_x_variant":[
        "Dziatlava"
    ],
    "name:oss_x_preferred":[
        "\u0414\u044f\u0442\u043b\u043e\u0432\u043e"
    ],
    "name:pol_x_preferred":[
        "Zdzi\u0119cio\u0142"
    ],
    "name:ron_x_preferred":[
        "Dziatlava"
    ],
    "name:rus_x_preferred":[
        "\u0414\u044f\u0442\u043b\u043e\u0432\u043e"
    ],
    "name:srp_x_preferred":[
        "\u0414\u0437\u0458\u0430\u0442\u043b\u0430\u0432\u0430"
    ],
    "name:swe_x_preferred":[
        "Dziatlava"
    ],
    "name:szl_x_preferred":[
        "D\u017aat\u0142awa"
    ],
    "name:tat_x_preferred":[
        "\u0414\u0437\u04d9\u0442\u043b\u0430\u0432\u0430"
    ],
    "name:ukr_x_preferred":[
        "\u0414\u044f\u0442\u043b\u043e\u0432\u043e"
    ],
    "name:und_x_variant":[
        "Zdzentsyul"
    ],
    "name:urd_x_preferred":[
        "\u0632\u06cc\u0627\u062a\u0644\u0648\u0648\u0627"
    ],
    "name:yid_x_preferred":[
        "\u05d6\u05e9\u05e2\u05d8\u05dc"
    ],
    "name:zho_x_preferred":[
        "\u4f73\u7279\u6d1b\u6c83"
    ],
    "qs:name":"Dzyatlava",
    "qs:photos_9r":0,
    "qs:photos_sr":0,
    "qs:pop_sr":"5",
    "wd:population":7764,
    "wd:wordcount":576,
    "wof:name":"Dzyatlava",
    "wof:placetype":"locality",
    "wof:population":7764
},
  "geometry": {"coordinates":[25.4068,53.4631],"type":"Point"}
}