{
  "type": "Feature",
  "properties": {
    "gn:country":"BY",
    "gn:fcode":"PPL",
    "gn:pop":8300,
    "iso:country":"BY",
    "name:bel_x_preferred":[
        "\u0414\u0437\u044f\u0442\u043b\u0430\u0432\u0430"
    ],
    "name:bul_x_preferred":[
        "\u0414\u044f\u0442\u043b\u043e\u0432\u043e"
    ],
    "name:cat_x_preferred":[
        "Dziat\u0142ava"
    ],
    "name:chi_x_preferred":[
        "\u4f73\u7279\u6d1b\u6c83"
    ],
    "name:cze_x_preferred":[
        "\u010ejatlava"
    ],
    "name:dut_x_preferred":[
        "Dzyatlava"
    ],
    "name:eng_x_preferred":[
        "Dzyatlava"
    ],
    "name:est_x_preferred":[
        "Dziat\u0142ava"
    ],
    "name:fin_x_preferred":[
        "Dzjatlava"
    ],
    "name:fre_x_preferred":[
        "Dziatlava"
    ],
    "name:ger_x_preferred":[
        "Dsjatlawa"
    ],
    "name:heb_x_preferred":[
        "\u05d6'\u05d8\u05dc"
    ],
    "name:hsb_x_preferred":[
        "Dzjatlawa"
    ],
    "name:lav_x_preferred":[
        "Dzjatlava"
    ],
    "name:lit_x_preferred":[
        "Zietela"
    ],
    "name:pol_x_preferred":[
        "Zdzi\u0119cio\u0142"
    ],
    "name:rus_x_preferred":[
        "\u0414\u044f\u0442\u043b\u043e\u0432\u043e"
    ],
    "name:srp_x_preferred":[
        "\u0414\u0437\u0458\u0430\u0442\u043b\u0430\u0432\u0430"
    ],
    "name:swe_x_preferred":[
        "Dziatlava"
    ],
    "name:tat_x_preferred":[
        "\u0414\u0437\u04d9\u0442\u043b\u0430\u0432\u0430"
    ],
    "name:ukr_x_preferred":[
        "\u0414\u044f\u0442\u043b\u043e\u0432\u043e"
    ],
    "name:unk_x_variant":[
        "Zdzentsyul"
    ],
    "name:yid_x_preferred":[
        "\u05d6\u05e9\u05e2\u05d8\u05dc"
    ],
    "qs:name":"Dzyatlava",
    "qs:photos_9r":0,
    "qs:photos_sr":0,
    "qs:pop_sr":"5",
    "wd:population":7764,
    "wd:wordcount":576,
    "wof:name":"Dzyatlava",
    "wof:placetype":"locality",
    "wof:population":7764
},
  "geometry": {"coordinates":[25.4068,53.4631],"type":"Point"}
}