{
  "type": "Feature",
  "properties": {
    "gn:admin1_code":"3.0",
    "gn:asciiname":"Mosevichi",
    "gn:country_code":"BY",
    "gn:dem":140,
    "gn:feature_class":"P",
    "gn:feature_code":"PPL",
    "gn:name":"Mosevichi",
    "gn:population":0,
    "gn:timezone":"Europe/Minsk",
    "iso:country":"BY",
    "name:rus_x_preferred":[
        "\u041c\u043e\u0441\u0435\u0432\u0438\u0447\u0438"
    ],
    "wof:name":"Mosevichi",
    "wof:placetype":"locality"
},
  "geometry": {"coordinates":[25.357,53.7399],"type":"Point"}
}