{
  "type": "Feature",
  "properties": {
    "gn:admin1_code":"5.0",
    "gn:asciiname":"Sitniki",
    "gn:country_code":"BY",
    "gn:dem":164,
    "gn:feature_class":"P",
    "gn:feature_code":"PPL",
    "gn:name":"Sitniki",
    "gn:population":0,
    "gn:timezone":"Europe/Minsk",
    "iso:country":"BY",
    "name:bak_x_preferred":[
        "\u0421\u0438\u0442\u043d\u0438\u043a\u0438"
    ],
    "name:bel_x_preferred":[
        "\u0421\u0456\u0442\u043d\u0456\u043a\u0456"
    ],
    "name:che_x_preferred":[
        "\u0421\u0438\u0442\u043d\u0438\u043a\u0438"
    ],
    "name:hye_x_preferred":[
        "\u054d\u056b\u057f\u0576\u056b\u056f\u056b"
    ],
    "name:kaz_x_preferred":[
        "\u0421\u0438\u0442\u043d\u0438\u043a\u0438"
    ],
    "name:kir_x_preferred":[
        "\u0421\u0438\u0442\u043d\u0438\u043a\u0438"
    ],
    "name:rus_x_preferred":[
        "\u0421\u0438\u0442\u043d\u0438\u043a\u0438"
    ],
    "name:tat_x_preferred":[
        "\u0421\u0438\u0442\u043d\u0438\u043a\u0438"
    ],
    "wof:name":"Sitniki",
    "wof:placetype":"locality"
},
  "geometry": {"coordinates":[28.1415,53.6206],"type":"Point"}
}