{
  "type": "Feature",
  "properties": {
    "gn:admin1_code":"7.0",
    "gn:asciiname":"Treybshi",
    "gn:country_code":"BY",
    "gn:dem":128,
    "gn:feature_class":"P",
    "gn:feature_code":"PPL",
    "gn:name":"Treybshi",
    "gn:population":0,
    "gn:timezone":"Europe/Minsk",
    "iso:country":"BY",
    "name:rus_x_preferred":[
        "\u0422\u0440\u0435\u0439\u0431\u0448\u0438"
    ],
    "wof:name":"Treybshi",
    "wof:placetype":"locality"
},
  "geometry": {"coordinates":[26.7664,55.3306],"type":"Point"}
}