{
  "type": "Feature",
  "properties": {
    "gn:admin1_code":"7.0",
    "gn:asciiname":"Zhavnina",
    "gn:country_code":"BY",
    "gn:dem":206,
    "gn:feature_class":"P",
    "gn:feature_code":"PPL",
    "gn:name":"Zhavnina",
    "gn:population":0,
    "gn:timezone":"Europe/Minsk",
    "iso:country":"BY",
    "name:rus_x_preferred":[
        "\u0416\u0430\u0432\u043d\u0438\u043d\u0430"
    ],
    "wof:name":"Zhavnina",
    "wof:placetype":"locality"
},
  "geometry": {"coordinates":[28.4028,55.0584],"type":"Point"}
}