{
  "type": "Feature",
  "properties": {
    "gn:admin1_code":"3.0",
    "gn:asciiname":"Sachywlyany",
    "gn:country_code":"BY",
    "gn:dem":193,
    "gn:feature_class":"P",
    "gn:feature_code":"PPL",
    "gn:name":"Sachywlyany",
    "gn:population":0,
    "gn:timezone":"Europe/Minsk",
    "iso:country":"BY",
    "name:bel_x_preferred":[
        "\u0421\u0430\u0447\u044b\u045e\u043b\u044f\u043d\u044b"
    ],
    "name:bel_x_variant":[
        "Sachawlyany",
        "\u0421\u0430\u0447\u0430\u045e\u043b\u044f\u043d\u044b"
    ],
    "name:rus_x_preferred":[
        "\u0421\u043e\u0447\u0435\u0432\u043b\u044f\u043d\u044b"
    ],
    "name:und_x_variant":[
        "Sochevlyany"
    ],
    "wof:name":"Sachywlyany",
    "wof:placetype":"locality"
},
  "geometry": {"coordinates":[25.3898,53.3657],"type":"Point"}
}