{
  "type": "Feature",
  "properties": {
    "gn:admin1_code":"7.0",
    "gn:asciiname":"Svistuny",
    "gn:country_code":"BY",
    "gn:dem":202,
    "gn:feature_class":"P",
    "gn:feature_code":"PPL",
    "gn:name":"Svistuny",
    "gn:population":0,
    "gn:timezone":"Europe/Minsk",
    "iso:country":"BY",
    "name:rus_x_preferred":[
        "\u0421\u0432\u0438\u0441\u0442\u0443\u043d\u044b"
    ],
    "wof:name":"Svistuny",
    "wof:placetype":"locality"
},
  "geometry": {"coordinates":[30.3088,54.7145],"type":"Point"}
}