{
  "type": "Feature",
  "properties": {
    "gn:admin1_code":"3.0",
    "gn:asciiname":"Matsvyeyewtsy",
    "gn:country_code":"BY",
    "gn:dem":172,
    "gn:feature_class":"P",
    "gn:feature_code":"PPL",
    "gn:name":"Matsvyeyewtsy",
    "gn:population":0,
    "gn:timezone":"Europe/Minsk",
    "iso:country":"BY",
    "name:bel_x_preferred":[
        "\u041c\u0430\u0446\u0432\u0435\u0435\u045e\u0446\u044b"
    ],
    "name:bel_x_variant":[
        "\u041c\u0430\u0442\u0432\u0435\u0435\u0432\u0446\u044b"
    ],
    "name:und_x_variant":[
        "Matseyovtse",
        "Matveyevtsy"
    ],
    "wof:name":"Matsvyeyewtsy",
    "wof:placetype":"locality"
},
  "geometry": {"coordinates":[24.5661,53.0598],"type":"Point"}
}