{
  "type": "Feature",
  "properties": {
    "gn:admin1_code":"1.0",
    "gn:asciiname":"Yagodnaya",
    "gn:country_code":"BY",
    "gn:dem":169,
    "gn:feature_class":"P",
    "gn:feature_code":"PPL",
    "gn:name":"Yagodnaya",
    "gn:population":0,
    "gn:timezone":"Europe/Minsk",
    "iso:country":"BY",
    "name:bel_x_preferred":[
        "Yahadnaya"
    ],
    "name:bel_x_variant":[
        "\u042f\u0433\u0430\u0434\u043d\u0430\u044f"
    ],
    "name:rus_x_preferred":[
        "\u042f\u0433\u043e\u0434\u043d\u0430\u044f"
    ],
    "wof:name":"Yagodnaya",
    "wof:placetype":"locality"
},
  "geometry": {"coordinates":[25.5904,53.1911],"type":"Point"}
}