{
  "type": "Feature",
  "properties": {
    "gn:admin1_code":"7.0",
    "gn:asciiname":"Noviki",
    "gn:country_code":"BY",
    "gn:dem":152,
    "gn:feature_class":"P",
    "gn:feature_code":"PPL",
    "gn:name":"Noviki",
    "gn:population":0,
    "gn:timezone":"Europe/Minsk",
    "iso:country":"BY",
    "name:rus_x_preferred":[
        "\u041d\u043e\u0432\u0438\u043a\u0438"
    ],
    "wof:name":"Noviki",
    "wof:placetype":"locality"
},
  "geometry": {"coordinates":[29.9289,55.2094],"type":"Point"}
}