{
  "type": "Feature",
  "properties": {
    "iso:country":"BY",
    "name:bel_x_preferred":[
        "\u0413\u043e\u0440\u0430\u0434 \u0427\u044d\u0440\u044b\u043a\u0430\u045e"
    ],
    "name:bel_x_variant":[
        "\u0427\u044d\u0440\u044b\u043a\u0430\u045e"
    ],
    "name:bul_x_preferred":[
        "\u0427\u0435\u0440\u0438\u043a\u043e\u0432"
    ],
    "name:ceb_x_preferred":[
        "Cherykaw"
    ],
    "name:ces_x_preferred":[
        "\u010ceryka\u016d"
    ],
    "name:che_x_preferred":[
        "\u0427\u0435\u0440\u0438\u043a\u043e\u0432"
    ],
    "name:deu_x_preferred":[
        "Tscherykau"
    ],
    "name:eng_x_preferred":[
        "Cherykaw"
    ],
    "name:est_x_preferred":[
        "\u010ceryka\u016d"
    ],
    "name:fin_x_preferred":[
        "T\u0161erykau"
    ],
    "name:fra_x_preferred":[
        "Tcherykaw"
    ],
    "name:frr_x_preferred":[
        "Tscherykau"
    ],
    "name:heb_x_preferred":[
        "\u05e6'\u05e8\u05d9\u05e7\u05d5\u05d1"
    ],
    "name:hsb_x_preferred":[
        "\u010cerykaw"
    ],
    "name:hye_x_preferred":[
        "\u0549\u0565\u0580\u056b\u056f\u0578\u057e"
    ],
    "name:ita_x_preferred":[
        "\u010c\u0117ryka\u016d"
    ],
    "name:jpn_x_preferred":[
        "\u30c1\u30a7\u30eb\u30a3\u30ab\u30a6"
    ],
    "name:lav_x_preferred":[
        "\u010cerikava"
    ],
    "name:lit_x_preferred":[
        "\u010cerykavas"
    ],
    "name:nld_x_preferred":[
        "Cherykaw"
    ],
    "name:pol_x_preferred":[
        "Czeryk\u00f3w"
    ],
    "name:rus_x_preferred":[
        "\u0427\u0435\u0440\u0438\u043a\u043e\u0432"
    ],
    "name:slv_x_preferred":[
        "\u010cerikov"
    ],
    "name:srp_x_preferred":[
        "\u0427\u0435\u0440\u0438\u043a\u0430\u0432"
    ],
    "name:swe_x_preferred":[
        "Tjeryka\u016d"
    ],
    "name:tat_x_preferred":[
        "\u0427\u0435\u0440\u044b\u043a\u0430\u0443"
    ],
    "name:ukr_x_preferred":[
        "\u0427\u0435\u0440\u0438\u043a\u043e\u0432"
    ],
    "name:unk_x_variant":[
        "Tscherikow"
    ],
    "name:zho_x_preferred":[
        "\u5207\u91cc\u79d1\u592b"
    ],
    "qs:gn_country":"BY",
    "qs:gn_fcode":"PPLA2",
    "qs:gn_pop":7874,
    "qs:name":"Cherikov",
    "qs:name_adm0":"Belarus",
    "qs:name_adm1":"Mahilyowskaya Voblasts'",
    "qs:photos":0,
    "qs:photos_1k":0,
    "qs:photos_9k":0,
    "qs:photos_9r":0,
    "qs:photos_all":0,
    "qs:photos_sr":0,
    "qs:placetype":"Town",
    "qs:pop_sr":"5",
    "qs:woe_adm0":23424765,
    "wd:population":8184,
    "wd:wordcount":366,
    "wof:name":"Cherikov",
    "wof:placetype":"locality",
    "wof:population":8184
},
  "geometry": {"coordinates":[31.3831,53.5689],"type":"Point"}
}