{
  "type": "Feature",
  "properties": {
    "gn:admin1_code":"5.0",
    "gn:asciiname":"Ugly",
    "gn:country_code":"BY",
    "gn:dem":205,
    "gn:feature_class":"P",
    "gn:feature_code":"PPL",
    "gn:name":"Ugly",
    "gn:population":0,
    "gn:timezone":"Europe/Minsk",
    "iso:country":"BY",
    "name:deu_x_preferred":[
        "Ugly"
    ],
    "name:fra_x_preferred":[
        "Ugly"
    ],
    "name:ita_x_preferred":[
        "Ugly"
    ],
    "name:kor_x_preferred":[
        "\uc5b4\uae00\ub9ac"
    ],
    "name:nld_x_preferred":[
        "Ugly"
    ],
    "name:por_x_preferred":[
        "Ugly"
    ],
    "name:rus_x_preferred":[
        "\u0423\u0433\u043b\u044b"
    ],
    "name:tur_x_preferred":[
        "Ugly"
    ],
    "name:ukr_x_preferred":[
        "\u0423\u0433\u043b\u0438"
    ],
    "wof:name":"Ugly",
    "wof:placetype":"locality"
},
  "geometry": {"coordinates":[27.4831,53.7189],"type":"Point"}
}