{
  "type": "Feature",
  "properties": {
    "gn:admin1_code":"1.0",
    "gn:asciiname":"Nalezniki",
    "gn:country_code":"BY",
    "gn:dem":146,
    "gn:feature_class":"P",
    "gn:feature_code":"PPL",
    "gn:name":"Nalezniki",
    "gn:population":0,
    "gn:timezone":"Europe/Minsk",
    "iso:country":"BY",
    "name:rus_x_preferred":[
        "\u041d\u0430\u043b\u0435\u0437\u043d\u0438\u043a\u0438"
    ],
    "wof:name":"Nalezniki",
    "wof:placetype":"locality"
},
  "geometry": {"coordinates":[24.0067,52.2955],"type":"Point"}
}