{
  "type": "Feature",
  "properties": {
    "gn:admin1_code":"7.0",
    "gn:asciiname":"Myanyutsyeva",
    "gn:country_code":"BY",
    "gn:dem":216,
    "gn:feature_class":"P",
    "gn:feature_code":"PPL",
    "gn:name":"Myanyutsyeva",
    "gn:population":0,
    "gn:timezone":"Europe/Minsk",
    "iso:country":"BY",
    "name:bel_x_preferred":[
        "\u041c\u044f\u043d\u044e\u0446\u0435\u0432\u0430"
    ],
    "name:und_x_variant":[
        "Minyutevo",
        "Menyutevo"
    ],
    "wof:name":"Myanyutsyeva",
    "wof:placetype":"locality"
},
  "geometry": {"coordinates":[29.5745,54.7023],"type":"Point"}
}