{
  "type": "Feature",
  "properties": {
    "gn:admin1_code":"6.0",
    "gn:asciiname":"Popovka",
    "gn:country_code":"BY",
    "gn:dem":165,
    "gn:feature_class":"P",
    "gn:feature_code":"PPL",
    "gn:name":"Popovka",
    "gn:population":0,
    "gn:timezone":"Europe/Minsk",
    "iso:country":"BY",
    "name:ceb_x_preferred":[
        "Popovka"
    ],
    "name:est_x_preferred":[
        "Popovka"
    ],
    "name:rus_x_preferred":[
        "\u041f\u043e\u043f\u043e\u0432\u043a\u0430"
    ],
    "name:swe_x_preferred":[
        "Popovka"
    ],
    "wof:name":"Popovka",
    "wof:placetype":"locality"
},
  "geometry": {"coordinates":[32.1073,53.3637],"type":"Point"}
}