{
  "type": "Feature",
  "properties": {
    "gn:admin1_code":"6.0",
    "gn:asciiname":"Zakhody",
    "gn:country_code":"BY",
    "gn:dem":166,
    "gn:feature_class":"P",
    "gn:feature_code":"PPL",
    "gn:name":"Zakhody",
    "gn:population":0,
    "gn:timezone":"Europe/Minsk",
    "iso:country":"BY",
    "name:bel_x_preferred":[
        "\u0417\u0430\u0445\u043e\u0434\u044b"
    ],
    "wof:name":"Zakhody",
    "wof:placetype":"locality"
},
  "geometry": {"coordinates":[30.4587,54.0423],"type":"Point"}
}