{
  "type": "Feature",
  "properties": {
    "gn:admin1_code":"2.0",
    "gn:asciiname":"Prilepovka",
    "gn:country_code":"BY",
    "gn:dem":155,
    "gn:feature_class":"P",
    "gn:feature_code":"PPL",
    "gn:name":"Prilepovka",
    "gn:population":0,
    "gn:timezone":"Europe/Minsk",
    "iso:country":"BY",
    "name:rus_x_preferred":[
        "\u041f\u0440\u0438\u043b\u0435\u043f\u043e\u0432\u043a\u0430"
    ],
    "wof:name":"Prilepovka",
    "wof:placetype":"locality"
},
  "geometry": {"coordinates":[30.6074,53.2808],"type":"Point"}
}