{
  "type": "Feature",
  "properties": {
    "gn:admin1_code":"3.0",
    "gn:asciiname":"Sokolovo",
    "gn:country_code":"BY",
    "gn:dem":178,
    "gn:feature_class":"P",
    "gn:feature_code":"PPL",
    "gn:name":"Sokolovo",
    "gn:population":0,
    "gn:timezone":"Europe/Minsk",
    "iso:country":"BY",
    "name:bel_x_preferred":[
        "Sakalova"
    ],
    "name:bel_x_variant":[
        "\u0421\u0430\u043a\u0430\u043b\u043e\u0432\u0430"
    ],
    "name:rus_x_preferred":[
        "\u0421\u043e\u043a\u043e\u043b\u043e\u0432\u043e"
    ],
    "wof:name":"Sokolovo",
    "wof:placetype":"locality"
},
  "geometry": {"coordinates":[25.2017,53.0474],"type":"Point"}
}