{
  "type": "Feature",
  "properties": {
    "gn:admin1_code":"5.0",
    "gn:asciiname":"Kruglaya",
    "gn:country_code":"BY",
    "gn:dem":150,
    "gn:feature_class":"P",
    "gn:feature_code":"PPL",
    "gn:name":"Kruglaya",
    "gn:population":0,
    "gn:timezone":"Europe/Minsk",
    "iso:country":"BY",
    "name:rus_x_preferred":[
        "\u041a\u0440\u0443\u0433\u043b\u0430\u044f"
    ],
    "wof:name":"Kruglaya",
    "wof:placetype":"locality"
},
  "geometry": {"coordinates":[26.2341,54.0982],"type":"Point"}
}