{
  "type": "Feature",
  "properties": {
    "gn:admin1_code":"5.0",
    "gn:asciiname":"Danilki",
    "gn:country_code":"BY",
    "gn:dem":166,
    "gn:feature_class":"P",
    "gn:feature_code":"PPL",
    "gn:name":"Danilki",
    "gn:population":0,
    "gn:timezone":"Europe/Minsk",
    "iso:country":"BY",
    "name:rus_x_preferred":[
        "\u0414\u0430\u043d\u0438\u043b\u043a\u0438"
    ],
    "wof:name":"Danilki",
    "wof:placetype":"locality"
},
  "geometry": {"coordinates":[26.1535,54.1629],"type":"Point"}
}