{
  "type": "Feature",
  "properties": {
    "gn:admin1_code":"5.0",
    "gn:asciiname":"Aleksandrino",
    "gn:country_code":"BY",
    "gn:dem":213,
    "gn:feature_class":"P",
    "gn:feature_code":"PPL",
    "gn:name":"Aleksandrino",
    "gn:population":0,
    "gn:timezone":"Europe/Minsk",
    "iso:country":"BY",
    "name:rus_x_preferred":[
        "\u0410\u043b\u0435\u043a\u0441\u0430\u043d\u0434\u0440\u0438\u043d\u043e"
    ],
    "wof:name":"Aleksandrino",
    "wof:placetype":"locality"
},
  "geometry": {"coordinates":[27.6953,54.3354],"type":"Point"}
}