{
  "type": "Feature",
  "properties": {
    "gn:admin1_code":"7.0",
    "gn:asciiname":"Gorodets",
    "gn:country_code":"BY",
    "gn:dem":140,
    "gn:feature_class":"P",
    "gn:feature_code":"PPL",
    "gn:name":"Gorodets",
    "gn:population":0,
    "gn:timezone":"Europe/Minsk",
    "iso:country":"BY",
    "name:rus_x_preferred":[
        "\u0413\u043e\u0440\u043e\u0434\u0435\u0446"
    ],
    "wof:name":"Gorodets",
    "wof:placetype":"locality"
},
  "geometry": {"coordinates":[29.0709,55.0591],"type":"Point"}
}