{
  "type": "Feature",
  "properties": {
    "gn:admin1_code":"2.0",
    "gn:asciiname":"Proskurni",
    "gn:country_code":"BY",
    "gn:dem":135,
    "gn:feature_class":"P",
    "gn:feature_code":"PPL",
    "gn:name":"Proskurni",
    "gn:population":0,
    "gn:timezone":"Europe/Minsk",
    "iso:country":"BY",
    "name:eng_x_preferred":[
        "Proskurni"
    ],
    "name:rus_x_preferred":[
        "\u041f\u0440\u043e\u0441\u043a\u0443\u0440\u043d\u0438"
    ],
    "name:und_x_variant":[
        "Praskurni"
    ],
    "wof:name":"Proskurni",
    "wof:placetype":"locality"
},
  "geometry": {"coordinates":[30.0863,52.8095],"type":"Point"}
}