{
  "type": "Feature",
  "properties": {
    "gn:admin1_code":"2.0",
    "gn:asciiname":"Novyye Zhuravichi",
    "gn:country_code":"BY",
    "gn:dem":159,
    "gn:feature_class":"P",
    "gn:feature_code":"PPL",
    "gn:name":"Novyye Zhuravichi",
    "gn:population":0,
    "gn:timezone":"Europe/Minsk",
    "iso:country":"BY",
    "name:eng_x_preferred":[
        "Novyye Zhuravichi"
    ],
    "name:rus_x_preferred":[
        "\u0416\u0443\u0440\u0430\u0432\u0438\u0447\u0438"
    ],
    "name:rus_x_variant":[
        "\u041d\u043e\u0432\u044b\u0435 \u0416\u0443\u0440\u0430\u0432\u0438\u0447\u0438"
    ],
    "name:und_x_variant":[
        "Zhuravichi",
        "Novo-Zhuravichi",
        "Novyye Zhuravichi"
    ],
    "wof:name":"Novyye Zhuravichi",
    "wof:placetype":"locality"
},
  "geometry": {"coordinates":[30.5863,53.2319],"type":"Point"}
}