{
  "type": "Feature",
  "properties": {
    "gn:admin1_code":"5.0",
    "gn:asciiname":"Belino",
    "gn:country_code":"BY",
    "gn:dem":164,
    "gn:feature_class":"P",
    "gn:feature_code":"PPL",
    "gn:name":"Belino",
    "gn:population":0,
    "gn:timezone":"Europe/Minsk",
    "iso:country":"BY",
    "name:rus_x_preferred":[
        "\u0411\u0435\u043b\u0438\u043d\u043e"
    ],
    "wof:name":"Belino",
    "wof:placetype":"locality"
},
  "geometry": {"coordinates":[28.7346,54.0967],"type":"Point"}
}