{
  "type": "Feature",
  "properties": {
    "gn:admin1_code":"1.0",
    "gn:asciiname":"Vyganovo",
    "gn:country_code":"BY",
    "gn:dem":154,
    "gn:feature_class":"P",
    "gn:feature_code":"PPL",
    "gn:name":"Vyganovo",
    "gn:population":0,
    "gn:timezone":"Europe/Minsk",
    "iso:country":"BY",
    "name:rus_x_preferred":[
        "\u0412\u044b\u0433\u0430\u043d\u043e\u0432\u043e"
    ],
    "wof:name":"Vyganovo",
    "wof:placetype":"locality"
},
  "geometry": {"coordinates":[23.4229,52.3575],"type":"Point"}
}