{
  "type": "Feature",
  "properties": {
    "gn:admin1_code":"5.0",
    "gn:asciiname":"Chashin",
    "gn:country_code":"BY",
    "gn:dem":170,
    "gn:feature_class":"P",
    "gn:feature_code":"PPL",
    "gn:name":"Chashin",
    "gn:population":0,
    "gn:timezone":"Europe/Minsk",
    "iso:country":"BY",
    "name:fas_x_preferred":[
        "\u0686\u0634\u06cc\u0646"
    ],
    "name:rus_x_preferred":[
        "\u0427\u0430\u0448\u0438\u043d"
    ],
    "wof:name":"Chashin",
    "wof:placetype":"locality"
},
  "geometry": {"coordinates":[27.2013,53.3409],"type":"Point"}
}