{
  "type": "Feature",
  "properties": {
    "gn:admin1_code":"1.0",
    "gn:asciiname":"Lepesy Malyye",
    "gn:country_code":"BY",
    "gn:dem":144,
    "gn:feature_class":"P",
    "gn:feature_code":"PPL",
    "gn:name":"Lepesy Malyye",
    "gn:population":0,
    "gn:timezone":"Europe/Minsk",
    "iso:country":"BY",
    "name:rus_x_preferred":[
        "\u041b\u0435\u043f\u0435\u0441\u044b \u041c\u0430\u043b\u044b\u0435"
    ],
    "name:und_x_variant":[
        "Malyye Lepesy"
    ],
    "wof:name":"Lepesy Malyye",
    "wof:placetype":"locality"
},
  "geometry": {"coordinates":[24.3868,52.2519],"type":"Point"}
}