{
  "type": "Feature",
  "properties": {
    "gn:admin1_code":"6.0",
    "gn:asciiname":"Pogrebishche",
    "gn:country_code":"BY",
    "gn:dem":200,
    "gn:feature_class":"P",
    "gn:feature_code":"PPL",
    "gn:name":"Pogrebishche",
    "gn:population":0,
    "gn:timezone":"Europe/Minsk",
    "iso:country":"BY",
    "name:rus_x_preferred":[
        "\u041f\u043e\u0433\u0440\u0435\u0431\u0438\u0449\u0435"
    ],
    "wof:name":"Pogrebishche",
    "wof:placetype":"locality"
},
  "geometry": {"coordinates":[29.5143,54.2842],"type":"Point"}
}