{
  "type": "Feature",
  "properties": {
    "gn:admin1_code":"7.0",
    "gn:asciiname":"Malinovshchina",
    "gn:country_code":"BY",
    "gn:dem":144,
    "gn:feature_class":"P",
    "gn:feature_code":"PPL",
    "gn:name":"Malinovshchina",
    "gn:population":0,
    "gn:timezone":"Europe/Minsk",
    "iso:country":"BY",
    "name:rus_x_preferred":[
        "\u041c\u0430\u043b\u0438\u043d\u043e\u0432\u0449\u0438\u043d\u0430"
    ],
    "wof:name":"Malinovshchina",
    "wof:placetype":"locality"
},
  "geometry": {"coordinates":[29.3994,54.7944],"type":"Point"}
}