{
  "type": "Feature",
  "properties": {
    "gn:admin1_code":"6.0",
    "gn:asciiname":"Zalos'ye",
    "gn:country_code":"BY",
    "gn:dem":180,
    "gn:feature_class":"P",
    "gn:feature_code":"PPL",
    "gn:name":"Zalos\u2019ye",
    "gn:population":0,
    "gn:timezone":"Europe/Minsk",
    "iso:country":"BY",
    "name:rus_x_preferred":[
        "\u0417\u0430\u043b\u043e\u0441\u044c\u0435"
    ],
    "name:und_x_variant":[
        "Zalos\u2019ye"
    ],
    "wof:name":"Zalos'ye",
    "wof:placetype":"locality"
},
  "geometry": {"coordinates":[29.5394,54.1473],"type":"Point"}
}