{
  "type": "Feature",
  "properties": {
    "gn:admin1_code":"6.0",
    "gn:asciiname":"Korzeyevo",
    "gn:country_code":"BY",
    "gn:dem":193,
    "gn:feature_class":"P",
    "gn:feature_code":"PPL",
    "gn:name":"Korzeyevo",
    "gn:population":0,
    "gn:timezone":"Europe/Minsk",
    "iso:country":"BY",
    "name:rus_x_preferred":[
        "\u041a\u043e\u0440\u0437\u0435\u0435\u0432\u043e"
    ],
    "name:und_x_variant":[
        "Karzeyevo"
    ],
    "wof:name":"Korzeyevo",
    "wof:placetype":"locality"
},
  "geometry": {"coordinates":[30.6818,54.07899999999999],"type":"Point"}
}