{
  "type": "Feature",
  "properties": {
    "gn:admin1_code":"1.0",
    "gn:asciiname":"Vishavichy",
    "gn:country_code":"BY",
    "gn:dem":138,
    "gn:feature_class":"P",
    "gn:feature_code":"PPL",
    "gn:name":"Vishavichy",
    "gn:population":0,
    "gn:timezone":"Europe/Minsk",
    "iso:country":"BY",
    "name:bel_x_preferred":[
        "\u0412\u0456\u0448\u0430\u0432\u0456\u0447\u044b"
    ],
    "name:und_x_variant":[
        "Wyszewicze",
        "Vishavichy",
        "Vysheviche",
        "Vishevichi"
    ],
    "wof:name":"Vishavichy",
    "wof:placetype":"locality"
},
  "geometry": {"coordinates":[26.1469,52.1324],"type":"Point"}
}