{
  "type": "Feature",
  "properties": {
    "gn:admin1_code":"5.0",
    "gn:asciiname":"Rudenka",
    "gn:country_code":"BY",
    "gn:dem":164,
    "gn:feature_class":"P",
    "gn:feature_code":"PPL",
    "gn:name":"Rudenka",
    "gn:population":0,
    "gn:timezone":"Europe/Minsk",
    "iso:country":"BY",
    "name:eng_x_preferred":[
        "Rudenka"
    ],
    "name:hun_x_preferred":[
        "Rudenka"
    ],
    "name:pol_x_preferred":[
        "Rudenka"
    ],
    "name:rus_x_preferred":[
        "\u0420\u0443\u0434\u0435\u043d\u043a\u0430"
    ],
    "name:ukr_x_preferred":[
        "\u0420\u0443\u0434\u0435\u043d\u043a\u0430"
    ],
    "name:und_x_variant":[
        "Rudenki"
    ],
    "wof:name":"Rudenka",
    "wof:placetype":"locality"
},
  "geometry": {"coordinates":[29.1484,53.7544],"type":"Point"}
}