{
  "type": "Feature",
  "properties": {
    "gn:admin1_code":"1.0",
    "gn:asciiname":"Kotel'nja-Bojarskaja",
    "gn:country_code":"BY",
    "gn:dem":134,
    "gn:feature_class":"P",
    "gn:feature_code":"PPL",
    "gn:name":"\u041a\u043e\u0442\u0435\u043b\u044c\u043d\u044f-\u0411\u043e\u044f\u0440\u0441\u043a\u0430\u044f",
    "gn:population":0,
    "gn:timezone":"Europe/Minsk",
    "iso:country":"BY",
    "name:rus_x_preferred":[
        "Kotel\u2019nya Boyarskaya"
    ],
    "name:rus_x_variant":[
        "\u041a\u043e\u0442\u0435\u043b\u044c\u043d\u044f-\u0411\u043e\u044f\u0440\u0441\u043a\u0430\u044f"
    ],
    "name:und_x_variant":[
        "Kotel\u2019nya Boyarska"
    ],
    "wof:name":"Kotel'nja-Bojarskaja",
    "wof:placetype":"neighbourhood"
},
  "geometry": {"coordinates":[23.6915,52.034],"type":"Point"}
}