{
  "type": "Feature",
  "properties": {
    "gn:admin1_code":"7.0",
    "gn:asciiname":"Okuni",
    "gn:country_code":"BY",
    "gn:dem":237,
    "gn:feature_class":"P",
    "gn:feature_code":"PPL",
    "gn:name":"Okuni",
    "gn:population":0,
    "gn:timezone":"Europe/Minsk",
    "iso:country":"BY",
    "name:rus_x_preferred":[
        "\u041e\u043a\u0443\u043d\u0438"
    ],
    "wof:name":"Okuni",
    "wof:placetype":"locality"
},
  "geometry": {"coordinates":[29.981,55.6578],"type":"Point"}
}