{
  "type": "Feature",
  "properties": {
    "gn:admin1_code":"6.0",
    "gn:asciiname":"Novobrashchino",
    "gn:country_code":"BY",
    "gn:dem":198,
    "gn:feature_class":"P",
    "gn:feature_code":"PPL",
    "gn:name":"Novobrashchino",
    "gn:population":0,
    "gn:timezone":"Europe/Minsk",
    "iso:country":"BY",
    "name:rus_x_preferred":[
        "\u041d\u043e\u0432\u043e\u0431\u0440\u0430\u0449\u0438\u043d\u043e"
    ],
    "name:und_x_variant":[
        "Novoye Brashchino"
    ],
    "wof:name":"Novobrashchino",
    "wof:placetype":"locality"
},
  "geometry": {"coordinates":[30.0909,54.2465],"type":"Point"}
}