{
  "type": "Feature",
  "properties": {
    "gn:admin1_code":"3.0",
    "gn:asciiname":"Ponarka",
    "gn:country_code":"BY",
    "gn:dem":225,
    "gn:feature_class":"P",
    "gn:feature_code":"PPL",
    "gn:name":"Ponarka",
    "gn:population":0,
    "gn:timezone":"Europe/Minsk",
    "iso:country":"BY",
    "name:rus_x_preferred":[
        "\u041f\u043e\u043d\u0430\u0440\u043a\u0430"
    ],
    "wof:name":"Ponarka",
    "wof:placetype":"locality"
},
  "geometry": {"coordinates":[26.2096,54.3572],"type":"Point"}
}