{
  "type": "Feature",
  "properties": {
    "gn:admin1_code":"7.0",
    "gn:asciiname":"Sovetskaya",
    "gn:country_code":"BY",
    "gn:dem":208,
    "gn:feature_class":"P",
    "gn:feature_code":"PPL",
    "gn:name":"Sovetskaya",
    "gn:population":0,
    "gn:timezone":"Europe/Minsk",
    "iso:country":"BY",
    "name:rus_x_preferred":[
        "\u0421\u043e\u0432\u0435\u0442\u0441\u043a\u0430\u044f"
    ],
    "wof:name":"Sovetskaya",
    "wof:placetype":"locality"
},
  "geometry": {"coordinates":[30.1127,54.6663],"type":"Point"}
}