{
  "type": "Feature",
  "properties": {
    "gn:admin1_code":"5.0",
    "gn:asciiname":"Smogorovka",
    "gn:country_code":"BY",
    "gn:dem":175,
    "gn:feature_class":"P",
    "gn:feature_code":"PPL",
    "gn:name":"Smogorovka",
    "gn:population":0,
    "gn:timezone":"Europe/Minsk",
    "iso:country":"BY",
    "name:rus_x_preferred":[
        "\u0421\u043c\u043e\u0433\u043e\u0440\u043e\u0432\u043a\u0430"
    ],
    "wof:name":"Smogorovka",
    "wof:placetype":"locality"
},
  "geometry": {"coordinates":[27.9474,53.742],"type":"Point"}
}