{
  "type": "Feature",
  "properties": {
    "gn:admin1_code":"6.0",
    "gn:asciiname":"Taymanava",
    "gn:country_code":"BY",
    "gn:dem":143,
    "gn:feature_class":"P",
    "gn:feature_code":"PPL",
    "gn:name":"Taymanava",
    "gn:population":0,
    "gn:timezone":"Europe/Minsk",
    "iso:country":"BY",
    "name:bel_x_preferred":[
        "\u0422\u0430\u0439\u043c\u0430\u043d\u0430\u0432\u0430"
    ],
    "name:und_x_variant":[
        "Taimanovo",
        "Taymanovo",
        "Taymonovo",
        "Taymanava"
    ],
    "wof:name":"Taymanava",
    "wof:placetype":"locality"
},
  "geometry": {"coordinates":[30.2845,53.4003],"type":"Point"}
}