{
  "type": "Feature",
  "properties": {
    "gn:admin1_code":"3.0",
    "gn:asciiname":"Biryulichi",
    "gn:country_code":"BY",
    "gn:dem":107,
    "gn:feature_class":"P",
    "gn:feature_code":"PPL",
    "gn:name":"Biryulichi",
    "gn:population":0,
    "gn:timezone":"Europe/Minsk",
    "iso:country":"BY",
    "name:bel_x_preferred":[
        "Birulichy"
    ],
    "name:bel_x_variant":[
        "\u0411\u0456\u0440\u0443\u043b\u0456\u0447\u044b"
    ],
    "name:rus_x_preferred":[
        "\u0411\u0438\u0440\u044e\u043b\u0438\u0447\u0438"
    ],
    "name:rus_x_variant":[
        "\u0411\u0438\u0440\u0443\u043b\u0438\u0447\u0438"
    ],
    "name:und_x_variant":[
        "Birulichi"
    ],
    "wof:name":"Biryulichi",
    "wof:placetype":"locality"
},
  "geometry": {"coordinates":[24.1895,53.5766],"type":"Point"}
}