{
  "type": "Feature",
  "properties": {
    "gn:admin1_code":"7.0",
    "gn:asciiname":"Simanovo",
    "gn:country_code":"BY",
    "gn:dem":266,
    "gn:feature_class":"P",
    "gn:feature_code":"PPL",
    "gn:name":"Simanovo",
    "gn:population":0,
    "gn:timezone":"Europe/Minsk",
    "iso:country":"BY",
    "name:rus_x_preferred":[
        "\u0421\u0438\u043c\u0430\u043d\u043e\u0432\u043e"
    ],
    "name:und_x_variant":[
        "Simonovo"
    ],
    "wof:name":"Simanovo",
    "wof:placetype":"locality"
},
  "geometry": {"coordinates":[30.7553,55.1478],"type":"Point"}
}