{
  "type": "Feature",
  "properties": {
    "gn:admin1_code":"7.0",
    "gn:asciiname":"Belevichi",
    "gn:country_code":"BY",
    "gn:dem":168,
    "gn:feature_class":"P",
    "gn:feature_code":"PPL",
    "gn:name":"Belevichi",
    "gn:population":0,
    "gn:timezone":"Europe/Minsk",
    "iso:country":"BY",
    "name:rus_x_preferred":[
        "\u0411\u0435\u043b\u0435\u0432\u0438\u0447\u0438"
    ],
    "wof:name":"Belevichi",
    "wof:placetype":"locality"
},
  "geometry": {"coordinates":[27.4718,55.0967],"type":"Point"}
}