{
  "type": "Feature",
  "properties": {
    "gn:admin1_code":"7.0",
    "gn:asciiname":"Ryzhanki",
    "gn:country_code":"BY",
    "gn:dem":184,
    "gn:feature_class":"P",
    "gn:feature_code":"PPL",
    "gn:name":"Ryzhanki",
    "gn:population":0,
    "gn:timezone":"Europe/Minsk",
    "iso:country":"BY",
    "name:rus_x_preferred":[
        "\u0420\u044b\u0436\u0430\u043d\u043a\u0438"
    ],
    "wof:name":"Ryzhanki",
    "wof:placetype":"locality"
},
  "geometry": {"coordinates":[29.5138,54.6453],"type":"Point"}
}