{
  "type": "Feature",
  "properties": {
    "gn:admin1_code":"7.0",
    "gn:asciiname":"Lipki",
    "gn:country_code":"BY",
    "gn:dem":237,
    "gn:feature_class":"P",
    "gn:feature_code":"PPL",
    "gn:name":"Lipki",
    "gn:population":0,
    "gn:timezone":"Europe/Minsk",
    "iso:country":"BY",
    "name:bel_x_preferred":[
        "\u041b\u0456\u043f\u043a\u0456"
    ],
    "name:ceb_x_preferred":[
        "Lipki"
    ],
    "name:deu_x_preferred":[
        "Lipki"
    ],
    "name:hye_x_preferred":[
        "\u053c\u056b\u057a\u056f\u056b"
    ],
    "name:ind_x_preferred":[
        "Lipki"
    ],
    "name:pol_x_preferred":[
        "Lipki"
    ],
    "name:rus_x_preferred":[
        "\u041b\u0438\u043f\u043a\u0438"
    ],
    "name:ukr_x_preferred":[
        "\u041b\u0456\u043f\u043a\u0456"
    ],
    "wof:name":"Lipki",
    "wof:placetype":"locality"
},
  "geometry": {"coordinates":[28.9153,54.7304],"type":"Point"}
}