{
  "type": "Feature",
  "properties": {
    "gn:admin1_code":"7.0",
    "gn:asciiname":"Buboli",
    "gn:country_code":"BY",
    "gn:dem":136,
    "gn:feature_class":"P",
    "gn:feature_code":"PPL",
    "gn:name":"Buboli",
    "gn:population":0,
    "gn:timezone":"Europe/Minsk",
    "iso:country":"BY",
    "name:rus_x_preferred":[
        "\u0411\u0443\u0431\u043e\u043b\u0438"
    ],
    "wof:name":"Buboli",
    "wof:placetype":"locality"
},
  "geometry": {"coordinates":[29.2855,55.2612],"type":"Point"}
}