{
  "type": "Feature",
  "properties": {
    "gn:admin1_code":"7.0",
    "gn:asciiname":"Lobany",
    "gn:country_code":"BY",
    "gn:dem":184,
    "gn:feature_class":"P",
    "gn:feature_code":"PPL",
    "gn:name":"Lobany",
    "gn:population":0,
    "gn:timezone":"Europe/Minsk",
    "iso:country":"BY",
    "name:rus_x_preferred":[
        "\u041b\u043e\u0431\u0430\u043d\u044b"
    ],
    "wof:name":"Lobany",
    "wof:placetype":"locality"
},
  "geometry": {"coordinates":[30.7123,54.6658],"type":"Point"}
}