{
  "type": "Feature",
  "properties": {
    "gn:admin1_code":"7.0",
    "gn:asciiname":"Volosachi",
    "gn:country_code":"BY",
    "gn:dem":200,
    "gn:feature_class":"P",
    "gn:feature_code":"PPL",
    "gn:name":"Volosachi",
    "gn:population":0,
    "gn:timezone":"Europe/Minsk",
    "iso:country":"BY",
    "name:rus_x_preferred":[
        "\u0412\u043e\u043b\u043e\u0441\u0430\u0447\u0438"
    ],
    "wof:name":"Volosachi",
    "wof:placetype":"locality"
},
  "geometry": {"coordinates":[28.8469,54.5809],"type":"Point"}
}