{
  "type": "Feature",
  "properties": {
    "gn:admin1_code":"7.0",
    "gn:asciiname":"Shemeli",
    "gn:country_code":"BY",
    "gn:dem":170,
    "gn:feature_class":"P",
    "gn:feature_code":"PPL",
    "gn:name":"Shemeli",
    "gn:population":0,
    "gn:timezone":"Europe/Minsk",
    "iso:country":"BY",
    "name:rus_x_preferred":[
        "\u0428\u0435\u043c\u0435\u043b\u0438"
    ],
    "wof:name":"Shemeli",
    "wof:placetype":"locality"
},
  "geometry": {"coordinates":[30.0937,55.8309],"type":"Point"}
}