{
  "type": "Feature",
  "properties": {
    "gn:admin1_code":"7.0",
    "gn:asciiname":"Krasnaya Khar'kovka",
    "gn:country_code":"BY",
    "gn:dem":182,
    "gn:feature_class":"P",
    "gn:feature_code":"PPL",
    "gn:name":"Krasnaya Khar\u2019kovka",
    "gn:population":0,
    "gn:timezone":"Europe/Minsk",
    "iso:country":"BY",
    "name:rus_x_preferred":[
        "\u041a\u0440\u0430\u0441\u043d\u0430\u044f \u0425\u0430\u0440\u044c\u043a\u043e\u0432\u043a\u0430"
    ],
    "name:und_x_variant":[
        "Krasnaya Khar\u2019kovka"
    ],
    "wof:name":"Krasnaya Khar'kovka",
    "wof:placetype":"locality"
},
  "geometry": {"coordinates":[30.4048,54.4615],"type":"Point"}
}