{
  "type": "Feature",
  "properties": {
    "gn:admin1_code":"6.0",
    "gn:asciiname":"Mostok",
    "gn:country_code":"BY",
    "gn:dem":169,
    "gn:feature_class":"P",
    "gn:feature_code":"PPL",
    "gn:name":"Mostok",
    "gn:population":0,
    "gn:timezone":"Europe/Minsk",
    "iso:country":"BY",
    "name:rus_x_preferred":[
        "\u041c\u043e\u0441\u0442\u043e\u043a"
    ],
    "wof:name":"Mostok",
    "wof:placetype":"locality"
},
  "geometry": {"coordinates":[31.2849,53.7405],"type":"Point"}
}