{
  "type": "Feature",
  "properties": {
    "gn:admin1_code":"3.0",
    "gn:asciiname":"Zubrovo",
    "gn:country_code":"BY",
    "gn:dem":128,
    "gn:feature_class":"P",
    "gn:feature_code":"PPL",
    "gn:name":"Zubrovo",
    "gn:population":0,
    "gn:timezone":"Europe/Minsk",
    "iso:country":"BY",
    "name:rus_x_preferred":[
        "\u0417\u0443\u0431\u0440\u043e\u0432\u043e"
    ],
    "name:und_x_variant":[
        "Zhubrovo"
    ],
    "wof:name":"Zubrovo",
    "wof:placetype":"locality"
},
  "geometry": {"coordinates":[24.4776,53.92676],"type":"Point"}
}