{
  "type": "Feature",
  "properties": {
    "gn:admin1_code":"6.0",
    "gn:asciiname":"Krasivyy",
    "gn:country_code":"BY",
    "gn:dem":174,
    "gn:feature_class":"P",
    "gn:feature_code":"PPL",
    "gn:name":"Krasivyy",
    "gn:population":0,
    "gn:timezone":"Europe/Minsk",
    "iso:country":"BY",
    "wof:name":"Krasivyy",
    "wof:placetype":"locality"
},
  "geometry": {"coordinates":[31.46111,53.81222],"type":"Point"}
}