{
  "type": "Feature",
  "properties": {
    "gn:admin1_code":"7.0",
    "gn:asciiname":"Stryzhava",
    "gn:country_code":"BY",
    "gn:dem":137,
    "gn:feature_class":"P",
    "gn:feature_code":"PPL",
    "gn:name":"Stryzhava",
    "gn:population":0,
    "gn:timezone":"Europe/Minsk",
    "iso:country":"BY",
    "name:bel_x_preferred":[
        "\u0421\u0442\u0440\u044b\u0436\u0430\u0432\u0430"
    ],
    "name:und_x_variant":[
        "Strizhevo"
    ],
    "wof:name":"Stryzhava",
    "wof:placetype":"locality"
},
  "geometry": {"coordinates":[29.2733,55.082],"type":"Point"}
}