{
  "type": "Feature",
  "properties": {
    "gn:admin1_code":"3.0",
    "gn:asciiname":"Tsyryn",
    "gn:country_code":"BY",
    "gn:dem":159,
    "gn:feature_class":"P",
    "gn:feature_code":"PPL",
    "gn:name":"Tsyryn",
    "gn:population":0,
    "gn:timezone":"Europe/Minsk",
    "iso:country":"BY",
    "name:bel_x_preferred":[
        "\u0426\u044b\u0440\u044b\u043d"
    ],
    "name:eng_x_preferred":[
        "Tsirin"
    ],
    "name:rus_x_preferred":[
        "\u0426\u0438\u0440\u0438\u043d"
    ],
    "name:und_x_variant":[
        "Cyryn",
        "Tsyryn"
    ],
    "wof:name":"Tsyryn",
    "wof:placetype":"locality"
},
  "geometry": {"coordinates":[26.1575,53.4077],"type":"Point"}
}