{
  "type": "Feature",
  "properties": {
    "gn:admin1_code":"3.0",
    "gn:asciiname":"Bor",
    "gn:country_code":"BY",
    "gn:dem":136,
    "gn:feature_class":"P",
    "gn:feature_code":"PPL",
    "gn:name":"Bor",
    "gn:population":0,
    "gn:timezone":"Europe/Minsk",
    "iso:country":"BY",
    "name:bel_x_preferred":[
        "\u0411\u043e\u0440"
    ],
    "name:und_x_variant":[
        "Bur"
    ],
    "wof:name":"Bor",
    "wof:placetype":"locality"
},
  "geometry": {"coordinates":[26.1528,53.7636],"type":"Point"}
}