{
  "type": "Feature",
  "properties": {
    "gn:admin1_code":"5.0",
    "gn:asciiname":"Novyy Rozhan",
    "gn:country_code":"BY",
    "gn:dem":150,
    "gn:feature_class":"P",
    "gn:feature_code":"PPL",
    "gn:name":"Novyy Rozhan",
    "gn:population":0,
    "gn:timezone":"Europe/Minsk",
    "iso:country":"BY",
    "name:rus_x_preferred":[
        "\u041d\u043e\u0432\u044b\u0439 \u0420\u043e\u0436\u0430\u043d"
    ],
    "name:und_x_variant":[
        "Ro\u017can Nowy",
        "Rozhan Novy",
        "Novyy Rozhan"
    ],
    "wof:name":"Novyy Rozhan",
    "wof:placetype":"locality"
},
  "geometry": {"coordinates":[27.1117,52.7915],"type":"Point"}
}