{
  "type": "Feature",
  "properties": {
    "gn:admin1_code":"5.0",
    "gn:asciiname":"Skawshyn",
    "gn:country_code":"BY",
    "gn:dem":139,
    "gn:feature_class":"P",
    "gn:feature_code":"PPL",
    "gn:name":"Skawshyn",
    "gn:population":0,
    "gn:timezone":"Europe/Minsk",
    "iso:country":"BY",
    "name:bel_x_preferred":[
        "\u0421\u043a\u0430\u045e\u0448\u044b\u043d"
    ],
    "name:eng_x_preferred":[
        "Skavshin"
    ],
    "name:rus_x_preferred":[
        "\u0421\u043a\u043e\u0432\u0448\u0438\u043d"
    ],
    "name:und_x_variant":[
        "Shavshin",
        "Skawshyn",
        "Skovshin"
    ],
    "wof:name":"Skawshyn",
    "wof:placetype":"locality"
},
  "geometry": {"coordinates":[27.8393,52.5346],"type":"Point"}
}