{
  "type": "Feature",
  "properties": {
    "gn:admin1_code":"7.0",
    "gn:asciiname":"Punty",
    "gn:country_code":"BY",
    "gn:dem":163,
    "gn:feature_class":"P",
    "gn:feature_code":"PPL",
    "gn:name":"Punty",
    "gn:population":0,
    "gn:timezone":"Europe/Minsk",
    "iso:country":"BY",
    "name:rus_x_preferred":[
        "\u041f\u0443\u043d\u0442\u044b"
    ],
    "wof:name":"Punty",
    "wof:placetype":"locality"
},
  "geometry": {"coordinates":[28.8543,54.8719],"type":"Point"}
}