{
  "type": "Feature",
  "properties": {
    "gn:admin1_code":"5.0",
    "gn:asciiname":"Nalazy",
    "gn:country_code":"BY",
    "gn:dem":158,
    "gn:feature_class":"P",
    "gn:feature_code":"PPL",
    "gn:name":"Nalazy",
    "gn:population":0,
    "gn:timezone":"Europe/Minsk",
    "iso:country":"BY",
    "name:rus_x_preferred":[
        "\u041d\u0430\u043b\u0430\u0437\u044b"
    ],
    "wof:name":"Nalazy",
    "wof:placetype":"locality"
},
  "geometry": {"coordinates":[28.9958,53.6601],"type":"Point"}
}