{
  "type": "Feature",
  "properties": {
    "gn:admin1_code":"7.0",
    "gn:asciiname":"Pyatnitsy",
    "gn:country_code":"BY",
    "gn:dem":149,
    "gn:feature_class":"P",
    "gn:feature_code":"PPL",
    "gn:name":"Pyatnitsy",
    "gn:population":0,
    "gn:timezone":"Europe/Minsk",
    "iso:country":"BY",
    "name:rus_x_preferred":[
        "\u041f\u044f\u0442\u043d\u0438\u0446\u044b"
    ],
    "name:und_x_variant":[
        "Pyatnitsa"
    ],
    "wof:name":"Pyatnitsy",
    "wof:placetype":"locality"
},
  "geometry": {"coordinates":[28.7322,55.1692],"type":"Point"}
}