{
  "type": "Feature",
  "properties": {
    "gn:admin1_code":"0.0",
    "gn:asciiname":"Grodno",
    "gn:country_code":"BY",
    "gn:dem":182,
    "gn:feature_class":"P",
    "gn:feature_code":"PPL",
    "gn:name":"Grodno",
    "gn:population":0,
    "gn:timezone":"Europe/Minsk",
    "iso:country":"BY",
    "name:rus_x_preferred":[
        "\u0413\u0440\u043e\u0434\u043d\u043e"
    ],
    "name:und_x_variant":[
        "Gradno"
    ],
    "wof:name":"Grodno",
    "wof:placetype":"locality"
},
  "geometry": {"coordinates":[23.8942,53.62865],"type":"Point"}
}