{
  "type": "Feature",
  "properties": {
    "gn:admin1_code":"6.0",
    "gn:asciiname":"Kalinino",
    "gn:country_code":"BY",
    "gn:dem":138,
    "gn:feature_class":"P",
    "gn:feature_code":"PPL",
    "gn:name":"Kalinino",
    "gn:population":0,
    "gn:timezone":"Europe/Minsk",
    "iso:country":"BY",
    "name:ceb_x_preferred":[
        "Kalinino"
    ],
    "name:deu_x_preferred":[
        "Kalinino"
    ],
    "name:kat_x_preferred":[
        "\u10d9\u10d0\u10da\u10d8\u10dc\u10d8\u10dc\u10dd"
    ],
    "name:rus_x_preferred":[
        "\u041f\u043e\u0441\u0451\u043b\u043e\u043a \u041a\u0430\u043b\u0438\u043d\u0438\u043d\u0430"
    ],
    "name:swe_x_preferred":[
        "Kalinino"
    ],
    "name:und_x_variant":[
        "Pos\u00eblok Kalinina",
        "Kalinino"
    ],
    "wof:name":"Kalinino",
    "wof:placetype":"locality"
},
  "geometry": {"coordinates":[30.3178,53.3776],"type":"Point"}
}