{
  "type": "Feature",
  "properties": {
    "gn:admin1_code":"6.0",
    "gn:asciiname":"Zayachen'ye",
    "gn:country_code":"BY",
    "gn:dem":142,
    "gn:feature_class":"P",
    "gn:feature_code":"PPL",
    "gn:name":"Zayachen\u2019ye",
    "gn:population":0,
    "gn:timezone":"Europe/Minsk",
    "iso:country":"BY",
    "name:rus_x_preferred":[
        "\u0417\u0430\u044f\u0447\u0435\u043d\u044c\u0435"
    ],
    "name:und_x_variant":[
        "Zayachen\u2019ye"
    ],
    "wof:name":"Zayachen'ye",
    "wof:placetype":"locality"
},
  "geometry": {"coordinates":[30.2663,53.43899999999999],"type":"Point"}
}