{
  "type": "Feature",
  "properties": {
    "gn:admin1_code":"6.0",
    "gn:asciiname":"Kudlachev",
    "gn:country_code":"BY",
    "gn:dem":177,
    "gn:feature_class":"P",
    "gn:feature_code":"PPL",
    "gn:name":"Kudlachev",
    "gn:population":0,
    "gn:timezone":"Europe/Minsk",
    "iso:country":"BY",
    "name:rus_x_preferred":[
        "\u041a\u0443\u0434\u043b\u0430\u0447\u0435\u0432"
    ],
    "wof:name":"Kudlachev",
    "wof:placetype":"locality"
},
  "geometry": {"coordinates":[32.2617,53.1409],"type":"Point"}
}