{
  "type": "Feature",
  "properties": {
    "gn:admin1_code":"6.0",
    "gn:asciiname":"Lugovoy",
    "gn:country_code":"BY",
    "gn:dem":165,
    "gn:feature_class":"P",
    "gn:feature_code":"PPL",
    "gn:name":"Lugovoy",
    "gn:population":0,
    "gn:timezone":"Europe/Minsk",
    "iso:country":"BY",
    "name:deu_x_preferred":[
        "Lugowoi"
    ],
    "name:hye_x_preferred":[
        "\u053c\u0578\u0582\u0563\u0578\u057e\u0578\u0575"
    ],
    "name:pol_x_preferred":[
        "\u0141ugowoj"
    ],
    "name:rus_x_preferred":[
        "\u041b\u0443\u0433\u043e\u0432\u043e\u0439"
    ],
    "name:ukr_x_preferred":[
        "\u041b\u0443\u0433\u043e\u0432\u0438\u0439"
    ],
    "wof:name":"Lugovoy",
    "wof:placetype":"locality"
},
  "geometry": {"coordinates":[32.47306,53.49222],"type":"Point"}
}