{
  "type": "Feature",
  "properties": {
    "gn:admin1_code":"6.0",
    "gn:asciiname":"Palyashchitsy",
    "gn:country_code":"BY",
    "gn:dem":195,
    "gn:feature_class":"P",
    "gn:feature_code":"PPL",
    "gn:name":"Palyashchitsy",
    "gn:population":0,
    "gn:timezone":"Europe/Minsk",
    "iso:country":"BY",
    "name:rus_x_preferred":[
        "\u041f\u0430\u043b\u044f\u0449\u0438\u0446\u044b"
    ],
    "name:und_x_variant":[
        "Polyashchitsy",
        "Polyashchitsa",
        "Palyashchitsy"
    ],
    "wof:name":"Palyashchitsy",
    "wof:placetype":"locality"
},
  "geometry": {"coordinates":[31.1114,54.26],"type":"Point"}
}