{
  "type": "Feature",
  "properties": {
    "gn:admin1_code":"5.0",
    "gn:asciiname":"Voroshilki",
    "gn:country_code":"BY",
    "gn:dem":199,
    "gn:feature_class":"P",
    "gn:feature_code":"PPL",
    "gn:name":"Voroshilki",
    "gn:population":0,
    "gn:timezone":"Europe/Minsk",
    "iso:country":"BY",
    "name:rus_x_preferred":[
        "\u0412\u043e\u0440\u043e\u0448\u0438\u043b\u043a\u0438"
    ],
    "name:und_x_variant":[
        "Voroshylki",
        "Woroszy\u0142ki",
        "Voroshilki"
    ],
    "wof:name":"Voroshilki",
    "wof:placetype":"locality"
},
  "geometry": {"coordinates":[26.4204,54.8931],"type":"Point"}
}