{
  "type": "Feature",
  "properties": {
    "gn:admin1_code":"7.0",
    "gn:asciiname":"Vasiliny Pervyye",
    "gn:country_code":"BY",
    "gn:dem":129,
    "gn:feature_class":"P",
    "gn:feature_code":"PPL",
    "gn:name":"Vasiliny Pervyye",
    "gn:population":0,
    "gn:timezone":"Europe/Minsk",
    "iso:country":"BY",
    "name:rus_x_preferred":[
        "\u0412\u0430\u0441\u0438\u043b\u0438\u043d\u044b \u041f\u0435\u0440\u0432\u044b\u0435"
    ],
    "name:und_x_variant":[
        "Vasiliny"
    ],
    "wof:name":"Vasiliny Pervyye",
    "wof:placetype":"locality"
},
  "geometry": {"coordinates":[26.9193,55.2766],"type":"Point"}
}