{
  "type": "Feature",
  "properties": {
    "gn:admin1_code":"5.0",
    "gn:asciiname":"Ostrovchitsy",
    "gn:country_code":"BY",
    "gn:dem":158,
    "gn:feature_class":"P",
    "gn:feature_code":"PPL",
    "gn:name":"Ostrovchitsy",
    "gn:population":0,
    "gn:timezone":"Europe/Minsk",
    "iso:country":"BY",
    "name:rus_x_preferred":[
        "\u041e\u0441\u0442\u0440\u043e\u0432\u0447\u0438\u0446\u044b"
    ],
    "name:und_x_variant":[
        "Ma\u0142e Ostrowczyce",
        "Male Ostrovchytse",
        "Ostrovchitsy"
    ],
    "wof:name":"Ostrovchitsy",
    "wof:placetype":"locality"
},
  "geometry": {"coordinates":[26.7348,52.8956],"type":"Point"}
}