{
  "type": "Feature",
  "properties": {
    "gn:admin1_code":"5.0",
    "gn:asciiname":"Zastarin'ye",
    "gn:country_code":"BY",
    "gn:dem":196,
    "gn:feature_class":"P",
    "gn:feature_code":"PPL",
    "gn:name":"Zastarin\u2019ye",
    "gn:population":0,
    "gn:timezone":"Europe/Minsk",
    "iso:country":"BY",
    "name:rus_x_preferred":[
        "\u0417\u0430\u0441\u0442\u0430\u0440\u0438\u043d\u044c\u0435"
    ],
    "name:und_x_variant":[
        "Zastarin\u2019ye"
    ],
    "wof:name":"Zastarin'ye",
    "wof:placetype":"locality"
},
  "geometry": {"coordinates":[27.4812,53.6474],"type":"Point"}
}