{
  "type": "Feature",
  "properties": {
    "gn:admin1_code":"3.0",
    "gn:asciiname":"Kashubintsy",
    "gn:country_code":"BY",
    "gn:dem":113,
    "gn:feature_class":"P",
    "gn:feature_code":"PPL",
    "gn:name":"Kashubintsy",
    "gn:population":0,
    "gn:timezone":"Europe/Minsk",
    "iso:country":"BY",
    "name:bel_x_preferred":[
        "\u041a\u0430\u0448\u0443\u0431\u0456\u043d\u0446\u044b"
    ],
    "name:rus_x_preferred":[
        "\u041a\u0430\u0448\u0443\u0431\u0438\u043d\u0446\u044b"
    ],
    "wof:name":"Kashubintsy",
    "wof:placetype":"locality"
},
  "geometry": {"coordinates":[24.2212,53.6228],"type":"Point"}
}