{
  "type": "Feature",
  "properties": {
    "gn:admin1_code":"1.0",
    "gn:asciiname":"Bizherevichi",
    "gn:country_code":"BY",
    "gn:dem":132,
    "gn:feature_class":"P",
    "gn:feature_code":"PPL",
    "gn:name":"Bizherevichi",
    "gn:population":0,
    "gn:timezone":"Europe/Minsk",
    "iso:country":"BY",
    "name:rus_x_preferred":[
        "\u0411\u0438\u0436\u0435\u0440\u0435\u0432\u0438\u0447\u0438"
    ],
    "name:und_x_variant":[
        "Bizhereviche",
        "Bizerewicze",
        "Bizherevichi"
    ],
    "wof:name":"Bizherevichi",
    "wof:placetype":"locality"
},
  "geometry": {"coordinates":[26.4461,52.0543],"type":"Point"}
}