{
  "type": "Feature",
  "properties": {
    "gn:admin1_code":"6.0",
    "gn:asciiname":"Svetlovka",
    "gn:country_code":"BY",
    "gn:dem":194,
    "gn:feature_class":"P",
    "gn:feature_code":"PPL",
    "gn:name":"Svetlovka",
    "gn:population":0,
    "gn:timezone":"Europe/Minsk",
    "iso:country":"BY",
    "name:rus_x_preferred":[
        "\u0421\u0432\u0435\u0442\u043b\u043e\u0432\u043a\u0430"
    ],
    "wof:name":"Svetlovka",
    "wof:placetype":"locality"
},
  "geometry": {"coordinates":[30.5063,54.0975],"type":"Point"}
}