{
  "type": "Feature",
  "properties": {
    "gn:admin1_code":"3.0",
    "gn:asciiname":"Dantsy",
    "gn:country_code":"BY",
    "gn:dem":122,
    "gn:feature_class":"P",
    "gn:feature_code":"PPL",
    "gn:name":"Dantsy",
    "gn:population":0,
    "gn:timezone":"Europe/Minsk",
    "iso:country":"BY",
    "name:rus_x_preferred":[
        "\u0414\u0430\u043d\u0446\u044b"
    ],
    "name:und_x_variant":[
        "Dontsy"
    ],
    "wof:name":"Dantsy",
    "wof:placetype":"locality"
},
  "geometry": {"coordinates":[24.8905,53.3794],"type":"Point"}
}