{
  "type": "Feature",
  "properties": {
    "gn:admin1_code":"7.0",
    "gn:asciiname":"Stanuli",
    "gn:country_code":"BY",
    "gn:dem":184,
    "gn:feature_class":"P",
    "gn:feature_code":"PPL",
    "gn:name":"Stanuli",
    "gn:population":0,
    "gn:timezone":"Europe/Minsk",
    "iso:country":"BY",
    "name:bel_x_preferred":[
        "\u0421\u0442\u0430\u043d\u0443\u043b\u0456"
    ],
    "wof:name":"Stanuli",
    "wof:placetype":"locality"
},
  "geometry": {"coordinates":[27.7518,55.1588],"type":"Point"}
}