{
  "type": "Feature",
  "properties": {
    "gn:admin1_code":"2.0",
    "gn:asciiname":"Khutor Babichi",
    "gn:country_code":"BY",
    "gn:dem":131,
    "gn:feature_class":"P",
    "gn:feature_code":"PPL",
    "gn:name":"Khutor Babichi",
    "gn:population":0,
    "gn:timezone":"Europe/Minsk",
    "iso:country":"BY",
    "name:rus_x_preferred":[
        "\u0425\u0443\u0442\u043e\u0440 \u0411\u0430\u0431\u0438\u0447\u0438"
    ],
    "wof:name":"Khutor Babichi",
    "wof:placetype":"locality"
},
  "geometry": {"coordinates":[30.0053,52.2633],"type":"Point"}
}