{
  "type": "Feature",
  "properties": {
    "gn:admin1_code":"1.0",
    "gn:asciiname":"Yundzily",
    "gn:country_code":"BY",
    "gn:dem":168,
    "gn:feature_class":"P",
    "gn:feature_code":"PPL",
    "gn:name":"Yundzily",
    "gn:population":0,
    "gn:timezone":"Europe/Minsk",
    "iso:country":"BY",
    "name:bel_x_preferred":[
        "\u042e\u043d\u0434\u0437\u0456\u043b\u044b"
    ],
    "name:und_x_variant":[
        "Yundzilovichi",
        "Yundziloviche",
        "Yundilovichi",
        "Yundily",
        "Yundzily"
    ],
    "wof:name":"Yundzily",
    "wof:placetype":"locality"
},
  "geometry": {"coordinates":[25.0475,52.8756],"type":"Point"}
}