{
  "type": "Feature",
  "properties": {
    "gn:admin1_code":"1.0",
    "gn:asciiname":"Lyubel'-Pol'",
    "gn:country_code":"BY",
    "gn:dem":135,
    "gn:feature_class":"P",
    "gn:feature_code":"PPL",
    "gn:name":"Lyubel\u2019-Pol\u2019",
    "gn:population":0,
    "gn:timezone":"Europe/Minsk",
    "iso:country":"BY",
    "name:rus_x_preferred":[
        "\u041b\u044e\u0431\u0435\u043b\u044c-\u041f\u043e\u043b\u044c"
    ],
    "name:und_x_variant":[
        "Lyubel\u2019-Pol\u2019"
    ],
    "wof:name":"Lyubel'-Pol'",
    "wof:placetype":"locality"
},
  "geometry": {"coordinates":[26.1753,52.2244],"type":"Point"}
}