{
  "type": "Feature",
  "properties": {
    "gn:admin1_code":"6.0",
    "gn:asciiname":"Krutaya Gora",
    "gn:country_code":"BY",
    "gn:dem":147,
    "gn:feature_class":"P",
    "gn:feature_code":"PPL",
    "gn:name":"Krutaya Gora",
    "gn:population":0,
    "gn:timezone":"Europe/Minsk",
    "iso:country":"BY",
    "name:rus_x_preferred":[
        "\u041a\u0440\u0443\u0442\u0430\u044f \u0413\u043e\u0440\u0430"
    ],
    "wof:name":"Krutaya Gora",
    "wof:placetype":"locality"
},
  "geometry": {"coordinates":[29.7019,53.1806],"type":"Point"}
}