{
  "type": "Feature",
  "properties": {
    "gn:admin1_code":"6.0",
    "gn:asciiname":"Zakhvat",
    "gn:country_code":"BY",
    "gn:dem":188,
    "gn:feature_class":"P",
    "gn:feature_code":"PPL",
    "gn:name":"Zakhvat",
    "gn:population":0,
    "gn:timezone":"Europe/Minsk",
    "iso:country":"BY",
    "name:rus_x_preferred":[
        "\u0417\u0430\u0445\u0432\u0430\u0442"
    ],
    "wof:name":"Zakhvat",
    "wof:placetype":"locality"
},
  "geometry": {"coordinates":[30.0932,54.0029],"type":"Point"}
}