{
  "type": "Feature",
  "properties": {
    "gn:admin1_code":"5.0",
    "gn:asciiname":"Gan'chitsy",
    "gn:country_code":"BY",
    "gn:dem":211,
    "gn:feature_class":"P",
    "gn:feature_code":"PPL",
    "gn:name":"Gan\u2019chitsy",
    "gn:population":0,
    "gn:timezone":"Europe/Minsk",
    "iso:country":"BY",
    "name:rus_x_preferred":[
        "\u0413\u0430\u043d\u044c\u0447\u0438\u0446\u044b"
    ],
    "name:und_x_variant":[
        "Gan\u2019chitsy"
    ],
    "wof:name":"Gan'chitsy",
    "wof:placetype":"locality"
},
  "geometry": {"coordinates":[26.6423,54.154],"type":"Point"}
}