{
  "type": "Feature",
  "properties": {
    "gn:admin1_code":"5.0",
    "gn:asciiname":"Vygonichi",
    "gn:country_code":"BY",
    "gn:dem":215,
    "gn:feature_class":"P",
    "gn:feature_code":"PPL",
    "gn:name":"Vygonichi",
    "gn:population":0,
    "gn:timezone":"Europe/Minsk",
    "iso:country":"BY",
    "name:rus_x_preferred":[
        "\u0412\u044b\u0433\u043e\u043d\u0438\u0447\u0438"
    ],
    "wof:name":"Vygonichi",
    "wof:placetype":"locality"
},
  "geometry": {"coordinates":[27.011,53.9545],"type":"Point"}
}