{
  "type": "Feature",
  "properties": {
    "gn:admin1_code":"6.0",
    "gn:asciiname":"Dowhavichy",
    "gn:country_code":"BY",
    "gn:dem":199,
    "gn:feature_class":"P",
    "gn:feature_code":"PPL",
    "gn:name":"Dowhavichy",
    "gn:population":0,
    "gn:timezone":"Europe/Minsk",
    "iso:country":"BY",
    "name:bel_x_preferred":[
        "\u0414\u043e\u045e\u0433\u0430\u0432\u0456\u0447\u044b"
    ],
    "name:eng_x_preferred":[
        "Dolgovichi"
    ],
    "name:rus_x_preferred":[
        "\u0414\u043e\u043b\u0433\u043e\u0432\u0438\u0447\u0438"
    ],
    "name:und_x_variant":[
        "Dowhavichy"
    ],
    "wof:name":"Dowhavichy",
    "wof:placetype":"locality"
},
  "geometry": {"coordinates":[31.3076,53.9408],"type":"Point"}
}