{
  "type": "Feature",
  "properties": {
    "gn:admin1_code":"7.0",
    "gn:asciiname":"Dumarishki Tret'i",
    "gn:country_code":"BY",
    "gn:dem":135,
    "gn:feature_class":"P",
    "gn:feature_code":"PPL",
    "gn:name":"Dumarishki Tret\u2019i",
    "gn:population":0,
    "gn:timezone":"Europe/Minsk",
    "iso:country":"BY",
    "name:rus_x_preferred":[
        "\u0414\u0443\u043c\u0430\u0440\u0438\u0448\u043a\u0438 \u0422\u0440\u0435\u0442\u044c\u0438"
    ],
    "name:und_x_variant":[
        "Dumarishki Tret\u2019i"
    ],
    "wof:name":"Dumarishki Tret'i",
    "wof:placetype":"locality"
},
  "geometry": {"coordinates":[27.1526,55.8372],"type":"Point"}
}