{
  "type": "Feature",
  "properties": {
    "gn:admin1_code":"7.0",
    "gn:asciiname":"Ryzhichi",
    "gn:country_code":"BY",
    "gn:dem":211,
    "gn:feature_class":"P",
    "gn:feature_code":"PPL",
    "gn:name":"Ryzhichi",
    "gn:population":0,
    "gn:timezone":"Europe/Minsk",
    "iso:country":"BY",
    "name:rus_x_preferred":[
        "\u0420\u044b\u0436\u0438\u0447\u0438"
    ],
    "name:und_x_variant":[
        "Rizhitsy"
    ],
    "wof:name":"Ryzhichi",
    "wof:placetype":"locality"
},
  "geometry": {"coordinates":[29.8291,54.4723],"type":"Point"}
}