{
  "type": "Feature",
  "properties": {
    "gn:admin1_code":"5.0",
    "gn:asciiname":"Volochek",
    "gn:country_code":"BY",
    "gn:dem":165,
    "gn:feature_class":"P",
    "gn:feature_code":"PPL",
    "gn:name":"Volochek",
    "gn:population":0,
    "gn:timezone":"Europe/Minsk",
    "iso:country":"BY",
    "name:rus_x_preferred":[
        "\u0412\u043e\u043b\u043e\u0447\u0435\u043a"
    ],
    "wof:name":"Volochek",
    "wof:placetype":"locality"
},
  "geometry": {"coordinates":[26.875,54.9094],"type":"Point"}
}