{
  "type": "Feature",
  "properties": {
    "gn:admin1_code":"6.0",
    "gn:asciiname":"Novyy Lan'kov",
    "gn:country_code":"BY",
    "gn:dem":185,
    "gn:feature_class":"P",
    "gn:feature_code":"PPL",
    "gn:name":"Novyy Lan\u2019kov",
    "gn:population":0,
    "gn:timezone":"Europe/Minsk",
    "iso:country":"BY",
    "name:rus_x_preferred":[
        "\u041d\u043e\u0432\u044b\u0439 \u041b\u0430\u043d\u044c\u043a\u043e\u0432"
    ],
    "name:und_x_variant":[
        "Novyy Lan\u2019kov"
    ],
    "wof:name":"Novyy Lan'kov",
    "wof:placetype":"locality"
},
  "geometry": {"coordinates":[29.7379,54.0424],"type":"Point"}
}