{
  "type": "Feature",
  "properties": {
    "gn:admin1_code":"7.0",
    "gn:asciiname":"Trosnitsa",
    "gn:country_code":"BY",
    "gn:dem":131,
    "gn:feature_class":"P",
    "gn:feature_code":"PPL",
    "gn:name":"Trosnitsa",
    "gn:population":0,
    "gn:timezone":"Europe/Minsk",
    "iso:country":"BY",
    "name:rus_x_preferred":[
        "\u0422\u0440\u043e\u0441\u043d\u0438\u0446\u0430"
    ],
    "wof:name":"Trosnitsa",
    "wof:placetype":"locality"
},
  "geometry": {"coordinates":[28.9016,55.4957],"type":"Point"}
}