{
  "type": "Feature",
  "properties": {
    "gn:admin1_code":"7.0",
    "gn:asciiname":"Patskovichi",
    "gn:country_code":"BY",
    "gn:dem":178,
    "gn:feature_class":"P",
    "gn:feature_code":"PPL",
    "gn:name":"Patskovichi",
    "gn:population":0,
    "gn:timezone":"Europe/Minsk",
    "iso:country":"BY",
    "name:rus_x_preferred":[
        "\u041f\u0430\u0446\u043a\u043e\u0432\u0438\u0447\u0438"
    ],
    "name:und_x_variant":[
        "Packowicze",
        "Patskoviche",
        "Patskovichi"
    ],
    "wof:name":"Patskovichi",
    "wof:placetype":"locality"
},
  "geometry": {"coordinates":[27.0046,54.9845],"type":"Point"}
}