{
  "type": "Feature",
  "properties": {
    "gn:admin1_code":"1.0",
    "gn:asciiname":"Chabakhi",
    "gn:country_code":"BY",
    "gn:dem":152,
    "gn:feature_class":"P",
    "gn:feature_code":"PPL",
    "gn:name":"Chabakhi",
    "gn:population":0,
    "gn:timezone":"Europe/Minsk",
    "iso:country":"BY",
    "name:rus_x_preferred":[
        "\u0427\u0430\u0431\u0430\u0445\u0438"
    ],
    "wof:name":"Chabakhi",
    "wof:placetype":"locality"
},
  "geometry": {"coordinates":[24.0802,52.4487],"type":"Point"}
}