{
  "type": "Feature",
  "properties": {
    "gn:admin1_code":"7.0",
    "gn:asciiname":"Maznevo",
    "gn:country_code":"BY",
    "gn:dem":176,
    "gn:feature_class":"P",
    "gn:feature_code":"PPL",
    "gn:name":"Mazn\u00ebvo",
    "gn:population":0,
    "gn:timezone":"Europe/Minsk",
    "iso:country":"BY",
    "name:rus_x_preferred":[
        "\u041c\u0430\u0437\u043d\u0451\u0432\u043e"
    ],
    "name:und_x_variant":[
        "Mazn\u00ebvo",
        "Maz\u2019n\u00ebvo"
    ],
    "wof:name":"Maznevo",
    "wof:placetype":"locality"
},
  "geometry": {"coordinates":[28.0122,55.1554],"type":"Point"}
}