{
  "type": "Feature",
  "properties": {
    "gn:admin1_code":"1.0",
    "gn:asciiname":"Luchitsa",
    "gn:country_code":"BY",
    "gn:dem":143,
    "gn:feature_class":"P",
    "gn:feature_code":"PPL",
    "gn:name":"Luchitsa",
    "gn:population":0,
    "gn:timezone":"Europe/Minsk",
    "iso:country":"BY",
    "name:rus_x_preferred":[
        "\u041b\u0443\u0447\u0438\u0446\u0430"
    ],
    "wof:name":"Luchitsa",
    "wof:placetype":"locality"
},
  "geometry": {"coordinates":[26.5882,51.8778],"type":"Point"}
}