{
  "type": "Feature",
  "properties": {
    "gn:admin1_code":"7.0",
    "gn:asciiname":"Yedlovichi",
    "gn:country_code":"BY",
    "gn:dem":141,
    "gn:feature_class":"P",
    "gn:feature_code":"PPL",
    "gn:name":"Yedlovichi",
    "gn:population":0,
    "gn:timezone":"Europe/Minsk",
    "iso:country":"BY",
    "name:eng_x_preferred":[
        "Yedlovichi"
    ],
    "name:rus_x_preferred":[
        "\u0415\u0434\u043b\u043e\u0432\u0438\u0447\u0438"
    ],
    "name:und_x_variant":[
        "Iodloviche",
        "Jod\u0142owicze",
        "Yedlovichi"
    ],
    "wof:name":"Yedlovichi",
    "wof:placetype":"locality"
},
  "geometry": {"coordinates":[26.9322,55.5787],"type":"Point"}
}