{
  "type": "Feature",
  "properties": {
    "gn:admin1_code":"5.0",
    "gn:asciiname":"Konyutichi",
    "gn:country_code":"BY",
    "gn:dem":225,
    "gn:feature_class":"P",
    "gn:feature_code":"PPL",
    "gn:name":"Konyutichi",
    "gn:population":0,
    "gn:timezone":"Europe/Minsk",
    "iso:country":"BY",
    "name:rus_x_preferred":[
        "\u041a\u043e\u043d\u044e\u0442\u0438\u0447\u0438"
    ],
    "wof:name":"Konyutichi",
    "wof:placetype":"locality"
},
  "geometry": {"coordinates":[27.5372,53.793],"type":"Point"}
}