{
  "type": "Feature",
  "properties": {
    "gn:admin1_code":"6.0",
    "gn:asciiname":"Shirokiye",
    "gn:country_code":"BY",
    "gn:dem":214,
    "gn:feature_class":"P",
    "gn:feature_code":"PPL",
    "gn:name":"Shirokiye",
    "gn:population":0,
    "gn:timezone":"Europe/Minsk",
    "iso:country":"BY",
    "name:rus_x_preferred":[
        "\u0428\u0438\u0440\u043e\u043a\u0438\u0435"
    ],
    "wof:name":"Shirokiye",
    "wof:placetype":"locality"
},
  "geometry": {"coordinates":[30.974,54.3898],"type":"Point"}
}