{
  "type": "Feature",
  "properties": {
    "gn:admin1_code":"6.0",
    "gn:asciiname":"Golochevka",
    "gn:country_code":"BY",
    "gn:dem":160,
    "gn:feature_class":"P",
    "gn:feature_code":"PPL",
    "gn:name":"Golochevka",
    "gn:population":0,
    "gn:timezone":"Europe/Minsk",
    "iso:country":"BY",
    "name:rus_x_preferred":[
        "\u0413\u043e\u043b\u043e\u0447\u0435\u0432\u043a\u0430"
    ],
    "name:und_x_variant":[
        "Golachevskiye"
    ],
    "wof:name":"Golochevka",
    "wof:placetype":"locality"
},
  "geometry": {"coordinates":[31.0689,53.7436],"type":"Point"}
}