{
  "type": "Feature",
  "properties": {
    "gn:admin1_code":"5.0",
    "gn:asciiname":"Rusalishki",
    "gn:country_code":"BY",
    "gn:dem":288,
    "gn:feature_class":"P",
    "gn:feature_code":"PPL",
    "gn:name":"Rusalishki",
    "gn:population":0,
    "gn:timezone":"Europe/Minsk",
    "iso:country":"BY",
    "name:rus_x_preferred":[
        "\u0420\u0443\u0441\u0430\u043b\u0438\u0448\u043a\u0438"
    ],
    "wof:name":"Rusalishki",
    "wof:placetype":"locality"
},
  "geometry": {"coordinates":[27.0134,54.16],"type":"Point"}
}