{
  "type": "Feature",
  "properties": {
    "gn:admin1_code":"1.0",
    "gn:asciiname":"Semonovshchina",
    "gn:country_code":"BY",
    "gn:dem":152,
    "gn:feature_class":"P",
    "gn:feature_code":"PPL",
    "gn:name":"Semonovshchina",
    "gn:population":0,
    "gn:timezone":"Europe/Minsk",
    "iso:country":"BY",
    "name:rus_x_preferred":[
        "\u0421\u0435\u043c\u043e\u043d\u043e\u0432\u0449\u0438\u043d\u0430"
    ],
    "wof:name":"Semonovshchina",
    "wof:placetype":"locality"
},
  "geometry": {"coordinates":[25.1027,52.2068],"type":"Point"}
}