{
  "type": "Feature",
  "properties": {
    "gn:admin1_code":"2.0",
    "gn:asciiname":"Babunichy",
    "gn:country_code":"BY",
    "gn:dem":130,
    "gn:feature_class":"P",
    "gn:feature_code":"PPL",
    "gn:name":"Babunichy",
    "gn:population":0,
    "gn:timezone":"Europe/Minsk",
    "iso:country":"BY",
    "name:bel_x_preferred":[
        "\u0411\u0430\u0431\u0443\u043d\u0438\u0447\u044b"
    ],
    "name:und_x_variant":[
        "Babunichi"
    ],
    "wof:name":"Babunichy",
    "wof:placetype":"locality"
},
  "geometry": {"coordinates":[28.464,52.2756],"type":"Point"}
}