{
  "type": "Feature",
  "properties": {
    "gn:admin1_code":"6.0",
    "gn:asciiname":"Starina",
    "gn:country_code":"BY",
    "gn:dem":146,
    "gn:feature_class":"P",
    "gn:feature_code":"PPL",
    "gn:name":"Starina",
    "gn:population":0,
    "gn:timezone":"Europe/Minsk",
    "iso:country":"BY",
    "name:bel_x_preferred":[
        "\u0421\u0442\u0430\u0440\u044b\u043d\u0430"
    ],
    "name:ceb_x_preferred":[
        "Starina"
    ],
    "name:deu_x_preferred":[
        "Starina"
    ],
    "name:epo_x_preferred":[
        "Starina"
    ],
    "name:fra_x_preferred":[
        "Starina"
    ],
    "name:pol_x_preferred":[
        "Starina"
    ],
    "name:rue_x_preferred":[
        "\u0421\u0442\u0430\u0440\u0438\u043d\u0430"
    ],
    "name:rus_x_preferred":[
        "\u0421\u0442\u0430\u0440\u0438\u043d\u0430"
    ],
    "name:slk_x_preferred":[
        "Starina"
    ],
    "name:srp_x_preferred":[
        "\u0421\u0442\u0430\u0440\u0438\u043d\u0430"
    ],
    "wof:name":"Starina",
    "wof:placetype":"locality"
},
  "geometry": {"coordinates":[30.50333,53.30639],"type":"Point"}
}