{
  "type": "Feature",
  "properties": {
    "gn:admin1_code":"2.0",
    "gn:asciiname":"Pererov",
    "gn:country_code":"BY",
    "gn:dem":123,
    "gn:feature_class":"P",
    "gn:feature_code":"PPL",
    "gn:name":"Pererov",
    "gn:population":0,
    "gn:timezone":"Europe/Minsk",
    "iso:country":"BY",
    "name:eng_x_preferred":[
        "Pererov"
    ],
    "name:rus_x_preferred":[
        "\u041f\u0435\u0440\u0435\u0440\u043e\u0432"
    ],
    "wof:name":"Pererov",
    "wof:placetype":"locality"
},
  "geometry": {"coordinates":[28.0048,52.0614],"type":"Point"}
}