{
  "type": "Feature",
  "properties": {
    "gn:admin1_code":"3.0",
    "gn:asciiname":"Radyuntsy",
    "gn:country_code":"BY",
    "gn:dem":155,
    "gn:feature_class":"P",
    "gn:feature_code":"PPL",
    "gn:name":"Radyuntsy",
    "gn:population":0,
    "gn:timezone":"Europe/Minsk",
    "iso:country":"BY",
    "name:rus_x_preferred":[
        "\u0420\u0430\u0434\u044e\u043d\u0446\u044b"
    ],
    "wof:name":"Radyuntsy",
    "wof:placetype":"locality"
},
  "geometry": {"coordinates":[24.9838,54.0991],"type":"Point"}
}