{
  "type": "Feature",
  "properties": {
    "gn:admin1_code":"3.0",
    "gn:asciiname":"Zarechanka",
    "gn:country_code":"BY",
    "gn:dem":127,
    "gn:feature_class":"P",
    "gn:feature_code":"PPL",
    "gn:name":"Zarechanka",
    "gn:population":0,
    "gn:timezone":"Europe/Minsk",
    "iso:country":"BY",
    "name:rus_x_preferred":[
        "\u0417\u0430\u0440\u0435\u0447\u0430\u043d\u043a\u0430"
    ],
    "wof:name":"Zarechanka",
    "wof:placetype":"locality"
},
  "geometry": {"coordinates":[23.7485,53.7364],"type":"Point"}
}