{
  "type": "Feature",
  "properties": {
    "gn:admin1_code":"3.0",
    "gn:asciiname":"Kryzhovka",
    "gn:country_code":"BY",
    "gn:dem":174,
    "gn:feature_class":"P",
    "gn:feature_code":"PPL",
    "gn:name":"Kryzhovka",
    "gn:population":0,
    "gn:timezone":"Europe/Minsk",
    "iso:country":"BY",
    "name:rus_x_preferred":[
        "\u041a\u0440\u044b\u0436\u043e\u0432\u043a\u0430"
    ],
    "name:und_x_variant":[
        "Kryzhovka Pervaya"
    ],
    "wof:name":"Kryzhovka",
    "wof:placetype":"locality"
},
  "geometry": {"coordinates":[25.8943,54.7421],"type":"Point"}
}