{
  "type": "Feature",
  "properties": {
    "gn:admin1_code":"7.0",
    "gn:asciiname":"Lipanty",
    "gn:country_code":"BY",
    "gn:dem":129,
    "gn:feature_class":"P",
    "gn:feature_code":"PPL",
    "gn:name":"Lipanty",
    "gn:population":0,
    "gn:timezone":"Europe/Minsk",
    "iso:country":"BY",
    "name:rus_x_preferred":[
        "\u041b\u0438\u043f\u0430\u043d\u0442\u044b"
    ],
    "wof:name":"Lipanty",
    "wof:placetype":"locality"
},
  "geometry": {"coordinates":[28.1056,55.6074],"type":"Point"}
}