{
  "type": "Feature",
  "properties": {
    "gn:admin1_code":"7.0",
    "gn:asciiname":"Dvorets",
    "gn:country_code":"BY",
    "gn:dem":171,
    "gn:feature_class":"P",
    "gn:feature_code":"PPL",
    "gn:name":"Dvorets",
    "gn:population":0,
    "gn:timezone":"Europe/Minsk",
    "iso:country":"BY",
    "name:rus_x_preferred":[
        "\u0414\u0432\u043e\u0440\u0435\u0446"
    ],
    "wof:name":"Dvorets",
    "wof:placetype":"locality"
},
  "geometry": {"coordinates":[28.9759,54.8651],"type":"Point"}
}