{
  "type": "Feature",
  "properties": {
    "gn:admin1_code":"7.0",
    "gn:asciiname":"Kukavka",
    "gn:country_code":"BY",
    "gn:dem":129,
    "gn:feature_class":"P",
    "gn:feature_code":"PPL",
    "gn:name":"Kukavka",
    "gn:population":0,
    "gn:timezone":"Europe/Minsk",
    "iso:country":"BY",
    "name:rus_x_preferred":[
        "\u041a\u0443\u043a\u0430\u0432\u043a\u0430"
    ],
    "wof:name":"Kukavka",
    "wof:placetype":"locality"
},
  "geometry": {"coordinates":[27.8277,55.403],"type":"Point"}
}