{
  "type": "Feature",
  "properties": {
    "gn:admin1_code":"6.0",
    "gn:asciiname":"Staryya Stayki",
    "gn:country_code":"BY",
    "gn:dem":171,
    "gn:feature_class":"P",
    "gn:feature_code":"PPL",
    "gn:name":"Staryya Stayki",
    "gn:population":0,
    "gn:timezone":"Europe/Minsk",
    "iso:country":"BY",
    "name:bel_x_preferred":[
        "\u0421\u0442\u0430\u0440\u044b\u044f \u0421\u0442\u0430\u0439\u043a\u0456"
    ],
    "name:und_x_variant":[
        "Staryye Stayki"
    ],
    "wof:name":"Staryya Stayki",
    "wof:placetype":"locality"
},
  "geometry": {"coordinates":[30.2968,54.2829],"type":"Point"}
}