{
  "type": "Feature",
  "properties": {
    "gn:admin1_code":"7.0",
    "gn:asciiname":"Rat'ki",
    "gn:country_code":"BY",
    "gn:dem":121,
    "gn:feature_class":"P",
    "gn:feature_code":"PPL",
    "gn:name":"Rat\u2019ki",
    "gn:population":0,
    "gn:timezone":"Europe/Minsk",
    "iso:country":"BY",
    "name:rus_x_preferred":[
        "\u0420\u0430\u0442\u044c\u043a\u0438"
    ],
    "name:und_x_variant":[
        "Rat\u2019ki"
    ],
    "wof:name":"Rat'ki",
    "wof:placetype":"locality"
},
  "geometry": {"coordinates":[27.5541,55.3729],"type":"Point"}
}