{
  "type": "Feature",
  "properties": {
    "gn:admin1_code":"2.0",
    "gn:asciiname":"Novaya Sloboda",
    "gn:country_code":"BY",
    "gn:dem":144,
    "gn:feature_class":"P",
    "gn:feature_code":"PPL",
    "gn:name":"Novaya Sloboda",
    "gn:population":0,
    "gn:timezone":"Europe/Minsk",
    "iso:country":"BY",
    "name:rus_x_preferred":[
        "\u041d\u043e\u0432\u0430\u044f \u0421\u043b\u043e\u0431\u043e\u0434\u0430"
    ],
    "wof:name":"Novaya Sloboda",
    "wof:placetype":"locality"
},
  "geometry": {"coordinates":[30.3394,52.84],"type":"Point"}
}