{
  "type": "Feature",
  "properties": {
    "gn:admin1_code":"6.0",
    "gn:asciiname":"Dubovoye",
    "gn:country_code":"BY",
    "gn:dem":157,
    "gn:feature_class":"P",
    "gn:feature_code":"PPL",
    "gn:name":"Dubovoye",
    "gn:population":0,
    "gn:timezone":"Europe/Minsk",
    "iso:country":"BY",
    "name:che_x_preferred":[
        "\u0414\u0443\u0431\u043e\u0432\u0438"
    ],
    "name:rus_x_preferred":[
        "\u0414\u0443\u0431\u043e\u0432\u043e\u0435"
    ],
    "wof:name":"Dubovoye",
    "wof:placetype":"locality"
},
  "geometry": {"coordinates":[28.5055,53.3366],"type":"Point"}
}