{
  "type": "Feature",
  "properties": {
    "gn:admin1_code":"7.0",
    "gn:asciiname":"Budniki",
    "gn:country_code":"BY",
    "gn:dem":136,
    "gn:feature_class":"P",
    "gn:feature_code":"PPL",
    "gn:name":"Budniki",
    "gn:population":0,
    "gn:timezone":"Europe/Minsk",
    "iso:country":"BY",
    "name:fra_x_preferred":[
        "Budniki"
    ],
    "name:pol_x_preferred":[
        "Budniki"
    ],
    "name:rus_x_preferred":[
        "\u0411\u0443\u0434\u043d\u0438\u043a\u0438"
    ],
    "wof:name":"Budniki",
    "wof:placetype":"locality"
},
  "geometry": {"coordinates":[29.5793,55.0076],"type":"Point"}
}