{
  "type": "Feature",
  "properties": {
    "gn:admin1_code":"5.0",
    "gn:asciiname":"Chernoleski",
    "gn:country_code":"BY",
    "gn:dem":208,
    "gn:feature_class":"P",
    "gn:feature_code":"PPL",
    "gn:name":"Chernoleski",
    "gn:population":0,
    "gn:timezone":"Europe/Minsk",
    "iso:country":"BY",
    "name:rus_x_preferred":[
        "\u0427\u0435\u0440\u043d\u043e\u043b\u0435\u0441\u043a\u0438"
    ],
    "wof:name":"Chernoleski",
    "wof:placetype":"locality"
},
  "geometry": {"coordinates":[27.4524,53.6758],"type":"Point"}
}