{
  "type": "Feature",
  "properties": {
    "gn:admin1_code":"6.0",
    "gn:asciiname":"Shchezher' Vtoroy",
    "gn:country_code":"BY",
    "gn:dem":169,
    "gn:feature_class":"P",
    "gn:feature_code":"PPL",
    "gn:name":"Shchezher\u2019 Vtoroy",
    "gn:population":0,
    "gn:timezone":"Europe/Minsk",
    "iso:country":"BY",
    "name:rus_x_preferred":[
        "\u0429\u0435\u0436\u0435\u0440\u044c \u0412\u0442\u043e\u0440\u043e\u0439"
    ],
    "name:und_x_variant":[
        "Shchezher\u2019 Vtoroy"
    ],
    "wof:name":"Shchezher' Vtoroy",
    "wof:placetype":"locality"
},
  "geometry": {"coordinates":[30.5414,53.8209],"type":"Point"}
}