{
  "type": "Feature",
  "properties": {
    "gn:admin1_code":"3.0",
    "gn:asciiname":"Radyushi",
    "gn:country_code":"BY",
    "gn:dem":139,
    "gn:feature_class":"P",
    "gn:feature_code":"PPL",
    "gn:name":"Radyushi",
    "gn:population":0,
    "gn:timezone":"Europe/Minsk",
    "iso:country":"BY",
    "name:rus_x_preferred":[
        "\u0420\u0430\u0434\u044e\u0448\u0438"
    ],
    "name:und_x_variant":[
        "Radziusze",
        "Radzyushe"
    ],
    "wof:name":"Radyushi",
    "wof:placetype":"locality"
},
  "geometry": {"coordinates":[26.2694,54.8164],"type":"Point"}
}