{
  "type": "Feature",
  "properties": {
    "gn:admin1_code":"1.0",
    "gn:asciiname":"Zakleten'ye",
    "gn:country_code":"BY",
    "gn:dem":152,
    "gn:feature_class":"P",
    "gn:feature_code":"PPL",
    "gn:name":"Zakleten\u2019ye",
    "gn:population":0,
    "gn:timezone":"Europe/Minsk",
    "iso:country":"BY",
    "name:rus_x_preferred":[
        "\u0417\u0430\u043a\u043b\u0435\u0442\u0435\u043d\u044c\u0435"
    ],
    "name:und_x_variant":[
        "Zakleten\u2019ye"
    ],
    "wof:name":"Zakleten'ye",
    "wof:placetype":"locality"
},
  "geometry": {"coordinates":[25.2912,52.3011],"type":"Point"}
}