{
  "type": "Feature",
  "properties": {
    "gn:admin1_code":"3.0",
    "gn:asciiname":"Roshchitsa",
    "gn:country_code":"BY",
    "gn:dem":217,
    "gn:feature_class":"P",
    "gn:feature_code":"PPL",
    "gn:name":"Roshchitsa",
    "gn:population":0,
    "gn:timezone":"Europe/Minsk",
    "iso:country":"BY",
    "name:bel_x_preferred":[
        "Roshchytsa"
    ],
    "name:bel_x_variant":[
        "\u0420\u043e\u0448\u0447\u044b\u0446\u0430"
    ],
    "name:rus_x_preferred":[
        "\u0420\u043e\u0449\u0438\u0446\u0430"
    ],
    "wof:name":"Roshchitsa",
    "wof:placetype":"locality"
},
  "geometry": {"coordinates":[25.716,53.5591],"type":"Point"}
}