{
  "type": "Feature",
  "properties": {
    "iso:country":"BY",
    "name:bel_x_preferred":[
        "\u0413\u043e\u0440\u0430\u0434 \u0427\u0430\u0448\u043d\u0456\u043a\u0456"
    ],
    "name:bel_x_variant":[
        "\u0427\u0430\u0448\u043d\u0456\u043a\u0456"
    ],
    "name:bul_x_preferred":[
        "\u0427\u0430\u0448\u043d\u0438\u043a\u0438"
    ],
    "name:ceb_x_preferred":[
        "Chashniki"
    ],
    "name:chu_x_preferred":[
        "\u0427\u0430\u0448\u043d\u0438\u0446\u0438"
    ],
    "name:deu_x_preferred":[
        "Tschaschniki"
    ],
    "name:eng_x_preferred":[
        "Chashniki"
    ],
    "name:est_x_preferred":[
        "\u010ca\u0161niki"
    ],
    "name:fin_x_preferred":[
        "T\u0161a\u0161niki"
    ],
    "name:fra_x_preferred":[
        "Tchachniki"
    ],
    "name:jpn_x_preferred":[
        "\u30c1\u30e3\u30fc\u30b7\u30e5\u30cb\u30ad"
    ],
    "name:lav_x_preferred":[
        "\u010ca\u0161\u0146iki"
    ],
    "name:lit_x_preferred":[
        "\u010ca\u0161nikai"
    ],
    "name:nld_x_preferred":[
        "Chashniki"
    ],
    "name:pol_x_preferred":[
        "Cza\u015bniki"
    ],
    "name:rus_x_preferred":[
        "\u0427\u0430\u0448\u043d\u0438\u043a\u0438"
    ],
    "name:srp_x_preferred":[
        "\u0427\u0430\u0448\u043d\u0438\u043a\u0438"
    ],
    "name:swe_x_preferred":[
        "Tjasjniki"
    ],
    "name:tat_x_preferred":[
        "\u0427\u0430\u0448\u043d\u0438\u043a\u0438"
    ],
    "name:ukr_x_preferred":[
        "\u0427\u0430\u0448\u043d\u0438\u043a\u0438"
    ],
    "name:zho_x_preferred":[
        "\u6070\u4ec0\u5c3c\u57fa"
    ],
    "qs:gn_country":"BY",
    "qs:gn_fcode":"PPLA2",
    "qs:gn_pop":11484,
    "qs:name":"Chashniki",
    "qs:name_adm0":"Belarus",
    "qs:name_adm1":"Vitsyebskaya Voblasts'",
    "qs:photos":0,
    "qs:photos_1k":0,
    "qs:photos_9k":0,
    "qs:photos_9r":0,
    "qs:photos_all":0,
    "qs:photos_sr":0,
    "qs:placetype":"Town",
    "qs:pop_sr":"6",
    "qs:woe_adm0":23424765,
    "wd:population":9203,
    "wd:wordcount":82,
    "wof:name":"Chashniki",
    "wof:placetype":"locality",
    "wof:population":9203
},
  "geometry": {"coordinates":[29.1608,54.8584],"type":"Point"}
}