{
  "type": "Feature",
  "properties": {
    "gn:admin1_code":"7.0",
    "gn:asciiname":"Palyavaya",
    "gn:country_code":"BY",
    "gn:dem":217,
    "gn:feature_class":"P",
    "gn:feature_code":"PPL",
    "gn:name":"Palyavaya",
    "gn:population":0,
    "gn:timezone":"Europe/Minsk",
    "iso:country":"BY",
    "name:bel_x_preferred":[
        "\u041f\u0430\u043b\u044f\u0432\u0430\u044f"
    ],
    "name:und_x_variant":[
        "Polevaya"
    ],
    "wof:name":"Palyavaya",
    "wof:placetype":"locality"
},
  "geometry": {"coordinates":[29.6439,54.3511],"type":"Point"}
}