{
  "type": "Feature",
  "properties": {
    "gn:admin1_code":"3.0",
    "gn:asciiname":"Zhukoyni",
    "gn:country_code":"BY",
    "gn:dem":141,
    "gn:feature_class":"P",
    "gn:feature_code":"PPL",
    "gn:name":"Zhukoyni",
    "gn:population":0,
    "gn:timezone":"Europe/Minsk",
    "iso:country":"BY",
    "name:rus_x_preferred":[
        "\u0416\u0443\u043a\u043e\u0439\u043d\u0438"
    ],
    "name:und_x_variant":[
        "\u0179ukojnie Strackie",
        "Zhukoyni Stratske",
        "Zhukoyne Stratske",
        "Zhukoyni"
    ],
    "wof:name":"Zhukoyni",
    "wof:placetype":"locality"
},
  "geometry": {"coordinates":[26.1654,54.8607],"type":"Point"}
}