{
  "type": "Feature",
  "properties": {
    "gn:admin1_code":"7.0",
    "gn:asciiname":"Rubaniki",
    "gn:country_code":"BY",
    "gn:dem":142,
    "gn:feature_class":"P",
    "gn:feature_code":"PPL",
    "gn:name":"Rubaniki",
    "gn:population":0,
    "gn:timezone":"Europe/Minsk",
    "iso:country":"BY",
    "name:rus_x_preferred":[
        "\u0420\u0443\u0431\u0430\u043d\u0438\u043a\u0438"
    ],
    "wof:name":"Rubaniki",
    "wof:placetype":"locality"
},
  "geometry": {"coordinates":[28.7629,55.1412],"type":"Point"}
}