{
  "type": "Feature",
  "properties": {
    "gn:admin1_code":"3.0",
    "gn:asciiname":"Malyye Pushchevyye",
    "gn:country_code":"BY",
    "gn:dem":215,
    "gn:feature_class":"P",
    "gn:feature_code":"PPL",
    "gn:name":"Malyye Pushch\u00ebvyye",
    "gn:population":0,
    "gn:timezone":"Europe/Minsk",
    "iso:country":"BY",
    "name:rus_x_preferred":[
        "\u041c\u0430\u043b\u044b\u0435 \u041f\u0443\u0449\u0451\u0432\u044b\u0435"
    ],
    "name:und_x_variant":[
        "Malyye Pushch\u00ebvyye"
    ],
    "wof:name":"Malyye Pushchevyye",
    "wof:placetype":"locality"
},
  "geometry": {"coordinates":[25.9055,54.5672],"type":"Point"}
}