{
  "type": "Feature",
  "properties": {
    "gn:admin1_code":"7.0",
    "gn:asciiname":"Voronovo",
    "gn:country_code":"BY",
    "gn:dem":125,
    "gn:feature_class":"P",
    "gn:feature_code":"PPL",
    "gn:name":"Voronovo",
    "gn:population":0,
    "gn:timezone":"Europe/Minsk",
    "iso:country":"BY",
    "name:rus_x_preferred":[
        "\u0412\u043e\u0440\u043e\u043d\u043e\u0432\u043e"
    ],
    "wof:name":"Voronovo",
    "wof:placetype":"locality"
},
  "geometry": {"coordinates":[28.7852,55.7301],"type":"Point"}
}