{
  "type": "Feature",
  "properties": {
    "gn:admin1_code":"1.0",
    "gn:asciiname":"Penchin",
    "gn:country_code":"BY",
    "gn:dem":179,
    "gn:feature_class":"P",
    "gn:feature_code":"PPL",
    "gn:name":"Penchin",
    "gn:population":0,
    "gn:timezone":"Europe/Minsk",
    "iso:country":"BY",
    "name:rus_x_preferred":[
        "\u041f\u0435\u043d\u0447\u0438\u043d"
    ],
    "wof:name":"Penchin",
    "wof:placetype":"locality"
},
  "geometry": {"coordinates":[26.135,53.3315],"type":"Point"}
}