{
  "type": "Feature",
  "properties": {
    "gn:admin1_code":"2.0",
    "gn:asciiname":"Tel'man",
    "gn:country_code":"BY",
    "gn:dem":115,
    "gn:feature_class":"P",
    "gn:feature_code":"PPL",
    "gn:name":"Tel\u2019man",
    "gn:population":0,
    "gn:timezone":"Europe/Minsk",
    "iso:country":"BY",
    "name:rus_x_preferred":[
        "\u0422\u0435\u043b\u044c\u043c\u0430\u043d"
    ],
    "name:und_x_variant":[
        "Tel\u2019man"
    ],
    "wof:name":"Tel'man",
    "wof:placetype":"locality"
},
  "geometry": {"coordinates":[30.3069,51.8119],"type":"Point"}
}