{
  "type": "Feature",
  "properties": {
    "gn:admin1_code":"1.0",
    "gn:asciiname":"Kuntsevichi",
    "gn:country_code":"BY",
    "gn:dem":180,
    "gn:feature_class":"P",
    "gn:feature_code":"PPL",
    "gn:name":"Kuntsevichi",
    "gn:population":0,
    "gn:timezone":"Europe/Minsk",
    "iso:country":"BY",
    "name:bel_x_preferred":[
        "Kuntsavichy"
    ],
    "name:bel_x_variant":[
        "\u041a\u0443\u043d\u0446\u0430\u0432\u0456\u0447\u044b"
    ],
    "name:rus_x_preferred":[
        "\u041a\u0443\u043d\u0446\u0435\u0432\u0438\u0447\u0438"
    ],
    "wof:name":"Kuntsevichi",
    "wof:placetype":"locality"
},
  "geometry": {"coordinates":[25.9464,53.075],"type":"Point"}
}