{
  "type": "Feature",
  "properties": {
    "gn:admin1_code":"0.0",
    "gn:asciiname":"Vel'ki Bur",
    "gn:country_code":"BY",
    "gn:dem":168,
    "gn:feature_class":"P",
    "gn:feature_code":"PPL",
    "gn:name":"Vel\u2019ki Bur",
    "gn:population":0,
    "gn:timezone":"Europe/Minsk",
    "iso:country":"BY",
    "name:und_x_variant":[
        "Wielki B\u00f3r",
        "Vel\u2019ki Bur"
    ],
    "wof:name":"Vel'ki Bur",
    "wof:placetype":"locality"
},
  "geometry": {"coordinates":[27.21667,54.28333000000001],"type":"Point"}
}