{
  "type": "Feature",
  "properties": {
    "gn:admin1_code":"6.0",
    "gn:asciiname":"Aleksandrovo",
    "gn:country_code":"BY",
    "gn:dem":196,
    "gn:feature_class":"P",
    "gn:feature_code":"PPL",
    "gn:name":"Aleksandrovo",
    "gn:population":0,
    "gn:timezone":"Europe/Minsk",
    "iso:country":"BY",
    "name:rus_x_preferred":[
        "\u0410\u043b\u0435\u043a\u0441\u0430\u043d\u0434\u0440\u043e\u0432\u043e"
    ],
    "wof:name":"Aleksandrovo",
    "wof:placetype":"locality"
},
  "geometry": {"coordinates":[29.7476,54.2695],"type":"Point"}
}