{
  "type": "Feature",
  "properties": {
    "gn:admin1_code":"2.0",
    "gn:asciiname":"Syawki",
    "gn:country_code":"BY",
    "gn:dem":115,
    "gn:feature_class":"P",
    "gn:feature_code":"PPL",
    "gn:name":"Syawki",
    "gn:population":0,
    "gn:timezone":"Europe/Minsk",
    "iso:country":"BY",
    "name:bel_x_preferred":[
        "\u0421\u044f\u045e\u043a\u0456"
    ],
    "name:und_x_variant":[
        "Sevki"
    ],
    "wof:name":"Syawki",
    "wof:placetype":"locality"
},
  "geometry": {"coordinates":[30.545,51.7843],"type":"Point"}
}