{
  "type": "Feature",
  "properties": {
    "gn:admin1_code":"7.0",
    "gn:asciiname":"Losvida",
    "gn:country_code":"BY",
    "gn:dem":179,
    "gn:feature_class":"P",
    "gn:feature_code":"PPL",
    "gn:name":"Losvida",
    "gn:population":0,
    "gn:timezone":"Europe/Minsk",
    "iso:country":"BY",
    "name:rus_x_preferred":[
        "\u041b\u043e\u0441\u0432\u0438\u0434\u0430"
    ],
    "wof:name":"Losvida",
    "wof:placetype":"locality"
},
  "geometry": {"coordinates":[30.1282,55.3493],"type":"Point"}
}