{
  "type": "Feature",
  "properties": {
    "gn:admin1_code":"6.0",
    "gn:asciiname":"Burosovo",
    "gn:country_code":"BY",
    "gn:dem":168,
    "gn:feature_class":"P",
    "gn:feature_code":"PPL",
    "gn:name":"Burosovo",
    "gn:population":0,
    "gn:timezone":"Europe/Minsk",
    "iso:country":"BY",
    "name:rus_x_preferred":[
        "\u0411\u0443\u0440\u043e\u0441\u043e\u0432\u043e"
    ],
    "wof:name":"Burosovo",
    "wof:placetype":"locality"
},
  "geometry": {"coordinates":[32.5518,53.364],"type":"Point"}
}