{
  "type": "Feature",
  "properties": {
    "gn:admin1_code":"6.0",
    "gn:asciiname":"Yelovets",
    "gn:country_code":"BY",
    "gn:dem":164,
    "gn:feature_class":"P",
    "gn:feature_code":"PPL",
    "gn:name":"Yelovets",
    "gn:population":0,
    "gn:timezone":"Europe/Minsk",
    "iso:country":"BY",
    "name:eng_x_preferred":[
        "Yelovets"
    ],
    "name:rus_x_preferred":[
        "\u0415\u043b\u043e\u0432\u0435\u0446"
    ],
    "wof:name":"Yelovets",
    "wof:placetype":"locality"
},
  "geometry": {"coordinates":[32.6525,53.4499],"type":"Point"}
}