{
  "type": "Feature",
  "properties": {
    "gn:admin1_code":"5.0",
    "gn:asciiname":"Vytreski",
    "gn:country_code":"BY",
    "gn:dem":182,
    "gn:feature_class":"P",
    "gn:feature_code":"PPL",
    "gn:name":"Vytreski",
    "gn:population":0,
    "gn:timezone":"Europe/Minsk",
    "iso:country":"BY",
    "name:rus_x_preferred":[
        "\u0412\u044b\u0442\u0440\u0435\u0441\u043a\u0438"
    ],
    "name:und_x_variant":[
        "Wytrzeski",
        "Vytsheski",
        "Vytreski"
    ],
    "wof:name":"Vytreski",
    "wof:placetype":"locality"
},
  "geometry": {"coordinates":[27.2053,54.7498],"type":"Point"}
}