{
  "type": "Feature",
  "properties": {
    "gn:admin1_code":"6.0",
    "gn:asciiname":"Petrovka",
    "gn:country_code":"BY",
    "gn:dem":192,
    "gn:feature_class":"P",
    "gn:feature_code":"PPL",
    "gn:name":"Petrovka",
    "gn:population":0,
    "gn:timezone":"Europe/Minsk",
    "iso:country":"BY",
    "name:aze_x_preferred":[
        "Petrovka"
    ],
    "name:bel_x_preferred":[
        "\u041f\u044f\u0442\u0440\u043e\u045e\u043a\u0430"
    ],
    "name:ceb_x_preferred":[
        "\u041f\u0435\u0442\u0440\u043e\u0432\u043a\u0430"
    ],
    "name:ces_x_preferred":[
        "Petrovka"
    ],
    "name:chv_x_preferred":[
        "\u041f\u0435\u0442\u0440\u043e\u0432\u043a\u0430"
    ],
    "name:deu_x_preferred":[
        "Petrowka"
    ],
    "name:fra_x_preferred":[
        "Petrovka"
    ],
    "name:hye_x_preferred":[
        "\u054a\u0565\u057f\u0580\u0578\u057e\u056f\u0561"
    ],
    "name:ita_x_preferred":[
        "Petrovka"
    ],
    "name:kaz_x_preferred":[
        "\u041f\u0435\u0442\u0440\u043e\u0432\u043a\u0430"
    ],
    "name:lav_x_preferred":[
        "Petrovka"
    ],
    "name:myv_x_preferred":[
        "\u041f\u0435\u0442\u0440\u043e\u0432\u043a\u0430"
    ],
    "name:rus_x_preferred":[
        "\u041f\u0435\u0442\u0440\u043e\u0432\u043a\u0430"
    ],
    "name:slk_x_preferred":[
        "Petrovka"
    ],
    "name:tat_x_preferred":[
        "\u041f\u0435\u0442\u0440\u043e\u0432\u043a\u0430"
    ],
    "name:ukr_x_preferred":[
        "\u041f\u0435\u0442\u0440\u043e\u0432\u043a\u0430"
    ],
    "wof:name":"Petrovka",
    "wof:placetype":"locality"
},
  "geometry": {"coordinates":[32.3356,53.6278],"type":"Point"}
}