{
  "type": "Feature",
  "properties": {
    "gn:admin1_code":"6.0",
    "gn:asciiname":"Petrovka",
    "gn:country_code":"BY",
    "gn:dem":192,
    "gn:feature_class":"P",
    "gn:feature_code":"PPL",
    "gn:name":"Petrovka",
    "gn:population":0,
    "gn:timezone":"Europe/Minsk",
    "iso:country":"BY",
    "name:rus_x_preferred":[
        "\u041f\u0435\u0442\u0440\u043e\u0432\u043a\u0430"
    ],
    "wof:name":"Petrovka",
    "wof:placetype":"locality"
},
  "geometry": {"coordinates":[32.3356,53.6278],"type":"Point"}
}