{
  "type": "Feature",
  "properties": {
    "gn:admin1_code":"6.0",
    "gn:asciiname":"Chirvony Sad",
    "gn:country_code":"BY",
    "gn:dem":177,
    "gn:feature_class":"P",
    "gn:feature_code":"PPL",
    "gn:name":"Chirvony Sad",
    "gn:population":0,
    "gn:timezone":"Europe/Minsk",
    "iso:country":"BY",
    "name:rus_x_preferred":[
        "\u0427\u0438\u0440\u0432\u043e\u043d\u044b \u0421\u0430\u0434"
    ],
    "name:und_x_variant":[
        "Chervonnyy Sad"
    ],
    "wof:name":"Chirvony Sad",
    "wof:placetype":"locality"
},
  "geometry": {"coordinates":[29.8325,53.8613],"type":"Point"}
}