{
  "type": "Feature",
  "properties": {
    "gn:admin1_code":"6.0",
    "gn:asciiname":"Belyy Kamen'",
    "gn:country_code":"BY",
    "gn:dem":151,
    "gn:feature_class":"P",
    "gn:feature_code":"PPL",
    "gn:name":"Belyy Kamen\u2019",
    "gn:population":0,
    "gn:timezone":"Europe/Minsk",
    "iso:country":"BY",
    "name:rus_x_preferred":[
        "\u0411\u0435\u043b\u044b\u0439 \u041a\u0430\u043c\u0435\u043d\u044c"
    ],
    "name:und_x_variant":[
        "Bely Kamen\u2019",
        "Belyy Kamen\u2019"
    ],
    "wof:name":"Belyy Kamen'",
    "wof:placetype":"locality"
},
  "geometry": {"coordinates":[32.1211,53.2288],"type":"Point"}
}