{
  "type": "Feature",
  "properties": {
    "gn:admin1_code":"3.0",
    "gn:asciiname":"Semerniki",
    "gn:country_code":"BY",
    "gn:dem":211,
    "gn:feature_class":"P",
    "gn:feature_code":"PPL",
    "gn:name":"Semerniki",
    "gn:population":0,
    "gn:timezone":"Europe/Minsk",
    "iso:country":"BY",
    "name:rus_x_preferred":[
        "\u0421\u0435\u043c\u0435\u0440\u043d\u0438\u043a\u0438"
    ],
    "name:und_x_variant":[
        "Siemierniki",
        "Seterniki",
        "Semerniki"
    ],
    "wof:name":"Semerniki",
    "wof:placetype":"locality"
},
  "geometry": {"coordinates":[26.0699,54.2357],"type":"Point"}
}