{
  "type": "Feature",
  "properties": {
    "gn:admin1_code":"3.0",
    "gn:asciiname":"Zhikhi",
    "gn:country_code":"BY",
    "gn:dem":160,
    "gn:feature_class":"P",
    "gn:feature_code":"PPL",
    "gn:name":"Zhikhi",
    "gn:population":0,
    "gn:timezone":"Europe/Minsk",
    "iso:country":"BY",
    "name:bel_x_preferred":[
        "Zhykhi"
    ],
    "name:bel_x_variant":[
        "\u0416\u044b\u0445\u0456"
    ],
    "name:rus_x_preferred":[
        "\u0416\u0438\u0445\u0438"
    ],
    "wof:name":"Zhikhi",
    "wof:placetype":"locality"
},
  "geometry": {"coordinates":[25.5968,53.3709],"type":"Point"}
}