{
  "type": "Feature",
  "properties": {
    "gn:admin1_code":"7.0",
    "gn:asciiname":"Zyuzino",
    "gn:country_code":"BY",
    "gn:dem":129,
    "gn:feature_class":"P",
    "gn:feature_code":"PPL",
    "gn:name":"Zyuzino",
    "gn:population":0,
    "gn:timezone":"Europe/Minsk",
    "iso:country":"BY",
    "name:rus_x_preferred":[
        "\u0417\u044e\u0437\u0438\u043d\u043e"
    ],
    "wof:name":"Zyuzino",
    "wof:placetype":"locality"
},
  "geometry": {"coordinates":[28.9508,55.5121],"type":"Point"}
}