{
  "type": "Feature",
  "properties": {
    "gn:admin1_code":"7.0",
    "gn:asciiname":"Avdeykovo",
    "gn:country_code":"BY",
    "gn:dem":172,
    "gn:feature_class":"P",
    "gn:feature_code":"PPL",
    "gn:name":"Avdeykovo",
    "gn:population":0,
    "gn:timezone":"Europe/Minsk",
    "iso:country":"BY",
    "name:rus_x_preferred":[
        "\u0410\u0432\u0434\u0435\u0439\u043a\u043e\u0432\u043e"
    ],
    "wof:name":"Avdeykovo",
    "wof:placetype":"locality"
},
  "geometry": {"coordinates":[30.0976,55.8244],"type":"Point"}
}