{
  "type": "Feature",
  "properties": {
    "gn:admin1_code":"1.0",
    "gn:asciiname":"Omelenets",
    "gn:country_code":"BY",
    "gn:dem":159,
    "gn:feature_class":"P",
    "gn:feature_code":"PPL",
    "gn:name":"Omelenets",
    "gn:population":0,
    "gn:timezone":"Europe/Minsk",
    "iso:country":"BY",
    "name:rus_x_preferred":[
        "\u041e\u043c\u0435\u043b\u0435\u043d\u0435\u0446"
    ],
    "wof:name":"Omelenets",
    "wof:placetype":"locality"
},
  "geometry": {"coordinates":[23.5497,52.5396],"type":"Point"}
}