{
  "type": "Feature",
  "properties": {
    "gn:admin1_code":"5.0",
    "gn:asciiname":"Gorelyy Lug",
    "gn:country_code":"BY",
    "gn:dem":206,
    "gn:feature_class":"P",
    "gn:feature_code":"PPL",
    "gn:name":"Gorelyy Lug",
    "gn:population":0,
    "gn:timezone":"Europe/Minsk",
    "iso:country":"BY",
    "name:eng_x_preferred":[
        "Gorelyy Lug"
    ],
    "name:rus_x_preferred":[
        "\u0413\u043e\u0440\u0435\u043b\u044b\u0439 \u041b\u0443\u0433"
    ],
    "name:und_x_variant":[
        "Gorely Lug",
        "Gorelyy Lug"
    ],
    "wof:name":"Gorelyy Lug",
    "wof:placetype":"locality"
},
  "geometry": {"coordinates":[28.175,54.4964],"type":"Point"}
}