{
  "type": "Feature",
  "properties": {
    "gn:admin1_code":"7.0",
    "gn:asciiname":"Krupchino",
    "gn:country_code":"BY",
    "gn:dem":149,
    "gn:feature_class":"P",
    "gn:feature_code":"PPL",
    "gn:name":"Krupchino",
    "gn:population":0,
    "gn:timezone":"Europe/Minsk",
    "iso:country":"BY",
    "name:rus_x_preferred":[
        "\u041a\u0440\u0443\u043f\u0447\u0438\u043d\u043e"
    ],
    "wof:name":"Krupchino",
    "wof:placetype":"locality"
},
  "geometry": {"coordinates":[29.6537,55.2972],"type":"Point"}
}