{
  "type": "Feature",
  "properties": {
    "gn:admin1_code":"5.0",
    "gn:asciiname":"Vetka",
    "gn:country_code":"BY",
    "gn:dem":170,
    "gn:feature_class":"P",
    "gn:feature_code":"PPL",
    "gn:name":"Vetka",
    "gn:population":0,
    "gn:timezone":"Europe/Minsk",
    "iso:country":"BY",
    "name:rus_x_preferred":[
        "\u0412\u0435\u0442\u043a\u0430"
    ],
    "wof:name":"Vetka",
    "wof:placetype":"locality"
},
  "geometry": {"coordinates":[27.447,53.1111],"type":"Point"}
}