{
  "type": "Feature",
  "properties": {
    "gn:admin1_code":"7.0",
    "gn:asciiname":"Klishi",
    "gn:country_code":"BY",
    "gn:dem":168,
    "gn:feature_class":"P",
    "gn:feature_code":"PPL",
    "gn:name":"Klishi",
    "gn:population":0,
    "gn:timezone":"Europe/Minsk",
    "iso:country":"BY",
    "name:rus_x_preferred":[
        "\u041a\u043b\u0438\u0448\u0438"
    ],
    "wof:name":"Klishi",
    "wof:placetype":"locality"
},
  "geometry": {"coordinates":[29.9325,55.1106],"type":"Point"}
}