{
  "type": "Feature",
  "properties": {
    "gn:country":"BY",
    "gn:fcode":"PPL",
    "gn:population":600,
    "iso:country":"BY",
    "name:bel_x_preferred":[
        "\u0428\u0447\u043e\u0440\u0441\u044b"
    ],
    "name:bul_x_preferred":[
        "\u0428\u0447\u043e\u0440\u0441\u0439"
    ],
    "name:ceb_x_preferred":[
        "Shchorsy"
    ],
    "name:ces_x_preferred":[
        "Szczorsy nad Niemnem"
    ],
    "name:eng_x_preferred":[
        "Shchorsy"
    ],
    "name:lit_x_preferred":[
        "\u0160\u010dorsai"
    ],
    "name:nld_x_preferred":[
        "Szczorsy nad Niemnem"
    ],
    "name:pol_x_preferred":[
        "Szczorsy"
    ],
    "name:rus_x_preferred":[
        "\u0429\u043e\u0440\u0441\u044b"
    ],
    "name:swe_x_preferred":[
        "Sjtjorsy"
    ],
    "name:und_x_variant":[
        "Sloboda"
    ],
    "qs_pg:aaroncc":"BY",
    "qs_pg:gn_country":"BY",
    "qs_pg:gn_fcode":"PPL",
    "qs_pg:gn_pop":600,
    "qs_pg:name":"Shchorsy",
    "qs_pg:photos_9r":0,
    "qs_pg:photos_sr":0,
    "qs_pg:pop_sr":2,
    "qs_pg:qs_pg_placetype":"locality",
    "wof:name":"Shchorsy",
    "wof:placetype":"locality",
    "wof:population":600
},
  "geometry": {"coordinates":[26.1855,53.6344],"type":"Point"}
}