{
  "type": "Feature",
  "properties": {
    "gn:admin1_code":"7.0",
    "gn:asciiname":"Novoye Zaozer'ye",
    "gn:country_code":"BY",
    "gn:dem":202,
    "gn:feature_class":"P",
    "gn:feature_code":"PPL",
    "gn:name":"Novoye Zaoz\u00ebr\u2019ye",
    "gn:population":0,
    "gn:timezone":"Europe/Minsk",
    "iso:country":"BY",
    "name:rus_x_preferred":[
        "\u041d\u043e\u0432\u043e\u0435 \u0417\u0430\u043e\u0437\u0451\u0440\u044c\u0435"
    ],
    "name:und_x_variant":[
        "Novoye Zaoz\u00ebr\u2019ye"
    ],
    "wof:name":"Novoye Zaozer'ye",
    "wof:placetype":"locality"
},
  "geometry": {"coordinates":[30.0197,54.3974],"type":"Point"}
}