{
  "type": "Feature",
  "properties": {
    "gn:admin1_code":"7.0",
    "gn:asciiname":"Monyakovo",
    "gn:country_code":"BY",
    "gn:dem":129,
    "gn:feature_class":"P",
    "gn:feature_code":"PPL",
    "gn:name":"Monyakovo",
    "gn:population":0,
    "gn:timezone":"Europe/Minsk",
    "iso:country":"BY",
    "name:rus_x_preferred":[
        "\u041c\u043e\u043d\u044f\u043a\u043e\u0432\u043e"
    ],
    "name:und_x_variant":[
        "Moniakowo",
        "Monyakovo",
        "Monyakova"
    ],
    "wof:name":"Monyakovo",
    "wof:placetype":"locality"
},
  "geometry": {"coordinates":[28.2359,55.5333],"type":"Point"}
}