{
  "type": "Feature",
  "properties": {
    "gn:admin1_code":"6.0",
    "gn:asciiname":"Malyya Slavyeni",
    "gn:country_code":"BY",
    "gn:dem":190,
    "gn:feature_class":"P",
    "gn:feature_code":"PPL",
    "gn:name":"Malyya Slavyeni",
    "gn:population":0,
    "gn:timezone":"Europe/Minsk",
    "iso:country":"BY",
    "name:bel_x_preferred":[
        "\u041c\u0430\u043b\u044b\u044f \u0421\u043b\u0430\u0432\u0435\u043d\u0456"
    ],
    "name:und_x_variant":[
        "Slaveni",
        "Bol\u2019shiye Slaveni",
        "Malyye Sloveni",
        "Sloveni",
        "Malyya Slavyeni"
    ],
    "wof:name":"Malyya Slavyeni",
    "wof:placetype":"locality"
},
  "geometry": {"coordinates":[30.4216,54.2715],"type":"Point"}
}