{
  "type": "Feature",
  "properties": {
    "gn:admin1_code":"3.0",
    "gn:asciiname":"Ogorodniki",
    "gn:country_code":"BY",
    "gn:dem":111,
    "gn:feature_class":"P",
    "gn:feature_code":"PPL",
    "gn:name":"Ogorodniki",
    "gn:population":0,
    "gn:timezone":"Europe/Minsk",
    "iso:country":"BY",
    "name:bel_x_preferred":[
        "Aharodniki"
    ],
    "name:bel_x_variant":[
        "\u0410\u0433\u0430\u0440\u043e\u0434\u043d\u0456\u043a\u0456"
    ],
    "name:rus_x_preferred":[
        "\u041e\u0433\u043e\u0440\u043e\u0434\u043d\u0438\u043a\u0438"
    ],
    "name:und_x_variant":[
        "Ogrodniki",
        "Ogorodniki"
    ],
    "wof:name":"Ogorodniki",
    "wof:placetype":"locality"
},
  "geometry": {"coordinates":[24.0632,53.5672],"type":"Point"}
}