{
  "type": "Feature",
  "properties": {
    "gn:admin1_code":"7.0",
    "gn:asciiname":"Novaya",
    "gn:country_code":"BY",
    "gn:dem":150,
    "gn:feature_class":"P",
    "gn:feature_code":"PPL",
    "gn:name":"Novaya",
    "gn:population":0,
    "gn:timezone":"Europe/Minsk",
    "iso:country":"BY",
    "name:rus_x_preferred":[
        "\u041d\u043e\u0432\u0430\u044f"
    ],
    "name:und_x_variant":[
        "Nowa",
        "Nova",
        "Novaya",
        "Novaya Derevnya"
    ],
    "wof:name":"Novaya",
    "wof:placetype":"locality"
},
  "geometry": {"coordinates":[26.8851,55.5518],"type":"Point"}
}