{
  "type": "Feature",
  "properties": {
    "gn:admin1_code":"7.0",
    "gn:asciiname":"Savarina",
    "gn:country_code":"BY",
    "gn:dem":125,
    "gn:feature_class":"P",
    "gn:feature_code":"PPL",
    "gn:name":"Savarina",
    "gn:population":0,
    "gn:timezone":"Europe/Minsk",
    "iso:country":"BY",
    "name:rus_x_preferred":[
        "\u0421\u0430\u0432\u0430\u0440\u0438\u043d\u0430"
    ],
    "wof:name":"Savarina",
    "wof:placetype":"locality"
},
  "geometry": {"coordinates":[27.6108,55.3885],"type":"Point"}
}