{
  "type": "Feature",
  "properties": {
    "gn:admin1_code":"7.0",
    "gn:asciiname":"Stomino",
    "gn:country_code":"BY",
    "gn:dem":156,
    "gn:feature_class":"P",
    "gn:feature_code":"PPL",
    "gn:name":"Stomino",
    "gn:population":0,
    "gn:timezone":"Europe/Minsk",
    "iso:country":"BY",
    "name:rus_x_preferred":[
        "\u0421\u0442\u043e\u043c\u0438\u043d\u043e"
    ],
    "wof:name":"Stomino",
    "wof:placetype":"locality"
},
  "geometry": {"coordinates":[28.0505,55.3611],"type":"Point"}
}