{
  "type": "Feature",
  "properties": {
    "gn:admin1_code":"7.0",
    "gn:asciiname":"Rudniki",
    "gn:country_code":"BY",
    "gn:dem":186,
    "gn:feature_class":"P",
    "gn:feature_code":"PPL",
    "gn:name":"Rudniki",
    "gn:population":0,
    "gn:timezone":"Europe/Minsk",
    "iso:country":"BY",
    "name:rus_x_preferred":[
        "\u0420\u0443\u0434\u043d\u0438\u043a\u0438"
    ],
    "wof:name":"Rudniki",
    "wof:placetype":"locality"
},
  "geometry": {"coordinates":[28.3074,55.287],"type":"Point"}
}