{
  "type": "Feature",
  "properties": {
    "gn:admin1_code":"6.0",
    "gn:asciiname":"Golovchitsy",
    "gn:country_code":"BY",
    "gn:dem":157,
    "gn:feature_class":"P",
    "gn:feature_code":"PPL",
    "gn:name":"Golovchitsy",
    "gn:population":0,
    "gn:timezone":"Europe/Minsk",
    "iso:country":"BY",
    "name:rus_x_preferred":[
        "\u0413\u043e\u043b\u043e\u0432\u0447\u0438\u0446\u044b"
    ],
    "wof:name":"Golovchitsy",
    "wof:placetype":"locality"
},
  "geometry": {"coordinates":[31.4644,53.4565],"type":"Point"}
}