{
  "type": "Feature",
  "properties": {
    "gn:admin1_code":"5.0",
    "gn:asciiname":"Osecheno",
    "gn:country_code":"BY",
    "gn:dem":183,
    "gn:feature_class":"P",
    "gn:feature_code":"PPL",
    "gn:name":"Osecheno",
    "gn:population":0,
    "gn:timezone":"Europe/Minsk",
    "iso:country":"BY",
    "name:rus_x_preferred":[
        "\u041e\u0441\u0435\u0447\u0435\u043d\u043e"
    ],
    "wof:name":"Osecheno",
    "wof:placetype":"locality"
},
  "geometry": {"coordinates":[29.3379,54.5692],"type":"Point"}
}