{
  "type": "Feature",
  "properties": {
    "gn:admin1_code":"6.0",
    "gn:asciiname":"Zakrupets",
    "gn:country_code":"BY",
    "gn:dem":140,
    "gn:feature_class":"P",
    "gn:feature_code":"PPL",
    "gn:name":"Zakrupets",
    "gn:population":0,
    "gn:timezone":"Europe/Minsk",
    "iso:country":"BY",
    "name:rus_x_preferred":[
        "\u0417\u0430\u043a\u0440\u0443\u043f\u0435\u0446"
    ],
    "wof:name":"Zakrupets",
    "wof:placetype":"locality"
},
  "geometry": {"coordinates":[31.0128,53.5945],"type":"Point"}
}