{
  "type": "Feature",
  "properties": {
    "gn:admin1_code":"5.0",
    "gn:asciiname":"Volovnitsa",
    "gn:country_code":"BY",
    "gn:dem":165,
    "gn:feature_class":"P",
    "gn:feature_code":"PPL",
    "gn:name":"Volovnitsa",
    "gn:population":0,
    "gn:timezone":"Europe/Minsk",
    "iso:country":"BY",
    "name:rus_x_preferred":[
        "\u0412\u043e\u043b\u043e\u0432\u043d\u0438\u0446\u0430"
    ],
    "wof:name":"Volovnitsa",
    "wof:placetype":"locality"
},
  "geometry": {"coordinates":[29.1129,53.7344],"type":"Point"}
}