{
  "type": "Feature",
  "properties": {
    "gn:admin1_code":"1.0",
    "gn:asciiname":"Zalyessye",
    "gn:country_code":"BY",
    "gn:dem":144,
    "gn:feature_class":"P",
    "gn:feature_code":"PPL",
    "gn:name":"Zalyessye",
    "gn:population":0,
    "gn:timezone":"Europe/Minsk",
    "iso:country":"BY",
    "name:bel_x_preferred":[
        "\u0417\u0430\u043b\u0435\u0441\u0441\u0435"
    ],
    "name:rus_x_preferred":[
        "Zales\u2019ye"
    ],
    "name:und_x_variant":[
        "Zalese",
        "Zalyessye"
    ],
    "wof:name":"Zalyessye",
    "wof:placetype":"locality"
},
  "geometry": {"coordinates":[24.4742,52.2173],"type":"Point"}
}