{
  "type": "Feature",
  "properties": {
    "gn:admin1_code":"7.0",
    "gn:asciiname":"Chupry",
    "gn:country_code":"BY",
    "gn:dem":200,
    "gn:feature_class":"P",
    "gn:feature_code":"PPL",
    "gn:name":"Chupry",
    "gn:population":0,
    "gn:timezone":"Europe/Minsk",
    "iso:country":"BY",
    "name:rus_x_preferred":[
        "\u0427\u0443\u043f\u0440\u044b"
    ],
    "name:und_x_variant":[
        "Czupry",
        "Chupry"
    ],
    "wof:name":"Chupry",
    "wof:placetype":"locality"
},
  "geometry": {"coordinates":[27.8894,54.6413],"type":"Point"}
}