{
  "type": "Feature",
  "properties": {
    "gn:admin1_code":"6.0",
    "gn:asciiname":"Zarestsye",
    "gn:country_code":"BY",
    "gn:dem":179,
    "gn:feature_class":"P",
    "gn:feature_code":"PPL",
    "gn:name":"Zarestsye",
    "gn:population":0,
    "gn:timezone":"Europe/Minsk",
    "iso:country":"BY",
    "name:bel_x_preferred":[
        "\u0417\u0430\u0440\u044d\u0441\u0446\u0435"
    ],
    "name:und_x_variant":[
        "Zares\u2019ye",
        "Zarest\u2019ye",
        "Zarestsye"
    ],
    "wof:name":"Zarestsye",
    "wof:placetype":"locality"
},
  "geometry": {"coordinates":[30.6967,54.0124],"type":"Point"}
}