{
  "type": "Feature",
  "properties": {
    "gn:admin1_code":"2.0",
    "gn:asciiname":"Padhallye",
    "gn:country_code":"BY",
    "gn:dem":152,
    "gn:feature_class":"P",
    "gn:feature_code":"PPL",
    "gn:name":"Padhallye",
    "gn:population":0,
    "gn:timezone":"Europe/Minsk",
    "iso:country":"BY",
    "name:bel_x_preferred":[
        "\u041f\u0430\u0434\u0433\u0430\u043b\u043b\u0435"
    ],
    "name:rus_x_preferred":[
        "Podgal\u2019ye"
    ],
    "wof:name":"Padhallye",
    "wof:placetype":"locality"
},
  "geometry": {"coordinates":[28.7688,51.5134],"type":"Point"}
}