{
  "type": "Feature",
  "properties": {
    "gn:admin1_code":"6.0",
    "gn:asciiname":"Lagodovo",
    "gn:country_code":"BY",
    "gn:dem":153,
    "gn:feature_class":"P",
    "gn:feature_code":"PPL",
    "gn:name":"Lagodovo",
    "gn:population":0,
    "gn:timezone":"Europe/Minsk",
    "iso:country":"BY",
    "name:rus_x_preferred":[
        "\u041b\u0430\u0433\u043e\u0434\u043e\u0432\u043e"
    ],
    "name:und_x_variant":[
        "Lagodov",
        "Lagoda",
        "Lagodovo"
    ],
    "wof:name":"Lagodovo",
    "wof:placetype":"locality"
},
  "geometry": {"coordinates":[30.1541,53.4747],"type":"Point"}
}