{
  "type": "Feature",
  "properties": {
    "gn:admin1_code":"7.0",
    "gn:asciiname":"Khotilovshchina",
    "gn:country_code":"BY",
    "gn:dem":175,
    "gn:feature_class":"P",
    "gn:feature_code":"PPL",
    "gn:name":"Khotilovshchina",
    "gn:population":0,
    "gn:timezone":"Europe/Minsk",
    "iso:country":"BY",
    "name:rus_x_preferred":[
        "\u0425\u043e\u0442\u0438\u043b\u043e\u0432\u0449\u0438\u043d\u0430"
    ],
    "wof:name":"Khotilovshchina",
    "wof:placetype":"locality"
},
  "geometry": {"coordinates":[27.7212,55.213],"type":"Point"}
}