{
  "type": "Feature",
  "properties": {
    "gn:admin1_code":"5.0",
    "gn:asciiname":"Yakovichi",
    "gn:country_code":"BY",
    "gn:dem":179,
    "gn:feature_class":"P",
    "gn:feature_code":"PPL",
    "gn:name":"Yakovichi",
    "gn:population":0,
    "gn:timezone":"Europe/Minsk",
    "iso:country":"BY",
    "name:rus_x_preferred":[
        "\u042f\u043a\u043e\u0432\u0438\u0447\u0438"
    ],
    "wof:name":"Yakovichi",
    "wof:placetype":"locality"
},
  "geometry": {"coordinates":[26.5336,54.3543],"type":"Point"}
}