{
  "type": "Feature",
  "properties": {
    "gn:admin1_code":"3.0",
    "gn:asciiname":"Okhonovo",
    "gn:country_code":"BY",
    "gn:dem":157,
    "gn:feature_class":"P",
    "gn:feature_code":"PPL",
    "gn:name":"Okhonovo",
    "gn:population":0,
    "gn:timezone":"Europe/Minsk",
    "iso:country":"BY",
    "name:bel_x_preferred":[
        "\u0410\u0445\u043e\u043d\u0430\u0432\u0430"
    ],
    "name:eng_x_preferred":[
        "Okhonovo"
    ],
    "name:rus_x_preferred":[
        "\u041e\u0445\u043e\u043d\u043e\u0432\u043e"
    ],
    "name:und_x_variant":[
        "Akhonava"
    ],
    "wof:name":"Okhonovo",
    "wof:placetype":"locality"
},
  "geometry": {"coordinates":[25.5328,53.5595],"type":"Point"}
}