{
  "type": "Feature",
  "properties": {
    "gn:admin1_code":"7.0",
    "gn:asciiname":"Mikhalina",
    "gn:country_code":"BY",
    "gn:dem":160,
    "gn:feature_class":"P",
    "gn:feature_code":"PPL",
    "gn:name":"Mikhalina",
    "gn:population":0,
    "gn:timezone":"Europe/Minsk",
    "iso:country":"BY",
    "name:rus_x_preferred":[
        "\u041c\u0438\u0445\u0430\u043b\u0438\u043d\u0430"
    ],
    "wof:name":"Mikhalina",
    "wof:placetype":"locality"
},
  "geometry": {"coordinates":[27.2512,55.0406],"type":"Point"}
}