{
  "type": "Feature",
  "properties": {
    "gn:admin1_code":"2.0",
    "gn:asciiname":"Yampol'",
    "gn:country_code":"BY",
    "gn:dem":132,
    "gn:feature_class":"P",
    "gn:feature_code":"PPL",
    "gn:name":"Yampol\u2019",
    "gn:population":0,
    "gn:timezone":"Europe/Minsk",
    "iso:country":"BY",
    "name:rus_x_preferred":[
        "\u042f\u043c\u043f\u043e\u043b\u044c"
    ],
    "name:und_x_variant":[
        "Yampol\u2019"
    ],
    "wof:name":"Yampol'",
    "wof:placetype":"locality"
},
  "geometry": {"coordinates":[30.4107,52.2542],"type":"Point"}
}