{
  "type": "Feature",
  "properties": {
    "gn:admin1_code":"7.0",
    "gn:asciiname":"Zamsheno",
    "gn:country_code":"BY",
    "gn:dem":230,
    "gn:feature_class":"P",
    "gn:feature_code":"PPL",
    "gn:name":"Zamsheno",
    "gn:population":0,
    "gn:timezone":"Europe/Minsk",
    "iso:country":"BY",
    "name:rus_x_preferred":[
        "\u0417\u0430\u043c\u0448\u0435\u043d\u043e"
    ],
    "name:und_x_variant":[
        "Zamshino"
    ],
    "wof:name":"Zamsheno",
    "wof:placetype":"locality"
},
  "geometry": {"coordinates":[30.833,55.1466],"type":"Point"}
}