{
  "type": "Feature",
  "properties": {
    "gn:admin1_code":"2.0",
    "gn:asciiname":"Ivanishchevichi",
    "gn:country_code":"BY",
    "gn:dem":142,
    "gn:feature_class":"P",
    "gn:feature_code":"PPL",
    "gn:name":"Ivanishchevichi",
    "gn:population":0,
    "gn:timezone":"Europe/Minsk",
    "iso:country":"BY",
    "name:rus_x_preferred":[
        "\u0418\u0432\u0430\u043d\u0438\u0449\u0435\u0432\u0438\u0447\u0438"
    ],
    "wof:name":"Ivanishchevichi",
    "wof:placetype":"locality"
},
  "geometry": {"coordinates":[29.1577,52.6434],"type":"Point"}
}