{
  "type": "Feature",
  "properties": {
    "gn:admin1_code":"6.0",
    "gn:asciiname":"Rasna",
    "gn:country_code":"BY",
    "gn:dem":193,
    "gn:feature_class":"P",
    "gn:feature_code":"PPL",
    "gn:name":"Rasna",
    "gn:population":0,
    "gn:timezone":"Europe/Minsk",
    "iso:country":"BY",
    "name:bel_x_preferred":[
        "\u0420\u0430\u0441\u043d\u0430"
    ],
    "name:hin_x_preferred":[
        "\u0930\u0938\u0928\u093e"
    ],
    "name:und_x_variant":[
        "Ryasha",
        "Ryasna"
    ],
    "wof:name":"Rasna",
    "wof:placetype":"locality"
},
  "geometry": {"coordinates":[31.1972,54.0108],"type":"Point"}
}