{
  "type": "Feature",
  "properties": {
    "gn:admin1_code":"3.0",
    "gn:asciiname":"Lazduny Pyershyya",
    "gn:country_code":"BY",
    "gn:dem":151,
    "gn:feature_class":"P",
    "gn:feature_code":"PPL",
    "gn:name":"Lazduny Pyershyya",
    "gn:population":0,
    "gn:timezone":"Europe/Minsk",
    "iso:country":"BY",
    "name:bel_x_preferred":[
        "\u041b\u0430\u0437\u0434\u0443\u043d\u044b \u041f\u0435\u0440\u0448\u044b\u044f"
    ],
    "name:und_x_variant":[
        "Lazduny",
        "Lazduny Pyershyya"
    ],
    "wof:name":"Lazduny Pyershyya",
    "wof:placetype":"locality"
},
  "geometry": {"coordinates":[25.972,53.9657],"type":"Point"}
}