{
  "type": "Feature",
  "properties": {
    "gn:admin1_code":"3.0",
    "gn:asciiname":"Drobishuny",
    "gn:country_code":"BY",
    "gn:dem":168,
    "gn:feature_class":"P",
    "gn:feature_code":"PPL",
    "gn:name":"Drobishuny",
    "gn:population":0,
    "gn:timezone":"Europe/Minsk",
    "iso:country":"BY",
    "name:rus_x_preferred":[
        "\u0414\u0440\u043e\u0431\u0438\u0448\u0443\u043d\u044b"
    ],
    "wof:name":"Drobishuny",
    "wof:placetype":"locality"
},
  "geometry": {"coordinates":[25.2062,54.2078],"type":"Point"}
}