{
  "type": "Feature",
  "properties": {
    "gn:admin1_code":"3.0",
    "gn:asciiname":"Karpovtsy",
    "gn:country_code":"BY",
    "gn:dem":141,
    "gn:feature_class":"P",
    "gn:feature_code":"PPL",
    "gn:name":"Karpovtsy",
    "gn:population":0,
    "gn:timezone":"Europe/Minsk",
    "iso:country":"BY",
    "name:rus_x_preferred":[
        "\u041a\u0430\u0440\u043f\u043e\u0432\u0446\u044b"
    ],
    "name:und_x_variant":[
        "Karpovtse"
    ],
    "wof:name":"Karpovtsy",
    "wof:placetype":"locality"
},
  "geometry": {"coordinates":[24.4668,53.2816],"type":"Point"}
}