{
  "type": "Feature",
  "properties": {
    "gn:admin1_code":"5.0",
    "gn:asciiname":"Selevtsy",
    "gn:country_code":"BY",
    "gn:dem":240,
    "gn:feature_class":"P",
    "gn:feature_code":"PPL",
    "gn:name":"Selevtsy",
    "gn:population":0,
    "gn:timezone":"Europe/Minsk",
    "iso:country":"BY",
    "name:rus_x_preferred":[
        "\u0421\u0435\u043b\u0435\u0432\u0446\u044b"
    ],
    "wof:name":"Selevtsy",
    "wof:placetype":"locality"
},
  "geometry": {"coordinates":[26.7976,54.1271],"type":"Point"}
}