{
  "type": "Feature",
  "properties": {
    "gn:admin1_code":"3.0",
    "gn:asciiname":"Dalyokiya",
    "gn:country_code":"BY",
    "gn:dem":142,
    "gn:feature_class":"P",
    "gn:feature_code":"PPL",
    "gn:name":"Dalyokiya",
    "gn:population":0,
    "gn:timezone":"Europe/Minsk",
    "iso:country":"BY",
    "name:bel_x_preferred":[
        "Dalyokiya"
    ],
    "name:bel_x_variant":[
        "\u0414\u0430\u043b\u0451\u043a\u0456\u044f"
    ],
    "name:rus_x_preferred":[
        "\u0414\u0430\u043b\u0451\u043a\u0438\u0435"
    ],
    "name:und_x_variant":[
        "Dal\u00ebkiye"
    ],
    "wof:name":"Dalyokiya",
    "wof:placetype":"locality"
},
  "geometry": {"coordinates":[25.2147,53.8174],"type":"Point"}
}