{
  "type": "Feature",
  "properties": {
    "gn:admin1_code":"3.0",
    "gn:asciiname":"Protenevichi",
    "gn:country_code":"BY",
    "gn:dem":196,
    "gn:feature_class":"P",
    "gn:feature_code":"PPL",
    "gn:name":"Protenevichi",
    "gn:population":0,
    "gn:timezone":"Europe/Minsk",
    "iso:country":"BY",
    "name:rus_x_preferred":[
        "\u041f\u0440\u043e\u0442\u0435\u043d\u0435\u0432\u0438\u0447\u0438"
    ],
    "wof:name":"Protenevichi",
    "wof:placetype":"locality"
},
  "geometry": {"coordinates":[26.0998,53.5607],"type":"Point"}
}