{
  "type": "Feature",
  "properties": {
    "gn:admin1_code":"3.0",
    "gn:asciiname":"Zapolichi",
    "gn:country_code":"BY",
    "gn:dem":171,
    "gn:feature_class":"P",
    "gn:feature_code":"PPL",
    "gn:name":"Zapolichi",
    "gn:population":0,
    "gn:timezone":"Europe/Minsk",
    "iso:country":"BY",
    "name:rus_x_preferred":[
        "\u0417\u0430\u043f\u043e\u043b\u0438\u0447\u0438"
    ],
    "wof:name":"Zapolichi",
    "wof:placetype":"locality"
},
  "geometry": {"coordinates":[24.3667,52.928],"type":"Point"}
}