{
  "type": "Feature",
  "properties": {
    "gn:admin1_code":"5.0",
    "gn:asciiname":"Hastsilavichy",
    "gn:country_code":"BY",
    "gn:dem":188,
    "gn:feature_class":"P",
    "gn:feature_code":"PPL",
    "gn:name":"Hastsilavichy",
    "gn:population":0,
    "gn:timezone":"Europe/Minsk",
    "iso:country":"BY",
    "name:bel_x_preferred":[
        "\u0413\u0430\u0441\u0446\u0456\u043b\u0430\u0432\u0456\u0447\u044b"
    ],
    "name:und_x_variant":[
        "Gostilovichi"
    ],
    "wof:name":"Hastsilavichy",
    "wof:placetype":"locality"
},
  "geometry": {"coordinates":[27.904,54.2143],"type":"Point"}
}