{
  "type": "Feature",
  "properties": {
    "gn:admin1_code":"5.0",
    "gn:asciiname":"Malyye Yanushkovichi",
    "gn:country_code":"BY",
    "gn:dem":248,
    "gn:feature_class":"P",
    "gn:feature_code":"PPL",
    "gn:name":"Malyye Yanushkovichi",
    "gn:population":0,
    "gn:timezone":"Europe/Minsk",
    "iso:country":"BY",
    "name:rus_x_preferred":[
        "\u041c\u0430\u043b\u044b\u0435 \u042f\u043d\u0443\u0448\u043a\u043e\u0432\u0438\u0447\u0438"
    ],
    "wof:name":"Malyye Yanushkovichi",
    "wof:placetype":"locality"
},
  "geometry": {"coordinates":[27.6197,54.2805],"type":"Point"}
}