{
  "type": "Feature",
  "properties": {
    "gn:admin1_code":"3.0",
    "gn:asciiname":"Neshkrupa",
    "gn:country_code":"BY",
    "gn:dem":146,
    "gn:feature_class":"P",
    "gn:feature_code":"PPL",
    "gn:name":"Neshkrupa",
    "gn:population":0,
    "gn:timezone":"Europe/Minsk",
    "iso:country":"BY",
    "name:rus_x_preferred":[
        "\u041d\u0435\u0448\u043a\u0440\u0443\u043f\u0430"
    ],
    "wof:name":"Neshkrupa",
    "wof:placetype":"locality"
},
  "geometry": {"coordinates":[25.10313,53.98569000000001],"type":"Point"}
}