{
  "type": "Feature",
  "properties": {
    "gn:admin1_code":"7.0",
    "gn:asciiname":"Grishany",
    "gn:country_code":"BY",
    "gn:dem":167,
    "gn:feature_class":"P",
    "gn:feature_code":"PPL",
    "gn:name":"Grishany",
    "gn:population":0,
    "gn:timezone":"Europe/Minsk",
    "iso:country":"BY",
    "name:rus_x_preferred":[
        "\u0413\u0440\u0438\u0448\u0430\u043d\u044b"
    ],
    "wof:name":"Grishany",
    "wof:placetype":"locality"
},
  "geometry": {"coordinates":[30.4232,54.6687],"type":"Point"}
}