{
  "type": "Feature",
  "properties": {
    "gn:admin1_code":"5.0",
    "gn:asciiname":"Zaluzh'ye",
    "gn:country_code":"BY",
    "gn:dem":168,
    "gn:feature_class":"P",
    "gn:feature_code":"PPL",
    "gn:name":"Zaluzh\u2019ye",
    "gn:population":0,
    "gn:timezone":"Europe/Minsk",
    "iso:country":"BY",
    "name:rus_x_preferred":[
        "\u0417\u0430\u043b\u0443\u0436\u044c\u0435"
    ],
    "name:und_x_variant":[
        "Zaluzh\u2019ye"
    ],
    "wof:name":"Zaluzh'ye",
    "wof:placetype":"locality"
},
  "geometry": {"coordinates":[28.184,53.4884],"type":"Point"}
}