{
  "type": "Feature",
  "properties": {
    "gn:admin1_code":"1.0",
    "gn:asciiname":"Tulyatichi",
    "gn:country_code":"BY",
    "gn:dem":158,
    "gn:feature_class":"P",
    "gn:feature_code":"PPL",
    "gn:name":"Tulyatichi",
    "gn:population":0,
    "gn:timezone":"Europe/Minsk",
    "iso:country":"BY",
    "name:rus_x_preferred":[
        "\u0422\u0443\u043b\u044f\u0442\u0438\u0447\u0438"
    ],
    "wof:name":"Tulyatichi",
    "wof:placetype":"locality"
},
  "geometry": {"coordinates":[25.3647,52.3043],"type":"Point"}
}