{
  "type": "Feature",
  "properties": {
    "gn:admin1_code":"5.0",
    "gn:asciiname":"Lokhovshchina",
    "gn:country_code":"BY",
    "gn:dem":219,
    "gn:feature_class":"P",
    "gn:feature_code":"PPL",
    "gn:name":"Lokhovshchina",
    "gn:population":0,
    "gn:timezone":"Europe/Minsk",
    "iso:country":"BY",
    "name:rus_x_preferred":[
        "\u041b\u043e\u0445\u043e\u0432\u0449\u0438\u043d\u0430"
    ],
    "wof:name":"Lokhovshchina",
    "wof:placetype":"locality"
},
  "geometry": {"coordinates":[26.4635,54.2622],"type":"Point"}
}