{
  "type": "Feature",
  "properties": {
    "gn:admin1_code":"5.0",
    "gn:asciiname":"Poperezh'ye",
    "gn:country_code":"BY",
    "gn:dem":173,
    "gn:feature_class":"P",
    "gn:feature_code":"PPL",
    "gn:name":"Pop\u00ebrezh\u2019ye",
    "gn:population":0,
    "gn:timezone":"Europe/Minsk",
    "iso:country":"BY",
    "name:rus_x_preferred":[
        "\u041f\u043e\u043f\u0451\u0440\u0435\u0436\u044c\u0435"
    ],
    "name:und_x_variant":[
        "Pop\u00ebrezh\u2019ye",
        "Podberez\u2019ye"
    ],
    "wof:name":"Poperezh'ye",
    "wof:placetype":"locality"
},
  "geometry": {"coordinates":[28.3126,54.474],"type":"Point"}
}