{
  "type": "Feature",
  "properties": {
    "gn:admin1_code":"2.0",
    "gn:asciiname":"Lipa",
    "gn:country_code":"BY",
    "gn:dem":132,
    "gn:feature_class":"P",
    "gn:feature_code":"PPL",
    "gn:name":"Lipa",
    "gn:population":0,
    "gn:timezone":"Europe/Minsk",
    "iso:country":"BY",
    "name:bel_x_preferred":[
        "\u041b\u0456\u043f\u0430"
    ],
    "name:bos_x_preferred":[
        "Lipa"
    ],
    "name:bul_x_preferred":[
        "\u041b\u0438\u043f\u0430"
    ],
    "name:ceb_x_preferred":[
        "Lipa"
    ],
    "name:deu_x_preferred":[
        "Lipa"
    ],
    "name:eng_x_preferred":[
        "Lipa"
    ],
    "name:fra_x_preferred":[
        "Lipa"
    ],
    "name:hrv_x_preferred":[
        "Lipa"
    ],
    "name:hun_x_preferred":[
        "Lipa"
    ],
    "name:hye_x_preferred":[
        "\u053c\u056b\u057a\u0561"
    ],
    "name:ita_x_preferred":[
        "Lipa"
    ],
    "name:nld_x_preferred":[
        "Lipa"
    ],
    "name:nor_x_preferred":[
        "LIPA"
    ],
    "name:pol_x_preferred":[
        "Lipa"
    ],
    "name:ron_x_preferred":[
        "Lipa"
    ],
    "name:rus_x_preferred":[
        "\u041b\u0438\u043f\u0430"
    ],
    "name:sco_x_preferred":[
        "Lipa"
    ],
    "name:slk_x_preferred":[
        "Lipa"
    ],
    "name:slv_x_preferred":[
        "Lipa"
    ],
    "name:sqi_x_preferred":[
        "Lipa"
    ],
    "name:srp_x_preferred":[
        "\u041b\u0438\u043f\u0430"
    ],
    "name:swe_x_preferred":[
        "Lipa"
    ],
    "name:ukr_x_preferred":[
        "\u041b\u0456\u043f\u0430"
    ],
    "wof:name":"Lipa",
    "wof:placetype":"locality"
},
  "geometry": {"coordinates":[30.8035,52.7276],"type":"Point"}
}