{
  "type": "Feature",
  "properties": {
    "gn:admin1_code":"5.0",
    "gn:asciiname":"Ivan'",
    "gn:country_code":"BY",
    "gn:dem":161,
    "gn:feature_class":"P",
    "gn:feature_code":"PPL",
    "gn:name":"Ivan\u2019",
    "gn:population":0,
    "gn:timezone":"Europe/Minsk",
    "iso:country":"BY",
    "name:rus_x_preferred":[
        "\u0418\u0432\u0430\u043d\u044c"
    ],
    "name:und_x_variant":[
        "Ivan\u2019"
    ],
    "wof:name":"Ivan'",
    "wof:placetype":"locality"
},
  "geometry": {"coordinates":[27.4475,52.9995],"type":"Point"}
}