{
  "type": "Feature",
  "properties": {
    "gn:admin1_code":"3.0",
    "gn:asciiname":"Azarichi",
    "gn:country_code":"BY",
    "gn:dem":147,
    "gn:feature_class":"P",
    "gn:feature_code":"PPL",
    "gn:name":"Azarichi",
    "gn:population":0,
    "gn:timezone":"Europe/Minsk",
    "iso:country":"BY",
    "name:bel_x_preferred":[
        "Azarychy"
    ],
    "name:bel_x_variant":[
        "\u0410\u0437\u0430\u0440\u044b\u0447\u044b"
    ],
    "name:rus_x_preferred":[
        "\u0410\u0437\u0430\u0440\u0438\u0447\u0438"
    ],
    "name:und_x_variant":[
        "Ozarichi"
    ],
    "wof:name":"Azarichi",
    "wof:placetype":"locality"
},
  "geometry": {"coordinates":[25.3342,53.1876],"type":"Point"}
}