{
  "type": "Feature",
  "properties": {
    "gn:admin1_code":"0.0",
    "gn:asciiname":"Koptyush",
    "gn:cc2":"BY",
    "gn:country_code":"BY",
    "gn:dem":142,
    "gn:feature_class":"P",
    "gn:feature_code":"PPL",
    "gn:name":"Koptyush",
    "gn:population":0,
    "gn:timezone":"Europe/Minsk",
    "iso:country":"BY",
    "name:bel_x_preferred":[
        "\u041a\u0430\u043f\u0446\u044e\u0433\u0456"
    ],
    "name:ceb_x_preferred":[
        "Koptyush"
    ],
    "name:swe_x_preferred":[
        "Koptyush"
    ],
    "name:und_x_variant":[
        "Kaptyugi",
        "Koptyush"
    ],
    "name:urd_x_preferred":[
        "\u0644\u0648\u067e\u062a\u06cc\u0648\u0634"
    ],
    "wof:name":"Koptyush",
    "wof:placetype":"locality"
},
  "geometry": {"coordinates":[28.93333,55.78333000000001],"type":"Point"}
}