{
  "type": "Feature",
  "properties": {
    "gn:admin1_code":"1.0",
    "gn:asciiname":"Yemel'yanovka",
    "gn:country_code":"BY",
    "gn:dem":173,
    "gn:feature_class":"P",
    "gn:feature_code":"PPL",
    "gn:name":"Yemel\u2019yanovka",
    "gn:population":0,
    "gn:timezone":"Europe/Minsk",
    "iso:country":"BY",
    "name:bel_x_preferred":[
        "Yemyal\u2019yanawka"
    ],
    "name:bel_x_variant":[
        "\u0415\u043c\u044f\u043b\u044c\u044f\u043d\u0430\u045e\u043a\u0430"
    ],
    "name:rus_x_preferred":[
        "\u0415\u043c\u0435\u043b\u044c\u044f\u043d\u043e\u0432\u043a\u0430"
    ],
    "name:und_x_variant":[
        "Yemel\u2019yanovka"
    ],
    "wof:name":"Yemel'yanovka",
    "wof:placetype":"locality"
},
  "geometry": {"coordinates":[25.9319,53.0262],"type":"Point"}
}