{
  "type": "Feature",
  "properties": {
    "gn:admin1_code":"3.0",
    "gn:asciiname":"Trudovaya",
    "gn:country_code":"BY",
    "gn:dem":157,
    "gn:feature_class":"P",
    "gn:feature_code":"PPL",
    "gn:name":"Trudovaya",
    "gn:population":0,
    "gn:timezone":"Europe/Minsk",
    "iso:country":"BY",
    "name:bel_x_preferred":[
        "Pratsownaya"
    ],
    "name:bel_x_variant":[
        "\u041f\u0440\u0430\u0446\u043e\u045e\u043d\u0430\u044f"
    ],
    "name:rus_x_preferred":[
        "\u0422\u0440\u0443\u0434\u043e\u0432\u0430\u044f"
    ],
    "wof:name":"Trudovaya",
    "wof:placetype":"locality"
},
  "geometry": {"coordinates":[24.6989,53.7382],"type":"Point"}
}