{
  "type": "Feature",
  "properties": {
    "gn:admin1_code":"5.0",
    "gn:asciiname":"Shabyn'ki",
    "gn:country_code":"BY",
    "gn:dem":160,
    "gn:feature_class":"P",
    "gn:feature_code":"PPL",
    "gn:name":"Shabyn\u2019ki",
    "gn:population":0,
    "gn:timezone":"Europe/Minsk",
    "iso:country":"BY",
    "name:rus_x_preferred":[
        "\u0428\u0430\u0431\u044b\u043d\u044c\u043a\u0438"
    ],
    "name:und_x_variant":[
        "Shabyn\u2019ki",
        "Shabyn\u2019ka"
    ],
    "wof:name":"Shabyn'ki",
    "wof:placetype":"locality"
},
  "geometry": {"coordinates":[28.7268,54.0236],"type":"Point"}
}