{
  "type": "Feature",
  "properties": {
    "gn:admin1_code":"5.0",
    "gn:asciiname":"Prokhody",
    "gn:country_code":"BY",
    "gn:dem":206,
    "gn:feature_class":"P",
    "gn:feature_code":"PPL",
    "gn:name":"Prokhody",
    "gn:population":0,
    "gn:timezone":"Europe/Minsk",
    "iso:country":"BY",
    "name:rus_x_preferred":[
        "\u041f\u0440\u043e\u0445\u043e\u0434\u044b"
    ],
    "wof:name":"Prokhody",
    "wof:placetype":"locality"
},
  "geometry": {"coordinates":[27.7166,54.4452],"type":"Point"}
}