{
  "type": "Feature",
  "properties": {
    "iso:country":"BY",
    "name:bel_x_preferred":[
        "\u0413\u043e\u0440\u0430\u0434 \u0423\u0437\u0434\u0430"
    ],
    "name:bel_x_variant":[
        "\u0423\u0437\u0434\u0430"
    ],
    "name:bul_x_preferred":[
        "\u0423\u0437\u0434\u0430"
    ],
    "name:ceb_x_preferred":[
        "Uzda"
    ],
    "name:chi_x_preferred":[
        "\u70cf\u8332\u9054"
    ],
    "name:deu_x_preferred":[
        "Usda"
    ],
    "name:dut_x_preferred":[
        "Uzda"
    ],
    "name:eng_x_preferred":[
        "Uzda"
    ],
    "name:est_x_preferred":[
        "Uzda"
    ],
    "name:fin_x_preferred":[
        "Uzda"
    ],
    "name:fra_x_preferred":[
        "Ouzda"
    ],
    "name:fre_x_preferred":[
        "Ouzda"
    ],
    "name:ger_x_preferred":[
        "Usda"
    ],
    "name:heb_x_preferred":[
        "\u05d0\u05d5\u05d6\u05d3\u05d4"
    ],
    "name:hsb_x_preferred":[
        "Uzda"
    ],
    "name:lav_x_preferred":[
        "Uzda"
    ],
    "name:lit_x_preferred":[
        "Uzda"
    ],
    "name:pol_x_preferred":[
        "Uzda"
    ],
    "name:rus_x_preferred":[
        "\u0423\u0437\u0434\u0430"
    ],
    "name:srp_x_preferred":[
        "\u0423\u0437\u0434\u0430"
    ],
    "name:swe_x_preferred":[
        "Uzda"
    ],
    "name:tat_x_preferred":[
        "\u0423\u0437\u0434\u0430"
    ],
    "name:ukr_x_preferred":[
        "\u0423\u0437\u0434\u0430"
    ],
    "name:zho_x_preferred":[
        "\u70cf\u8332\u9054"
    ],
    "qs:gn_country":"BY",
    "qs:gn_fcode":"PPL",
    "qs:gn_pop":10000,
    "qs:name":"Uzda",
    "qs:name_adm0":"Belarus",
    "qs:name_adm1":"Minskaya Voblasts'",
    "qs:photos":0,
    "qs:photos_1k":0,
    "qs:photos_9k":1,
    "qs:photos_9r":1,
    "qs:photos_all":16,
    "qs:photos_sr":0,
    "qs:placetype":"Town",
    "qs:pop_sr":"6",
    "qs:woe_adm0":23424765,
    "wd:elevation":172.0,
    "wd:population":9943,
    "wd:wordcount":387,
    "wof:name":"Uzda",
    "wof:placetype":"locality",
    "wof:population":9943
},
  "geometry": {"coordinates":[27.2137,53.4627],"type":"Point"}
}