{
  "type": "Feature",
  "properties": {
    "gn:admin1_code":"7.0",
    "gn:asciiname":"Yetishki",
    "gn:country_code":"BY",
    "gn:dem":184,
    "gn:feature_class":"P",
    "gn:feature_code":"PPL",
    "gn:name":"Yetishki",
    "gn:population":0,
    "gn:timezone":"Europe/Minsk",
    "iso:country":"BY",
    "name:rus_x_preferred":[
        "\u0415\u0442\u0438\u0448\u043a\u0438"
    ],
    "wof:name":"Yetishki",
    "wof:placetype":"locality"
},
  "geometry": {"coordinates":[26.4811,55.1345],"type":"Point"}
}