{
  "type": "Feature",
  "properties": {
    "gn:admin1_code":"3.0",
    "gn:asciiname":"Paluzhzha",
    "gn:country_code":"BY",
    "gn:dem":150,
    "gn:feature_class":"P",
    "gn:feature_code":"PPL",
    "gn:name":"Paluzhzha",
    "gn:population":0,
    "gn:timezone":"Europe/Minsk",
    "iso:country":"BY",
    "name:bel_x_preferred":[
        "\u041f\u0430\u043b\u0443\u0436\u0436\u0430"
    ],
    "name:rus_x_preferred":[
        "Poluzh\u2019ye"
    ],
    "wof:name":"Paluzhzha",
    "wof:placetype":"locality"
},
  "geometry": {"coordinates":[26.1176,53.5286],"type":"Point"}
}