{
  "type": "Feature",
  "properties": {
    "gn:admin1_code":"3.0",
    "gn:asciiname":"Zhodzishki",
    "gn:country_code":"BY",
    "gn:dem":147,
    "gn:feature_class":"P",
    "gn:feature_code":"PPL",
    "gn:name":"Zhodzishki",
    "gn:population":0,
    "gn:timezone":"Europe/Minsk",
    "iso:country":"BY",
    "name:bel_x_preferred":[
        "\u0416\u043e\u0434\u0437\u0456\u0448\u043a\u0456"
    ],
    "name:eng_x_preferred":[
        "Zhodishki"
    ],
    "name:rus_x_preferred":[
        "\u0416\u043e\u0434\u0438\u0448\u043a\u0438"
    ],
    "name:und_x_variant":[
        "\u017bodziszki",
        "Zhodzishki"
    ],
    "wof:name":"Zhodzishki",
    "wof:placetype":"locality"
},
  "geometry": {"coordinates":[26.4419,54.6258],"type":"Point"}
}