{
  "type": "Feature",
  "properties": {
    "gn:admin1_code":"7.0",
    "gn:asciiname":"Duboviki",
    "gn:country_code":"BY",
    "gn:dem":187,
    "gn:feature_class":"P",
    "gn:feature_code":"PPL",
    "gn:name":"Duboviki",
    "gn:population":0,
    "gn:timezone":"Europe/Minsk",
    "iso:country":"BY",
    "name:rus_x_preferred":[
        "\u0414\u0443\u0431\u043e\u0432\u0438\u043a\u0438"
    ],
    "wof:name":"Duboviki",
    "wof:placetype":"locality"
},
  "geometry": {"coordinates":[29.2092,55.8583],"type":"Point"}
}