{
  "type": "Feature",
  "properties": {
    "gn:admin1_code":"5.0",
    "gn:asciiname":"Lyado",
    "gn:country_code":"BY",
    "gn:dem":274,
    "gn:feature_class":"P",
    "gn:feature_code":"PPL",
    "gn:name":"Lyado",
    "gn:population":0,
    "gn:timezone":"Europe/Minsk",
    "iso:country":"BY",
    "name:rus_x_preferred":[
        "\u041b\u044f\u0434\u043e"
    ],
    "wof:name":"Lyado",
    "wof:placetype":"locality"
},
  "geometry": {"coordinates":[27.9319,54.4156],"type":"Point"}
}