{
  "type": "Feature",
  "properties": {
    "gn:admin1_code":"2.0",
    "gn:asciiname":"Bobrech'ye",
    "gn:country_code":"BY",
    "gn:dem":119,
    "gn:feature_class":"P",
    "gn:feature_code":"PPL",
    "gn:name":"Bobrech\u2019ye",
    "gn:population":0,
    "gn:timezone":"Europe/Minsk",
    "iso:country":"BY",
    "name:rus_x_preferred":[
        "\u0411\u043e\u0431\u0440\u0435\u0447\u044c\u0435"
    ],
    "name:und_x_variant":[
        "Bobrech\u2019ye"
    ],
    "wof:name":"Bobrech'ye",
    "wof:placetype":"locality"
},
  "geometry": {"coordinates":[28.7541,52.2097],"type":"Point"}
}