{
  "type": "Feature",
  "properties": {
    "gn:admin1_code":"2.0",
    "gn:asciiname":"Paparatnaye",
    "gn:country_code":"BY",
    "gn:dem":136,
    "gn:feature_class":"P",
    "gn:feature_code":"PPL",
    "gn:name":"Paparatnaye",
    "gn:population":0,
    "gn:timezone":"Europe/Minsk",
    "iso:country":"BY",
    "name:bel_x_preferred":[
        "\u041f\u0430\u043f\u0430\u0440\u0430\u0442\u043d\u0430\u0435"
    ],
    "name:und_x_variant":[
        "Paporotnoye"
    ],
    "wof:name":"Paparatnaye",
    "wof:placetype":"locality"
},
  "geometry": {"coordinates":[29.9954,52.7651],"type":"Point"}
}