{
  "type": "Feature",
  "properties": {
    "gn:admin1_code":"5.0",
    "gn:asciiname":"Al'zhutki",
    "gn:country_code":"BY",
    "gn:dem":176,
    "gn:feature_class":"P",
    "gn:feature_code":"PPL",
    "gn:name":"Al\u2019zhutki",
    "gn:population":0,
    "gn:timezone":"Europe/Minsk",
    "iso:country":"BY",
    "name:rus_x_preferred":[
        "\u0410\u043b\u044c\u0436\u0443\u0442\u043a\u0438"
    ],
    "name:und_x_variant":[
        "El\u017cutki",
        "El\u2019zhutki",
        "Al\u2019zhutki"
    ],
    "wof:name":"Al'zhutki",
    "wof:placetype":"locality"
},
  "geometry": {"coordinates":[27.353,54.7505],"type":"Point"}
}