{
  "type": "Feature",
  "properties": {
    "gn:admin1_code":"6.0",
    "gn:asciiname":"Dubrovka",
    "gn:country_code":"BY",
    "gn:dem":159,
    "gn:feature_class":"P",
    "gn:feature_code":"PPL",
    "gn:name":"Dubrovka",
    "gn:population":0,
    "gn:timezone":"Europe/Minsk",
    "iso:country":"BY",
    "name:aze_x_preferred":[
        "Dubrovka"
    ],
    "name:bel_x_preferred":[
        "\u0414\u0443\u0431\u0440\u043e\u045e\u043a\u0430"
    ],
    "name:ceb_x_preferred":[
        "Dubrovka"
    ],
    "name:ces_x_preferred":[
        "Dubrovka"
    ],
    "name:dan_x_preferred":[
        "Dubrovka"
    ],
    "name:deu_x_preferred":[
        "Dubrowka"
    ],
    "name:fin_x_preferred":[
        "Dubrovka"
    ],
    "name:fra_x_preferred":[
        "Doubrovka"
    ],
    "name:hun_x_preferred":[
        "Dubrovka"
    ],
    "name:hye_x_preferred":[
        "\u0534\u0578\u0582\u0562\u0580\u0578\u057e\u056f\u0561"
    ],
    "name:ita_x_preferred":[
        "Dubrovka"
    ],
    "name:kaz_x_preferred":[
        "\u0414\u0443\u0431\u0440\u043e\u0432\u043a\u0430"
    ],
    "name:lav_x_preferred":[
        "Dubrovka"
    ],
    "name:pol_x_preferred":[
        "Dubrowka"
    ],
    "name:rus_x_preferred":[
        "\u0414\u0443\u0431\u0440\u043e\u0432\u043a\u0430"
    ],
    "name:swe_x_preferred":[
        "Dubrovka"
    ],
    "name:tat_x_preferred":[
        "\u0414\u0443\u0431\u0440\u043e\u0432\u043a\u0430"
    ],
    "name:ukr_x_preferred":[
        "\u0414\u0443\u0431\u0440\u043e\u0432\u043a\u0430"
    ],
    "wof:name":"Dubrovka",
    "wof:placetype":"locality"
},
  "geometry": {"coordinates":[32.0471,53.1482],"type":"Point"}
}