{
  "type": "Feature",
  "properties": {
    "gn:admin1_code":"7.0",
    "gn:asciiname":"Semino",
    "gn:country_code":"BY",
    "gn:dem":162,
    "gn:feature_class":"P",
    "gn:feature_code":"PPL",
    "gn:name":"S\u00ebmino",
    "gn:population":0,
    "gn:timezone":"Europe/Minsk",
    "iso:country":"BY",
    "name:rus_x_preferred":[
        "\u0421\u0451\u043c\u0438\u043d\u043e"
    ],
    "name:und_x_variant":[
        "S\u00ebmino"
    ],
    "wof:name":"Semino",
    "wof:placetype":"locality"
},
  "geometry": {"coordinates":[30.6521,55.2977],"type":"Point"}
}