{
  "type": "Feature",
  "properties": {
    "gn:admin1_code":"6.0",
    "gn:asciiname":"Strumensk",
    "gn:country_code":"BY",
    "gn:dem":158,
    "gn:feature_class":"P",
    "gn:feature_code":"PPL",
    "gn:name":"Strumensk",
    "gn:population":0,
    "gn:timezone":"Europe/Minsk",
    "iso:country":"BY",
    "name:rus_x_preferred":[
        "\u0421\u0442\u0440\u0443\u043c\u0435\u043d\u0441\u043a"
    ],
    "wof:name":"Strumensk",
    "wof:placetype":"locality"
},
  "geometry": {"coordinates":[31.1322,53.1492],"type":"Point"}
}