{
  "type": "Feature",
  "properties": {
    "gn:admin1_code":"2.0",
    "gn:asciiname":"Yurkyevichy",
    "gn:country_code":"BY",
    "gn:dem":132,
    "gn:feature_class":"P",
    "gn:feature_code":"PPL",
    "gn:name":"Yurkyevichy",
    "gn:population":0,
    "gn:timezone":"Europe/Minsk",
    "iso:country":"BY",
    "name:bel_x_preferred":[
        "\u042e\u0440\u043a\u0435\u0432\u0456\u0447\u044b"
    ],
    "name:und_x_variant":[
        "Yurkevichi"
    ],
    "wof:name":"Yurkyevichy",
    "wof:placetype":"locality"
},
  "geometry": {"coordinates":[27.6108,52.3101],"type":"Point"}
}