{
  "type": "Feature",
  "properties": {
    "gn:admin1_code":"6.0",
    "gn:asciiname":"Pankratavichy",
    "gn:country_code":"BY",
    "gn:dem":143,
    "gn:feature_class":"P",
    "gn:feature_code":"PPL",
    "gn:name":"Pankratavichy",
    "gn:population":0,
    "gn:timezone":"Europe/Minsk",
    "iso:country":"BY",
    "name:bel_x_preferred":[
        "\u041f\u0430\u043d\u043a\u0440\u0430\u0442\u0430\u0432\u0456\u0447\u044b"
    ],
    "name:eng_x_preferred":[
        "Pankratovichi"
    ],
    "name:rus_x_preferred":[
        "\u041f\u0430\u043d\u043a\u0440\u0430\u0442\u043e\u0432\u0438\u0447\u0438"
    ],
    "name:und_x_variant":[
        "Pankratavichy"
    ],
    "wof:name":"Pankratavichy",
    "wof:placetype":"locality"
},
  "geometry": {"coordinates":[29.4592,52.9585],"type":"Point"}
}