{
  "type": "Feature",
  "properties": {
    "gn:admin1_code":"6.0",
    "gn:asciiname":"Osmolovichi",
    "gn:country_code":"BY",
    "gn:dem":184,
    "gn:feature_class":"P",
    "gn:feature_code":"PPL",
    "gn:name":"Osmolovichi",
    "gn:population":0,
    "gn:timezone":"Europe/Minsk",
    "iso:country":"BY",
    "name:eng_x_preferred":[
        "Osmolovichi"
    ],
    "name:rus_x_preferred":[
        "\u041e\u0441\u043c\u043e\u043b\u043e\u0432\u0438\u0447\u0438"
    ],
    "wof:name":"Osmolovichi",
    "wof:placetype":"locality"
},
  "geometry": {"coordinates":[31.9976,53.53100000000001],"type":"Point"}
}