{
  "type": "Feature",
  "properties": {
    "gn:admin1_code":"6.0",
    "gn:asciiname":"Uluki",
    "gn:country_code":"BY",
    "gn:dem":135,
    "gn:feature_class":"P",
    "gn:feature_code":"PPL",
    "gn:name":"Uluki",
    "gn:population":0,
    "gn:timezone":"Europe/Minsk",
    "iso:country":"BY",
    "name:rus_x_preferred":[
        "\u0423\u043b\u0443\u043a\u0438"
    ],
    "wof:name":"Uluki",
    "wof:placetype":"locality"
},
  "geometry": {"coordinates":[30.9454,53.5798],"type":"Point"}
}