{
  "type": "Feature",
  "properties": {
    "gn:admin1_code":"7.0",
    "gn:asciiname":"Svyatitsa",
    "gn:country_code":"BY",
    "gn:dem":155,
    "gn:feature_class":"P",
    "gn:feature_code":"PPL",
    "gn:name":"Svyatitsa",
    "gn:population":0,
    "gn:timezone":"Europe/Minsk",
    "iso:country":"BY",
    "name:rus_x_preferred":[
        "\u0421\u0432\u044f\u0442\u0438\u0446\u0430"
    ],
    "wof:name":"Svyatitsa",
    "wof:placetype":"locality"
},
  "geometry": {"coordinates":[28.0433,55.9895],"type":"Point"}
}