{
  "type": "Feature",
  "properties": {
    "gn:admin1_code":"1.0",
    "gn:asciiname":"Khomichevo",
    "gn:country_code":"BY",
    "gn:dem":137,
    "gn:feature_class":"P",
    "gn:feature_code":"PPL",
    "gn:name":"Khomich\u00ebvo",
    "gn:population":0,
    "gn:timezone":"Europe/Minsk",
    "iso:country":"BY",
    "name:rus_x_preferred":[
        "Khomich\u00ebvo"
    ],
    "name:rus_x_variant":[
        "\u0425\u043e\u043c\u0438\u0447\u0451\u0432\u043e"
    ],
    "name:und_x_variant":[
        "Khomich\u00ebvo",
        "Khomich\u00ebva"
    ],
    "wof:name":"Khomichevo",
    "wof:placetype":"locality"
},
  "geometry": {"coordinates":[25.5967,52.0158],"type":"Point"}
}