{
  "type": "Feature",
  "properties": {
    "gn:admin1_code":"7.0",
    "gn:asciiname":"Krugi",
    "gn:country_code":"BY",
    "gn:dem":219,
    "gn:feature_class":"P",
    "gn:feature_code":"PPL",
    "gn:name":"Krugi",
    "gn:population":0,
    "gn:timezone":"Europe/Minsk",
    "iso:country":"BY",
    "name:rus_x_preferred":[
        "\u041a\u0440\u0443\u0433\u0438"
    ],
    "wof:name":"Krugi",
    "wof:placetype":"locality"
},
  "geometry": {"coordinates":[30.0408,54.4347],"type":"Point"}
}