{
  "type": "Feature",
  "properties": {
    "gn:admin1_code":"7.0",
    "gn:asciiname":"Chertsy",
    "gn:country_code":"BY",
    "gn:dem":159,
    "gn:feature_class":"P",
    "gn:feature_code":"PPL",
    "gn:name":"Chertsy",
    "gn:population":0,
    "gn:timezone":"Europe/Minsk",
    "iso:country":"BY",
    "name:bel_x_preferred":[
        "\u0427\u044d\u0440\u0446\u044b"
    ],
    "wof:name":"Chertsy",
    "wof:placetype":"locality"
},
  "geometry": {"coordinates":[28.8569,54.8426],"type":"Point"}
}