{
  "type": "Feature",
  "properties": {
    "gn:admin1_code":"3.0",
    "gn:asciiname":"Ben'ki",
    "gn:country_code":"BY",
    "gn:dem":134,
    "gn:feature_class":"P",
    "gn:feature_code":"PPL",
    "gn:name":"Ben\u2019ki",
    "gn:population":0,
    "gn:timezone":"Europe/Minsk",
    "iso:country":"BY",
    "name:rus_x_preferred":[
        "\u0411\u0435\u043d\u044c\u043a\u0438"
    ],
    "name:und_x_variant":[
        "Ben\u2019ki"
    ],
    "wof:name":"Ben'ki",
    "wof:placetype":"locality"
},
  "geometry": {"coordinates":[24.6286,53.9523],"type":"Point"}
}