{
  "type": "Feature",
  "properties": {
    "gn:admin1_code":"7.0",
    "gn:asciiname":"Dvorishche",
    "gn:country_code":"BY",
    "gn:dem":149,
    "gn:feature_class":"P",
    "gn:feature_code":"PPL",
    "gn:name":"Dvorishche",
    "gn:population":0,
    "gn:timezone":"Europe/Minsk",
    "iso:country":"BY",
    "name:rus_x_preferred":[
        "\u0414\u0432\u043e\u0440\u0438\u0449\u0435"
    ],
    "wof:name":"Dvorishche",
    "wof:placetype":"locality"
},
  "geometry": {"coordinates":[28.7187,54.8286],"type":"Point"}
}