{
  "type": "Feature",
  "properties": {
    "gn:admin1_code":"7.0",
    "gn:asciiname":"Zasinniki",
    "gn:country_code":"BY",
    "gn:dem":159,
    "gn:feature_class":"P",
    "gn:feature_code":"PPL",
    "gn:name":"Zasinniki",
    "gn:population":0,
    "gn:timezone":"Europe/Minsk",
    "iso:country":"BY",
    "name:rus_x_preferred":[
        "\u0417\u0430\u0441\u0438\u043d\u043d\u0438\u043a\u0438"
    ],
    "wof:name":"Zasinniki",
    "wof:placetype":"locality"
},
  "geometry": {"coordinates":[29.6601,55.2845],"type":"Point"}
}