{
  "type": "Feature",
  "properties": {
    "gn:admin1_code":"6.0",
    "gn:asciiname":"Lebedevka",
    "gn:country_code":"BY",
    "gn:dem":149,
    "gn:feature_class":"P",
    "gn:feature_code":"PPL",
    "gn:name":"Lebedevka",
    "gn:population":0,
    "gn:timezone":"Europe/Minsk",
    "iso:country":"BY",
    "name:rus_x_preferred":[
        "\u041b\u0435\u0431\u0435\u0434\u0435\u0432\u043a\u0430"
    ],
    "wof:name":"Lebedevka",
    "wof:placetype":"locality"
},
  "geometry": {"coordinates":[29.5071,53.1044],"type":"Point"}
}