{
  "type": "Feature",
  "properties": {
    "gn:admin1_code":"3.0",
    "gn:asciiname":"Malakhovichi",
    "gn:country_code":"BY",
    "gn:dem":139,
    "gn:feature_class":"P",
    "gn:feature_code":"PPL",
    "gn:name":"Malakhovichi",
    "gn:population":0,
    "gn:timezone":"Europe/Minsk",
    "iso:country":"BY",
    "name:rus_x_preferred":[
        "\u041c\u0430\u043b\u0430\u0445\u043e\u0432\u0438\u0447\u0438"
    ],
    "name:und_x_variant":[
        "Malakhoviche",
        "Malakhovichi"
    ],
    "wof:name":"Malakhovichi",
    "wof:placetype":"locality"
},
  "geometry": {"coordinates":[23.843,53.6296],"type":"Point"}
}