{
  "type": "Feature",
  "properties": {
    "gn:admin1_code":"2.0",
    "gn:asciiname":"Staryy Dovsk",
    "gn:country_code":"BY",
    "gn:dem":162,
    "gn:feature_class":"P",
    "gn:feature_code":"PPL",
    "gn:name":"Staryy Dovsk",
    "gn:population":0,
    "gn:timezone":"Europe/Minsk",
    "iso:country":"BY",
    "name:rus_x_preferred":[
        "\u0421\u0442\u0430\u0440\u044b\u0439 \u0414\u043e\u0432\u0441\u043a"
    ],
    "name:und_x_variant":[
        "Staro-Dovsk",
        "Staryy Dovsk"
    ],
    "wof:name":"Staryy Dovsk",
    "wof:placetype":"locality"
},
  "geometry": {"coordinates":[30.4483,53.1933],"type":"Point"}
}