{
  "type": "Feature",
  "properties": {
    "gn:admin1_code":"3.0",
    "gn:asciiname":"Chesheyki",
    "gn:country_code":"BY",
    "gn:dem":138,
    "gn:feature_class":"P",
    "gn:feature_code":"PPL",
    "gn:name":"Chesheyki",
    "gn:population":0,
    "gn:timezone":"Europe/Minsk",
    "iso:country":"BY",
    "name:rus_x_preferred":[
        "\u0427\u0435\u0448\u0435\u0439\u043a\u0438"
    ],
    "wof:name":"Chesheyki",
    "wof:placetype":"locality"
},
  "geometry": {"coordinates":[24.9854,53.8054],"type":"Point"}
}