{
  "type": "Feature",
  "properties": {
    "gn:admin1_code":"2.0",
    "gn:asciiname":"Krasnyy Ales",
    "gn:country_code":"BY",
    "gn:dem":153,
    "gn:feature_class":"P",
    "gn:feature_code":"PPL",
    "gn:name":"Krasnyy Ales",
    "gn:population":0,
    "gn:timezone":"Europe/Minsk",
    "iso:country":"BY",
    "name:rus_x_preferred":[
        "\u041a\u0440\u0430\u0441\u043d\u044b\u0439 \u0410\u043b\u0435\u0441"
    ],
    "wof:name":"Krasnyy Ales",
    "wof:placetype":"locality"
},
  "geometry": {"coordinates":[31.4673,52.2555],"type":"Point"}
}