{
  "type": "Feature",
  "properties": {
    "gn:admin1_code":"2.0",
    "gn:asciiname":"Zhary",
    "gn:country_code":"BY",
    "gn:dem":123,
    "gn:feature_class":"P",
    "gn:feature_code":"PPL",
    "gn:name":"Zhary",
    "gn:population":0,
    "gn:timezone":"Europe/Minsk",
    "iso:country":"BY",
    "name:rus_x_preferred":[
        "\u0416\u0430\u0440\u044b"
    ],
    "wof:name":"Zhary",
    "wof:placetype":"locality"
},
  "geometry": {"coordinates":[30.2665,52.3103],"type":"Point"}
}