{
  "type": "Feature",
  "properties": {
    "gn:admin1_code":"6.0",
    "gn:asciiname":"Rafalin",
    "gn:country_code":"BY",
    "gn:dem":145,
    "gn:feature_class":"P",
    "gn:feature_code":"PPL",
    "gn:name":"Rafalin",
    "gn:population":0,
    "gn:timezone":"Europe/Minsk",
    "iso:country":"BY",
    "name:rus_x_preferred":[
        "\u0420\u0430\u0444\u0430\u043b\u0438\u043d"
    ],
    "wof:name":"Rafalin",
    "wof:placetype":"locality"
},
  "geometry": {"coordinates":[28.8889,53.4594],"type":"Point"}
}