{
  "type": "Feature",
  "properties": {
    "gn:admin1_code":"1.0",
    "gn:asciiname":"Spochinok",
    "gn:country_code":"BY",
    "gn:dem":199,
    "gn:feature_class":"P",
    "gn:feature_code":"PPL",
    "gn:name":"Spochinok",
    "gn:population":0,
    "gn:timezone":"Europe/Minsk",
    "iso:country":"BY",
    "name:bel_x_preferred":[
        "Spachynak"
    ],
    "name:bel_x_variant":[
        "\u0421\u043f\u0430\u0447\u044b\u043d\u0430\u043a"
    ],
    "name:rus_x_preferred":[
        "\u0421\u043f\u043e\u0447\u0438\u043d\u043e\u043a"
    ],
    "wof:name":"Spochinok",
    "wof:placetype":"locality"
},
  "geometry": {"coordinates":[25.8208,53.1191],"type":"Point"}
}