{
  "type": "Feature",
  "properties": {
    "gn:admin1_code":"5.0",
    "gn:asciiname":"Pristan'",
    "gn:country_code":"BY",
    "gn:dem":169,
    "gn:feature_class":"P",
    "gn:feature_code":"PPL",
    "gn:name":"Pristan\u2019",
    "gn:population":0,
    "gn:timezone":"Europe/Minsk",
    "iso:country":"BY",
    "name:rus_x_preferred":[
        "\u041f\u0440\u0438\u0441\u0442\u0430\u043d\u044c"
    ],
    "name:und_x_variant":[
        "Pristan\u2019"
    ],
    "wof:name":"Pristan'",
    "wof:placetype":"locality"
},
  "geometry": {"coordinates":[27.8299,53.4863],"type":"Point"}
}