{
  "type": "Feature",
  "properties": {
    "gn:admin1_code":"1.0",
    "gn:asciiname":"Zagozhe",
    "gn:country_code":"BY",
    "gn:dem":185,
    "gn:feature_class":"P",
    "gn:feature_code":"PPL",
    "gn:name":"Zagozhe",
    "gn:population":0,
    "gn:timezone":"Europe/Minsk",
    "iso:country":"BY",
    "name:rus_x_preferred":[
        "Zagor\u2019ye"
    ],
    "name:rus_x_variant":[
        "\u0417\u0430\u0433\u043e\u0440\u044c\u0435"
    ],
    "name:und_x_variant":[
        "Zagor\u2019ye"
    ],
    "wof:name":"Zagozhe",
    "wof:placetype":"locality"
},
  "geometry": {"coordinates":[26.0897,53.2199],"type":"Point"}
}