{
  "type": "Feature",
  "properties": {
    "gn:admin1_code":"7.0",
    "gn:asciiname":"Bol'shoye Zhezhlino",
    "gn:country_code":"BY",
    "gn:dem":154,
    "gn:feature_class":"P",
    "gn:feature_code":"PPL",
    "gn:name":"Bol\u2019shoye Zhezhlino",
    "gn:population":0,
    "gn:timezone":"Europe/Minsk",
    "iso:country":"BY",
    "name:rus_x_preferred":[
        "\u0411\u043e\u043b\u044c\u0448\u043e\u0435 \u0416\u0435\u0436\u043b\u0438\u043d\u043e"
    ],
    "name:und_x_variant":[
        "Bol\u2019shoye Zhezhlino"
    ],
    "wof:name":"Bol'shoye Zhezhlino",
    "wof:placetype":"locality"
},
  "geometry": {"coordinates":[28.7957,54.9086],"type":"Point"}
}