{
  "type": "Feature",
  "properties": {
    "gn:admin1_code":"7.0",
    "gn:asciiname":"Meshchentsy",
    "gn:country_code":"BY",
    "gn:dem":243,
    "gn:feature_class":"P",
    "gn:feature_code":"PPL",
    "gn:name":"Meshchentsy",
    "gn:population":0,
    "gn:timezone":"Europe/Minsk",
    "iso:country":"BY",
    "name:rus_x_preferred":[
        "\u041c\u0435\u0449\u0435\u043d\u0446\u044b"
    ],
    "wof:name":"Meshchentsy",
    "wof:placetype":"locality"
},
  "geometry": {"coordinates":[29.6897,54.6932],"type":"Point"}
}