{
  "type": "Feature",
  "properties": {
    "gn:admin1_code":"7.0",
    "gn:asciiname":"Podgai",
    "gn:country_code":"BY",
    "gn:dem":183,
    "gn:feature_class":"P",
    "gn:feature_code":"PPL",
    "gn:name":"Podgai",
    "gn:population":0,
    "gn:timezone":"Europe/Minsk",
    "iso:country":"BY",
    "name:rus_x_preferred":[
        "\u041f\u043e\u0434\u0433\u0430\u0438"
    ],
    "wof:name":"Podgai",
    "wof:placetype":"locality"
},
  "geometry": {"coordinates":[27.742,55.1009],"type":"Point"}
}