{
  "type": "Feature",
  "properties": {
    "gn:admin1_code":"3.0",
    "gn:asciiname":"Chereshlya",
    "gn:country_code":"BY",
    "gn:dem":132,
    "gn:feature_class":"P",
    "gn:feature_code":"PPL",
    "gn:name":"Chereshlya",
    "gn:population":0,
    "gn:timezone":"Europe/Minsk",
    "iso:country":"BY",
    "name:rus_x_preferred":[
        "\u0427\u0435\u0440\u0435\u0448\u043b\u044f"
    ],
    "name:und_x_variant":[
        "Chereshle",
        "Chereshli",
        "Chereshlya"
    ],
    "wof:name":"Chereshlya",
    "wof:placetype":"locality"
},
  "geometry": {"coordinates":[25.898,53.8051],"type":"Point"}
}