{
  "type": "Feature",
  "properties": {
    "gn:admin1_code":"5.0",
    "gn:asciiname":"Slavinka",
    "gn:country_code":"BY",
    "gn:dem":186,
    "gn:feature_class":"P",
    "gn:feature_code":"PPL",
    "gn:name":"Slavinka",
    "gn:population":0,
    "gn:timezone":"Europe/Minsk",
    "iso:country":"BY",
    "name:rus_x_preferred":[
        "\u0421\u043b\u0430\u0432\u0438\u043d\u043a\u0430"
    ],
    "wof:name":"Slavinka",
    "wof:placetype":"locality"
},
  "geometry": {"coordinates":[26.9174,53.0424],"type":"Point"}
}