{
  "type": "Feature",
  "properties": {
    "gn:admin1_code":"1.0",
    "gn:asciiname":"Khotinovo",
    "gn:country_code":"BY",
    "gn:dem":146,
    "gn:feature_class":"P",
    "gn:feature_code":"PPL",
    "gn:name":"Khotinovo",
    "gn:population":0,
    "gn:timezone":"Europe/Minsk",
    "iso:country":"BY",
    "name:rus_x_preferred":[
        "\u0425\u043e\u0442\u0438\u043d\u043e\u0432\u043e"
    ],
    "wof:name":"Khotinovo",
    "wof:placetype":"locality"
},
  "geometry": {"coordinates":[23.5689,52.3438],"type":"Point"}
}