{
  "type": "Feature",
  "properties": {
    "gn:admin1_code":"6.0",
    "gn:asciiname":"Zimnitsy",
    "gn:country_code":"BY",
    "gn:dem":173,
    "gn:feature_class":"P",
    "gn:feature_code":"PPL",
    "gn:name":"Zimnitsy",
    "gn:population":0,
    "gn:timezone":"Europe/Minsk",
    "iso:country":"BY",
    "name:rus_x_preferred":[
        "\u0417\u0438\u043c\u043d\u0438\u0446\u044b"
    ],
    "wof:name":"Zimnitsy",
    "wof:placetype":"locality"
},
  "geometry": {"coordinates":[32.0253,53.6382],"type":"Point"}
}