{
  "type": "Feature",
  "properties": {
    "gn:admin1_code":"7.0",
    "gn:asciiname":"Zal'khov'ye",
    "gn:country_code":"BY",
    "gn:dem":189,
    "gn:feature_class":"P",
    "gn:feature_code":"PPL",
    "gn:name":"Zal\u2019khov\u2019ye",
    "gn:population":0,
    "gn:timezone":"Europe/Minsk",
    "iso:country":"BY",
    "name:rus_x_preferred":[
        "\u0417\u0430\u043b\u044c\u0445\u043e\u0432\u044c\u0435"
    ],
    "name:und_x_variant":[
        "Zal\u2019khov\u2019ye"
    ],
    "wof:name":"Zal'khov'ye",
    "wof:placetype":"locality"
},
  "geometry": {"coordinates":[28.3556,54.896],"type":"Point"}
}