{
  "type": "Feature",
  "properties": {
    "gn:admin1_code":"2.0",
    "gn:asciiname":"Duyanovka",
    "gn:country_code":"BY",
    "gn:dem":138,
    "gn:feature_class":"P",
    "gn:feature_code":"PPL",
    "gn:name":"Duyanovka",
    "gn:population":0,
    "gn:timezone":"Europe/Minsk",
    "iso:country":"BY",
    "name:rus_x_preferred":[
        "\u0414\u0443\u044f\u043d\u043e\u0432\u043a\u0430"
    ],
    "wof:name":"Duyanovka",
    "wof:placetype":"locality"
},
  "geometry": {"coordinates":[31.1873,52.2796],"type":"Point"}
}