{
  "type": "Feature",
  "properties": {
    "gn:admin1_code":"5.0",
    "gn:asciiname":"Men'ki",
    "gn:country_code":"BY",
    "gn:dem":292,
    "gn:feature_class":"P",
    "gn:feature_code":"PPL",
    "gn:name":"Men\u2019ki",
    "gn:population":0,
    "gn:timezone":"Europe/Minsk",
    "iso:country":"BY",
    "name:rus_x_preferred":[
        "\u041c\u0435\u043d\u044c\u043a\u0438"
    ],
    "name:und_x_variant":[
        "Men\u2019ki"
    ],
    "wof:name":"Men'ki",
    "wof:placetype":"locality"
},
  "geometry": {"coordinates":[26.9864,53.9127],"type":"Point"}
}