{
  "type": "Feature",
  "properties": {
    "gn:admin1_code":"2.0",
    "gn:asciiname":"Abol'tsy",
    "gn:country_code":"BY",
    "gn:dem":137,
    "gn:feature_class":"P",
    "gn:feature_code":"PPL",
    "gn:name":"Abol\u2019tsy",
    "gn:population":0,
    "gn:timezone":"Europe/Minsk",
    "iso:country":"BY",
    "name:rus_x_preferred":[
        "\u0410\u0431\u043e\u043b\u044c\u0446\u044b"
    ],
    "name:und_x_variant":[
        "Abol\u2019tsy",
        "Obol\u2019tsy"
    ],
    "wof:name":"Abol'tsy",
    "wof:placetype":"locality"
},
  "geometry": {"coordinates":[29.9126,52.7052],"type":"Point"}
}