{
  "type": "Feature",
  "properties": {
    "gn:admin1_code":"7.0",
    "gn:asciiname":"Kashino",
    "gn:country_code":"BY",
    "gn:dem":198,
    "gn:feature_class":"P",
    "gn:feature_code":"PPL",
    "gn:name":"Kashino",
    "gn:population":0,
    "gn:timezone":"Europe/Minsk",
    "iso:country":"BY",
    "name:che_x_preferred":[
        "\u041a\u0430\u0448\u0438\u043d\u043e"
    ],
    "name:rus_x_preferred":[
        "\u041a\u0430\u0448\u0438\u043d\u043e"
    ],
    "wof:name":"Kashino",
    "wof:placetype":"locality"
},
  "geometry": {"coordinates":[30.2461,54.6036],"type":"Point"}
}