{
  "type": "Feature",
  "properties": {
    "gn:admin1_code":"3.0",
    "gn:asciiname":"Smalyanaya Pyech",
    "gn:country_code":"BY",
    "gn:dem":131,
    "gn:feature_class":"P",
    "gn:feature_code":"PPL",
    "gn:name":"Smalyanaya Pyech",
    "gn:population":0,
    "gn:timezone":"Europe/Minsk",
    "iso:country":"BY",
    "name:bel_x_preferred":[
        "Smalyanaya Pyech"
    ],
    "name:bel_x_variant":[
        "\u0421\u043c\u0430\u043b\u044f\u043d\u0430\u044f \u041f\u0435\u0447"
    ],
    "name:rus_x_preferred":[
        "\u0421\u043c\u043e\u043b\u044f\u043d\u0430\u044f \u041f\u0435\u0447\u044c"
    ],
    "name:und_x_variant":[
        "Smolyanaya Pech\u2019"
    ],
    "wof:name":"Smalyanaya Pyech",
    "wof:placetype":"locality"
},
  "geometry": {"coordinates":[25.1524,53.3258],"type":"Point"}
}