{
  "type": "Feature",
  "properties": {
    "gn:admin1_code":"5.0",
    "gn:asciiname":"Zhirblevichi",
    "gn:country_code":"BY",
    "gn:dem":241,
    "gn:feature_class":"P",
    "gn:feature_code":"PPL",
    "gn:name":"Zhirblevichi",
    "gn:population":0,
    "gn:timezone":"Europe/Minsk",
    "iso:country":"BY",
    "name:rus_x_preferred":[
        "\u0416\u0438\u0440\u0431\u043b\u0435\u0432\u0438\u0447\u0438"
    ],
    "wof:name":"Zhirblevichi",
    "wof:placetype":"locality"
},
  "geometry": {"coordinates":[27.7489,54.3004],"type":"Point"}
}