{
  "type": "Feature",
  "properties": {
    "gn:admin1_code":"6.0",
    "gn:asciiname":"Tristivka",
    "gn:country_code":"BY",
    "gn:dem":152,
    "gn:feature_class":"P",
    "gn:feature_code":"PPL",
    "gn:name":"Tristivka",
    "gn:population":0,
    "gn:timezone":"Europe/Minsk",
    "iso:country":"BY",
    "name:rus_x_preferred":[
        "\u0422\u0440\u0438\u0441\u0442\u0438\u0432\u043a\u0430"
    ],
    "wof:name":"Tristivka",
    "wof:placetype":"locality"
},
  "geometry": {"coordinates":[30.5047,53.3353],"type":"Point"}
}