{
  "type": "Feature",
  "properties": {
    "gn:admin1_code":"6.0",
    "gn:asciiname":"Zhavoronki",
    "gn:country_code":"BY",
    "gn:dem":148,
    "gn:feature_class":"P",
    "gn:feature_code":"PPL",
    "gn:name":"Zhavoronki",
    "gn:population":0,
    "gn:timezone":"Europe/Minsk",
    "iso:country":"BY",
    "name:ara_x_preferred":[
        "\u0632\u0647\u0627\u0641\u0648\u0631\u0648\u0646\u0643\u064a"
    ],
    "name:ceb_x_preferred":[
        "Zhavoronki"
    ],
    "name:che_x_preferred":[
        "\u0416\u0430\u0432\u043e\u0440\u043e\u043d\u043a\u0438"
    ],
    "name:rus_x_preferred":[
        "\u0416\u0430\u0432\u043e\u0440\u043e\u043d\u043a\u0438"
    ],
    "wof:name":"Zhavoronki",
    "wof:placetype":"locality"
},
  "geometry": {"coordinates":[29.6255,53.1142],"type":"Point"}
}