{
  "type": "Feature",
  "properties": {
    "gn:admin1_code":"2.0",
    "gn:asciiname":"Yantarnyy",
    "gn:country_code":"BY",
    "gn:dem":143,
    "gn:feature_class":"P",
    "gn:feature_code":"PPL",
    "gn:name":"Yantarnyy",
    "gn:population":0,
    "gn:timezone":"Europe/Minsk",
    "iso:country":"BY",
    "name:rus_x_preferred":[
        "\u042f\u043d\u0442\u0430\u0440\u043d\u044b\u0439"
    ],
    "name:und_x_variant":[
        "Pos\u00eblok Yantarnyy"
    ],
    "wof:name":"Yantarnyy",
    "wof:placetype":"locality"
},
  "geometry": {"coordinates":[30.9865,52.5017],"type":"Point"}
}