{
  "type": "Feature",
  "properties": {
    "gn:admin1_code":"6.0",
    "gn:asciiname":"Svetozer'ye",
    "gn:country_code":"BY",
    "gn:dem":185,
    "gn:feature_class":"P",
    "gn:feature_code":"PPL",
    "gn:name":"Svetoz\u00ebr\u2019ye",
    "gn:population":0,
    "gn:timezone":"Europe/Minsk",
    "iso:country":"BY",
    "name:rus_x_preferred":[
        "\u0421\u0432\u0435\u0442\u043e\u0437\u0451\u0440\u044c\u0435"
    ],
    "name:und_x_variant":[
        "Svetoz\u00ebr\u2019ye",
        "Svyatozer\u2019ye"
    ],
    "wof:name":"Svetozer'ye",
    "wof:placetype":"locality"
},
  "geometry": {"coordinates":[31.1494,53.7673],"type":"Point"}
}