{
  "type": "Feature",
  "properties": {
    "gn:admin1_code":"3.0",
    "gn:asciiname":"Masyuny",
    "gn:country_code":"BY",
    "gn:dem":175,
    "gn:feature_class":"P",
    "gn:feature_code":"PPL",
    "gn:name":"Masyuny",
    "gn:population":0,
    "gn:timezone":"Europe/Minsk",
    "iso:country":"BY",
    "name:rus_x_preferred":[
        "\u041c\u0430\u0441\u044e\u043d\u044b"
    ],
    "wof:name":"Masyuny",
    "wof:placetype":"locality"
},
  "geometry": {"coordinates":[25.5197,54.2415],"type":"Point"}
}