{
  "type": "Feature",
  "properties": {
    "gn:admin1_code":"5.0",
    "gn:asciiname":"Shabun'ki",
    "gn:country_code":"BY",
    "gn:dem":151,
    "gn:feature_class":"P",
    "gn:feature_code":"PPL",
    "gn:name":"Shabun\u2019ki",
    "gn:population":0,
    "gn:timezone":"Europe/Minsk",
    "iso:country":"BY",
    "name:rus_x_preferred":[
        "\u0428\u0430\u0431\u0443\u043d\u044c\u043a\u0438"
    ],
    "name:und_x_variant":[
        "Shabun\u2019ki"
    ],
    "wof:name":"Shabun'ki",
    "wof:placetype":"locality"
},
  "geometry": {"coordinates":[27.5212,52.9031],"type":"Point"}
}