{
  "type": "Feature",
  "properties": {
    "gn:admin1_code":"3.0",
    "gn:asciiname":"Kondaki",
    "gn:country_code":"BY",
    "gn:dem":155,
    "gn:feature_class":"P",
    "gn:feature_code":"PPL",
    "gn:name":"Kondaki",
    "gn:population":0,
    "gn:timezone":"Europe/Minsk",
    "iso:country":"BY",
    "name:bel_x_preferred":[
        "Kandaki"
    ],
    "name:bel_x_variant":[
        "\u041a\u0430\u043d\u0434\u0430\u043a\u0456"
    ],
    "name:rus_x_preferred":[
        "\u041a\u043e\u043d\u0434\u0430\u043a\u0438"
    ],
    "wof:name":"Kondaki",
    "wof:placetype":"locality"
},
  "geometry": {"coordinates":[24.6747,53.1937],"type":"Point"}
}