{
  "type": "Feature",
  "properties": {
    "gn:admin1_code":"6.0",
    "gn:asciiname":"Tsyomny Lyes",
    "gn:country_code":"BY",
    "gn:dem":225,
    "gn:feature_class":"P",
    "gn:feature_code":"PPL",
    "gn:name":"Tsyomny Lyes",
    "gn:population":0,
    "gn:timezone":"Europe/Minsk",
    "iso:country":"BY",
    "name:bel_x_preferred":[
        "\u0426\u0451\u043c\u043d\u044b \u041b\u0435\u0441"
    ],
    "name:eng_x_preferred":[
        "T\u00ebmnyy Les"
    ],
    "name:rus_x_preferred":[
        "\u0422\u0435\u043c\u043d\u044b\u0439_\u043b\u0435\u0441"
    ],
    "name:und_x_variant":[
        "Teninyy Les",
        "T\u00ebmnyy Les",
        "Tsyomny Lyes"
    ],
    "wof:name":"Tsyomny Lyes",
    "wof:placetype":"locality"
},
  "geometry": {"coordinates":[31.2357,54.0996],"type":"Point"}
}