{
  "type": "Feature",
  "properties": {
    "gn:admin1_code":"5.0",
    "gn:asciiname":"Vedritsa",
    "gn:country_code":"BY",
    "gn:dem":176,
    "gn:feature_class":"P",
    "gn:feature_code":"PPL",
    "gn:name":"Vedritsa",
    "gn:population":0,
    "gn:timezone":"Europe/Minsk",
    "iso:country":"BY",
    "name:rus_x_preferred":[
        "\u0412\u0435\u0434\u0440\u0438\u0446\u0430"
    ],
    "wof:name":"Vedritsa",
    "wof:placetype":"locality"
},
  "geometry": {"coordinates":[28.662,53.7663],"type":"Point"}
}