{
  "type": "Feature",
  "properties": {
    "gn:admin1_code":"7.0",
    "gn:asciiname":"Babichi",
    "gn:country_code":"BY",
    "gn:dem":197,
    "gn:feature_class":"P",
    "gn:feature_code":"PPL",
    "gn:name":"Babichi",
    "gn:population":0,
    "gn:timezone":"Europe/Minsk",
    "iso:country":"BY",
    "name:rus_x_preferred":[
        "\u0411\u0430\u0431\u0438\u0447\u0438"
    ],
    "wof:name":"Babichi",
    "wof:placetype":"locality"
},
  "geometry": {"coordinates":[30.6178,54.4352],"type":"Point"}
}