{
  "type": "Feature",
  "properties": {
    "gn:admin1_code":"3.0",
    "gn:asciiname":"Norshty",
    "gn:country_code":"BY",
    "gn:dem":200,
    "gn:feature_class":"P",
    "gn:feature_code":"PPL",
    "gn:name":"Norshty",
    "gn:population":0,
    "gn:timezone":"Europe/Minsk",
    "iso:country":"BY",
    "name:rus_x_preferred":[
        "\u041d\u043e\u0440\u0448\u0442\u044b"
    ],
    "wof:name":"Norshty",
    "wof:placetype":"locality"
},
  "geometry": {"coordinates":[25.9232,54.2936],"type":"Point"}
}