{
  "type": "Feature",
  "properties": {
    "gn:admin1_code":"1.0",
    "gn:asciiname":"Grivkovichi",
    "gn:country_code":"BY",
    "gn:dem":133,
    "gn:feature_class":"P",
    "gn:feature_code":"PPL",
    "gn:name":"Grivkovichi",
    "gn:population":0,
    "gn:timezone":"Europe/Minsk",
    "iso:country":"BY",
    "name:rus_x_preferred":[
        "\u0413\u0440\u0438\u0432\u043a\u043e\u0432\u0438\u0447\u0438"
    ],
    "name:und_x_variant":[
        "Grzywkowicze",
        "Grivkovichi",
        "Gzhivkoviche"
    ],
    "wof:name":"Grivkovichi",
    "wof:placetype":"locality"
},
  "geometry": {"coordinates":[26.4712,52.0119],"type":"Point"}
}