{
  "type": "Feature",
  "properties": {
    "gn:admin1_code":"5.0",
    "gn:asciiname":"Vomel'na",
    "gn:country_code":"BY",
    "gn:dem":163,
    "gn:feature_class":"P",
    "gn:feature_code":"PPL",
    "gn:name":"Vomel\u2019na",
    "gn:population":0,
    "gn:timezone":"Europe/Minsk",
    "iso:country":"BY",
    "name:bel_x_preferred":[
        "\u0412\u043e\u043c\u0435\u043b\u044c\u043d\u0430"
    ],
    "name:eng_x_preferred":[
        "Omel'no"
    ],
    "name:rus_x_preferred":[
        "\u041e\u043c\u0435\u043b\u044c\u043d\u043e"
    ],
    "name:rus_x_variant":[
        "Omel\u2019no"
    ],
    "name:und_x_variant":[
        "Vomel\u2019na"
    ],
    "wof:name":"Vomel'na",
    "wof:placetype":"locality"
},
  "geometry": {"coordinates":[28.037,53.3639],"type":"Point"}
}