{
  "type": "Feature",
  "properties": {
    "gn:admin1_code":"5.0",
    "gn:asciiname":"Ogorodniki",
    "gn:country_code":"BY",
    "gn:dem":267,
    "gn:feature_class":"P",
    "gn:feature_code":"PPL",
    "gn:name":"Ogorodniki",
    "gn:population":0,
    "gn:timezone":"Europe/Minsk",
    "iso:country":"BY",
    "name:rus_x_preferred":[
        "\u041e\u0433\u043e\u0440\u043e\u0434\u043d\u0438\u043a\u0438"
    ],
    "wof:name":"Ogorodniki",
    "wof:placetype":"locality"
},
  "geometry": {"coordinates":[27.0697,54.0786],"type":"Point"}
}