{
  "type": "Feature",
  "properties": {
    "gn:admin1_code":"6.0",
    "gn:asciiname":"Kvartyany",
    "gn:country_code":"BY",
    "gn:dem":195,
    "gn:feature_class":"P",
    "gn:feature_code":"PPL",
    "gn:name":"Kvartyany",
    "gn:population":0,
    "gn:timezone":"Europe/Minsk",
    "iso:country":"BY",
    "name:rus_x_preferred":[
        "\u041a\u0432\u0430\u0440\u0442\u044f\u043d\u044b"
    ],
    "wof:name":"Kvartyany",
    "wof:placetype":"locality"
},
  "geometry": {"coordinates":[31.0876,54.2907],"type":"Point"}
}