{
  "type": "Feature",
  "properties": {
    "gn:admin1_code":"2.0",
    "gn:asciiname":"Verbichev",
    "gn:country_code":"BY",
    "gn:dem":140,
    "gn:feature_class":"P",
    "gn:feature_code":"PPL",
    "gn:name":"Verbichev",
    "gn:population":0,
    "gn:timezone":"Europe/Minsk",
    "iso:country":"BY",
    "name:rus_x_preferred":[
        "\u0412\u0435\u0440\u0431\u0438\u0447\u0435\u0432"
    ],
    "wof:name":"Verbichev",
    "wof:placetype":"locality"
},
  "geometry": {"coordinates":[29.9725,52.9654],"type":"Point"}
}