{
  "type": "Feature",
  "properties": {
    "gn:admin1_code":"1.0",
    "gn:asciiname":"Mikashevichy",
    "gn:country_code":"BY",
    "gn:dem":128,
    "gn:feature_class":"P",
    "gn:feature_code":"PPL",
    "gn:name":"Mikashevichy",
    "gn:population":14000,
    "gn:timezone":"Europe/Minsk",
    "iso:country":"BY",
    "name:bel_x_preferred":[
        "\u041c\u0456\u043a\u0430\u0448\u0435\u0432\u0456\u0447\u044b"
    ],
    "name:bel_x_variant":[
        "\u041c\u0456\u043a\u0430\u0448\u044d\u0432\u0456\u0447\u044b"
    ],
    "name:bul_x_preferred":[
        "\u041c\u0438\u043a\u0430\u0448\u0435\u0432\u0438\u0447\u0438"
    ],
    "name:ceb_x_preferred":[
        "Mikashevichy"
    ],
    "name:ces_x_preferred":[
        "Mika\u0161evi\u010dy"
    ],
    "name:deu_x_preferred":[
        "Mikaschewitschy"
    ],
    "name:eng_x_preferred":[
        "Mikashevichi"
    ],
    "name:est_x_preferred":[
        "Mika\u0161evi\u010dy"
    ],
    "name:fin_x_preferred":[
        "Mika\u0161evit\u0161y"
    ],
    "name:fra_x_preferred":[
        "Mikachevitchy"
    ],
    "name:heb_x_preferred":[
        "\u05de\u05d9\u05e7\u05e9\u05d1\u05d9\u05e5'"
    ],
    "name:hsb_x_preferred":[
        "Mika\u0161ewi\u010dy"
    ],
    "name:ita_x_preferred":[
        "Mika\u0161evi\u010di"
    ],
    "name:kor_x_preferred":[
        "\ubbf8\uce74\uc170\ube44\uce58"
    ],
    "name:lav_x_preferred":[
        "Mika\u0161evi\u010di"
    ],
    "name:lit_x_preferred":[
        "Mika\u0161evi\u010dai"
    ],
    "name:pol_x_preferred":[
        "Mikaszewicze"
    ],
    "name:rus_x_preferred":[
        "\u041c\u0438\u043a\u0430\u0448\u0435\u0432\u0438\u0447\u0438"
    ],
    "name:srp_x_preferred":[
        "\u041c\u0438\u043a\u0430\u0448\u0435\u0432\u0438\u0447\u0438"
    ],
    "name:swe_x_preferred":[
        "Mikasjevitjy"
    ],
    "name:ukr_x_preferred":[
        "\u041c\u0456\u043a\u0430\u0448\u0435\u0432\u0438\u0447\u0456"
    ],
    "name:und_x_variant":[
        "Mikaszewicze",
        "Mikashevichy",
        "Mikashevichi",
        "Mikasheviche",
        "Makasheviche"
    ],
    "name:zho_x_preferred":[
        "\u7c73\u5361\u820d\u7dad\u5947"
    ],
    "wof:name":"Mikashevichy",
    "wof:placetype":"locality",
    "wof:population":14000
},
  "geometry": {"coordinates":[27.476,52.2173],"type":"Point"}
}