{
  "type": "Feature",
  "properties": {
    "gn:admin1_code":"1.0",
    "gn:asciiname":"Mikashevichy",
    "gn:country_code":"BY",
    "gn:dem":128,
    "gn:feature_class":"P",
    "gn:feature_code":"PPL",
    "gn:name":"Mikashevichy",
    "gn:population":14000,
    "gn:timezone":"Europe/Minsk",
    "iso:country":"BY",
    "name:bel_x_preferred":[
        "\u041c\u0456\u043a\u0430\u0448\u0435\u0432\u0456\u0447\u044b"
    ],
    "name:eng_x_preferred":[
        "Mikashevichi"
    ],
    "name:rus_x_preferred":[
        "\u041c\u0438\u043a\u0430\u0448\u0435\u0432\u0438\u0447\u0438"
    ],
    "name:und_x_variant":[
        "Mikaszewicze",
        "Mikashevichy",
        "Mikashevichi",
        "Mikasheviche",
        "Makasheviche"
    ],
    "wof:name":"Mikashevichy",
    "wof:placetype":"locality",
    "wof:population":14000
},
  "geometry": {"coordinates":[27.476,52.2173],"type":"Point"}
}