{
  "type": "Feature",
  "properties": {
    "gn:admin1_code":"3.0",
    "gn:asciiname":"Pentenishki",
    "gn:country_code":"BY",
    "gn:dem":160,
    "gn:feature_class":"P",
    "gn:feature_code":"PPL",
    "gn:name":"Pentenishki",
    "gn:population":0,
    "gn:timezone":"Europe/Minsk",
    "iso:country":"BY",
    "name:rus_x_preferred":[
        "\u041f\u0435\u043d\u0442\u0435\u043d\u0438\u0448\u043a\u0438"
    ],
    "name:und_x_variant":[
        "Pentinishki"
    ],
    "wof:name":"Pentenishki",
    "wof:placetype":"locality"
},
  "geometry": {"coordinates":[24.9515,54.0378],"type":"Point"}
}