{
  "type": "Feature",
  "properties": {
    "gn:admin1_code":"7.0",
    "gn:asciiname":"Pushkary",
    "gn:country_code":"BY",
    "gn:dem":165,
    "gn:feature_class":"P",
    "gn:feature_code":"PPL",
    "gn:name":"Pushkary",
    "gn:population":0,
    "gn:timezone":"Europe/Minsk",
    "iso:country":"BY",
    "name:rus_x_preferred":[
        "\u041f\u0443\u0448\u043a\u0430\u0440\u044b"
    ],
    "wof:name":"Pushkary",
    "wof:placetype":"locality"
},
  "geometry": {"coordinates":[29.9064,54.882],"type":"Point"}
}