{
  "type": "Feature",
  "properties": {
    "gn:admin1_code":"5.0",
    "gn:asciiname":"Volkovshchina",
    "gn:country_code":"BY",
    "gn:dem":275,
    "gn:feature_class":"P",
    "gn:feature_code":"PPL",
    "gn:name":"Volkovshchina",
    "gn:population":0,
    "gn:timezone":"Europe/Minsk",
    "iso:country":"BY",
    "name:rus_x_preferred":[
        "\u0412\u043e\u043b\u043a\u043e\u0432\u0449\u0438\u043d\u0430"
    ],
    "name:und_x_variant":[
        "Wo\u0142kowszczyzna",
        "Volkovshchyzna",
        "Volkovshchina"
    ],
    "wof:name":"Volkovshchina",
    "wof:placetype":"locality"
},
  "geometry": {"coordinates":[27.0348,54.1982],"type":"Point"}
}