{
  "type": "Feature",
  "properties": {
    "gn:admin1_code":"2.0",
    "gn:asciiname":"Mironenki",
    "gn:country_code":"BY",
    "gn:dem":142,
    "gn:feature_class":"P",
    "gn:feature_code":"PPL",
    "gn:name":"Mironenki",
    "gn:population":0,
    "gn:timezone":"Europe/Minsk",
    "iso:country":"BY",
    "name:rus_x_preferred":[
        "\u041c\u0438\u0440\u043e\u043d\u0435\u043d\u043a\u0438"
    ],
    "wof:name":"Mironenki",
    "wof:placetype":"locality"
},
  "geometry": {"coordinates":[29.5771,52.3885],"type":"Point"}
}