{
  "type": "Feature",
  "properties": {
    "gn:admin1_code":"6.0",
    "gn:asciiname":"Turchanka",
    "gn:country_code":"BY",
    "gn:dem":147,
    "gn:feature_class":"P",
    "gn:feature_code":"PPL",
    "gn:name":"Turchanka",
    "gn:population":0,
    "gn:timezone":"Europe/Minsk",
    "iso:country":"BY",
    "name:rus_x_preferred":[
        "\u0422\u0443\u0440\u0447\u0430\u043d\u043a\u0430"
    ],
    "wof:name":"Turchanka",
    "wof:placetype":"locality"
},
  "geometry": {"coordinates":[29.1944,53.5032],"type":"Point"}
}