{
  "type": "Feature",
  "properties": {
    "gn:admin1_code":"7.0",
    "gn:asciiname":"Tserkovno",
    "gn:country_code":"BY",
    "gn:dem":141,
    "gn:feature_class":"P",
    "gn:feature_code":"PPL",
    "gn:name":"Tserkovno",
    "gn:population":0,
    "gn:timezone":"Europe/Minsk",
    "iso:country":"BY",
    "name:rus_x_preferred":[
        "\u0426\u0435\u0440\u043a\u043e\u0432\u043d\u043e"
    ],
    "wof:name":"Tserkovno",
    "wof:placetype":"locality"
},
  "geometry": {"coordinates":[28.23063,56.03325],"type":"Point"}
}