{
  "type": "Feature",
  "properties": {
    "gn:admin1_code":"5.0",
    "gn:asciiname":"Troyanovo",
    "gn:country_code":"BY",
    "gn:dem":192,
    "gn:feature_class":"P",
    "gn:feature_code":"PPL",
    "gn:name":"Troyanovo",
    "gn:population":0,
    "gn:timezone":"Europe/Minsk",
    "iso:country":"BY",
    "name:eng_x_preferred":[
        "Troyanovo"
    ],
    "name:rus_x_preferred":[
        "\u0422\u0440\u043e\u044f\u043d\u043e\u0432\u043e"
    ],
    "wof:name":"Troyanovo",
    "wof:placetype":"locality"
},
  "geometry": {"coordinates":[26.9311,53.1952],"type":"Point"}
}