{
  "type": "Feature",
  "properties": {
    "gn:admin1_code":"2.0",
    "gn:asciiname":"Dubetskoye",
    "gn:country_code":"BY",
    "gn:dem":129,
    "gn:feature_class":"P",
    "gn:feature_code":"PPL",
    "gn:name":"Dubetskoye",
    "gn:population":0,
    "gn:timezone":"Europe/Minsk",
    "iso:country":"BY",
    "name:rus_x_preferred":[
        "\u0414\u0443\u0431\u0435\u0446\u043a\u043e\u0435"
    ],
    "wof:name":"Dubetskoye",
    "wof:placetype":"locality"
},
  "geometry": {"coordinates":[31.5218,52.4484],"type":"Point"}
}