{
  "type": "Feature",
  "properties": {
    "gn:admin1_code":"7.0",
    "gn:asciiname":"Savskiy Bor",
    "gn:country_code":"BY",
    "gn:dem":167,
    "gn:feature_class":"P",
    "gn:feature_code":"PPL",
    "gn:name":"Savskiy Bor",
    "gn:population":0,
    "gn:timezone":"Europe/Minsk",
    "iso:country":"BY",
    "name:rus_x_preferred":[
        "\u0421\u0430\u0432\u0441\u043a\u0438\u0439 \u0411\u043e\u0440"
    ],
    "wof:name":"Savskiy Bor",
    "wof:placetype":"locality"
},
  "geometry": {"coordinates":[28.2152,54.7109],"type":"Point"}
}