{
  "type": "Feature",
  "properties": {
    "gn:admin1_code":"1.0",
    "gn:asciiname":"Vorotnoye",
    "gn:country_code":"BY",
    "gn:dem":151,
    "gn:feature_class":"P",
    "gn:feature_code":"PPL",
    "gn:name":"Vorotnoye",
    "gn:population":0,
    "gn:timezone":"Europe/Minsk",
    "iso:country":"BY",
    "name:rus_x_preferred":[
        "\u0412\u043e\u0440\u043e\u0442\u043d\u043e\u0435"
    ],
    "name:und_x_variant":[
        "Vorotno"
    ],
    "wof:name":"Vorotnoye",
    "wof:placetype":"locality"
},
  "geometry": {"coordinates":[24.6004,52.4422],"type":"Point"}
}