{
  "type": "Feature",
  "properties": {
    "gn:admin1_code":"2.0",
    "gn:asciiname":"Yadvin",
    "gn:country_code":"BY",
    "gn:dem":146,
    "gn:feature_class":"P",
    "gn:feature_code":"PPL",
    "gn:name":"Yadvin",
    "gn:population":0,
    "gn:timezone":"Europe/Minsk",
    "iso:country":"BY",
    "wof:name":"Yadvin",
    "wof:placetype":"locality"
},
  "geometry": {"coordinates":[31.22833,52.19417],"type":"Point"}
}