{
  "type": "Feature",
  "properties": {
    "gn:admin1_code":"3.0",
    "gn:asciiname":"Magentsy",
    "gn:country_code":"BY",
    "gn:dem":151,
    "gn:feature_class":"P",
    "gn:feature_code":"PPL",
    "gn:name":"Magentsy",
    "gn:population":0,
    "gn:timezone":"Europe/Minsk",
    "iso:country":"BY",
    "name:rus_x_preferred":[
        "\u041c\u0430\u0433\u0435\u043d\u0446\u044b"
    ],
    "name:und_x_variant":[
        "Magen\u2019tsya",
        "Magie\u0144ce",
        "Magentsy"
    ],
    "wof:name":"Magentsy",
    "wof:placetype":"locality"
},
  "geometry": {"coordinates":[26.0752,54.0782],"type":"Point"}
}