{
  "type": "Feature",
  "properties": {
    "gn:admin1_code":"5.0",
    "gn:asciiname":"Staryy Sverzhen'",
    "gn:country_code":"BY",
    "gn:dem":170,
    "gn:feature_class":"P",
    "gn:feature_code":"PPL",
    "gn:name":"Staryy Sverzhen\u2019",
    "gn:population":0,
    "gn:timezone":"Europe/Minsk",
    "iso:country":"BY",
    "name:rus_x_preferred":[
        "\u0421\u0442\u0430\u0440\u044b\u0439 \u0421\u0432\u0435\u0440\u0436\u0435\u043d\u044c"
    ],
    "name:und_x_variant":[
        "Stary Sverzhen\u2019",
        "Stary \u015awier\u017ce\u0144",
        "Staryy Sverzhen\u2019"
    ],
    "wof:name":"Staryy Sverzhen'",
    "wof:placetype":"locality"
},
  "geometry": {"coordinates":[26.6767,53.4586],"type":"Point"}
}