{
  "type": "Feature",
  "properties": {
    "gn:admin1_code":"1.0",
    "gn:asciiname":"Mogylovtse",
    "gn:country_code":"BY",
    "gn:dem":163,
    "gn:feature_class":"P",
    "gn:feature_code":"PPL",
    "gn:name":"Mogylovtse",
    "gn:population":447,
    "gn:timezone":"Europe/Minsk",
    "iso:country":"BY",
    "name:eng_x_preferred":[
        "Mogil\u00ebvtsy"
    ],
    "name:rus_x_preferred":[
        "\u041c\u043e\u0433\u0438\u043b\u0435\u0432\u0446\u044b"
    ],
    "name:rus_x_variant":[
        "Mogil\u00ebvtsy",
        "\u041c\u043e\u0433\u0438\u043b\u0451\u0432\u0446\u044b"
    ],
    "wof:name":"Mogylovtse",
    "wof:placetype":"locality",
    "wof:population":447
},
  "geometry": {"coordinates":[24.6751,52.8732],"type":"Point"}
}