{
  "type": "Feature",
  "properties": {
    "gn:admin1_code":"6.0",
    "gn:asciiname":"Uzdevichi",
    "gn:country_code":"BY",
    "gn:dem":179,
    "gn:feature_class":"P",
    "gn:feature_code":"PPL",
    "gn:name":"Uzdevichi",
    "gn:population":0,
    "gn:timezone":"Europe/Minsk",
    "iso:country":"BY",
    "name:rus_x_preferred":[
        "\u0423\u0437\u0434\u0435\u0432\u0438\u0447\u0438"
    ],
    "wof:name":"Uzdevichi",
    "wof:placetype":"locality"
},
  "geometry": {"coordinates":[32.061,53.5621],"type":"Point"}
}