{
  "type": "Feature",
  "properties": {
    "gn:admin1_code":"6.0",
    "gn:asciiname":"Khodaravichy",
    "gn:country_code":"BY",
    "gn:dem":190,
    "gn:feature_class":"P",
    "gn:feature_code":"PPL",
    "gn:name":"Khodaravichy",
    "gn:population":0,
    "gn:timezone":"Europe/Minsk",
    "iso:country":"BY",
    "name:bel_x_preferred":[
        "\u0425\u043e\u0434\u0430\u0440\u0430\u0432\u0456\u0447\u044b"
    ],
    "name:und_x_variant":[
        "Khodbrovichi",
        "Khodorovichi",
        "Khodaravichy"
    ],
    "wof:name":"Khodaravichy",
    "wof:placetype":"locality"
},
  "geometry": {"coordinates":[31.1631,54.2257],"type":"Point"}
}