{
  "type": "Feature",
  "properties": {
    "gn:admin1_code":"2.0",
    "gn:asciiname":"Uborak",
    "gn:country_code":"BY",
    "gn:dem":132,
    "gn:feature_class":"P",
    "gn:feature_code":"PPL",
    "gn:name":"Uborak",
    "gn:population":0,
    "gn:timezone":"Europe/Minsk",
    "iso:country":"BY",
    "name:bel_x_preferred":[
        "\u0423\u0431\u043e\u0440\u0430\u043a"
    ],
    "name:und_x_variant":[
        "Uborok"
    ],
    "wof:name":"Uborak",
    "wof:placetype":"locality"
},
  "geometry": {"coordinates":[30.4998,52.0542],"type":"Point"}
}