{
  "type": "Feature",
  "properties": {
    "gn:admin1_code":"6.0",
    "gn:asciiname":"Gorbachevka",
    "gn:country_code":"BY",
    "gn:dem":153,
    "gn:feature_class":"P",
    "gn:feature_code":"PPL",
    "gn:name":"Gorbachevka",
    "gn:population":0,
    "gn:timezone":"Europe/Minsk",
    "iso:country":"BY",
    "name:rus_x_preferred":[
        "\u0413\u043e\u0440\u0431\u0430\u0447\u0435\u0432\u043a\u0430"
    ],
    "wof:name":"Gorbachevka",
    "wof:placetype":"locality"
},
  "geometry": {"coordinates":[32.1425,53.2912],"type":"Point"}
}