{
  "type": "Feature",
  "properties": {
    "gn:admin1_code":"7.0",
    "gn:asciiname":"Katuzhino",
    "gn:country_code":"BY",
    "gn:dem":210,
    "gn:feature_class":"P",
    "gn:feature_code":"PPL",
    "gn:name":"Katuzhino",
    "gn:population":0,
    "gn:timezone":"Europe/Minsk",
    "iso:country":"BY",
    "name:rus_x_preferred":[
        "\u041a\u0430\u0442\u0443\u0436\u0438\u043d\u043e"
    ],
    "wof:name":"Katuzhino",
    "wof:placetype":"locality"
},
  "geometry": {"coordinates":[29.691,54.4486],"type":"Point"}
}