{
  "type": "Feature",
  "properties": {
    "gn:admin1_code":"3.0",
    "gn:asciiname":"Minoyty",
    "gn:country_code":"BY",
    "gn:dem":137,
    "gn:feature_class":"P",
    "gn:feature_code":"PPL",
    "gn:name":"Minoyty",
    "gn:population":0,
    "gn:timezone":"Europe/Minsk",
    "iso:country":"BY",
    "name:bel_x_preferred":[
        "\u041c\u0456\u043d\u043e\u0439\u0442\u044b"
    ],
    "name:eng_x_preferred":[
        "Minoyty"
    ],
    "name:rus_x_preferred":[
        "\u041c\u0438\u043d\u043e\u0439\u0442\u044b"
    ],
    "wof:name":"Minoyty",
    "wof:placetype":"locality"
},
  "geometry": {"coordinates":[25.3647,53.7987],"type":"Point"}
}