{
  "type": "Feature",
  "properties": {
    "gn:admin1_code":"5.0",
    "gn:asciiname":"Ruch'e",
    "gn:country_code":"BY",
    "gn:dem":179,
    "gn:feature_class":"P",
    "gn:feature_code":"PPL",
    "gn:name":"Ruch\u2019\u00eb",
    "gn:population":0,
    "gn:timezone":"Europe/Minsk",
    "iso:country":"BY",
    "name:rus_x_preferred":[
        "\u0420\u0443\u0447\u044c\u0451"
    ],
    "name:und_x_variant":[
        "Ruch\u2019\u00eb"
    ],
    "wof:name":"Ruch'e",
    "wof:placetype":"locality"
},
  "geometry": {"coordinates":[27.5902,54.6661],"type":"Point"}
}