{
  "type": "Feature",
  "properties": {
    "gn:admin1_code":"7.0",
    "gn:asciiname":"Zadetuni",
    "gn:country_code":"BY",
    "gn:dem":173,
    "gn:feature_class":"P",
    "gn:feature_code":"PPL",
    "gn:name":"Zadetuni",
    "gn:population":0,
    "gn:timezone":"Europe/Minsk",
    "iso:country":"BY",
    "name:eng_x_preferred":[
        "Zadetuni"
    ],
    "name:rus_x_preferred":[
        "\u0417\u0430\u0434\u0435\u0442\u0443\u043d\u0438"
    ],
    "wof:name":"Zadetuni",
    "wof:placetype":"locality"
},
  "geometry": {"coordinates":[30.7283,55.2414],"type":"Point"}
}