{
  "type": "Feature",
  "properties": {
    "gn:admin1_code":"5.0",
    "gn:asciiname":"Nedreska",
    "gn:country_code":"BY",
    "gn:dem":220,
    "gn:feature_class":"P",
    "gn:feature_code":"PPL",
    "gn:name":"Nedreska",
    "gn:population":0,
    "gn:timezone":"Europe/Minsk",
    "iso:country":"BY",
    "name:rus_x_preferred":[
        "\u041d\u0435\u0434\u0440\u0435\u0441\u043a\u0430"
    ],
    "wof:name":"Nedreska",
    "wof:placetype":"locality"
},
  "geometry": {"coordinates":[27.2756,54.0324],"type":"Point"}
}