{
  "type": "Feature",
  "properties": {
    "gn:admin1_code":"6.0",
    "gn:asciiname":"Asmolovichi",
    "gn:country_code":"BY",
    "gn:dem":207,
    "gn:feature_class":"P",
    "gn:feature_code":"PPL",
    "gn:name":"Asmolovichi",
    "gn:population":0,
    "gn:timezone":"Europe/Minsk",
    "iso:country":"BY",
    "name:rus_x_preferred":[
        "\u0410\u0441\u043c\u043e\u043b\u043e\u0432\u0438\u0447\u0438"
    ],
    "name:und_x_variant":[
        "Osmolovichi",
        "Asmolovichi"
    ],
    "wof:name":"Asmolovichi",
    "wof:placetype":"locality"
},
  "geometry": {"coordinates":[31.4485,54.0372],"type":"Point"}
}