{
  "type": "Feature",
  "properties": {
    "gn:admin1_code":"6.0",
    "gn:asciiname":"Belaya",
    "gn:country_code":"BY",
    "gn:dem":189,
    "gn:feature_class":"P",
    "gn:feature_code":"PPL",
    "gn:name":"Belaya",
    "gn:population":0,
    "gn:timezone":"Europe/Minsk",
    "iso:country":"BY",
    "name:ben_x_preferred":[
        "\u09ac\u09c7\u09b2\u09be\u09df\u09be"
    ],
    "name:heb_x_preferred":[
        "\u05d1\u05dc\u05d0\u05d9\u05d9\u05d4"
    ],
    "name:hin_x_preferred":[
        "\u092c\u0947\u0932\u093e\u092f\u093e"
    ],
    "name:ind_x_preferred":[
        "Belaya"
    ],
    "name:rus_x_preferred":[
        "\u0411\u0435\u043b\u0430\u044f"
    ],
    "wof:name":"Belaya",
    "wof:placetype":"locality"
},
  "geometry": {"coordinates":[30.8266,54.1326],"type":"Point"}
}