{
  "type": "Feature",
  "properties": {
    "gn:admin1_code":"3.0",
    "gn:asciiname":"Zhitomlya",
    "gn:country_code":"BY",
    "gn:dem":126,
    "gn:feature_class":"P",
    "gn:feature_code":"PPL",
    "gn:name":"Zhitomlya",
    "gn:population":0,
    "gn:timezone":"Europe/Minsk",
    "iso:country":"BY",
    "name:bel_x_preferred":[
        "\u0416\u044b\u0442\u043e\u043c\u043b\u044f"
    ],
    "name:eng_x_preferred":[
        "Zhitomlya"
    ],
    "name:rus_x_preferred":[
        "\u0416\u0438\u0442\u043e\u043c\u043b\u044f"
    ],
    "name:und_x_variant":[
        "\u017bydomla",
        "Zhydomlya",
        "Zhidomlya",
        "Zhitomlya",
        "Zhytomlya"
    ],
    "wof:name":"Zhitomlya",
    "wof:placetype":"locality"
},
  "geometry": {"coordinates":[24.1026,53.6328],"type":"Point"}
}