{
  "type": "Feature",
  "properties": {
    "gn:admin1_code":"3.0",
    "gn:asciiname":"Kovarika",
    "gn:country_code":"BY",
    "gn:dem":147,
    "gn:feature_class":"P",
    "gn:feature_code":"PPL",
    "gn:name":"Kovarika",
    "gn:population":0,
    "gn:timezone":"Europe/Minsk",
    "iso:country":"BY",
    "name:rus_x_preferred":[
        "\u041a\u043e\u0432\u0430\u0440\u0438\u043a\u0430"
    ],
    "wof:name":"Kovarika",
    "wof:placetype":"locality"
},
  "geometry": {"coordinates":[25.214,54.0348],"type":"Point"}
}