{
  "type": "Feature",
  "properties": {
    "gn:admin1_code":"2.0",
    "gn:asciiname":"Vydritsa",
    "gn:country_code":"BY",
    "gn:dem":146,
    "gn:feature_class":"P",
    "gn:feature_code":"PPL",
    "gn:name":"Vydritsa",
    "gn:population":0,
    "gn:timezone":"Europe/Minsk",
    "iso:country":"BY",
    "name:rus_x_preferred":[
        "\u0412\u044b\u0434\u0440\u0438\u0446\u0430"
    ],
    "wof:name":"Vydritsa",
    "wof:placetype":"locality"
},
  "geometry": {"coordinates":[30.5349,52.9755],"type":"Point"}
}