{
  "type": "Feature",
  "properties": {
    "gn:admin1_code":"7.0",
    "gn:asciiname":"Kurmalevka",
    "gn:country_code":"BY",
    "gn:dem":154,
    "gn:feature_class":"P",
    "gn:feature_code":"PPL",
    "gn:name":"Kurmal\u00ebvka",
    "gn:population":0,
    "gn:timezone":"Europe/Minsk",
    "iso:country":"BY",
    "name:rus_x_preferred":[
        "\u041a\u0443\u0440\u043c\u0430\u043b\u0451\u0432\u043a\u0430"
    ],
    "name:und_x_variant":[
        "Kurmal\u00ebvka",
        "Kurmel\u00ebvka"
    ],
    "wof:name":"Kurmalevka",
    "wof:placetype":"locality"
},
  "geometry": {"coordinates":[28.8469,55.0339],"type":"Point"}
}