{
  "type": "Feature",
  "properties": {
    "gn:admin1_code":"7.0",
    "gn:asciiname":"Strigi",
    "gn:country_code":"BY",
    "gn:dem":149,
    "gn:feature_class":"P",
    "gn:feature_code":"PPL",
    "gn:name":"Strigi",
    "gn:population":0,
    "gn:timezone":"Europe/Minsk",
    "iso:country":"BY",
    "name:deu_x_preferred":[
        "Strigi"
    ],
    "name:eng_x_preferred":[
        "Strigi"
    ],
    "name:fra_x_preferred":[
        "Strigi"
    ],
    "name:ita_x_preferred":[
        "Strigi"
    ],
    "name:jpn_x_preferred":[
        "Strigi"
    ],
    "name:nld_x_preferred":[
        "Strigi"
    ],
    "name:rus_x_preferred":[
        "\u0421\u0442\u0440\u0438\u0433\u0438"
    ],
    "name:rus_x_variant":[
        "Strigi"
    ],
    "name:spa_x_preferred":[
        "Strigi"
    ],
    "name:zho_x_preferred":[
        "Strigi"
    ],
    "wof:name":"Strigi",
    "wof:placetype":"locality"
},
  "geometry": {"coordinates":[30.0299,54.8855],"type":"Point"}
}