{
  "type": "Feature",
  "properties": {
    "gn:admin1_code":"2.0",
    "gn:asciiname":"Vysokaya Griva",
    "gn:country_code":"BY",
    "gn:dem":140,
    "gn:feature_class":"P",
    "gn:feature_code":"PPL",
    "gn:name":"Vysokaya Griva",
    "gn:population":0,
    "gn:timezone":"Europe/Minsk",
    "iso:country":"BY",
    "name:rus_x_preferred":[
        "\u0412\u044b\u0441\u043e\u043a\u0430\u044f \u0413\u0440\u0438\u0432\u0430"
    ],
    "wof:name":"Vysokaya Griva",
    "wof:placetype":"locality"
},
  "geometry": {"coordinates":[30.5393,52.6835],"type":"Point"}
}