{
  "type": "Feature",
  "properties": {
    "gn:admin1_code":"3.0",
    "gn:asciiname":"Gvozdikyany",
    "gn:country_code":"BY",
    "gn:dem":165,
    "gn:feature_class":"P",
    "gn:feature_code":"PPL",
    "gn:name":"Gvozdikyany",
    "gn:population":0,
    "gn:timezone":"Europe/Minsk",
    "iso:country":"BY",
    "name:rus_x_preferred":[
        "\u0413\u0432\u043e\u0437\u0434\u0438\u043a\u044f\u043d\u044b"
    ],
    "wof:name":"Gvozdikyany",
    "wof:placetype":"locality"
},
  "geometry": {"coordinates":[25.9384,54.8576],"type":"Point"}
}