{
  "type": "Feature",
  "properties": {
    "gn:admin1_code":"6.0",
    "gn:asciiname":"Verbilovo",
    "gn:country_code":"BY",
    "gn:dem":161,
    "gn:feature_class":"P",
    "gn:feature_code":"PPL",
    "gn:name":"Verbilovo",
    "gn:population":0,
    "gn:timezone":"Europe/Minsk",
    "iso:country":"BY",
    "name:rus_x_preferred":[
        "\u0412\u0435\u0440\u0431\u0438\u043b\u043e\u0432\u043e"
    ],
    "wof:name":"Verbilovo",
    "wof:placetype":"locality"
},
  "geometry": {"coordinates":[28.4855,53.43600000000001],"type":"Point"}
}