{
  "type": "Feature",
  "properties": {
    "gn:admin1_code":"1.0",
    "gn:asciiname":"Orkhovo",
    "gn:country_code":"BY",
    "gn:dem":168,
    "gn:feature_class":"P",
    "gn:feature_code":"PPL",
    "gn:name":"Orkhovo",
    "gn:population":0,
    "gn:timezone":"Europe/Minsk",
    "iso:country":"BY",
    "name:rus_x_preferred":[
        "\u041e\u0440\u0445\u043e\u0432\u043e"
    ],
    "name:und_x_variant":[
        "Orkhov"
    ],
    "wof:name":"Orkhovo",
    "wof:placetype":"locality"
},
  "geometry": {"coordinates":[23.6135,51.5404],"type":"Point"}
}