{
  "type": "Feature",
  "properties": {
    "gn:admin1_code":"7.0",
    "gn:asciiname":"Staishche",
    "gn:country_code":"BY",
    "gn:dem":144,
    "gn:feature_class":"P",
    "gn:feature_code":"PPL",
    "gn:name":"Staishche",
    "gn:population":0,
    "gn:timezone":"Europe/Minsk",
    "iso:country":"BY",
    "name:rus_x_preferred":[
        "\u0421\u0442\u0430\u0438\u0449\u0435"
    ],
    "wof:name":"Staishche",
    "wof:placetype":"locality"
},
  "geometry": {"coordinates":[29.1952,54.7869],"type":"Point"}
}