{
  "type": "Feature",
  "properties": {
    "gn:admin1_code":"3.0",
    "gn:asciiname":"Velikoye Selo",
    "gn:country_code":"BY",
    "gn:dem":154,
    "gn:feature_class":"P",
    "gn:feature_code":"PPL",
    "gn:name":"Velikoye Selo",
    "gn:population":0,
    "gn:timezone":"Europe/Minsk",
    "iso:country":"BY",
    "name:rus_x_preferred":[
        "\u0412\u0435\u043b\u0438\u043a\u043e\u0435 \u0421\u0435\u043b\u043e"
    ],
    "wof:name":"Velikoye Selo",
    "wof:placetype":"locality"
},
  "geometry": {"coordinates":[25.21457,53.99622],"type":"Point"}
}