{
  "type": "Feature",
  "properties": {
    "gn:admin1_code":"5.0",
    "gn:asciiname":"Virkovo",
    "gn:country_code":"BY",
    "gn:dem":168,
    "gn:feature_class":"P",
    "gn:feature_code":"PPL",
    "gn:name":"Virkovo",
    "gn:population":0,
    "gn:timezone":"Europe/Minsk",
    "iso:country":"BY",
    "name:rus_x_preferred":[
        "\u0412\u0438\u0440\u043a\u043e\u0432\u043e"
    ],
    "wof:name":"Virkovo",
    "wof:placetype":"locality"
},
  "geometry": {"coordinates":[27.1778,53.3291],"type":"Point"}
}