{
  "type": "Feature",
  "properties": {
    "gn:admin1_code":"7.0",
    "gn:asciiname":"Savchenki",
    "gn:country_code":"BY",
    "gn:dem":160,
    "gn:feature_class":"P",
    "gn:feature_code":"PPL",
    "gn:name":"Savchenki",
    "gn:population":0,
    "gn:timezone":"Europe/Minsk",
    "iso:country":"BY",
    "name:rus_x_preferred":[
        "\u0421\u0430\u0432\u0447\u0435\u043d\u043a\u0438"
    ],
    "wof:name":"Savchenki",
    "wof:placetype":"locality"
},
  "geometry": {"coordinates":[28.448,55.2536],"type":"Point"}
}