{
  "type": "Feature",
  "properties": {
    "gn:admin1_code":"5.0",
    "gn:asciiname":"Volchki",
    "gn:country_code":"BY",
    "gn:dem":218,
    "gn:feature_class":"P",
    "gn:feature_code":"PPL",
    "gn:name":"Volchki",
    "gn:population":0,
    "gn:timezone":"Europe/Minsk",
    "iso:country":"BY",
    "name:rus_x_preferred":[
        "\u0412\u043e\u043b\u0447\u043a\u0438"
    ],
    "wof:name":"Volchki",
    "wof:placetype":"locality"
},
  "geometry": {"coordinates":[26.8453,54.0944],"type":"Point"}
}