{
  "type": "Feature",
  "properties": {
    "gn:admin1_code":"3.0",
    "gn:asciiname":"Khvedevichi",
    "gn:country_code":"BY",
    "gn:dem":153,
    "gn:feature_class":"P",
    "gn:feature_code":"PPL",
    "gn:name":"Khvedevichi",
    "gn:population":0,
    "gn:timezone":"Europe/Minsk",
    "iso:country":"BY",
    "name:rus_x_preferred":[
        "\u0425\u0432\u0434\u0435\u0432\u0438\u0447\u0438"
    ],
    "name:und_x_variant":[
        "Chwiedziewicze",
        "Khvedbevichi",
        "Khvedzeviche",
        "Khvedzevichi",
        "Khvedevichi"
    ],
    "wof:name":"Khvedevichi",
    "wof:placetype":"locality"
},
  "geometry": {"coordinates":[26.4528,54.7916],"type":"Point"}
}