{
  "type": "Feature",
  "properties": {
    "gn:admin1_code":"3.0",
    "gn:asciiname":"Filevichi",
    "gn:country_code":"BY",
    "gn:dem":129,
    "gn:feature_class":"P",
    "gn:feature_code":"PPL",
    "gn:name":"Filevichi",
    "gn:population":0,
    "gn:timezone":"Europe/Minsk",
    "iso:country":"BY",
    "name:rus_x_preferred":[
        "\u0424\u0438\u043b\u0435\u0432\u0438\u0447\u0438"
    ],
    "name:und_x_variant":[
        "Fileviche",
        "Filevichi"
    ],
    "wof:name":"Filevichi",
    "wof:placetype":"locality"
},
  "geometry": {"coordinates":[24.4582,53.7873],"type":"Point"}
}