{
  "type": "Feature",
  "properties": {
    "gn:admin1_code":"7.0",
    "gn:asciiname":"Veretei",
    "gn:country_code":"BY",
    "gn:dem":189,
    "gn:feature_class":"P",
    "gn:feature_code":"PPL",
    "gn:name":"Veretei",
    "gn:population":0,
    "gn:timezone":"Europe/Minsk",
    "iso:country":"BY",
    "name:rus_x_preferred":[
        "\u0412\u0435\u0440\u0435\u0442\u0435\u0438"
    ],
    "name:und_x_variant":[
        "Wierecieje",
        "Veretseye",
        "Veretei"
    ],
    "wof:name":"Veretei",
    "wof:placetype":"locality"
},
  "geometry": {"coordinates":[27.7364,55.0318],"type":"Point"}
}