{
  "type": "Feature",
  "properties": {
    "gn:admin1_code":"5.0",
    "gn:asciiname":"Novyy Gutkov",
    "gn:country_code":"BY",
    "gn:dem":165,
    "gn:feature_class":"P",
    "gn:feature_code":"PPL",
    "gn:name":"Novyy Gutkov",
    "gn:population":0,
    "gn:timezone":"Europe/Minsk",
    "iso:country":"BY",
    "name:rus_x_preferred":[
        "\u041d\u043e\u0432\u044b\u0439 \u0413\u0443\u0442\u043a\u043e\u0432"
    ],
    "name:und_x_variant":[
        "Neu-Gudkovo",
        "Novoye Gudkovo",
        "Novyy Gutkov",
        "Novoye Gutkovo"
    ],
    "wof:name":"Novyy Gutkov",
    "wof:placetype":"locality"
},
  "geometry": {"coordinates":[27.9005,53.0698],"type":"Point"}
}