{
  "type": "Feature",
  "properties": {
    "gn:admin1_code":"6.0",
    "gn:asciiname":"Sirotino",
    "gn:country_code":"BY",
    "gn:dem":178,
    "gn:feature_class":"P",
    "gn:feature_code":"PPL",
    "gn:name":"Sirotino",
    "gn:population":0,
    "gn:timezone":"Europe/Minsk",
    "iso:country":"BY",
    "name:rus_x_preferred":[
        "\u0421\u0438\u0440\u043e\u0442\u0438\u043d\u043e"
    ],
    "wof:name":"Sirotino",
    "wof:placetype":"locality"
},
  "geometry": {"coordinates":[30.0993,53.9984],"type":"Point"}
}