{
  "type": "Feature",
  "properties": {
    "gn:admin1_code":"3.0",
    "gn:asciiname":"Zagrit'kovo",
    "gn:country_code":"BY",
    "gn:dem":161,
    "gn:feature_class":"P",
    "gn:feature_code":"PPL",
    "gn:name":"Zagrit\u2019kovo",
    "gn:population":0,
    "gn:timezone":"Europe/Minsk",
    "iso:country":"BY",
    "name:bel_x_preferred":[
        "Zahryts\u2019kava"
    ],
    "name:bel_x_variant":[
        "\u0417\u0430\u0433\u0440\u044b\u0446\u044c\u043a\u0430\u0432\u0430"
    ],
    "name:rus_x_preferred":[
        "\u0417\u0430\u0433\u0440\u0438\u0442\u044c\u043a\u043e\u0432\u043e"
    ],
    "name:und_x_variant":[
        "Zagrit\u2019kovo",
        "Zagritskovo"
    ],
    "wof:name":"Zagrit'kovo",
    "wof:placetype":"locality"
},
  "geometry": {"coordinates":[25.4413,53.1551],"type":"Point"}
}