{
  "type": "Feature",
  "properties": {
    "gn:admin1_code":"7.0",
    "gn:asciiname":"Podymkhi",
    "gn:country_code":"BY",
    "gn:dem":154,
    "gn:feature_class":"P",
    "gn:feature_code":"PPL",
    "gn:name":"Podymkhi",
    "gn:population":0,
    "gn:timezone":"Europe/Minsk",
    "iso:country":"BY",
    "name:rus_x_preferred":[
        "\u041f\u043e\u0434\u044b\u043c\u0445\u0438"
    ],
    "wof:name":"Podymkhi",
    "wof:placetype":"locality"
},
  "geometry": {"coordinates":[28.7482,54.8232],"type":"Point"}
}