{
  "type": "Feature",
  "properties": {
    "gn:admin1_code":"3.0",
    "gn:asciiname":"Ioni",
    "gn:country_code":"BY",
    "gn:dem":174,
    "gn:feature_class":"P",
    "gn:feature_code":"PPL",
    "gn:name":"Ioni",
    "gn:population":0,
    "gn:timezone":"Europe/Minsk",
    "iso:country":"BY",
    "name:rus_x_preferred":[
        "\u0418\u043e\u043d\u0438"
    ],
    "wof:name":"Ioni",
    "wof:placetype":"locality"
},
  "geometry": {"coordinates":[25.1453,54.1341],"type":"Point"}
}