{
  "type": "Feature",
  "properties": {
    "gn:admin1_code":"6.0",
    "gn:asciiname":"Yaseny",
    "gn:country_code":"BY",
    "gn:dem":172,
    "gn:feature_class":"P",
    "gn:feature_code":"PPL",
    "gn:name":"Yaseny",
    "gn:population":0,
    "gn:timezone":"Europe/Minsk",
    "iso:country":"BY",
    "name:rus_x_preferred":[
        "\u042f\u0441\u0435\u043d\u044b"
    ],
    "wof:name":"Yaseny",
    "wof:placetype":"locality"
},
  "geometry": {"coordinates":[28.9323,53.0513],"type":"Point"}
}