{
  "type": "Feature",
  "properties": {
    "gn:admin1_code":"3.0",
    "gn:asciiname":"Burtishki",
    "gn:country_code":"BY",
    "gn:dem":196,
    "gn:feature_class":"P",
    "gn:feature_code":"PPL",
    "gn:name":"Burtishki",
    "gn:population":0,
    "gn:timezone":"Europe/Minsk",
    "iso:country":"BY",
    "name:rus_x_preferred":[
        "\u0411\u0443\u0440\u0442\u0438\u0448\u043a\u0438"
    ],
    "wof:name":"Burtishki",
    "wof:placetype":"locality"
},
  "geometry": {"coordinates":[25.7461,54.4032],"type":"Point"}
}