{
  "type": "Feature",
  "properties": {
    "gn:admin1_code":"2.0",
    "gn:asciiname":"Sverzhen'",
    "gn:country_code":"BY",
    "gn:dem":144,
    "gn:feature_class":"P",
    "gn:feature_code":"PPL",
    "gn:name":"Sverzhen\u2019",
    "gn:population":0,
    "gn:timezone":"Europe/Minsk",
    "iso:country":"BY",
    "name:rus_x_preferred":[
        "\u0421\u0432\u0435\u0440\u0436\u0435\u043d\u044c"
    ],
    "name:und_x_variant":[
        "Sverzhen\u2019"
    ],
    "wof:name":"Sverzhen'",
    "wof:placetype":"locality"
},
  "geometry": {"coordinates":[30.3222,53.1331],"type":"Point"}
}