{
  "type": "Feature",
  "properties": {
    "gn:admin1_code":"5.0",
    "gn:asciiname":"Trubichino",
    "gn:country_code":"BY",
    "gn:dem":174,
    "gn:feature_class":"P",
    "gn:feature_code":"PPL",
    "gn:name":"Trubichino",
    "gn:population":0,
    "gn:timezone":"Europe/Minsk",
    "iso:country":"BY",
    "name:rus_x_preferred":[
        "\u0422\u0440\u0443\u0431\u0438\u0447\u0438\u043d\u043e"
    ],
    "wof:name":"Trubichino",
    "wof:placetype":"locality"
},
  "geometry": {"coordinates":[27.9857,54.0827],"type":"Point"}
}