{
  "type": "Feature",
  "properties": {
    "gn:admin1_code":"6.0",
    "gn:asciiname":"Zavodskaya Slabada",
    "gn:country_code":"BY",
    "gn:dem":177,
    "gn:feature_class":"P",
    "gn:feature_code":"PPL",
    "gn:name":"Zavodskaya Slabada",
    "gn:population":0,
    "gn:timezone":"Europe/Minsk",
    "iso:country":"BY",
    "name:bel_x_preferred":[
        "\u0417\u0430\u0432\u043e\u0434\u0441\u043a\u0430\u044f \u0421\u043b\u0430\u0431\u0430\u0434\u0430"
    ],
    "name:und_x_variant":[
        "Zavodskaya Sloboda"
    ],
    "wof:name":"Zavodskaya Slabada",
    "wof:placetype":"locality"
},
  "geometry": {"coordinates":[30.015,53.7838],"type":"Point"}
}