{
  "type": "Feature",
  "properties": {
    "gn:admin1_code":"3.0",
    "gn:asciiname":"Yezhevtsy",
    "gn:country_code":"BY",
    "gn:dem":142,
    "gn:feature_class":"P",
    "gn:feature_code":"PPL",
    "gn:name":"Yezhevtsy",
    "gn:population":0,
    "gn:timezone":"Europe/Minsk",
    "iso:country":"BY",
    "name:rus_x_preferred":[
        "\u0415\u0436\u0435\u0432\u0446\u044b"
    ],
    "wof:name":"Yezhevtsy",
    "wof:placetype":"locality"
},
  "geometry": {"coordinates":[24.1728,53.2831],"type":"Point"}
}