{
  "type": "Feature",
  "properties": {
    "gn:admin1_code":"7.0",
    "gn:asciiname":"Poluch'ye",
    "gn:country_code":"BY",
    "gn:dem":149,
    "gn:feature_class":"P",
    "gn:feature_code":"PPL",
    "gn:name":"Poluch\u2019ye",
    "gn:population":0,
    "gn:timezone":"Europe/Minsk",
    "iso:country":"BY",
    "name:rus_x_preferred":[
        "\u041f\u043e\u043b\u0443\u0447\u044c\u0435"
    ],
    "name:und_x_variant":[
        "Poluch\u2019ye"
    ],
    "wof:name":"Poluch'ye",
    "wof:placetype":"locality"
},
  "geometry": {"coordinates":[29.3692,55.6718],"type":"Point"}
}