{
  "type": "Feature",
  "properties": {
    "gn:admin1_code":"5.0",
    "gn:asciiname":"Tseperka",
    "gn:country_code":"BY",
    "gn:dem":175,
    "gn:feature_class":"P",
    "gn:feature_code":"PPL",
    "gn:name":"Tseperka",
    "gn:population":0,
    "gn:timezone":"Europe/Minsk",
    "iso:country":"BY",
    "name:rus_x_preferred":[
        "\u0426\u0435\u043f\u0435\u0440\u043a\u0430"
    ],
    "wof:name":"Tseperka",
    "wof:placetype":"locality"
},
  "geometry": {"coordinates":[26.7213,53.049],"type":"Point"}
}