{
  "type": "Feature",
  "properties": {
    "gn:admin1_code":"5.0",
    "gn:asciiname":"Bielewo",
    "gn:country_code":"BY",
    "gn:dem":207,
    "gn:feature_class":"P",
    "gn:feature_code":"PPL",
    "gn:name":"Bielewo",
    "gn:population":0,
    "gn:timezone":"Europe/Minsk",
    "iso:country":"BY",
    "name:fra_x_preferred":[
        "Bielewo"
    ],
    "name:pol_x_preferred":[
        "Bielewo"
    ],
    "name:rus_x_preferred":[
        "\u0411\u0435\u043b\u0451\u0432\u043e"
    ],
    "name:ukr_x_preferred":[
        "\u0411\u0435\u043b\u0435\u0432\u043e"
    ],
    "name:und_x_variant":[
        "Bel\u00ebvo"
    ],
    "wof:name":"Bielewo",
    "wof:placetype":"locality"
},
  "geometry": {"coordinates":[26.9308,54.1843],"type":"Point"}
}