{
  "type": "Feature",
  "properties": {
    "gn:admin1_code":"7.0",
    "gn:asciiname":"Salanik",
    "gn:country_code":"BY",
    "gn:dem":127,
    "gn:feature_class":"P",
    "gn:feature_code":"PPL",
    "gn:name":"Salanik",
    "gn:population":0,
    "gn:timezone":"Europe/Minsk",
    "iso:country":"BY",
    "name:bel_x_preferred":[
        "\u0421\u0430\u043b\u0430\u043d\u0456\u043a"
    ],
    "name:und_x_variant":[
        "Solonik",
        "Soloniki",
        "Salanik"
    ],
    "wof:name":"Salanik",
    "wof:placetype":"locality"
},
  "geometry": {"coordinates":[28.8561,55.4854],"type":"Point"}
}