{
  "type": "Feature",
  "properties": {
    "gn:admin1_code":"6.0",
    "gn:asciiname":"Suyanets",
    "gn:country_code":"BY",
    "gn:dem":159,
    "gn:feature_class":"P",
    "gn:feature_code":"PPL",
    "gn:name":"Suyanets",
    "gn:population":0,
    "gn:timezone":"Europe/Minsk",
    "iso:country":"BY",
    "name:rus_x_preferred":[
        "\u0421\u0443\u044f\u043d\u0435\u0446"
    ],
    "wof:name":"Suyanets",
    "wof:placetype":"locality"
},
  "geometry": {"coordinates":[29.4232,53.2034],"type":"Point"}
}