{
  "type": "Feature",
  "properties": {
    "gn:admin1_code":"1.0",
    "gn:asciiname":"Mefedovichi",
    "gn:country_code":"BY",
    "gn:dem":146,
    "gn:feature_class":"P",
    "gn:feature_code":"PPL",
    "gn:name":"Mefedovichi",
    "gn:population":0,
    "gn:timezone":"Europe/Minsk",
    "iso:country":"BY",
    "name:rus_x_preferred":[
        "\u041c\u0435\u0444\u0435\u0434\u043e\u0432\u0438\u0447\u0438"
    ],
    "name:und_x_variant":[
        "Mekhvedoviche",
        "Mefedovichi",
        "Mekhvedovichi"
    ],
    "wof:name":"Mefedovichi",
    "wof:placetype":"locality"
},
  "geometry": {"coordinates":[24.6805,52.1746],"type":"Point"}
}