{
  "type": "Feature",
  "properties": {
    "gn:admin1_code":"3.0",
    "gn:asciiname":"Osinovka",
    "gn:country_code":"BY",
    "gn:dem":263,
    "gn:feature_class":"P",
    "gn:feature_code":"PPL",
    "gn:name":"Osinovka",
    "gn:population":0,
    "gn:timezone":"Europe/Minsk",
    "iso:country":"BY",
    "name:rus_x_preferred":[
        "\u041e\u0441\u0438\u043d\u043e\u0432\u043a\u0430"
    ],
    "wof:name":"Osinovka",
    "wof:placetype":"locality"
},
  "geometry": {"coordinates":[25.7834,54.723],"type":"Point"}
}