{
  "type": "Feature",
  "properties": {
    "gn:admin1_code":"7.0",
    "gn:asciiname":"Milashovo",
    "gn:country_code":"BY",
    "gn:dem":142,
    "gn:feature_class":"P",
    "gn:feature_code":"PPL",
    "gn:name":"Milashovo",
    "gn:population":0,
    "gn:timezone":"Europe/Minsk",
    "iso:country":"BY",
    "name:rus_x_preferred":[
        "\u041c\u0438\u043b\u0430\u0448\u0451\u0432\u043e"
    ],
    "name:und_x_variant":[
        "Mi\u0142aszowo",
        "Milashovo",
        "Milash\u00ebvo",
        "Miloshovo"
    ],
    "wof:name":"Milashovo",
    "wof:placetype":"locality"
},
  "geometry": {"coordinates":[27.5783,55.7165],"type":"Point"}
}