{
  "type": "Feature",
  "properties": {
    "gn:admin1_code":"7.0",
    "gn:asciiname":"Marchanki",
    "gn:country_code":"BY",
    "gn:dem":176,
    "gn:feature_class":"P",
    "gn:feature_code":"PPL",
    "gn:name":"Marchanki",
    "gn:population":0,
    "gn:timezone":"Europe/Minsk",
    "iso:country":"BY",
    "name:bel_x_preferred":[
        "\u041c\u0430\u0440\u0447\u0430\u043d\u043a\u0456"
    ],
    "name:eng_x_preferred":[
        "Marchenki"
    ],
    "name:rus_x_preferred":[
        "\u041c\u0430\u0440\u0447\u0435\u043d\u043a\u0438"
    ],
    "name:und_x_variant":[
        "Marchanki"
    ],
    "wof:name":"Marchanki",
    "wof:placetype":"locality"
},
  "geometry": {"coordinates":[30.1857,55.8343],"type":"Point"}
}