{
  "type": "Feature",
  "properties": {
    "gn:admin1_code":"6.0",
    "gn:asciiname":"Rynkovka",
    "gn:country_code":"BY",
    "gn:dem":167,
    "gn:feature_class":"P",
    "gn:feature_code":"PPL",
    "gn:name":"Rynkovka",
    "gn:population":0,
    "gn:timezone":"Europe/Minsk",
    "iso:country":"BY",
    "name:rus_x_preferred":[
        "\u0420\u044b\u043d\u043a\u043e\u0432\u043a\u0430"
    ],
    "wof:name":"Rynkovka",
    "wof:placetype":"locality"
},
  "geometry": {"coordinates":[31.1707,53.6364],"type":"Point"}
}