{
  "type": "Feature",
  "properties": {
    "gn:admin1_code":"7.0",
    "gn:asciiname":"Boriskovichi",
    "gn:country_code":"BY",
    "gn:dem":187,
    "gn:feature_class":"P",
    "gn:feature_code":"PPL",
    "gn:name":"Boriskovichi",
    "gn:population":0,
    "gn:timezone":"Europe/Minsk",
    "iso:country":"BY",
    "name:rus_x_preferred":[
        "\u0411\u043e\u0440\u0438\u0441\u043a\u043e\u0432\u0438\u0447\u0438"
    ],
    "wof:name":"Boriskovichi",
    "wof:placetype":"locality"
},
  "geometry": {"coordinates":[28.0656,55.2262],"type":"Point"}
}