{
  "type": "Feature",
  "properties": {
    "gn:admin1_code":"7.0",
    "gn:asciiname":"Idolta",
    "gn:country_code":"BY",
    "gn:dem":140,
    "gn:feature_class":"P",
    "gn:feature_code":"PPL",
    "gn:name":"Idolta",
    "gn:population":0,
    "gn:timezone":"Europe/Minsk",
    "iso:country":"BY",
    "name:bel_x_preferred":[
        "\u0406\u0434\u043e\u043b\u0442\u0430"
    ],
    "wof:name":"Idolta",
    "wof:placetype":"locality"
},
  "geometry": {"coordinates":[27.5654,55.7192],"type":"Point"}
}