{
  "type": "Feature",
  "properties": {
    "gn:admin1_code":"6.0",
    "gn:asciiname":"Malyy Krushnikovskiy",
    "gn:country_code":"BY",
    "gn:dem":162,
    "gn:feature_class":"P",
    "gn:feature_code":"PPL",
    "gn:name":"Malyy Krushnikovskiy",
    "gn:population":0,
    "gn:timezone":"Europe/Minsk",
    "iso:country":"BY",
    "name:rus_x_preferred":[
        "\u041c\u0430\u043b\u044b\u0439 \u041a\u0440\u0443\u0448\u043d\u0438\u043a\u043e\u0432\u0441\u043a\u0438\u0439"
    ],
    "wof:name":"Malyy Krushnikovskiy",
    "wof:placetype":"locality"
},
  "geometry": {"coordinates":[29.8878,53.6398],"type":"Point"}
}