{
  "type": "Feature",
  "properties": {
    "gn:admin1_code":"5.0",
    "gn:asciiname":"Lyakhovo",
    "gn:country_code":"BY",
    "gn:dem":160,
    "gn:feature_class":"P",
    "gn:feature_code":"PPL",
    "gn:name":"Lyakhovo",
    "gn:population":0,
    "gn:timezone":"Europe/Minsk",
    "iso:country":"BY",
    "name:rus_x_preferred":[
        "\u041b\u044f\u0445\u043e\u0432\u043e"
    ],
    "wof:name":"Lyakhovo",
    "wof:placetype":"locality"
},
  "geometry": {"coordinates":[27.7796,53.1163],"type":"Point"}
}