{
  "type": "Feature",
  "properties": {
    "gn:admin1_code":"7.0",
    "gn:asciiname":"Patsen'ki",
    "gn:country_code":"BY",
    "gn:dem":187,
    "gn:feature_class":"P",
    "gn:feature_code":"PPL",
    "gn:name":"Patsen\u2019ki",
    "gn:population":0,
    "gn:timezone":"Europe/Minsk",
    "iso:country":"BY",
    "name:rus_x_preferred":[
        "\u041f\u0430\u0446\u0435\u043d\u044c\u043a\u0438"
    ],
    "name:und_x_variant":[
        "Patsen\u2019ki",
        "Paten\u2019ki"
    ],
    "wof:name":"Patsen'ki",
    "wof:placetype":"locality"
},
  "geometry": {"coordinates":[31.1267,54.6351],"type":"Point"}
}