{
  "type": "Feature",
  "properties": {
    "gn:admin1_code":"3.0",
    "gn:asciiname":"Begeni",
    "gn:country_code":"BY",
    "gn:dem":173,
    "gn:feature_class":"P",
    "gn:feature_code":"PPL",
    "gn:name":"Begeni",
    "gn:population":0,
    "gn:timezone":"Europe/Minsk",
    "iso:country":"BY",
    "name:rus_x_preferred":[
        "\u0411\u0435\u0433\u0435\u043d\u0438"
    ],
    "name:und_x_variant":[
        "Begene",
        "Begene Vel\u2019ke",
        "Begeni"
    ],
    "wof:name":"Begeni",
    "wof:placetype":"locality"
},
  "geometry": {"coordinates":[24.2036,53.181],"type":"Point"}
}