{
  "type": "Feature",
  "properties": {
    "gn:admin1_code":"5.0",
    "gn:asciiname":"Sinyahova",
    "gn:country_code":"BY",
    "gn:dem":153,
    "gn:feature_class":"P",
    "gn:feature_code":"PPL",
    "gn:name":"Sinyahova",
    "gn:population":0,
    "gn:timezone":"Europe/Minsk",
    "iso:country":"BY",
    "name:bel_x_preferred":[
        "\u0421\u0456\u043d\u044f\u0433\u043e\u0432\u0430"
    ],
    "name:und_x_variant":[
        "Sinyagovo",
        "Sinegovo"
    ],
    "wof:name":"Sinyahova",
    "wof:placetype":"locality"
},
  "geometry": {"coordinates":[28.1526,52.9075],"type":"Point"}
}