{
  "type": "Feature",
  "properties": {
    "gn:admin1_code":"3.0",
    "gn:asciiname":"Klochki",
    "gn:country_code":"BY",
    "gn:dem":139,
    "gn:feature_class":"P",
    "gn:feature_code":"PPL",
    "gn:name":"Klochki",
    "gn:population":0,
    "gn:timezone":"Europe/Minsk",
    "iso:country":"BY",
    "name:rus_x_preferred":[
        "\u041a\u043b\u043e\u0447\u043a\u0438"
    ],
    "wof:name":"Klochki",
    "wof:placetype":"locality"
},
  "geometry": {"coordinates":[23.6994,53.5552],"type":"Point"}
}