{
  "type": "Feature",
  "properties": {
    "gn:admin1_code":"0.0",
    "gn:asciiname":"Zadvor'ye",
    "gn:country_code":"BY",
    "gn:dem":163,
    "gn:feature_class":"P",
    "gn:feature_code":"PPL",
    "gn:name":"Zadvor\u2019ye",
    "gn:population":0,
    "gn:timezone":"Europe/Minsk",
    "iso:country":"BY",
    "name:und_x_variant":[
        "Zadworje",
        "Zadvor\u2019ye"
    ],
    "wof:name":"Zadvor'ye",
    "wof:placetype":"locality"
},
  "geometry": {"coordinates":[26.91667,52.93333000000001],"type":"Point"}
}