{
  "type": "Feature",
  "properties": {
    "gn:admin1_code":"0.0",
    "gn:asciiname":"Denisovka",
    "gn:country_code":"BY",
    "gn:dem":171,
    "gn:feature_class":"P",
    "gn:feature_code":"PPL",
    "gn:name":"Denisovka",
    "gn:population":0,
    "gn:timezone":"Europe/Minsk",
    "iso:country":"BY",
    "name:ceb_x_preferred":[
        "Denisovka"
    ],
    "name:swe_x_preferred":[
        "Denisovka"
    ],
    "wof:name":"Denisovka",
    "wof:placetype":"locality"
},
  "geometry": {"coordinates":[30.23333,55.45],"type":"Point"}
}