{
  "type": "Feature",
  "properties": {
    "gn:admin1_code":"3.0",
    "gn:asciiname":"Meshtuny",
    "gn:country_code":"BY",
    "gn:dem":145,
    "gn:feature_class":"P",
    "gn:feature_code":"PPL",
    "gn:name":"Meshtuny",
    "gn:population":0,
    "gn:timezone":"Europe/Minsk",
    "iso:country":"BY",
    "name:rus_x_preferred":[
        "\u041c\u0435\u0448\u0442\u0443\u043d\u044b"
    ],
    "wof:name":"Meshtuny",
    "wof:placetype":"locality"
},
  "geometry": {"coordinates":[24.1313,53.3091],"type":"Point"}
}