{
  "type": "Feature",
  "properties": {
    "gn:admin1_code":"3.0",
    "gn:asciiname":"Yushkovichi",
    "gn:country_code":"BY",
    "gn:dem":172,
    "gn:feature_class":"P",
    "gn:feature_code":"PPL",
    "gn:name":"Yushkovichi",
    "gn:population":0,
    "gn:timezone":"Europe/Minsk",
    "iso:country":"BY",
    "name:rus_x_preferred":[
        "\u042e\u0448\u043a\u043e\u0432\u0438\u0447\u0438"
    ],
    "wof:name":"Yushkovichi",
    "wof:placetype":"locality"
},
  "geometry": {"coordinates":[24.1711,52.9725],"type":"Point"}
}