{
  "type": "Feature",
  "properties": {
    "gn:admin1_code":"6.0",
    "gn:asciiname":"Kozel'skaya Buda",
    "gn:country_code":"BY",
    "gn:dem":166,
    "gn:feature_class":"P",
    "gn:feature_code":"PPL",
    "gn:name":"Kozel\u2019skaya Buda",
    "gn:population":0,
    "gn:timezone":"Europe/Minsk",
    "iso:country":"BY",
    "wof:name":"Kozel'skaya Buda",
    "wof:placetype":"locality"
},
  "geometry": {"coordinates":[31.6975,53.29083000000001],"type":"Point"}
}