{
  "type": "Feature",
  "properties": {
    "gn:admin1_code":"6.0",
    "gn:asciiname":"Rakshyna",
    "gn:country_code":"BY",
    "gn:dem":215,
    "gn:feature_class":"P",
    "gn:feature_code":"PPL",
    "gn:name":"Rakshyna",
    "gn:population":0,
    "gn:timezone":"Europe/Minsk",
    "iso:country":"BY",
    "name:bel_x_preferred":[
        "\u0420\u0430\u043a\u0448\u044b\u043d\u0430"
    ],
    "name:und_x_variant":[
        "Rakshino",
        "Rakoyeshchina",
        "Rakovshchina",
        "Rakshyna"
    ],
    "wof:name":"Rakshyna",
    "wof:placetype":"locality"
},
  "geometry": {"coordinates":[31.2796,54.0395],"type":"Point"}
}