{
  "type": "Feature",
  "properties": {
    "gn:admin1_code":"5.0",
    "gn:asciiname":"Tristenets",
    "gn:country_code":"BY",
    "gn:dem":179,
    "gn:feature_class":"P",
    "gn:feature_code":"PPL",
    "gn:name":"Tristenets",
    "gn:population":0,
    "gn:timezone":"Europe/Minsk",
    "iso:country":"BY",
    "name:rus_x_preferred":[
        "\u0422\u0440\u0438\u0441\u0442\u0435\u043d\u0435\u0446"
    ],
    "name:und_x_variant":[
        "Trostenets"
    ],
    "wof:name":"Tristenets",
    "wof:placetype":"locality"
},
  "geometry": {"coordinates":[27.5218,53.5241],"type":"Point"}
}