{
  "type": "Feature",
  "properties": {
    "gn:admin1_code":"5.0",
    "gn:asciiname":"Sosnovoye Boloto",
    "gn:country_code":"BY",
    "gn:dem":186,
    "gn:feature_class":"P",
    "gn:feature_code":"PPL",
    "gn:name":"Sosnovoye Boloto",
    "gn:population":0,
    "gn:timezone":"Europe/Minsk",
    "iso:country":"BY",
    "name:rus_x_preferred":[
        "\u0421\u043e\u0441\u043d\u043e\u0432\u043e\u0435 \u0411\u043e\u043b\u043e\u0442\u043e"
    ],
    "wof:name":"Sosnovoye Boloto",
    "wof:placetype":"locality"
},
  "geometry": {"coordinates":[28.7612,53.7961],"type":"Point"}
}