{
  "type": "Feature",
  "properties": {
    "gn:admin1_code":"5.0",
    "gn:asciiname":"Stanovishche",
    "gn:country_code":"BY",
    "gn:dem":235,
    "gn:feature_class":"P",
    "gn:feature_code":"PPL",
    "gn:name":"Stanovishche",
    "gn:population":0,
    "gn:timezone":"Europe/Minsk",
    "iso:country":"BY",
    "name:rus_x_preferred":[
        "\u0421\u0442\u0430\u043d\u043e\u0432\u0438\u0449\u0435"
    ],
    "wof:name":"Stanovishche",
    "wof:placetype":"locality"
},
  "geometry": {"coordinates":[27.9424,54.5011],"type":"Point"}
}