{
  "type": "Feature",
  "properties": {
    "gn:admin1_code":"7.0",
    "gn:asciiname":"Pashino",
    "gn:country_code":"BY",
    "gn:dem":165,
    "gn:feature_class":"P",
    "gn:feature_code":"PPL",
    "gn:name":"Pashino",
    "gn:population":0,
    "gn:timezone":"Europe/Minsk",
    "iso:country":"BY",
    "name:rus_x_preferred":[
        "\u041f\u0430\u0448\u0438\u043d\u043e"
    ],
    "wof:name":"Pashino",
    "wof:placetype":"locality"
},
  "geometry": {"coordinates":[30.49,54.5507],"type":"Point"}
}