{
  "type": "Feature",
  "properties": {
    "gn:admin1_code":"5.0",
    "gn:asciiname":"Byerazinskaye",
    "gn:country_code":"BY",
    "gn:dem":179,
    "gn:feature_class":"P",
    "gn:feature_code":"PPL",
    "gn:name":"Byerazinskaye",
    "gn:population":0,
    "gn:timezone":"Europe/Minsk",
    "iso:country":"BY",
    "name:bel_x_preferred":[
        "\u0411\u0435\u0440\u0430\u0437\u0456\u043d\u0441\u043a\u0430\u0435"
    ],
    "name:und_x_variant":[
        "Berezinskoye"
    ],
    "wof:name":"Byerazinskaye",
    "wof:placetype":"locality"
},
  "geometry": {"coordinates":[26.6079,54.2168],"type":"Point"}
}