{
  "type": "Feature",
  "properties": {
    "gn:admin1_code":"1.0",
    "gn:asciiname":"Khotyazh",
    "gn:country_code":"BY",
    "gn:dem":156,
    "gn:feature_class":"P",
    "gn:feature_code":"PPL",
    "gn:name":"Khotyazh",
    "gn:population":0,
    "gn:timezone":"Europe/Minsk",
    "iso:country":"BY",
    "name:rus_x_preferred":[
        "\u0425\u043e\u0442\u044f\u0436"
    ],
    "wof:name":"Khotyazh",
    "wof:placetype":"locality"
},
  "geometry": {"coordinates":[26.217,52.8561],"type":"Point"}
}