{
  "type": "Feature",
  "properties": {
    "gn:admin1_code":"3.0",
    "gn:asciiname":"Dyakovtsy",
    "gn:country_code":"BY",
    "gn:dem":123,
    "gn:feature_class":"P",
    "gn:feature_code":"PPL",
    "gn:name":"Dyakovtsy",
    "gn:population":0,
    "gn:timezone":"Europe/Minsk",
    "iso:country":"BY",
    "name:rus_x_preferred":[
        "\u0414\u044f\u043a\u043e\u0432\u0446\u044b"
    ],
    "wof:name":"Dyakovtsy",
    "wof:placetype":"locality"
},
  "geometry": {"coordinates":[24.7136,53.4946],"type":"Point"}
}