{
  "type": "Feature",
  "properties": {
    "gn:admin1_code":"7.0",
    "gn:asciiname":"Koski-Bol'shiye",
    "gn:country_code":"BY",
    "gn:dem":128,
    "gn:feature_class":"P",
    "gn:feature_code":"PPL",
    "gn:name":"Koski-Bol\u2019shiye",
    "gn:population":0,
    "gn:timezone":"Europe/Minsk",
    "iso:country":"BY",
    "name:rus_x_preferred":[
        "\u041a\u043e\u0441\u043a\u0438-\u0411\u043e\u043b\u044c\u0448\u0438\u0435"
    ],
    "name:und_x_variant":[
        "Koski-Bol\u2019shiye"
    ],
    "wof:name":"Koski-Bol'shiye",
    "wof:placetype":"locality"
},
  "geometry": {"coordinates":[26.8514,55.2577],"type":"Point"}
}