{
  "type": "Feature",
  "properties": {
    "gn:admin1_code":"3.0",
    "gn:asciiname":"Polyany",
    "gn:country_code":"BY",
    "gn:dem":161,
    "gn:feature_class":"P",
    "gn:feature_code":"PPL",
    "gn:name":"Polyany",
    "gn:population":0,
    "gn:timezone":"Europe/Minsk",
    "iso:country":"BY",
    "name:bel_x_preferred":[
        "\u041f\u0430\u043b\u044f\u043d\u044b"
    ],
    "name:rus_x_preferred":[
        "\u041f\u043e\u043b\u044f\u043d\u044b"
    ],
    "name:ukr_x_preferred":[
        "\u041f\u043e\u043b\u044f\u043d\u0438"
    ],
    "wof:name":"Polyany",
    "wof:placetype":"locality"
},
  "geometry": {"coordinates":[26.0629,54.8718],"type":"Point"}
}