{
  "type": "Feature",
  "properties": {
    "gn:admin1_code":"7.0",
    "gn:asciiname":"Pankry",
    "gn:country_code":"BY",
    "gn:dem":169,
    "gn:feature_class":"P",
    "gn:feature_code":"PPL",
    "gn:name":"Pankry",
    "gn:population":0,
    "gn:timezone":"Europe/Minsk",
    "iso:country":"BY",
    "name:rus_x_preferred":[
        "\u041f\u0430\u043d\u043a\u0440\u044b"
    ],
    "wof:name":"Pankry",
    "wof:placetype":"locality"
},
  "geometry": {"coordinates":[29.9452,55.8409],"type":"Point"}
}