{
  "type": "Feature",
  "properties": {
    "gn:admin1_code":"2.0",
    "gn:asciiname":"Novoye Vysokoye",
    "gn:country_code":"BY",
    "gn:dem":132,
    "gn:feature_class":"P",
    "gn:feature_code":"PPL",
    "gn:name":"Novoye Vysokoye",
    "gn:population":0,
    "gn:timezone":"Europe/Minsk",
    "iso:country":"BY",
    "name:rus_x_preferred":[
        "\u041d\u043e\u0432\u043e\u0435 \u0412\u044b\u0441\u043e\u043a\u043e\u0435"
    ],
    "name:und_x_variant":[
        "Novo-Vysokoye"
    ],
    "wof:name":"Novoye Vysokoye",
    "wof:placetype":"locality"
},
  "geometry": {"coordinates":[28.8464,51.7606],"type":"Point"}
}