{
  "type": "Feature",
  "properties": {
    "gn:admin1_code":"6.0",
    "gn:asciiname":"Drozhzhinsk",
    "gn:country_code":"BY",
    "gn:dem":148,
    "gn:feature_class":"P",
    "gn:feature_code":"PPL",
    "gn:name":"Drozhzhinsk",
    "gn:population":0,
    "gn:timezone":"Europe/Minsk",
    "iso:country":"BY",
    "wof:name":"Drozhzhinsk",
    "wof:placetype":"locality"
},
  "geometry": {"coordinates":[31.7486,53.18729],"type":"Point"}
}