{
  "type": "Feature",
  "properties": {
    "gn:admin1_code":"5.0",
    "gn:asciiname":"Dekhnovka",
    "gn:country_code":"BY",
    "gn:dem":242,
    "gn:feature_class":"P",
    "gn:feature_code":"PPL",
    "gn:name":"Dekhnovka",
    "gn:population":0,
    "gn:timezone":"Europe/Minsk",
    "iso:country":"BY",
    "name:rus_x_preferred":[
        "\u0414\u0435\u0445\u043d\u043e\u0432\u043a\u0430"
    ],
    "wof:name":"Dekhnovka",
    "wof:placetype":"locality"
},
  "geometry": {"coordinates":[27.3013,54.0138],"type":"Point"}
}