{
  "type": "Feature",
  "properties": {
    "gn:admin1_code":"7.0",
    "gn:asciiname":"Khimy",
    "gn:country_code":"BY",
    "gn:dem":160,
    "gn:feature_class":"P",
    "gn:feature_code":"PPL",
    "gn:name":"Khimy",
    "gn:population":0,
    "gn:timezone":"Europe/Minsk",
    "iso:country":"BY",
    "name:rus_x_preferred":[
        "\u0425\u0438\u043c\u044b"
    ],
    "wof:name":"Khimy",
    "wof:placetype":"locality"
},
  "geometry": {"coordinates":[30.2768,54.3594],"type":"Point"}
}