{
  "type": "Feature",
  "properties": {
    "gn:admin1_code":"0.0",
    "gn:asciiname":"Vilkovshchina",
    "gn:country_code":"BY",
    "gn:dem":218,
    "gn:feature_class":"P",
    "gn:feature_code":"PPL",
    "gn:name":"Vilkovshchina",
    "gn:population":0,
    "gn:timezone":"Europe/Minsk",
    "iso:country":"BY",
    "wof:name":"Vilkovshchina",
    "wof:placetype":"locality"
},
  "geometry": {"coordinates":[27.55,53.83333],"type":"Point"}
}