{
  "type": "Feature",
  "properties": {
    "gn:admin1_code":"2.0",
    "gn:asciiname":"Batsun'",
    "gn:country_code":"BY",
    "gn:dem":136,
    "gn:feature_class":"P",
    "gn:feature_code":"PPL",
    "gn:name":"Batsun\u2019",
    "gn:population":0,
    "gn:timezone":"Europe/Minsk",
    "iso:country":"BY",
    "name:rus_x_preferred":[
        "\u0411\u0430\u0446\u0443\u043d\u044c"
    ],
    "name:und_x_variant":[
        "Batsun\u2019"
    ],
    "wof:name":"Batsun'",
    "wof:placetype":"locality"
},
  "geometry": {"coordinates":[30.5752,52.5831],"type":"Point"}
}