{
  "type": "Feature",
  "properties": {
    "gn:admin1_code":"7.0",
    "gn:asciiname":"Demeshkovo",
    "gn:country_code":"BY",
    "gn:dem":151,
    "gn:feature_class":"P",
    "gn:feature_code":"PPL",
    "gn:name":"Demeshkovo",
    "gn:population":0,
    "gn:timezone":"Europe/Minsk",
    "iso:country":"BY",
    "name:rus_x_preferred":[
        "\u0414\u0435\u043c\u0435\u0448\u043a\u043e\u0432\u043e"
    ],
    "wof:name":"Demeshkovo",
    "wof:placetype":"locality"
},
  "geometry": {"coordinates":[28.9207,54.9659],"type":"Point"}
}