{
  "type": "Feature",
  "properties": {
    "gn:admin1_code":"4.0",
    "gn:asciiname":"Kamuna",
    "gn:country_code":"BY",
    "gn:dem":136,
    "gn:feature_class":"P",
    "gn:feature_code":"PPL",
    "gn:name":"Kamuna",
    "gn:population":0,
    "gn:timezone":"Europe/Minsk",
    "iso:country":"BY",
    "name:bel_x_preferred":[
        "\u041a\u0430\u043c\u0443\u043d\u0430"
    ],
    "name:und_x_variant":[
        "Imeni Belorusskogo Voyennogo Okruga",
        "Kommuna",
        "Kamuna"
    ],
    "wof:name":"Kamuna",
    "wof:placetype":"locality"
},
  "geometry": {"coordinates":[28.0474,52.6168],"type":"Point"}
}