{
  "type": "Feature",
  "properties": {
    "gn:admin1_code":"3.0",
    "gn:asciiname":"Danilawtsy",
    "gn:country_code":"BY",
    "gn:dem":118,
    "gn:feature_class":"P",
    "gn:feature_code":"PPL",
    "gn:name":"Danilawtsy",
    "gn:population":0,
    "gn:timezone":"Europe/Minsk",
    "iso:country":"BY",
    "name:bel_x_preferred":[
        "\u0414\u0430\u043d\u0456\u043b\u0430\u045e\u0446\u044b"
    ],
    "name:und_x_variant":[
        "Danilovtse",
        "Danilovtsy",
        "Danilawtsy"
    ],
    "wof:name":"Danilawtsy",
    "wof:placetype":"locality"
},
  "geometry": {"coordinates":[24.4257,53.3295],"type":"Point"}
}