{
  "type": "Feature",
  "properties": {
    "gn:admin1_code":"7.0",
    "gn:asciiname":"Stan'ki",
    "gn:country_code":"BY",
    "gn:dem":151,
    "gn:feature_class":"P",
    "gn:feature_code":"PPL",
    "gn:name":"Stan\u2019ki",
    "gn:population":0,
    "gn:timezone":"Europe/Minsk",
    "iso:country":"BY",
    "name:rus_x_preferred":[
        "\u0421\u0442\u0430\u043d\u044c\u043a\u0438"
    ],
    "name:und_x_variant":[
        "Stan\u2019ki"
    ],
    "wof:name":"Stan'ki",
    "wof:placetype":"locality"
},
  "geometry": {"coordinates":[30.0175,54.9178],"type":"Point"}
}