{
  "type": "Feature",
  "properties": {
    "gn:admin1_code":"3.0",
    "gn:asciiname":"Frantishkovo",
    "gn:country_code":"BY",
    "gn:dem":219,
    "gn:feature_class":"P",
    "gn:feature_code":"PPL",
    "gn:name":"Frantishkovo",
    "gn:population":0,
    "gn:timezone":"Europe/Minsk",
    "iso:country":"BY",
    "name:bel_x_preferred":[
        "Frantsishkova"
    ],
    "name:bel_x_variant":[
        "\u0424\u0440\u0430\u043d\u0446\u0456\u0448\u043a\u043e\u0432\u0430"
    ],
    "name:rus_x_preferred":[
        "\u0424\u0440\u0430\u043d\u0442\u0438\u0448\u043a\u043e\u0432\u043e"
    ],
    "wof:name":"Frantishkovo",
    "wof:placetype":"locality"
},
  "geometry": {"coordinates":[25.9629,53.4644],"type":"Point"}
}