{
  "type": "Feature",
  "properties": {
    "gn:admin1_code":"7.0",
    "gn:asciiname":"Krasnyy Dvor",
    "gn:country_code":"BY",
    "gn:dem":167,
    "gn:feature_class":"P",
    "gn:feature_code":"PPL",
    "gn:name":"Krasnyy Dvor",
    "gn:population":0,
    "gn:timezone":"Europe/Minsk",
    "iso:country":"BY",
    "name:rus_x_preferred":[
        "\u041a\u0440\u0430\u0441\u043d\u044b\u0439 \u0414\u0432\u043e\u0440"
    ],
    "name:und_x_variant":[
        "Chirvonyy Dvor"
    ],
    "wof:name":"Krasnyy Dvor",
    "wof:placetype":"locality"
},
  "geometry": {"coordinates":[30.3064,55.3386],"type":"Point"}
}