{
  "type": "Feature",
  "properties": {
    "gn:admin1_code":"7.0",
    "gn:asciiname":"Popkov Lug",
    "gn:country_code":"BY",
    "gn:dem":136,
    "gn:feature_class":"P",
    "gn:feature_code":"PPL",
    "gn:name":"Popkov Lug",
    "gn:population":0,
    "gn:timezone":"Europe/Minsk",
    "iso:country":"BY",
    "name:rus_x_preferred":[
        "\u041f\u043e\u043f\u043a\u043e\u0432 \u041b\u0443\u0433"
    ],
    "wof:name":"Popkov Lug",
    "wof:placetype":"locality"
},
  "geometry": {"coordinates":[27.7719,55.6131],"type":"Point"}
}