{
  "type": "Feature",
  "properties": {
    "gn:admin1_code":"1.0",
    "gn:asciiname":"Belyy Lesok",
    "gn:country_code":"BY",
    "gn:dem":169,
    "gn:feature_class":"P",
    "gn:feature_code":"PPL",
    "gn:name":"Belyy Lesok",
    "gn:population":0,
    "gn:timezone":"Europe/Minsk",
    "iso:country":"BY",
    "name:rus_x_preferred":[
        "\u0411\u0435\u043b\u044b\u0439 \u041b\u0435\u0441\u043e\u043a"
    ],
    "wof:name":"Belyy Lesok",
    "wof:placetype":"locality"
},
  "geometry": {"coordinates":[24.0683,52.6228],"type":"Point"}
}