{
  "type": "Feature",
  "properties": {
    "gn:admin1_code":"3.0",
    "gn:asciiname":"Zhadeyki",
    "gn:country_code":"BY",
    "gn:dem":175,
    "gn:feature_class":"P",
    "gn:feature_code":"PPL",
    "gn:name":"Zhadeyki",
    "gn:population":0,
    "gn:timezone":"Europe/Minsk",
    "iso:country":"BY",
    "name:bel_x_preferred":[
        "Zhadzyeyki"
    ],
    "name:bel_x_variant":[
        "\u0416\u0430\u0434\u0437\u0435\u0439\u043a\u0456"
    ],
    "name:rus_x_preferred":[
        "\u0416\u0430\u0434\u0435\u0439\u043a\u0438"
    ],
    "wof:name":"Zhadeyki",
    "wof:placetype":"locality"
},
  "geometry": {"coordinates":[24.6141,53.2417],"type":"Point"}
}