{
  "type": "Feature",
  "properties": {
    "gn:admin1_code":"7.0",
    "gn:asciiname":"Kazarmennyy Gorodok",
    "gn:country_code":"BY",
    "gn:dem":144,
    "gn:feature_class":"P",
    "gn:feature_code":"PPL",
    "gn:name":"Kazarmennyy Gorodok",
    "gn:population":0,
    "gn:timezone":"Europe/Minsk",
    "iso:country":"BY",
    "name:rus_x_preferred":[
        "\u041a\u0430\u0437\u0430\u0440\u043c\u0435\u043d\u043d\u044b\u0439 \u0413\u043e\u0440\u043e\u0434\u043e\u043a"
    ],
    "wof:name":"Kazarmennyy Gorodok",
    "wof:placetype":"locality"
},
  "geometry": {"coordinates":[29.2251,55.6393],"type":"Point"}
}