{
  "type": "Feature",
  "properties": {
    "gn:admin1_code":"7.0",
    "gn:asciiname":"Dedkovo",
    "gn:country_code":"BY",
    "gn:dem":129,
    "gn:feature_class":"P",
    "gn:feature_code":"PPL",
    "gn:name":"Dedkovo",
    "gn:population":0,
    "gn:timezone":"Europe/Minsk",
    "iso:country":"BY",
    "name:rus_x_preferred":[
        "\u0414\u0435\u0434\u043a\u043e\u0432\u043e"
    ],
    "name:und_x_variant":[
        "Dzietkowo",
        "Dzetkovo",
        "Detkovo",
        "Dedkovo"
    ],
    "wof:name":"Dedkovo",
    "wof:placetype":"locality"
},
  "geometry": {"coordinates":[26.8605,55.2454],"type":"Point"}
}