{
  "type": "Feature",
  "properties": {
    "gn:admin1_code":"7.0",
    "gn:asciiname":"Adampol'ye",
    "gn:country_code":"BY",
    "gn:dem":139,
    "gn:feature_class":"P",
    "gn:feature_code":"PPL",
    "gn:name":"Adampol\u2019ye",
    "gn:population":0,
    "gn:timezone":"Europe/Minsk",
    "iso:country":"BY",
    "name:rus_x_preferred":[
        "\u0410\u0434\u0430\u043c\u043f\u043e\u043b\u044c\u0435"
    ],
    "name:und_x_variant":[
        "Adampol\u2019ye"
    ],
    "wof:name":"Adampol'ye",
    "wof:placetype":"locality"
},
  "geometry": {"coordinates":[29.15,55.5231],"type":"Point"}
}