{
  "type": "Feature",
  "properties": {
    "gn:admin1_code":"3.0",
    "gn:asciiname":"Bobyli",
    "gn:country_code":"BY",
    "gn:dem":161,
    "gn:feature_class":"P",
    "gn:feature_code":"PPL",
    "gn:name":"Bobyli",
    "gn:population":0,
    "gn:timezone":"Europe/Minsk",
    "iso:country":"BY",
    "name:rus_x_preferred":[
        "\u0411\u043e\u0431\u044b\u043b\u0438"
    ],
    "wof:name":"Bobyli",
    "wof:placetype":"locality"
},
  "geometry": {"coordinates":[24.218,53.1718],"type":"Point"}
}