{
  "type": "Feature",
  "properties": {
    "gn:admin1_code":"2.0",
    "gn:asciiname":"Zagoriny",
    "gn:country_code":"BY",
    "gn:dem":123,
    "gn:feature_class":"P",
    "gn:feature_code":"PPL",
    "gn:name":"Zagoriny",
    "gn:population":0,
    "gn:timezone":"Europe/Minsk",
    "iso:country":"BY",
    "name:rus_x_preferred":[
        "\u0417\u0430\u0433\u043e\u0440\u0438\u043d\u044b"
    ],
    "wof:name":"Zagoriny",
    "wof:placetype":"locality"
},
  "geometry": {"coordinates":[29.1411,52.1103],"type":"Point"}
}