{
  "type": "Feature",
  "properties": {
    "gn:admin1_code":"6.0",
    "gn:asciiname":"Svekrovo",
    "gn:country_code":"BY",
    "gn:dem":159,
    "gn:feature_class":"P",
    "gn:feature_code":"PPL",
    "gn:name":"Svekrovo",
    "gn:population":0,
    "gn:timezone":"Europe/Minsk",
    "iso:country":"BY",
    "name:rus_x_preferred":[
        "\u0421\u0432\u0435\u043a\u0440\u043e\u0432\u043e"
    ],
    "wof:name":"Svekrovo",
    "wof:placetype":"locality"
},
  "geometry": {"coordinates":[29.6665,53.5596],"type":"Point"}
}