{
  "type": "Feature",
  "properties": {
    "gn:admin1_code":"1.0",
    "gn:asciiname":"Nyamyerzha",
    "gn:country_code":"BY",
    "gn:dem":147,
    "gn:feature_class":"P",
    "gn:feature_code":"PPL",
    "gn:name":"Nyamyerzha",
    "gn:population":0,
    "gn:timezone":"Europe/Minsk",
    "iso:country":"BY",
    "name:bel_x_preferred":[
        "\u041d\u044f\u043c\u0435\u0440\u0436\u0430"
    ],
    "name:und_x_variant":[
        "Nemezha",
        "Nemerzha",
        "Nyamyerzha"
    ],
    "wof:name":"Nyamyerzha",
    "wof:placetype":"locality"
},
  "geometry": {"coordinates":[25.0704,52.2945],"type":"Point"}
}