{
  "type": "Feature",
  "properties": {
    "gn:admin1_code":"1.0",
    "gn:asciiname":"Stasyuki",
    "gn:country_code":"BY",
    "gn:dem":157,
    "gn:feature_class":"P",
    "gn:feature_code":"PPL",
    "gn:name":"Stasyuki",
    "gn:population":0,
    "gn:timezone":"Europe/Minsk",
    "iso:country":"BY",
    "name:rus_x_preferred":[
        "\u0421\u0442\u0430\u0441\u044e\u043a\u0438"
    ],
    "wof:name":"Stasyuki",
    "wof:placetype":"locality"
},
  "geometry": {"coordinates":[24.6539,52.572],"type":"Point"}
}