{
  "type": "Feature",
  "properties": {
    "gn:admin1_code":"7.0",
    "gn:asciiname":"Puzovichi",
    "gn:country_code":"BY",
    "gn:dem":151,
    "gn:feature_class":"P",
    "gn:feature_code":"PPL",
    "gn:name":"Puzovichi",
    "gn:population":0,
    "gn:timezone":"Europe/Minsk",
    "iso:country":"BY",
    "name:rus_x_preferred":[
        "\u041f\u0443\u0437\u043e\u0432\u0438\u0447\u0438"
    ],
    "wof:name":"Puzovichi",
    "wof:placetype":"locality"
},
  "geometry": {"coordinates":[26.8917,55.5691],"type":"Point"}
}