{
  "type": "Feature",
  "properties": {
    "gn:admin1_code":"6.0",
    "gn:asciiname":"Pogost",
    "gn:country_code":"BY",
    "gn:dem":150,
    "gn:feature_class":"P",
    "gn:feature_code":"PPL",
    "gn:name":"Pogost",
    "gn:population":0,
    "gn:timezone":"Europe/Minsk",
    "iso:country":"BY",
    "name:rus_x_preferred":[
        "\u041f\u043e\u0433\u043e\u0441\u0442"
    ],
    "wof:name":"Pogost",
    "wof:placetype":"locality"
},
  "geometry": {"coordinates":[28.652,52.9587],"type":"Point"}
}