{
  "type": "Feature",
  "properties": {
    "gn:admin1_code":"7.0",
    "gn:asciiname":"Tributishki",
    "gn:country_code":"BY",
    "gn:dem":152,
    "gn:feature_class":"P",
    "gn:feature_code":"PPL",
    "gn:name":"Tributishki",
    "gn:population":0,
    "gn:timezone":"Europe/Minsk",
    "iso:country":"BY",
    "name:rus_x_preferred":[
        "\u0422\u0440\u0438\u0431\u0443\u0442\u0438\u0448\u043a\u0438"
    ],
    "wof:name":"Tributishki",
    "wof:placetype":"locality"
},
  "geometry": {"coordinates":[26.5089,55.3636],"type":"Point"}
}