{
  "type": "Feature",
  "properties": {
    "gn:admin1_code":"7.0",
    "gn:asciiname":"Svirduny",
    "gn:country_code":"BY",
    "gn:dem":204,
    "gn:feature_class":"P",
    "gn:feature_code":"PPL",
    "gn:name":"Svirduny",
    "gn:population":0,
    "gn:timezone":"Europe/Minsk",
    "iso:country":"BY",
    "name:rus_x_preferred":[
        "\u0421\u0432\u0438\u0440\u0434\u0443\u043d\u044b"
    ],
    "wof:name":"Svirduny",
    "wof:placetype":"locality"
},
  "geometry": {"coordinates":[26.364,55.0442],"type":"Point"}
}