{
  "type": "Feature",
  "properties": {
    "gn:admin1_code":"7.0",
    "gn:asciiname":"Trubilino",
    "gn:country_code":"BY",
    "gn:dem":142,
    "gn:feature_class":"P",
    "gn:feature_code":"PPL",
    "gn:name":"Trubilino",
    "gn:population":0,
    "gn:timezone":"Europe/Minsk",
    "iso:country":"BY",
    "name:rus_x_preferred":[
        "\u0422\u0440\u0443\u0431\u0438\u043b\u0438\u043d\u043e"
    ],
    "wof:name":"Trubilino",
    "wof:placetype":"locality"
},
  "geometry": {"coordinates":[29.419,55.0033],"type":"Point"}
}