{
  "type": "Feature",
  "properties": {
    "gn:admin1_code":"5.0",
    "gn:asciiname":"Novodvor'ye",
    "gn:country_code":"BY",
    "gn:dem":194,
    "gn:feature_class":"P",
    "gn:feature_code":"PPL",
    "gn:name":"Novodvor\u2019ye",
    "gn:population":0,
    "gn:timezone":"Europe/Minsk",
    "iso:country":"BY",
    "name:rus_x_preferred":[
        "\u041d\u043e\u0432\u043e\u0434\u0432\u043e\u0440\u044c\u0435"
    ],
    "name:und_x_variant":[
        "Novodvor\u2019ye"
    ],
    "wof:name":"Novodvor'ye",
    "wof:placetype":"locality"
},
  "geometry": {"coordinates":[28.0961,54.0736],"type":"Point"}
}