{
  "type": "Feature",
  "properties": {
    "gn:admin1_code":"7.0",
    "gn:asciiname":"Bytsevo",
    "gn:country_code":"BY",
    "gn:dem":128,
    "gn:feature_class":"P",
    "gn:feature_code":"PPL",
    "gn:name":"Bytsevo",
    "gn:population":0,
    "gn:timezone":"Europe/Minsk",
    "iso:country":"BY",
    "name:rus_x_preferred":[
        "\u0411\u044b\u0446\u0435\u0432\u043e"
    ],
    "wof:name":"Bytsevo",
    "wof:placetype":"locality"
},
  "geometry": {"coordinates":[29.2211,55.0958],"type":"Point"}
}