{
  "type": "Feature",
  "properties": {
    "gn:admin1_code":"3.0",
    "gn:asciiname":"Machulina",
    "gn:country_code":"BY",
    "gn:dem":135,
    "gn:feature_class":"P",
    "gn:feature_code":"PPL",
    "gn:name":"Machulina",
    "gn:population":0,
    "gn:timezone":"Europe/Minsk",
    "iso:country":"BY",
    "name:bel_x_preferred":[
        "\u041c\u0430\u0447\u0443\u043b\u0456\u043d\u0430"
    ],
    "name:und_x_variant":[
        "Mochulino",
        "Mochul\u2019na",
        "Mochulina",
        "Machulina"
    ],
    "wof:name":"Machulina",
    "wof:placetype":"locality"
},
  "geometry": {"coordinates":[24.467,53.2411],"type":"Point"}
}