{
  "type": "Feature",
  "properties": {
    "gn:admin1_code":"5.0",
    "gn:asciiname":"Radevtsy",
    "gn:country_code":"BY",
    "gn:dem":175,
    "gn:feature_class":"P",
    "gn:feature_code":"PPL",
    "gn:name":"Radevtsy",
    "gn:population":0,
    "gn:timezone":"Europe/Minsk",
    "iso:country":"BY",
    "name:rus_x_preferred":[
        "\u0420\u0430\u0434\u0435\u0432\u0446\u044b"
    ],
    "wof:name":"Radevtsy",
    "wof:placetype":"locality"
},
  "geometry": {"coordinates":[27.1637,54.2522],"type":"Point"}
}