{
  "type": "Feature",
  "properties": {
    "gn:admin1_code":"7.0",
    "gn:asciiname":"Alekhny",
    "gn:country_code":"BY",
    "gn:dem":138,
    "gn:feature_class":"P",
    "gn:feature_code":"PPL",
    "gn:name":"Al\u00ebkhny",
    "gn:population":0,
    "gn:timezone":"Europe/Minsk",
    "iso:country":"BY",
    "name:rus_x_preferred":[
        "\u0410\u043b\u0451\u0445\u043d\u044b"
    ],
    "name:und_x_variant":[
        "Al\u00ebkhny"
    ],
    "wof:name":"Alekhny",
    "wof:placetype":"locality"
},
  "geometry": {"coordinates":[27.0537,55.8277],"type":"Point"}
}