{
  "type": "Feature",
  "properties": {
    "gn:admin1_code":"7.0",
    "gn:asciiname":"Andreyevshchina",
    "gn:country_code":"BY",
    "gn:dem":173,
    "gn:feature_class":"P",
    "gn:feature_code":"PPL",
    "gn:name":"Andreyevshchina",
    "gn:population":0,
    "gn:timezone":"Europe/Minsk",
    "iso:country":"BY",
    "name:rus_x_preferred":[
        "\u0410\u043d\u0434\u0440\u0435\u0435\u0432\u0449\u0438\u043d\u0430"
    ],
    "wof:name":"Andreyevshchina",
    "wof:placetype":"locality"
},
  "geometry": {"coordinates":[30.2813,54.8076],"type":"Point"}
}