{
  "type": "Feature",
  "properties": {
    "gn:admin1_code":"5.0",
    "gn:asciiname":"Vishnya",
    "gn:country_code":"BY",
    "gn:dem":236,
    "gn:feature_class":"P",
    "gn:feature_code":"PPL",
    "gn:name":"Vishnya",
    "gn:population":0,
    "gn:timezone":"Europe/Minsk",
    "iso:country":"BY",
    "name:rus_x_preferred":[
        "\u0412\u0438\u0448\u043d\u044f"
    ],
    "wof:name":"Vishnya",
    "wof:placetype":"locality"
},
  "geometry": {"coordinates":[27.8691,54.1058],"type":"Point"}
}