{
  "type": "Feature",
  "properties": {
    "gn:admin1_code":"7.0",
    "gn:asciiname":"Al'brekhtava",
    "gn:country_code":"BY",
    "gn:dem":156,
    "gn:feature_class":"P",
    "gn:feature_code":"PPL",
    "gn:name":"Al\u2019brekhtava",
    "gn:population":0,
    "gn:timezone":"Europe/Minsk",
    "iso:country":"BY",
    "name:bel_x_preferred":[
        "\u0410\u043b\u044c\u0431\u0440\u044d\u0445\u0442\u0430\u0432\u0430"
    ],
    "name:eng_x_preferred":[
        "Al'brekhtovo"
    ],
    "name:rus_x_preferred":[
        "\u0410\u043b\u044c\u0431\u0440\u0435\u0445\u0442\u043e\u0432\u043e"
    ],
    "name:und_x_variant":[
        "Al\u2019brekhtovo Pervoye",
        "Al\u2019brekhtovo",
        "Al\u2019brekhtava"
    ],
    "wof:name":"Al'brekhtava",
    "wof:placetype":"locality"
},
  "geometry": {"coordinates":[28.839,55.8724],"type":"Point"}
}