{
  "type": "Feature",
  "properties": {
    "gn:admin1_code":"5.0",
    "gn:asciiname":"Nitiyevskiye",
    "gn:country_code":"BY",
    "gn:dem":190,
    "gn:feature_class":"P",
    "gn:feature_code":"PPL",
    "gn:name":"Nitiyevskiye",
    "gn:population":0,
    "gn:timezone":"Europe/Minsk",
    "iso:country":"BY",
    "name:rus_x_preferred":[
        "\u041d\u0438\u0442\u0438\u0435\u0432\u0441\u043a\u0438\u0435"
    ],
    "name:und_x_variant":[
        "Natiyevskiye"
    ],
    "wof:name":"Nitiyevskiye",
    "wof:placetype":"locality"
},
  "geometry": {"coordinates":[27.5234,53.6366],"type":"Point"}
}