{
  "type": "Feature",
  "properties": {
    "gn:admin1_code":"7.0",
    "gn:asciiname":"Parshchevshchina",
    "gn:country_code":"BY",
    "gn:dem":154,
    "gn:feature_class":"P",
    "gn:feature_code":"PPL",
    "gn:name":"Parshchevshchina",
    "gn:population":0,
    "gn:timezone":"Europe/Minsk",
    "iso:country":"BY",
    "name:rus_x_preferred":[
        "\u041f\u0430\u0440\u0449\u0435\u0432\u0449\u0438\u043d\u0430"
    ],
    "wof:name":"Parshchevshchina",
    "wof:placetype":"locality"
},
  "geometry": {"coordinates":[29.2443,54.707],"type":"Point"}
}