{
  "type": "Feature",
  "properties": {
    "gn:admin1_code":"7.0",
    "gn:asciiname":"Ramzhino Pervoye",
    "gn:country_code":"BY",
    "gn:dem":189,
    "gn:feature_class":"P",
    "gn:feature_code":"PPL",
    "gn:name":"Ramzhino Pervoye",
    "gn:population":0,
    "gn:timezone":"Europe/Minsk",
    "iso:country":"BY",
    "name:rus_x_preferred":[
        "\u0420\u0430\u043c\u0436\u0438\u043d\u043e \u041f\u0435\u0440\u0432\u043e\u0435"
    ],
    "wof:name":"Ramzhino Pervoye",
    "wof:placetype":"locality"
},
  "geometry": {"coordinates":[27.7249,55.0458],"type":"Point"}
}