{
  "type": "Feature",
  "properties": {
    "gn:admin1_code":"7.0",
    "gn:asciiname":"Sosnino",
    "gn:country_code":"BY",
    "gn:dem":162,
    "gn:feature_class":"P",
    "gn:feature_code":"PPL",
    "gn:name":"Sosnino",
    "gn:population":0,
    "gn:timezone":"Europe/Minsk",
    "iso:country":"BY",
    "name:rus_x_preferred":[
        "\u0421\u043e\u0441\u043d\u0438\u043d\u043e"
    ],
    "wof:name":"Sosnino",
    "wof:placetype":"locality"
},
  "geometry": {"coordinates":[29.5498,55.1889],"type":"Point"}
}