{
  "type": "Feature",
  "properties": {
    "gn:admin1_code":"6.0",
    "gn:asciiname":"Komarichi",
    "gn:country_code":"BY",
    "gn:dem":144,
    "gn:feature_class":"P",
    "gn:feature_code":"PPL",
    "gn:name":"Komarichi",
    "gn:population":0,
    "gn:timezone":"Europe/Minsk",
    "iso:country":"BY",
    "name:bel_x_preferred":[
        "\u041a\u0430\u043c\u0430\u0440\u044b\u0447\u044b"
    ],
    "name:che_x_preferred":[
        "\u041a\u043e\u043c\u0430\u0440\u0438\u0447\u0438"
    ],
    "name:deu_x_preferred":[
        "Komaritschi"
    ],
    "name:fin_x_preferred":[
        "Komarit\u0161i"
    ],
    "name:ita_x_preferred":[
        "Komari\u010di"
    ],
    "name:lav_x_preferred":[
        "Komari\u010di"
    ],
    "name:rus_x_preferred":[
        "\u041a\u043e\u043c\u0430\u0440\u0438\u0447\u0438"
    ],
    "name:ukr_x_preferred":[
        "\u041a\u043e\u043c\u0430\u0440\u0438\u0447\u0456"
    ],
    "wof:name":"Komarichi",
    "wof:placetype":"locality"
},
  "geometry": {"coordinates":[30.26778,53.39944000000001],"type":"Point"}
}