{
  "type": "Feature",
  "properties": {
    "gn:admin1_code":"6.0",
    "gn:asciiname":"Smogilovka",
    "gn:country_code":"BY",
    "gn:dem":169,
    "gn:feature_class":"P",
    "gn:feature_code":"PPL",
    "gn:name":"Smogilovka",
    "gn:population":0,
    "gn:timezone":"Europe/Minsk",
    "iso:country":"BY",
    "name:rus_x_preferred":[
        "\u0421\u043c\u043e\u0433\u0438\u043b\u043e\u0432\u043a\u0430"
    ],
    "wof:name":"Smogilovka",
    "wof:placetype":"locality"
},
  "geometry": {"coordinates":[29.5661,54.083],"type":"Point"}
}