{
  "type": "Feature",
  "properties": {
    "gn:admin1_code":"7.0",
    "gn:asciiname":"Grushevo",
    "gn:country_code":"BY",
    "gn:dem":140,
    "gn:feature_class":"P",
    "gn:feature_code":"PPL",
    "gn:name":"Grush\u00ebvo",
    "gn:population":0,
    "gn:timezone":"Europe/Minsk",
    "iso:country":"BY",
    "name:che_x_preferred":[
        "\u0413\u0440\u0443\u0448\u0435\u0432\u043e"
    ],
    "name:rus_x_preferred":[
        "\u0413\u0440\u0443\u0448\u0451\u0432\u043e"
    ],
    "name:rus_x_variant":[
        "\u0413\u0440\u0443\u0448\u0435\u0432\u043e"
    ],
    "name:tgk_x_preferred":[
        "\u0413\u0440\u0443\u0448\u0435\u0432\u043e"
    ],
    "name:und_x_variant":[
        "Grush\u00ebvo"
    ],
    "wof:name":"Grushevo",
    "wof:placetype":"locality"
},
  "geometry": {"coordinates":[29.3055,54.8686],"type":"Point"}
}