{
  "type": "Feature",
  "properties": {
    "gn:admin1_code":"1.0",
    "gn:asciiname":"Mantyuty",
    "gn:country_code":"BY",
    "gn:dem":151,
    "gn:feature_class":"P",
    "gn:feature_code":"PPL",
    "gn:name":"Mantyuty",
    "gn:population":0,
    "gn:timezone":"Europe/Minsk",
    "iso:country":"BY",
    "name:rus_x_preferred":[
        "\u041c\u0430\u043d\u0442\u044e\u0442\u044b"
    ],
    "name:und_x_variant":[
        "Mantsiuty"
    ],
    "wof:name":"Mantyuty",
    "wof:placetype":"locality"
},
  "geometry": {"coordinates":[25.4445,52.8938],"type":"Point"}
}