{
  "type": "Feature",
  "properties": {
    "gn:admin1_code":"3.0",
    "gn:asciiname":"Bershty",
    "gn:country_code":"BY",
    "gn:dem":124,
    "gn:feature_class":"P",
    "gn:feature_code":"PPL",
    "gn:name":"Bershty",
    "gn:population":0,
    "gn:timezone":"Europe/Minsk",
    "iso:country":"BY",
    "name:bel_x_preferred":[
        "\u0411\u0435\u0440\u0448\u0442\u044b"
    ],
    "name:eng_x_preferred":[
        "Bershty"
    ],
    "name:rus_x_preferred":[
        "\u0411\u0435\u0440\u0448\u0442\u044b"
    ],
    "name:und_x_variant":[
        "Berszty",
        "Byershty"
    ],
    "wof:name":"Bershty",
    "wof:placetype":"locality"
},
  "geometry": {"coordinates":[24.3944,53.8576],"type":"Point"}
}