{
  "type": "Feature",
  "properties": {
    "gn:admin1_code":"6.0",
    "gn:asciiname":"Pribor",
    "gn:country_code":"BY",
    "gn:dem":169,
    "gn:feature_class":"P",
    "gn:feature_code":"PPL",
    "gn:name":"Pribor",
    "gn:population":0,
    "gn:timezone":"Europe/Minsk",
    "iso:country":"BY",
    "name:rus_x_preferred":[
        "\u041f\u0440\u0438\u0431\u043e\u0440"
    ],
    "wof:name":"Pribor",
    "wof:placetype":"locality"
},
  "geometry": {"coordinates":[29.7384,53.8863],"type":"Point"}
}