{
  "type": "Feature",
  "properties": {
    "gn:admin1_code":"3.0",
    "gn:asciiname":"Levashi",
    "gn:country_code":"BY",
    "gn:dem":140,
    "gn:feature_class":"P",
    "gn:feature_code":"PPL",
    "gn:name":"Levashi",
    "gn:population":0,
    "gn:timezone":"Europe/Minsk",
    "iso:country":"BY",
    "name:rus_x_preferred":[
        "\u041b\u0435\u0432\u0430\u0448\u0438"
    ],
    "wof:name":"Levashi",
    "wof:placetype":"locality"
},
  "geometry": {"coordinates":[25.4925,53.9911],"type":"Point"}
}