{
  "type": "Feature",
  "properties": {
    "gn:admin1_code":"6.0",
    "gn:asciiname":"Druzhnaya",
    "gn:country_code":"BY",
    "gn:dem":227,
    "gn:feature_class":"P",
    "gn:feature_code":"PPL",
    "gn:name":"Druzhnaya",
    "gn:population":0,
    "gn:timezone":"Europe/Minsk",
    "iso:country":"BY",
    "name:rus_x_preferred":[
        "\u0414\u0440\u0443\u0436\u043d\u0430\u044f"
    ],
    "wof:name":"Druzhnaya",
    "wof:placetype":"locality"
},
  "geometry": {"coordinates":[31.2105,54.4607],"type":"Point"}
}