{
  "type": "Feature",
  "properties": {
    "gn:admin1_code":"7.0",
    "gn:asciiname":"Vydreya",
    "gn:country_code":"BY",
    "gn:dem":183,
    "gn:feature_class":"P",
    "gn:feature_code":"PPL",
    "gn:name":"Vydreya",
    "gn:population":0,
    "gn:timezone":"Europe/Minsk",
    "iso:country":"BY",
    "name:rus_x_preferred":[
        "\u0411\u043e\u043b\u044c\u0448\u0430\u044f \u0412\u044b\u0434\u0440\u0435\u044f"
    ],
    "name:und_x_variant":[
        "Velikaya Vydreya",
        "Vydreya",
        "Bol\u2019shaya Vydreya"
    ],
    "wof:name":"Vydreya",
    "wof:placetype":"locality"
},
  "geometry": {"coordinates":[30.5681,55.0106],"type":"Point"}
}