{
  "type": "Feature",
  "properties": {
    "gn:admin1_code":"5.0",
    "gn:asciiname":"Logi",
    "gn:country_code":"BY",
    "gn:dem":190,
    "gn:feature_class":"P",
    "gn:feature_code":"PPL",
    "gn:name":"Logi",
    "gn:population":0,
    "gn:timezone":"Europe/Minsk",
    "iso:country":"BY",
    "name:bul_x_preferred":[
        "\u041b\u043e\u0433\u0438"
    ],
    "name:dan_x_preferred":[
        "Loge"
    ],
    "name:deu_x_preferred":[
        "Logi"
    ],
    "name:fin_x_preferred":[
        "Logi"
    ],
    "name:fra_x_preferred":[
        "Logi"
    ],
    "name:hrv_x_preferred":[
        "Logi"
    ],
    "name:ita_x_preferred":[
        "Logi"
    ],
    "name:nld_x_preferred":[
        "Logi"
    ],
    "name:rus_x_preferred":[
        "\u041b\u043e\u0433\u0438"
    ],
    "name:spa_x_preferred":[
        "Logi"
    ],
    "name:swe_x_preferred":[
        "Loge"
    ],
    "wof:name":"Logi",
    "wof:placetype":"locality"
},
  "geometry": {"coordinates":[28.1716,54.2766],"type":"Point"}
}