{
  "type": "Feature",
  "properties": {
    "gn:admin1_code":"7.0",
    "gn:asciiname":"Nikitenki",
    "gn:country_code":"BY",
    "gn:dem":128,
    "gn:feature_class":"P",
    "gn:feature_code":"PPL",
    "gn:name":"Nikitenki",
    "gn:population":0,
    "gn:timezone":"Europe/Minsk",
    "iso:country":"BY",
    "name:rus_x_preferred":[
        "\u041d\u0438\u043a\u0438\u0442\u0435\u043d\u043a\u0438"
    ],
    "name:und_x_variant":[
        "Mikicienki",
        "Mikitsenki",
        "Nikitenki"
    ],
    "wof:name":"Nikitenki",
    "wof:placetype":"locality"
},
  "geometry": {"coordinates":[27.7362,55.4219],"type":"Point"}
}