{
  "type": "Feature",
  "properties": {
    "gn:admin1_code":"7.0",
    "gn:asciiname":"Plitnitsa",
    "gn:country_code":"BY",
    "gn:dem":191,
    "gn:feature_class":"P",
    "gn:feature_code":"PPL",
    "gn:name":"Plitnitsa",
    "gn:population":0,
    "gn:timezone":"Europe/Minsk",
    "iso:country":"BY",
    "name:rus_x_preferred":[
        "\u041f\u043b\u0438\u0442\u043d\u0438\u0446\u0430"
    ],
    "wof:name":"Plitnitsa",
    "wof:placetype":"locality"
},
  "geometry": {"coordinates":[27.8395,54.9011],"type":"Point"}
}