{
  "type": "Feature",
  "properties": {
    "gn:admin1_code":"3.0",
    "gn:asciiname":"Krushino",
    "gn:country_code":"BY",
    "gn:dem":115,
    "gn:feature_class":"P",
    "gn:feature_code":"PPL",
    "gn:name":"Krushino",
    "gn:population":0,
    "gn:timezone":"Europe/Minsk",
    "iso:country":"BY",
    "name:rus_x_preferred":[
        "\u041a\u0440\u0443\u0448\u0438\u043d\u043e"
    ],
    "wof:name":"Krushino",
    "wof:placetype":"locality"
},
  "geometry": {"coordinates":[24.69400000000001,53.3669],"type":"Point"}
}