{
  "type": "Feature",
  "properties": {
    "gn:country":"BY",
    "gn:fcode":"PPL",
    "gn:pop":170,
    "iso:country":"BY",
    "name:rus_x_preferred":[
        "\u0417\u0430\u0433\u043e\u0440\u044c\u0435"
    ],
    "qs:name":"Zagor\u2019ye",
    "qs:photos_9r":0,
    "qs:photos_sr":0,
    "qs:pop_sr":"1",
    "wof:name":"Zagor\u2019ye",
    "wof:placetype":"locality",
    "wof:population":170
},
  "geometry": {"coordinates":[28.0159,54.0087],"type":"Point"}
}