{
  "type": "Feature",
  "properties": {
    "gn:admin1_code":"7.0",
    "gn:asciiname":"Rubezh",
    "gn:country_code":"BY",
    "gn:dem":200,
    "gn:feature_class":"P",
    "gn:feature_code":"PPL",
    "gn:name":"Rubezh",
    "gn:population":0,
    "gn:timezone":"Europe/Minsk",
    "iso:country":"BY",
    "name:rus_x_preferred":[
        "\u0420\u0443\u0431\u0435\u0436"
    ],
    "wof:name":"Rubezh",
    "wof:placetype":"locality"
},
  "geometry": {"coordinates":[26.7309,55.0538],"type":"Point"}
}