{
  "type": "Feature",
  "properties": {
    "gn:admin1_code":"7.0",
    "gn:asciiname":"Platony",
    "gn:country_code":"BY",
    "gn:dem":161,
    "gn:feature_class":"P",
    "gn:feature_code":"PPL",
    "gn:name":"Platony",
    "gn:population":0,
    "gn:timezone":"Europe/Minsk",
    "iso:country":"BY",
    "name:rus_x_preferred":[
        "\u041f\u043b\u0430\u0442\u043e\u043d\u044b"
    ],
    "wof:name":"Platony",
    "wof:placetype":"locality"
},
  "geometry": {"coordinates":[30.1558,54.9041],"type":"Point"}
}