{
  "type": "Feature",
  "properties": {
    "gn:admin1_code":"6.0",
    "gn:asciiname":"Nikitinichi",
    "gn:country_code":"BY",
    "gn:dem":190,
    "gn:feature_class":"P",
    "gn:feature_code":"PPL",
    "gn:name":"Nikitinichi",
    "gn:population":0,
    "gn:timezone":"Europe/Minsk",
    "iso:country":"BY",
    "name:eng_x_preferred":[
        "Nikitinichi"
    ],
    "name:rus_x_preferred":[
        "\u041d\u0438\u043a\u0438\u0442\u0438\u043d\u0438\u0447\u0438"
    ],
    "name:und_x_variant":[
        "Mikitinichi",
        "Nikitinichi"
    ],
    "wof:name":"Nikitinichi",
    "wof:placetype":"locality"
},
  "geometry": {"coordinates":[30.3756,54.2791],"type":"Point"}
}