{
  "type": "Feature",
  "properties": {
    "gn:admin1_code":"6.0",
    "gn:asciiname":"Malyye Slizhi",
    "gn:country_code":"BY",
    "gn:dem":187,
    "gn:feature_class":"P",
    "gn:feature_code":"PPL",
    "gn:name":"Malyye Slizhi",
    "gn:population":0,
    "gn:timezone":"Europe/Minsk",
    "iso:country":"BY",
    "name:rus_x_preferred":[
        "\u041c\u0430\u043b\u044b\u0435 \u0421\u043b\u0438\u0436\u0438"
    ],
    "wof:name":"Malyye Slizhi",
    "wof:placetype":"locality"
},
  "geometry": {"coordinates":[30.5968,54.2201],"type":"Point"}
}