{
  "type": "Feature",
  "properties": {
    "gn:admin1_code":"3.0",
    "gn:asciiname":"Paseka",
    "gn:country_code":"BY",
    "gn:dem":165,
    "gn:feature_class":"P",
    "gn:feature_code":"PPL",
    "gn:name":"Paseka",
    "gn:population":0,
    "gn:timezone":"Europe/Minsk",
    "iso:country":"BY",
    "name:ceb_x_preferred":[
        "Paseka"
    ],
    "name:ces_x_preferred":[
        "Paseka"
    ],
    "name:deu_x_preferred":[
        "Paseka"
    ],
    "name:nld_x_preferred":[
        "Paseka"
    ],
    "name:rus_x_preferred":[
        "\u041f\u0430\u0441\u0435\u043a\u0430"
    ],
    "name:slk_x_preferred":[
        "Paseka"
    ],
    "name:swe_x_preferred":[
        "Paseka"
    ],
    "wof:name":"Paseka",
    "wof:placetype":"locality"
},
  "geometry": {"coordinates":[25.4373,53.1481],"type":"Point"}
}