{
  "type": "Feature",
  "properties": {
    "gn:admin1_code":"1.0",
    "gn:asciiname":"Mozoli",
    "gn:country_code":"BY",
    "gn:dem":150,
    "gn:feature_class":"P",
    "gn:feature_code":"PPL",
    "gn:name":"Mozoli",
    "gn:population":0,
    "gn:timezone":"Europe/Minsk",
    "iso:country":"BY",
    "name:rus_x_preferred":[
        "\u041c\u043e\u0437\u043e\u043b\u0438"
    ],
    "wof:name":"Mozoli",
    "wof:placetype":"locality"
},
  "geometry": {"coordinates":[24.7634,52.9074],"type":"Point"}
}