{
  "type": "Feature",
  "properties": {
    "gn:admin1_code":"1.0",
    "gn:asciiname":"Gershony",
    "gn:country_code":"BY",
    "gn:dem":136,
    "gn:feature_class":"P",
    "gn:feature_code":"PPL",
    "gn:name":"Gershony",
    "gn:population":0,
    "gn:timezone":"Europe/Minsk",
    "iso:country":"BY",
    "name:bel_x_preferred":[
        "\u0413\u0435\u0440\u0448\u043e\u043d\u044b"
    ],
    "name:und_x_variant":[
        "Hershony"
    ],
    "wof:name":"Gershony",
    "wof:placetype":"locality"
},
  "geometry": {"coordinates":[23.7117,52.0496],"type":"Point"}
}