{
  "type": "Feature",
  "properties": {
    "gn:admin1_code":"5.0",
    "gn:asciiname":"Uznatsk",
    "gn:country_code":"BY",
    "gn:dem":185,
    "gn:feature_class":"P",
    "gn:feature_code":"PPL",
    "gn:name":"Uznatsk",
    "gn:population":0,
    "gn:timezone":"Europe/Minsk",
    "iso:country":"BY",
    "name:eng_x_preferred":[
        "Uznatsk"
    ],
    "name:rus_x_preferred":[
        "\u0423\u0437\u043d\u0430\u0446\u043a"
    ],
    "wof:name":"Uznatsk",
    "wof:placetype":"locality"
},
  "geometry": {"coordinates":[28.9849,54.4709],"type":"Point"}
}