{
  "type": "Feature",
  "properties": {
    "gn:admin1_code":"5.0",
    "gn:asciiname":"Sidorovtsy",
    "gn:country_code":"BY",
    "gn:dem":223,
    "gn:feature_class":"P",
    "gn:feature_code":"PPL",
    "gn:name":"Sidorovtsy",
    "gn:population":0,
    "gn:timezone":"Europe/Minsk",
    "iso:country":"BY",
    "name:rus_x_preferred":[
        "\u0421\u0438\u0434\u043e\u0440\u043e\u0432\u0446\u044b"
    ],
    "name:und_x_variant":[
        "Sidorovtse"
    ],
    "wof:name":"Sidorovtsy",
    "wof:placetype":"locality"
},
  "geometry": {"coordinates":[26.9747,53.9463],"type":"Point"}
}