{
  "type": "Feature",
  "properties": {
    "gn:admin1_code":"5.0",
    "gn:asciiname":"Yezzhentsy",
    "gn:country_code":"BY",
    "gn:dem":161,
    "gn:feature_class":"P",
    "gn:feature_code":"PPL",
    "gn:name":"Yezzhentsy",
    "gn:population":0,
    "gn:timezone":"Europe/Minsk",
    "iso:country":"BY",
    "name:rus_x_preferred":[
        "\u0415\u0437\u0436\u0435\u043d\u0446\u044b"
    ],
    "wof:name":"Yezzhentsy",
    "wof:placetype":"locality"
},
  "geometry": {"coordinates":[26.9082,54.7103],"type":"Point"}
}