{
  "type": "Feature",
  "properties": {
    "gn:admin1_code":"6.0",
    "gn:asciiname":"Dubrava",
    "gn:country_code":"BY",
    "gn:dem":184,
    "gn:feature_class":"P",
    "gn:feature_code":"PPL",
    "gn:name":"Dubrava",
    "gn:population":0,
    "gn:timezone":"Europe/Minsk",
    "iso:country":"BY",
    "name:rus_x_preferred":[
        "\u0414\u0443\u0431\u0440\u0430\u0432\u0430"
    ],
    "name:und_x_variant":[
        "Dubrova"
    ],
    "wof:name":"Dubrava",
    "wof:placetype":"locality"
},
  "geometry": {"coordinates":[30.1422,53.9956],"type":"Point"}
}