{
  "type": "Feature",
  "properties": {
    "gn:admin1_code":"3.0",
    "gn:asciiname":"Slabony",
    "gn:country_code":"BY",
    "gn:dem":181,
    "gn:feature_class":"P",
    "gn:feature_code":"PPL",
    "gn:name":"Slabony",
    "gn:population":0,
    "gn:timezone":"Europe/Minsk",
    "iso:country":"BY",
    "name:rus_x_preferred":[
        "\u0421\u043b\u0430\u0431\u043e\u043d\u044b"
    ],
    "name:und_x_variant":[
        "Slabsny"
    ],
    "wof:name":"Slabony",
    "wof:placetype":"locality"
},
  "geometry": {"coordinates":[26.298,54.4461],"type":"Point"}
}