{
  "type": "Feature",
  "properties": {
    "gn:admin1_code":"0.0",
    "gn:asciiname":"Rakshni",
    "gn:cc2":"BY",
    "gn:country_code":"BY",
    "gn:dem":118,
    "gn:feature_class":"P",
    "gn:feature_code":"PPL",
    "gn:name":"Rakshni",
    "gn:population":0,
    "gn:timezone":"Europe/Minsk",
    "iso:country":"BY",
    "name:und_x_variant":[
        "Rakszyno",
        "Rakshni"
    ],
    "wof:name":"Rakshni",
    "wof:placetype":"locality"
},
  "geometry": {"coordinates":[27.88333,55.93333000000001],"type":"Point"}
}