{
  "type": "Feature",
  "properties": {
    "gn:admin1_code":"3.0",
    "gn:asciiname":"Shchechitsy",
    "gn:country_code":"BY",
    "gn:dem":113,
    "gn:feature_class":"P",
    "gn:feature_code":"PPL",
    "gn:name":"Shchechitsy",
    "gn:population":0,
    "gn:timezone":"Europe/Minsk",
    "iso:country":"BY",
    "name:rus_x_preferred":[
        "\u0429\u0435\u0447\u0438\u0446\u044b"
    ],
    "wof:name":"Shchechitsy",
    "wof:placetype":"locality"
},
  "geometry": {"coordinates":[24.3378,53.4257],"type":"Point"}
}