{
  "type": "Feature",
  "properties": {
    "gn:admin1_code":"7.0",
    "gn:asciiname":"Kyakshty",
    "gn:country_code":"BY",
    "gn:dem":142,
    "gn:feature_class":"P",
    "gn:feature_code":"PPL",
    "gn:name":"Kyakshty",
    "gn:population":0,
    "gn:timezone":"Europe/Minsk",
    "iso:country":"BY",
    "name:rus_x_preferred":[
        "\u041a\u044f\u043a\u0448\u0442\u044b"
    ],
    "wof:name":"Kyakshty",
    "wof:placetype":"locality"
},
  "geometry": {"coordinates":[26.6769,55.4733],"type":"Point"}
}