{
  "type": "Feature",
  "properties": {
    "gn:admin1_code":"5.0",
    "gn:asciiname":"Styudenets",
    "gn:country_code":"BY",
    "gn:dem":182,
    "gn:feature_class":"P",
    "gn:feature_code":"PPL",
    "gn:name":"Styudenets",
    "gn:population":0,
    "gn:timezone":"Europe/Minsk",
    "iso:country":"BY",
    "name:rus_x_preferred":[
        "\u0421\u0442\u044e\u0434\u0435\u043d\u0435\u0446"
    ],
    "name:und_x_variant":[
        "Studenets"
    ],
    "wof:name":"Styudenets",
    "wof:placetype":"locality"
},
  "geometry": {"coordinates":[27.2383,54.3539],"type":"Point"}
}