{
  "type": "Feature",
  "properties": {
    "gn:admin1_code":"7.0",
    "gn:asciiname":"Pnevo",
    "gn:country_code":"BY",
    "gn:dem":202,
    "gn:feature_class":"P",
    "gn:feature_code":"PPL",
    "gn:name":"Pn\u00ebvo",
    "gn:population":0,
    "gn:timezone":"Europe/Minsk",
    "iso:country":"BY",
    "name:rus_x_preferred":[
        "\u041f\u043d\u0451\u0432\u043e"
    ],
    "name:und_x_variant":[
        "Pn\u00ebvo"
    ],
    "wof:name":"Pnevo",
    "wof:placetype":"locality"
},
  "geometry": {"coordinates":[30.8332,55.1049],"type":"Point"}
}