{
  "type": "Feature",
  "properties": {
    "gn:admin1_code":"2.0",
    "gn:asciiname":"Golubovka",
    "gn:country_code":"BY",
    "gn:dem":107,
    "gn:feature_class":"P",
    "gn:feature_code":"PPL",
    "gn:name":"Golubovka",
    "gn:population":0,
    "gn:timezone":"Europe/Minsk",
    "iso:country":"BY",
    "name:rus_x_preferred":[
        "\u0413\u043e\u043b\u0443\u0431\u043e\u0432\u043a\u0430"
    ],
    "wof:name":"Golubovka",
    "wof:placetype":"locality"
},
  "geometry": {"coordinates":[30.5091,51.4872],"type":"Point"}
}