{
  "type": "Feature",
  "properties": {
    "gn:admin1_code":"7.0",
    "gn:asciiname":"Mis'kiye",
    "gn:country_code":"BY",
    "gn:dem":151,
    "gn:feature_class":"P",
    "gn:feature_code":"PPL",
    "gn:name":"Mis\u2019kiye",
    "gn:population":0,
    "gn:timezone":"Europe/Minsk",
    "iso:country":"BY",
    "name:rus_x_preferred":[
        "\u041c\u0438\u0441\u044c\u043a\u0438\u0435"
    ],
    "name:und_x_variant":[
        "Mis\u2019kiye"
    ],
    "wof:name":"Mis'kiye",
    "wof:placetype":"locality"
},
  "geometry": {"coordinates":[26.8863,55.0974],"type":"Point"}
}