{
  "type": "Feature",
  "properties": {
    "gn:admin1_code":"7.0",
    "gn:asciiname":"Ilyushino",
    "gn:country_code":"BY",
    "gn:dem":172,
    "gn:feature_class":"P",
    "gn:feature_code":"PPL",
    "gn:name":"Ilyushino",
    "gn:population":0,
    "gn:timezone":"Europe/Minsk",
    "iso:country":"BY",
    "name:rus_x_preferred":[
        "\u0418\u043b\u044e\u0448\u0438\u043d\u043e"
    ],
    "wof:name":"Ilyushino",
    "wof:placetype":"locality"
},
  "geometry": {"coordinates":[28.5642,55.1017],"type":"Point"}
}