{
  "type": "Feature",
  "properties": {
    "gn:admin1_code":"3.0",
    "gn:asciiname":"Zavalki",
    "gn:country_code":"BY",
    "gn:dem":139,
    "gn:feature_class":"P",
    "gn:feature_code":"PPL",
    "gn:name":"Zavalki",
    "gn:population":0,
    "gn:timezone":"Europe/Minsk",
    "iso:country":"BY",
    "name:rus_x_preferred":[
        "\u0417\u0430\u0432\u0430\u043b\u043a\u0438"
    ],
    "wof:name":"Zavalki",
    "wof:placetype":"locality"
},
  "geometry": {"coordinates":[24.48692,53.61969000000001],"type":"Point"}
}