{
  "type": "Feature",
  "properties": {
    "gn:admin1_code":"5.0",
    "gn:asciiname":"Lyubovshi",
    "gn:country_code":"BY",
    "gn:dem":168,
    "gn:feature_class":"P",
    "gn:feature_code":"PPL",
    "gn:name":"Lyubovshi",
    "gn:population":0,
    "gn:timezone":"Europe/Minsk",
    "iso:country":"BY",
    "name:rus_x_preferred":[
        "\u041b\u044e\u0431\u043e\u0432\u0448\u0438"
    ],
    "wof:name":"Lyubovshi",
    "wof:placetype":"locality"
},
  "geometry": {"coordinates":[26.8871,54.6776],"type":"Point"}
}