{
  "type": "Feature",
  "properties": {
    "gn:admin1_code":"1.0",
    "gn:asciiname":"Zagorodnaya",
    "gn:country_code":"BY",
    "gn:dem":134,
    "gn:feature_class":"P",
    "gn:feature_code":"PPL",
    "gn:name":"Zagorodnaya",
    "gn:population":0,
    "gn:timezone":"Europe/Minsk",
    "iso:country":"BY",
    "name:rus_x_preferred":[
        "\u0417\u0430\u0433\u043e\u0440\u043e\u0434\u043d\u0430\u044f"
    ],
    "wof:name":"Zagorodnaya",
    "wof:placetype":"locality"
},
  "geometry": {"coordinates":[23.3227,52.2583],"type":"Point"}
}