{
  "type": "Feature",
  "properties": {
    "gn:admin1_code":"7.0",
    "gn:asciiname":"Kaverzy",
    "gn:country_code":"BY",
    "gn:dem":167,
    "gn:feature_class":"P",
    "gn:feature_code":"PPL",
    "gn:name":"Kaverzy",
    "gn:population":0,
    "gn:timezone":"Europe/Minsk",
    "iso:country":"BY",
    "name:rus_x_preferred":[
        "\u041a\u0430\u0432\u0435\u0440\u0437\u044b"
    ],
    "wof:name":"Kaverzy",
    "wof:placetype":"locality"
},
  "geometry": {"coordinates":[30.3971,55.7419],"type":"Point"}
}