{
  "type": "Feature",
  "properties": {
    "gn:admin1_code":"3.0",
    "gn:asciiname":"Budrovtsy",
    "gn:country_code":"BY",
    "gn:dem":135,
    "gn:feature_class":"P",
    "gn:feature_code":"PPL",
    "gn:name":"Budrovtsy",
    "gn:population":0,
    "gn:timezone":"Europe/Minsk",
    "iso:country":"BY",
    "name:bel_x_preferred":[
        "Budrawtsy"
    ],
    "name:bel_x_variant":[
        "\u0411\u0443\u0434\u0440\u0430\u045e\u0446\u044b"
    ],
    "name:rus_x_preferred":[
        "\u0411\u0443\u0434\u0440\u043e\u0432\u0446\u044b"
    ],
    "wof:name":"Budrovtsy",
    "wof:placetype":"locality"
},
  "geometry": {"coordinates":[24.6095,53.5359],"type":"Point"}
}