{
  "type": "Feature",
  "properties": {
    "gn:admin1_code":"7.0",
    "gn:asciiname":"Ivashkovo",
    "gn:country_code":"BY",
    "gn:dem":205,
    "gn:feature_class":"P",
    "gn:feature_code":"PPL",
    "gn:name":"Ivashkovo",
    "gn:population":0,
    "gn:timezone":"Europe/Minsk",
    "iso:country":"BY",
    "name:rus_x_preferred":[
        "\u0418\u0432\u0430\u0448\u043a\u043e\u0432\u043e"
    ],
    "wof:name":"Ivashkovo",
    "wof:placetype":"locality"
},
  "geometry": {"coordinates":[30.1126,54.6947],"type":"Point"}
}