{
  "type": "Feature",
  "properties": {
    "gn:admin1_code":"2.0",
    "gn:asciiname":"Nekrashevka",
    "gn:country_code":"BY",
    "gn:dem":126,
    "gn:feature_class":"P",
    "gn:feature_code":"PPL",
    "gn:name":"Nekrashevka",
    "gn:population":0,
    "gn:timezone":"Europe/Minsk",
    "iso:country":"BY",
    "name:rus_x_preferred":[
        "\u041d\u0435\u043a\u0440\u0430\u0448\u0435\u0432\u043a\u0430"
    ],
    "wof:name":"Nekrashevka",
    "wof:placetype":"locality"
},
  "geometry": {"coordinates":[29.0271,51.7029],"type":"Point"}
}