{
  "type": "Feature",
  "properties": {
    "gn:admin1_code":"2.0",
    "gn:asciiname":"Shestovichi",
    "gn:country_code":"BY",
    "gn:dem":118,
    "gn:feature_class":"P",
    "gn:feature_code":"PPL",
    "gn:name":"Shestovichi",
    "gn:population":0,
    "gn:timezone":"Europe/Minsk",
    "iso:country":"BY",
    "name:rus_x_preferred":[
        "\u0428\u0435\u0441\u0442\u043e\u0432\u0438\u0447\u0438"
    ],
    "wof:name":"Shestovichi",
    "wof:placetype":"locality"
},
  "geometry": {"coordinates":[28.6582,52.0915],"type":"Point"}
}