{
  "type": "Feature",
  "properties": {
    "gn:admin1_code":"0.0",
    "gn:asciiname":"Zorya",
    "gn:country_code":"BY",
    "gn:dem":194,
    "gn:feature_class":"P",
    "gn:feature_code":"PPL",
    "gn:name":"Zorya",
    "gn:population":0,
    "gn:timezone":"Europe/Minsk",
    "iso:country":"BY",
    "name:afr_x_preferred":[
        "Die Zori"
    ],
    "name:bel_x_preferred":[
        "\u0417\u0430\u0440\u0430-\u0417\u0430\u0440\u0430\u043d\u0456\u0446\u0430"
    ],
    "name:bul_x_preferred":[
        "\u0417\u043e\u0440\u0438"
    ],
    "name:ces_x_preferred":[
        "Zora"
    ],
    "name:deu_x_preferred":[
        "Zorya"
    ],
    "name:ell_x_preferred":[
        "\u0396\u03cc\u03c1\u03b9\u03b1"
    ],
    "name:fra_x_preferred":[
        "Zorya"
    ],
    "name:hrv_x_preferred":[
        "Zora"
    ],
    "name:mkd_x_preferred":[
        "\u0417\u043e\u0440\u0430"
    ],
    "name:por_x_preferred":[
        "Zorya"
    ],
    "name:rus_x_preferred":[
        "\u0417\u0430\u0440\u044f"
    ],
    "wof:name":"Zorya",
    "wof:placetype":"locality"
},
  "geometry": {"coordinates":[30.11667000000001,54.35],"type":"Point"}
}