{
  "type": "Feature",
  "properties": {
    "gn:admin1_code":"0.0",
    "gn:asciiname":"Budynki",
    "gn:cc2":"BY",
    "gn:country_code":"BY",
    "gn:dem":143,
    "gn:feature_class":"P",
    "gn:feature_code":"PPL",
    "gn:name":"Budynki",
    "gn:population":0,
    "gn:timezone":"Europe/Minsk",
    "iso:country":"BY",
    "name:und_x_variant":[
        "Lesnyye Budynki",
        "Budynki"
    ],
    "wof:name":"Budynki",
    "wof:placetype":"locality"
},
  "geometry": {"coordinates":[27.25,51.78333],"type":"Point"}
}