{
  "type": "Feature",
  "properties": {
    "gn:admin1_code":"2.0",
    "gn:asciiname":"Lyadtsy",
    "gn:country_code":"BY",
    "gn:dem":135,
    "gn:feature_class":"P",
    "gn:feature_code":"PPL",
    "gn:name":"Lyadtsy",
    "gn:population":0,
    "gn:timezone":"Europe/Minsk",
    "iso:country":"BY",
    "name:rus_x_preferred":[
        "\u041b\u044f\u0434\u0446\u044b"
    ],
    "wof:name":"Lyadtsy",
    "wof:placetype":"locality"
},
  "geometry": {"coordinates":[31.1154,52.1013],"type":"Point"}
}