{
  "type": "Feature",
  "properties": {
    "gn:admin1_code":"7.0",
    "gn:asciiname":"Brovchino",
    "gn:country_code":"BY",
    "gn:dem":179,
    "gn:feature_class":"P",
    "gn:feature_code":"PPL",
    "gn:name":"Brovchino",
    "gn:population":0,
    "gn:timezone":"Europe/Minsk",
    "iso:country":"BY",
    "name:rus_x_preferred":[
        "\u0411\u0440\u043e\u0432\u0447\u0438\u043d\u043e"
    ],
    "name:und_x_variant":[
        "Brovcheno"
    ],
    "wof:name":"Brovchino",
    "wof:placetype":"locality"
},
  "geometry": {"coordinates":[28.6074,55.0885],"type":"Point"}
}