{
  "type": "Feature",
  "properties": {
    "gn:admin1_code":"2.0",
    "gn:asciiname":"Klinsk",
    "gn:country_code":"BY",
    "gn:dem":115,
    "gn:feature_class":"P",
    "gn:feature_code":"PPL",
    "gn:name":"Klinsk",
    "gn:population":0,
    "gn:timezone":"Europe/Minsk",
    "iso:country":"BY",
    "name:rus_x_preferred":[
        "\u041a\u043b\u0438\u043d\u0441\u043a"
    ],
    "wof:name":"Klinsk",
    "wof:placetype":"locality"
},
  "geometry": {"coordinates":[29.0988,52.1711],"type":"Point"}
}