{
  "type": "Feature",
  "properties": {
    "gn:admin1_code":"7.0",
    "gn:asciiname":"Trumpichi",
    "gn:country_code":"BY",
    "gn:dem":124,
    "gn:feature_class":"P",
    "gn:feature_code":"PPL",
    "gn:name":"Trumpichi",
    "gn:population":0,
    "gn:timezone":"Europe/Minsk",
    "iso:country":"BY",
    "name:rus_x_preferred":[
        "\u0422\u0440\u0443\u043c\u0440\u0438\u0447\u0438"
    ],
    "wof:name":"Trumpichi",
    "wof:placetype":"locality"
},
  "geometry": {"coordinates":[27.2258,55.2433],"type":"Point"}
}