{
  "type": "Feature",
  "properties": {
    "gn:admin1_code":"5.0",
    "gn:asciiname":"Khvatynka",
    "gn:country_code":"BY",
    "gn:dem":194,
    "gn:feature_class":"P",
    "gn:feature_code":"PPL",
    "gn:name":"Khvatynka",
    "gn:population":0,
    "gn:timezone":"Europe/Minsk",
    "iso:country":"BY",
    "name:rus_x_preferred":[
        "\u0425\u0432\u0430\u0442\u044b\u043d\u043a\u0430"
    ],
    "wof:name":"Khvatynka",
    "wof:placetype":"locality"
},
  "geometry": {"coordinates":[29.4296,54.5249],"type":"Point"}
}