{
  "type": "Feature",
  "properties": {
    "gn:admin1_code":"5.0",
    "gn:asciiname":"Ostrov Pervyy",
    "gn:country_code":"BY",
    "gn:dem":181,
    "gn:feature_class":"P",
    "gn:feature_code":"PPL",
    "gn:name":"Ostrov Pervyy",
    "gn:population":0,
    "gn:timezone":"Europe/Minsk",
    "iso:country":"BY",
    "name:rus_x_preferred":[
        "\u041e\u0441\u0442\u0440\u043e\u0432 \u041f\u0435\u0440\u0432\u044b\u0439"
    ],
    "wof:name":"Ostrov Pervyy",
    "wof:placetype":"locality"
},
  "geometry": {"coordinates":[27.7469,54.5401],"type":"Point"}
}