{
  "type": "Feature",
  "properties": {
    "gn:admin1_code":"2.0",
    "gn:asciiname":"Mikhnovka",
    "gn:country_code":"BY",
    "gn:dem":120,
    "gn:feature_class":"P",
    "gn:feature_code":"PPL",
    "gn:name":"Mikhnovka",
    "gn:population":0,
    "gn:timezone":"Europe/Minsk",
    "iso:country":"BY",
    "name:rus_x_preferred":[
        "\u041c\u0438\u0445\u043d\u043e\u0432\u043a\u0430"
    ],
    "wof:name":"Mikhnovka",
    "wof:placetype":"locality"
},
  "geometry": {"coordinates":[30.2837,51.8857],"type":"Point"}
}