{
  "type": "Feature",
  "properties": {
    "gn:admin1_code":"5.0",
    "gn:asciiname":"Kozlevshchina",
    "gn:country_code":"BY",
    "gn:dem":216,
    "gn:feature_class":"P",
    "gn:feature_code":"PPL",
    "gn:name":"Kozlevshchina",
    "gn:population":0,
    "gn:timezone":"Europe/Minsk",
    "iso:country":"BY",
    "name:rus_x_preferred":[
        "\u041a\u043e\u0437\u043b\u0435\u0432\u0449\u0438\u043d\u0430"
    ],
    "name:und_x_variant":[
        "Ko\u017alewszczyzna",
        "Kozlevshchina"
    ],
    "wof:name":"Kozlevshchina",
    "wof:placetype":"locality"
},
  "geometry": {"coordinates":[27.4813,54.3004],"type":"Point"}
}