{
  "type": "Feature",
  "properties": {
    "gn:admin1_code":"7.0",
    "gn:asciiname":"Gryada",
    "gn:country_code":"BY",
    "gn:dem":159,
    "gn:feature_class":"P",
    "gn:feature_code":"PPL",
    "gn:name":"Gryada",
    "gn:population":0,
    "gn:timezone":"Europe/Minsk",
    "iso:country":"BY",
    "name:che_x_preferred":[
        "\u0413\u0440\u044f\u0434\u0430"
    ],
    "name:rus_x_preferred":[
        "\u0413\u0440\u044f\u0434\u0430"
    ],
    "wof:name":"Gryada",
    "wof:placetype":"locality"
},
  "geometry": {"coordinates":[29.7204,55.3657],"type":"Point"}
}