{
  "type": "Feature",
  "properties": {
    "gn:admin1_code":"7.0",
    "gn:asciiname":"Dvukhpol'ye",
    "gn:country_code":"BY",
    "gn:dem":159,
    "gn:feature_class":"P",
    "gn:feature_code":"PPL",
    "gn:name":"Dvukhpol\u2019ye",
    "gn:population":0,
    "gn:timezone":"Europe/Minsk",
    "iso:country":"BY",
    "name:rus_x_preferred":[
        "\u0414\u0432\u0443\u0445\u043f\u043e\u043b\u044c\u0435"
    ],
    "name:und_x_variant":[
        "Dvukhpol\u2019ye"
    ],
    "wof:name":"Dvukhpol'ye",
    "wof:placetype":"locality"
},
  "geometry": {"coordinates":[30.5294,55.5973],"type":"Point"}
}