{
  "type": "Feature",
  "properties": {
    "gn:admin1_code":"1.0",
    "gn:asciiname":"Kamenitsa",
    "gn:country_code":"BY",
    "gn:dem":140,
    "gn:feature_class":"P",
    "gn:feature_code":"PPL",
    "gn:name":"Kamenitsa",
    "gn:population":0,
    "gn:timezone":"Europe/Minsk",
    "iso:country":"BY",
    "name:ceb_x_preferred":[
        "Kamenitsa"
    ],
    "name:fra_x_preferred":[
        "Kamenitsa"
    ],
    "name:swe_x_preferred":[
        "Kamenitsa"
    ],
    "name:und_x_variant":[
        "Kamienica"
    ],
    "wof:name":"Kamenitsa",
    "wof:placetype":"locality"
},
  "geometry": {"coordinates":[23.81667,52.03333],"type":"Point"}
}