{
  "type": "Feature",
  "properties": {
    "gn:admin1_code":"7.0",
    "gn:asciiname":"Rafolovo",
    "gn:country_code":"BY",
    "gn:dem":216,
    "gn:feature_class":"P",
    "gn:feature_code":"PPL",
    "gn:name":"Rafolovo",
    "gn:population":0,
    "gn:timezone":"Europe/Minsk",
    "iso:country":"BY",
    "name:rus_x_preferred":[
        "\u0420\u0430\u0444\u043e\u043b\u043e\u0432\u043e"
    ],
    "name:und_x_variant":[
        "Rafalovo"
    ],
    "wof:name":"Rafolovo",
    "wof:placetype":"locality"
},
  "geometry": {"coordinates":[29.5572,54.525],"type":"Point"}
}