{
  "type": "Feature",
  "properties": {
    "iso:country":"BY",
    "name:bel_x_preferred":[
        "\u0410\u0433\u0440\u0430\u0433\u0430\u0440\u0430\u0434\u043e\u043a \u0406\u043b\u044c\u044f"
    ],
    "name:bel_x_variant":[
        "\u0406\u043b\u044c\u043b\u044f",
        "\u0406\u043b\u044c\u044f"
    ],
    "name:ceb_x_preferred":[
        "Il'ya"
    ],
    "name:eng_x_preferred":[
        "Il'ya"
    ],
    "name:eng_x_variant":[
        "Ilya"
    ],
    "name:heb_x_preferred":[
        "\u05d0\u05d9\u05dc\u05d9\u05d4"
    ],
    "name:nld_x_preferred":[
        "Ilya"
    ],
    "name:pol_x_preferred":[
        "Ilia"
    ],
    "name:rus_x_preferred":[
        "\u0418\u043b\u044c\u044f"
    ],
    "name:swe_x_preferred":[
        "Ilja"
    ],
    "name:ukr_x_preferred":[
        "\u0406\u043b\u043b\u044f"
    ],
    "name:unk_x_variant":[
        "Ilia"
    ],
    "name:zho_x_preferred":[
        "\u6208\u7f85\u5b63\u8b1d"
    ],
    "qs:gn_country":"BY",
    "qs:gn_fcode":"PPL",
    "qs:gn_pop":1800,
    "qs:name":"Il'ya",
    "qs:name_adm0":"Belarus",
    "qs:name_adm1":"Minskaya Voblasts'",
    "qs:photos":0,
    "qs:photos_1k":0,
    "qs:photos_9k":0,
    "qs:photos_9r":0,
    "qs:photos_all":0,
    "qs:photos_sr":0,
    "qs:placetype":"Town",
    "qs:pop_sr":"3",
    "qs:woe_adm0":23424765,
    "wd:wordcount":623,
    "wof:name":"Il'ya",
    "wof:placetype":"locality",
    "wof:population":1800
},
  "geometry": {"coordinates":[27.2958,54.4167],"type":"Point"}
}