{
  "type": "Feature",
  "properties": {
    "gn:admin1_code":"1.0",
    "gn:asciiname":"Koshevichi",
    "gn:country_code":"BY",
    "gn:dem":140,
    "gn:feature_class":"P",
    "gn:feature_code":"PPL",
    "gn:name":"Koshevichi",
    "gn:population":0,
    "gn:timezone":"Europe/Minsk",
    "iso:country":"BY",
    "name:rus_x_preferred":[
        "\u041a\u043e\u0448\u0435\u0432\u0438\u0447\u0438"
    ],
    "name:und_x_variant":[
        "Kosheviche",
        "Koshevichi"
    ],
    "wof:name":"Koshevichi",
    "wof:placetype":"locality"
},
  "geometry": {"coordinates":[25.9767,52.1725],"type":"Point"}
}