{
  "type": "Feature",
  "properties": {
    "gn:admin1_code":"6.0",
    "gn:asciiname":"Pervoye Maya",
    "gn:country_code":"BY",
    "gn:dem":161,
    "gn:feature_class":"P",
    "gn:feature_code":"PPL",
    "gn:name":"Pervoye Maya",
    "gn:population":0,
    "gn:timezone":"Europe/Minsk",
    "iso:country":"BY",
    "name:ceb_x_preferred":[
        "Pervoye Maya"
    ],
    "name:rus_x_preferred":[
        "\u041f\u0435\u0440\u0432\u043e\u0435 \u041c\u0430\u044f"
    ],
    "name:swe_x_preferred":[
        "Pervoye Maya"
    ],
    "wof:name":"Pervoye Maya",
    "wof:placetype":"locality"
},
  "geometry": {"coordinates":[32.1755,53.3175],"type":"Point"}
}