{
  "type": "Feature",
  "properties": {
    "gn:admin1_code":"5.0",
    "gn:asciiname":"Polelyum",
    "gn:country_code":"BY",
    "gn:dem":178,
    "gn:feature_class":"P",
    "gn:feature_code":"PPL",
    "gn:name":"Polelyum",
    "gn:population":0,
    "gn:timezone":"Europe/Minsk",
    "iso:country":"BY",
    "name:rus_x_preferred":[
        "\u041f\u043e\u043b\u0435\u043b\u044e\u043c"
    ],
    "wof:name":"Polelyum",
    "wof:placetype":"locality"
},
  "geometry": {"coordinates":[28.686,54.0506],"type":"Point"}
}