{
  "type": "Feature",
  "properties": {
    "gn:admin1_code":"5.0",
    "gn:asciiname":"Ostrovo",
    "gn:country_code":"BY",
    "gn:dem":177,
    "gn:feature_class":"P",
    "gn:feature_code":"PPL",
    "gn:name":"Ostrovo",
    "gn:population":0,
    "gn:timezone":"Europe/Minsk",
    "iso:country":"BY",
    "name:bos_x_preferred":[
        "Ostrovo"
    ],
    "name:bul_x_preferred":[
        "\u041e\u0441\u0442\u0440\u043e\u0432\u043e"
    ],
    "name:ceb_x_preferred":[
        "Ostrovo"
    ],
    "name:fra_x_preferred":[
        "Ostrovo"
    ],
    "name:por_x_preferred":[
        "Ostrovo"
    ],
    "name:rus_x_preferred":[
        "\u041e\u0441\u0442\u0440\u043e\u0432\u043e"
    ],
    "name:slv_x_preferred":[
        "Ostrovo"
    ],
    "name:srp_x_preferred":[
        "\u041e\u0441\u0442\u0440\u043e\u0432\u043e"
    ],
    "name:swe_x_preferred":[
        "Ostrovo"
    ],
    "wof:name":"Ostrovo",
    "wof:placetype":"locality"
},
  "geometry": {"coordinates":[29.0007,54.2946],"type":"Point"}
}