{
  "type": "Feature",
  "properties": {
    "gn:admin1_code":"0.0",
    "gn:asciiname":"Venslaventy",
    "gn:cc2":"BY",
    "gn:country_code":"BY",
    "gn:dem":185,
    "gn:feature_class":"P",
    "gn:feature_code":"PPL",
    "gn:name":"Venslaventy",
    "gn:population":0,
    "gn:timezone":"Europe/Minsk",
    "iso:country":"BY",
    "name:und_x_variant":[
        "Ventslaventy",
        "W\u0119s\u0142awini\u0119ta",
        "Venslaventy"
    ],
    "wof:name":"Venslaventy",
    "wof:placetype":"locality"
},
  "geometry": {"coordinates":[26.26667,54.45],"type":"Point"}
}