{
  "type": "Feature",
  "properties": {
    "gn:admin1_code":"6.0",
    "gn:asciiname":"Pavlenka",
    "gn:country_code":"BY",
    "gn:dem":160,
    "gn:feature_class":"P",
    "gn:feature_code":"PPL",
    "gn:name":"Pavlenka",
    "gn:population":0,
    "gn:timezone":"Europe/Minsk",
    "iso:country":"BY",
    "name:rus_x_preferred":[
        "\u041f\u0430\u0432\u043b\u0435\u043d\u043a\u0430"
    ],
    "wof:name":"Pavlenka",
    "wof:placetype":"locality"
},
  "geometry": {"coordinates":[32.079,53.1488],"type":"Point"}
}