{
  "type": "Feature",
  "properties": {
    "gn:admin1_code":"7.0",
    "gn:asciiname":"Zadorozh'ye",
    "gn:country_code":"BY",
    "gn:dem":141,
    "gn:feature_class":"P",
    "gn:feature_code":"PPL",
    "gn:name":"Zadorozh\u2019ye",
    "gn:population":0,
    "gn:timezone":"Europe/Minsk",
    "iso:country":"BY",
    "name:rus_x_preferred":[
        "\u0417\u0430\u0434\u043e\u0440\u043e\u0436\u044c\u0435"
    ],
    "name:und_x_variant":[
        "Zadorozh\u2019ye"
    ],
    "wof:name":"Zadorozh'ye",
    "wof:placetype":"locality"
},
  "geometry": {"coordinates":[29.6936,55.0992],"type":"Point"}
}