{
  "type": "Feature",
  "properties": {
    "gn:admin1_code":"1.0",
    "gn:asciiname":"Ozerets",
    "gn:country_code":"BY",
    "gn:dem":196,
    "gn:feature_class":"P",
    "gn:feature_code":"PPL",
    "gn:name":"Ozerets",
    "gn:population":0,
    "gn:timezone":"Europe/Minsk",
    "iso:country":"BY",
    "name:rus_x_preferred":[
        "\u041e\u0437\u0435\u0440\u0435\u0446"
    ],
    "wof:name":"Ozerets",
    "wof:placetype":"locality"
},
  "geometry": {"coordinates":[26.1404,53.2951],"type":"Point"}
}