{
  "type": "Feature",
  "properties": {
    "gn:admin1_code":"6.0",
    "gn:asciiname":"Bayanovo",
    "gn:country_code":"BY",
    "gn:dem":135,
    "gn:feature_class":"P",
    "gn:feature_code":"PPL",
    "gn:name":"Bayanovo",
    "gn:population":0,
    "gn:timezone":"Europe/Minsk",
    "iso:country":"BY",
    "name:rus_x_preferred":[
        "\u0411\u0430\u044f\u043d\u043e\u0432\u043e"
    ],
    "wof:name":"Bayanovo",
    "wof:placetype":"locality"
},
  "geometry": {"coordinates":[28.7347,52.788],"type":"Point"}
}