{
  "type": "Feature",
  "properties": {
    "gn:admin1_code":"7.0",
    "gn:asciiname":"Zachistiki",
    "gn:country_code":"BY",
    "gn:dem":129,
    "gn:feature_class":"P",
    "gn:feature_code":"PPL",
    "gn:name":"Zachistiki",
    "gn:population":0,
    "gn:timezone":"Europe/Minsk",
    "iso:country":"BY",
    "name:rus_x_preferred":[
        "\u0417\u0430\u0447\u0438\u0441\u0442\u0438\u043a\u0438"
    ],
    "wof:name":"Zachistiki",
    "wof:placetype":"locality"
},
  "geometry": {"coordinates":[27.59,55.4112],"type":"Point"}
}