{
  "type": "Feature",
  "properties": {
    "gn:admin1_code":"0.0",
    "gn:asciiname":"Verkhovaya",
    "gn:country_code":"BY",
    "gn:dem":189,
    "gn:feature_class":"P",
    "gn:feature_code":"PPL",
    "gn:name":"Verkhovaya",
    "gn:population":0,
    "gn:timezone":"Europe/Minsk",
    "iso:country":"BY",
    "wof:name":"Verkhovaya",
    "wof:placetype":"locality"
},
  "geometry": {"coordinates":[32.44858,53.66605],"type":"Point"}
}