{
  "type": "Feature",
  "properties": {
    "gn:admin1_code":"7.0",
    "gn:asciiname":"Syarhyeyevichy",
    "gn:country_code":"BY",
    "gn:dem":170,
    "gn:feature_class":"P",
    "gn:feature_code":"PPL",
    "gn:name":"Syarhyeyevichy",
    "gn:population":0,
    "gn:timezone":"Europe/Minsk",
    "iso:country":"BY",
    "name:bel_x_preferred":[
        "\u0421\u044f\u0440\u0433\u0435\u0435\u0432\u0456\u0447\u044b"
    ],
    "name:und_x_variant":[
        "Sierhiejewicze",
        "Sergeyevichi",
        "Syarhyeyevichy"
    ],
    "wof:name":"Syarhyeyevichy",
    "wof:placetype":"locality"
},
  "geometry": {"coordinates":[27.2285,55.0155],"type":"Point"}
}