{
  "type": "Feature",
  "properties": {
    "gn:admin1_code":"5.0",
    "gn:asciiname":"Boroviki",
    "gn:country_code":"BY",
    "gn:dem":158,
    "gn:feature_class":"P",
    "gn:feature_code":"PPL",
    "gn:name":"Boroviki",
    "gn:population":0,
    "gn:timezone":"Europe/Minsk",
    "iso:country":"BY",
    "name:rus_x_preferred":[
        "\u0411\u043e\u0440\u043e\u0432\u0438\u043a\u0438"
    ],
    "wof:name":"Boroviki",
    "wof:placetype":"locality"
},
  "geometry": {"coordinates":[28.0682,52.9967],"type":"Point"}
}