{
  "type": "Feature",
  "properties": {
    "gn:admin1_code":"3.0",
    "gn:asciiname":"Daynova",
    "gn:country_code":"BY",
    "gn:dem":175,
    "gn:feature_class":"P",
    "gn:feature_code":"PPL",
    "gn:name":"Daynova",
    "gn:population":0,
    "gn:timezone":"Europe/Minsk",
    "iso:country":"BY",
    "name:rus_x_preferred":[
        "\u0414\u0430\u0439\u043d\u043e\u0432\u0430"
    ],
    "name:und_x_variant":[
        "Deynova"
    ],
    "wof:name":"Daynova",
    "wof:placetype":"locality"
},
  "geometry": {"coordinates":[25.5737,54.0988],"type":"Point"}
}