{
  "type": "Feature",
  "properties": {
    "gn:admin1_code":"5.0",
    "gn:asciiname":"Yavidovshchina",
    "gn:country_code":"BY",
    "gn:dem":182,
    "gn:feature_class":"P",
    "gn:feature_code":"PPL",
    "gn:name":"Yavidovshchina",
    "gn:population":0,
    "gn:timezone":"Europe/Minsk",
    "iso:country":"BY",
    "name:rus_x_preferred":[
        "\u042f\u0432\u0438\u0434\u043e\u0432\u0449\u0438\u043d\u0430"
    ],
    "wof:name":"Yavidovshchina",
    "wof:placetype":"locality"
},
  "geometry": {"coordinates":[26.7389,53.9916],"type":"Point"}
}