{
  "type": "Feature",
  "properties": {
    "gn:admin1_code":"6.0",
    "gn:asciiname":"Lyskovshchina",
    "gn:country_code":"BY",
    "gn:dem":188,
    "gn:feature_class":"P",
    "gn:feature_code":"PPL",
    "gn:name":"Lyskovshchina",
    "gn:population":0,
    "gn:timezone":"Europe/Minsk",
    "iso:country":"BY",
    "name:rus_x_preferred":[
        "\u041b\u044b\u0441\u043a\u043e\u0432\u0449\u0438\u043d\u0430"
    ],
    "wof:name":"Lyskovshchina",
    "wof:placetype":"locality"
},
  "geometry": {"coordinates":[29.7414,54.2791],"type":"Point"}
}