{
  "type": "Feature",
  "properties": {
    "gn:admin1_code":"5.0",
    "gn:asciiname":"Shchedrovshchina",
    "gn:country_code":"BY",
    "gn:dem":239,
    "gn:feature_class":"P",
    "gn:feature_code":"PPL",
    "gn:name":"Shchedrovshchina",
    "gn:population":0,
    "gn:timezone":"Europe/Minsk",
    "iso:country":"BY",
    "name:rus_x_preferred":[
        "\u0429\u0435\u0434\u0440\u043e\u0432\u0449\u0438\u043d\u0430"
    ],
    "wof:name":"Shchedrovshchina",
    "wof:placetype":"locality"
},
  "geometry": {"coordinates":[27.3646,54.1539],"type":"Point"}
}