{
  "type": "Feature",
  "properties": {
    "gn:admin1_code":"5.0",
    "gn:asciiname":"Murzy",
    "gn:country_code":"BY",
    "gn:dem":214,
    "gn:feature_class":"P",
    "gn:feature_code":"PPL",
    "gn:name":"Murzy",
    "gn:population":0,
    "gn:timezone":"Europe/Minsk",
    "iso:country":"BY",
    "name:rus_x_preferred":[
        "\u041c\u0443\u0440\u0437\u044b"
    ],
    "wof:name":"Murzy",
    "wof:placetype":"locality"
},
  "geometry": {"coordinates":[26.8739,54.1591],"type":"Point"}
}