{
  "type": "Feature",
  "properties": {
    "gn:admin1_code":"7.0",
    "gn:asciiname":"Sergeyki",
    "gn:country_code":"BY",
    "gn:dem":172,
    "gn:feature_class":"P",
    "gn:feature_code":"PPL",
    "gn:name":"Sergeyki",
    "gn:population":0,
    "gn:timezone":"Europe/Minsk",
    "iso:country":"BY",
    "name:rus_x_preferred":[
        "\u0421\u0435\u0440\u0433\u0435\u0439\u043a\u0438"
    ],
    "wof:name":"Sergeyki",
    "wof:placetype":"locality"
},
  "geometry": {"coordinates":[29.4742,54.7618],"type":"Point"}
}