{
  "type": "Feature",
  "properties": {
    "gn:admin1_code":"3.0",
    "gn:asciiname":"Byarozawka",
    "gn:country_code":"BY",
    "gn:dem":137,
    "gn:feature_class":"P",
    "gn:feature_code":"PPL",
    "gn:name":"Byarozawka",
    "gn:population":0,
    "gn:timezone":"Europe/Minsk",
    "iso:country":"BY",
    "name:bel_x_preferred":[
        "Byarozawka"
    ],
    "name:bel_x_variant":[
        "\u0411\u044f\u0440\u043e\u0437\u0430\u045e\u043a\u0430"
    ],
    "name:rus_x_preferred":[
        "Ber\u00ebzovka"
    ],
    "name:rus_x_variant":[
        "\u0411\u0435\u0440\u0451\u0437\u043e\u0432\u043a\u0430"
    ],
    "name:und_x_variant":[
        "Bzhozuvka"
    ],
    "wof:name":"Byarozawka",
    "wof:placetype":"locality"
},
  "geometry": {"coordinates":[24.9374,53.8956],"type":"Point"}
}