{
  "type": "Feature",
  "properties": {
    "gn:admin1_code":"3.0",
    "gn:asciiname":"Byarozawka",
    "gn:country_code":"BY",
    "gn:dem":137,
    "gn:feature_class":"P",
    "gn:feature_code":"PPL",
    "gn:name":"Byarozawka",
    "gn:population":0,
    "gn:timezone":"Europe/Minsk",
    "iso:country":"BY",
    "name:bel_x_preferred":[
        "Byarozawka"
    ],
    "name:bel_x_variant":[
        "\u0411\u044f\u0440\u043e\u0437\u0430\u045e\u043a\u0430"
    ],
    "name:ces_x_preferred":[
        "Bjaroza\u016dka"
    ],
    "name:est_x_preferred":[
        "Biaroza\u016dka"
    ],
    "name:fin_x_preferred":[
        "Bjarozauka"
    ],
    "name:fra_x_preferred":[
        "Biarozawka"
    ],
    "name:hsb_x_preferred":[
        "Bjarozawka"
    ],
    "name:hun_x_preferred":[
        "Bjarozavka"
    ],
    "name:lav_x_preferred":[
        "Bjarozavka"
    ],
    "name:lit_x_preferred":[
        "Biarozauka"
    ],
    "name:pol_x_preferred":[
        "Brzoz\u00f3wka"
    ],
    "name:rus_x_preferred":[
        "Ber\u00ebzovka"
    ],
    "name:rus_x_variant":[
        "\u0411\u0435\u0440\u0451\u0437\u043e\u0432\u043a\u0430"
    ],
    "name:srp_x_preferred":[
        "\u0411\u0458\u0430\u0440\u043e\u0437\u0430\u0432\u043a\u0430"
    ],
    "name:ukr_x_preferred":[
        "\u0411\u0435\u0440\u0435\u0437\u043e\u0432\u043a\u0430"
    ],
    "name:und_x_variant":[
        "Bzhozuvka"
    ],
    "name:zho_x_preferred":[
        "\u5225\u5ed6\u4f50\u592b\u5361"
    ],
    "wof:name":"Byarozawka",
    "wof:placetype":"locality"
},
  "geometry": {"coordinates":[24.9374,53.8956],"type":"Point"}
}