{
  "type": "Feature",
  "properties": {
    "gn:admin1_code":"2.0",
    "gn:asciiname":"Zaloz'ye",
    "gn:country_code":"BY",
    "gn:dem":147,
    "gn:feature_class":"P",
    "gn:feature_code":"PPL",
    "gn:name":"Zaloz\u2019ye",
    "gn:population":0,
    "gn:timezone":"Europe/Minsk",
    "iso:country":"BY",
    "name:rus_x_preferred":[
        "\u0417\u0430\u043b\u043e\u0437\u044c\u0435"
    ],
    "name:und_x_variant":[
        "Zaloz\u2019ye",
        "Zalaz\u2019ye"
    ],
    "wof:name":"Zaloz'ye",
    "wof:placetype":"locality"
},
  "geometry": {"coordinates":[30.2119,53.229],"type":"Point"}
}