{
  "type": "Feature",
  "properties": {
    "gn:admin1_code":"3.0",
    "gn:asciiname":"Pykhovchitsy",
    "gn:country_code":"BY",
    "gn:dem":118,
    "gn:feature_class":"P",
    "gn:feature_code":"PPL",
    "gn:name":"Pykhovchitsy",
    "gn:population":0,
    "gn:timezone":"Europe/Minsk",
    "iso:country":"BY",
    "name:rus_x_preferred":[
        "\u041f\u044b\u0445\u043e\u0432\u0447\u0438\u0446\u044b"
    ],
    "wof:name":"Pykhovchitsy",
    "wof:placetype":"locality"
},
  "geometry": {"coordinates":[23.8843,53.3248],"type":"Point"}
}