{
  "type": "Feature",
  "properties": {
    "gn:admin1_code":"3.0",
    "gn:asciiname":"Bolotse-Klintsy",
    "gn:country_code":"BY",
    "gn:dem":159,
    "gn:feature_class":"P",
    "gn:feature_code":"PPL",
    "gn:name":"Bolotse-Klintsy",
    "gn:population":0,
    "gn:timezone":"Europe/Minsk",
    "iso:country":"BY",
    "name:rus_x_preferred":[
        "\u0411\u043e\u043b\u043e\u0446\u0435-\u041a\u043b\u0438\u043d\u0446\u044b"
    ],
    "name:und_x_variant":[
        "Bolotse"
    ],
    "wof:name":"Bolotse-Klintsy",
    "wof:placetype":"locality"
},
  "geometry": {"coordinates":[26.1559,53.6417],"type":"Point"}
}