{
  "type": "Feature",
  "properties": {
    "gn:admin1_code":"7.0",
    "gn:asciiname":"Ksty",
    "gn:country_code":"BY",
    "gn:dem":211,
    "gn:feature_class":"P",
    "gn:feature_code":"PPL",
    "gn:name":"Ksty",
    "gn:population":0,
    "gn:timezone":"Europe/Minsk",
    "iso:country":"BY",
    "name:rus_x_preferred":[
        "\u041a\u0441\u0442\u044b"
    ],
    "wof:name":"Ksty",
    "wof:placetype":"locality"
},
  "geometry": {"coordinates":[28.2466,55.2764],"type":"Point"}
}