{
  "type": "Feature",
  "properties": {
    "gn:admin1_code":"3.0",
    "gn:asciiname":"Nyesutychy",
    "gn:country_code":"BY",
    "gn:dem":190,
    "gn:feature_class":"P",
    "gn:feature_code":"PPL",
    "gn:name":"Nyesutychy",
    "gn:population":0,
    "gn:timezone":"Europe/Minsk",
    "iso:country":"BY",
    "name:bel_x_preferred":[
        "\u041d\u0435\u0441\u0443\u0442\u044b\u0447\u044b"
    ],
    "name:rus_x_preferred":[
        "\u041d\u0435\u0441\u0443\u0442\u044b\u0447\u0438"
    ],
    "name:und_x_variant":[
        "Nesutichi",
        "Nesutychi"
    ],
    "wof:name":"Nyesutychy",
    "wof:placetype":"locality"
},
  "geometry": {"coordinates":[25.9396,53.6429],"type":"Point"}
}