{
  "type": "Feature",
  "properties": {
    "gn:admin1_code":"1.0",
    "gn:asciiname":"Novinka",
    "gn:country_code":"BY",
    "gn:dem":141,
    "gn:feature_class":"P",
    "gn:feature_code":"PPL",
    "gn:name":"Novinka",
    "gn:population":0,
    "gn:timezone":"Europe/Minsk",
    "iso:country":"BY",
    "name:rus_x_preferred":[
        "\u041d\u043e\u0432\u0438\u043d\u043a\u0430"
    ],
    "wof:name":"Novinka",
    "wof:placetype":"locality"
},
  "geometry": {"coordinates":[25.4137,52.3564],"type":"Point"}
}