{
  "type": "Feature",
  "properties": {
    "gn:admin1_code":"7.0",
    "gn:asciiname":"Vyaren'ki",
    "gn:country_code":"BY",
    "gn:dem":213,
    "gn:feature_class":"P",
    "gn:feature_code":"PPL",
    "gn:name":"Vyaren\u2019ki",
    "gn:population":0,
    "gn:timezone":"Europe/Minsk",
    "iso:country":"BY",
    "name:bel_x_preferred":[
        "\u0412\u044f\u0440\u044d\u043d\u044c\u043a\u0456"
    ],
    "name:eng_x_preferred":[
        "Varen'ki"
    ],
    "name:rus_x_preferred":[
        "Veren\u2019ki"
    ],
    "name:rus_x_variant":[
        "\u0412\u0435\u0440\u0435\u043d\u044c\u043a\u0438"
    ],
    "name:und_x_variant":[
        "Wiere\u0144ki",
        "Varen\u2019ki",
        "Vyaren\u2019ki"
    ],
    "wof:name":"Vyaren'ki",
    "wof:placetype":"locality"
},
  "geometry": {"coordinates":[26.7461,54.9968],"type":"Point"}
}