{
  "type": "Feature",
  "properties": {
    "gn:admin1_code":"7.0",
    "gn:asciiname":"Sharagi",
    "gn:country_code":"BY",
    "gn:dem":141,
    "gn:feature_class":"P",
    "gn:feature_code":"PPL",
    "gn:name":"Sharagi",
    "gn:population":0,
    "gn:timezone":"Europe/Minsk",
    "iso:country":"BY",
    "name:rus_x_preferred":[
        "\u0428\u0430\u0440\u0430\u0433\u0438"
    ],
    "wof:name":"Sharagi",
    "wof:placetype":"locality"
},
  "geometry": {"coordinates":[28.2556,55.4139],"type":"Point"}
}