{
  "type": "Feature",
  "properties": {
    "gn:admin1_code":"3.0",
    "gn:asciiname":"Asatniki",
    "gn:country_code":"BY",
    "gn:dem":239,
    "gn:feature_class":"P",
    "gn:feature_code":"PPL",
    "gn:name":"Asatniki",
    "gn:population":0,
    "gn:timezone":"Europe/Minsk",
    "iso:country":"BY",
    "name:rus_x_preferred":[
        "\u0410\u0441\u0430\u0442\u043d\u0438\u043a\u0438"
    ],
    "wof:name":"Asatniki",
    "wof:placetype":"locality"
},
  "geometry": {"coordinates":[25.971,54.5352],"type":"Point"}
}