{
  "type": "Feature",
  "properties": {
    "gn:admin1_code":"6.0",
    "gn:asciiname":"Teplukhi",
    "gn:country_code":"BY",
    "gn:dem":151,
    "gn:feature_class":"P",
    "gn:feature_code":"PPL",
    "gn:name":"Teplukhi",
    "gn:population":0,
    "gn:timezone":"Europe/Minsk",
    "iso:country":"BY",
    "name:rus_x_preferred":[
        "\u0422\u0435\u043f\u043b\u0443\u0445\u0438"
    ],
    "name:und_x_variant":[
        "Teplukha"
    ],
    "wof:name":"Teplukhi",
    "wof:placetype":"locality"
},
  "geometry": {"coordinates":[28.6658,53.3434],"type":"Point"}
}