{
  "type": "Feature",
  "properties": {
    "gn:admin1_code":"7.0",
    "gn:asciiname":"Khorobrovo",
    "gn:country_code":"BY",
    "gn:dem":143,
    "gn:feature_class":"P",
    "gn:feature_code":"PPL",
    "gn:name":"Khorobrovo",
    "gn:population":0,
    "gn:timezone":"Europe/Minsk",
    "iso:country":"BY",
    "name:rus_x_preferred":[
        "\u0425\u043e\u0440\u043e\u0431\u0440\u043e\u0432\u043e"
    ],
    "wof:name":"Khorobrovo",
    "wof:placetype":"locality"
},
  "geometry": {"coordinates":[27.5402,55.6655],"type":"Point"}
}