{
  "type": "Feature",
  "properties": {
    "gn:admin1_code":"1.0",
    "gn:asciiname":"Glinishche",
    "gn:country_code":"BY",
    "gn:dem":153,
    "gn:feature_class":"P",
    "gn:feature_code":"PPL",
    "gn:name":"Glinishche",
    "gn:population":0,
    "gn:timezone":"Europe/Minsk",
    "iso:country":"BY",
    "name:rus_x_preferred":[
        "\u0413\u043b\u0438\u043d\u0438\u0449\u0435"
    ],
    "wof:name":"Glinishche",
    "wof:placetype":"locality"
},
  "geometry": {"coordinates":[25.7915,52.4798],"type":"Point"}
}