{
  "type": "Feature",
  "properties": {
    "gn:admin1_code":"1.0",
    "gn:asciiname":"Korochin",
    "gn:country_code":"BY",
    "gn:dem":144,
    "gn:feature_class":"P",
    "gn:feature_code":"PPL",
    "gn:name":"Korochin",
    "gn:population":0,
    "gn:timezone":"Europe/Minsk",
    "iso:country":"BY",
    "name:rus_x_preferred":[
        "\u041a\u043e\u0440\u043e\u0447\u0438\u043d"
    ],
    "name:und_x_variant":[
        "Korechin"
    ],
    "wof:name":"Korochin",
    "wof:placetype":"locality"
},
  "geometry": {"coordinates":[25.3405,52.5583],"type":"Point"}
}