{
  "type": "Feature",
  "properties": {
    "gn:admin1_code":"6.0",
    "gn:asciiname":"Zabolotnoye",
    "gn:country_code":"BY",
    "gn:dem":153,
    "gn:feature_class":"P",
    "gn:feature_code":"PPL",
    "gn:name":"Zabolotnoye",
    "gn:population":0,
    "gn:timezone":"Europe/Minsk",
    "iso:country":"BY",
    "name:rus_x_preferred":[
        "\u0417\u0430\u0431\u043e\u043b\u043e\u0442\u043d\u043e\u0435"
    ],
    "wof:name":"Zabolotnoye",
    "wof:placetype":"locality"
},
  "geometry": {"coordinates":[30.52,53.3654],"type":"Point"}
}