{
  "type": "Feature",
  "properties": {
    "gn:admin1_code":"5.0",
    "gn:asciiname":"Pal'chik",
    "gn:country_code":"BY",
    "gn:dem":166,
    "gn:feature_class":"P",
    "gn:feature_code":"PPL",
    "gn:name":"Pal\u2019chik",
    "gn:population":0,
    "gn:timezone":"Europe/Minsk",
    "iso:country":"BY",
    "name:rus_x_preferred":[
        "\u041f\u0430\u043b\u044c\u0447\u0438\u043a"
    ],
    "name:und_x_variant":[
        "Krasny Pal\u2019chik",
        "Krasnyy Pal\u2019chik",
        "Pal\u2019chik"
    ],
    "wof:name":"Pal'chik",
    "wof:placetype":"locality"
},
  "geometry": {"coordinates":[28.4244,53.6529],"type":"Point"}
}