{
  "type": "Feature",
  "properties": {
    "gn:admin1_code":"3.0",
    "gn:asciiname":"Bol'shaya Kolonaya",
    "gn:country_code":"BY",
    "gn:dem":168,
    "gn:feature_class":"P",
    "gn:feature_code":"PPL",
    "gn:name":"Bol\u2019shaya Kolonaya",
    "gn:population":0,
    "gn:timezone":"Europe/Minsk",
    "iso:country":"BY",
    "name:rus_x_preferred":[
        "\u0411\u043e\u043b\u044c\u0448\u0430\u044f \u041a\u043e\u043b\u043e\u043d\u0430\u044f"
    ],
    "name:und_x_variant":[
        "Bol\u2019shaya Kolonaya"
    ],
    "wof:name":"Bol'shaya Kolonaya",
    "wof:placetype":"locality"
},
  "geometry": {"coordinates":[24.2279,52.9417],"type":"Point"}
}