{
  "type": "Feature",
  "properties": {
    "gn:admin1_code":"2.0",
    "gn:asciiname":"Vetel'skaya",
    "gn:country_code":"BY",
    "gn:dem":117,
    "gn:feature_class":"P",
    "gn:feature_code":"PPL",
    "gn:name":"Vetel\u2019skaya",
    "gn:population":0,
    "gn:timezone":"Europe/Minsk",
    "iso:country":"BY",
    "name:rus_x_preferred":[
        "\u0412\u0435\u0442\u0435\u043b\u044c\u0441\u043a\u0430\u044f"
    ],
    "name:und_x_variant":[
        "Vetel\u2019skaya"
    ],
    "wof:name":"Vetel'skaya",
    "wof:placetype":"locality"
},
  "geometry": {"coordinates":[29.0201,52.2043],"type":"Point"}
}