{
  "type": "Feature",
  "properties": {
    "gn:admin1_code":"7.0",
    "gn:asciiname":"Mezhdurech'ye",
    "gn:country_code":"BY",
    "gn:dem":133,
    "gn:feature_class":"P",
    "gn:feature_code":"PPL",
    "gn:name":"Mezhdurech\u2019ye",
    "gn:population":0,
    "gn:timezone":"Europe/Minsk",
    "iso:country":"BY",
    "name:rus_x_preferred":[
        "\u041c\u0435\u0436\u0434\u0443\u0440\u0435\u0447\u044c\u0435"
    ],
    "name:und_x_variant":[
        "Mezhdurech\u2019ye"
    ],
    "wof:name":"Mezhdurech'ye",
    "wof:placetype":"locality"
},
  "geometry": {"coordinates":[27.6326,55.7528],"type":"Point"}
}