{
  "type": "Feature",
  "properties": {
    "gn:admin1_code":"5.0",
    "gn:asciiname":"Krilovichi",
    "gn:country_code":"BY",
    "gn:dem":218,
    "gn:feature_class":"P",
    "gn:feature_code":"PPL",
    "gn:name":"Krilovichi",
    "gn:population":0,
    "gn:timezone":"Europe/Minsk",
    "iso:country":"BY",
    "name:rus_x_preferred":[
        "\u041a\u0440\u0438\u043b\u043e\u0432\u0438\u0447\u0438"
    ],
    "wof:name":"Krilovichi",
    "wof:placetype":"locality"
},
  "geometry": {"coordinates":[27.125,53.7342],"type":"Point"}
}