{
  "type": "Feature",
  "properties": {
    "gn:admin1_code":"7.0",
    "gn:asciiname":"Adamishki",
    "gn:country_code":"BY",
    "gn:dem":162,
    "gn:feature_class":"P",
    "gn:feature_code":"PPL",
    "gn:name":"Adamishki",
    "gn:population":0,
    "gn:timezone":"Europe/Minsk",
    "iso:country":"BY",
    "name:rus_x_preferred":[
        "\u0410\u0434\u0430\u043c\u0438\u0448\u043a\u0438"
    ],
    "wof:name":"Adamishki",
    "wof:placetype":"locality"
},
  "geometry": {"coordinates":[27.011,55.8151],"type":"Point"}
}