{
  "type": "Feature",
  "properties": {
    "gn:admin1_code":"7.0",
    "gn:asciiname":"Dolgoye",
    "gn:country_code":"BY",
    "gn:dem":160,
    "gn:feature_class":"P",
    "gn:feature_code":"PPL",
    "gn:name":"Dolgoye",
    "gn:population":0,
    "gn:timezone":"Europe/Minsk",
    "iso:country":"BY",
    "name:rus_x_preferred":[
        "\u0414\u043e\u043b\u0433\u043e\u0435"
    ],
    "wof:name":"Dolgoye",
    "wof:placetype":"locality"
},
  "geometry": {"coordinates":[28.9549,54.9351],"type":"Point"}
}