{
  "type": "Feature",
  "properties": {
    "gn:admin1_code":"1.0",
    "gn:asciiname":"Oleshkovichi",
    "gn:country_code":"BY",
    "gn:dem":143,
    "gn:feature_class":"P",
    "gn:feature_code":"PPL",
    "gn:name":"Oleshkovichi",
    "gn:population":0,
    "gn:timezone":"Europe/Minsk",
    "iso:country":"BY",
    "name:rus_x_preferred":[
        "\u041e\u043b\u0435\u0448\u043a\u043e\u0432\u0438\u0447\u0438"
    ],
    "name:und_x_variant":[
        "Oleshkoviche",
        "Oleshkovichi"
    ],
    "wof:name":"Oleshkovichi",
    "wof:placetype":"locality"
},
  "geometry": {"coordinates":[23.7384,52.2662],"type":"Point"}
}