{
  "type": "Feature",
  "properties": {
    "gn:admin1_code":"1.0",
    "gn:asciiname":"Volovel'",
    "gn:country_code":"BY",
    "gn:dem":150,
    "gn:feature_class":"P",
    "gn:feature_code":"PPL",
    "gn:name":"Volovel\u2019",
    "gn:population":0,
    "gn:timezone":"Europe/Minsk",
    "iso:country":"BY",
    "name:eng_x_preferred":[
        "Volovel'"
    ],
    "name:rus_x_preferred":[
        "\u0412\u043e\u043b\u043e\u0432\u0435\u043b\u044c"
    ],
    "name:rus_x_variant":[
        "Volovel\u2019"
    ],
    "name:und_x_variant":[
        "Wo\u0142owel"
    ],
    "wof:name":"Volovel'",
    "wof:placetype":"locality"
},
  "geometry": {"coordinates":[24.9654,52.1378],"type":"Point"}
}