{
  "type": "Feature",
  "properties": {
    "gn:admin1_code":"2.0",
    "gn:asciiname":"Kurytsichy",
    "gn:country_code":"BY",
    "gn:dem":127,
    "gn:feature_class":"P",
    "gn:feature_code":"PPL",
    "gn:name":"Kurytsichy",
    "gn:population":0,
    "gn:timezone":"Europe/Minsk",
    "iso:country":"BY",
    "name:bel_x_preferred":[
        "\u041a\u0443\u0440\u044b\u0446\u0456\u0447\u044b"
    ],
    "name:eng_x_preferred":[
        "Kuritichi"
    ],
    "name:rus_x_preferred":[
        "\u041a\u0443\u0440\u0438\u0442\u0438\u0447\u0438"
    ],
    "name:und_x_variant":[
        "Krutichi",
        "Kurytsichy"
    ],
    "wof:name":"Kurytsichy",
    "wof:placetype":"locality"
},
  "geometry": {"coordinates":[28.6123,52.2796],"type":"Point"}
}