{
  "type": "Feature",
  "properties": {
    "gn:admin1_code":"1.0",
    "gn:asciiname":"Yakimovichi",
    "gn:country_code":"BY",
    "gn:dem":184,
    "gn:feature_class":"P",
    "gn:feature_code":"PPL",
    "gn:name":"Yakimovichi",
    "gn:population":0,
    "gn:timezone":"Europe/Minsk",
    "iso:country":"BY",
    "name:rus_x_preferred":[
        "\u042f\u043a\u0438\u043c\u043e\u0432\u0438\u0447\u0438"
    ],
    "wof:name":"Yakimovichi",
    "wof:placetype":"locality"
},
  "geometry": {"coordinates":[26.1437,53.1682],"type":"Point"}
}