{
  "type": "Feature",
  "properties": {
    "gn:admin1_code":"1.0",
    "gn:asciiname":"Ostrov",
    "gn:country_code":"BY",
    "gn:dem":135,
    "gn:feature_class":"P",
    "gn:feature_code":"PPL",
    "gn:name":"Ostrov",
    "gn:population":0,
    "gn:timezone":"Europe/Minsk",
    "iso:country":"BY",
    "name:rus_x_preferred":[
        "\u041e\u0441\u0442\u0440\u043e\u0432"
    ],
    "name:und_x_variant":[
        "Ostr\u00f3w",
        "Ostruv",
        "Ostrov"
    ],
    "wof:name":"Ostrov",
    "wof:placetype":"locality"
},
  "geometry": {"coordinates":[26.2221,51.9177],"type":"Point"}
}