{
  "type": "Feature",
  "properties": {
    "gn:admin1_code":"2.0",
    "gn:asciiname":"Sosnovyy",
    "gn:country_code":"BY",
    "gn:dem":169,
    "gn:feature_class":"P",
    "gn:feature_code":"PPL",
    "gn:name":"Sosnovyy",
    "gn:population":0,
    "gn:timezone":"Europe/Minsk",
    "iso:country":"BY",
    "name:rus_x_preferred":[
        "\u041f\u043e\u0441\u0451\u043b\u043e\u043a \u0421\u043e\u0441\u043d\u043e\u0432\u044b\u0439"
    ],
    "name:und_x_variant":[
        "Pos\u00eblok Sosnovyy",
        "Sosnovyy"
    ],
    "wof:name":"Sosnovyy",
    "wof:placetype":"locality"
},
  "geometry": {"coordinates":[29.1722,52.0024],"type":"Point"}
}