{
  "type": "Feature",
  "properties": {
    "gn:admin1_code":"1.0",
    "gn:asciiname":"Chepeli",
    "gn:country_code":"BY",
    "gn:dem":164,
    "gn:feature_class":"P",
    "gn:feature_code":"PPL",
    "gn:name":"Chepeli",
    "gn:population":0,
    "gn:timezone":"Europe/Minsk",
    "iso:country":"BY",
    "name:rus_x_preferred":[
        "\u0427\u0435\u043f\u0435\u043b\u0438"
    ],
    "wof:name":"Chepeli",
    "wof:placetype":"locality"
},
  "geometry": {"coordinates":[23.4426,52.4054],"type":"Point"}
}