{
  "type": "Feature",
  "properties": {
    "gn:admin1_code":"3.0",
    "gn:asciiname":"Golynka",
    "gn:country_code":"BY",
    "gn:dem":144,
    "gn:feature_class":"P",
    "gn:feature_code":"PPL",
    "gn:name":"Golynka",
    "gn:population":0,
    "gn:timezone":"Europe/Minsk",
    "iso:country":"BY",
    "name:rus_x_preferred":[
        "\u0413\u043e\u043b\u044b\u043d\u043a\u0430"
    ],
    "wof:name":"Golynka",
    "wof:placetype":"locality"
},
  "geometry": {"coordinates":[24.3556,53.1178],"type":"Point"}
}