{
  "type": "Feature",
  "properties": {
    "gn:country":"BY",
    "gn:fcode":"PPLA2",
    "gn:pop":10552,
    "iso:country":"BY",
    "name:bel_x_preferred":[
        "\u041f\u0435\u0442\u0440\u044b\u043a\u0430\u045e"
    ],
    "name:bul_x_preferred":[
        "\u041f\u0435\u0442\u0440\u0438\u043a\u043e\u0432"
    ],
    "name:chi_x_preferred":[
        "\u5f7c\u5f97\u91cc\u79d1\u592b"
    ],
    "name:dut_x_preferred":[
        "Pyetrykaw"
    ],
    "name:eng_x_preferred":[
        "Pyetrykaw"
    ],
    "name:est_x_preferred":[
        "Pietryka\u016d"
    ],
    "name:fin_x_preferred":[
        "Petrykau"
    ],
    "name:fre_x_preferred":[
        "Petrykaw"
    ],
    "name:ger_x_preferred":[
        "Petrykau"
    ],
    "name:heb_x_preferred":[
        "\u05e4\u05d8\u05e8\u05d9\u05e7\u05d5\u05d1"
    ],
    "name:hsb_x_preferred":[
        "Petrykaw"
    ],
    "name:lav_x_preferred":[
        "Pjetrikava"
    ],
    "name:lit_x_preferred":[
        "Petrykavas"
    ],
    "name:pol_x_preferred":[
        "Petryk\u00f3w"
    ],
    "name:rus_x_preferred":[
        "\u041f\u0435\u0442\u0440\u0438\u043a\u043e\u0432"
    ],
    "name:srp_x_preferred":[
        "\u041f\u0435\u0442\u0440\u0438\u043a\u0430\u0432"
    ],
    "name:swe_x_preferred":[
        "Petryka\u016d"
    ],
    "name:tat_x_preferred":[
        "\u041f\u0435\u0442\u0440\u044b\u043a\u0430\u0443"
    ],
    "name:ukr_x_preferred":[
        "\u041f\u0435\u0442\u0440\u0438\u043a\u043e\u0432"
    ],
    "name:unk_x_variant":[
        "Petrikov"
    ],
    "qs:name":"Pyetrykaw",
    "qs:photos_9r":0,
    "qs:photos_sr":0,
    "qs:pop_sr":"6",
    "wd:population":10408,
    "wd:wordcount":561,
    "wof:name":"Pyetrykaw",
    "wof:placetype":"locality",
    "wof:population":10408
},
  "geometry": {"coordinates":[28.4921,52.1289],"type":"Point"}
}