{
  "type": "Feature",
  "properties": {
    "gn:admin1_code":"6.0",
    "gn:asciiname":"Rog",
    "gn:country_code":"BY",
    "gn:dem":152,
    "gn:feature_class":"P",
    "gn:feature_code":"PPL",
    "gn:name":"Rog",
    "gn:population":0,
    "gn:timezone":"Europe/Minsk",
    "iso:country":"BY",
    "name:fas_x_preferred":[
        "\u0628\u06cc\u0645\u0627\u0631\u06cc"
    ],
    "name:new_x_preferred":[
        "\u0930\u094b\u0917"
    ],
    "name:rus_x_preferred":[
        "\u0420\u043e\u0433"
    ],
    "wof:name":"Rog",
    "wof:placetype":"locality"
},
  "geometry": {"coordinates":[29.6282,53.1832],"type":"Point"}
}