{
  "type": "Feature",
  "properties": {
    "gn:admin1_code":"5.0",
    "gn:asciiname":"Dubovruch'ye",
    "gn:country_code":"BY",
    "gn:dem":178,
    "gn:feature_class":"P",
    "gn:feature_code":"PPL",
    "gn:name":"Dubovruch\u2019ye",
    "gn:population":0,
    "gn:timezone":"Europe/Minsk",
    "iso:country":"BY",
    "name:rus_x_preferred":[
        "\u0414\u0443\u0431\u043e\u0432\u0440\u0443\u0447\u044c\u0435"
    ],
    "name:und_x_variant":[
        "Dubovruch\u2019ye"
    ],
    "wof:name":"Dubovruch'ye",
    "wof:placetype":"locality"
},
  "geometry": {"coordinates":[28.6799,53.8812],"type":"Point"}
}