{
  "type": "Feature",
  "properties": {
    "gn:admin1_code":"7.0",
    "gn:asciiname":"Pukhovka",
    "gn:country_code":"BY",
    "gn:dem":178,
    "gn:feature_class":"P",
    "gn:feature_code":"PPL",
    "gn:name":"Pukhovka",
    "gn:population":0,
    "gn:timezone":"Europe/Minsk",
    "iso:country":"BY",
    "name:rus_x_preferred":[
        "\u041f\u0443\u0445\u043e\u0432\u043a\u0430"
    ],
    "name:und_x_variant":[
        "Pukhuvka",
        "Puchowka",
        "Pukhovka"
    ],
    "wof:name":"Pukhovka",
    "wof:placetype":"locality"
},
  "geometry": {"coordinates":[27.0264,55.0924],"type":"Point"}
}