{
  "type": "Feature",
  "properties": {
    "gn:admin1_code":"7.0",
    "gn:asciiname":"Belishki",
    "gn:country_code":"BY",
    "gn:dem":187,
    "gn:feature_class":"P",
    "gn:feature_code":"PPL",
    "gn:name":"Belishki",
    "gn:population":0,
    "gn:timezone":"Europe/Minsk",
    "iso:country":"BY",
    "name:rus_x_preferred":[
        "\u0411\u0435\u043b\u0438\u0448\u043a\u0438"
    ],
    "wof:name":"Belishki",
    "wof:placetype":"locality"
},
  "geometry": {"coordinates":[26.3124,54.9956],"type":"Point"}
}