{
  "type": "Feature",
  "properties": {
    "gn:admin1_code":"5.0",
    "gn:asciiname":"Khotovka",
    "gn:country_code":"BY",
    "gn:dem":200,
    "gn:feature_class":"P",
    "gn:feature_code":"PPL",
    "gn:name":"Khotovka",
    "gn:population":0,
    "gn:timezone":"Europe/Minsk",
    "iso:country":"BY",
    "name:rus_x_preferred":[
        "\u0425\u043e\u0442\u043e\u0432\u043a\u0430"
    ],
    "wof:name":"Khotovka",
    "wof:placetype":"locality"
},
  "geometry": {"coordinates":[26.6606,53.7345],"type":"Point"}
}