{
  "type": "Feature",
  "properties": {
    "gn:admin1_code":"0.0",
    "gn:asciiname":"Burdykovshchina",
    "gn:country_code":"BY",
    "gn:dem":201,
    "gn:feature_class":"P",
    "gn:feature_code":"PPL",
    "gn:name":"Burdykovshchina",
    "gn:population":0,
    "gn:timezone":"Europe/Minsk",
    "iso:country":"BY",
    "name:bel_x_preferred":[
        "Burdykovshchina"
    ],
    "wof:name":"Burdykovshchina",
    "wof:placetype":"locality"
},
  "geometry": {"coordinates":[25.86667000000001,53.35],"type":"Point"}
}