{
  "type": "Feature",
  "properties": {
    "gn:admin1_code":"2.0",
    "gn:asciiname":"Smelyy",
    "gn:country_code":"BY",
    "gn:dem":130,
    "gn:feature_class":"P",
    "gn:feature_code":"PPL",
    "gn:name":"Smelyy",
    "gn:population":0,
    "gn:timezone":"Europe/Minsk",
    "iso:country":"BY",
    "name:rus_x_preferred":[
        "\u0421\u043c\u0435\u043b\u044b\u0439"
    ],
    "wof:name":"Smelyy",
    "wof:placetype":"locality"
},
  "geometry": {"coordinates":[30.603,52.0708],"type":"Point"}
}