{
  "type": "Feature",
  "properties": {
    "gn:admin1_code":"5.0",
    "gn:asciiname":"Zhuravy",
    "gn:country_code":"BY",
    "gn:dem":176,
    "gn:feature_class":"P",
    "gn:feature_code":"PPL",
    "gn:name":"Zhuravy",
    "gn:population":0,
    "gn:timezone":"Europe/Minsk",
    "iso:country":"BY",
    "name:rus_x_preferred":[
        "\u0416\u0443\u0440\u0430\u0432\u044b"
    ],
    "wof:name":"Zhuravy",
    "wof:placetype":"locality"
},
  "geometry": {"coordinates":[29.3128,54.4592],"type":"Point"}
}