{
  "type": "Feature",
  "properties": {
    "gn:admin1_code":"7.0",
    "gn:asciiname":"Moiseyevo",
    "gn:country_code":"BY",
    "gn:dem":160,
    "gn:feature_class":"P",
    "gn:feature_code":"PPL",
    "gn:name":"Moiseyevo",
    "gn:population":0,
    "gn:timezone":"Europe/Minsk",
    "iso:country":"BY",
    "name:rus_x_preferred":[
        "\u041c\u043e\u0438\u0441\u0435\u0435\u0432\u043e"
    ],
    "wof:name":"Moiseyevo",
    "wof:placetype":"locality"
},
  "geometry": {"coordinates":[29.6754,55.7432],"type":"Point"}
}