{
  "type": "Feature",
  "properties": {
    "gn:country":"BY",
    "gn:fcode":"PPL",
    "gn:pop":188,
    "iso:country":"BY",
    "name:rus_x_preferred":[
        "\u0421\u043b\u043e\u0431\u043e\u0434\u0449\u0438\u043d\u0430"
    ],
    "qs:name":"Slobodshchina",
    "qs:photos_9r":0,
    "qs:photos_sr":0,
    "qs:pop_sr":"1",
    "wof:name":"Slobodshchina",
    "wof:placetype":"locality",
    "wof:population":188
},
  "geometry": {"coordinates":[27.7903,53.9903],"type":"Point"}
}