{
  "type": "Feature",
  "properties": {
    "gn:admin1_code":"5.0",
    "gn:asciiname":"Navasyolki",
    "gn:country_code":"BY",
    "gn:dem":170,
    "gn:feature_class":"P",
    "gn:feature_code":"PPL",
    "gn:name":"Navasyolki",
    "gn:population":0,
    "gn:timezone":"Europe/Minsk",
    "iso:country":"BY",
    "name:bel_x_preferred":[
        "\u041d\u0430\u0432\u0430\u0441\u0451\u043b\u043a\u0456"
    ],
    "name:rus_x_preferred":[
        "Novos\u00eblki"
    ],
    "wof:name":"Navasyolki",
    "wof:placetype":"locality"
},
  "geometry": {"coordinates":[29.0599,53.848],"type":"Point"}
}