{
  "type": "Feature",
  "properties": {
    "gn:admin1_code":"1.0",
    "gn:asciiname":"Skoki",
    "gn:country_code":"BY",
    "gn:dem":133,
    "gn:feature_class":"P",
    "gn:feature_code":"PPL",
    "gn:name":"Skoki",
    "gn:population":1000,
    "gn:timezone":"Europe/Minsk",
    "iso:country":"BY",
    "name:bel_x_preferred":[
        "\u0421\u043a\u043e\u043a\u0456"
    ],
    "name:rus_x_preferred":[
        "\u0421\u043a\u043e\u043a\u0438"
    ],
    "wof:name":"Skoki",
    "wof:placetype":"locality",
    "wof:population":1000
},
  "geometry": {"coordinates":[23.6329,52.15519000000001],"type":"Point"}
}