{
  "type": "Feature",
  "properties": {
    "gn:admin1_code":"5.0",
    "gn:asciiname":"Logoviny",
    "gn:country_code":"BY",
    "gn:dem":175,
    "gn:feature_class":"P",
    "gn:feature_code":"PPL",
    "gn:name":"Logoviny",
    "gn:population":0,
    "gn:timezone":"Europe/Minsk",
    "iso:country":"BY",
    "name:rus_x_preferred":[
        "\u041b\u043e\u0433\u043e\u0432\u0438\u043d\u044b"
    ],
    "wof:name":"Logoviny",
    "wof:placetype":"locality"
},
  "geometry": {"coordinates":[26.7596,54.9089],"type":"Point"}
}