{
  "type": "Feature",
  "properties": {
    "gn:admin1_code":"7.0",
    "gn:asciiname":"Mineyty",
    "gn:country_code":"BY",
    "gn:dem":168,
    "gn:feature_class":"P",
    "gn:feature_code":"PPL",
    "gn:name":"Mineyty",
    "gn:population":0,
    "gn:timezone":"Europe/Minsk",
    "iso:country":"BY",
    "name:rus_x_preferred":[
        "\u041c\u0438\u043d\u0435\u0439\u0442\u044b"
    ],
    "wof:name":"Mineyty",
    "wof:placetype":"locality"
},
  "geometry": {"coordinates":[27.4352,55.7223],"type":"Point"}
}