{
  "type": "Feature",
  "properties": {
    "gn:admin1_code":"5.0",
    "gn:asciiname":"Zagor'ye",
    "gn:country_code":"BY",
    "gn:dem":211,
    "gn:feature_class":"P",
    "gn:feature_code":"PPL",
    "gn:name":"Zagor\u2019ye",
    "gn:population":0,
    "gn:timezone":"Europe/Minsk",
    "iso:country":"BY",
    "name:rus_x_preferred":[
        "\u0417\u0430\u0433\u043e\u0440\u044c\u0435"
    ],
    "name:und_x_variant":[
        "Zagor\u2019ye"
    ],
    "wof:name":"Zagor'ye",
    "wof:placetype":"locality"
},
  "geometry": {"coordinates":[27.8075,54.4646],"type":"Point"}
}