{
  "type": "Feature",
  "properties": {
    "gn:admin1_code":"6.0",
    "gn:asciiname":"Dowhaye",
    "gn:country_code":"BY",
    "gn:dem":157,
    "gn:feature_class":"P",
    "gn:feature_code":"PPL",
    "gn:name":"Dowhaye",
    "gn:population":0,
    "gn:timezone":"Europe/Minsk",
    "iso:country":"BY",
    "name:bel_x_preferred":[
        "\u0414\u043e\u045e\u0433\u0430\u0435"
    ],
    "name:eng_x_preferred":[
        "Dolgoye"
    ],
    "name:rus_x_preferred":[
        "\u0414\u043e\u043b\u0433\u043e\u0435"
    ],
    "name:und_x_variant":[
        "Dolgoye",
        "Dowhaye"
    ],
    "wof:name":"Dowhaye",
    "wof:placetype":"locality"
},
  "geometry": {"coordinates":[29.678,53.597],"type":"Point"}
}