{
  "type": "Feature",
  "properties": {
    "gn:admin1_code":"6.0",
    "gn:asciiname":"Chuch'ye",
    "gn:country_code":"BY",
    "gn:dem":140,
    "gn:feature_class":"P",
    "gn:feature_code":"PPL",
    "gn:name":"Chuch\u2019ye",
    "gn:population":0,
    "gn:timezone":"Europe/Minsk",
    "iso:country":"BY",
    "name:rus_x_preferred":[
        "\u0427\u0443\u0447\u044c\u0435"
    ],
    "name:und_x_variant":[
        "Chuch\u2019ye",
        "Chuch\u2019ya"
    ],
    "wof:name":"Chuch'ye",
    "wof:placetype":"locality"
},
  "geometry": {"coordinates":[29.0118,53.3599],"type":"Point"}
}