{
  "type": "Feature",
  "properties": {
    "gn:admin1_code":"3.0",
    "gn:asciiname":"Mezhany",
    "gn:country_code":"BY",
    "gn:dem":175,
    "gn:feature_class":"P",
    "gn:feature_code":"PPL",
    "gn:name":"Mezhany",
    "gn:population":0,
    "gn:timezone":"Europe/Minsk",
    "iso:country":"BY",
    "name:rus_x_preferred":[
        "\u041c\u0435\u0436\u0430\u043d\u044b"
    ],
    "name:und_x_variant":[
        "Mizhany"
    ],
    "wof:name":"Mezhany",
    "wof:placetype":"locality"
},
  "geometry": {"coordinates":[26.055,54.551],"type":"Point"}
}