{
  "type": "Feature",
  "properties": {
    "gn:admin1_code":"7.0",
    "gn:asciiname":"Osinovik",
    "gn:country_code":"BY",
    "gn:dem":179,
    "gn:feature_class":"P",
    "gn:feature_code":"PPL",
    "gn:name":"Osinovik",
    "gn:population":0,
    "gn:timezone":"Europe/Minsk",
    "iso:country":"BY",
    "name:rus_x_preferred":[
        "\u041e\u0441\u0438\u043d\u043e\u0432\u0438\u043a"
    ],
    "wof:name":"Osinovik",
    "wof:placetype":"locality"
},
  "geometry": {"coordinates":[27.9405,54.7629],"type":"Point"}
}