{
  "type": "Feature",
  "properties": {
    "gn:admin1_code":"5.0",
    "gn:asciiname":"Malaya Ganuta",
    "gn:country_code":"BY",
    "gn:dem":170,
    "gn:feature_class":"P",
    "gn:feature_code":"PPL",
    "gn:name":"Malaya Ganuta",
    "gn:population":0,
    "gn:timezone":"Europe/Minsk",
    "iso:country":"BY",
    "name:rus_x_preferred":[
        "\u041c\u0430\u043b\u0430\u044f \u0413\u0430\u043d\u0443\u0442\u0430"
    ],
    "wof:name":"Malaya Ganuta",
    "wof:placetype":"locality"
},
  "geometry": {"coordinates":[28.7192,53.7109],"type":"Point"}
}