{
  "type": "Feature",
  "properties": {
    "gn:admin1_code":"3.0",
    "gn:asciiname":"Litavortsy",
    "gn:country_code":"BY",
    "gn:dem":171,
    "gn:feature_class":"P",
    "gn:feature_code":"PPL",
    "gn:name":"Litavortsy",
    "gn:population":0,
    "gn:timezone":"Europe/Minsk",
    "iso:country":"BY",
    "name:bel_x_preferred":[
        "Litavartsy"
    ],
    "name:bel_x_variant":[
        "\u041b\u0456\u0442\u0430\u0432\u0430\u0440\u0446\u044b"
    ],
    "name:rus_x_preferred":[
        "\u041b\u0438\u0442\u0430\u0432\u043e\u0440\u0446\u044b"
    ],
    "wof:name":"Litavortsy",
    "wof:placetype":"locality"
},
  "geometry": {"coordinates":[25.5344,53.4321],"type":"Point"}
}