{
  "type": "Feature",
  "properties": {
    "gn:admin1_code":"7.0",
    "gn:asciiname":"Pashen'ki",
    "gn:country_code":"BY",
    "gn:dem":126,
    "gn:feature_class":"P",
    "gn:feature_code":"PPL",
    "gn:name":"Pashen\u2019ki",
    "gn:population":0,
    "gn:timezone":"Europe/Minsk",
    "iso:country":"BY",
    "name:rus_x_preferred":[
        "\u041f\u0430\u0448\u0435\u043d\u044c\u043a\u0438"
    ],
    "name:und_x_variant":[
        "Pashen\u2019ki"
    ],
    "wof:name":"Pashen'ki",
    "wof:placetype":"locality"
},
  "geometry": {"coordinates":[27.9246,55.8652],"type":"Point"}
}