{
  "type": "Feature",
  "properties": {
    "gn:admin1_code":"7.0",
    "gn:asciiname":"Bystromovtsy",
    "gn:country_code":"BY",
    "gn:dem":137,
    "gn:feature_class":"P",
    "gn:feature_code":"PPL",
    "gn:name":"Bystromovtsy",
    "gn:population":0,
    "gn:timezone":"Europe/Minsk",
    "iso:country":"BY",
    "name:rus_x_preferred":[
        "\u0411\u044b\u0441\u0442\u0440\u043e\u043c\u043e\u0432\u0446\u044b"
    ],
    "name:und_x_variant":[
        "Bystromovtse",
        "Bystromovtsy"
    ],
    "wof:name":"Bystromovtsy",
    "wof:placetype":"locality"
},
  "geometry": {"coordinates":[27.1829,55.764],"type":"Point"}
}