{
  "type": "Feature",
  "properties": {
    "gn:admin1_code":"3.0",
    "gn:asciiname":"Kragli Bol'shiye",
    "gn:country_code":"BY",
    "gn:dem":140,
    "gn:feature_class":"P",
    "gn:feature_code":"PPL",
    "gn:name":"Kragli Bol\u2019shiye",
    "gn:population":0,
    "gn:timezone":"Europe/Minsk",
    "iso:country":"BY",
    "name:rus_x_preferred":[
        "\u041a\u0440\u0430\u0433\u043b\u0438 \u0411\u043e\u043b\u044c\u0448\u0438\u0435"
    ],
    "name:und_x_variant":[
        "Kragli Bol\u2019shiye",
        "Bol\u2019shiye Kragli"
    ],
    "wof:name":"Kragli Bol'shiye",
    "wof:placetype":"locality"
},
  "geometry": {"coordinates":[25.3533,53.54600000000001],"type":"Point"}
}