{
  "type": "Feature",
  "properties": {
    "gn:admin1_code":"5.0",
    "gn:asciiname":"Damanavichy",
    "gn:country_code":"BY",
    "gn:dem":138,
    "gn:feature_class":"P",
    "gn:feature_code":"PPL",
    "gn:name":"Damanavichy",
    "gn:population":0,
    "gn:timezone":"Europe/Minsk",
    "iso:country":"BY",
    "name:bel_x_preferred":[
        "\u0414\u0430\u043c\u0430\u043d\u0430\u0432\u0456\u0447\u044b"
    ],
    "name:und_x_variant":[
        "Domanovichi"
    ],
    "wof:name":"Damanavichy",
    "wof:placetype":"locality"
},
  "geometry": {"coordinates":[27.7719,52.5203],"type":"Point"}
}