{
  "type": "Feature",
  "properties": {
    "gn:admin1_code":"2.0",
    "gn:asciiname":"Luginichi",
    "gn:country_code":"BY",
    "gn:dem":135,
    "gn:feature_class":"P",
    "gn:feature_code":"PPL",
    "gn:name":"Luginichi",
    "gn:population":0,
    "gn:timezone":"Europe/Minsk",
    "iso:country":"BY",
    "name:rus_x_preferred":[
        "\u041b\u0443\u0433\u0438\u043d\u0438\u0447\u0438"
    ],
    "wof:name":"Luginichi",
    "wof:placetype":"locality"
},
  "geometry": {"coordinates":[30.7628,52.7241],"type":"Point"}
}