{
  "type": "Feature",
  "properties": {
    "gn:admin1_code":"3.0",
    "gn:asciiname":"Mishkeniki",
    "gn:country_code":"BY",
    "gn:dem":219,
    "gn:feature_class":"P",
    "gn:feature_code":"PPL",
    "gn:name":"Mishkeniki",
    "gn:population":0,
    "gn:timezone":"Europe/Minsk",
    "iso:country":"BY",
    "name:rus_x_preferred":[
        "\u041c\u0438\u0448\u043a\u0435\u043d\u0438\u043a\u0438"
    ],
    "wof:name":"Mishkeniki",
    "wof:placetype":"locality"
},
  "geometry": {"coordinates":[23.7193,53.5133],"type":"Point"}
}