{
  "type": "Feature",
  "properties": {
    "gn:admin1_code":"6.0",
    "gn:asciiname":"Zavidovka",
    "gn:country_code":"BY",
    "gn:dem":196,
    "gn:feature_class":"P",
    "gn:feature_code":"PPL",
    "gn:name":"Zavidovka",
    "gn:population":0,
    "gn:timezone":"Europe/Minsk",
    "iso:country":"BY",
    "name:rus_x_preferred":[
        "\u0417\u0430\u0432\u0438\u0434\u043e\u0432\u043a\u0430"
    ],
    "wof:name":"Zavidovka",
    "wof:placetype":"locality"
},
  "geometry": {"coordinates":[32.2967,53.578],"type":"Point"}
}