{
  "type": "Feature",
  "properties": {
    "gn:admin1_code":"1.0",
    "gn:asciiname":"Yagolki",
    "gn:country_code":"BY",
    "gn:dem":139,
    "gn:feature_class":"P",
    "gn:feature_code":"PPL",
    "gn:name":"Yagolki",
    "gn:population":0,
    "gn:timezone":"Europe/Minsk",
    "iso:country":"BY",
    "name:rus_x_preferred":[
        "\u042f\u0433\u043e\u043b\u043a\u0438"
    ],
    "wof:name":"Yagolki",
    "wof:placetype":"locality"
},
  "geometry": {"coordinates":[24.2789,52.1535],"type":"Point"}
}