{
  "type": "Feature",
  "properties": {
    "gn:admin1_code":"1.0",
    "gn:asciiname":"Semenovtsy",
    "gn:country_code":"BY",
    "gn:dem":142,
    "gn:feature_class":"P",
    "gn:feature_code":"PPL",
    "gn:name":"Sem\u00ebnovtsy",
    "gn:population":0,
    "gn:timezone":"Europe/Minsk",
    "iso:country":"BY",
    "name:rus_x_preferred":[
        "\u0421\u0435\u043c\u0451\u043d\u043e\u0432\u0446\u044b"
    ],
    "name:und_x_variant":[
        "Sem\u00ebnovtsy"
    ],
    "wof:name":"Semenovtsy",
    "wof:placetype":"locality"
},
  "geometry": {"coordinates":[24.0378,52.2544],"type":"Point"}
}