{
  "type": "Feature",
  "properties": {
    "gn:admin1_code":"3.0",
    "gn:asciiname":"Kovantsy",
    "gn:country_code":"BY",
    "gn:dem":178,
    "gn:feature_class":"P",
    "gn:feature_code":"PPL",
    "gn:name":"Kovantsy",
    "gn:population":0,
    "gn:timezone":"Europe/Minsk",
    "iso:country":"BY",
    "name:rus_x_preferred":[
        "\u041a\u043e\u0432\u0430\u043d\u0446\u044b"
    ],
    "wof:name":"Kovantsy",
    "wof:placetype":"locality"
},
  "geometry": {"coordinates":[25.336,54.1995],"type":"Point"}
}