{
  "type": "Feature",
  "properties": {
    "gn:admin1_code":"6.0",
    "gn:asciiname":"Lozovka",
    "gn:country_code":"BY",
    "gn:dem":170,
    "gn:feature_class":"P",
    "gn:feature_code":"PPL",
    "gn:name":"Lozovka",
    "gn:population":0,
    "gn:timezone":"Europe/Minsk",
    "iso:country":"BY",
    "name:rus_x_preferred":[
        "\u041b\u043e\u0437\u043e\u0432\u043a\u0430"
    ],
    "wof:name":"Lozovka",
    "wof:placetype":"locality"
},
  "geometry": {"coordinates":[32.4822,53.4327],"type":"Point"}
}