{
  "type": "Feature",
  "properties": {
    "gn:admin1_code":"7.0",
    "gn:asciiname":"Beseda",
    "gn:country_code":"BY",
    "gn:dem":182,
    "gn:feature_class":"P",
    "gn:feature_code":"PPL",
    "gn:name":"Beseda",
    "gn:population":0,
    "gn:timezone":"Europe/Minsk",
    "iso:country":"BY",
    "name:rus_x_preferred":[
        "\u0411\u0435\u0441\u0435\u0434\u0430"
    ],
    "wof:name":"Beseda",
    "wof:placetype":"locality"
},
  "geometry": {"coordinates":[28.3322,54.8949],"type":"Point"}
}