{
  "type": "Feature",
  "properties": {
    "gn:admin1_code":"5.0",
    "gn:asciiname":"Golyshovo",
    "gn:country_code":"BY",
    "gn:dem":303,
    "gn:feature_class":"P",
    "gn:feature_code":"PPL",
    "gn:name":"Golyshovo",
    "gn:population":0,
    "gn:timezone":"Europe/Minsk",
    "iso:country":"BY",
    "name:rus_x_preferred":[
        "\u0413\u043e\u043b\u044b\u0448\u043e\u0432\u043e"
    ],
    "name:und_x_variant":[
        "Galyshevo",
        "Golyshevo"
    ],
    "wof:name":"Golyshovo",
    "wof:placetype":"locality"
},
  "geometry": {"coordinates":[27.1275,53.8544],"type":"Point"}
}