{
  "type": "Feature",
  "properties": {
    "gn:admin1_code":"7.0",
    "gn:asciiname":"Gorovatki",
    "gn:country_code":"BY",
    "gn:dem":119,
    "gn:feature_class":"P",
    "gn:feature_code":"PPL",
    "gn:name":"Gorovatki",
    "gn:population":0,
    "gn:timezone":"Europe/Minsk",
    "iso:country":"BY",
    "name:rus_x_preferred":[
        "\u0413\u043e\u0440\u043e\u0432\u0430\u0442\u043a\u0438"
    ],
    "wof:name":"Gorovatki",
    "wof:placetype":"locality"
},
  "geometry": {"coordinates":[28.0759,55.8832],"type":"Point"}
}