{
  "type": "Feature",
  "properties": {
    "gn:admin1_code":"1.0",
    "gn:asciiname":"Krywlyany",
    "gn:country_code":"BY",
    "gn:dem":148,
    "gn:feature_class":"P",
    "gn:feature_code":"PPL",
    "gn:name":"Krywlyany",
    "gn:population":0,
    "gn:timezone":"Europe/Minsk",
    "iso:country":"BY",
    "name:bel_x_preferred":[
        "\u041a\u0440\u044b\u045e\u043b\u044f\u043d\u044b"
    ],
    "name:und_x_variant":[
        "Kzhivlyany",
        "Krivlyany",
        "Krywlyany",
        "Kryvlyany"
    ],
    "wof:name":"Krywlyany",
    "wof:placetype":"locality"
},
  "geometry": {"coordinates":[24.071,52.286],"type":"Point"}
}