{
  "type": "Feature",
  "properties": {
    "gn:admin1_code":"2.0",
    "gn:asciiname":"Yanovka",
    "gn:country_code":"BY",
    "gn:dem":131,
    "gn:feature_class":"P",
    "gn:feature_code":"PPL",
    "gn:name":"Yanovka",
    "gn:population":0,
    "gn:timezone":"Europe/Minsk",
    "iso:country":"BY",
    "name:rus_x_preferred":[
        "\u042f\u043d\u043e\u0432\u043a\u0430"
    ],
    "wof:name":"Yanovka",
    "wof:placetype":"locality"
},
  "geometry": {"coordinates":[30.419,52.1921],"type":"Point"}
}