{
  "type": "Feature",
  "properties": {
    "gn:admin1_code":"7.0",
    "gn:asciiname":"Leshnya",
    "gn:country_code":"BY",
    "gn:dem":131,
    "gn:feature_class":"P",
    "gn:feature_code":"PPL",
    "gn:name":"Leshnya",
    "gn:population":0,
    "gn:timezone":"Europe/Minsk",
    "iso:country":"BY",
    "name:rus_x_preferred":[
        "\u041b\u0435\u0448\u043d\u044f"
    ],
    "wof:name":"Leshnya",
    "wof:placetype":"locality"
},
  "geometry": {"coordinates":[28.347,55.8384],"type":"Point"}
}