{
  "type": "Feature",
  "properties": {
    "gn:admin1_code":"7.0",
    "gn:asciiname":"Rusinovo",
    "gn:country_code":"BY",
    "gn:dem":173,
    "gn:feature_class":"P",
    "gn:feature_code":"PPL",
    "gn:name":"Rusinovo",
    "gn:population":0,
    "gn:timezone":"Europe/Minsk",
    "iso:country":"BY",
    "name:bul_x_preferred":[
        "\u0420\u0443\u0441\u0438\u043d\u043e\u0432\u043e"
    ],
    "name:ceb_x_preferred":[
        "Rusinovo"
    ],
    "name:fra_x_preferred":[
        "Roussinovo"
    ],
    "name:hun_x_preferred":[
        "Ruszinovo"
    ],
    "name:mkd_x_preferred":[
        "\u0420\u0443\u0441\u0438\u043d\u043e\u0432\u043e"
    ],
    "name:por_x_preferred":[
        "Rusinovo"
    ],
    "name:rus_x_preferred":[
        "\u0420\u0443\u0441\u0438\u043d\u043e\u0432\u043e"
    ],
    "name:sqi_x_preferred":[
        "Rusinova"
    ],
    "name:srp_x_preferred":[
        "\u0420\u0443\u0441\u0438\u043d\u043e\u0432\u043e"
    ],
    "name:swe_x_preferred":[
        "Rusinovo"
    ],
    "name:ukr_x_preferred":[
        "\u0420\u0443\u0441\u0438\u043d\u043e\u0432\u043e"
    ],
    "wof:name":"Rusinovo",
    "wof:placetype":"locality"
},
  "geometry": {"coordinates":[29.553,54.8286],"type":"Point"}
}