{
  "type": "Feature",
  "properties": {
    "gn:admin1_code":"2.0",
    "gn:asciiname":"Vuts'",
    "gn:country_code":"BY",
    "gn:dem":149,
    "gn:feature_class":"P",
    "gn:feature_code":"PPL",
    "gn:name":"Vuts\u2019",
    "gn:population":0,
    "gn:timezone":"Europe/Minsk",
    "iso:country":"BY",
    "name:bel_x_preferred":[
        "\u0412\u0443\u0446\u044c"
    ],
    "name:rus_x_preferred":[
        "Ut\u2019"
    ],
    "name:und_x_variant":[
        "Vuts\u2019",
        "Ut\u2019"
    ],
    "wof:name":"Vuts'",
    "wof:placetype":"locality"
},
  "geometry": {"coordinates":[31.3823,52.2263],"type":"Point"}
}