{
  "type": "Feature",
  "properties": {
    "gn:admin1_code":"6.0",
    "gn:asciiname":"Mezhenin",
    "gn:country_code":"BY",
    "gn:dem":171,
    "gn:feature_class":"P",
    "gn:feature_code":"PPL",
    "gn:name":"Mezhenin",
    "gn:population":0,
    "gn:timezone":"Europe/Minsk",
    "iso:country":"BY",
    "name:rus_x_preferred":[
        "\u041c\u0435\u0436\u0435\u043d\u0438\u043d"
    ],
    "wof:name":"Mezhenin",
    "wof:placetype":"locality"
},
  "geometry": {"coordinates":[31.9441,53.4615],"type":"Point"}
}