{
  "type": "Feature",
  "properties": {
    "gn:admin1_code":"6.0",
    "gn:asciiname":"Dolgaya Dubrava",
    "gn:country_code":"BY",
    "gn:dem":174,
    "gn:feature_class":"P",
    "gn:feature_code":"PPL",
    "gn:name":"Dolgaya Dubrava",
    "gn:population":0,
    "gn:timezone":"Europe/Minsk",
    "iso:country":"BY",
    "name:rus_x_preferred":[
        "\u0414\u043e\u043b\u0433\u0430\u044f \u0414\u0443\u0431\u0440\u0430\u0432\u0430"
    ],
    "wof:name":"Dolgaya Dubrava",
    "wof:placetype":"locality"
},
  "geometry": {"coordinates":[32.4273,53.2561],"type":"Point"}
}