{
  "type": "Feature",
  "properties": {
    "gn:admin1_code":"1.0",
    "gn:asciiname":"Barany",
    "gn:country_code":"BY",
    "gn:dem":151,
    "gn:feature_class":"P",
    "gn:feature_code":"PPL",
    "gn:name":"Barany",
    "gn:population":0,
    "gn:timezone":"Europe/Minsk",
    "iso:country":"BY",
    "name:rus_x_preferred":[
        "\u0411\u0430\u0440\u0430\u043d\u044b"
    ],
    "wof:name":"Barany",
    "wof:placetype":"locality"
},
  "geometry": {"coordinates":[25.3298,52.6923],"type":"Point"}
}