{
  "type": "Feature",
  "properties": {
    "gn:admin1_code":"5.0",
    "gn:asciiname":"Mozhany",
    "gn:country_code":"BY",
    "gn:dem":175,
    "gn:feature_class":"P",
    "gn:feature_code":"PPL",
    "gn:name":"Mozhany",
    "gn:population":0,
    "gn:timezone":"Europe/Minsk",
    "iso:country":"BY",
    "name:rus_x_preferred":[
        "\u041c\u043e\u0436\u0430\u043d\u044b"
    ],
    "wof:name":"Mozhany",
    "wof:placetype":"locality"
},
  "geometry": {"coordinates":[29.4183,54.1214],"type":"Point"}
}