{
  "type": "Feature",
  "properties": {
    "gn:admin1_code":"6.0",
    "gn:asciiname":"Lysaya Gora",
    "gn:country_code":"BY",
    "gn:dem":200,
    "gn:feature_class":"P",
    "gn:feature_code":"PPL",
    "gn:name":"Lysaya Gora",
    "gn:population":0,
    "gn:timezone":"Europe/Minsk",
    "iso:country":"BY",
    "name:rus_x_preferred":[
        "\u041b\u044b\u0441\u0430\u044f \u0413\u043e\u0440\u0430"
    ],
    "wof:name":"Lysaya Gora",
    "wof:placetype":"locality"
},
  "geometry": {"coordinates":[30.5107,54.1776],"type":"Point"}
}