{
  "type": "Feature",
  "properties": {
    "gn:admin1_code":"0.0",
    "gn:asciiname":"Khaletskovshchyzna",
    "gn:cc2":"BY",
    "gn:country_code":"BY",
    "gn:dem":283,
    "gn:feature_class":"P",
    "gn:feature_code":"PPL",
    "gn:name":"Khaletskovshchyzna",
    "gn:population":0,
    "gn:timezone":"Europe/Minsk",
    "iso:country":"BY",
    "name:und_x_variant":[
        "Chaleckowszczyzna",
        "Khaletskovshchyzna"
    ],
    "wof:name":"Khaletskovshchyzna",
    "wof:placetype":"locality"
},
  "geometry": {"coordinates":[27.08333,54.13333000000001],"type":"Point"}
}