{
  "type": "Feature",
  "properties": {
    "gn:admin1_code":"2.0",
    "gn:asciiname":"Medvezhiy Log",
    "gn:country_code":"BY",
    "gn:dem":124,
    "gn:feature_class":"P",
    "gn:feature_code":"PPL",
    "gn:name":"Medvezhiy Log",
    "gn:population":0,
    "gn:timezone":"Europe/Minsk",
    "iso:country":"BY",
    "name:rus_x_preferred":[
        "\u041c\u0435\u0434\u0432\u0435\u0436\u0438\u0439 \u041b\u043e\u0433"
    ],
    "wof:name":"Medvezhiy Log",
    "wof:placetype":"locality"
},
  "geometry": {"coordinates":[31.178,52.3869],"type":"Point"}
}