{
  "type": "Feature",
  "properties": {
    "gn:admin1_code":"5.0",
    "gn:asciiname":"Adamki",
    "gn:country_code":"BY",
    "gn:dem":203,
    "gn:feature_class":"P",
    "gn:feature_code":"PPL",
    "gn:name":"Adamki",
    "gn:population":0,
    "gn:timezone":"Europe/Minsk",
    "iso:country":"BY",
    "name:pol_x_preferred":[
        "Adamki"
    ],
    "name:rus_x_preferred":[
        "\u0410\u0434\u0430\u043c\u043a\u0438"
    ],
    "name:ukr_x_preferred":[
        "\u0410\u0434\u0430\u043c\u043a\u0456"
    ],
    "wof:name":"Adamki",
    "wof:placetype":"locality"
},
  "geometry": {"coordinates":[26.6616,53.8981],"type":"Point"}
}