{
  "type": "Feature",
  "properties": {
    "gn:admin1_code":"3.0",
    "gn:asciiname":"Rachkyany",
    "gn:country_code":"BY",
    "gn:dem":176,
    "gn:feature_class":"P",
    "gn:feature_code":"PPL",
    "gn:name":"Rachkyany",
    "gn:population":0,
    "gn:timezone":"Europe/Minsk",
    "iso:country":"BY",
    "name:rus_x_preferred":[
        "\u0420\u0430\u0447\u043a\u044f\u043d\u044b"
    ],
    "wof:name":"Rachkyany",
    "wof:placetype":"locality"
},
  "geometry": {"coordinates":[26.1448,54.4742],"type":"Point"}
}