{
  "type": "Feature",
  "properties": {
    "gn:admin1_code":"3.0",
    "gn:asciiname":"Shinkovshchizna",
    "gn:country_code":"BY",
    "gn:dem":149,
    "gn:feature_class":"P",
    "gn:feature_code":"PPL",
    "gn:name":"Shinkovshchizna",
    "gn:population":0,
    "gn:timezone":"Europe/Minsk",
    "iso:country":"BY",
    "name:rus_x_preferred":[
        "\u0428\u0438\u043d\u043a\u043e\u0432\u0449\u0438\u0437\u043d\u0430"
    ],
    "name:und_x_variant":[
        "Shinkovshchina",
        "\u0428\u0438\u043d\u043a\u043e\u0432\u0449\u0438\u043d\u0430"
    ],
    "wof:name":"Shinkovshchizna",
    "wof:placetype":"locality"
},
  "geometry": {"coordinates":[24.7663,53.8917],"type":"Point"}
}