{
  "type": "Feature",
  "properties": {
    "gn:admin1_code":"1.0",
    "gn:asciiname":"Tukhavichy",
    "gn:country_code":"BY",
    "gn:dem":155,
    "gn:feature_class":"P",
    "gn:feature_code":"PPL",
    "gn:name":"Tukhavichy",
    "gn:population":0,
    "gn:timezone":"Europe/Minsk",
    "iso:country":"BY",
    "name:bel_x_preferred":[
        "\u0422\u0443\u0445\u0430\u0432\u0456\u0447\u044b"
    ],
    "name:eng_x_preferred":[
        "Tukhovichi"
    ],
    "name:rus_x_preferred":[
        "\u0422\u0443\u0445\u043e\u0432\u0438\u0447\u0438"
    ],
    "name:und_x_variant":[
        "Tukhoviche",
        "Tukhovichi",
        "Tukhavichy"
    ],
    "wof:name":"Tukhavichy",
    "wof:placetype":"locality"
},
  "geometry": {"coordinates":[25.9668,52.8146],"type":"Point"}
}