{
  "type": "Feature",
  "properties": {
    "gn:admin1_code":"4.0",
    "gn:asciiname":"Malyya Haradzyatsichy",
    "gn:country_code":"BY",
    "gn:dem":134,
    "gn:feature_class":"P",
    "gn:feature_code":"PPL",
    "gn:name":"Malyya Haradzyatsichy",
    "gn:population":0,
    "gn:timezone":"Europe/Minsk",
    "iso:country":"BY",
    "name:bel_x_preferred":[
        "\u041c\u0430\u043b\u044b\u044f \u0413\u0430\u0440\u0430\u0434\u0437\u044f\u0446\u0456\u0447\u044b"
    ],
    "name:und_x_variant":[
        "Malyye Gorodyatichi",
        "Malyya Haradzyatsichy"
    ],
    "wof:name":"Malyya Haradzyatsichy",
    "wof:placetype":"locality"
},
  "geometry": {"coordinates":[28.3299,52.5478],"type":"Point"}
}