{
  "type": "Feature",
  "properties": {
    "gn:admin1_code":"2.0",
    "gn:asciiname":"Lyubovichi",
    "gn:country_code":"BY",
    "gn:dem":123,
    "gn:feature_class":"P",
    "gn:feature_code":"PPL",
    "gn:name":"Lyubovichi",
    "gn:population":0,
    "gn:timezone":"Europe/Minsk",
    "iso:country":"BY",
    "name:rus_x_preferred":[
        "\u041b\u044e\u0431\u043e\u0432\u0438\u0447\u0438"
    ],
    "wof:name":"Lyubovichi",
    "wof:placetype":"locality"
},
  "geometry": {"coordinates":[27.6481,52.0503],"type":"Point"}
}