{
  "type": "Feature",
  "properties": {
    "gn:admin1_code":"1.0",
    "gn:asciiname":"Shenevtsy",
    "gn:country_code":"BY",
    "gn:dem":159,
    "gn:feature_class":"P",
    "gn:feature_code":"PPL",
    "gn:name":"Shenevtsy",
    "gn:population":0,
    "gn:timezone":"Europe/Minsk",
    "iso:country":"BY",
    "name:rus_x_preferred":[
        "\u0428\u0435\u043d\u0435\u0432\u0446\u044b"
    ],
    "wof:name":"Shenevtsy",
    "wof:placetype":"locality"
},
  "geometry": {"coordinates":[24.49,52.6867],"type":"Point"}
}