{
  "type": "Feature",
  "properties": {
    "gn:admin1_code":"3.0",
    "gn:asciiname":"Aleksandrovo",
    "gn:country_code":"BY",
    "gn:dem":129,
    "gn:feature_class":"P",
    "gn:feature_code":"PPL",
    "gn:name":"Aleksandrovo",
    "gn:population":0,
    "gn:timezone":"Europe/Minsk",
    "iso:country":"BY",
    "name:bel_x_preferred":[
        "Alyaksandrava"
    ],
    "name:bel_x_variant":[
        "\u0410\u043b\u044f\u043a\u0441\u0430\u043d\u0434\u0440\u0430\u0432\u0430"
    ],
    "name:rus_x_preferred":[
        "\u0410\u043b\u0435\u043a\u0441\u0430\u043d\u0434\u0440\u043e\u0432\u043e"
    ],
    "wof:name":"Aleksandrovo",
    "wof:placetype":"locality"
},
  "geometry": {"coordinates":[24.009,53.6182],"type":"Point"}
}