{
  "type": "Feature",
  "properties": {
    "gn:admin1_code":"5.0",
    "gn:asciiname":"Zuyevka",
    "gn:country_code":"BY",
    "gn:dem":283,
    "gn:feature_class":"P",
    "gn:feature_code":"PPL",
    "gn:name":"Zuy\u00ebvka",
    "gn:population":0,
    "gn:timezone":"Europe/Minsk",
    "iso:country":"BY",
    "name:rus_x_preferred":[
        "\u0417\u0443\u0451\u0432\u043a\u0430"
    ],
    "name:und_x_variant":[
        "Zuy\u00ebvka"
    ],
    "wof:name":"Zuyevka",
    "wof:placetype":"locality"
},
  "geometry": {"coordinates":[26.9599,53.8649],"type":"Point"}
}