{
  "type": "Feature",
  "properties": {
    "gn:admin1_code":"5.0",
    "gn:asciiname":"Ozloml'",
    "gn:country_code":"BY",
    "gn:dem":137,
    "gn:feature_class":"P",
    "gn:feature_code":"PPL",
    "gn:name":"Ozloml\u2019",
    "gn:population":0,
    "gn:timezone":"Europe/Minsk",
    "iso:country":"BY",
    "name:rus_x_preferred":[
        "\u041e\u0437\u043b\u043e\u043c\u043b\u044c"
    ],
    "name:und_x_variant":[
        "Ozloml\u2019"
    ],
    "wof:name":"Ozloml'",
    "wof:placetype":"locality"
},
  "geometry": {"coordinates":[28.212,52.7548],"type":"Point"}
}