{
  "type": "Feature",
  "properties": {
    "gn:admin1_code":"1.0",
    "gn:asciiname":"Karasi",
    "gn:country_code":"BY",
    "gn:dem":153,
    "gn:feature_class":"P",
    "gn:feature_code":"PPL",
    "gn:name":"Karasi",
    "gn:population":0,
    "gn:timezone":"Europe/Minsk",
    "iso:country":"BY",
    "name:jpn_x_preferred":[
        "\u30ab\u30e9\u30b8"
    ],
    "name:rus_x_preferred":[
        "\u041a\u0430\u0440\u0430\u0441\u0438"
    ],
    "wof:name":"Karasi",
    "wof:placetype":"locality"
},
  "geometry": {"coordinates":[24.8569,52.8487],"type":"Point"}
}