{
  "type": "Feature",
  "properties": {
    "gn:admin1_code":"5.0",
    "gn:asciiname":"Garutishki",
    "gn:country_code":"BY",
    "gn:dem":241,
    "gn:feature_class":"P",
    "gn:feature_code":"PPL",
    "gn:name":"Garutishki",
    "gn:population":0,
    "gn:timezone":"Europe/Minsk",
    "iso:country":"BY",
    "name:rus_x_preferred":[
        "\u0413\u0430\u0440\u0443\u0442\u0438\u0448\u043a\u0438"
    ],
    "name:und_x_variant":[
        "Gorutishki"
    ],
    "wof:name":"Garutishki",
    "wof:placetype":"locality"
},
  "geometry": {"coordinates":[27.0868,53.7632],"type":"Point"}
}