{
  "type": "Feature",
  "properties": {
    "gn:admin1_code":"3.0",
    "gn:asciiname":"Ludy",
    "gn:country_code":"BY",
    "gn:dem":242,
    "gn:feature_class":"P",
    "gn:feature_code":"PPL",
    "gn:name":"Ludy",
    "gn:population":0,
    "gn:timezone":"Europe/Minsk",
    "iso:country":"BY",
    "name:rus_x_preferred":[
        "\u041b\u0443\u0434\u044b"
    ],
    "wof:name":"Ludy",
    "wof:placetype":"locality"
},
  "geometry": {"coordinates":[25.7996,54.2878],"type":"Point"}
}