{
  "type": "Feature",
  "properties": {
    "gn:admin1_code":"7.0",
    "gn:asciiname":"Krulyewshchyna",
    "gn:country_code":"BY",
    "gn:dem":197,
    "gn:feature_class":"P",
    "gn:feature_code":"PPL",
    "gn:name":"Krulyewshchyna",
    "gn:population":0,
    "gn:timezone":"Europe/Minsk",
    "iso:country":"BY",
    "name:bel_x_preferred":[
        "\u041a\u0440\u0443\u043b\u0435\u045e\u0448\u0447\u044b\u043d\u0430"
    ],
    "name:eng_x_preferred":[
        "Krulevshchizna"
    ],
    "name:rus_x_preferred":[
        "\u041a\u0440\u0443\u043b\u0435\u0432\u0449\u0438\u043d\u0430"
    ],
    "name:und_x_variant":[
        "Kr\u00f3lewszczyzna",
        "Krulevshchyzna",
        "Krulevshchizna",
        "Krulyewshchyna",
        "Krulevshchina"
    ],
    "wof:name":"Krulyewshchyna",
    "wof:placetype":"locality"
},
  "geometry": {"coordinates":[27.7801,55.0257],"type":"Point"}
}