{
  "type": "Feature",
  "properties": {
    "gn:admin1_code":"3.0",
    "gn:asciiname":"Kovshovo",
    "gn:country_code":"BY",
    "gn:dem":113,
    "gn:feature_class":"P",
    "gn:feature_code":"PPL",
    "gn:name":"Kovshovo",
    "gn:population":0,
    "gn:timezone":"Europe/Minsk",
    "iso:country":"BY",
    "name:bel_x_preferred":[
        "Kawshova"
    ],
    "name:bel_x_variant":[
        "\u041a\u0430\u045e\u0448\u043e\u0432\u0430"
    ],
    "name:rus_x_preferred":[
        "\u041a\u043e\u0432\u0448\u043e\u0432\u043e"
    ],
    "wof:name":"Kovshovo",
    "wof:placetype":"locality"
},
  "geometry": {"coordinates":[24.1878,53.5252],"type":"Point"}
}