{
  "type": "Feature",
  "properties": {
    "gn:admin1_code":"5.0",
    "gn:asciiname":"Zamuzhan'ye",
    "gn:country_code":"BY",
    "gn:dem":164,
    "gn:feature_class":"P",
    "gn:feature_code":"PPL",
    "gn:name":"Zamuzhan\u2019ye",
    "gn:population":0,
    "gn:timezone":"Europe/Minsk",
    "iso:country":"BY",
    "name:rus_x_preferred":[
        "\u0417\u0430\u043c\u0443\u0436\u0430\u043d\u044c\u0435"
    ],
    "name:und_x_variant":[
        "Zamuzhan\u2019ye"
    ],
    "wof:name":"Zamuzhan'ye",
    "wof:placetype":"locality"
},
  "geometry": {"coordinates":[28.7913,54.2556],"type":"Point"}
}