{
  "type": "Feature",
  "properties": {
    "gn:admin1_code":"3.0",
    "gn:asciiname":"Lipnishki",
    "gn:country_code":"BY",
    "gn:dem":147,
    "gn:feature_class":"P",
    "gn:feature_code":"PPL",
    "gn:name":"Lipnishki",
    "gn:population":0,
    "gn:timezone":"Europe/Minsk",
    "iso:country":"BY",
    "name:rus_x_preferred":[
        "\u041b\u0438\u043f\u043d\u0438\u0448\u043a\u0438"
    ],
    "wof:name":"Lipnishki",
    "wof:placetype":"locality"
},
  "geometry": {"coordinates":[25.9079,54.8362],"type":"Point"}
}