{
  "type": "Feature",
  "properties": {
    "gn:admin1_code":"2.0",
    "gn:asciiname":"Kirovo",
    "gn:country_code":"BY",
    "gn:dem":105,
    "gn:feature_class":"P",
    "gn:feature_code":"PPL",
    "gn:name":"Kirovo",
    "gn:population":0,
    "gn:timezone":"Europe/Minsk",
    "iso:country":"BY",
    "name:eng_x_preferred":[
        "Kirova"
    ],
    "name:rus_x_preferred":[
        "\u041a\u0438\u0440\u043e\u0432\u043e"
    ],
    "name:und_x_variant":[
        "Lukoyedy",
        "Kirova"
    ],
    "wof:name":"Kirovo",
    "wof:placetype":"locality"
},
  "geometry": {"coordinates":[30.5863,51.3942],"type":"Point"}
}