{
  "type": "Feature",
  "properties": {
    "gn:admin1_code":"6.0",
    "gn:asciiname":"Mostovoy",
    "gn:country_code":"BY",
    "gn:dem":186,
    "gn:feature_class":"P",
    "gn:feature_code":"PPL",
    "gn:name":"Mostovoy",
    "gn:population":0,
    "gn:timezone":"Europe/Minsk",
    "iso:country":"BY",
    "name:rus_x_preferred":[
        "\u041c\u043e\u0441\u0442\u043e\u0432\u043e\u0439"
    ],
    "wof:name":"Mostovoy",
    "wof:placetype":"locality"
},
  "geometry": {"coordinates":[31.1212,54.2205],"type":"Point"}
}