{
  "type": "Feature",
  "properties": {
    "gn:admin1_code":"5.0",
    "gn:asciiname":"Krasnovinka",
    "gn:country_code":"BY",
    "gn:dem":185,
    "gn:feature_class":"P",
    "gn:feature_code":"PPL",
    "gn:name":"Krasnovinka",
    "gn:population":0,
    "gn:timezone":"Europe/Minsk",
    "iso:country":"BY",
    "name:rus_x_preferred":[
        "\u041a\u0440\u0430\u0441\u043d\u043e\u0432\u0438\u043d\u043a\u0430"
    ],
    "wof:name":"Krasnovinka",
    "wof:placetype":"locality"
},
  "geometry": {"coordinates":[29.4503,54.553],"type":"Point"}
}