{
  "type": "Feature",
  "properties": {
    "gn:admin1_code":"5.0",
    "gn:asciiname":"Shpakovshchina",
    "gn:country_code":"BY",
    "gn:dem":175,
    "gn:feature_class":"P",
    "gn:feature_code":"PPL",
    "gn:name":"Shpakovshchina",
    "gn:population":0,
    "gn:timezone":"Europe/Minsk",
    "iso:country":"BY",
    "name:rus_x_preferred":[
        "\u0428\u043f\u0430\u043a\u043e\u0432\u0449\u0438\u043d\u0430"
    ],
    "wof:name":"Shpakovshchina",
    "wof:placetype":"locality"
},
  "geometry": {"coordinates":[28.0206,54.0896],"type":"Point"}
}