{
  "type": "Feature",
  "properties": {
    "gn:admin1_code":"6.0",
    "gn:asciiname":"Bakova Sloboda",
    "gn:country_code":"BY",
    "gn:dem":209,
    "gn:feature_class":"P",
    "gn:feature_code":"PPL",
    "gn:name":"Bakova Sloboda",
    "gn:population":0,
    "gn:timezone":"Europe/Minsk",
    "iso:country":"BY",
    "name:rus_x_preferred":[
        "\u0411\u0430\u043a\u043e\u0432\u0430 \u0421\u043b\u043e\u0431\u043e\u0434\u0430"
    ],
    "wof:name":"Bakova Sloboda",
    "wof:placetype":"locality"
},
  "geometry": {"coordinates":[29.9911,54.2665],"type":"Point"}
}