{
  "type": "Feature",
  "properties": {
    "gn:admin1_code":"1.0",
    "gn:asciiname":"Nowosiele",
    "gn:country_code":"BY",
    "gn:dem":137,
    "gn:feature_class":"P",
    "gn:feature_code":"PPL",
    "gn:name":"Nowosiele",
    "gn:population":0,
    "gn:timezone":"Europe/Minsk",
    "iso:country":"BY",
    "name:rus_x_preferred":[
        "Novosel\u2019ye"
    ],
    "name:rus_x_variant":[
        "\u041d\u043e\u0432\u043e\u0441\u0435\u043b\u044c\u0435"
    ],
    "name:und_x_variant":[
        "Novosele",
        "Nowosiele",
        "Novosel\u2019ye"
    ],
    "wof:name":"Nowosiele",
    "wof:placetype":"locality"
},
  "geometry": {"coordinates":[26.0711,52.2091],"type":"Point"}
}