{
  "type": "Feature",
  "properties": {
    "gn:admin1_code":"5.0",
    "gn:asciiname":"Vladyki",
    "gn:country_code":"BY",
    "gn:dem":187,
    "gn:feature_class":"P",
    "gn:feature_code":"PPL",
    "gn:name":"Vladyki",
    "gn:population":0,
    "gn:timezone":"Europe/Minsk",
    "iso:country":"BY",
    "name:rus_x_preferred":[
        "\u0412\u043b\u0430\u0434\u044b\u043a\u0438"
    ],
    "name:und_x_variant":[
        "W\u0142adyki",
        "Vladyki"
    ],
    "wof:name":"Vladyki",
    "wof:placetype":"locality"
},
  "geometry": {"coordinates":[27.3843,54.4387],"type":"Point"}
}