{
  "type": "Feature",
  "properties": {
    "gn:admin1_code":"1.0",
    "gn:asciiname":"Dubnavichy",
    "gn:country_code":"BY",
    "gn:dem":132,
    "gn:feature_class":"P",
    "gn:feature_code":"PPL",
    "gn:name":"Dubnavichy",
    "gn:population":0,
    "gn:timezone":"Europe/Minsk",
    "iso:country":"BY",
    "name:bel_x_preferred":[
        "\u0414\u0443\u0431\u043d\u0430\u0432\u0456\u0447\u044b"
    ],
    "name:eng_x_preferred":[
        "Dubnovichi"
    ],
    "name:rus_x_preferred":[
        "\u0414\u0443\u0431\u043d\u043e\u0432\u0438\u0447\u0438"
    ],
    "name:und_x_variant":[
        "Dubnoviche",
        "Dubnowicze",
        "Dubnovichi",
        "Dubnavichy"
    ],
    "wof:name":"Dubnavichy",
    "wof:placetype":"locality"
},
  "geometry": {"coordinates":[26.4319,52.283],"type":"Point"}
}