{
  "type": "Feature",
  "properties": {
    "gn:admin1_code":"7.0",
    "gn:asciiname":"Gribovo",
    "gn:country_code":"BY",
    "gn:dem":158,
    "gn:feature_class":"P",
    "gn:feature_code":"PPL",
    "gn:name":"Gribovo",
    "gn:population":0,
    "gn:timezone":"Europe/Minsk",
    "iso:country":"BY",
    "name:rus_x_preferred":[
        "\u0413\u0440\u0438\u0431\u043e\u0432\u043e"
    ],
    "wof:name":"Gribovo",
    "wof:placetype":"locality"
},
  "geometry": {"coordinates":[28.7487,55.8019],"type":"Point"}
}