{
  "type": "Feature",
  "properties": {
    "gn:admin1_code":"3.0",
    "gn:asciiname":"Ruda-Lipichanskaya",
    "gn:country_code":"BY",
    "gn:dem":120,
    "gn:feature_class":"P",
    "gn:feature_code":"PPL",
    "gn:name":"Ruda-Lipichanskaya",
    "gn:population":0,
    "gn:timezone":"Europe/Minsk",
    "iso:country":"BY",
    "name:rus_x_preferred":[
        "\u0420\u0443\u0434\u0430-\u041b\u0438\u043f\u0438\u0447\u0430\u043d\u0441\u043a\u0430\u044f"
    ],
    "name:und_x_variant":[
        "Lipichanskaya Ruda"
    ],
    "wof:name":"Ruda-Lipichanskaya",
    "wof:placetype":"locality"
},
  "geometry": {"coordinates":[25.0368,53.4497],"type":"Point"}
}