{
  "type": "Feature",
  "properties": {
    "gn:admin1_code":"3.0",
    "gn:asciiname":"Zhukowshchyna",
    "gn:country_code":"BY",
    "gn:dem":138,
    "gn:feature_class":"P",
    "gn:feature_code":"PPL",
    "gn:name":"Zhukowshchyna",
    "gn:population":0,
    "gn:timezone":"Europe/Minsk",
    "iso:country":"BY",
    "name:bel_x_preferred":[
        "\u0416\u0443\u043a\u043e\u045e\u0448\u0447\u044b\u043d\u0430"
    ],
    "name:rus_x_preferred":[
        "\u0416\u0443\u043a\u043e\u0432\u0449\u0438\u043d\u0430"
    ],
    "name:und_x_variant":[
        "Zhukovshchina"
    ],
    "wof:name":"Zhukowshchyna",
    "wof:placetype":"locality"
},
  "geometry": {"coordinates":[25.35733,53.52967],"type":"Point"}
}