{
  "type": "Feature",
  "properties": {
    "gn:admin1_code":"7.0",
    "gn:asciiname":"Germanovshchina",
    "gn:country_code":"BY",
    "gn:dem":159,
    "gn:feature_class":"P",
    "gn:feature_code":"PPL",
    "gn:name":"Germanovshchina",
    "gn:population":0,
    "gn:timezone":"Europe/Minsk",
    "iso:country":"BY",
    "name:rus_x_preferred":[
        "\u0413\u0435\u0440\u043c\u0430\u043d\u043e\u0432\u0449\u0438\u043d\u0430"
    ],
    "wof:name":"Germanovshchina",
    "wof:placetype":"locality"
},
  "geometry": {"coordinates":[28.0483,55.1865],"type":"Point"}
}