{
  "type": "Feature",
  "properties": {
    "gn:admin1_code":"1.0",
    "gn:asciiname":"Vyalikaye Syalo",
    "gn:country_code":"BY",
    "gn:dem":172,
    "gn:feature_class":"P",
    "gn:feature_code":"PPL",
    "gn:name":"Vyalikaye Syalo",
    "gn:population":0,
    "gn:timezone":"Europe/Minsk",
    "iso:country":"BY",
    "name:bel_x_preferred":[
        "\u0412\u044f\u043b\u0456\u043a\u0430\u0435 \u0421\u044f\u043b\u043e"
    ],
    "name:eng_x_preferred":[
        "Velikoye Selo"
    ],
    "name:rus_x_preferred":[
        "\u0412\u0435\u043b.\u0421\u0435\u043b\u043e"
    ],
    "name:und_x_variant":[
        "Vel\u2019ko Selo",
        "Wielki Sio\u0142o",
        "Vel\u2019ke Selo",
        "Vyalikaye Syalo"
    ],
    "wof:name":"Vyalikaye Syalo",
    "wof:placetype":"locality"
},
  "geometry": {"coordinates":[24.3202,52.6331],"type":"Point"}
}