{
  "type": "Feature",
  "properties": {
    "gn:admin1_code":"5.0",
    "gn:asciiname":"Zhutino",
    "gn:country_code":"BY",
    "gn:dem":169,
    "gn:feature_class":"P",
    "gn:feature_code":"PPL",
    "gn:name":"Zhutino",
    "gn:population":0,
    "gn:timezone":"Europe/Minsk",
    "iso:country":"BY",
    "name:rus_x_preferred":[
        "\u0416\u0443\u0442\u0438\u043d\u043e"
    ],
    "wof:name":"Zhutino",
    "wof:placetype":"locality"
},
  "geometry": {"coordinates":[27.1278,54.9908],"type":"Point"}
}