{
  "type": "Feature",
  "properties": {
    "gn:admin1_code":"3.0",
    "gn:asciiname":"Krasuli",
    "gn:country_code":"BY",
    "gn:dem":144,
    "gn:feature_class":"P",
    "gn:feature_code":"PPL",
    "gn:name":"Krasuli",
    "gn:population":0,
    "gn:timezone":"Europe/Minsk",
    "iso:country":"BY",
    "name:rus_x_preferred":[
        "\u041a\u0440\u0430\u0441\u0443\u043b\u0438"
    ],
    "wof:name":"Krasuli",
    "wof:placetype":"locality"
},
  "geometry": {"coordinates":[24.9361,53.6429],"type":"Point"}
}