{
  "type": "Feature",
  "properties": {
    "gn:admin1_code":"5.0",
    "gn:asciiname":"Metlichino",
    "gn:country_code":"BY",
    "gn:dem":225,
    "gn:feature_class":"P",
    "gn:feature_code":"PPL",
    "gn:name":"Metlichino",
    "gn:population":0,
    "gn:timezone":"Europe/Minsk",
    "iso:country":"BY",
    "name:rus_x_preferred":[
        "\u041c\u0435\u0442\u043b\u0438\u0447\u0438\u043d\u043e"
    ],
    "wof:name":"Metlichino",
    "wof:placetype":"locality"
},
  "geometry": {"coordinates":[27.6738,54.1283],"type":"Point"}
}