{
  "type": "Feature",
  "properties": {
    "gn:admin1_code":"6.0",
    "gn:asciiname":"Podkryazhnik",
    "gn:country_code":"BY",
    "gn:dem":180,
    "gn:feature_class":"P",
    "gn:feature_code":"PPL",
    "gn:name":"Podkryazhnik",
    "gn:population":0,
    "gn:timezone":"Europe/Minsk",
    "iso:country":"BY",
    "name:rus_x_preferred":[
        "\u041f\u043e\u0434\u043a\u0440\u044f\u0436\u043d\u0438\u043a"
    ],
    "wof:name":"Podkryazhnik",
    "wof:placetype":"locality"
},
  "geometry": {"coordinates":[29.4927,53.8335],"type":"Point"}
}