{
  "type": "Feature",
  "properties": {
    "gn:admin1_code":"5.0",
    "gn:asciiname":"Sakovka",
    "gn:country_code":"BY",
    "gn:dem":188,
    "gn:feature_class":"P",
    "gn:feature_code":"PPL",
    "gn:name":"Sakovka",
    "gn:population":0,
    "gn:timezone":"Europe/Minsk",
    "iso:country":"BY",
    "name:rus_x_preferred":[
        "\u0421\u0430\u043a\u043e\u0432\u043a\u0430"
    ],
    "wof:name":"Sakovka",
    "wof:placetype":"locality"
},
  "geometry": {"coordinates":[28.1946,54.0574],"type":"Point"}
}