{
  "type": "Feature",
  "properties": {
    "gn:admin1_code":"7.0",
    "gn:asciiname":"Lazhok",
    "gn:country_code":"BY",
    "gn:dem":140,
    "gn:feature_class":"P",
    "gn:feature_code":"PPL",
    "gn:name":"Lazhok",
    "gn:population":0,
    "gn:timezone":"Europe/Minsk",
    "iso:country":"BY",
    "name:bel_x_preferred":[
        "\u041b\u0430\u0436\u043e\u043a"
    ],
    "name:und_x_variant":[
        "Lozhok"
    ],
    "wof:name":"Lazhok",
    "wof:placetype":"locality"
},
  "geometry": {"coordinates":[29.7514,55.1989],"type":"Point"}
}