{
  "type": "Feature",
  "properties": {
    "gn:admin1_code":"1.0",
    "gn:asciiname":"Ramyel'",
    "gn:country_code":"BY",
    "gn:dem":127,
    "gn:feature_class":"P",
    "gn:feature_code":"PPL",
    "gn:name":"Ramyel\u2019",
    "gn:population":0,
    "gn:timezone":"Europe/Minsk",
    "iso:country":"BY",
    "name:bel_x_preferred":[
        "\u0420\u0430\u043c\u0435\u043b\u044c"
    ],
    "name:rus_x_preferred":[
        "Remel\u2019"
    ],
    "name:und_x_variant":[
        "Romel\u2019",
        "Ramyel\u2019"
    ],
    "wof:name":"Ramyel'",
    "wof:placetype":"locality"
},
  "geometry": {"coordinates":[27.3396,52.0407],"type":"Point"}
}