{
  "type": "Feature",
  "properties": {
    "gn:admin1_code":"6.0",
    "gn:asciiname":"Gorodyanka",
    "gn:country_code":"BY",
    "gn:dem":185,
    "gn:feature_class":"P",
    "gn:feature_code":"PPL",
    "gn:name":"Gorodyanka",
    "gn:population":0,
    "gn:timezone":"Europe/Minsk",
    "iso:country":"BY",
    "name:rus_x_preferred":[
        "\u0413\u043e\u0440\u043e\u0434\u044f\u043d\u043a\u0430"
    ],
    "wof:name":"Gorodyanka",
    "wof:placetype":"locality"
},
  "geometry": {"coordinates":[30.2662,54.1509],"type":"Point"}
}