{
  "type": "Feature",
  "properties": {
    "gn:country":"BY",
    "gn:fcode":"PPL",
    "gn:population":8300,
    "iso:country":"BY",
    "name:bel_x_preferred":[
        "\u0413\u043e\u0440\u0430\u0434 \u0410\u0441\u0442\u0440\u0430\u0432\u0435\u0446"
    ],
    "name:bel_x_variant":[
        "\u0410\u0441\u0442\u0440\u0430\u0432\u0435\u0446"
    ],
    "name:bul_x_preferred":[
        "\u041e\u0441\u0442\u0440\u043e\u0432\u0435\u0446"
    ],
    "name:ceb_x_preferred":[
        "Astravyets"
    ],
    "name:ces_x_preferred":[
        "Astravec"
    ],
    "name:eng_x_preferred":[
        "Astravyets"
    ],
    "name:est_x_preferred":[
        "Astraviec"
    ],
    "name:fin_x_preferred":[
        "Astravets"
    ],
    "name:fra_x_preferred":[
        "Astraviets"
    ],
    "name:fra_x_variant":[
        "Astravets"
    ],
    "name:frr_x_preferred":[
        "Astrawets"
    ],
    "name:heb_x_preferred":[
        "\u05d0\u05e1\u05d8\u05e8\u05d1\u05d9\u05d9\u05e5"
    ],
    "name:hsb_x_preferred":[
        "Astrawjec"
    ],
    "name:ita_x_preferred":[
        "Astravec"
    ],
    "name:jpn_x_preferred":[
        "\u30a2\u30b9\u30c8\u30e9\u30f4\u30a7\u30c4"
    ],
    "name:kaz_x_preferred":[
        "\u041e\u0441\u0442\u0440\u043e\u0432\u0435\u0446"
    ],
    "name:lav_x_preferred":[
        "Astravjeca"
    ],
    "name:lit_x_preferred":[
        "Astravas"
    ],
    "name:nld_x_preferred":[
        "Astravyets"
    ],
    "name:pol_x_preferred":[
        "Ostrowiec"
    ],
    "name:rus_x_preferred":[
        "\u041e\u0441\u0442\u0440\u043e\u0432\u0435\u0446"
    ],
    "name:srp_x_preferred":[
        "\u0410\u0441\u0442\u0440\u0430\u0432\u0435\u0446"
    ],
    "name:swe_x_preferred":[
        "Ostrovets"
    ],
    "name:tat_x_preferred":[
        "\u0410\u0441\u0442\u0440\u0430\u0432\u0435\u0442\u0441"
    ],
    "name:ukr_x_preferred":[
        "\u041e\u0441\u0442\u0440\u043e\u0432\u0435\u0446\u044c"
    ],
    "name:zho_x_preferred":[
        "\u5967\u65af\u7279\u7f85\u97cb\u8328"
    ],
    "qs:name":"Astravyets",
    "qs:photos_9r":0,
    "qs:photos_sr":0,
    "qs:pop_sr":"5",
    "wd:population":8285,
    "wd:wordcount":155,
    "wof:name":"Astravyets",
    "wof:placetype":"locality",
    "wof:population":8285
},
  "geometry": {"coordinates":[25.95537,54.61378],"type":"Point"}
}