{
  "type": "Feature",
  "properties": {
    "gn:admin1_code":"1.0",
    "gn:asciiname":"Selets",
    "gn:country_code":"BY",
    "gn:dem":144,
    "gn:feature_class":"P",
    "gn:feature_code":"PPL",
    "gn:name":"Selets",
    "gn:population":0,
    "gn:timezone":"Europe/Minsk",
    "iso:country":"BY",
    "name:rus_x_preferred":[
        "\u0421\u0435\u043b\u0435\u0446"
    ],
    "wof:name":"Selets",
    "wof:placetype":"locality"
},
  "geometry": {"coordinates":[24.4922,52.2243],"type":"Point"}
}