{
  "type": "Feature",
  "properties": {
    "gn:admin1_code":"1.0",
    "gn:asciiname":"Flerovo",
    "gn:country_code":"BY",
    "gn:dem":133,
    "gn:feature_class":"P",
    "gn:feature_code":"PPL",
    "gn:name":"Flerovo",
    "gn:population":0,
    "gn:timezone":"Europe/Minsk",
    "iso:country":"BY",
    "name:rus_x_preferred":[
        "\u0424\u043b\u0435\u0440\u043e\u0432\u043e"
    ],
    "wof:name":"Flerovo",
    "wof:placetype":"locality"
},
  "geometry": {"coordinates":[27.1851,52.3151],"type":"Point"}
}