{
  "type": "Feature",
  "properties": {
    "gn:admin1_code":"1.0",
    "gn:asciiname":"Barany",
    "gn:country_code":"BY",
    "gn:dem":141,
    "gn:feature_class":"P",
    "gn:feature_code":"PPL",
    "gn:name":"Barany",
    "gn:population":0,
    "gn:timezone":"Europe/Minsk",
    "iso:country":"BY",
    "name:deu_x_preferred":[
        "Barany"
    ],
    "name:fra_x_preferred":[
        "Barany"
    ],
    "name:pol_x_preferred":[
        "Barany"
    ],
    "name:rus_x_preferred":[
        "\u0411\u0430\u0440\u0430\u043d\u044b"
    ],
    "name:ukr_x_preferred":[
        "\u0411\u0430\u0440\u0430\u043d\u0438"
    ],
    "wof:name":"Barany",
    "wof:placetype":"locality"
},
  "geometry": {"coordinates":[24.176,52.1163],"type":"Point"}
}