{
  "type": "Feature",
  "properties": {
    "gn:admin1_code":"7.0",
    "gn:asciiname":"Gramoshche",
    "gn:country_code":"BY",
    "gn:dem":131,
    "gn:feature_class":"P",
    "gn:feature_code":"PPL",
    "gn:name":"Gramoshche",
    "gn:population":0,
    "gn:timezone":"Europe/Minsk",
    "iso:country":"BY",
    "name:rus_x_preferred":[
        "\u0413\u0440\u0430\u043c\u043e\u0449\u0435"
    ],
    "wof:name":"Gramoshche",
    "wof:placetype":"locality"
},
  "geometry": {"coordinates":[28.4563,55.6655],"type":"Point"}
}