{
  "type": "Feature",
  "properties": {
    "gn:admin1_code":"5.0",
    "gn:asciiname":"Bortniki",
    "gn:country_code":"BY",
    "gn:dem":288,
    "gn:feature_class":"P",
    "gn:feature_code":"PPL",
    "gn:name":"Bortniki",
    "gn:population":0,
    "gn:timezone":"Europe/Minsk",
    "iso:country":"BY",
    "name:rus_x_preferred":[
        "\u0411\u043e\u0440\u0442\u043d\u0438\u043a\u0438"
    ],
    "wof:name":"Bortniki",
    "wof:placetype":"locality"
},
  "geometry": {"coordinates":[27.0984,54.0792],"type":"Point"}
}