{
  "type": "Feature",
  "properties": {
    "gn:admin1_code":"1.0",
    "gn:asciiname":"Chernyakovo",
    "gn:country_code":"BY",
    "gn:dem":153,
    "gn:feature_class":"P",
    "gn:feature_code":"PPL",
    "gn:name":"Chernyakovo",
    "gn:population":0,
    "gn:timezone":"Europe/Minsk",
    "iso:country":"BY",
    "name:rus_x_preferred":[
        "\u0427\u0435\u0440\u043d\u044f\u043a\u043e\u0432\u043e"
    ],
    "wof:name":"Chernyakovo",
    "wof:placetype":"locality"
},
  "geometry": {"coordinates":[24.9201,52.3513],"type":"Point"}
}