{
  "type": "Feature",
  "properties": {
    "gn:admin1_code":"2.0",
    "gn:asciiname":"Bronnoye",
    "gn:country_code":"BY",
    "gn:dem":140,
    "gn:feature_class":"P",
    "gn:feature_code":"PPL",
    "gn:name":"Bronnoye",
    "gn:population":0,
    "gn:timezone":"Europe/Minsk",
    "iso:country":"BY",
    "name:rus_x_preferred":[
        "\u0411\u0440\u043e\u043d\u043d\u043e\u0435"
    ],
    "wof:name":"Bronnoye",
    "wof:placetype":"locality"
},
  "geometry": {"coordinates":[29.8972,53.1134],"type":"Point"}
}