{
  "type": "Feature",
  "properties": {
    "gn:admin1_code":"7.0",
    "gn:asciiname":"Sosnovtsy",
    "gn:country_code":"BY",
    "gn:dem":127,
    "gn:feature_class":"P",
    "gn:feature_code":"PPL",
    "gn:name":"Sosnovtsy",
    "gn:population":0,
    "gn:timezone":"Europe/Minsk",
    "iso:country":"BY",
    "name:rus_x_preferred":[
        "\u0421\u043e\u0441\u043d\u043e\u0432\u0446\u044b"
    ],
    "name:und_x_variant":[
        "Sosn\u00f3wka",
        "Sosnuvka",
        "Sosnovtsy"
    ],
    "wof:name":"Sosnovtsy",
    "wof:placetype":"locality"
},
  "geometry": {"coordinates":[27.3699,55.4055],"type":"Point"}
}