{
  "type": "Feature",
  "properties": {
    "gn:admin1_code":"3.0",
    "gn:asciiname":"Ivez'",
    "gn:country_code":"BY",
    "gn:dem":176,
    "gn:feature_class":"P",
    "gn:feature_code":"PPL",
    "gn:name":"Ivez\u2019",
    "gn:population":0,
    "gn:timezone":"Europe/Minsk",
    "iso:country":"BY",
    "name:bel_x_preferred":[
        "Ivyaz\u2019"
    ],
    "name:bel_x_variant":[
        "\u0406\u0432\u044f\u0437\u044c"
    ],
    "name:eng_x_preferred":[
        "Ives'"
    ],
    "name:rus_x_preferred":[
        "\u0418\u0432\u0435\u0441\u044c"
    ],
    "name:rus_x_variant":[
        "\u0418\u0432\u0435\u0437\u044c"
    ],
    "name:und_x_variant":[
        "Ives\u2019",
        "Ivez\u2019"
    ],
    "wof:name":"Ivez'",
    "wof:placetype":"locality"
},
  "geometry": {"coordinates":[25.5434,53.3385],"type":"Point"}
}