{
  "type": "Feature",
  "properties": {
    "gn:admin1_code":"2.0",
    "gn:asciiname":"Stanki",
    "gn:country_code":"BY",
    "gn:dem":135,
    "gn:feature_class":"P",
    "gn:feature_code":"PPL",
    "gn:name":"Stanki",
    "gn:population":0,
    "gn:timezone":"Europe/Minsk",
    "iso:country":"BY",
    "name:rus_x_preferred":[
        "\u0421\u0442\u0430\u043d\u043a\u0438"
    ],
    "wof:name":"Stanki",
    "wof:placetype":"locality"
},
  "geometry": {"coordinates":[31.0521,52.5453],"type":"Point"}
}