{
  "type": "Feature",
  "properties": {
    "gn:admin1_code":"3.0",
    "gn:asciiname":"Kirpichevshchina",
    "gn:country_code":"BY",
    "gn:dem":124,
    "gn:feature_class":"P",
    "gn:feature_code":"PPL",
    "gn:name":"Kirpich\u00ebvshchina",
    "gn:population":0,
    "gn:timezone":"Europe/Minsk",
    "iso:country":"BY",
    "name:rus_x_preferred":[
        "Kirpich\u00ebvshchina"
    ],
    "name:rus_x_variant":[
        "\u041a\u0438\u0440\u043f\u0438\u0447\u0451\u0432\u0449\u0438\u043d\u0430"
    ],
    "name:und_x_variant":[
        "Krupichovshchyzna"
    ],
    "wof:name":"Kirpichevshchina",
    "wof:placetype":"locality"
},
  "geometry": {"coordinates":[24.4474,53.7372],"type":"Point"}
}