{
  "type": "Feature",
  "properties": {
    "gn:admin1_code":"7.0",
    "gn:asciiname":"Turchino",
    "gn:country_code":"BY",
    "gn:dem":177,
    "gn:feature_class":"P",
    "gn:feature_code":"PPL",
    "gn:name":"Turchino",
    "gn:population":0,
    "gn:timezone":"Europe/Minsk",
    "iso:country":"BY",
    "name:rus_x_preferred":[
        "\u0422\u0443\u0440\u0447\u0438\u043d\u043e"
    ],
    "wof:name":"Turchino",
    "wof:placetype":"locality"
},
  "geometry": {"coordinates":[27.4401,55.0408],"type":"Point"}
}