{
  "type": "Feature",
  "properties": {
    "gn:admin1_code":"6.0",
    "gn:asciiname":"Boyarshchina",
    "gn:country_code":"BY",
    "gn:dem":152,
    "gn:feature_class":"P",
    "gn:feature_code":"PPL",
    "gn:name":"Boyarshchina",
    "gn:population":0,
    "gn:timezone":"Europe/Minsk",
    "iso:country":"BY",
    "name:rus_x_preferred":[
        "\u0411\u043e\u044f\u0440\u0449\u0438\u043d\u0430"
    ],
    "wof:name":"Boyarshchina",
    "wof:placetype":"locality"
},
  "geometry": {"coordinates":[28.7902,53.1043],"type":"Point"}
}