{
  "type": "Feature",
  "properties": {
    "gn:admin1_code":"7.0",
    "gn:asciiname":"Nizhnyaya Verovoysha",
    "gn:country_code":"BY",
    "gn:dem":183,
    "gn:feature_class":"P",
    "gn:feature_code":"PPL",
    "gn:name":"Nizhnyaya Verovoysha",
    "gn:population":0,
    "gn:timezone":"Europe/Minsk",
    "iso:country":"BY",
    "name:rus_x_preferred":[
        "\u041d\u0438\u0436\u043d\u044f\u044f \u0412\u0435\u0440\u043e\u0432\u043e\u0439\u0448\u0430"
    ],
    "wof:name":"Nizhnyaya Verovoysha",
    "wof:placetype":"locality"
},
  "geometry": {"coordinates":[30.2601,54.5165],"type":"Point"}
}