{
  "type": "Feature",
  "properties": {
    "gn:admin1_code":"7.0",
    "gn:asciiname":"Glybochka",
    "gn:country_code":"BY",
    "gn:dem":144,
    "gn:feature_class":"P",
    "gn:feature_code":"PPL",
    "gn:name":"Glybochka",
    "gn:population":0,
    "gn:timezone":"Europe/Minsk",
    "iso:country":"BY",
    "name:rus_x_preferred":[
        "\u0413\u043b\u044b\u0431\u043e\u0447\u043a\u0430"
    ],
    "wof:name":"Glybochka",
    "wof:placetype":"locality"
},
  "geometry": {"coordinates":[28.5004,55.3178],"type":"Point"}
}