{
  "type": "Feature",
  "properties": {
    "gn:admin1_code":"7.0",
    "gn:asciiname":"Stukany",
    "gn:country_code":"BY",
    "gn:dem":224,
    "gn:feature_class":"P",
    "gn:feature_code":"PPL",
    "gn:name":"Stukany",
    "gn:population":0,
    "gn:timezone":"Europe/Minsk",
    "iso:country":"BY",
    "name:rus_x_preferred":[
        "\u0421\u0442\u0443\u043a\u0430\u043d\u044b"
    ],
    "wof:name":"Stukany",
    "wof:placetype":"locality"
},
  "geometry": {"coordinates":[29.5384,54.51300000000001],"type":"Point"}
}