{
  "type": "Feature",
  "properties": {
    "gn:admin1_code":"6.0",
    "gn:asciiname":"Novina",
    "gn:country_code":"BY",
    "gn:dem":162,
    "gn:feature_class":"P",
    "gn:feature_code":"PPL",
    "gn:name":"Novina",
    "gn:population":0,
    "gn:timezone":"Europe/Minsk",
    "iso:country":"BY",
    "name:rus_x_preferred":[
        "\u041d\u043e\u0432\u0438\u043d\u0430"
    ],
    "wof:name":"Novina",
    "wof:placetype":"locality"
},
  "geometry": {"coordinates":[28.622,53.4481],"type":"Point"}
}