{
  "type": "Feature",
  "properties": {
    "gn:admin1_code":"7.0",
    "gn:asciiname":"Norytsa",
    "gn:country_code":"BY",
    "gn:dem":169,
    "gn:feature_class":"P",
    "gn:feature_code":"PPL",
    "gn:name":"Norytsa",
    "gn:population":0,
    "gn:timezone":"Europe/Minsk",
    "iso:country":"BY",
    "name:bel_x_preferred":[
        "\u041d\u043e\u0440\u044b\u0446\u0430"
    ],
    "name:und_x_variant":[
        "Noritsa"
    ],
    "wof:name":"Norytsa",
    "wof:placetype":"locality"
},
  "geometry": {"coordinates":[27.3355,55.0753],"type":"Point"}
}