{
  "type": "Feature",
  "properties": {
    "gn:admin1_code":"2.0",
    "gn:asciiname":"Lutski",
    "gn:country_code":"BY",
    "gn:dem":141,
    "gn:feature_class":"P",
    "gn:feature_code":"PPL",
    "gn:name":"Lutski",
    "gn:population":0,
    "gn:timezone":"Europe/Minsk",
    "iso:country":"BY",
    "name:bel_x_preferred":[
        "\u041b\u0443\u0446\u043a\u0456"
    ],
    "name:rus_x_preferred":[
        "Pos\u00eblok Lukskiy"
    ],
    "name:und_x_variant":[
        "Lukskiy"
    ],
    "wof:name":"Lutski",
    "wof:placetype":"locality"
},
  "geometry": {"coordinates":[29.9596,52.9715],"type":"Point"}
}