{
  "type": "Feature",
  "properties": {
    "gn:admin1_code":"5.0",
    "gn:asciiname":"Vishnevaya",
    "gn:country_code":"BY",
    "gn:dem":187,
    "gn:feature_class":"P",
    "gn:feature_code":"PPL",
    "gn:name":"Vishn\u00ebvaya",
    "gn:population":0,
    "gn:timezone":"Europe/Minsk",
    "iso:country":"BY",
    "name:rus_x_preferred":[
        "\u0412\u0438\u0448\u043d\u0451\u0432\u0430\u044f"
    ],
    "name:und_x_variant":[
        "Vishn\u00ebvaya"
    ],
    "wof:name":"Vishnevaya",
    "wof:placetype":"locality"
},
  "geometry": {"coordinates":[28.2035,54.4794],"type":"Point"}
}