{
  "type": "Feature",
  "properties": {
    "gn:admin1_code":"1.0",
    "gn:asciiname":"Yazhony",
    "gn:country_code":"BY",
    "gn:dem":155,
    "gn:feature_class":"P",
    "gn:feature_code":"PPL",
    "gn:name":"Yazhony",
    "gn:population":0,
    "gn:timezone":"Europe/Minsk",
    "iso:country":"BY",
    "name:bel_x_preferred":[
        "\u042f\u0436\u043e\u043d\u044b"
    ],
    "name:und_x_variant":[
        "Yezhony",
        "Yezhona",
        "Yazhony"
    ],
    "wof:name":"Yazhony",
    "wof:placetype":"locality"
},
  "geometry": {"coordinates":[25.6319,52.9953],"type":"Point"}
}