{
  "type": "Feature",
  "properties": {
    "gn:admin1_code":"1.0",
    "gn:asciiname":"Vitchin",
    "gn:country_code":"BY",
    "gn:dem":135,
    "gn:feature_class":"P",
    "gn:feature_code":"PPL",
    "gn:name":"Vitchin",
    "gn:population":0,
    "gn:timezone":"Europe/Minsk",
    "iso:country":"BY",
    "name:rus_x_preferred":[
        "\u0412\u0438\u0442\u0447\u0438\u043d"
    ],
    "name:und_x_variant":[
        "Vichyn",
        "Wiczyn",
        "Vitchin",
        "Vichin"
    ],
    "wof:name":"Vitchin",
    "wof:placetype":"locality"
},
  "geometry": {"coordinates":[26.9444,52.2641],"type":"Point"}
}