{
  "type": "Feature",
  "properties": {
    "gn:admin1_code":"3.0",
    "gn:asciiname":"Khodyuki",
    "gn:country_code":"BY",
    "gn:dem":138,
    "gn:feature_class":"P",
    "gn:feature_code":"PPL",
    "gn:name":"Khodyuki",
    "gn:population":0,
    "gn:timezone":"Europe/Minsk",
    "iso:country":"BY",
    "name:bel_x_preferred":[
        "Khadzyuki"
    ],
    "name:bel_x_variant":[
        "\u0425\u0430\u0434\u0437\u044e\u043a\u0456"
    ],
    "name:rus_x_preferred":[
        "\u0425\u043e\u0434\u044e\u043a\u0438"
    ],
    "wof:name":"Khodyuki",
    "wof:placetype":"locality"
},
  "geometry": {"coordinates":[25.1423,53.7638],"type":"Point"}
}