{
  "type": "Feature",
  "properties": {
    "gn:admin1_code":"7.0",
    "gn:asciiname":"Deruki",
    "gn:country_code":"BY",
    "gn:dem":150,
    "gn:feature_class":"P",
    "gn:feature_code":"PPL",
    "gn:name":"Deruki",
    "gn:population":0,
    "gn:timezone":"Europe/Minsk",
    "iso:country":"BY",
    "name:rus_x_preferred":[
        "\u0414\u0435\u0440\u0443\u043a\u0438"
    ],
    "name:und_x_variant":[
        "Dzieruki",
        "Dzeruki",
        "Deruki"
    ],
    "wof:name":"Deruki",
    "wof:placetype":"locality"
},
  "geometry": {"coordinates":[26.9761,55.7282],"type":"Point"}
}