{
  "type": "Feature",
  "properties": {
    "gn:admin1_code":"2.0",
    "gn:asciiname":"Gorodok",
    "gn:country_code":"BY",
    "gn:dem":137,
    "gn:feature_class":"P",
    "gn:feature_code":"PPL",
    "gn:name":"Gorodok",
    "gn:population":0,
    "gn:timezone":"Europe/Minsk",
    "iso:country":"BY",
    "name:ceb_x_preferred":[
        "Gorodok"
    ],
    "name:ces_x_preferred":[
        "Gorodok"
    ],
    "name:ita_x_preferred":[
        "Gorodok"
    ],
    "name:rus_x_preferred":[
        "\u0413\u043e\u0440\u043e\u0434\u043e\u043a"
    ],
    "name:spa_x_preferred":[
        "Gorodok"
    ],
    "name:swe_x_preferred":[
        "Gorodok"
    ],
    "wof:name":"Gorodok",
    "wof:placetype":"locality"
},
  "geometry": {"coordinates":[30.3356,52.5781],"type":"Point"}
}