{
  "type": "Feature",
  "properties": {
    "gn:admin1_code":"5.0",
    "gn:asciiname":"Novyy Budkov",
    "gn:country_code":"BY",
    "gn:dem":166,
    "gn:feature_class":"P",
    "gn:feature_code":"PPL",
    "gn:name":"Novyy Budkov",
    "gn:population":0,
    "gn:timezone":"Europe/Minsk",
    "iso:country":"BY",
    "name:rus_x_preferred":[
        "\u041d\u043e\u0432\u044b\u0439 \u0411\u0443\u0434\u043a\u043e\u0432"
    ],
    "name:und_x_variant":[
        "Novo-Budkov"
    ],
    "wof:name":"Novyy Budkov",
    "wof:placetype":"locality"
},
  "geometry": {"coordinates":[28.777,53.6539],"type":"Point"}
}