{
  "type": "Feature",
  "properties": {
    "gn:admin1_code":"2.0",
    "gn:asciiname":"Poselok Yashchitskiy",
    "gn:country_code":"BY",
    "gn:dem":136,
    "gn:feature_class":"P",
    "gn:feature_code":"PPL",
    "gn:name":"Pos\u00eblok Yashchitskiy",
    "gn:population":0,
    "gn:timezone":"Europe/Minsk",
    "iso:country":"BY",
    "name:rus_x_preferred":[
        "\u041f\u043e\u0441\u0451\u043b\u043e\u043a \u042f\u0449\u0438\u0446\u043a\u0438\u0439"
    ],
    "name:und_x_variant":[
        "Pos\u00eblok Yashchitskiy"
    ],
    "wof:name":"Poselok Yashchitskiy",
    "wof:placetype":"locality"
},
  "geometry": {"coordinates":[29.8173,52.7235],"type":"Point"}
}