{
  "type": "Feature",
  "properties": {
    "gn:admin1_code":"7.0",
    "gn:asciiname":"Babashki",
    "gn:country_code":"BY",
    "gn:dem":154,
    "gn:feature_class":"P",
    "gn:feature_code":"PPL",
    "gn:name":"Babashki",
    "gn:population":0,
    "gn:timezone":"Europe/Minsk",
    "iso:country":"BY",
    "name:rus_x_preferred":[
        "\u0411\u0430\u0431\u0430\u0448\u043a\u0438"
    ],
    "name:und_x_variant":[
        "Babaszki",
        "Babashki"
    ],
    "wof:name":"Babashki",
    "wof:placetype":"locality"
},
  "geometry": {"coordinates":[26.9673,55.7774],"type":"Point"}
}