{
  "type": "Feature",
  "properties": {
    "gn:admin1_code":"3.0",
    "gn:asciiname":"Rudnya",
    "gn:country_code":"BY",
    "gn:dem":154,
    "gn:feature_class":"P",
    "gn:feature_code":"PPL",
    "gn:name":"Rudnya",
    "gn:population":0,
    "gn:timezone":"Europe/Minsk",
    "iso:country":"BY",
    "name:eng_x_preferred":[
        "Rudnya"
    ],
    "name:rus_x_preferred":[
        "\u0420\u0443\u0434\u043d\u044f"
    ],
    "name:und_x_variant":[
        "Rudnia",
        "Rudnya"
    ],
    "wof:name":"Rudnya",
    "wof:placetype":"locality"
},
  "geometry": {"coordinates":[24.0468,52.8416],"type":"Point"}
}