{
  "type": "Feature",
  "properties": {
    "gn:admin1_code":"7.0",
    "gn:asciiname":"Grebeni",
    "gn:country_code":"BY",
    "gn:dem":184,
    "gn:feature_class":"P",
    "gn:feature_code":"PPL",
    "gn:name":"Grebeni",
    "gn:population":0,
    "gn:timezone":"Europe/Minsk",
    "iso:country":"BY",
    "name:rus_x_preferred":[
        "\u0413\u0440\u0435\u0431\u0435\u043d\u0438"
    ],
    "name:und_x_variant":[
        "Hrebienie",
        "Grebeni"
    ],
    "wof:name":"Grebeni",
    "wof:placetype":"locality"
},
  "geometry": {"coordinates":[27.8076,54.6535],"type":"Point"}
}