{
  "type": "Feature",
  "properties": {
    "gn:admin1_code":"0.0",
    "gn:asciiname":"Kobylichi",
    "gn:country_code":"BY",
    "gn:dem":165,
    "gn:feature_class":"P",
    "gn:feature_code":"PPL",
    "gn:name":"Kobylichi",
    "gn:population":0,
    "gn:timezone":"Europe/Minsk",
    "iso:country":"BY",
    "wof:name":"Kobylichi",
    "wof:placetype":"locality"
},
  "geometry": {"coordinates":[27.85,53.46666999999999],"type":"Point"}
}