{
  "type": "Feature",
  "properties": {
    "gn:admin1_code":"6.0",
    "gn:asciiname":"Nasetskoye",
    "gn:country_code":"BY",
    "gn:dem":165,
    "gn:feature_class":"P",
    "gn:feature_code":"PPL",
    "gn:name":"Nasetskoye",
    "gn:population":0,
    "gn:timezone":"Europe/Minsk",
    "iso:country":"BY",
    "name:rus_x_preferred":[
        "\u041d\u0430\u0441\u0435\u0442\u0441\u043a\u043e\u0435"
    ],
    "wof:name":"Nasetskoye",
    "wof:placetype":"locality"
},
  "geometry": {"coordinates":[31.9528,53.3286],"type":"Point"}
}