{
  "type": "Feature",
  "properties": {
    "gn:admin1_code":"2.0",
    "gn:asciiname":"Shyichy",
    "gn:country_code":"BY",
    "gn:dem":125,
    "gn:feature_class":"P",
    "gn:feature_code":"PPL",
    "gn:name":"Shyichy",
    "gn:population":0,
    "gn:timezone":"Europe/Minsk",
    "iso:country":"BY",
    "name:bel_x_preferred":[
        "\u0428\u044b\u0456\u0447\u044b"
    ],
    "name:und_x_variant":[
        "Shiichi"
    ],
    "wof:name":"Shyichy",
    "wof:placetype":"locality"
},
  "geometry": {"coordinates":[29.2275,52.2584],"type":"Point"}
}