{
  "type": "Feature",
  "properties": {
    "gn:admin1_code":"5.0",
    "gn:asciiname":"Malyye Zavshitsy",
    "gn:country_code":"BY",
    "gn:dem":157,
    "gn:feature_class":"P",
    "gn:feature_code":"PPL",
    "gn:name":"Malyye Zavshitsy",
    "gn:population":0,
    "gn:timezone":"Europe/Minsk",
    "iso:country":"BY",
    "name:rus_x_preferred":[
        "\u041c\u0430\u043b\u044b\u0435 \u0417\u0430\u0432\u0448\u0438\u0446\u044b"
    ],
    "wof:name":"Malyye Zavshitsy",
    "wof:placetype":"locality"
},
  "geometry": {"coordinates":[27.3394,52.8241],"type":"Point"}
}