{
  "type": "Feature",
  "properties": {
    "gn:admin1_code":"3.0",
    "gn:asciiname":"Khvinyavichy",
    "gn:country_code":"BY",
    "gn:dem":162,
    "gn:feature_class":"P",
    "gn:feature_code":"PPL",
    "gn:name":"Khvinyavichy",
    "gn:population":0,
    "gn:timezone":"Europe/Minsk",
    "iso:country":"BY",
    "name:bel_x_preferred":[
        "\u0425\u0432\u0456\u043d\u044f\u0432\u0456\u0447\u044b"
    ],
    "name:rus_x_preferred":[
        "\u0425\u0432\u0438\u043d\u0435\u0432\u0438\u0447\u0438"
    ],
    "name:und_x_variant":[
        "Khvinevichi"
    ],
    "wof:name":"Khvinyavichy",
    "wof:placetype":"locality"
},
  "geometry": {"coordinates":[25.2577,53.4882],"type":"Point"}
}