{
  "type": "Feature",
  "properties": {
    "gn:admin1_code":"1.0",
    "gn:asciiname":"Tyshkavichy",
    "gn:country_code":"BY",
    "gn:dem":140,
    "gn:feature_class":"P",
    "gn:feature_code":"PPL",
    "gn:name":"Tyshkavichy",
    "gn:population":0,
    "gn:timezone":"Europe/Minsk",
    "iso:country":"BY",
    "name:bel_x_preferred":[
        "\u0422\u044b\u0448\u043a\u0430\u0432\u0456\u0447\u044b"
    ],
    "name:eng_x_preferred":[
        "Tyshkovichi"
    ],
    "name:rus_x_preferred":[
        "\u0422\u044b\u0448\u043a\u043e\u0432\u0438\u0447\u0438"
    ],
    "name:und_x_variant":[
        "Tyshkoviche",
        "Tyshkavichy"
    ],
    "wof:name":"Tyshkavichy",
    "wof:placetype":"locality"
},
  "geometry": {"coordinates":[25.6115,52.3505],"type":"Point"}
}