{
  "type": "Feature",
  "properties": {
    "gn:admin1_code":"7.0",
    "gn:asciiname":"Chernoruch'ye Vtoroye",
    "gn:country_code":"BY",
    "gn:dem":133,
    "gn:feature_class":"P",
    "gn:feature_code":"PPL",
    "gn:name":"Chernoruch\u2019ye Vtoroye",
    "gn:population":0,
    "gn:timezone":"Europe/Minsk",
    "iso:country":"BY",
    "name:rus_x_preferred":[
        "\u0427\u0435\u0440\u043d\u043e\u0440\u0443\u0447\u044c\u0435 \u0412\u0442\u043e\u0440\u043e\u0435"
    ],
    "name:und_x_variant":[
        "Chernoruch\u2019ye Vtoroye"
    ],
    "wof:name":"Chernoruch'ye Vtoroye",
    "wof:placetype":"locality"
},
  "geometry": {"coordinates":[28.743,55.4358],"type":"Point"}
}