{
  "type": "Feature",
  "properties": {
    "gn:admin1_code":"7.0",
    "gn:asciiname":"Kryuchki",
    "gn:country_code":"BY",
    "gn:dem":158,
    "gn:feature_class":"P",
    "gn:feature_code":"PPL",
    "gn:name":"Kryuchki",
    "gn:population":0,
    "gn:timezone":"Europe/Minsk",
    "iso:country":"BY",
    "name:rus_x_preferred":[
        "\u041a\u0440\u044e\u0447\u043a\u0438"
    ],
    "wof:name":"Kryuchki",
    "wof:placetype":"locality"
},
  "geometry": {"coordinates":[30.4147,55.4597],"type":"Point"}
}