{
  "type": "Feature",
  "properties": {
    "gn:admin1_code":"3.0",
    "gn:asciiname":"Dravneli",
    "gn:country_code":"BY",
    "gn:dem":137,
    "gn:feature_class":"P",
    "gn:feature_code":"PPL",
    "gn:name":"Dravneli",
    "gn:population":0,
    "gn:timezone":"Europe/Minsk",
    "iso:country":"BY",
    "name:rus_x_preferred":[
        "\u0414\u0440\u0430\u0432\u043d\u0435\u043b\u0438"
    ],
    "wof:name":"Dravneli",
    "wof:placetype":"locality"
},
  "geometry": {"coordinates":[25.83,54.869],"type":"Point"}
}