{
  "type": "Feature",
  "properties": {
    "gn:admin1_code":"6.0",
    "gn:asciiname":"Ukhlyast'",
    "gn:country_code":"BY",
    "gn:dem":147,
    "gn:feature_class":"P",
    "gn:feature_code":"PPL",
    "gn:name":"Ukhlyast\u2019",
    "gn:population":0,
    "gn:timezone":"Europe/Minsk",
    "iso:country":"BY",
    "name:rus_x_preferred":[
        "\u0423\u0445\u043b\u044f\u0441\u0442\u044c"
    ],
    "name:und_x_variant":[
        "Ukhlyast\u2019"
    ],
    "wof:name":"Ukhlyast'",
    "wof:placetype":"locality"
},
  "geometry": {"coordinates":[30.476,53.5177],"type":"Point"}
}