{
  "type": "Feature",
  "properties": {
    "gn:admin1_code":"2.0",
    "gn:asciiname":"Letovishche",
    "gn:country_code":"BY",
    "gn:dem":135,
    "gn:feature_class":"P",
    "gn:feature_code":"PPL",
    "gn:name":"Letovishche",
    "gn:population":0,
    "gn:timezone":"Europe/Minsk",
    "iso:country":"BY",
    "name:rus_x_preferred":[
        "\u041b\u0435\u0442\u043e\u0432\u0438\u0449\u0435"
    ],
    "wof:name":"Letovishche",
    "wof:placetype":"locality"
},
  "geometry": {"coordinates":[28.6668,52.0518],"type":"Point"}
}