{
  "type": "Feature",
  "properties": {
    "gn:country":"BY",
    "gn:fcode":"PPL",
    "gn:population":630,
    "iso:country":"BY",
    "name:arz_x_preferred":[
        "\u062a\u0648\u0631\u0686\u064a\u0643"
    ],
    "name:bel_x_preferred":[
        "\u0422\u0443\u0440\u044d\u0446"
    ],
    "name:bul_x_preferred":[
        "\u0422\u0443\u0440\u0435\u0446"
    ],
    "name:ceb_x_preferred":[
        "Turets"
    ],
    "name:ceb_x_variant":[
        "Turec"
    ],
    "name:che_x_preferred":[
        "\u0422\u0443\u0440\u0435\u0446"
    ],
    "name:deu_x_preferred":[
        "Turec"
    ],
    "name:eng_x_preferred":[
        "Turets"
    ],
    "name:eng_x_variant":[
        "Turjec",
        "Turec"
    ],
    "name:lit_x_preferred":[
        "Turecas"
    ],
    "name:nld_x_preferred":[
        "Turjec"
    ],
    "name:nld_x_variant":[
        "Turec"
    ],
    "name:pol_x_preferred":[
        "Turzec"
    ],
    "name:rus_x_preferred":[
        "\u0422\u0443\u0440\u0435\u0446"
    ],
    "name:swe_x_preferred":[
        "Turets"
    ],
    "name:szl_x_preferred":[
        "Turzec"
    ],
    "name:tat_x_preferred":[
        "\u0422\u0443\u0440\u044d\u0446"
    ],
    "name:ukr_x_preferred":[
        "\u0422\u0443\u0440\u0435\u0446\u044c"
    ],
    "name:und_x_variant":[
        "Tuzhets"
    ],
    "qs:name":"Turets",
    "qs:photos_9r":0,
    "qs:photos_sr":0,
    "qs:pop_sr":"2",
    "wof:name":"Turets",
    "wof:placetype":"locality",
    "wof:population":630
},
  "geometry": {"coordinates":[26.3125,53.5263],"type":"Point"}
}