{
  "type": "Feature",
  "properties": {
    "gn:country":"BY",
    "gn:fcode":"PPL",
    "gn:pop":630,
    "iso:country":"BY",
    "name:bel_x_preferred":[
        "\u0422\u0443\u0440\u044d\u0446"
    ],
    "name:bul_x_preferred":[
        "\u0422\u0443\u0440\u0435\u0446"
    ],
    "name:eng_x_preferred":[
        "Turets"
    ],
    "name:nld_x_preferred":[
        "Turjec"
    ],
    "name:pol_x_preferred":[
        "Turzec"
    ],
    "name:rus_x_preferred":[
        "\u0422\u0443\u0440\u0435\u0446"
    ],
    "name:swe_x_preferred":[
        "Turets"
    ],
    "name:szl_x_preferred":[
        "Turzec"
    ],
    "name:ukr_x_preferred":[
        "\u0422\u0443\u0440\u0435\u0446\u044c"
    ],
    "name:unk_x_variant":[
        "Tuzhets"
    ],
    "qs:name":"Turets",
    "qs:photos_9r":0,
    "qs:photos_sr":0,
    "qs:pop_sr":"2",
    "wof:name":"Turets",
    "wof:placetype":"locality",
    "wof:population":630
},
  "geometry": {"coordinates":[26.3125,53.5263],"type":"Point"}
}