{
  "type": "Feature",
  "properties": {
    "gn:admin1_code":"3.0",
    "gn:asciiname":"Verbilki",
    "gn:country_code":"BY",
    "gn:dem":149,
    "gn:feature_class":"P",
    "gn:feature_code":"PPL",
    "gn:name":"Verbilki",
    "gn:population":0,
    "gn:timezone":"Europe/Minsk",
    "iso:country":"BY",
    "name:bel_x_preferred":[
        "Vyarbilki"
    ],
    "name:bel_x_variant":[
        "\u0412\u044f\u0440\u0431\u0456\u043b\u043a\u0456"
    ],
    "name:rus_x_preferred":[
        "\u0412\u0435\u0440\u0431\u0438\u043b\u043a\u0438"
    ],
    "name:und_x_variant":[
        "Vezhbilka",
        "Verbilka",
        "Verbilki"
    ],
    "wof:name":"Verbilki",
    "wof:placetype":"locality"
},
  "geometry": {"coordinates":[24.7018,53.5584],"type":"Point"}
}