{
  "type": "Feature",
  "properties": {
    "gn:admin1_code":"1.0",
    "gn:asciiname":"Vol'ka",
    "gn:country_code":"BY",
    "gn:dem":148,
    "gn:feature_class":"P",
    "gn:feature_code":"PPL",
    "gn:name":"Vol\u2019ka",
    "gn:population":0,
    "gn:timezone":"Europe/Minsk",
    "iso:country":"BY",
    "name:bel_x_preferred":[
        "\u0412\u043e\u043b\u044c\u043a\u0430"
    ],
    "name:eng_x_preferred":[
        "Vol'ka"
    ],
    "name:rus_x_preferred":[
        "\u0412\u043e\u043b\u044c\u043a\u0430"
    ],
    "name:und_x_variant":[
        "Vul\u2019ka",
        "Vol\u2019ka"
    ],
    "wof:name":"Vol'ka",
    "wof:placetype":"locality"
},
  "geometry": {"coordinates":[25.643,52.7829],"type":"Point"}
}