{
  "type": "Feature",
  "properties": {
    "gn:admin1_code":"7.0",
    "gn:asciiname":"Zhuki",
    "gn:country_code":"BY",
    "gn:dem":148,
    "gn:feature_class":"P",
    "gn:feature_code":"PPL",
    "gn:name":"Zhuki",
    "gn:population":0,
    "gn:timezone":"Europe/Minsk",
    "iso:country":"BY",
    "name:rus_x_preferred":[
        "\u0416\u0443\u043a\u0438"
    ],
    "wof:name":"Zhuki",
    "wof:placetype":"locality"
},
  "geometry": {"coordinates":[26.9723,55.1497],"type":"Point"}
}