{
  "type": "Feature",
  "properties": {
    "gn:admin1_code":"7.0",
    "gn:asciiname":"Mazhuyki",
    "gn:country_code":"BY",
    "gn:dem":185,
    "gn:feature_class":"P",
    "gn:feature_code":"PPL",
    "gn:name":"Mazhuyki",
    "gn:population":0,
    "gn:timezone":"Europe/Minsk",
    "iso:country":"BY",
    "name:rus_x_preferred":[
        "\u041c\u0430\u0436\u0443\u0439\u043a\u0438"
    ],
    "wof:name":"Mazhuyki",
    "wof:placetype":"locality"
},
  "geometry": {"coordinates":[28.3899,55.2287],"type":"Point"}
}