{
  "type": "Feature",
  "properties": {
    "gn:admin1_code":"3.0",
    "gn:asciiname":"Lavryshevo",
    "gn:country_code":"BY",
    "gn:dem":133,
    "gn:feature_class":"P",
    "gn:feature_code":"PPL",
    "gn:name":"Lavrysh\u00ebvo",
    "gn:population":0,
    "gn:timezone":"Europe/Minsk",
    "iso:country":"BY",
    "wof:name":"Lavryshevo",
    "wof:placetype":"locality"
},
  "geometry": {"coordinates":[26.1539,53.6908],"type":"Point"}
}