{
  "type": "Feature",
  "properties": {
    "gn:admin1_code":"5.0",
    "gn:asciiname":"Apoliny",
    "gn:country_code":"BY",
    "gn:dem":160,
    "gn:feature_class":"P",
    "gn:feature_code":"PPL",
    "gn:name":"Apoliny",
    "gn:population":0,
    "gn:timezone":"Europe/Minsk",
    "iso:country":"BY",
    "name:rus_x_preferred":[
        "\u0410\u043f\u043e\u043b\u0438\u043d\u044b"
    ],
    "wof:name":"Apoliny",
    "wof:placetype":"locality"
},
  "geometry": {"coordinates":[27.6806,53.1846],"type":"Point"}
}