{
  "type": "Feature",
  "properties": {
    "gn:admin1_code":"5.0",
    "gn:asciiname":"Ubel'",
    "gn:country_code":"BY",
    "gn:dem":166,
    "gn:feature_class":"P",
    "gn:feature_code":"PPL",
    "gn:name":"Ubel\u2019",
    "gn:population":0,
    "gn:timezone":"Europe/Minsk",
    "iso:country":"BY",
    "name:rus_x_preferred":[
        "\u0423\u0431\u0435\u043b\u044c"
    ],
    "name:und_x_variant":[
        "Ubel\u2019"
    ],
    "wof:name":"Ubel'",
    "wof:placetype":"locality"
},
  "geometry": {"coordinates":[28.1257,53.7217],"type":"Point"}
}