{
  "type": "Feature",
  "properties": {
    "gn:admin1_code":"2.0",
    "gn:asciiname":"Nikol'sk",
    "gn:country_code":"BY",
    "gn:dem":154,
    "gn:feature_class":"P",
    "gn:feature_code":"PPL",
    "gn:name":"Nikol\u2019sk",
    "gn:population":0,
    "gn:timezone":"Europe/Minsk",
    "iso:country":"BY",
    "name:rus_x_preferred":[
        "\u041d\u0438\u043a\u043e\u043b\u044c\u0441\u043a"
    ],
    "name:und_x_variant":[
        "Nikol\u2019sk",
        "Nikol\u2019skiy"
    ],
    "wof:name":"Nikol'sk",
    "wof:placetype":"locality"
},
  "geometry": {"coordinates":[30.8638,53.297],"type":"Point"}
}