{
  "type": "Feature",
  "properties": {
    "gn:admin1_code":"6.0",
    "gn:asciiname":"Turlovka",
    "gn:country_code":"BY",
    "gn:dem":157,
    "gn:feature_class":"P",
    "gn:feature_code":"PPL",
    "gn:name":"Turlovka",
    "gn:population":0,
    "gn:timezone":"Europe/Minsk",
    "iso:country":"BY",
    "name:rus_x_preferred":[
        "\u0422\u0443\u0440\u043b\u043e\u0432\u043a\u0430"
    ],
    "wof:name":"Turlovka",
    "wof:placetype":"locality"
},
  "geometry": {"coordinates":[29.9212,53.6449],"type":"Point"}
}