{
  "type": "Feature",
  "properties": {
    "gn:admin1_code":"7.0",
    "gn:asciiname":"Margi",
    "gn:country_code":"BY",
    "gn:dem":201,
    "gn:feature_class":"P",
    "gn:feature_code":"PPL",
    "gn:name":"Margi",
    "gn:population":0,
    "gn:timezone":"Europe/Minsk",
    "iso:country":"BY",
    "name:ceb_x_preferred":[
        "Marg\u00ed"
    ],
    "name:ell_x_preferred":[
        "\u039c\u03b1\u03c1\u03b3\u03af"
    ],
    "name:pol_x_preferred":[
        "Marji"
    ],
    "name:rus_x_preferred":[
        "\u041c\u0430\u0440\u0433\u0438"
    ],
    "name:swe_x_preferred":[
        "Marg\u00ed"
    ],
    "name:urd_x_preferred":[
        "\u0645\u0627\u0631\u06af\u06cc"
    ],
    "wof:name":"Margi",
    "wof:placetype":"locality"
},
  "geometry": {"coordinates":[29.8549,54.6188],"type":"Point"}
}