{
  "type": "Feature",
  "properties": {
    "gn:admin1_code":"3.0",
    "gn:asciiname":"Vintsuki",
    "gn:country_code":"BY",
    "gn:dem":176,
    "gn:feature_class":"P",
    "gn:feature_code":"PPL",
    "gn:name":"Vintsuki",
    "gn:population":0,
    "gn:timezone":"Europe/Minsk",
    "iso:country":"BY",
    "name:rus_x_preferred":[
        "\u0412\u0438\u043d\u0446\u0443\u043a\u0438"
    ],
    "name:und_x_variant":[
        "Vyntsuki",
        "Ventsuki",
        "Vintsuki"
    ],
    "wof:name":"Vintsuki",
    "wof:placetype":"locality"
},
  "geometry": {"coordinates":[25.5028,54.155],"type":"Point"}
}