{
  "type": "Feature",
  "properties": {
    "gn:admin1_code":"7.0",
    "gn:asciiname":"Dedino",
    "gn:country_code":"BY",
    "gn:dem":174,
    "gn:feature_class":"P",
    "gn:feature_code":"PPL",
    "gn:name":"Dedino",
    "gn:population":0,
    "gn:timezone":"Europe/Minsk",
    "iso:country":"BY",
    "name:rus_x_preferred":[
        "\u0414\u0435\u0434\u0438\u043d\u043e"
    ],
    "name:und_x_variant":[
        "Dzedzino",
        "Dziedzina",
        "Dedino"
    ],
    "wof:name":"Dedino",
    "wof:placetype":"locality"
},
  "geometry": {"coordinates":[27.9453,54.96100000000001],"type":"Point"}
}