{
  "type": "Feature",
  "properties": {
    "gn:admin1_code":"2.0",
    "gn:asciiname":"Kruchpol'ye",
    "gn:country_code":"BY",
    "gn:dem":143,
    "gn:feature_class":"P",
    "gn:feature_code":"PPL",
    "gn:name":"Kruchpol\u2019ye",
    "gn:population":0,
    "gn:timezone":"Europe/Minsk",
    "iso:country":"BY",
    "name:rus_x_preferred":[
        "\u041a\u0440\u0443\u0447\u043f\u043e\u043b\u044c\u0435"
    ],
    "name:und_x_variant":[
        "Kruchpol\u2019ye"
    ],
    "wof:name":"Kruchpol'ye",
    "wof:placetype":"locality"
},
  "geometry": {"coordinates":[29.8675,53.1021],"type":"Point"}
}