{
  "type": "Feature",
  "properties": {
    "gn:admin1_code":"0.0",
    "gn:asciiname":"Dyatel",
    "gn:country_code":"BY",
    "gn:dem":211,
    "gn:feature_class":"P",
    "gn:feature_code":"PPL",
    "gn:name":"Dyatel",
    "gn:population":0,
    "gn:timezone":"Europe/Minsk",
    "iso:country":"BY",
    "wof:name":"Dyatel",
    "wof:placetype":"locality"
},
  "geometry": {"coordinates":[30.86667000000001,54.41667],"type":"Point"}
}