{
  "type": "Feature",
  "properties": {
    "gn:admin1_code":"7.0",
    "gn:asciiname":"Novyye Ranchitsy",
    "gn:country_code":"BY",
    "gn:dem":136,
    "gn:feature_class":"P",
    "gn:feature_code":"PPL",
    "gn:name":"Novyye Ranchitsy",
    "gn:population":0,
    "gn:timezone":"Europe/Minsk",
    "iso:country":"BY",
    "name:rus_x_preferred":[
        "\u041d\u043e\u0432\u044b\u0435 \u0420\u0430\u043d\u0447\u0438\u0446\u044b"
    ],
    "wof:name":"Novyye Ranchitsy",
    "wof:placetype":"locality"
},
  "geometry": {"coordinates":[29.4958,55.012],"type":"Point"}
}