{
  "type": "Feature",
  "properties": {
    "gn:admin1_code":"3.0",
    "gn:asciiname":"Popishki",
    "gn:country_code":"BY",
    "gn:dem":148,
    "gn:feature_class":"P",
    "gn:feature_code":"PPL",
    "gn:name":"Popishki",
    "gn:population":0,
    "gn:timezone":"Europe/Minsk",
    "iso:country":"BY",
    "name:rus_x_preferred":[
        "\u041f\u043e\u043f\u0438\u0448\u043a\u0438"
    ],
    "wof:name":"Popishki",
    "wof:placetype":"locality"
},
  "geometry": {"coordinates":[24.9821,54.0295],"type":"Point"}
}