{
  "type": "Feature",
  "properties": {
    "gn:admin1_code":"5.0",
    "gn:asciiname":"Rubilki",
    "gn:country_code":"BY",
    "gn:dem":200,
    "gn:feature_class":"P",
    "gn:feature_code":"PPL",
    "gn:name":"Rubilki",
    "gn:population":0,
    "gn:timezone":"Europe/Minsk",
    "iso:country":"BY",
    "name:bel_x_preferred":[
        "\u0420\u0443\u0431\u0456\u043b\u043a\u0456"
    ],
    "name:eng_x_preferred":[
        "Rubilki"
    ],
    "name:rus_x_preferred":[
        "\u0420\u0443\u0431\u0438\u043b\u043a\u0438"
    ],
    "wof:name":"Rubilki",
    "wof:placetype":"locality"
},
  "geometry": {"coordinates":[27.409,53.6902],"type":"Point"}
}