{
  "type": "Feature",
  "properties": {
    "gn:admin1_code":"3.0",
    "gn:asciiname":"Cherevki",
    "gn:country_code":"BY",
    "gn:dem":141,
    "gn:feature_class":"P",
    "gn:feature_code":"PPL",
    "gn:name":"Cherevki",
    "gn:population":0,
    "gn:timezone":"Europe/Minsk",
    "iso:country":"BY",
    "name:rus_x_preferred":[
        "\u0427\u0435\u0440\u0435\u0432\u043a\u0438"
    ],
    "wof:name":"Cherevki",
    "wof:placetype":"locality"
},
  "geometry": {"coordinates":[25.54241,53.86281],"type":"Point"}
}