{
  "type": "Feature",
  "properties": {
    "gn:admin1_code":"5.0",
    "gn:asciiname":"Buslovka",
    "gn:country_code":"BY",
    "gn:dem":154,
    "gn:feature_class":"P",
    "gn:feature_code":"PPL",
    "gn:name":"Buslovka",
    "gn:population":0,
    "gn:timezone":"Europe/Minsk",
    "iso:country":"BY",
    "name:rus_x_preferred":[
        "\u0411\u0443\u0441\u043b\u043e\u0432\u043a\u0430"
    ],
    "wof:name":"Buslovka",
    "wof:placetype":"locality"
},
  "geometry": {"coordinates":[27.7188,53.0434],"type":"Point"}
}