{
  "type": "Feature",
  "properties": {
    "gn:admin1_code":"5.0",
    "gn:asciiname":"Sivtsy",
    "gn:country_code":"BY",
    "gn:dem":179,
    "gn:feature_class":"P",
    "gn:feature_code":"PPL",
    "gn:name":"Sivtsy",
    "gn:population":0,
    "gn:timezone":"Europe/Minsk",
    "iso:country":"BY",
    "name:rus_x_preferred":[
        "\u0421\u0438\u0432\u0446\u044b"
    ],
    "name:und_x_variant":[
        "Siwce",
        "Sivtse",
        "Sivtsy"
    ],
    "wof:name":"Sivtsy",
    "wof:placetype":"locality"
},
  "geometry": {"coordinates":[27.3829,54.7091],"type":"Point"}
}