{
  "type": "Feature",
  "properties": {
    "gn:admin1_code":"7.0",
    "gn:asciiname":"Mit'kovtsy",
    "gn:country_code":"BY",
    "gn:dem":138,
    "gn:feature_class":"P",
    "gn:feature_code":"PPL",
    "gn:name":"Mit\u2019kovtsy",
    "gn:population":0,
    "gn:timezone":"Europe/Minsk",
    "iso:country":"BY",
    "name:rus_x_preferred":[
        "\u041c\u0438\u0442\u044c\u043a\u043e\u0432\u0446\u044b"
    ],
    "name:und_x_variant":[
        "Mit\u2019kovtsy"
    ],
    "wof:name":"Mit'kovtsy",
    "wof:placetype":"locality"
},
  "geometry": {"coordinates":[29.2865,54.8796],"type":"Point"}
}