{
  "type": "Feature",
  "properties": {
    "gn:admin1_code":"2.0",
    "gn:asciiname":"Proletariy",
    "gn:country_code":"BY",
    "gn:dem":139,
    "gn:feature_class":"P",
    "gn:feature_code":"PPL",
    "gn:name":"Proletariy",
    "gn:population":0,
    "gn:timezone":"Europe/Minsk",
    "iso:country":"BY",
    "name:bel_x_preferred":[
        "\u041f\u0440\u0430\u043b\u0435\u0442\u0430\u0440\u044b\u0439"
    ],
    "name:ceb_x_preferred":[
        "Proletariy"
    ],
    "name:che_x_preferred":[
        "\u041f\u0440\u043e\u043b\u0435\u0442\u0430\u0440\u0438"
    ],
    "name:deu_x_preferred":[
        "Proletari"
    ],
    "name:est_x_preferred":[
        "Proletari"
    ],
    "name:fin_x_preferred":[
        "Proletari"
    ],
    "name:hye_x_preferred":[
        "\u054a\u0580\u0578\u056c\u0565\u057f\u0561\u0580\u056b"
    ],
    "name:ita_x_preferred":[
        "Proletarij"
    ],
    "name:pol_x_preferred":[
        "Proletarij"
    ],
    "name:rus_x_preferred":[
        "\u041f\u0440\u043e\u043b\u0435\u0442\u0430\u0440\u0438\u0439"
    ],
    "name:srp_x_preferred":[
        "\u041f\u0440\u043e\u043b\u0435\u0442\u0430\u0440\u0438\u0458"
    ],
    "wof:name":"Proletariy",
    "wof:placetype":"locality"
},
  "geometry": {"coordinates":[31.28056,53.06889],"type":"Point"}
}