{
  "type": "Feature",
  "properties": {
    "gn:admin1_code":"6.0",
    "gn:asciiname":"Krapivka",
    "gn:country_code":"BY",
    "gn:dem":151,
    "gn:feature_class":"P",
    "gn:feature_code":"PPL",
    "gn:name":"Krapivka",
    "gn:population":0,
    "gn:timezone":"Europe/Minsk",
    "iso:country":"BY",
    "name:rus_x_preferred":[
        "\u041a\u0440\u0430\u043f\u0438\u0432\u043a\u0430"
    ],
    "wof:name":"Krapivka",
    "wof:placetype":"locality"
},
  "geometry": {"coordinates":[29.3214,53.1461],"type":"Point"}
}