{
  "type": "Feature",
  "properties": {
    "gn:admin1_code":"0.0",
    "gn:asciiname":"Malo-Borovaya",
    "gn:country_code":"BY",
    "gn:dem":182,
    "gn:feature_class":"P",
    "gn:feature_code":"PPL",
    "gn:name":"Malo-Borovaya",
    "gn:population":0,
    "gn:timezone":"Europe/Minsk",
    "iso:country":"BY",
    "wof:name":"Malo-Borovaya",
    "wof:placetype":"locality"
},
  "geometry": {"coordinates":[27.96667,53.13333000000001],"type":"Point"}
}