{
  "type": "Feature",
  "properties": {
    "gn:admin1_code":"7.0",
    "gn:asciiname":"Chernichenki",
    "gn:country_code":"BY",
    "gn:dem":137,
    "gn:feature_class":"P",
    "gn:feature_code":"PPL",
    "gn:name":"Chernichenki",
    "gn:population":0,
    "gn:timezone":"Europe/Minsk",
    "iso:country":"BY",
    "name:rus_x_preferred":[
        "\u0427\u0435\u0440\u043d\u0438\u0447\u0435\u043d\u043a\u0438"
    ],
    "wof:name":"Chernichenki",
    "wof:placetype":"locality"
},
  "geometry": {"coordinates":[28.6967,55.246],"type":"Point"}
}