{
  "type": "Feature",
  "properties": {
    "gn:admin1_code":"7.0",
    "gn:asciiname":"Vyarkhowye",
    "gn:country_code":"BY",
    "gn:dem":137,
    "gn:feature_class":"P",
    "gn:feature_code":"PPL",
    "gn:name":"Vyarkhowye",
    "gn:population":0,
    "gn:timezone":"Europe/Minsk",
    "iso:country":"BY",
    "name:bel_x_preferred":[
        "\u0412\u044f\u0440\u0445\u043e\u045e\u0435"
    ],
    "name:eng_x_preferred":[
        "Verkhov'ye"
    ],
    "name:rus_x_preferred":[
        "\u0412\u0435\u0440\u0445\u043e\u0432\u044c\u0435"
    ],
    "name:und_x_variant":[
        "Verkhov\u2019ye",
        "Vyarkhowye"
    ],
    "wof:name":"Vyarkhowye",
    "wof:placetype":"locality"
},
  "geometry": {"coordinates":[29.3933,54.9659],"type":"Point"}
}