{
  "type": "Feature",
  "properties": {
    "gn:admin1_code":"7.0",
    "gn:asciiname":"Tarasovo",
    "gn:country_code":"BY",
    "gn:dem":155,
    "gn:feature_class":"P",
    "gn:feature_code":"PPL",
    "gn:name":"Tarasovo",
    "gn:population":0,
    "gn:timezone":"Europe/Minsk",
    "iso:country":"BY",
    "name:che_x_preferred":[
        "\u0422\u0430\u0440\u0430\u0441\u043e\u0432\u043e"
    ],
    "name:rus_x_preferred":[
        "\u0422\u0430\u0440\u0430\u0441\u043e\u0432\u043e"
    ],
    "wof:name":"Tarasovo",
    "wof:placetype":"locality"
},
  "geometry": {"coordinates":[29.6523,55.6788],"type":"Point"}
}