{
  "type": "Feature",
  "properties": {
    "gn:admin1_code":"5.0",
    "gn:asciiname":"Pisarevshchina",
    "gn:country_code":"BY",
    "gn:dem":188,
    "gn:feature_class":"P",
    "gn:feature_code":"PPL",
    "gn:name":"Pisarevshchina",
    "gn:population":0,
    "gn:timezone":"Europe/Minsk",
    "iso:country":"BY",
    "name:rus_x_preferred":[
        "\u041f\u0438\u0441\u0430\u0440\u0435\u0432\u0449\u0438\u043d\u0430"
    ],
    "wof:name":"Pisarevshchina",
    "wof:placetype":"locality"
},
  "geometry": {"coordinates":[27.1598,53.6199],"type":"Point"}
}