{
  "type": "Feature",
  "properties": {
    "gn:admin1_code":"0.0",
    "gn:asciiname":"Dubenskiye",
    "gn:country_code":"BY",
    "gn:dem":163,
    "gn:feature_class":"P",
    "gn:feature_code":"PPL",
    "gn:name":"Dubenskiye",
    "gn:population":0,
    "gn:timezone":"Europe/Minsk",
    "iso:country":"BY",
    "wof:name":"Dubenskiye",
    "wof:placetype":"locality"
},
  "geometry": {"coordinates":[29.63333,53.65],"type":"Point"}
}