{
  "type": "Feature",
  "properties": {
    "gn:admin1_code":"5.0",
    "gn:asciiname":"Myatlichytsy",
    "gn:country_code":"BY",
    "gn:dem":241,
    "gn:feature_class":"P",
    "gn:feature_code":"PPL",
    "gn:name":"Myatlichytsy",
    "gn:population":0,
    "gn:timezone":"Europe/Minsk",
    "iso:country":"BY",
    "name:bel_x_preferred":[
        "\u041c\u044f\u0442\u043b\u0456\u0447\u044b\u0446\u044b"
    ],
    "name:und_x_variant":[
        "Mietliczyce",
        "Metlichitsy",
        "Myatlichytsy"
    ],
    "wof:name":"Myatlichytsy",
    "wof:placetype":"locality"
},
  "geometry": {"coordinates":[27.8832,54.4856],"type":"Point"}
}