{
  "type": "Feature",
  "properties": {
    "gn:admin1_code":"5.0",
    "gn:asciiname":"Zaremby",
    "gn:country_code":"BY",
    "gn:dem":198,
    "gn:feature_class":"P",
    "gn:feature_code":"PPL",
    "gn:name":"Zaremby",
    "gn:population":0,
    "gn:timezone":"Europe/Minsk",
    "iso:country":"BY",
    "name:rus_x_preferred":[
        "\u0417\u0430\u0440\u0435\u043c\u0431\u044b"
    ],
    "wof:name":"Zaremby",
    "wof:placetype":"locality"
},
  "geometry": {"coordinates":[28.1766,54.4758],"type":"Point"}
}