{
  "type": "Feature",
  "properties": {
    "gn:admin1_code":"7.0",
    "gn:asciiname":"Chernetskoye",
    "gn:country_code":"BY",
    "gn:dem":155,
    "gn:feature_class":"P",
    "gn:feature_code":"PPL",
    "gn:name":"Chernetskoye",
    "gn:population":0,
    "gn:timezone":"Europe/Minsk",
    "iso:country":"BY",
    "name:rus_x_preferred":[
        "\u0427\u0435\u0440\u043d\u0435\u0446\u043a\u043e\u0435"
    ],
    "wof:name":"Chernetskoye",
    "wof:placetype":"locality"
},
  "geometry": {"coordinates":[29.643,55.1695],"type":"Point"}
}