{
  "type": "Feature",
  "properties": {
    "gn:admin1_code":"5.0",
    "gn:asciiname":"Kulikovo",
    "gn:country_code":"BY",
    "gn:dem":191,
    "gn:feature_class":"P",
    "gn:feature_code":"PPL",
    "gn:name":"Kulikovo",
    "gn:population":0,
    "gn:timezone":"Europe/Minsk",
    "iso:country":"BY",
    "name:rus_x_preferred":[
        "\u041a\u0443\u043b\u0438\u043a\u043e\u0432\u043e"
    ],
    "wof:name":"Kulikovo",
    "wof:placetype":"locality"
},
  "geometry": {"coordinates":[27.3844,54.8269],"type":"Point"}
}