{
  "type": "Feature",
  "properties": {
    "gn:admin1_code":"5.0",
    "gn:asciiname":"Turok",
    "gn:country_code":"BY",
    "gn:dem":138,
    "gn:feature_class":"P",
    "gn:feature_code":"PPL",
    "gn:name":"Turok",
    "gn:population":0,
    "gn:timezone":"Europe/Minsk",
    "iso:country":"BY",
    "name:deu_x_preferred":[
        "Turok"
    ],
    "name:fra_x_preferred":[
        "Turok"
    ],
    "name:ita_x_preferred":[
        "Turok"
    ],
    "name:lit_x_preferred":[
        "Turokas"
    ],
    "name:pol_x_preferred":[
        "Turok"
    ],
    "name:por_x_preferred":[
        "Turok"
    ],
    "name:rus_x_preferred":[
        "\u0422\u0443\u0440\u043e\u043a"
    ],
    "name:spa_x_preferred":[
        "Turok"
    ],
    "wof:name":"Turok",
    "wof:placetype":"locality"
},
  "geometry": {"coordinates":[27.9038,52.6638],"type":"Point"}
}