{
  "type": "Feature",
  "properties": {
    "gn:admin1_code":"5.0",
    "gn:asciiname":"Khomichi",
    "gn:country_code":"BY",
    "gn:dem":235,
    "gn:feature_class":"P",
    "gn:feature_code":"PPL",
    "gn:name":"Khomichi",
    "gn:population":0,
    "gn:timezone":"Europe/Minsk",
    "iso:country":"BY",
    "name:rus_x_preferred":[
        "\u0425\u043e\u043c\u0438\u0447\u0438"
    ],
    "wof:name":"Khomichi",
    "wof:placetype":"locality"
},
  "geometry": {"coordinates":[26.8197,53.9213],"type":"Point"}
}