{
  "type": "Feature",
  "properties": {
    "gn:admin1_code":"1.0",
    "gn:asciiname":"Mokraye",
    "gn:country_code":"BY",
    "gn:dem":167,
    "gn:feature_class":"P",
    "gn:feature_code":"PPL",
    "gn:name":"Mokraye",
    "gn:population":0,
    "gn:timezone":"Europe/Minsk",
    "iso:country":"BY",
    "name:bel_x_preferred":[
        "\u041c\u043e\u043a\u0440\u0430\u0435"
    ],
    "name:bel_x_variant":[
        "Mokraye"
    ],
    "name:und_x_variant":[
        "Mokroye",
        "Mokraye"
    ],
    "wof:name":"Mokraye",
    "wof:placetype":"locality"
},
  "geometry": {"coordinates":[24.4181,52.6533],"type":"Point"}
}