{
  "type": "Feature",
  "properties": {
    "gn:admin1_code":"6.0",
    "gn:asciiname":"Prodvino",
    "gn:country_code":"BY",
    "gn:dem":134,
    "gn:feature_class":"P",
    "gn:feature_code":"PPL",
    "gn:name":"Prodvino",
    "gn:population":0,
    "gn:timezone":"Europe/Minsk",
    "iso:country":"BY",
    "name:rus_x_preferred":[
        "\u041f\u0440\u043e\u0434\u0432\u0438\u043d\u043e"
    ],
    "wof:name":"Prodvino",
    "wof:placetype":"locality"
},
  "geometry": {"coordinates":[29.2256,52.9857],"type":"Point"}
}