{
  "type": "Feature",
  "properties": {
    "gn:admin1_code":"6.0",
    "gn:asciiname":"Lutno",
    "gn:country_code":"BY",
    "gn:dem":191,
    "gn:feature_class":"P",
    "gn:feature_code":"PPL",
    "gn:name":"Lutno",
    "gn:population":0,
    "gn:timezone":"Europe/Minsk",
    "iso:country":"BY",
    "name:rus_x_preferred":[
        "\u041b\u0443\u0442\u043d\u043e"
    ],
    "wof:name":"Lutno",
    "wof:placetype":"locality"
},
  "geometry": {"coordinates":[30.1435,54.1976],"type":"Point"}
}