{
  "type": "Feature",
  "properties": {
    "gn:admin1_code":"6.0",
    "gn:asciiname":"Tsitowka",
    "gn:country_code":"BY",
    "gn:dem":167,
    "gn:feature_class":"P",
    "gn:feature_code":"PPL",
    "gn:name":"Tsitowka",
    "gn:population":0,
    "gn:timezone":"Europe/Minsk",
    "iso:country":"BY",
    "name:bel_x_preferred":[
        "\u0426\u0456\u0442\u043e\u045e\u043a\u0430"
    ],
    "name:und_x_variant":[
        "Titovka",
        "Podtitovka"
    ],
    "wof:name":"Tsitowka",
    "wof:placetype":"locality"
},
  "geometry": {"coordinates":[31.6986,53.4333],"type":"Point"}
}