{
  "type": "Feature",
  "properties": {
    "gn:admin1_code":"5.0",
    "gn:asciiname":"Mazulevshchina",
    "gn:country_code":"BY",
    "gn:dem":221,
    "gn:feature_class":"P",
    "gn:feature_code":"PPL",
    "gn:name":"Mazul\u00ebvshchina",
    "gn:population":0,
    "gn:timezone":"Europe/Minsk",
    "iso:country":"BY",
    "name:rus_x_preferred":[
        "\u041c\u0430\u0437\u0443\u043b\u0451\u0432\u0449\u0438\u043d\u0430"
    ],
    "name:und_x_variant":[
        "Mazul\u00ebvshchina"
    ],
    "wof:name":"Mazulevshchina",
    "wof:placetype":"locality"
},
  "geometry": {"coordinates":[26.7013,53.8668],"type":"Point"}
}