{
  "type": "Feature",
  "properties": {
    "gn:admin1_code":"7.0",
    "gn:asciiname":"Velikoye Pole",
    "gn:country_code":"BY",
    "gn:dem":193,
    "gn:feature_class":"P",
    "gn:feature_code":"PPL",
    "gn:name":"Velikoye Pole",
    "gn:population":0,
    "gn:timezone":"Europe/Minsk",
    "iso:country":"BY",
    "name:rus_x_preferred":[
        "\u0412\u0435\u043b\u0438\u043a\u043e\u0435 \u041f\u043e\u043b\u0435"
    ],
    "name:und_x_variant":[
        "Wielkie Pole",
        "Velikoye Pole"
    ],
    "wof:name":"Velikoye Pole",
    "wof:placetype":"locality"
},
  "geometry": {"coordinates":[27.8552,54.6824],"type":"Point"}
}