{
  "type": "Feature",
  "properties": {
    "gn:admin1_code":"6.0",
    "gn:asciiname":"Budochka",
    "gn:country_code":"BY",
    "gn:dem":168,
    "gn:feature_class":"P",
    "gn:feature_code":"PPL",
    "gn:name":"Budochka",
    "gn:population":0,
    "gn:timezone":"Europe/Minsk",
    "iso:country":"BY",
    "name:rus_x_preferred":[
        "\u0411\u0443\u0434\u043e\u0447\u043a\u0430"
    ],
    "wof:name":"Budochka",
    "wof:placetype":"locality"
},
  "geometry": {"coordinates":[32.4294,53.4735],"type":"Point"}
}