{
  "type": "Feature",
  "properties": {
    "gn:admin1_code":"3.0",
    "gn:asciiname":"Ballya-Sol'naya",
    "gn:country_code":"BY",
    "gn:dem":94,
    "gn:feature_class":"P",
    "gn:feature_code":"PPL",
    "gn:name":"Ballya-Sol\u2019naya",
    "gn:population":0,
    "gn:timezone":"Europe/Minsk",
    "iso:country":"BY",
    "name:rus_x_preferred":[
        "\u0411\u0430\u043b\u043b\u044f-\u0421\u043e\u043b\u044c\u043d\u0430\u044f"
    ],
    "name:und_x_variant":[
        "Ballya-Sol\u2019naya",
        "Balya-Sol\u2019naya"
    ],
    "wof:name":"Ballya-Sol'naya",
    "wof:placetype":"locality"
},
  "geometry": {"coordinates":[23.7781,53.7251],"type":"Point"}
}