{
  "type": "Feature",
  "properties": {
    "gn:admin1_code":"0.0",
    "gn:asciiname":"Matvyan'tse",
    "gn:country_code":"BY",
    "gn:dem":162,
    "gn:feature_class":"P",
    "gn:feature_code":"PPL",
    "gn:name":"Matvyan\u2019tse",
    "gn:population":0,
    "gn:timezone":"Europe/Minsk",
    "iso:country":"BY",
    "wof:name":"Matvyan'tse",
    "wof:placetype":"locality"
},
  "geometry": {"coordinates":[25.26667,54.06667],"type":"Point"}
}