{
  "type": "Feature",
  "properties": {
    "gn:admin1_code":"6.0",
    "gn:asciiname":"Viduytsy",
    "gn:country_code":"BY",
    "gn:dem":149,
    "gn:feature_class":"P",
    "gn:feature_code":"PPL",
    "gn:name":"Viduytsy",
    "gn:population":0,
    "gn:timezone":"Europe/Minsk",
    "iso:country":"BY",
    "name:rus_x_preferred":[
        "\u0412\u0438\u0434\u0443\u0439\u0446\u044b"
    ],
    "wof:name":"Viduytsy",
    "wof:placetype":"locality"
},
  "geometry": {"coordinates":[31.7347,53.2265],"type":"Point"}
}