{
  "type": "Feature",
  "properties": {
    "gn:admin1_code":"7.0",
    "gn:asciiname":"Ozery",
    "gn:country_code":"BY",
    "gn:dem":173,
    "gn:feature_class":"P",
    "gn:feature_code":"PPL",
    "gn:name":"Oz\u00ebry",
    "gn:population":0,
    "gn:timezone":"Europe/Minsk",
    "iso:country":"BY",
    "name:eng_x_preferred":[
        "Oz\u00ebry"
    ],
    "name:rus_x_preferred":[
        "\u041e\u0437\u0435\u0440\u044b"
    ],
    "name:rus_x_variant":[
        "\u041e\u0437\u0451\u0440\u044b"
    ],
    "wof:name":"Ozery",
    "wof:placetype":"locality"
},
  "geometry": {"coordinates":[30.7617,54.7625],"type":"Point"}
}