{
  "type": "Feature",
  "properties": {
    "gn:admin1_code":"5.0",
    "gn:asciiname":"Sobkovshchina",
    "gn:country_code":"BY",
    "gn:dem":258,
    "gn:feature_class":"P",
    "gn:feature_code":"PPL",
    "gn:name":"Sobkovshchina",
    "gn:population":0,
    "gn:timezone":"Europe/Minsk",
    "iso:country":"BY",
    "name:rus_x_preferred":[
        "\u0421\u043e\u0431\u043a\u043e\u0432\u0449\u0438\u043d\u0430"
    ],
    "wof:name":"Sobkovshchina",
    "wof:placetype":"locality"
},
  "geometry": {"coordinates":[26.8703,53.7863],"type":"Point"}
}