{
  "type": "Feature",
  "properties": {
    "gn:admin1_code":"6.0",
    "gn:asciiname":"Lekerta",
    "gn:country_code":"BY",
    "gn:dem":148,
    "gn:feature_class":"P",
    "gn:feature_code":"PPL",
    "gn:name":"Lekerta",
    "gn:population":0,
    "gn:timezone":"Europe/Minsk",
    "iso:country":"BY",
    "name:rus_x_preferred":[
        "\u041b\u0435\u043a\u0435\u0440\u0442\u0430"
    ],
    "wof:name":"Lekerta",
    "wof:placetype":"locality"
},
  "geometry": {"coordinates":[29.147,53.1126],"type":"Point"}
}