{
  "type": "Feature",
  "properties": {
    "gn:admin1_code":"7.0",
    "gn:asciiname":"Nesterovshchina",
    "gn:country_code":"BY",
    "gn:dem":172,
    "gn:feature_class":"P",
    "gn:feature_code":"PPL",
    "gn:name":"Nesterovshchina",
    "gn:population":0,
    "gn:timezone":"Europe/Minsk",
    "iso:country":"BY",
    "name:eng_x_preferred":[
        "Nesterovshchina"
    ],
    "name:rus_x_preferred":[
        "\u041d\u0435\u0441\u0442\u0435\u0440\u043e\u0432\u0449\u0438\u043d\u0430"
    ],
    "name:und_x_variant":[
        "Nes\u2019tserovshchyzna"
    ],
    "wof:name":"Nesterovshchina",
    "wof:placetype":"locality"
},
  "geometry": {"coordinates":[28.0096,54.9549],"type":"Point"}
}