{
  "type": "Feature",
  "properties": {
    "gn:admin1_code":"7.0",
    "gn:asciiname":"Melevtsy",
    "gn:country_code":"BY",
    "gn:dem":155,
    "gn:feature_class":"P",
    "gn:feature_code":"PPL",
    "gn:name":"Mel\u00ebvtsy",
    "gn:population":0,
    "gn:timezone":"Europe/Minsk",
    "iso:country":"BY",
    "name:pol_x_preferred":[
        "Mielowce"
    ],
    "name:rus_x_preferred":[
        "\u041c\u0435\u043b\u0451\u0432\u0446\u044b"
    ],
    "name:und_x_variant":[
        "Mel\u00ebvtse",
        "Mel\u00ebvtsy"
    ],
    "wof:name":"Melevtsy",
    "wof:placetype":"locality"
},
  "geometry": {"coordinates":[27.1866,55.5899],"type":"Point"}
}