{
  "type": "Feature",
  "properties": {
    "gn:admin1_code":"3.0",
    "gn:asciiname":"Lobachi",
    "gn:country_code":"BY",
    "gn:dem":158,
    "gn:feature_class":"P",
    "gn:feature_code":"PPL",
    "gn:name":"Lobachi",
    "gn:population":0,
    "gn:timezone":"Europe/Minsk",
    "iso:country":"BY",
    "name:rus_x_preferred":[
        "\u041b\u043e\u0431\u0430\u0447\u0438"
    ],
    "wof:name":"Lobachi",
    "wof:placetype":"locality"
},
  "geometry": {"coordinates":[25.8431,54.028],"type":"Point"}
}