{
  "type": "Feature",
  "properties": {
    "gn:admin1_code":"0.0",
    "gn:asciiname":"Novaya Zhittya",
    "gn:cc2":"BY",
    "gn:country_code":"BY",
    "gn:dem":136,
    "gn:feature_class":"P",
    "gn:feature_code":"PPL",
    "gn:name":"Novaya Zhittya",
    "gn:population":0,
    "gn:timezone":"Europe/Minsk",
    "iso:country":"BY",
    "name:und_x_variant":[
        "Novo-Zhittya",
        "Novaya Zhittya"
    ],
    "wof:name":"Novaya Zhittya",
    "wof:placetype":"locality"
},
  "geometry": {"coordinates":[29.55,52.96666999999999],"type":"Point"}
}