{
  "type": "Feature",
  "properties": {
    "gn:admin1_code":"5.0",
    "gn:asciiname":"Zelenyy Gay",
    "gn:country_code":"BY",
    "gn:dem":181,
    "gn:feature_class":"P",
    "gn:feature_code":"PPL",
    "gn:name":"Zel\u00ebnyy Gay",
    "gn:population":0,
    "gn:timezone":"Europe/Minsk",
    "iso:country":"BY",
    "name:rus_x_preferred":[
        "\u0417\u0435\u043b\u0451\u043d\u044b\u0439 \u0413\u0430\u0439"
    ],
    "name:und_x_variant":[
        "Zel\u00ebnyy Gay"
    ],
    "wof:name":"Zelenyy Gay",
    "wof:placetype":"locality"
},
  "geometry": {"coordinates":[28.7122,53.8412],"type":"Point"}
}