{
  "type": "Feature",
  "properties": {
    "gn:admin1_code":"1.0",
    "gn:asciiname":"Yablochno",
    "gn:country_code":"BY",
    "gn:dem":157,
    "gn:feature_class":"P",
    "gn:feature_code":"PPL",
    "gn:name":"Yablochno",
    "gn:population":0,
    "gn:timezone":"Europe/Minsk",
    "iso:country":"BY",
    "name:rus_x_preferred":[
        "\u042f\u0431\u043b\u043e\u0447\u043d\u043e"
    ],
    "name:und_x_variant":[
        "Yablochnoye"
    ],
    "wof:name":"Yablochno",
    "wof:placetype":"locality"
},
  "geometry": {"coordinates":[24.0422,51.7029],"type":"Point"}
}