{
  "type": "Feature",
  "properties": {
    "gn:admin1_code":"5.0",
    "gn:asciiname":"Belye Borki",
    "gn:country_code":"BY",
    "gn:dem":173,
    "gn:feature_class":"P",
    "gn:feature_code":"PPL",
    "gn:name":"Belye Borki",
    "gn:population":0,
    "gn:timezone":"Europe/Minsk",
    "iso:country":"BY",
    "name:eng_x_historical":[
        "Barki"
    ],
    "name:eng_x_preferred":[
        "Belye Borki"
    ],
    "name:eng_x_variant":[
        "Barki"
    ],
    "name:rus_x_preferred":[
        "\u0411\u0435\u043b\u044b\u0435 \u0411\u043e\u0440\u043a\u0438"
    ],
    "wof:name":"Belye Borki",
    "wof:placetype":"locality"
},
  "geometry": {"coordinates":[29.1172,54.5719],"type":"Point"}
}