{
  "type": "Feature",
  "properties": {
    "gn:admin1_code":"3.0",
    "gn:asciiname":"Rozhanka",
    "gn:country_code":"BY",
    "gn:dem":145,
    "gn:feature_class":"P",
    "gn:feature_code":"PPL",
    "gn:name":"Rozhanka",
    "gn:population":0,
    "gn:timezone":"Europe/Minsk",
    "iso:country":"BY",
    "name:bel_x_preferred":[
        "\u0420\u0430\u0436\u0430\u043d\u043a\u0430"
    ],
    "name:eng_x_preferred":[
        "Rozhanka"
    ],
    "name:rus_x_preferred":[
        "\u0420\u043e\u0436\u0430\u043d\u043a\u0430"
    ],
    "name:rus_x_variant":[
        "Pos\u00eblok Rozhanka"
    ],
    "name:und_x_variant":[
        "R\u00f3\u017canka",
        "Ruzhanka",
        "Rozhanka",
        "Razhanka"
    ],
    "wof:name":"Rozhanka",
    "wof:placetype":"locality"
},
  "geometry": {"coordinates":[24.7365,53.536],"type":"Point"}
}