{
  "type": "Feature",
  "properties": {
    "gn:admin1_code":"6.0",
    "gn:asciiname":"Bol'shoye Zapol'ye",
    "gn:country_code":"BY",
    "gn:dem":212,
    "gn:feature_class":"P",
    "gn:feature_code":"PPL",
    "gn:name":"Bol\u2019shoye Zapol\u2019ye",
    "gn:population":0,
    "gn:timezone":"Europe/Minsk",
    "iso:country":"BY",
    "name:rus_x_preferred":[
        "\u0411\u043e\u043b\u044c\u0448\u043e\u0435 \u0417\u0430\u043f\u043e\u043b\u044c\u0435"
    ],
    "name:und_x_variant":[
        "Bol\u2019shoye Zapol\u2019ye"
    ],
    "wof:name":"Bol'shoye Zapol'ye",
    "wof:placetype":"locality"
},
  "geometry": {"coordinates":[31.2178,54.0415],"type":"Point"}
}