{
  "type": "Feature",
  "properties": {
    "gn:admin1_code":"5.0",
    "gn:asciiname":"Ukhvala",
    "gn:country_code":"BY",
    "gn:dem":174,
    "gn:feature_class":"P",
    "gn:feature_code":"PPL",
    "gn:name":"Ukhvala",
    "gn:population":0,
    "gn:timezone":"Europe/Minsk",
    "iso:country":"BY",
    "name:bel_x_preferred":[
        "\u0423\u0445\u0432\u0430\u043b\u0430"
    ],
    "name:eng_x_preferred":[
        "Ukhvala"
    ],
    "name:rus_x_preferred":[
        "\u0423\u0445\u0432\u0430\u043b\u0430"
    ],
    "wof:name":"Ukhvala",
    "wof:placetype":"locality"
},
  "geometry": {"coordinates":[29.2142,54.1062],"type":"Point"}
}