{
  "type": "Feature",
  "properties": {
    "gn:admin1_code":"7.0",
    "gn:asciiname":"Novoye Selo",
    "gn:country_code":"BY",
    "gn:dem":205,
    "gn:feature_class":"P",
    "gn:feature_code":"PPL",
    "gn:name":"Novoye Selo",
    "gn:population":0,
    "gn:timezone":"Europe/Minsk",
    "iso:country":"BY",
    "name:rus_x_preferred":[
        "\u041d\u043e\u0432\u043e\u0435 \u0421\u0435\u043b\u043e"
    ],
    "wof:name":"Novoye Selo",
    "wof:placetype":"locality"
},
  "geometry": {"coordinates":[30.2943,54.6519],"type":"Point"}
}