{
  "type": "Feature",
  "properties": {
    "gn:admin1_code":"3.0",
    "gn:asciiname":"Lazduny Druhiya",
    "gn:country_code":"BY",
    "gn:dem":144,
    "gn:feature_class":"P",
    "gn:feature_code":"PPL",
    "gn:name":"Lazduny Druhiya",
    "gn:population":0,
    "gn:timezone":"Europe/Minsk",
    "iso:country":"BY",
    "name:bel_x_preferred":[
        "\u041b\u0430\u0437\u0434\u0443\u043d\u044b \u0414\u0440\u0443\u0433\u0456\u044f"
    ],
    "name:und_x_variant":[
        "Lazduny Pervyye"
    ],
    "wof:name":"Lazduny Druhiya",
    "wof:placetype":"locality"
},
  "geometry": {"coordinates":[25.9598,53.9286],"type":"Point"}
}