{
  "type": "Feature",
  "properties": {
    "gn:admin1_code":"3.0",
    "gn:asciiname":"Kukhari",
    "gn:country_code":"BY",
    "gn:dem":145,
    "gn:feature_class":"P",
    "gn:feature_code":"PPL",
    "gn:name":"Kukhari",
    "gn:population":0,
    "gn:timezone":"Europe/Minsk",
    "iso:country":"BY",
    "name:rus_x_preferred":[
        "\u041a\u0443\u0445\u0430\u0440\u0438"
    ],
    "wof:name":"Kukhari",
    "wof:placetype":"locality"
},
  "geometry": {"coordinates":[24.5587,53.6326],"type":"Point"}
}