{
  "type": "Feature",
  "properties": {
    "gn:admin1_code":"3.0",
    "gn:asciiname":"Navasady",
    "gn:country_code":"BY",
    "gn:dem":181,
    "gn:feature_class":"P",
    "gn:feature_code":"PPL",
    "gn:name":"Navasady",
    "gn:population":0,
    "gn:timezone":"Europe/Minsk",
    "iso:country":"BY",
    "name:bel_x_preferred":[
        "\u041d\u0430\u0432\u0430\u0441\u0430\u0434\u044b"
    ],
    "name:und_x_variant":[
        "Novosady"
    ],
    "wof:name":"Navasady",
    "wof:placetype":"locality"
},
  "geometry": {"coordinates":[24.4546,52.938],"type":"Point"}
}