{
  "type": "Feature",
  "properties": {
    "gn:admin1_code":"0.0",
    "gn:asciiname":"Koze Penno",
    "gn:cc2":"BY",
    "gn:country_code":"BY",
    "gn:dem":147,
    "gn:feature_class":"P",
    "gn:feature_code":"PPL",
    "gn:name":"Koze Penno",
    "gn:population":0,
    "gn:timezone":"Europe/Minsk",
    "iso:country":"BY",
    "name:und_x_variant":[
        "Kozie Pienno",
        "Koze Penno"
    ],
    "wof:name":"Koze Penno",
    "wof:placetype":"locality"
},
  "geometry": {"coordinates":[26.35,53.91667],"type":"Point"}
}