{
  "type": "Feature",
  "properties": {
    "gn:admin1_code":"7.0",
    "gn:asciiname":"Zaborovno",
    "gn:country_code":"BY",
    "gn:dem":142,
    "gn:feature_class":"P",
    "gn:feature_code":"PPL",
    "gn:name":"Zaborovno",
    "gn:population":0,
    "gn:timezone":"Europe/Minsk",
    "iso:country":"BY",
    "name:rus_x_preferred":[
        "\u0417\u0430\u0431\u043e\u0440\u043e\u0432\u043d\u043e"
    ],
    "wof:name":"Zaborovno",
    "wof:placetype":"locality"
},
  "geometry": {"coordinates":[28.4962,55.2217],"type":"Point"}
}