{
  "type": "Feature",
  "properties": {
    "gn:admin1_code":"3.0",
    "gn:asciiname":"Odla",
    "gn:country_code":"BY",
    "gn:dem":122,
    "gn:feature_class":"P",
    "gn:feature_code":"PPL",
    "gn:name":"Odla",
    "gn:population":0,
    "gn:timezone":"Europe/Minsk",
    "iso:country":"BY",
    "name:rus_x_preferred":[
        "\u041e\u0434\u043b\u0430"
    ],
    "wof:name":"Odla",
    "wof:placetype":"locality"
},
  "geometry": {"coordinates":[23.8634,53.3713],"type":"Point"}
}