{
  "type": "Feature",
  "properties": {
    "gn:admin1_code":"1.0",
    "gn:asciiname":"Vybrody",
    "gn:country_code":"BY",
    "gn:dem":164,
    "gn:feature_class":"P",
    "gn:feature_code":"PPL",
    "gn:name":"Vybrody",
    "gn:population":0,
    "gn:timezone":"Europe/Minsk",
    "iso:country":"BY",
    "name:rus_x_preferred":[
        "\u0412\u044b\u0431\u0440\u043e\u0434\u044b"
    ],
    "wof:name":"Vybrody",
    "wof:placetype":"locality"
},
  "geometry": {"coordinates":[24.1941,52.7428],"type":"Point"}
}