{
  "type": "Feature",
  "properties": {
    "gn:admin1_code":"5.0",
    "gn:asciiname":"Usha Vtoraya",
    "gn:country_code":"BY",
    "gn:dem":258,
    "gn:feature_class":"P",
    "gn:feature_code":"PPL",
    "gn:name":"Usha Vtoraya",
    "gn:population":0,
    "gn:timezone":"Europe/Minsk",
    "iso:country":"BY",
    "name:rus_x_preferred":[
        "\u0423\u0448\u0430 \u0412\u0442\u043e\u0440\u0430\u044f"
    ],
    "wof:name":"Usha Vtoraya",
    "wof:placetype":"locality"
},
  "geometry": {"coordinates":[27.1268,54.0932],"type":"Point"}
}