{
  "type": "Feature",
  "properties": {
    "gn:admin1_code":"7.0",
    "gn:asciiname":"Osinniki",
    "gn:country_code":"BY",
    "gn:dem":175,
    "gn:feature_class":"P",
    "gn:feature_code":"PPL",
    "gn:name":"Osinniki",
    "gn:population":0,
    "gn:timezone":"Europe/Minsk",
    "iso:country":"BY",
    "name:rus_x_preferred":[
        "\u041e\u0441\u0438\u043d\u043d\u0438\u043a\u0438"
    ],
    "name:und_x_variant":[
        "Osinowszczyzna",
        "Osinovshchyzna",
        "Osinniki"
    ],
    "wof:name":"Osinniki",
    "wof:placetype":"locality"
},
  "geometry": {"coordinates":[27.3279,54.9943],"type":"Point"}
}