{
  "type": "Feature",
  "properties": {
    "gn:admin1_code":"5.0",
    "gn:asciiname":"Shklennikovo",
    "gn:country_code":"BY",
    "gn:dem":199,
    "gn:feature_class":"P",
    "gn:feature_code":"PPL",
    "gn:name":"Shklennikovo",
    "gn:population":0,
    "gn:timezone":"Europe/Minsk",
    "iso:country":"BY",
    "name:rus_x_preferred":[
        "\u0428\u043a\u043b\u0435\u043d\u043d\u0438\u043a\u043e\u0432\u043e"
    ],
    "name:und_x_variant":[
        "Szklennikowo",
        "Shklennikovo"
    ],
    "wof:name":"Shklennikovo",
    "wof:placetype":"locality"
},
  "geometry": {"coordinates":[27.0555,54.7892],"type":"Point"}
}