{
  "type": "Feature",
  "properties": {
    "iso:country":"BY",
    "name:bel_x_preferred":[
        "\u0413\u043e\u0440\u0430\u0434 \u0414\u0440\u0430\u0433\u0456\u0447\u044b\u043d"
    ],
    "name:bel_x_variant":[
        "\u0414\u0440\u0430\u0433\u0456\u0447\u044b\u043d"
    ],
    "name:bul_x_preferred":[
        "\u0414\u0440\u043e\u0433\u0438\u0447\u0438\u043d"
    ],
    "name:ceb_x_preferred":[
        "Drahichyn"
    ],
    "name:ces_x_preferred":[
        "Drahi\u010dyn"
    ],
    "name:che_x_preferred":[
        "\u0414\u0440\u043e\u0433\u0438\u0447\u0438\u043d"
    ],
    "name:deu_x_preferred":[
        "Drahitschyn"
    ],
    "name:ell_x_preferred":[
        "\u039d\u03c4\u03c1\u03b1\u03c7\u03b9\u03c4\u03c3\u03af\u03bd"
    ],
    "name:eng_x_preferred":[
        "Drahichyn"
    ],
    "name:est_x_preferred":[
        "Drahi\u010dyn"
    ],
    "name:fin_x_preferred":[
        "Drahit\u0161yn"
    ],
    "name:fra_x_preferred":[
        "Drahitchyn"
    ],
    "name:frr_x_preferred":[
        "Drahitschyn"
    ],
    "name:heb_x_preferred":[
        "\u05d3\u05e8\u05d5\u05d4\u05d9\u05e6'\u05d9\u05df"
    ],
    "name:hsb_x_preferred":[
        "Drahi\u010dyn"
    ],
    "name:ita_x_preferred":[
        "Drahi\u010dyn"
    ],
    "name:jpn_x_preferred":[
        "\u30c9\u30ed\u30d2\u30c1\u30f3"
    ],
    "name:lav_x_preferred":[
        "Drahi\u010dina"
    ],
    "name:lit_x_preferred":[
        "Drohi\u010dinas"
    ],
    "name:nld_x_preferred":[
        "Drahichyn"
    ],
    "name:pol_x_preferred":[
        "Drohiczyn"
    ],
    "name:rus_x_preferred":[
        "\u0414\u0440\u043e\u0433\u0438\u0447\u0438\u043d"
    ],
    "name:spa_x_preferred":[
        "Drahi\u010dyn"
    ],
    "name:srp_x_preferred":[
        "\u0414\u0440\u0430\u0433\u0438\u0447\u0438\u043d"
    ],
    "name:swe_x_preferred":[
        "Drahitjyn"
    ],
    "name:swe_x_variant":[
        "Drah\u0456tjyn"
    ],
    "name:tat_x_preferred":[
        "\u0414\u0440\u0430\u04bb\u0438\u0447\u044b\u043d"
    ],
    "name:ukr_x_preferred":[
        "\u0414\u0440\u043e\u0433\u0438\u0447\u0438\u043d"
    ],
    "name:unk_x_variant":[
        "Drohiczyn"
    ],
    "name:yid_x_preferred":[
        "\u05d3\u05e8\u05d0\u05d4\u05d9\u05d8\u05e9\u05d9\u05df"
    ],
    "name:zho_x_preferred":[
        "\u5fb7\u7f85\u5409\u6b3d"
    ],
    "qs:gn_country":"BY",
    "qs:gn_fcode":"PPL",
    "qs:gn_pop":13389,
    "qs:name":"Drogichin",
    "qs:name_adm0":"Belarus",
    "qs:name_adm1":"Brestskaya Voblasts'",
    "qs:photos":0,
    "qs:photos_1k":0,
    "qs:photos_9k":1,
    "qs:photos_9r":1,
    "qs:photos_all":2,
    "qs:photos_sr":0,
    "qs:placetype":"Town",
    "qs:pop_sr":"6",
    "qs:woe_adm0":23424765,
    "wd:population":14800,
    "wd:wordcount":54,
    "wof:name":"Drogichin",
    "wof:placetype":"locality",
    "wof:population":14800
},
  "geometry": {"coordinates":[25.1597,52.1874],"type":"Point"}
}