{
  "type": "Feature",
  "properties": {
    "gn:admin1_code":"5.0",
    "gn:asciiname":"Kostyushki",
    "gn:country_code":"BY",
    "gn:dem":177,
    "gn:feature_class":"P",
    "gn:feature_code":"PPL",
    "gn:name":"Kostyushki",
    "gn:population":0,
    "gn:timezone":"Europe/Minsk",
    "iso:country":"BY",
    "name:rus_x_preferred":[
        "\u041a\u043e\u0441\u0442\u044e\u0448\u043a\u0438"
    ],
    "wof:name":"Kostyushki",
    "wof:placetype":"locality"
},
  "geometry": {"coordinates":[27.0867,54.2637],"type":"Point"}
}