{
  "type": "Feature",
  "properties": {
    "gn:admin1_code":"3.0",
    "gn:asciiname":"Burnosy",
    "gn:country_code":"BY",
    "gn:dem":127,
    "gn:feature_class":"P",
    "gn:feature_code":"PPL",
    "gn:name":"Burnosy",
    "gn:population":0,
    "gn:timezone":"Europe/Minsk",
    "iso:country":"BY",
    "name:rus_x_preferred":[
        "\u0411\u0443\u0440\u043d\u043e\u0441\u044b"
    ],
    "wof:name":"Burnosy",
    "wof:placetype":"locality"
},
  "geometry": {"coordinates":[25.5859,53.8241],"type":"Point"}
}