{
  "type": "Feature",
  "properties": {
    "gn:admin1_code":"1.0",
    "gn:asciiname":"Dombrovka",
    "gn:country_code":"BY",
    "gn:dem":153,
    "gn:feature_class":"P",
    "gn:feature_code":"PPL",
    "gn:name":"Dombrovka",
    "gn:population":0,
    "gn:timezone":"Europe/Minsk",
    "iso:country":"BY",
    "name:bak_x_preferred":[
        "\u0414\u043e\u043c\u0431\u0440\u043e\u0432\u043a\u0430"
    ],
    "name:che_x_preferred":[
        "\u0414\u043e\u043c\u0431\u0440\u043e\u0432\u043a\u0430"
    ],
    "name:hye_x_preferred":[
        "\u0534\u0578\u0574\u0562\u0580\u0578\u057e\u056f\u0561"
    ],
    "name:kaz_x_preferred":[
        "\u0414\u043e\u043c\u0431\u0440\u043e\u0432\u043a\u0430"
    ],
    "name:kir_x_preferred":[
        "\u0414\u043e\u043c\u0431\u0440\u043e\u0432\u043a\u0430"
    ],
    "name:rus_x_preferred":[
        "\u0414\u043e\u043c\u0431\u0440\u043e\u0432\u043a\u0430"
    ],
    "name:tat_x_preferred":[
        "\u0414\u043e\u043c\u0431\u0440\u043e\u0432\u043a\u0430"
    ],
    "wof:name":"Dombrovka",
    "wof:placetype":"locality"
},
  "geometry": {"coordinates":[23.6116,51.7038],"type":"Point"}
}