{
  "type": "Feature",
  "properties": {
    "gn:admin1_code":"7.0",
    "gn:asciiname":"Bol'shiye Spory",
    "gn:country_code":"BY",
    "gn:dem":169,
    "gn:feature_class":"P",
    "gn:feature_code":"PPL",
    "gn:name":"Bol\u2019shiye Spory",
    "gn:population":0,
    "gn:timezone":"Europe/Minsk",
    "iso:country":"BY",
    "name:rus_x_preferred":[
        "\u0411\u043e\u043b\u044c\u0448\u0438\u0435 \u0421\u043f\u043e\u0440\u044b"
    ],
    "name:und_x_variant":[
        "Bol\u2019shiye Spory"
    ],
    "wof:name":"Bol'shiye Spory",
    "wof:placetype":"locality"
},
  "geometry": {"coordinates":[26.7814,55.0495],"type":"Point"}
}