{
  "type": "Feature",
  "properties": {
    "gn:admin1_code":"7.0",
    "gn:asciiname":"Popovtsy",
    "gn:country_code":"BY",
    "gn:dem":178,
    "gn:feature_class":"P",
    "gn:feature_code":"PPL",
    "gn:name":"Popovtsy",
    "gn:population":0,
    "gn:timezone":"Europe/Minsk",
    "iso:country":"BY",
    "name:bel_x_preferred":[
        "\u041f\u0430\u043f\u043e\u045e\u0446\u044b"
    ],
    "name:ita_x_preferred":[
        "Popovcy"
    ],
    "name:pol_x_preferred":[
        "Popowcy"
    ],
    "name:rus_x_preferred":[
        "\u041f\u043e\u043f\u043e\u0432\u0446\u044b"
    ],
    "name:ukr_x_preferred":[
        "\u041f\u043e\u043f\u0456\u0432\u0449\u0438\u043d\u0430"
    ],
    "name:und_x_variant":[
        "Popovtse",
        "Popowce",
        "Popovtsy"
    ],
    "wof:name":"Popovtsy",
    "wof:placetype":"locality"
},
  "geometry": {"coordinates":[26.5364,54.9892],"type":"Point"}
}