{
  "type": "Feature",
  "properties": {
    "gn:admin1_code":"5.0",
    "gn:asciiname":"Pekhuri",
    "gn:country_code":"BY",
    "gn:dem":179,
    "gn:feature_class":"P",
    "gn:feature_code":"PPL",
    "gn:name":"Pekhuri",
    "gn:population":0,
    "gn:timezone":"Europe/Minsk",
    "iso:country":"BY",
    "name:rus_x_preferred":[
        "\u041f\u0435\u0445\u0443\u0440\u0438"
    ],
    "wof:name":"Pekhuri",
    "wof:placetype":"locality"
},
  "geometry": {"coordinates":[26.9811,54.959],"type":"Point"}
}