{
  "type": "Feature",
  "properties": {
    "gn:admin1_code":"5.0",
    "gn:asciiname":"Morozy",
    "gn:country_code":"BY",
    "gn:dem":222,
    "gn:feature_class":"P",
    "gn:feature_code":"PPL",
    "gn:name":"Morozy",
    "gn:population":0,
    "gn:timezone":"Europe/Minsk",
    "iso:country":"BY",
    "name:rus_x_preferred":[
        "\u041c\u043e\u0440\u043e\u0437\u044b"
    ],
    "wof:name":"Morozy",
    "wof:placetype":"locality"
},
  "geometry": {"coordinates":[27.4567,54.4855],"type":"Point"}
}