{
  "type": "Feature",
  "properties": {
    "gn:admin1_code":"2.0",
    "gn:asciiname":"Zvenyatskoye",
    "gn:country_code":"BY",
    "gn:dem":125,
    "gn:feature_class":"P",
    "gn:feature_code":"PPL",
    "gn:name":"Zvenyatskoye",
    "gn:population":0,
    "gn:timezone":"Europe/Minsk",
    "iso:country":"BY",
    "name:rus_x_preferred":[
        "\u0417\u0432\u0435\u043d\u044f\u0442\u0441\u043a\u043e\u0435"
    ],
    "name:und_x_variant":[
        "Zvinyatskoye",
        "Zvenyatskoye"
    ],
    "wof:name":"Zvenyatskoye",
    "wof:placetype":"locality"
},
  "geometry": {"coordinates":[30.1095,51.8295],"type":"Point"}
}