{
  "type": "Feature",
  "properties": {
    "gn:admin1_code":"7.0",
    "gn:asciiname":"Solodkovichi",
    "gn:country_code":"BY",
    "gn:dem":156,
    "gn:feature_class":"P",
    "gn:feature_code":"PPL",
    "gn:name":"Solodkovichi",
    "gn:population":0,
    "gn:timezone":"Europe/Minsk",
    "iso:country":"BY",
    "name:rus_x_preferred":[
        "\u0421\u043e\u043b\u043e\u0434\u043a\u043e\u0432\u0438\u0447\u0438"
    ],
    "wof:name":"Solodkovichi",
    "wof:placetype":"locality"
},
  "geometry": {"coordinates":[30.4308,55.6391],"type":"Point"}
}