{
  "type": "Feature",
  "properties": {
    "gn:admin1_code":"5.0",
    "gn:asciiname":"Mrochki",
    "gn:country_code":"BY",
    "gn:dem":159,
    "gn:feature_class":"P",
    "gn:feature_code":"PPL",
    "gn:name":"Mrochki",
    "gn:population":0,
    "gn:timezone":"Europe/Minsk",
    "iso:country":"BY",
    "name:rus_x_preferred":[
        "\u041c\u0440\u043e\u0447\u043a\u0438"
    ],
    "wof:name":"Mrochki",
    "wof:placetype":"locality"
},
  "geometry": {"coordinates":[27.2303,53.3052],"type":"Point"}
}