{
  "type": "Feature",
  "properties": {
    "gn:admin1_code":"7.0",
    "gn:asciiname":"Sergeychiki",
    "gn:country_code":"BY",
    "gn:dem":141,
    "gn:feature_class":"P",
    "gn:feature_code":"PPL",
    "gn:name":"Sergeychiki",
    "gn:population":0,
    "gn:timezone":"Europe/Minsk",
    "iso:country":"BY",
    "name:rus_x_preferred":[
        "\u0421\u0435\u0440\u0433\u0435\u0439\u0447\u0438\u043a\u0438"
    ],
    "wof:name":"Sergeychiki",
    "wof:placetype":"locality"
},
  "geometry": {"coordinates":[28.2667,55.4149],"type":"Point"}
}