{
  "type": "Feature",
  "properties": {
    "gn:admin1_code":"6.0",
    "gn:asciiname":"Gornoye",
    "gn:country_code":"BY",
    "gn:dem":160,
    "gn:feature_class":"P",
    "gn:feature_code":"PPL",
    "gn:name":"Gornoye",
    "gn:population":0,
    "gn:timezone":"Europe/Minsk",
    "iso:country":"BY",
    "name:rus_x_preferred":[
        "\u0413\u043e\u0440\u043d\u043e\u0435"
    ],
    "wof:name":"Gornoye",
    "wof:placetype":"locality"
},
  "geometry": {"coordinates":[28.5786,53.0646],"type":"Point"}
}