{
  "type": "Feature",
  "properties": {
    "gn:admin1_code":"1.0",
    "gn:asciiname":"Zales'ye",
    "gn:country_code":"BY",
    "gn:dem":148,
    "gn:feature_class":"P",
    "gn:feature_code":"PPL",
    "gn:name":"Zales\u2019ye",
    "gn:population":0,
    "gn:timezone":"Europe/Minsk",
    "iso:country":"BY",
    "name:rus_x_preferred":[
        "\u0417\u0430\u043b\u0435\u0441\u044c\u0435"
    ],
    "name:und_x_variant":[
        "Zales\u2019ye"
    ],
    "wof:name":"Zales'ye",
    "wof:placetype":"locality"
},
  "geometry": {"coordinates":[25.894,52.1332],"type":"Point"}
}