{
  "type": "Feature",
  "properties": {
    "gn:country":"BY",
    "gn:fcode":"PPL",
    "gn:pop":464,
    "iso:country":"BY",
    "name:rus_x_preferred":[
        "\u0421\u0443\u043c\u0430\u0440\u043e\u043a\u043e\u0432\u043e"
    ],
    "qs:name":"Sumarokovo",
    "qs:photos_9r":0,
    "qs:photos_sr":0,
    "qs:pop_sr":"2",
    "wof:name":"Sumarokovo",
    "wof:placetype":"locality",
    "wof:population":464
},
  "geometry": {"coordinates":[30.1965,53.9669],"type":"Point"}
}