{
  "type": "Feature",
  "properties": {
    "gn:admin1_code":"7.0",
    "gn:asciiname":"Golochevo",
    "gn:country_code":"BY",
    "gn:dem":193,
    "gn:feature_class":"P",
    "gn:feature_code":"PPL",
    "gn:name":"Golochevo",
    "gn:population":0,
    "gn:timezone":"Europe/Minsk",
    "iso:country":"BY",
    "name:rus_x_preferred":[
        "\u0413\u043e\u043b\u043e\u0447\u0435\u0432\u043e"
    ],
    "wof:name":"Golochevo",
    "wof:placetype":"locality"
},
  "geometry": {"coordinates":[30.2935,54.4423],"type":"Point"}
}