{
  "type": "Feature",
  "properties": {
    "gn:admin1_code":"3.0",
    "gn:asciiname":"Koval'tsy",
    "gn:country_code":"BY",
    "gn:dem":115,
    "gn:feature_class":"P",
    "gn:feature_code":"PPL",
    "gn:name":"Koval\u2019tsy",
    "gn:population":0,
    "gn:timezone":"Europe/Minsk",
    "iso:country":"BY",
    "name:rus_x_preferred":[
        "\u041a\u043e\u0432\u0430\u043b\u044c\u0446\u044b"
    ],
    "name:und_x_variant":[
        "Koval\u2019tsy"
    ],
    "wof:name":"Koval'tsy",
    "wof:placetype":"locality"
},
  "geometry": {"coordinates":[24.0017,53.6055],"type":"Point"}
}