{
  "type": "Feature",
  "properties": {
    "gn:admin1_code":"0.0",
    "gn:asciiname":"Popki",
    "gn:country_code":"BY",
    "gn:dem":135,
    "gn:feature_class":"P",
    "gn:feature_code":"PPL",
    "gn:name":"Popki",
    "gn:population":0,
    "gn:timezone":"Europe/Minsk",
    "iso:country":"BY",
    "name:ceb_x_preferred":[
        "Popki"
    ],
    "name:lit_x_preferred":[
        "Popkai"
    ],
    "name:pol_x_preferred":[
        "Popki"
    ],
    "name:ukr_x_preferred":[
        "\u041f\u043e\u043f\u043a\u0456"
    ],
    "wof:name":"Popki",
    "wof:placetype":"locality"
},
  "geometry": {"coordinates":[30.03333,52.81667],"type":"Point"}
}