{
  "type": "Feature",
  "properties": {
    "gn:country":"BY",
    "gn:fcode":"PPLA2",
    "gn:pop":34591,
    "iso:country":"BY",
    "name:ara_x_preferred":[
        "\u0623\u0633\u064a\u0628\u0648\u0641\u064a\u062a\u0634\u064a"
    ],
    "name:bel_x_preferred":[
        "\u0410\u0441\u0456\u043f\u043e\u043f\u043e\u0432\u0456\u0447\u044b"
    ],
    "name:bul_x_preferred":[
        "\u041e\u0441\u0438\u043f\u043e\u0432\u0438\u0447\u0438"
    ],
    "name:chi_x_preferred":[
        "\u5967\u897f\u6ce2\u7dad\u5947"
    ],
    "name:cze_x_preferred":[
        "Asipovi\u010dy"
    ],
    "name:dut_x_preferred":[
        "Asipovitsjy"
    ],
    "name:eng_x_preferred":[
        "Asipovichy"
    ],
    "name:epo_x_preferred":[
        "Asipovi\u0109i"
    ],
    "name:est_x_preferred":[
        "Asipovi\u010dy"
    ],
    "name:fin_x_preferred":[
        "Asipovit\u0161y"
    ],
    "name:fre_x_preferred":[
        "Assipovitchy"
    ],
    "name:ger_x_preferred":[
        "Assipowitschy"
    ],
    "name:hsb_x_preferred":[
        "Asipowi\u010dy"
    ],
    "name:jpn_x_preferred":[
        "\u30a2\u30b7\u30dd\u30f4\u30a3\u30fc\u30c1"
    ],
    "name:kor_x_preferred":[
        "\uc544\uc2dc\ud3ec\ube44\uce58"
    ],
    "name:lav_x_preferred":[
        "Asipovi\u010di"
    ],
    "name:lit_x_preferred":[
        "Asipovi\u010dai"
    ],
    "name:pol_x_preferred":[
        "Osipowicze"
    ],
    "name:rus_x_preferred":[
        "\u041e\u0441\u0438\u043f\u043e\u0432\u0438\u0447\u0438"
    ],
    "name:srp_x_preferred":[
        "\u0410\u0441\u0438\u043f\u043e\u0432\u0438\u0447\u0438"
    ],
    "name:swe_x_preferred":[
        "As\u0456popov\u0456tjy"
    ],
    "name:tat_x_preferred":[
        "\u0410\u0441\u0438\u043f\u043e\u0432\u0438\u0447\u044b"
    ],
    "name:tur_x_preferred":[
        "Asipovi\u010dy"
    ],
    "name:ukr_x_preferred":[
        "\u041e\u0441\u0438\u043f\u043e\u0432\u0438\u0447\u0456"
    ],
    "name:unk_x_variant":[
        "Sipovichi"
    ],
    "name:wel_x_preferred":[
        "Asipovichy"
    ],
    "qs:name":"Asipovichy",
    "qs:photos_9r":0,
    "qs:photos_sr":0,
    "qs:pop_sr":"7",
    "wd:elevation":136.0,
    "wd:population":35400,
    "wd:wordcount":118,
    "wof:name":"Asipovichy",
    "wof:placetype":"locality",
    "wof:population":35400
},
  "geometry": {"coordinates":[28.6386,53.3011],"type":"Point"}
}