{
  "type": "Feature",
  "properties": {
    "gn:admin1_code":"6.0",
    "gn:asciiname":"Butromeyevka",
    "gn:country_code":"BY",
    "gn:dem":159,
    "gn:feature_class":"P",
    "gn:feature_code":"PPL",
    "gn:name":"Butromeyevka",
    "gn:population":0,
    "gn:timezone":"Europe/Minsk",
    "iso:country":"BY",
    "name:rus_x_preferred":[
        "\u0411\u0443\u0442\u0440\u043e\u043c\u0435\u0435\u0432\u043a\u0430"
    ],
    "wof:name":"Butromeyevka",
    "wof:placetype":"locality"
},
  "geometry": {"coordinates":[30.5459,53.6386],"type":"Point"}
}