{
  "type": "Feature",
  "properties": {
    "gn:admin1_code":"1.0",
    "gn:asciiname":"Yamenka",
    "gn:country_code":"BY",
    "gn:dem":152,
    "gn:feature_class":"P",
    "gn:feature_code":"PPL",
    "gn:name":"Yamenka",
    "gn:population":0,
    "gn:timezone":"Europe/Minsk",
    "iso:country":"BY",
    "name:rus_x_preferred":[
        "\u042f\u043c\u0435\u043d\u043a\u0430"
    ],
    "wof:name":"Yamenka",
    "wof:placetype":"locality"
},
  "geometry": {"coordinates":[23.8206,52.4656],"type":"Point"}
}