{
  "type": "Feature",
  "properties": {
    "gn:admin1_code":"5.0",
    "gn:asciiname":"Kaverlyany",
    "gn:country_code":"BY",
    "gn:dem":245,
    "gn:feature_class":"P",
    "gn:feature_code":"PPL",
    "gn:name":"Kaverlyany",
    "gn:population":0,
    "gn:timezone":"Europe/Minsk",
    "iso:country":"BY",
    "name:rus_x_preferred":[
        "\u041a\u0430\u0432\u0435\u0440\u043b\u044f\u043d\u044b"
    ],
    "wof:name":"Kaverlyany",
    "wof:placetype":"locality"
},
  "geometry": {"coordinates":[27.2276,53.779],"type":"Point"}
}