{
  "type": "Feature",
  "properties": {
    "gn:admin1_code":"2.0",
    "gn:asciiname":"Dubnyaki",
    "gn:country_code":"BY",
    "gn:dem":131,
    "gn:feature_class":"P",
    "gn:feature_code":"PPL",
    "gn:name":"Dubnyaki",
    "gn:population":0,
    "gn:timezone":"Europe/Minsk",
    "iso:country":"BY",
    "name:rus_x_preferred":[
        "\u0414\u0443\u0431\u043d\u044f\u043a\u0438"
    ],
    "wof:name":"Dubnyaki",
    "wof:placetype":"locality"
},
  "geometry": {"coordinates":[29.0128,52.3629],"type":"Point"}
}