{
  "type": "Feature",
  "properties": {
    "gn:admin1_code":"6.0",
    "gn:asciiname":"Trylyesina",
    "gn:country_code":"BY",
    "gn:dem":187,
    "gn:feature_class":"P",
    "gn:feature_code":"PPL",
    "gn:name":"Trylyesina",
    "gn:population":0,
    "gn:timezone":"Europe/Minsk",
    "iso:country":"BY",
    "name:bel_x_preferred":[
        "\u0422\u0440\u044b\u043b\u0435\u0441\u0456\u043d\u0430"
    ],
    "name:und_x_variant":[
        "Trilesino"
    ],
    "wof:name":"Trylyesina",
    "wof:placetype":"locality"
},
  "geometry": {"coordinates":[30.9771,54.0535],"type":"Point"}
}