{
  "type": "Feature",
  "properties": {
    "gn:admin1_code":"2.0",
    "gn:asciiname":"Vysokiy Khutor",
    "gn:country_code":"BY",
    "gn:dem":141,
    "gn:feature_class":"P",
    "gn:feature_code":"PPL",
    "gn:name":"Vysokiy Khutor",
    "gn:population":0,
    "gn:timezone":"Europe/Minsk",
    "iso:country":"BY",
    "name:rus_x_preferred":[
        "\u0412\u044b\u0441\u043e\u043a\u0438\u0439 \u0425\u0443\u0442\u043e\u0440"
    ],
    "wof:name":"Vysokiy Khutor",
    "wof:placetype":"locality"
},
  "geometry": {"coordinates":[31.3837,52.2313],"type":"Point"}
}