{
  "type": "Feature",
  "properties": {
    "gn:admin1_code":"6.0",
    "gn:asciiname":"Shupeni",
    "gn:country_code":"BY",
    "gn:dem":193,
    "gn:feature_class":"P",
    "gn:feature_code":"PPL",
    "gn:name":"Shupeni",
    "gn:population":0,
    "gn:timezone":"Europe/Minsk",
    "iso:country":"BY",
    "name:rus_x_preferred":[
        "\u0428\u0443\u043f\u0435\u043d\u0438"
    ],
    "wof:name":"Shupeni",
    "wof:placetype":"locality"
},
  "geometry": {"coordinates":[29.8308,54.195],"type":"Point"}
}