{
  "type": "Feature",
  "properties": {
    "gn:admin1_code":"6.0",
    "gn:asciiname":"Bel'giyskiy",
    "gn:country_code":"BY",
    "gn:dem":171,
    "gn:feature_class":"P",
    "gn:feature_code":"PPL",
    "gn:name":"Bel\u2019giyskiy",
    "gn:population":0,
    "gn:timezone":"Europe/Minsk",
    "iso:country":"BY",
    "name:rus_x_preferred":[
        "\u0411\u0435\u043b\u044c\u0433\u0438\u0439\u0441\u043a\u0438\u0439"
    ],
    "name:und_x_variant":[
        "Bel\u2019giyskiy"
    ],
    "wof:name":"Bel'giyskiy",
    "wof:placetype":"locality"
},
  "geometry": {"coordinates":[31.3326,53.7018],"type":"Point"}
}