{
  "type": "Feature",
  "properties": {
    "gn:admin1_code":"7.0",
    "gn:asciiname":"Ozhuny",
    "gn:country_code":"BY",
    "gn:dem":153,
    "gn:feature_class":"P",
    "gn:feature_code":"PPL",
    "gn:name":"Ozhuny",
    "gn:population":0,
    "gn:timezone":"Europe/Minsk",
    "iso:country":"BY",
    "name:rus_x_preferred":[
        "\u041e\u0436\u0443\u043d\u044b"
    ],
    "wof:name":"Ozhuny",
    "wof:placetype":"locality"
},
  "geometry": {"coordinates":[27.2008,55.1001],"type":"Point"}
}