{
  "type": "Feature",
  "properties": {
    "gn:admin1_code":"5.0",
    "gn:asciiname":"Romashki",
    "gn:country_code":"BY",
    "gn:dem":183,
    "gn:feature_class":"P",
    "gn:feature_code":"PPL",
    "gn:name":"Romashki",
    "gn:population":0,
    "gn:timezone":"Europe/Minsk",
    "iso:country":"BY",
    "name:rus_x_preferred":[
        "\u0420\u043e\u043c\u0430\u0448\u043a\u0438"
    ],
    "wof:name":"Romashki",
    "wof:placetype":"locality"
},
  "geometry": {"coordinates":[27.105,54.9485],"type":"Point"}
}