{
  "type": "Feature",
  "properties": {
    "gn:admin1_code":"5.0",
    "gn:asciiname":"Smol'ye",
    "gn:country_code":"BY",
    "gn:dem":164,
    "gn:feature_class":"P",
    "gn:feature_code":"PPL",
    "gn:name":"Smol\u2019ye",
    "gn:population":0,
    "gn:timezone":"Europe/Minsk",
    "iso:country":"BY",
    "name:rus_x_preferred":[
        "\u0421\u043c\u043e\u043b\u044c\u0435"
    ],
    "name:und_x_variant":[
        "Smol\u2019ye"
    ],
    "wof:name":"Smol'ye",
    "wof:placetype":"locality"
},
  "geometry": {"coordinates":[28.5237,54.0515],"type":"Point"}
}