{
  "type": "Feature",
  "properties": {
    "gn:admin1_code":"5.0",
    "gn:asciiname":"Chernyaty",
    "gn:country_code":"BY",
    "gn:dem":160,
    "gn:feature_class":"P",
    "gn:feature_code":"PPL",
    "gn:name":"Chernyaty",
    "gn:population":0,
    "gn:timezone":"Europe/Minsk",
    "iso:country":"BY",
    "name:rus_x_preferred":[
        "\u0427\u0435\u0440\u043d\u044f\u0442\u044b"
    ],
    "name:und_x_variant":[
        "Czerniaty",
        "Chernyaty"
    ],
    "wof:name":"Chernyaty",
    "wof:placetype":"locality"
},
  "geometry": {"coordinates":[26.8834,55.0066],"type":"Point"}
}