{
  "type": "Feature",
  "properties": {
    "gn:admin1_code":"7.0",
    "gn:asciiname":"Chisti",
    "gn:country_code":"BY",
    "gn:dem":189,
    "gn:feature_class":"P",
    "gn:feature_code":"PPL",
    "gn:name":"Chisti",
    "gn:population":0,
    "gn:timezone":"Europe/Minsk",
    "iso:country":"BY",
    "name:rus_x_preferred":[
        "\u0427\u0438\u0441\u0442\u0438-\u041c\u0438\u043b\u044c\u0447\u0430\u043d\u0441\u043a\u0438\u0435"
    ],
    "name:und_x_variant":[
        "Czyste Milcza\u0144skie",
        "Chisti Mil\u2019chinskiye",
        "Chisti-Mil\u2019chanskiye"
    ],
    "wof:name":"Chisti",
    "wof:placetype":"locality"
},
  "geometry": {"coordinates":[27.737,54.7024],"type":"Point"}
}