{
  "type": "Feature",
  "properties": {
    "gn:admin1_code":"7.0",
    "gn:asciiname":"Buk",
    "gn:country_code":"BY",
    "gn:dem":206,
    "gn:feature_class":"P",
    "gn:feature_code":"PPL",
    "gn:name":"Buk",
    "gn:population":0,
    "gn:timezone":"Europe/Minsk",
    "iso:country":"BY",
    "name:bel_x_preferred":[
        "\u0411\u0443\u043a"
    ],
    "name:ceb_x_preferred":[
        "Buk"
    ],
    "name:deu_x_preferred":[
        "Buk"
    ],
    "name:epo_x_preferred":[
        "Buk"
    ],
    "name:est_x_preferred":[
        "Buk"
    ],
    "name:fra_x_preferred":[
        "Buk"
    ],
    "name:jav_x_preferred":[
        "Buk"
    ],
    "name:lav_x_preferred":[
        "Buka"
    ],
    "name:msa_x_preferred":[
        "Buk"
    ],
    "name:nld_x_preferred":[
        "Buk"
    ],
    "name:pol_x_preferred":[
        "Buk"
    ],
    "name:por_x_preferred":[
        "Buk"
    ],
    "name:ron_x_preferred":[
        "Buk"
    ],
    "name:rus_x_preferred":[
        "\u0411\u0443\u043a"
    ],
    "name:srp_x_preferred":[
        "\u0411\u0443\u043a"
    ],
    "name:szl_x_preferred":[
        "Buk"
    ],
    "name:ukr_x_preferred":[
        "\u0411\u0443\u043a"
    ],
    "name:vie_x_preferred":[
        "Buk"
    ],
    "wof:name":"Buk",
    "wof:placetype":"locality"
},
  "geometry": {"coordinates":[29.646,54.5049],"type":"Point"}
}