{
  "type": "Feature",
  "properties": {
    "gn:admin1_code":"7.0",
    "gn:asciiname":"Buk",
    "gn:country_code":"BY",
    "gn:dem":206,
    "gn:feature_class":"P",
    "gn:feature_code":"PPL",
    "gn:name":"Buk",
    "gn:population":0,
    "gn:timezone":"Europe/Minsk",
    "iso:country":"BY",
    "name:rus_x_preferred":[
        "\u0411\u0443\u043a"
    ],
    "wof:name":"Buk",
    "wof:placetype":"locality"
},
  "geometry": {"coordinates":[29.646,54.5049],"type":"Point"}
}