{
  "type": "Feature",
  "properties": {
    "gn:admin1_code":"2.0",
    "gn:asciiname":"Zhuravichy",
    "gn:country_code":"BY",
    "gn:dem":151,
    "gn:feature_class":"P",
    "gn:feature_code":"PPL",
    "gn:name":"Zhuravichy",
    "gn:population":0,
    "gn:timezone":"Europe/Minsk",
    "iso:country":"BY",
    "name:bel_x_preferred":[
        "\u0416\u0443\u0440\u0430\u0432\u0456\u0447\u044b"
    ],
    "name:eng_x_preferred":[
        "Zhuravichi"
    ],
    "name:rus_x_preferred":[
        "\u041d\u043e\u0432.\u0416\u0443\u0440\u0430\u0432\u0438\u0447\u0438"
    ],
    "name:und_x_variant":[
        "Zhuravichi",
        "Zhuravichy"
    ],
    "wof:name":"Zhuravichy",
    "wof:placetype":"locality"
},
  "geometry": {"coordinates":[30.5432,53.2483],"type":"Point"}
}