{
  "type": "Feature",
  "properties": {
    "iso:country":"BY",
    "name:bel_x_preferred":[
        "\u0413\u0430\u0440\u0430\u0434\u0441\u043a\u0456 \u043f\u0430\u0441\u0451\u043b\u0430\u043a \u0411\u044f\u0433\u043e\u043c\u043b\u044c"
    ],
    "name:bel_x_variant":[
        "\u0411\u044f\u0433\u043e\u043c\u0435\u043b\u044c",
        "\u0411\u044f\u0433\u043e\u043c\u043b\u044c"
    ],
    "name:ceb_x_preferred":[
        "Byahoml'"
    ],
    "name:ceb_x_variant":[
        "Biahom\u013a"
    ],
    "name:che_x_preferred":[
        "\u0411\u0435\u0433\u043e\u043c\u043b\u044c"
    ],
    "name:eng_x_preferred":[
        "Begoml'"
    ],
    "name:eng_x_variant":[
        "Begoml",
        "Biahom\u013a"
    ],
    "name:est_x_preferred":[
        "Biahoml"
    ],
    "name:lit_x_preferred":[
        "Biahomlis"
    ],
    "name:pol_x_preferred":[
        "Biehomla"
    ],
    "name:rus_x_preferred":[
        "\u0411\u0435\u0433\u043e\u043c\u043b\u044c"
    ],
    "name:srp_x_preferred":[
        "\u0411\u0458\u0430\u0433\u043e\u043c\u0459"
    ],
    "name:swe_x_preferred":[
        "Bjahoml"
    ],
    "name:tat_x_preferred":[
        "\u0411\u044f\u0433\u043e\u043c\u043b\u044c"
    ],
    "name:ukr_x_preferred":[
        "\u0411\u0435\u0433\u043e\u043c\u043b\u044c"
    ],
    "name:und_x_variant":[
        "Begomlya"
    ],
    "qs:gn_country":"BY",
    "qs:gn_fcode":"PPL",
    "qs:gn_pop":3500,
    "qs:name":"Begoml'",
    "qs:name_adm0":"Belarus",
    "qs:name_adm1":"Vitsyebskaya Voblasts'",
    "qs:photos":0,
    "qs:photos_1k":0,
    "qs:photos_9k":1,
    "qs:photos_9r":1,
    "qs:photos_all":1,
    "qs:photos_sr":0,
    "qs:placetype":"Town",
    "qs:pop_sr":"4",
    "qs:woe_adm0":23424765,
    "wd:wordcount":1185,
    "wof:name":"Begoml'",
    "wof:placetype":"locality",
    "wof:population":3500
},
  "geometry": {"coordinates":[28.0577,54.7316],"type":"Point"}
}