{
  "type": "Feature",
  "properties": {
    "gn:admin1_code":"7.0",
    "gn:asciiname":"Motevki",
    "gn:country_code":"BY",
    "gn:dem":160,
    "gn:feature_class":"P",
    "gn:feature_code":"PPL",
    "gn:name":"Motevki",
    "gn:population":0,
    "gn:timezone":"Europe/Minsk",
    "iso:country":"BY",
    "name:rus_x_preferred":[
        "\u041c\u043e\u0442\u0435\u0432\u043a\u0438"
    ],
    "wof:name":"Motevki",
    "wof:placetype":"locality"
},
  "geometry": {"coordinates":[27.5194,55.5323],"type":"Point"}
}