{
  "type": "Feature",
  "properties": {
    "gn:admin1_code":"3.0",
    "gn:asciiname":"Dubawtsy",
    "gn:country_code":"BY",
    "gn:dem":119,
    "gn:feature_class":"P",
    "gn:feature_code":"PPL",
    "gn:name":"Dubawtsy",
    "gn:population":0,
    "gn:timezone":"Europe/Minsk",
    "iso:country":"BY",
    "name:bel_x_preferred":[
        "\u0414\u0443\u0431\u0430\u045e\u0446\u044b"
    ],
    "name:und_x_variant":[
        "Dubovtse",
        "Dubovtsy"
    ],
    "wof:name":"Dubawtsy",
    "wof:placetype":"locality"
},
  "geometry": {"coordinates":[24.4074,53.3451],"type":"Point"}
}