{
  "type": "Feature",
  "properties": {
    "gn:admin1_code":"5.0",
    "gn:asciiname":"Veleshino Vtoroye",
    "gn:country_code":"BY",
    "gn:dem":173,
    "gn:feature_class":"P",
    "gn:feature_code":"PPL",
    "gn:name":"Veleshino Vtoroye",
    "gn:population":0,
    "gn:timezone":"Europe/Minsk",
    "iso:country":"BY",
    "name:rus_x_preferred":[
        "\u0412\u0435\u043b\u0435\u0448\u0438\u043d\u043e \u0412\u0442\u043e\u0440\u043e\u0435"
    ],
    "name:und_x_variant":[
        "Veleshin Vtoroy"
    ],
    "wof:name":"Veleshino Vtoroye",
    "wof:placetype":"locality"
},
  "geometry": {"coordinates":[27.1482,53.2551],"type":"Point"}
}