{
  "type": "Feature",
  "properties": {
    "gn:admin1_code":"7.0",
    "gn:asciiname":"Bereshovo",
    "gn:country_code":"BY",
    "gn:dem":149,
    "gn:feature_class":"P",
    "gn:feature_code":"PPL",
    "gn:name":"Bereshovo",
    "gn:population":0,
    "gn:timezone":"Europe/Minsk",
    "iso:country":"BY",
    "name:rus_x_preferred":[
        "\u0411\u0435\u0440\u0435\u0448\u043e\u0432\u043e"
    ],
    "wof:name":"Bereshovo",
    "wof:placetype":"locality"
},
  "geometry": {"coordinates":[29.8172,55.0143],"type":"Point"}
}