{
  "type": "Feature",
  "properties": {
    "gn:admin1_code":"2.0",
    "gn:asciiname":"Marokharava",
    "gn:country_code":"BY",
    "gn:dem":135,
    "gn:feature_class":"P",
    "gn:feature_code":"PPL",
    "gn:name":"Marokharava",
    "gn:population":0,
    "gn:timezone":"Europe/Minsk",
    "iso:country":"BY",
    "name:bel_x_preferred":[
        "\u041c\u0430\u0440\u043e\u0445\u0430\u0440\u0430\u0432\u0430"
    ],
    "name:und_x_variant":[
        "Khutor Morokhorovo",
        "Morokhorovo",
        "Marokharava"
    ],
    "wof:name":"Marokharava",
    "wof:placetype":"locality"
},
  "geometry": {"coordinates":[27.9975,52.3115],"type":"Point"}
}