{
  "type": "Feature",
  "properties": {
    "gn:admin1_code":"2.0",
    "gn:asciiname":"Novodruzheskiy",
    "gn:country_code":"BY",
    "gn:dem":146,
    "gn:feature_class":"P",
    "gn:feature_code":"PPL",
    "gn:name":"Novodruzheskiy",
    "gn:population":0,
    "gn:timezone":"Europe/Minsk",
    "iso:country":"BY",
    "name:rus_x_preferred":[
        "\u041d\u043e\u0432\u043e\u0434\u0440\u0443\u0436\u0435\u0441\u043a\u0438\u0439"
    ],
    "wof:name":"Novodruzheskiy",
    "wof:placetype":"locality"
},
  "geometry": {"coordinates":[31.3011,52.2939],"type":"Point"}
}