{
  "type": "Feature",
  "properties": {
    "gn:admin1_code":"6.0",
    "gn:asciiname":"Poletniki",
    "gn:country_code":"BY",
    "gn:dem":166,
    "gn:feature_class":"P",
    "gn:feature_code":"PPL",
    "gn:name":"Poletniki",
    "gn:population":0,
    "gn:timezone":"Europe/Minsk",
    "iso:country":"BY",
    "name:rus_x_preferred":[
        "\u041f\u043e\u043b\u0435\u0442\u043d\u0438\u043a\u0438"
    ],
    "name:und_x_variant":[
        "Poletniki Novaki",
        "Poletniki"
    ],
    "wof:name":"Poletniki",
    "wof:placetype":"locality"
},
  "geometry": {"coordinates":[30.4077,53.8416],"type":"Point"}
}