{
  "type": "Feature",
  "properties": {
    "gn:admin1_code":"7.0",
    "gn:asciiname":"Yakubovo",
    "gn:country_code":"BY",
    "gn:dem":184,
    "gn:feature_class":"P",
    "gn:feature_code":"PPL",
    "gn:name":"Yakubovo",
    "gn:population":0,
    "gn:timezone":"Europe/Minsk",
    "iso:country":"BY",
    "name:eng_x_preferred":[
        "Yakubovo"
    ],
    "name:rus_x_preferred":[
        "\u042f\u043a\u0443\u0431\u043e\u0432\u043e"
    ],
    "wof:name":"Yakubovo",
    "wof:placetype":"locality"
},
  "geometry": {"coordinates":[30.5707,54.5962],"type":"Point"}
}