{
  "type": "Feature",
  "properties": {
    "gn:admin1_code":"0.0",
    "gn:asciiname":"Vel'ki Karatsk",
    "gn:country_code":"BY",
    "gn:dem":172,
    "gn:feature_class":"P",
    "gn:feature_code":"PPL",
    "gn:name":"Vel\u2019ki Karatsk",
    "gn:population":0,
    "gn:timezone":"Europe/Minsk",
    "iso:country":"BY",
    "name:und_x_variant":[
        "Wielki Karack",
        "Vel\u2019ki Karatsk"
    ],
    "wof:name":"Vel'ki Karatsk",
    "wof:placetype":"locality"
},
  "geometry": {"coordinates":[26.57634,52.92769000000001],"type":"Point"}
}