{
  "type": "Feature",
  "properties": {
    "gn:admin1_code":"5.0",
    "gn:asciiname":"Poselok Vishnevka",
    "gn:country_code":"BY",
    "gn:dem":170,
    "gn:feature_class":"P",
    "gn:feature_code":"PPL",
    "gn:name":"Pos\u00eblok Vishn\u00ebvka",
    "gn:population":0,
    "gn:timezone":"Europe/Minsk",
    "iso:country":"BY",
    "name:rus_x_preferred":[
        "\u041f\u043e\u0441\u0451\u043b\u043e\u043a \u0412\u0438\u0448\u043d\u0451\u0432\u043a\u0430"
    ],
    "name:und_x_variant":[
        "Pos\u00eblok Vishn\u00ebvka",
        "Vishn\u00ebvka"
    ],
    "wof:name":"Poselok Vishnevka",
    "wof:placetype":"locality"
},
  "geometry": {"coordinates":[28.042,53.5981],"type":"Point"}
}