{
  "type": "Feature",
  "properties": {
    "gn:admin1_code":"7.0",
    "gn:asciiname":"Krasyni",
    "gn:country_code":"BY",
    "gn:dem":238,
    "gn:feature_class":"P",
    "gn:feature_code":"PPL",
    "gn:name":"Krasyni",
    "gn:population":0,
    "gn:timezone":"Europe/Minsk",
    "iso:country":"BY",
    "name:rus_x_preferred":[
        "\u041a\u0440\u0430\u0441\u044b\u043d\u0438"
    ],
    "name:und_x_variant":[
        "Krasynya"
    ],
    "wof:name":"Krasyni",
    "wof:placetype":"locality"
},
  "geometry": {"coordinates":[30.5747,55.1113],"type":"Point"}
}