{
  "type": "Feature",
  "properties": {
    "gn:admin1_code":"1.0",
    "gn:asciiname":"Vyalikiya Vikaravichy",
    "gn:country_code":"BY",
    "gn:dem":134,
    "gn:feature_class":"P",
    "gn:feature_code":"PPL",
    "gn:name":"Vyalikiya Vikaravichy",
    "gn:population":0,
    "gn:timezone":"Europe/Minsk",
    "iso:country":"BY",
    "name:bel_x_preferred":[
        "\u0412\u044f\u043b\u0456\u043a\u0456\u044f \u0412\u0456\u043a\u0430\u0440\u0430\u0432\u0456\u0447\u044b"
    ],
    "name:rus_x_preferred":[
        "Bol\u2019shiye Vikorovichi"
    ],
    "name:und_x_variant":[
        "Vel\u2019ke Vikareviche",
        "Vyalikiya Vikaravichy"
    ],
    "wof:name":"Vyalikiya Vikaravichy",
    "wof:placetype":"locality"
},
  "geometry": {"coordinates":[26.88582,51.85826],"type":"Point"}
}