{
  "type": "Feature",
  "properties": {
    "gn:admin1_code":"3.0",
    "gn:asciiname":"Muravana-Ashmyanka",
    "gn:country_code":"BY",
    "gn:dem":206,
    "gn:feature_class":"P",
    "gn:feature_code":"PPL",
    "gn:name":"Muravana-Ashmyanka",
    "gn:population":0,
    "gn:timezone":"Europe/Minsk",
    "iso:country":"BY",
    "name:bel_x_preferred":[
        "\u041c\u0443\u0440\u0430\u0432\u0430\u043d\u0430-\u0410\u0448\u043c\u044f\u043d\u043a\u0430"
    ],
    "name:eng_x_preferred":[
        "Murovano-Oshmyanka"
    ],
    "name:rus_x_preferred":[
        "\u041c\u0443\u0440\u043e\u0432\u0430\u043d\u043e-\u041e\u0448\u043c\u044f\u043d\u043a\u0430"
    ],
    "name:und_x_variant":[
        "Murovana Oshmyanka",
        "Murovanaya-Oshmyanka",
        "Muravana-Ashmyanka"
    ],
    "wof:name":"Muravana-Ashmyanka",
    "wof:placetype":"locality"
},
  "geometry": {"coordinates":[25.7861,54.4595],"type":"Point"}
}