{
  "type": "Feature",
  "properties": {
    "gn:admin1_code":"3.0",
    "gn:asciiname":"Yelenka",
    "gn:country_code":"BY",
    "gn:dem":179,
    "gn:feature_class":"P",
    "gn:feature_code":"PPL",
    "gn:name":"Yelenka",
    "gn:population":0,
    "gn:timezone":"Europe/Minsk",
    "iso:country":"BY",
    "name:bel_x_preferred":[
        "Yelyenka"
    ],
    "name:rus_x_preferred":[
        "\u0415\u043b\u0435\u043d\u043a\u0430"
    ],
    "wof:name":"Yelenka",
    "wof:placetype":"locality"
},
  "geometry": {"coordinates":[25.7026,53.4415],"type":"Point"}
}