{
  "type": "Feature",
  "properties": {
    "gn:admin1_code":"3.0",
    "gn:asciiname":"Studenets",
    "gn:country_code":"BY",
    "gn:dem":126,
    "gn:feature_class":"P",
    "gn:feature_code":"PPL",
    "gn:name":"Studenets",
    "gn:population":0,
    "gn:timezone":"Europe/Minsk",
    "iso:country":"BY",
    "name:ceb_x_preferred":[
        "Studenets"
    ],
    "name:rus_x_preferred":[
        "\u0421\u0442\u0443\u0434\u0435\u043d\u0435\u0446"
    ],
    "name:swe_x_preferred":[
        "Studenets"
    ],
    "wof:name":"Studenets",
    "wof:placetype":"locality"
},
  "geometry": {"coordinates":[24.4094,53.2961],"type":"Point"}
}