{
  "type": "Feature",
  "properties": {
    "gn:admin1_code":"7.0",
    "gn:asciiname":"Sasnowka",
    "gn:country_code":"BY",
    "gn:dem":152,
    "gn:feature_class":"P",
    "gn:feature_code":"PPL",
    "gn:name":"Sasnowka",
    "gn:population":0,
    "gn:timezone":"Europe/Minsk",
    "iso:country":"BY",
    "name:bel_x_preferred":[
        "\u0421\u0430\u0441\u043d\u043e\u045e\u043a\u0430"
    ],
    "name:und_x_variant":[
        "Sosnovka"
    ],
    "wof:name":"Sasnowka",
    "wof:placetype":"locality"
},
  "geometry": {"coordinates":[30.1706,55.0856],"type":"Point"}
}