{
  "type": "Feature",
  "properties": {
    "gn:admin1_code":"6.0",
    "gn:asciiname":"Kovgary",
    "gn:country_code":"BY",
    "gn:dem":156,
    "gn:feature_class":"P",
    "gn:feature_code":"PPL",
    "gn:name":"Kovgary",
    "gn:population":0,
    "gn:timezone":"Europe/Minsk",
    "iso:country":"BY",
    "name:rus_x_preferred":[
        "\u041a\u043e\u0432\u0433\u0430\u0440\u044b"
    ],
    "wof:name":"Kovgary",
    "wof:placetype":"locality"
},
  "geometry": {"coordinates":[28.4581,53.1622],"type":"Point"}
}