{
  "type": "Feature",
  "properties": {
    "gn:admin1_code":"6.0",
    "gn:asciiname":"Novaya Trasna",
    "gn:country_code":"BY",
    "gn:dem":153,
    "gn:feature_class":"P",
    "gn:feature_code":"PPL",
    "gn:name":"Novaya Trasna",
    "gn:population":0,
    "gn:timezone":"Europe/Minsk",
    "iso:country":"BY",
    "name:rus_x_preferred":[
        "\u041d\u043e\u0432\u0430\u044f \u0422\u0440\u0430\u0441\u043d\u0430"
    ],
    "wof:name":"Novaya Trasna",
    "wof:placetype":"locality"
},
  "geometry": {"coordinates":[30.4953,53.4618],"type":"Point"}
}