{
  "type": "Feature",
  "properties": {
    "gn:admin1_code":"5.0",
    "gn:asciiname":"Mil'kovshchina",
    "gn:country_code":"BY",
    "gn:dem":190,
    "gn:feature_class":"P",
    "gn:feature_code":"PPL",
    "gn:name":"Mil\u2019kovshchina",
    "gn:population":0,
    "gn:timezone":"Europe/Minsk",
    "iso:country":"BY",
    "name:rus_x_preferred":[
        "\u041c\u0438\u043b\u044c\u043a\u043e\u0432\u0449\u0438\u043d\u0430"
    ],
    "name:und_x_variant":[
        "Mil\u2019kovshchina",
        "Mel\u2019kovshchina"
    ],
    "wof:name":"Mil'kovshchina",
    "wof:placetype":"locality"
},
  "geometry": {"coordinates":[26.2604,54.1854],"type":"Point"}
}