{
  "type": "Feature",
  "properties": {
    "gn:admin1_code":"7.0",
    "gn:asciiname":"Vyshedki",
    "gn:country_code":"BY",
    "gn:dem":161,
    "gn:feature_class":"P",
    "gn:feature_code":"PPL",
    "gn:name":"Vyshedki",
    "gn:population":0,
    "gn:timezone":"Europe/Minsk",
    "iso:country":"BY",
    "name:rus_x_preferred":[
        "\u0412\u044b\u0448\u0435\u0434\u043a\u0438"
    ],
    "wof:name":"Vyshedki",
    "wof:placetype":"locality"
},
  "geometry": {"coordinates":[27.5427,55.1364],"type":"Point"}
}