{
  "type": "Feature",
  "properties": {
    "gn:admin1_code":"5.0",
    "gn:asciiname":"Polyadki",
    "gn:country_code":"BY",
    "gn:dem":177,
    "gn:feature_class":"P",
    "gn:feature_code":"PPL",
    "gn:name":"Polyadki",
    "gn:population":0,
    "gn:timezone":"Europe/Minsk",
    "iso:country":"BY",
    "name:rus_x_preferred":[
        "\u041f\u043e\u043b\u044f\u0434\u043a\u0438"
    ],
    "name:und_x_variant":[
        "Palyadki"
    ],
    "wof:name":"Polyadki",
    "wof:placetype":"locality"
},
  "geometry": {"coordinates":[28.6985,53.87],"type":"Point"}
}