{
  "type": "Feature",
  "properties": {
    "gn:admin1_code":"5.0",
    "gn:asciiname":"Kosteshi",
    "gn:country_code":"BY",
    "gn:dem":160,
    "gn:feature_class":"P",
    "gn:feature_code":"PPL",
    "gn:name":"Kosteshi",
    "gn:population":0,
    "gn:timezone":"Europe/Minsk",
    "iso:country":"BY",
    "name:rus_x_preferred":[
        "\u041a\u043e\u0441\u0442\u0435\u0448\u0438"
    ],
    "wof:name":"Kosteshi",
    "wof:placetype":"locality"
},
  "geometry": {"coordinates":[28.1413,52.8739],"type":"Point"}
}