{
  "type": "Feature",
  "properties": {
    "gn:admin1_code":"6.0",
    "gn:asciiname":"Gorodetsk",
    "gn:country_code":"BY",
    "gn:dem":175,
    "gn:feature_class":"P",
    "gn:feature_code":"PPL",
    "gn:name":"Gorodetsk",
    "gn:population":0,
    "gn:timezone":"Europe/Minsk",
    "iso:country":"BY",
    "name:rus_x_preferred":[
        "\u0413\u043e\u0440\u043e\u0434\u0435\u0446\u043a"
    ],
    "name:und_x_variant":[
        "Gorodets"
    ],
    "wof:name":"Gorodetsk",
    "wof:placetype":"locality"
},
  "geometry": {"coordinates":[31.0138,54.1591],"type":"Point"}
}