{
  "type": "Feature",
  "properties": {
    "gn:admin1_code":"5.0",
    "gn:asciiname":"Khutor Malyye Novoselki",
    "gn:country_code":"BY",
    "gn:dem":223,
    "gn:feature_class":"P",
    "gn:feature_code":"PPL",
    "gn:name":"Khutor Malyye Novoselki",
    "gn:population":0,
    "gn:timezone":"Europe/Minsk",
    "iso:country":"BY",
    "name:rus_x_preferred":[
        "\u041c\u0430\u043b\u044b\u0435 \u041d\u043e\u0432\u043e\u0441\u0451\u043b\u043a\u0438"
    ],
    "name:und_x_variant":[
        "Novos\u00eblki",
        "Malyye Novos\u00eblki"
    ],
    "wof:name":"Khutor Malyye Novoselki",
    "wof:placetype":"locality"
},
  "geometry": {"coordinates":[27.1335,53.7303],"type":"Point"}
}