{
  "type": "Feature",
  "properties": {
    "gn:admin1_code":"7.0",
    "gn:asciiname":"Drozdy",
    "gn:country_code":"BY",
    "gn:dem":144,
    "gn:feature_class":"P",
    "gn:feature_code":"PPL",
    "gn:name":"Drozdy",
    "gn:population":0,
    "gn:timezone":"Europe/Minsk",
    "iso:country":"BY",
    "name:pol_x_preferred":[
        "Drozdy"
    ],
    "name:rus_x_preferred":[
        "\u0414\u0440\u043e\u0437\u0434\u044b"
    ],
    "wof:name":"Drozdy",
    "wof:placetype":"locality"
},
  "geometry": {"coordinates":[27.5176,55.7065],"type":"Point"}
}