{
  "type": "Feature",
  "properties": {
    "gn:admin1_code":"1.0",
    "gn:asciiname":"Velikoye-Pole",
    "gn:country_code":"BY",
    "gn:dem":149,
    "gn:feature_class":"P",
    "gn:feature_code":"PPL",
    "gn:name":"Velikoye-Pole",
    "gn:population":0,
    "gn:timezone":"Europe/Minsk",
    "iso:country":"BY",
    "name:rus_x_preferred":[
        "\u0412\u0435\u043b\u0438\u043a\u043e\u0435-\u041f\u043e\u043b\u0435"
    ],
    "wof:name":"Velikoye-Pole",
    "wof:placetype":"locality"
},
  "geometry": {"coordinates":[23.5925,52.31100000000001],"type":"Point"}
}