{
  "type": "Feature",
  "properties": {
    "gn:admin1_code":"7.0",
    "gn:asciiname":"Strakhi",
    "gn:country_code":"BY",
    "gn:dem":182,
    "gn:feature_class":"P",
    "gn:feature_code":"PPL",
    "gn:name":"Strakhi",
    "gn:population":0,
    "gn:timezone":"Europe/Minsk",
    "iso:country":"BY",
    "name:rus_x_preferred":[
        "\u0421\u0442\u0440\u0430\u0445\u0438"
    ],
    "wof:name":"Strakhi",
    "wof:placetype":"locality"
},
  "geometry": {"coordinates":[31.1141,54.5921],"type":"Point"}
}