{
  "type": "Feature",
  "properties": {
    "gn:admin1_code":"6.0",
    "gn:asciiname":"Roshcha",
    "gn:country_code":"BY",
    "gn:dem":173,
    "gn:feature_class":"P",
    "gn:feature_code":"PPL",
    "gn:name":"Roshcha",
    "gn:population":0,
    "gn:timezone":"Europe/Minsk",
    "iso:country":"BY",
    "name:rus_x_preferred":[
        "\u0420\u043e\u0449\u0430"
    ],
    "wof:name":"Roshcha",
    "wof:placetype":"locality"
},
  "geometry": {"coordinates":[30.9893,53.8669],"type":"Point"}
}