{
  "type": "Feature",
  "properties": {
    "gn:admin1_code":"7.0",
    "gn:asciiname":"Nacha",
    "gn:country_code":"BY",
    "gn:dem":138,
    "gn:feature_class":"P",
    "gn:feature_code":"PPL",
    "gn:name":"Nacha",
    "gn:population":0,
    "gn:timezone":"Europe/Minsk",
    "iso:country":"BY",
    "name:bel_x_preferred":[
        "\u041d\u0430\u0447\u0430"
    ],
    "name:ceb_x_preferred":[
        "Nacha"
    ],
    "name:swe_x_preferred":[
        "Nacha"
    ],
    "wof:name":"Nacha",
    "wof:placetype":"locality"
},
  "geometry": {"coordinates":[28.3493,55.3941],"type":"Point"}
}