{
  "type": "Feature",
  "properties": {
    "gn:admin1_code":"1.0",
    "gn:asciiname":"Vily",
    "gn:country_code":"BY",
    "gn:dem":150,
    "gn:feature_class":"P",
    "gn:feature_code":"PPL",
    "gn:name":"Vily",
    "gn:population":0,
    "gn:timezone":"Europe/Minsk",
    "iso:country":"BY",
    "name:rus_x_preferred":[
        "\u0412\u0438\u043b\u044b"
    ],
    "wof:name":"Vily",
    "wof:placetype":"locality"
},
  "geometry": {"coordinates":[25.8048,52.2579],"type":"Point"}
}