{
  "type": "Feature",
  "properties": {
    "gn:admin1_code":"6.0",
    "gn:asciiname":"Motyga",
    "gn:country_code":"BY",
    "gn:dem":181,
    "gn:feature_class":"P",
    "gn:feature_code":"PPL",
    "gn:name":"Motyga",
    "gn:population":0,
    "gn:timezone":"Europe/Minsk",
    "iso:country":"BY",
    "name:rus_x_preferred":[
        "\u041c\u043e\u0442\u044b\u0433\u0430"
    ],
    "wof:name":"Motyga",
    "wof:placetype":"locality"
},
  "geometry": {"coordinates":[29.478,53.8146],"type":"Point"}
}