{
  "type": "Feature",
  "properties": {
    "gn:admin1_code":"7.0",
    "gn:asciiname":"Zakharovo",
    "gn:country_code":"BY",
    "gn:dem":138,
    "gn:feature_class":"P",
    "gn:feature_code":"PPL",
    "gn:name":"Zakharovo",
    "gn:population":0,
    "gn:timezone":"Europe/Minsk",
    "iso:country":"BY",
    "name:rus_x_preferred":[
        "\u0417\u0430\u0445\u0430\u0440\u043e\u0432\u043e"
    ],
    "name:und_x_variant":[
        "Zakharova"
    ],
    "wof:name":"Zakharovo",
    "wof:placetype":"locality"
},
  "geometry": {"coordinates":[29.2639,55.3711],"type":"Point"}
}