{
  "type": "Feature",
  "properties": {
    "gn:country":"BY",
    "gn:fcode":"PPL",
    "gn:population":20,
    "iso:country":"BY",
    "name:rus_x_preferred":[
        "\u0417\u0430\u0442\u0438\u0448\u044c\u0435"
    ],
    "qs:name":"Zatish\u2019ye",
    "qs:photos_9r":0,
    "qs:photos_sr":0,
    "qs:pop_sr":"1",
    "wof:name":"Zatish\u2019ye",
    "wof:placetype":"locality",
    "wof:population":20
},
  "geometry": {"coordinates":[30.2477,53.9082],"type":"Point"}
}