{
  "type": "Feature",
  "properties": {
    "gn:admin1_code":"7.0",
    "gn:asciiname":"Skakunovshchina",
    "gn:country_code":"BY",
    "gn:dem":135,
    "gn:feature_class":"P",
    "gn:feature_code":"PPL",
    "gn:name":"Skakunovshchina",
    "gn:population":0,
    "gn:timezone":"Europe/Minsk",
    "iso:country":"BY",
    "name:rus_x_preferred":[
        "\u0421\u043a\u0430\u043a\u0443\u043d\u043e\u0432\u0449\u0438\u043d\u0430"
    ],
    "wof:name":"Skakunovshchina",
    "wof:placetype":"locality"
},
  "geometry": {"coordinates":[29.1163,55.0671],"type":"Point"}
}