{
  "type": "Feature",
  "properties": {
    "gn:admin1_code":"7.0",
    "gn:asciiname":"Kovali",
    "gn:country_code":"BY",
    "gn:dem":186,
    "gn:feature_class":"P",
    "gn:feature_code":"PPL",
    "gn:name":"Kovali",
    "gn:population":0,
    "gn:timezone":"Europe/Minsk",
    "iso:country":"BY",
    "name:rus_x_preferred":[
        "\u041a\u043e\u0432\u0430\u043b\u0438"
    ],
    "name:und_x_variant":[
        "Kowale",
        "Kovale",
        "Kovali"
    ],
    "wof:name":"Kovali",
    "wof:placetype":"locality"
},
  "geometry": {"coordinates":[26.2504,55.024],"type":"Point"}
}