{
  "type": "Feature",
  "properties": {
    "gn:admin1_code":"2.0",
    "gn:asciiname":"Staryye Gromyki",
    "gn:country_code":"BY",
    "gn:dem":123,
    "gn:feature_class":"P",
    "gn:feature_code":"PPL",
    "gn:name":"Staryye Gromyki",
    "gn:population":0,
    "gn:timezone":"Europe/Minsk",
    "iso:country":"BY",
    "name:rus_x_preferred":[
        "\u0421\u0442\u0430\u0440\u044b\u0435 \u0413\u0440\u043e\u043c\u044b\u043a\u0438"
    ],
    "wof:name":"Staryye Gromyki",
    "wof:placetype":"locality"
},
  "geometry": {"coordinates":[31.3527,52.6931],"type":"Point"}
}