{
  "type": "Feature",
  "properties": {
    "gn:admin1_code":"7.0",
    "gn:asciiname":"Rakusino",
    "gn:country_code":"BY",
    "gn:dem":128,
    "gn:feature_class":"P",
    "gn:feature_code":"PPL",
    "gn:name":"Rakusino",
    "gn:population":0,
    "gn:timezone":"Europe/Minsk",
    "iso:country":"BY",
    "name:rus_x_preferred":[
        "\u0420\u0430\u043a\u0443\u0441\u0438\u043d\u043e"
    ],
    "wof:name":"Rakusino",
    "wof:placetype":"locality"
},
  "geometry": {"coordinates":[28.067,55.6749],"type":"Point"}
}