{
  "type": "Feature",
  "properties": {
    "gn:admin1_code":"2.0",
    "gn:asciiname":"Zaprudovka",
    "gn:country_code":"BY",
    "gn:dem":138,
    "gn:feature_class":"P",
    "gn:feature_code":"PPL",
    "gn:name":"Zaprudovka",
    "gn:population":0,
    "gn:timezone":"Europe/Minsk",
    "iso:country":"BY",
    "name:rus_x_preferred":[
        "\u0417\u0430\u043f\u0440\u0443\u0434\u043e\u0432\u043a\u0430"
    ],
    "wof:name":"Zaprudovka",
    "wof:placetype":"locality"
},
  "geometry": {"coordinates":[31.2421,52.2716],"type":"Point"}
}