{
  "type": "Feature",
  "properties": {
    "gn:admin1_code":"2.0",
    "gn:asciiname":"Niwki",
    "gn:country_code":"BY",
    "gn:dem":143,
    "gn:feature_class":"P",
    "gn:feature_code":"PPL",
    "gn:name":"Niwki",
    "gn:population":0,
    "gn:timezone":"Europe/Minsk",
    "iso:country":"BY",
    "name:bel_x_preferred":[
        "\u041d\u0456\u045e\u043a\u0456"
    ],
    "name:deu_x_preferred":[
        "Niwki"
    ],
    "name:fra_x_preferred":[
        "Niwki"
    ],
    "name:pol_x_preferred":[
        "Niwki"
    ],
    "name:ukr_x_preferred":[
        "\u041d\u0456\u0432\u043a\u0456"
    ],
    "name:und_x_variant":[
        "Niuki",
        "Nivki",
        "Niwki"
    ],
    "wof:name":"Niwki",
    "wof:placetype":"locality"
},
  "geometry": {"coordinates":[31.4099,52.1582],"type":"Point"}
}