{
  "type": "Feature",
  "properties": {
    "gn:admin1_code":"3.0",
    "gn:asciiname":"Songayly",
    "gn:country_code":"BY",
    "gn:dem":154,
    "gn:feature_class":"P",
    "gn:feature_code":"PPL",
    "gn:name":"Songayly",
    "gn:population":0,
    "gn:timezone":"Europe/Minsk",
    "iso:country":"BY",
    "name:rus_x_preferred":[
        "\u0421\u043e\u043d\u0433\u0430\u0439\u043b\u044b"
    ],
    "wof:name":"Songayly",
    "wof:placetype":"locality"
},
  "geometry": {"coordinates":[25.4074,53.9511],"type":"Point"}
}