{
  "type": "Feature",
  "properties": {
    "gn:admin1_code":"7.0",
    "gn:asciiname":"Tadulino",
    "gn:country_code":"BY",
    "gn:dem":178,
    "gn:feature_class":"P",
    "gn:feature_code":"PPL",
    "gn:name":"Tadulino",
    "gn:population":0,
    "gn:timezone":"Europe/Minsk",
    "iso:country":"BY",
    "name:rus_x_preferred":[
        "\u0422\u0430\u0434\u0443\u043b\u0438\u043d\u043e"
    ],
    "wof:name":"Tadulino",
    "wof:placetype":"locality"
},
  "geometry": {"coordinates":[28.8725,54.7995],"type":"Point"}
}