{
  "type": "Feature",
  "properties": {
    "gn:admin1_code":"2.0",
    "gn:asciiname":"Borovoye Lyado",
    "gn:country_code":"BY",
    "gn:dem":144,
    "gn:feature_class":"P",
    "gn:feature_code":"PPL",
    "gn:name":"Borovoye Lyado",
    "gn:population":0,
    "gn:timezone":"Europe/Minsk",
    "iso:country":"BY",
    "name:rus_x_preferred":[
        "\u0411\u043e\u0440\u043e\u0432\u043e\u0435 \u041b\u044f\u0434\u043e"
    ],
    "wof:name":"Borovoye Lyado",
    "wof:placetype":"locality"
},
  "geometry": {"coordinates":[30.5843,52.7288],"type":"Point"}
}