{
  "type": "Feature",
  "properties": {
    "gn:admin1_code":"3.0",
    "gn:asciiname":"Penchitsy",
    "gn:country_code":"BY",
    "gn:dem":145,
    "gn:feature_class":"P",
    "gn:feature_code":"PPL",
    "gn:name":"Penchitsy",
    "gn:population":0,
    "gn:timezone":"Europe/Minsk",
    "iso:country":"BY",
    "name:rus_x_preferred":[
        "\u041f\u0435\u043d\u0447\u0438\u0446\u044b"
    ],
    "wof:name":"Penchitsy",
    "wof:placetype":"locality"
},
  "geometry": {"coordinates":[25.4435,53.5083],"type":"Point"}
}