{
  "type": "Feature",
  "properties": {
    "gn:admin1_code":"3.0",
    "gn:asciiname":"Myakishi",
    "gn:country_code":"BY",
    "gn:dem":150,
    "gn:feature_class":"P",
    "gn:feature_code":"PPL",
    "gn:name":"Myakishi",
    "gn:population":0,
    "gn:timezone":"Europe/Minsk",
    "iso:country":"BY",
    "name:rus_x_preferred":[
        "\u041c\u044f\u043a\u0438\u0448\u0438"
    ],
    "wof:name":"Myakishi",
    "wof:placetype":"locality"
},
  "geometry": {"coordinates":[24.7479,53.7994],"type":"Point"}
}