{
  "type": "Feature",
  "properties": {
    "gn:admin1_code":"7.0",
    "gn:asciiname":"Transhevichi",
    "gn:country_code":"BY",
    "gn:dem":180,
    "gn:feature_class":"P",
    "gn:feature_code":"PPL",
    "gn:name":"Transhevichi",
    "gn:population":0,
    "gn:timezone":"Europe/Minsk",
    "iso:country":"BY",
    "name:rus_x_preferred":[
        "\u0422\u0440\u0430\u043d\u0448\u0435\u0432\u0438\u0447\u0438"
    ],
    "wof:name":"Transhevichi",
    "wof:placetype":"locality"
},
  "geometry": {"coordinates":[26.5426,55.0577],"type":"Point"}
}