{
  "type": "Feature",
  "properties": {
    "gn:admin1_code":"5.0",
    "gn:asciiname":"Sysuny",
    "gn:country_code":"BY",
    "gn:dem":279,
    "gn:feature_class":"P",
    "gn:feature_code":"PPL",
    "gn:name":"Sysuny",
    "gn:population":0,
    "gn:timezone":"Europe/Minsk",
    "iso:country":"BY",
    "name:rus_x_preferred":[
        "\u0421\u044b\u0441\u0443\u043d\u044b"
    ],
    "wof:name":"Sysuny",
    "wof:placetype":"locality"
},
  "geometry": {"coordinates":[27.0048,54.1563],"type":"Point"}
}