{
  "type": "Feature",
  "properties": {
    "gn:admin1_code":"5.0",
    "gn:asciiname":"Ponya",
    "gn:country_code":"BY",
    "gn:dem":180,
    "gn:feature_class":"P",
    "gn:feature_code":"PPL",
    "gn:name":"Ponya",
    "gn:population":0,
    "gn:timezone":"Europe/Minsk",
    "iso:country":"BY",
    "name:rus_x_preferred":[
        "\u041f\u043e\u043d\u044f"
    ],
    "name:und_x_variant":[
        "Ponia",
        "Ponya"
    ],
    "wof:name":"Ponya",
    "wof:placetype":"locality"
},
  "geometry": {"coordinates":[27.6468,54.7526],"type":"Point"}
}