{
  "type": "Feature",
  "properties": {
    "gn:admin1_code":"7.0",
    "gn:asciiname":"Pesochanka",
    "gn:country_code":"BY",
    "gn:dem":145,
    "gn:feature_class":"P",
    "gn:feature_code":"PPL",
    "gn:name":"Pesochanka",
    "gn:population":0,
    "gn:timezone":"Europe/Minsk",
    "iso:country":"BY",
    "name:rus_x_preferred":[
        "\u041f\u0435\u0441\u043e\u0447\u0430\u043d\u043a\u0430"
    ],
    "name:und_x_variant":[
        "Peschanka",
        "Pesochanka"
    ],
    "wof:name":"Pesochanka",
    "wof:placetype":"locality"
},
  "geometry": {"coordinates":[30.2454,54.8932],"type":"Point"}
}