{
  "type": "Feature",
  "properties": {
    "gn:admin1_code":"5.0",
    "gn:asciiname":"Teshkovka",
    "gn:country_code":"BY",
    "gn:dem":169,
    "gn:feature_class":"P",
    "gn:feature_code":"PPL",
    "gn:name":"Teshkovka",
    "gn:population":0,
    "gn:timezone":"Europe/Minsk",
    "iso:country":"BY",
    "name:rus_x_preferred":[
        "\u0422\u0435\u0448\u043a\u043e\u0432\u043a\u0430"
    ],
    "wof:name":"Teshkovka",
    "wof:placetype":"locality"
},
  "geometry": {"coordinates":[28.7185,54.0108],"type":"Point"}
}