{
  "type": "Feature",
  "properties": {
    "gn:admin1_code":"3.0",
    "gn:asciiname":"Yakhimovshchina",
    "gn:country_code":"BY",
    "gn:dem":176,
    "gn:feature_class":"P",
    "gn:feature_code":"PPL",
    "gn:name":"Yakhimovshchina",
    "gn:population":0,
    "gn:timezone":"Europe/Minsk",
    "iso:country":"BY",
    "name:bel_x_preferred":[
        "\u042f\u0445\u0456\u043c\u0430\u045e\u0448\u0447\u044b\u043d\u0430"
    ],
    "name:rus_x_preferred":[
        "\u042f\u0445\u0438\u043c\u043e\u0432\u0449\u0438\u043d\u0430"
    ],
    "name:und_x_variant":[
        "Jachimowszcyzna",
        "Yakhimovshchyzna",
        "Yakhimovshchina",
        "Yakhimawshchyna"
    ],
    "wof:name":"Yakhimovshchina",
    "wof:placetype":"locality"
},
  "geometry": {"coordinates":[26.0506,54.1258],"type":"Point"}
}