{
  "type": "Feature",
  "properties": {
    "gn:admin1_code":"7.0",
    "gn:asciiname":"Novoselovo",
    "gn:country_code":"BY",
    "gn:dem":131,
    "gn:feature_class":"P",
    "gn:feature_code":"PPL",
    "gn:name":"Novos\u00eblovo",
    "gn:population":0,
    "gn:timezone":"Europe/Minsk",
    "iso:country":"BY",
    "name:rus_x_preferred":[
        "\u041d\u043e\u0432\u043e\u0441\u0451\u043b\u043e\u0432\u043e"
    ],
    "name:und_x_variant":[
        "Novos\u00eblovo"
    ],
    "wof:name":"Novoselovo",
    "wof:placetype":"locality"
},
  "geometry": {"coordinates":[29.0318,54.9168],"type":"Point"}
}