{
  "type": "Feature",
  "properties": {
    "gn:admin1_code":"7.0",
    "gn:asciiname":"Pligovki",
    "gn:country_code":"BY",
    "gn:dem":127,
    "gn:feature_class":"P",
    "gn:feature_code":"PPL",
    "gn:name":"Pligovki",
    "gn:population":0,
    "gn:timezone":"Europe/Minsk",
    "iso:country":"BY",
    "name:rus_x_preferred":[
        "\u041f\u043b\u0438\u0433\u043e\u0432\u043a\u0438"
    ],
    "wof:name":"Pligovki",
    "wof:placetype":"locality"
},
  "geometry": {"coordinates":[28.4619,55.5517],"type":"Point"}
}