{
  "type": "Feature",
  "properties": {
    "gn:admin1_code":"7.0",
    "gn:asciiname":"Verkhniye Morozy",
    "gn:country_code":"BY",
    "gn:dem":139,
    "gn:feature_class":"P",
    "gn:feature_code":"PPL",
    "gn:name":"Verkhniye Morozy",
    "gn:population":0,
    "gn:timezone":"Europe/Minsk",
    "iso:country":"BY",
    "name:rus_x_preferred":[
        "\u0412\u0435\u0440\u0445\u043d\u0438\u0435 \u041c\u043e\u0440\u043e\u0437\u044b"
    ],
    "wof:name":"Verkhniye Morozy",
    "wof:placetype":"locality"
},
  "geometry": {"coordinates":[28.3766,55.4728],"type":"Point"}
}