{
  "type": "Feature",
  "properties": {
    "gn:admin1_code":"5.0",
    "gn:asciiname":"Vitkovshchina",
    "gn:country_code":"BY",
    "gn:dem":200,
    "gn:feature_class":"P",
    "gn:feature_code":"PPL",
    "gn:name":"Vitkovshchina",
    "gn:population":0,
    "gn:timezone":"Europe/Minsk",
    "iso:country":"BY",
    "name:rus_x_preferred":[
        "\u0412\u0438\u0442\u043a\u043e\u0432\u0449\u0438\u043d\u0430"
    ],
    "name:und_x_variant":[
        "Witkowszczyzna",
        "Vitkovshchyzna",
        "Vitkovshchina"
    ],
    "wof:name":"Vitkovshchina",
    "wof:placetype":"locality"
},
  "geometry": {"coordinates":[26.7185,54.168],"type":"Point"}
}