{
  "type": "Feature",
  "properties": {
    "gn:admin1_code":"3.0",
    "gn:asciiname":"Lovtsy",
    "gn:country_code":"BY",
    "gn:dem":216,
    "gn:feature_class":"P",
    "gn:feature_code":"PPL",
    "gn:name":"Lovtsy",
    "gn:population":0,
    "gn:timezone":"Europe/Minsk",
    "iso:country":"BY",
    "name:bel_x_preferred":[
        "Lawtsy"
    ],
    "name:bel_x_variant":[
        "\u041b\u0430\u045e\u0446\u044b"
    ],
    "name:rus_x_preferred":[
        "\u041b\u043e\u0432\u0446\u044b"
    ],
    "wof:name":"Lovtsy",
    "wof:placetype":"locality"
},
  "geometry": {"coordinates":[25.7076,53.63800000000001],"type":"Point"}
}