{
  "type": "Feature",
  "properties": {
    "gn:admin1_code":"7.0",
    "gn:asciiname":"Vorob'i",
    "gn:country_code":"BY",
    "gn:dem":143,
    "gn:feature_class":"P",
    "gn:feature_code":"PPL",
    "gn:name":"Vorob\u2019i",
    "gn:population":0,
    "gn:timezone":"Europe/Minsk",
    "iso:country":"BY",
    "name:rus_x_preferred":[
        "\u0412\u043e\u0440\u043e\u0431\u044c\u0438"
    ],
    "name:und_x_variant":[
        "Vorob\u2019i"
    ],
    "wof:name":"Vorob'i",
    "wof:placetype":"locality"
},
  "geometry": {"coordinates":[28.5174,55.3895],"type":"Point"}
}