{
  "type": "Feature",
  "properties": {
    "gn:admin1_code":"2.0",
    "gn:asciiname":"Yaskinya",
    "gn:country_code":"BY",
    "gn:dem":141,
    "gn:feature_class":"P",
    "gn:feature_code":"PPL",
    "gn:name":"Yaskinya",
    "gn:population":0,
    "gn:timezone":"Europe/Minsk",
    "iso:country":"BY",
    "name:rus_x_preferred":[
        "\u042f\u0441\u043a\u0438\u043d\u044f"
    ],
    "wof:name":"Yaskinya",
    "wof:placetype":"locality"
},
  "geometry": {"coordinates":[29.7544,53.0394],"type":"Point"}
}