{
  "type": "Feature",
  "properties": {
    "gn:admin1_code":"7.0",
    "gn:asciiname":"Tsyatsyerki",
    "gn:country_code":"BY",
    "gn:dem":154,
    "gn:feature_class":"P",
    "gn:feature_code":"PPL",
    "gn:name":"Tsyatsyerki",
    "gn:population":0,
    "gn:timezone":"Europe/Minsk",
    "iso:country":"BY",
    "name:bel_x_preferred":[
        "\u0426\u044f\u0446\u0435\u0440\u043a\u0456"
    ],
    "name:eng_x_preferred":[
        "Tet\u00ebrki"
    ],
    "name:rus_x_preferred":[
        "\u0422\u0435\u0442\u0435\u0440\u043a\u0438"
    ],
    "name:und_x_variant":[
        "Tsetserki",
        "Tet\u00ebrki",
        "Tsyatsyerki"
    ],
    "wof:name":"Tsyatsyerki",
    "wof:placetype":"locality"
},
  "geometry": {"coordinates":[27.2552,55.5454],"type":"Point"}
}