{
  "type": "Feature",
  "properties": {
    "gn:admin1_code":"7.0",
    "gn:asciiname":"Plino",
    "gn:country_code":"BY",
    "gn:dem":155,
    "gn:feature_class":"P",
    "gn:feature_code":"PPL",
    "gn:name":"Plino",
    "gn:population":0,
    "gn:timezone":"Europe/Minsk",
    "iso:country":"BY",
    "name:rus_x_preferred":[
        "\u041f\u043b\u0438\u043d\u043e"
    ],
    "name:und_x_variant":[
        "Plina"
    ],
    "wof:name":"Plino",
    "wof:placetype":"locality"
},
  "geometry": {"coordinates":[28.5366,55.1802],"type":"Point"}
}