{
  "type": "Feature",
  "properties": {
    "gn:admin1_code":"5.0",
    "gn:asciiname":"Prudniki",
    "gn:country_code":"BY",
    "gn:dem":168,
    "gn:feature_class":"P",
    "gn:feature_code":"PPL",
    "gn:name":"Prudniki",
    "gn:population":0,
    "gn:timezone":"Europe/Minsk",
    "iso:country":"BY",
    "name:rus_x_preferred":[
        "\u041f\u0440\u0443\u0434\u043d\u0438\u043a\u0438"
    ],
    "wof:name":"Prudniki",
    "wof:placetype":"locality"
},
  "geometry": {"coordinates":[26.9602,54.9308],"type":"Point"}
}