{
  "type": "Feature",
  "properties": {
    "gn:admin1_code":"3.0",
    "gn:asciiname":"Rybnitsa",
    "gn:country_code":"BY",
    "gn:dem":126,
    "gn:feature_class":"P",
    "gn:feature_code":"PPL",
    "gn:name":"Rybnitsa",
    "gn:population":0,
    "gn:timezone":"Europe/Minsk",
    "iso:country":"BY",
    "name:bel_x_preferred":[
        "\u0420\u044b\u0431\u043d\u0456\u0446\u0430"
    ],
    "name:eng_x_preferred":[
        "Rybnitsa"
    ],
    "name:rus_x_preferred":[
        "\u0420\u044b\u0431\u043d\u0438\u0446\u0430"
    ],
    "wof:name":"Rybnitsa",
    "wof:placetype":"locality"
},
  "geometry": {"coordinates":[24.0456,53.823],"type":"Point"}
}