{
  "type": "Feature",
  "properties": {
    "gn:admin1_code":"5.0",
    "gn:asciiname":"Podgat'ye",
    "gn:country_code":"BY",
    "gn:dem":177,
    "gn:feature_class":"P",
    "gn:feature_code":"PPL",
    "gn:name":"Podgat\u2019ye",
    "gn:population":0,
    "gn:timezone":"Europe/Minsk",
    "iso:country":"BY",
    "name:rus_x_preferred":[
        "\u041f\u043e\u0434\u0433\u0430\u0442\u044c\u0435"
    ],
    "name:und_x_variant":[
        "Podgat\u2019ye",
        "Podgat\u2019"
    ],
    "wof:name":"Podgat'ye",
    "wof:placetype":"locality"
},
  "geometry": {"coordinates":[27.5886,53.603],"type":"Point"}
}