{
  "type": "Feature",
  "properties": {
    "gn:admin1_code":"1.0",
    "gn:asciiname":"Belenok",
    "gn:country_code":"BY",
    "gn:dem":152,
    "gn:feature_class":"P",
    "gn:feature_code":"PPL",
    "gn:name":"Belenok",
    "gn:population":0,
    "gn:timezone":"Europe/Minsk",
    "iso:country":"BY",
    "name:rus_x_preferred":[
        "\u0411\u0435\u043b\u0435\u043d\u043e\u043a"
    ],
    "name:und_x_variant":[
        "Bielinek",
        "Belinok",
        "Belenok",
        "Belinek"
    ],
    "wof:name":"Belenok",
    "wof:placetype":"locality"
},
  "geometry": {"coordinates":[25.0946,52.2479],"type":"Point"}
}