{
  "type": "Feature",
  "properties": {
    "gn:admin1_code":"2.0",
    "gn:asciiname":"Barsuki",
    "gn:country_code":"BY",
    "gn:dem":155,
    "gn:feature_class":"P",
    "gn:feature_code":"PPL",
    "gn:name":"Barsuki",
    "gn:population":0,
    "gn:timezone":"Europe/Minsk",
    "iso:country":"BY",
    "name:bel_x_preferred":[
        "\u0411\u0430\u0440\u0441\u0443\u043a\u0456"
    ],
    "wof:name":"Barsuki",
    "wof:placetype":"locality"
},
  "geometry": {"coordinates":[30.7086,53.1365],"type":"Point"}
}