{
  "type": "Feature",
  "properties": {
    "gn:admin1_code":"2.0",
    "gn:asciiname":"Kalinovaya",
    "gn:country_code":"BY",
    "gn:dem":127,
    "gn:feature_class":"P",
    "gn:feature_code":"PPL",
    "gn:name":"Kalinovaya",
    "gn:population":0,
    "gn:timezone":"Europe/Minsk",
    "iso:country":"BY",
    "name:rus_x_preferred":[
        "\u041a\u0430\u043b\u0438\u043d\u043e\u0432\u0430\u044f"
    ],
    "wof:name":"Kalinovaya",
    "wof:placetype":"locality"
},
  "geometry": {"coordinates":[28.9885,51.7034],"type":"Point"}
}