{
  "type": "Feature",
  "properties": {
    "gn:admin1_code":"7.0",
    "gn:asciiname":"Sokoly",
    "gn:country_code":"BY",
    "gn:dem":196,
    "gn:feature_class":"P",
    "gn:feature_code":"PPL",
    "gn:name":"Sokoly",
    "gn:population":0,
    "gn:timezone":"Europe/Minsk",
    "iso:country":"BY",
    "name:rus_x_preferred":[
        "\u0421\u043e\u043a\u043e\u043b\u044b"
    ],
    "wof:name":"Sokoly",
    "wof:placetype":"locality"
},
  "geometry": {"coordinates":[27.0596,55.0385],"type":"Point"}
}