{
  "type": "Feature",
  "properties": {
    "gn:admin1_code":"6.0",
    "gn:asciiname":"Trusok",
    "gn:country_code":"BY",
    "gn:dem":162,
    "gn:feature_class":"P",
    "gn:feature_code":"PPL",
    "gn:name":"Trusok",
    "gn:population":0,
    "gn:timezone":"Europe/Minsk",
    "iso:country":"BY",
    "name:rus_x_preferred":[
        "\u0422\u0440\u0443\u0441\u043e\u043a"
    ],
    "wof:name":"Trusok",
    "wof:placetype":"locality"
},
  "geometry": {"coordinates":[32.2575,53.2828],"type":"Point"}
}