{
  "type": "Feature",
  "properties": {
    "gn:admin1_code":"1.0",
    "gn:asciiname":"Vyalikaya Hats'",
    "gn:country_code":"BY",
    "gn:dem":149,
    "gn:feature_class":"P",
    "gn:feature_code":"PPL",
    "gn:name":"Vyalikaya Hats\u2019",
    "gn:population":0,
    "gn:timezone":"Europe/Minsk",
    "iso:country":"BY",
    "name:bel_x_preferred":[
        "\u0412\u044f\u043b\u0456\u043a\u0430\u044f \u0413\u0430\u0446\u044c"
    ],
    "name:rus_x_preferred":[
        "Velikaya Gat\u2019"
    ],
    "name:und_x_variant":[
        "Vel\u2019ka Gats\u2019",
        "Vyalikaya Hats\u2019"
    ],
    "wof:name":"Vyalikaya Hats'",
    "wof:placetype":"locality"
},
  "geometry": {"coordinates":[25.657,52.5522],"type":"Point"}
}