{
  "type": "Feature",
  "properties": {
    "gn:admin1_code":"6.0",
    "gn:asciiname":"Bol'shiye Sloveni",
    "gn:country_code":"BY",
    "gn:dem":190,
    "gn:feature_class":"P",
    "gn:feature_code":"PPL",
    "gn:name":"Bol\u2019shiye Sloveni",
    "gn:population":0,
    "gn:timezone":"Europe/Minsk",
    "iso:country":"BY",
    "name:rus_x_preferred":[
        "\u0411\u043e\u043b\u044c\u0448\u0438\u0435 \u0421\u043b\u043e\u0432\u0435\u043d\u0438"
    ],
    "name:und_x_variant":[
        "Bol\u2019shiye Sloveni"
    ],
    "wof:name":"Bol'shiye Sloveni",
    "wof:placetype":"locality"
},
  "geometry": {"coordinates":[30.4216,54.2589],"type":"Point"}
}