{
  "type": "Feature",
  "properties": {
    "gn:admin1_code":"7.0",
    "gn:asciiname":"Maloye Sitna",
    "gn:country_code":"BY",
    "gn:dem":149,
    "gn:feature_class":"P",
    "gn:feature_code":"PPL",
    "gn:name":"Maloye Sitna",
    "gn:population":0,
    "gn:timezone":"Europe/Minsk",
    "iso:country":"BY",
    "name:bel_x_preferred":[
        "\u041c\u0430\u043b\u043e\u0435 \u0421\u0456\u0442\u043d\u0430"
    ],
    "name:eng_x_preferred":[
        "Maloye Sitno"
    ],
    "name:rus_x_preferred":[
        "\u041c\u0430\u043b.\u0421\u0438\u0442\u043d\u043e"
    ],
    "name:und_x_variant":[
        "Maloye Sitno"
    ],
    "wof:name":"Maloye Sitna",
    "wof:placetype":"locality"
},
  "geometry": {"coordinates":[29.3555,55.692],"type":"Point"}
}