{
  "type": "Feature",
  "properties": {
    "gn:admin1_code":"7.0",
    "gn:asciiname":"Malyakovo",
    "gn:country_code":"BY",
    "gn:dem":170,
    "gn:feature_class":"P",
    "gn:feature_code":"PPL",
    "gn:name":"Malyakovo",
    "gn:population":0,
    "gn:timezone":"Europe/Minsk",
    "iso:country":"BY",
    "name:rus_x_preferred":[
        "\u041c\u0430\u043b\u044f\u043a\u043e\u0432\u043e"
    ],
    "wof:name":"Malyakovo",
    "wof:placetype":"locality"
},
  "geometry": {"coordinates":[27.2904,54.9767],"type":"Point"}
}