{
  "type": "Feature",
  "properties": {
    "gn:admin1_code":"7.0",
    "gn:asciiname":"Zastenok-Rechnyye",
    "gn:country_code":"BY",
    "gn:dem":168,
    "gn:feature_class":"P",
    "gn:feature_code":"PPL",
    "gn:name":"Zastenok-Rechnyye",
    "gn:population":0,
    "gn:timezone":"Europe/Minsk",
    "iso:country":"BY",
    "name:rus_x_preferred":[
        "\u0417\u0430\u0441\u0442\u0435\u043d\u043e\u043a-\u0420\u0435\u0447\u043d\u044b\u0435"
    ],
    "name:und_x_variant":[
        "Rechnyye"
    ],
    "wof:name":"Zastenok-Rechnyye",
    "wof:placetype":"locality"
},
  "geometry": {"coordinates":[27.9689,54.9811],"type":"Point"}
}