{
  "type": "Feature",
  "properties": {
    "gn:admin1_code":"7.0",
    "gn:asciiname":"Savin Dub",
    "gn:country_code":"BY",
    "gn:dem":164,
    "gn:feature_class":"P",
    "gn:feature_code":"PPL",
    "gn:name":"Savin Dub",
    "gn:population":0,
    "gn:timezone":"Europe/Minsk",
    "iso:country":"BY",
    "name:rus_x_preferred":[
        "\u0421\u0430\u0432\u0438\u043d \u0414\u0443\u0431"
    ],
    "wof:name":"Savin Dub",
    "wof:placetype":"locality"
},
  "geometry": {"coordinates":[28.4372,54.93],"type":"Point"}
}