{
  "type": "Feature",
  "properties": {
    "gn:admin1_code":"2.0",
    "gn:asciiname":"Pukhichin",
    "gn:country_code":"BY",
    "gn:dem":140,
    "gn:feature_class":"P",
    "gn:feature_code":"PPL",
    "gn:name":"Pukhichin",
    "gn:population":0,
    "gn:timezone":"Europe/Minsk",
    "iso:country":"BY",
    "name:rus_x_preferred":[
        "\u041f\u0443\u0445\u0438\u0447\u0438\u043d"
    ],
    "wof:name":"Pukhichin",
    "wof:placetype":"locality"
},
  "geometry": {"coordinates":[29.0382,52.5977],"type":"Point"}
}