{
  "type": "Feature",
  "properties": {
    "gn:admin1_code":"2.0",
    "gn:asciiname":"Balotnya",
    "gn:country_code":"BY",
    "gn:dem":149,
    "gn:feature_class":"P",
    "gn:feature_code":"PPL",
    "gn:name":"Balotnya",
    "gn:population":0,
    "gn:timezone":"Europe/Minsk",
    "iso:country":"BY",
    "name:bel_x_preferred":[
        "\u0411\u0430\u043b\u043e\u0442\u043d\u044f"
    ],
    "name:und_x_variant":[
        "Volotnya",
        "Bolotnya",
        "Balotnya"
    ],
    "wof:name":"Balotnya",
    "wof:placetype":"locality"
},
  "geometry": {"coordinates":[30.6115,53.2097],"type":"Point"}
}