{
  "type": "Feature",
  "properties": {
    "gn:admin1_code":"7.0",
    "gn:asciiname":"Zaborok",
    "gn:country_code":"BY",
    "gn:dem":152,
    "gn:feature_class":"P",
    "gn:feature_code":"PPL",
    "gn:name":"Zaborok",
    "gn:population":0,
    "gn:timezone":"Europe/Minsk",
    "iso:country":"BY",
    "name:rus_x_preferred":[
        "\u0417\u0430\u0431\u043e\u0440\u043e\u043a"
    ],
    "wof:name":"Zaborok",
    "wof:placetype":"locality"
},
  "geometry": {"coordinates":[30.4702,55.5786],"type":"Point"}
}