{
  "type": "Feature",
  "properties": {
    "gn:admin1_code":"5.0",
    "gn:asciiname":"Kolodki",
    "gn:country_code":"BY",
    "gn:dem":161,
    "gn:feature_class":"P",
    "gn:feature_code":"PPL",
    "gn:name":"Kolodki",
    "gn:population":0,
    "gn:timezone":"Europe/Minsk",
    "iso:country":"BY",
    "name:rus_x_preferred":[
        "\u041a\u043e\u043b\u043e\u0434\u043a\u0438"
    ],
    "wof:name":"Kolodki",
    "wof:placetype":"locality"
},
  "geometry": {"coordinates":[26.7245,54.6424],"type":"Point"}
}