{
  "type": "Feature",
  "properties": {
    "gn:admin1_code":"6.0",
    "gn:asciiname":"Staraya Vodva",
    "gn:country_code":"BY",
    "gn:dem":194,
    "gn:feature_class":"P",
    "gn:feature_code":"PPL",
    "gn:name":"Staraya Vodva",
    "gn:population":0,
    "gn:timezone":"Europe/Minsk",
    "iso:country":"BY",
    "name:eng_x_preferred":[
        "Staraya Vodva"
    ],
    "name:rus_x_preferred":[
        "\u0421\u0442.\u0432\u043e\u0434\u0432\u0430"
    ],
    "name:rus_x_variant":[
        "\u0421\u0442\u0430\u0440\u0430\u044f \u0412\u043e\u0434\u0432\u0430"
    ],
    "name:und_x_variant":[
        "Vodva",
        "Staraya Vodva"
    ],
    "wof:name":"Staraya Vodva",
    "wof:placetype":"locality"
},
  "geometry": {"coordinates":[30.1952,54.0729],"type":"Point"}
}