{
  "type": "Feature",
  "properties": {
    "gn:admin1_code":"5.0",
    "gn:asciiname":"Orekhovskaya",
    "gn:country_code":"BY",
    "gn:dem":270,
    "gn:feature_class":"P",
    "gn:feature_code":"PPL",
    "gn:name":"Orekhovskaya",
    "gn:population":0,
    "gn:timezone":"Europe/Minsk",
    "iso:country":"BY",
    "name:rus_x_preferred":[
        "\u041e\u0440\u0435\u0445\u043e\u0432\u0441\u043a\u0430\u044f"
    ],
    "wof:name":"Orekhovskaya",
    "wof:placetype":"locality"
},
  "geometry": {"coordinates":[27.2802,53.8198],"type":"Point"}
}