{
  "type": "Feature",
  "properties": {
    "gn:admin1_code":"7.0",
    "gn:asciiname":"Teshelovo",
    "gn:country_code":"BY",
    "gn:dem":187,
    "gn:feature_class":"P",
    "gn:feature_code":"PPL",
    "gn:name":"Teshelovo",
    "gn:population":0,
    "gn:timezone":"Europe/Minsk",
    "iso:country":"BY",
    "name:rus_x_preferred":[
        "\u0422\u0435\u0448\u0435\u043b\u043e\u0432\u043e"
    ],
    "wof:name":"Teshelovo",
    "wof:placetype":"locality"
},
  "geometry": {"coordinates":[27.0294,55.0794],"type":"Point"}
}