{
  "type": "Feature",
  "properties": {
    "gn:admin1_code":"1.0",
    "gn:asciiname":"Botovo",
    "gn:country_code":"BY",
    "gn:dem":140,
    "gn:feature_class":"P",
    "gn:feature_code":"PPL",
    "gn:name":"Botovo",
    "gn:population":0,
    "gn:timezone":"Europe/Minsk",
    "iso:country":"BY",
    "name:deu_x_preferred":[
        "Botovo"
    ],
    "name:rus_x_preferred":[
        "\u0411\u043e\u0442\u043e\u0432\u043e"
    ],
    "name:srp_x_preferred":[
        "\u0411\u043e\u0442\u043e\u0432\u043e"
    ],
    "name:und_x_variant":[
        "Botowo"
    ],
    "wof:name":"Botovo",
    "wof:placetype":"locality"
},
  "geometry": {"coordinates":[26.3169,52.3376],"type":"Point"}
}