{
  "type": "Feature",
  "properties": {
    "gn:admin1_code":"3.0",
    "gn:asciiname":"Skilondishki",
    "gn:country_code":"BY",
    "gn:dem":207,
    "gn:feature_class":"P",
    "gn:feature_code":"PPL",
    "gn:name":"Skilondishki",
    "gn:population":0,
    "gn:timezone":"Europe/Minsk",
    "iso:country":"BY",
    "name:rus_x_preferred":[
        "\u0421\u043a\u0438\u043b\u043e\u043d\u0434\u0438\u0448\u043a\u0438"
    ],
    "name:und_x_variant":[
        "Shkilondishki"
    ],
    "wof:name":"Skilondishki",
    "wof:placetype":"locality"
},
  "geometry": {"coordinates":[26.0203,54.5193],"type":"Point"}
}