{
  "type": "Feature",
  "properties": {
    "gn:admin1_code":"5.0",
    "gn:asciiname":"Mostishche",
    "gn:country_code":"BY",
    "gn:dem":150,
    "gn:feature_class":"P",
    "gn:feature_code":"PPL",
    "gn:name":"Mostishche",
    "gn:population":0,
    "gn:timezone":"Europe/Minsk",
    "iso:country":"BY",
    "name:rus_x_preferred":[
        "\u041c\u043e\u0441\u0442\u0438\u0449\u0435"
    ],
    "wof:name":"Mostishche",
    "wof:placetype":"locality"
},
  "geometry": {"coordinates":[26.8361,54.3672],"type":"Point"}
}