{
  "type": "Feature",
  "properties": {
    "gn:admin1_code":"2.0",
    "gn:asciiname":"Zabiyaka",
    "gn:country_code":"BY",
    "gn:dem":133,
    "gn:feature_class":"P",
    "gn:feature_code":"PPL",
    "gn:name":"Zabiyaka",
    "gn:population":0,
    "gn:timezone":"Europe/Minsk",
    "iso:country":"BY",
    "name:rus_x_preferred":[
        "\u0417\u0430\u0431\u0438\u044f\u043a\u0430"
    ],
    "wof:name":"Zabiyaka",
    "wof:placetype":"locality"
},
  "geometry": {"coordinates":[30.9319,52.4828],"type":"Point"}
}