{
  "type": "Feature",
  "properties": {
    "gn:admin1_code":"2.0",
    "gn:asciiname":"Kharomtsy",
    "gn:country_code":"BY",
    "gn:dem":135,
    "gn:feature_class":"P",
    "gn:feature_code":"PPL",
    "gn:name":"Kharomtsy",
    "gn:population":0,
    "gn:timezone":"Europe/Minsk",
    "iso:country":"BY",
    "name:bel_x_preferred":[
        "\u0425\u0430\u0440\u043e\u043c\u0446\u044b"
    ],
    "name:eng_x_preferred":[
        "Khoromtsy"
    ],
    "name:rus_x_preferred":[
        "\u0425\u043e\u0440\u043e\u043c\u0446\u044b"
    ],
    "name:und_x_variant":[
        "Khoromtsy",
        "Kharomtsy"
    ],
    "wof:name":"Kharomtsy",
    "wof:placetype":"locality"
},
  "geometry": {"coordinates":[28.6353,52.6866],"type":"Point"}
}