{
  "type": "Feature",
  "properties": {
    "gn:admin1_code":"7.0",
    "gn:asciiname":"Virshaly",
    "gn:country_code":"BY",
    "gn:dem":172,
    "gn:feature_class":"P",
    "gn:feature_code":"PPL",
    "gn:name":"Virshaly",
    "gn:population":0,
    "gn:timezone":"Europe/Minsk",
    "iso:country":"BY",
    "name:rus_x_preferred":[
        "\u0412\u0438\u0440\u0448\u0430\u043b\u044b"
    ],
    "wof:name":"Virshaly",
    "wof:placetype":"locality"
},
  "geometry": {"coordinates":[26.4593,55.0738],"type":"Point"}
}