{
  "type": "Feature",
  "properties": {
    "gn:admin1_code":"1.0",
    "gn:asciiname":"Zhukhovtsy",
    "gn:country_code":"BY",
    "gn:dem":141,
    "gn:feature_class":"P",
    "gn:feature_code":"PPL",
    "gn:name":"Zhukhovtsy",
    "gn:population":0,
    "gn:timezone":"Europe/Minsk",
    "iso:country":"BY",
    "name:rus_x_preferred":[
        "\u0416\u0443\u0445\u043e\u0432\u0446\u044b"
    ],
    "wof:name":"Zhukhovtsy",
    "wof:placetype":"locality"
},
  "geometry": {"coordinates":[24.4978,52.2911],"type":"Point"}
}