{
  "type": "Feature",
  "properties": {
    "gn:admin1_code":"7.0",
    "gn:asciiname":"Pestuny",
    "gn:country_code":"BY",
    "gn:dem":153,
    "gn:feature_class":"P",
    "gn:feature_code":"PPL",
    "gn:name":"Pestuny",
    "gn:population":0,
    "gn:timezone":"Europe/Minsk",
    "iso:country":"BY",
    "name:rus_x_preferred":[
        "\u041f\u0435\u0441\u0442\u0443\u043d\u044b"
    ],
    "wof:name":"Pestuny",
    "wof:placetype":"locality"
},
  "geometry": {"coordinates":[27.6808,55.5623],"type":"Point"}
}