{
  "type": "Feature",
  "properties": {
    "gn:admin1_code":"7.0",
    "gn:asciiname":"Yanovo",
    "gn:country_code":"BY",
    "gn:dem":145,
    "gn:feature_class":"P",
    "gn:feature_code":"PPL",
    "gn:name":"Yanovo",
    "gn:population":0,
    "gn:timezone":"Europe/Minsk",
    "iso:country":"BY",
    "name:rus_x_preferred":[
        "\u042f\u043d\u043e\u0432\u043e"
    ],
    "wof:name":"Yanovo",
    "wof:placetype":"locality"
},
  "geometry": {"coordinates":[27.5091,55.5986],"type":"Point"}
}