{
  "type": "Feature",
  "properties": {
    "gn:admin1_code":"1.0",
    "gn:asciiname":"Vyzorok",
    "gn:country_code":"BY",
    "gn:dem":195,
    "gn:feature_class":"P",
    "gn:feature_code":"PPL",
    "gn:name":"Vyzorok",
    "gn:population":0,
    "gn:timezone":"Europe/Minsk",
    "iso:country":"BY",
    "name:rus_x_preferred":[
        "\u0412\u044b\u0437\u043e\u0440\u043e\u043a"
    ],
    "wof:name":"Vyzorok",
    "wof:placetype":"locality"
},
  "geometry": {"coordinates":[26.1025,53.3104],"type":"Point"}
}