{
  "type": "Feature",
  "properties": {
    "gn:admin1_code":"7.0",
    "gn:asciiname":"Shukhovtsy",
    "gn:country_code":"BY",
    "gn:dem":186,
    "gn:feature_class":"P",
    "gn:feature_code":"PPL",
    "gn:name":"Shukhovtsy",
    "gn:population":0,
    "gn:timezone":"Europe/Minsk",
    "iso:country":"BY",
    "name:rus_x_preferred":[
        "\u0428\u0443\u0445\u043e\u0432\u0446\u044b"
    ],
    "wof:name":"Shukhovtsy",
    "wof:placetype":"locality"
},
  "geometry": {"coordinates":[30.8962,54.6862],"type":"Point"}
}