{
  "type": "Feature",
  "properties": {
    "gn:admin1_code":"6.0",
    "gn:asciiname":"Barchitsy",
    "gn:country_code":"BY",
    "gn:dem":152,
    "gn:feature_class":"P",
    "gn:feature_code":"PPL",
    "gn:name":"Barchitsy",
    "gn:population":0,
    "gn:timezone":"Europe/Minsk",
    "iso:country":"BY",
    "name:eng_x_preferred":[
        "Barchitsa"
    ],
    "name:rus_x_preferred":[
        "\u0411\u0430\u0440\u0447\u0438\u0446\u044b"
    ],
    "name:und_x_variant":[
        "Barchitsy"
    ],
    "wof:name":"Barchitsy",
    "wof:placetype":"locality"
},
  "geometry": {"coordinates":[29.6682,53.25899999999999],"type":"Point"}
}