{
  "type": "Feature",
  "properties": {
    "gn:admin1_code":"5.0",
    "gn:asciiname":"Kapatsevichy",
    "gn:country_code":"BY",
    "gn:dem":142,
    "gn:feature_class":"P",
    "gn:feature_code":"PPL",
    "gn:name":"Kapatsevichy",
    "gn:population":0,
    "gn:timezone":"Europe/Minsk",
    "iso:country":"BY",
    "name:bel_x_preferred":[
        "\u041a\u0430\u043f\u0430\u0446\u044d\u0432\u0456\u0447\u044b"
    ],
    "name:eng_x_preferred":[
        "Kopatsevichi"
    ],
    "name:rus_x_preferred":[
        "\u041a\u043e\u043f\u0430\u0446\u0435\u0432\u0438\u0447\u0438"
    ],
    "name:und_x_variant":[
        "Kopatsevichi",
        "Kapatsevichy"
    ],
    "wof:name":"Kapatsevichy",
    "wof:placetype":"locality"
},
  "geometry": {"coordinates":[27.3796,52.6307],"type":"Point"}
}