{
  "type": "Feature",
  "properties": {
    "gn:admin1_code":"7.0",
    "gn:asciiname":"Konopel'chitsy",
    "gn:country_code":"BY",
    "gn:dem":200,
    "gn:feature_class":"P",
    "gn:feature_code":"PPL",
    "gn:name":"Konopel\u2019chitsy",
    "gn:population":0,
    "gn:timezone":"Europe/Minsk",
    "iso:country":"BY",
    "name:rus_x_preferred":[
        "\u041a\u043e\u043d\u043e\u043f\u0435\u043b\u044c\u0447\u0438\u0446\u044b"
    ],
    "name:und_x_variant":[
        "Konopel\u2019chitsy"
    ],
    "wof:name":"Konopel'chitsy",
    "wof:placetype":"locality"
},
  "geometry": {"coordinates":[29.7193,54.4497],"type":"Point"}
}