{
  "type": "Feature",
  "properties": {
    "gn:admin1_code":"1.0",
    "gn:asciiname":"Ulasy",
    "gn:country_code":"BY",
    "gn:dem":185,
    "gn:feature_class":"P",
    "gn:feature_code":"PPL",
    "gn:name":"Ulasy",
    "gn:population":0,
    "gn:timezone":"Europe/Minsk",
    "iso:country":"BY",
    "name:rus_x_preferred":[
        "\u0423\u043b\u0430\u0441\u044b"
    ],
    "wof:name":"Ulasy",
    "wof:placetype":"locality"
},
  "geometry": {"coordinates":[26.1192,53.2363],"type":"Point"}
}