{
  "type": "Feature",
  "properties": {
    "gn:admin1_code":"3.0",
    "gn:asciiname":"Gumenniki",
    "gn:country_code":"BY",
    "gn:dem":171,
    "gn:feature_class":"P",
    "gn:feature_code":"PPL",
    "gn:name":"Gumenniki",
    "gn:population":0,
    "gn:timezone":"Europe/Minsk",
    "iso:country":"BY",
    "name:rus_x_preferred":[
        "\u0413\u0443\u043c\u0435\u043d\u043d\u0438\u043a\u0438"
    ],
    "wof:name":"Gumenniki",
    "wof:placetype":"locality"
},
  "geometry": {"coordinates":[25.2028,52.9599],"type":"Point"}
}