{
  "type": "Feature",
  "properties": {
    "gn:admin1_code":"5.0",
    "gn:asciiname":"Velikiye Ukropovichi",
    "gn:country_code":"BY",
    "gn:dem":222,
    "gn:feature_class":"P",
    "gn:feature_code":"PPL",
    "gn:name":"Velikiye Ukropovichi",
    "gn:population":0,
    "gn:timezone":"Europe/Minsk",
    "iso:country":"BY",
    "name:rus_x_preferred":[
        "\u0412\u0435\u043b\u0438\u043a\u0438\u0435 \u0423\u043a\u0440\u043e\u043f\u043e\u0432\u0438\u0447\u0438"
    ],
    "name:und_x_variant":[
        "Bol\u2019shiye Ukropovichi"
    ],
    "wof:name":"Velikiye Ukropovichi",
    "wof:placetype":"locality"
},
  "geometry": {"coordinates":[27.7109,54.3406],"type":"Point"}
}