{
  "type": "Feature",
  "properties": {
    "gn:admin1_code":"7.0",
    "gn:asciiname":"Lopunovo",
    "gn:country_code":"BY",
    "gn:dem":130,
    "gn:feature_class":"P",
    "gn:feature_code":"PPL",
    "gn:name":"Lopunovo",
    "gn:population":0,
    "gn:timezone":"Europe/Minsk",
    "iso:country":"BY",
    "name:rus_x_preferred":[
        "\u041b\u043e\u043f\u0443\u043d\u043e\u0432\u043e"
    ],
    "wof:name":"Lopunovo",
    "wof:placetype":"locality"
},
  "geometry": {"coordinates":[27.855,55.3683],"type":"Point"}
}