{
  "type": "Feature",
  "properties": {
    "gn:admin1_code":"3.0",
    "gn:asciiname":"Atsminava",
    "gn:country_code":"BY",
    "gn:dem":149,
    "gn:feature_class":"P",
    "gn:feature_code":"PPL",
    "gn:name":"Atsminava",
    "gn:population":0,
    "gn:timezone":"Europe/Minsk",
    "iso:country":"BY",
    "name:bel_x_preferred":[
        "\u0410\u0446\u043c\u0456\u043d\u0430\u0432\u0430"
    ],
    "name:eng_x_preferred":[
        "Otminovo"
    ],
    "name:rus_x_preferred":[
        "\u041e\u0442\u043c\u0438\u043d\u043e\u0432\u043e"
    ],
    "name:und_x_variant":[
        "Ayminova",
        "Otsminovo",
        "Ots\u2019minuv",
        "Otsminova",
        "Otminovo",
        "Atsminava"
    ],
    "wof:name":"Atsminava",
    "wof:placetype":"locality"
},
  "geometry": {"coordinates":[25.7059,53.7918],"type":"Point"}
}