{
  "type": "Feature",
  "properties": {
    "gn:admin1_code":"5.0",
    "gn:asciiname":"Khonevichi",
    "gn:country_code":"BY",
    "gn:dem":188,
    "gn:feature_class":"P",
    "gn:feature_code":"PPL",
    "gn:name":"Khonevichi",
    "gn:population":0,
    "gn:timezone":"Europe/Minsk",
    "iso:country":"BY",
    "name:rus_x_preferred":[
        "\u0425\u043e\u043d\u0435\u0432\u0438\u0447\u0438"
    ],
    "wof:name":"Khonevichi",
    "wof:placetype":"locality"
},
  "geometry": {"coordinates":[26.5206,54.8199],"type":"Point"}
}