{
  "type": "Feature",
  "properties": {
    "gn:admin1_code":"3.0",
    "gn:asciiname":"Kozly",
    "gn:country_code":"BY",
    "gn:dem":120,
    "gn:feature_class":"P",
    "gn:feature_code":"PPL",
    "gn:name":"Kozly",
    "gn:population":0,
    "gn:timezone":"Europe/Minsk",
    "iso:country":"BY",
    "name:rus_x_preferred":[
        "\u041a\u043e\u0437\u043b\u044b"
    ],
    "wof:name":"Kozly",
    "wof:placetype":"locality"
},
  "geometry": {"coordinates":[23.9122,53.4008],"type":"Point"}
}