{
  "type": "Feature",
  "properties": {
    "gn:admin1_code":"6.0",
    "gn:asciiname":"Beskakovo",
    "gn:country_code":"BY",
    "gn:dem":190,
    "gn:feature_class":"P",
    "gn:feature_code":"PPL",
    "gn:name":"Beskakovo",
    "gn:population":0,
    "gn:timezone":"Europe/Minsk",
    "iso:country":"BY",
    "name:rus_x_preferred":[
        "\u0411\u0435\u0441\u043a\u0430\u043a\u043e\u0432\u043e"
    ],
    "name:und_x_variant":[
        "Biskakova"
    ],
    "wof:name":"Beskakovo",
    "wof:placetype":"locality"
},
  "geometry": {"coordinates":[31.585,53.9466],"type":"Point"}
}