{
  "type": "Feature",
  "properties": {
    "gn:admin1_code":"5.0",
    "gn:asciiname":"Yushavichy",
    "gn:country_code":"BY",
    "gn:dem":185,
    "gn:feature_class":"P",
    "gn:feature_code":"PPL",
    "gn:name":"Yushavichy",
    "gn:population":0,
    "gn:timezone":"Europe/Minsk",
    "iso:country":"BY",
    "name:bel_x_preferred":[
        "\u042e\u0448\u0430\u0432\u0456\u0447\u044b"
    ],
    "name:und_x_variant":[
        "Yusheviche",
        "Yushevichi",
        "Yushavichy"
    ],
    "wof:name":"Yushavichy",
    "wof:placetype":"locality"
},
  "geometry": {"coordinates":[26.8405,53.2492],"type":"Point"}
}