{
  "type": "Feature",
  "properties": {
    "gn:admin1_code":"3.0",
    "gn:asciiname":"Tereshki",
    "gn:country_code":"BY",
    "gn:dem":234,
    "gn:feature_class":"P",
    "gn:feature_code":"PPL",
    "gn:name":"Tereshki",
    "gn:population":0,
    "gn:timezone":"Europe/Minsk",
    "iso:country":"BY",
    "name:rus_x_preferred":[
        "\u0422\u0435\u0440\u0435\u0448\u043a\u0438"
    ],
    "wof:name":"Tereshki",
    "wof:placetype":"locality"
},
  "geometry": {"coordinates":[26.4139,54.3573],"type":"Point"}
}