{
  "type": "Feature",
  "properties": {
    "gn:admin1_code":"2.0",
    "gn:asciiname":"Karavatsichy",
    "gn:country_code":"BY",
    "gn:dem":130,
    "gn:feature_class":"P",
    "gn:feature_code":"PPL",
    "gn:name":"Karavatsichy",
    "gn:population":0,
    "gn:timezone":"Europe/Minsk",
    "iso:country":"BY",
    "name:bel_x_preferred":[
        "\u041a\u0430\u0440\u0430\u0432\u0430\u0446\u0456\u0447\u044b"
    ],
    "name:eng_x_preferred":[
        "Korovatichi"
    ],
    "name:rus_x_preferred":[
        "\u041a\u043e\u0440\u043e\u0432\u0430\u0442\u0438\u0447\u0438"
    ],
    "name:und_x_variant":[
        "Karovotichi"
    ],
    "wof:name":"Karavatsichy",
    "wof:placetype":"locality"
},
  "geometry": {"coordinates":[30.1094,52.232],"type":"Point"}
}