{
  "type": "Feature",
  "properties": {
    "gn:admin1_code":"3.0",
    "gn:asciiname":"Galimshchina",
    "gn:country_code":"BY",
    "gn:dem":142,
    "gn:feature_class":"P",
    "gn:feature_code":"PPL",
    "gn:name":"Galimshchina",
    "gn:population":0,
    "gn:timezone":"Europe/Minsk",
    "iso:country":"BY",
    "name:rus_x_preferred":[
        "\u0413\u0430\u043b\u0438\u043c\u0449\u0438\u043d\u0430"
    ],
    "name:und_x_variant":[
        "Galimshchizna",
        "Galimshchina"
    ],
    "wof:name":"Galimshchina",
    "wof:placetype":"locality"
},
  "geometry": {"coordinates":[25.7265,54.0298],"type":"Point"}
}