{
  "type": "Feature",
  "properties": {
    "gn:admin1_code":"0.0",
    "gn:asciiname":"Gryadki",
    "gn:country_code":"BY",
    "gn:dem":173,
    "gn:feature_class":"P",
    "gn:feature_code":"PPL",
    "gn:name":"Gryadki",
    "gn:population":0,
    "gn:timezone":"Europe/Minsk",
    "iso:country":"BY",
    "wof:name":"Gryadki",
    "wof:placetype":"locality"
},
  "geometry": {"coordinates":[30.76667,55.28333000000001],"type":"Point"}
}