{
  "type": "Feature",
  "properties": {
    "gn:admin1_code":"7.0",
    "gn:asciiname":"Tenyugi",
    "gn:country_code":"BY",
    "gn:dem":137,
    "gn:feature_class":"P",
    "gn:feature_code":"PPL",
    "gn:name":"Tenyugi",
    "gn:population":0,
    "gn:timezone":"Europe/Minsk",
    "iso:country":"BY",
    "name:rus_x_preferred":[
        "\u0422\u0435\u043d\u044e\u0433\u0438"
    ],
    "wof:name":"Tenyugi",
    "wof:placetype":"locality"
},
  "geometry": {"coordinates":[29.1309,55.2138],"type":"Point"}
}