{
  "type": "Feature",
  "properties": {
    "gn:admin1_code":"7.0",
    "gn:asciiname":"Delikatory",
    "gn:country_code":"BY",
    "gn:dem":137,
    "gn:feature_class":"P",
    "gn:feature_code":"PPL",
    "gn:name":"Delikatory",
    "gn:population":0,
    "gn:timezone":"Europe/Minsk",
    "iso:country":"BY",
    "name:rus_x_preferred":[
        "\u0414\u0435\u043b\u0438\u043a\u0430\u0442\u043e\u0440\u044b"
    ],
    "wof:name":"Delikatory",
    "wof:placetype":"locality"
},
  "geometry": {"coordinates":[27.2916,55.7452],"type":"Point"}
}