{
  "type": "Feature",
  "properties": {
    "gn:admin1_code":"6.0",
    "gn:asciiname":"Bashkirovka",
    "gn:country_code":"BY",
    "gn:dem":194,
    "gn:feature_class":"P",
    "gn:feature_code":"PPL",
    "gn:name":"Bashkirovka",
    "gn:population":0,
    "gn:timezone":"Europe/Minsk",
    "iso:country":"BY",
    "name:rus_x_preferred":[
        "\u0411\u0430\u0448\u043a\u0438\u0440\u043e\u0432\u043a\u0430"
    ],
    "wof:name":"Bashkirovka",
    "wof:placetype":"locality"
},
  "geometry": {"coordinates":[30.4439,54.1781],"type":"Point"}
}