{
  "type": "Feature",
  "properties": {
    "gn:admin1_code":"1.0",
    "gn:asciiname":"Plotytsi",
    "gn:country_code":"BY",
    "gn:dem":152,
    "gn:feature_class":"P",
    "gn:feature_code":"PPL",
    "gn:name":"Plotytsi",
    "gn:population":0,
    "gn:timezone":"Europe/Minsk",
    "iso:country":"BY",
    "name:rus_x_preferred":[
        "\u041f\u043b\u043e\u0442\u044b\u0446\u0438"
    ],
    "wof:name":"Plotytsi",
    "wof:placetype":"locality"
},
  "geometry": {"coordinates":[24.2047,51.9656],"type":"Point"}
}