{
  "type": "Feature",
  "properties": {
    "gn:admin1_code":"2.0",
    "gn:asciiname":"Slabada",
    "gn:country_code":"BY",
    "gn:dem":142,
    "gn:feature_class":"P",
    "gn:feature_code":"PPL",
    "gn:name":"Slabada",
    "gn:population":0,
    "gn:timezone":"Europe/Minsk",
    "iso:country":"BY",
    "name:bel_x_preferred":[
        "\u0421\u043b\u0430\u0431\u0430\u0434\u0430"
    ],
    "name:eng_x_preferred":[
        "Sloboda"
    ],
    "name:rus_x_preferred":[
        "\u0421\u043b\u043e\u0431\u043e\u0434\u0430"
    ],
    "name:und_x_variant":[
        "Slabada"
    ],
    "wof:name":"Slabada",
    "wof:placetype":"locality"
},
  "geometry": {"coordinates":[28.9855,52.0429],"type":"Point"}
}