{
  "type": "Feature",
  "properties": {
    "gn:admin1_code":"5.0",
    "gn:asciiname":"Suhvazdy",
    "gn:country_code":"BY",
    "gn:dem":261,
    "gn:feature_class":"P",
    "gn:feature_code":"PPL",
    "gn:name":"Suhvazdy",
    "gn:population":0,
    "gn:timezone":"Europe/Minsk",
    "iso:country":"BY",
    "name:bel_x_preferred":[
        "\u0421\u0443\u0433\u0432\u0430\u0437\u0434\u044b"
    ],
    "name:und_x_variant":[
        "Sugwozdy",
        "Sugvozdy",
        "Suhvazdy"
    ],
    "wof:name":"Suhvazdy",
    "wof:placetype":"locality"
},
  "geometry": {"coordinates":[26.6898,54.1177],"type":"Point"}
}