{
  "type": "Feature",
  "properties": {
    "gn:admin1_code":"5.0",
    "gn:asciiname":"Serpishchino",
    "gn:country_code":"BY",
    "gn:dem":288,
    "gn:feature_class":"P",
    "gn:feature_code":"PPL",
    "gn:name":"Serpishchino",
    "gn:population":0,
    "gn:timezone":"Europe/Minsk",
    "iso:country":"BY",
    "name:rus_x_preferred":[
        "\u0421\u0435\u0440\u043f\u0438\u0449\u0438\u043d\u043e"
    ],
    "name:und_x_variant":[
        "Serpishcheno"
    ],
    "wof:name":"Serpishchino",
    "wof:placetype":"locality"
},
  "geometry": {"coordinates":[27.5643,54.2601],"type":"Point"}
}