{
  "type": "Feature",
  "properties": {
    "gn:admin1_code":"5.0",
    "gn:asciiname":"Solomorech'ye",
    "gn:country_code":"BY",
    "gn:dem":232,
    "gn:feature_class":"P",
    "gn:feature_code":"PPL",
    "gn:name":"Solomorech\u2019ye",
    "gn:population":0,
    "gn:timezone":"Europe/Minsk",
    "iso:country":"BY",
    "name:rus_x_preferred":[
        "\u0421\u043e\u043b\u043e\u043c\u043e\u0440\u0435\u0447\u044c\u0435"
    ],
    "name:und_x_variant":[
        "Solomorech\u2019ye"
    ],
    "wof:name":"Solomorech'ye",
    "wof:placetype":"locality"
},
  "geometry": {"coordinates":[27.4667,54.0725],"type":"Point"}
}