{
  "type": "Feature",
  "properties": {
    "gn:admin1_code":"6.0",
    "gn:asciiname":"Lipovka",
    "gn:country_code":"BY",
    "gn:dem":148,
    "gn:feature_class":"P",
    "gn:feature_code":"PPL",
    "gn:name":"Lipovka",
    "gn:population":0,
    "gn:timezone":"Europe/Minsk",
    "iso:country":"BY",
    "name:rus_x_preferred":[
        "\u041b\u0438\u043f\u043e\u0432\u043a\u0430"
    ],
    "wof:name":"Lipovka",
    "wof:placetype":"locality"
},
  "geometry": {"coordinates":[32.0777,53.2947],"type":"Point"}
}