{
  "type": "Feature",
  "properties": {
    "gn:admin1_code":"6.0",
    "gn:asciiname":"Zadnyaya Gryada",
    "gn:country_code":"BY",
    "gn:dem":155,
    "gn:feature_class":"P",
    "gn:feature_code":"PPL",
    "gn:name":"Zadnyaya Gryada",
    "gn:population":0,
    "gn:timezone":"Europe/Minsk",
    "iso:country":"BY",
    "name:rus_x_preferred":[
        "\u0417\u0430\u0434\u043d\u044f\u044f \u0413\u0440\u044f\u0434\u0430"
    ],
    "wof:name":"Zadnyaya Gryada",
    "wof:placetype":"locality"
},
  "geometry": {"coordinates":[28.5262,53.2086],"type":"Point"}
}