{
  "type": "Feature",
  "properties": {
    "gn:admin1_code":"2.0",
    "gn:asciiname":"Hlushkavichy",
    "gn:country_code":"BY",
    "gn:dem":155,
    "gn:feature_class":"P",
    "gn:feature_code":"PPL",
    "gn:name":"Hlushkavichy",
    "gn:population":0,
    "gn:timezone":"Europe/Minsk",
    "iso:country":"BY",
    "name:bel_x_preferred":[
        "\u0413\u043b\u0443\u0448\u043a\u0430\u0432\u0456\u0447\u044b"
    ],
    "name:und_x_variant":[
        "Glushkovichi",
        "Glushkevichi",
        "Hlushkavichy"
    ],
    "wof:name":"Hlushkavichy",
    "wof:placetype":"locality"
},
  "geometry": {"coordinates":[27.7744,51.5697],"type":"Point"}
}