{
  "type": "Feature",
  "properties": {
    "gn:admin1_code":"7.0",
    "gn:asciiname":"Mezhdules'ye",
    "gn:country_code":"BY",
    "gn:dem":139,
    "gn:feature_class":"P",
    "gn:feature_code":"PPL",
    "gn:name":"Mezhdules\u2019ye",
    "gn:population":0,
    "gn:timezone":"Europe/Minsk",
    "iso:country":"BY",
    "name:rus_x_preferred":[
        "\u041c\u0435\u0436\u0434\u0443\u043b\u0435\u0441\u044c\u0435"
    ],
    "name:und_x_variant":[
        "Mezhdules\u2019ye"
    ],
    "wof:name":"Mezhdules'ye",
    "wof:placetype":"locality"
},
  "geometry": {"coordinates":[28.8097,55.3762],"type":"Point"}
}