{
  "type": "Feature",
  "properties": {
    "gn:admin1_code":"5.0",
    "gn:asciiname":"Obez",
    "gn:country_code":"BY",
    "gn:dem":194,
    "gn:feature_class":"P",
    "gn:feature_code":"PPL",
    "gn:name":"Ob\u00ebz",
    "gn:population":0,
    "gn:timezone":"Europe/Minsk",
    "iso:country":"BY",
    "name:rus_x_preferred":[
        "\u041e\u0431\u0451\u0437"
    ],
    "name:und_x_variant":[
        "Ob\u00ebz"
    ],
    "wof:name":"Obez",
    "wof:placetype":"locality"
},
  "geometry": {"coordinates":[28.6056,54.5253],"type":"Point"}
}