{
  "type": "Feature",
  "properties": {
    "gn:admin1_code":"3.0",
    "gn:asciiname":"Martinovo",
    "gn:country_code":"BY",
    "gn:dem":151,
    "gn:feature_class":"P",
    "gn:feature_code":"PPL",
    "gn:name":"Martinovo",
    "gn:population":0,
    "gn:timezone":"Europe/Minsk",
    "iso:country":"BY",
    "name:rus_x_preferred":[
        "\u041c\u0430\u0440\u0442\u0438\u043d\u043e\u0432\u043e"
    ],
    "wof:name":"Martinovo",
    "wof:placetype":"locality"
},
  "geometry": {"coordinates":[26.1051,54.9337],"type":"Point"}
}