{
  "type": "Feature",
  "properties": {
    "gn:admin1_code":"3.0",
    "gn:asciiname":"Martinovo",
    "gn:country_code":"BY",
    "gn:dem":151,
    "gn:feature_class":"P",
    "gn:feature_code":"PPL",
    "gn:name":"Martinovo",
    "gn:population":0,
    "gn:timezone":"Europe/Minsk",
    "iso:country":"BY",
    "name:ara_x_preferred":[
        "\u0645\u0627\u0631\u062a\u064a\u0646\u0648\u06a4\u0648"
    ],
    "name:bul_x_preferred":[
        "\u041c\u0430\u0440\u0442\u0438\u043d\u043e\u0432\u043e"
    ],
    "name:ceb_x_preferred":[
        "Martinovo"
    ],
    "name:kaz_x_preferred":[
        "\u041c\u0430\u0440\u0442\u0438\u043d\u043e\u0432\u043e"
    ],
    "name:msa_x_preferred":[
        "Martinovo"
    ],
    "name:ron_x_preferred":[
        "Martinovo"
    ],
    "name:rus_x_preferred":[
        "\u041c\u0430\u0440\u0442\u0438\u043d\u043e\u0432\u043e"
    ],
    "name:swe_x_preferred":[
        "Martinovo"
    ],
    "name:ukr_x_preferred":[
        "\u041c\u0430\u0440\u0442\u0438\u043d\u043e\u0432\u043e"
    ],
    "wof:name":"Martinovo",
    "wof:placetype":"locality"
},
  "geometry": {"coordinates":[26.1051,54.9337],"type":"Point"}
}