{
  "type": "Feature",
  "properties": {
    "gn:admin1_code":"3.0",
    "gn:asciiname":"Bayarsk",
    "gn:country_code":"BY",
    "gn:dem":171,
    "gn:feature_class":"P",
    "gn:feature_code":"PPL",
    "gn:name":"Bayarsk",
    "gn:population":0,
    "gn:timezone":"Europe/Minsk",
    "iso:country":"BY",
    "name:bel_x_preferred":[
        "\u0411\u0430\u044f\u0440\u0441\u043a"
    ],
    "name:und_x_variant":[
        "Boyarska",
        "Bojarska",
        "Boyarsk",
        "Bayarsk"
    ],
    "wof:name":"Bayarsk",
    "wof:placetype":"locality"
},
  "geometry": {"coordinates":[26.3193,54.2383],"type":"Point"}
}