{
  "type": "Feature",
  "properties": {
    "gn:admin1_code":"6.0",
    "gn:asciiname":"Podknyazhen'ye",
    "gn:country_code":"BY",
    "gn:dem":188,
    "gn:feature_class":"P",
    "gn:feature_code":"PPL",
    "gn:name":"Podknyazhen\u2019ye",
    "gn:population":0,
    "gn:timezone":"Europe/Minsk",
    "iso:country":"BY",
    "name:rus_x_preferred":[
        "\u041f\u043e\u0434\u043a\u043d\u044f\u0436\u0435\u043d\u044c\u0435"
    ],
    "name:und_x_variant":[
        "Podknyazhen\u2019ye"
    ],
    "wof:name":"Podknyazhen'ye",
    "wof:placetype":"locality"
},
  "geometry": {"coordinates":[30.2157,54.3167],"type":"Point"}
}