{
  "type": "Feature",
  "properties": {
    "gn:admin1_code":"6.0",
    "gn:asciiname":"Zelenaya Roshcha",
    "gn:country_code":"BY",
    "gn:dem":149,
    "gn:feature_class":"P",
    "gn:feature_code":"PPL",
    "gn:name":"Zel\u00ebnaya Roshcha",
    "gn:population":0,
    "gn:timezone":"Europe/Minsk",
    "iso:country":"BY",
    "name:rus_x_preferred":[
        "\u0417\u0435\u043b\u0451\u043d\u0430\u044f \u0420\u043e\u0449\u0430"
    ],
    "name:und_x_variant":[
        "Zel\u00ebnaya Roshcha"
    ],
    "wof:name":"Zelenaya Roshcha",
    "wof:placetype":"locality"
},
  "geometry": {"coordinates":[30.5875,53.3554],"type":"Point"}
}