{
  "type": "Feature",
  "properties": {
    "gn:admin1_code":"3.0",
    "gn:asciiname":"Noviki",
    "gn:country_code":"BY",
    "gn:dem":123,
    "gn:feature_class":"P",
    "gn:feature_code":"PPL",
    "gn:name":"Noviki",
    "gn:population":0,
    "gn:timezone":"Europe/Minsk",
    "iso:country":"BY",
    "name:bel_x_preferred":[
        "Naviki"
    ],
    "name:bel_x_variant":[
        "\u041d\u0430\u0432\u0456\u043a\u0456"
    ],
    "name:rus_x_preferred":[
        "\u041d\u043e\u0432\u0438\u043a\u0438"
    ],
    "wof:name":"Noviki",
    "wof:placetype":"locality"
},
  "geometry": {"coordinates":[25.2447,53.231],"type":"Point"}
}