{
  "type": "Feature",
  "properties": {
    "gn:admin1_code":"7.0",
    "gn:asciiname":"Maysyutino",
    "gn:country_code":"BY",
    "gn:dem":141,
    "gn:feature_class":"P",
    "gn:feature_code":"PPL",
    "gn:name":"Maysyutino",
    "gn:population":0,
    "gn:timezone":"Europe/Minsk",
    "iso:country":"BY",
    "name:rus_x_preferred":[
        "\u041c\u0430\u0439\u0441\u044e\u0442\u0438\u043d\u043e"
    ],
    "wof:name":"Maysyutino",
    "wof:placetype":"locality"
},
  "geometry": {"coordinates":[27.5114,55.2304],"type":"Point"}
}