{
  "type": "Feature",
  "properties": {
    "gn:admin1_code":"5.0",
    "gn:asciiname":"Zamost'ye",
    "gn:country_code":"BY",
    "gn:dem":176,
    "gn:feature_class":"P",
    "gn:feature_code":"PPL",
    "gn:name":"Zamost\u2019ye",
    "gn:population":0,
    "gn:timezone":"Europe/Minsk",
    "iso:country":"BY",
    "name:rus_x_preferred":[
        "\u0417\u0430\u043c\u043e\u0441\u0442\u044c\u0435"
    ],
    "name:und_x_variant":[
        "Zamost\u2019ye"
    ],
    "wof:name":"Zamost'ye",
    "wof:placetype":"locality"
},
  "geometry": {"coordinates":[27.6876,53.5703],"type":"Point"}
}