{
  "type": "Feature",
  "properties": {
    "gn:admin1_code":"1.0",
    "gn:asciiname":"Dubovo",
    "gn:country_code":"BY",
    "gn:dem":185,
    "gn:feature_class":"P",
    "gn:feature_code":"PPL",
    "gn:name":"Dubovo",
    "gn:population":0,
    "gn:timezone":"Europe/Minsk",
    "iso:country":"BY",
    "name:rus_x_preferred":[
        "\u0414\u0443\u0431\u043e\u0432\u043e"
    ],
    "wof:name":"Dubovo",
    "wof:placetype":"locality"
},
  "geometry": {"coordinates":[26.1101,53.1582],"type":"Point"}
}