{
  "type": "Feature",
  "properties": {
    "gn:admin1_code":"6.0",
    "gn:asciiname":"Bozok",
    "gn:country_code":"BY",
    "gn:dem":156,
    "gn:feature_class":"P",
    "gn:feature_code":"PPL",
    "gn:name":"Bozok",
    "gn:population":0,
    "gn:timezone":"Europe/Minsk",
    "iso:country":"BY",
    "name:deu_x_preferred":[
        "Bozok"
    ],
    "name:rus_x_preferred":[
        "\u0411\u043e\u0437\u043e\u043a"
    ],
    "name:tur_x_preferred":[
        "Bozok"
    ],
    "wof:name":"Bozok",
    "wof:placetype":"locality"
},
  "geometry": {"coordinates":[28.7904,53.4795],"type":"Point"}
}