{
  "type": "Feature",
  "properties": {
    "gn:admin1_code":"1.0",
    "gn:asciiname":"Vidamlya",
    "gn:country_code":"BY",
    "gn:dem":152,
    "gn:feature_class":"P",
    "gn:feature_code":"PPL",
    "gn:name":"Vidamlya",
    "gn:population":0,
    "gn:timezone":"Europe/Minsk",
    "iso:country":"BY",
    "name:bel_x_preferred":[
        "\u0412\u0456\u0434\u0430\u043c\u043b\u044f"
    ],
    "name:eng_x_preferred":[
        "Vidomlya"
    ],
    "name:rus_x_preferred":[
        "\u0412\u0438\u0434\u043e\u043c\u043b\u044f"
    ],
    "name:und_x_variant":[
        "Widomla",
        "Vidomlya",
        "Vidamlya"
    ],
    "wof:name":"Vidamlya",
    "wof:placetype":"locality"
},
  "geometry": {"coordinates":[23.78657,52.32749],"type":"Point"}
}