{
  "type": "Feature",
  "properties": {
    "gn:admin1_code":"6.0",
    "gn:asciiname":"Cherchenovka",
    "gn:country_code":"BY",
    "gn:dem":163,
    "gn:feature_class":"P",
    "gn:feature_code":"PPL",
    "gn:name":"Cherchenovka",
    "gn:population":0,
    "gn:timezone":"Europe/Minsk",
    "iso:country":"BY",
    "name:rus_x_preferred":[
        "\u0427\u0435\u0440\u0447\u0435\u043d\u043e\u0432\u043a\u0430"
    ],
    "wof:name":"Cherchenovka",
    "wof:placetype":"locality"
},
  "geometry": {"coordinates":[32.1656,53.4359],"type":"Point"}
}