{
  "type": "Feature",
  "properties": {
    "gn:admin1_code":"3.0",
    "gn:asciiname":"Stul'gi",
    "gn:country_code":"BY",
    "gn:dem":260,
    "gn:feature_class":"P",
    "gn:feature_code":"PPL",
    "gn:name":"Stul\u2019gi",
    "gn:population":0,
    "gn:timezone":"Europe/Minsk",
    "iso:country":"BY",
    "name:rus_x_preferred":[
        "\u0421\u0442\u0443\u043b\u044c\u0433\u0438"
    ],
    "name:und_x_variant":[
        "Stul\u2019ge",
        "Stul\u2019gi"
    ],
    "wof:name":"Stul'gi",
    "wof:placetype":"locality"
},
  "geometry": {"coordinates":[25.7407,54.3477],"type":"Point"}
}