{
  "type": "Feature",
  "properties": {
    "gn:admin1_code":"1.0",
    "gn:asciiname":"Radchytsk",
    "gn:country_code":"BY",
    "gn:dem":137,
    "gn:feature_class":"P",
    "gn:feature_code":"PPL",
    "gn:name":"Radchytsk",
    "gn:population":0,
    "gn:timezone":"Europe/Minsk",
    "iso:country":"BY",
    "name:bel_x_preferred":[
        "\u0420\u0430\u0434\u0447\u044b\u0446\u043a"
    ],
    "name:und_x_variant":[
        "Radchysk",
        "Radchissk",
        "Radchisk",
        "Radchitsk",
        "Radchytsk"
    ],
    "wof:name":"Radchytsk",
    "wof:placetype":"locality"
},
  "geometry": {"coordinates":[26.5635,51.95607],"type":"Point"}
}