{
  "type": "Feature",
  "properties": {
    "gn:admin1_code":"1.0",
    "gn:asciiname":"Padlyasyeyki",
    "gn:country_code":"BY",
    "gn:dem":190,
    "gn:feature_class":"P",
    "gn:feature_code":"PPL",
    "gn:name":"Padlyasyeyki",
    "gn:population":0,
    "gn:timezone":"Europe/Minsk",
    "iso:country":"BY",
    "name:bel_x_preferred":[
        "\u041f\u0430\u0434\u043b\u044f\u0441\u0435\u0439\u043a\u0456"
    ],
    "name:und_x_variant":[
        "Podliseyki",
        "Podleseyki",
        "Padlyasyeyki"
    ],
    "wof:name":"Padlyasyeyki",
    "wof:placetype":"locality"
},
  "geometry": {"coordinates":[26.2582,53.179],"type":"Point"}
}