{
  "type": "Feature",
  "properties": {
    "gn:admin1_code":"5.0",
    "gn:asciiname":"Staraya Guta",
    "gn:country_code":"BY",
    "gn:dem":171,
    "gn:feature_class":"P",
    "gn:feature_code":"PPL",
    "gn:name":"Staraya Guta",
    "gn:population":0,
    "gn:timezone":"Europe/Minsk",
    "iso:country":"BY",
    "name:rus_x_preferred":[
        "\u0421\u0442\u0430\u0440\u0430\u044f \u0413\u0443\u0442\u0430"
    ],
    "wof:name":"Staraya Guta",
    "wof:placetype":"locality"
},
  "geometry": {"coordinates":[27.0482,53.2746],"type":"Point"}
}