{
  "type": "Feature",
  "properties": {
    "gn:admin1_code":"7.0",
    "gn:asciiname":"Khalaleyevka",
    "gn:country_code":"BY",
    "gn:dem":210,
    "gn:feature_class":"P",
    "gn:feature_code":"PPL",
    "gn:name":"Khalaleyevka",
    "gn:population":0,
    "gn:timezone":"Europe/Minsk",
    "iso:country":"BY",
    "name:rus_x_preferred":[
        "\u0425\u0430\u043b\u0430\u043b\u0435\u0435\u0432\u043a\u0430"
    ],
    "name:und_x_variant":[
        "Khololeyevka",
        "Khalileyevka",
        "Khalaleyevka"
    ],
    "wof:name":"Khalaleyevka",
    "wof:placetype":"locality"
},
  "geometry": {"coordinates":[30.8004,54.4295],"type":"Point"}
}