{
  "type": "Feature",
  "properties": {
    "gn:admin1_code":"5.0",
    "gn:asciiname":"Terlyuki",
    "gn:country_code":"BY",
    "gn:dem":194,
    "gn:feature_class":"P",
    "gn:feature_code":"PPL",
    "gn:name":"Terlyuki",
    "gn:population":0,
    "gn:timezone":"Europe/Minsk",
    "iso:country":"BY",
    "name:rus_x_preferred":[
        "\u0422\u0435\u0440\u043b\u044e\u043a\u0438"
    ],
    "wof:name":"Terlyuki",
    "wof:placetype":"locality"
},
  "geometry": {"coordinates":[26.6676,54.9676],"type":"Point"}
}