{
  "type": "Feature",
  "properties": {
    "gn:admin1_code":"6.0",
    "gn:asciiname":"Yavulin",
    "gn:country_code":"BY",
    "gn:dem":173,
    "gn:feature_class":"P",
    "gn:feature_code":"PPL",
    "gn:name":"Yavulin",
    "gn:population":0,
    "gn:timezone":"Europe/Minsk",
    "iso:country":"BY",
    "name:rus_x_preferred":[
        "\u042f\u0432\u0443\u043b\u0438\u043d"
    ],
    "wof:name":"Yavulin",
    "wof:placetype":"locality"
},
  "geometry": {"coordinates":[32.1809,53.4528],"type":"Point"}
}