{
  "type": "Feature",
  "properties": {
    "gn:admin1_code":"3.0",
    "gn:asciiname":"Porech'ye",
    "gn:country_code":"BY",
    "gn:dem":130,
    "gn:feature_class":"P",
    "gn:feature_code":"PPL",
    "gn:name":"Porech\u2019ye",
    "gn:population":0,
    "gn:timezone":"Europe/Minsk",
    "iso:country":"BY",
    "name:rus_x_preferred":[
        "\u041f\u043e\u0440\u0435\u0447\u044c\u0435"
    ],
    "name:und_x_variant":[
        "Porech\u2019ye"
    ],
    "wof:name":"Porech'ye",
    "wof:placetype":"locality"
},
  "geometry": {"coordinates":[23.8304,53.2577],"type":"Point"}
}