{
  "type": "Feature",
  "properties": {
    "gn:admin1_code":"3.0",
    "gn:asciiname":"Korolino",
    "gn:country_code":"BY",
    "gn:dem":116,
    "gn:feature_class":"P",
    "gn:feature_code":"PPL",
    "gn:name":"Korolino",
    "gn:population":0,
    "gn:timezone":"Europe/Minsk",
    "iso:country":"BY",
    "name:rus_x_preferred":[
        "\u041a\u043e\u0440\u043e\u043b\u0438\u043d\u043e"
    ],
    "name:rus_x_variant":[
        "\u041a\u0430\u0440\u043e\u043b\u0438\u043d"
    ],
    "name:und_x_variant":[
        "Karolin"
    ],
    "wof:name":"Korolino",
    "wof:placetype":"locality"
},
  "geometry": {"coordinates":[24.4296,53.5261],"type":"Point"}
}