{
  "type": "Feature",
  "properties": {
    "gn:admin1_code":"5.0",
    "gn:asciiname":"Ganusovshchina",
    "gn:country_code":"BY",
    "gn:dem":183,
    "gn:feature_class":"P",
    "gn:feature_code":"PPL",
    "gn:name":"Ganusovshchina",
    "gn:population":0,
    "gn:timezone":"Europe/Minsk",
    "iso:country":"BY",
    "name:rus_x_preferred":[
        "\u0413\u0430\u043d\u0443\u0441\u043e\u0432\u0449\u0438\u043d\u0430"
    ],
    "wof:name":"Ganusovshchina",
    "wof:placetype":"locality"
},
  "geometry": {"coordinates":[26.7072,53.2683],"type":"Point"}
}