{
  "type": "Feature",
  "properties": {
    "gn:admin1_code":"3.0",
    "gn:asciiname":"Sunchitsy",
    "gn:country_code":"BY",
    "gn:dem":244,
    "gn:feature_class":"P",
    "gn:feature_code":"PPL",
    "gn:name":"Sunchitsy",
    "gn:population":0,
    "gn:timezone":"Europe/Minsk",
    "iso:country":"BY",
    "name:bel_x_preferred":[
        "Sunchytsy"
    ],
    "name:bel_x_variant":[
        "\u0421\u0443\u043d\u0447\u044b\u0446\u044b"
    ],
    "name:rus_x_preferred":[
        "\u0421\u0443\u043d\u0447\u0438\u0446\u044b"
    ],
    "wof:name":"Sunchitsy",
    "wof:placetype":"locality"
},
  "geometry": {"coordinates":[25.8355,53.633],"type":"Point"}
}