{
  "type": "Feature",
  "properties": {
    "gn:admin1_code":"6.0",
    "gn:asciiname":"Berezuyki",
    "gn:country_code":"BY",
    "gn:dem":166,
    "gn:feature_class":"P",
    "gn:feature_code":"PPL",
    "gn:name":"Berezuyki",
    "gn:population":0,
    "gn:timezone":"Europe/Minsk",
    "iso:country":"BY",
    "name:rus_x_preferred":[
        "\u0411\u0435\u0440\u0435\u0437\u0443\u0439\u043a\u0438"
    ],
    "wof:name":"Berezuyki",
    "wof:placetype":"locality"
},
  "geometry": {"coordinates":[31.7363,53.8862],"type":"Point"}
}