{
  "type": "Feature",
  "properties": {
    "gn:admin1_code":"1.0",
    "gn:asciiname":"Polonka",
    "gn:country_code":"BY",
    "gn:dem":189,
    "gn:feature_class":"P",
    "gn:feature_code":"PPL",
    "gn:name":"Polonka",
    "gn:population":0,
    "gn:timezone":"Europe/Minsk",
    "iso:country":"BY",
    "name:bel_x_preferred":[
        "\u041f\u0430\u043b\u043e\u043d\u043a\u0430"
    ],
    "name:eng_x_preferred":[
        "Polonka"
    ],
    "name:rus_x_preferred":[
        "\u041f\u043e\u043b\u043e\u043d\u043a\u0430"
    ],
    "name:und_x_variant":[
        "Palonka"
    ],
    "wof:name":"Polonka",
    "wof:placetype":"locality"
},
  "geometry": {"coordinates":[25.719,53.1441],"type":"Point"}
}