{
  "type": "Feature",
  "properties": {
    "gn:admin1_code":"3.0",
    "gn:asciiname":"Trumpy",
    "gn:country_code":"BY",
    "gn:dem":150,
    "gn:feature_class":"P",
    "gn:feature_code":"PPL",
    "gn:name":"Trumpy",
    "gn:population":0,
    "gn:timezone":"Europe/Minsk",
    "iso:country":"BY",
    "name:rus_x_preferred":[
        "\u0422\u0440\u0443\u043c\u043f\u044b"
    ],
    "wof:name":"Trumpy",
    "wof:placetype":"locality"
},
  "geometry": {"coordinates":[24.1474,53.265],"type":"Point"}
}