{
  "type": "Feature",
  "properties": {
    "gn:admin1_code":"7.0",
    "gn:asciiname":"Berespol'ye",
    "gn:country_code":"BY",
    "gn:dem":168,
    "gn:feature_class":"P",
    "gn:feature_code":"PPL",
    "gn:name":"Berespol\u2019ye",
    "gn:population":0,
    "gn:timezone":"Europe/Minsk",
    "iso:country":"BY",
    "name:rus_x_preferred":[
        "\u0411\u0435\u0440\u0435\u0441\u043f\u043e\u043b\u044c\u0435"
    ],
    "name:und_x_variant":[
        "Berespol\u2019ye"
    ],
    "wof:name":"Berespol'ye",
    "wof:placetype":"locality"
},
  "geometry": {"coordinates":[28.0941,54.9211],"type":"Point"}
}