{
  "type": "Feature",
  "properties": {
    "gn:admin1_code":"6.0",
    "gn:asciiname":"Amkhovaya Pyershaya",
    "gn:country_code":"BY",
    "gn:dem":184,
    "gn:feature_class":"P",
    "gn:feature_code":"PPL",
    "gn:name":"Amkhovaya Pyershaya",
    "gn:population":0,
    "gn:timezone":"Europe/Minsk",
    "iso:country":"BY",
    "name:bel_x_preferred":[
        "\u0410\u043c\u0445\u043e\u0432\u0430\u044f \u041f\u0435\u0440\u0448\u0430\u044f"
    ],
    "name:und_x_variant":[
        "Amkhovaya",
        "Amkhovaya Pervaya"
    ],
    "wof:name":"Amkhovaya Pyershaya",
    "wof:placetype":"locality"
},
  "geometry": {"coordinates":[30.5273,53.7932],"type":"Point"}
}