{
  "type": "Feature",
  "properties": {
    "gn:admin1_code":"3.0",
    "gn:asciiname":"Pashki",
    "gn:country_code":"BY",
    "gn:dem":138,
    "gn:feature_class":"P",
    "gn:feature_code":"PPL",
    "gn:name":"Pashki",
    "gn:population":0,
    "gn:timezone":"Europe/Minsk",
    "iso:country":"BY",
    "name:rus_x_preferred":[
        "\u041f\u0430\u0448\u043a\u0438"
    ],
    "wof:name":"Pashki",
    "wof:placetype":"locality"
},
  "geometry": {"coordinates":[24.9063,53.9264],"type":"Point"}
}