{
  "type": "Feature",
  "properties": {
    "gn:asciiname":"Byelagruda",
    "gn:country_code":"BY",
    "gn:dem":157,
    "gn:feature_class":"P",
    "gn:feature_code":"PPL",
    "gn:name":"Byelagruda",
    "gn:population":700,
    "gn:timezone":"Europe/Minsk",
    "iso:country":"BY",
    "name:bel_x_preferred":[
        "\u0411\u0435\u043b\u0430\u0433\u0440\u0443\u0434\u0430"
    ],
    "name:eng_x_preferred":[
        "Byelagruda"
    ],
    "name:rus_x_preferred":[
        "\u0411\u0435\u043b\u043e\u0433\u0440\u0443\u0434\u0430"
    ],
    "wof:name":"Byelagruda",
    "wof:placetype":"locality",
    "wof:population":700
},
  "geometry": {"coordinates":[25.16582,53.79781],"type":"Point"}
}