{
  "type": "Feature",
  "properties": {
    "gn:admin1_code":"5.0",
    "gn:asciiname":"Sinilo",
    "gn:country_code":"BY",
    "gn:dem":185,
    "gn:feature_class":"P",
    "gn:feature_code":"PPL",
    "gn:name":"Sinilo",
    "gn:population":0,
    "gn:timezone":"Europe/Minsk",
    "iso:country":"BY",
    "name:rus_x_preferred":[
        "\u0421\u0438\u043d\u0438\u043b\u043e"
    ],
    "name:und_x_variant":[
        "Sinelo"
    ],
    "wof:name":"Sinilo",
    "wof:placetype":"locality"
},
  "geometry": {"coordinates":[27.7256,53.7796],"type":"Point"}
}