{
  "type": "Feature",
  "properties": {
    "gn:admin1_code":"5.0",
    "gn:asciiname":"Zagorany",
    "gn:country_code":"BY",
    "gn:dem":219,
    "gn:feature_class":"P",
    "gn:feature_code":"PPL",
    "gn:name":"Zagorany",
    "gn:population":0,
    "gn:timezone":"Europe/Minsk",
    "iso:country":"BY",
    "name:rus_x_preferred":[
        "\u0417\u0430\u0433\u043e\u0440\u0430\u043d\u044b"
    ],
    "name:und_x_variant":[
        "Zagoryane"
    ],
    "wof:name":"Zagorany",
    "wof:placetype":"locality"
},
  "geometry": {"coordinates":[27.3889,54.31100000000001],"type":"Point"}
}