{
  "type": "Feature",
  "properties": {
    "gn:admin1_code":"3.0",
    "gn:asciiname":"Shcherbovichi",
    "gn:country_code":"BY",
    "gn:dem":112,
    "gn:feature_class":"P",
    "gn:feature_code":"PPL",
    "gn:name":"Shcherbovichi",
    "gn:population":0,
    "gn:timezone":"Europe/Minsk",
    "iso:country":"BY",
    "name:bel_x_preferred":[
        "Shcherbavichy"
    ],
    "name:bel_x_variant":[
        "\u0428\u0447\u044d\u0440\u0431\u0430\u0432\u0456\u0447\u044b"
    ],
    "name:rus_x_preferred":[
        "\u0429\u0435\u0440\u0431\u043e\u0432\u0438\u0447\u0438"
    ],
    "name:und_x_variant":[
        "Shcherboviche"
    ],
    "wof:name":"Shcherbovichi",
    "wof:placetype":"locality"
},
  "geometry": {"coordinates":[24.0919,53.5136],"type":"Point"}
}