{
  "type": "Feature",
  "properties": {
    "gn:admin1_code":"5.0",
    "gn:asciiname":"Khramtsovo",
    "gn:country_code":"BY",
    "gn:dem":189,
    "gn:feature_class":"P",
    "gn:feature_code":"PPL",
    "gn:name":"Khramtsovo",
    "gn:population":0,
    "gn:timezone":"Europe/Minsk",
    "iso:country":"BY",
    "name:rus_x_preferred":[
        "\u0425\u0440\u0430\u043c\u0446\u043e\u0432\u043e"
    ],
    "wof:name":"Khramtsovo",
    "wof:placetype":"locality"
},
  "geometry": {"coordinates":[27.2967,54.2921],"type":"Point"}
}