{
  "type": "Feature",
  "properties": {
    "gn:admin1_code":"3.0",
    "gn:asciiname":"Skerdimy",
    "gn:country_code":"BY",
    "gn:dem":141,
    "gn:feature_class":"P",
    "gn:feature_code":"PPL",
    "gn:name":"Skerdimy",
    "gn:population":0,
    "gn:timezone":"Europe/Minsk",
    "iso:country":"BY",
    "name:rus_x_preferred":[
        "\u0421\u043a\u0435\u0440\u0434\u0438\u043c\u044b"
    ],
    "wof:name":"Skerdimy",
    "wof:placetype":"locality"
},
  "geometry": {"coordinates":[26.1583,54.7735],"type":"Point"}
}