{
  "type": "Feature",
  "properties": {
    "gn:admin1_code":"2.0",
    "gn:asciiname":"Novyya Halowchytsy",
    "gn:country_code":"BY",
    "gn:dem":136,
    "gn:feature_class":"P",
    "gn:feature_code":"PPL",
    "gn:name":"Novyya Halowchytsy",
    "gn:population":0,
    "gn:timezone":"Europe/Minsk",
    "iso:country":"BY",
    "name:bel_x_preferred":[
        "\u041d\u043e\u0432\u044b\u044f \u0413\u0430\u043b\u043e\u045e\u0447\u044b\u0446\u044b"
    ],
    "name:und_x_variant":[
        "Novo-Golovchitsy",
        "Novyye Golovchitsy",
        "Novyya Halowchytsy"
    ],
    "wof:name":"Novyya Halowchytsy",
    "wof:placetype":"locality"
},
  "geometry": {"coordinates":[28.6114,52.4827],"type":"Point"}
}