{
  "type": "Feature",
  "properties": {
    "gn:admin1_code":"5.0",
    "gn:asciiname":"Zhiznova",
    "gn:country_code":"BY",
    "gn:dem":172,
    "gn:feature_class":"P",
    "gn:feature_code":"PPL",
    "gn:name":"Zhiznova",
    "gn:population":0,
    "gn:timezone":"Europe/Minsk",
    "iso:country":"BY",
    "name:rus_x_preferred":[
        "\u0416\u0438\u0437\u043d\u043e\u0432\u0430"
    ],
    "wof:name":"Zhiznova",
    "wof:placetype":"locality"
},
  "geometry": {"coordinates":[27.5036,54.6191],"type":"Point"}
}