{
  "type": "Feature",
  "properties": {
    "gn:admin1_code":"5.0",
    "gn:asciiname":"Zhuravinka",
    "gn:country_code":"BY",
    "gn:dem":194,
    "gn:feature_class":"P",
    "gn:feature_code":"PPL",
    "gn:name":"Zhuravinka",
    "gn:population":0,
    "gn:timezone":"Europe/Minsk",
    "iso:country":"BY",
    "name:rus_x_preferred":[
        "\u0416\u0443\u0440\u0430\u0432\u0438\u043d\u043a\u0430"
    ],
    "wof:name":"Zhuravinka",
    "wof:placetype":"locality"
},
  "geometry": {"coordinates":[26.9301,53.6663],"type":"Point"}
}