{
  "type": "Feature",
  "properties": {
    "gn:admin1_code":"6.0",
    "gn:asciiname":"Poselok Derevtsy",
    "gn:country_code":"BY",
    "gn:dem":155,
    "gn:feature_class":"P",
    "gn:feature_code":"PPL",
    "gn:name":"Pos\u00eblok Derevtsy",
    "gn:population":0,
    "gn:timezone":"Europe/Minsk",
    "iso:country":"BY",
    "name:rus_x_preferred":[
        "\u041f\u043e\u0441\u0451\u043b\u043e\u043a \u0414\u0435\u0440\u0435\u0432\u0446\u044b"
    ],
    "name:und_x_variant":[
        "Pos\u00eblok Derevtsy"
    ],
    "wof:name":"Poselok Derevtsy",
    "wof:placetype":"locality"
},
  "geometry": {"coordinates":[28.5862,53.2584],"type":"Point"}
}