{
  "type": "Feature",
  "properties": {
    "gn:admin1_code":"5.0",
    "gn:asciiname":"Vesnino",
    "gn:country_code":"BY",
    "gn:dem":251,
    "gn:feature_class":"P",
    "gn:feature_code":"PPL",
    "gn:name":"Vesnino",
    "gn:population":0,
    "gn:timezone":"Europe/Minsk",
    "iso:country":"BY",
    "name:eng_x_preferred":[
        "Vesnino"
    ],
    "name:rus_x_preferred":[
        "\u0412\u0435\u0441\u043d\u0438\u043d\u043e"
    ],
    "name:und_x_variant":[
        "Wie\u015bnina",
        "Vesnino"
    ],
    "wof:name":"Vesnino",
    "wof:placetype":"locality"
},
  "geometry": {"coordinates":[27.687,54.1424],"type":"Point"}
}