{
  "type": "Feature",
  "properties": {
    "gn:admin1_code":"5.0",
    "gn:asciiname":"Verkhlevka",
    "gn:country_code":"BY",
    "gn:dem":173,
    "gn:feature_class":"P",
    "gn:feature_code":"PPL",
    "gn:name":"Verkhl\u00ebvka",
    "gn:population":0,
    "gn:timezone":"Europe/Minsk",
    "iso:country":"BY",
    "name:rus_x_preferred":[
        "\u0412\u0435\u0440\u0445\u043b\u0451\u0432\u043a\u0430"
    ],
    "name:und_x_variant":[
        "Verkhl\u00ebvka"
    ],
    "wof:name":"Verkhlevka",
    "wof:placetype":"locality"
},
  "geometry": {"coordinates":[29.3277,53.9097],"type":"Point"}
}