{
  "type": "Feature",
  "properties": {
    "gn:admin1_code":"7.0",
    "gn:asciiname":"Artyushki",
    "gn:country_code":"BY",
    "gn:dem":150,
    "gn:feature_class":"P",
    "gn:feature_code":"PPL",
    "gn:name":"Artyushki",
    "gn:population":0,
    "gn:timezone":"Europe/Minsk",
    "iso:country":"BY",
    "name:rus_x_preferred":[
        "\u0410\u0440\u0442\u044e\u0448\u043a\u0438"
    ],
    "wof:name":"Artyushki",
    "wof:placetype":"locality"
},
  "geometry": {"coordinates":[28.7085,55.1564],"type":"Point"}
}