{
  "type": "Feature",
  "properties": {
    "gn:admin1_code":"5.0",
    "gn:asciiname":"Pletivishche",
    "gn:country_code":"BY",
    "gn:dem":174,
    "gn:feature_class":"P",
    "gn:feature_code":"PPL",
    "gn:name":"Pletivishche",
    "gn:population":0,
    "gn:timezone":"Europe/Minsk",
    "iso:country":"BY",
    "name:rus_x_preferred":[
        "\u041f\u043b\u0435\u0442\u0438\u0432\u0438\u0449\u0435"
    ],
    "name:und_x_variant":[
        "Pletevishche"
    ],
    "wof:name":"Pletivishche",
    "wof:placetype":"locality"
},
  "geometry": {"coordinates":[28.5236,53.6933],"type":"Point"}
}