{
  "type": "Feature",
  "properties": {
    "gn:admin1_code":"6.0",
    "gn:asciiname":"Banevka",
    "gn:country_code":"BY",
    "gn:dem":162,
    "gn:feature_class":"P",
    "gn:feature_code":"PPL",
    "gn:name":"Ban\u00ebvka",
    "gn:population":0,
    "gn:timezone":"Europe/Minsk",
    "iso:country":"BY",
    "name:rus_x_preferred":[
        "\u0411\u0430\u043d\u0451\u0432\u043a\u0430"
    ],
    "name:und_x_variant":[
        "Ban\u00ebvka"
    ],
    "wof:name":"Banevka",
    "wof:placetype":"locality"
},
  "geometry": {"coordinates":[28.9393,53.1384],"type":"Point"}
}