{
  "type": "Feature",
  "properties": {
    "gn:admin1_code":"1.0",
    "gn:asciiname":"Yuvsichi",
    "gn:country_code":"BY",
    "gn:dem":158,
    "gn:feature_class":"P",
    "gn:feature_code":"PPL",
    "gn:name":"Yuvsichi",
    "gn:population":0,
    "gn:timezone":"Europe/Minsk",
    "iso:country":"BY",
    "name:rus_x_preferred":[
        "\u042e\u0432\u0441\u0438\u0447\u0438"
    ],
    "wof:name":"Yuvsichi",
    "wof:placetype":"locality"
},
  "geometry": {"coordinates":[23.5783,52.4922],"type":"Point"}
}