{
  "type": "Feature",
  "properties": {
    "gn:admin1_code":"7.0",
    "gn:asciiname":"Rechki",
    "gn:country_code":"BY",
    "gn:dem":150,
    "gn:feature_class":"P",
    "gn:feature_code":"PPL",
    "gn:name":"Rechki",
    "gn:population":0,
    "gn:timezone":"Europe/Minsk",
    "iso:country":"BY",
    "name:rus_x_preferred":[
        "\u0420\u0435\u0447\u043a\u0438"
    ],
    "wof:name":"Rechki",
    "wof:placetype":"locality"
},
  "geometry": {"coordinates":[30.2972,54.8684],"type":"Point"}
}