{
  "type": "Feature",
  "properties": {
    "gn:admin1_code":"7.0",
    "gn:asciiname":"Ul'yanavichy",
    "gn:country_code":"BY",
    "gn:dem":175,
    "gn:feature_class":"P",
    "gn:feature_code":"PPL",
    "gn:name":"Ul\u2019yanavichy",
    "gn:population":0,
    "gn:timezone":"Europe/Minsk",
    "iso:country":"BY",
    "name:bel_x_preferred":[
        "\u0423\u043b\u044c\u044f\u043d\u0430\u0432\u0456\u0447\u044b"
    ],
    "name:rus_x_preferred":[
        "Ul\u2019yanovichi"
    ],
    "name:und_x_variant":[
        "Ul\u2019yanavichy"
    ],
    "wof:name":"Ul'yanavichy",
    "wof:placetype":"locality"
},
  "geometry": {"coordinates":[29.5317,54.7909],"type":"Point"}
}