{
  "type": "Feature",
  "properties": {
    "gn:admin1_code":"7.0",
    "gn:asciiname":"Malyy Polsvizh",
    "gn:country_code":"BY",
    "gn:dem":163,
    "gn:feature_class":"P",
    "gn:feature_code":"PPL",
    "gn:name":"Malyy Polsvizh",
    "gn:population":0,
    "gn:timezone":"Europe/Minsk",
    "iso:country":"BY",
    "name:rus_x_preferred":[
        "\u041c\u0430\u043b\u044b\u0439 \u041f\u043e\u043b\u0441\u0432\u0438\u0436"
    ],
    "wof:name":"Malyy Polsvizh",
    "wof:placetype":"locality"
},
  "geometry": {"coordinates":[28.7193,54.8529],"type":"Point"}
}