{
  "type": "Feature",
  "properties": {
    "gn:admin1_code":"3.0",
    "gn:asciiname":"Kotovichi",
    "gn:country_code":"BY",
    "gn:dem":151,
    "gn:feature_class":"P",
    "gn:feature_code":"PPL",
    "gn:name":"Kotovichi",
    "gn:population":0,
    "gn:timezone":"Europe/Minsk",
    "iso:country":"BY",
    "name:rus_x_preferred":[
        "\u041a\u043e\u0442\u043e\u0432\u0438\u0447\u0438"
    ],
    "wof:name":"Kotovichi",
    "wof:placetype":"locality"
},
  "geometry": {"coordinates":[24.8592,53.8558],"type":"Point"}
}