{
  "type": "Feature",
  "properties": {
    "gn:admin1_code":"3.0",
    "gn:asciiname":"Voronki",
    "gn:country_code":"BY",
    "gn:dem":142,
    "gn:feature_class":"P",
    "gn:feature_code":"PPL",
    "gn:name":"Voronki",
    "gn:population":0,
    "gn:timezone":"Europe/Minsk",
    "iso:country":"BY",
    "name:rus_x_preferred":[
        "\u0412\u043e\u0440\u043e\u043d\u043a\u0438"
    ],
    "wof:name":"Voronki",
    "wof:placetype":"locality"
},
  "geometry": {"coordinates":[24.5202,53.6472],"type":"Point"}
}