{
  "type": "Feature",
  "properties": {
    "gn:admin1_code":"7.0",
    "gn:asciiname":"Svistelki",
    "gn:country_code":"BY",
    "gn:dem":188,
    "gn:feature_class":"P",
    "gn:feature_code":"PPL",
    "gn:name":"Svistelki",
    "gn:population":0,
    "gn:timezone":"Europe/Minsk",
    "iso:country":"BY",
    "name:rus_x_preferred":[
        "\u0421\u0432\u0438\u0441\u0442\u0435\u043b\u043a\u0438"
    ],
    "wof:name":"Svistelki",
    "wof:placetype":"locality"
},
  "geometry": {"coordinates":[30.463,54.4866],"type":"Point"}
}