{
  "type": "Feature",
  "properties": {
    "gn:admin1_code":"5.0",
    "gn:asciiname":"Krawczonki",
    "gn:country_code":"BY",
    "gn:dem":186,
    "gn:feature_class":"P",
    "gn:feature_code":"PPL",
    "gn:name":"Krawczonki",
    "gn:population":0,
    "gn:timezone":"Europe/Minsk",
    "iso:country":"BY",
    "name:rus_x_preferred":[
        "\u041a\u0440\u0430\u0432\u0447\u0451\u043d\u043a\u0438"
    ],
    "name:und_x_variant":[
        "Kravchonki",
        "Kravch\u00ebnki"
    ],
    "wof:name":"Krawczonki",
    "wof:placetype":"locality"
},
  "geometry": {"coordinates":[27.3052,54.3196],"type":"Point"}
}