{
  "type": "Feature",
  "properties": {
    "gn:admin1_code":"1.0",
    "gn:asciiname":"Sudilovichi",
    "gn:country_code":"BY",
    "gn:dem":147,
    "gn:feature_class":"P",
    "gn:feature_code":"PPL",
    "gn:name":"Sudilovichi",
    "gn:population":0,
    "gn:timezone":"Europe/Minsk",
    "iso:country":"BY",
    "name:eng_x_preferred":[
        "Sudilovichi"
    ],
    "name:rus_x_preferred":[
        "\u0421\u0443\u0434\u0438\u043b\u043e\u0432\u0438\u0447\u0438"
    ],
    "name:und_x_variant":[
        "Sudziloviche"
    ],
    "wof:name":"Sudilovichi",
    "wof:placetype":"locality"
},
  "geometry": {"coordinates":[25.0462,52.3529],"type":"Point"}
}