{
  "type": "Feature",
  "properties": {
    "gn:admin1_code":"7.0",
    "gn:asciiname":"Galenchino",
    "gn:country_code":"BY",
    "gn:dem":133,
    "gn:feature_class":"P",
    "gn:feature_code":"PPL",
    "gn:name":"Galenchino",
    "gn:population":0,
    "gn:timezone":"Europe/Minsk",
    "iso:country":"BY",
    "name:rus_x_preferred":[
        "\u0413\u0430\u043b\u0435\u043d\u0447\u0438\u043d\u043e"
    ],
    "name:und_x_variant":[
        "Golenchino"
    ],
    "wof:name":"Galenchino",
    "wof:placetype":"locality"
},
  "geometry": {"coordinates":[28.1909,55.4667],"type":"Point"}
}