{
  "type": "Feature",
  "properties": {
    "gn:admin1_code":"5.0",
    "gn:asciiname":"Krasnyy Pakhar'",
    "gn:country_code":"BY",
    "gn:dem":175,
    "gn:feature_class":"P",
    "gn:feature_code":"PPL",
    "gn:name":"Krasnyy Pakhar\u2019",
    "gn:population":0,
    "gn:timezone":"Europe/Minsk",
    "iso:country":"BY",
    "name:rus_x_preferred":[
        "\u041a\u0440\u0430\u0441\u043d\u044b\u0439 \u041f\u0430\u0445\u0430\u0440\u044c"
    ],
    "name:und_x_variant":[
        "Krasnyy Pakhar\u2019"
    ],
    "wof:name":"Krasnyy Pakhar'",
    "wof:placetype":"locality"
},
  "geometry": {"coordinates":[29.4038,54.0915],"type":"Point"}
}