{
  "type": "Feature",
  "properties": {
    "gn:admin1_code":"7.0",
    "gn:asciiname":"Babinichy",
    "gn:country_code":"BY",
    "gn:dem":173,
    "gn:feature_class":"P",
    "gn:feature_code":"PPL",
    "gn:name":"Babinichy",
    "gn:population":0,
    "gn:timezone":"Europe/Minsk",
    "iso:country":"BY",
    "name:bel_x_preferred":[
        "\u0411\u0430\u0431\u0456\u043d\u0456\u0447\u044b"
    ],
    "name:eng_x_preferred":[
        "Babinichi"
    ],
    "name:rus_x_preferred":[
        "\u0411\u0430\u0431\u0438\u043d\u0438\u0447\u0438"
    ],
    "name:und_x_variant":[
        "Babinichi"
    ],
    "wof:name":"Babinichy",
    "wof:placetype":"locality"
},
  "geometry": {"coordinates":[30.3547,55.2609],"type":"Point"}
}