{
  "type": "Feature",
  "properties": {
    "gn:admin1_code":"3.0",
    "gn:asciiname":"Lukashino",
    "gn:country_code":"BY",
    "gn:dem":139,
    "gn:feature_class":"P",
    "gn:feature_code":"PPL",
    "gn:name":"Lukashino",
    "gn:population":0,
    "gn:timezone":"Europe/Minsk",
    "iso:country":"BY",
    "name:bel_x_preferred":[
        "Lukashyna"
    ],
    "name:bel_x_variant":[
        "\u041b\u0443\u043a\u0430\u0448\u044b\u043d\u0430"
    ],
    "name:rus_x_preferred":[
        "\u041b\u0443\u043a\u0430\u0448\u0438\u043d\u043e"
    ],
    "name:und_x_variant":[
        "Lukoshyn",
        "Lukashen",
        "Lukashek",
        "Lukashino"
    ],
    "wof:name":"Lukashino",
    "wof:placetype":"locality"
},
  "geometry": {"coordinates":[25.7015,53.9196],"type":"Point"}
}