{
  "type": "Feature",
  "properties": {
    "gn:admin1_code":"5.0",
    "gn:asciiname":"Zamenka",
    "gn:country_code":"BY",
    "gn:dem":189,
    "gn:feature_class":"P",
    "gn:feature_code":"PPL",
    "gn:name":"Zamenka",
    "gn:population":0,
    "gn:timezone":"Europe/Minsk",
    "iso:country":"BY",
    "name:rus_x_preferred":[
        "\u0417\u0430\u043c\u0435\u043d\u043a\u0430"
    ],
    "wof:name":"Zamenka",
    "wof:placetype":"locality"
},
  "geometry": {"coordinates":[26.6277,53.8243],"type":"Point"}
}