{
  "type": "Feature",
  "properties": {
    "gn:admin1_code":"6.0",
    "gn:asciiname":"Shablavy",
    "gn:country_code":"BY",
    "gn:dem":197,
    "gn:feature_class":"P",
    "gn:feature_code":"PPL",
    "gn:name":"Shablavy",
    "gn:population":0,
    "gn:timezone":"Europe/Minsk",
    "iso:country":"BY",
    "name:rus_x_preferred":[
        "\u0428\u0430\u0431\u043b\u0430\u0432\u044b"
    ],
    "wof:name":"Shablavy",
    "wof:placetype":"locality"
},
  "geometry": {"coordinates":[31.1766,54.0606],"type":"Point"}
}