{
  "type": "Feature",
  "properties": {
    "gn:admin1_code":"1.0",
    "gn:asciiname":"Kozlyakevichi",
    "gn:country_code":"BY",
    "gn:dem":190,
    "gn:feature_class":"P",
    "gn:feature_code":"PPL",
    "gn:name":"Kozlyakevichi",
    "gn:population":0,
    "gn:timezone":"Europe/Minsk",
    "iso:country":"BY",
    "name:bel_x_preferred":[
        "Kazlyakyevichy"
    ],
    "name:bel_x_variant":[
        "\u041a\u0430\u0437\u043b\u044f\u043a\u0435\u0432\u0456\u0447\u044b"
    ],
    "name:rus_x_preferred":[
        "\u041a\u043e\u0437\u043b\u044f\u043a\u0435\u0432\u0438\u0447\u0438"
    ],
    "name:rus_x_variant":[
        "\u041a\u043e\u0437\u043b\u044f\u043a\u043e\u0432\u0438\u0447\u0438"
    ],
    "name:und_x_variant":[
        "Kozlyakovichi"
    ],
    "wof:name":"Kozlyakevichi",
    "wof:placetype":"locality"
},
  "geometry": {"coordinates":[25.9371,53.1698],"type":"Point"}
}