{
  "type": "Feature",
  "properties": {
    "gn:admin1_code":"6.0",
    "gn:asciiname":"Dobraye",
    "gn:country_code":"BY",
    "gn:dem":164,
    "gn:feature_class":"P",
    "gn:feature_code":"PPL",
    "gn:name":"Dobraye",
    "gn:population":0,
    "gn:timezone":"Europe/Minsk",
    "iso:country":"BY",
    "name:bel_x_preferred":[
        "\u0414\u043e\u0431\u0440\u0430\u0435"
    ],
    "name:und_x_variant":[
        "Dabroye",
        "Dobroye",
        "Dobraye"
    ],
    "wof:name":"Dobraye",
    "wof:placetype":"locality"
},
  "geometry": {"coordinates":[31.6099,53.88800000000001],"type":"Point"}
}