{
  "type": "Feature",
  "properties": {
    "gn:admin1_code":"5.0",
    "gn:asciiname":"Babiy Les",
    "gn:country_code":"BY",
    "gn:dem":181,
    "gn:feature_class":"P",
    "gn:feature_code":"PPL",
    "gn:name":"Babiy Les",
    "gn:population":0,
    "gn:timezone":"Europe/Minsk",
    "iso:country":"BY",
    "name:rus_x_preferred":[
        "\u0411\u0430\u0431\u0438\u0439 \u041b\u0435\u0441"
    ],
    "wof:name":"Babiy Les",
    "wof:placetype":"locality"
},
  "geometry": {"coordinates":[28.1904,54.1569],"type":"Point"}
}