{
  "type": "Feature",
  "properties": {
    "gn:admin1_code":"3.0",
    "gn:asciiname":"Karolin",
    "gn:country_code":"BY",
    "gn:dem":124,
    "gn:feature_class":"P",
    "gn:feature_code":"PPL",
    "gn:name":"Karolin",
    "gn:population":0,
    "gn:timezone":"Europe/Minsk",
    "iso:country":"BY",
    "name:rus_x_preferred":[
        "\u041a\u0430\u0440\u043e\u043b\u0438\u043d"
    ],
    "name:und_x_variant":[
        "Korolino"
    ],
    "wof:name":"Karolin",
    "wof:placetype":"locality"
},
  "geometry": {"coordinates":[23.689,53.6348],"type":"Point"}
}