{
  "type": "Feature",
  "properties": {
    "gn:admin1_code":"7.0",
    "gn:asciiname":"Stanulevo",
    "gn:country_code":"BY",
    "gn:dem":146,
    "gn:feature_class":"P",
    "gn:feature_code":"PPL",
    "gn:name":"Stanulevo",
    "gn:population":0,
    "gn:timezone":"Europe/Minsk",
    "iso:country":"BY",
    "name:rus_x_preferred":[
        "\u0421\u0442\u0430\u043d\u0443\u043b\u0435\u0432\u043e"
    ],
    "wof:name":"Stanulevo",
    "wof:placetype":"locality"
},
  "geometry": {"coordinates":[27.6361,55.6346],"type":"Point"}
}