{
  "type": "Feature",
  "properties": {
    "gn:admin1_code":"2.0",
    "gn:asciiname":"Zarizh'ye",
    "gn:country_code":"BY",
    "gn:dem":133,
    "gn:feature_class":"P",
    "gn:feature_code":"PPL",
    "gn:name":"Zarizh\u2019ye",
    "gn:population":0,
    "gn:timezone":"Europe/Minsk",
    "iso:country":"BY",
    "name:rus_x_preferred":[
        "\u0417\u0430\u0440\u0438\u0436\u044c\u0435"
    ],
    "name:und_x_variant":[
        "Zarizh\u2019ye"
    ],
    "wof:name":"Zarizh'ye",
    "wof:placetype":"locality"
},
  "geometry": {"coordinates":[29.0187,52.5004],"type":"Point"}
}