{
  "type": "Feature",
  "properties": {
    "gn:admin1_code":"7.0",
    "gn:asciiname":"Svirkovshchina",
    "gn:country_code":"BY",
    "gn:dem":178,
    "gn:feature_class":"P",
    "gn:feature_code":"PPL",
    "gn:name":"Svirkovshchina",
    "gn:population":0,
    "gn:timezone":"Europe/Minsk",
    "iso:country":"BY",
    "name:rus_x_preferred":[
        "\u0421\u0432\u0438\u0440\u043a\u043e\u0432\u0449\u0438\u043d\u0430"
    ],
    "wof:name":"Svirkovshchina",
    "wof:placetype":"locality"
},
  "geometry": {"coordinates":[27.3773,54.9013],"type":"Point"}
}