{
  "type": "Feature",
  "properties": {
    "gn:admin1_code":"3.0",
    "gn:asciiname":"Duborovshchina",
    "gn:country_code":"BY",
    "gn:dem":126,
    "gn:feature_class":"P",
    "gn:feature_code":"PPL",
    "gn:name":"Duborovshchina",
    "gn:population":0,
    "gn:timezone":"Europe/Minsk",
    "iso:country":"BY",
    "name:rus_x_preferred":[
        "\u0414\u0443\u0431\u043e\u0440\u043e\u0432\u0449\u0438\u043d\u0430"
    ],
    "wof:name":"Duborovshchina",
    "wof:placetype":"locality"
},
  "geometry": {"coordinates":[25.1329,53.3473],"type":"Point"}
}