{
  "type": "Feature",
  "properties": {
    "gn:admin1_code":"7.0",
    "gn:asciiname":"Telepy",
    "gn:country_code":"BY",
    "gn:dem":143,
    "gn:feature_class":"P",
    "gn:feature_code":"PPL",
    "gn:name":"Telepy",
    "gn:population":0,
    "gn:timezone":"Europe/Minsk",
    "iso:country":"BY",
    "name:rus_x_preferred":[
        "\u0422\u0435\u043b\u0435\u043f\u044b"
    ],
    "wof:name":"Telepy",
    "wof:placetype":"locality"
},
  "geometry": {"coordinates":[29.6615,55.0201],"type":"Point"}
}