{
  "type": "Feature",
  "properties": {
    "gn:admin1_code":"1.0",
    "gn:asciiname":"Bol'shaya Lotva",
    "gn:country_code":"BY",
    "gn:dem":182,
    "gn:feature_class":"P",
    "gn:feature_code":"PPL",
    "gn:name":"Bol\u2019shaya Lotva",
    "gn:population":0,
    "gn:timezone":"Europe/Minsk",
    "iso:country":"BY",
    "name:rus_x_preferred":[
        "Bol\u2019shaya Lotva"
    ],
    "name:rus_x_variant":[
        "\u0411\u043e\u043b\u044c\u0448\u0430\u044f \u041b\u043e\u0442\u0432\u0430"
    ],
    "name:und_x_variant":[
        "Vel\u2019ka Lotva",
        "Bol\u2019shaya Lotva",
        "Bol\u2019shaya Lotova"
    ],
    "wof:name":"Bol'shaya Lotva",
    "wof:placetype":"locality"
},
  "geometry": {"coordinates":[26.2534,53.0629],"type":"Point"}
}