{
  "type": "Feature",
  "properties": {
    "gn:admin1_code":"5.0",
    "gn:asciiname":"Gumnishche",
    "gn:country_code":"BY",
    "gn:dem":178,
    "gn:feature_class":"P",
    "gn:feature_code":"PPL",
    "gn:name":"Gumnishche",
    "gn:population":0,
    "gn:timezone":"Europe/Minsk",
    "iso:country":"BY",
    "name:rus_x_preferred":[
        "\u0413\u0443\u043c\u043d\u0438\u0449\u0435"
    ],
    "wof:name":"Gumnishche",
    "wof:placetype":"locality"
},
  "geometry": {"coordinates":[28.7201,54.2881],"type":"Point"}
}