{
  "type": "Feature",
  "properties": {
    "gn:admin1_code":"7.0",
    "gn:asciiname":"Kadrishki",
    "gn:country_code":"BY",
    "gn:dem":136,
    "gn:feature_class":"P",
    "gn:feature_code":"PPL",
    "gn:name":"Kadrishki",
    "gn:population":0,
    "gn:timezone":"Europe/Minsk",
    "iso:country":"BY",
    "name:rus_x_preferred":[
        "\u041a\u0430\u0434\u0440\u0438\u0448\u043a\u0438"
    ],
    "wof:name":"Kadrishki",
    "wof:placetype":"locality"
},
  "geometry": {"coordinates":[27.5265,55.4446],"type":"Point"}
}