{
  "type": "Feature",
  "properties": {
    "gn:admin1_code":"5.0",
    "gn:asciiname":"Ugodino",
    "gn:country_code":"BY",
    "gn:dem":159,
    "gn:feature_class":"P",
    "gn:feature_code":"PPL",
    "gn:name":"Ugodino",
    "gn:population":0,
    "gn:timezone":"Europe/Minsk",
    "iso:country":"BY",
    "name:rus_x_preferred":[
        "\u0423\u0433\u043e\u0434\u0438\u043d\u043e"
    ],
    "name:und_x_variant":[
        "Ugoden\u2019"
    ],
    "wof:name":"Ugodino",
    "wof:placetype":"locality"
},
  "geometry": {"coordinates":[28.2131,53.3911],"type":"Point"}
}