{
  "type": "Feature",
  "properties": {
    "gn:admin1_code":"7.0",
    "gn:asciiname":"Polevache",
    "gn:country_code":"BY",
    "gn:dem":193,
    "gn:feature_class":"P",
    "gn:feature_code":"PPL",
    "gn:name":"Polevache",
    "gn:population":0,
    "gn:timezone":"Europe/Minsk",
    "iso:country":"BY",
    "name:rus_x_preferred":[
        "\u041f\u043e\u043b\u0435\u0432\u0430\u0447\u0435"
    ],
    "wof:name":"Polevache",
    "wof:placetype":"locality"
},
  "geometry": {"coordinates":[28.2288,55.2807],"type":"Point"}
}