{
  "type": "Feature",
  "properties": {
    "gn:admin1_code":"1.0",
    "gn:asciiname":"Shcherbovo",
    "gn:country_code":"BY",
    "gn:dem":150,
    "gn:feature_class":"P",
    "gn:feature_code":"PPL",
    "gn:name":"Shcherbovo",
    "gn:population":0,
    "gn:timezone":"Europe/Minsk",
    "iso:country":"BY",
    "name:rus_x_preferred":[
        "\u0429\u0435\u0440\u0431\u043e\u0432\u043e"
    ],
    "wof:name":"Shcherbovo",
    "wof:placetype":"locality"
},
  "geometry": {"coordinates":[23.904,52.359],"type":"Point"}
}