{
  "type": "Feature",
  "properties": {
    "gn:admin1_code":"7.0",
    "gn:asciiname":"Novyye Goryany",
    "gn:country_code":"BY",
    "gn:dem":120,
    "gn:feature_class":"P",
    "gn:feature_code":"PPL",
    "gn:name":"Novyye Goryany",
    "gn:population":0,
    "gn:timezone":"Europe/Minsk",
    "iso:country":"BY",
    "name:rus_x_preferred":[
        "\u041d\u043e\u0432\u044b\u0435 \u0413\u043e\u0440\u044f\u043d\u044b"
    ],
    "wof:name":"Novyye Goryany",
    "wof:placetype":"locality"
},
  "geometry": {"coordinates":[29.0449,55.4043],"type":"Point"}
}