{
  "type": "Feature",
  "properties": {
    "gn:admin1_code":"7.0",
    "gn:asciiname":"Poddub'ye",
    "gn:country_code":"BY",
    "gn:dem":215,
    "gn:feature_class":"P",
    "gn:feature_code":"PPL",
    "gn:name":"Poddub\u2019ye",
    "gn:population":0,
    "gn:timezone":"Europe/Minsk",
    "iso:country":"BY",
    "name:rus_x_preferred":[
        "\u041f\u043e\u0434\u0434\u0443\u0431\u044c\u0435"
    ],
    "name:und_x_variant":[
        "Poddub\u2019ye"
    ],
    "wof:name":"Poddub'ye",
    "wof:placetype":"locality"
},
  "geometry": {"coordinates":[30.4644,55.1951],"type":"Point"}
}