{
  "type": "Feature",
  "properties": {
    "gn:admin1_code":"3.0",
    "gn:asciiname":"Malaya Pokaz'",
    "gn:country_code":"BY",
    "gn:dem":160,
    "gn:feature_class":"P",
    "gn:feature_code":"PPL",
    "gn:name":"Malaya Pokaz\u2019",
    "gn:population":0,
    "gn:timezone":"Europe/Minsk",
    "iso:country":"BY",
    "name:rus_x_preferred":[
        "\u041c\u0430\u043b\u0430\u044f \u041f\u043e\u043a\u0430\u0437\u044c"
    ],
    "name:und_x_variant":[
        "Malaya Pokaz\u2019"
    ],
    "wof:name":"Malaya Pokaz'",
    "wof:placetype":"locality"
},
  "geometry": {"coordinates":[25.4773,54.0224],"type":"Point"}
}