{
  "type": "Feature",
  "properties": {
    "gn:admin1_code":"1.0",
    "gn:asciiname":"Mazichi",
    "gn:country_code":"BY",
    "gn:dem":139,
    "gn:feature_class":"P",
    "gn:feature_code":"PPL",
    "gn:name":"Mazichi",
    "gn:population":0,
    "gn:timezone":"Europe/Minsk",
    "iso:country":"BY",
    "name:rus_x_preferred":[
        "\u041c\u0430\u0437\u0438\u0447\u0438"
    ],
    "wof:name":"Mazichi",
    "wof:placetype":"locality"
},
  "geometry": {"coordinates":[24.2856,52.2136],"type":"Point"}
}