{
  "type": "Feature",
  "properties": {
    "gn:admin1_code":"6.0",
    "gn:asciiname":"Vyshkovka",
    "gn:country_code":"BY",
    "gn:dem":160,
    "gn:feature_class":"P",
    "gn:feature_code":"PPL",
    "gn:name":"Vyshkovka",
    "gn:population":0,
    "gn:timezone":"Europe/Minsk",
    "iso:country":"BY",
    "name:rus_x_preferred":[
        "\u0412\u044b\u0448\u043a\u043e\u0432\u043a\u0430"
    ],
    "wof:name":"Vyshkovka",
    "wof:placetype":"locality"
},
  "geometry": {"coordinates":[30.6887,53.3079],"type":"Point"}
}