{
  "type": "Feature",
  "properties": {
    "gn:admin1_code":"7.0",
    "gn:asciiname":"Kozly",
    "gn:country_code":"BY",
    "gn:dem":173,
    "gn:feature_class":"P",
    "gn:feature_code":"PPL",
    "gn:name":"Kozly",
    "gn:population":0,
    "gn:timezone":"Europe/Minsk",
    "iso:country":"BY",
    "name:rus_x_preferred":[
        "\u041a\u043e\u0437\u043b\u044b"
    ],
    "wof:name":"Kozly",
    "wof:placetype":"locality"
},
  "geometry": {"coordinates":[29.9931,55.2876],"type":"Point"}
}