{
  "type": "Feature",
  "properties": {
    "gn:admin1_code":"1.0",
    "gn:asciiname":"Radzyezh",
    "gn:country_code":"BY",
    "gn:dem":159,
    "gn:feature_class":"P",
    "gn:feature_code":"PPL",
    "gn:name":"Radzyezh",
    "gn:population":0,
    "gn:timezone":"Europe/Minsk",
    "iso:country":"BY",
    "name:bel_x_preferred":[
        "\u0420\u0430\u0434\u0437\u0435\u0436"
    ],
    "name:und_x_variant":[
        "Radezh",
        "Radzyezh"
    ],
    "wof:name":"Radzyezh",
    "wof:placetype":"locality"
},
  "geometry": {"coordinates":[23.8183,51.7092],"type":"Point"}
}