{
  "type": "Feature",
  "properties": {
    "gn:admin1_code":"5.0",
    "gn:asciiname":"Novaya Guta",
    "gn:country_code":"BY",
    "gn:dem":164,
    "gn:feature_class":"P",
    "gn:feature_code":"PPL",
    "gn:name":"Novaya Guta",
    "gn:population":0,
    "gn:timezone":"Europe/Minsk",
    "iso:country":"BY",
    "name:rus_x_preferred":[
        "\u041d\u043e\u0432\u0430\u044f \u0413\u0443\u0442\u0430"
    ],
    "wof:name":"Novaya Guta",
    "wof:placetype":"locality"
},
  "geometry": {"coordinates":[26.9725,53.3073],"type":"Point"}
}