{
  "type": "Feature",
  "properties": {
    "gn:admin1_code":"3.0",
    "gn:asciiname":"Yatskovshchina",
    "gn:country_code":"BY",
    "gn:dem":164,
    "gn:feature_class":"P",
    "gn:feature_code":"PPL",
    "gn:name":"Yatskovshchina",
    "gn:population":0,
    "gn:timezone":"Europe/Minsk",
    "iso:country":"BY",
    "name:rus_x_preferred":[
        "\u042f\u0446\u043a\u043e\u0432\u0449\u0438\u043d\u0430"
    ],
    "wof:name":"Yatskovshchina",
    "wof:placetype":"locality"
},
  "geometry": {"coordinates":[25.8619,54.179],"type":"Point"}
}