{
  "type": "Feature",
  "properties": {
    "gn:admin1_code":"7.0",
    "gn:asciiname":"Bereznitsa",
    "gn:country_code":"BY",
    "gn:dem":135,
    "gn:feature_class":"P",
    "gn:feature_code":"PPL",
    "gn:name":"Ber\u00ebznitsa",
    "gn:population":0,
    "gn:timezone":"Europe/Minsk",
    "iso:country":"BY",
    "name:rus_x_preferred":[
        "\u0411\u0435\u0440\u0451\u0437\u043d\u0438\u0446\u0430"
    ],
    "name:und_x_variant":[
        "Ber\u00ebznitsa"
    ],
    "wof:name":"Bereznitsa",
    "wof:placetype":"locality"
},
  "geometry": {"coordinates":[29.4713,55.2214],"type":"Point"}
}