{
  "type": "Feature",
  "properties": {
    "gn:admin1_code":"3.0",
    "gn:asciiname":"Gaygoly",
    "gn:country_code":"BY",
    "gn:dem":151,
    "gn:feature_class":"P",
    "gn:feature_code":"PPL",
    "gn:name":"Gaygoly",
    "gn:population":0,
    "gn:timezone":"Europe/Minsk",
    "iso:country":"BY",
    "name:rus_x_preferred":[
        "\u0413\u0430\u0439\u0433\u043e\u043b\u044b"
    ],
    "wof:name":"Gaygoly",
    "wof:placetype":"locality"
},
  "geometry": {"coordinates":[26.1375,54.7229],"type":"Point"}
}