{
  "type": "Feature",
  "properties": {
    "gn:admin1_code":"7.0",
    "gn:asciiname":"Kevlichi",
    "gn:country_code":"BY",
    "gn:dem":125,
    "gn:feature_class":"P",
    "gn:feature_code":"PPL",
    "gn:name":"Kevlichi",
    "gn:population":0,
    "gn:timezone":"Europe/Minsk",
    "iso:country":"BY",
    "name:rus_x_preferred":[
        "\u041a\u0435\u0432\u043b\u0438\u0447\u0438"
    ],
    "wof:name":"Kevlichi",
    "wof:placetype":"locality"
},
  "geometry": {"coordinates":[27.2972,55.2757],"type":"Point"}
}