{
  "type": "Feature",
  "properties": {
    "gn:admin1_code":"7.0",
    "gn:asciiname":"Mamchikovo",
    "gn:country_code":"BY",
    "gn:dem":193,
    "gn:feature_class":"P",
    "gn:feature_code":"PPL",
    "gn:name":"Mamchikovo",
    "gn:population":0,
    "gn:timezone":"Europe/Minsk",
    "iso:country":"BY",
    "name:rus_x_preferred":[
        "\u041c\u0430\u043c\u0447\u0438\u043a\u043e\u0432\u043e"
    ],
    "wof:name":"Mamchikovo",
    "wof:placetype":"locality"
},
  "geometry": {"coordinates":[29.8856,55.5579],"type":"Point"}
}