{
  "type": "Feature",
  "properties": {
    "gn:admin1_code":"2.0",
    "gn:asciiname":"Kamyenka",
    "gn:country_code":"BY",
    "gn:dem":155,
    "gn:feature_class":"P",
    "gn:feature_code":"PPL",
    "gn:name":"Kamyenka",
    "gn:population":0,
    "gn:timezone":"Europe/Minsk",
    "iso:country":"BY",
    "name:bel_x_preferred":[
        "\u041a\u0430\u043c\u0435\u043d\u043a\u0430"
    ],
    "name:und_x_variant":[
        "Kamenka"
    ],
    "wof:name":"Kamyenka",
    "wof:placetype":"locality"
},
  "geometry": {"coordinates":[30.6713,53.1851],"type":"Point"}
}