{
  "type": "Feature",
  "properties": {
    "gn:admin1_code":"7.0",
    "gn:asciiname":"Veretei",
    "gn:country_code":"BY",
    "gn:dem":155,
    "gn:feature_class":"P",
    "gn:feature_code":"PPL",
    "gn:name":"Veretei",
    "gn:population":0,
    "gn:timezone":"Europe/Minsk",
    "iso:country":"BY",
    "name:rus_x_preferred":[
        "\u0412\u0435\u0440\u0435\u0442\u0435\u0438"
    ],
    "wof:name":"Veretei",
    "wof:placetype":"locality"
},
  "geometry": {"coordinates":[27.4153,55.1475],"type":"Point"}
}