{
  "type": "Feature",
  "properties": {
    "gn:admin1_code":"7.0",
    "gn:asciiname":"Fabiyanovo",
    "gn:country_code":"BY",
    "gn:dem":154,
    "gn:feature_class":"P",
    "gn:feature_code":"PPL",
    "gn:name":"Fabiyanovo",
    "gn:population":0,
    "gn:timezone":"Europe/Minsk",
    "iso:country":"BY",
    "name:rus_x_preferred":[
        "\u0424\u0430\u0431\u0438\u044f\u043d\u043e\u0432\u043e"
    ],
    "name:und_x_variant":[
        "Fab\u2019yanovo"
    ],
    "wof:name":"Fabiyanovo",
    "wof:placetype":"locality"
},
  "geometry": {"coordinates":[27.9084,55.3347],"type":"Point"}
}