{
  "type": "Feature",
  "properties": {
    "gn:admin1_code":"5.0",
    "gn:asciiname":"Plebantsy",
    "gn:country_code":"BY",
    "gn:dem":184,
    "gn:feature_class":"P",
    "gn:feature_code":"PPL",
    "gn:name":"Plebantsy",
    "gn:population":0,
    "gn:timezone":"Europe/Minsk",
    "iso:country":"BY",
    "name:rus_x_preferred":[
        "\u041f\u043b\u0435\u0431\u0430\u043d\u0446\u044b"
    ],
    "name:und_x_variant":[
        "Pleba\u0144ce",
        "Pleban\u2019tse",
        "Plebantsy"
    ],
    "wof:name":"Plebantsy",
    "wof:placetype":"locality"
},
  "geometry": {"coordinates":[27.478,54.68],"type":"Point"}
}