{
  "type": "Feature",
  "properties": {
    "gn:admin1_code":"6.0",
    "gn:asciiname":"Bezvodichi",
    "gn:country_code":"BY",
    "gn:dem":202,
    "gn:feature_class":"P",
    "gn:feature_code":"PPL",
    "gn:name":"Bezvodichi",
    "gn:population":0,
    "gn:timezone":"Europe/Minsk",
    "iso:country":"BY",
    "name:rus_x_preferred":[
        "\u0411\u0435\u0437\u0432\u043e\u0434\u0438\u0447\u0438"
    ],
    "wof:name":"Bezvodichi",
    "wof:placetype":"locality"
},
  "geometry": {"coordinates":[31.4511,53.9766],"type":"Point"}
}