{
  "type": "Feature",
  "properties": {
    "gn:admin1_code":"1.0",
    "gn:asciiname":"Radost'",
    "gn:country_code":"BY",
    "gn:dem":144,
    "gn:feature_class":"P",
    "gn:feature_code":"PPL",
    "gn:name":"\u0420\u0430\u0434\u043e\u0441\u0442\u044c",
    "gn:population":0,
    "gn:timezone":"Europe/Minsk",
    "iso:country":"BY",
    "name:rus_x_preferred":[
        "Radost\u2019"
    ],
    "name:rus_x_variant":[
        "\u0420\u0430\u0434\u043e\u0441\u0442\u044c"
    ],
    "name:und_x_variant":[
        "Rados\u2019ts\u2019"
    ],
    "wof:name":"Radost'",
    "wof:placetype":"locality"
},
  "geometry": {"coordinates":[23.7828,52.3727],"type":"Point"}
}