{
  "type": "Feature",
  "properties": {
    "gn:admin1_code":"7.0",
    "gn:asciiname":"Khveshchenki",
    "gn:country_code":"BY",
    "gn:dem":156,
    "gn:feature_class":"P",
    "gn:feature_code":"PPL",
    "gn:name":"Khveshchenki",
    "gn:population":0,
    "gn:timezone":"Europe/Minsk",
    "iso:country":"BY",
    "name:rus_x_preferred":[
        "\u0425\u0432\u0435\u0449\u0435\u043d\u043a\u0438"
    ],
    "wof:name":"Khveshchenki",
    "wof:placetype":"locality"
},
  "geometry": {"coordinates":[29.7603,55.4296],"type":"Point"}
}