{
  "type": "Feature",
  "properties": {
    "gn:admin1_code":"3.0",
    "gn:asciiname":"Litvinki",
    "gn:country_code":"BY",
    "gn:dem":106,
    "gn:feature_class":"P",
    "gn:feature_code":"PPL",
    "gn:name":"Litvinki",
    "gn:population":0,
    "gn:timezone":"Europe/Minsk",
    "iso:country":"BY",
    "name:rus_x_preferred":[
        "\u041b\u0438\u0442\u0432\u0438\u043d\u043a\u0438"
    ],
    "name:und_x_variant":[
        "Litwinka",
        "Litvinka",
        "Litvinki"
    ],
    "wof:name":"Litvinki",
    "wof:placetype":"locality"
},
  "geometry": {"coordinates":[24.029,53.4684],"type":"Point"}
}