{
  "type": "Feature",
  "properties": {
    "gn:admin1_code":"5.0",
    "gn:asciiname":"Nekasetsk",
    "gn:country_code":"BY",
    "gn:dem":184,
    "gn:feature_class":"P",
    "gn:feature_code":"PPL",
    "gn:name":"Nekasetsk",
    "gn:population":0,
    "gn:timezone":"Europe/Minsk",
    "iso:country":"BY",
    "name:rus_x_preferred":[
        "\u041d\u0435\u043a\u0430\u0441\u0435\u0446\u043a"
    ],
    "name:und_x_variant":[
        "Niekasieck",
        "Nekasetsk"
    ],
    "wof:name":"Nekasetsk",
    "wof:placetype":"locality"
},
  "geometry": {"coordinates":[27.0049,54.8957],"type":"Point"}
}