{
  "type": "Feature",
  "properties": {
    "gn:admin1_code":"6.0",
    "gn:asciiname":"Vil'cha",
    "gn:country_code":"BY",
    "gn:dem":147,
    "gn:feature_class":"P",
    "gn:feature_code":"PPL",
    "gn:name":"Vil\u2019cha",
    "gn:population":0,
    "gn:timezone":"Europe/Minsk",
    "iso:country":"BY",
    "name:rus_x_preferred":[
        "\u0412\u0438\u043b\u044c\u0447\u0430"
    ],
    "name:und_x_variant":[
        "Vil\u2019chi",
        "Vil\u2019cha"
    ],
    "wof:name":"Vil'cha",
    "wof:placetype":"locality"
},
  "geometry": {"coordinates":[28.852,52.9936],"type":"Point"}
}