{
  "type": "Feature",
  "properties": {
    "gn:admin1_code":"4.0",
    "gn:asciiname":"Kutenka",
    "gn:country_code":"BY",
    "gn:dem":133,
    "gn:feature_class":"P",
    "gn:feature_code":"PPL",
    "gn:name":"Kutenka",
    "gn:population":0,
    "gn:timezone":"Europe/Minsk",
    "iso:country":"BY",
    "name:rus_x_preferred":[
        "\u041a\u0443\u0442\u0435\u043d\u043a\u0430"
    ],
    "wof:name":"Kutenka",
    "wof:placetype":"locality"
},
  "geometry": {"coordinates":[28.1157,52.6587],"type":"Point"}
}