{
  "type": "Feature",
  "properties": {
    "gn:admin1_code":"5.0",
    "gn:asciiname":"Grozovok",
    "gn:country_code":"BY",
    "gn:dem":184,
    "gn:feature_class":"P",
    "gn:feature_code":"PPL",
    "gn:name":"Grozovok",
    "gn:population":0,
    "gn:timezone":"Europe/Minsk",
    "iso:country":"BY",
    "name:rus_x_preferred":[
        "\u0413\u0440\u043e\u0437\u043e\u0432\u043e\u043a"
    ],
    "wof:name":"Grozovok",
    "wof:placetype":"locality"
},
  "geometry": {"coordinates":[27.3161,53.1588],"type":"Point"}
}