{
  "type": "Feature",
  "properties": {
    "gn:admin1_code":"5.0",
    "gn:asciiname":"Partyzanski",
    "gn:country_code":"BY",
    "gn:dem":195,
    "gn:feature_class":"P",
    "gn:feature_code":"PPL",
    "gn:name":"Partyzanski",
    "gn:population":0,
    "gn:timezone":"Europe/Minsk",
    "iso:country":"BY",
    "name:bel_x_preferred":[
        "\u041f\u0430\u0440\u0442\u044b\u0437\u0430\u043d\u0441\u043a\u0456"
    ],
    "name:und_x_variant":[
        "Partizanskiy"
    ],
    "wof:name":"Partyzanski",
    "wof:placetype":"locality"
},
  "geometry": {"coordinates":[27.3356,54.37300000000001],"type":"Point"}
}