{
  "type": "Feature",
  "properties": {
    "gn:admin1_code":"6.0",
    "gn:asciiname":"Skachok",
    "gn:country_code":"BY",
    "gn:dem":168,
    "gn:feature_class":"P",
    "gn:feature_code":"PPL",
    "gn:name":"Skachok",
    "gn:population":0,
    "gn:timezone":"Europe/Minsk",
    "iso:country":"BY",
    "name:bel_x_preferred":[
        "\u0421\u043a\u0430\u0447\u043e\u043a"
    ],
    "name:rus_x_preferred":[
        "Skach\u00ebk"
    ],
    "wof:name":"Skachok",
    "wof:placetype":"locality"
},
  "geometry": {"coordinates":[29.6177,53.3648],"type":"Point"}
}