{
  "type": "Feature",
  "properties": {
    "gn:admin1_code":"5.0",
    "gn:asciiname":"Yakubovichi",
    "gn:country_code":"BY",
    "gn:dem":210,
    "gn:feature_class":"P",
    "gn:feature_code":"PPL",
    "gn:name":"Yakubovichi",
    "gn:population":0,
    "gn:timezone":"Europe/Minsk",
    "iso:country":"BY",
    "name:rus_x_preferred":[
        "\u042f\u043a\u0443\u0431\u043e\u0432\u0438\u0447\u0438"
    ],
    "wof:name":"Yakubovichi",
    "wof:placetype":"locality"
},
  "geometry": {"coordinates":[27.0258,53.1488],"type":"Point"}
}