{
  "type": "Feature",
  "properties": {
    "gn:admin1_code":"1.0",
    "gn:asciiname":"Krotovo",
    "gn:country_code":"BY",
    "gn:dem":169,
    "gn:feature_class":"P",
    "gn:feature_code":"PPL",
    "gn:name":"Krotovo",
    "gn:population":0,
    "gn:timezone":"Europe/Minsk",
    "iso:country":"BY",
    "name:rus_x_preferred":[
        "\u041a\u0440\u043e\u0442\u043e\u0432\u043e"
    ],
    "name:und_x_variant":[
        "Krotowo",
        "Krotovo"
    ],
    "wof:name":"Krotovo",
    "wof:placetype":"locality"
},
  "geometry": {"coordinates":[25.7575,52.2339],"type":"Point"}
}