{
  "type": "Feature",
  "properties": {
    "gn:admin1_code":"3.0",
    "gn:asciiname":"Lopatishki",
    "gn:country_code":"BY",
    "gn:dem":144,
    "gn:feature_class":"P",
    "gn:feature_code":"PPL",
    "gn:name":"Lopatishki",
    "gn:population":0,
    "gn:timezone":"Europe/Minsk",
    "iso:country":"BY",
    "name:rus_x_preferred":[
        "\u041b\u043e\u043f\u0430\u0442\u0438\u0448\u043a\u0438"
    ],
    "wof:name":"Lopatishki",
    "wof:placetype":"locality"
},
  "geometry": {"coordinates":[25.1537,54.0695],"type":"Point"}
}