{
  "type": "Feature",
  "properties": {
    "gn:admin1_code":"2.0",
    "gn:asciiname":"Prigorodnaya",
    "gn:country_code":"BY",
    "gn:dem":127,
    "gn:feature_class":"P",
    "gn:feature_code":"PPL",
    "gn:name":"Prigorodnaya",
    "gn:population":0,
    "gn:timezone":"Europe/Minsk",
    "iso:country":"BY",
    "name:rus_x_preferred":[
        "\u041f\u0440\u0438\u0433\u043e\u0440\u043e\u0434\u043d\u0430\u044f"
    ],
    "wof:name":"Prigorodnaya",
    "wof:placetype":"locality"
},
  "geometry": {"coordinates":[30.443,52.3361],"type":"Point"}
}