{
  "type": "Feature",
  "properties": {
    "gn:admin1_code":"3.0",
    "gn:asciiname":"Kusentsy",
    "gn:country_code":"BY",
    "gn:dem":167,
    "gn:feature_class":"P",
    "gn:feature_code":"PPL",
    "gn:name":"Kusentsy",
    "gn:population":0,
    "gn:timezone":"Europe/Minsk",
    "iso:country":"BY",
    "name:rus_x_preferred":[
        "\u041a\u0443\u0441\u0435\u043d\u0446\u044b"
    ],
    "wof:name":"Kusentsy",
    "wof:placetype":"locality"
},
  "geometry": {"coordinates":[24.377,52.96],"type":"Point"}
}