{
  "type": "Feature",
  "properties": {
    "gn:admin1_code":"5.0",
    "gn:asciiname":"Yavishchi",
    "gn:country_code":"BY",
    "gn:dem":169,
    "gn:feature_class":"P",
    "gn:feature_code":"PPL",
    "gn:name":"Yavishchi",
    "gn:population":0,
    "gn:timezone":"Europe/Minsk",
    "iso:country":"BY",
    "name:rus_x_preferred":[
        "\u042f\u0432\u0438\u0449\u0438"
    ],
    "wof:name":"Yavishchi",
    "wof:placetype":"locality"
},
  "geometry": {"coordinates":[26.9923,53.3413],"type":"Point"}
}