{
  "type": "Feature",
  "properties": {
    "gn:admin1_code":"7.0",
    "gn:asciiname":"Goreliki",
    "gn:country_code":"BY",
    "gn:dem":203,
    "gn:feature_class":"P",
    "gn:feature_code":"PPL",
    "gn:name":"Goreliki",
    "gn:population":0,
    "gn:timezone":"Europe/Minsk",
    "iso:country":"BY",
    "name:rus_x_preferred":[
        "\u0413\u043e\u0440\u0435\u043b\u0438\u043a\u0438"
    ],
    "wof:name":"Goreliki",
    "wof:placetype":"locality"
},
  "geometry": {"coordinates":[29.9173,54.3305],"type":"Point"}
}