{
  "type": "Feature",
  "properties": {
    "gn:admin1_code":"7.0",
    "gn:asciiname":"Chernyavshchina",
    "gn:country_code":"BY",
    "gn:dem":174,
    "gn:feature_class":"P",
    "gn:feature_code":"PPL",
    "gn:name":"Chernyavshchina",
    "gn:population":0,
    "gn:timezone":"Europe/Minsk",
    "iso:country":"BY",
    "name:rus_x_preferred":[
        "\u0427\u0435\u0440\u043d\u044f\u0432\u0449\u0438\u043d\u0430"
    ],
    "wof:name":"Chernyavshchina",
    "wof:placetype":"locality"
},
  "geometry": {"coordinates":[27.3259,55.6764],"type":"Point"}
}