{
  "type": "Feature",
  "properties": {
    "gn:admin1_code":"5.0",
    "gn:asciiname":"Puzichi",
    "gn:country_code":"BY",
    "gn:dem":141,
    "gn:feature_class":"P",
    "gn:feature_code":"PPL",
    "gn:name":"Puzichi",
    "gn:population":0,
    "gn:timezone":"Europe/Minsk",
    "iso:country":"BY",
    "name:rus_x_preferred":[
        "\u041f\u0443\u0437\u0438\u0447\u0438"
    ],
    "name:und_x_variant":[
        "Puzicze",
        "Puziche",
        "Puzichi"
    ],
    "wof:name":"Puzichi",
    "wof:placetype":"locality"
},
  "geometry": {"coordinates":[27.2527,52.5276],"type":"Point"}
}