{
  "type": "Feature",
  "properties": {
    "gn:admin1_code":"2.0",
    "gn:asciiname":"Rudnya-Pribytkovskaya",
    "gn:country_code":"BY",
    "gn:dem":132,
    "gn:feature_class":"P",
    "gn:feature_code":"PPL",
    "gn:name":"Rudnya-Pribytkovskaya",
    "gn:population":0,
    "gn:timezone":"Europe/Minsk",
    "iso:country":"BY",
    "name:rus_x_preferred":[
        "\u0420\u0443\u0434\u043d\u044f-\u041f\u0440\u0438\u0431\u044b\u0442\u043a\u043e\u0432\u0441\u043a\u0430\u044f"
    ],
    "name:und_x_variant":[
        "Rudnya"
    ],
    "wof:name":"Rudnya-Pribytkovskaya",
    "wof:placetype":"locality"
},
  "geometry": {"coordinates":[31.1374,52.2831],"type":"Point"}
}