{
  "type": "Feature",
  "properties": {
    "gn:admin1_code":"6.0",
    "gn:asciiname":"Zhitin",
    "gn:country_code":"BY",
    "gn:dem":161,
    "gn:feature_class":"P",
    "gn:feature_code":"PPL",
    "gn:name":"Zhitin",
    "gn:population":0,
    "gn:timezone":"Europe/Minsk",
    "iso:country":"BY",
    "name:rus_x_preferred":[
        "\u0416\u0438\u0442\u0438\u043d"
    ],
    "wof:name":"Zhitin",
    "wof:placetype":"locality"
},
  "geometry": {"coordinates":[28.1805,53.2423],"type":"Point"}
}