{
  "type": "Feature",
  "properties": {
    "gn:admin1_code":"5.0",
    "gn:asciiname":"Ferma-Gay",
    "gn:country_code":"BY",
    "gn:dem":210,
    "gn:feature_class":"P",
    "gn:feature_code":"PPL",
    "gn:name":"Ferma-Gay",
    "gn:population":0,
    "gn:timezone":"Europe/Minsk",
    "iso:country":"BY",
    "name:rus_x_preferred":[
        "\u0424\u0435\u0440\u043c\u0430-\u0413\u0430\u0439"
    ],
    "wof:name":"Ferma-Gay",
    "wof:placetype":"locality"
},
  "geometry": {"coordinates":[27.1607,53.7127],"type":"Point"}
}