{
  "type": "Feature",
  "properties": {
    "gn:admin1_code":"5.0",
    "gn:asciiname":"Stetski",
    "gn:country_code":"BY",
    "gn:dem":265,
    "gn:feature_class":"P",
    "gn:feature_code":"PPL",
    "gn:name":"Stetski",
    "gn:population":0,
    "gn:timezone":"Europe/Minsk",
    "iso:country":"BY",
    "name:rus_x_preferred":[
        "\u0421\u0442\u0435\u0446\u043a\u0438"
    ],
    "wof:name":"Stetski",
    "wof:placetype":"locality"
},
  "geometry": {"coordinates":[26.9813,54.0972],"type":"Point"}
}