{
  "type": "Feature",
  "properties": {
    "gn:admin1_code":"5.0",
    "gn:asciiname":"Staryna",
    "gn:country_code":"BY",
    "gn:dem":150,
    "gn:feature_class":"P",
    "gn:feature_code":"PPL",
    "gn:name":"Staryna",
    "gn:population":0,
    "gn:timezone":"Europe/Minsk",
    "iso:country":"BY",
    "name:bel_x_preferred":[
        "\u0421\u0442\u0430\u0440\u044b\u043d\u0430"
    ],
    "name:und_x_variant":[
        "Starina"
    ],
    "wof:name":"Staryna",
    "wof:placetype":"locality"
},
  "geometry": {"coordinates":[26.9297,52.8629],"type":"Point"}
}