{
  "type": "Feature",
  "properties": {
    "gn:admin1_code":"5.0",
    "gn:asciiname":"Slovensk",
    "gn:country_code":"BY",
    "gn:dem":160,
    "gn:feature_class":"P",
    "gn:feature_code":"PPL",
    "gn:name":"Slovensk",
    "gn:population":0,
    "gn:timezone":"Europe/Minsk",
    "iso:country":"BY",
    "name:rus_x_preferred":[
        "\u0421\u043b\u043e\u0432\u0435\u043d\u0441\u043a"
    ],
    "wof:name":"Slovensk",
    "wof:placetype":"locality"
},
  "geometry": {"coordinates":[26.3959,54.149],"type":"Point"}
}