{
  "type": "Feature",
  "properties": {
    "gn:admin1_code":"7.0",
    "gn:asciiname":"Boyary Pervyye",
    "gn:country_code":"BY",
    "gn:dem":126,
    "gn:feature_class":"P",
    "gn:feature_code":"PPL",
    "gn:name":"Boyary Pervyye",
    "gn:population":0,
    "gn:timezone":"Europe/Minsk",
    "iso:country":"BY",
    "name:rus_x_preferred":[
        "\u0411\u043e\u044f\u0440\u044b \u041f\u0435\u0440\u0432\u044b\u0435"
    ],
    "wof:name":"Boyary Pervyye",
    "wof:placetype":"locality"
},
  "geometry": {"coordinates":[27.7931,55.4456],"type":"Point"}
}