{
  "type": "Feature",
  "properties": {
    "gn:admin1_code":"7.0",
    "gn:asciiname":"Malyshki",
    "gn:country_code":"BY",
    "gn:dem":135,
    "gn:feature_class":"P",
    "gn:feature_code":"PPL",
    "gn:name":"Malyshki",
    "gn:population":0,
    "gn:timezone":"Europe/Minsk",
    "iso:country":"BY",
    "name:rus_x_preferred":[
        "\u041c\u0430\u043b\u044b\u0448\u043a\u0438"
    ],
    "wof:name":"Malyshki",
    "wof:placetype":"locality"
},
  "geometry": {"coordinates":[29.3762,55.3493],"type":"Point"}
}