{
  "type": "Feature",
  "properties": {
    "gn:admin1_code":"3.0",
    "gn:asciiname":"Pekari",
    "gn:country_code":"BY",
    "gn:dem":137,
    "gn:feature_class":"P",
    "gn:feature_code":"PPL",
    "gn:name":"Pekari",
    "gn:population":0,
    "gn:timezone":"Europe/Minsk",
    "iso:country":"BY",
    "name:rus_x_preferred":[
        "\u041f\u0435\u043a\u0430\u0440\u0438"
    ],
    "name:und_x_variant":[
        "Pekary",
        "Pekari"
    ],
    "wof:name":"Pekari",
    "wof:placetype":"locality"
},
  "geometry": {"coordinates":[24.4361,53.1822],"type":"Point"}
}