{
  "type": "Feature",
  "properties": {
    "gn:admin1_code":"1.0",
    "gn:asciiname":"Yermaki",
    "gn:country_code":"BY",
    "gn:dem":139,
    "gn:feature_class":"P",
    "gn:feature_code":"PPL",
    "gn:name":"Yermaki",
    "gn:population":0,
    "gn:timezone":"Europe/Minsk",
    "iso:country":"BY",
    "name:rus_x_preferred":[
        "\u0415\u0440\u043c\u0430\u043a\u0438"
    ],
    "wof:name":"Yermaki",
    "wof:placetype":"locality"
},
  "geometry": {"coordinates":[26.3214,52.2239],"type":"Point"}
}