{
  "type": "Feature",
  "properties": {
    "gn:admin1_code":"7.0",
    "gn:asciiname":"Kacheno",
    "gn:country_code":"BY",
    "gn:dem":163,
    "gn:feature_class":"P",
    "gn:feature_code":"PPL",
    "gn:name":"Kacheno",
    "gn:population":0,
    "gn:timezone":"Europe/Minsk",
    "iso:country":"BY",
    "name:rus_x_preferred":[
        "\u041a\u0430\u0447\u0435\u043d\u043e"
    ],
    "wof:name":"Kacheno",
    "wof:placetype":"locality"
},
  "geometry": {"coordinates":[29.8468,55.0609],"type":"Point"}
}