{
  "type": "Feature",
  "properties": {
    "gn:admin1_code":"2.0",
    "gn:asciiname":"Sadki",
    "gn:country_code":"BY",
    "gn:dem":120,
    "gn:feature_class":"P",
    "gn:feature_code":"PPL",
    "gn:name":"Sadki",
    "gn:population":0,
    "gn:timezone":"Europe/Minsk",
    "iso:country":"BY",
    "name:ceb_x_preferred":[
        "Sadki"
    ],
    "name:nld_x_preferred":[
        "Sadki"
    ],
    "name:pol_x_preferred":[
        "Sadki"
    ],
    "name:rus_x_preferred":[
        "\u0421\u0430\u0434\u043a\u0438"
    ],
    "name:ukr_x_preferred":[
        "\u0421\u0430\u0434\u043a\u0456"
    ],
    "wof:name":"Sadki",
    "wof:placetype":"locality"
},
  "geometry": {"coordinates":[29.0558,52.2297],"type":"Point"}
}