{
  "type": "Feature",
  "properties": {
    "gn:admin1_code":"3.0",
    "gn:asciiname":"Lyakhovichi",
    "gn:country_code":"BY",
    "gn:dem":135,
    "gn:feature_class":"P",
    "gn:feature_code":"PPL",
    "gn:name":"Lyakhovichi",
    "gn:population":0,
    "gn:timezone":"Europe/Minsk",
    "iso:country":"BY",
    "name:bel_x_preferred":[
        "Lyakhavichy"
    ],
    "name:bel_x_variant":[
        "\u041b\u044f\u0445\u0430\u0432\u0456\u0447\u044b"
    ],
    "name:rus_x_preferred":[
        "\u041b\u044f\u0445\u043e\u0432\u0438\u0447\u0438"
    ],
    "name:und_x_variant":[
        "Lyakhoviche",
        "Lyakhovichi"
    ],
    "wof:name":"Lyakhovichi",
    "wof:placetype":"locality"
},
  "geometry": {"coordinates":[24.7108,53.2179],"type":"Point"}
}