{
  "type": "Feature",
  "properties": {
    "gn:admin1_code":"6.0",
    "gn:asciiname":"Studenka",
    "gn:country_code":"BY",
    "gn:dem":177,
    "gn:feature_class":"P",
    "gn:feature_code":"PPL",
    "gn:name":"Stud\u00ebnka",
    "gn:population":0,
    "gn:timezone":"Europe/Minsk",
    "iso:country":"BY",
    "name:rus_x_preferred":[
        "\u0421\u0442\u0443\u0434\u0451\u043d\u043a\u0430"
    ],
    "name:und_x_variant":[
        "Stud\u00ebnka"
    ],
    "wof:name":"Studenka",
    "wof:placetype":"locality"
},
  "geometry": {"coordinates":[29.5218,53.8129],"type":"Point"}
}