{
  "type": "Feature",
  "properties": {
    "gn:admin1_code":"7.0",
    "gn:asciiname":"Dran'ki",
    "gn:country_code":"BY",
    "gn:dem":140,
    "gn:feature_class":"P",
    "gn:feature_code":"PPL",
    "gn:name":"Dran\u2019ki",
    "gn:population":0,
    "gn:timezone":"Europe/Minsk",
    "iso:country":"BY",
    "name:rus_x_preferred":[
        "\u0414\u0440\u0430\u043d\u044c\u043a\u0438"
    ],
    "name:und_x_variant":[
        "Dran\u2019ki",
        "Dron\u2019ki"
    ],
    "wof:name":"Dran'ki",
    "wof:placetype":"locality"
},
  "geometry": {"coordinates":[28.229,55.4038],"type":"Point"}
}