{
  "type": "Feature",
  "properties": {
    "gn:admin1_code":"6.0",
    "gn:asciiname":"Sklimin",
    "gn:country_code":"BY",
    "gn:dem":192,
    "gn:feature_class":"P",
    "gn:feature_code":"PPL",
    "gn:name":"Sklimin",
    "gn:population":0,
    "gn:timezone":"Europe/Minsk",
    "iso:country":"BY",
    "name:rus_x_preferred":[
        "\u0421\u043a\u043b\u0438\u043c\u0438\u043d"
    ],
    "wof:name":"Sklimin",
    "wof:placetype":"locality"
},
  "geometry": {"coordinates":[32.217,53.6934],"type":"Point"}
}