{
  "type": "Feature",
  "properties": {
    "gn:admin1_code":"3.0",
    "gn:asciiname":"Ozero Timnitsa",
    "gn:country_code":"BY",
    "gn:dem":114,
    "gn:feature_class":"P",
    "gn:feature_code":"PPL",
    "gn:name":"Ozero Timnitsa",
    "gn:population":0,
    "gn:timezone":"Europe/Minsk",
    "iso:country":"BY",
    "name:rus_x_preferred":[
        "\u041e\u0437\u0435\u0440\u043e \u0422\u0438\u043c\u043d\u0438\u0446\u0430"
    ],
    "wof:name":"Ozero Timnitsa",
    "wof:placetype":"locality"
},
  "geometry": {"coordinates":[24.385,53.71],"type":"Point"}
}