{
  "type": "Feature",
  "properties": {
    "gn:admin1_code":"6.0",
    "gn:asciiname":"Kustovka",
    "gn:country_code":"BY",
    "gn:dem":198,
    "gn:feature_class":"P",
    "gn:feature_code":"PPL",
    "gn:name":"Kustovka",
    "gn:population":0,
    "gn:timezone":"Europe/Minsk",
    "iso:country":"BY",
    "name:rus_x_preferred":[
        "\u041a\u0443\u0441\u0442\u043e\u0432\u043a\u0430"
    ],
    "wof:name":"Kustovka",
    "wof:placetype":"locality"
},
  "geometry": {"coordinates":[30.5954,54.3706],"type":"Point"}
}