{
  "type": "Feature",
  "properties": {
    "gn:admin1_code":"3.0",
    "gn:asciiname":"Tumashi",
    "gn:country_code":"BY",
    "gn:dem":128,
    "gn:feature_class":"P",
    "gn:feature_code":"PPL",
    "gn:name":"Tumashi",
    "gn:population":0,
    "gn:timezone":"Europe/Minsk",
    "iso:country":"BY",
    "name:bel_x_preferred":[
        "Tumashy"
    ],
    "name:bel_x_variant":[
        "\u0422\u0443\u043c\u0430\u0448\u044b"
    ],
    "name:rus_x_preferred":[
        "\u0422\u0443\u043c\u0430\u0448\u0438"
    ],
    "wof:name":"Tumashi",
    "wof:placetype":"locality"
},
  "geometry": {"coordinates":[24.9745,53.3047],"type":"Point"}
}