{
  "type": "Feature",
  "properties": {
    "gn:admin1_code":"7.0",
    "gn:asciiname":"Mayskoye",
    "gn:country_code":"BY",
    "gn:dem":211,
    "gn:feature_class":"P",
    "gn:feature_code":"PPL",
    "gn:name":"Mayskoye",
    "gn:population":0,
    "gn:timezone":"Europe/Minsk",
    "iso:country":"BY",
    "name:rus_x_preferred":[
        "\u041c\u0430\u0439\u0441\u043a\u043e\u0435"
    ],
    "wof:name":"Mayskoye",
    "wof:placetype":"locality"
},
  "geometry": {"coordinates":[30.0458,54.7349],"type":"Point"}
}