{
  "type": "Feature",
  "properties": {
    "gn:admin1_code":"6.0",
    "gn:asciiname":"Revut",
    "gn:country_code":"BY",
    "gn:dem":151,
    "gn:feature_class":"P",
    "gn:feature_code":"PPL",
    "gn:name":"Revut",
    "gn:population":0,
    "gn:timezone":"Europe/Minsk",
    "iso:country":"BY",
    "name:rus_x_preferred":[
        "\u0420\u0435\u0432\u0443\u0442"
    ],
    "name:und_x_variant":[
        "Rvut"
    ],
    "wof:name":"Revut",
    "wof:placetype":"locality"
},
  "geometry": {"coordinates":[31.903,53.6081],"type":"Point"}
}