{
  "type": "Feature",
  "properties": {
    "gn:admin1_code":"7.0",
    "gn:asciiname":"Belyany",
    "gn:country_code":"BY",
    "gn:dem":134,
    "gn:feature_class":"P",
    "gn:feature_code":"PPL",
    "gn:name":"Belyany",
    "gn:population":0,
    "gn:timezone":"Europe/Minsk",
    "iso:country":"BY",
    "name:rus_x_preferred":[
        "\u0411\u0435\u043b\u044f\u043d\u044b"
    ],
    "wof:name":"Belyany",
    "wof:placetype":"locality"
},
  "geometry": {"coordinates":[28.0562,55.5755],"type":"Point"}
}