{
  "type": "Feature",
  "properties": {
    "gn:admin1_code":"7.0",
    "gn:asciiname":"Rassolay",
    "gn:country_code":"BY",
    "gn:dem":141,
    "gn:feature_class":"P",
    "gn:feature_code":"PPL",
    "gn:name":"Rassolay",
    "gn:population":0,
    "gn:timezone":"Europe/Minsk",
    "iso:country":"BY",
    "name:rus_x_preferred":[
        "\u0420\u0430\u0441\u0441\u043e\u043b\u0430\u0439"
    ],
    "name:und_x_variant":[
        "Bol\u2019shoy Rassolay"
    ],
    "wof:name":"Rassolay",
    "wof:placetype":"locality"
},
  "geometry": {"coordinates":[29.3311,55.4508],"type":"Point"}
}