{
  "type": "Feature",
  "properties": {
    "gn:admin1_code":"3.0",
    "gn:asciiname":"Mateykovshchina",
    "gn:country_code":"BY",
    "gn:dem":165,
    "gn:feature_class":"P",
    "gn:feature_code":"PPL",
    "gn:name":"Mateykovshchina",
    "gn:population":0,
    "gn:timezone":"Europe/Minsk",
    "iso:country":"BY",
    "name:rus_x_preferred":[
        "\u041c\u0430\u0442\u0435\u0439\u043a\u043e\u0432\u0449\u0438\u043d\u0430"
    ],
    "wof:name":"Mateykovshchina",
    "wof:placetype":"locality"
},
  "geometry": {"coordinates":[24.123,53.2463],"type":"Point"}
}