{
  "type": "Feature",
  "properties": {
    "gn:admin1_code":"5.0",
    "gn:asciiname":"Bol'shaya Ganuta",
    "gn:country_code":"BY",
    "gn:dem":167,
    "gn:feature_class":"P",
    "gn:feature_code":"PPL",
    "gn:name":"Bol\u2019shaya Ganuta",
    "gn:population":0,
    "gn:timezone":"Europe/Minsk",
    "iso:country":"BY",
    "name:rus_x_preferred":[
        "\u0411\u043e\u043b\u044c\u0448\u0430\u044f \u0413\u0430\u043d\u0443\u0442\u0430"
    ],
    "name:und_x_variant":[
        "Bol\u2019shaya Ganuta"
    ],
    "wof:name":"Bol'shaya Ganuta",
    "wof:placetype":"locality"
},
  "geometry": {"coordinates":[28.7451,53.7062],"type":"Point"}
}