{
  "type": "Feature",
  "properties": {
    "gn:admin1_code":"6.0",
    "gn:asciiname":"Shipyagi",
    "gn:country_code":"BY",
    "gn:dem":187,
    "gn:feature_class":"P",
    "gn:feature_code":"PPL",
    "gn:name":"Shipyagi",
    "gn:population":0,
    "gn:timezone":"Europe/Minsk",
    "iso:country":"BY",
    "name:rus_x_preferred":[
        "\u0428\u0438\u043f\u044f\u0433\u0438"
    ],
    "wof:name":"Shipyagi",
    "wof:placetype":"locality"
},
  "geometry": {"coordinates":[29.6727,54.1179],"type":"Point"}
}