{
  "type": "Feature",
  "properties": {
    "gn:admin1_code":"7.0",
    "gn:asciiname":"Rudkovshchina",
    "gn:country_code":"BY",
    "gn:dem":163,
    "gn:feature_class":"P",
    "gn:feature_code":"PPL",
    "gn:name":"Rudkovshchina",
    "gn:population":0,
    "gn:timezone":"Europe/Minsk",
    "iso:country":"BY",
    "name:rus_x_preferred":[
        "\u0420\u0443\u0434\u043a\u043e\u0432\u0449\u0438\u043d\u0430"
    ],
    "wof:name":"Rudkovshchina",
    "wof:placetype":"locality"
},
  "geometry": {"coordinates":[29.9407,54.8406],"type":"Point"}
}