{
  "type": "Feature",
  "properties": {
    "gn:admin1_code":"7.0",
    "gn:asciiname":"Kemyantsy",
    "gn:country_code":"BY",
    "gn:dem":145,
    "gn:feature_class":"P",
    "gn:feature_code":"PPL",
    "gn:name":"Kemyantsy",
    "gn:population":0,
    "gn:timezone":"Europe/Minsk",
    "iso:country":"BY",
    "name:rus_x_preferred":[
        "\u041a\u0435\u043c\u044f\u043d\u0446\u044b"
    ],
    "wof:name":"Kemyantsy",
    "wof:placetype":"locality"
},
  "geometry": {"coordinates":[26.8754,55.5414],"type":"Point"}
}