{
  "type": "Feature",
  "properties": {
    "gn:admin1_code":"2.0",
    "gn:asciiname":"Sidaravichy",
    "gn:country_code":"BY",
    "gn:dem":144,
    "gn:feature_class":"P",
    "gn:feature_code":"PPL",
    "gn:name":"Sidaravichy",
    "gn:population":0,
    "gn:timezone":"Europe/Minsk",
    "iso:country":"BY",
    "name:bel_x_preferred":[
        "\u0421\u0456\u0434\u0430\u0440\u0430\u0432\u0456\u0447\u044b"
    ],
    "name:eng_x_preferred":[
        "Sidorovichi"
    ],
    "name:rus_x_preferred":[
        "\u0421\u0438\u0434\u043e\u0440\u043e\u0432\u0438\u0447\u0438"
    ],
    "name:und_x_variant":[
        "Sidorovichi",
        "Sidaravichy"
    ],
    "wof:name":"Sidaravichy",
    "wof:placetype":"locality"
},
  "geometry": {"coordinates":[31.1472,53.0399],"type":"Point"}
}