{
  "type": "Feature",
  "properties": {
    "gn:admin1_code":"1.0",
    "gn:asciiname":"Gitovichi",
    "gn:country_code":"BY",
    "gn:dem":144,
    "gn:feature_class":"P",
    "gn:feature_code":"PPL",
    "gn:name":"Gitovichi",
    "gn:population":0,
    "gn:timezone":"Europe/Minsk",
    "iso:country":"BY",
    "name:rus_x_preferred":[
        "\u0413\u0438\u0442\u043e\u0432\u0438\u0447\u0438"
    ],
    "wof:name":"Gitovichi",
    "wof:placetype":"locality"
},
  "geometry": {"coordinates":[23.8379,52.1741],"type":"Point"}
}