{
  "type": "Feature",
  "properties": {
    "gn:admin1_code":"3.0",
    "gn:asciiname":"Sinevichi",
    "gn:country_code":"BY",
    "gn:dem":92,
    "gn:feature_class":"P",
    "gn:feature_code":"PPL",
    "gn:name":"Sinevichi",
    "gn:population":0,
    "gn:timezone":"Europe/Minsk",
    "iso:country":"BY",
    "name:rus_x_preferred":[
        "\u0421\u0438\u043d\u0435\u0432\u0438\u0447\u0438"
    ],
    "name:und_x_variant":[
        "Sineviche",
        "Sinevichi"
    ],
    "wof:name":"Sinevichi",
    "wof:placetype":"locality"
},
  "geometry": {"coordinates":[23.7668,53.8912],"type":"Point"}
}