{
  "type": "Feature",
  "properties": {
    "gn:admin1_code":"5.0",
    "gn:asciiname":"Meleshkovichi",
    "gn:country_code":"BY",
    "gn:dem":165,
    "gn:feature_class":"P",
    "gn:feature_code":"PPL",
    "gn:name":"Meleshkovichi",
    "gn:population":0,
    "gn:timezone":"Europe/Minsk",
    "iso:country":"BY",
    "name:rus_x_preferred":[
        "\u041c\u0435\u043b\u0435\u0448\u043a\u043e\u0432\u0438\u0447\u0438"
    ],
    "wof:name":"Meleshkovichi",
    "wof:placetype":"locality"
},
  "geometry": {"coordinates":[29.0955,54.6361],"type":"Point"}
}