{
  "type": "Feature",
  "properties": {
    "gn:admin1_code":"2.0",
    "gn:asciiname":"Tramets",
    "gn:country_code":"BY",
    "gn:dem":131,
    "gn:feature_class":"P",
    "gn:feature_code":"PPL",
    "gn:name":"Tramets",
    "gn:population":0,
    "gn:timezone":"Europe/Minsk",
    "iso:country":"BY",
    "name:rus_x_preferred":[
        "\u0422\u0440\u0430\u043c\u0435\u0446"
    ],
    "wof:name":"Tramets",
    "wof:placetype":"locality"
},
  "geometry": {"coordinates":[29.0978,52.4761],"type":"Point"}
}