{
  "type": "Feature",
  "properties": {
    "gn:admin1_code":"5.0",
    "gn:asciiname":"Smolina",
    "gn:country_code":"BY",
    "gn:dem":186,
    "gn:feature_class":"P",
    "gn:feature_code":"PPL",
    "gn:name":"Smolina",
    "gn:population":0,
    "gn:timezone":"Europe/Minsk",
    "iso:country":"BY",
    "name:nld_x_preferred":[
        "Smolina"
    ],
    "name:pol_x_preferred":[
        "Smolina"
    ],
    "name:rus_x_preferred":[
        "\u0421\u043c\u043e\u043b\u0438\u043d\u0430"
    ],
    "wof:name":"Smolina",
    "wof:placetype":"locality"
},
  "geometry": {"coordinates":[28.1986,54.33],"type":"Point"}
}