{
  "type": "Feature",
  "properties": {
    "gn:admin1_code":"7.0",
    "gn:asciiname":"Yakimovtsy",
    "gn:country_code":"BY",
    "gn:dem":129,
    "gn:feature_class":"P",
    "gn:feature_code":"PPL",
    "gn:name":"Yakimovtsy",
    "gn:population":0,
    "gn:timezone":"Europe/Minsk",
    "iso:country":"BY",
    "name:rus_x_preferred":[
        "\u042f\u043a\u0438\u043c\u043e\u0432\u0446\u044b"
    ],
    "wof:name":"Yakimovtsy",
    "wof:placetype":"locality"
},
  "geometry": {"coordinates":[27.2643,55.2411],"type":"Point"}
}