{
  "type": "Feature",
  "properties": {
    "gn:admin1_code":"7.0",
    "gn:asciiname":"Tesishche",
    "gn:country_code":"BY",
    "gn:dem":179,
    "gn:feature_class":"P",
    "gn:feature_code":"PPL",
    "gn:name":"Tesishche",
    "gn:population":0,
    "gn:timezone":"Europe/Minsk",
    "iso:country":"BY",
    "name:rus_x_preferred":[
        "\u0422\u0435\u0441\u0438\u0449\u0435"
    ],
    "wof:name":"Tesishche",
    "wof:placetype":"locality"
},
  "geometry": {"coordinates":[29.8684,54.6925],"type":"Point"}
}