{
  "type": "Feature",
  "properties": {
    "gn:admin1_code":"7.0",
    "gn:asciiname":"Luchezarnaya",
    "gn:country_code":"BY",
    "gn:dem":159,
    "gn:feature_class":"P",
    "gn:feature_code":"PPL",
    "gn:name":"Luchezarnaya",
    "gn:population":0,
    "gn:timezone":"Europe/Minsk",
    "iso:country":"BY",
    "name:rus_x_preferred":[
        "\u041b\u0443\u0447\u0435\u0437\u0430\u0440\u043d\u0430\u044f"
    ],
    "wof:name":"Luchezarnaya",
    "wof:placetype":"locality"
},
  "geometry": {"coordinates":[30.2727,54.8311],"type":"Point"}
}