{
  "type": "Feature",
  "properties": {
    "gn:admin1_code":"3.0",
    "gn:asciiname":"Vasilevichi",
    "gn:country_code":"BY",
    "gn:dem":148,
    "gn:feature_class":"P",
    "gn:feature_code":"PPL",
    "gn:name":"Vasilevichi",
    "gn:population":0,
    "gn:timezone":"Europe/Minsk",
    "iso:country":"BY",
    "name:rus_x_preferred":[
        "\u0412\u0430\u0441\u0438\u043b\u0435\u0432\u0438\u0447\u0438"
    ],
    "wof:name":"Vasilevichi",
    "wof:placetype":"locality"
},
  "geometry": {"coordinates":[25.8003,54.0609],"type":"Point"}
}