{
  "type": "Feature",
  "properties": {
    "gn:admin1_code":"5.0",
    "gn:asciiname":"Terkhovichi",
    "gn:country_code":"BY",
    "gn:dem":201,
    "gn:feature_class":"P",
    "gn:feature_code":"PPL",
    "gn:name":"Terkhovichi",
    "gn:population":0,
    "gn:timezone":"Europe/Minsk",
    "iso:country":"BY",
    "name:rus_x_preferred":[
        "\u0422\u0435\u0440\u0445\u043e\u0432\u0438\u0447\u0438"
    ],
    "name:und_x_variant":[
        "Terechowicze",
        "Terekhovichi",
        "Terkhovichi"
    ],
    "wof:name":"Terkhovichi",
    "wof:placetype":"locality"
},
  "geometry": {"coordinates":[27.8439,54.2247],"type":"Point"}
}