{
  "type": "Feature",
  "properties": {
    "gn:admin1_code":"5.0",
    "gn:asciiname":"Poselok Bluzha",
    "gn:country_code":"BY",
    "gn:dem":161,
    "gn:feature_class":"P",
    "gn:feature_code":"PPL",
    "gn:name":"Pos\u00eblok Bluzha",
    "gn:population":0,
    "gn:timezone":"Europe/Minsk",
    "iso:country":"BY",
    "name:rus_x_preferred":[
        "\u041f\u043e\u0441\u0451\u043b\u043e\u043a \u0411\u043b\u0443\u0436\u0430"
    ],
    "name:und_x_variant":[
        "Pos\u00eblok Bluzha"
    ],
    "wof:name":"Poselok Bluzha",
    "wof:placetype":"locality"
},
  "geometry": {"coordinates":[28.2546,53.4066],"type":"Point"}
}