{
  "type": "Feature",
  "properties": {
    "gn:admin1_code":"7.0",
    "gn:asciiname":"Mazury",
    "gn:country_code":"BY",
    "gn:dem":132,
    "gn:feature_class":"P",
    "gn:feature_code":"PPL",
    "gn:name":"Mazury",
    "gn:population":0,
    "gn:timezone":"Europe/Minsk",
    "iso:country":"BY",
    "name:rus_x_preferred":[
        "\u041c\u0430\u0437\u0443\u0440\u044b"
    ],
    "wof:name":"Mazury",
    "wof:placetype":"locality"
},
  "geometry": {"coordinates":[29.5406,55.4245],"type":"Point"}
}