{
  "type": "Feature",
  "properties": {
    "gn:admin1_code":"2.0",
    "gn:asciiname":"Srednyaya Rudnya",
    "gn:country_code":"BY",
    "gn:dem":122,
    "gn:feature_class":"P",
    "gn:feature_code":"PPL",
    "gn:name":"Srednyaya Rudnya",
    "gn:population":0,
    "gn:timezone":"Europe/Minsk",
    "iso:country":"BY",
    "name:rus_x_preferred":[
        "\u0421\u0440\u0435\u0434\u043d\u044f\u044f \u0420\u0443\u0434\u043d\u044f"
    ],
    "wof:name":"Srednyaya Rudnya",
    "wof:placetype":"locality"
},
  "geometry": {"coordinates":[28.5512,52.1954],"type":"Point"}
}