{
  "type": "Feature",
  "properties": {
    "gn:admin1_code":"1.0",
    "gn:asciiname":"Plekhovo",
    "gn:country_code":"BY",
    "gn:dem":148,
    "gn:feature_class":"P",
    "gn:feature_code":"PPL",
    "gn:name":"Plekhovo",
    "gn:population":0,
    "gn:timezone":"Europe/Minsk",
    "iso:country":"BY",
    "name:rus_x_preferred":[
        "\u041f\u043b\u0435\u0445\u043e\u0432\u043e"
    ],
    "wof:name":"Plekhovo",
    "wof:placetype":"locality"
},
  "geometry": {"coordinates":[25.4349,52.7848],"type":"Point"}
}