{
  "type": "Feature",
  "properties": {
    "gn:admin1_code":"7.0",
    "gn:asciiname":"Ivyes'",
    "gn:country_code":"BY",
    "gn:dem":181,
    "gn:feature_class":"P",
    "gn:feature_code":"PPL",
    "gn:name":"Ivyes\u2019",
    "gn:population":0,
    "gn:timezone":"Europe/Minsk",
    "iso:country":"BY",
    "name:bel_x_preferred":[
        "\u0406\u0432\u0435\u0441\u044c"
    ],
    "name:und_x_variant":[
        "Ivyes\u2019"
    ],
    "wof:name":"Ivyes'",
    "wof:placetype":"locality"
},
  "geometry": {"coordinates":[28.2656,55.1858],"type":"Point"}
}