{
  "type": "Feature",
  "properties": {
    "gn:admin1_code":"5.0",
    "gn:asciiname":"Vayhany",
    "gn:country_code":"BY",
    "gn:dem":188,
    "gn:feature_class":"P",
    "gn:feature_code":"PPL",
    "gn:name":"Vayhany",
    "gn:population":0,
    "gn:timezone":"Europe/Minsk",
    "iso:country":"BY",
    "name:bel_x_preferred":[
        "\u0412\u0430\u0439\u0433\u0430\u043d\u044b"
    ],
    "name:und_x_variant":[
        "Voygany"
    ],
    "wof:name":"Vayhany",
    "wof:placetype":"locality"
},
  "geometry": {"coordinates":[26.0909,54.1648],"type":"Point"}
}