{
  "type": "Feature",
  "properties": {
    "gn:admin1_code":"7.0",
    "gn:asciiname":"Bagrinovo",
    "gn:country_code":"BY",
    "gn:dem":182,
    "gn:feature_class":"P",
    "gn:feature_code":"PPL",
    "gn:name":"Bagrinovo",
    "gn:population":0,
    "gn:timezone":"Europe/Minsk",
    "iso:country":"BY",
    "name:rus_x_preferred":[
        "\u0411\u0430\u0433\u0440\u0438\u043d\u043e\u0432\u043e"
    ],
    "wof:name":"Bagrinovo",
    "wof:placetype":"locality"
},
  "geometry": {"coordinates":[30.3093,54.5835],"type":"Point"}
}