{
  "type": "Feature",
  "properties": {
    "gn:admin1_code":"7.0",
    "gn:asciiname":"Zakharni",
    "gn:country_code":"BY",
    "gn:dem":136,
    "gn:feature_class":"P",
    "gn:feature_code":"PPL",
    "gn:name":"Zakharni",
    "gn:population":0,
    "gn:timezone":"Europe/Minsk",
    "iso:country":"BY",
    "name:rus_x_preferred":[
        "\u0417\u0430\u0445\u0430\u0440\u043d\u0438"
    ],
    "wof:name":"Zakharni",
    "wof:placetype":"locality"
},
  "geometry": {"coordinates":[27.7309,55.6515],"type":"Point"}
}