{
  "type": "Feature",
  "properties": {
    "gn:admin1_code":"6.0",
    "gn:asciiname":"Zhukovka",
    "gn:country_code":"BY",
    "gn:dem":167,
    "gn:feature_class":"P",
    "gn:feature_code":"PPL",
    "gn:name":"Zhukovka",
    "gn:population":0,
    "gn:timezone":"Europe/Minsk",
    "iso:country":"BY",
    "name:rus_x_preferred":[
        "\u0416\u0443\u043a\u043e\u0432\u043a\u0430"
    ],
    "wof:name":"Zhukovka",
    "wof:placetype":"locality"
},
  "geometry": {"coordinates":[32.1117,53.0892],"type":"Point"}
}