{
  "type": "Feature",
  "properties": {
    "gn:admin1_code":"3.0",
    "gn:asciiname":"Kupry",
    "gn:country_code":"BY",
    "gn:dem":167,
    "gn:feature_class":"P",
    "gn:feature_code":"PPL",
    "gn:name":"Kupry",
    "gn:population":0,
    "gn:timezone":"Europe/Minsk",
    "iso:country":"BY",
    "name:rus_x_preferred":[
        "\u041a\u0443\u043f\u0440\u044b"
    ],
    "wof:name":"Kupry",
    "wof:placetype":"locality"
},
  "geometry": {"coordinates":[24.90032,53.57867],"type":"Point"}
}