{
  "type": "Feature",
  "properties": {
    "gn:admin1_code":"3.0",
    "gn:asciiname":"Yaroshichi",
    "gn:country_code":"BY",
    "gn:dem":221,
    "gn:feature_class":"P",
    "gn:feature_code":"PPL",
    "gn:name":"Yaroshichi",
    "gn:population":0,
    "gn:timezone":"Europe/Minsk",
    "iso:country":"BY",
    "name:bel_x_preferred":[
        "Yaroshychy"
    ],
    "name:bel_x_variant":[
        "\u042f\u0440\u043e\u0448\u044b\u0447\u044b"
    ],
    "name:rus_x_preferred":[
        "\u042f\u0440\u043e\u0448\u0438\u0447\u0438"
    ],
    "wof:name":"Yaroshichi",
    "wof:placetype":"locality"
},
  "geometry": {"coordinates":[25.8685,53.4465],"type":"Point"}
}