{
  "type": "Feature",
  "properties": {
    "gn:admin1_code":"6.0",
    "gn:asciiname":"Zaselech'ye",
    "gn:country_code":"BY",
    "gn:dem":156,
    "gn:feature_class":"P",
    "gn:feature_code":"PPL",
    "gn:name":"Zaselech\u2019ye",
    "gn:population":0,
    "gn:timezone":"Europe/Minsk",
    "iso:country":"BY",
    "name:rus_x_preferred":[
        "\u0417\u0430\u0441\u0435\u043b\u0435\u0447\u044c\u0435"
    ],
    "name:und_x_variant":[
        "Zaselech\u2019ye"
    ],
    "wof:name":"Zaselech'ye",
    "wof:placetype":"locality"
},
  "geometry": {"coordinates":[28.7891,53.2565],"type":"Point"}
}