{
  "type": "Feature",
  "properties": {
    "gn:admin1_code":"7.0",
    "gn:asciiname":"Poluyanovo",
    "gn:country_code":"BY",
    "gn:dem":240,
    "gn:feature_class":"P",
    "gn:feature_code":"PPL",
    "gn:name":"Poluyanovo",
    "gn:population":0,
    "gn:timezone":"Europe/Minsk",
    "iso:country":"BY",
    "name:rus_x_preferred":[
        "\u041f\u043e\u043b\u0443\u044f\u043d\u043e\u0432\u043e"
    ],
    "wof:name":"Poluyanovo",
    "wof:placetype":"locality"
},
  "geometry": {"coordinates":[30.0515,55.6047],"type":"Point"}
}