{
  "type": "Feature",
  "properties": {
    "gn:admin1_code":"5.0",
    "gn:asciiname":"Gorodishche",
    "gn:country_code":"BY",
    "gn:dem":178,
    "gn:feature_class":"P",
    "gn:feature_code":"PPL",
    "gn:name":"Gorodishche",
    "gn:population":0,
    "gn:timezone":"Europe/Minsk",
    "iso:country":"BY",
    "name:rus_x_preferred":[
        "\u0413\u043e\u0440\u043e\u0434\u0438\u0449\u0435"
    ],
    "wof:name":"Gorodishche",
    "wof:placetype":"locality"
},
  "geometry": {"coordinates":[28.1065,53.688],"type":"Point"}
}