{
  "type": "Feature",
  "properties": {
    "gn:admin1_code":"5.0",
    "gn:asciiname":"Andriyevshchina",
    "gn:country_code":"BY",
    "gn:dem":186,
    "gn:feature_class":"P",
    "gn:feature_code":"PPL",
    "gn:name":"Andriyevshchina",
    "gn:population":0,
    "gn:timezone":"Europe/Minsk",
    "iso:country":"BY",
    "name:rus_x_preferred":[
        "\u0410\u043d\u0434\u0440\u0438\u0435\u0432\u0449\u0438\u043d\u0430"
    ],
    "wof:name":"Andriyevshchina",
    "wof:placetype":"locality"
},
  "geometry": {"coordinates":[26.9605,53.6404],"type":"Point"}
}