{
  "type": "Feature",
  "properties": {
    "gn:admin1_code":"7.0",
    "gn:asciiname":"Padruksha",
    "gn:country_code":"BY",
    "gn:dem":140,
    "gn:feature_class":"P",
    "gn:feature_code":"PPL",
    "gn:name":"Padruksha",
    "gn:population":0,
    "gn:timezone":"Europe/Minsk",
    "iso:country":"BY",
    "name:bel_x_preferred":[
        "\u041f\u0430\u0434\u0440\u0443\u043a\u0448\u0430"
    ],
    "name:und_x_variant":[
        "Podruksha"
    ],
    "wof:name":"Padruksha",
    "wof:placetype":"locality"
},
  "geometry": {"coordinates":[26.7084,55.4521],"type":"Point"}
}