{
  "type": "Feature",
  "properties": {
    "gn:admin1_code":"1.0",
    "gn:asciiname":"Zasimy",
    "gn:country_code":"BY",
    "gn:dem":153,
    "gn:feature_class":"P",
    "gn:feature_code":"PPL",
    "gn:name":"Zasimy",
    "gn:population":0,
    "gn:timezone":"Europe/Minsk",
    "iso:country":"BY",
    "name:rus_x_preferred":[
        "\u0417\u0430\u0441\u0438\u043c\u044b"
    ],
    "name:und_x_variant":[
        "Zosimy"
    ],
    "wof:name":"Zasimy",
    "wof:placetype":"locality"
},
  "geometry": {"coordinates":[24.3493,52.4758],"type":"Point"}
}