{
  "type": "Feature",
  "properties": {
    "gn:admin1_code":"1.0",
    "gn:asciiname":"Slonimtsy",
    "gn:country_code":"BY",
    "gn:dem":156,
    "gn:feature_class":"P",
    "gn:feature_code":"PPL",
    "gn:name":"Slonimtsy",
    "gn:population":0,
    "gn:timezone":"Europe/Minsk",
    "iso:country":"BY",
    "name:rus_x_preferred":[
        "\u0421\u043b\u043e\u043d\u0438\u043c\u0446\u044b"
    ],
    "name:und_x_variant":[
        "Slonimtse",
        "Slonimtsy"
    ],
    "wof:name":"Slonimtsy",
    "wof:placetype":"locality"
},
  "geometry": {"coordinates":[24.487,52.5332],"type":"Point"}
}