{
  "type": "Feature",
  "properties": {
    "gn:admin1_code":"3.0",
    "gn:asciiname":"Vishnevichi",
    "gn:country_code":"BY",
    "gn:dem":176,
    "gn:feature_class":"P",
    "gn:feature_code":"PPL",
    "gn:name":"Vishn\u00ebvichi",
    "gn:population":0,
    "gn:timezone":"Europe/Minsk",
    "iso:country":"BY",
    "name:rus_x_preferred":[
        "\u0412\u0438\u0448\u043d\u0451\u0432\u0438\u0447\u0438"
    ],
    "name:und_x_variant":[
        "Vishn\u00ebvichi"
    ],
    "wof:name":"Vishnevichi",
    "wof:placetype":"locality"
},
  "geometry": {"coordinates":[24.3234,53.1864],"type":"Point"}
}