{
  "type": "Feature",
  "properties": {
    "gn:admin1_code":"5.0",
    "gn:asciiname":"Moshchenka",
    "gn:country_code":"BY",
    "gn:dem":249,
    "gn:feature_class":"P",
    "gn:feature_code":"PPL",
    "gn:name":"Moshchenka",
    "gn:population":0,
    "gn:timezone":"Europe/Minsk",
    "iso:country":"BY",
    "name:rus_x_preferred":[
        "\u041c\u043e\u0449\u0435\u043d\u043a\u0430"
    ],
    "wof:name":"Moshchenka",
    "wof:placetype":"locality"
},
  "geometry": {"coordinates":[27.7566,54.1326],"type":"Point"}
}