{
  "type": "Feature",
  "properties": {
    "gn:admin1_code":"1.0",
    "gn:asciiname":"Izin",
    "gn:country_code":"BY",
    "gn:dem":137,
    "gn:feature_class":"P",
    "gn:feature_code":"PPL",
    "gn:name":"Izin",
    "gn:population":0,
    "gn:timezone":"Europe/Minsk",
    "iso:country":"BY",
    "name:rus_x_preferred":[
        "\u0418\u0437\u0438\u043d"
    ],
    "wof:name":"Izin",
    "wof:placetype":"locality"
},
  "geometry": {"coordinates":[25.9238,52.0492],"type":"Point"}
}