{
  "type": "Feature",
  "properties": {
    "gn:admin1_code":"5.0",
    "gn:asciiname":"Dumichi",
    "gn:country_code":"BY",
    "gn:dem":171,
    "gn:feature_class":"P",
    "gn:feature_code":"PPL",
    "gn:name":"Dumichi",
    "gn:population":0,
    "gn:timezone":"Europe/Minsk",
    "iso:country":"BY",
    "name:rus_x_preferred":[
        "\u0414\u0443\u043c\u0438\u0447\u0438"
    ],
    "wof:name":"Dumichi",
    "wof:placetype":"locality"
},
  "geometry": {"coordinates":[27.0771,53.2418],"type":"Point"}
}