{
  "type": "Feature",
  "properties": {
    "gn:admin1_code":"5.0",
    "gn:asciiname":"Gruzdovka",
    "gn:country_code":"BY",
    "gn:dem":194,
    "gn:feature_class":"P",
    "gn:feature_code":"PPL",
    "gn:name":"Gruzdovka",
    "gn:population":0,
    "gn:timezone":"Europe/Minsk",
    "iso:country":"BY",
    "name:rus_x_preferred":[
        "\u0413\u0440\u0443\u0437\u0434\u043e\u0432\u043a\u0430"
    ],
    "wof:name":"Gruzdovka",
    "wof:placetype":"locality"
},
  "geometry": {"coordinates":[26.7462,54.2334],"type":"Point"}
}