{
  "type": "Feature",
  "properties": {
    "gn:admin1_code":"7.0",
    "gn:asciiname":"Kelesy",
    "gn:country_code":"BY",
    "gn:dem":160,
    "gn:feature_class":"P",
    "gn:feature_code":"PPL",
    "gn:name":"Kelesy",
    "gn:population":0,
    "gn:timezone":"Europe/Minsk",
    "iso:country":"BY",
    "name:rus_x_preferred":[
        "\u041a\u0435\u043b\u0435\u0441\u044b"
    ],
    "name:und_x_variant":[
        "Kelisy"
    ],
    "wof:name":"Kelesy",
    "wof:placetype":"locality"
},
  "geometry": {"coordinates":[29.8835,54.8104],"type":"Point"}
}