{
  "type": "Feature",
  "properties": {
    "gn:admin1_code":"2.0",
    "gn:asciiname":"Yubileynyy",
    "gn:country_code":"BY",
    "gn:dem":123,
    "gn:feature_class":"P",
    "gn:feature_code":"PPL",
    "gn:name":"Yubileynyy",
    "gn:population":0,
    "gn:timezone":"Europe/Minsk",
    "iso:country":"BY",
    "name:rus_x_preferred":[
        "\u042e\u0431\u0438\u043b\u0435\u0439\u043d\u044b\u0439"
    ],
    "wof:name":"Yubileynyy",
    "wof:placetype":"locality"
},
  "geometry": {"coordinates":[31.0915,52.3953],"type":"Point"}
}