{
  "type": "Feature",
  "properties": {
    "gn:admin1_code":"6.0",
    "gn:asciiname":"Pralyetarskaye",
    "gn:country_code":"BY",
    "gn:dem":177,
    "gn:feature_class":"P",
    "gn:feature_code":"PPL",
    "gn:name":"Pralyetarskaye",
    "gn:population":0,
    "gn:timezone":"Europe/Minsk",
    "iso:country":"BY",
    "name:bel_x_preferred":[
        "\u041f\u0440\u0430\u043b\u0435\u0442\u0430\u0440\u0441\u043a\u0430\u0435"
    ],
    "name:eng_x_preferred":[
        "Proletarskoye"
    ],
    "name:rus_x_preferred":[
        "\u041f\u0440\u043e\u043b\u0435\u0442\u0430\u0440\u0441\u043a\u043e\u0435"
    ],
    "name:und_x_variant":[
        "Tserkovishe",
        "Tserkovishche",
        "Proletarskoye",
        "Pralyetarskaye"
    ],
    "wof:name":"Pralyetarskaye",
    "wof:placetype":"locality"
},
  "geometry": {"coordinates":[32.1197,53.4257],"type":"Point"}
}