{
  "type": "Feature",
  "properties": {
    "gn:admin1_code":"6.0",
    "gn:asciiname":"Zamyshki",
    "gn:country_code":"BY",
    "gn:dem":189,
    "gn:feature_class":"P",
    "gn:feature_code":"PPL",
    "gn:name":"Zamyshki",
    "gn:population":0,
    "gn:timezone":"Europe/Minsk",
    "iso:country":"BY",
    "name:rus_x_preferred":[
        "\u0417\u0430\u043c\u044b\u0448\u043a\u0438"
    ],
    "wof:name":"Zamyshki",
    "wof:placetype":"locality"
},
  "geometry": {"coordinates":[29.8196,54.3179],"type":"Point"}
}