{
  "type": "Feature",
  "properties": {
    "gn:admin1_code":"5.0",
    "gn:asciiname":"Kraysk",
    "gn:country_code":"BY",
    "gn:dem":191,
    "gn:feature_class":"P",
    "gn:feature_code":"PPL",
    "gn:name":"Kraysk",
    "gn:population":0,
    "gn:timezone":"Europe/Minsk",
    "iso:country":"BY",
    "name:bel_x_preferred":[
        "\u041a\u0440\u0430\u0439\u0441\u043a"
    ],
    "wof:name":"Kraysk",
    "wof:placetype":"locality"
},
  "geometry": {"coordinates":[27.5023,54.5196],"type":"Point"}
}