{
  "type": "Feature",
  "properties": {
    "gn:admin1_code":"7.0",
    "gn:asciiname":"Sporuny",
    "gn:country_code":"BY",
    "gn:dem":166,
    "gn:feature_class":"P",
    "gn:feature_code":"PPL",
    "gn:name":"Sporuny",
    "gn:population":0,
    "gn:timezone":"Europe/Minsk",
    "iso:country":"BY",
    "name:rus_x_preferred":[
        "\u0421\u043f\u043e\u0440\u0443\u043d\u044b"
    ],
    "wof:name":"Sporuny",
    "wof:placetype":"locality"
},
  "geometry": {"coordinates":[27.2022,55.5648],"type":"Point"}
}