{
  "type": "Feature",
  "properties": {
    "gn:admin1_code":"7.0",
    "gn:asciiname":"Babakhino",
    "gn:country_code":"BY",
    "gn:dem":205,
    "gn:feature_class":"P",
    "gn:feature_code":"PPL",
    "gn:name":"Babakhino",
    "gn:population":0,
    "gn:timezone":"Europe/Minsk",
    "iso:country":"BY",
    "name:rus_x_preferred":[
        "\u0411\u0430\u0431\u0430\u0445\u0438\u043d\u043e"
    ],
    "wof:name":"Babakhino",
    "wof:placetype":"locality"
},
  "geometry": {"coordinates":[30.1278,55.581],"type":"Point"}
}