{
  "type": "Feature",
  "properties": {
    "gn:admin1_code":"6.0",
    "gn:asciiname":"Novoandreyevka",
    "gn:country_code":"BY",
    "gn:dem":139,
    "gn:feature_class":"P",
    "gn:feature_code":"PPL",
    "gn:name":"Novoandreyevka",
    "gn:population":0,
    "gn:timezone":"Europe/Minsk",
    "iso:country":"BY",
    "name:rus_x_preferred":[
        "\u041d\u043e\u0432\u043e\u0430\u043d\u0434\u0440\u0435\u0435\u0432\u043a\u0430"
    ],
    "wof:name":"Novoandreyevka",
    "wof:placetype":"locality"
},
  "geometry": {"coordinates":[28.5813,52.8183],"type":"Point"}
}