{
  "type": "Feature",
  "properties": {
    "gn:admin1_code":"3.0",
    "gn:asciiname":"Cherepki",
    "gn:country_code":"BY",
    "gn:dem":168,
    "gn:feature_class":"P",
    "gn:feature_code":"PPL",
    "gn:name":"Cherepki",
    "gn:population":0,
    "gn:timezone":"Europe/Minsk",
    "iso:country":"BY",
    "name:rus_x_preferred":[
        "\u0427\u0435\u0440\u0435\u043f\u043a\u0438"
    ],
    "wof:name":"Cherepki",
    "wof:placetype":"locality"
},
  "geometry": {"coordinates":[24.3758,52.9221],"type":"Point"}
}