{
  "type": "Feature",
  "properties": {
    "gn:admin1_code":"6.0",
    "gn:asciiname":"Priles'ye",
    "gn:country_code":"BY",
    "gn:dem":165,
    "gn:feature_class":"P",
    "gn:feature_code":"PPL",
    "gn:name":"Priles\u2019ye",
    "gn:population":0,
    "gn:timezone":"Europe/Minsk",
    "iso:country":"BY",
    "name:rus_x_preferred":[
        "\u041f\u0440\u0438\u043b\u0435\u0441\u044c\u0435"
    ],
    "name:und_x_variant":[
        "Priles\u2019ye"
    ],
    "wof:name":"Priles'ye",
    "wof:placetype":"locality"
},
  "geometry": {"coordinates":[31.1751,53.8128],"type":"Point"}
}