{
  "type": "Feature",
  "properties": {
    "gn:admin1_code":"7.0",
    "gn:asciiname":"Mnyukhi",
    "gn:country_code":"BY",
    "gn:dem":138,
    "gn:feature_class":"P",
    "gn:feature_code":"PPL",
    "gn:name":"Mnyukhi",
    "gn:population":0,
    "gn:timezone":"Europe/Minsk",
    "iso:country":"BY",
    "name:rus_x_preferred":[
        "\u041c\u043d\u044e\u0445\u0438"
    ],
    "name:und_x_variant":[
        "Mniuchy",
        "Mnyukhy",
        "Mnyukhi"
    ],
    "wof:name":"Mnyukhi",
    "wof:placetype":"locality"
},
  "geometry": {"coordinates":[27.7769,55.5852],"type":"Point"}
}