{
  "type": "Feature",
  "properties": {
    "gn:admin1_code":"6.0",
    "gn:asciiname":"Derazhnya",
    "gn:country_code":"BY",
    "gn:dem":147,
    "gn:feature_class":"P",
    "gn:feature_code":"PPL",
    "gn:name":"Derazhnya",
    "gn:population":0,
    "gn:timezone":"Europe/Minsk",
    "iso:country":"BY",
    "name:rus_x_preferred":[
        "\u0414\u0435\u0440\u0430\u0436\u043d\u044f"
    ],
    "wof:name":"Derazhnya",
    "wof:placetype":"locality"
},
  "geometry": {"coordinates":[31.8804,53.3095],"type":"Point"}
}