{
  "type": "Feature",
  "properties": {
    "gn:admin1_code":"7.0",
    "gn:asciiname":"Subochi",
    "gn:country_code":"BY",
    "gn:dem":182,
    "gn:feature_class":"P",
    "gn:feature_code":"PPL",
    "gn:name":"Subochi",
    "gn:population":0,
    "gn:timezone":"Europe/Minsk",
    "iso:country":"BY",
    "name:rus_x_preferred":[
        "\u0421\u0443\u0431\u043e\u0447\u0438"
    ],
    "wof:name":"Subochi",
    "wof:placetype":"locality"
},
  "geometry": {"coordinates":[26.4535,55.0398],"type":"Point"}
}