{
  "type": "Feature",
  "properties": {
    "gn:admin1_code":"2.0",
    "gn:asciiname":"Novyy Krupets",
    "gn:country_code":"BY",
    "gn:dem":147,
    "gn:feature_class":"P",
    "gn:feature_code":"PPL",
    "gn:name":"Novyy Krupets",
    "gn:population":0,
    "gn:timezone":"Europe/Minsk",
    "iso:country":"BY",
    "name:rus_x_preferred":[
        "\u041d\u043e\u0432\u044b\u0439 \u041a\u0440\u0443\u043f\u0435\u0446"
    ],
    "name:und_x_variant":[
        "Novy Krupets",
        "Novyy Krupets"
    ],
    "wof:name":"Novyy Krupets",
    "wof:placetype":"locality"
},
  "geometry": {"coordinates":[31.365,52.3367],"type":"Point"}
}