{
  "type": "Feature",
  "properties": {
    "gn:admin1_code":"3.0",
    "gn:asciiname":"Paviloyti",
    "gn:country_code":"BY",
    "gn:dem":281,
    "gn:feature_class":"P",
    "gn:feature_code":"PPL",
    "gn:name":"Paviloyti",
    "gn:population":0,
    "gn:timezone":"Europe/Minsk",
    "iso:country":"BY",
    "name:rus_x_preferred":[
        "\u041f\u0430\u0432\u0438\u043b\u043e\u0439\u0442\u0438"
    ],
    "wof:name":"Paviloyti",
    "wof:placetype":"locality"
},
  "geometry": {"coordinates":[25.7722,54.31800000000001],"type":"Point"}
}