{
  "type": "Feature",
  "properties": {
    "gn:admin1_code":"1.0",
    "gn:asciiname":"Dastoyeva",
    "gn:country_code":"BY",
    "gn:dem":151,
    "gn:feature_class":"P",
    "gn:feature_code":"PPL",
    "gn:name":"Dastoyeva",
    "gn:population":0,
    "gn:timezone":"Europe/Minsk",
    "iso:country":"BY",
    "name:bel_x_preferred":[
        "\u0414\u0430\u0441\u0442\u043e\u0435\u0432\u0430"
    ],
    "name:eng_x_preferred":[
        "Dostoyevo"
    ],
    "name:rus_x_preferred":[
        "\u0414\u043e\u0441\u0442\u043e\u0435\u0432\u043e"
    ],
    "name:und_x_variant":[
        "Dastoyeva"
    ],
    "wof:name":"Dastoyeva",
    "wof:placetype":"locality"
},
  "geometry": {"coordinates":[25.6811,52.232],"type":"Point"}
}