{
  "type": "Feature",
  "properties": {
    "gn:admin1_code":"1.0",
    "gn:asciiname":"Malyye Shchitniki",
    "gn:country_code":"BY",
    "gn:dem":143,
    "gn:feature_class":"P",
    "gn:feature_code":"PPL",
    "gn:name":"Malyye Shchitniki",
    "gn:population":0,
    "gn:timezone":"Europe/Minsk",
    "iso:country":"BY",
    "name:rus_x_preferred":[
        "\u041c\u0430\u043b\u044b\u0435 \u0429\u0438\u0442\u043d\u0438\u043a\u0438"
    ],
    "wof:name":"Malyye Shchitniki",
    "wof:placetype":"locality"
},
  "geometry": {"coordinates":[23.4963,52.2335],"type":"Point"}
}