{
  "type": "Feature",
  "properties": {
    "gn:admin1_code":"1.0",
    "gn:asciiname":"Malyye Doropeyevichi",
    "gn:country_code":"BY",
    "gn:dem":150,
    "gn:feature_class":"P",
    "gn:feature_code":"PPL",
    "gn:name":"Malyye Doropeyevichi",
    "gn:population":0,
    "gn:timezone":"Europe/Minsk",
    "iso:country":"BY",
    "name:rus_x_preferred":[
        "\u041c\u0430\u043b\u044b\u0435 \u0414\u043e\u0440\u043e\u043f\u0435\u0435\u0432\u0438\u0447\u0438"
    ],
    "wof:name":"Malyye Doropeyevichi",
    "wof:placetype":"locality"
},
  "geometry": {"coordinates":[24.3366,51.9565],"type":"Point"}
}