{
  "type": "Feature",
  "properties": {
    "gn:admin1_code":"7.0",
    "gn:asciiname":"Martsyukhova",
    "gn:country_code":"BY",
    "gn:dem":227,
    "gn:feature_class":"P",
    "gn:feature_code":"PPL",
    "gn:name":"Martsyukhova",
    "gn:population":0,
    "gn:timezone":"Europe/Minsk",
    "iso:country":"BY",
    "name:bel_x_preferred":[
        "\u041c\u0430\u0440\u0446\u044e\u0445\u043e\u0432\u0430"
    ],
    "name:und_x_variant":[
        "Martyukhovo"
    ],
    "wof:name":"Martsyukhova",
    "wof:placetype":"locality"
},
  "geometry": {"coordinates":[29.9685,54.4894],"type":"Point"}
}