{
  "type": "Feature",
  "properties": {
    "gn:admin1_code":"3.0",
    "gn:asciiname":"Olenets",
    "gn:country_code":"BY",
    "gn:dem":146,
    "gn:feature_class":"P",
    "gn:feature_code":"PPL",
    "gn:name":"Olenets",
    "gn:population":0,
    "gn:timezone":"Europe/Minsk",
    "iso:country":"BY",
    "name:rus_x_preferred":[
        "\u041e\u043b\u0435\u043d\u0435\u0446"
    ],
    "name:und_x_variant":[
        "Oleniec",
        "Olenets"
    ],
    "wof:name":"Olenets",
    "wof:placetype":"locality"
},
  "geometry": {"coordinates":[26.5774,54.4206],"type":"Point"}
}