{
  "type": "Feature",
  "properties": {
    "gn:admin1_code":"6.0",
    "gn:asciiname":"Dal'niy",
    "gn:country_code":"BY",
    "gn:dem":167,
    "gn:feature_class":"P",
    "gn:feature_code":"PPL",
    "gn:name":"Dal\u2019niy",
    "gn:population":0,
    "gn:timezone":"Europe/Minsk",
    "iso:country":"BY",
    "name:rus_x_preferred":[
        "\u0414\u0430\u043b\u044c\u043d\u0438\u0439"
    ],
    "name:und_x_variant":[
        "Dal\u2019niy"
    ],
    "wof:name":"Dal'niy",
    "wof:placetype":"locality"
},
  "geometry": {"coordinates":[29.6688,53.7836],"type":"Point"}
}