{
  "type": "Feature",
  "properties": {
    "gn:admin1_code":"5.0",
    "gn:asciiname":"Korenishetsy",
    "gn:country_code":"BY",
    "gn:dem":182,
    "gn:feature_class":"P",
    "gn:feature_code":"PPL",
    "gn:name":"Korenishetsy",
    "gn:population":0,
    "gn:timezone":"Europe/Minsk",
    "iso:country":"BY",
    "name:rus_x_preferred":[
        "\u041a\u043e\u0440\u0435\u043d\u0438\u0448\u0435\u0446\u044b"
    ],
    "name:und_x_variant":[
        "Koreniszcze",
        "Korenishche",
        "Korenishetsy"
    ],
    "wof:name":"Korenishetsy",
    "wof:placetype":"locality"
},
  "geometry": {"coordinates":[27.2657,54.737],"type":"Point"}
}