{
  "type": "Feature",
  "properties": {
    "gn:admin1_code":"2.0",
    "gn:asciiname":"Charot",
    "gn:country_code":"BY",
    "gn:dem":143,
    "gn:feature_class":"P",
    "gn:feature_code":"PPL",
    "gn:name":"Charot",
    "gn:population":0,
    "gn:timezone":"Europe/Minsk",
    "iso:country":"BY",
    "name:rus_x_preferred":[
        "\u0427\u0430\u0440\u043e\u0442"
    ],
    "wof:name":"Charot",
    "wof:placetype":"locality"
},
  "geometry": {"coordinates":[30.6507,52.6809],"type":"Point"}
}