{
  "type": "Feature",
  "properties": {
    "gn:admin1_code":"1.0",
    "gn:asciiname":"Padkraichy",
    "gn:country_code":"BY",
    "gn:dem":155,
    "gn:feature_class":"P",
    "gn:feature_code":"PPL",
    "gn:name":"Padkraichy",
    "gn:population":0,
    "gn:timezone":"Europe/Minsk",
    "iso:country":"BY",
    "name:bel_x_preferred":[
        "\u041f\u0430\u0434\u043a\u0440\u0430\u0456\u0447\u044b"
    ],
    "name:und_x_variant":[
        "Podkraiche",
        "Podkraichi",
        "Podkraychi",
        "Padkraichy"
    ],
    "wof:name":"Padkraichy",
    "wof:placetype":"locality"
},
  "geometry": {"coordinates":[24.7158,52.4343],"type":"Point"}
}