{
  "type": "Feature",
  "properties": {
    "gn:admin1_code":"7.0",
    "gn:asciiname":"Promyshlyada",
    "gn:country_code":"BY",
    "gn:dem":136,
    "gn:feature_class":"P",
    "gn:feature_code":"PPL",
    "gn:name":"Promyshlyada",
    "gn:population":0,
    "gn:timezone":"Europe/Minsk",
    "iso:country":"BY",
    "name:rus_x_preferred":[
        "\u041f\u0440\u043e\u043c\u044b\u0448\u043b\u044f\u0434\u0430"
    ],
    "wof:name":"Promyshlyada",
    "wof:placetype":"locality"
},
  "geometry": {"coordinates":[27.0034,55.1805],"type":"Point"}
}