{
  "type": "Feature",
  "properties": {
    "gn:admin1_code":"3.0",
    "gn:asciiname":"Zagornyata",
    "gn:country_code":"BY",
    "gn:dem":210,
    "gn:feature_class":"P",
    "gn:feature_code":"PPL",
    "gn:name":"Zagornyata",
    "gn:population":0,
    "gn:timezone":"Europe/Minsk",
    "iso:country":"BY",
    "name:rus_x_preferred":[
        "\u0417\u0430\u0433\u043e\u0440\u043d\u044f\u0442\u0430"
    ],
    "wof:name":"Zagornyata",
    "wof:placetype":"locality"
},
  "geometry": {"coordinates":[26.1523,54.2983],"type":"Point"}
}