{
  "type": "Feature",
  "properties": {
    "gn:admin1_code":"5.0",
    "gn:asciiname":"Grud",
    "gn:country_code":"BY",
    "gn:dem":165,
    "gn:feature_class":"P",
    "gn:feature_code":"PPL",
    "gn:name":"Grud",
    "gn:population":0,
    "gn:timezone":"Europe/Minsk",
    "iso:country":"BY",
    "name:rus_x_preferred":[
        "\u0413\u0440\u0443\u0434"
    ],
    "name:und_x_variant":[
        "Novyy Grud"
    ],
    "wof:name":"Grud",
    "wof:placetype":"locality"
},
  "geometry": {"coordinates":[28.0235,53.597],"type":"Point"}
}