{
  "type": "Feature",
  "properties": {
    "gn:admin1_code":"1.0",
    "gn:asciiname":"Yamichno",
    "gn:country_code":"BY",
    "gn:dem":163,
    "gn:feature_class":"P",
    "gn:feature_code":"PPL",
    "gn:name":"Yamichno",
    "gn:population":0,
    "gn:timezone":"Europe/Minsk",
    "iso:country":"BY",
    "name:rus_x_preferred":[
        "\u042f\u043c\u0438\u0447\u043d\u043e"
    ],
    "name:und_x_variant":[
        "Jamiczna",
        "Jamiczno",
        "Yamichno"
    ],
    "wof:name":"Yamichno",
    "wof:placetype":"locality"
},
  "geometry": {"coordinates":[25.7427,52.8822],"type":"Point"}
}