{
  "type": "Feature",
  "properties": {
    "gn:admin1_code":"3.0",
    "gn:asciiname":"Kunevichi",
    "gn:country_code":"BY",
    "gn:dem":207,
    "gn:feature_class":"P",
    "gn:feature_code":"PPL",
    "gn:name":"Kun\u00ebvichi",
    "gn:population":0,
    "gn:timezone":"Europe/Minsk",
    "iso:country":"BY",
    "name:rus_x_preferred":[
        "\u041a\u0443\u043d\u0451\u0432\u0438\u0447\u0438"
    ],
    "name:und_x_variant":[
        "Kun\u00ebvichi"
    ],
    "wof:name":"Kunevichi",
    "wof:placetype":"locality"
},
  "geometry": {"coordinates":[26.0567,53.3777],"type":"Point"}
}