{
  "type": "Feature",
  "properties": {
    "gn:admin1_code":"7.0",
    "gn:asciiname":"Mnyuta Druhoye",
    "gn:country_code":"BY",
    "gn:dem":159,
    "gn:feature_class":"P",
    "gn:feature_code":"PPL",
    "gn:name":"Mnyuta Druhoye",
    "gn:population":0,
    "gn:timezone":"Europe/Minsk",
    "iso:country":"BY",
    "name:bel_x_preferred":[
        "\u041c\u043d\u044e\u0442\u0430 \u0414\u0440\u0443\u0433\u043e\u0435"
    ],
    "name:und_x_variant":[
        "Mnyuto Drugoye"
    ],
    "wof:name":"Mnyuta Druhoye",
    "wof:placetype":"locality"
},
  "geometry": {"coordinates":[27.9537,55.2578],"type":"Point"}
}