{
  "type": "Feature",
  "properties": {
    "gn:admin1_code":"3.0",
    "gn:asciiname":"Hnyezna",
    "gn:country_code":"BY",
    "gn:dem":144,
    "gn:feature_class":"P",
    "gn:feature_code":"PPL",
    "gn:name":"Hnyezna",
    "gn:population":500,
    "gn:timezone":"Europe/Minsk",
    "iso:country":"BY",
    "name:bel_x_preferred":[
        "\u0413\u043d\u0435\u0437\u043d\u0430"
    ],
    "name:rus_x_preferred":[
        "\u0413\u043d\u0435\u0437\u043d\u043e"
    ],
    "name:und_x_variant":[
        "Gnezno",
        "Hniezno",
        "Gnezdovo",
        "Hnyezna"
    ],
    "wof:name":"Hnyezna",
    "wof:placetype":"locality",
    "wof:population":500
},
  "geometry": {"coordinates":[24.3421,53.1243],"type":"Point"}
}