{
  "type": "Feature",
  "properties": {
    "gn:admin1_code":"3.0",
    "gn:asciiname":"Bogudenka",
    "gn:country_code":"BY",
    "gn:dem":253,
    "gn:feature_class":"P",
    "gn:feature_code":"PPL",
    "gn:name":"Bogudenka",
    "gn:population":0,
    "gn:timezone":"Europe/Minsk",
    "iso:country":"BY",
    "name:bel_x_preferred":[
        "Bahudzyenka"
    ],
    "name:bel_x_variant":[
        "\u0411\u0430\u0433\u0443\u0434\u0437\u0435\u043d\u043a\u0430"
    ],
    "name:rus_x_preferred":[
        "\u0411\u043e\u0433\u0443\u0434\u0435\u043d\u043a\u0430"
    ],
    "wof:name":"Bogudenka",
    "wof:placetype":"locality"
},
  "geometry": {"coordinates":[25.8273,53.4781],"type":"Point"}
}