{
  "type": "Feature",
  "properties": {
    "gn:admin1_code":"5.0",
    "gn:asciiname":"Komora",
    "gn:country_code":"BY",
    "gn:dem":156,
    "gn:feature_class":"P",
    "gn:feature_code":"PPL",
    "gn:name":"Komora",
    "gn:population":0,
    "gn:timezone":"Europe/Minsk",
    "iso:country":"BY",
    "name:bos_x_preferred":[
        "Komora"
    ],
    "name:hrv_x_preferred":[
        "Komora"
    ],
    "name:hun_x_preferred":[
        "Komora"
    ],
    "name:nld_x_preferred":[
        "Komora"
    ],
    "name:rus_x_preferred":[
        "\u041a\u043e\u043c\u043e\u0440\u0430"
    ],
    "name:slv_x_preferred":[
        "Komora"
    ],
    "name:spa_x_preferred":[
        "Komora"
    ],
    "name:srp_x_preferred":[
        "\u041a\u043e\u043c\u043e\u0440\u0430"
    ],
    "name:ukr_x_preferred":[
        "\u041a\u043e\u043c\u043e\u0440\u0430"
    ],
    "wof:name":"Komora",
    "wof:placetype":"locality"
},
  "geometry": {"coordinates":[27.7177,53.0584],"type":"Point"}
}