{
  "type": "Feature",
  "properties": {
    "gn:admin1_code":"3.0",
    "gn:asciiname":"Mal'kavichy",
    "gn:country_code":"BY",
    "gn:dem":121,
    "gn:feature_class":"P",
    "gn:feature_code":"PPL",
    "gn:name":"Mal\u2019kavichy",
    "gn:population":0,
    "gn:timezone":"Europe/Minsk",
    "iso:country":"BY",
    "name:bel_x_preferred":[
        "\u041c\u0430\u043b\u044c\u043a\u0430\u0432\u0456\u0447\u0456"
    ],
    "name:rus_x_preferred":[
        "Mal\u2019kovichi"
    ],
    "name:rus_x_variant":[
        "\u041c\u0430\u043b\u044c\u043a\u043e\u0432\u0438\u0447\u0438"
    ],
    "name:und_x_variant":[
        "Malkiewicze",
        "Mal\u2019kevichi",
        "Mal\u2019kavichy"
    ],
    "wof:name":"Mal'kavichy",
    "wof:placetype":"locality"
},
  "geometry": {"coordinates":[24.8024,53.3983],"type":"Point"}
}