{
  "type": "Feature",
  "properties": {
    "gn:admin1_code":"5.0",
    "gn:asciiname":"Briyalevo",
    "gn:country_code":"BY",
    "gn:dem":170,
    "gn:feature_class":"P",
    "gn:feature_code":"PPL",
    "gn:name":"Briyalevo",
    "gn:population":0,
    "gn:timezone":"Europe/Minsk",
    "iso:country":"BY",
    "name:rus_x_preferred":[
        "\u0411\u0440\u0438\u044f\u043b\u0435\u0432\u043e"
    ],
    "name:und_x_variant":[
        "Brialevo"
    ],
    "wof:name":"Briyalevo",
    "wof:placetype":"locality"
},
  "geometry": {"coordinates":[28.8833,53.8615],"type":"Point"}
}