{
  "type": "Feature",
  "properties": {
    "gn:admin1_code":"2.0",
    "gn:asciiname":"Poselok Gorochichskiy",
    "gn:country_code":"BY",
    "gn:dem":137,
    "gn:feature_class":"P",
    "gn:feature_code":"PPL",
    "gn:name":"Pos\u00eblok Gorochichskiy",
    "gn:population":0,
    "gn:timezone":"Europe/Minsk",
    "iso:country":"BY",
    "name:rus_x_preferred":[
        "\u041f\u043e\u0441\u0451\u043b\u043e\u043a \u0413\u043e\u0440\u043e\u0447\u0438\u0447\u0441\u043a\u0438\u0439"
    ],
    "name:und_x_variant":[
        "Pos\u00eblok Gorochichskiy"
    ],
    "wof:name":"Poselok Gorochichskiy",
    "wof:placetype":"locality"
},
  "geometry": {"coordinates":[29.423,52.2701],"type":"Point"}
}