{
  "type": "Feature",
  "properties": {
    "gn:admin1_code":"3.0",
    "gn:asciiname":"Girdevka",
    "gn:country_code":"BY",
    "gn:dem":165,
    "gn:feature_class":"P",
    "gn:feature_code":"PPL",
    "gn:name":"Girdevka",
    "gn:population":0,
    "gn:timezone":"Europe/Minsk",
    "iso:country":"BY",
    "name:bel_x_preferred":[
        "Hirdzyewka"
    ],
    "name:bel_x_variant":[
        "\u0413\u0456\u0440\u0434\u0437\u0435\u045e\u043a\u0430"
    ],
    "name:rus_x_preferred":[
        "\u0413\u0438\u0440\u0434\u0435\u0432\u043a\u0430"
    ],
    "wof:name":"Girdevka",
    "wof:placetype":"locality"
},
  "geometry": {"coordinates":[24.7551,53.5637],"type":"Point"}
}