{
  "type": "Feature",
  "properties": {
    "gn:admin1_code":"7.0",
    "gn:asciiname":"Goryani",
    "gn:country_code":"BY",
    "gn:dem":139,
    "gn:feature_class":"P",
    "gn:feature_code":"PPL",
    "gn:name":"Goryani",
    "gn:population":0,
    "gn:timezone":"Europe/Minsk",
    "iso:country":"BY",
    "name:rus_x_preferred":[
        "\u0413\u043e\u0440\u044f\u043d\u0438"
    ],
    "wof:name":"Goryani",
    "wof:placetype":"locality"
},
  "geometry": {"coordinates":[29.1716,55.1056],"type":"Point"}
}