{
  "type": "Feature",
  "properties": {
    "gn:admin1_code":"7.0",
    "gn:asciiname":"Goryani",
    "gn:country_code":"BY",
    "gn:dem":139,
    "gn:feature_class":"P",
    "gn:feature_code":"PPL",
    "gn:name":"Goryani",
    "gn:population":0,
    "gn:timezone":"Europe/Minsk",
    "iso:country":"BY",
    "name:bul_x_preferred":[
        "\u0413\u043e\u0440\u044f\u043d\u0441\u043a\u043e \u0434\u0432\u0438\u0436\u0435\u043d\u0438\u0435"
    ],
    "name:rus_x_preferred":[
        "\u0413\u043e\u0440\u044f\u043d\u0438"
    ],
    "name:rus_x_variant":[
        "\u0413\u043e\u0440\u044f\u043d\u0441\u043a\u043e\u0435 \u0434\u0432\u0438\u0436\u0435\u043d\u0438\u0435"
    ],
    "name:ukr_x_preferred":[
        "\u0413\u043e\u0440\u044f\u043d\u0441\u044c\u043a\u0438\u0439 \u0440\u0443\u0445"
    ],
    "wof:name":"Goryani",
    "wof:placetype":"locality"
},
  "geometry": {"coordinates":[29.1716,55.1056],"type":"Point"}
}