{
  "type": "Feature",
  "properties": {
    "gn:admin1_code":"7.0",
    "gn:asciiname":"Kudyany",
    "gn:country_code":"BY",
    "gn:dem":143,
    "gn:feature_class":"P",
    "gn:feature_code":"PPL",
    "gn:name":"Kudyany",
    "gn:population":0,
    "gn:timezone":"Europe/Minsk",
    "iso:country":"BY",
    "name:rus_x_preferred":[
        "\u041a\u0443\u0434\u044f\u043d\u044b"
    ],
    "wof:name":"Kudyany",
    "wof:placetype":"locality"
},
  "geometry": {"coordinates":[29.7842,55.053],"type":"Point"}
}