{
  "type": "Feature",
  "properties": {
    "gn:admin1_code":"1.0",
    "gn:asciiname":"Bogushi",
    "gn:country_code":"BY",
    "gn:dem":166,
    "gn:feature_class":"P",
    "gn:feature_code":"PPL",
    "gn:name":"Bogushi",
    "gn:population":0,
    "gn:timezone":"Europe/Minsk",
    "iso:country":"BY",
    "name:rus_x_preferred":[
        "\u0411\u043e\u0433\u0443\u0448\u0438"
    ],
    "name:und_x_variant":[
        "Bogushe",
        "Bogushi"
    ],
    "wof:name":"Bogushi",
    "wof:placetype":"locality"
},
  "geometry": {"coordinates":[25.9574,52.9924],"type":"Point"}
}