{
  "type": "Feature",
  "properties": {
    "gn:admin1_code":"7.0",
    "gn:asciiname":"Pavlyuchenki",
    "gn:country_code":"BY",
    "gn:dem":149,
    "gn:feature_class":"P",
    "gn:feature_code":"PPL",
    "gn:name":"Pavlyuchenki",
    "gn:population":0,
    "gn:timezone":"Europe/Minsk",
    "iso:country":"BY",
    "name:rus_x_preferred":[
        "\u041f\u0430\u0432\u043b\u044e\u0447\u0435\u043d\u043a\u0438"
    ],
    "wof:name":"Pavlyuchenki",
    "wof:placetype":"locality"
},
  "geometry": {"coordinates":[30.244,55.1086],"type":"Point"}
}