{
  "type": "Feature",
  "properties": {
    "gn:admin1_code":"7.0",
    "gn:asciiname":"Konnyy Bor",
    "gn:country_code":"BY",
    "gn:dem":145,
    "gn:feature_class":"P",
    "gn:feature_code":"PPL",
    "gn:name":"Konnyy Bor",
    "gn:population":0,
    "gn:timezone":"Europe/Minsk",
    "iso:country":"BY",
    "name:rus_x_preferred":[
        "\u041a\u043e\u043d\u043d\u044b\u0439 \u0411\u043e\u0440"
    ],
    "wof:name":"Konnyy Bor",
    "wof:placetype":"locality"
},
  "geometry": {"coordinates":[29.0827,55.679],"type":"Point"}
}