{
  "type": "Feature",
  "properties": {
    "gn:admin1_code":"0.0",
    "gn:asciiname":"Ostrovy",
    "gn:country_code":"BY",
    "gn:dem":148,
    "gn:feature_class":"P",
    "gn:feature_code":"PPL",
    "gn:name":"Ostrovy",
    "gn:population":0,
    "gn:timezone":"Europe/Minsk",
    "iso:country":"BY",
    "name:und_x_variant":[
        "Repishchi",
        "Ostrovy"
    ],
    "wof:name":"Ostrovy",
    "wof:placetype":"locality"
},
  "geometry": {"coordinates":[30.74064000000001,52.90947],"type":"Point"}
}