{
  "type": "Feature",
  "properties": {
    "gn:admin1_code":"3.0",
    "gn:asciiname":"Dudichi",
    "gn:country_code":"BY",
    "gn:dem":162,
    "gn:feature_class":"P",
    "gn:feature_code":"PPL",
    "gn:name":"Dudichi",
    "gn:population":0,
    "gn:timezone":"Europe/Minsk",
    "iso:country":"BY",
    "name:rus_x_preferred":[
        "\u0414\u0443\u0434\u0438\u0447\u0438"
    ],
    "name:und_x_variant":[
        "Dudziche",
        "Dudichi"
    ],
    "wof:name":"Dudichi",
    "wof:placetype":"locality"
},
  "geometry": {"coordinates":[24.1068,53.0759],"type":"Point"}
}