{
  "type": "Feature",
  "properties": {
    "gn:admin1_code":"6.0",
    "gn:asciiname":"Yelenovka",
    "gn:country_code":"BY",
    "gn:dem":167,
    "gn:feature_class":"P",
    "gn:feature_code":"PPL",
    "gn:name":"Yel\u00ebnovka",
    "gn:population":0,
    "gn:timezone":"Europe/Minsk",
    "iso:country":"BY",
    "name:aze_x_preferred":[
        "Yelenovka"
    ],
    "name:rus_x_preferred":[
        "\u0415\u043b\u0451\u043d\u043e\u0432\u043a\u0430"
    ],
    "name:und_x_variant":[
        "Yel\u00ebnovka"
    ],
    "wof:name":"Yelenovka",
    "wof:placetype":"locality"
},
  "geometry": {"coordinates":[32.323,53.2287],"type":"Point"}
}