{
  "type": "Feature",
  "properties": {
    "gn:admin1_code":"7.0",
    "gn:asciiname":"Krasnobel'",
    "gn:country_code":"BY",
    "gn:dem":173,
    "gn:feature_class":"P",
    "gn:feature_code":"PPL",
    "gn:name":"Krasnobel\u2019",
    "gn:population":0,
    "gn:timezone":"Europe/Minsk",
    "iso:country":"BY",
    "name:rus_x_preferred":[
        "\u041a\u0440\u0430\u0441\u043d\u043e\u0431\u0435\u043b\u044c"
    ],
    "name:und_x_variant":[
        "Krasnobel\u2019"
    ],
    "wof:name":"Krasnobel'",
    "wof:placetype":"locality"
},
  "geometry": {"coordinates":[30.57,54.7174],"type":"Point"}
}