{
  "type": "Feature",
  "properties": {
    "gn:admin1_code":"6.0",
    "gn:asciiname":"Malyatsichy",
    "gn:country_code":"BY",
    "gn:dem":175,
    "gn:feature_class":"P",
    "gn:feature_code":"PPL",
    "gn:name":"Malyatsichy",
    "gn:population":0,
    "gn:timezone":"Europe/Minsk",
    "iso:country":"BY",
    "name:bel_x_preferred":[
        "\u041c\u0430\u043b\u044f\u0446\u0456\u0447\u044b"
    ],
    "name:eng_x_preferred":[
        "Molyatichi"
    ],
    "name:rus_x_preferred":[
        "\u041c\u043e\u043b\u044f\u0442\u0438\u0447\u0438"
    ],
    "name:und_x_variant":[
        "Malyatichi",
        "Molyatichki",
        "Molyatichi",
        "Malyatsichy"
    ],
    "wof:name":"Malyatsichy",
    "wof:placetype":"locality"
},
  "geometry": {"coordinates":[31.5422,53.8571],"type":"Point"}
}