{
  "type": "Feature",
  "properties": {
    "gn:admin1_code":"6.0",
    "gn:asciiname":"Dosova Seliba",
    "gn:country_code":"BY",
    "gn:dem":153,
    "gn:feature_class":"P",
    "gn:feature_code":"PPL",
    "gn:name":"Dosova Seliba",
    "gn:population":0,
    "gn:timezone":"Europe/Minsk",
    "iso:country":"BY",
    "name:rus_x_preferred":[
        "\u0414\u043e\u0441\u043e\u0432\u0430 \u0421\u0435\u043b\u0438\u0431\u0430"
    ],
    "wof:name":"Dosova Seliba",
    "wof:placetype":"locality"
},
  "geometry": {"coordinates":[30.1417,53.7299],"type":"Point"}
}