{
  "type": "Feature",
  "properties": {
    "gn:admin1_code":"7.0",
    "gn:asciiname":"Mikhalovo",
    "gn:country_code":"BY",
    "gn:dem":174,
    "gn:feature_class":"P",
    "gn:feature_code":"PPL",
    "gn:name":"Mikhalovo",
    "gn:population":0,
    "gn:timezone":"Europe/Minsk",
    "iso:country":"BY",
    "name:rus_x_preferred":[
        "\u041c\u0438\u0445\u0430\u043b\u043e\u0432\u043e"
    ],
    "wof:name":"Mikhalovo",
    "wof:placetype":"locality"
},
  "geometry": {"coordinates":[28.8004,54.6454],"type":"Point"}
}