{
  "type": "Feature",
  "properties": {
    "gn:admin1_code":"7.0",
    "gn:asciiname":"Korovo",
    "gn:country_code":"BY",
    "gn:dem":200,
    "gn:feature_class":"P",
    "gn:feature_code":"PPL",
    "gn:name":"Korovo",
    "gn:population":0,
    "gn:timezone":"Europe/Minsk",
    "iso:country":"BY",
    "name:rus_x_preferred":[
        "\u041a\u043e\u0440\u043e\u0432\u043e"
    ],
    "name:und_x_variant":[
        "Korevo"
    ],
    "wof:name":"Korovo",
    "wof:placetype":"locality"
},
  "geometry": {"coordinates":[30.318,54.5676],"type":"Point"}
}