{
  "type": "Feature",
  "properties": {
    "gn:admin1_code":"6.0",
    "gn:asciiname":"Kisyalyova Buda",
    "gn:country_code":"BY",
    "gn:dem":187,
    "gn:feature_class":"P",
    "gn:feature_code":"PPL",
    "gn:name":"Kisyalyova Buda",
    "gn:population":0,
    "gn:timezone":"Europe/Minsk",
    "iso:country":"BY",
    "name:bel_x_preferred":[
        "\u041a\u0456\u0441\u044f\u043b\u0451\u0432\u0430 \u0411\u0443\u0434\u0430"
    ],
    "name:und_x_variant":[
        "Yanova Buda",
        "Kisel\u00ebva Buda",
        "Kisyalyova Buda"
    ],
    "wof:name":"Kisyalyova Buda",
    "wof:placetype":"locality"
},
  "geometry": {"coordinates":[32.1262,53.7226],"type":"Point"}
}