{
  "type": "Feature",
  "properties": {
    "gn:admin1_code":"3.0",
    "gn:asciiname":"Lishki",
    "gn:country_code":"BY",
    "gn:dem":126,
    "gn:feature_class":"P",
    "gn:feature_code":"PPL",
    "gn:name":"Lishki",
    "gn:population":0,
    "gn:timezone":"Europe/Minsk",
    "iso:country":"BY",
    "name:fas_x_preferred":[
        "\u0644\u06cc\u0634\u06a9\u06cc"
    ],
    "name:msa_x_preferred":[
        "Lishki"
    ],
    "name:rus_x_preferred":[
        "\u041b\u0438\u0448\u043a\u0438"
    ],
    "name:ukr_x_preferred":[
        "\u041b\u0456\u0448\u043a\u0456"
    ],
    "wof:name":"Lishki",
    "wof:placetype":"locality"
},
  "geometry": {"coordinates":[23.8374,53.2959],"type":"Point"}
}