{
  "type": "Feature",
  "properties": {
    "gn:admin1_code":"6.0",
    "gn:asciiname":"Pislyatino",
    "gn:country_code":"BY",
    "gn:dem":184,
    "gn:feature_class":"P",
    "gn:feature_code":"PPL",
    "gn:name":"Pislyatino",
    "gn:population":0,
    "gn:timezone":"Europe/Minsk",
    "iso:country":"BY",
    "name:rus_x_preferred":[
        "\u041f\u0438\u0441\u043b\u044f\u0442\u0438\u043d\u043e"
    ],
    "name:und_x_variant":[
        "Pislyatin"
    ],
    "wof:name":"Pislyatino",
    "wof:placetype":"locality"
},
  "geometry": {"coordinates":[32.3268,53.5524],"type":"Point"}
}