{
  "type": "Feature",
  "properties": {
    "gn:admin1_code":"6.0",
    "gn:asciiname":"Vydrenka",
    "gn:country_code":"BY",
    "gn:dem":149,
    "gn:feature_class":"P",
    "gn:feature_code":"PPL",
    "gn:name":"Vydrenka",
    "gn:population":0,
    "gn:timezone":"Europe/Minsk",
    "iso:country":"BY",
    "name:eng_x_preferred":[
        "Vydrenka"
    ],
    "name:rus_x_preferred":[
        "\u0412\u044b\u0434\u0440\u0435\u043d\u043a\u0430"
    ],
    "name:und_x_variant":[
        "Vydrinka",
        "Vydrenka"
    ],
    "wof:name":"Vydrenka",
    "wof:placetype":"locality"
},
  "geometry": {"coordinates":[31.3027,53.132],"type":"Point"}
}