{
  "type": "Feature",
  "properties": {
    "gn:admin1_code":"3.0",
    "gn:asciiname":"Dubrovniki",
    "gn:country_code":"BY",
    "gn:dem":195,
    "gn:feature_class":"P",
    "gn:feature_code":"PPL",
    "gn:name":"Dubrovniki",
    "gn:population":0,
    "gn:timezone":"Europe/Minsk",
    "iso:country":"BY",
    "name:bel_x_preferred":[
        "Dubrowniki"
    ],
    "name:bel_x_variant":[
        "\u0414\u0443\u0431\u0440\u043e\u045e\u043d\u0456\u043a\u0456"
    ],
    "name:rus_x_preferred":[
        "\u0414\u0443\u0431\u0440\u043e\u0432\u043d\u0438\u043a\u0438"
    ],
    "wof:name":"Dubrovniki",
    "wof:placetype":"locality"
},
  "geometry": {"coordinates":[24.6699,53.0387],"type":"Point"}
}