{
  "type": "Feature",
  "properties": {
    "gn:admin1_code":"7.0",
    "gn:asciiname":"Zaozernaya",
    "gn:country_code":"BY",
    "gn:dem":134,
    "gn:feature_class":"P",
    "gn:feature_code":"PPL",
    "gn:name":"Zaoz\u00ebrnaya",
    "gn:population":0,
    "gn:timezone":"Europe/Minsk",
    "iso:country":"BY",
    "name:rus_x_preferred":[
        "\u0417\u0430\u043e\u0437\u0451\u0440\u043d\u0430\u044f"
    ],
    "name:und_x_variant":[
        "Zaoz\u00ebrnaya"
    ],
    "wof:name":"Zaozernaya",
    "wof:placetype":"locality"
},
  "geometry": {"coordinates":[28.9271,55.0873],"type":"Point"}
}