{
  "type": "Feature",
  "properties": {
    "gn:admin1_code":"7.0",
    "gn:asciiname":"Kulakovo",
    "gn:country_code":"BY",
    "gn:dem":157,
    "gn:feature_class":"P",
    "gn:feature_code":"PPL",
    "gn:name":"Kulakovo",
    "gn:population":0,
    "gn:timezone":"Europe/Minsk",
    "iso:country":"BY",
    "name:rus_x_preferred":[
        "\u041a\u0443\u043b\u0430\u043a\u043e\u0432\u043e"
    ],
    "wof:name":"Kulakovo",
    "wof:placetype":"locality"
},
  "geometry": {"coordinates":[30.4704,55.4106],"type":"Point"}
}