{
  "type": "Feature",
  "properties": {
    "gn:admin1_code":"7.0",
    "gn:asciiname":"Safonovo",
    "gn:country_code":"BY",
    "gn:dem":125,
    "gn:feature_class":"P",
    "gn:feature_code":"PPL",
    "gn:name":"Safonovo",
    "gn:population":0,
    "gn:timezone":"Europe/Minsk",
    "iso:country":"BY",
    "name:bel_x_preferred":[
        "\u0421\u0430\u0444\u043e\u043d\u0430\u0432\u0430"
    ],
    "name:ceb_x_preferred":[
        "Safonovo"
    ],
    "name:ces_x_preferred":[
        "Safonovo"
    ],
    "name:deu_x_preferred":[
        "Safonowo"
    ],
    "name:ita_x_preferred":[
        "Safonovo"
    ],
    "name:nld_x_preferred":[
        "Safonovo"
    ],
    "name:rus_x_preferred":[
        "\u0421\u0430\u0444\u043e\u043d\u043e\u0432\u043e"
    ],
    "name:tat_x_preferred":[
        "\u0421\u0430\u0444\u043e\u043d\u043e\u0432\u043e"
    ],
    "wof:name":"Safonovo",
    "wof:placetype":"locality"
},
  "geometry": {"coordinates":[28.1701,55.7476],"type":"Point"}
}