{
  "type": "Feature",
  "properties": {
    "gn:admin1_code":"5.0",
    "gn:asciiname":"Tesny",
    "gn:country_code":"BY",
    "gn:dem":169,
    "gn:feature_class":"P",
    "gn:feature_code":"PPL",
    "gn:name":"T\u00ebsny",
    "gn:population":0,
    "gn:timezone":"Europe/Minsk",
    "iso:country":"BY",
    "name:rus_x_preferred":[
        "\u0422\u0451\u0441\u043d\u044b"
    ],
    "name:und_x_variant":[
        "T\u00ebsny"
    ],
    "wof:name":"Tesny",
    "wof:placetype":"locality"
},
  "geometry": {"coordinates":[27.2138,54.2811],"type":"Point"}
}