{
  "type": "Feature",
  "properties": {
    "gn:admin1_code":"7.0",
    "gn:asciiname":"Novoye Rtishchevo",
    "gn:country_code":"BY",
    "gn:dem":217,
    "gn:feature_class":"P",
    "gn:feature_code":"PPL",
    "gn:name":"Novoye Rtishchevo",
    "gn:population":0,
    "gn:timezone":"Europe/Minsk",
    "iso:country":"BY",
    "name:rus_x_preferred":[
        "\u041d\u043e\u0432\u043e\u0435 \u0420\u0442\u0438\u0449\u0435\u0432\u043e"
    ],
    "wof:name":"Novoye Rtishchevo",
    "wof:placetype":"locality"
},
  "geometry": {"coordinates":[29.9591,54.4344],"type":"Point"}
}