{
  "type": "Feature",
  "properties": {
    "gn:admin1_code":"2.0",
    "gn:asciiname":"Novyye Katsury",
    "gn:country_code":"BY",
    "gn:dem":117,
    "gn:feature_class":"P",
    "gn:feature_code":"PPL",
    "gn:name":"Novyye Katsury",
    "gn:population":0,
    "gn:timezone":"Europe/Minsk",
    "iso:country":"BY",
    "name:rus_x_preferred":[
        "\u041d\u043e\u0432\u044b\u0435 \u041a\u0430\u0446\u0443\u0440\u0438"
    ],
    "wof:name":"Novyye Katsury",
    "wof:placetype":"locality"
},
  "geometry": {"coordinates":[28.9813,52.1964],"type":"Point"}
}