{
  "type": "Feature",
  "properties": {
    "gn:admin1_code":"7.0",
    "gn:asciiname":"Moski",
    "gn:country_code":"BY",
    "gn:dem":113,
    "gn:feature_class":"P",
    "gn:feature_code":"PPL",
    "gn:name":"Moski",
    "gn:population":0,
    "gn:timezone":"Europe/Minsk",
    "iso:country":"BY",
    "name:rus_x_preferred":[
        "\u041c\u043e\u0441\u043a\u0438"
    ],
    "wof:name":"Moski",
    "wof:placetype":"locality"
},
  "geometry": {"coordinates":[28.5479,55.5489],"type":"Point"}
}