{
  "type": "Feature",
  "properties": {
    "gn:admin1_code":"1.0",
    "gn:asciiname":"Khaby",
    "gn:country_code":"BY",
    "gn:dem":137,
    "gn:feature_class":"P",
    "gn:feature_code":"PPL",
    "gn:name":"Khaby",
    "gn:population":0,
    "gn:timezone":"Europe/Minsk",
    "iso:country":"BY",
    "name:rus_x_preferred":[
        "\u0425\u0430\u0431\u044b"
    ],
    "name:und_x_variant":[
        "Chaby",
        "Khaby"
    ],
    "wof:name":"Khaby",
    "wof:placetype":"locality"
},
  "geometry": {"coordinates":[23.91,52.1331],"type":"Point"}
}