{
  "type": "Feature",
  "properties": {
    "gn:admin1_code":"6.0",
    "gn:asciiname":"Skrubilovka",
    "gn:country_code":"BY",
    "gn:dem":201,
    "gn:feature_class":"P",
    "gn:feature_code":"PPL",
    "gn:name":"Skrubilovka",
    "gn:population":0,
    "gn:timezone":"Europe/Minsk",
    "iso:country":"BY",
    "name:rus_x_preferred":[
        "\u0421\u043a\u0440\u0443\u0431\u0438\u043b\u043e\u0432\u043a\u0430"
    ],
    "wof:name":"Skrubilovka",
    "wof:placetype":"locality"
},
  "geometry": {"coordinates":[30.1439,54.1002],"type":"Point"}
}