{
  "type": "Feature",
  "properties": {
    "gn:admin1_code":"5.0",
    "gn:asciiname":"Repishche",
    "gn:country_code":"BY",
    "gn:dem":181,
    "gn:feature_class":"P",
    "gn:feature_code":"PPL",
    "gn:name":"Repishche",
    "gn:population":0,
    "gn:timezone":"Europe/Minsk",
    "iso:country":"BY",
    "name:rus_x_preferred":[
        "\u0420\u0435\u043f\u0438\u0449\u0435"
    ],
    "wof:name":"Repishche",
    "wof:placetype":"locality"
},
  "geometry": {"coordinates":[28.5032,53.8524],"type":"Point"}
}