{
  "type": "Feature",
  "properties": {
    "gn:admin1_code":"7.0",
    "gn:asciiname":"Sipovichi",
    "gn:country_code":"BY",
    "gn:dem":141,
    "gn:feature_class":"P",
    "gn:feature_code":"PPL",
    "gn:name":"Sipovichi",
    "gn:population":0,
    "gn:timezone":"Europe/Minsk",
    "iso:country":"BY",
    "name:rus_x_preferred":[
        "\u0421\u0438\u043f\u043e\u0432\u0438\u0447\u0438"
    ],
    "name:und_x_variant":[
        "Sipoviche",
        "Sipowicze",
        "Sipovichi"
    ],
    "wof:name":"Sipovichi",
    "wof:placetype":"locality"
},
  "geometry": {"coordinates":[26.7572,55.4288],"type":"Point"}
}