{
  "type": "Feature",
  "properties": {
    "gn:admin1_code":"3.0",
    "gn:asciiname":"Murav'evka",
    "gn:country_code":"BY",
    "gn:dem":153,
    "gn:feature_class":"P",
    "gn:feature_code":"PPL",
    "gn:name":"Murav\u2019\u00ebvka",
    "gn:population":0,
    "gn:timezone":"Europe/Minsk",
    "iso:country":"BY",
    "name:rus_x_preferred":[
        "\u041c\u0443\u0440\u0430\u0432\u044c\u0451\u0432\u043a\u0430"
    ],
    "name:und_x_variant":[
        "Murav\u2019\u00ebvka"
    ],
    "wof:name":"Murav'evka",
    "wof:placetype":"locality"
},
  "geometry": {"coordinates":[24.6247,53.6409],"type":"Point"}
}