{
  "type": "Feature",
  "properties": {
    "gn:admin1_code":"5.0",
    "gn:asciiname":"Chereyevka",
    "gn:country_code":"BY",
    "gn:dem":183,
    "gn:feature_class":"P",
    "gn:feature_code":"PPL",
    "gn:name":"Cherey\u00ebvka",
    "gn:population":0,
    "gn:timezone":"Europe/Minsk",
    "iso:country":"BY",
    "name:rus_x_preferred":[
        "\u0427\u0435\u0440\u0435\u0451\u0432\u043a\u0430"
    ],
    "name:und_x_variant":[
        "Cherey\u00ebvka"
    ],
    "wof:name":"Chereyevka",
    "wof:placetype":"locality"
},
  "geometry": {"coordinates":[29.232,54.5715],"type":"Point"}
}