{
  "type": "Feature",
  "properties": {
    "gn:admin1_code":"5.0",
    "gn:asciiname":"Dovzhani",
    "gn:country_code":"BY",
    "gn:dem":182,
    "gn:feature_class":"P",
    "gn:feature_code":"PPL",
    "gn:name":"Dovzhani",
    "gn:population":0,
    "gn:timezone":"Europe/Minsk",
    "iso:country":"BY",
    "name:rus_x_preferred":[
        "\u0414\u043e\u0432\u0436\u0430\u043d\u0438"
    ],
    "wof:name":"Dovzhani",
    "wof:placetype":"locality"
},
  "geometry": {"coordinates":[27.089,54.7646],"type":"Point"}
}