{
  "type": "Feature",
  "properties": {
    "gn:admin1_code":"1.0",
    "gn:asciiname":"Sulovy",
    "gn:country_code":"BY",
    "gn:dem":153,
    "gn:feature_class":"P",
    "gn:feature_code":"PPL",
    "gn:name":"Sulovy",
    "gn:population":0,
    "gn:timezone":"Europe/Minsk",
    "iso:country":"BY",
    "name:rus_x_preferred":[
        "\u0421\u0443\u043b\u043e\u0432\u044b"
    ],
    "wof:name":"Sulovy",
    "wof:placetype":"locality"
},
  "geometry": {"coordinates":[25.7606,52.1408],"type":"Point"}
}