{
  "type": "Feature",
  "properties": {
    "gn:admin1_code":"1.0",
    "gn:asciiname":"Krytyshyn",
    "gn:country_code":"BY",
    "gn:dem":142,
    "gn:feature_class":"P",
    "gn:feature_code":"PPL",
    "gn:name":"Krytyshyn",
    "gn:population":0,
    "gn:timezone":"Europe/Minsk",
    "iso:country":"BY",
    "name:bel_x_preferred":[
        "\u041a\u0440\u044b\u0442\u044b\u0448\u044b\u043d"
    ],
    "name:eng_x_preferred":[
        "Krytyshin"
    ],
    "name:rus_x_preferred":[
        "\u041a\u0440\u044b\u0442\u044b\u0448\u0438\u043d"
    ],
    "name:und_x_variant":[
        "Krityshin",
        "Krytyshin",
        "Krytyshyn"
    ],
    "wof:name":"Krytyshyn",
    "wof:placetype":"locality"
},
  "geometry": {"coordinates":[25.4801,52.0798],"type":"Point"}
}