{
  "type": "Feature",
  "properties": {
    "gn:admin1_code":"7.0",
    "gn:asciiname":"Mironchiki",
    "gn:country_code":"BY",
    "gn:dem":169,
    "gn:feature_class":"P",
    "gn:feature_code":"PPL",
    "gn:name":"Mironchiki",
    "gn:population":0,
    "gn:timezone":"Europe/Minsk",
    "iso:country":"BY",
    "name:rus_x_preferred":[
        "\u041c\u0438\u0440\u043e\u043d\u0447\u0438\u043a\u0438"
    ],
    "wof:name":"Mironchiki",
    "wof:placetype":"locality"
},
  "geometry": {"coordinates":[28.1909,55.3375],"type":"Point"}
}