{
  "type": "Feature",
  "properties": {
    "gn:admin1_code":"3.0",
    "gn:asciiname":"Shadyuny",
    "gn:country_code":"BY",
    "gn:dem":135,
    "gn:feature_class":"P",
    "gn:feature_code":"PPL",
    "gn:name":"Shadyuny",
    "gn:population":0,
    "gn:timezone":"Europe/Minsk",
    "iso:country":"BY",
    "name:rus_x_preferred":[
        "\u0428\u0430\u0434\u044e\u043d\u044b"
    ],
    "wof:name":"Shadyuny",
    "wof:placetype":"locality"
},
  "geometry": {"coordinates":[25.8617,54.8615],"type":"Point"}
}