{
  "type": "Feature",
  "properties": {
    "gn:admin1_code":"1.0",
    "gn:asciiname":"Pzhikolese",
    "gn:country_code":"BY",
    "gn:dem":162,
    "gn:feature_class":"P",
    "gn:feature_code":"PPL",
    "gn:name":"Pzhikolese",
    "gn:population":0,
    "gn:timezone":"Europe/Minsk",
    "iso:country":"BY",
    "name:rus_x_preferred":[
        "Prikoles\u2019"
    ],
    "name:rus_x_variant":[
        "\u041f\u0440\u0438\u043a\u043e\u043b\u0435\u0441\u044c"
    ],
    "name:und_x_variant":[
        "Prikoles\u2019ye",
        "Pzhikolese"
    ],
    "wof:name":"Pzhikolese",
    "wof:placetype":"locality"
},
  "geometry": {"coordinates":[24.1172,52.6882],"type":"Point"}
}