{
  "type": "Feature",
  "properties": {
    "gn:admin1_code":"3.0",
    "gn:asciiname":"Vladislavovo",
    "gn:country_code":"BY",
    "gn:dem":169,
    "gn:feature_class":"P",
    "gn:feature_code":"PPL",
    "gn:name":"Vladislavovo",
    "gn:population":0,
    "gn:timezone":"Europe/Minsk",
    "iso:country":"BY",
    "name:rus_x_preferred":[
        "\u0412\u043b\u0430\u0434\u0438\u0441\u043b\u0430\u0432\u043e\u0432\u043e"
    ],
    "wof:name":"Vladislavovo",
    "wof:placetype":"locality"
},
  "geometry": {"coordinates":[25.3311,53.9741],"type":"Point"}
}