{
  "type": "Feature",
  "properties": {
    "gn:admin1_code":"5.0",
    "gn:asciiname":"Gastil'",
    "gn:country_code":"BY",
    "gn:dem":258,
    "gn:feature_class":"P",
    "gn:feature_code":"PPL",
    "gn:name":"Gastil\u2019",
    "gn:population":0,
    "gn:timezone":"Europe/Minsk",
    "iso:country":"BY",
    "name:rus_x_preferred":[
        "\u0413\u0430\u0441\u0442\u0438\u043b\u044c"
    ],
    "name:und_x_variant":[
        "Gastil\u2019"
    ],
    "wof:name":"Gastil'",
    "wof:placetype":"locality"
},
  "geometry": {"coordinates":[26.9856,54.155],"type":"Point"}
}