{
  "type": "Feature",
  "properties": {
    "gn:admin1_code":"1.0",
    "gn:asciiname":"Dymniki",
    "gn:country_code":"BY",
    "gn:dem":151,
    "gn:feature_class":"P",
    "gn:feature_code":"PPL",
    "gn:name":"Dymniki",
    "gn:population":0,
    "gn:timezone":"Europe/Minsk",
    "iso:country":"BY",
    "name:rus_x_preferred":[
        "\u0414\u044b\u043c\u043d\u0438\u043a\u0438"
    ],
    "wof:name":"Dymniki",
    "wof:placetype":"locality"
},
  "geometry": {"coordinates":[24.097,52.3938],"type":"Point"}
}