{
  "type": "Feature",
  "properties": {
    "gn:admin1_code":"5.0",
    "gn:asciiname":"Nasledniki",
    "gn:country_code":"BY",
    "gn:dem":260,
    "gn:feature_class":"P",
    "gn:feature_code":"PPL",
    "gn:name":"Nasledniki",
    "gn:population":0,
    "gn:timezone":"Europe/Minsk",
    "iso:country":"BY",
    "name:rus_x_preferred":[
        "\u041d\u0430\u0441\u043b\u0435\u0434\u043d\u0438\u043a\u0438"
    ],
    "wof:name":"Nasledniki",
    "wof:placetype":"locality"
},
  "geometry": {"coordinates":[27.0859,53.7857],"type":"Point"}
}