{
  "type": "Feature",
  "properties": {
    "gn:admin1_code":"2.0",
    "gn:asciiname":"Sperizh'ye",
    "gn:country_code":"BY",
    "gn:dem":109,
    "gn:feature_class":"P",
    "gn:feature_code":"PPL",
    "gn:name":"Sperizh\u2019ye",
    "gn:population":0,
    "gn:timezone":"Europe/Minsk",
    "iso:country":"BY",
    "name:eng_x_preferred":[
        "Sperizh'ye"
    ],
    "name:rus_x_preferred":[
        "\u0421\u043f\u0435\u0440\u0438\u0436\u044c\u0435"
    ],
    "name:und_x_variant":[
        "Sperizh\u2019ye"
    ],
    "wof:name":"Sperizh'ye",
    "wof:placetype":"locality"
},
  "geometry": {"coordinates":[30.2436,51.7183],"type":"Point"}
}