{
  "type": "Feature",
  "properties": {
    "gn:admin1_code":"7.0",
    "gn:asciiname":"Khatsily",
    "gn:country_code":"BY",
    "gn:dem":135,
    "gn:feature_class":"P",
    "gn:feature_code":"PPL",
    "gn:name":"Khatsily",
    "gn:population":0,
    "gn:timezone":"Europe/Minsk",
    "iso:country":"BY",
    "name:bel_x_preferred":[
        "\u0425\u0430\u0446\u0456\u043b\u044b"
    ],
    "name:und_x_variant":[
        "Choci\u0142y",
        "Khotsily",
        "Khatsily",
        "Khotily"
    ],
    "wof:name":"Khatsily",
    "wof:placetype":"locality"
},
  "geometry": {"coordinates":[26.8044,55.144],"type":"Point"}
}