{
  "type": "Feature",
  "properties": {
    "gn:admin1_code":"5.0",
    "gn:asciiname":"Zaostrov'ye",
    "gn:country_code":"BY",
    "gn:dem":161,
    "gn:feature_class":"P",
    "gn:feature_code":"PPL",
    "gn:name":"Zaostrov\u2019ye",
    "gn:population":0,
    "gn:timezone":"Europe/Minsk",
    "iso:country":"BY",
    "name:rus_x_preferred":[
        "\u0417\u0430\u043e\u0441\u0442\u0440\u043e\u0432\u044c\u0435"
    ],
    "name:und_x_variant":[
        "Zaostrov\u2019ye"
    ],
    "wof:name":"Zaostrov'ye",
    "wof:placetype":"locality"
},
  "geometry": {"coordinates":[28.4892,52.9888],"type":"Point"}
}