{
  "type": "Feature",
  "properties": {
    "gn:admin1_code":"7.0",
    "gn:asciiname":"Korolinovo",
    "gn:country_code":"BY",
    "gn:dem":202,
    "gn:feature_class":"P",
    "gn:feature_code":"PPL",
    "gn:name":"Korolinovo",
    "gn:population":0,
    "gn:timezone":"Europe/Minsk",
    "iso:country":"BY",
    "name:rus_x_preferred":[
        "\u041a\u043e\u0440\u043e\u043b\u0438\u043d\u043e\u0432\u043e"
    ],
    "wof:name":"Korolinovo",
    "wof:placetype":"locality"
},
  "geometry": {"coordinates":[26.6463,55.0227],"type":"Point"}
}