{
  "type": "Feature",
  "properties": {
    "gn:admin1_code":"5.0",
    "gn:asciiname":"Vyalyatsichy",
    "gn:country_code":"BY",
    "gn:dem":160,
    "gn:feature_class":"P",
    "gn:feature_code":"PPL",
    "gn:name":"Vyalyatsichy",
    "gn:population":0,
    "gn:timezone":"Europe/Minsk",
    "iso:country":"BY",
    "name:bel_x_preferred":[
        "\u0412\u044f\u043b\u044f\u0446\u0456\u0447\u044b"
    ],
    "name:eng_x_preferred":[
        "Velyatichi"
    ],
    "name:rus_x_preferred":[
        "\u0412\u0435\u043b\u044f\u0442\u0438\u0447\u0438"
    ],
    "name:und_x_variant":[
        "Vilyatichi",
        "Vyalyatsichy"
    ],
    "wof:name":"Vyalyatsichy",
    "wof:placetype":"locality"
},
  "geometry": {"coordinates":[28.9071,54.164],"type":"Point"}
}