{
  "type": "Feature",
  "properties": {
    "gn:admin1_code":"1.0",
    "gn:asciiname":"Pare",
    "gn:country_code":"BY",
    "gn:dem":139,
    "gn:feature_class":"P",
    "gn:feature_code":"PPL",
    "gn:name":"Pare",
    "gn:population":0,
    "gn:timezone":"Europe/Minsk",
    "iso:country":"BY",
    "name:bel_x_preferred":[
        "\u041f\u0430\u0440\u044d"
    ],
    "name:und_x_variant":[
        "Pary",
        "Para",
        "Pare"
    ],
    "wof:name":"Pare",
    "wof:placetype":"locality"
},
  "geometry": {"coordinates":[26.13849,51.89869],"type":"Point"}
}