{
  "type": "Feature",
  "properties": {
    "gn:admin1_code":"1.0",
    "gn:asciiname":"Zarechka",
    "gn:country_code":"BY",
    "gn:dem":145,
    "gn:feature_class":"P",
    "gn:feature_code":"PPL",
    "gn:name":"Zarechka",
    "gn:population":0,
    "gn:timezone":"Europe/Minsk",
    "iso:country":"BY",
    "name:bel_x_preferred":[
        "\u0417\u0430\u0440\u044d\u0447\u043a\u0430"
    ],
    "name:eng_x_preferred":[
        "Zarechka"
    ],
    "name:rus_x_preferred":[
        "\u0417\u0430\u0440\u0435\u0447\u043a\u0430"
    ],
    "name:und_x_variant":[
        "Zarzeczka",
        "Zazhechka",
        "Zarech\u2019ye"
    ],
    "wof:name":"Zarechka",
    "wof:placetype":"locality"
},
  "geometry": {"coordinates":[25.1201,52.05],"type":"Point"}
}