{
  "type": "Feature",
  "properties": {
    "gn:admin1_code":"1.0",
    "gn:asciiname":"Derevnaya",
    "gn:country_code":"BY",
    "gn:dem":181,
    "gn:feature_class":"P",
    "gn:feature_code":"PPL",
    "gn:name":"Derevnaya",
    "gn:population":0,
    "gn:timezone":"Europe/Minsk",
    "iso:country":"BY",
    "name:bel_x_preferred":[
        "\u0414\u0437\u0435\u0440\u0430\u045e\u043d\u0430\u044f"
    ],
    "name:eng_x_preferred":[
        "Darevnaya"
    ],
    "name:rus_x_preferred":[
        "\u0414\u0435\u0440\u0435\u0432\u043d\u0430\u044f"
    ],
    "name:und_x_variant":[
        "Derevna",
        "Darevnaya",
        "Derevnaya",
        "Dzyerawnaya"
    ],
    "wof:name":"Derevnaya",
    "wof:placetype":"locality"
},
  "geometry": {"coordinates":[25.8314,53.0772],"type":"Point"}
}