{
  "type": "Feature",
  "properties": {
    "gn:admin1_code":"1.0",
    "gn:asciiname":"Gichitsy",
    "gn:country_code":"BY",
    "gn:dem":149,
    "gn:feature_class":"P",
    "gn:feature_code":"PPL",
    "gn:name":"Gichitsy",
    "gn:population":0,
    "gn:timezone":"Europe/Minsk",
    "iso:country":"BY",
    "name:rus_x_preferred":[
        "\u0413\u0438\u0447\u0438\u0446\u044b"
    ],
    "name:und_x_variant":[
        "Gichitse",
        "Gichitsy"
    ],
    "wof:name":"Gichitsy",
    "wof:placetype":"locality"
},
  "geometry": {"coordinates":[25.4373,52.6653],"type":"Point"}
}