{
  "type": "Feature",
  "properties": {
    "gn:admin1_code":"7.0",
    "gn:asciiname":"Krasnyy Bor",
    "gn:country_code":"BY",
    "gn:dem":162,
    "gn:feature_class":"P",
    "gn:feature_code":"PPL",
    "gn:name":"Krasnyy Bor",
    "gn:population":0,
    "gn:timezone":"Europe/Minsk",
    "iso:country":"BY",
    "name:rus_x_preferred":[
        "\u041a\u0440\u0430\u0441\u043d\u044b\u0439 \u0411\u043e\u0440"
    ],
    "wof:name":"Krasnyy Bor",
    "wof:placetype":"locality"
},
  "geometry": {"coordinates":[28.56946,56.06659000000001],"type":"Point"}
}