{
  "type": "Feature",
  "properties": {
    "gn:admin1_code":"3.0",
    "gn:asciiname":"Karnolinka",
    "gn:country_code":"BY",
    "gn:dem":151,
    "gn:feature_class":"P",
    "gn:feature_code":"PPL",
    "gn:name":"Karnolinka",
    "gn:population":0,
    "gn:timezone":"Europe/Minsk",
    "iso:country":"BY",
    "name:rus_x_preferred":[
        "\u041a\u0430\u0440\u043d\u043e\u043b\u0438\u043d\u043a\u0430"
    ],
    "wof:name":"Karnolinka",
    "wof:placetype":"locality"
},
  "geometry": {"coordinates":[26.362,54.4881],"type":"Point"}
}