{
  "type": "Feature",
  "properties": {
    "gn:admin1_code":"1.0",
    "gn:asciiname":"Grudoviki",
    "gn:country_code":"BY",
    "gn:dem":143,
    "gn:feature_class":"P",
    "gn:feature_code":"PPL",
    "gn:name":"Grudoviki",
    "gn:population":0,
    "gn:timezone":"Europe/Minsk",
    "iso:country":"BY",
    "name:rus_x_preferred":[
        "\u0413\u0440\u0443\u0434\u043e\u0432\u0438\u043a\u0438"
    ],
    "wof:name":"Grudoviki",
    "wof:placetype":"locality"
},
  "geometry": {"coordinates":[23.9406,52.4382],"type":"Point"}
}