{
  "type": "Feature",
  "properties": {
    "gn:admin1_code":"6.0",
    "gn:asciiname":"Zhevzhik",
    "gn:country_code":"BY",
    "gn:dem":181,
    "gn:feature_class":"P",
    "gn:feature_code":"PPL",
    "gn:name":"Zhevzhik",
    "gn:population":0,
    "gn:timezone":"Europe/Minsk",
    "iso:country":"BY",
    "name:rus_x_preferred":[
        "\u0416\u0435\u0432\u0436\u0438\u043a"
    ],
    "wof:name":"Zhevzhik",
    "wof:placetype":"locality"
},
  "geometry": {"coordinates":[31.9463,53.4984],"type":"Point"}
}