{
  "type": "Feature",
  "properties": {
    "gn:admin1_code":"5.0",
    "gn:asciiname":"Makasichi",
    "gn:country_code":"BY",
    "gn:dem":246,
    "gn:feature_class":"P",
    "gn:feature_code":"PPL",
    "gn:name":"Makasichi",
    "gn:population":0,
    "gn:timezone":"Europe/Minsk",
    "iso:country":"BY",
    "name:rus_x_preferred":[
        "\u041c\u0430\u043a\u0430\u0441\u0438\u0447\u0438"
    ],
    "wof:name":"Makasichi",
    "wof:placetype":"locality"
},
  "geometry": {"coordinates":[26.8653,53.9171],"type":"Point"}
}