{
  "type": "Feature",
  "properties": {
    "gn:admin1_code":"7.0",
    "gn:asciiname":"Kevly",
    "gn:country_code":"BY",
    "gn:dem":125,
    "gn:feature_class":"P",
    "gn:feature_code":"PPL",
    "gn:name":"Kevly",
    "gn:population":0,
    "gn:timezone":"Europe/Minsk",
    "iso:country":"BY",
    "name:rus_x_preferred":[
        "\u041a\u0435\u0432\u043b\u044b"
    ],
    "wof:name":"Kevly",
    "wof:placetype":"locality"
},
  "geometry": {"coordinates":[28.5569,55.6921],"type":"Point"}
}