{
  "type": "Feature",
  "properties": {
    "gn:admin1_code":"7.0",
    "gn:asciiname":"Nosachi",
    "gn:country_code":"BY",
    "gn:dem":224,
    "gn:feature_class":"P",
    "gn:feature_code":"PPL",
    "gn:name":"Nosachi",
    "gn:population":0,
    "gn:timezone":"Europe/Minsk",
    "iso:country":"BY",
    "name:rus_x_preferred":[
        "\u041d\u043e\u0441\u0430\u0447\u0438"
    ],
    "wof:name":"Nosachi",
    "wof:placetype":"locality"
},
  "geometry": {"coordinates":[30.0738,55.575],"type":"Point"}
}