{
  "type": "Feature",
  "properties": {
    "gn:admin1_code":"5.0",
    "gn:asciiname":"Urved'",
    "gn:country_code":"BY",
    "gn:dem":177,
    "gn:feature_class":"P",
    "gn:feature_code":"PPL",
    "gn:name":"Urved\u2019",
    "gn:population":0,
    "gn:timezone":"Europe/Minsk",
    "iso:country":"BY",
    "name:rus_x_preferred":[
        "\u0423\u0440\u0432\u0435\u0434\u044c"
    ],
    "name:und_x_variant":[
        "Urved\u2019"
    ],
    "wof:name":"Urved'",
    "wof:placetype":"locality"
},
  "geometry": {"coordinates":[26.8307,52.9507],"type":"Point"}
}