{
  "type": "Feature",
  "properties": {
    "gn:admin1_code":"0.0",
    "gn:asciiname":"Sleptsy",
    "gn:country_code":"BY",
    "gn:dem":121,
    "gn:feature_class":"P",
    "gn:feature_code":"PPL",
    "gn:name":"Sleptsy",
    "gn:population":0,
    "gn:timezone":"Europe/Minsk",
    "iso:country":"BY",
    "wof:name":"Sleptsy",
    "wof:placetype":"locality"
},
  "geometry": {"coordinates":[27.83333,52.05],"type":"Point"}
}