{
  "type": "Feature",
  "properties": {
    "gn:admin1_code":"7.0",
    "gn:asciiname":"Dorozhkovichi",
    "gn:country_code":"BY",
    "gn:dem":128,
    "gn:feature_class":"P",
    "gn:feature_code":"PPL",
    "gn:name":"Dorozhkovichi",
    "gn:population":0,
    "gn:timezone":"Europe/Minsk",
    "iso:country":"BY",
    "name:rus_x_preferred":[
        "\u0414\u043e\u0440\u043e\u0436\u043a\u043e\u0432\u0438\u0447\u0438"
    ],
    "wof:name":"Dorozhkovichi",
    "wof:placetype":"locality"
},
  "geometry": {"coordinates":[28.1498,55.567],"type":"Point"}
}