{
  "type": "Feature",
  "properties": {
    "gn:admin1_code":"0.0",
    "gn:asciiname":"Vydemki",
    "gn:country_code":"BY",
    "gn:dem":231,
    "gn:feature_class":"P",
    "gn:feature_code":"PPL",
    "gn:name":"Vydemki",
    "gn:population":0,
    "gn:timezone":"Europe/Minsk",
    "iso:country":"BY",
    "wof:name":"Vydemki",
    "wof:placetype":"locality"
},
  "geometry": {"coordinates":[30.63333,55.13333000000001],"type":"Point"}
}