{
  "type": "Feature",
  "properties": {
    "gn:admin1_code":"6.0",
    "gn:asciiname":"Tuguldova",
    "gn:country_code":"BY",
    "gn:dem":204,
    "gn:feature_class":"P",
    "gn:feature_code":"PPL",
    "gn:name":"Tuguldova",
    "gn:population":0,
    "gn:timezone":"Europe/Minsk",
    "iso:country":"BY",
    "name:rus_x_preferred":[
        "\u0422\u0443\u0433\u043e\u043b\u044c\u0434\u043e\u0432\u043e"
    ],
    "name:und_x_variant":[
        "Tugol\u2019dovo",
        "Tuguldova"
    ],
    "wof:name":"Tuguldova",
    "wof:placetype":"locality"
},
  "geometry": {"coordinates":[31.2513,53.9964],"type":"Point"}
}