{
  "type": "Feature",
  "properties": {
    "gn:admin1_code":"3.0",
    "gn:asciiname":"Patsuki",
    "gn:country_code":"BY",
    "gn:dem":129,
    "gn:feature_class":"P",
    "gn:feature_code":"PPL",
    "gn:name":"Patsuki",
    "gn:population":0,
    "gn:timezone":"Europe/Minsk",
    "iso:country":"BY",
    "name:rus_x_preferred":[
        "\u041f\u0430\u0446\u0443\u043a\u0438"
    ],
    "wof:name":"Patsuki",
    "wof:placetype":"locality"
},
  "geometry": {"coordinates":[25.1781,53.6466],"type":"Point"}
}