{
  "type": "Feature",
  "properties": {
    "gn:admin1_code":"3.0",
    "gn:asciiname":"Zhilichi",
    "gn:country_code":"BY",
    "gn:dem":152,
    "gn:feature_class":"P",
    "gn:feature_code":"PPL",
    "gn:name":"Zhilichi",
    "gn:population":0,
    "gn:timezone":"Europe/Minsk",
    "iso:country":"BY",
    "name:rus_x_preferred":[
        "\u0416\u0438\u043b\u0438\u0447\u0438"
    ],
    "wof:name":"Zhilichi",
    "wof:placetype":"locality"
},
  "geometry": {"coordinates":[24.5944,53.588],"type":"Point"}
}