{
  "type": "Feature",
  "properties": {
    "gn:admin1_code":"7.0",
    "gn:asciiname":"Batyarshchina",
    "gn:country_code":"BY",
    "gn:dem":136,
    "gn:feature_class":"P",
    "gn:feature_code":"PPL",
    "gn:name":"Batyarshchina",
    "gn:population":0,
    "gn:timezone":"Europe/Minsk",
    "iso:country":"BY",
    "name:rus_x_preferred":[
        "\u0411\u0430\u0442\u044f\u0440\u0449\u0438\u043d\u0430"
    ],
    "wof:name":"Batyarshchina",
    "wof:placetype":"locality"
},
  "geometry": {"coordinates":[28.9419,55.2606],"type":"Point"}
}