{
  "type": "Feature",
  "properties": {
    "gn:admin1_code":"7.0",
    "gn:asciiname":"Demidenki",
    "gn:country_code":"BY",
    "gn:dem":196,
    "gn:feature_class":"P",
    "gn:feature_code":"PPL",
    "gn:name":"Demidenki",
    "gn:population":0,
    "gn:timezone":"Europe/Minsk",
    "iso:country":"BY",
    "name:rus_x_preferred":[
        "\u0414\u0435\u043c\u0438\u0434\u0435\u043d\u043a\u0438"
    ],
    "wof:name":"Demidenki",
    "wof:placetype":"locality"
},
  "geometry": {"coordinates":[27.7116,55.0434],"type":"Point"}
}