{
  "type": "Feature",
  "properties": {
    "gn:admin1_code":"1.0",
    "gn:asciiname":"Guta",
    "gn:country_code":"BY",
    "gn:dem":147,
    "gn:feature_class":"P",
    "gn:feature_code":"PPL",
    "gn:name":"Guta",
    "gn:population":0,
    "gn:timezone":"Europe/Minsk",
    "iso:country":"BY",
    "name:bul_x_preferred":[
        "\u0413\u0443\u0442\u0430"
    ],
    "name:ceb_x_preferred":[
        "Guta"
    ],
    "name:deu_x_preferred":[
        "Guta"
    ],
    "name:ita_x_preferred":[
        "Guta"
    ],
    "name:lav_x_preferred":[
        "Guta"
    ],
    "name:rus_x_preferred":[
        "\u0413\u0443\u0442\u0430"
    ],
    "name:slk_x_preferred":[
        "Guta"
    ],
    "name:spa_x_preferred":[
        "Guta"
    ],
    "wof:name":"Guta",
    "wof:placetype":"locality"
},
  "geometry": {"coordinates":[25.281,52.1051],"type":"Point"}
}