{
  "type": "Feature",
  "properties": {
    "gn:admin1_code":"6.0",
    "gn:asciiname":"Latyshchina",
    "gn:country_code":"BY",
    "gn:dem":162,
    "gn:feature_class":"P",
    "gn:feature_code":"PPL",
    "gn:name":"Latyshchina",
    "gn:population":0,
    "gn:timezone":"Europe/Minsk",
    "iso:country":"BY",
    "name:rus_x_preferred":[
        "\u041b\u0430\u0442\u044b\u0449\u0438\u043d\u0430"
    ],
    "name:und_x_variant":[
        "Latyshchino",
        "Iatyshchino"
    ],
    "wof:name":"Latyshchina",
    "wof:placetype":"locality"
},
  "geometry": {"coordinates":[31.4211,53.6054],"type":"Point"}
}