{
  "type": "Feature",
  "properties": {
    "gn:admin1_code":"3.0",
    "gn:asciiname":"Povsaty",
    "gn:country_code":"BY",
    "gn:dem":169,
    "gn:feature_class":"P",
    "gn:feature_code":"PPL",
    "gn:name":"Povsaty",
    "gn:population":0,
    "gn:timezone":"Europe/Minsk",
    "iso:country":"BY",
    "name:bel_x_preferred":[
        "Pawsaty"
    ],
    "name:bel_x_variant":[
        "\u041f\u0430\u045e\u0441\u0430\u0442\u044b"
    ],
    "name:rus_x_preferred":[
        "\u041f\u043e\u0432\u0441\u0430\u0442\u044b"
    ],
    "wof:name":"Povsaty",
    "wof:placetype":"locality"
},
  "geometry": {"coordinates":[25.5838,53.5058],"type":"Point"}
}