{
  "type": "Feature",
  "properties": {
    "gn:admin1_code":"3.0",
    "gn:asciiname":"Svetilovichi",
    "gn:country_code":"BY",
    "gn:dem":166,
    "gn:feature_class":"P",
    "gn:feature_code":"PPL",
    "gn:name":"Svetilovichi",
    "gn:population":0,
    "gn:timezone":"Europe/Minsk",
    "iso:country":"BY",
    "name:rus_x_preferred":[
        "\u0421\u0432\u0435\u0442\u0438\u043b\u043e\u0432\u0438\u0447\u0438"
    ],
    "wof:name":"Svetilovichi",
    "wof:placetype":"locality"
},
  "geometry": {"coordinates":[26.5494,54.6599],"type":"Point"}
}