{
  "type": "Feature",
  "properties": {
    "gn:admin1_code":"3.0",
    "gn:asciiname":"Kosily",
    "gn:country_code":"BY",
    "gn:dem":118,
    "gn:feature_class":"P",
    "gn:feature_code":"PPL",
    "gn:name":"Kosily",
    "gn:population":0,
    "gn:timezone":"Europe/Minsk",
    "iso:country":"BY",
    "name:rus_x_preferred":[
        "\u041a\u043e\u0441\u0438\u043b\u044b"
    ],
    "wof:name":"Kosily",
    "wof:placetype":"locality"
},
  "geometry": {"coordinates":[24.2908,53.4183],"type":"Point"}
}