{
  "type": "Feature",
  "properties": {
    "gn:admin1_code":"3.0",
    "gn:asciiname":"Zabolot'",
    "gn:country_code":"BY",
    "gn:dem":129,
    "gn:feature_class":"P",
    "gn:feature_code":"PPL",
    "gn:name":"Zabolot\u2019",
    "gn:population":0,
    "gn:timezone":"Europe/Minsk",
    "iso:country":"BY",
    "name:rus_x_preferred":[
        "\u0417\u0430\u0431\u043e\u043b\u043e\u0442\u044c"
    ],
    "name:und_x_variant":[
        "Zabolot\u2019"
    ],
    "wof:name":"Zabolot'",
    "wof:placetype":"locality"
},
  "geometry": {"coordinates":[23.8947,53.7075],"type":"Point"}
}