{
  "type": "Feature",
  "properties": {
    "gn:admin1_code":"5.0",
    "gn:asciiname":"Yurzhishki",
    "gn:country_code":"BY",
    "gn:dem":225,
    "gn:feature_class":"P",
    "gn:feature_code":"PPL",
    "gn:name":"Yurzhishki",
    "gn:population":0,
    "gn:timezone":"Europe/Minsk",
    "iso:country":"BY",
    "name:rus_x_preferred":[
        "\u042e\u0440\u0436\u0438\u0448\u043a\u0438"
    ],
    "wof:name":"Yurzhishki",
    "wof:placetype":"locality"
},
  "geometry": {"coordinates":[26.9307,53.9524],"type":"Point"}
}