{
  "type": "Feature",
  "properties": {
    "gn:admin1_code":"0.0",
    "gn:asciiname":"Shily",
    "gn:cc2":"BY",
    "gn:country_code":"BY",
    "gn:dem":203,
    "gn:feature_class":"P",
    "gn:feature_code":"PPL",
    "gn:name":"Shily",
    "gn:population":0,
    "gn:timezone":"Europe/Minsk",
    "iso:country":"BY",
    "name:und_x_variant":[
        "Szy\u0142y",
        "Shily"
    ],
    "wof:name":"Shily",
    "wof:placetype":"locality"
},
  "geometry": {"coordinates":[27.95,54.58333],"type":"Point"}
}