{
  "type": "Feature",
  "properties": {
    "gn:admin1_code":"1.0",
    "gn:asciiname":"Vorotsevichi",
    "gn:country_code":"BY",
    "gn:dem":146,
    "gn:feature_class":"P",
    "gn:feature_code":"PPL",
    "gn:name":"Vorotsevichi",
    "gn:population":0,
    "gn:timezone":"Europe/Minsk",
    "iso:country":"BY",
    "name:rus_x_preferred":[
        "\u0412\u043e\u0440\u043e\u0446\u0435\u0432\u0438\u0447\u0438"
    ],
    "name:und_x_variant":[
        "Vorotseviche",
        "Worocewicze",
        "Vorotsevichi"
    ],
    "wof:name":"Vorotsevichi",
    "wof:placetype":"locality"
},
  "geometry": {"coordinates":[25.3853,52.109],"type":"Point"}
}