{
  "type": "Feature",
  "properties": {
    "gn:admin1_code":"1.0",
    "gn:asciiname":"Podber'ye",
    "gn:country_code":"BY",
    "gn:dem":143,
    "gn:feature_class":"P",
    "gn:feature_code":"PPL",
    "gn:name":"Podber\u2019ye",
    "gn:population":0,
    "gn:timezone":"Europe/Minsk",
    "iso:country":"BY",
    "name:rus_x_preferred":[
        "\u041f\u043e\u0434\u0431\u0435\u0440\u044c\u0435"
    ],
    "name:und_x_variant":[
        "Podber\u2019ye"
    ],
    "wof:name":"Podber'ye",
    "wof:placetype":"locality"
},
  "geometry": {"coordinates":[24.4896,52.2765],"type":"Point"}
}