{
  "type": "Feature",
  "properties": {
    "gn:admin1_code":"1.0",
    "gn:asciiname":"Menevezh",
    "gn:country_code":"BY",
    "gn:dem":152,
    "gn:feature_class":"P",
    "gn:feature_code":"PPL",
    "gn:name":"Menevezh",
    "gn:population":0,
    "gn:timezone":"Europe/Minsk",
    "iso:country":"BY",
    "name:rus_x_preferred":[
        "\u041c\u0435\u043d\u0435\u0432\u0435\u0436"
    ],
    "wof:name":"Menevezh",
    "wof:placetype":"locality"
},
  "geometry": {"coordinates":[24.8546,52.3375],"type":"Point"}
}