{
  "type": "Feature",
  "properties": {
    "gn:admin1_code":"3.0",
    "gn:asciiname":"Buyaki",
    "gn:country_code":"BY",
    "gn:dem":141,
    "gn:feature_class":"P",
    "gn:feature_code":"PPL",
    "gn:name":"Buyaki",
    "gn:population":0,
    "gn:timezone":"Europe/Minsk",
    "iso:country":"BY",
    "name:rus_x_preferred":[
        "\u0411\u0443\u044f\u043a\u0438"
    ],
    "wof:name":"Buyaki",
    "wof:placetype":"locality"
},
  "geometry": {"coordinates":[26.2944,54.7641],"type":"Point"}
}