{
  "type": "Feature",
  "properties": {
    "gn:admin1_code":"1.0",
    "gn:asciiname":"Shamyatowka",
    "gn:country_code":"BY",
    "gn:dem":147,
    "gn:feature_class":"P",
    "gn:feature_code":"PPL",
    "gn:name":"Shamyatowka",
    "gn:population":0,
    "gn:timezone":"Europe/Minsk",
    "iso:country":"BY",
    "name:bel_x_preferred":[
        "\u0428\u0430\u043c\u044f\u0442\u043e\u045e\u043a\u0430"
    ],
    "name:bel_x_variant":[
        "Shamyatowka"
    ],
    "name:und_x_variant":[
        "Shemetovka"
    ],
    "wof:name":"Shamyatowka",
    "wof:placetype":"locality"
},
  "geometry": {"coordinates":[24.6541,52.3271],"type":"Point"}
}