{
  "type": "Feature",
  "properties": {
    "gn:admin1_code":"7.0",
    "gn:asciiname":"Mamonovka",
    "gn:country_code":"BY",
    "gn:dem":128,
    "gn:feature_class":"P",
    "gn:feature_code":"PPL",
    "gn:name":"Mamonovka",
    "gn:population":0,
    "gn:timezone":"Europe/Minsk",
    "iso:country":"BY",
    "name:ceb_x_preferred":[
        "Mamonovka"
    ],
    "name:hye_x_preferred":[
        "\u0544\u0561\u0574\u0578\u0576\u0578\u057e\u056f\u0561"
    ],
    "name:lit_x_preferred":[
        "Bonava"
    ],
    "name:pol_x_preferred":[
        "Ban\u00f3wka"
    ],
    "name:rus_x_preferred":[
        "\u041c\u0430\u043c\u043e\u043d\u043e\u0432\u043a\u0430"
    ],
    "name:ukr_x_preferred":[
        "\u0411\u0430\u043d\u0443\u0432\u043a\u0430"
    ],
    "name:zho_x_preferred":[
        "\u5df4\u52aa\u592b\u5361\u6cb3"
    ],
    "wof:name":"Mamonovka",
    "wof:placetype":"locality"
},
  "geometry": {"coordinates":[27.9045,55.4315],"type":"Point"}
}