{
  "type": "Feature",
  "properties": {
    "gn:admin1_code":"7.0",
    "gn:asciiname":"Mamonovka",
    "gn:country_code":"BY",
    "gn:dem":128,
    "gn:feature_class":"P",
    "gn:feature_code":"PPL",
    "gn:name":"Mamonovka",
    "gn:population":0,
    "gn:timezone":"Europe/Minsk",
    "iso:country":"BY",
    "name:rus_x_preferred":[
        "\u041c\u0430\u043c\u043e\u043d\u043e\u0432\u043a\u0430"
    ],
    "wof:name":"Mamonovka",
    "wof:placetype":"locality"
},
  "geometry": {"coordinates":[27.9045,55.4315],"type":"Point"}
}