{
  "type": "Feature",
  "properties": {
    "gn:admin1_code":"7.0",
    "gn:asciiname":"Shestovo",
    "gn:country_code":"BY",
    "gn:dem":122,
    "gn:feature_class":"P",
    "gn:feature_code":"PPL",
    "gn:name":"Shestovo",
    "gn:population":0,
    "gn:timezone":"Europe/Minsk",
    "iso:country":"BY",
    "name:rus_x_preferred":[
        "\u0428\u0435\u0441\u0442\u043e\u0432\u043e"
    ],
    "wof:name":"Shestovo",
    "wof:placetype":"locality"
},
  "geometry": {"coordinates":[28.9653,55.4229],"type":"Point"}
}