{
  "type": "Feature",
  "properties": {
    "gn:admin1_code":"7.0",
    "gn:asciiname":"Khroly",
    "gn:country_code":"BY",
    "gn:dem":161,
    "gn:feature_class":"P",
    "gn:feature_code":"PPL",
    "gn:name":"Khroly",
    "gn:population":0,
    "gn:timezone":"Europe/Minsk",
    "iso:country":"BY",
    "name:rus_x_preferred":[
        "\u0425\u0440\u043e\u043b\u044b"
    ],
    "wof:name":"Khroly",
    "wof:placetype":"locality"
},
  "geometry": {"coordinates":[27.1755,55.1241],"type":"Point"}
}