{
  "type": "Feature",
  "properties": {
    "gn:admin1_code":"7.0",
    "gn:asciiname":"Shipuli",
    "gn:country_code":"BY",
    "gn:dem":140,
    "gn:feature_class":"P",
    "gn:feature_code":"PPL",
    "gn:name":"Shipuli",
    "gn:population":0,
    "gn:timezone":"Europe/Minsk",
    "iso:country":"BY",
    "name:rus_x_preferred":[
        "\u0428\u0438\u043f\u0443\u043b\u0438"
    ],
    "wof:name":"Shipuli",
    "wof:placetype":"locality"
},
  "geometry": {"coordinates":[29.2036,54.9993],"type":"Point"}
}