{
  "type": "Feature",
  "properties": {
    "gn:admin1_code":"7.0",
    "gn:asciiname":"Kovalenki",
    "gn:country_code":"BY",
    "gn:dem":161,
    "gn:feature_class":"P",
    "gn:feature_code":"PPL",
    "gn:name":"Kovalenki",
    "gn:population":0,
    "gn:timezone":"Europe/Minsk",
    "iso:country":"BY",
    "name:rus_x_preferred":[
        "\u041a\u043e\u0432\u0430\u043b\u0435\u043d\u043a\u0438"
    ],
    "wof:name":"Kovalenki",
    "wof:placetype":"locality"
},
  "geometry": {"coordinates":[27.5921,55.2062],"type":"Point"}
}