{
  "type": "Feature",
  "properties": {
    "gn:admin1_code":"1.0",
    "gn:asciiname":"Pogor'ye",
    "gn:country_code":"BY",
    "gn:dem":141,
    "gn:feature_class":"P",
    "gn:feature_code":"PPL",
    "gn:name":"Pogor\u2019ye",
    "gn:population":0,
    "gn:timezone":"Europe/Minsk",
    "iso:country":"BY",
    "name:rus_x_preferred":[
        "\u041f\u043e\u0433\u043e\u0440\u044c\u0435"
    ],
    "name:und_x_variant":[
        "Pogor\u2019ye"
    ],
    "wof:name":"Pogor'ye",
    "wof:placetype":"locality"
},
  "geometry": {"coordinates":[25.5723,52.9147],"type":"Point"}
}