{
  "type": "Feature",
  "properties": {
    "gn:admin1_code":"5.0",
    "gn:asciiname":"Plikovichi",
    "gn:country_code":"BY",
    "gn:dem":167,
    "gn:feature_class":"P",
    "gn:feature_code":"PPL",
    "gn:name":"Plikovichi",
    "gn:population":0,
    "gn:timezone":"Europe/Minsk",
    "iso:country":"BY",
    "name:rus_x_preferred":[
        "\u041f\u043b\u0438\u043a\u043e\u0432\u0438\u0447\u0438"
    ],
    "wof:name":"Plikovichi",
    "wof:placetype":"locality"
},
  "geometry": {"coordinates":[26.9964,54.5368],"type":"Point"}
}