{
  "type": "Feature",
  "properties": {
    "gn:admin1_code":"1.0",
    "gn:asciiname":"Koreni",
    "gn:country_code":"BY",
    "gn:dem":184,
    "gn:feature_class":"P",
    "gn:feature_code":"PPL",
    "gn:name":"Koreni",
    "gn:population":0,
    "gn:timezone":"Europe/Minsk",
    "iso:country":"BY",
    "name:rus_x_preferred":[
        "\u041a\u043e\u0440\u0435\u043d\u0438"
    ],
    "wof:name":"Koreni",
    "wof:placetype":"locality"
},
  "geometry": {"coordinates":[26.2123,53.0803],"type":"Point"}
}