{
  "type": "Feature",
  "properties": {
    "gn:country":"BY",
    "gn:fcode":"PPLA2",
    "gn:pop":6100,
    "iso:country":"BY",
    "name:bel_x_preferred":[
        "\u041a\u0440\u0430\u0441\u043d\u0430\u043f\u043e\u043b\u043b\u0435"
    ],
    "name:bul_x_preferred":[
        "\u041a\u0440\u0430\u0441\u043d\u0430\u043f\u043e\u043b\u0439\u0435"
    ],
    "name:deu_x_preferred":[
        "Krasnapolle"
    ],
    "name:eng_x_preferred":[
        "Krasnapollye"
    ],
    "name:est_x_preferred":[
        "Krasnapo\u0142le"
    ],
    "name:fin_x_preferred":[
        "Krasnapolle"
    ],
    "name:fra_x_preferred":[
        "Krasnapolle"
    ],
    "name:heb_x_preferred":[
        "\u05e7\u05e8\u05e1\u05e0\u05d5\u05e4\u05d5\u05dc\u05d9\u05d4"
    ],
    "name:hsb_x_preferred":[
        "Krasnapolle"
    ],
    "name:hye_x_preferred":[
        "\u053f\u0580\u0561\u057d\u0576\u0578\u057a\u0578\u056c\u0575\u0565"
    ],
    "name:nld_x_preferred":[
        "Krasnapolle"
    ],
    "name:pol_x_preferred":[
        "Krasnopole"
    ],
    "name:rus_x_preferred":[
        "\u041a\u0440\u0430\u0441\u043d\u043e\u043f\u043e\u043b\u044c\u0435"
    ],
    "name:srp_x_preferred":[
        "\u041a\u0440\u0430\u0441\u043d\u0430\u043f\u043e\u0459\u0435"
    ],
    "name:swe_x_preferred":[
        "Krasnapolle"
    ],
    "name:ukr_x_preferred":[
        "\u041a\u0440\u0430\u0441\u043d\u043e\u043f\u0456\u043b\u043b\u044f"
    ],
    "name:unk_x_variant":[
        "Krasnopole"
    ],
    "qs:name":"Krasnapollye",
    "qs:photos_9r":0,
    "qs:photos_sr":0,
    "qs:pop_sr":"5",
    "wof:name":"Krasnapollye",
    "wof:placetype":"locality",
    "wof:population":6100
},
  "geometry": {"coordinates":[31.3999,53.3353],"type":"Point"}
}