{
  "type": "Feature",
  "properties": {
    "gn:admin1_code":"7.0",
    "gn:asciiname":"Degterovo",
    "gn:country_code":"BY",
    "gn:dem":119,
    "gn:feature_class":"P",
    "gn:feature_code":"PPL",
    "gn:name":"Degterovo",
    "gn:population":0,
    "gn:timezone":"Europe/Minsk",
    "iso:country":"BY",
    "name:rus_x_preferred":[
        "\u0414\u0435\u0433\u0442\u0435\u0440\u043e\u0432\u043e"
    ],
    "name:und_x_variant":[
        "Degtyarevo"
    ],
    "wof:name":"Degterovo",
    "wof:placetype":"locality"
},
  "geometry": {"coordinates":[27.8878,55.9231],"type":"Point"}
}