{
  "type": "Feature",
  "properties": {
    "gn:admin1_code":"5.0",
    "gn:asciiname":"Yarkovo",
    "gn:country_code":"BY",
    "gn:dem":233,
    "gn:feature_class":"P",
    "gn:feature_code":"PPL",
    "gn:name":"Yarkovo",
    "gn:population":0,
    "gn:timezone":"Europe/Minsk",
    "iso:country":"BY",
    "name:rus_x_preferred":[
        "\u042f\u0440\u043a\u043e\u0432\u043e"
    ],
    "wof:name":"Yarkovo",
    "wof:placetype":"locality"
},
  "geometry": {"coordinates":[27.3993,53.892],"type":"Point"}
}