{
  "type": "Feature",
  "properties": {
    "gn:admin1_code":"6.0",
    "gn:asciiname":"Sharayevka",
    "gn:country_code":"BY",
    "gn:dem":181,
    "gn:feature_class":"P",
    "gn:feature_code":"PPL",
    "gn:name":"Sharayevka",
    "gn:population":0,
    "gn:timezone":"Europe/Minsk",
    "iso:country":"BY",
    "name:rus_x_preferred":[
        "\u0428\u0430\u0440\u0430\u0435\u0432\u043a\u0430"
    ],
    "wof:name":"Sharayevka",
    "wof:placetype":"locality"
},
  "geometry": {"coordinates":[29.9776,53.9101],"type":"Point"}
}