{
  "type": "Feature",
  "properties": {
    "gn:admin1_code":"6.0",
    "gn:asciiname":"Staraya Buda",
    "gn:country_code":"BY",
    "gn:dem":159,
    "gn:feature_class":"P",
    "gn:feature_code":"PPL",
    "gn:name":"Staraya Buda",
    "gn:population":0,
    "gn:timezone":"Europe/Minsk",
    "iso:country":"BY",
    "name:rus_x_preferred":[
        "\u0421\u0442\u0430\u0440\u0430\u044f \u0411\u0443\u0434\u0430"
    ],
    "wof:name":"Staraya Buda",
    "wof:placetype":"locality"
},
  "geometry": {"coordinates":[31.2886,53.2142],"type":"Point"}
}