{
  "type": "Feature",
  "properties": {
    "gn:admin1_code":"7.0",
    "gn:asciiname":"Butyazhi",
    "gn:country_code":"BY",
    "gn:dem":162,
    "gn:feature_class":"P",
    "gn:feature_code":"PPL",
    "gn:name":"Butyazhi",
    "gn:population":0,
    "gn:timezone":"Europe/Minsk",
    "iso:country":"BY",
    "name:rus_x_preferred":[
        "\u0411\u0443\u0442\u044f\u0436\u0438"
    ],
    "name:und_x_variant":[
        "Butezhi"
    ],
    "wof:name":"Butyazhi",
    "wof:placetype":"locality"
},
  "geometry": {"coordinates":[30.0609,55.0629],"type":"Point"}
}