{
  "type": "Feature",
  "properties": {
    "gn:admin1_code":"3.0",
    "gn:asciiname":"Spasyuki",
    "gn:country_code":"BY",
    "gn:dem":192,
    "gn:feature_class":"P",
    "gn:feature_code":"PPL",
    "gn:name":"Spasyuki",
    "gn:population":0,
    "gn:timezone":"Europe/Minsk",
    "iso:country":"BY",
    "name:bel_x_preferred":[
        "\u0421\u043f\u0430\u0441\u044e\u043a\u0456"
    ],
    "name:rus_x_preferred":[
        "\u0421\u043f\u0430\u0441\u044e\u043a\u0438"
    ],
    "wof:name":"Spasyuki",
    "wof:placetype":"locality"
},
  "geometry": {"coordinates":[25.4829,53.3232],"type":"Point"}
}