{
  "type": "Feature",
  "properties": {
    "gn:admin1_code":"6.0",
    "gn:asciiname":"Malaya Krapivnya",
    "gn:country_code":"BY",
    "gn:dem":148,
    "gn:feature_class":"P",
    "gn:feature_code":"PPL",
    "gn:name":"Malaya Krapivnya",
    "gn:population":0,
    "gn:timezone":"Europe/Minsk",
    "iso:country":"BY",
    "name:rus_x_preferred":[
        "\u041c\u0430\u043b\u0430\u044f \u041a\u0440\u0430\u043f\u0438\u0432\u043d\u044f"
    ],
    "name:und_x_variant":[
        "Malaya Krapivna"
    ],
    "wof:name":"Malaya Krapivnya",
    "wof:placetype":"locality"
},
  "geometry": {"coordinates":[32.1991,53.2513],"type":"Point"}
}