{
  "type": "Feature",
  "properties": {
    "gn:admin1_code":"5.0",
    "gn:asciiname":"Tkachi",
    "gn:country_code":"BY",
    "gn:dem":206,
    "gn:feature_class":"P",
    "gn:feature_code":"PPL",
    "gn:name":"Tkachi",
    "gn:population":0,
    "gn:timezone":"Europe/Minsk",
    "iso:country":"BY",
    "name:rus_x_preferred":[
        "\u0422\u043a\u0430\u0447\u0438"
    ],
    "wof:name":"Tkachi",
    "wof:placetype":"locality"
},
  "geometry": {"coordinates":[26.7966,53.9189],"type":"Point"}
}