{
  "type": "Feature",
  "properties": {
    "gn:admin1_code":"5.0",
    "gn:asciiname":"Lankovshchina",
    "gn:country_code":"BY",
    "gn:dem":176,
    "gn:feature_class":"P",
    "gn:feature_code":"PPL",
    "gn:name":"Lankovshchina",
    "gn:population":0,
    "gn:timezone":"Europe/Minsk",
    "iso:country":"BY",
    "name:rus_x_preferred":[
        "\u041b\u0430\u043d\u043a\u043e\u0432\u0449\u0438\u043d\u0430"
    ],
    "wof:name":"Lankovshchina",
    "wof:placetype":"locality"
},
  "geometry": {"coordinates":[28.6836,54.2583],"type":"Point"}
}