{
  "type": "Feature",
  "properties": {
    "gn:admin1_code":"5.0",
    "gn:asciiname":"Rum",
    "gn:country_code":"BY",
    "gn:dem":146,
    "gn:feature_class":"P",
    "gn:feature_code":"PPL",
    "gn:name":"Rum",
    "gn:population":0,
    "gn:timezone":"Europe/Minsk",
    "iso:country":"BY",
    "name:eng_x_preferred":[
        "Rum"
    ],
    "name:rus_x_preferred":[
        "\u0420\u0443\u043c"
    ],
    "wof:name":"Rum",
    "wof:placetype":"locality"
},
  "geometry": {"coordinates":[26.3885,54.0085],"type":"Point"}
}