{
  "type": "Feature",
  "properties": {
    "gn:admin1_code":"5.0",
    "gn:asciiname":"Tychiny",
    "gn:country_code":"BY",
    "gn:dem":148,
    "gn:feature_class":"P",
    "gn:feature_code":"PPL",
    "gn:name":"Tychiny",
    "gn:population":0,
    "gn:timezone":"Europe/Minsk",
    "iso:country":"BY",
    "name:rus_x_preferred":[
        "\u0422\u044b\u0447\u0438\u043d\u044b"
    ],
    "wof:name":"Tychiny",
    "wof:placetype":"locality"
},
  "geometry": {"coordinates":[27.4981,52.7602],"type":"Point"}
}