{
  "type": "Feature",
  "properties": {
    "gn:admin1_code":"6.0",
    "gn:asciiname":"Lyebyadzyanka",
    "gn:country_code":"BY",
    "gn:dem":180,
    "gn:feature_class":"P",
    "gn:feature_code":"PPL",
    "gn:name":"Lyebyadzyanka",
    "gn:population":0,
    "gn:timezone":"Europe/Minsk",
    "iso:country":"BY",
    "name:bel_x_preferred":[
        "\u041b\u0435\u0431\u044f\u0434\u0437\u044f\u043d\u043a\u0430"
    ],
    "name:und_x_variant":[
        "Lebedyanka"
    ],
    "wof:name":"Lyebyadzyanka",
    "wof:placetype":"locality"
},
  "geometry": {"coordinates":[29.8373,53.9062],"type":"Point"}
}