{
  "type": "Feature",
  "properties": {
    "gn:admin1_code":"7.0",
    "gn:asciiname":"Romanishki",
    "gn:country_code":"BY",
    "gn:dem":208,
    "gn:feature_class":"P",
    "gn:feature_code":"PPL",
    "gn:name":"Romanishki",
    "gn:population":0,
    "gn:timezone":"Europe/Minsk",
    "iso:country":"BY",
    "name:rus_x_preferred":[
        "\u0420\u043e\u043c\u0430\u043d\u0438\u0448\u043a\u0438"
    ],
    "wof:name":"Romanishki",
    "wof:placetype":"locality"
},
  "geometry": {"coordinates":[26.2665,55.0498],"type":"Point"}
}