{
  "type": "Feature",
  "properties": {
    "gn:admin1_code":"7.0",
    "gn:asciiname":"Novaya Luka",
    "gn:country_code":"BY",
    "gn:dem":129,
    "gn:feature_class":"P",
    "gn:feature_code":"PPL",
    "gn:name":"Novaya Luka",
    "gn:population":0,
    "gn:timezone":"Europe/Minsk",
    "iso:country":"BY",
    "name:rus_x_preferred":[
        "\u041d\u043e\u0432\u0430\u044f \u041b\u0443\u043a\u0430"
    ],
    "name:und_x_variant":[
        "Nova Luka",
        "Novyye Luki",
        "Novaya Luka"
    ],
    "wof:name":"Novaya Luka",
    "wof:placetype":"locality"
},
  "geometry": {"coordinates":[26.8476,55.4174],"type":"Point"}
}