{
  "type": "Feature",
  "properties": {
    "gn:admin1_code":"5.0",
    "gn:asciiname":"Azarki-Dvorishche",
    "gn:country_code":"BY",
    "gn:dem":174,
    "gn:feature_class":"P",
    "gn:feature_code":"PPL",
    "gn:name":"Azarki-Dvorishche",
    "gn:population":0,
    "gn:timezone":"Europe/Minsk",
    "iso:country":"BY",
    "name:rus_x_preferred":[
        "\u0410\u0437\u0430\u0440\u043a\u0438-\u0414\u0432\u043e\u0440\u0438\u0449\u0435"
    ],
    "wof:name":"Azarki-Dvorishche",
    "wof:placetype":"locality"
},
  "geometry": {"coordinates":[26.9869,54.8356],"type":"Point"}
}