{
  "type": "Feature",
  "properties": {
    "gn:admin1_code":"7.0",
    "gn:asciiname":"Boyary",
    "gn:country_code":"BY",
    "gn:dem":250,
    "gn:feature_class":"P",
    "gn:feature_code":"PPL",
    "gn:name":"Boyary",
    "gn:population":0,
    "gn:timezone":"Europe/Minsk",
    "iso:country":"BY",
    "name:rus_x_preferred":[
        "\u0411\u043e\u044f\u0440\u044b"
    ],
    "wof:name":"Boyary",
    "wof:placetype":"locality"
},
  "geometry": {"coordinates":[30.5583,55.1335],"type":"Point"}
}