{
  "type": "Feature",
  "properties": {
    "gn:admin1_code":"5.0",
    "gn:asciiname":"Kalyuga",
    "gn:country_code":"BY",
    "gn:dem":177,
    "gn:feature_class":"P",
    "gn:feature_code":"PPL",
    "gn:name":"Kalyuga",
    "gn:population":0,
    "gn:timezone":"Europe/Minsk",
    "iso:country":"BY",
    "name:rus_x_preferred":[
        "\u041a\u0430\u043b\u044e\u0433\u0430"
    ],
    "wof:name":"Kalyuga",
    "wof:placetype":"locality"
},
  "geometry": {"coordinates":[27.4915,53.2314],"type":"Point"}
}