{
  "type": "Feature",
  "properties": {
    "gn:admin1_code":"7.0",
    "gn:asciiname":"Lutik",
    "gn:country_code":"BY",
    "gn:dem":141,
    "gn:feature_class":"P",
    "gn:feature_code":"PPL",
    "gn:name":"Lutik",
    "gn:population":0,
    "gn:timezone":"Europe/Minsk",
    "iso:country":"BY",
    "name:rus_x_preferred":[
        "\u041b\u0443\u0442\u0438\u043a"
    ],
    "wof:name":"Lutik",
    "wof:placetype":"locality"
},
  "geometry": {"coordinates":[29.2342,54.8825],"type":"Point"}
}