{
  "type": "Feature",
  "properties": {
    "gn:country":"BY",
    "gn:fcode":"PPL",
    "gn:population":2445,
    "iso:country":"BY",
    "name:bel_x_preferred":[
        "\u042d\u043d\u0435\u0440\u0433\u0435\u0442\u044b\u043a\u0430\u045e"
    ],
    "name:rus_x_preferred":[
        "\u042d\u043d\u0435\u0440\u0433\u0435\u0442\u0438\u043a\u043e\u0432"
    ],
    "name:und_x_variant":[
        "Energetikov"
    ],
    "qs:name":"Enyerhyetykaw",
    "qs:photos_9r":0,
    "qs:photos_sr":0,
    "qs:pop_sr":"4",
    "wof:name":"Enyerhyetykaw",
    "wof:placetype":"locality",
    "wof:population":2445
},
  "geometry": {"coordinates":[27.0535,53.5871],"type":"Point"}
}