{
  "type": "Feature",
  "properties": {
    "gn:admin1_code":"5.0",
    "gn:asciiname":"Artyukhi",
    "gn:country_code":"BY",
    "gn:dem":166,
    "gn:feature_class":"P",
    "gn:feature_code":"PPL",
    "gn:name":"Artyukhi",
    "gn:population":0,
    "gn:timezone":"Europe/Minsk",
    "iso:country":"BY",
    "name:rus_x_preferred":[
        "\u0410\u0440\u0442\u044e\u0445\u0438"
    ],
    "name:und_x_variant":[
        "Ortsyukhy"
    ],
    "wof:name":"Artyukhi",
    "wof:placetype":"locality"
},
  "geometry": {"coordinates":[26.8286,53.4752],"type":"Point"}
}