{
  "type": "Feature",
  "properties": {
    "gn:admin1_code":"3.0",
    "gn:asciiname":"Starodvortsy",
    "gn:country_code":"BY",
    "gn:dem":149,
    "gn:feature_class":"P",
    "gn:feature_code":"PPL",
    "gn:name":"Starodvortsy",
    "gn:population":0,
    "gn:timezone":"Europe/Minsk",
    "iso:country":"BY",
    "name:rus_x_preferred":[
        "\u0421\u0442\u0430\u0440\u043e\u0434\u0432\u043e\u0440\u0446\u044b"
    ],
    "name:und_x_variant":[
        "Starodvortsa",
        "Starodvortsy"
    ],
    "wof:name":"Starodvortsy",
    "wof:placetype":"locality"
},
  "geometry": {"coordinates":[24.7965,53.8145],"type":"Point"}
}