{
  "type": "Feature",
  "properties": {
    "gn:admin1_code":"7.0",
    "gn:asciiname":"Pateyenki",
    "gn:country_code":"BY",
    "gn:dem":139,
    "gn:feature_class":"P",
    "gn:feature_code":"PPL",
    "gn:name":"Pateyenki",
    "gn:population":0,
    "gn:timezone":"Europe/Minsk",
    "iso:country":"BY",
    "name:rus_x_preferred":[
        "\u041f\u0430\u0442\u0435\u0435\u043d\u043a\u0438"
    ],
    "wof:name":"Pateyenki",
    "wof:placetype":"locality"
},
  "geometry": {"coordinates":[27.7809,55.625],"type":"Point"}
}