{
  "type": "Feature",
  "properties": {
    "gn:admin1_code":"7.0",
    "gn:asciiname":"Spasskoye",
    "gn:country_code":"BY",
    "gn:dem":131,
    "gn:feature_class":"P",
    "gn:feature_code":"PPL",
    "gn:name":"Spasskoye",
    "gn:population":0,
    "gn:timezone":"Europe/Minsk",
    "iso:country":"BY",
    "name:rus_x_preferred":[
        "\u0421\u043f\u0430\u0441\u0441\u043a\u043e\u0435"
    ],
    "wof:name":"Spasskoye",
    "wof:placetype":"locality"
},
  "geometry": {"coordinates":[29.4176,55.3615],"type":"Point"}
}