{
  "type": "Feature",
  "properties": {
    "gn:admin1_code":"7.0",
    "gn:asciiname":"Ploskaye",
    "gn:country_code":"BY",
    "gn:dem":210,
    "gn:feature_class":"P",
    "gn:feature_code":"PPL",
    "gn:name":"Ploskaye",
    "gn:population":0,
    "gn:timezone":"Europe/Minsk",
    "iso:country":"BY",
    "name:bel_x_preferred":[
        "\u041f\u043b\u043e\u0441\u043a\u0430\u0435"
    ],
    "name:eng_x_preferred":[
        "Ploskoye"
    ],
    "name:rus_x_preferred":[
        "\u041f\u043b\u043e\u0441\u043a\u043e\u0435"
    ],
    "name:und_x_variant":[
        "Ploskoye",
        "Ploskaye"
    ],
    "wof:name":"Ploskaye",
    "wof:placetype":"locality"
},
  "geometry": {"coordinates":[29.5336,54.4425],"type":"Point"}
}