{
  "type": "Feature",
  "properties": {
    "gn:admin1_code":"5.0",
    "gn:asciiname":"Zarechnoye",
    "gn:country_code":"BY",
    "gn:dem":177,
    "gn:feature_class":"P",
    "gn:feature_code":"PPL",
    "gn:name":"Zarechnoye",
    "gn:population":0,
    "gn:timezone":"Europe/Minsk",
    "iso:country":"BY",
    "name:rus_x_preferred":[
        "\u0417\u0430\u0440\u0435\u0447\u043d\u043e\u0435"
    ],
    "wof:name":"Zarechnoye",
    "wof:placetype":"locality"
},
  "geometry": {"coordinates":[27.2099,54.6774],"type":"Point"}
}