{
  "type": "Feature",
  "properties": {
    "gn:admin1_code":"7.0",
    "gn:asciiname":"Zaobol'",
    "gn:country_code":"BY",
    "gn:dem":137,
    "gn:feature_class":"P",
    "gn:feature_code":"PPL",
    "gn:name":"Zaobol\u2019",
    "gn:population":0,
    "gn:timezone":"Europe/Minsk",
    "iso:country":"BY",
    "name:rus_x_preferred":[
        "\u0417\u0430\u043e\u0431\u043e\u043b\u044c"
    ],
    "name:und_x_variant":[
        "Zaobol\u2019"
    ],
    "wof:name":"Zaobol'",
    "wof:placetype":"locality"
},
  "geometry": {"coordinates":[29.5668,55.4362],"type":"Point"}
}