{
  "type": "Feature",
  "properties": {
    "gn:admin1_code":"1.0",
    "gn:asciiname":"Rossokhi",
    "gn:country_code":"BY",
    "gn:dem":159,
    "gn:feature_class":"P",
    "gn:feature_code":"PPL",
    "gn:name":"Rossokhi",
    "gn:population":0,
    "gn:timezone":"Europe/Minsk",
    "iso:country":"BY",
    "name:rus_x_preferred":[
        "\u0420\u043e\u0441\u0441\u043e\u0445\u0438"
    ],
    "wof:name":"Rossokhi",
    "wof:placetype":"locality"
},
  "geometry": {"coordinates":[24.5961,52.6108],"type":"Point"}
}