{
  "type": "Feature",
  "properties": {
    "gn:admin1_code":"1.0",
    "gn:asciiname":"Selovshchina",
    "gn:country_code":"BY",
    "gn:dem":150,
    "gn:feature_class":"P",
    "gn:feature_code":"PPL",
    "gn:name":"Selovshchina",
    "gn:population":0,
    "gn:timezone":"Europe/Minsk",
    "iso:country":"BY",
    "name:rus_x_preferred":[
        "\u0421\u0435\u043b\u043e\u0432\u0449\u0438\u043d\u0430"
    ],
    "wof:name":"Selovshchina",
    "wof:placetype":"locality"
},
  "geometry": {"coordinates":[24.9187,52.5473],"type":"Point"}
}