{
  "type": "Feature",
  "properties": {
    "gn:admin1_code":"7.0",
    "gn:asciiname":"Chuvatovo",
    "gn:country_code":"BY",
    "gn:dem":211,
    "gn:feature_class":"P",
    "gn:feature_code":"PPL",
    "gn:name":"Chuvatovo",
    "gn:population":0,
    "gn:timezone":"Europe/Minsk",
    "iso:country":"BY",
    "name:rus_x_preferred":[
        "\u0427\u0443\u0432\u0430\u0442\u043e\u0432\u043e"
    ],
    "wof:name":"Chuvatovo",
    "wof:placetype":"locality"
},
  "geometry": {"coordinates":[29.8991,54.5672],"type":"Point"}
}