{
  "type": "Feature",
  "properties": {
    "gn:admin1_code":"7.0",
    "gn:asciiname":"Shugaylovo",
    "gn:country_code":"BY",
    "gn:dem":206,
    "gn:feature_class":"P",
    "gn:feature_code":"PPL",
    "gn:name":"Shugaylovo",
    "gn:population":0,
    "gn:timezone":"Europe/Minsk",
    "iso:country":"BY",
    "name:rus_x_preferred":[
        "\u0428\u0443\u0433\u0430\u0439\u043b\u043e\u0432\u043e"
    ],
    "wof:name":"Shugaylovo",
    "wof:placetype":"locality"
},
  "geometry": {"coordinates":[30.5024,54.5379],"type":"Point"}
}