{
  "type": "Feature",
  "properties": {
    "gn:admin1_code":"7.0",
    "gn:asciiname":"Tribany",
    "gn:country_code":"BY",
    "gn:dem":192,
    "gn:feature_class":"P",
    "gn:feature_code":"PPL",
    "gn:name":"Tribany",
    "gn:population":0,
    "gn:timezone":"Europe/Minsk",
    "iso:country":"BY",
    "name:rus_x_preferred":[
        "\u0422\u0440\u0438\u0431\u0430\u043d\u044b"
    ],
    "wof:name":"Tribany",
    "wof:placetype":"locality"
},
  "geometry": {"coordinates":[31.0369,54.574],"type":"Point"}
}