{
  "type": "Feature",
  "properties": {
    "gn:admin1_code":"6.0",
    "gn:asciiname":"Maloye Chernoye",
    "gn:country_code":"BY",
    "gn:dem":199,
    "gn:feature_class":"P",
    "gn:feature_code":"PPL",
    "gn:name":"Maloye Ch\u00ebrnoye",
    "gn:population":0,
    "gn:timezone":"Europe/Minsk",
    "iso:country":"BY",
    "name:rus_x_preferred":[
        "\u041c\u0430\u043b\u043e\u0435 \u0427\u0451\u0440\u043d\u043e\u0435"
    ],
    "name:und_x_variant":[
        "Maloye Ch\u00ebrnoye"
    ],
    "wof:name":"Maloye Chernoye",
    "wof:placetype":"locality"
},
  "geometry": {"coordinates":[30.1367,54.1778],"type":"Point"}
}