{
  "type": "Feature",
  "properties": {
    "gn:admin1_code":"3.0",
    "gn:asciiname":"Snezhnaya",
    "gn:country_code":"BY",
    "gn:dem":188,
    "gn:feature_class":"P",
    "gn:feature_code":"PPL",
    "gn:name":"Snezhnaya",
    "gn:population":0,
    "gn:timezone":"Europe/Minsk",
    "iso:country":"BY",
    "name:bel_x_preferred":[
        "Snyezhnaya"
    ],
    "name:rus_x_preferred":[
        "\u0421\u043d\u0435\u0436\u043d\u0430\u044f"
    ],
    "wof:name":"Snezhnaya",
    "wof:placetype":"locality"
},
  "geometry": {"coordinates":[24.9793,53.1821],"type":"Point"}
}