{
  "type": "Feature",
  "properties": {
    "gn:admin1_code":"3.0",
    "gn:asciiname":"Gotevichi",
    "gn:country_code":"BY",
    "gn:dem":172,
    "gn:feature_class":"P",
    "gn:feature_code":"PPL",
    "gn:name":"Gotevichi",
    "gn:population":0,
    "gn:timezone":"Europe/Minsk",
    "iso:country":"BY",
    "name:rus_x_preferred":[
        "\u0413\u043e\u0442\u0435\u0432\u0438\u0447\u0438"
    ],
    "wof:name":"Gotevichi",
    "wof:placetype":"locality"
},
  "geometry": {"coordinates":[24.2509,53.2235],"type":"Point"}
}