{
  "type": "Feature",
  "properties": {
    "gn:admin1_code":"7.0",
    "gn:asciiname":"Ostanovka",
    "gn:country_code":"BY",
    "gn:dem":135,
    "gn:feature_class":"P",
    "gn:feature_code":"PPL",
    "gn:name":"Ostanovka",
    "gn:population":0,
    "gn:timezone":"Europe/Minsk",
    "iso:country":"BY",
    "name:eng_x_preferred":[
        "Ostankovo"
    ],
    "name:rus_x_preferred":[
        "\u041e\u0441\u0442\u0430\u043d\u043e\u0432\u043a\u0430"
    ],
    "name:und_x_variant":[
        "Ostanuvka",
        "Ostankovo",
        "Ostanovka"
    ],
    "wof:name":"Ostanovka",
    "wof:placetype":"locality"
},
  "geometry": {"coordinates":[27.4022,55.4451],"type":"Point"}
}