{
  "type": "Feature",
  "properties": {
    "gn:admin1_code":"7.0",
    "gn:asciiname":"Monastyr'",
    "gn:country_code":"BY",
    "gn:dem":243,
    "gn:feature_class":"P",
    "gn:feature_code":"PPL",
    "gn:name":"Monastyr\u2019",
    "gn:population":0,
    "gn:timezone":"Europe/Minsk",
    "iso:country":"BY",
    "name:rus_x_preferred":[
        "\u041c\u043e\u043d\u0430\u0441\u0442\u044b\u0440\u044c"
    ],
    "name:und_x_variant":[
        "Monastyr\u2019"
    ],
    "wof:name":"Monastyr'",
    "wof:placetype":"locality"
},
  "geometry": {"coordinates":[29.7405,54.5871],"type":"Point"}
}