{
  "type": "Feature",
  "properties": {
    "gn:admin1_code":"6.0",
    "gn:asciiname":"Samulki",
    "gn:country_code":"BY",
    "gn:dem":169,
    "gn:feature_class":"P",
    "gn:feature_code":"PPL",
    "gn:name":"Samulki",
    "gn:population":0,
    "gn:timezone":"Europe/Minsk",
    "iso:country":"BY",
    "name:rus_x_preferred":[
        "\u0421\u0430\u043c\u0443\u043b\u043a\u0438"
    ],
    "wof:name":"Samulki",
    "wof:placetype":"locality"
},
  "geometry": {"coordinates":[30.7689,53.8281],"type":"Point"}
}