{
  "type": "Feature",
  "properties": {
    "iso:country":"BY",
    "name:bel_x_preferred":[
        "\u041f\u0430\u043f\u043b\u0430\u0432\u044b"
    ],
    "name:eng_x_preferred":[
        "Poplavy"
    ],
    "name:rus_x_preferred":[
        "\u041f\u043e\u043f\u043b\u0430\u0432\u044b"
    ],
    "name:unk_x_variant":[
        "Paplavy"
    ],
    "qs:gn_country":"BY",
    "qs:gn_fcode":"PPL",
    "qs:gn_pop":650,
    "qs:name":"Poplavy",
    "qs:name_adm0":"Belarus",
    "qs:name_adm1":"Minskaya Voblasts'",
    "qs:photos":0,
    "qs:photos_1k":0,
    "qs:photos_9k":0,
    "qs:photos_9r":0,
    "qs:photos_all":0,
    "qs:photos_sr":0,
    "qs:placetype":"Town",
    "qs:pop_sr":"2",
    "qs:woe_adm0":23424765,
    "wof:name":"Poplavy",
    "wof:placetype":"locality",
    "wof:population":650
},
  "geometry": {"coordinates":[28.8698,53.8066],"type":"Point"}
}