{
  "type": "Feature",
  "properties": {
    "gn:admin1_code":"6.0",
    "gn:asciiname":"Irtishchevo",
    "gn:country_code":"BY",
    "gn:dem":206,
    "gn:feature_class":"P",
    "gn:feature_code":"PPL",
    "gn:name":"Irtishchevo",
    "gn:population":0,
    "gn:timezone":"Europe/Minsk",
    "iso:country":"BY",
    "name:rus_x_preferred":[
        "\u0418\u0440\u0442\u0438\u0449\u0435\u0432\u043e"
    ],
    "wof:name":"Irtishchevo",
    "wof:placetype":"locality"
},
  "geometry": {"coordinates":[31.5005,54.0789],"type":"Point"}
}