{
  "type": "Feature",
  "properties": {
    "gn:admin1_code":"5.0",
    "gn:asciiname":"Mochany",
    "gn:country_code":"BY",
    "gn:dem":240,
    "gn:feature_class":"P",
    "gn:feature_code":"PPL",
    "gn:name":"Mochany",
    "gn:population":0,
    "gn:timezone":"Europe/Minsk",
    "iso:country":"BY",
    "name:rus_x_preferred":[
        "\u041c\u043e\u0447\u0430\u043d\u044b"
    ],
    "wof:name":"Mochany",
    "wof:placetype":"locality"
},
  "geometry": {"coordinates":[27.6279,54.0788],"type":"Point"}
}