{
  "type": "Feature",
  "properties": {
    "gn:admin1_code":"6.0",
    "gn:asciiname":"Sidorovka",
    "gn:country_code":"BY",
    "gn:dem":184,
    "gn:feature_class":"P",
    "gn:feature_code":"PPL",
    "gn:name":"Sidorovka",
    "gn:population":0,
    "gn:timezone":"Europe/Minsk",
    "iso:country":"BY",
    "name:bak_x_preferred":[
        "\u0421\u0438\u0434\u043e\u0440\u043e\u0432\u043a\u0430"
    ],
    "name:che_x_preferred":[
        "\u0421\u0438\u0434\u043e\u0440\u043e\u0432\u043a\u0430"
    ],
    "name:hye_x_preferred":[
        "\u054d\u056b\u0564\u0578\u0580\u0578\u057e\u056f\u0561"
    ],
    "name:kaz_x_preferred":[
        "\u0421\u0438\u0434\u043e\u0440\u043e\u0432\u043a\u0430"
    ],
    "name:kir_x_preferred":[
        "\u0421\u0438\u0434\u043e\u0440\u043e\u0432\u043a\u0430"
    ],
    "name:rus_x_preferred":[
        "\u0421\u0438\u0434\u043e\u0440\u043e\u0432\u043a\u0430"
    ],
    "name:tat_x_preferred":[
        "\u0421\u0438\u0434\u043e\u0440\u043e\u0432\u043a\u0430"
    ],
    "name:ukr_x_preferred":[
        "\u0421\u0438\u0434\u043e\u0440\u043e\u0432\u043a\u0430"
    ],
    "wof:name":"Sidorovka",
    "wof:placetype":"locality"
},
  "geometry": {"coordinates":[32.1714,53.5637],"type":"Point"}
}