{
  "type": "Feature",
  "properties": {
    "gn:admin1_code":"5.0",
    "gn:asciiname":"Kuleshi",
    "gn:country_code":"BY",
    "gn:dem":150,
    "gn:feature_class":"P",
    "gn:feature_code":"PPL",
    "gn:name":"Kuleshi",
    "gn:population":0,
    "gn:timezone":"Europe/Minsk",
    "iso:country":"BY",
    "name:rus_x_preferred":[
        "\u041a\u0443\u043b\u0435\u0448\u0438"
    ],
    "wof:name":"Kuleshi",
    "wof:placetype":"locality"
},
  "geometry": {"coordinates":[27.5219,52.9103],"type":"Point"}
}