{
  "type": "Feature",
  "properties": {
    "gn:admin1_code":"7.0",
    "gn:asciiname":"Myazha",
    "gn:country_code":"BY",
    "gn:dem":150,
    "gn:feature_class":"P",
    "gn:feature_code":"PPL",
    "gn:name":"Myazha",
    "gn:population":0,
    "gn:timezone":"Europe/Minsk",
    "iso:country":"BY",
    "name:bel_x_preferred":[
        "\u041c\u044f\u0436\u0430"
    ],
    "name:eng_x_preferred":[
        "Mezha"
    ],
    "name:rus_x_preferred":[
        "\u041c\u0435\u0436\u0430"
    ],
    "name:und_x_variant":[
        "Mezha",
        "Myazha"
    ],
    "wof:name":"Myazha",
    "wof:placetype":"locality"
},
  "geometry": {"coordinates":[30.421,55.6805],"type":"Point"}
}