{
  "type": "Feature",
  "properties": {
    "gn:admin1_code":"2.0",
    "gn:asciiname":"Zarubanoye",
    "gn:country_code":"BY",
    "gn:dem":138,
    "gn:feature_class":"P",
    "gn:feature_code":"PPL",
    "gn:name":"Zarubanoye",
    "gn:population":0,
    "gn:timezone":"Europe/Minsk",
    "iso:country":"BY",
    "name:rus_x_preferred":[
        "\u0417\u0430\u0440\u0443\u0431\u0430\u043d\u043e\u0435"
    ],
    "name:und_x_variant":[
        "Khutor Zarubany",
        "Zarubany",
        "Zarubanoye"
    ],
    "wof:name":"Zarubanoye",
    "wof:placetype":"locality"
},
  "geometry": {"coordinates":[28.5625,51.929],"type":"Point"}
}