{
  "type": "Feature",
  "properties": {
    "gn:admin1_code":"5.0",
    "gn:asciiname":"Zvonka",
    "gn:country_code":"BY",
    "gn:dem":172,
    "gn:feature_class":"P",
    "gn:feature_code":"PPL",
    "gn:name":"Zvonka",
    "gn:population":0,
    "gn:timezone":"Europe/Minsk",
    "iso:country":"BY",
    "name:rus_x_preferred":[
        "\u0417\u0432\u043e\u043d\u043a\u0430"
    ],
    "name:und_x_variant":[
        "Mashuki"
    ],
    "wof:name":"Zvonka",
    "wof:placetype":"locality"
},
  "geometry": {"coordinates":[26.4819,52.9118],"type":"Point"}
}