{
  "type": "Feature",
  "properties": {
    "gn:admin1_code":"7.0",
    "gn:asciiname":"Levshi",
    "gn:country_code":"BY",
    "gn:dem":138,
    "gn:feature_class":"P",
    "gn:feature_code":"PPL",
    "gn:name":"Levshi",
    "gn:population":0,
    "gn:timezone":"Europe/Minsk",
    "iso:country":"BY",
    "name:rus_x_preferred":[
        "\u041b\u0435\u0432\u0448\u0438"
    ],
    "wof:name":"Levshi",
    "wof:placetype":"locality"
},
  "geometry": {"coordinates":[29.2623,55.3572],"type":"Point"}
}