{
  "type": "Feature",
  "properties": {
    "gn:admin1_code":"0.0",
    "gn:asciiname":"Chervonyy Ostrov",
    "gn:cc2":"BY",
    "gn:country_code":"BY",
    "gn:dem":146,
    "gn:feature_class":"P",
    "gn:feature_code":"PPL",
    "gn:name":"Chervonyy Ostrov",
    "gn:population":0,
    "gn:timezone":"Europe/Minsk",
    "iso:country":"BY",
    "name:und_x_variant":[
        "Chervony Ostrov",
        "Chervonyy Ostrov"
    ],
    "wof:name":"Chervonyy Ostrov",
    "wof:placetype":"locality"
},
  "geometry": {"coordinates":[29.45,53.06667],"type":"Point"}
}