{
  "type": "Feature",
  "properties": {
    "gn:admin1_code":"5.0",
    "gn:asciiname":"Agarki",
    "gn:country_code":"BY",
    "gn:dem":236,
    "gn:feature_class":"P",
    "gn:feature_code":"PPL",
    "gn:name":"Agarki",
    "gn:population":0,
    "gn:timezone":"Europe/Minsk",
    "iso:country":"BY",
    "name:rus_x_preferred":[
        "\u0410\u0433\u0430\u0440\u043a\u0438"
    ],
    "wof:name":"Agarki",
    "wof:placetype":"locality"
},
  "geometry": {"coordinates":[27.2873,54.1139],"type":"Point"}
}