{
  "type": "Feature",
  "properties": {
    "gn:admin1_code":"6.0",
    "gn:asciiname":"Kopani",
    "gn:country_code":"BY",
    "gn:dem":158,
    "gn:feature_class":"P",
    "gn:feature_code":"PPL",
    "gn:name":"Kopani",
    "gn:population":0,
    "gn:timezone":"Europe/Minsk",
    "iso:country":"BY",
    "name:eng_x_preferred":[
        "Kopani"
    ],
    "name:rus_x_preferred":[
        "\u041a\u043e\u043f\u0430\u043d\u0438"
    ],
    "name:rus_x_variant":[
        "\u041a\u043e\u043f\u0430\u043d\u0456"
    ],
    "wof:name":"Kopani",
    "wof:placetype":"locality"
},
  "geometry": {"coordinates":[30.734,53.7181],"type":"Point"}
}