{
  "type": "Feature",
  "properties": {
    "gn:admin1_code":"7.0",
    "gn:asciiname":"Shupeyki",
    "gn:country_code":"BY",
    "gn:dem":119,
    "gn:feature_class":"P",
    "gn:feature_code":"PPL",
    "gn:name":"Shupeyki",
    "gn:population":0,
    "gn:timezone":"Europe/Minsk",
    "iso:country":"BY",
    "name:rus_x_preferred":[
        "\u0428\u0443\u043f\u0435\u0439\u043a\u0438"
    ],
    "wof:name":"Shupeyki",
    "wof:placetype":"locality"
},
  "geometry": {"coordinates":[28.3234,55.5956],"type":"Point"}
}