{
  "type": "Feature",
  "properties": {
    "gn:admin1_code":"6.0",
    "gn:asciiname":"Pyachary",
    "gn:country_code":"BY",
    "gn:dem":171,
    "gn:feature_class":"P",
    "gn:feature_code":"PPL",
    "gn:name":"Pyachary",
    "gn:population":0,
    "gn:timezone":"Europe/Minsk",
    "iso:country":"BY",
    "name:bel_x_preferred":[
        "\u041f\u044f\u0447\u0430\u0440\u044b"
    ],
    "name:und_x_variant":[
        "Pechary"
    ],
    "wof:name":"Pyachary",
    "wof:placetype":"locality"
},
  "geometry": {"coordinates":[32.223,53.4324],"type":"Point"}
}