{
  "type": "Feature",
  "properties": {
    "gn:admin1_code":"2.0",
    "gn:asciiname":"Al'sagorka",
    "gn:country_code":"BY",
    "gn:dem":145,
    "gn:feature_class":"P",
    "gn:feature_code":"PPL",
    "gn:name":"Al\u2019sagorka",
    "gn:population":0,
    "gn:timezone":"Europe/Minsk",
    "iso:country":"BY",
    "name:rus_x_preferred":[
        "\u0410\u043b\u044c\u0441\u0430\u0433\u043e\u0440\u043a\u0430"
    ],
    "name:und_x_variant":[
        "Al\u2019sagorka"
    ],
    "wof:name":"Al'sagorka",
    "wof:placetype":"locality"
},
  "geometry": {"coordinates":[30.0084,52.9884],"type":"Point"}
}