{
  "type": "Feature",
  "properties": {
    "gn:admin1_code":"5.0",
    "gn:asciiname":"Rochevichi",
    "gn:country_code":"BY",
    "gn:dem":259,
    "gn:feature_class":"P",
    "gn:feature_code":"PPL",
    "gn:name":"Rochevichi",
    "gn:population":0,
    "gn:timezone":"Europe/Minsk",
    "iso:country":"BY",
    "name:rus_x_preferred":[
        "\u0420\u043e\u0447\u0435\u0432\u0438\u0447\u0438"
    ],
    "wof:name":"Rochevichi",
    "wof:placetype":"locality"
},
  "geometry": {"coordinates":[26.8406,53.8199],"type":"Point"}
}