{
  "type": "Feature",
  "properties": {
    "gn:admin1_code":"6.0",
    "gn:asciiname":"Trosna",
    "gn:country_code":"BY",
    "gn:dem":204,
    "gn:feature_class":"P",
    "gn:feature_code":"PPL",
    "gn:name":"Trosna",
    "gn:population":0,
    "gn:timezone":"Europe/Minsk",
    "iso:country":"BY",
    "name:rus_x_preferred":[
        "\u0422\u0440\u043e\u0441\u043d\u0430"
    ],
    "wof:name":"Trosna",
    "wof:placetype":"locality"
},
  "geometry": {"coordinates":[30.127,54.2058],"type":"Point"}
}