{
  "type": "Feature",
  "properties": {
    "gn:admin1_code":"6.0",
    "gn:asciiname":"Sininshchina",
    "gn:country_code":"BY",
    "gn:dem":179,
    "gn:feature_class":"P",
    "gn:feature_code":"PPL",
    "gn:name":"Sininshchina",
    "gn:population":0,
    "gn:timezone":"Europe/Minsk",
    "iso:country":"BY",
    "name:rus_x_preferred":[
        "\u0421\u0438\u043d\u0438\u043d\u0449\u0438\u043d\u0430"
    ],
    "wof:name":"Sininshchina",
    "wof:placetype":"locality"
},
  "geometry": {"coordinates":[30.0351,53.79],"type":"Point"}
}