{
  "type": "Feature",
  "properties": {
    "gn:admin1_code":"7.0",
    "gn:asciiname":"Rybaki",
    "gn:country_code":"BY",
    "gn:dem":187,
    "gn:feature_class":"P",
    "gn:feature_code":"PPL",
    "gn:name":"Rybaki",
    "gn:population":0,
    "gn:timezone":"Europe/Minsk",
    "iso:country":"BY",
    "name:rus_x_preferred":[
        "\u0420\u044b\u0431\u0430\u043a\u0438"
    ],
    "wof:name":"Rybaki",
    "wof:placetype":"locality"
},
  "geometry": {"coordinates":[30.6035,55.2463],"type":"Point"}
}