{
  "type": "Feature",
  "properties": {
    "gn:admin1_code":"7.0",
    "gn:asciiname":"Murav'i",
    "gn:country_code":"BY",
    "gn:dem":146,
    "gn:feature_class":"P",
    "gn:feature_code":"PPL",
    "gn:name":"Murav\u2019i",
    "gn:population":0,
    "gn:timezone":"Europe/Minsk",
    "iso:country":"BY",
    "name:rus_x_preferred":[
        "\u041c\u0443\u0440\u0430\u0432\u044c\u0438"
    ],
    "name:und_x_variant":[
        "Murav\u2019i"
    ],
    "wof:name":"Murav'i",
    "wof:placetype":"locality"
},
  "geometry": {"coordinates":[28.375,55.3004],"type":"Point"}
}