{
  "type": "Feature",
  "properties": {
    "gn:admin1_code":"6.0",
    "gn:asciiname":"Brytsalavichy",
    "gn:country_code":"BY",
    "gn:dem":150,
    "gn:feature_class":"P",
    "gn:feature_code":"PPL",
    "gn:name":"Brytsalavichy",
    "gn:population":0,
    "gn:timezone":"Europe/Minsk",
    "iso:country":"BY",
    "name:bel_x_preferred":[
        "\u0411\u0440\u044b\u0446\u0430\u043b\u0430\u0432\u0456\u0447\u044b"
    ],
    "name:und_x_variant":[
        "Britsalovichi",
        "Brytsalavichy"
    ],
    "wof:name":"Brytsalavichy",
    "wof:placetype":"locality"
},
  "geometry": {"coordinates":[28.8298,53.3747],"type":"Point"}
}