{
  "type": "Feature",
  "properties": {
    "gn:admin1_code":"0.0",
    "gn:asciiname":"Zaozertsy",
    "gn:cc2":"BY",
    "gn:country_code":"BY",
    "gn:dem":133,
    "gn:feature_class":"P",
    "gn:feature_code":"PPL",
    "gn:name":"Zaozertsy",
    "gn:population":0,
    "gn:timezone":"Europe/Minsk",
    "iso:country":"BY",
    "name:und_x_variant":[
        "Zaozertse",
        "Zaozertsy"
    ],
    "wof:name":"Zaozertsy",
    "wof:placetype":"locality"
},
  "geometry": {"coordinates":[28.15,55.38333000000001],"type":"Point"}
}