{
  "type": "Feature",
  "properties": {
    "gn:admin1_code":"2.0",
    "gn:asciiname":"Selishche Vtoroye",
    "gn:country_code":"BY",
    "gn:dem":129,
    "gn:feature_class":"P",
    "gn:feature_code":"PPL",
    "gn:name":"Selishche Vtoroye",
    "gn:population":0,
    "gn:timezone":"Europe/Minsk",
    "iso:country":"BY",
    "name:rus_x_preferred":[
        "\u0421\u0435\u043b\u0438\u0449\u0435 \u0412\u0442\u043e\u0440\u043e\u0435"
    ],
    "name:und_x_variant":[
        "Vtoroye Selishche"
    ],
    "wof:name":"Selishche Vtoroye",
    "wof:placetype":"locality"
},
  "geometry": {"coordinates":[31.4906,52.37600000000001],"type":"Point"}
}