{
  "type": "Feature",
  "properties": {
    "gn:admin1_code":"5.0",
    "gn:asciiname":"Ber'ye",
    "gn:country_code":"BY",
    "gn:dem":162,
    "gn:feature_class":"P",
    "gn:feature_code":"PPL",
    "gn:name":"Ber\u2019ye",
    "gn:population":0,
    "gn:timezone":"Europe/Minsk",
    "iso:country":"BY",
    "name:rus_x_preferred":[
        "\u0411\u0435\u0440\u044c\u0435"
    ],
    "name:und_x_variant":[
        "Ber\u2019ye",
        "Ber\u2019ya"
    ],
    "wof:name":"Ber'ye",
    "wof:placetype":"locality"
},
  "geometry": {"coordinates":[29.0297,53.9749],"type":"Point"}
}