{
  "type": "Feature",
  "properties": {
    "gn:gn_country":"BY",
    "gn:gn_fcode":"PPL",
    "gn:gn_pop":6300,
    "gn:population":6300,
    "iso:country":"BY",
    "name:bel_x_preferred":[
        "\u0420\u0430\u043a\u0430\u045e"
    ],
    "name:eng_x_preferred":[
        "Rakov"
    ],
    "name:est_x_preferred":[
        "Raka\u016d"
    ],
    "name:fre_x_preferred":[
        "Rak\u00f3w"
    ],
    "name:ger_x_preferred":[
        "Rakaw"
    ],
    "name:heb_x_preferred":[
        "\u05e8\u05d0\u05e7\u05d0\u05d1"
    ],
    "name:pol_x_preferred":[
        "Rak\u00f3w"
    ],
    "name:rus_x_preferred":[
        "\u0420\u0430\u043a\u043e\u0432"
    ],
    "name:swe_x_preferred":[
        "Raka\u016d"
    ],
    "name:unk_x_variant":[
        "Rak\u00f3w"
    ],
    "qs_pg:aaroncc":"BY",
    "qs_pg:gn_country":"BY",
    "qs_pg:gn_fcode":"PPL",
    "qs_pg:gn_pop":6300,
    "qs_pg:name":"Rakaw",
    "qs_pg:photos_9r":0,
    "qs_pg:photos_sr":0,
    "qs_pg:pop_sr":5,
    "qs_pg:qs_pg_placetype":"locality",
    "wof:name":"Rakaw",
    "wof:placetype":"locality",
    "wof:population":6300
},
  "geometry": {"coordinates":[27.0562,53.9674],"type":"Point"}
}