{
  "type": "Feature",
  "properties": {
    "gn:admin1_code":"6.0",
    "gn:asciiname":"Kazimirovka",
    "gn:country_code":"BY",
    "gn:dem":178,
    "gn:feature_class":"P",
    "gn:feature_code":"PPL",
    "gn:name":"Kazimirovka",
    "gn:population":0,
    "gn:timezone":"Europe/Minsk",
    "iso:country":"BY",
    "name:rus_x_preferred":[
        "\u041a\u0430\u0437\u0438\u043c\u0438\u0440\u043e\u0432\u043a\u0430"
    ],
    "wof:name":"Kazimirovka",
    "wof:placetype":"locality"
},
  "geometry": {"coordinates":[30.2507,53.9246],"type":"Point"}
}