{
  "type": "Feature",
  "properties": {
    "gn:admin1_code":"2.0",
    "gn:asciiname":"Bulavki",
    "gn:country_code":"BY",
    "gn:dem":129,
    "gn:feature_class":"P",
    "gn:feature_code":"PPL",
    "gn:name":"Bulavki",
    "gn:population":0,
    "gn:timezone":"Europe/Minsk",
    "iso:country":"BY",
    "name:rus_x_preferred":[
        "\u0411\u0443\u043b\u0430\u0432\u043a\u0438"
    ],
    "wof:name":"Bulavki",
    "wof:placetype":"locality"
},
  "geometry": {"coordinates":[29.3525,52.2555],"type":"Point"}
}