{
  "type": "Feature",
  "properties": {
    "gn:admin1_code":"3.0",
    "gn:asciiname":"Gorbatovichi",
    "gn:country_code":"BY",
    "gn:dem":201,
    "gn:feature_class":"P",
    "gn:feature_code":"PPL",
    "gn:name":"Gorbatovichi",
    "gn:population":0,
    "gn:timezone":"Europe/Minsk",
    "iso:country":"BY",
    "name:rus_x_preferred":[
        "\u0413\u043e\u0440\u0431\u0430\u0442\u043e\u0432\u0438\u0447\u0438"
    ],
    "wof:name":"Gorbatovichi",
    "wof:placetype":"locality"
},
  "geometry": {"coordinates":[26.0722,53.392],"type":"Point"}
}