{
  "type": "Feature",
  "properties": {
    "gn:admin1_code":"5.0",
    "gn:asciiname":"Pomorshchina",
    "gn:country_code":"BY",
    "gn:dem":209,
    "gn:feature_class":"P",
    "gn:feature_code":"PPL",
    "gn:name":"Pomorshchina",
    "gn:population":0,
    "gn:timezone":"Europe/Minsk",
    "iso:country":"BY",
    "name:rus_x_preferred":[
        "\u041f\u043e\u043c\u043e\u0440\u0449\u0438\u043d\u0430"
    ],
    "wof:name":"Pomorshchina",
    "wof:placetype":"locality"
},
  "geometry": {"coordinates":[27.0634,53.9581],"type":"Point"}
}