{
  "type": "Feature",
  "properties": {
    "gn:admin1_code":"5.0",
    "gn:asciiname":"Utekha",
    "gn:country_code":"BY",
    "gn:dem":222,
    "gn:feature_class":"P",
    "gn:feature_code":"PPL",
    "gn:name":"Utekha",
    "gn:population":0,
    "gn:timezone":"Europe/Minsk",
    "iso:country":"BY",
    "name:rus_x_preferred":[
        "\u0423\u0442\u0435\u0445\u0430"
    ],
    "wof:name":"Utekha",
    "wof:placetype":"locality"
},
  "geometry": {"coordinates":[28.6279,54.6056],"type":"Point"}
}