{
  "type": "Feature",
  "properties": {
    "gn:admin1_code":"7.0",
    "gn:admin2_code":"623176",
    "gn:asciiname":"Paris",
    "gn:country_code":"BY",
    "gn:dem":153,
    "gn:elevation":"151.0",
    "gn:feature_class":"P",
    "gn:feature_code":"PPL",
    "gn:name":"Paris",
    "gn:population":330,
    "gn:timezone":"Europe/Minsk",
    "iso:country":"BY",
    "name:bel_x_historical":[
        "\u041d\u0430\u0432\u0430\u0434\u0440\u0443\u0446\u043a"
    ],
    "name:bel_x_preferred":[
        "\u041f\u0430\u0440\u044b\u0301\u0436"
    ],
    "name:bel_x_variant":[
        "\u041d\u0430\u0432\u0430\u0434\u0440\u0443\u0446\u043a"
    ],
    "name:deu_x_preferred":[
        "Paris"
    ],
    "name:rus_x_preferred":[
        "\u041f\u0430\u0440\u0438\u0436"
    ],
    "name:und_x_variant":[
        "Navadrutsk",
        "Novodrutsk",
        "Paris"
    ],
    "wof:name":"Paris",
    "wof:placetype":"locality",
    "wof:population":330
},
  "geometry": {"coordinates":[27.38456,55.15464],"type":"Point"}
}