{
  "type": "Feature",
  "properties": {
    "gn:admin1_code":"7.0",
    "gn:asciiname":"Ubertsy",
    "gn:country_code":"BY",
    "gn:dem":178,
    "gn:feature_class":"P",
    "gn:feature_code":"PPL",
    "gn:name":"Ubertsy",
    "gn:population":0,
    "gn:timezone":"Europe/Minsk",
    "iso:country":"BY",
    "name:rus_x_preferred":[
        "\u0423\u0431\u0435\u0440\u0446\u044b"
    ],
    "wof:name":"Ubertsy",
    "wof:placetype":"locality"
},
  "geometry": {"coordinates":[28.4639,54.9611],"type":"Point"}
}