{
  "type": "Feature",
  "properties": {
    "gn:admin1_code":"1.0",
    "gn:asciiname":"Zalese",
    "gn:country_code":"BY",
    "gn:dem":182,
    "gn:feature_class":"P",
    "gn:feature_code":"PPL",
    "gn:name":"Zalese",
    "gn:population":0,
    "gn:timezone":"Europe/Minsk",
    "iso:country":"BY",
    "name:rus_x_preferred":[
        "Zales\u2019ye"
    ],
    "name:rus_x_variant":[
        "\u0417\u0430\u043b\u0435\u0441\u044c\u0435"
    ],
    "wof:name":"Zalese",
    "wof:placetype":"locality"
},
  "geometry": {"coordinates":[26.1718,53.2826],"type":"Point"}
}