{
  "type": "Feature",
  "properties": {
    "gn:admin1_code":"5.0",
    "gn:asciiname":"Sosnovtsy",
    "gn:country_code":"BY",
    "gn:dem":290,
    "gn:feature_class":"P",
    "gn:feature_code":"PPL",
    "gn:name":"Sosnovtsy",
    "gn:population":0,
    "gn:timezone":"Europe/Minsk",
    "iso:country":"BY",
    "name:rus_x_preferred":[
        "\u0421\u043e\u0441\u043d\u043e\u0432\u0446\u044b"
    ],
    "wof:name":"Sosnovtsy",
    "wof:placetype":"locality"
},
  "geometry": {"coordinates":[26.9957,54.0602],"type":"Point"}
}