{
  "type": "Feature",
  "properties": {
    "gn:admin1_code":"3.0",
    "gn:asciiname":"Savichi",
    "gn:country_code":"BY",
    "gn:dem":194,
    "gn:feature_class":"P",
    "gn:feature_code":"PPL",
    "gn:name":"Savichi",
    "gn:population":0,
    "gn:timezone":"Europe/Minsk",
    "iso:country":"BY",
    "name:bel_x_preferred":[
        "Savichy"
    ],
    "name:bel_x_variant":[
        "\u0421\u0430\u0432\u0456\u0447\u044b"
    ],
    "name:rus_x_preferred":[
        "\u0421\u0430\u0432\u0438\u0447\u0438"
    ],
    "wof:name":"Savichi",
    "wof:placetype":"locality"
},
  "geometry": {"coordinates":[24.6237,53.168],"type":"Point"}
}