{
  "type": "Feature",
  "properties": {
    "gn:admin1_code":"3.0",
    "gn:asciiname":"Goridenyaty",
    "gn:country_code":"BY",
    "gn:dem":166,
    "gn:feature_class":"P",
    "gn:feature_code":"PPL",
    "gn:name":"Goridenyaty",
    "gn:population":0,
    "gn:timezone":"Europe/Minsk",
    "iso:country":"BY",
    "name:rus_x_preferred":[
        "\u0413\u043e\u0440\u0438\u0434\u0435\u043d\u044f\u0442\u044b"
    ],
    "name:und_x_variant":[
        "Horodzini\u0119ta",
        "Goridinenty",
        "Goridenyaty"
    ],
    "wof:name":"Goridenyaty",
    "wof:placetype":"locality"
},
  "geometry": {"coordinates":[26.4741,54.551],"type":"Point"}
}