{
  "type": "Feature",
  "properties": {
    "gn:admin1_code":"6.0",
    "gn:asciiname":"Budovlya",
    "gn:country_code":"BY",
    "gn:dem":174,
    "gn:feature_class":"P",
    "gn:feature_code":"PPL",
    "gn:name":"Budovlya",
    "gn:population":0,
    "gn:timezone":"Europe/Minsk",
    "iso:country":"BY",
    "name:rus_x_preferred":[
        "\u0411\u0443\u0434\u043e\u0432\u043b\u044f"
    ],
    "wof:name":"Budovlya",
    "wof:placetype":"locality"
},
  "geometry": {"coordinates":[29.9888,53.7891],"type":"Point"}
}