{
  "type": "Feature",
  "properties": {
    "gn:admin1_code":"5.0",
    "gn:asciiname":"Bol'shiye Nestanovichi",
    "gn:country_code":"BY",
    "gn:dem":202,
    "gn:feature_class":"P",
    "gn:feature_code":"PPL",
    "gn:name":"Bol\u2019shiye Nestanovichi",
    "gn:population":0,
    "gn:timezone":"Europe/Minsk",
    "iso:country":"BY",
    "name:rus_x_preferred":[
        "\u0411\u043e\u043b\u044c\u0448\u0438\u0435 \u041d\u0435\u0441\u0442\u0430\u043d\u043e\u0432\u0438\u0447\u0438"
    ],
    "name:und_x_variant":[
        "Bol\u2019shiye Nestanovichi"
    ],
    "wof:name":"Bol'shiye Nestanovichi",
    "wof:placetype":"locality"
},
  "geometry": {"coordinates":[27.6279,54.4784],"type":"Point"}
}