{
  "type": "Feature",
  "properties": {
    "gn:admin1_code":"6.0",
    "gn:asciiname":"Penyugi",
    "gn:country_code":"BY",
    "gn:dem":155,
    "gn:feature_class":"P",
    "gn:feature_code":"PPL",
    "gn:name":"Penyugi",
    "gn:population":0,
    "gn:timezone":"Europe/Minsk",
    "iso:country":"BY",
    "name:rus_x_preferred":[
        "\u041f\u0435\u043d\u044e\u0433\u0438"
    ],
    "wof:name":"Penyugi",
    "wof:placetype":"locality"
},
  "geometry": {"coordinates":[30.072,53.5093],"type":"Point"}
}