{
  "type": "Feature",
  "properties": {
    "gn:admin1_code":"6.0",
    "gn:asciiname":"Novyye Ovchinenki",
    "gn:country_code":"BY",
    "gn:dem":197,
    "gn:feature_class":"P",
    "gn:feature_code":"PPL",
    "gn:name":"Novyye Ovchinenki",
    "gn:population":0,
    "gn:timezone":"Europe/Minsk",
    "iso:country":"BY",
    "name:rus_x_preferred":[
        "\u041d\u043e\u0432\u044b\u0435 \u041e\u0432\u0447\u0438\u043d\u0435\u043d\u043a\u0438"
    ],
    "wof:name":"Novyye Ovchinenki",
    "wof:placetype":"locality"
},
  "geometry": {"coordinates":[30.1348,54.1558],"type":"Point"}
}