{
  "type": "Feature",
  "properties": {
    "gn:admin1_code":"7.0",
    "gn:asciiname":"Yanuylovo",
    "gn:country_code":"BY",
    "gn:dem":212,
    "gn:feature_class":"P",
    "gn:feature_code":"PPL",
    "gn:name":"Yanuylovo",
    "gn:population":0,
    "gn:timezone":"Europe/Minsk",
    "iso:country":"BY",
    "name:rus_x_preferred":[
        "\u042f\u043d\u0443\u0439\u043b\u043e\u0432\u043e"
    ],
    "name:und_x_variant":[
        "Yanuilovo",
        "Yanuylovo"
    ],
    "wof:name":"Yanuylovo",
    "wof:placetype":"locality"
},
  "geometry": {"coordinates":[30.0802,55.5711],"type":"Point"}
}