{
  "type": "Feature",
  "properties": {
    "gn:admin1_code":"5.0",
    "gn:asciiname":"Sivitsa",
    "gn:country_code":"BY",
    "gn:dem":167,
    "gn:feature_class":"P",
    "gn:feature_code":"PPL",
    "gn:name":"Sivitsa",
    "gn:population":0,
    "gn:timezone":"Europe/Minsk",
    "iso:country":"BY",
    "name:rus_x_preferred":[
        "\u0421\u0438\u0432\u0438\u0446\u0430"
    ],
    "wof:name":"Sivitsa",
    "wof:placetype":"locality"
},
  "geometry": {"coordinates":[28.5987,54.1186],"type":"Point"}
}