{
  "type": "Feature",
  "properties": {
    "gn:admin1_code":"3.0",
    "gn:asciiname":"Chekhovtsy",
    "gn:country_code":"BY",
    "gn:dem":143,
    "gn:feature_class":"P",
    "gn:feature_code":"PPL",
    "gn:name":"Chekhovtsy",
    "gn:population":0,
    "gn:timezone":"Europe/Minsk",
    "iso:country":"BY",
    "name:rus_x_preferred":[
        "\u0427\u0435\u0445\u043e\u0432\u0446\u044b"
    ],
    "name:und_x_variant":[
        "Chekhovtsi"
    ],
    "wof:name":"Chekhovtsy",
    "wof:placetype":"locality"
},
  "geometry": {"coordinates":[25.7587,54.0554],"type":"Point"}
}