{
  "type": "Feature",
  "properties": {
    "gn:admin1_code":"3.0",
    "gn:asciiname":"Studzieniec",
    "gn:country_code":"BY",
    "gn:dem":205,
    "gn:feature_class":"P",
    "gn:feature_code":"PPL",
    "gn:name":"Studzieniec",
    "gn:population":0,
    "gn:timezone":"Europe/Minsk",
    "iso:country":"BY",
    "name:rus_x_preferred":[
        "\u0421\u0442\u0443\u0434\u0451\u043d\u0435\u0446"
    ],
    "name:und_x_variant":[
        "Stud\u00ebnets"
    ],
    "wof:name":"Studzieniec",
    "wof:placetype":"locality"
},
  "geometry": {"coordinates":[26.2518,54.4321],"type":"Point"}
}