{
  "type": "Feature",
  "properties": {
    "gn:admin1_code":"5.0",
    "gn:asciiname":"Lopatino",
    "gn:country_code":"BY",
    "gn:dem":158,
    "gn:feature_class":"P",
    "gn:feature_code":"PPL",
    "gn:name":"Lopatino",
    "gn:population":0,
    "gn:timezone":"Europe/Minsk",
    "iso:country":"BY",
    "name:rus_x_preferred":[
        "\u041b\u043e\u043f\u0430\u0442\u0438\u043d\u043e"
    ],
    "wof:name":"Lopatino",
    "wof:placetype":"locality"
},
  "geometry": {"coordinates":[27.2542,52.8761],"type":"Point"}
}