{
  "type": "Feature",
  "properties": {
    "gn:admin1_code":"6.0",
    "gn:asciiname":"Grakovka",
    "gn:country_code":"BY",
    "gn:dem":150,
    "gn:feature_class":"P",
    "gn:feature_code":"PPL",
    "gn:name":"Grakovka",
    "gn:population":0,
    "gn:timezone":"Europe/Minsk",
    "iso:country":"BY",
    "name:rus_x_preferred":[
        "\u0413\u0440\u0430\u043a\u043e\u0432\u043a\u0430"
    ],
    "wof:name":"Grakovka",
    "wof:placetype":"locality"
},
  "geometry": {"coordinates":[31.2481,53.3898],"type":"Point"}
}