{
  "type": "Feature",
  "properties": {
    "gn:admin1_code":"5.0",
    "gn:asciiname":"Polyanka",
    "gn:country_code":"BY",
    "gn:dem":171,
    "gn:feature_class":"P",
    "gn:feature_code":"PPL",
    "gn:name":"Polyanka",
    "gn:population":0,
    "gn:timezone":"Europe/Minsk",
    "iso:country":"BY",
    "name:rus_x_preferred":[
        "\u041f\u043e\u043b\u044f\u043d\u043a\u0430"
    ],
    "wof:name":"Polyanka",
    "wof:placetype":"locality"
},
  "geometry": {"coordinates":[28.7069,53.7206],"type":"Point"}
}