{
  "type": "Feature",
  "properties": {
    "gn:admin1_code":"7.0",
    "gn:asciiname":"Pevedomshchina",
    "gn:country_code":"BY",
    "gn:dem":122,
    "gn:feature_class":"P",
    "gn:feature_code":"PPL",
    "gn:name":"Pevedomshchina",
    "gn:population":0,
    "gn:timezone":"Europe/Minsk",
    "iso:country":"BY",
    "name:rus_x_preferred":[
        "\u041f\u0435\u0432\u0435\u0434\u043e\u043c\u0449\u0438\u043d\u0430"
    ],
    "wof:name":"Pevedomshchina",
    "wof:placetype":"locality"
},
  "geometry": {"coordinates":[27.2415,55.2979],"type":"Point"}
}