{
  "type": "Feature",
  "properties": {
    "gn:admin1_code":"5.0",
    "gn:asciiname":"Kondratovichi",
    "gn:country_code":"BY",
    "gn:dem":291,
    "gn:feature_class":"P",
    "gn:feature_code":"PPL",
    "gn:name":"Kondratovichi",
    "gn:population":0,
    "gn:timezone":"Europe/Minsk",
    "iso:country":"BY",
    "name:rus_x_preferred":[
        "\u041a\u043e\u043d\u0434\u0440\u0430\u0442\u043e\u0432\u0438\u0447\u0438"
    ],
    "name:und_x_variant":[
        "Kondratowicze",
        "Kondratovichi"
    ],
    "wof:name":"Kondratovichi",
    "wof:placetype":"locality"
},
  "geometry": {"coordinates":[27.7558,54.152],"type":"Point"}
}