{
  "type": "Feature",
  "properties": {
    "gn:admin1_code":"0.0",
    "gn:asciiname":"Dubniki",
    "gn:country_code":"BY",
    "gn:dem":154,
    "gn:feature_class":"P",
    "gn:feature_code":"PPL",
    "gn:name":"Dubniki",
    "gn:population":0,
    "gn:timezone":"Europe/Minsk",
    "iso:country":"BY",
    "wof:name":"Dubniki",
    "wof:placetype":"locality"
},
  "geometry": {"coordinates":[27.71667,55.95],"type":"Point"}
}