{
  "type": "Feature",
  "properties": {
    "gn:admin1_code":"7.0",
    "gn:asciiname":"Matyasy",
    "gn:country_code":"BY",
    "gn:dem":173,
    "gn:feature_class":"P",
    "gn:feature_code":"PPL",
    "gn:name":"Matyasy",
    "gn:population":0,
    "gn:timezone":"Europe/Minsk",
    "iso:country":"BY",
    "name:rus_x_preferred":[
        "\u041c\u0430\u0442\u044f\u0441\u044b"
    ],
    "wof:name":"Matyasy",
    "wof:placetype":"locality"
},
  "geometry": {"coordinates":[27.8884,55.2091],"type":"Point"}
}