{
  "type": "Feature",
  "properties": {
    "gn:admin1_code":"5.0",
    "gn:asciiname":"Komarovshchina",
    "gn:country_code":"BY",
    "gn:dem":189,
    "gn:feature_class":"P",
    "gn:feature_code":"PPL",
    "gn:name":"Komarovshchina",
    "gn:population":0,
    "gn:timezone":"Europe/Minsk",
    "iso:country":"BY",
    "name:rus_x_preferred":[
        "\u041a\u043e\u043c\u0430\u0440\u043e\u0432\u0449\u0438\u043d\u0430"
    ],
    "wof:name":"Komarovshchina",
    "wof:placetype":"locality"
},
  "geometry": {"coordinates":[27.1054,53.6023],"type":"Point"}
}