{
  "type": "Feature",
  "properties": {
    "gn:admin1_code":"2.0",
    "gn:asciiname":"Shyrokaye",
    "gn:country_code":"BY",
    "gn:dem":140,
    "gn:feature_class":"P",
    "gn:feature_code":"PPL",
    "gn:name":"Shyrokaye",
    "gn:population":0,
    "gn:timezone":"Europe/Minsk",
    "iso:country":"BY",
    "name:bel_x_preferred":[
        "\u0428\u044b\u0440\u043e\u043a\u0430\u0435"
    ],
    "name:und_x_variant":[
        "Shirokoye"
    ],
    "wof:name":"Shyrokaye",
    "wof:placetype":"locality"
},
  "geometry": {"coordinates":[30.8843,52.6943],"type":"Point"}
}