{
  "type": "Feature",
  "properties": {
    "gn:admin1_code":"5.0",
    "gn:asciiname":"Khorastava",
    "gn:country_code":"BY",
    "gn:dem":137,
    "gn:feature_class":"P",
    "gn:feature_code":"PPL",
    "gn:name":"Khorastava",
    "gn:population":0,
    "gn:timezone":"Europe/Minsk",
    "iso:country":"BY",
    "name:bel_x_preferred":[
        "\u0425\u043e\u0440\u0430\u0441\u0442\u0430\u0432\u0430"
    ],
    "name:und_x_variant":[
        "Chorost\u00f3w",
        "Khorostuv",
        "Khorostov",
        "Khorastava"
    ],
    "wof:name":"Khorastava",
    "wof:placetype":"locality"
},
  "geometry": {"coordinates":[27.2849,52.4966],"type":"Point"}
}