{
  "type": "Feature",
  "properties": {
    "gn:admin1_code":"3.0",
    "gn:asciiname":"Koroby",
    "gn:country_code":"BY",
    "gn:dem":221,
    "gn:feature_class":"P",
    "gn:feature_code":"PPL",
    "gn:name":"Koroby",
    "gn:population":0,
    "gn:timezone":"Europe/Minsk",
    "iso:country":"BY",
    "name:rus_x_preferred":[
        "\u041a\u043e\u0440\u043e\u0431\u044b"
    ],
    "name:und_x_variant":[
        "Koraby",
        "Koroby"
    ],
    "wof:name":"Koroby",
    "wof:placetype":"locality"
},
  "geometry": {"coordinates":[25.9833,54.2802],"type":"Point"}
}