{
  "type": "Feature",
  "properties": {
    "gn:admin1_code":"2.0",
    "gn:asciiname":"Khvoynaya Polyana",
    "gn:country_code":"BY",
    "gn:dem":136,
    "gn:feature_class":"P",
    "gn:feature_code":"PPL",
    "gn:name":"Khvoynaya Polyana",
    "gn:population":0,
    "gn:timezone":"Europe/Minsk",
    "iso:country":"BY",
    "name:rus_x_preferred":[
        "\u0425\u0432\u043e\u0439\u043d\u0430\u044f \u041f\u043e\u043b\u044f\u043d\u0430"
    ],
    "wof:name":"Khvoynaya Polyana",
    "wof:placetype":"locality"
},
  "geometry": {"coordinates":[30.0313,52.0916],"type":"Point"}
}