{
  "type": "Feature",
  "properties": {
    "gn:admin1_code":"7.0",
    "gn:asciiname":"Vaytsyakhi",
    "gn:country_code":"BY",
    "gn:dem":127,
    "gn:feature_class":"P",
    "gn:feature_code":"PPL",
    "gn:name":"Vaytsyakhi",
    "gn:population":0,
    "gn:timezone":"Europe/Minsk",
    "iso:country":"BY",
    "name:bel_x_preferred":[
        "\u0412\u0430\u0439\u0446\u044f\u0445\u0456"
    ],
    "name:und_x_variant":[
        "Wojciechy",
        "Voytsekhy",
        "Vaytsyakhi",
        "Voytekhy"
    ],
    "wof:name":"Vaytsyakhi",
    "wof:placetype":"locality"
},
  "geometry": {"coordinates":[27.2293,55.237],"type":"Point"}
}