{
  "type": "Feature",
  "properties": {
    "gn:admin1_code":"5.0",
    "gn:asciiname":"Mil'cha",
    "gn:country_code":"BY",
    "gn:dem":182,
    "gn:feature_class":"P",
    "gn:feature_code":"PPL",
    "gn:name":"Mil\u2019cha",
    "gn:population":0,
    "gn:timezone":"Europe/Minsk",
    "iso:country":"BY",
    "name:bel_x_preferred":[
        "\u041c\u0456\u043b\u044c\u0447\u0430"
    ],
    "name:eng_x_preferred":[
        "Mil'cha"
    ],
    "name:rus_x_preferred":[
        "\u041c\u0438\u043b\u044c\u0447\u0430"
    ],
    "name:und_x_variant":[
        "Milcza",
        "Mil\u2019cha"
    ],
    "wof:name":"Mil'cha",
    "wof:placetype":"locality"
},
  "geometry": {"coordinates":[27.616,54.6821],"type":"Point"}
}