{
  "type": "Feature",
  "properties": {
    "gn:admin1_code":"3.0",
    "gn:asciiname":"Zawilje",
    "gn:country_code":"BY",
    "gn:dem":147,
    "gn:feature_class":"P",
    "gn:feature_code":"PPL",
    "gn:name":"Zawilje",
    "gn:population":0,
    "gn:timezone":"Europe/Minsk",
    "iso:country":"BY",
    "name:rus_x_preferred":[
        "\u0417\u0430\u0432\u0435\u043b\u044c\u0435"
    ],
    "name:und_x_variant":[
        "Zavel\u2019ye"
    ],
    "wof:name":"Zawilje",
    "wof:placetype":"locality"
},
  "geometry": {"coordinates":[26.4653,54.4952],"type":"Point"}
}