{
  "type": "Feature",
  "properties": {
    "gn:admin1_code":"3.0",
    "gn:asciiname":"Lishchitsy",
    "gn:country_code":"BY",
    "gn:dem":117,
    "gn:feature_class":"P",
    "gn:feature_code":"PPL",
    "gn:name":"Lishchitsy",
    "gn:population":0,
    "gn:timezone":"Europe/Minsk",
    "iso:country":"BY",
    "name:rus_x_preferred":[
        "\u041b\u0438\u0449\u0438\u0446\u044b"
    ],
    "wof:name":"Lishchitsy",
    "wof:placetype":"locality"
},
  "geometry": {"coordinates":[24.2894,53.6812],"type":"Point"}
}