{
  "type": "Feature",
  "properties": {
    "gn:admin1_code":"0.0",
    "gn:asciiname":"Popovka",
    "gn:country_code":"BY",
    "gn:dem":135,
    "gn:feature_class":"P",
    "gn:feature_code":"PPL",
    "gn:name":"Popovka",
    "gn:population":0,
    "gn:timezone":"Europe/Minsk",
    "iso:country":"BY",
    "name:ceb_x_preferred":[
        "Popovka"
    ],
    "name:est_x_preferred":[
        "Popovka"
    ],
    "name:swe_x_preferred":[
        "Popovka"
    ],
    "wof:name":"Popovka",
    "wof:placetype":"locality"
},
  "geometry": {"coordinates":[30.83333,52.68333000000001],"type":"Point"}
}