{
  "type": "Feature",
  "properties": {
    "gn:admin1_code":"7.0",
    "gn:asciiname":"Babrova",
    "gn:country_code":"BY",
    "gn:dem":138,
    "gn:feature_class":"P",
    "gn:feature_code":"PPL",
    "gn:name":"Babrova",
    "gn:population":0,
    "gn:timezone":"Europe/Minsk",
    "iso:country":"BY",
    "name:bel_x_preferred":[
        "\u0411\u0430\u0431\u0440\u043e\u0432\u0430"
    ],
    "name:eng_x_preferred":[
        "Bobrovo"
    ],
    "name:rus_x_preferred":[
        "\u0411\u043e\u0431\u0440\u043e\u0432\u043e"
    ],
    "name:und_x_variant":[
        "Babrova"
    ],
    "wof:name":"Babrova",
    "wof:placetype":"locality"
},
  "geometry": {"coordinates":[28.9943,55.0173],"type":"Point"}
}