{
  "type": "Feature",
  "properties": {
    "gn:admin1_code":"7.0",
    "gn:asciiname":"Voron'",
    "gn:country_code":"BY",
    "gn:dem":166,
    "gn:feature_class":"P",
    "gn:feature_code":"PPL",
    "gn:name":"Voron\u2019",
    "gn:population":0,
    "gn:timezone":"Europe/Minsk",
    "iso:country":"BY",
    "name:eng_x_preferred":[
        "Voron'"
    ],
    "name:rus_x_preferred":[
        "\u0412\u043e\u0440\u043e\u043d\u044c"
    ],
    "name:und_x_variant":[
        "Voron\u2019"
    ],
    "wof:name":"Voron'",
    "wof:placetype":"locality"
},
  "geometry": {"coordinates":[28.6292,55.0054],"type":"Point"}
}