{
  "type": "Feature",
  "properties": {
    "gn:admin1_code":"5.0",
    "gn:asciiname":"Borovik",
    "gn:country_code":"BY",
    "gn:dem":169,
    "gn:feature_class":"P",
    "gn:feature_code":"PPL",
    "gn:name":"Borovik",
    "gn:population":0,
    "gn:timezone":"Europe/Minsk",
    "iso:country":"BY",
    "name:rus_x_preferred":[
        "\u0411\u043e\u0440\u043e\u0432\u0438\u043a"
    ],
    "wof:name":"Borovik",
    "wof:placetype":"locality"
},
  "geometry": {"coordinates":[26.8302,53.6038],"type":"Point"}
}