{
  "type": "Feature",
  "properties": {
    "gn:admin1_code":"3.0",
    "gn:asciiname":"Chernyy Bor",
    "gn:country_code":"BY",
    "gn:dem":148,
    "gn:feature_class":"P",
    "gn:feature_code":"PPL",
    "gn:name":"Ch\u00ebrnyy Bor",
    "gn:population":0,
    "gn:timezone":"Europe/Minsk",
    "iso:country":"BY",
    "name:rus_x_preferred":[
        "\u0427\u0451\u0440\u043d\u044b\u0439 \u0411\u043e\u0440"
    ],
    "name:und_x_variant":[
        "Ch\u00ebrnyy Bor"
    ],
    "wof:name":"Chernyy Bor",
    "wof:placetype":"locality"
},
  "geometry": {"coordinates":[26.3646,54.5559],"type":"Point"}
}