{
  "type": "Feature",
  "properties": {
    "gn:admin1_code":"1.0",
    "gn:asciiname":"Kivatichi",
    "gn:country_code":"BY",
    "gn:dem":153,
    "gn:feature_class":"P",
    "gn:feature_code":"PPL",
    "gn:name":"Kivatichi",
    "gn:population":0,
    "gn:timezone":"Europe/Minsk",
    "iso:country":"BY",
    "name:rus_x_preferred":[
        "\u041a\u0438\u0432\u0430\u0442\u0438\u0447\u0438"
    ],
    "wof:name":"Kivatichi",
    "wof:placetype":"locality"
},
  "geometry": {"coordinates":[24.1577,52.3592],"type":"Point"}
}