{
  "type": "Feature",
  "properties": {
    "gn:admin1_code":"5.0",
    "gn:asciiname":"Kal'zberg",
    "gn:country_code":"BY",
    "gn:dem":210,
    "gn:feature_class":"P",
    "gn:feature_code":"PPL",
    "gn:name":"Kal\u2019zberg",
    "gn:population":0,
    "gn:timezone":"Europe/Minsk",
    "iso:country":"BY",
    "name:rus_x_preferred":[
        "\u041a\u0430\u043b\u044c\u0437\u0431\u0435\u0440\u0433"
    ],
    "name:und_x_variant":[
        "Kal\u2019zberg"
    ],
    "wof:name":"Kal'zberg",
    "wof:placetype":"locality"
},
  "geometry": {"coordinates":[27.2502,54.1383],"type":"Point"}
}