{
  "type": "Feature",
  "properties": {
    "gn:admin1_code":"1.0",
    "gn:asciiname":"Zosin Malyy",
    "gn:country_code":"BY",
    "gn:dem":156,
    "gn:feature_class":"P",
    "gn:feature_code":"PPL",
    "gn:name":"Zosin Malyy",
    "gn:population":0,
    "gn:timezone":"Europe/Minsk",
    "iso:country":"BY",
    "name:rus_x_preferred":[
        "\u0417\u043e\u0441\u0438\u043d \u041c\u0430\u043b\u044b\u0439"
    ],
    "name:und_x_variant":[
        "Malyy Zosin"
    ],
    "wof:name":"Zosin Malyy",
    "wof:placetype":"locality"
},
  "geometry": {"coordinates":[24.1913,52.4602],"type":"Point"}
}