{
  "type": "Feature",
  "properties": {
    "gn:admin1_code":"7.0",
    "gn:asciiname":"Vysokaye",
    "gn:country_code":"BY",
    "gn:dem":200,
    "gn:feature_class":"P",
    "gn:feature_code":"PPL",
    "gn:name":"Vysokaye",
    "gn:population":0,
    "gn:timezone":"Europe/Minsk",
    "iso:country":"BY",
    "name:bel_x_preferred":[
        "\u0412\u044b\u0441\u043e\u043a\u0430\u0435"
    ],
    "name:und_x_variant":[
        "Vysokoye"
    ],
    "wof:name":"Vysokaye",
    "wof:placetype":"locality"
},
  "geometry": {"coordinates":[30.4706,54.6377],"type":"Point"}
}