{
  "type": "Feature",
  "properties": {
    "gn:admin1_code":"7.0",
    "gn:asciiname":"Shelomy",
    "gn:country_code":"BY",
    "gn:dem":142,
    "gn:feature_class":"P",
    "gn:feature_code":"PPL",
    "gn:name":"Shelomy",
    "gn:population":0,
    "gn:timezone":"Europe/Minsk",
    "iso:country":"BY",
    "name:rus_x_preferred":[
        "\u0428\u0435\u043b\u043e\u043c\u044b"
    ],
    "wof:name":"Shelomy",
    "wof:placetype":"locality"
},
  "geometry": {"coordinates":[29.56,54.9398],"type":"Point"}
}