{
  "type": "Feature",
  "properties": {
    "gn:admin1_code":"3.0",
    "gn:asciiname":"Mel'khovo",
    "gn:country_code":"BY",
    "gn:dem":127,
    "gn:feature_class":"P",
    "gn:feature_code":"PPL",
    "gn:name":"Mel\u2019khovo",
    "gn:population":0,
    "gn:timezone":"Europe/Minsk",
    "iso:country":"BY",
    "name:rus_x_preferred":[
        "\u041c\u0435\u043b\u044c\u0445\u043e\u0432\u043e"
    ],
    "name:und_x_variant":[
        "Mel\u2019khovo"
    ],
    "wof:name":"Mel'khovo",
    "wof:placetype":"locality"
},
  "geometry": {"coordinates":[25.5621,53.8232],"type":"Point"}
}