{
  "type": "Feature",
  "properties": {
    "gn:admin1_code":"7.0",
    "gn:asciiname":"Babariki",
    "gn:country_code":"BY",
    "gn:dem":134,
    "gn:feature_class":"P",
    "gn:feature_code":"PPL",
    "gn:name":"Babariki",
    "gn:population":0,
    "gn:timezone":"Europe/Minsk",
    "iso:country":"BY",
    "name:rus_x_preferred":[
        "\u0411\u0430\u0431\u0430\u0440\u0438\u043a\u0438"
    ],
    "wof:name":"Babariki",
    "wof:placetype":"locality"
},
  "geometry": {"coordinates":[27.5841,55.7668],"type":"Point"}
}