{
  "type": "Feature",
  "properties": {
    "gn:admin1_code":"7.0",
    "gn:asciiname":"Lugi",
    "gn:country_code":"BY",
    "gn:dem":229,
    "gn:feature_class":"P",
    "gn:feature_code":"PPL",
    "gn:name":"Lugi",
    "gn:population":0,
    "gn:timezone":"Europe/Minsk",
    "iso:country":"BY",
    "name:bre_x_preferred":[
        "Lugi"
    ],
    "name:cat_x_preferred":[
        "Loges"
    ],
    "name:deu_x_preferred":[
        "Lugi"
    ],
    "name:rus_x_preferred":[
        "\u041b\u0443\u0433\u0438"
    ],
    "name:spa_x_preferred":[
        "Lugi"
    ],
    "wof:name":"Lugi",
    "wof:placetype":"locality"
},
  "geometry": {"coordinates":[30.9066,55.143],"type":"Point"}
}