{
  "type": "Feature",
  "properties": {
    "gn:admin1_code":"6.0",
    "gn:asciiname":"Lipaki",
    "gn:country_code":"BY",
    "gn:dem":158,
    "gn:feature_class":"P",
    "gn:feature_code":"PPL",
    "gn:name":"Lipaki",
    "gn:population":0,
    "gn:timezone":"Europe/Minsk",
    "iso:country":"BY",
    "name:rus_x_preferred":[
        "\u041b\u0438\u043f\u0430\u043a\u0438"
    ],
    "wof:name":"Lipaki",
    "wof:placetype":"locality"
},
  "geometry": {"coordinates":[32.3999,53.2605],"type":"Point"}
}