{
  "type": "Feature",
  "properties": {
    "gn:admin1_code":"0.0",
    "gn:asciiname":"Novo-Nikol'sk",
    "gn:country_code":"BY",
    "gn:dem":138,
    "gn:feature_class":"P",
    "gn:feature_code":"PPL",
    "gn:name":"Novo-Nikol\u2019sk",
    "gn:population":0,
    "gn:timezone":"Europe/Minsk",
    "iso:country":"BY",
    "wof:name":"Novo-Nikol'sk",
    "wof:placetype":"locality"
},
  "geometry": {"coordinates":[30.91667,52.88333000000001],"type":"Point"}
}