{
  "type": "Feature",
  "properties": {
    "gn:admin1_code":"2.0",
    "gn:asciiname":"Shchibrin",
    "gn:country_code":"BY",
    "gn:dem":131,
    "gn:feature_class":"P",
    "gn:feature_code":"PPL",
    "gn:name":"Shchibrin",
    "gn:population":0,
    "gn:timezone":"Europe/Minsk",
    "iso:country":"BY",
    "name:rus_x_preferred":[
        "\u0429\u0438\u0431\u0440\u0438\u043d"
    ],
    "name:und_x_variant":[
        "Shibrin",
        "Shchibri"
    ],
    "wof:name":"Shchibrin",
    "wof:placetype":"locality"
},
  "geometry": {"coordinates":[30.0851,53.1279],"type":"Point"}
}