{
  "type": "Feature",
  "properties": {
    "gn:admin1_code":"5.0",
    "gn:asciiname":"Vishevka",
    "gn:country_code":"BY",
    "gn:dem":289,
    "gn:feature_class":"P",
    "gn:feature_code":"PPL",
    "gn:name":"Vishevka",
    "gn:population":0,
    "gn:timezone":"Europe/Minsk",
    "iso:country":"BY",
    "name:rus_x_preferred":[
        "\u0412\u0438\u0448\u043d\u0451\u0432\u043a\u0430"
    ],
    "name:und_x_variant":[
        "Vishn\u00ebvka",
        "Vishevka"
    ],
    "wof:name":"Vishevka",
    "wof:placetype":"locality"
},
  "geometry": {"coordinates":[27.1931,53.9471],"type":"Point"}
}