{
  "type": "Feature",
  "properties": {
    "gn:admin1_code":"2.0",
    "gn:asciiname":"Poles'ye",
    "gn:country_code":"BY",
    "gn:dem":131,
    "gn:feature_class":"P",
    "gn:feature_code":"PPL",
    "gn:name":"Poles\u2019ye",
    "gn:population":0,
    "gn:timezone":"Europe/Minsk",
    "iso:country":"BY",
    "name:rus_x_preferred":[
        "\u041f\u043e\u043b\u0435\u0441\u044c\u0435"
    ],
    "name:und_x_variant":[
        "Poles\u2019ye"
    ],
    "wof:name":"Poles'ye",
    "wof:placetype":"locality"
},
  "geometry": {"coordinates":[30.6485,52.3688],"type":"Point"}
}