{
  "type": "Feature",
  "properties": {
    "gn:admin1_code":"2.0",
    "gn:asciiname":"Lyubanskiy",
    "gn:country_code":"BY",
    "gn:dem":148,
    "gn:feature_class":"P",
    "gn:feature_code":"PPL",
    "gn:name":"Lyubanskiy",
    "gn:population":0,
    "gn:timezone":"Europe/Minsk",
    "iso:country":"BY",
    "name:rus_x_preferred":[
        "\u041b\u044e\u0431\u0430\u043d\u044c"
    ],
    "name:und_x_variant":[
        "Lyuban\u2019",
        "Lyubanskiy"
    ],
    "wof:name":"Lyubanskiy",
    "wof:placetype":"locality"
},
  "geometry": {"coordinates":[30.4815,52.956],"type":"Point"}
}