{
  "type": "Feature",
  "properties": {
    "gn:admin1_code":"3.0",
    "gn:asciiname":"Dubrovskoye SMU",
    "gn:country_code":"BY",
    "gn:dem":119,
    "gn:feature_class":"P",
    "gn:feature_code":"PPL",
    "gn:name":"Dubrovskoye SMU",
    "gn:population":0,
    "gn:timezone":"Europe/Minsk",
    "iso:country":"BY",
    "name:rus_x_preferred":[
        "\u0414\u0443\u0431\u0440\u043e\u0432\u043e \u041f\u0435\u0440\u0432\u043e\u0435"
    ],
    "name:rus_x_variant":[
        "\u0414\u0443\u0431\u0440\u043e\u0432\u0441\u043a\u043e\u0435 \u0421\u041c\u0423"
    ],
    "name:und_x_variant":[
        "Dubrovo Pervoye",
        "Dubrovskoye SMU"
    ],
    "wof:name":"Dubrovskoye SMU",
    "wof:placetype":"locality"
},
  "geometry": {"coordinates":[25.0476,53.5799],"type":"Point"}
}