{
  "type": "Feature",
  "properties": {
    "gn:admin1_code":"6.0",
    "gn:asciiname":"Syemukachy",
    "gn:country_code":"BY",
    "gn:dem":166,
    "gn:feature_class":"P",
    "gn:feature_code":"PPL",
    "gn:name":"Syemukachy",
    "gn:population":0,
    "gn:timezone":"Europe/Minsk",
    "iso:country":"BY",
    "name:bel_x_preferred":[
        "\u0421\u0435\u043c\u0443\u043a\u0430\u0447\u044b"
    ],
    "name:und_x_variant":[
        "Semukachi"
    ],
    "wof:name":"Syemukachy",
    "wof:placetype":"locality"
},
  "geometry": {"coordinates":[29.8645,53.7471],"type":"Point"}
}