{
  "type": "Feature",
  "properties": {
    "gn:admin1_code":"5.0",
    "gn:asciiname":"Povyazyn'",
    "gn:country_code":"BY",
    "gn:dem":206,
    "gn:feature_class":"P",
    "gn:feature_code":"PPL",
    "gn:name":"Povyazyn\u2019",
    "gn:population":0,
    "gn:timezone":"Europe/Minsk",
    "iso:country":"BY",
    "name:rus_x_preferred":[
        "\u041f\u043e\u0432\u044f\u0437\u044b\u043d\u044c"
    ],
    "name:und_x_variant":[
        "Povyazyn\u2019"
    ],
    "wof:name":"Povyazyn'",
    "wof:placetype":"locality"
},
  "geometry": {"coordinates":[27.2057,54.1361],"type":"Point"}
}