{
  "type": "Feature",
  "properties": {
    "gn:admin1_code":"1.0",
    "gn:asciiname":"Dymsk",
    "gn:country_code":"BY",
    "gn:dem":149,
    "gn:feature_class":"P",
    "gn:feature_code":"PPL",
    "gn:name":"Dymsk",
    "gn:population":0,
    "gn:timezone":"Europe/Minsk",
    "iso:country":"BY",
    "name:rus_x_preferred":[
        "\u0414\u044b\u043c\u0441\u043a"
    ],
    "wof:name":"Dymsk",
    "wof:placetype":"locality"
},
  "geometry": {"coordinates":[24.982,52.224],"type":"Point"}
}