{
  "type": "Feature",
  "properties": {
    "gn:admin1_code":"1.0",
    "gn:asciiname":"Netchin",
    "gn:country_code":"BY",
    "gn:dem":158,
    "gn:feature_class":"P",
    "gn:feature_code":"PPL",
    "gn:name":"Netchin",
    "gn:population":0,
    "gn:timezone":"Europe/Minsk",
    "iso:country":"BY",
    "name:rus_x_preferred":[
        "\u041d\u0435\u0442\u0447\u0438\u043d"
    ],
    "wof:name":"Netchin",
    "wof:placetype":"locality"
},
  "geometry": {"coordinates":[26.1672,52.8407],"type":"Point"}
}