{
  "type": "Feature",
  "properties": {
    "gn:admin1_code":"7.0",
    "gn:asciiname":"Starodvorishche",
    "gn:country_code":"BY",
    "gn:dem":140,
    "gn:feature_class":"P",
    "gn:feature_code":"PPL",
    "gn:name":"Starodvorishche",
    "gn:population":0,
    "gn:timezone":"Europe/Minsk",
    "iso:country":"BY",
    "name:rus_x_preferred":[
        "\u0421\u0442\u0430\u0440\u043e\u0434\u0432\u043e\u0440\u0438\u0449\u0435"
    ],
    "name:und_x_variant":[
        "Staroye Dvorishche"
    ],
    "wof:name":"Starodvorishche",
    "wof:placetype":"locality"
},
  "geometry": {"coordinates":[26.7301,55.4341],"type":"Point"}
}